Workbook

Sheet 指数历史财务比率比较
E1: 指数历史财务比率比较
C3: 指数代码 | E3: 882004.WI | G3: 对比指数 | I3: 881001.WI | K3: 指数指标 | M3: 单季度营收同比(%)
C4: 指数简称 | E4: =[1]!s_info_name(E3) -> 可选消费 | G4: 对比指数简称 | I4: =[1]!s_info_name(I3) -> 万得全A | K4: 差异比较方式 | M4: 绝对差额
C8: =M3&"历史比较" -> 单季度营收同比(%)历史比较
R25: 单季度营收同比(%)
R26: 单季度净利同比(%)
R27: 单季度净利率(%)
R28: 单季度ROE(%)
R29: 单季度ROA(%)
R32: 绝对差额
G33: =E4 -> 可选消费 | I33: =I4 -> 万得全A | K33: =M4 -> 绝对差额 | R33: 比值
E34: =Data!A5 -> 45107 | G34: =IF(M$3="单季度营收同比(%)",Data!F5,IF(M$3="单季度净利同比(%)",Data!G5,IF(M$3="单季度净利率(%)",Data!H5,IF(M$3="单季度ROE(%)",Data!I5,IF(M$3="单季度ROA(%)",Data!J5,))))) -> 2.5599 | I34: =IF(M$3="单季度营收同比(%)",Data!Q5,IF(M$3="单季度净利同比(%)",Data!R5,IF(M$3="单季度净利率(%)",Data!S5,IF(M$3="单季度ROE(%)",Data!T5,IF(M$3="单季度ROA(%)",Data!U5,))))) -> 2.3476 | K34: =IFERROR(IF(M$4="绝对差额",G34-I34,IF(M$4="比值",G34/I34,)),0) -> 0.2123
E35: =Data!A6 -> 45016 | G35: =IF(M$3="单季度营收同比(%)",Data!F6,IF(M$3="单季度净利同比(%)",Data!G6,IF(M$3="单季度净利率(%)",Data!H6,IF(M$3="单季度ROE(%)",Data!I6,IF(M$3="单季度ROA(%)",Data!J6,))))) -> 2.1926 | I35: =IF(M$3="单季度营收同比(%)",Data!Q6,IF(M$3="单季度净利同比(%)",Data!R6,IF(M$3="单季度净利率(%)",Data!S6,IF(M$3="单季度ROE(%)",Data!T6,IF(M$3="单季度ROA(%)",Data!U6,))))) -> 2.4567 | K35: =IFERROR(IF(M$4="绝对差额",G35-I35,IF(M$4="比值",G35/I35,)),0) -> -0.2641
E36: =Data!A7 -> 44926 | G36: =IF(M$3="单季度营收同比(%)",Data!F7,IF(M$3="单季度净利同比(%)",Data!G7,IF(M$3="单季度净利率(%)",Data!H7,IF(M$3="单季度ROE(%)",Data!I7,IF(M$3="单季度ROA(%)",Data!J7,))))) -> -0.5473 | I36: =IF(M$3="单季度营收同比(%)",Data!Q7,IF(M$3="单季度净利同比(%)",Data!R7,IF(M$3="单季度净利率(%)",Data!S7,IF(M$3="单季度ROE(%)",Data!T7,IF(M$3="单季度ROA(%)",Data!U7,))))) -> 1.3351 | K36: =IFERROR(IF(M$4="绝对差额",G36-I36,IF(M$4="比值",G36/I36,)),0) -> -1.8824
E37: =Data!A8 -> 44834 | G37: =IF(M$3="单季度营收同比(%)",Data!F8,IF(M$3="单季度净利同比(%)",Data!G8,IF(M$3="单季度净利率(%)",Data!H8,IF(M$3="单季度ROE(%)",Data!I8,IF(M$3="单季度ROA(%)",Data!J8,))))) -> 2.0097 | I37: =IF(M$3="单季度营收同比(%)",Data!Q8,IF(M$3="单季度净利同比(%)",Data!R8,IF(M$3="单季度净利率(%)",Data!S8,IF(M$3="单季度ROE(%)",Data!T8,IF(M$3="单季度ROA(%)",Data!U8,))))) -> 2.3919 | K37: =IFERROR(IF(M$4="绝对差额",G37-I37,IF(M$4="比值",G37/I37,)),0) -> -0.3822
E38: =Data!A9 -> 44742 | G38: =IF(M$3="单季度营收同比(%)",Data!F9,IF(M$3="单季度净利同比(%)",Data!G9,IF(M$3="单季度净利率(%)",Data!H9,IF(M$3="单季度ROE(%)",Data!I9,IF(M$3="单季度ROA(%)",Data!J9,))))) -> 1.9853 | I38: =IF(M$3="单季度营收同比(%)",Data!Q9,IF(M$3="单季度净利同比(%)",Data!R9,IF(M$3="单季度净利率(%)",Data!S9,IF(M$3="单季度ROE(%)",Data!T9,IF(M$3="单季度ROA(%)",Data!U9,))))) -> 2.7371 | K38: =IFERROR(IF(M$4="绝对差额",G38-I38,IF(M$4="比值",G38/I38,)),0) -> -0.7518
E39: =Data!A10 -> 44651 | G39: =IF(M$3="单季度营收同比(%)",Data!F10,IF(M$3="单季度净利同比(%)",Data!G10,IF(M$3="单季度净利率(%)",Data!H10,IF(M$3="单季度ROE(%)",Data!I10,IF(M$3="单季度ROA(%)",Data!J10,))))) -> 1.886 | I39: =IF(M$3="单季度营收同比(%)",Data!Q10,IF(M$3="单季度净利同比(%)",Data!R10,IF(M$3="单季度净利率(%)",Data!S10,IF(M$3="单季度ROE(%)",Data!T10,IF(M$3="单季度ROA(%)",Data!U10,))))) -> 2.5507 | K39: =IFERROR(IF(M$4="绝对差额",G39-I39,IF(M$4="比值",G39/I39,)),0) -> -0.6647
E40: =Data!A11 -> 44561 | G40: =IF(M$3="单季度营收同比(%)",Data!F11,IF(M$3="单季度净利同比(%)",Data!G11,IF(M$3="单季度净利率(%)",Data!H11,IF(M$3="单季度ROE(%)",Data!I11,IF(M$3="单季度ROA(%)",Data!J11,))))) -> -0.5604 | I40: =IF(M$3="单季度营收同比(%)",Data!Q11,IF(M$3="单季度净利同比(%)",Data!R11,IF(M$3="单季度净利率(%)",Data!S11,IF(M$3="单季度ROE(%)",Data!T11,IF(M$3="单季度ROA(%)",Data!U11,))))) -> 1.465 | K40: =IFERROR(IF(M$4="绝对差额",G40-I40,IF(M$4="比值",G40/I40,)),0) -> -2.0254
E41: =Data!A12 -> 44469 | G41: =IF(M$3="单季度营收同比(%)",Data!F12,IF(M$3="单季度净利同比(%)",Data!G12,IF(M$3="单季度净利率(%)",Data!H12,IF(M$3="单季度ROE(%)",Data!I12,IF(M$3="单季度ROA(%)",Data!J12,))))) -> 1.8912 | I41: =IF(M$3="单季度营收同比(%)",Data!Q12,IF(M$3="单季度净利同比(%)",Data!R12,IF(M$3="单季度净利率(%)",Data!S12,IF(M$3="单季度ROE(%)",Data!T12,IF(M$3="单季度ROA(%)",Data!U12,))))) -> 2.5918 | K41: =IFERROR(IF(M$4="绝对差额",G41-I41,IF(M$4="比值",G41/I41,)),0) -> -0.7006
E42: =Data!A13 -> 44377 | G42: =IF(M$3="单季度营收同比(%)",Data!F13,IF(M$3="单季度净利同比(%)",Data!G13,IF(M$3="单季度净利率(%)",Data!H13,IF(M$3="单季度ROE(%)",Data!I13,IF(M$3="单季度ROA(%)",Data!J13,))))) -> 2.4143 | I42: =IF(M$3="单季度营收同比(%)",Data!Q13,IF(M$3="单季度净利同比(%)",Data!R13,IF(M$3="单季度净利率(%)",Data!S13,IF(M$3="单季度ROE(%)",Data!T13,IF(M$3="单季度ROA(%)",Data!U13,))))) -> 2.9392 | K42: =IFERROR(IF(M$4="绝对差额",G42-I42,IF(M$4="比值",G42/I42,)),0) -> -0.5249
E43: =Data!A14 -> 44286 | G43: =IF(M$3="单季度营收同比(%)",Data!F14,IF(M$3="单季度净利同比(%)",Data!G14,IF(M$3="单季度净利率(%)",Data!H14,IF(M$3="单季度ROE(%)",Data!I14,IF(M$3="单季度ROA(%)",Data!J14,))))) -> 2.1736 | I43: =IF(M$3="单季度营收同比(%)",Data!Q14,IF(M$3="单季度净利同比(%)",Data!R14,IF(M$3="单季度净利率(%)",Data!S14,IF(M$3="单季度ROE(%)",Data!T14,IF(M$3="单季度ROA(%)",Data!U14,))))) -> 2.7165 | K43: =IFERROR(IF(M$4="绝对差额",G43-I43,IF(M$4="比值",G43/I43,)),0) -> -0.5429
E44: =Data!A15 -> 44196 | G44: =IF(M$3="单季度营收同比(%)",Data!F15,IF(M$3="单季度净利同比(%)",Data!G15,IF(M$3="单季度净利率(%)",Data!H15,IF(M$3="单季度ROE(%)",Data!I15,IF(M$3="单季度ROA(%)",Data!J15,))))) -> 0.2219 | I44: =IF(M$3="单季度营收同比(%)",Data!Q15,IF(M$3="单季度净利同比(%)",Data!R15,IF(M$3="单季度净利率(%)",Data!S15,IF(M$3="单季度ROE(%)",Data!T15,IF(M$3="单季度ROA(%)",Data!U15,))))) -> 1.769 | K44: =IFERROR(IF(M$4="绝对差额",G44-I44,IF(M$4="比值",G44/I44,)),0) -> -1.5471
E45: =Data!A16 -> 44104 | G45: =IF(M$3="单季度营收同比(%)",Data!F16,IF(M$3="单季度净利同比(%)",Data!G16,IF(M$3="单季度净利率(%)",Data!H16,IF(M$3="单季度ROE(%)",Data!I16,IF(M$3="单季度ROA(%)",Data!J16,))))) -> 2.7236 | I45: =IF(M$3="单季度营收同比(%)",Data!Q16,IF(M$3="单季度净利同比(%)",Data!R16,IF(M$3="单季度净利率(%)",Data!S16,IF(M$3="单季度ROE(%)",Data!T16,IF(M$3="单季度ROA(%)",Data!U16,))))) -> 2.8857 | K45: =IFERROR(IF(M$4="绝对差额",G45-I45,IF(M$4="比值",G45/I45,)),0) -> -0.1621
... E102: =Data!A73 -> 38898 | G102: =IF(M$3="单季度营收同比(%)",Data!F73,IF(M$3="单季度净利同比(%)",Data!G73,IF(M$3="单季度净利率(%)",Data!H73,IF(M$3="单季度ROE(%)",Data!I73,IF(M$3="单季度ROA(%)",Data!J73,))))) -> 1.795 | I102: =IF(M$3="单季度营收同比(%)",Data!Q73,IF(M$3="单季度净利同比(%)",Data!R73,IF(M$3="单季度净利率(%)",Data!S73,IF(M$3="单季度ROE(%)",Data!T73,IF(M$3="单季度ROA(%)",Data!U73,))))) -> 3.0593 | K102: =IFERROR(IF(M$4="绝对差额",G102-I102,IF(M$4="比值",G102/I102,)),0) -> -1.2643

Sheet Wind模板
A1: 指数历史财务比率比较

Sheet Data
B1: =[1]!s_info_name(B2) -> 可选消费 | M1: =[1]!s_info_name(M2) -> 万得全A
B2: =指数历史财务比率比较!E3 -> 882004.WI | M2: =指数历史财务比率比较!I3 -> 881001.WI
A3: 日期 | B3: 市盈率PE(TTM) | C3: 市净率PB(LF,内地) | D3: 市销率PS(TTM) | E3: 股息率(近12个月) | F3: 单季度.净资产收益率ROE | G3: 单季度.总资产净利率ROA | H3: 单季度.销售净利率 | I3: 单季度.营业收入同比增长率 | J3: 单季度.归属母公司股东的净利润同比增长率 | L3: 日期 | M3: 市盈率PE(TTM) | N3: 市净率PB(LF,内地) | O3: 市销率PS(TTM) | P3: 股息率(近12个月) | Q3: 单季度.净资产收益率ROE | R3: 单季度.总资产净利率ROA | S3: 单季度.销售净利率 | T3: 单季度.营业收入同比增长率 | U3: 单季度.归属母公司股东的净利润同比增长率
A4: Date | B4: pe_ttm | C4: pb_lf | D4: ps_ttm | E4: dividendyield2 | F4: qfa_roe | G4: qfa_roa | H4: qfa_netprofitmargin | I4: qfa_yoysales | J4: qfa_yoynetprofit | L4: Date | M4: pe_ttm | N4: pb_lf | O4: ps_ttm | P4: dividendyield2 | Q4: qfa_roe | R4: qfa_roa | S4: qfa_netprofitmargin | T4: qfa_yoysales | U4: qfa_yoynetprofit
A5: 45107 | B5: =[1]!WSD(B2,B4:J4,"-69Q","","Per=FQ","Days=Alldays","TradingCalendar=SSE","Sort=D","rptType=1","cols=9;rows=69") -> 32.738701 | C5: 2.3087001 | D5: 1.3668 | E5: 1.7472 | F5: 2.5599 | G5: 1.0827 | H5: 5.8942 | I5: 20.6736 | J5: 30.2466 | L5: 45107 | M5: =[1]!WSD(M2,M4:U4,"-69Q","","Per=FQ","Days=Alldays","TradingCalendar=SSE","Sort=D","rptType=1","cols=9;rows=69") -> 17.3321 | N5: 1.6267 | O5: 1.2947 | P5: 2.1184 | Q5: 2.3476 | R5: 0.3868 | S5: 8.6358 | T5: 1.4551 | U5: -9.2791
A6: 45016 | B6: 41.427101 | C6: 2.3317001 | D6: 1.378 | E6: 1.7341 | F6: 2.1926 | G6: 0.9319 | H6: 5.562 | I6: 3.3054 | J6: 17.7123 | L6: 45016 | M6: 17.921 | N6: 1.6777 | O6: 1.3272 | P6: 1.917 | Q6: 2.4567 | R6: 0.4048 | S6: 9.4063 | T6: 3.8157 | U6: 1.9473
A7: 44926 | B7: 41.1511 | C7: 2.2167001 | D7: 1.3237 | E7: 1.7233 | F7: -0.5473 | G7: -0.2277 | H7: -1.2368 | I7: 1.6699 | J7: -29.0247 | L7: 44926 | M7: 16.717699 | N7: 1.5877 | O7: 1.2399 | P7: 2.0572 | Q7: 1.3351 | R7: 0.225 | S7: 4.5445 | T7: 2.6033 | U7: -8.4559
A8: 44834 | B8: 41.038601 | C8: 2.1781001 | D8: 1.2995 | E8: 1.9264 | F8: 2.0097 | G8: 0.8549 | H8: 4.7795 | I8: 11.0663 | J8: 9.6456 | L8: 44834 | M8: 16.218201 | N8: 1.5778 | O8: 1.2198 | P8: 2.0866 | Q8: 2.3919 | R8: 0.3951 | S8: 8.4212 | T8: 6.7824 | U8: -0.5518
A9: 44742 | B9: 45.249199 | C9: 2.5929999 | D9: 1.4915 | E9: 1.7261 | F9: 1.9853 | G9: 0.8322 | H9: 5.3226 | I9: -9.1632 | J9: -15.8423 | L9: 44742 | M9: 18.2582 | N9: 1.7939 | O9: 1.3828 | P9: 1.6922 | Q9: 2.7371 | R9: 0.4568 | S9: 9.4432 | T9: 5.3189 | U9: -0.3507
A10: 44651 | B10: 34.195599 | C10: 2.2307999 | D10: 1.2714 | E10: 1.7423 | F10: 1.886 | G10: 0.8041 | H10: 4.8876 | I10: -1.5473 | J10: -11.8687 | L10: 44651 | M10: 17.5522 | N10: 1.7418 | O10: 1.356 | P10: 1.6336 | Q10: 2.5507 | R10: 0.426 | S10: 9.2178 | T10: 10.6827 | U10: 3.0445
A11: 44561 | B11: 40.805 | C11: 2.7916 | D11: 1.5688 | E11: 1.4416 | F11: -0.5604 | G11: -0.1971 | H11: -1.0264 | I11: -3.6888 | J11: -367.7635 | L11: 44561 | M11: 20.1092 | N11: 2.0295 | O11: 1.5638 | P11: 1.4398 | Q11: 1.465 | R11: 0.2441 | S11: 4.7105 | T11: 9.7886 | U11: -10.3347
A12: 44469 | B12: 33.939301 | C12: 2.5980999 | D12: 1.4253 | E12: 1.5547 | F12: 1.8912 | G12: 0.8534 | H12: 4.9926 | I12: -3.1685 | J12: -28.8203 | L12: 44469 | M12: 19.1147 | N12: 2.0074 | O12: 1.5515 | P12: 1.5034 | Q12: 2.5918 | R12: 0.4185 | S12: 8.8517 | T12: 14.6369 | U12: -1.4507
A13: 44377 | B13: 38.728699 | C13: 2.8575001 | D13: 1.6002 | E13: 1.2537 | F13: 2.4143 | G13: 1.0643 | H13: 5.9584 | I13: 11.3624 | J13: 15.4917 | L13: 44377 | M13: 20.886 | N13: 2.0666001 | O13: 1.6473 | P13: 1.5252 | Q13: 2.9392 | R13: 0.4801 | S13: 9.8167 | T13: 23.51 | U13: 36.8688
A14: 44286 | B14: 53.500099 | C14: 2.6459999 | D14: 1.6129 | E14: 1.3313 | F14: 2.1736 | G14: 0.951 | H14: 5.4351 | I14: 51.3635 | J14: 437.2698 | L14: 44286 | M14: 21.4877 | N14: 1.939 | O14: 1.6347 | P14: 1.4699 | Q14: 2.7165 | R14: 0.4344 | S14: 9.8397 | T14: 31.2318 | U14: 53.5846
A15: 44196 | B15: 66.3479 | C15: 2.7844999 | D15: 1.6874 | E15: 1.2732 | F15: 0.2219 | G15: 0.2232 | H15: 1.0376 | I15: 7.1301 | J15: 110.7861 | L15: 44196 | M15: 23.3577 | N15: 2.0269001 | O15: 1.6803 | P15: 1.4414 | Q15: 1.769 | R15: 0.2934 | S15: 5.7788 | T15: 9.2776 | U15: 61.3482
A16: 44104 | B16: 62.364899 | C16: 2.4660001 | D16: 1.4597 | E16: 1.403 | F16: 2.7236 | G16: 1.1932 | H16: 6.2252 | I16: 7.7473 | J16: 11.8106 | L16: 44104 | M16: 22.4496 | N16: 1.913 | O16: 1.558 | P16: 1.5713 | Q16: 2.8857 | R16: 0.4512 | S16: 10.3138 | T16: 7.5597 | U16: 18.0635
A17: 44012 | B17: 51.834099 | C17: 2.1687 | D17: 1.2574 | E17: 1.8716 | F17: 2.1813 | G17: 0.9659 | H17: 5.4483 | I17: -2.0901 | J17: -7.5714 | L17: 44012 | M17: 19.6231 | N17: 1.7462 | O17: 1.42 | P17: 1.6055 | Q17: 2.3627 | R17: 0.3649 | S17: 8.5279 | T17: 3.9447 | U17: -11.649
... A73: 38898 | B73: 97.344299 | C73: 2.2783 | D73: 0.8761 | E73: 1.2438 | F73: 1.795 | G73: 0.6589 | H73: 2.2951 | I73: 13.0765 | J73: 62.6269 | L73: 38898 | M73: 30.889099 | N73: 2.3146 | O73: 1.1342 | P73: 1.784 | Q73: 3.0593 | R73: 0.8967 | S73: 5.5482 | T73: 22.5008 | U73: 26.0716
