Workbook
Name DATES: '[1]FAI Growth by sector'!$C$4:$AX$4
Name DES: '[1]FAI Growth by sector'!$A$6:$A$76
Name IDS: '[1]FAI Growth by sector'!#REF!
Name OBS: '[1]FAI Growth by sector'!$C$6:$AX$76
Name UNITS: '[1]FAI Growth by sector'!#REF!

Sheet Sector Top picks
Q1: Source: Bloomberg, Wind, CICC Research
D2: A-share and H-share Sector Top Picks：February 2026
B4: Sector | C4: Stock name | D4: Ticker | E4: Price | F4: Chg. YTD (%) | G4: TP | H4: Turnover Avg | I4: Up/ down (%) | J4: Earnings growth (%) | L4: P/E (x) | N4: P/B (x) | P4: Div. Yield （%）
H5: 3M, mn | J5: 26E | K5: 27E | L5: 26E | M5: 27E | N5: 26E | O5: 27E | P5: 26E | Q5: 27E
A6: 1 | B6: Food, Beverage & Tobacco | C6: KWEICHOW MOUTAI | D6: 600519.SH | E6: 1555 | F6: 12.911892 | G6: 1860 | H6: 5982.4907 | I6: 19.614148 | J6: 0.049272017 | K6: 0.069356588 | L6: 20.495855 | M6: 19.201561 | N6: 7.0152486 | O6: 6.4113665 | P6: 3.7153055 | Q6: 3.8142122
A7: 2 | B7: Food, Beverage & Tobacco | C7: WLY | D7: 000858.SZ | E7: 108.89 | F7: 2.7845951 | G7: 128 | H7: 2333.2573 | I7: 17.549821 | J7: 0.024531501 | K7: 0.08459084 | L7: 16.079445 | M7: 14.780779 | N7: 2.8328737 | O7: 2.6324824 | P7: 4.4512811 | Q7: 4.733217
A8: 3 | B8: Food, Beverage & Tobacco | C8: SHANXI FEN WINE | D8: 600809.SH | E8: 180.21 | F8: 4.9563192 | G8: 228 | H8: 1091.9437 | I8: 26.519061 | J8: 0.062324402 | K8: 0.098764928 | L8: 16.997736 | M8: 15.479299 | N8: 4.7900165 | O8: 4.1827593 | P8: 3.5003607 | Q8: 3.8149936
A9: 4 | B9: Food, Beverage & Tobacco | C9: ANJOY FOOD | D9: 603345.SH | E9: 90.39 | F9: 14.013623 | G9: 100 | H9: 450.05614 | I9: 10.631707 | J9: 0.12229718 | K9: 0.11231323 | L9: 18.906087 | M9: 17.070822 | N9: 1.9814547 | O9: 1.903308 | P9: 2.9848435 | Q9: 3.1618542
A10: 5 | B10: Media & Entertainment | C10: CENTURY HUATONG | D10: 002602.SZ | E10: 19.42 | F10: 13.833529 | G10: 26.5 | H10: 3252.7971 | I10: 36.457261 | J10: 0.4875999 | K10: 0.2263865 | L10: 16.598291 | M10: 13.551989 | N10: 3.785575 | O10: 3.0136561 | P10: 0.30895984 | Q10: 0.28321318
A11: 6 | B11: Elec EQPT, Grid | C11: FIRST | D11: 603806.SH | E11: 18.6 | F11: 33.237822 | G11: 23.2 | H11: 607.10945 | I11: 24.731183 | J11: 0.44838373 | K11: 0.32354212 | L11: 28.181818 | M11: 21.453287 | N11: 2.6878613 | O11: 2.5074144 | P11: 1.5913978 | Q11: 1.9516129
A12: 7 | B12: Elec EQPT, Grid | C12: GINLONG TECHNOLOGIES | D12: 300763.SZ | E12: 80.8 | F12: 13.149419 | G12: 102.6 | H12: 1103.4249 | I12: 26.980198 | J12: 0.30828352 | K12: 0.14099217 | L12: 21.003379 | M12: 17.283422 | N12: 2.9607915 | O12: - | P12: 0.55693069 | Q12: -
A13: 8 | B13: Elec EQPT, Grid | C13: DKEM | D13: 300842.SZ | E13: 107.71 | F13: 81.727687 | G13: - | H13: 852.57306 | I13: - | J13: 2.1608857 | K13: 0.49490799 | L13: 36.474771 | M13: 24.385329 | N13: 6.4885542 | O13: 5.2058966 | P13: 0.31566243 | Q13: 0.46420945
A14: 9 | B14: Mechanical Equipment | C14: CHINT POWER | D14: 002150.SZ | E14: 23.39 | F14: 16.368159 | G14: 28 | H14: 545.43216 | I14: 19.709277 | J14: 0.38023212 | K14: 0.40648576 | L14: 21.399817 | M14: 15.287582 | N14: 3.3083451 | O14: 2.7071759 | P14: 0.72680633 | Q14: -
A15: 10 | B15: Elec EQPT, Grid | C15: MEGMEET | D15: 002851.SZ | E15: 117.6 | F15: 30.565116 | G15: - | H15: 1967.0426 | I15: - | J15: 1.9381503 | K15: 0.58601101 | L15: 69.014085 | M15: 40.692042 | N15: 8.4928143 | O15: 7.006673 | P15: 0.23979592 | Q15: 0.15306122
A16: 11 | B16: Elec EQPT, Grid | C16: NARI-TECH | D16: 600406.SH | E16: 25.24 | F16: 12.27758 | G16: 29.2 | H16: 1818.2427 | I16: 15.689382 | J16: 0.12762595 | K16: 0.11641546 | L16: 21.499148 | M16: 19.106737 | N16: 3.4349483 | O16: 3.1129748 | P16: 2.3652932 | Q16: 2.5515055
A17: 12 | B17: Elec EQPT, Grid | C17: CATL | D17: 300750.SZ | E17: 362.94 | F17: -1.1762784 | G17: 445 | H17: 10541.293 | I17: 22.609798 | J17: 0.26340254 | K17: 0.21693317 | L17: 18.951491 | M17: 15.673691 | N17: 4.4242631 | O17: 3.7557821 | P17: 2.283022 | Q17: 2.6453408
A18: 13 | B18: Non-ferrous Metals | C18: CMOC | D18: 603993.SH | E18: 22.17 | F18: 10.85 | G18: 35 | H18: 5272.3032 | I18: 57.870997 | J18: 0.33324918 | K18: 0.070007754 | L18: 18.383085 | M18: 16.569507 | N18: 4.6565848 | O18: 3.9504633 | P18: 2.2868742 | Q18: 2.5078935
A19: 14 | B19: Non-ferrous Metals | C19: XINGYE SILVER&TIN | D19: 000426.SZ | E19: 50.02 | F19: 40.505618 | G19: 85 | H19: 3288.3885 | I19: 69.932027 | J19: 0.27045358 | K19: 0.17755182 | L19: 34.736111 | M19: 29.545186 | N19: 7.4070783 | O19: 6.0461743 | P19: 0.40983607 | Q19: 0.46981208
A20: 15 | B20: Communication | C20: ZHONGJI INNOLIGHT | D20: 300308.SZ | E20: 561.99 | F20: -7.8704918 | G20: 830 | H20: 19010.014 | I20: 47.689461 | J20: 1.1335218 | K20: 0.29975577 | L20: 28.458072 | M20: 21.2875 | N20: 12.228073 | O20: 7.9884861 | P20: 0.51566754 | Q20: 0.74449723
A21: 16 | B21: Electronics | C21: FII | D21: 601138.SH | E21: 53.88 | F21: -12.692887 | G21: 79 | H21: 11288.077 | I21: 46.622123 | J21: 0.81222013 | K21: 0.26628977 | L21: 16.964736 | M21: 13.402985 | N21: 5.0018567 | O21: 4.1123493 | P21: 2.9008909 | Q21: 3.6247216
A22: 17 | B22: Electronics | C22: AMEC | D22: 688012.SH | E22: 356.88 | F22: 30.85949 | G22: 480 | H22: 4532.7343 | I22: 34.498991 | J22: 0.53482864 | K22: 0.3586761 | L22: 68.71005 | M22: 50.578231 | N22: 8.911529 | O22: 7.6586978 | P22: 0.12833445 | Q22: 0.29757902
A23: 18 | B23: Electronics | C23: ACCOTEST | D23: 688200.SH | E23: 272.9 | F23: 43.480547 | G23: 368 | H23: 558.02002 | I23: 34.84793 | J23: 0.25989881 | K23: 0.23554214 | L23: 55.979487 | M23: 44.482478 | N23: 8.2701982 | O23: 7.2516143 | P23: 0.50311469 | Q23: 0.6112129
A24: 19 | B24: Electronics | C24: JCET | D24: 600584.SH | E24: 44.66 | F24: 21.424687 | G24: 83 | H24: 2986.0818 | I24: 85.848634 | J24: 0.48751128 | K24: 0.26311574 | L24: 34.40678 | M24: 27.115968 | N24: 2.5999884 | O24: 2.4063797 | P24: 0.45006717 | Q24: 0.62024183
A25: 20 | B25: Mechanical Equipment | C25: JEREH GROUP | D25: 002353.SZ | E25: 87 | F25: 22.82931 | G25: 100 | H25: 1458.2178 | I25: 14.942529 | J25: 0.23791352 | K25: 0.1822608 | L25: 23.268254 | M25: 19.638826 | N25: 3.3385778 | O25: 2.9415742 | P25: 1.0678161 | Q25: 1.2448276
A26: 21 | B26: Communication | C26: CICT MOBILE | D26: 688387.SH | E26: 16.67 | F26: 29.224806 | G26: 22.61 | H26: 1859.4751 | I26: 35.632873 | J26: -2.3135314 | K26: 1.0596194 | L26: 595.35714 | M26: 264.60317 | N26: 9.1342466 | O26: 8.6822917 | P26: - | Q26: -
A27: 22 | B27: National Defense | C27: AVIC HI-TECH | D27: 600862.SH | E27: 25.81 | F27: 9.2255607 | G27: 27.61 | H27: 824.86172 | I27: 6.9740411 | J27: 0.1674777 | K27: 0.14183189 | L27: 24.937198 | M27: 21.872881 | N27: 3.8407738 | O27: 3.3333333 | P27: 1.0461062 | Q27: 1.1623402
B29: Sector | C29: Stock name | D29: Ticker | E29: Price | F29: Chg. YTD (%) | G29: TP | H29: Turnover Avg | I29: Up/ down (%) | J29: Earnings growth (%) | L29: P/E (x) | N29: P/B (x) | P29: Div. Yield （%）
H30: 3M, mn | J30: 26E | K30: 27E | L30: 26E | M30: 27E | N30: 26E | O30: 27E | P30: 26E | Q30: 27E
A31: 1 | B31: Information Technology | C31: NETEASE-S | D31: 9999.HK | E31: 192.6 | F31: -10.251631 | G31: 275 | H31: 1231.3437 | I31: 42.78297 | J31: 0.059719423 | K31: 0.10463082 | L31: 13.249085 | M31: 11.986472 | N31: 2.86723 | O31: 2.5002037 | P31: 2.5482445 | Q31: 2.9633061
A32: 2 | B32: Consumer Discretionary | C32: KUAISHOU-W | D32: 1024.HK | E32: 73 | F32: 14.151681 | G32: 89 | H32: 2502.5486 | I32: 21.917808 | J32: 0.12951113 | K32: 0.16184041 | L32: 11.944625 | M32: 10.289704 | N32: 2.7376356 | O32: 2.1935725 | P32: 0 | Q32: 0
A33: 3 | B33: Consumer Discretionary | C33: ALIBABA-W | D33: 9988.HK | E33: 159.6 | F33: 11.764706 | G33: 197 | H33: 14055.417 | I33: 23.433584 | J33: -0.34751305 | K33: 0.40574861 | L33: 26.30354 | M33: 18.409062 | N33: 2.4002197 | O33: 2.3695655 | P33: 0.6560857 | Q33: 0.76402238
A34: 4 | B34: Information Technology | C34: TENCENT | D34: 0700.HK | E34: 558.5 | F34: -6.7612688 | G34: 700 | H34: 12088.018 | I34: 25.335721 | J34: 0.12580609 | K34: 0.10838203 | L34: 15.69335 | M34: 14.109552 | N34: 3.2605378 | O34: 2.7732235 | P34: 1.1460876 | Q34: 1.281965
A35: 5 | B35: Industrials | C35: GOLDWIND | D35: 2208.HK | E35: 13.12 | F35: -2.1625652 | G35: 21.8 | H35: 638.33021 | I35: 66.158537 | J35: 0.34964021 | K35: 0.19037273 | L35: 11.108306 | M35: 9.3896963 | N35: 1.1121028 | O35: 1.0268429 | P35: 2.7719104 | Q35: 3.2524894
A36: 6 | B36: Materials | C36: NANSHAN AL INTL | D36: 2610.HK | E36: 61.7 | F36: 27.374071 | G36: 100 | H36: 159.91573 | I36: 62.074554 | J36: 0.3368984 | K36: - | L36: 9.2910565 | M36: - | N36: 1.9842709 | O36: - | P36: 2.1526077 | Q36: -
A37: 7 | B37: Materials | C37: ZIJIN GOLD INTL | D37: 2259.HK | E37: 205.8 | F37: 40.958904 | G37: 300 | H37: 842.59944 | I37: 45.772595 | J37: 1.1766383 | K37: 0.10729446 | L37: 22.399427 | M37: 20.278465 | N37: 7.7339185 | O37: 5.8982818 | P37: 0.70610406 | Q37: 0.88452821
A38: 8 | B38: Materials | C38: LYGEND RESOURCE | D38: 2245.HK | E38: 25.58 | F38: 11.996497 | G38: 30 | H38: 117.38818 | I38: 17.279124 | J38: 0.55620053 | K38: 0.21125805 | L38: 9.3494004 | M38: 8.5409936 | N38: 2.0375823 | O38: 1.4685871 | P38: 6.5583749 | Q38: -
A39: 9 | B39: Information Technology | C39: YOFC | D39: 6869.HK | E39: 86.5 | F39: 67.311412 | G39: 97 | H39: 1410.2525 | I39: 12.138728 | J39: 0.75309754 | K39: 0.39360062 | L39: 38.032444 | M39: 27.379022 | N39: 4.2258271 | O39: 3.7543633 | P39: 0.70289129 | Q39: 1.0699567
A40: 10 | B40: Industrials | C40: SANY INT'L | D40: 0631.HK | E40: 12.9 | F40: 48.960739 | G40: 14.7 | H40: 99.659225 | I40: 13.953488 | J40: 0.26421053 | K40: 0.24612823 | L40: 12.975333 | M40: 10.638086 | N40: 2.3382079 | O40: 2.0441068 | P40: 4.1894985 | Q40: 5.6732792

Sheet Summary-A share
B1: Updated | C1: 46062
B2: Sector | C2: Market cap （Rmb bn） | D2: Weight of market cap | E2: Free-float market value （Rmb bn） | F2: Weight of free-float market value | G2: Number of covered companies | H2: Proportion | I2: P/E (x) | O2: P/B(x) | U2: Dividend yield | AA2: ROE | AG2: Income (YoY) | AL2: Net profit(YoY)
I3: 2023A | J3: 2024A | K3: 2025E | L3: 2026E | M3: 2027E | N3: 2028E | O3: 2023A | P3: 2024A | Q3: 2025E | R3: 2026E | S3: 2027E | T3: 2028E | U3: 2023A | V3: 2024A | W3: 2025E | X3: 2026E | Y3: 2027E | Z3: 2028E | AA3: 2023A | AB3: 2024A | AC3: 2025E | AD3: 2026E | AE3: 2027E | AF3: 2028E | AG3: 2024A | AH3: 2025E | AI3: 2026E | AJ3: 2027E | AK3: 2028E | AL3: 2024A | AM3: 2025E | AN3: 2026E | AO3: 2027E | AP3: 2028E
B5: CICC covered companies-A share | C5: 69057.772 | D5: 1 | E5: 53653.958 | F5: 1 | G5: 1081 | H5: 1 | I5: 17.109596 | J5: 16.57237 | K5: 15.532857 | L5: 13.831363 | M5: 16.074216 | N5: 93.107388 | O5: 1.5208479 | P5: 1.4353903 | Q5: 1.4919398 | R5: 1.4064272 | S5: 1.5670892 | T5: 12.551605 | U5: 0.022913534 | V5: 0.024297942 | W5: 0.024947912 | X5: 0.027192556 | Y5: 0.022395327 | Z5: 0.0044931625 | AA5: 0.088888591 | AB5: 0.08661346 | AC5: 0.096050569 | AD5: 0.10168392 | AE5: 0.097490864 | AF5: 0.12257694 | AG5: 0.0081662946 | AH5: -0.081592504 | AI5: 0.036907714 | AJ5: -0.20874729 | AK5: -0.68088213 | AL5: 0.032416982 | AM5: 0.066923429 | AN5: 0.1230171 | AO5: -0.13953106 | AP5: =SUMIFS('A share covered list'!AC4:AC9640,'A share covered list'!AC4:AC9640,"<>0",'A share covered list'!AB4:AB9640,"<>0")/SUMIFS('A share covered list'!AB4:AB9640,'A share covered list'!AC4:AC9640,"<>0",'A share covered list'!AB4:AB9640,"<>0")-1 -> -0.82735832
B6: Financials | C6: 19429.734 | D6: 0.28135478 | E6: 13285.502 | F6: 0.24761458 | G6: 45 | H6: 0.041628122 | I6: 8.8843216 | J6: 8.0161494 | K6: 7.7500798 | L6: 7.2170522 | M6: 7.1937952 | N6: - | O6: 0.79054011 | P6: 0.73773443 | Q6: 0.69377519 | R6: 0.64823661 | S6: 0.61710183 | T6: - | U6: 0.034763445 | V6: 0.036729716 | W6: 0.038941667 | X6: 0.040301306 | Y6: 0.041234162 | Z6: 0.00013180055 | AA6: 0.088981483 | AB6: 0.092031023 | AC6: 0.089518458 | AD6: 0.089820136 | AE6: 0.085782513 | AF6: - | AG6: 0.0031817869 | AH6: -0.11256208 | AI6: 0.034339873 | AJ6: 0.03260908 | AK6: - | AL6: 0.10830289 | AM6: 0.03433121 | AN6: 0.073856686 | AO6: 0.0032329233 | AP6: -
B7: Non-financials | C7: 49628.038 | D7: 0.71864522 | E7: 40368.455 | F7: 0.75238542 | G7: 1036 | H7: 0.95837188 | I7: 26.80126 | J7: 28.421204 | K7: 25.557308 | L7: 21.543039 | M7: 31.040978 | N7: 67.253269 | O7: 2.3793994 | P7: 2.2761106 | Q7: 2.7094462 | R7: 2.5893312 | S7: 3.9303168 | T7: 9.0975577 | U7: 0.018285121 | V7: 0.019442261 | W7: 0.019482143 | X7: 0.022072458 | Y7: 0.015037136 | Z7: 0.0061967071 | AA7: 0.088779388 | AB7: 0.080084946 | AC7: 0.10601454 | AD7: 0.1201934 | AE7: 0.12661704 | AF7: 0.13527309 | AG7: 0.0095223859 | AH7: -0.073219803 | AI7: 0.037572466 | AJ7: -0.27103397 | AK7: -0.56454941 | AL7: -0.056997752 | AM7: 0.11205782 | AN7: 0.18633718 | AO7: -0.30598067 | AP7: =(SUMIFS('A share covered list'!AC4:AC9640,'A share covered list'!AC4:AC9640,"<>0",'A share covered list'!AB4:AB9640,"<>0")-SUMIFS('A share covered list'!AC$4:AC$9640,'A share covered list'!$E$4:$E$9640,'Summary-A share'!$B23,'A share covered list'!AC$4:AC$9640,"<>0",'A share covered list'!AB$4:AB$9640,"<>0")-SUMIFS('A share covered list'!AC$4:AC$9640,'A share covered list'!$E$4:$E$9640,'Summary-A share'!$B24,'A share covered list'!AC$4:AC$9640,"<>0",'A share covered list'!AB$4:AB$9640,"<>0")-SUMIFS('A share covered list'!AC$4:AC$9640,'A share covered list'!$E$4:$E$9640,'Summary-A share'!$B25,'A share covered list'!AC$4:AC$9640,"<>0",'A share covered list'!AB$4:AB$9640,"<>0"))/(SUMIFS('A share covered list'!AB4:AB9640,'A share covered list'!AC4:AC9640,"<>0",'A share covered list'!AB4:AB9640,"<>0")-(SUMIFS('A share covered list'!AB$4:AB$9640,'A share covered list'!$E$4:$E$9640,'Summary-A share'!$B23,'A share covered list'!AC$4:AC$9640,"<>0",'A share covered list'!AB$4:AB$9640,"<>0")+SUMIFS('A share covered list'!AB$4:AB$9640,'A share covered list'!$E$4:$E$9640,'Summary-A share'!$B24,'A share covered list'!AC$4:AC$9640,"<>0",'A share covered list'!AB$4:AB$9640,"<>0")+SUMIFS('A share covered list'!AB$4:AB$9640,'A share covered list'!$E$4:$E$9640,'Summary-A share'!$B25,'A share covered list'!AC$4:AC$9640,"<>0",'A share covered list'!AB$4:AB$9640,"<>0")))-1 -> -0.53844655
B8: Main board | C8: 56870.87 | D8: 0.82352599 | E8: 44152.059 | F8: 0.82290405 | G8: 720 | H8: 0.66604995 | I8: 14.841383 | J8: 14.269502 | K8: 13.599091 | L8: 12.207929 | M8: 14.129822 | N8: 107.96956 | O8: 1.3248433 | P8: 1.2502298 | Q8: 1.30299 | R8: 1.2264618 | S8: 1.3437893 | T8: 13.025527 | U8: 0.0263325 | V8: 0.027930561 | W8: 0.028567686 | X8: 0.030867819 | Y8: 0.025302342 | Z8: 0.0037486945 | AA8: 0.08926684 | AB8: 0.087615517 | AC8: 0.095814492 | AD8: 0.10046436 | AE8: 0.095103064 | AF8: 0.12064073 | AG8: 0.0088224964 | AH8: -0.09753299 | AI8: 0.031168125 | AJ8: -0.20198356 | AK8: -0.70930329 | AL8: 0.040077104 | AM8: 0.049298253 | AN8: 0.11395563 | AO8: -0.13601677 | AP8: =IFERROR(SUMIFS('A share covered list'!AC$4:AC$9640,'A share covered list'!$C$4:$C$9640,'Summary-A share'!$B8,'A share covered list'!AC$4:AC$9640,"<>0",'A share covered list'!AB$4:AB$9640,"<>0")/SUMIFS('A share covered list'!AB$4:AB$9640,'A share covered list'!$C$4:$C$9640,'Summary-A share'!$B8,'A share covered list'!AC$4:AC$9640,"<>0",'A share covered list'!AB$4:AB$9640,"<>0"),"-")-1 -> -0.86913144
B9: ChiNext Board | C9: 6975.7353 | D9: 0.10101304 | E9: 5854.8854 | F9: 0.10912309 | G9: 203 | H9: 0.18778908 | I9: 43.379169 | J9: 42.100341 | K9: 32.37862 | L9: 27.388485 | M9: 30.445906 | N9: 39.515821 | O9: 4.5600909 | P9: 4.2250628 | Q9: 4.0241043 | R9: 3.8432223 | S9: 4.9405468 | T9: 7.9657108 | U9: 0.009738444 | V9: 0.010927378 | W9: 0.012006274 | X9: 0.014762933 | Y9: 0.013396408 | Z9: 0.012053498 | AA9: 0.10512167 | AB9: 0.10035697 | AC9: 0.12428276 | AD9: 0.14032256 | AE9: 0.16227294 | AF9: 0.20158283 | AG9: 0.0086459811 | AH9: 0.13053457 | AI9: 0.080482844 | AJ9: -0.2060675 | AK9: -0.34813846 | AL9: 0.030375721 | AM9: 0.30025125 | AN9: 0.18219829 | AO9: -0.10042144 | AP9: =IFERROR(SUMIFS('A share covered list'!AC$4:AC$9640,'A share covered list'!$C$4:$C$9640,'Summary-A share'!$B9,'A share covered list'!AC$4:AC$9640,"<>0",'A share covered list'!AB$4:AB$9640,"<>0")/SUMIFS('A share covered list'!AB$4:AB$9640,'A share covered list'!$C$4:$C$9640,'Summary-A share'!$B9,'A share covered list'!AC$4:AC$9640,"<>0",'A share covered list'!AB$4:AB$9640,"<>0"),"-")-1 -> #VALUE!
B10: SSE STAR Market | C10: 5211.1666 | D10: 0.075460972 | E10: 3647.0133 | F10: 0.067972867 | G10: 158 | H10: 0.14616096 | I10: 108.97746 | J10: 246.58431 | K10: 99.006501 | L10: 61.432022 | M10: 106.08977 | N10: 131.76478 | O10: 5.1580773 | P10: 5.0412999 | Q10: 5.4077011 | R10: 5.317531 | S10: 12.857487 | T10: 19.418123 | U10: 0.0036123627 | V10: 0.0029943371 | W10: 0.0032735549 | X10: 0.0042757182 | Y10: 0.0032129389 | Z10: 0.0025982666 | AA10: 0.047331597 | AB10: 0.020444528 | AC10: 0.054619656 | AD10: 0.086559596 | AE10: 0.12119441 | AF10: 0.1473696 | AG10: -0.024844881 | AH10: 0.15901736 | AI10: 0.15917445 | AJ10: -0.45067627 | AK10: -0.39067091 | AL10: -0.55805193 | AM10: 1.4905871 | AN10: 0.61164322 | AO10: -0.42094302 | AP10: =IFERROR(SUMIFS('A share covered list'!AC$4:AC$9640,'A share covered list'!$C$4:$C$9640,'Summary-A share'!$B10,'A share covered list'!AC$4:AC$9640,"<>0",'A share covered list'!AB$4:AB$9640,"<>0")/SUMIFS('A share covered list'!AB$4:AB$9640,'A share covered list'!$C$4:$C$9640,'Summary-A share'!$B10,'A share covered list'!AC$4:AC$9640,"<>0",'A share covered list'!AB$4:AB$9640,"<>0"),"-")-1 -> -0.19485488
B11: Oil & gas | C11: 3231.2096 | D11: 0.046710804 | E11: 1461.3131 | F11: 0.027193271 | G11: 14 | H11: 0.012738854 | I11: 15.901428 | J11: 15.593672 | K11: 20.465644 | L11: 18.515026 | M11: 113.40196 | N11: 729.74026 | O11: 1.5861838 | P11: 1.4970662 | Q11: 2.7086909 | R11: 2.4868846 | S11: 13.179308 | T11: 57.943005 | U11: 0.032625993 | V11: 0.032329123 | W11: 0.021528885 | X11: 0.023823954 | Y11: 0.0026339579 | Z11: 0.00047962224 | AA11: 0.099751029 | AB11: 0.096004727 | AC11: 0.13235307 | AD11: 0.1343171 | AE11: 0.11621764 | AF11: 0.079402231 | AG11: -0.022814055 | AH11: -0.66150383 | AI11: 0.072093047 | AJ11: -0.53433868 | AK11: -0.92969642 | AL11: 0.019735943 | AM11: -0.23805612 | AN11: 0.10535323 | AO11: -0.83673098 | AP11: =IFERROR(SUMIFS('A share covered list'!AC$4:AC$9640,'A share covered list'!$E$4:$E$9640,'Summary-A share'!$B11,'A share covered list'!AC$4:AC$9640,"<>0",'A share covered list'!AB$4:AB$9640,"<>0")/SUMIFS('A share covered list'!AB$4:AB$9640,'A share covered list'!$E$4:$E$9640,'Summary-A share'!$B11,'A share covered list'!AC$4:AC$9640,"<>0",'A share covered list'!AB$4:AB$9640,"<>0")-1,"-") -> -0.84459956
B12: Non-ferrous metals | C12: 3387.5699 | D12: 0.04897117 | E12: 2885.7354 | F12: 0.053700049 | G12: 31 | H12: 0.028207461 | I12: 45.273441 | J12: 35.939361 | K12: 27.079972 | L12: 18.816756 | M12: 26.492578 | N12: 389.45957 | O12: 4.2971973 | P12: 3.8353598 | Q12: 4.6852834 | R12: 3.9414839 | S12: 5.8241488 | T12: 87.381427 | U12: 0.0080912876 | V12: 0.010361195 | W12: 0.012211653 | X12: 0.017386699 | Y12: 0.011958682 | Z12: 0.00041280329 | AA12: 0.094916518 | AB12: 0.10671753 | AC12: 0.17301655 | AD12: 0.2094667 | AE12: 0.21984077 | AF12: 0.16046519 | AG12: 0.0330362 | AH12: -0.021420413 | AI12: 0.12300225 | AJ12: -0.39794899 | AK12: -0.84970009 | AL12: 0.25971748 | AM12: 0.32715648 | AN12: 0.43914135 | AO12: -0.2897348 | AP12: =IFERROR(SUMIFS('A share covered list'!AC$4:AC$9640,'A share covered list'!$E$4:$E$9640,'Summary-A share'!$B12,'A share covered list'!AC$4:AC$9640,"<>0",'A share covered list'!AB$4:AB$9640,"<>0")/SUMIFS('A share covered list'!AB$4:AB$9640,'A share covered list'!$E$4:$E$9640,'Summary-A share'!$B12,'A share covered list'!AC$4:AC$9640,"<>0",'A share covered list'!AB$4:AB$9640,"<>0")-1,"-") -> -0.93197605
B13: Coal | C13: 639.07978 | D13: 0.0092386239 | E13: 516.79903 | F13: 0.0096170053 | G13: 6 | H13: 0.0054595086 | I13: 8.5851017 | J13: 9.6653331 | K13: 13.310374 | L13: 12.051706 | M13: 316.74776 | N13: - | O13: 1.2284673 | P13: 1.1478266 | Q13: 1.3609775 | R13: 1.282166 | S13: 30.184555 | T13: - | U13: 0.059550338 | V13: 0.049838326 | W13: 0.037811633 | X13: 0.041507869 | Y13: 0.0014207146 | Z13: 0 | AA13: 0.14309293 | AB13: 0.11875706 | AC13: 0.10224938 | AD13: 0.10638876 | AE13: 0.095295245 | AF13: - | AG13: -0.016461975 | AH13: -0.10480736 | AI13: 0.019096156 | AJ13: -0.9765278 | AK13: -1 | AL13: -0.11176349 | AM13: -0.27384963 | AN13: 0.10443903 | AO13: -0.96195173 | AP13: =IFERROR(SUMIFS('A share covered list'!AC$4:AC$9640,'A share covered list'!$E$4:$E$9640,'Summary-A share'!$B13,'A share covered list'!AC$4:AC$9640,"<>0",'A share covered list'!AB$4:AB$9640,"<>0")/SUMIFS('A share covered list'!AB$4:AB$9640,'A share covered list'!$E$4:$E$9640,'Summary-A share'!$B13,'A share covered list'!AC$4:AC$9640,"<>0",'A share covered list'!AB$4:AB$9640,"<>0")-1,"-") -> -1
B14: Construction materials | C14: 551.1975 | D14: 0.0079681858 | E14: 485.18694 | F14: 0.0090287425 | G14: 19 | H14: 0.017288444 | I14: 19.329198 | J14: 33.82873 | K14: 21.251512 | L14: 17.371176 | M14: 18.259971 | N14: 375.38052 | O14: 1.073516 | P14: 1.0766238 | Q14: 1.1604991 | R14: 1.1147308 | S14: 1.5161251 | T14: 43.656926 | U14: 0.026634419 | V14: 0.025151076 | W14: 0.022187111 | X14: 0.026748053 | Y14: 0.026586169 | Z14: 0.0023324308 | AA14: 0.055538568 | AB14: 0.031825723 | AC14: 0.054607837 | AD14: 0.06417129 | AE14: 0.083029981 | AF14: 0.11630045 | AG14: -0.1361507 | AH14: 0.026540257 | AI14: 0.041441724 | AJ14: -0.43140181 | AK14: -0.9638647 | AL14: -0.4286159 | AM14: 0.59182695 | AN14: 0.22337785 | AO14: -0.048674496 | AP14: =IFERROR(SUMIFS('A share covered list'!AC$4:AC$9640,'A share covered list'!$E$4:$E$9640,'Summary-A share'!$B14,'A share covered list'!AC$4:AC$9640,"<>0",'A share covered list'!AB$4:AB$9640,"<>0")/SUMIFS('A share covered list'!AB$4:AB$9640,'A share covered list'!$E$4:$E$9640,'Summary-A share'!$B14,'A share covered list'!AC$4:AC$9640,"<>0",'A share covered list'!AB$4:AB$9640,"<>0")-1,"-") -> -0.9513561
B15: Steel | C15: 119.48396 | D15: 0.0017272763 | E15: 111.93292 | F15: 0.0020829364 | G15: 5 | H15: 0.0045495905 | I15: 33.208728 | J15: -29.840254 | K15: 17.511195 | L15: 13.664836 | M15: 118.93448 | N15: 98.236407 | O15: 0.61280482 | P15: 0.62988582 | Q15: 0.69136808 | R15: 0.66459922 | S15: 11.770369 | T15: 10.836987 | U15: 0.018676148 | V15: 0.0094654616 | W15: 0.016111284 | X15: 0.025961895 | Y15: 0.0028620578 | Z15: 0.003455945 | AA15: 0.018453125 | AB15: -0.021108594 | AC15: 0.039481491 | AD15: 0.048635726 | AE15: 0.098965152 | AF15: 0.081627591 | AG15: -0.072008687 | AH15: 0.052995998 | AI15: 0.016374368 | AJ15: -0.96497257 | AK15: 0.12562725 | AL15: -2.1128836 | AM15: -2.7040673 | AN15: 0.28147858 | AO15: -0.88510619 | AP15: =IFERROR(SUMIFS('A share covered list'!AC$4:AC$9640,'A share covered list'!$E$4:$E$9640,'Summary-A share'!$B15,'A share covered list'!AC$4:AC$9640,"<>0",'A share covered list'!AB$4:AB$9640,"<>0")/SUMIFS('A share covered list'!AB$4:AB$9640,'A share covered list'!$E$4:$E$9640,'Summary-A share'!$B15,'A share covered list'!AC$4:AC$9640,"<>0",'A share covered list'!AB$4:AB$9640,"<>0")-1,"-") -> 0.21069658
B16: Chemicals | C16: 2289.0039 | D16: 0.033090151 | E16: 2156.7935 | F16: 0.04013532 | G16: 88 | H16: 0.080072793 | I16: 28.516359 | J16: 31.284165 | K16: 22.63943 | L16: 19.063974 | M16: 28.437809 | N16: 148.75581 | O16: 2.6355826 | P16: 2.5032707 | Q16: 2.4532587 | R16: 2.3957313 | S16: 4.1251177 | T16: 18.709133 | U16: 0.013651799 | V16: 0.014796977 | W16: 0.016738228 | X16: 0.021000759 | Y16: 0.013807268 | Z16: 0.0024597686 | AA16: 0.092423534 | AB16: 0.080017183 | AC16: 0.10836221 | AD16: 0.12566799 | AE16: 0.14505751 | AF16: 0.12651499 | AG16: 0.00026561483 | AH16: 0.087484878 | AI16: 0.040307516 | AJ16: -0.43917056 | AK16: -0.8032559 | AL16: -0.088473065 | AM16: 0.3818442 | AN16: 0.18755039 | AO16: -0.32962579 | AP16: =IFERROR(SUMIFS('A share covered list'!AC$4:AC$9640,'A share covered list'!$E$4:$E$9640,'Summary-A share'!$B16,'A share covered list'!AC$4:AC$9640,"<>0",'A share covered list'!AB$4:AB$9640,"<>0")/SUMIFS('A share covered list'!AB$4:AB$9640,'A share covered list'!$E$4:$E$9640,'Summary-A share'!$B16,'A share covered list'!AC$4:AC$9640,"<>0",'A share covered list'!AB$4:AB$9640,"<>0")-1,"-") -> -0.80882892
B17: Construction | C17: 533.58727 | D17: 0.0077136099 | E17: 486.80914 | F17: 0.0090589297 | G17: 15 | H17: 0.013648772 | I17: 6.0026216 | J17: 6.8139812 | K17: 9.1797639 | L17: 9.50859 | M17: 9.5962547 | N17: - | O17: 0.40125782 | P17: 0.38492516 | Q17: 0.8515732 | R17: 0.86147625 | S17: 0.85760648 | T17: - | U17: 0.03568134 | V17: 0.03556412 | W17: 0.027626577 | X17: 0.028162216 | Y17: 0.028071491 | Z17: 0 | AA17: 0.066847096 | AB17: 0.056490493 | AC17: 0.092766351 | AD17: 0.09059979 | AE17: 0.089368874 | AF17: - | AG17: -0.020348002 | AH17: -0.23787276 | AI17: -0.025483081 | AJ17: 0.029783801 | AK17: -1 | AL17: -0.11907277 | AM17: -0.25771716 | AN17: -0.034582007 | AO17: -0.0091353071 | AP17: =IFERROR(SUMIFS('A share covered list'!AC$4:AC$9640,'A share covered list'!$E$4:$E$9640,'Summary-A share'!$B17,'A share covered list'!AC$4:AC$9640,"<>0",'A share covered list'!AB$4:AB$9640,"<>0")/SUMIFS('A share covered list'!AB$4:AB$9640,'A share covered list'!$E$4:$E$9640,'Summary-A share'!$B17,'A share covered list'!AC$4:AC$9640,"<>0",'A share covered list'!AB$4:AB$9640,"<>0")-1,"-") -> -1
B18: Electricity and utilities | C18: 1676.0872 | D18: 0.024229744 | E18: 1565.2093 | F18: 0.029126653 | G18: 20 | H18: 0.018198362 | I18: 18.319936 | J18: 15.99587 | K18: 17.996598 | L18: 17.698773 | M18: 23.085653 | N18: 139.83334 | O18: 1.4986515 | P18: 1.3740206 | Q18: 2.3452058 | R18: 2.2201827 | S18: 3.0923956 | T18: 11.640094 | U18: 0.028175168 | V18: 0.032499005 | W18: 0.03016287 | X18: 0.031769528 | Y18: 0.026422569 | Z18: 0.0031868688 | AA18: 0.08180441 | AB18: 0.085898461 | AC18: 0.13031384 | AD18: 0.12544275 | AE18: 0.13395313 | AF18: - | AG18: -0.0090949627 | AH18: -0.20874799 | AI18: 0.007549803 | AJ18: -0.15674241 | AK18: -0.841832 | AL18: 0.14529164 | AM18: -0.11117257 | AN18: 0.016827447 | AO18: -0.23334322 | AP18: =IFERROR(SUMIFS('A share covered list'!AC$4:AC$9640,'A share covered list'!$E$4:$E$9640,'Summary-A share'!$B18,'A share covered list'!AC$4:AC$9640,"<>0",'A share covered list'!AB$4:AB$9640,"<>0")/SUMIFS('A share covered list'!AB$4:AB$9640,'A share covered list'!$E$4:$E$9640,'Summary-A share'!$B18,'A share covered list'!AC$4:AC$9640,"<>0",'A share covered list'!AB$4:AB$9640,"<>0")-1,"-") -> -0.83490595
B19: Electrical equipment and new energy | C19: 4522.7235 | D19: 0.065381104 | E19: 4117.9211 | F19: 0.076629535 | G19: 85 | H19: 0.077343039 | I19: 31.639604 | J19: 46.731455 | K19: 34.334637 | L19: 22.884536 | M19: 27.82912 | N19: 32.143301 | O19: 3.6470891 | P19: 3.4610145 | Q19: 3.6423226 | R19: 3.2922689 | S19: 5.2501975 | T19: 7.418759 | U19: 0.011892738 | V19: 0.011040997 | W19: 0.013172154 | X19: 0.017233335 | Y19: 0.01502224 | Z19: 0.015093823 | AA19: 0.11526974 | AB19: 0.074061774 | AC19: 0.10608304 | AD19: 0.14386435 | AE19: 0.18865841 | AF19: 0.13007907 | AG19: -0.058948696 | AH19: 0.052041834 | AI19: 0.20596972 | AJ19: -0.31294418 | AK19: -0.40317064 | AL19: -0.32294845 | AM19: 0.36105868 | AN19: 0.50034227 | AO19: -0.17767662 | AP19: =IFERROR(SUMIFS('A share covered list'!AC$4:AC$9640,'A share covered list'!$E$4:$E$9640,'Summary-A share'!$B19,'A share covered list'!AC$4:AC$9640,"<>0",'A share covered list'!AB$4:AB$9640,"<>0")/SUMIFS('A share covered list'!AB$4:AB$9640,'A share covered list'!$E$4:$E$9640,'Summary-A share'!$B19,'A share covered list'!AC$4:AC$9640,"<>0",'A share covered list'!AB$4:AB$9640,"<>0")-1,"-") -> -0.13421711
B20: Machinery | C20: 2730.3633 | D20: 0.039470502 | E20: 2414.7927 | F20: 0.044936373 | G20: 97 | H20: 0.088262056 | I20: 39.908997 | J20: 39.687874 | K20: 28.886082 | L20: 24.424531 | M20: 98.451464 | N20: 300.76275 | O20: 3.8740224 | P20: 3.6351558 | Q20: 3.506824 | R20: 3.3277478 | S20: 14.081867 | T20: 59.967155 | U20: 0.0092597898 | V20: 0.010400562 | W20: 0.012490924 | X20: 0.014643132 | Y20: 0.003327363 | Z20: 0.0014550078 | AA20: 0.097071406 | AB20: 0.091593613 | AC20: 0.12140186 | AD20: 0.13624613 | AE20: 0.1430336 | AF20: 0.19938358 | AG20: 0.054794719 | AH20: 0.1898947 | AI20: 0.10913677 | AJ20: -0.77314637 | AK20: -0.64184289 | AL20: 0.0055715259 | AM20: 0.37394453 | AN20: 0.18266683 | AO20: -0.75191298 | AP20: =IFERROR(SUMIFS('A share covered list'!AC$4:AC$9640,'A share covered list'!$E$4:$E$9640,'Summary-A share'!$B20,'A share covered list'!AC$4:AC$9640,"<>0",'A share covered list'!AB$4:AB$9640,"<>0")/SUMIFS('A share covered list'!AB$4:AB$9640,'A share covered list'!$E$4:$E$9640,'Summary-A share'!$B20,'A share covered list'!AC$4:AC$9640,"<>0",'A share covered list'!AB$4:AB$9640,"<>0")-1,"-") -> -0.67266071
B21: High-end equipment | C21: 1461.564 | D21: 0.021128567 | E21: 1409.5377 | F21: 0.026229793 | G21: 36 | H21: 0.032757052 | I21: 54.674724 | J21: 74.832901 | K21: 56.046313 | L21: 49.247836 | M21: 53.179979 | N21: 49.326502 | O21: 4.1034573 | P21: 3.8314233 | Q21: 3.9291572 | R21: 3.8609614 | S21: 4.278827 | T21: 4.2796936 | U21: 0.006519679 | V21: 0.0053441929 | W21: 0.00711143 | X21: 0.0097595043 | Y21: 0.0063371978 | Z21: 0.0067897883 | AA21: 0.075052181 | AB21: 0.051199715 | AC21: 0.070105544 | AD21: 0.078398601 | AE21: 0.080459358 | AF21: 0.081721663 | AG21: -0.035329157 | AH21: 0.11571677 | AI21: 0.10212887 | AJ21: -0.019982022 | AK21: 0.078289516 | AL21: -0.26937587 | AM21: 0.33519758 | AN21: 0.13804621 | AO21: -0.073940291 | AP21: =IFERROR(SUMIFS('A share covered list'!AC$4:AC$9640,'A share covered list'!$E$4:$E$9640,'Summary-A share'!$B21,'A share covered list'!AC$4:AC$9640,"<>0",'A share covered list'!AB$4:AB$9640,"<>0")/SUMIFS('A share covered list'!AB$4:AB$9640,'A share covered list'!$E$4:$E$9640,'Summary-A share'!$B21,'A share covered list'!AC$4:AC$9640,"<>0",'A share covered list'!AB$4:AB$9640,"<>0")-1,"-") -> 0.078121845
B22: Transportation and logistics | C22: 1512.4005 | D22: 0.021863466 | E22: 1354.8599 | F22: 0.025212306 | G22: 32 | H22: 0.029117379 | I22: 16.206947 | J22: 13.135002 | K22: 13.172316 | L22: 14.806722 | M22: 26.363266 | N22: 59.73266 | O22: 1.1150977 | P22: 1.0317878 | Q22: 1.2406855 | R22: 1.2757373 | S22: 1.9480398 | T22: 7.7142335 | U22: 0.029491674 | V22: 0.038463208 | W22: 0.035069613 | X22: 0.032194151 | Y22: 0.019125873 | Z22: 0.0087280784 | AA22: 0.06880369 | AB22: 0.078552539 | AC22: 0.094188865 | AD22: 0.086159334 | AE22: 0.073892203 | AF22: 0.12765412 | AG22: 0.041305483 | AH22: 0.31219025 | AI22: -0.54200608 | AJ22: -0.34991176 | AK22: -0.56538234 | AL22: 0.23387468 | AM22: -0.0028327002 | AN22: -0.11038273 | AO22: -0.43835784 | AP22: =IFERROR(SUMIFS('A share covered list'!AC$4:AC$9640,'A share covered list'!$E$4:$E$9640,'Summary-A share'!$B22,'A share covered list'!AC$4:AC$9640,"<>0",'A share covered list'!AB$4:AB$9640,"<>0")/SUMIFS('A share covered list'!AB$4:AB$9640,'A share covered list'!$E$4:$E$9640,'Summary-A share'!$B22,'A share covered list'!AC$4:AC$9640,"<>0",'A share covered list'!AB$4:AB$9640,"<>0")-1,"-") -> -0.5586457
B23: Banks | C23: 13519.8 | D23: 0.19544407 | E23: 8874.5526 | F23: 0.1651447 | G23: 22 | H23: 0.020018198 | I23: 6.9991547 | J23: 6.8559872 | K23: 6.7646664 | L23: 6.6391243 | M23: 6.5560644 | N23: - | O23: 0.65285819 | P23: 0.60987679 | Q23: 0.5619214 | R23: 0.52986573 | S23: 0.50862287 | T23: - | U23: 0.042285839 | V23: 0.043298417 | W23: 0.044129861 | X23: 0.044970108 | Y23: 0.045292185 | Z23: 0 | AA23: 0.093276719 | AB23: 0.088955357 | AC23: 0.083067127 | AD23: 0.079809582 | AE23: 0.077580518 | AF23: - | AG23: -0.0028779803 | AH23: 0.0089901987 | AI23: 0.024227601 | AJ23: 0.022587788 | AK23: -1 | AL23: 0.020882111 | AM23: 0.013499677 | AN23: 0.018909443 | AO23: 0.012669168 | AP23: =IFERROR(SUMIFS('A share covered list'!AC$4:AC$9640,'A share covered list'!$E$4:$E$9640,'Summary-A share'!$B23,'A share covered list'!AC$4:AC$9640,"<>0",'A share covered list'!AB$4:AB$9640,"<>0")/SUMIFS('A share covered list'!AB$4:AB$9640,'A share covered list'!$E$4:$E$9640,'Summary-A share'!$B23,'A share covered list'!AC$4:AC$9640,"<>0",'A share covered list'!AB$4:AB$9640,"<>0")-1,"-") -> -1
B24: Non-bank financials | C24: 5888.692 | D24: 0.08512773 | E24: 4390.8597 | F24: 0.081708592 | G24: 22 | H24: 0.020018198 | I24: 23.103979 | J24: 13.042428 | K24: 11.600651 | L24: 8.9911923 | M24: 9.2195293 | N24: 1790.0882 | O24: 1.5234308 | P24: 1.4136635 | Q24: 1.49428 | R24: 1.3227721 | S24: 1.2007276 | T24: 136.07991 | U24: 0.017550313 | V24: 0.021700072 | W24: 0.027170604 | X24: 0.029727617 | Y24: 0.032066119 | Z24: 0.00043440037 | AA24: 0.06593803 | AB24: 0.1083896 | AC24: 0.12881001 | AD24: 0.14711865 | AE24: 0.1302374 | AF24: 0.07601855 | AG24: 0.013755465 | AH24: -0.32028193 | AI24: 0.059705609 | AJ24: 0.06044195 | AK24: -0.99700627 | AL24: 0.77144773 | AM24: 0.12428411 | AN24: 0.29022387 | AO24: -0.024766663 | AP24: =IFERROR(SUMIFS('A share covered list'!AC$4:AC$9640,'A share covered list'!$E$4:$E$9640,'Summary-A share'!$B24,'A share covered list'!AC$4:AC$9640,"<>0",'A share covered list'!AB$4:AB$9640,"<>0")/SUMIFS('A share covered list'!AB$4:AB$9640,'A share covered list'!$E$4:$E$9640,'Summary-A share'!$B24,'A share covered list'!AC$4:AC$9640,"<>0",'A share covered list'!AB$4:AB$9640,"<>0")-1,"-") -> -0.99484968
B25: Diversified financials | C25: 21.24179 | D25: 0.0003070742 | E25: 20.09016 | F25: 0.0003738536 | G25: 1 | H25: 0.00090991811 | I25: 46.413604 | J25: 60.483693 | K25: 25.64102 | L25: 24.278274 | M25: - | N25: - | O25: 5.6654141 | P25: 6.2637584 | Q25: 4.2183487 | R25: 3.5939075 | S25: - | T25: - | U25: 0.018831274 | V25: 0.022485133 | W25: 0 | X25: 0 | Y25: 0 | Z25: 0 | AA25: 0.12206365 | AB25: 0.10356111 | AC25: 0.16451564 | AD25: 0.14802978 | AE25: - | AF25: - | AG25: -0.029630731 | AH25: 0.0919392 | AI25: 0.11241428 | AJ25: -1 | AK25: - | AL25: -0.23262616 | AM25: 1.3588646 | AN25: 0.056130271 | AO25: -1 | AP25: =IFERROR(SUMIFS('A share covered list'!AC$4:AC$9640,'A share covered list'!$E$4:$E$9640,'Summary-A share'!$B25,'A share covered list'!AC$4:AC$9640,"<>0",'A share covered list'!AB$4:AB$9640,"<>0")/SUMIFS('A share covered list'!AB$4:AB$9640,'A share covered list'!$E$4:$E$9640,'Summary-A share'!$B25,'A share covered list'!AC$4:AC$9640,"<>0",'A share covered list'!AB$4:AB$9640,"<>0")-1,"-") -> -
B26: Real estate | C26: 406.19472 | D26: 0.0058720059 | E26: 365.39004 | F26: 0.006799467 | G26: 15 | H26: 0.013648772 | I26: 29.744087 | J26: -5.6173573 | K26: -5.7437524 | L26: -11.113134 | M26: -22.357197 | N26: - | O26: 0.29386311 | P26: 0.32585799 | Q26: 0.61748601 | R26: 0.65942503 | S26: 0.72478357 | T26: - | U26: 0.016352589 | V26: 0.011360322 | W26: 0.013265067 | X26: 0.012776286 | Y26: 0.011319226 | Z26: 0 | AA26: 0.0098797153 | AB26: -0.058009127 | AC26: -0.10750568 | AD26: -0.059337449 | AE26: -0.032418356 | AF26: - | AG26: -0.16470524 | AH26: 0.0047049731 | AI26: -0.17635951 | AJ26: -0.21820717 | AK26: -1 | AL26: -6.295032 | AM26: -0.022005659 | AN26: -0.48315639 | AO26: -0.50292811 | AP26: =IFERROR(SUMIFS('A share covered list'!AC$4:AC$9640,'A share covered list'!$E$4:$E$9640,'Summary-A share'!$B26,'A share covered list'!AC$4:AC$9640,"<>0",'A share covered list'!AB$4:AB$9640,"<>0")/SUMIFS('A share covered list'!AB$4:AB$9640,'A share covered list'!$E$4:$E$9640,'Summary-A share'!$B26,'A share covered list'!AC$4:AC$9640,"<>0",'A share covered list'!AB$4:AB$9640,"<>0")-1,"-") -> -1
B27: Auto | C27: 2827.5237 | D27: 0.040875067 | E27: 2093.9544 | F27: 0.038965961 | G27: 60 | H27: 0.054595086 | I27: 27.155352 | J27: 24.115138 | K27: 21.341229 | L27: 16.05317 | M27: 15.446375 | N27: 14.844609 | O27: 2.7116152 | P27: 2.4553154 | Q27: 2.4040297 | R27: 2.1518765 | S27: 2.1333374 | T27: 1.9790357 | U27: 0.013332259 | V27: 0.016108556 | W27: 0.015687822 | X27: 0.021373935 | Y27: 0.020198557 | Z27: 0.021385437 | AA27: 0.099855646 | AB27: 0.10181635 | AC27: 0.1126472 | AD27: 0.13404683 | AE27: 0.13811249 | AF27: 0.13357733 | AG27: 0.11083313 | AH27: 0.10747442 | AI27: 0.16253904 | AJ27: 0.015706285 | AK27: 0.034420687 | AL27: 0.12607075 | AM27: 0.12997889 | AN27: 0.32940905 | AO27: 0.039283919 | AP27: =IFERROR(SUMIFS('A share covered list'!AC$4:AC$9640,'A share covered list'!$E$4:$E$9640,'Summary-A share'!$B27,'A share covered list'!AC$4:AC$9640,"<>0",'A share covered list'!AB$4:AB$9640,"<>0")/SUMIFS('A share covered list'!AB$4:AB$9640,'A share covered list'!$E$4:$E$9640,'Summary-A share'!$B27,'A share covered list'!AC$4:AC$9640,"<>0",'A share covered list'!AB$4:AB$9640,"<>0")-1,"-") -> 0.040537723
B28: Home appliances | C28: 850.89584 | D28: 0.012300666 | E28: 738.84027 | F28: 0.013748924 | G28: 30 | H28: 0.027297543 | I28: 12.440665 | J28: 11.646432 | K28: 11.44306 | L28: 10.479479 | M28: 157.40628 | N28: - | O28: 2.227483 | P28: 2.0293225 | Q28: 1.9815596 | R28: 1.8071958 | S28: 19.60416 | T28: - | U28: 0.040476815 | V28: 0.046555569 | W28: 0.04720123 | X28: 0.051457144 | Y28: 0.0028380559 | Z28: 0 | AA28: 0.17904855 | AB28: 0.17424413 | AC28: 0.17316693 | AD28: 0.17245093 | AE28: 0.12454497 | AF28: - | AG28: 0.035122723 | AH28: 0.029022693 | AI28: 0.066391838 | AJ28: -0.8755884 | AK28: -1 | AL28: 0.068195363 | AM28: 0.017772587 | AN28: 0.091949313 | AO28: -0.93342401 | AP28: =IFERROR(SUMIFS('A share covered list'!AC$4:AC$9640,'A share covered list'!$E$4:$E$9640,'Summary-A share'!$B28,'A share covered list'!AC$4:AC$9640,"<>0",'A share covered list'!AB$4:AB$9640,"<>0")/SUMIFS('A share covered list'!AB$4:AB$9640,'A share covered list'!$E$4:$E$9640,'Summary-A share'!$B28,'A share covered list'!AC$4:AC$9640,"<>0",'A share covered list'!AB$4:AB$9640,"<>0")-1,"-") -> -1
B29: Light manufacturing | C29: 515.03201 | D29: 0.0074453725 | E29: 461.25356 | F29: 0.0085833713 | G29: 48 | H29: 0.043676069 | I29: 21.929061 | J29: 25.322061 | K29: 18.075852 | L29: 18.13882 | M29: 27.866682 | N29: 67.494727 | O29: 2.2183231 | P29: 2.1306859 | Q29: 2.0299858 | R29: 2.1293929 | S29: 3.4359767 | T29: 8.8606286 | U29: 0.022216523 | V29: 0.023123981 | W29: 0.026370147 | X29: 0.026217108 | Y29: 0.015957998 | Z29: 0.007537182 | AA29: 0.10115906 | AB29: 0.084143461 | AC29: 0.11230374 | AD29: 0.11739424 | AE29: 0.12330053 | AF29: 0.12363505 | AG29: 0.011660835 | AH29: 0.13350954 | AI29: -0.074022897 | AJ29: -0.5054451 | AK29: -0.66042474 | AL29: -0.13399384 | AM29: 0.40087783 | AN29: -0.0034714009 | AO29: -0.34908577 | AP29: =IFERROR(SUMIFS('A share covered list'!AC$4:AC$9640,'A share covered list'!$E$4:$E$9640,'Summary-A share'!$B29,'A share covered list'!AC$4:AC$9640,"<>0",'A share covered list'!AB$4:AB$9640,"<>0")/SUMIFS('A share covered list'!AB$4:AB$9640,'A share covered list'!$E$4:$E$9640,'Summary-A share'!$B29,'A share covered list'!AC$4:AC$9640,"<>0",'A share covered list'!AB$4:AB$9640,"<>0")-1,"-") -> -0.58712802
B30: Textiles & apparel | C30: 268.5528 | D30: 0.0038822357 | E30: 251.14984 | F30: 0.004673595 | G30: 24 | H30: 0.021838035 | I30: 17.458926 | J30: 18.649305 | K30: 17.183805 | L30: 15.22674 | M30: 27.371116 | N30: 36.313983 | O30: 1.9442158 | P30: 1.887956 | Q30: 1.845143 | R30: 1.7903793 | S30: 3.5899983 | T30: 6.5471923 | U30: 0.037098354 | V30: 0.037736227 | W30: 0.035637424 | X30: 0.039385477 | Y30: 0.022044976 | Z30: 0.01524069 | AA30: 0.11135942 | AB30: 0.10123465 | AC30: 0.10737686 | AD30: 0.11758126 | AE30: 0.1311601 | AF30: 0.16904274 | AG30: 0.054680422 | AH30: 0.052858824 | AI30: 0.066580021 | AJ30: -0.520728 | AK30: -0.42724716 | AL30: -0.06382969 | AM30: 0.085283803 | AN30: 0.12852815 | AO30: -0.44369312 | AP30: =IFERROR(SUMIFS('A share covered list'!AC$4:AC$9640,'A share covered list'!$E$4:$E$9640,'Summary-A share'!$B30,'A share covered list'!AC$4:AC$9640,"<>0",'A share covered list'!AB$4:AB$9640,"<>0")/SUMIFS('A share covered list'!AB$4:AB$9640,'A share covered list'!$E$4:$E$9640,'Summary-A share'!$B30,'A share covered list'!AC$4:AC$9640,"<>0",'A share covered list'!AB$4:AB$9640,"<>0")-1,"-") -> -0.24626511
B31: Retail | C31: 371.91888 | D31: 0.0053765097 | E31: 339.59726 | F31: 0.0063194946 | G31: 22 | H31: 0.020018198 | I31: 25.691323 | J31: 30.800484 | K31: 25.850337 | L31: 19.723947 | M31: 127.77819 | N31: - | O31: 1.653194 | P31: 1.6085527 | Q31: 1.6837869 | R31: 1.6072629 | S31: 11.230659 | T31: - | U31: 0.01882656 | V31: 0.020887737 | W31: 0.023750959 | X31: 0.027368576 | Y31: 0.0037171278 | Z31: 0 | AA31: 0.064348342 | AB31: 0.052224917 | AC31: 0.065135976 | AD31: 0.081487895 | AE31: 0.087891826 | AF31: - | AG31: -0.091390958 | AH31: -0.050308418 | AI31: 0.058008816 | AJ31: -0.89266001 | AK31: -1 | AL31: -0.16587925 | AM31: 0.19149256 | AN31: 0.31060672 | AO31: -0.84563918 | AP31: =IFERROR(SUMIFS('A share covered list'!AC$4:AC$9640,'A share covered list'!$E$4:$E$9640,'Summary-A share'!$B31,'A share covered list'!AC$4:AC$9640,"<>0",'A share covered list'!AB$4:AB$9640,"<>0")/SUMIFS('A share covered list'!AB$4:AB$9640,'A share covered list'!$E$4:$E$9640,'Summary-A share'!$B31,'A share covered list'!AC$4:AC$9640,"<>0",'A share covered list'!AB$4:AB$9640,"<>0")-1,"-") -> -1
B32: Consumer services | C32: 317.36023 | D32: 0.0045878025 | E32: 285.27637 | F32: 0.0053086485 | G32: 13 | H32: 0.011828935 | I32: 30.138988 | J32: 32.422044 | K32: 35.450173 | L32: 27.965738 | M32: 50.10835 | N32: - | O32: 2.8638494 | P32: 2.7193524 | Q32: 2.8353739 | R32: 2.6285577 | S32: 4.6384545 | T32: - | U32: 0.015786158 | V32: 0.014369427 | W32: 0.013685804 | X32: 0.019194812 | Y32: 0.011405682 | Z32: 0 | AA32: 0.09502142 | AB32: 0.083873562 | AC32: 0.079981949 | AD32: 0.093992074 | AE32: 0.092568496 | AF32: - | AG32: 0.017759919 | AH32: 0.042910606 | AI32: 0.092314578 | AJ32: -0.61387842 | AK32: -1 | AL32: -0.070416792 | AM32: -0.08541929 | AN32: 0.26762873 | AO32: -0.44189465 | AP32: =IFERROR(SUMIFS('A share covered list'!AC$4:AC$9640,'A share covered list'!$E$4:$E$9640,'Summary-A share'!$B32,'A share covered list'!AC$4:AC$9640,"<>0",'A share covered list'!AB$4:AB$9640,"<>0")/SUMIFS('A share covered list'!AB$4:AB$9640,'A share covered list'!$E$4:$E$9640,'Summary-A share'!$B32,'A share covered list'!AC$4:AC$9640,"<>0",'A share covered list'!AB$4:AB$9640,"<>0")-1,"-") -> -1
B33: Food and beverage | C33: 4007.1283 | D33: 0.057927591 | E33: 3898.0271 | F33: 0.072537574 | G33: 59 | H33: 0.053685168 | I33: 20.558496 | J33: 19.627768 | K33: 19.968358 | L33: 19.929691 | M33: 26.67147 | N33: 169.58447 | O33: 4.7270454 | P33: 4.4678425 | Q33: 4.3617606 | R33: 4.2340655 | S33: 6.1891486 | T33: 27.554597 | U33: 0.033937257 | V33: 0.036736666 | W33: 0.03740124 | X33: 0.037673166 | Y33: 0.02269272 | Z33: 0.0038446161 | AA33: 0.22993148 | AB33: 0.22762866 | AC33: 0.21843361 | AD33: 0.21245014 | AE33: 0.23205127 | AF33: 0.16271026 | AG33: 0.027476382 | AH33: -0.024506584 | AI33: 0.013241586 | AJ33: -0.3501412 | AK33: -0.70537932 | AL33: 0.047418954 | AM33: -0.0170565 | AN33: 0.0019402125 | AO33: -0.25277121 | AP33: =IFERROR(SUMIFS('A share covered list'!AC$4:AC$9640,'A share covered list'!$E$4:$E$9640,'Summary-A share'!$B33,'A share covered list'!AC$4:AC$9640,"<>0",'A share covered list'!AB$4:AB$9640,"<>0")/SUMIFS('A share covered list'!AB$4:AB$9640,'A share covered list'!$E$4:$E$9640,'Summary-A share'!$B33,'A share covered list'!AC$4:AC$9640,"<>0",'A share covered list'!AB$4:AB$9640,"<>0")-1,"-") -> -0.84272457
B34: Agriculture | C34: 592.69352 | D34: 0.0085680579 | E34: 410.3423 | F34: 0.0076359743 | G34: 23 | H34: 0.020928116 | I34: 319.04081 | J34: 25.091358 | K34: 25.409747 | L34: 22.289253 | M34: 18.785342 | N34: 199.10023 | O34: 2.2950659 | P34: 2.170212 | Q34: 2.1810628 | R34: 2.0463612 | S34: 2.097011 | T34: 63.805612 | U34: 0.0086359407 | V34: 0.014127479 | W34: 0.014684453 | X34: 0.016317219 | Y34: 0.01978191 | Z34: 0.0011560612 | AA34: 0.0071936438 | AB34: 0.08649241 | AC34: 0.085835677 | AD34: 0.091809325 | AE34: 0.11163017 | AF34: 0.3204698 | AG34: -0.0057550846 | AH34: 0.062703766 | AI34: 0.060131846 | AJ34: 0.030636832 | AK34: -0.97783125 | AL34: 11.715167 | AM34: -0.012530196 | AN34: 0.13999993 | AO34: 0.18652364 | AP34: =IFERROR(SUMIFS('A share covered list'!AC$4:AC$9640,'A share covered list'!$E$4:$E$9640,'Summary-A share'!$B34,'A share covered list'!AC$4:AC$9640,"<>0",'A share covered list'!AB$4:AB$9640,"<>0")/SUMIFS('A share covered list'!AB$4:AB$9640,'A share covered list'!$E$4:$E$9640,'Summary-A share'!$B34,'A share covered list'!AC$4:AC$9640,"<>0",'A share covered list'!AB$4:AB$9640,"<>0")-1,"-") -> -0.90564882
B35: Pharmaceuticals | C35: 3562.4671 | D35: 0.051499507 | E35: 2835.078 | F35: 0.052757375 | G35: 91 | H35: 0.082802548 | I35: 34.576603 | J35: 37.613702 | K35: 28.661066 | L35: 25.580126 | M35: 33.508795 | N35: 45.525375 | O35: 3.4716149 | P35: 3.3368894 | Q35: 3.2973094 | R35: 3.052136 | S35: 4.0158556 | T35: 5.3249414 | U35: 0.013306391 | V35: 0.014047762 | W35: 0.014334982 | X35: 0.015936403 | Y35: 0.011652512 | Z35: 0.009168138 | AA35: 0.10040358 | AB35: 0.088714731 | AC35: 0.11504489 | AD35: 0.11931669 | AE35: 0.11984482 | AF35: 0.11697793 | AG35: 0.0081160667 | AH35: 0.071216676 | AI35: 0.079073659 | AJ35: -0.23119851 | AK35: -0.084520584 | AL35: -0.080744466 | AM35: 0.31236225 | AN35: 0.12044276 | AO35: -0.23661458 | AP35: =IFERROR(SUMIFS('A share covered list'!AC$4:AC$9640,'A share covered list'!$E$4:$E$9640,'Summary-A share'!$B35,'A share covered list'!AC$4:AC$9640,"<>0",'A share covered list'!AB$4:AB$9640,"<>0")/SUMIFS('A share covered list'!AB$4:AB$9640,'A share covered list'!$E$4:$E$9640,'Summary-A share'!$B35,'A share covered list'!AC$4:AC$9640,"<>0",'A share covered list'!AB$4:AB$9640,"<>0")-1,"-") -> -0.26395345
B36: Electronics | C36: 5708.7729 | D36: 0.082526795 | E36: 4646.4802 | F36: 0.086465381 | G36: 95 | H36: 0.08644222 | I36: 76.723279 | J36: 85.81219 | K36: 53.981555 | L36: 46.440101 | M36: 101.69868 | N36: 107.56612 | O36: 4.1350484 | P36: 4.0096845 | Q36: 4.8696042 | R36: 5.091011 | S36: 14.375037 | T36: 15.581873 | U36: 0.0048862778 | V36: 0.0046291062 | W36: 0.0056141715 | X36: 0.006525842 | Y36: 0.0033050746 | Z36: 0.003227233 | AA36: 0.053895616 | AB36: 0.046726281 | AC36: 0.090208669 | AD36: 0.10962532 | AE36: 0.1413493 | AF36: 0.14716852 | AG36: 0.1305826 | AH36: 0.075948171 | AI36: -0.07993593 | AJ36: -0.64180775 | AK36: -0.23867225 | AL36: -0.10591631 | AM36: 0.58965762 | AN36: 0.16239099 | AO36: -0.54335591 | AP36: =IFERROR(SUMIFS('A share covered list'!AC$4:AC$9640,'A share covered list'!$E$4:$E$9640,'Summary-A share'!$B36,'A share covered list'!AC$4:AC$9640,"<>0",'A share covered list'!AB$4:AB$9640,"<>0")/SUMIFS('A share covered list'!AB$4:AB$9640,'A share covered list'!$E$4:$E$9640,'Summary-A share'!$B36,'A share covered list'!AC$4:AC$9640,"<>0",'A share covered list'!AB$4:AB$9640,"<>0")-1,"-") -> -0.054547327
B37: Media | C37: 1057.1261 | D37: 0.015281958 | E37: 981.8994 | F37: 0.018271961 | G37: 33 | H37: 0.030027298 | I37: 36.586253 | J37: 54.683797 | K37: 31.851326 | L37: 22.853 | M37: 21.360393 | N37: 27.704607 | O37: 3.3819567 | P37: 3.388246 | Q37: 3.3154652 | R37: 3.0615481 | S37: 2.9559729 | T37: 4.7559294 | U37: 0.015243921 | V37: 0.015465391 | W37: 0.016227014 | X37: 0.019415698 | Y37: 0.022252824 | Z37: 0.017475465 | AA37: 0.092437907 | AB37: 0.061960694 | AC37: 0.10409191 | AD37: 0.13396701 | AE37: 0.1383857 | AF37: 0.17874605 | AG37: 0.039157245 | AH37: 0.098148311 | AI37: 0.10163819 | AJ37: 0.0098451344 | AK37: -0.22914936 | AL37: -0.33094892 | AM37: 0.71684524 | AN37: 0.39374812 | AO37: 0.069877307 | AP37: =IFERROR(SUMIFS('A share covered list'!AC$4:AC$9640,'A share covered list'!$E$4:$E$9640,'Summary-A share'!$B37,'A share covered list'!AC$4:AC$9640,"<>0",'A share covered list'!AB$4:AB$9640,"<>0")/SUMIFS('A share covered list'!AB$4:AB$9640,'A share covered list'!$E$4:$E$9640,'Summary-A share'!$B37,'A share covered list'!AC$4:AC$9640,"<>0",'A share covered list'!AB$4:AB$9640,"<>0")-1,"-") -> -0.2289949
B38: Computers | C38: 3278.8767 | D38: 0.047399887 | E38: 3015.8882 | F38: 0.056122034 | G38: 74 | H38: 0.06733394 | I38: 75.468545 | J38: 84.232749 | K38: 46.409225 | L38: 27.618103 | M38: 27.156497 | N38: 140.81728 | O38: 5.6331502 | P38: 5.6880429 | Q38: 5.5082232 | R38: 5.1030256 | S38: 6.2041811 | T38: 16.196973 | U38: 0.007079585 | V38: 0.0072946081 | W38: 0.0098511419 | X38: 0.017253921 | Y38: 0.018190269 | Z38: 0.0015289901 | AA38: 0.074642358 | AB38: 0.067527689 | AC38: 0.11868811 | AD38: 0.18477104 | AE38: 0.22846029 | AF38: 0.11479284 | AG38: 0.20252631 | AH38: 0.37920037 | AI38: 0.59879638 | AJ38: 0.15008889 | AK38: -0.8220386 | AL38: -0.10404746 | AM38: 0.81500011 | AN38: 0.68039147 | AO38: 0.016998028 | AP38: =IFERROR(SUMIFS('A share covered list'!AC$4:AC$9640,'A share covered list'!$E$4:$E$9640,'Summary-A share'!$B38,'A share covered list'!AC$4:AC$9640,"<>0",'A share covered list'!AB$4:AB$9640,"<>0")/SUMIFS('A share covered list'!AB$4:AB$9640,'A share covered list'!$E$4:$E$9640,'Summary-A share'!$B38,'A share covered list'!AC$4:AC$9640,"<>0",'A share covered list'!AB$4:AB$9640,"<>0")-1,"-") -> -0.80715082
B39: Telecommunications | C39: 3326.2327 | D39: 0.04808447 | E39: 1162.471 | F39: 0.021632181 | G39: 19 | H39: 0.017288444 | I39: 18.193484 | J39: 17.323126 | K39: 16.493594 | L39: 16.877674 | M39: 16.077216 | N39: 49.736824 | O39: 1.6987811 | P39: 1.6380931 | Q39: 1.592868 | R39: 1.5580842 | S39: 1.521057 | T39: 4.446797 | U39: 0.037022412 | V39: 0.03987938 | W39: 0.042624998 | X39: 0.041789816 | Y39: 0.04435712 | Z39: 0.011475247 | AA39: 0.09337305 | AB39: 0.094561056 | AC39: 0.096574952 | AD39: 0.092316287 | AE39: 0.094609481 | AF39: 0.085388335 | AG39: 0.037243019 | AH39: 0.035437828 | AI39: 0.0088122898 | AJ39: 0.012519869 | AK39: -0.50480275 | AL39: 0.050242514 | AM39: 0.050294242 | AN39: -0.022756741 | AO39: 0.049788397 | AP39: =IFERROR(SUMIFS('A share covered list'!AC$4:AC$9640,'A share covered list'!$E$4:$E$9640,'Summary-A share'!$B39,'A share covered list'!AC$4:AC$9640,"<>0",'A share covered list'!AB$4:AB$9640,"<>0")/SUMIFS('A share covered list'!AB$4:AB$9640,'A share covered list'!$E$4:$E$9640,'Summary-A share'!$B39,'A share covered list'!AC$4:AC$9640,"<>0",'A share covered list'!AB$4:AB$9640,"<>0")-1,"-") -> -0.67675428

Sheet A share covered list
A1: Updated | B1: 46062 | E1: 0
A2: Ticker | B2: Bloomberg ticker | C2: Listed Sector | D2: Name | E2: Sector | F2: Analyst | G2: Analyst | H2: Restricted list | I2: Ranking | J2: Target Price | K2: Closed price （Rmb） | L2: Price change （Week） | M2: Price change （since 2024） | N2: Share （mn） | O2: Free-float share (mn) | P2: Market cap （Rmb mn） | Q2: Free-float market value （Rmb mn） | R2: Income（Rmb mn） | X2: Net profit（Rmb mn） | AD2: Market cap（Rmb mn） | AJ2: Owner's equity(Rmb mn) | AP2: Market cap（Rmb mn） | AV2: Dividend(Rmb mn) | BB2: Market cap（Rmb mn） | BH2: OCF（Rmb mn） | BN2: EPS（Rmb） | BT2: BPS | BZ2: DPS | CF2: OCF per share | CL2: PE（X） | CR2: PB（X） | CX2: Dividend yield | DD2: ROE | DJ2: Income (YoY) | DO2: Net profit（YoY）
C3: 上市板 | R3: 2023A | S3: 2024A | T3: 2025E | U3: 2026E | V3: 2027E | W3: 2028E | X3: 2023A | Y3: 2024A | Z3: 2025E | AA3: 2026E | AB3: 2027E | AC3: 2028E | AD3: 2023A | AE3: 2024A | AF3: 2025E | AG3: 2026E | AH3: 2027E | AI3: 2028E | AJ3: 2023A | AK3: 2024A | AL3: 2025E | AM3: 2026E | AN3: 2027E | AO3: 2028E | AP3: 2023A | AQ3: 2024A | AR3: 2025E | AS3: 2026E | AT3: 2027E | AU3: 2028E | AV3: 2023A | AW3: 2024A | AX3: 2025E | AY3: 2026E | AZ3: 2027E | BA3: 2028E | BB3: 2023A | BC3: 2024A | BD3: 2025E | BE3: 2026E | BF3: 2027E | BG3: 2028E | BH3: 2023A | BI3: 2024A | BJ3: 2025E | BK3: 2026E | BL3: 2027E | BM3: 2028E | BN3: 2023A | BO3: 2024A | BP3: 2025E | BQ3: 2026E | BR3: 2027E | BS3: 2028E | BT3: 2023A | BU3: 2024A | BV3: 2025E | BW3: 2026E | BX3: 2027E | BY3: 2028E | BZ3: 2023A | CA3: 2024A | CB3: 2025E | CC3: 2026E | CD3: 2027E | CE3: 2028E | CF3: 2023A | CG3: 2024A | CH3: 2025E | CI3: 2026E | CJ3: 2027E | CK3: 2028E | CL3: 2023A | CM3: 2024A | CN3: 2025E | CO3: 2026E | CP3: 2027E | CQ3: 2028E | CR3: 2023A | CS3: 2024A | CT3: 2025E | CU3: 2026E | CV3: 2027E | CW3: 2028E | CX3: 2023A | CY3: 2024A | CZ3: 2025E | DA3: 2026E | DB3: 2027E | DC3: 2028E | DD3: 2023A | DE3: 2024A | DF3: 2025E | DG3: 2026E | DH3: 2027E | DI3: 2028E | DJ3: 2024A | DK3: 2025E | DL3: 2026E | DM3: 2027E | DN3: 2028E | DO3: 2024A | DP3: 2025E | DQ3: 2026E | DR3: 2027E | DS3: 2028E
A4: 920026.BJ | B4: 920026 CH Equity | C4: Beijing Stock Exchange | D4: Zhuozhao Dispensing Technology | E4: Machinery | F4: 刘中玉 | G4: Zhongyu LIU | H4: N | I4: Outperform | K4: 36.66 | L4: -0.0416 | M4: 0.0327 | N4: 82.08 | O4: 37.21 | P4: 3008.95 | Q4: 1364.29 | R4: 262.57085 | S4: 125.11995 | T4: 313.7 | U4: 355.37 | X4: 63.932682 | Y4: -20.750805 | Z4: 72.3 | AA4: 78.4 | AD4: 3008.95 | AE4: 3008.95 | AF4: 3008.95 | AG4: 3008.95 | AH4: 3008.95 | AI4: 3008.95 | AJ4: 616.75193 | AK4: 569.54798 | AL4: 633.24 | AM4: 668.26 | AP4: 3008.95 | AQ4: 3008.95 | AR4: 3008.95 | AS4: 3008.95 | AT4: 3008.95 | AU4: 3008.95 | AV4: 55.812527 | AX4: 43.38 | AY4: 47.04 | BB4: 3008.95 | BC4: 3008.95 | BD4: 3008.95 | BE4: 3008.95 | BF4: 3008.95 | BG4: 3008.95 | BH4: 150.66521 | BI4: 34.991339 | BJ4: 30.21 | BK4: 68.96 | BN4: 0.77890694 | BO4: -0.25281196 | BP4: 0.88084795 | BQ4: 0.95516569 | BT4: 7.5140342 | BU4: 6.9389373 | BV4: 7.7149123 | BW4: 8.1415692 | BZ4: 0.67997718 | CB4: 0.52850877 | CC4: 0.57309942 | CF4: 1.8355898 | CG4: 0.42630774 | CH4: 0.36805556 | CI4: 0.84015595 | CL4: 47.064348 | CM4: -145.00401 | CN4: 41.617566 | CO4: 38.379464 | CR4: 4.8787038 | CS4: 5.2830492 | CT4: 4.7516739 | CU4: 4.5026636 | CX4: 0.018548838 | CZ4: 0.014416989 | DA4: 0.01563336 | DD4: 10.366029 | DE4: -3.6433814 | DF4: 11.417472 | DG4: 11.731961 | DJ4: -0.5234812 | DK4: 1.5071942 | DL4: 0.13283392 | DO4: -1.3245727 | DP4: -4.4842021 | DQ4: 0.084370678
A5: 920077.BJ | B5: 920077 CH Equity | C5: Beijing Stock Exchange | D5: Jilin Tangu Carbon Fiber | E5: Chemicals | F5: 严蓓娜 | G5: Beina YAN | H5: N | I5: Outperform | J5: 18.8 | K5: 17.43 | L5: -0.0219 | M5: 0.0241 | N5: 587.68 | O5: 316.96 | P5: 10243.29 | Q5: 5524.56 | R5: 2049.237 | S5: 1603.2355 | T5: 1603.24 | U5: 2463.64 | V5: 2745.52 | X5: 231.38924 | Y5: 93.870517 | Z5: 93.87 | AA5: 164.72 | AB5: 217.61 | AD5: 10243.29 | AE5: 10243.29 | AF5: 10243.29 | AG5: 10243.29 | AH5: 10243.29 | AI5: 10243.29 | AJ5: 2427.8498 | AK5: 2454.5516 | AL5: 2446.3 | AM5: 2611.02 | AN5: 2803.93 | AP5: 10243.29 | AQ5: 10243.29 | AR5: 10243.29 | AS5: 10243.29 | AT5: 10243.29 | AU5: 10243.29 | AV5: 58.768182 | AY5: 24.71 | AZ5: 32.64 | BB5: 10243.29 | BC5: 10243.29 | BD5: 10243.29 | BE5: 10243.29 | BF5: 10243.29 | BG5: 10243.29 | BH5: -595.17996 | BI5: -317.66138 | BJ5: -317.66 | BK5: 192.21 | BL5: 482.13 | BN5: 0.39373339 | BO5: 0.15973066 | BP5: 0.15972978 | BQ5: 0.28028859 | BR5: 0.37028655 | BT5: 4.1312445 | BU5: 4.1766805 | BV5: 4.1626395 | BW5: 4.4429281 | BX5: 4.771185 | BZ5: 0.10000031 | CC5: 0.042046692 | CD5: 0.05554043 | CF5: -1.012762 | CG5: -0.54053461 | CH5: -0.54053226 | CI5: 0.32706575 | CJ5: 0.82039545 | CL5: 44.268653 | CM5: 109.12148 | CN5: 109.12208 | CO5: 62.186073 | CP5: 47.07178 | CR5: 4.219079 | CS5: 4.1731818 | CT5: 4.1872583 | CU5: 3.923099 | CV5: 3.6531903 | CX5: 0.0057372369 | DA5: 0.0024123109 | DB5: 0.0031864762 | DD5: 9.5306243 | DE5: 3.8243448 | DF5: 3.8372236 | DG5: 6.3086457 | DH5: 7.7608927 | DJ5: -0.21764273 | DK5: 2.8070673e-06 | DL5: 0.53666326 | DM5: 0.11441607 | DO5: -0.59431771 | DP5: -5.5096106e-06 | DQ5: 0.75476723 | DR5: 0.32109034
A6: 920139.BJ | B6: 920139 CH Equity | C6: Beijing Stock Exchange | D6: Sino IC Technology | E6: Electronics | F6: 于新彦 | G6: Xinyan YU | H6: N | I6: Outperform | K6: 21.16 | L6: -0.0117 | M6: 0.0124 | N6: 269.51 | O6: 258.32 | P6: 5702.78 | Q6: 5466.1 | R6: 315.48963 | S6: 276.27555 | T6: 367.52 | U6: 439.5 | X6: 74.862559 | Y6: -14.983229 | Z6: 57.61 | AA6: 75.03 | AD6: 5702.78 | AE6: 5702.78 | AF6: 5702.78 | AG6: 5702.78 | AH6: 5702.78 | AI6: 5702.78 | AJ6: 1115.6817 | AK6: 1099.682 | AL6: 1157.56 | AM6: 1223.94 | AP6: 5702.78 | AQ6: 5702.78 | AR6: 5702.78 | AS6: 5702.78 | AT6: 5702.78 | AU6: 5702.78 | AV6: 15.7412 | AX6: 8.64 | AY6: 11.25 | BB6: 5702.78 | BC6: 5702.78 | BD6: 5702.78 | BE6: 5702.78 | BF6: 5702.78 | BG6: 5702.78 | BH6: 172.36836 | BI6: 143.88133 | BJ6: 205.48 | BK6: 225.59 | BN6: 0.27777284 | BO6: -0.055594334 | BP6: 0.2137583 | BQ6: 0.27839412 | BT6: 4.139667 | BU6: 4.0803014 | BV6: 4.295054 | BW6: 4.5413528 | BZ6: 0.058406738 | CB6: 0.03205818 | CC6: 0.041742421 | CF6: 0.63956201 | CG6: 0.53386269 | CH6: 0.76242069 | CI6: 0.83703759 | CL6: 76.176664 | CM6: -380.61088 | CN6: 98.989412 | CO6: 76.006664 | CR6: 5.111476 | CS6: 5.1858445 | CT6: 4.9265524 | CU6: 4.6593624 | CX6: 0.0027602678 | CZ6: 0.0015150506 | DA6: 0.0019727221 | DD6: 6.7100287 | DE6: -1.3625056 | DF6: 4.9768479 | DG6: 6.1302025 | DJ6: -0.12429592 | DK6: 0.3302661 | DL6: 0.19585329 | DO6: -1.2001432 | DP6: -4.8449656 | DQ6: 0.30237806
A7: 920368.BJ | B7: 920368 CH Equity | C7: Beijing Stock Exchange | D7: LINTON Technologies Group | E7: Machinery | F7: 张梓丁 | G7: Ziding ZHANG | H7: N | I7: Outperform | J7: 25 | K7: 58.86 | L7: 0.0096 | M7: 1.3629 | N7: 234.78 | O7: 223.36 | P7: 13819.18 | Q7: 13147.1 | R7: 6001.5771 | S7: 5669.2786 | T7: 7052.35 | X7: 681.48159 | Y7: 340.49299 | Z7: 787.44 | AD7: 13819.18 | AE7: 13819.18 | AF7: 13819.18 | AG7: 13819.18 | AH7: 13819.18 | AI7: 13819.18 | AJ7: 3991.1548 | AK7: 4332.2163 | AL7: 5226.01 | AP7: 13819.18 | AQ7: 13819.18 | AR7: 13819.18 | AS7: 13819.18 | AT7: 13819.18 | AU7: 13819.18 | AV7: 70.049892 | AW7: 35.217066 | AX7: 39.37 | BB7: 13819.18 | BC7: 13819.18 | BD7: 13819.18 | BE7: 13819.18 | BF7: 13819.18 | BG7: 13819.18 | BH7: 463.4203 | BI7: -493.75486 | BJ7: 1809.34 | BN7: 2.902639 | BO7: 1.450264 | BP7: 3.3539484 | BT7: 16.999552 | BU7: 18.452237 | BV7: 22.259179 | BZ7: 0.29836397 | CA7: 0.15000028 | CB7: 0.1676889 | CF7: 1.9738491 | CG7: -2.1030533 | CH7: 7.7065338 | CL7: 20.278141 | CM7: 40.585799 | CN7: 17.549502 | CR7: 3.4624515 | CS7: 3.1898638 | CT7: 2.644308 | CX7: 0.0050690339 | CY7: 0.0025484194 | CZ7: 0.0028489389 | DD7: 17.074797 | DE7: 7.8595565 | DF7: 15.067709 | DJ7: -0.055368524 | DK7: 0.24395897 | DO7: -0.50036363 | DP7: 1.3126468
A8: 920394.BJ | B8: 920394 CH Equity | C8: Beijing Stock Exchange | D8: Metastar Special Paper | E8: Light manufacturing | F8: 徐贇妍 | G8: Yunyan XU | H8: N | I8: Outperform | J8: 18 | K8: 57.59 | L8: 0.0016 | M8: 0.4074 | N8: 146.25 | O8: 145.17 | P8: 8422.54 | Q8: 8360.5 | R8: 340.47177 | S8: 407.9459 | T8: 527.37 | U8: 634.83 | X8: 81.633867 | Y8: 100.52256 | Z8: 115.74 | AA8: 138.05 | AD8: 8422.54 | AE8: 8422.54 | AF8: 8422.54 | AG8: 8422.54 | AH8: 8422.54 | AI8: 8422.54 | AJ8: 666.41081 | AK8: 735.19118 | AL8: 769.93 | AM8: 907.98 | AP8: 8422.54 | AQ8: 8422.54 | AR8: 8422.54 | AS8: 8422.54 | AT8: 8422.54 | AU8: 8422.54 | AV8: 29.25 | AW8: 29.25 | BB8: 8422.54 | BC8: 8422.54 | BD8: 8422.54 | BE8: 8422.54 | BF8: 8422.54 | BG8: 8422.54 | BH8: 35.168225 | BI8: 42.481697 | BJ8: 140.06 | BK8: 155.08 | BN8: 0.55818029 | BO8: 0.68733373 | BP8: 0.79138462 | BQ8: 0.94393162 | BT8: 4.5566551 | BU8: 5.0269483 | BV8: 5.2644786 | BW8: 6.2084103 | BZ8: 0.2 | CA8: 0.2 | CF8: 0.2404665 | CG8: 0.29047314 | CH8: 0.95767521 | CI8: 1.0603761 | CL8: 103.17458 | CM8: 83.787561 | CN8: 72.771211 | CO8: 61.010793 | CR8: 12.638661 | CS8: 11.456258 | CT8: 10.939358 | CU8: 9.2761294 | CX8: 0.0034728241 | CY8: 0.0034728241 | DD8: 12.249781 | DE8: 13.672982 | DF8: 15.032535 | DG8: 15.204079 | DJ8: 0.19817833 | DK8: 0.29274495 | DL8: 0.20376586 | DO8: 0.23138303 | DP8: 0.15138335 | DQ8: 0.19275963
A9: 920402.BJ | B9: 920402 CH Equity | C9: Beijing Stock Exchange | D9: Silane Technology Development | E9: Chemicals | F9: 李熹凌 | G9: Xiling LI | H9: N | I9: Outperform | K9: 10.3 | L9: -0.0087 | M9: 0.0198 | N9: 422.06 | O9: 272.87 | P9: 4347.22 | Q9: 2810.59 | R9: 1120.6856 | S9: 705.43248 | T9: 1127.31 | U9: 1295.22 | X9: 308.23496 | Y9: 77.673267 | Z9: 241.93 | AA9: 251.46 | AD9: 4347.22 | AE9: 4347.22 | AF9: 4347.22 | AG9: 4347.22 | AH9: 4347.22 | AI9: 4347.22 | AJ9: 1645.5301 | AK9: 1663.2026 | AL9: 1827.39 | AM9: 2030.47 | AP9: 4347.22 | AQ9: 4347.22 | AR9: 4347.22 | AS9: 4347.22 | AT9: 4347.22 | AU9: 4347.22 | AV9: 60.000708 | AW9: 8.4412013 | AX9: 48.39 | AY9: 50.29 | BB9: 4347.22 | BC9: 4347.22 | BD9: 4347.22 | BE9: 4347.22 | BF9: 4347.22 | BG9: 4347.22 | BH9: 218.74276 | BI9: 195.08055 | BJ9: 385.26 | BK9: 369.66 | BN9: 0.73031076 | BO9: 0.18403371 | BP9: 0.57321234 | BQ9: 0.59579207 | BT9: 3.8988061 | BU9: 3.9406782 | BV9: 4.3296925 | BW9: 4.8108563 | BZ9: 0.14216156 | CA9: 0.020000003 | CB9: 0.11465195 | CC9: 0.11915367 | CF9: 0.51827409 | CG9: 0.46221047 | CH9: 0.91280861 | CI9: 0.87584704 | CL9: 14.103592 | CM9: 55.968033 | CN9: 17.968917 | CO9: 17.287919 | CR9: 2.6418356 | CS9: 2.6137645 | CT9: 2.3789229 | CU9: 2.140992 | CX9: 0.013802087 | CY9: 0.001941747 | CZ9: 0.011131252 | DA9: 0.011568313 | DD9: 18.731652 | DE9: 4.6701024 | DF9: 13.239101 | DG9: 12.384325 | DJ9: -0.37053486 | DK9: 0.59804095 | DL9: 0.14894749 | DO9: -0.7480063 | DP9: 2.1147138 | DQ9: 0.03939156
A10: 920425.BJ | B10: 920425 CH Equity | C10: Beijing Stock Exchange | D10: Leetro Automation | E10: Electrical equipment and new energy | F10: 刘中玉 | G10: Zhongyu LIU | H10: N | I10: Outperform | K10: 24.83 | L10: 0.0273 | M10: 0.1926 | N10: 70.94 | O10: 59.21 | P10: 1761.35 | Q10: 1470.27 | R10: 83.29403 | S10: 77.857773 | T10: 87.56 | U10: 94.83 | X10: 27.54826 | Y10: 16.882989 | Z10: 31.21 | AA10: 33.77 | AD10: 1761.35 | AE10: 1761.35 | AF10: 1761.35 | AG10: 1761.35 | AH10: 1761.35 | AI10: 1761.35 | AJ10: 245.12724 | AK10: 244.72362 | AL10: 260.86 | AM10: 277.1 | AP10: 1761.35 | AQ10: 1761.35 | AR10: 1761.35 | AS10: 1761.35 | AT10: 1761.35 | AU10: 1761.35 | AV10: 14.476847 | AW10: 10.133793 | AX10: 17.53 | AY10: 18.97 | BB10: 1761.35 | BC10: 1761.35 | BD10: 1761.35 | BE10: 1761.35 | BF10: 1761.35 | BG10: 1761.35 | BH10: 19.730743 | BI10: 26.824638 | BJ10: 34.94 | BK10: 35.94 | BN10: 0.38833183 | BO10: 0.23798969 | BP10: 0.43994925 | BQ10: 0.47603609 | BT10: 3.4554164 | BU10: 3.4497268 | BV10: 3.677192 | BW10: 3.9061178 | BZ10: 0.20407171 | CA10: 0.14285019 | CB10: 0.24711023 | CC10: 0.26740908 | CF10: 0.27813283 | CG10: 0.37813136 | CH10: 0.4925289 | CI10: 0.50662532 | CL10: 63.936888 | CM10: 104.32691 | CN10: 56.435437 | CO10: 52.15724 | CR10: 7.185452 | CS10: 7.1973029 | CT10: 6.7520892 | CU10: 6.3563695 | CX10: 0.0082191767 | CY10: 0.0057534236 | CZ10: 0.0099525932 | DA10: 0.010770148 | DD10: 11.238351 | DE10: 6.8987982 | DF10: 11.964272 | DG10: 12.186936 | DJ10: -0.065265874 | DK10: 0.12461476 | DL10: 0.08302878 | DO10: -0.38714864 | DP10: 0.84860635 | DQ10: 0.082024992
A11: 920438.BJ | B11: 920438 CH Equity | C11: Beijing Stock Exchange | D11: Gabrielle Optech | E11: Electronics | F11: 于新彦 | G11: Xinyan YU | H11: N | I11: Outperform | K11: 53.46 | L11: 0.1264 | M11: 0.3315 | N11: 144.63 | O11: 138.78 | P11: 7731.92 | Q11: 7418.93 | R11: 808.33755 | S11: 566.20485 | T11: 810.96 | U11: 883.59 | X11: 104.21122 | Y11: 70.253057 | Z11: 128.6 | AA11: 148.89 | AD11: 7731.92 | AE11: 7731.92 | AF11: 7731.92 | AG11: 7731.92 | AH11: 7731.92 | AI11: 7731.92 | AJ11: 681.13225 | AK11: 942.37728 | AL11: 1014 | AM11: 1162.88 | AP11: 7731.92 | AQ11: 7731.92 | AR11: 7731.92 | AS11: 7731.92 | AT11: 7731.92 | AU11: 7731.92 | AW11: 28.25 | BB11: 7731.92 | BC11: 7731.92 | BD11: 7731.92 | BE11: 7731.92 | BF11: 7731.92 | BG11: 7731.92 | BH11: 199.84095 | BI11: 90.067406 | BJ11: 172.91 | BK11: 182.46 | BN11: 0.72053666 | BO11: 0.48574332 | BP11: 0.88916546 | BQ11: 1.0294545 | BT11: 4.7094811 | BU11: 6.5157801 | BV11: 7.0109936 | BW11: 8.0403789 | CA11: 0.195326 | CF11: 1.3817392 | CG11: 0.62274359 | CH11: 1.1955334 | CI11: 1.261564 | CL11: 74.1947 | CM11: 110.05813 | CN11: 60.123795 | CO11: 51.930418 | CR11: 11.351569 | CS11: 8.204697 | CT11: 7.6251677 | CU11: 6.6489406 | CY11: 0.0036536849 | DD11: 15.299704 | DE11: 7.4548759 | DF11: 12.682446 | DG11: 12.803557 | DJ11: -0.29954404 | DK11: 0.43227313 | DL11: 0.089560521 | DO11: -0.32585898 | DP11: 0.83052534 | DQ11: 0.15777605
A12: 920491.BJ | B12: 920491 CH Equity | C12: Beijing Stock Exchange | D12: Audiowell Electronics (Guangdong) | E12: Machinery | F12: 于新彦 | G12: Xinyan YU | H12: N | I12: Outperform | K12: 27.61 | L12: 0.0015 | M12: -0.0769 | N12: 141.14 | O12: 115.58 | P12: 3896.96 | Q12: 3191.03 | R12: 467.08077 | S12: 617.16436 | T12: 562.61 | U12: 671.52 | X12: 76.980518 | Y12: 87.655306 | Z12: 93.99 | AA12: 110.74 | AD12: 3896.96 | AE12: 3896.96 | AF12: 3896.96 | AG12: 3896.96 | AH12: 3896.96 | AI12: 3896.96 | AJ12: 924.80508 | AK12: 1006.1317 | AL12: 1018.79 | AM12: 1129.53 | AP12: 3896.96 | AQ12: 3896.96 | AR12: 3896.96 | AS12: 3896.96 | AT12: 3896.96 | AU12: 3896.96 | AV12: 28.22967 | AW12: 42.342954 | BB12: 3896.96 | BC12: 3896.96 | BD12: 3896.96 | BE12: 3896.96 | BF12: 3896.96 | BG12: 3896.96 | BH12: 71.526665 | BI12: 77.24019 | BJ12: 53.82 | BK12: 90.68 | BN12: 0.54541957 | BO12: 0.62105219 | BP12: 0.66593453 | BQ12: 0.78461102 | BT12: 6.5523954 | BU12: 7.1286079 | BV12: 7.2182939 | BW12: 8.0029049 | BZ12: 0.20001183 | CA12: 0.30000676 | CF12: 0.50677813 | CG12: 0.54725939 | CH12: 0.38132351 | CI12: 0.64248264 | CL12: 50.622678 | CM12: 44.457777 | CN12: 41.461432 | CO12: 35.190175 | CR12: 4.2138177 | CS12: 3.8732106 | CT12: 3.8250866 | CU12: 3.4500722 | CX12: 0.0072440234 | CY12: 0.010865637 | DD12: 8.3239722 | DE12: 8.7121103 | DF12: 9.22565 | DG12: 9.8040778 | DJ12: 0.32132257 | DK12: -0.088395186 | DL12: 0.19357992 | DO12: 0.13866869 | DP12: 0.072268238 | DQ12: 0.17821045
A13: 920510.BJ | B13: 920510 CH Equity | C13: Beijing Stock Exchange | D13: Fengguang Precision Machinery | E13: Machinery | F13: 刘中玉 | G13: Zhongyu LIU | H13: N | I13: Outperform | K13: 17.42 | L13: -0.0252 | M13: -0.1709 | N13: 184.21 | O13: 93.9 | P13: 3209.01 | Q13: 1635.72 | R13: 211.08318 | S13: 232.38945 | T13: 251.58 | U13: 285.88 | X13: 35.57565 | Y13: 21.056781 | Z13: 41.9 | AA13: 47.57 | AD13: 3209.01 | AE13: 3209.01 | AF13: 3209.01 | AG13: 3209.01 | AH13: 3209.01 | AI13: 3209.01 | AJ13: 428.68797 | AK13: 400.06715 | AL13: 470.58 | AM13: 518.16 | AP13: 3209.01 | AQ13: 3209.01 | AR13: 3209.01 | AS13: 3209.01 | AT13: 3209.01 | AU13: 3209.01 | AV13: 15.789765 | BB13: 3209.01 | BC13: 3209.01 | BD13: 3209.01 | BE13: 3209.01 | BF13: 3209.01 | BG13: 3209.01 | BH13: 46.181545 | BI13: 64.308426 | BJ13: 31.7 | BK13: 87.17 | BN13: 0.19312551 | BO13: 0.11430857 | BP13: 0.22745779 | BQ13: 0.25823788 | BT13: 2.3271699 | BU13: 2.1717993 | BV13: 2.5545844 | BW13: 2.8128766 | BZ13: 0.085716114 | CF13: 0.25070053 | CG13: 0.34910388 | CH13: 0.17208621 | CI13: 0.47320992 | CL13: 90.202427 | CM13: 152.39794 | CN13: 76.587351 | CO13: 67.458692 | CR13: 7.4856544 | CS13: 8.0211784 | CT13: 6.8192656 | CU13: 6.1930871 | CX13: 0.0049204475 | DD13: 8.2987284 | DE13: 5.2633117 | DF13: 8.9039058 | DG13: 9.180562 | DJ13: 0.10093778 | DK13: 0.082579274 | DL13: 0.13633834 | DO13: -0.40811255 | DP13: 0.98985779 | DQ13: 0.1353222
A14: 920578.BJ | B14: 920578 CH Equity | C14: Beijing Stock Exchange | D14: Juneng Robotics | E14: Machinery | F14: 郭威秀 | G14: Weixiu GUO | H14: N | I14: Outperform | K14: 24.26 | L14: 0.0121 | M14: -0.0687 | N14: 76.48 | O14: 23 | P14: 1855.38 | Q14: 557.98 | R14: 216.53438 | S14: 252.59617 | T14: 260.01 | U14: 299.53 | X14: 24.659649 | Y14: -1.1503502 | Z14: 36.71 | AA14: 41.1 | AD14: 1855.38 | AE14: 1855.38 | AF14: 1855.38 | AG14: 1855.38 | AH14: 1855.38 | AI14: 1855.38 | AJ14: 266.66458 | AK14: 265.76174 | AL14: 272.59 | AM14: 299.81 | AP14: 1855.38 | AQ14: 1855.38 | AR14: 1855.38 | AS14: 1855.38 | AT14: 1855.38 | AU14: 1855.38 | AX14: 13.88 | AY14: 19.07 | BB14: 1855.38 | BC14: 1855.38 | BD14: 1855.38 | BE14: 1855.38 | BF14: 1855.38 | BG14: 1855.38 | BH14: 7.9114103 | BI14: -29.843647 | BJ14: 42.67 | BK14: 49.79 | BN14: 0.32243265 | BO14: -0.01504119 | BP14: 0.47999477 | BQ14: 0.5373954 | BT14: 3.4867231 | BU14: 3.4749181 | BV14: 3.5641998 | BW14: 3.9201098 | CB14: 0.18148536 | CC14: 0.24934623 | CF14: 0.10344417 | CG14: -0.39021505 | CH14: 0.55792364 | CI14: 0.65101987 | CL14: 75.239514 | CM14: -1612.8827 | CN14: 50.541542 | CO14: 45.143066 | CR14: 6.9577293 | CS14: 6.9813661 | CT14: 6.8064859 | CU14: 6.1885194 | CZ14: 0.0074809473 | DA14: 0.010278218 | DD14: 9.2474406 | DE14: -0.4328502 | DF14: 13.467112 | DG14: 13.708682 | DJ14: 0.1665407 | DK14: 0.029350531 | DL14: 0.15199415 | DO14: -1.0466491 | DP14: -32.912021 | DQ14: 0.11958594
A15: 920593.BJ | B15: 920593 CH Equity | C15: Beijing Stock Exchange | D15: DINGS’ Intelligent Control Technology | E15: Machinery | F15: 张若熙 | G15: Ruoxi ZHANG | H15: N | I15: Outperform | J15: 40 | K15: 33.4 | L15: 0.018 | M15: -0.0854 | N15: 190.3 | O15: 161.61 | P15: 6356.17 | Q15: 5397.78 | R15: 282.46585 | S15: 223.71708 | T15: 416.74 | U15: 508.91 | V15: 623.58 | W15: 806.03 | X15: 80.910082 | Y15: 38.700349 | Z15: 87.46 | AA15: 104.66 | AB15: 122.91 | AC15: 147.17 | AD15: 6356.17 | AE15: 6356.17 | AF15: 6356.17 | AG15: 6356.17 | AH15: 6356.17 | AI15: 6356.17 | AJ15: 667.71993 | AK15: 670.40592 | AL15: 734.18 | AM15: 786.94 | AN15: 899.39 | AO15: 1034.27 | AP15: 6356.17 | AQ15: 6356.17 | AR15: 6356.17 | AS15: 6356.17 | AT15: 6356.17 | AU15: 6356.17 | AV15: 86.43967 | AW15: 26.892342 | BB15: 6356.17 | BC15: 6356.17 | BD15: 6356.17 | BE15: 6356.17 | BF15: 6356.17 | BG15: 6356.17 | BH15: 79.0402 | BI15: 43.693516 | BJ15: 91.56 | BK15: 114.31 | BL15: 144.78 | BM15: 176.38 | BN15: 0.42517121 | BO15: 0.20336494 | BP15: 0.45959012 | BQ15: 0.54997373 | BR15: 0.64587493 | BS15: 0.77335786 | BT15: 3.5087752 | BU15: 3.5228898 | BV15: 3.8580137 | BW15: 4.1352601 | BX15: 4.7261692 | BY15: 5.4349448 | BZ15: 0.45422843 | CA15: 0.14131551 | CF15: 0.41534524 | CG15: 0.22960334 | CH15: 0.48113505 | CI15: 0.60068313 | CJ15: 0.76079874 | CK15: 0.92685234 | CL15: 78.558442 | CM15: 164.24064 | CN15: 72.675166 | CO15: 60.731607 | CP15: 51.714018 | CQ15: 43.189305 | CR15: 9.5192156 | CS15: 9.4810768 | CT15: 8.6575091 | CU15: 8.0770707 | CV15: 7.0672011 | CW15: 6.1455616 | CX15: 0.013599333 | CY15: 0.0042309035 | DD15: 12.117368 | DE15: 5.7726741 | DF15: 11.91261 | DG15: 13.299616 | DH15: 13.665929 | DI15: 14.22936 | DJ15: -0.20798541 | DK15: 0.86279925 | DL15: 0.22116907 | DM15: 0.22532471 | DN15: 0.29258475 | DO15: -0.52168694 | DP15: 1.2599279 | DQ15: 0.19666133 | DR15: 0.17437416 | DS15: 0.1973802
A16: 920640.BJ | B16: 920640 CH Equity | C16: Beijing Stock Exchange | D16: AVIC Forstar S&T | E16: Telecommunications | F16: 于新彦 | G16: Xinyan YU | H16: N | I16: Outperform | K16: 44.58 | L16: -0.0243 | M16: 0.185 | N16: 187.73 | O16: 180.6 | P16: 8368.91 | Q16: 8051.25 | R16: 815.14438 | S16: 762.79754 | T16: 950.17 | U16: 1103.5 | X16: 146.17223 | Y16: 51.126712 | Z16: 171.59 | AA16: 199.73 | AD16: 8368.91 | AE16: 8368.91 | AF16: 8368.91 | AG16: 8368.91 | AH16: 8368.91 | AI16: 8368.91 | AJ16: 890.8022 | AK16: 906.31116 | AL16: 1032.75 | AM16: 1206.74 | AP16: 8368.91 | AQ16: 8368.91 | AR16: 8368.91 | AS16: 8368.91 | AT16: 8368.91 | AU16: 8368.91 | AV16: 56.3184 | AW16: 18.7728 | AX16: 25.74 | AY16: 23.97 | BB16: 8368.91 | BC16: 8368.91 | BD16: 8368.91 | BE16: 8368.91 | BF16: 8368.91 | BG16: 8368.91 | BH16: 125.42425 | BI16: 107.83145 | BJ16: 195.67 | BK16: 193.45 | BN16: 0.7786301 | BO16: 0.27234173 | BP16: 0.91402546 | BQ16: 1.0639216 | BT16: 4.7451244 | BU16: 4.8277375 | BV16: 5.5012518 | BW16: 6.4280616 | BZ16: 0.2999968 | CA16: 0.099998935 | CB16: 0.13711181 | CC16: 0.12768338 | CF16: 0.66810979 | CG16: 0.5743965 | CH16: 1.0422948 | CI16: 1.0304693 | CL16: 57.253762 | CM16: 163.68958 | CN16: 48.772714 | CO16: 41.901117 | CR16: 9.3948017 | CS16: 9.2340361 | CT16: 8.1035197 | CU16: 6.9351393 | CX16: 0.0067294785 | CY16: 0.0022431595 | CZ16: 0.0030756694 | DA16: 0.0028641723 | DD16: 16.409056 | DE16: 5.6411875 | DF16: 16.614863 | DG16: 16.551204 | DJ16: -0.06421787 | DK16: 0.24563852 | DL16: 0.16137112 | DO16: -0.65022965 | DP16: 2.3561712 | DQ16: 0.16399557
A17: 920725.BJ | B17: 920725 CH Equity | C17: Beijing Stock Exchange | D17: Zhecheng Huifeng Diamond Technology | E17: Chemicals | F17: 徐卓楠 | G17: Zhuonan XU | H17: N | I17: Outperform | J17: 17.2 | K17: 33.97 | L17: -0.0122 | M17: 0.0077 | N17: 91.28 | O17: 42.08 | P17: 3100.61 | Q17: 1429.38 | R17: 495.51718 | S17: 216.29453 | T17: 571.61 | U17: 640.42 | X17: 69.883182 | Y17: 3.9393311 | Z17: 87.66 | AA17: 100.07 | AD17: 3100.61 | AE17: 3100.61 | AF17: 3100.61 | AG17: 3100.61 | AH17: 3100.61 | AI17: 3100.61 | AJ17: 648.76432 | AK17: 635.02355 | AL17: 718.99 | AM17: 807.48 | AP17: 3100.61 | AQ17: 3100.61 | AR17: 3100.61 | AS17: 3100.61 | AT17: 3100.61 | AU17: 3100.61 | AV17: 13.746 | AW17: 9.0665 | AX17: 11.58 | AY17: 13.22 | BB17: 3100.61 | BC17: 3100.61 | BD17: 3100.61 | BE17: 3100.61 | BF17: 3100.61 | BG17: 3100.61 | BH17: -46.114048 | BI17: 30.525758 | BJ17: 98.49 | BK17: 88.51 | BN17: 0.76559139 | BO17: 0.043156563 | BP17: 0.96034181 | BQ17: 1.0962971 | BT17: 7.1074093 | BU17: 6.956875 | BV17: 7.8767528 | BW17: 8.8461876 | BZ17: 0.15059159 | CA17: 0.099326249 | CB17: 0.1268624 | CC17: 0.1448291 | CF17: -0.50519334 | CG17: 0.33441891 | CH17: 1.0789877 | CI17: 0.96965381 | CL17: 44.368472 | CM17: 787.09048 | CN17: 35.370865 | CO17: 30.984411 | CR17: 4.7792548 | CS17: 4.8826693 | CT17: 4.3124522 | CU17: 3.8398598 | CX17: 0.0044333212 | CY17: 0.002924102 | CZ17: 0.003734749 | DA17: 0.0042636771 | DD17: 10.771736 | DE17: 0.62034409 | DF17: 12.192103 | DG17: 12.392877 | DJ17: -0.56349742 | DK17: 1.6427391 | DL17: 0.12037928 | DO17: -0.94362977 | DP17: 21.252509 | DQ17: 0.1415697
A18: 920781.BJ | B18: 920781 CH Equity | C18: Beijing Stock Exchange | D18: Chengdu Rich Technology | E18: Machinery | F18: 刘中玉 | G18: Zhongyu LIU | H18: N | I18: Outperform | K18: 9.09 | L18: 0.0089 | M18: 0.0145 | N18: 154.57 | O18: 102.08 | P18: 1405.01 | Q18: 927.93 | R18: 373.24569 | S18: 450.54694 | T18: 442.66 | U18: 487.01 | X18: 24.900941 | Y18: 22.971585 | Z18: 37.94 | AA18: 48 | AD18: 1405.01 | AE18: 1405.01 | AF18: 1405.01 | AG18: 1405.01 | AH18: 1405.01 | AI18: 1405.01 | AJ18: 392.76045 | AK18: 409.98342 | AL18: 423.16 | AM18: 460.46 | AP18: 1405.01 | AQ18: 1405.01 | AR18: 1405.01 | AS18: 1405.01 | AT18: 1405.01 | AU18: 1405.01 | AV18: 7.0257752 | AW18: 2.8103101 | AX18: 10.7 | AY18: 13.54 | BB18: 1405.01 | BC18: 1405.01 | BD18: 1405.01 | BE18: 1405.01 | BF18: 1405.01 | BG18: 1405.01 | BH18: -34.740972 | BI18: 6.4577163 | BJ18: -10.1 | BK18: 33.6 | BN18: 0.16109815 | BO18: 0.14861607 | BP18: 0.24545513 | BQ18: 0.31053891 | BT18: 2.5409876 | BU18: 2.6524126 | BV18: 2.7376593 | BW18: 2.9789739 | BZ18: 0.045453679 | CA18: 0.018181472 | CB18: 0.0692243 | CC18: 0.087597852 | CF18: -0.22475883 | CG18: 0.041778588 | CH18: -0.065342563 | CI18: 0.21737724 | CL18: 56.423971 | CM18: 61.162953 | CN18: 37.03242 | CO18: 29.271042 | CR18: 3.5772696 | CS18: 3.4269923 | CT18: 3.3202807 | CU18: 3.0513182 | CX18: 0.0050005162 | CY18: 0.0020002065 | CZ18: 0.0076156042 | DA18: 0.0096369421 | DD18: 6.3399819 | DE18: 5.6030523 | DF18: 8.9658758 | DG18: 10.424358 | DJ18: 0.20710554 | DK18: -0.017505263 | DL18: 0.10018976 | DO18: -0.077481242 | DP18: 0.65160564 | DQ18: 0.26515551
A19: 920932.BJ | B19: 920932 CH Equity | C19: Beijing Stock Exchange | D19: Keda Automatic Control | E19: Computers | F19: 郭威秀 | G19: Weixiu GUO | H19: N | I19: Outperform | K19: 19.74 | L19: 0.0154 | M19: -0.0836 | N19: 105.35 | O19: 86.81 | P19: 2079.62 | Q19: 1713.69 | R19: 426.13726 | S19: 433.64888 | T19: 639.92 | U19: 850.38 | X19: 55.145955 | Y19: 34.511625 | Z19: 100.75 | AA19: 131.92 | AD19: 2079.62 | AE19: 2079.62 | AF19: 2079.62 | AG19: 2079.62 | AH19: 2079.62 | AI19: 2079.62 | AJ19: 685.95686 | AK19: 707.94213 | AL19: 781.66 | AM19: 903.51 | AP19: 2079.62 | AQ19: 2079.62 | AR19: 2079.62 | AS19: 2079.62 | AT19: 2079.62 | AU19: 2079.62 | AV19: 15.295175 | AW19: 2.2942763 | AX19: 10.08 | AY19: 13.19 | BB19: 2079.62 | BC19: 2079.62 | BD19: 2079.62 | BE19: 2079.62 | BF19: 2079.62 | BG19: 2079.62 | BH19: -3.6234825 | BI19: 75.834759 | BJ19: -13.31 | BK19: 22.73 | BN19: 0.52345472 | BO19: 0.32759018 | BP19: 0.95633602 | BQ19: 1.2522069 | BT19: 6.5112184 | BU19: 6.7199063 | BV19: 7.4196488 | BW19: 8.5762696 | BZ19: 0.14518439 | CA19: 0.021777658 | CB19: 0.095681063 | CC19: 0.12520171 | CF19: -0.034394708 | CG19: 0.71983634 | CH19: -0.12634077 | CI19: 0.215757 | CL19: 37.711198 | CM19: 60.258536 | CN19: 20.64139 | CO19: 15.764251 | CR19: 3.0317067 | CS19: 2.9375565 | CT19: 2.6605174 | CU19: 2.3017122 | CX19: 0.0073547933 | CY19: 0.001103219 | CZ19: 0.0048470394 | DA19: 0.0063425049 | DD19: 8.0392745 | DE19: 4.8749218 | DF19: 12.889236 | DG19: 14.600835 | DJ19: 0.017627229 | DK19: 0.4756639 | DL19: 0.32888486 | DO19: -0.37417667 | DP19: 1.9193062 | DQ19: 0.30937965
A20: 920978.BJ | B20: 920978 CH Equity | C20: Beijing Stock Exchange | D20: Kait Automotive Electronic & Electrical Systems | E20: Auto | F20: 刘中玉 | G20: Zhongyu LIU | H20: N | I20: Outperform | K20: 32.66 | L20: 0.1193 | M20: -0.1149 | N20: 180.03 | O20: 100.93 | P20: 5879.73 | Q20: 3296.53 | R20: 653.26857 | S20: 826.36294 | T20: 807.03 | U20: 980.69 | X20: 113.6964 | Y20: 137.84569 | Z20: 127.87 | AA20: 150.85 | AD20: 5879.73 | AE20: 5879.73 | AF20: 5879.73 | AG20: 5879.73 | AH20: 5879.73 | AI20: 5879.73 | AJ20: 587.92465 | AK20: 676.15112 | AL20: 665.3 | AM20: 759.91 | AP20: 5879.73 | AQ20: 5879.73 | AR20: 5879.73 | AS20: 5879.73 | AT20: 5879.73 | AU20: 5879.73 | AV20: 99.999994 | AW20: 59.998813 | AX20: 56.23 | AY20: 60.34 | BB20: 5879.73 | BC20: 5879.73 | BD20: 5879.73 | BE20: 5879.73 | BF20: 5879.73 | BG20: 5879.73 | BH20: 46.642006 | BI20: 125.74463 | BJ20: 77.54 | BK20: 83.64 | BN20: 0.6315414 | BO20: 0.7656818 | BP20: 0.71027051 | BQ20: 0.8379159 | BT20: 3.2657037 | BU20: 3.7557691 | BV20: 3.6954952 | BW20: 4.2210187 | BZ20: 0.55546295 | CA20: 0.3332712 | CB20: 0.31233683 | CC20: 0.33516636 | CF20: 0.25907907 | CG20: 0.69846484 | CH20: 0.43070599 | CI20: 0.46458924 | CL20: 51.714303 | CM20: 42.654434 | CN20: 45.982091 | CO20: 38.977328 | CR20: 10.000822 | CS20: 8.6958815 | CT20: 8.8377123 | CU20: 7.7374031 | CX20: 0.017007583 | CY20: 0.010204348 | CZ20: 0.0095633643 | DA20: 0.010262376 | DD20: 19.338601 | DE20: 20.386817 | DF20: 19.219901 | DG20: 19.851035 | DJ20: 0.26496664 | DK20: -0.023395222 | DL20: 0.21518407 | DO20: 0.21240159 | DP20: -0.072368558 | DQ20: 0.17971377
A21: 920982.BJ | B21: 920982 CH Equity | C21: Beijing Stock Exchange | D21: Jinbo Bio-Pharmaceutical | E21: Pharmaceuticals | F21: 徐卓楠 | G21: Zhuonan XU | H21: N | I21: Outperform | J21: 435 | K21: 224.39 | L21: 0.0442 | M21: -0.0398 | N21: 115.07 | O21: 54.91 | P21: 25819.51 | Q21: 12320.16 | R21: 780.26021 | S21: 1442.8314 | T21: 2148.13 | U21: 2805.86 | X21: 299.79629 | Y21: 732.30162 | Z21: 1095.52 | AA21: 1430.56 | AD21: 25819.51 | AE21: 25819.51 | AF21: 25819.51 | AG21: 25819.51 | AH21: 25819.51 | AI21: 25819.51 | AJ21: 953.1312 | AK21: 1531.2079 | AL21: 2630.74 | AM21: 4061.3 | AP21: 25819.51 | AQ21: 25819.51 | AR21: 25819.51 | AS21: 25819.51 | AT21: 25819.51 | AU21: 25819.51 | AV21: 102.129 | AW21: 265.5354 | BB21: 25819.51 | BC21: 25819.51 | BD21: 25819.51 | BE21: 25819.51 | BF21: 25819.51 | BG21: 25819.51 | BH21: 295.56638 | BI21: 767.15539 | BJ21: 1093.52 | BK21: 1471.86 | BN21: 2.6053384 | BO21: 6.3639665 | BP21: 9.5204658 | BQ21: 12.432085 | BT21: 8.2830556 | BU21: 13.306752 | BV21: 22.862084 | BW21: 35.294169 | BZ21: 0.88753802 | CA21: 2.3075989 | CF21: 2.568579 | CG21: 6.6668584 | CH21: 9.5030851 | CI21: 12.790997 | CL21: 86.123513 | CM21: 35.258027 | CN21: 23.568269 | CO21: 18.048533 | CR21: 27.089146 | CS21: 16.862184 | CT21: 9.8145427 | CU21: 6.3574496 | CX21: 0.0039554972 | CY21: 0.010284293 | DD21: 31.453833 | DE21: 47.825093 | DF21: 41.643036 | DG21: 35.224189 | DJ21: 0.84916695 | DK21: 0.48882953 | DL21: 0.30618724 | DO21: 1.442664 | DP21: 0.4959956 | DQ21: 0.30582737
A22: 600000.SH | B22: 600000 CH Equity | C22: Main board | D22: Shanghai Pudong Development Bank | E22: Banks | F22: 张帅帅 | G22: Shuaishuai ZHANG | H22: N | I22: Outperform | J22: 14.19 | K22: 10.12 | L22: 0.006 | M22: -0.1865 | N22: 33305.84 | O22: 33305.84 | P22: 337055.08 | Q22: 337055.08 | R22: 173434 | S22: 170748 | T22: 174152.92 | U22: 178245.53 | V22: 184295.57 | X22: 36702 | Y22: 45257 | Z22: 50175.96 | AA22: 50775.68 | AB22: 52099.57 | AD22: 337055.08 | AE22: 337055.08 | AF22: 337055.08 | AG22: 337055.08 | AH22: 337055.08 | AI22: 337055.08 | AJ22: 732884 | AK22: 744781 | AL22: 778210.78 | AM22: 801747.89 | AN22: 835198.76 | AP22: 337055.08 | AQ22: 337055.08 | AR22: 337055.08 | AS22: 337055.08 | AT22: 337055.08 | AU22: 337055.08 | AV22: 9422.0489 | AW22: 12409.749 | AX22: 15144.16 | AY22: 15327.35 | AZ22: 15723.69 | BB22: 337055.08 | BC22: 337055.08 | BD22: 337055.08 | BE22: 337055.08 | BF22: 337055.08 | BG22: 337055.08 | BH22: 388397 | BI22: -333654 | BN22: 1.1019689 | BO22: 1.3588308 | BP22: 1.5065214 | BQ22: 1.5245278 | BR22: 1.5642773 | BT22: 22.004669 | BU22: 22.361874 | BV22: 23.365595 | BW22: 24.072292 | BX22: 25.076646 | BZ22: 0.2828948 | CA22: 0.37259978 | CB22: 0.45469984 | CC22: 0.46020007 | CD22: 0.47210009 | CF22: 11.661528 | CG22: -10.017883 | CL22: 9.1835617 | CM22: 7.4475789 | CN22: 6.7174615 | CO22: 6.6381205 | CP22: 6.4694407 | CR22: 0.45990236 | CS22: 0.45255596 | CT22: 0.43311541 | CU22: 0.42040033 | CV22: 0.40356272 | CX22: 0.027954033 | CY22: 0.036818162 | CZ22: 0.044930817 | DA22: 0.045474318 | DB22: 0.046650209 | DD22: 5.0078867 | DE22: 6.0765514 | DF22: 6.4476054 | DG22: 6.333123 | DH22: 6.2379846 | DJ22: -0.015487159 | DK22: 0.0199412 | DL22: 0.023500094 | DM22: 0.03394217 | DO22: 0.23309356 | DP22: 0.10868948 | DQ22: 0.011952337 | DR22: 0.026073309
A23: 600007.SH | B23: 600007 CH Equity | C23: Main board | D23: China World Trade Center | E23: Real estate | F23: 宋志达 | G23: Zhida SONG | H23: N | I23: Outperform | J23: 23.5 | K23: 20.78 | L23: 0.0318 | M23: 0.0484 | N23: 1007.28 | O23: 1007.28 | P23: 20931.33 | Q23: 20931.33 | R23: 3953.7619 | S23: 3912.0679 | T23: 3912.07 | U23: 3692.59 | V23: 3550.22 | X23: 1259.2013 | Y23: 1262.3891 | Z23: 1262.39 | AA23: 1113.74 | AB23: 1036.37 | AD23: 20931.33 | AE23: 20931.33 | AF23: 20931.33 | AG23: 20931.33 | AH23: 20931.33 | AI23: 20931.33 | AJ23: 9703.984 | AK23: 9658.0385 | AL23: 9653.08 | AM23: 9658.81 | AN23: 9717.64 | AP23: 20931.33 | AQ23: 20931.33 | AR23: 20931.33 | AS23: 20931.33 | AT23: 20931.33 | AU23: 20931.33 | AV23: 1309.4673 | AW23: 1108.0108 | AX23: 1108.01 | AY23: 977.54 | AZ23: 909.63 | BB23: 20931.33 | BC23: 20931.33 | BD23: 20931.33 | BE23: 20931.33 | BF23: 20931.33 | BG23: 20931.33 | BH23: 1918.6609 | BI23: 1796.2954 | BJ23: 1796.3 | BK23: 1630.49 | BL23: 1537.63 | BN23: 1.2501006 | BO23: 1.2532653 | BP23: 1.2532662 | BQ23: 1.1056906 | BR23: 1.0288798 | BT23: 9.6338496 | BU23: 9.5882361 | BV23: 9.5833135 | BW23: 9.5890021 | BX23: 9.6474069 | BZ23: 1.3000033 | CA23: 1.1000028 | CB23: 1.100002 | CC23: 0.97047494 | CD23: 0.90305575 | CF23: 1.904794 | CG23: 1.7833129 | CH23: 1.7833174 | CI23: 1.6187058 | CJ23: 1.526517 | CL23: 16.622703 | CM23: 16.580728 | CN23: 16.580716 | CO23: 18.793731 | CP23: 20.196773 | CR23: 2.1569832 | CS23: 2.1672444 | CT23: 2.1683577 | CU23: 2.1670713 | CV23: 2.153952 | CX23: 0.062560157 | CY23: 0.052935518 | CZ23: 0.05293548 | DA23: 0.04670224 | DB23: 0.043457821 | DD23: 12.976127 | DE23: 13.070864 | DF23: 13.077588 | DG23: 11.53082 | DH23: 10.664832 | DJ23: -0.010545381 | DK23: 5.2504201e-07 | DL23: -0.056103291 | DM23: -0.038555594 | DO23: 0.0025315626 | DP23: 7.335298e-07 | DQ23: -0.11775283 | DR23: -0.069468637
A24: 600009.SH | B24: 600009 CH Equity | C24: Main board | D24: Shanghai International Airport | E24: Transportation and logistics | F24: 冯启斌 | G24: Qibin FENG | H24: N | I24: Outperform | J24: 34.5 | K24: 30.94 | L24: 0.0141 | M24: -0.0556 | N24: 2488.31 | O24: 2046.28 | P24: 76988.41 | Q24: 63311.89 | R24: 11047.016 | S24: 12368.804 | T24: 13351.93 | U24: 14161.79 | V24: 15110.75 | X24: 934.04971 | Y24: 1933.9487 | Z24: 2257.22 | AA24: 2818.67 | AB24: 3446.93 | AD24: 76988.41 | AE24: 76988.41 | AF24: 76988.41 | AG24: 76988.41 | AH24: 76988.41 | AI24: 76988.41 | AJ24: 42026.572 | AK24: 43530.097 | AL24: 43330.62 | AM24: 45472.12 | AN24: 48073.45 | AP24: 76988.41 | AQ24: 76988.41 | AR24: 76988.41 | AS24: 76988.41 | AT24: 76988.41 | AU24: 76988.41 | AV24: 298.61776 | AW24: 995.35177 | AX24: 677.17 | AY24: 845.6 | AZ24: 1034.08 | BB24: 76988.41 | BC24: 76988.41 | BD24: 76988.41 | BE24: 76988.41 | BF24: 76988.41 | BG24: 76988.41 | BH24: 4020.0865 | BI24: 5530.8164 | BJ24: 5348.23 | BK24: 5484.61 | BL24: 5941.98 | BN24: 0.37537514 | BO24: 0.77721374 | BP24: 0.90712974 | BQ24: 1.1327648 | BR24: 1.3852494 | BT24: 16.889605 | BU24: 17.49384 | BV24: 17.413674 | BW24: 18.274299 | BX24: 19.319719 | BZ24: 0.12000826 | CA24: 0.40001116 | CB24: 0.27214053 | CC24: 0.33982904 | CD24: 0.41557523 | CF24: 1.6155891 | CG24: 2.22272 | CH24: 2.1493423 | CI24: 2.2041506 | CJ24: 2.3879581 | CL24: 82.424317 | CM24: 39.80892 | CN24: 34.107624 | CO24: 27.313737 | CP24: 22.335356 | CR24: 1.8318984 | CS24: 1.7686248 | CT24: 1.7767669 | CU24: 1.6930904 | CV24: 1.6014746 | CX24: 0.0038787366 | CY24: 0.012928592 | CZ24: 0.0087957395 | DA24: 0.010983471 | DB24: 0.013431632 | DD24: 2.2225218 | DE24: 4.4427852 | DF24: 5.2092954 | DG24: 6.1986773 | DH24: 7.1701324 | DJ24: 0.11965114 | DK24: 0.079484313 | DL24: 0.060654902 | DM24: 0.067008478 | DO24: 1.0704987 | DP24: 0.16715608 | DQ24: 0.24873517 | DR24: 0.22289236
A25: 600011.SH | B25: 600011 CH Equity | C25: Main board | D25: Huaneng Power International | E25: Electricity and utilities | F25: 刘佳妮 | G25: Jiani LIU | H25: N | I25: Outperform | J25: 10.49 | K25: 6.92 | L25: 0.0102 | M25: -0.0724 | N25: 15698.09 | O25: 10997.71 | P25: 108630.81 | Q25: 76104.15 | R25: 254396.69 | S25: 245550.92 | T25: 239702.28 | U25: 236874.02 | V25: 236442.13 | X25: 8445.5604 | Y25: 10135.494 | Z25: 16030.49 | AA25: 14362.98 | AB25: 14565.19 | AD25: 108630.81 | AE25: 108630.81 | AF25: 108630.81 | AG25: 108630.81 | AH25: 108630.81 | AI25: 108630.81 | AJ25: 171362.56 | AK25: 203047.83 | AL25: 66111.66 | AM25: 70997.18 | AN25: 75088.5 | AP25: 108630.81 | AQ25: 108630.81 | AR25: 108630.81 | AS25: 108630.81 | AT25: 108630.81 | AU25: 108630.81 | AV25: 3139.6187 | AW25: 4238.4852 | AX25: 6553.03 | AY25: 7549.44 | AZ25: 6984.46 | BB25: 108630.81 | BC25: 108630.81 | BD25: 108630.81 | BE25: 108630.81 | BF25: 108630.81 | BG25: 108630.81 | BH25: 45497.117 | BI25: 50530.261 | BJ25: 63623.27 | BK25: 56511.2 | BL25: 57223.59 | BN25: 0.53799924 | BO25: 0.6456514 | BP25: 1.0211746 | BQ25: 0.9149508 | BR25: 0.92783198 | BT25: 10.916141 | BU25: 12.934556 | BV25: 4.2114461 | BW25: 4.5226636 | BX25: 4.7832889 | BZ25: 0.20000004 | CA25: 0.27000006 | CB25: 0.41744123 | CC25: 0.48091456 | CD25: 0.44492419 | CF25: 2.8982581 | CG25: 3.2188796 | CH25: 4.0529306 | CI25: 3.5998774 | CJ25: 3.6452581 | CL25: 12.862475 | CM25: 10.717861 | CN25: 6.7765121 | CO25: 7.5632501 | CP25: 7.4582487 | CR25: 0.63392382 | CS25: 0.5350011 | CT25: 1.6431415 | CU25: 1.5300722 | CV25: 1.4467037 | CX25: 0.028901733 | CY25: 0.03901734 | CZ25: 0.060323862 | DA25: 0.069496306 | DB25: 0.064295387 | DD25: 4.9284747 | DE25: 4.9916781 | DF25: 24.247599 | DG25: 20.230353 | DH25: 19.397364 | DJ25: -0.034771564 | DK25: -0.023818454 | DL25: -0.011799053 | DM25: -0.0018232899 | DO25: 0.20009724 | DP25: 0.58161904 | DQ25: -0.10402115 | DR25: 0.014078555
A26: 600015.SH | B26: 600015 CH Equity | C26: Main board | D26: Huaxia Bank | E26: Banks | F26: 张帅帅 | G26: Shuaishuai ZHANG | H26: N | I26: Outperform | J26: 7.94 | K26: 6.58 | L26: 0.0233 | M26: -0.0271 | N26: 15914.93 | O26: 15387.22 | P26: 104720.23 | Q26: 101247.93 | R26: 93207 | S26: 97146 | T26: 88768.72 | U26: 88026.44 | V26: 90332.79 | X26: 26363 | Y26: 27676 | Z26: 26751.76 | AA26: 25395.98 | AB26: 25112.84 | AD26: 104720.23 | AE26: 104720.23 | AF26: 104720.23 | AG26: 104720.23 | AH26: 104720.23 | AI26: 104720.23 | AJ26: 321762 | AK26: 365684 | AL26: 384569.76 | AM26: 402478.34 | AN26: 420324.75 | AP26: 104720.23 | AQ26: 104720.23 | AR26: 104720.23 | AS26: 104720.23 | AT26: 104720.23 | AU26: 104720.23 | AV26: 6111.3325 | AW26: 6445.546 | AX26: 6203.64 | AY26: 5864.65 | AZ26: 5793.03 | BB26: 104720.23 | BC26: 104720.23 | BD26: 104720.23 | BE26: 104720.23 | BF26: 104720.23 | BG26: 104720.23 | BH26: 253177 | BI26: 42495 | BN26: 1.6564949 | BO26: 1.738996 | BP26: 1.6809223 | BQ26: 1.5957331 | BR26: 1.5779422 | BT26: 20.21762 | BU26: 22.977418 | BV26: 24.164087 | BW26: 25.289357 | BX26: 26.410719 | BZ26: 0.38399996 | CA26: 0.40499996 | CB26: 0.38980002 | CC26: 0.36849989 | CD26: 0.36399972 | CF26: 15.908144 | CG26: 2.6701343 | CL26: 3.9722425 | CM26: 3.7837921 | CN26: 3.9145174 | CO26: 4.1234963 | CP26: 4.1699875 | CR26: 0.32545866 | CS26: 0.28636809 | CT26: 0.2723049 | CU26: 0.26018849 | CV26: 0.24914124 | CX26: 0.058358662 | CY26: 0.061550152 | CZ26: 0.05924013 | DA26: 0.056003028 | DB26: 0.055319111 | DD26: 8.193323 | DE26: 7.568283 | DF26: 6.9562828 | DG26: 6.3098998 | DH26: 5.974628 | DJ26: 0.042260774 | DK26: -0.086233916 | DL26: -0.0083619545 | DM26: 0.026200651 | DO26: 0.04980465 | DP26: -0.033394999 | DQ26: -0.05068003 | DR26: -0.011149009
A27: 600016.SH | B27: 600016 CH Equity | C27: Main board | D27: China Minsheng Bank | E27: Banks | F27: 张帅帅 | G27: Shuaishuai ZHANG | H27: N | I27: Outperform | J27: 5.2 | K27: 3.88 | L27: 0.0347 | M27: 0.0131 | N27: 43782.42 | O27: 35462.12 | P27: 169875.78 | Q27: 137593.04 | R27: 140817 | S27: 136290 | T27: 143834.5 | U27: 148530.63 | V27: 152729.02 | X27: 35823 | Y27: 32296 | Z27: 31177.2 | AA27: 31675.73 | AB27: 32908.85 | AD27: 169875.78 | AE27: 169875.78 | AF27: 169875.78 | AG27: 169875.78 | AH27: 169875.78 | AI27: 169875.78 | AJ27: 637801 | AK27: 656568 | AL27: 675172.45 | AM27: 695262.02 | AN27: 720145.38 | AP27: 169875.78 | AQ27: 169875.78 | AR27: 169875.78 | AS27: 169875.78 | AT27: 169875.78 | AU27: 169875.78 | AV27: 9457.0024 | AW27: 8406.2244 | AX27: 8060.34 | AY27: 8209.2 | AZ27: 8576.98 | BB27: 169875.78 | BC27: 169875.78 | BD27: 169875.78 | BE27: 169875.78 | BF27: 169875.78 | BG27: 169875.78 | BH27: 73676 | BI27: -231638 | BN27: 0.81820512 | BO27: 0.73764767 | BP27: 0.71209403 | BQ27: 0.72348057 | BR27: 0.7516453 | BT27: 14.567514 | BU27: 14.996156 | BV27: 15.421086 | BW27: 15.879936 | BX27: 16.448277 | BZ27: 0.21599999 | CA27: 0.19199999 | CB27: 0.18409992 | CC27: 0.18749991 | CD27: 0.19590009 | CF27: 1.6827759 | CG27: -5.2906623 | CL27: 4.7420869 | CM27: 5.2599635 | CN27: 5.4487183 | CO27: 5.3629634 | CP27: 5.162009 | CR27: 0.26634605 | CS27: 0.25873296 | CT27: 0.25160354 | CU27: 0.24433347 | CV27: 0.23589095 | CX27: 0.055670104 | CY27: 0.049484537 | CZ27: 0.047448436 | DA27: 0.048324723 | DB27: 0.050489717 | DD27: 5.6166422 | DE27: 4.9189117 | DF27: 4.6176647 | DG27: 4.5559414 | DH27: 4.5697509 | DJ27: -0.032148107 | DK27: 0.055356226 | DL27: 0.032649538 | DM27: 0.028266156 | DO27: -0.098456299 | DP27: -0.034642061 | DQ27: 0.015990211 | DR27: 0.03892949
A28: 600020.SH | B28: 600020 CH Equity | C28: Main board | D28: Zhongyuan Expressway | E28: Transportation and logistics | F28: 张文杰 | G28: Wenjie ZHANG | H28: N | I28: Outperform | J28: 5.17 | K28: 4.08 | L28: 0.0149 | M28: -0.0423 | N28: 2247.37 | O28: 2247.37 | P28: 9169.28 | Q28: 9169.28 | R28: 5702.8189 | S28: 6969.1092 | T28: 7737.57 | U28: 8353.99 | V28: 5634.18 | X28: 828.42739 | Y28: 880.3902 | Z28: 1062.26 | AA28: 1141.01 | AB28: 1292.92 | AD28: 9169.28 | AE28: 9169.28 | AF28: 9169.28 | AG28: 9169.28 | AH28: 9169.28 | AI28: 9169.28 | AJ28: 14763.378 | AK28: 15205.792 | AL28: 15885.98 | AM28: 16566.01 | AN28: 17363.78 | AP28: 9169.28 | AQ28: 9169.28 | AR28: 9169.28 | AS28: 9169.28 | AT28: 9169.28 | AU28: 9169.28 | AV28: 334.8584 | AW28: 382.05321 | AX28: 460.98 | AY28: 495.15 | AZ28: 561.07 | BB28: 9169.28 | BC28: 9169.28 | BD28: 9169.28 | BE28: 9169.28 | BF28: 9169.28 | BG28: 9169.28 | BH28: 2531.5807 | BI28: 2111.2177 | BJ28: 2275.65 | BK28: 2627.89 | BL28: 4140.64 | BN28: 0.36862083 | BO28: 0.39174244 | BP28: 0.47266805 | BQ28: 0.50770901 | BR28: 0.57530358 | BT28: 6.5691801 | BU28: 6.7660386 | BV28: 7.0686981 | BW28: 7.3712873 | BX28: 7.7262667 | BZ28: 0.14900012 | CA28: 0.17000014 | CB28: 0.20511976 | CC28: 0.2203242 | CD28: 0.24965626 | CF28: 1.1264637 | CG28: 0.93941707 | CH28: 1.0125836 | CI28: 1.1693179 | CJ28: 1.842438 | CL28: 11.068297 | CM28: 10.415018 | CN28: 8.6318604 | CO28: 8.0361084 | CP28: 7.091916 | CR28: 0.62108278 | CS28: 0.60301232 | CT28: 0.57719322 | CU28: 0.55349961 | CV28: 0.52806935 | CX28: 0.036519596 | CY28: 0.041666653 | CZ28: 0.050274394 | DA28: 0.054000968 | DB28: 0.061190192 | DD28: 5.6113673 | DE28: 5.7898345 | DF28: 6.6867766 | DG28: 6.8876573 | DH28: 7.4460745 | DJ28: 0.22204639 | DK28: 0.11026671 | DL28: 0.079665838 | DM28: -0.32557018 | DO28: 0.062724638 | DP28: 0.20657863 | DQ28: 0.074134393 | DR28: 0.13313643
A29: 600023.SH | B29: 600023 CH Equity | C29: Main board | D29: Zheneng Electric Power | E29: Electricity and utilities | F29: 刘佳妮 | G29: Jiani LIU | H29: N | I29: Outperform | J29: 3.91 | K29: 4.96 | L29: 0.004 | M29: 0.002 | N29: 13408.73 | O29: 13408.73 | P29: 66507.31 | Q29: 66507.31 | R29: 95975.196 | S29: 88003.044 | X29: 6519.7707 | Y29: 7753.383 | AD29: 66507.31 | AE29: 66507.31 | AF29: 66507.31 | AG29: 66507.31 | AH29: 66507.31 | AI29: 66507.31 | AJ29: 79967.254 | AK29: 86820.7 | AP29: 66507.31 | AQ29: 66507.31 | AR29: 66507.31 | AS29: 66507.31 | AT29: 66507.31 | AU29: 66507.31 | AV29: 3352.1832 | AW29: 3888.5325 | BB29: 66507.31 | BC29: 66507.31 | BD29: 66507.31 | BE29: 66507.31 | BF29: 66507.31 | BG29: 66507.31 | BH29: 11477.291 | BI29: 13706.855 | BN29: 0.48623328 | BO29: 0.57823396 | BT29: 5.9638202 | BU29: 6.4749384 | BZ29: 0.25000005 | CA29: 0.29000006 | CF29: 0.85595659 | CG29: 1.0222336 | CL29: 10.200866 | CM29: 8.577844 | CR29: 0.8316818 | CS29: 0.76603056 | CX29: 0.050403229 | CY29: 0.058467746 | DD29: 8.1530506 | DE29: 8.9303392 | DJ29: -0.083064717 | DO29: 0.189211
A30: 600025.SH | B30: 600025 CH Equity | C30: Main board | D30: Huaneng Lancang River Hydropower | E30: Electricity and utilities | F30: 刘佳妮 | G30: Jiani LIU | H30: N | I30: Outperform | J30: 10.36 | K30: 9.19 | L30: 0.0143 | M30: 0.0121 | N30: 18631.09 | O30: 18000 | P30: 171219.76 | Q30: 165420 | R30: 23461.332 | S30: 24881.607 | T30: 26494.84 | U30: 27349.46 | X30: 7638.0747 | Y30: 8297.029 | Z30: 8859.38 | AA30: 9397.67 | AD30: 171219.76 | AE30: 171219.76 | AF30: 171219.76 | AG30: 171219.76 | AH30: 171219.76 | AI30: 171219.76 | AJ30: 70723.344 | AK30: 79168.492 | AL30: 86672.53 | AM30: 92226.2 | AP30: 171219.76 | AQ30: 171219.76 | AR30: 171219.76 | AS30: 171219.76 | AT30: 171219.76 | AU30: 171219.76 | AV30: 3240 | AW30: 3600 | AX30: 3844 | AY30: 4077.56 | BB30: 171219.76 | BC30: 171219.76 | BD30: 171219.76 | BE30: 171219.76 | BF30: 171219.76 | BG30: 171219.76 | BH30: 17062.571 | BI30: 17553.802 | BJ30: 19065.46 | BK30: 20487.7 | BN30: 0.40996392 | BO30: 0.44533245 | BP30: 0.47551593 | BQ30: 0.50440795 | BT30: 3.7959853 | BU30: 4.2492679 | BV30: 4.6520375 | BW30: 4.9501237 | BZ30: 0.17390287 | CA30: 0.19322541 | CB30: 0.2063218 | CC30: 0.21885783 | CF30: 0.91581176 | CG30: 0.94217794 | CH30: 1.0233143 | CI30: 1.0996512 | CL30: 22.416612 | CM30: 20.636274 | CN30: 19.326382 | CO30: 18.219384 | CR30: 2.4209794 | CS30: 2.162726 | CT30: 1.975479 | CU30: 1.8565197 | CX30: 0.01892305 | CY30: 0.021025611 | CZ30: 0.02245068 | DA30: 0.023814775 | DD30: 10.799934 | DE30: 10.480216 | DF30: 10.22167 | DG30: 10.189805 | DJ30: 0.060536855 | DK30: 0.064836373 | DL30: 0.032256092 | DO30: 0.086272298 | DP30: 0.067777398 | DQ30: 0.060759331
A31: 600026.SH | B31: 600026 CH Equity | C31: Main board | D31: COSCO SHIPPING Energy Transportation | E31: Transportation and logistics | F31: 刘钢贤 | G31: Gangxian LIU | H31: N | I31: Outperform | J31: 13.5 | K31: 15.97 | L31: 0.0625 | M31: 0.3673 | N31: 5465.22 | O31: 3474.78 | P31: 87279.58 | Q31: 55492.18 | R31: 22090.522 | S31: 23243.743 | T31: 26642 | U31: 31054.24 | V31: 33719.54 | W31: 33483 | X31: 3350.5847 | Y31: 4036.5237 | Z31: 5077.77 | AA31: 6128.4 | AB31: 3542.17 | AC31: 3435.17 | AD31: 87279.58 | AE31: 87279.58 | AF31: 87279.58 | AG31: 87279.58 | AH31: 87279.58 | AI31: 87279.58 | AJ31: 37103.324 | AK31: 38985.157 | AL31: 38926.42 | AM31: 42515.93 | AN31: 42993.9 | AO31: 44657.98 | AP31: 87279.58 | AQ31: 87279.58 | AR31: 87279.58 | AS31: 87279.58 | AT31: 87279.58 | AU31: 87279.58 | AV31: 1669.7717 | AW31: 2051.4338 | AX31: 2538.88 | AY31: 3064.2 | AZ31: 1771.08 | BA31: 1717.58 | BB31: 87279.58 | BC31: 87279.58 | BD31: 87279.58 | BE31: 87279.58 | BF31: 87279.58 | BG31: 87279.58 | BH31: 8822.1571 | BI31: 8625.2862 | BJ31: 8205.01 | BK31: 9900.55 | BL31: 7653.96 | BM31: 7440.66 | BN31: 0.61307407 | BO31: 0.73858393 | BP31: 0.92910624 | BQ31: 1.1213455 | BR31: 0.64812944 | BS31: 0.62855109 | BT31: 6.7889899 | BU31: 7.1333189 | BV31: 7.1225715 | BW31: 7.779363 | BX31: 7.8668196 | BY31: 8.1713051 | BZ31: 0.3055269 | CA31: 0.37536162 | CB31: 0.4645522 | CC31: 0.56067276 | CD31: 0.32406381 | CE31: 0.31427463 | CF31: 1.6142364 | CG31: 1.5782139 | CH31: 1.5013138 | CI31: 1.8115556 | CJ31: 1.4004853 | CK31: 1.3614566 | CL31: 26.04906 | CM31: 21.622462 | CN31: 17.188565 | CO31: 14.241822 | CP31: 24.640144 | CQ31: 25.407645 | CR31: 2.3523386 | CS31: 2.23879 | CT31: 2.2421682 | CU31: 2.0528677 | CV31: 2.0300457 | CW31: 1.9544005 | CX31: 0.019131299 | CY31: 0.023504167 | CZ31: 0.029089049 | DA31: 0.035107868 | DB31: 0.020292032 | DC31: 0.019679059 | DD31: 9.0304166 | DE31: 10.354001 | DF31: 13.044534 | DG31: 14.414362 | DH31: 8.2387734 | DI31: 7.6921751 | DJ31: 0.052204334 | DK31: 0.14620092 | DL31: 0.16561219 | DM31: 0.085827249 | DN31: -0.0070149237 | DO31: 0.20472219 | DP31: 0.2579562 | DQ31: 0.20690776 | DR31: -0.42200738 | DS31: -0.030207472
A32: 600028.SH | B32: 600028 CH Equity | C32: Main board | D32: Sinopec | E32: Oil & gas | F32: 严蓓娜 | G32: Beina YAN | H32: N | I32: Outperform | J32: 6.4 | K32: 6.5 | L32: 0.0188 | M32: 0.0518 | N32: 120925.51 | O32: 94752.48 | P32: 786015.84 | Q32: 615891.09 | R32: 3212215 | S32: 3074562 | X32: 60463 | Y32: 50313 | AD32: 786015.84 | AE32: 786015.84 | AF32: 786015.84 | AG32: 786015.84 | AH32: 786015.84 | AI32: 786015.84 | AJ32: 958655 | AK32: 976293 | AP32: 786015.84 | AQ32: 786015.84 | AR32: 786015.84 | AS32: 786015.84 | AT32: 786015.84 | AU32: 786015.84 | AV32: 41724.944 | AW32: 34742.508 | BB32: 786015.84 | BC32: 786015.84 | BD32: 786015.84 | BE32: 786015.84 | BF32: 786015.84 | BG32: 786015.84 | BH32: 161475 | BI32: 149360 | BN32: 0.50000203 | BO32: 0.41606606 | BT32: 7.927649 | BU32: 8.0735074 | BZ32: 0.34504666 | CA32: 0.28730503 | CF32: 1.3353262 | CG32: 1.2351405 | CL32: 12.999948 | CM32: 15.62252 | CR32: 0.81991524 | CS32: 0.8051024 | CX32: 0.053084101 | CY32: 0.044200773 | DD32: 6.3070656 | DE32: 5.1534734 | DJ32: -0.042852985 | DO32: -0.16787126
A33: 600030.SH | B33: 600030 CH Equity | C33: Main board | D33: CITIC Securities | E33: Non-bank financials | F33: 樊优 | G33: You FAN | H33: N | I33: Outperform | J33: 40 | K33: 28.16 | L33: 0.0108 | M33: -0.0192 | N33: 14820.55 | O33: 12176.55 | P33: 417346.6 | Q33: 342891.68 | R33: 60067.993 | S33: 63789.216 | T33: 80623.56 | U33: 81592.69 | V33: 84937.25 | X33: 19720.547 | Y33: 21703.697 | Z33: 29264.14 | AA33: 29642.07 | AB33: 31497.48 | AD33: 417346.6 | AE33: 417346.6 | AF33: 417346.6 | AG33: 417346.6 | AH33: 417346.6 | AI33: 417346.6 | AJ33: 274199.21 | AK33: 298766.67 | AL33: 283904.47 | AM33: 303155.25 | AN33: 324127.24 | AP33: 417346.6 | AQ33: 417346.6 | AR33: 417346.6 | AS33: 417346.6 | AT33: 417346.6 | AU33: 417346.6 | AV33: 7039.7597 | AW33: 7706.6844 | AX33: 11914.24 | AY33: 12066.89 | AZ33: 12822.74 | BB33: 417346.6 | BC33: 417346.6 | BD33: 417346.6 | BE33: 417346.6 | BF33: 417346.6 | BG33: 417346.6 | BH33: -40836.96 | BI33: 172563 | BN33: 1.3306218 | BO33: 1.4644326 | BP33: 1.974565 | BQ33: 2.0000654 | BR33: 2.1252572 | BT33: 18.501284 | BU33: 20.158946 | BV33: 19.156136 | BW33: 20.455061 | BX33: 21.870122 | BZ33: 0.4749999 | CA33: 0.51999989 | CB33: 0.80389999 | CC33: 0.81419988 | CD33: 0.86520001 | CF33: -2.7554281 | CG33: 11.643495 | CL33: 21.163033 | CM33: 19.229287 | CN33: 14.261366 | CO33: 14.079536 | CP33: 13.250158 | CR33: 1.5220562 | CS33: 1.3968981 | CT33: 1.4700248 | CU33: 1.3766761 | CV33: 1.2876011 | CX33: 0.016867898 | CY33: 0.018465909 | CZ33: 0.028547591 | DA33: 0.028913354 | DB33: 0.030724439 | DD33: 7.1920512 | DE33: 7.2644303 | DF33: 10.307742 | DG33: 9.7778514 | DH33: 9.7176282 | DJ33: 0.061950179 | DK33: 0.2639058 | DL33: 0.012020432 | DM33: 0.040990927 | DO33: 0.10056258 | DP33: 0.34834819 | DQ33: 0.012914441 | DR33: 0.062593807
A34: 600031.SH | B34: 600031 CH Equity | C34: Main board | D34: Sany Heavy Industry | E34: Machinery | F34: 刘中玉 | G34: Zhongyu LIU | H34: N | I34: Outperform | J34: 22.6 | K34: 22.98 | L34: 0.0748 | M34: 0.0876 | N34: 9195 | O34: 8474.39 | P34: 211301.2 | Q34: 194741.48 | R34: 73221.725 | S34: 77773.391 | T34: 89165.92 | U34: 100323.05 | X34: 4527.498 | Y34: 5975.451 | Z34: 8515.17 | AA34: 10525.39 | AD34: 211301.2 | AE34: 211301.2 | AF34: 211301.2 | AG34: 211301.2 | AH34: 211301.2 | AI34: 211301.2 | AJ34: 69172.953 | AK34: 73001.599 | AL34: 78226.32 | AM34: 85485.68 | AP34: 211301.2 | AQ34: 211301.2 | AR34: 211301.2 | AS34: 211301.2 | AT34: 211301.2 | AU34: 211301.2 | AV34: 1862.1929 | AW34: 3029.9056 | AX34: 4318.57 | AY34: 5338.07 | BB34: 211301.2 | BC34: 211301.2 | BD34: 211301.2 | BE34: 211301.2 | BF34: 211301.2 | BG34: 211301.2 | BH34: 5708.22 | BI34: 14814.278 | BJ34: 17264.68 | BK34: 14162.26 | BN34: 0.49238695 | BO34: 0.64985873 | BP34: 0.92606525 | BQ34: 1.1446862 | BT34: 7.5228878 | BU34: 7.9392712 | BV34: 8.5074845 | BW34: 9.2969744 | BZ34: 0.20252234 | CA34: 0.32951665 | CB34: 0.46966504 | CC34: 0.58054051 | CF34: 0.62079608 | CG34: 1.6111232 | CH34: 1.8776161 | CI34: 1.5402132 | CL34: 46.670634 | CM34: 35.361548 | CN34: 24.814678 | CO34: 20.07538 | CR34: 3.0546795 | CS34: 2.8944736 | CT34: 2.7011522 | CU34: 2.4717731 | CX34: 0.0088129783 | CY34: 0.014339273 | CZ34: 0.020437981 | DA34: 0.025262848 | DD34: 6.5451854 | DE34: 8.18537 | DF34: 10.8853 | DG34: 12.31246 | DJ34: 0.06216278 | DK34: 0.14648363 | DL34: 0.12512774 | DO34: 0.31981306 | DP34: 0.42502549 | DQ34: 0.23607515
A35: 600036.SH | B35: 600036 CH Equity | C35: Main board | D35: China Merchants Bank | E35: Banks | F35: 张帅帅 | G35: Shuaishuai ZHANG | H35: N | I35: Outperform | J35: 58.35 | K35: 39.6 | L35: 0.0299 | M35: -0.0351 | N35: 25219.85 | O35: 20628.94 | P35: 998705.89 | Q35: 816906.2 | R35: 339123 | S35: 337488 | T35: 337794.16 | U35: 347101.11 | V35: 361036.57 | X35: 146602 | Y35: 148391 | Z35: 149255.33 | AA35: 151415.68 | AB35: 154720.44 | AD35: 998705.89 | AE35: 998705.89 | AF35: 998705.89 | AG35: 998705.89 | AH35: 998705.89 | AI35: 998705.89 | AJ35: 1085729 | AK35: 1233475 | AL35: 1303524.7 | AM35: 1400286.2 | AN35: 1499758.2 | AP35: 998705.89 | AQ35: 998705.89 | AR35: 998705.89 | AS35: 998705.89 | AT35: 998705.89 | AU35: 998705.89 | AV35: 49734 | AW35: 50440 | AX35: 50744.85 | AY35: 51509.01 | AZ35: 52674.17 | BB35: 998705.89 | BC35: 998705.89 | BD35: 998705.89 | BE35: 998705.89 | BF35: 998705.89 | BG35: 998705.89 | BH35: 357753 | BI35: 447023 | BN35: 5.8129608 | BO35: 5.883897 | BP35: 5.9181688 | BQ35: 6.0038295 | BR35: 6.1348676 | BT35: 43.050573 | BU35: 48.908895 | BV35: 51.686457 | BW35: 55.523177 | BX35: 59.467372 | BZ35: 1.9720181 | CA35: 2.0000119 | CB35: 2.0120996 | CC35: 2.0423995 | CD35: 2.0885997 | CF35: 14.185374 | CG35: 17.725046 | CL35: 6.812362 | CM35: 6.7302322 | CN35: 6.6912578 | CO35: 6.5957891 | CP35: 6.454906 | CR35: 0.91984822 | CS35: 0.80966853 | CT35: 0.76615802 | CU35: 0.71321555 | CV35: 0.66591127 | CX35: 0.049798445 | CY35: 0.050505359 | CZ35: 0.050810605 | DA35: 0.051575755 | DB35: 0.052742424 | DD35: 13.502633 | DE35: 12.030321 | DF35: 11.450135 | DG35: 10.813195 | DH35: 10.316359 | DJ35: -0.0048212595 | DK35: 0.000907173 | DL35: 0.027552134 | DM35: 0.040148129 | DO35: 0.012203108 | DP35: 0.0058246794 | DQ35: 0.01447419 | DR35: 0.021825745
A36: 600037.SH | B36: 600037 CH Equity | C36: Main board | D36: Gehua CATV Network | E36: Media | F36: 张雪晴 | G36: Xueqing ZHANG | H36: N | I36: Neutral | J36: 8.1 | K36: 7.93 | L36: -0.0075 | M36: 0.0863 | N36: 1391.78 | O36: 1391.78 | P36: 11036.8 | Q36: 11036.8 | R36: 2433.8809 | S36: 2314.1386 | T36: 2409.29 | U36: 2566.69 | V36: 2660.11 | X36: -172.41804 | Y36: -69.520904 | Z36: 197.17 | AA36: 319.93 | AB36: 325.14 | AD36: 11036.8 | AE36: 11036.8 | AF36: 11036.8 | AG36: 11036.8 | AH36: 11036.8 | AI36: 11036.8 | AJ36: 12827.176 | AK36: 12710.532 | AL36: 12879.67 | AM36: 13173.97 | AN36: 13457.51 | AP36: 11036.8 | AQ36: 11036.8 | AR36: 11036.8 | AS36: 11036.8 | AT36: 11036.8 | AU36: 11036.8 | AV36: 37.578003 | AW36: 37.578003 | AX36: 25.63 | AY36: 41.59 | AZ36: 42.27 | BB36: 11036.8 | BC36: 11036.8 | BD36: 11036.8 | BE36: 11036.8 | BF36: 11036.8 | BG36: 11036.8 | BH36: 747.27796 | BI36: 1074.444 | BJ36: 960.4 | BK36: 842.63 | BL36: 835.39 | BN36: -0.12388311 | BO36: -0.049951072 | BP36: 0.1416675 | BQ36: 0.2298711 | BR36: 0.23361451 | BT36: 9.216382 | BU36: 9.1325727 | BV36: 9.2540991 | BW36: 9.4655549 | BX36: 9.6692796 | BZ36: 0.026999959 | CA36: 0.026999959 | CB36: 0.018415267 | CC36: 0.029882596 | CD36: 0.030371179 | CF36: 0.53692247 | CG36: 0.7719927 | CH36: 0.69005159 | CI36: 0.60543333 | CJ36: 0.60023136 | CL36: -64.011864 | CM36: -158.75513 | CN36: 55.976061 | CO36: 34.497546 | CP36: 33.944762 | CR36: 0.8604232 | CS36: 0.86831928 | CT36: 0.85691637 | CU36: 0.83777328 | CV36: 0.820122 | CX36: 0.0034047915 | CY36: 0.0034047915 | CZ36: 0.0023222311 | DA36: 0.0037683024 | DB36: 0.0038299145 | DD36: -1.3441621 | DE36: -0.54695511 | DF36: 1.5308622 | DG36: 2.4285011 | DH36: 2.4160487 | DJ36: -0.049198107 | DK36: 0.041117428 | DL36: 0.06533045 | DM36: 0.036397072 | DO36: -0.59678868 | DP36: -3.8361254 | DQ36: 0.62260993 | DR36: 0.016284812
A37: 600038.SH | B37: 600038 CH Equity | C37: Main board | D37: Avicopter PLC | E37: High-end equipment | F37: 刘中玉 | G37: Zhongyu LIU | H37: N | I37: Outperform | J37: 44.21 | K37: 36.9 | L37: 0.0293 | M37: 0.0213 | N37: 819.89 | O37: 668.94 | P37: 30254.06 | Q37: 24683.71 | R37: 23329.929 | S37: 29765.64 | T37: 33505.94 | U37: 38270.26 | V37: 42097.29 | W37: 48411.88 | X37: 442.68795 | Y37: 555.87255 | Z37: 653.16 | AA37: 805.45 | AB37: 1003.18 | AC37: 1259.09 | AD37: 30254.06 | AE37: 30254.06 | AF37: 30254.06 | AG37: 30254.06 | AH37: 30254.06 | AI37: 30254.06 | AJ37: 10216.619 | AK37: 16388.062 | AL37: 16717.73 | AM37: 17326.65 | AN37: 18087.48 | AO37: 19044.71 | AP37: 30254.06 | AQ37: 30254.06 | AR37: 30254.06 | AS37: 30254.06 | AT37: 30254.06 | AU37: 30254.06 | AV37: 146.3212 | AW37: 167.25822 | AX37: 196.53 | AY37: 242.36 | AZ37: 301.85 | BA37: 359.91 | BB37: 30254.06 | BC37: 30254.06 | BD37: 30254.06 | BE37: 30254.06 | BF37: 30254.06 | BG37: 30254.06 | BH37: 716.61545 | BI37: 2567.7719 | BJ37: 2474.36 | BK37: 2426.72 | BL37: 2556.24 | BM37: 2951.78 | BN37: 0.53993578 | BO37: 0.67798431 | BP37: 0.79664345 | BQ37: 0.98238788 | BR37: 1.2235544 | BS37: 1.5356816 | BT37: 12.460963 | BU37: 19.988123 | BV37: 20.390211 | BW37: 21.132896 | BX37: 22.060862 | BY37: 23.228372 | BZ37: 0.17846442 | CA37: 0.2040008 | CB37: 0.23970289 | CC37: 0.29560063 | CD37: 0.36815914 | CE37: 0.43897352 | CF37: 0.87403852 | CG37: 3.1318493 | CH37: 3.017917 | CI37: 2.9598117 | CJ37: 3.1177841 | CK37: 3.6002147 | CL37: 68.34173 | CM37: 54.426253 | CN37: 46.319524 | CO37: 37.561686 | CP37: 30.158157 | CQ37: 24.028513 | CR37: 2.9612596 | CS37: 1.8461035 | CT37: 1.809699 | CU37: 1.7460998 | CV37: 1.672652 | CW37: 1.5885808 | CX37: 0.0048364153 | CY37: 0.0055284552 | CZ37: 0.0064959876 | DA37: 0.0080108257 | DB37: 0.0099771733 | DC37: 0.011896255 | DD37: 4.3330182 | DE37: 3.3919358 | DF37: 3.9069898 | DG37: 4.6486193 | DH37: 5.5462674 | DI37: 6.6112322 | DJ37: 0.27585642 | DK37: 0.1256583 | DL37: 0.14219329 | DM37: 0.1000001 | DN37: 0.14999992 | DO37: 0.25567582 | DP37: 0.17501754 | DQ37: 0.2331588 | DR37: 0.2454901 | DS37: 0.25509879
A38: 600054.SH | B38: 600054 CH Equity | C38: Main board | D38: Huangshan Tourism | E38: Consumer services | F38: 赖晟炜 | G38: Shengwei LAI | H38: N | I38: Neutral | J38: 11.7 | K38: 13.67 | L38: 0.038 | M38: 0.2146 | N38: 729.38 | O38: 513.3 | P38: 9970.62 | Q38: 7016.81 | R38: 1929.4419 | S38: 1931.1319 | T38: 2098.29 | U38: 2149.03 | X38: 422.90694 | Y38: 315.009 | Z38: 322.79 | AA38: 338.54 | AD38: 9970.62 | AE38: 9970.62 | AF38: 9970.62 | AG38: 9970.62 | AH38: 9970.62 | AI38: 9970.62 | AJ38: 4691.7168 | AK38: 4859.0662 | AL38: 4886.15 | AM38: 5127.62 | AP38: 9970.62 | AQ38: 9970.62 | AR38: 9970.62 | AS38: 9970.62 | AT38: 9970.62 | AU38: 9970.62 | AV38: 152.4403 | AW38: 125.45326 | AX38: 128.55 | AY38: 134.83 | BB38: 9970.62 | BC38: 9970.62 | BD38: 9970.62 | BE38: 9970.62 | BF38: 9970.62 | BG38: 9970.62 | BH38: 722.89353 | BI38: 521.663 | BJ38: 706.54 | BK38: 664.89 | BN38: 0.57981703 | BO38: 0.43188599 | BP38: 0.44255395 | BQ38: 0.46414763 | BT38: 6.4324725 | BU38: 6.6619131 | BV38: 6.6990458 | BW38: 7.0301078 | BZ38: 0.20899984 | CA38: 0.17199987 | CB38: 0.17624558 | CC38: 0.18485563 | CF38: 0.99110687 | CG38: 0.7152143 | CH38: 0.96868573 | CI38: 0.91158244 | CL38: 23.576392 | CM38: 31.651857 | CN38: 30.888875 | CO38: 29.451823 | CR38: 2.1251538 | CS38: 2.0519622 | CT38: 2.0405882 | CU38: 1.9444928 | CX38: 0.015288949 | CY38: 0.012582293 | CZ38: 0.012892879 | DA38: 0.01352273 | DD38: 9.013906 | DE38: 6.4829124 | DF38: 6.6062237 | DG38: 6.6022833 | DJ38: 0.00087589396 | DK38: 0.086559646 | DL38: 0.024181595 | DO38: -0.255134 | DP38: 0.024700875 | DQ38: 0.048793333
A39: 600059.SH | B39: 600059 CH Equity | C39: Main board | D39: Guyuelongshan Shaoxing Wine | E39: Food and beverage | F39: 武雨欣 | G39: Yuxin WU | H39: N | I39: Neutral | J39: 9.5 | K39: 9.95 | L39: -0.0349 | M39: 0.0745 | N39: 911.54 | O39: 911.54 | P39: 9069.85 | Q39: 9069.85 | R39: 1783.7017 | S39: 1936.2769 | T39: 2073.04 | U39: 2221.32 | X39: 396.62553 | Y39: 205.5672 | Z39: 216.21 | AA39: 243.28 | AD39: 9069.85 | AE39: 9069.85 | AF39: 9069.85 | AG39: 9069.85 | AH39: 9069.85 | AI39: 9069.85 | AJ39: 5854.7541 | AK39: 5934.0415 | AL39: 6038.55 | AM39: 6206.14 | AP39: 9069.85 | AQ39: 9069.85 | AR39: 9069.85 | AS39: 9069.85 | AT39: 9069.85 | AU39: 9069.85 | AV39: 127.61594 | AW39: 72.923393 | AX39: 76.7 | AY39: 86.3 | BB39: 9069.85 | BC39: 9069.85 | BD39: 9069.85 | BE39: 9069.85 | BF39: 9069.85 | BG39: 9069.85 | BH39: 393.39991 | BI39: 387.20771 | BJ39: 194.52 | BK39: 235.9 | BN39: 0.43511588 | BO39: 0.22551638 | BP39: 0.237192 | BQ39: 0.266889 | BT39: 6.4229261 | BU39: 6.509908 | BV39: 6.6245584 | BW39: 6.8084121 | BZ39: 0.14000037 | CA39: 0.080000212 | CB39: 0.084143318 | CC39: 0.094674946 | CF39: 0.43157723 | CG39: 0.42478412 | CH39: 0.21339711 | CI39: 0.25879281 | CL39: 22.86754 | CM39: 44.121096 | CN39: 41.949262 | CO39: 37.281527 | CR39: 1.5491428 | CS39: 1.528444 | CT39: 1.5019914 | CU39: 1.4614317 | CX39: 0.014070347 | CY39: 0.0080401984 | CZ39: 0.0084565897 | DA39: 0.0095150416 | DD39: 6.7744182 | DE39: 3.4642022 | DF39: 3.5804953 | DG39: 3.9199889 | DJ39: 0.085538537 | DK39: 0.070632004 | DL39: 0.071527805 | DO39: -0.48170962 | DP39: 0.051772863 | DQ39: 0.12520235
A40: 600060.SH | B40: 600060 CH Equity | C40: Main board | D40: Hisense Visual | E40: Home appliances | F40: 褚君 | G40: Jun CHU | H40: N | I40: Outperform | J40: 30.8 | K40: 24.28 | L40: 0.021 | M40: 0 | N40: 1304.97 | O40: 1300.17 | P40: 31684.73 | Q40: 31568.1 | R40: 53615.559 | S40: 58530.242 | T40: 62238.56 | U40: 67453.25 | V40: 72874.04 | X40: 2095.8547 | Y40: 2246.2173 | Z40: 2508.45 | AA40: 2823.29 | AB40: 3172.85 | AD40: 31684.73 | AE40: 31684.73 | AF40: 31684.73 | AG40: 31684.73 | AH40: 31684.73 | AI40: 31684.73 | AJ40: 25232.256 | AK40: 24998.997 | AL40: 20938.24 | AM40: 22507.31 | AN40: 24268.52 | AP40: 31684.73 | AQ40: 31684.73 | AR40: 31684.73 | AS40: 31684.73 | AT40: 31684.73 | AU40: 31684.73 | AV40: 1051.2395 | AW40: 1148.3756 | AX40: 1254.22 | AY40: 1411.65 | AZ40: 1586.43 | BB40: 31684.73 | BC40: 31684.73 | BD40: 31684.73 | BE40: 31684.73 | BF40: 31684.73 | BG40: 31684.73 | BH40: 2927.5957 | BI40: 3594.6549 | BJ40: 2292.64 | BK40: 2988.14 | BL40: 3375.26 | BN40: 1.6060558 | BO40: 1.7212789 | BP40: 1.9222281 | BQ40: 2.1634903 | BR40: 2.4313586 | BT40: 19.335507 | BU40: 19.15676 | BV40: 16.044997 | BW40: 17.247377 | BX40: 18.596995 | BZ40: 0.80556601 | CA40: 0.88000152 | CB40: 0.96111022 | CC40: 1.081749 | CD40: 1.2156831 | CF40: 2.2434199 | CG40: 2.7545882 | CH40: 1.7568526 | CI40: 2.2898151 | CJ40: 2.5864656 | CL40: 15.117809 | CM40: 14.105817 | CN40: 12.631199 | CO40: 11.222627 | CP40: 9.9862048 | CR40: 1.2557232 | CS40: 1.2674401 | CT40: 1.5132471 | CU40: 1.4077529 | CV40: 1.3055897 | CX40: 0.03317811 | CY40: 0.036243818 | CZ40: 0.039584368 | DA40: 0.044553007 | DB40: 0.050069229 | DD40: 8.3062517 | DE40: 8.9852298 | DF40: 11.980233 | DG40: 12.54388 | DH40: 13.073933 | DJ40: 0.09166524 | DK40: 0.063357303 | DL40: 0.083785518 | DM40: 0.080363659 | DO40: 0.071742858 | DP40: 0.11674414 | DQ40: 0.12551177 | DR40: 0.123813
A41: 600062.SH | B41: 600062 CH Equity | C41: Main board | D41: China Resources Double-Crane Pharmaceutical | E41: Pharmaceuticals | F41: 朱言音 | G41: Yanyin ZHU | H41: N | I41: Outperform | J41: 25 | K41: 18.68 | L41: 0.018 | M41: 0.0213 | N41: 1038.76 | O41: 1032.98 | P41: 19403.99 | Q41: 19296.03 | R41: 10222.132 | S41: 11211.624 | T41: 11211.62 | U41: 11767.09 | V41: 12357.77 | W41: 13047.59 | X41: 1333.0295 | Y41: 1627.7184 | Z41: 1627.72 | AA41: 1742.37 | AB41: 1864.14 | AC41: 1998.17 | AD41: 19403.99 | AE41: 19403.99 | AF41: 19403.99 | AG41: 19403.99 | AH41: 19403.99 | AI41: 19403.99 | AJ41: 11789.773 | AK41: 11111.755 | AL41: 10407.86 | AM41: 11660.94 | AN41: 13001.32 | AO41: 14439.14 | AP41: 19403.99 | AQ41: 19403.99 | AR41: 19403.99 | AS41: 19403.99 | AT41: 19403.99 | AU41: 19403.99 | AV41: 267.1918 | AW41: 489.34027 | AX41: 489.29 | AY41: 523.75 | AZ41: 560.36 | BA41: 600.65 | BB41: 19403.99 | BC41: 19403.99 | BD41: 19403.99 | BE41: 19403.99 | BF41: 19403.99 | BG41: 19403.99 | BH41: 1630.7821 | BI41: 1825.1152 | BJ41: 1825.12 | BK41: 2274.61 | BL41: 2462.24 | BM41: 2667.4 | BN41: 1.2832892 | BO41: 1.5669822 | BP41: 1.5669837 | BQ41: 1.6773557 | BR41: 1.794582 | BS41: 1.9236108 | BT41: 11.349852 | BU41: 10.697134 | BV41: 10.019504 | BW41: 11.225827 | BX41: 12.516192 | BY41: 13.900362 | BZ41: 0.25722188 | CA41: 0.47108116 | CB41: 0.47103277 | CC41: 0.50420694 | CD41: 0.53945088 | CE41: 0.57823751 | CF41: 1.5699315 | CG41: 1.7570134 | CH41: 1.757018 | CI41: 2.1897358 | CJ41: 2.3703647 | CK41: 2.5678694 | CL41: 14.55631 | CM41: 11.920975 | CN41: 11.920963 | CO41: 11.13655 | CP41: 10.409084 | CQ41: 9.7108805 | CR41: 1.6458324 | CS41: 1.7462579 | CT41: 1.8643592 | CU41: 1.6640159 | CV41: 1.4924631 | CW41: 1.3438467 | CX41: 0.013769941 | CY41: 0.025218538 | CZ41: 0.025215948 | DA41: 0.026991871 | DB41: 0.028878597 | DC41: 0.030954974 | DD41: 11.30666 | DE41: 14.648617 | DF41: 15.639334 | DG41: 14.941934 | DH41: 14.338083 | DI41: 13.838567 | DJ41: 0.096798941 | DK41: -3.2699902e-07 | DL41: 0.049544134 | DM41: 0.050197627 | DN41: 0.055820751 | DO41: 0.22106708 | DP41: 9.8005896e-07 | DQ41: 0.070435947 | DR41: 0.069887567 | DS41: 0.071899106
A42: 600066.SH | B42: 600066 CH Equity | C42: Main board | D42: Yutong Bus | E42: Auto | F42: 常菁 | G42: Jing CHANG | H42: N | I42: Outperform | J42: 38 | K42: 31.58 | L42: 0.029 | M42: -0.0343 | N42: 2213.94 | O42: 2213.94 | P42: 69916.2 | Q42: 69916.2 | R42: 27041.989 | S42: 37217.587 | T42: 42578.42 | U42: 47296.04 | V42: 51760.16 | W42: 55313.98 | X42: 1817.0842 | Y42: 4116.1944 | Z42: 4827.67 | AA42: 5504.9 | AB42: 6372.9 | AC42: 6914.88 | AD42: 69916.2 | AE42: 69916.2 | AF42: 69916.2 | AG42: 69916.2 | AH42: 69916.2 | AI42: 69916.2 | AJ42: 14056.62 | AK42: 13657.511 | AL42: 15104.97 | AM42: 17288.96 | AN42: 20340.95 | AO42: 23934.92 | AP42: 69916.2 | AQ42: 69916.2 | AR42: 69916.2 | AS42: 69916.2 | AT42: 69916.2 | AU42: 69916.2 | AV42: 3320.9088 | AW42: 3320.9088 | AX42: 3320.91 | AY42: 3320.91 | AZ42: 3320.91 | BA42: 3320.91 | BB42: 69916.2 | BC42: 69916.2 | BD42: 69916.2 | BE42: 69916.2 | BF42: 69916.2 | BG42: 69916.2 | BH42: 4716.6977 | BI42: 7210.5903 | BJ42: 6338.83 | BK42: 9377.52 | BL42: 9182.96 | BM42: 8631.03 | BN42: 0.82074679 | BO42: 1.8592168 | BP42: 2.1805785 | BQ42: 2.4864721 | BR42: 2.8785333 | BS42: 3.1233367 | BT42: 6.3491421 | BU42: 6.1688715 | BV42: 6.8226646 | BW42: 7.8091367 | BX42: 9.1876699 | BY42: 10.811007 | BZ42: 1.4999995 | CA42: 1.4999995 | CB42: 1.5 | CC42: 1.5 | CD42: 1.5 | CE42: 1.5 | CF42: 2.1304542 | CG42: 3.2569041 | CH42: 2.8631444 | CI42: 4.2356703 | CJ42: 4.1477908 | CK42: 3.8984932 | CL42: 38.477139 | CM42: 16.985641 | CN42: 14.48239 | CO42: 12.700721 | CP42: 10.970861 | CQ42: 10.110978 | CR42: 4.9738985 | CS42: 5.1192489 | CT42: 4.6286884 | CU42: 4.0439795 | CV42: 3.4372141 | CW42: 2.921096 | CX42: 0.047498417 | CY42: 0.047498417 | CZ42: 0.047498434 | DA42: 0.047498434 | DB42: 0.047498434 | DC42: 0.047498434 | DD42: 12.926893 | DE42: 30.138686 | DF42: 31.960805 | DG42: 31.84055 | DH42: 31.330395 | DI42: 28.890341 | DJ42: 0.37628878 | DK42: 0.14404033 | DL42: 0.11079838 | DM42: 0.09438676 | DN42: 0.06865937 | DO42: 1.2652745 | DP42: 0.1728479 | DQ42: 0.14028092 | DR42: 0.15767771 | DS42: 0.085044485
A43: 600085.SH | B43: 600085 CH Equity | C43: Main board | D43: Tongrentang | E43: Pharmaceuticals | F43: 朱言音 | G43: Yanyin ZHU | H43: N | I43: Outperform | J43: 47 | K43: 31.53 | L43: 0.0468 | M43: -0.0226 | N43: 1371.47 | O43: 1371.47 | P43: 43242.46 | Q43: 43242.46 | R43: 17860.891 | S43: 18597.282 | T43: 18600.41 | U43: 19236.3 | V43: 19852.15 | W43: 20438.48 | X43: 1668.8345 | Y43: 1526.2749 | Z43: 1385.86 | AA43: 1481 | AB43: 1632.35 | AC43: 1761.48 | AD43: 43242.46 | AE43: 43242.46 | AF43: 43242.46 | AG43: 43242.46 | AH43: 43242.46 | AI43: 43242.46 | AJ43: 20257.106 | AK43: 20901.001 | AL43: 14087.59 | AM43: 15119.51 | AN43: 16271.95 | AO43: 17504.47 | AP43: 43242.46 | AQ43: 43242.46 | AR43: 43242.46 | AS43: 43242.46 | AT43: 43242.46 | AU43: 43242.46 | AV43: 685.73513 | AW43: 1371.4703 | AX43: 449.08 | AY43: 479.91 | AZ43: 528.96 | BA43: 570.8 | BB43: 43242.46 | BC43: 43242.46 | BD43: 43242.46 | BE43: 43242.46 | BF43: 43242.46 | BG43: 43242.46 | BH43: 1869.4919 | BI43: 760.98527 | BJ43: 5110.49 | BK43: 2419.54 | BL43: 2792 | BM43: 2926.49 | BN43: 1.2168217 | BO43: 1.1128752 | BP43: 1.0104924 | BQ43: 1.0798632 | BR43: 1.1902193 | BS43: 1.2843737 | BT43: 14.77036 | BU43: 15.239853 | BV43: 10.271891 | BW43: 11.02431 | BX43: 11.864605 | BY43: 12.76329 | BZ43: 0.5000001 | CA43: 1.0000002 | CB43: 0.32744428 | CC43: 0.3499238 | CD43: 0.38568835 | CE43: 0.41619576 | CF43: 1.36313 | CG43: 0.55486833 | CH43: 3.7262864 | CI43: 1.7641946 | CJ43: 2.0357718 | CK43: 2.1338345 | CL43: 25.911772 | CM43: 28.332025 | CN43: 31.202618 | CO43: 29.19815 | CP43: 26.490924 | CQ43: 24.548936 | CR43: 2.134681 | CS43: 2.0689181 | CT43: 3.0695428 | CU43: 2.8600437 | CV43: 2.6574848 | CW43: 2.4703667 | CX43: 0.015857912 | CY43: 0.031715824 | CZ43: 0.010385163 | DA43: 0.01109812 | DB43: 0.012232422 | DC43: 0.013199989 | DD43: 8.2382671 | DE43: 7.3024011 | DF43: 9.8374527 | DG43: 9.795291 | DH43: 10.03168 | DI43: 10.06303 | DJ43: 0.041229193 | DK43: 0.00016821787 | DL43: 0.034186881 | DM43: 0.032014992 | DN43: 0.029534836 | DO43: -0.085424638 | DP43: -0.091998449 | DQ43: 0.068650513 | DR43: 0.10219446 | DS43: 0.079106809
A44: 600089.SH | B44: 600089 CH Equity | C44: Main board | D44: TBEA | E44: Electrical equipment and new energy | F44: 曲昊源 | G44: Haoyuan QU | H44: N | I44: Outperform | J44: 22.3 | K44: 27.55 | L44: -0.0282 | M44: 0.2399 | N44: 5052.79 | O44: 5052.79 | P44: 139204.44 | Q44: 139204.44 | R44: 98123.484 | S44: 97782.191 | T44: 100587.65 | U44: 112824.08 | X44: 10702.711 | Y44: 4134.7555 | Z44: 6025.2 | AA44: 6886.68 | AD44: 139204.44 | AE44: 139204.44 | AF44: 139204.44 | AG44: 139204.44 | AH44: 139204.44 | AI44: 139204.44 | AJ44: 87731.878 | AK44: 90043.152 | AL44: 72238.45 | AM44: 77296.5 | AP44: 139204.44 | AQ44: 139204.44 | AR44: 139204.44 | AS44: 139204.44 | AT44: 139204.44 | AU44: 139204.44 | AV44: 1004.0497 | AW44: 1255.0622 | AX44: 1828.64 | AY44: 2090.1 | BB44: 139204.44 | BC44: 139204.44 | BD44: 139204.44 | BE44: 139204.44 | BF44: 139204.44 | BG44: 139204.44 | BH44: 25812.076 | BI44: 12949.256 | BJ44: 7182.01 | BK44: 13327.73 | BN44: 2.1181784 | BO44: 0.81831137 | BP44: 1.1924501 | BQ44: 1.362946 | BT44: 17.363056 | BU44: 17.820482 | BV44: 14.296745 | BW44: 15.297786 | BZ44: 0.19871195 | CA44: 0.24838994 | CB44: 0.36190699 | CC44: 0.41365266 | CF44: 5.1084799 | CG44: 2.5627932 | CH44: 1.4213949 | CI44: 2.6376972 | CL44: 13.006466 | CM44: 33.66691 | CN44: 23.103704 | CO44: 20.213578 | CR44: 1.5867031 | CS44: 1.5459748 | CT44: 1.9270131 | CU44: 1.8009152 | CX44: 0.0072127709 | CY44: 0.0090159637 | CZ44: 0.013136363 | DA44: 0.015014607 | DD44: 12.199341 | DE44: 4.5919711 | DF44: 8.3407105 | DG44: 8.9094332 | DJ44: -0.0034781961 | DK44: 0.028690899 | DL44: 0.12164943 | DO44: -0.61367212 | DP44: 0.45720829 | DQ44: 0.14297949
A45: 600096.SH | B45: 600096 CH Equity | C45: Main board | D45: Yuntianhua | E45: Chemicals | F45: 贾雄伟 | G45: Xiongwei JIA | H45: N | I45: Outperform | J45: 40 | K45: 35.78 | L45: 0.0211 | M45: 0.0709 | N45: 1822.99 | O45: 1822.99 | P45: 65226.61 | Q45: 65226.61 | R45: 69060.213 | S45: 61536.937 | T45: 51887.07 | U45: 52552.45 | X45: 4522.1982 | Y45: 5332.959 | Z45: 5806.19 | AA45: 5827.51 | AD45: 65226.61 | AE45: 65226.61 | AF45: 65226.61 | AG45: 65226.61 | AH45: 65226.61 | AI45: 65226.61 | AJ45: 22010.482 | AK45: 24576.494 | AL45: 25596.38 | AM45: 28871.7 | AP45: 65226.61 | AQ45: 65226.61 | AR45: 65226.61 | AS45: 65226.61 | AT45: 65226.61 | AU45: 65226.61 | AV45: 1822.9907 | AW45: 2552.187 | AX45: 2552.19 | AY45: 2552.19 | BB45: 65226.61 | BC45: 65226.61 | BD45: 65226.61 | BE45: 65226.61 | BF45: 65226.61 | BG45: 65226.61 | BH45: 9437.1658 | BI45: 10752.13 | BJ45: 9291.42 | BK45: 9171.38 | BN45: 2.4806489 | BO45: 2.9253913 | BP45: 3.1849818 | BQ45: 3.1966769 | BT45: 12.073836 | BU45: 13.48142 | BV45: 14.040878 | BW45: 15.837553 | BZ45: 1.0000004 | CA45: 1.4000006 | CB45: 1.4000022 | CC45: 1.4000022 | CF45: 5.1767513 | CG45: 5.8980741 | CH45: 5.0968025 | CI45: 5.0309546 | CL45: 14.423651 | CM45: 12.230848 | CN45: 11.233978 | CO45: 11.192878 | CR45: 2.963434 | CS45: 2.6540243 | CT45: 2.5482748 | CU45: 2.2591884 | CX45: 0.027948574 | CY45: 0.039128003 | CZ45: 0.039128049 | DA45: 0.039128049 | DD45: 20.545657 | DE45: 21.69943 | DF45: 22.683637 | DG45: 20.18416 | DJ45: -0.10893792 | DK45: -0.15681422 | DL45: 0.012823619 | DO45: 0.17928469 | DP45: 0.088737031 | DQ45: 0.0036719432
A46: 600104.SH | B46: 600104 CH Equity | C46: Main board | D46: SAIC Motor | E46: Auto | F46: 邓学 | G46: Xue DENG | H46: N | I46: Outperform | J46: 23.5 | K46: 14.45 | L46: 0.0285 | M46: -0.0506 | N46: 11495.28 | O46: 11495.28 | P46: 166106.76 | Q46: 166106.76 | R46: 726199.11 | S46: 614074.06 | T46: 646186.73 | U46: 645972.37 | V46: 648018.68 | W46: 653041.61 | X46: 14106.165 | Y46: 1666.3768 | Z46: 11990.97 | AA46: 14017.97 | AB46: 13289.66 | AC46: 12941.45 | AD46: 166106.76 | AE46: 166106.76 | AF46: 166106.76 | AG46: 166106.76 | AH46: 166106.76 | AI46: 166106.76 | AJ46: 342907.23 | AK46: 346734.98 | AL46: 298812.44 | AM46: 305500.54 | AN46: 310221.26 | AO46: 315038.98 | AP46: 166106.76 | AQ46: 166106.76 | AR46: 166106.76 | AS46: 166106.76 | AT46: 166106.76 | AU46: 166106.76 | AV46: 4232.236 | AW46: 1005.3903 | AX46: 7329.87 | AY46: 8568.93 | AZ46: 8123.73 | BA46: 7910.88 | BB46: 166106.76 | BC46: 166106.76 | BD46: 166106.76 | BE46: 166106.76 | BF46: 166106.76 | BG46: 166106.76 | BH46: 42334.423 | BI46: 69267.79 | BJ46: 32851.77 | BK46: 34307.74 | BL46: 35855.36 | BM46: 37346.52 | BN46: 1.2271267 | BO46: 0.14496182 | BP46: 1.0431212 | BQ46: 1.2194544 | BR46: 1.1560971 | BS46: 1.1258055 | BT46: 29.830264 | BU46: 30.163248 | BV46: 25.994359 | BW46: 26.576172 | BX46: 26.986838 | BY46: 27.405942 | BZ46: 0.36817163 | CA46: 0.087461136 | CB46: 0.63764171 | CC46: 0.7454303 | CD46: 0.70670136 | CE46: 0.68818506 | CF46: 3.6827657 | CG46: 6.0257592 | CH46: 2.8578486 | CI46: 2.9845067 | CJ46: 3.1191376 | CK46: 3.2488569 | CL46: 11.775473 | CM46: 99.681395 | CN46: 13.852654 | CO46: 11.849559 | CP46: 12.498947 | CQ46: 12.835251 | CR46: 0.48440728 | CS46: 0.47905971 | CT46: 0.55588971 | CU46: 0.54372002 | CV46: 0.53544609 | CW46: 0.5272578 | CX46: 0.025479011 | CY46: 0.0060526751 | CZ46: 0.044127464 | DA46: 0.051586883 | DB46: 0.048906679 | DC46: 0.047625274 | DD46: 4.1136972 | DE46: 0.4805909 | DF46: 4.0128751 | DG46: 4.5885254 | DH46: 4.2839295 | DI46: 4.1078885 | DJ46: -0.15439987 | DK46: 0.052294455 | DL46: -0.00033173074 | DM46: 0.003167798 | DN46: 0.0077512117 | DO46: -0.8818689 | DP46: 6.1958337 | DQ46: 0.16904387 | DR46: -0.051955454 | DS46: -0.026201573
A47: 600109.SH | B47: 600109 CH Equity | C47: Main board | D47: Sinolink Securities | E47: Non-bank financials | F47: 樊优 | G47: You FAN | H47: N | I47: Neutral | J47: 11.8 | K47: 9.16 | L47: 0.0066 | M47: -0.0151 | N47: 3705.36 | O47: 3705.36 | P47: 33941.14 | Q47: 33941.14 | R47: 6729.8722 | S47: 6664.107 | T47: 8174.28 | U47: 9238.61 | V47: 9837.9 | X47: 1718.4388 | Y47: 1670.271 | Z47: 2199.36 | AA47: 2634 | AB47: 2838.69 | AD47: 33941.14 | AE47: 33941.14 | AF47: 33941.14 | AG47: 33941.14 | AH47: 33941.14 | AI47: 33941.14 | AJ47: 32796.541 | AK47: 33954.126 | AL47: 35487.84 | AM47: 37681.96 | AN47: 39993.86 | AP47: 33941.14 | AQ47: 33941.14 | AR47: 33941.14 | AS47: 33941.14 | AT47: 33941.14 | AU47: 33941.14 | AV47: 516.66405 | AW47: 441.99155 | AX47: 539.81 | AY47: 646.73 | AZ47: 696.85 | BB47: 33941.14 | BC47: 33941.14 | BD47: 33941.14 | BE47: 33941.14 | BF47: 33941.14 | BG47: 33941.14 | BH47: -5625.1335 | BI47: 11784.076 | BN47: 0.46377107 | BO47: 0.45077157 | BP47: 0.59356176 | BQ47: 0.7108621 | BR47: 0.7661037 | BT47: 8.8511077 | BU47: 9.1635161 | BV47: 9.5774338 | BW47: 10.169581 | BX47: 10.793515 | BZ47: 0.13943694 | CA47: 0.11928437 | CB47: 0.14568355 | CC47: 0.17453905 | CD47: 0.1880654 | CF47: -1.5181071 | CG47: 3.1802783 | CL47: 19.751149 | CM47: 20.320739 | CN47: 15.43228 | CO47: 12.885778 | CP47: 11.956621 | CR47: 1.0349 | CS47: 0.99961754 | CT47: 0.95641606 | CU47: 0.9007265 | CV47: 0.84865877 | CX47: 0.015222354 | CY47: 0.013022295 | CZ47: 0.015904298 | DA47: 0.019054457 | DB47: 0.020531131 | DD47: 5.2396952 | DE47: 4.9191988 | DF47: 6.1975031 | DG47: 6.9900823 | DH47: 7.0978145 | DJ47: -0.0097721403 | DK47: 0.22661296 | DL47: 0.13020474 | DM47: 0.064867983 | DO47: -0.028029979 | DP47: 0.31676839 | DQ47: 0.19762113 | DR47: 0.077710706
A48: 600111.SH | B48: 600111 CH Equity | C48: Main board | D48: Northern Rare Earth | E48: Non-ferrous metals | F48: 齐丁 | G48: Ding QI | H48: N | I48: Outperform | J48: 36.16 | K48: 50.11 | L48: 0.0514 | M48: 0.0865 | N48: 3615.07 | O48: 3615.07 | P48: 181150.95 | Q48: 181150.95 | R48: 33496.993 | S48: 32966.315 | T48: 35097.65 | U48: 36188 | X48: 2370.7402 | Y48: 1004.2769 | Z48: 2064.98 | AA48: 2255.85 | AD48: 181150.95 | AE48: 181150.95 | AF48: 181150.95 | AG48: 181150.95 | AH48: 181150.95 | AI48: 181150.95 | AJ48: 26901.292 | AK48: 28155.498 | AL48: 24370.19 | AM48: 26365.87 | AP48: 181150.95 | AQ48: 181150.95 | AR48: 181150.95 | AS48: 181150.95 | AT48: 181150.95 | AU48: 181150.95 | AV48: 253.05461 | AW48: 126.5273 | AX48: 260.16 | AY48: 284.21 | BB48: 181150.95 | BC48: 181150.95 | BD48: 181150.95 | BE48: 181150.95 | BF48: 181150.95 | BG48: 181150.95 | BH48: 2427.8409 | BI48: 1025.5776 | BJ48: 4612.29 | BK48: 4645.78 | BN48: 0.65579371 | BO48: 0.2778029 | BP48: 0.57121439 | BQ48: 0.62401281 | BT48: 7.4414304 | BU48: 7.7883686 | BV48: 6.7412775 | BW48: 7.2933221 | BZ48: 0.069999919 | CA48: 0.03499996 | CB48: 0.071965411 | CC48: 0.078618118 | CF48: 0.6715889 | CG48: 0.28369507 | CH48: 1.2758508 | CI48: 1.2851148 | CL48: 76.411136 | CM48: 180.37948 | CN48: 87.725281 | CO48: 80.302746 | CR48: 6.7339127 | CS48: 6.4339459 | CT48: 7.4333007 | CU48: 6.8706608 | CX48: 0.0013969268 | CY48: 0.00069846338 | CZ48: 0.0014361503 | DA48: 0.0015689126 | DD48: 8.8127373 | DE48: 3.5668946 | DF48: 8.4733849 | DG48: 8.5559475 | DJ48: -0.015842563 | DK48: 0.064651906 | DL48: 0.031066182 | DO48: -0.57638676 | DP48: 1.0561859 | DQ48: 0.092431888
A49: 600115.SH | B49: 600115 CH Equity | C49: Main board | D49: China Eastern Airlines | E49: Transportation and logistics | F49: 冯启斌 | G49: Qibin FENG | H49: N | I49: Outperform | J49: 6.5 | K49: 6.3 | L49: 0.1496 | M49: 0.05 | N49: 22087.74 | O49: 17024.96 | P49: 139152.74 | Q49: 107257.28 | R49: 113741 | S49: 132120 | T49: 137116.13 | U49: 148329.56 | X49: -8168 | Y49: -4226 | Z49: 1494.11 | AA49: 5930.32 | AD49: 139152.74 | AE49: 139152.74 | AF49: 139152.74 | AG49: 139152.74 | AH49: 139152.74 | AI49: 139152.74 | AJ49: 41221 | AK49: 41409 | AL49: 42026.11 | AM49: 47956.43 | AP49: 139152.74 | AQ49: 139152.74 | AR49: 139152.74 | AS49: 139152.74 | AT49: 139152.74 | AU49: 139152.74 | BB49: 139152.74 | BC49: 139152.74 | BD49: 139152.74 | BE49: 139152.74 | BF49: 139152.74 | BG49: 139152.74 | BH49: 26573 | BI49: 37314 | BJ49: 25674.39 | BK49: 26722.69 | BN49: -0.36979791 | BO49: -0.19132786 | BP49: 0.067644313 | BQ49: 0.26848922 | BT49: 1.8662389 | BU49: 1.8747504 | BV49: 1.9026895 | BW49: 2.1711787 | CF49: 1.2030656 | CG49: 1.6893535 | CH49: 1.1623819 | CI49: 1.2098427 | CL49: -17.03633 | CM49: -32.927766 | CN49: 93.1342 | CO49: 23.464626 | CR49: 3.375773 | CS49: 3.3604468 | CT49: 3.3111021 | CU49: 2.9016493 | DD49: -19.815143 | DE49: -10.205511 | DF49: 3.5551946 | DG49: 12.366058 | DJ49: 0.16158641 | DK49: 0.037815092 | DL49: 0.081780532 | DO49: -0.48261508 | DP49: -1.3535518 | DQ49: 2.9691321
A50: 600118.SH | B50: 600118 CH Equity | C50: Main board | D50: China Spacesat | E50: High-end equipment | F50: 刘中玉 | G50: Zhongyu LIU | H50: N | I50: Outperform | J50: 52.2 | K50: 90.55 | L50: -0.0083 | M50: -0.0463 | N50: 1182.49 | O50: 1182.49 | P50: 107074.39 | Q50: 107074.39 | R50: 6881.1633 | S50: 5156.4929 | T50: 5748.02 | U50: 7034.58 | V50: 8382.38 | W50: 9883.37 | X50: 157.53518 | Y50: 27.913995 | Z50: 67.97 | AA50: 128.45 | AB50: 246.66 | AC50: 425.78 | AD50: 107074.39 | AE50: 107074.39 | AF50: 107074.39 | AG50: 107074.39 | AH50: 107074.39 | AI50: 107074.39 | AJ50: 8192.3326 | AK50: 8082.4576 | AL50: 6397.08 | AM50: 6490.18 | AN50: 6670.05 | AO50: 6967.56 | AP50: 107074.39 | AQ50: 107074.39 | AR50: 107074.39 | AS50: 107074.39 | AT50: 107074.39 | AU50: 107074.39 | AV50: 47.299565 | AW50: 11.824891 | BB50: 107074.39 | BC50: 107074.39 | BD50: 107074.39 | BE50: 107074.39 | BF50: 107074.39 | BG50: 107074.39 | BH50: -1067.7499 | BI50: -316.76701 | BJ50: 89.3 | BK50: 217.67 | BL50: 817.07 | BM50: 1477.82 | BN50: 0.13322327 | BO50: 0.023606115 | BP50: 0.057480402 | BQ50: 0.10862671 | BR50: 0.20859373 | BS50: 0.3600707 | BT50: 6.9280355 | BU50: 6.8351171 | BV50: 5.4098386 | BW50: 5.4885707 | BX50: 5.640682 | BY50: 5.8922782 | BZ50: 0.039999971 | CA50: 0.0099999927 | CF50: -0.90296741 | CG50: -0.26788134 | CH50: 0.075518609 | CI50: 0.18407767 | CJ50: 0.69097413 | CK50: 1.2497526 | CL50: 679.68556 | CM50: 3835.8676 | CN50: 1575.3184 | CO50: 833.58809 | CP50: 434.0971 | CQ50: 251.4782 | CR50: 13.070074 | CS50: 13.247752 | CT50: 16.73801 | CU50: 16.497908 | CV50: 16.053012 | CW50: 15.367559 | CX50: 0.0004417449 | CY50: 0.00011043622 | DD50: 1.9229588 | DE50: 0.34536519 | DF50: 1.062516 | DG50: 1.9791439 | DH50: 3.6980233 | DI50: 6.110891 | DJ50: -0.25063645 | DK50: 0.114715 | DL50: 0.22382664 | DM50: 0.19159637 | DN50: 0.1790649 | DO50: -0.82280787 | DP50: 1.4349793 | DQ50: 0.88980433 | DR50: 0.92028026 | DS50: 0.72618179
A51: 600131.SH | B51: 600131 CH Equity | C51: Main board | D51: State Grid Information & Communication | E51: Computers | F51: 曲昊源 | G51: Haoyuan QU | H51: N | I51: Outperform | J51: 24.2 | K51: 18.25 | L51: -0.0455 | M51: 0.1339 | N51: 1198.36 | O51: 1195.91 | P51: 21869.98 | Q51: 21825.27 | R51: 7673.3195 | S51: 7315.1697 | T51: 10741.3 | U51: 11541.44 | X51: 828.2497 | Y51: 682.47271 | Z51: 995.13 | AA51: 1165.38 | AD51: 21869.98 | AE51: 21869.98 | AF51: 21869.98 | AG51: 21869.98 | AH51: 21869.98 | AI51: 21869.98 | AJ51: 6331.8286 | AK51: 6787.7654 | AL51: 7577.68 | AM51: 8443.92 | AP51: 21869.98 | AQ51: 21869.98 | AR51: 21869.98 | AS51: 21869.98 | AT51: 21869.98 | AU51: 21869.98 | AV51: 248.82421 | AW51: 205.42881 | AX51: 299.14 | AY51: 350.32 | BB51: 21869.98 | BC51: 21869.98 | BD51: 21869.98 | BE51: 21869.98 | BF51: 21869.98 | BG51: 21869.98 | BH51: 919.0339 | BI51: 757.86664 | BJ51: 565.19 | BK51: 1253.21 | BN51: 0.69115266 | BO51: 0.56950558 | BP51: 0.83040989 | BQ51: 0.97247905 | BT51: 5.283745 | BU51: 5.6642123 | BV51: 6.3233753 | BW51: 7.0462298 | BZ51: 0.20763728 | CA51: 0.17142496 | CB51: 0.24962449 | CC51: 0.29233285 | CF51: 0.7669097 | CG51: 0.63241984 | CH51: 0.47163624 | CI51: 1.0457709 | CL51: 26.405056 | CM51: 32.045208 | CN51: 21.977008 | CO51: 18.766394 | CR51: 3.4539753 | CS51: 3.2219705 | CT51: 2.886105 | CU51: 2.5900269 | CX51: 0.011377432 | CY51: 0.009393187 | CZ51: 0.01367811 | DA51: 0.016018305 | DD51: 13.080735 | DE51: 10.054453 | DF51: 13.132384 | DG51: 13.80141 | DJ51: -0.046674686 | DK51: 0.46835965 | DL51: 0.074491914 | DO51: -0.17600609 | DP51: 0.45812424 | DQ51: 0.17108318
A52: 600132.SH | B52: 600132 CH Equity | C52: Main board | D52: Chongqing Brewery | E52: Food and beverage | F52: 王雪骄 | G52: Xuejiao WANG | H52: N | I52: Outperform | J52: 65 | K52: 55.61 | L52: 0.0321 | M52: 0.0645 | N52: 483.97 | O52: 483.97 | P52: 26913.64 | Q52: 26913.64 | R52: 14814.836 | S52: 14644.598 | T52: 14721.87 | U52: 14884.54 | V52: 15138.96 | W52: 15400.6 | X52: 1336.5973 | Y52: 1114.593 | Z52: 1230.91 | AA52: 1239.66 | AB52: 1267.55 | AC52: 1336.31 | AD52: 26913.64 | AE52: 26913.64 | AF52: 26913.64 | AG52: 26913.64 | AH52: 26913.64 | AI52: 26913.64 | AJ52: 3652.1485 | AK52: 2453.6581 | AL52: 1254.6 | AM52: 1263.35 | AN52: 1291.23 | AO52: 1360 | AP52: 26913.64 | AQ52: 26913.64 | AR52: 26913.64 | AS52: 26913.64 | AT52: 26913.64 | AU52: 26913.64 | AV52: 1355.1194 | AW52: 1161.5309 | AX52: 1230.91 | AY52: 1239.66 | AZ52: 1267.55 | BA52: 1336.31 | BB52: 26913.64 | BC52: 26913.64 | BD52: 26913.64 | BE52: 26913.64 | BF52: 26913.64 | BG52: 26913.64 | BH52: 3096.9488 | BI52: 2542.0467 | BJ52: 2072.2 | BK52: 2962.01 | BL52: 3034.21 | BM52: 3192.2 | BN52: 2.7617359 | BO52: 2.3030209 | BP52: 2.5433601 | BQ52: 2.5614398 | BR52: 2.6190673 | BS52: 2.7611422 | BT52: 7.5462292 | BU52: 5.0698558 | BV52: 2.5923094 | BW52: 2.6103891 | BX52: 2.667996 | BY52: 2.8100915 | BZ52: 2.8000069 | CA52: 2.4000059 | CB52: 2.5433601 | CC52: 2.5614398 | CD52: 2.6190673 | CE52: 2.7611422 | CF52: 6.3990512 | CG52: 5.2524882 | CH52: 4.2816704 | CI52: 6.1202347 | CJ52: 6.2694175 | CK52: 6.5958634 | CL52: 20.135937 | CM52: 24.146607 | CN52: 21.864832 | CO52: 21.710501 | CP52: 21.232803 | CQ52: 20.140267 | CR52: 7.3692621 | CS52: 10.968782 | CT52: 21.451969 | CU52: 21.303392 | CV52: 20.843413 | CW52: 19.789441 | CX52: 0.050350653 | CY52: 0.043157703 | CZ52: 0.045735545 | DA52: 0.046060659 | DB52: 0.047096937 | DC52: 0.049651775 | DD52: 36.597562 | DE52: 45.425768 | DF52: 98.111749 | DG52: 98.124827 | DH52: 98.16609 | DI52: 98.258088 | DJ52: -0.011491087 | DK52: 0.0052764957 | DL52: 0.011049547 | DM52: 0.017092903 | DN52: 0.017282561 | DO52: -0.16609661 | DP52: 0.10435823 | DQ52: 0.007108562 | DR52: 0.022498104 | DS52: 0.054246381
A53: 600138.SH | B53: 600138 CH Equity | C53: Main board | D53: CYTS Tours | E53: Consumer services | F53: 赖晟炜 | G53: Shengwei LAI | H53: N | I53: Outperform | J53: 9.85 | K53: 10.05 | L53: 0.0101 | M53: 0.0172 | N53: 723.84 | O53: 723.84 | P53: 7274.59 | Q53: 7274.59 | R53: 9634.8396 | S53: 9956.8184 | T53: 10605.78 | U53: 10892.59 | X53: 193.9974 | Y53: 160.4499 | Z53: 135.07 | AA53: 239.39 | AD53: 7274.59 | AE53: 7274.59 | AF53: 7274.59 | AG53: 7274.59 | AH53: 7274.59 | AI53: 7274.59 | AJ53: 8347.4317 | AK53: 8494.557 | AL53: 6457.04 | AM53: 6718.25 | AP53: 7274.59 | AQ53: 7274.59 | AR53: 7274.59 | AS53: 7274.59 | AT53: 7274.59 | AU53: 7274.59 | AV53: 61.5264 | AW53: 50.6688 | AX53: 42.65 | AY53: 75.6 | BB53: 7274.59 | BC53: 7274.59 | BD53: 7274.59 | BE53: 7274.59 | BF53: 7274.59 | BG53: 7274.59 | BH53: 920.48574 | BI53: 282.66836 | BJ53: 617.95 | BK53: 878.45 | BN53: 0.26801143 | BO53: 0.22166487 | BP53: 0.18660201 | BQ53: 0.33072226 | BT53: 11.53215 | BU53: 11.735407 | BV53: 8.9205349 | BW53: 9.281402 | BZ53: 0.085 | CA53: 0.07 | CB53: 0.058921861 | CC53: 0.10444297 | CF53: 1.2716702 | CG53: 0.39051221 | CH53: 0.85371076 | CI53: 1.2135969 | CL53: 37.49839 | CM53: 45.338701 | CN53: 53.857926 | CO53: 30.388028 | CR53: 0.87147644 | CS53: 0.8563825 | CT53: 1.1266137 | CU53: 1.0828103 | CX53: 0.0084577138 | CY53: 0.006965176 | CZ53: 0.0058628734 | DA53: 0.010392338 | DD53: 2.3240369 | DE53: 1.8888554 | DF53: 2.0918254 | DG53: 3.5632791 | DJ53: 0.033418184 | DK53: 0.065177606 | DL53: 0.027042801 | DO53: -0.17292755 | DP53: -0.1581796 | DQ53: 0.77234027
A54: 600141.SH | B54: 600141 CH Equity | C54: Main board | D54: Xingfa Chemicals Group | E54: Chemicals | F54: 李唐懿 | G54: Tangyi LI | H54: N | I54: Outperform | J54: 30 | K54: 37.6 | L54: 0.0226 | M54: 0.0873 | N54: 1116.82 | O54: 1116.82 | P54: 41992.6 | Q54: 41992.6 | R54: 28105.346 | S54: 28396.485 | T54: 29066.22 | U54: 29128.76 | X54: 1378.9178 | Y54: 1601.3821 | Z54: 1824.32 | AA54: 1908.07 | AD54: 41992.6 | AE54: 41992.6 | AF54: 41992.6 | AG54: 41992.6 | AH54: 41992.6 | AI54: 41992.6 | AJ54: 21969.932 | AK54: 22882.028 | AL54: 22184.26 | AM54: 22979.49 | AP54: 41992.6 | AQ54: 41992.6 | AR54: 41992.6 | AS54: 41992.6 | AT54: 41992.6 | AU54: 41992.6 | AV54: 661.95275 | AW54: 1103.2552 | AX54: 1112.83 | AY54: 1163.92 | BB54: 41992.6 | BC54: 41992.6 | BD54: 41992.6 | BE54: 41992.6 | BF54: 41992.6 | BG54: 41992.6 | BH54: 1453.446 | BI54: 1588.6196 | BJ54: 5102.87 | BK54: 5240.26 | BN54: 1.2346822 | BO54: 1.4338766 | BP54: 1.6334951 | BQ54: 1.7084848 | BT54: 19.671865 | BU54: 20.488555 | BV54: 19.863774 | BW54: 20.575822 | BZ54: 0.59271212 | CA54: 0.98785408 | CB54: 0.99642736 | CC54: 1.0421733 | CF54: 1.3014147 | CG54: 1.4224491 | CH54: 4.5691069 | CI54: 4.6921259 | CL54: 30.453302 | CM54: 26.222723 | CN54: 23.01822 | CO54: 22.007893 | CR54: 1.9113669 | CS54: 1.8351783 | CT54: 1.8929006 | CU54: 1.8273948 | CX54: 0.015763557 | CY54: 0.02627261 | CZ54: 0.026500622 | DA54: 0.027717264 | DD54: 6.2763863 | DE54: 6.9984275 | DF54: 8.2234882 | DG54: 8.303361 | DJ54: 0.010358854 | DK54: 0.023585138 | DL54: 0.0021516386 | DO54: 0.16133254 | DP54: 0.13921592 | DQ54: 0.045907516
A55: 600150.SH | B55: 600150 CH Equity | C55: Main board | D55: China CSSC Holdings | E55: Machinery | F55: 刘中玉 | G55: Zhongyu LIU | H55: N | I55: Outperform | J55: 41 | K55: 33.91 | L55: 0.0245 | M55: 0.0195 | N55: 7525.62 | O55: 7525.62 | P55: 255193.82 | Q55: 255193.82 | R55: 74838.504 | S55: 78584.406 | T55: 152076.02 | U55: 191012.11 | X55: 2957.397 | Y55: 3614.1356 | Z55: 10530.77 | AA55: 15583.9 | AD55: 255193.82 | AE55: 255193.82 | AF55: 255193.82 | AG55: 255193.82 | AH55: 255193.82 | AI55: 255193.82 | AJ55: 52472.529 | AK55: 55266.403 | AL55: 60536.08 | AM55: 73513.65 | AP55: 255193.82 | AQ55: 255193.82 | AR55: 255193.82 | AS55: 255193.82 | AT55: 255193.82 | AU55: 255193.82 | AV55: 894.48575 | AW55: 1118.1072 | AX55: 2606.33 | AY55: 3856.96 | BB55: 255193.82 | BC55: 255193.82 | BD55: 255193.82 | BE55: 255193.82 | BF55: 255193.82 | BG55: 255193.82 | BH55: 18212.879 | BI55: 5235.2688 | BJ55: 53476.08 | BK55: 38464.56 | BN55: 0.39297718 | BO55: 0.48024423 | BP55: 1.3993226 | BQ55: 2.0707796 | BT55: 6.9725191 | BU55: 7.3437674 | BV55: 8.043999 | BW55: 9.768451 | BZ55: 0.11885875 | CA55: 0.14857343 | CB55: 0.34632761 | CC55: 0.5125106 | CF55: 2.4201168 | CG55: 0.69565947 | CH55: 7.1058703 | CI55: 5.1111483 | CL55: 86.290012 | CM55: 70.609918 | CN55: 24.233159 | CO55: 16.375479 | CR55: 4.8633795 | CS55: 4.6175218 | CT55: 4.2155657 | CU55: 3.4713801 | CX55: 0.0035051231 | CY55: 0.0043814039 | CZ55: 0.010213139 | DA55: 0.015113846 | DD55: 5.6360862 | DE55: 6.5394805 | DF55: 17.395857 | DG55: 21.198648 | DJ55: 0.050053139 | DK55: 0.93519334 | DL55: 0.25603044 | DO55: 0.22206645 | DP55: 1.9137728 | DQ55: 0.4798443
A56: 600153.SH | B56: 600153 CH Equity | C56: Main board | D56: Xiamen C & D | E56: Transportation and logistics | F56: 宋志达 | G56: Zhida SONG | H56: N | I56: Outperform | J56: 16.65 | K56: 9.52 | L56: 0.0292 | M56: 0.0292 | N56: 2899.54 | O56: 2899.54 | P56: 27603.61 | Q56: 27603.61 | R56: 763678.15 | S56: 701296.1 | T56: 1215200.6 | X56: 13103.998 | Y56: 2945.8068 | Z56: 17887.18 | AD56: 27603.61 | AE56: 27603.61 | AF56: 27603.61 | AG56: 27603.61 | AH56: 27603.61 | AI56: 27603.61 | AJ56: 224639.05 | AK56: 228157.81 | AL56: 88035.35 | AP56: 27603.61 | AQ56: 27603.61 | AR56: 27603.61 | AS56: 27603.61 | AT56: 27603.61 | AU56: 27603.61 | AV56: 2102.8499 | AW56: 2062.9666 | AX56: 5630.02 | BB56: 27603.61 | BC56: 27603.61 | BD56: 27603.61 | BE56: 27603.61 | BF56: 27603.61 | BG56: 27603.61 | BH56: 29394.968 | BI56: 11213.142 | BJ56: 23938.6 | BN56: 4.519337 | BO56: 1.0159566 | BP56: 6.1689716 | BT56: 77.474029 | BU56: 78.687589 | BV56: 30.361833 | BZ56: 0.72523571 | CA56: 0.71148066 | CB56: 1.9416942 | CF56: 10.137804 | CG56: 3.8672143 | CH56: 8.2559992 | CL56: 2.1065029 | CM56: 9.3704754 | CN56: 1.5432064 | CR56: 0.12287984 | CS56: 0.12098472 | CT56: 0.31355143 | CX56: 0.076180251 | CY56: 0.074735393 | CZ56: 0.20395955 | DD56: 5.8333574 | DE56: 1.2911269 | DF56: 20.318179 | DJ56: -0.081686319 | DK56: 0.73279253 | DO56: -0.77519787 | DP56: 5.0720819
A57: 600158.SH | B57: 600158 CH Equity | C57: Main board | D57: China Sports Industry Group | E57: Media | F57: 陶冶 | G57: Ye TAO | H57: N | I57: Neutral | J57: 8.22 | K57: 9.71 | L57: 0.021 | M57: 0.1123 | N57: 959.51 | O57: 959.51 | P57: 9316.87 | Q57: 9316.87 | R57: 3811.4888 | S57: 2517.8288 | T57: 1973.03 | X57: 71.948494 | Y57: 62.788641 | Z57: 129.3 | AD57: 9316.87 | AE57: 9316.87 | AF57: 9316.87 | AG57: 9316.87 | AH57: 9316.87 | AI57: 9316.87 | AJ57: 3650.2389 | AK57: 3590.5973 | AL57: 2700.02 | AP57: 9316.87 | AQ57: 9316.87 | AR57: 9316.87 | AS57: 9316.87 | AT57: 9316.87 | AU57: 9316.87 | AV57: 22.068801 | AW57: 18.902407 | AX57: 40.66 | BB57: 9316.87 | BC57: 9316.87 | BD57: 9316.87 | BE57: 9316.87 | BF57: 9316.87 | BG57: 9316.87 | BH57: -138.52037 | BI57: -36.289208 | BJ57: 903.14 | BN57: 0.074984621 | BO57: 0.065438235 | BP57: 0.13475628 | BT57: 3.804274 | BU57: 3.7421156 | BV57: 2.8139571 | BZ57: 0.023000074 | CA57: 0.019700063 | CB57: 0.042375796 | CF57: -0.14436573 | CG57: -0.037820562 | CH57: 0.94125126 | CL57: 129.49361 | CM57: 148.38464 | CN57: 72.056226 | CR57: 2.5524 | CS57: 2.5947967 | CT57: 3.450667 | CX57: 0.0023686925 | CY57: 0.0020288367 | CZ57: 0.0043641266 | DD57: 1.9710626 | DE57: 1.7486963 | DF57: 4.7888534 | DJ57: -0.33941069 | DK57: -0.21637642 | DO57: -0.12731126 | DP57: 1.0592897
A58: 600160.SH | B58: 600160 CH Equity | C58: Main board | D58: Zhejiang Juhua | E58: Chemicals | F58: 李熹凌 | G58: Xiling LI | H58: N | I58: Outperform | J58: 43.56 | K58: 39.3 | L58: 0.0455 | M58: 0.0274 | N58: 2699.75 | O58: 2699.75 | P58: 106100.02 | Q58: 106100.02 | R58: 20655.217 | S58: 24462.373 | T58: 24227.76 | U58: 27523.43 | V58: 28438.86 | X58: 943.5053 | Y58: 1959.5349 | Z58: 3712.93 | AA58: 5822.26 | AB58: 6109.05 | AD58: 106100.02 | AE58: 106100.02 | AF58: 106100.02 | AG58: 106100.02 | AH58: 106100.02 | AI58: 106100.02 | AJ58: 16376.682 | AK58: 19189.909 | AL58: 20883.58 | AM58: 25529.28 | AN58: 29793.36 | AP58: 106100.02 | AQ58: 106100.02 | AR58: 106100.02 | AS58: 106100.02 | AT58: 106100.02 | AU58: 106100.02 | AV58: 296.97207 | AW58: 620.9416 | AX58: 1176.56 | AY58: 1844.97 | AZ58: 2443.62 | BB58: 106100.02 | BC58: 106100.02 | BD58: 106100.02 | BE58: 106100.02 | BF58: 106100.02 | BG58: 106100.02 | BH58: 2196.3374 | BI58: 2764.8171 | BJ58: 6813.99 | BK58: 9102.6 | BL58: 9755.44 | BN58: 0.34947877 | BO58: 0.72582086 | BP58: 1.3752866 | BQ58: 2.1565923 | BR58: 2.2628206 | BT58: 6.0659993 | BU58: 7.1080317 | BV58: 7.7353755 | BW58: 9.4561645 | BX58: 11.0356 | BZ58: 0.10999984 | CA58: 0.22999967 | CB58: 0.43580332 | CC58: 0.6833855 | CD58: 0.90512825 | CF58: 0.81353362 | CG58: 1.0241012 | CH58: 2.5239337 | CI58: 3.3716455 | CJ58: 3.6134605 | CL58: 112.45302 | CM58: 54.145513 | CN58: 28.57582 | CO58: 18.223168 | CP58: 17.367679 | CR58: 6.4787252 | CS58: 5.5289487 | CT58: 5.0805475 | CU58: 4.156013 | CV58: 3.5611969 | CX58: 0.0027989822 | CY58: 0.0058524174 | CZ58: 0.011089159 | DA58: 0.017388969 | DB58: 0.023031287 | DD58: 5.7612728 | DE58: 10.211278 | DF58: 17.779183 | DG58: 22.806205 | DH58: 20.504737 | DJ58: 0.18431935 | DK58: -0.0095907727 | DL58: 0.13602867 | DM58: 0.033260026 | DO58: 1.0768668 | DP58: 0.89480171 | DQ58: 0.5681039 | DR58: 0.049257505
A59: 600163.SH | B59: 600163 CH Equity | C59: Main board | D59: Zhongmin Energy | E59: Electricity and utilities | F59: 蒋雨岑 | G59: Yucen JIANG | H59: N | I59: Outperform | J59: 7.05 | K59: 5.92 | L59: 0.0207 | M59: 0.0923 | N59: 1903 | O59: 1903 | P59: 11265.74 | Q59: 11265.74 | R59: 1731.8115 | S59: 1741.2081 | T59: 1738.73 | U59: 1933.94 | X59: 678.47354 | Y59: 651.14631 | Z59: 661.84 | AA59: 797.75 | AD59: 11265.74 | AE59: 11265.74 | AF59: 11265.74 | AG59: 11265.74 | AH59: 11265.74 | AI59: 11265.74 | AJ59: 6429.6781 | AK59: 6933.6361 | AL59: 7273.59 | AM59: 7910.79 | AP59: 11265.74 | AQ59: 11265.74 | AR59: 11265.74 | AS59: 11265.74 | AT59: 11265.74 | AU59: 11265.74 | AV59: 95.149807 | AW59: 196.0086 | AX59: 160.54 | AY59: 193.51 | BB59: 11265.74 | BC59: 11265.74 | BD59: 11265.74 | BE59: 11265.74 | BF59: 11265.74 | BG59: 11265.74 | BH59: 1029.3808 | BI59: 798.18348 | BJ59: 1370.97 | BK59: 1172.49 | BN59: 0.3565284 | BO59: 0.34216832 | BP59: 0.3477877 | BQ59: 0.41920652 | BT59: 3.3787063 | BU59: 3.6435292 | BV59: 3.8221703 | BW59: 4.15701 | BZ59: 0.049999899 | CA59: 0.10299979 | CB59: 0.084361534 | CC59: 0.10168681 | CF59: 0.54092529 | CG59: 0.41943431 | CH59: 0.72042564 | CI59: 0.61612717 | CL59: 16.604539 | CM59: 17.301396 | CN59: 17.021848 | CO59: 14.121893 | CR59: 1.7521468 | CS59: 1.6247954 | CT59: 1.5488555 | CU59: 1.424098 | CX59: 0.0084459438 | CY59: 0.017398644 | CZ59: 0.014250284 | DA59: 0.017176857 | DD59: 10.552216 | DE59: 9.3911231 | DF59: 9.0992206 | DG59: 10.084328 | DJ59: 0.0054258707 | DK59: -0.0014232111 | DL59: 0.1122716 | DO59: -0.04027752 | DP59: 0.016422873 | DQ59: 0.20535175
A60: 600176.SH | B60: 600176 CH Equity | C60: Main board | D60: China Jushi | E60: Construction materials | F60: 陈彦 | G60: Yan CHEN | H60: N | I60: Outperform | J60: 21 | K60: 21.99 | L60: 0.0913 | M60: 0.286 | N60: 4003.14 | O60: 4003.14 | P60: 88028.98 | Q60: 88028.98 | R60: 14875.802 | S60: 15855.767 | T60: 19366.65 | U60: 21614.64 | V60: 23208.93 | X60: 3044.442 | Y60: 2444.8133 | Z60: 3528.57 | AA60: 4444.09 | AB60: 5021.44 | AD60: 88028.98 | AE60: 88028.98 | AF60: 88028.98 | AG60: 88028.98 | AH60: 88028.98 | AI60: 88028.98 | AJ60: 29998.232 | AK60: 31448.123 | AL60: 32608.67 | AM60: 35666.11 | AN60: 39132.12 | AP60: 88028.98 | AQ60: 88028.98 | AR60: 88028.98 | AS60: 88028.98 | AT60: 88028.98 | AU60: 88028.98 | AV60: 1100.8626 | AW60: 960.75281 | AX60: 1386.64 | AY60: 1555.43 | AZ60: 1757.5 | BB60: 88028.98 | BC60: 88028.98 | BD60: 88028.98 | BE60: 88028.98 | BF60: 88028.98 | BG60: 88028.98 | BH60: 867.22285 | BI60: 2032.3128 | BJ60: 5072.99 | BK60: 6616.25 | BL60: 7474.66 | BN60: 0.76051349 | BO60: 0.6107239 | BP60: 0.88145056 | BQ60: 1.110151 | BR60: 1.2543753 | BT60: 7.4936754 | BU60: 7.8558638 | BV60: 8.1457731 | BW60: 8.9095335 | BX60: 9.7753563 | BZ60: 0.27499978 | CA60: 0.2399998 | CB60: 0.34638809 | CC60: 0.38855249 | CD60: 0.43903036 | CF60: 0.21663565 | CG60: 0.50767966 | CH60: 1.2672527 | CI60: 1.6527651 | CJ60: 1.8671992 | CL60: 28.914652 | CM60: 36.006423 | CN60: 24.947494 | CO60: 19.8081 | CP60: 17.530625 | CR60: 2.9344723 | CS60: 2.7991808 | CT60: 2.6995575 | CU60: 2.4681408 | CV60: 2.2495326 | CX60: 0.012505684 | CY60: 0.010914051 | CZ60: 0.015752085 | DA60: 0.017669522 | DB60: 0.019965016 | DD60: 10.148738 | DE60: 7.7741152 | DF60: 10.820957 | DG60: 12.46026 | DH60: 12.832016 | DJ60: 0.06587642 | DK60: 0.22142625 | DL60: 0.11607532 | DM60: 0.07375973 | DO60: -0.19695849 | DP60: 0.44328814 | DQ60: 0.25945921 | DR60: 0.12991411
A61: 600183.SH | B61: 600183 CH Equity | C61: Main board | D61: Shengyi Technology | E61: Electronics | F61: 唐宗其 | G61: Zongqi TANG | H61: N | I61: Outperform | J61: 21.3 | K61: 63.04 | L61: -0.0571 | M61: -0.1172 | N61: 2429.12 | O61: 2394.5 | P61: 153131.68 | Q61: 150949.37 | R61: 16586.073 | S61: 20388.33 | X61: 1163.9953 | Y61: 1738.6695 | AD61: 153131.68 | AE61: 153131.68 | AF61: 153131.68 | AG61: 153131.68 | AH61: 153131.68 | AI61: 153131.68 | AJ61: 15700.193 | AK61: 16504.959 | AP61: 153131.68 | AQ61: 153131.68 | AR61: 153131.68 | AS61: 153131.68 | AT61: 153131.68 | AU61: 153131.68 | AV61: 1064.0486 | AW61: 1457.6163 | BB61: 153131.68 | BC61: 153131.68 | BD61: 153131.68 | BE61: 153131.68 | BF61: 153131.68 | BG61: 153131.68 | BH61: 2743.1369 | BI61: 1456.1206 | BN61: 0.47918394 | BO61: 0.71576106 | BT61: 6.4633253 | BU61: 6.7946247 | BZ61: 0.43803872 | CA61: 0.60005941 | CF61: 1.1292719 | CG61: 0.59944365 | CL61: 131.55696 | CM61: 88.074058 | CR61: 9.7534905 | CS61: 9.2779195 | CX61: 0.0069485858 | CY61: 0.0095187117 | DD61: 7.4138918 | DE61: 10.534225 | DJ61: 0.22924398 | DO61: 0.49370836
A62: 600188.SH | B62: 600188 CH Equity | C62: Main board | D62: Yankuang Energy Group | E62: Coal | F62: 陈彦 | G62: Yan CHEN | H62: N | I62: Outperform | J62: 18 | K62: 15.57 | L62: 0.1258 | M62: 0.184 | N62: 10037.48 | O62: 5923.91 | P62: 156283.57 | Q62: 92235.3 | R62: 150024.86 | S62: 139124.43 | T62: 131902.13 | U62: 136629.76 | X62: 20139.502 | Y62: 14425.051 | Z62: 9916.92 | AA62: 12363.66 | AD62: 156283.57 | AE62: 156283.57 | AF62: 156283.57 | AG62: 156283.57 | AH62: 156283.57 | AI62: 156283.57 | AJ62: 118333.68 | AK62: 133010.26 | AL62: 92715.24 | AM62: 99764.21 | AP62: 156283.57 | AQ62: 156283.57 | AR62: 156283.57 | AS62: 156283.57 | AT62: 156283.57 | AU62: 156283.57 | AV62: 11507.225 | AW62: 7729.4074 | AX62: 5314.69 | AY62: 6625.95 | BB62: 156283.57 | BC62: 156283.57 | BD62: 156283.57 | BE62: 156283.57 | BF62: 156283.57 | BG62: 156283.57 | BH62: 16167.858 | BI62: 22341.926 | BJ62: 32709.59 | BK62: 31856.09 | BN62: 2.0064301 | BO62: 1.4371188 | BP62: 0.98798902 | BQ62: 1.2317494 | BT62: 11.789183 | BU62: 13.25136 | BV62: 9.2369041 | BW62: 9.939169 | BZ62: 1.1464257 | CA62: 0.77005457 | CB62: 0.52948449 | CC62: 0.66012087 | CF62: 1.6107487 | CG62: 2.2258501 | CH62: 3.2587452 | CI62: 3.1737139 | CL62: 7.7600514 | CM62: 10.834178 | CN62: 15.759285 | CO62: 12.640559 | CR62: 1.3207023 | CS62: 1.1749738 | CT62: 1.6856298 | CU62: 1.5665294 | CX62: 0.073630418 | CY62: 0.049457581 | CZ62: 0.03400671 | DA62: 0.042396971 | DD62: 17.019247 | DE62: 10.845066 | DF62: 10.696106 | DG62: 12.392881 | DJ62: -0.072657465 | DK62: -0.051912549 | DL62: 0.035841953 | DO62: -0.28374341 | DP62: -0.31252097 | DQ62: 0.24672378
A63: 600195.SH | B63: 600195 CH Equity | C63: Main board | D63: China Animal Husbandry Industry | E63: Agriculture | F63: 王思洋 | G63: Siyang WANG | H63: N | I63: Outperform | J63: 8 | K63: 7.93 | L63: 0.0063 | M63: 0.0076 | N63: 1021.15 | O63: 1021.15 | P63: 8097.71 | Q63: 8097.71 | R63: 5406.3126 | S63: 6017.1904 | T63: 6828.64 | U63: 7891.03 | X63: 403.05161 | Y63: 70.884446 | Z63: 250.4 | AA63: 279.77 | AD63: 8097.71 | AE63: 8097.71 | AF63: 8097.71 | AG63: 8097.71 | AH63: 8097.71 | AI63: 8097.71 | AJ63: 6540.8152 | AK63: 6499.4476 | AL63: 5731.96 | AM63: 5928.77 | AP63: 8097.71 | AQ63: 8097.71 | AR63: 8097.71 | AS63: 8097.71 | AT63: 8097.71 | AU63: 8097.71 | AV63: 121.51664 | AW63: 23.48641 | AX63: 82.97 | AY63: 92.7 | BB63: 8097.71 | BC63: 8097.71 | BD63: 8097.71 | BE63: 8097.71 | BF63: 8097.71 | BG63: 8097.71 | BH63: 372.46143 | BI63: 419.56559 | BJ63: 486.82 | BK63: 418.17 | BN63: 0.39470363 | BO63: 0.069416291 | BP63: 0.24521373 | BQ63: 0.27397542 | BT63: 6.4053422 | BU63: 6.3648314 | BV63: 5.61324 | BW63: 5.8059737 | BZ63: 0.1189998 | CA63: 0.022999961 | CB63: 0.08125153 | CC63: 0.090780003 | CF63: 0.36474703 | CG63: 0.41087557 | CH63: 0.47673701 | CI63: 0.40950889 | CL63: 20.091 | CM63: 114.23818 | CN63: 32.339097 | CO63: 28.944168 | CR63: 1.2380276 | CS63: 1.2459074 | CT63: 1.4127297 | CU63: 1.365833 | CX63: 0.015006297 | CY63: 0.0029003768 | CZ63: 0.010246107 | DA63: 0.011447681 | DD63: 6.1621006 | DE63: 1.0906226 | DF63: 4.3684883 | DG63: 4.718854 | DJ63: 0.11299343 | DK63: 0.13485524 | DL63: 0.15557856 | DO63: -0.8241306 | DP63: 2.5325098 | DQ63: 0.11729233
A64: 600201.SH | B64: 600201 CH Equity | C64: Main board | D64: Jinyu Bio-Technology | E64: Agriculture | F64: 王思洋 | G64: Siyang WANG | H64: N | I64: Outperform | J64: 10 | K64: 15.62 | L64: -0.0405 | M64: 0.0365 | N64: 1111.75 | O64: 1111.75 | P64: 17365.5 | Q64: 17365.5 | R64: 1598.2255 | S64: 1255.4558 | T64: 1373.35 | U64: 1540.69 | X64: 283.63079 | Y64: 108.98519 | Z64: 199.92 | AA64: 266.29 | AD64: 17365.5 | AE64: 17365.5 | AF64: 17365.5 | AG64: 17365.5 | AH64: 17365.5 | AI64: 17365.5 | AJ64: 5654.9396 | AK64: 5415.3784 | AL64: 5481.21 | AM64: 5686.86 | AP64: 17365.5 | AQ64: 17365.5 | AR64: 17365.5 | AS64: 17365.5 | AT64: 17365.5 | AU64: 17365.5 | AV64: 89.36541 | AW64: 33.05053 | AX64: 60.64 | AY64: 80.76 | BB64: 17365.5 | BC64: 17365.5 | BD64: 17365.5 | BE64: 17365.5 | BF64: 17365.5 | BG64: 17365.5 | BH64: 414.83326 | BI64: 289.55221 | BJ64: 379.41 | BK64: 423.84 | BN64: 0.25512102 | BO64: 0.0980303 | BP64: 0.1798246 | BQ64: 0.23952327 | BT64: 5.0865209 | BU64: 4.8710397 | BV64: 4.9302541 | BW64: 5.1152327 | BZ64: 0.080382649 | CA64: 0.029728383 | CB64: 0.054544637 | CC64: 0.072642231 | CF64: 0.37313538 | CG64: 0.26044724 | CH64: 0.34127277 | CI64: 0.38123679 | CL64: 61.225722 | CM64: 159.33817 | CN64: 86.862245 | CO64: 65.212738 | CR64: 3.0708551 | CS64: 3.2067011 | CT64: 3.1681873 | CU64: 3.0536183 | CX64: 0.0051461467 | CY64: 0.0019032294 | CZ64: 0.0034919812 | DA64: 0.0046506003 | DD64: 5.015629 | DE64: 2.0125129 | DF64: 3.6473698 | DG64: 4.6825489 | DJ64: -0.21446893 | DK64: 0.093905533 | DL64: 0.12184804 | DO64: -0.6157498 | DP64: 0.83437774 | DQ64: 0.33198279
A65: 600210.SH | B65: 600210 CH Equity | C65: Main board | D65: Zijiang Enterprise Group | E65: Light manufacturing | F65: 徐卓楠 | G65: Zhuonan XU | H65: N | I65: Outperform | J65: 9 | K65: 7.56 | L65: 0.0216 | M65: 0.0286 | N65: 1516.74 | O65: 1516.74 | P65: 11466.53 | Q65: 11466.53 | R65: 9115.509 | S65: 10636.949 | T65: 11664.12 | U65: 11290.84 | X65: 559.54605 | Y65: 808.8135 | Z65: 962.55 | AA65: 917.05 | AD65: 11466.53 | AE65: 11466.53 | AF65: 11466.53 | AG65: 11466.53 | AH65: 11466.53 | AI65: 11466.53 | AJ65: 6255.3648 | AK65: 6627.1265 | AL65: 6669.45 | AM65: 7008.97 | AP65: 11466.53 | AQ65: 11466.53 | AR65: 11466.53 | AS65: 11466.53 | AT65: 11466.53 | AU65: 11466.53 | AV65: 379.18404 | AW65: 455.02085 | AX65: 577.53 | AY65: 550.23 | BB65: 11466.53 | BC65: 11466.53 | BD65: 11466.53 | BE65: 11466.53 | BF65: 11466.53 | BG65: 11466.53 | BH65: 2695.7821 | BI65: 988.84039 | BJ65: 1025.48 | BK65: 1432.03 | BN65: 0.36891363 | BO65: 0.53325784 | BP65: 0.63461767 | BQ65: 0.60461912 | BT65: 4.1242169 | BU65: 4.3693227 | BV65: 4.3972269 | BW65: 4.6210755 | BZ65: 0.24999937 | CA65: 0.29999924 | CB65: 0.3807706 | CC65: 0.36277147 | CF65: 1.7773528 | CG65: 0.65195115 | CH65: 0.67610797 | CI65: 0.94414995 | CL65: 20.492558 | CM65: 14.176977 | CN65: 11.912659 | CO65: 12.503713 | CR65: 1.8330714 | CS65: 1.7302416 | CT65: 1.7192617 | CU65: 1.6359793 | CX65: 0.03306877 | CY65: 0.039682524 | CZ65: 0.050366589 | DA65: 0.047985746 | DD65: 8.9450588 | DE65: 12.204588 | DF65: 14.432225 | DG65: 13.083948 | DJ65: 0.16690675 | DK65: 0.096566311 | DL65: -0.032002414 | DO65: 0.44548156 | DP65: 0.19007657 | DQ65: -0.047270272
A66: 600216.SH | B66: 600216 CH Equity | C66: Main board | D66: Zhejiang Medicine | E66: Pharmaceuticals | F66: 侯一林 | G66: Yilin HOU | H66: N | I66: Outperform | J66: 18.5 | K66: 15.6 | L66: 0.0871 | M66: 0.1255 | N66: 961.64 | O66: 951.39 | P66: 15001.55 | Q66: 14841.68 | R66: 7794.146 | S66: 9375.2169 | T66: 9689.39 | U66: 10372.77 | V66: 11171.32 | X66: 429.63963 | Y66: 1160.5107 | Z66: 1091.75 | AA66: 1098.55 | AB66: 1247.65 | AD66: 15001.55 | AE66: 15001.55 | AF66: 15001.55 | AG66: 15001.55 | AH66: 15001.55 | AI66: 15001.55 | AJ66: 9986.3938 | AK66: 10867.942 | AL66: 11384.09 | AM66: 12155.11 | AN66: 13073.2 | AP66: 15001.55 | AQ66: 15001.55 | AR66: 15001.55 | AS66: 15001.55 | AT66: 15001.55 | AU66: 15001.55 | AV66: 144.24566 | AW66: 352.24679 | AX66: 327.53 | AY66: 329.57 | AZ66: 374.3 | BB66: 15001.55 | BC66: 15001.55 | BD66: 15001.55 | BE66: 15001.55 | BF66: 15001.55 | BG66: 15001.55 | BH66: 634.31116 | BI66: 1223.2986 | BJ66: 1877.97 | BK66: 1702.97 | BL66: 2252.59 | BN66: 0.44677803 | BO66: 1.2068037 | BP66: 1.1353001 | BQ66: 1.1423714 | BR66: 1.297419 | BT66: 10.384753 | BU66: 11.301466 | BV66: 11.838203 | BW66: 12.63998 | BX66: 13.594692 | BZ66: 0.14999965 | CA66: 0.36629798 | CB66: 0.34059523 | CC66: 0.34271661 | CD66: 0.3892309 | CF66: 0.65961395 | CG66: 1.2720963 | CH66: 1.9528826 | CI66: 1.7709018 | CJ66: 2.3424462 | CL66: 34.916588 | CM66: 12.92668 | CN66: 13.740829 | CO66: 13.655774 | CP66: 12.023845 | CR66: 1.5021989 | CS66: 1.3803487 | CT66: 1.3177645 | CU66: 1.2341764 | CV66: 1.1475041 | CX66: 0.0096153839 | CY66: 0.023480693 | CZ66: 0.021833077 | DA66: 0.021969063 | DB66: 0.024950755 | DD66: 4.30225 | DE66: 10.678293 | DF66: 9.5901385 | DG66: 9.0377627 | DH66: 9.5435701 | DJ66: 0.20285365 | DK66: 0.03351102 | DL66: 0.070528692 | DM66: 0.076985222 | DO66: 1.7011258 | DP66: -0.059250356 | DQ66: 0.0062285322 | DR66: 0.13572436
A67: 600219.SH | B67: 600219 CH Equity | C67: Main board | D67: Nanshan Aluminium | E67: Non-ferrous metals | F67: 齐丁 | G67: Ding QI | H67: N | I67: Outperform | J67: 9.75 | K67: 6.74 | L67: 0.0135 | M67: 0.2528 | N67: 11483.7 | O67: 11483.7 | P67: 77400.15 | Q67: 77400.15 | R67: 28843.6 | S67: 33477.18 | T67: 34472.4 | U67: 43902.39 | V67: 48350.44 | X67: 3473.974 | Y67: 4829.9543 | Z67: 5311.75 | AA67: 7463.82 | AB67: 8339.98 | AD67: 77400.15 | AE67: 77400.15 | AF67: 77400.15 | AG67: 77400.15 | AH67: 77400.15 | AI67: 77400.15 | AJ67: 54028.098 | AK67: 56224.322 | AL67: 53652.69 | AM67: 58943.37 | AN67: 64229.6 | AP67: 77400.15 | AQ67: 77400.15 | AR67: 77400.15 | AS67: 77400.15 | AT67: 77400.15 | AU67: 77400.15 | AV67: 1402.6069 | AW67: 1973.4722 | AX67: 2173.5 | AY67: 3054.11 | AZ67: 3412.62 | BB67: 77400.15 | BC67: 77400.15 | BD67: 77400.15 | BE67: 77400.15 | BF67: 77400.15 | BG67: 77400.15 | BH67: 4230.3974 | BI67: 7616.9706 | BJ67: 7279.85 | BK67: 9412.85 | BL67: 10734.27 | BN67: 0.30251347 | BO67: 0.42059217 | BP67: 0.46254691 | BQ67: 0.64994906 | BR67: 0.72624503 | BT67: 4.7047639 | BU67: 4.896011 | BV67: 4.6720735 | BW67: 5.1327856 | BX67: 5.5931102 | BZ67: 0.12213893 | CA67: 0.17184986 | CB67: 0.18926827 | CC67: 0.26595174 | CD67: 0.29717077 | CF67: 0.36838279 | CG67: 0.6632854 | CH67: 0.63392896 | CI67: 0.81967049 | CJ67: 0.93473967 | CL67: 22.280003 | CM67: 16.025027 | CN67: 14.571497 | CO67: 10.370045 | CP67: 9.2806158 | CR67: 1.4325907 | CS67: 1.3766311 | CT67: 1.4426145 | CU67: 1.3131273 | CV67: 1.2050542 | CX67: 0.018121501 | CY67: 0.025497008 | CZ67: 0.028081341 | DA67: 0.039458709 | DB67: 0.044090612 | DD67: 6.4299395 | DE67: 8.590507 | DF67: 9.9002492 | DG67: 12.662696 | DH67: 12.984636 | DJ67: 0.160645 | DK67: 0.029728305 | DL67: 0.27355188 | DM67: 0.10131681 | DO67: 0.39032542 | DP67: 0.099751606 | DQ67: 0.40515273 | DR67: 0.11738761
A68: 600223.SH | B68: 600223 CH Equity | C68: Main board | D68: Lushang Freda Pharmaceutical | E68: Chemicals | F68: 徐卓楠 | G68: Zhuonan XU | H68: N | I68: Outperform | J68: 9 | K68: 7.56 | L68: 0.0272 | M68: 0.0272 | N68: 1016.57 | O68: 1016.57 | P68: 7685.26 | Q68: 7685.26 | R68: 4578.7463 | S68: 3982.5771 | T68: 4071.32 | U68: 4335.31 | X68: 303.38717 | Y68: 243.5253 | Z68: 247.12 | AA68: 301.42 | AD68: 7685.26 | AE68: 7685.26 | AF68: 7685.26 | AG68: 7685.26 | AH68: 7685.26 | AI68: 7685.26 | AJ68: 4680.1411 | AK68: 4788.3657 | AL68: 4240.19 | AM68: 4428.14 | AP68: 7685.26 | AQ68: 7685.26 | AR68: 7685.26 | AS68: 7685.26 | AT68: 7685.26 | AU68: 7685.26 | AV68: 101.65688 | AW68: 111.82257 | AX68: 113.47 | AY68: 138.41 | BB68: 7685.26 | BC68: 7685.26 | BD68: 7685.26 | BE68: 7685.26 | BF68: 7685.26 | BG68: 7685.26 | BH68: 474.15286 | BI68: 228.653 | BJ68: -2186.93 | BK68: 221.06 | BN68: 0.29844199 | BO68: 0.23955586 | BP68: 0.24309197 | BQ68: 0.29650688 | BT68: 4.6038552 | BU68: 4.7103158 | BV68: 4.1710753 | BW68: 4.3559617 | BZ68: 0.099999879 | CA68: 0.10999987 | CB68: 0.11162045 | CC68: 0.13615393 | CF68: 0.46642421 | CG68: 0.22492598 | CH68: -2.1512832 | CI68: 0.21745674 | CL68: 25.331526 | CM68: 31.558364 | CN68: 31.099304 | CO68: 25.496848 | CR68: 1.6421001 | CS68: 1.604986 | CT68: 1.8124801 | CU68: 1.7355504 | CX68: 0.013227513 | CY68: 0.014550264 | CZ68: 0.014764627 | DA68: 0.018009801 | DD68: 6.4824365 | DE68: 5.0857706 | DF68: 5.8280407 | DG68: 6.8069212 | DJ68: -0.13020358 | DK68: 0.022282778 | DL68: 0.064841378 | DO68: -0.19731183 | DP68: 0.014761111 | DQ68: 0.2197313
A69: 600233.SH | B69: 600233 CH Equity | C69: Main board | D69: YTO Express | E69: Transportation and logistics | F69: 冯启斌 | G69: Qibin FENG | H69: N | I69: Outperform | J69: 21.5 | K69: 18 | L69: 0.0727 | M69: 0.0962 | N69: 3422.57 | O69: 3422.57 | P69: 61606.34 | Q69: 61606.34 | R69: 57684.35 | S69: 69032.667 | T69: 74462.99 | U69: 83312.78 | V69: 91422.44 | W69: 100596.83 | X69: 3722.5423 | Y69: 4012.3339 | Z69: 4289.87 | AA69: 4998.94 | AB69: 6169.84 | AC69: 7260.45 | AD69: 61606.34 | AE69: 61606.34 | AF69: 61606.34 | AG69: 61606.34 | AH69: 61606.34 | AI69: 61606.34 | AJ69: 29346.904 | AK69: 32208.083 | AL69: 35109.57 | AM69: 38735.75 | AN69: 43155.96 | AO69: 47948.47 | AP69: 61606.34 | AQ69: 61606.34 | AR69: 61606.34 | AS69: 61606.34 | AT69: 61606.34 | AU69: 61606.34 | AV69: 1196.5581 | AW69: 1231.2814 | AX69: 1372.76 | AY69: 1749.63 | AZ69: 2467.94 | BA69: 2904.18 | BB69: 61606.34 | BC69: 61606.34 | BD69: 61606.34 | BE69: 61606.34 | BF69: 61606.34 | BG69: 61606.34 | BH69: 6037.7604 | BI69: 5856.6057 | BJ69: 7933.43 | BK69: 8240.98 | BL69: 10667.32 | BM69: 12147.8 | BN69: 1.0876453 | BO69: 1.1723161 | BP69: 1.2534061 | BQ69: 1.4605808 | BR69: 1.8026921 | BS69: 2.1213445 | BT69: 8.5745225 | BU69: 9.4104964 | BV69: 10.258247 | BW69: 11.317738 | BX69: 12.609226 | BY69: 14.009493 | BZ69: 0.34960807 | CA69: 0.35975346 | CB69: 0.40109041 | CC69: 0.51120357 | CD69: 0.72107802 | CE69: 0.84853779 | CF69: 1.7641014 | CG69: 1.7111719 | CH69: 2.3179745 | CI69: 2.4078339 | CJ69: 3.1167573 | CK69: 3.5493211 | CL69: 16.549534 | CM69: 15.35424 | CN69: 14.360887 | CO69: 12.323881 | CP69: 9.985079 | CQ69: 8.4851958 | CR69: 2.099245 | CS69: 1.9127602 | CT69: 1.754688 | CU69: 1.5904259 | CV69: 1.427528 | CW69: 1.2848448 | CX69: 0.019422646 | CY69: 0.019986278 | CZ69: 0.022282772 | DA69: 0.028400161 | DB69: 0.040059838 | DC69: 0.047140927 | DD69: 12.684617 | DE69: 12.457537 | DF69: 12.21852 | DG69: 12.905236 | DH69: 14.296612 | DI69: 15.142193 | DJ69: 0.1967313 | DK69: 0.078663094 | DL69: 0.11884817 | DM69: 0.097339928 | DN69: 0.10035162 | DO69: 0.077847786 | DP69: 0.069170729 | DQ69: 0.16528939 | DR69: 0.23422966 | DS69: 0.17676471
A70: 600258.SH | B70: 600258 CH Equity | C70: Main board | D70: BTG Hotels | E70: Consumer services | F70: 林思婕 | G70: Sijie LIN | H70: N | I70: Outperform | J70: 16 | K70: 17.4 | L70: 0.0211 | M70: 0.0388 | N70: 1116.6 | O70: 1116.6 | P70: 19428.89 | Q70: 19428.89 | R70: 7792.9244 | S70: 7751.2235 | T70: 7763.17 | U70: 7819.05 | X70: 795.07273 | Y70: 806.31328 | Z70: 825.08 | AA70: 924.4 | AD70: 19428.89 | AE70: 19428.89 | AF70: 19428.89 | AG70: 19428.89 | AH70: 19428.89 | AI70: 19428.89 | AJ70: 11272.921 | AK70: 11820.511 | AL70: 12121.34 | AM70: 12633.2 | AP70: 19428.89 | AQ70: 19428.89 | AR70: 19428.89 | AS70: 19428.89 | AT70: 19428.89 | AU70: 19428.89 | AV70: 245.65269 | AW70: 401.97713 | AX70: 412.54 | AY70: 462.2 | BB70: 19428.89 | BC70: 19428.89 | BD70: 19428.89 | BE70: 19428.89 | BF70: 19428.89 | BG70: 19428.89 | BH70: 4013.7779 | BI70: 3370.8666 | BJ70: 2314.29 | BK70: 2218.9 | BN70: 0.71204794 | BO70: 0.7221147 | BP70: 0.73892173 | BQ70: 0.82787032 | BT70: 10.095756 | BU70: 10.586164 | BV70: 10.855579 | BW70: 11.313989 | BZ70: 0.22000062 | CA70: 0.36000101 | CB70: 0.36946086 | CC70: 0.41393516 | CF70: 3.5946426 | CG70: 3.0188667 | CH70: 2.0726222 | CI70: 1.9871933 | CL70: 24.43662 | CM70: 24.095957 | CN70: 23.547886 | CO70: 21.017839 | CR70: 1.7235009 | CS70: 1.6436591 | CT70: 1.6028665 | CU70: 1.5379231 | CX70: 0.012643681 | CY70: 0.02068966 | CZ70: 0.021233328 | DA70: 0.023789316 | DD70: 7.0529433 | DE70: 6.8213067 | DF70: 6.8068382 | DG70: 7.3172276 | DJ70: -0.0053511246 | DK70: 0.0015412368 | DL70: 0.0071980905 | DO70: 0.014137756 | DP70: 0.02327473 | DQ70: 0.12037621
A71: 600259.SH | B71: 600259 CH Equity | C71: Main board | D71: China Rare Earth Nonferrous Metals | E71: Non-ferrous metals | F71: 王政 | G71: Zheng WANG | H71: N | I71: Outperform | J71: 70.21 | K71: 77.61 | L71: 0.0119 | M71: 0.3795 | N71: 336.44 | O71: 336.44 | P71: 26110.79 | Q71: 26110.79 | R71: 20805.26 | S71: 12596.137 | T71: 13041.51 | U71: 13564.83 | X71: 203.38251 | Y71: -298.50371 | Z71: 259.66 | AA71: 342.32 | AD71: 26110.79 | AE71: 26110.79 | AF71: 26110.79 | AG71: 26110.79 | AH71: 26110.79 | AI71: 26110.79 | AJ71: 3958.8122 | AK71: 3637.2456 | AL71: 3619.71 | AM71: 3962.03 | AP71: 26110.79 | AQ71: 26110.79 | AR71: 26110.79 | AS71: 26110.79 | AT71: 26110.79 | AU71: 26110.79 | BB71: 26110.79 | BC71: 26110.79 | BD71: 26110.79 | BE71: 26110.79 | BF71: 26110.79 | BG71: 26110.79 | BH71: -476.7549 | BI71: -4.99428 | BJ71: 630.15 | BK71: 725.5 | BN71: 0.60451348 | BO71: -0.88724203 | BP71: 0.77178695 | BQ71: 1.0174771 | BT71: 11.76677 | BU71: 10.810978 | BV71: 10.758857 | BW71: 11.776335 | CF71: -1.4170577 | CG71: -0.014844489 | CH71: 1.8729937 | CI71: 2.1564023 | CL71: 128.38267 | CM71: -87.472247 | CN71: 100.55761 | CO71: 76.27597 | CR71: 6.5956123 | CS71: 7.1787262 | CT71: 7.2135033 | CU71: 6.5902555 | DD71: 5.1374631 | DE71: -8.2068615 | DF71: 7.1735028 | DG71: 8.6400153 | DJ71: -0.39456961 | DK71: 0.035357927 | DL71: 0.040127255 | DO71: -2.467696 | DP71: -1.8698719 | DQ71: 0.31833937
A72: 600266.SH | B72: 600266 CH Equity | C72: Main board | D72: Beijing Urban Construction Investment & Development | E72: Real estate | F72: 宋志达 | G72: Zhida SONG | H72: N | I72: Outperform | J72: 6.8 | K72: 5.76 | L72: 0.0569 | M72: 0.1361 | N72: 2075.74 | O72: 2075.74 | P72: 11956.28 | Q72: 11956.28 | R72: 20363.033 | S72: 25442.188 | T72: 26299.7 | U72: 22342.48 | V72: 20204.57 | X72: 558.89368 | Y72: -951.04434 | Z72: -361.32 | AA72: 356.23 | AB72: 805.56 | AD72: 11956.28 | AE72: 11956.28 | AF72: 11956.28 | AG72: 11956.28 | AH72: 11956.28 | AI72: 11956.28 | AJ72: 26578.197 | AK72: 24420.093 | AL72: 21779.88 | AM72: 22032.32 | AN72: 22705.57 | AP72: 11956.28 | AQ72: 11956.28 | AR72: 11956.28 | AS72: 11956.28 | AT72: 11956.28 | AU72: 11956.28 | AV72: 207.57435 | AW72: 103.78718 | AX72: 103.79 | AY72: 132.3 | AZ72: 299.19 | BB72: 11956.28 | BC72: 11956.28 | BD72: 11956.28 | BE72: 11956.28 | BF72: 11956.28 | BG72: 11956.28 | BH72: 13115.821 | BI72: 5574.8595 | BJ72: 5290.49 | BK72: 5766.89 | BL72: 6076.97 | BN72: 0.26925033 | BO72: -0.45817123 | BP72: -0.17406804 | BQ72: 0.17161591 | BR72: 0.38808329 | BT72: 12.804203 | BU72: 11.764524 | BV72: 10.492586 | BW72: 10.6142 | BX72: 10.938542 | BZ72: 0.10000017 | CA72: 0.050000084 | CB72: 0.050001445 | CC72: 0.063736306 | CD72: 0.14413655 | CF72: 6.3186244 | CG72: 2.6857215 | CH72: 2.5487248 | CI72: 2.7782333 | CJ72: 2.9276162 | CL72: 21.392763 | CM72: -12.571738 | CN72: -33.090557 | CO72: 33.563372 | CP72: 14.842197 | CR72: 0.44985293 | CS72: 0.4896083 | CT72: 0.54895987 | CU72: 0.54267004 | CV72: 0.52657916 | CX72: 0.017361115 | CY72: 0.0086805574 | CZ72: 0.0086807937 | DA72: 0.011065315 | DB72: 0.02502367 | DD72: 2.1028276 | DE72: -3.8945157 | DF72: -1.6589623 | DG72: 1.616852 | DH72: 3.5478519 | DJ72: 0.24943014 | DK72: 0.033704354 | DL72: -0.15046636 | DM72: -0.095688124 | DO72: -2.7016552 | DP72: -0.62008081 | DQ72: -1.9859128 | DR72: 1.261348
A73: 600271.SH | B73: 600271 CH Equity | C73: Main board | D73: Aisino | E73: Computers | F73: 车姝韵 | G73: Shuyun CHE | H73: N | I73: Outperform | J73: 17.4 | K73: 10.14 | L73: 0.0263 | M73: -0.1326 | N73: 1852.88 | O73: 1852.88 | P73: 18788.25 | Q73: 18788.25 | R73: 12574.822 | S73: 8308.6806 | T73: 21067.74 | X73: 202.71532 | Y73: 15.954802 | Z73: 1189.03 | AD73: 18788.25 | AE73: 18788.25 | AF73: 18788.25 | AG73: 18788.25 | AH73: 18788.25 | AI73: 18788.25 | AJ73: 17445.203 | AK73: 17100.284 | AL73: 16153.44 | AP73: 18788.25 | AQ73: 18788.25 | AR73: 18788.25 | AS73: 18788.25 | AT73: 18788.25 | AU73: 18788.25 | AV73: 61.145193 | AW73: 7.4115385 | AX73: 355.83 | BB73: 18788.25 | BC73: 18788.25 | BD73: 18788.25 | BE73: 18788.25 | BF73: 18788.25 | BG73: 18788.25 | BH73: 874.98477 | BI73: -167.01741 | BJ73: 3033.98 | BN73: 0.10940553 | BO73: 0.0086108124 | BP73: 0.64171992 | BT73: 9.4151823 | BU73: 9.2290294 | BV73: 8.7180174 | BZ73: 0.033000083 | CA73: 0.00400001 | CB73: 0.19204158 | CF73: 0.47222959 | CG73: -0.090139357 | CH73: 1.6374401 | CL73: 92.682929 | CM73: 1177.5922 | CN73: 15.801325 | CR73: 1.0769866 | CS73: 1.0987098 | CT73: 1.1631114 | CX73: 0.0032544379 | CY73: 0.00039447732 | CZ73: 0.018938965 | DD73: 1.1620118 | DE73: 0.093301387 | DF73: 7.360847 | DJ73: -0.33926059 | DK73: 1.53563 | DO73: -0.92129454 | DP73: 73.524898
A74: 600276.SH | B74: 600276 CH Equity | C74: Main board | D74: Hengrui Pharmaceuticals | E74: Pharmaceuticals | F74: 张琎 | G74: Jin ZHANG | H74: N | I74: Outperform | J74: 73.4 | K74: 57.31 | L74: 0.0145 | M74: -0.0379 | N74: 6637.2 | O74: 6379 | P74: 380377.92 | Q74: 365580.62 | R74: 22819.785 | S74: 27984.605 | T74: 33822.72 | U74: 36938.93 | V74: 41070.35 | W74: 45868.11 | X74: 4302.4359 | Y74: 6336.527 | Z74: 9028.41 | AA74: 9902.66 | AB74: 11113.68 | AC74: 12652.26 | AD74: 380377.92 | AE74: 380377.92 | AF74: 380377.92 | AG74: 380377.92 | AH74: 380377.92 | AI74: 380377.92 | AJ74: 41033.086 | AK74: 46090.251 | AL74: 63626.09 | AM74: 71713.34 | AN74: 80351.36 | AO74: 90225.2 | AP74: 380377.92 | AQ74: 380377.92 | AR74: 380377.92 | AS74: 380377.92 | AT74: 380377.92 | AU74: 380377.92 | AV74: 1273.7683 | AW74: 1274.1302 | AX74: 1815.41 | AY74: 2475.67 | AZ74: 2778.42 | BA74: 3163.07 | BB74: 380377.92 | BC74: 380377.92 | BD74: 380377.92 | BE74: 380377.92 | BF74: 380377.92 | BG74: 380377.92 | BH74: 7643.6651 | BI74: 7422.753 | BJ74: 8282.29 | BK74: 9196.25 | BL74: 10193.54 | BM74: 9889.72 | BN74: 0.64823057 | BO74: 0.95469882 | BP74: 1.3602739 | BQ74: 1.4919936 | BR74: 1.6744531 | BS74: 1.9062647 | BT74: 6.1822887 | BU74: 6.9442311 | BV74: 9.5862849 | BW74: 10.804758 | BX74: 12.106213 | BY74: 13.593865 | BZ74: 0.19191351 | CA74: 0.19196803 | CB74: 0.27352046 | CC74: 0.37299916 | CD74: 0.41861327 | CE74: 0.47656693 | CF74: 1.15164 | CG74: 1.1183561 | CH74: 1.247859 | CI74: 1.3855617 | CJ74: 1.5358193 | CK74: 1.490044 | CL74: 88.409898 | CM74: 60.029401 | CN74: 42.131219 | CO74: 38.411691 | CP74: 34.2261 | CQ74: 30.06403 | CR74: 9.2700295 | CS74: 8.2528933 | CT74: 5.9783325 | CU74: 5.3041445 | CV74: 4.7339326 | CW74: 4.2158723 | CX74: 0.0033486915 | CY74: 0.0033496429 | CZ74: 0.0047726482 | DA74: 0.0065084482 | DB74: 0.0073043672 | DC74: 0.0083155983 | DD74: 10.485285 | DE74: 13.748085 | DF74: 14.189792 | DG74: 13.808672 | DH74: 13.831353 | DI74: 14.022978 | DJ74: 0.22633082 | DK74: 0.2086188 | DL74: 0.092133631 | DM74: 0.1118446 | DN74: 0.11681809 | DO74: 0.47277661 | DP74: 0.42481993 | DQ74: 0.096833219 | DR74: 0.12229239 | DS74: 0.13844019
A75: 600298.SH | B75: 600298 CH Equity | C75: Main board | D75: Angel Yeast | E75: Food and beverage | F75: 武雨欣 | G75: Yuxin WU | H75: N | I75: Outperform | J75: 43 | K75: 43.84 | L75: 0.062 | M75: 0.0023 | N75: 867.98 | O75: 857.15 | P75: 38052.18 | Q75: 37577.48 | R75: 13581.132 | S75: 15196.913 | T75: 16794.59 | U75: 18774.41 | X75: 1270.165 | Y75: 1324.5691 | Z75: 1606.92 | AA75: 1849.3 | AD75: 38052.18 | AE75: 38052.18 | AF75: 38052.18 | AG75: 38052.18 | AH75: 38052.18 | AI75: 38052.18 | AJ75: 10596.302 | AK75: 11339.471 | AL75: 12006.66 | AM75: 13293.54 | AP75: 38052.18 | AQ75: 38052.18 | AR75: 38052.18 | AS75: 38052.18 | AT75: 38052.18 | AU75: 38052.18 | AV75: 428.86289 | AW75: 477.47616 | AX75: 562.42 | AY75: 647.25 | BB75: 38052.18 | BC75: 38052.18 | BD75: 38052.18 | BE75: 38052.18 | BF75: 38052.18 | BG75: 38052.18 | BH75: 1320.8696 | BI75: 1649.8569 | BJ75: 2239.11 | BK75: 2433.04 | BN75: 1.4633574 | BO75: 1.5260365 | BP75: 1.851333 | BQ75: 2.130579 | BT75: 12.208002 | BU75: 13.064208 | BV75: 13.832876 | BW75: 15.315491 | BZ75: 0.49409305 | CA75: 0.55010042 | CB75: 0.64796424 | CC75: 0.74569691 | CF75: 1.5217743 | CG75: 1.9008006 | CH75: 2.5796793 | CI75: 2.8031061 | CL75: 29.958454 | CM75: 28.727968 | CN75: 23.680196 | CO75: 20.576532 | CR75: 3.5910811 | CS75: 3.3557278 | CT75: 3.1692561 | CU75: 2.8624565 | CX75: 0.011270389 | CY75: 0.012547932 | CZ75: 0.014780231 | DA75: 0.017009538 | DD75: 11.986871 | DE75: 11.681048 | DF75: 13.383572 | DG75: 13.911268 | DJ75: 0.11897253 | DK75: 0.10513167 | DL75: 0.11788439 | DO75: 0.04283234 | DP75: 0.21316431 | DQ75: 0.15083514
A76: 600305.SH | B76: 600305 CH Equity | C76: Main board | D76: Hengshun Vinegar | E76: Food and beverage | F76: 王尧 | G76: Yao WANG | H76: N | I76: Outperform | J76: 9 | K76: 8.19 | L76: 0.0149 | M76: 0.0341 | N76: 1106.47 | O76: 1102.99 | P76: 9062 | Q76: 9033.47 | R76: 2106.4107 | S76: 2195.8705 | T76: 2335.01 | U76: 2512.92 | V76: 2707.33 | W76: 2920.06 | X76: 86.899447 | Y76: 127.34206 | Z76: 184.8 | AA76: 211.64 | AB76: 183.57 | AC76: 188.02 | AD76: 9062 | AE76: 9062 | AF76: 9062 | AG76: 9062 | AH76: 9062 | AI76: 9062 | AJ76: 3337.3111 | AK76: 3328.9675 | AL76: 3391.92 | AM76: 3442.62 | AN76: 3441.88 | AO76: 3470.04 | AP76: 9062 | AQ76: 9062 | AR76: 9062 | AS76: 9062 | AT76: 9062 | AU76: 9062 | AV76: 77.205367 | AW76: 110.64715 | AX76: 160.94 | AY76: 184.31 | AZ76: 159.86 | BA76: 163.73 | BB76: 9062 | BC76: 9062 | BD76: 9062 | BE76: 9062 | BF76: 9062 | BG76: 9062 | BH76: 248.4524 | BI76: 494.27993 | BJ76: 345.71 | BK76: 389.14 | BL76: 374.38 | BM76: 375.29 | BN76: 0.078537554 | BO76: 0.11508858 | BP76: 0.16701763 | BQ76: 0.19127496 | BR76: 0.16590599 | BS76: 0.16992779 | BT76: 3.0161786 | BU76: 3.0086378 | BV76: 3.0655327 | BW76: 3.1113541 | BX76: 3.1106853 | BY76: 3.1361356 | BZ76: 0.069776285 | CA76: 0.10000014 | CB76: 0.14545356 | CC76: 0.16657478 | CD76: 0.14447748 | CE76: 0.14797509 | CF76: 0.22454508 | CG76: 0.44671788 | CH76: 0.31244408 | CI76: 0.35169503 | CJ76: 0.33835531 | CK76: 0.33917775 | CL76: 104.28145 | CM76: 71.162663 | CN76: 49.036797 | CO76: 42.817993 | CP76: 49.365365 | CQ76: 48.197 | CR76: 2.7153597 | CS76: 2.7221654 | CT76: 2.6716432 | CU76: 2.6322975 | CV76: 2.6328634 | CW76: 2.6114973 | CX76: 0.0085196829 | CY76: 0.012210015 | CZ76: 0.017759876 | DA76: 0.020338777 | DB76: 0.017640697 | DC76: 0.018067755 | DD76: 2.6038761 | DE76: 3.8252719 | DF76: 5.4482417 | DG76: 6.1476434 | DH76: 5.3334224 | DI76: 5.4183813 | DJ76: 0.042470266 | DK76: 0.063364161 | DL76: 0.076192393 | DM76: 0.077364182 | DN76: 0.078575571 | DO76: 0.4653955 | DP76: 0.45120946 | DQ76: 0.1452381 | DR76: -0.13263088 | DS76: 0.024241434
A77: 600309.SH | B77: 600309 CH Equity | C77: Main board | D77: Wanhua Chemical | E77: Chemicals | F77: 贾雄伟 | G77: Xiongwei JIA | H77: N | I77: Outperform | J77: 105 | K77: 86.7 | L77: 0.0793 | M77: 0.1307 | N77: 3130.47 | O77: 3130.47 | P77: 271411.89 | Q77: 271411.89 | R77: 175360.94 | S77: 182069.12 | T77: 177459.26 | U77: 205219.88 | V77: 222932.51 | X77: 16815.756 | Y77: 13033.067 | Z77: 13062.33 | AA77: 17256.4 | AB77: 22855.48 | AD77: 271411.89 | AE77: 271411.89 | AF77: 271411.89 | AG77: 271411.89 | AH77: 271411.89 | AI77: 271411.89 | AJ77: 94454.216 | AK77: 103500.15 | AL77: 103763.54 | AM77: 117101.24 | AN77: 134779.8 | AP77: 271411.89 | AQ77: 271411.89 | AR77: 271411.89 | AS77: 271411.89 | AT77: 271411.89 | AU77: 271411.89 | AV77: 5102.0883 | AW77: 3924.6833 | AX77: 3918.7 | AY77: 5176.92 | AZ77: 6856.64 | BB77: 271411.89 | BC77: 271411.89 | BD77: 271411.89 | BE77: 271411.89 | BF77: 271411.89 | BG77: 271411.89 | BH77: 26796.753 | BI77: 30053.435 | BJ77: 31286.12 | BK77: 43490.32 | BL77: 49389.44 | BN77: 5.3716393 | BO77: 4.1632939 | BP77: 4.1726418 | BQ77: 5.5123991 | BR77: 7.300974 | BT77: 30.172535 | BU77: 33.062176 | BV77: 33.146313 | BW77: 37.40692 | BX77: 43.054174 | BZ77: 1.6298154 | CA77: 1.2537042 | CB77: 1.2517929 | CC77: 1.6537197 | CD77: 2.1902909 | CF77: 8.5599774 | CG77: 9.6002949 | CH77: 9.9940648 | CI77: 13.892585 | CJ77: 15.777005 | CL77: 16.140333 | CM77: 20.824868 | CN77: 20.778214 | CO77: 15.728187 | CP77: 11.875134 | CR77: 2.8734757 | CS77: 2.6223333 | CT77: 2.6156769 | CU77: 2.3177542 | CV77: 2.0137431 | CX77: 0.018798323 | CY77: 0.014460248 | CZ77: 0.014438203 | DA77: 0.019074035 | DB77: 0.025262858 | DD77: 17.803076 | DE77: 12.592317 | DF77: 12.588555 | DG77: 14.736309 | DH77: 16.957645 | DJ77: 0.038253579 | DK77: -0.025319281 | DL77: 0.15643376 | DM77: 0.086310498 | DO77: -0.22494909 | DP77: 0.0022453186 | DQ77: 0.32108131 | DR77: 0.32446397
A78: 600312.SH | B78: 600312 CH Equity | C78: Main board | D78: Pinggao Electric | E78: Electrical equipment and new energy | F78: 曲昊源 | G78: Haoyuan QU | H78: N | I78: Outperform | J78: 21.56 | K78: 21.09 | L78: -0.0213 | M78: 0.2156 | N78: 1356.92 | O78: 1356.92 | P78: 28617.47 | Q78: 28617.47 | R78: 11077 | S78: 12401.611 | T78: 13408.35 | U78: 15490.4 | X78: 815.71432 | Y78: 1023.1711 | Z78: 1298.4 | AA78: 1714.75 | AD78: 28617.47 | AE78: 28617.47 | AF78: 28617.47 | AG78: 28617.47 | AH78: 28617.47 | AI78: 28617.47 | AJ78: 10489.447 | AK78: 10965.256 | AL78: 11377.65 | AM78: 12594.76 | AP78: 28617.47 | AQ78: 28617.47 | AR78: 28617.47 | AS78: 28617.47 | AT78: 28617.47 | AU78: 28617.47 | AV78: 287.66732 | AW78: 392.15026 | AX78: 497.64 | AY78: 657.21 | BB78: 28617.47 | BC78: 28617.47 | BD78: 28617.47 | BE78: 28617.47 | BF78: 28617.47 | BG78: 28617.47 | BH78: 2503.9492 | BI78: 3008.1565 | BJ78: 1046.84 | BK78: 1791.74 | BN78: 0.60115137 | BO78: 0.7540394 | BP78: 0.95687292 | BQ78: 1.2637075 | BT78: 7.7303359 | BU78: 8.0809895 | BV78: 8.3849085 | BW78: 9.2818737 | BZ78: 0.2120002 | CA78: 0.28900028 | CB78: 0.36674233 | CC78: 0.48433953 | CF78: 1.8453182 | CG78: 2.2169004 | CH78: 0.77148248 | CI78: 1.3204463 | CL78: 35.082711 | CM78: 27.969387 | CN78: 22.040565 | CO78: 16.689004 | CR78: 2.7282152 | CS78: 2.6098314 | CT78: 2.5152356 | CU78: 2.2721727 | CX78: 0.010052158 | CY78: 0.013703177 | CZ78: 0.017389378 | DA78: 0.022965342 | DD78: 7.7765233 | DE78: 9.3310281 | DF78: 11.411847 | DG78: 13.614789 | DJ78: 0.11958213 | DK78: 0.081178054 | DL78: 0.15528011 | DO78: 0.25432534 | DP78: 0.26899591 | DQ78: 0.32066389
A79: 600315.SH | B79: 600315 CH Equity | C79: Main board | D79: Shanghai Jahwa | E79: Chemicals | F79: 徐卓楠 | G79: Zhuonan XU | H79: N | I79: Outperform | J79: 30 | K79: 21.94 | L79: 0.0558 | M79: -0.0258 | N79: 672.23 | O79: 672.23 | P79: 14748.64 | Q79: 14748.64 | R79: 6597.5999 | S79: 5678.512 | T79: 6252.45 | U79: 6682.23 | X79: 500.049 | Y79: -833.09252 | Z79: 414.01 | AA79: 490.25 | AD79: 14748.64 | AE79: 14748.64 | AF79: 14748.64 | AG79: 14748.64 | AH79: 14748.64 | AI79: 14748.64 | AJ79: 7690.1176 | AK79: 6691.7509 | AL79: 7105.76 | AM79: 7596.02 | AP79: 14748.64 | AQ79: 14748.64 | AR79: 14748.64 | AS79: 14748.64 | AT79: 14748.64 | AU79: 14748.64 | AV79: 155.30876 | AW79: 20.166779 | BB79: 14748.64 | BC79: 14748.64 | BD79: 14748.64 | BE79: 14748.64 | BF79: 14748.64 | BG79: 14748.64 | BH79: 103.14783 | BI79: 273.19671 | BJ79: 700.73 | BK79: 725.26 | BN79: 0.74386594 | BO79: -1.2392969 | BP79: 0.61587552 | BQ79: 0.72928908 | BT79: 11.439712 | BU79: 9.9545555 | BV79: 10.57043 | BW79: 11.299734 | BZ79: 0.23103515 | CA79: 0.029999821 | CF79: 0.15344127 | CG79: 0.40640363 | CH79: 1.0423962 | CI79: 1.0788867 | CL79: 29.494389 | CM79: -17.703484 | CN79: 35.623874 | CO79: 30.083916 | CR79: 1.9178692 | CS79: 2.2040032 | CT79: 2.0755894 | CU79: 1.9416273 | CX79: 0.010530378 | CY79: 0.0013673654 | DD79: 6.5024884 | DE79: -12.449545 | DF79: 5.8264 | DG79: 6.4540378 | DJ79: -0.1393064 | DK79: 0.1010719 | DL79: 0.068737855 | DO79: -2.6660218 | DP79: -1.4969556 | DQ79: 0.18415014
A80: 600323.SH | B80: 600323 CH Equity | C80: Main board | D80: Grandblue Environment | E80: Electricity and utilities | F80: 刘佳妮 | G80: Jiani LIU | H80: N | I80: Outperform | J80: 31 | K80: 29.31 | L80: 0.0252 | M80: 0.0248 | N80: 815.35 | O80: 815.35 | P80: 23897.82 | Q80: 23897.82 | R80: 12541.289 | S80: 11886.247 | T80: 14496.61 | U80: 15512.72 | X80: 1429.6398 | Y80: 1663.9019 | Z80: 2109.69 | AA80: 2335.69 | AD80: 23897.82 | AE80: 23897.82 | AF80: 23897.82 | AG80: 23897.82 | AH80: 23897.82 | AI80: 23897.82 | AJ80: 12839.87 | AK80: 15220.869 | AL80: 14859.44 | AM80: 16367.8 | AP80: 23897.82 | AQ80: 23897.82 | AR80: 23897.82 | AS80: 23897.82 | AT80: 23897.82 | AU80: 23897.82 | AV80: 391.36663 | AW80: 652.27772 | AX80: 827.03 | AY80: 915.63 | BB80: 23897.82 | BC80: 23897.82 | BD80: 23897.82 | BE80: 23897.82 | BF80: 23897.82 | BG80: 23897.82 | BH80: 2482.0507 | BI80: 3272.6844 | BJ80: 3798.14 | BK80: 4079.53 | BN80: 1.7534063 | BO80: 2.040721 | BP80: 2.5874655 | BQ80: 2.8646471 | BT80: 15.747679 | BU80: 18.667896 | BV80: 18.224615 | BW80: 20.074569 | BZ80: 0.47999832 | CA80: 0.7999972 | CB80: 1.0143251 | CC80: 1.1229901 | CF80: 3.0441537 | CG80: 4.0138399 | CH80: 4.658294 | CI80: 5.0034096 | CL80: 16.715972 | CM80: 14.362517 | CN80: 11.327645 | CO80: 10.231589 | CR80: 1.8612198 | CS80: 1.5700694 | CT80: 1.6082585 | CU80: 1.4600508 | CX80: 0.016376667 | CY80: 0.027294444 | CZ80: 0.034606922 | DA80: 0.038314373 | DD80: 11.134379 | DE80: 10.931714 | DF80: 14.197641 | DG80: 14.27003 | DJ80: -0.052230825 | DK80: 0.21961203 | DL80: 0.070092939 | DO80: 0.16386089 | DP80: 0.2679173 | DQ80: 0.10712474
A81: 600325.SH | B81: 600325 CH Equity | C81: Main board | D81: Huafa Industrial | E81: Real estate | F81: 宋志达 | G81: Zhida SONG | H81: N | I81: Outperform | J81: 8.98 | K81: 4.44 | L81: 0.1045 | M81: 0.0521 | N81: 2752.15 | O81: 2752.15 | P81: 12219.56 | Q81: 12219.56 | R81: 72144.91 | S81: 59992.368 | T81: 67082.51 | U81: 64352.87 | X81: 1837.8419 | Y81: 951.30405 | Z81: 1449.13 | AA81: 1480.85 | AD81: 12219.56 | AE81: 12219.56 | AF81: 12219.56 | AG81: 12219.56 | AH81: 12219.56 | AI81: 12219.56 | AJ81: 131699.56 | AK81: 124988.39 | AL81: 22607.38 | AM81: 23285.31 | AP81: 12219.56 | AQ81: 12219.56 | AR81: 12219.56 | AS81: 12219.56 | AT81: 12219.56 | AU81: 12219.56 | AV81: 1018.2963 | AW81: 285.44538 | AX81: 802.92 | AY81: 820.5 | BB81: 12219.56 | BC81: 12219.56 | BD81: 12219.56 | BE81: 12219.56 | BF81: 12219.56 | BG81: 12219.56 | BH81: 50543.848 | BI81: 15899.669 | BJ81: 6978.46 | BK81: 13118.52 | BN81: 0.66778404 | BO81: 0.3456585 | BP81: 0.5265447 | BQ81: 0.53807024 | BT81: 47.853335 | BU81: 45.414819 | BV81: 8.2144433 | BW81: 8.4607707 | BZ81: 0.37000028 | CA81: 0.10371723 | CB81: 0.29174282 | CC81: 0.29813055 | CF81: 18.365223 | CG81: 5.777181 | CH81: 2.5356394 | CI81: 4.7666443 | CL81: 6.6488637 | CM81: 12.845063 | CN81: 8.4323422 | CO81: 8.2517203 | CR81: 0.092783607 | CS81: 0.097765557 | CT81: 0.54051199 | CU81: 0.52477549 | CX81: 0.083333302 | CY81: 0.02335971 | CZ81: 0.065707767 | DA81: 0.067146444 | DD81: 1.3954807 | DE81: 0.76111391 | DF81: 6.4099865 | DG81: 6.3595889 | DJ81: -0.16844629 | DK81: 0.11818407 | DL81: -0.040690785 | DO81: -0.48237981 | DP81: 0.52330898 | DQ81: 0.021888995
A82: 600332.SH | B82: 600332 CH Equity | C82: Main board | D82: Baiyunshan Pharmaceutical | E82: Pharmaceuticals | F82: 朱言音 | G82: Yanyin ZHU | H82: N | I82: Outperform | J82: 34 | K82: 25.61 | L82: 0.0203 | M82: -0.0051 | N82: 1625.79 | O82: 1405.89 | P82: 41636.51 | Q82: 36004.87 | R82: 75515.404 | S82: 74992.82 | T82: 78500.5 | U82: 82061.56 | V82: 86214.39 | W82: 90590.33 | X82: 4055.6787 | Y82: 2835.4962 | Z82: 3120 | AA82: 3431.4 | AB82: 3686.43 | AC82: 3866.8 | AD82: 41636.51 | AE82: 41636.51 | AF82: 41636.51 | AG82: 41636.51 | AH82: 41636.51 | AI82: 41636.51 | AJ82: 36677.824 | AK82: 37769.636 | AL82: 37806.81 | AM82: 39898.26 | AN82: 42111 | AO82: 44394.58 | AP82: 41636.51 | AQ82: 41636.51 | AR82: 41636.51 | AS82: 41636.51 | AT82: 41636.51 | AU82: 41636.51 | AV82: 1217.7174 | AW82: 1300.6328 | AX82: 1339.95 | AY82: 1473.69 | AZ82: 1583.22 | BA82: 1660.69 | BB82: 41636.51 | BC82: 41636.51 | BD82: 41636.51 | BE82: 41636.51 | BF82: 41636.51 | BG82: 41636.51 | BH82: 4103.625 | BI82: 3442.4266 | BJ82: 4009.13 | BK82: 2326.82 | BL82: 2738.21 | BM82: 3364.67 | BN82: 2.4945895 | BO82: 1.7440728 | BP82: 1.919067 | BQ82: 2.1106047 | BR82: 2.26747 | BS82: 2.378413 | BT82: 22.560001 | BU82: 23.231559 | BV82: 23.254424 | BW82: 24.540845 | BX82: 25.901869 | BY82: 27.306466 | BZ82: 0.74900044 | CA82: 0.80000047 | CB82: 0.82418394 | CC82: 0.90644548 | CD82: 0.97381581 | CE82: 1.0214665 | CF82: 2.5240806 | CG82: 2.117387 | CH82: 2.4659581 | CI82: 1.4311935 | CJ82: 1.6842335 | CK82: 2.06956 | CL82: 10.266225 | CM82: 14.68403 | CN82: 13.345035 | CO82: 12.133972 | CP82: 11.294534 | CQ82: 10.767692 | CR82: 1.1351958 | CS82: 1.1023805 | CT82: 1.1012966 | CU82: 1.0435671 | CV82: 0.9887324 | CW82: 0.93787372 | CX82: 0.029246385 | CY82: 0.031237795 | CZ82: 0.032182092 | DA82: 0.035394177 | DB82: 0.038024801 | DC82: 0.039885427 | DD82: 11.057577 | DE82: 7.5073432 | DF82: 8.2524815 | DG82: 8.6003751 | DH82: 8.7540785 | DI82: 8.7100723 | DJ82: -0.0069202241 | DK82: 0.046773538 | DL82: 0.045363533 | DM82: 0.050606277 | DN82: 0.050756492 | DO82: -0.30085779 | DP82: 0.10033653 | DQ82: 0.099807692 | DR82: 0.074322434 | DS82: 0.048928096
A83: 600346.SH | B83: 600346 CH Equity | C83: Main board | D83: Hengli Petrochemical | E83: Oil & gas | F83: 严蓓娜 | G83: Beina YAN | H83: N | I83: Outperform | J83: 17.8 | K83: 24.72 | L83: 0.03 | M83: 0.0972 | N83: 7039.1 | O83: 7039.1 | P83: 174006.55 | Q83: 174006.55 | R83: 234790.67 | S83: 236273.28 | T83: 229072.82 | U83: 235400.06 | X83: 6904.6039 | Y83: 7043.5682 | Z83: 6764.43 | AA83: 7602.55 | AD83: 174006.55 | AE83: 174006.55 | AF83: 174006.55 | AG83: 174006.55 | AH83: 174006.55 | AI83: 174006.55 | AJ83: 59998.562 | AK83: 63417.563 | AL83: 67130.48 | AM83: 71165.85 | AP83: 174006.55 | AQ83: 174006.55 | AR83: 174006.55 | AS83: 174006.55 | AT83: 174006.55 | AU83: 174006.55 | AV83: 3871.5049 | AW83: 3167.5949 | AX83: 3720.44 | AY83: 4181.4 | BB83: 174006.55 | BC83: 174006.55 | BD83: 174006.55 | BE83: 174006.55 | BF83: 174006.55 | BG83: 174006.55 | BH83: 23535.79 | BI83: 22732.565 | BJ83: 18772.6 | BK83: 22995.78 | BN83: 0.98089299 | BO83: 1.0006348 | BP83: 0.96097939 | BQ83: 1.0800457 | BT83: 8.5236127 | BU83: 9.0093283 | BV83: 9.5367987 | BW83: 10.110078 | BZ83: 0.54999998 | CA83: 0.44999999 | CB83: 0.52853916 | CC83: 0.5940248 | CF83: 3.3435795 | CG83: 3.2294704 | CH83: 2.6669034 | CI83: 3.2668637 | CL83: 25.201525 | CM83: 24.704318 | CN83: 25.723756 | CO83: 22.887919 | CR83: 2.9001787 | CS83: 2.7438227 | CT83: 2.5920647 | CU83: 2.445085 | CX83: 0.022249191 | CY83: 0.018203883 | CZ83: 0.021381034 | DA83: 0.02403013 | DD83: 11.507949 | DE83: 11.106652 | DF83: 10.07654 | DG83: 10.682863 | DJ83: 0.0063145783 | DK83: -0.03047512 | DL83: 0.027621086 | DO83: 0.020126334 | DP83: -0.039630229 | DQ83: 0.12390105
A84: 600350.SH | B84: 600350 CH Equity | C84: Main board | D84: Shandong Hi-speed | E84: Transportation and logistics | F84: 张文杰 | G84: Wenjie ZHANG | H84: N | I84: Outperform | J84: 11.5 | K84: 10.18 | L84: -0.0029 | M84: 0.0441 | N84: 4834.57 | O84: 4834.57 | P84: 49215.93 | Q84: 49215.93 | R84: 26545.644 | S84: 28494.276 | T84: 25935.78 | U84: 26604.71 | X84: 3297.2316 | Y84: 3196.1284 | Z84: 3372.59 | AA84: 3302.86 | AD84: 49215.93 | AE84: 49215.93 | AF84: 49215.93 | AG84: 49215.93 | AH84: 49215.93 | AI84: 49215.93 | AJ84: 54941.712 | AK84: 57295.932 | AL84: 44622.36 | AM84: 45901.67 | AP84: 49215.93 | AQ84: 49215.93 | AR84: 49215.93 | AS84: 49215.93 | AT84: 49215.93 | AU84: 49215.93 | AV84: 2032.967 | AW84: 2030.5197 | AX84: 2023.55 | AY84: 1981.72 | BB84: 49215.93 | BC84: 49215.93 | BD84: 49215.93 | BE84: 49215.93 | BF84: 49215.93 | BG84: 49215.93 | BH84: 6010.2942 | BI84: 6840.7078 | BJ84: 6418.32 | BK84: 9374.7 | BN84: 0.68201135 | BO84: 0.66109879 | BP84: 0.69759875 | BQ84: 0.68317555 | BT84: 11.364343 | BU84: 11.851299 | BV84: 9.2298508 | BW84: 9.494468 | BZ84: 0.42050627 | CA84: 0.42000007 | CB84: 0.41855842 | CC84: 0.40990616 | CF84: 1.2431911 | CG84: 1.4149568 | CH84: 1.3275886 | CI84: 1.939097 | CL84: 14.92644 | CM84: 15.398609 | CN84: 14.592918 | CO84: 14.901004 | CR84: 0.89578443 | CS84: 0.85897773 | CT84: 1.1029432 | CU84: 1.0722035 | CX84: 0.041307093 | CY84: 0.041257368 | CZ84: 0.041115753 | DA84: 0.040265825 | DD84: 6.0013267 | DE84: 5.5782814 | DF84: 7.5580718 | DG84: 7.1955116 | DJ84: 0.073406827 | DK84: -0.089789811 | DL84: 0.025791783 | DO84: -0.030663077 | DP84: 0.055211063 | DQ84: -0.020675505
A85: 600352.SH | B85: 600352 CH Equity | C85: Main board | D85: Zhejiang Longsheng | E85: Chemicals | F85: 李熹凌 | G85: Xiling LI | H85: N | I85: Outperform | J85: 16.92 | K85: 14.95 | L85: 0.0912 | M85: 0.4024 | N85: 3253.33 | O85: 3253.33 | P85: 48637.31 | Q85: 48637.31 | R85: 15303.106 | S85: 15883.857 | T85: 15993.37 | U85: 24678.91 | V85: 20940.69 | X85: 1533.9513 | Y85: 2030.2893 | Z85: 2043.67 | AA85: 2753.04 | AB85: 2790.89 | AD85: 48637.31 | AE85: 48637.31 | AF85: 48637.31 | AG85: 48637.31 | AH85: 48637.31 | AI85: 48637.31 | AJ85: 35713.344 | AK85: 37252.189 | AL85: 35510.74 | AM85: 37037.58 | AN85: 38176.65 | AP85: 48637.31 | AQ85: 48637.31 | AR85: 48637.31 | AS85: 48637.31 | AT85: 48637.31 | AU85: 48637.31 | AV85: 813.33296 | AW85: 1463.9993 | AX85: 1226.2 | AY85: 1651.83 | AZ85: 1674.53 | BB85: 48637.31 | BC85: 48637.31 | BD85: 48637.31 | BE85: 48637.31 | BF85: 48637.31 | BG85: 48637.31 | BH85: 2751.0605 | BI85: 9265.3819 | BJ85: 4539.98 | BK85: 11912.17 | BL85: 5113.99 | BN85: 0.4715019 | BO85: 0.62406499 | BP85: 0.6281779 | BQ85: 0.84622218 | BR85: 0.85785641 | BT85: 10.977474 | BU85: 11.45048 | BV85: 10.915198 | BW85: 11.384514 | BX85: 11.734638 | BZ85: 0.25000014 | CA85: 0.45000026 | CB85: 0.37690612 | CC85: 0.50773515 | CD85: 0.51471262 | CF85: 0.84561373 | CG85: 2.8479687 | CH85: 1.3954871 | CI85: 3.6615314 | CJ85: 1.5719248 | CL85: 31.707207 | CM85: 23.955851 | CN85: 23.799004 | CO85: 17.666765 | CP85: 17.427168 | CR85: 1.3618806 | CS85: 1.3056229 | CT85: 1.3696507 | CU85: 1.3131881 | CV85: 1.2740068 | CX85: 0.016722408 | CY85: 0.030100335 | CZ85: 0.025211098 | DA85: 0.033962199 | DB85: 0.034428919 | DD85: 4.2951767 | DE85: 5.450121 | DF85: 5.7550758 | DG85: 7.433099 | DH85: 7.3104633 | DJ85: 0.037949888 | DK85: 0.0068946323 | DL85: 0.54307129 | DM85: -0.15147427 | DO85: 0.32356835 | DP85: 0.0065905157 | DQ85: 0.34710594 | DR85: 0.013748438
A86: 600361.SH | B86: 600361 CH Equity | C86: Main board | D86: Innovation New Material Technology | E86: Machinery | F86: 王畅舟 | G86: Changzhou WANG | H86: N | I86: Outperform | J86: 5.6 | K86: 4.44 | L86: 0.0114 | M86: 0.0472 | N86: 3756.07 | O86: 3756.07 | P86: 16676.96 | Q86: 16676.96 | R86: 72843.632 | S86: 80941.533 | T86: 87787.35 | U86: 98360.26 | X86: 957.8717 | Y86: 1010.3627 | Z86: 1111.42 | AA86: 1284.95 | AD86: 16676.96 | AE86: 16676.96 | AF86: 16676.96 | AG86: 16676.96 | AH86: 16676.96 | AI86: 16676.96 | AJ86: 10277.029 | AK86: 10930.33 | AL86: 10954.09 | AM86: 12127.9 | AP86: 16676.96 | AQ86: 16676.96 | AR86: 16676.96 | AS86: 16676.96 | AT86: 16676.96 | AU86: 16676.96 | AV86: 287.52051 | AW86: 303.49063 | AX86: 111.14 | AY86: 128.5 | BB86: 16676.96 | BC86: 16676.96 | BD86: 16676.96 | BE86: 16676.96 | BF86: 16676.96 | BG86: 16676.96 | BH86: 582.36833 | BI86: 1516.8912 | BJ86: 1871.17 | BK86: 1754.42 | BN86: 0.25501966 | BO86: 0.26899463 | BP86: 0.2958997 | BQ86: 0.34209959 | BT86: 2.7361121 | BU86: 2.9100442 | BV86: 2.91637 | BW86: 3.2288802 | BZ86: 0.07654823 | CA86: 0.080800047 | CB86: 0.029589438 | CC86: 0.03421129 | CF86: 0.15504725 | CG86: 0.40385061 | CH86: 0.49817229 | CI86: 0.46708927 | CL86: 17.410432 | CM86: 16.505915 | CN86: 15.005093 | CO86: 12.978684 | CR86: 1.6227414 | CS86: 1.5257509 | CT86: 1.5224414 | CU86: 1.3750905 | CX86: 0.017240583 | CY86: 0.018198199 | CZ86: 0.0066642841 | DA86: 0.0077052412 | DD86: 9.3205122 | DE86: 9.2436613 | DF86: 10.146165 | DG86: 10.594992 | DJ86: 0.11116828 | DK86: 0.084577306 | DL86: 0.12043774 | DO86: 0.054799573 | DP86: 0.10002086 | DQ86: 0.15613359
A87: 600369.SH | B87: 600369 CH Equity | C87: Main board | D87: Southwest Securities | E87: Non-bank financials | F87: 樊优 | G87: You FAN | H87: N | I87: Neutral | J87: 5.06 | K87: 4.61 | L87: 0.0313 | M87: 0.029 | N87: 6645.11 | O87: 6645.11 | P87: 30633.95 | Q87: 30633.95 | R87: 2328.769 | S87: 2565.6508 | T87: 3238.29 | U87: 3650.63 | V87: 3928.73 | X87: 602.22929 | Y87: 699.39401 | Z87: 917.99 | AA87: 1069.95 | AB87: 1155.54 | AD87: 30633.95 | AE87: 30633.95 | AF87: 30633.95 | AG87: 30633.95 | AH87: 30633.95 | AI87: 30633.95 | AJ87: 25402.446 | AK87: 25811.325 | AL87: 26164.48 | AM87: 26493.06 | AN87: 26784.5 | AP87: 30633.95 | AQ87: 30633.95 | AR87: 30633.95 | AS87: 30633.95 | AT87: 30633.95 | AU87: 30633.95 | AV87: 232.57882 | AW87: 564.83428 | AX87: 955.57 | AY87: 1113.72 | AZ87: 1202.76 | BB87: 30633.95 | BC87: 30633.95 | BD87: 30633.95 | BE87: 30633.95 | BF87: 30633.95 | BG87: 30633.95 | BH87: -1562.1526 | BI87: 10395.821 | BN87: 0.090627437 | BO87: 0.10524942 | BP87: 0.13814519 | BQ87: 0.16101314 | BR87: 0.17389328 | BT87: 3.8227277 | BU87: 3.8842585 | BV87: 3.9374036 | BW87: 3.9868505 | BX87: 4.0307083 | BZ87: 0.034999995 | CA87: 0.084999989 | CB87: 0.14380048 | CC87: 0.16759993 | CD87: 0.18099926 | CF87: -0.23508304 | CG87: 1.5644318 | CL87: 50.867586 | CM87: 43.800704 | CN87: 33.370679 | CO87: 28.631198 | CP87: 26.510506 | CR87: 1.2059449 | CS87: 1.1868414 | CT87: 1.170822 | CU87: 1.1563009 | CV87: 1.1437193 | CX87: 0.0075921916 | CY87: 0.01843818 | CZ87: 0.03119317 | DA87: 0.036355743 | DB87: 0.039262322 | DD87: 2.3707531 | DE87: 2.7096401 | DF87: 3.5085352 | DG87: 4.0386048 | DH87: 4.3142116 | DJ87: 0.10171975 | DK87: 0.26217099 | DL87: 0.12733264 | DM87: 0.076178632 | DO87: 0.16134174 | DP87: 0.31255057 | DQ87: 0.16553557 | DR87: 0.079994392
A88: 600372.SH | B88: 600372 CH Equity | C88: Main board | D88: China Avionics Systems | E88: High-end equipment | F88: 刘中玉 | G88: Zhongyu LIU | H88: N | I88: Outperform | J88: 13.12 | K88: 15.4 | L88: 0.0274 | M88: 0.1475 | N88: 4838.9 | O88: 4838.9 | P88: 74519.01 | Q88: 74519.01 | R88: 29006.921 | S88: 23879.725 | T88: 25047.52 | U88: 27324.82 | V88: 29818.47 | W88: 32549.54 | X88: 1886.4206 | Y88: 1040.7258 | Z88: 1120.04 | AA88: 1269.37 | AB88: 1402.48 | AC88: 1553.92 | AD88: 74519.01 | AE88: 74519.01 | AF88: 74519.01 | AG88: 74519.01 | AH88: 74519.01 | AI88: 74519.01 | AJ88: 37694.958 | AK88: 39212.628 | AL88: 37594.84 | AM88: 37809.88 | AN88: 38017.44 | AO88: 38251.15 | AP88: 74519.01 | AQ88: 74519.01 | AR88: 74519.01 | AS88: 74519.01 | AT88: 74519.01 | AU88: 74519.01 | AV88: 1180.6908 | AW88: 338.72276 | AX88: 1054.34 | AY88: 1194.91 | AZ88: 1320.21 | BA88: 1462.77 | BB88: 74519.01 | BC88: 74519.01 | BD88: 74519.01 | BE88: 74519.01 | BF88: 74519.01 | BG88: 74519.01 | BH88: -1017.258 | BI88: -1988.7141 | BJ88: -4611.74 | BK88: 2276.95 | BL88: 2595.68 | BM88: 2722.12 | BN88: 0.38984492 | BO88: 0.21507486 | BP88: 0.23146583 | BQ88: 0.26232615 | BR88: 0.28983447 | BS88: 0.32113084 | BT88: 7.7899849 | BU88: 8.1036244 | BV88: 7.7692947 | BW88: 7.8137345 | BX88: 7.8566286 | BY88: 7.9049267 | BZ88: 0.24399983 | CA88: 0.069999951 | CB88: 0.21788836 | CC88: 0.24693835 | CD88: 0.27283267 | CE88: 0.30229391 | CF88: -0.21022505 | CG88: -0.41098475 | CH88: -0.95305545 | CI88: 0.47055116 | CJ88: 0.53641943 | CK88: 0.56254934 | CL88: 39.502861 | CM88: 71.602927 | CN88: 66.532454 | CO88: 58.705507 | CP88: 53.133742 | CQ88: 47.9555 | CR88: 1.976896 | CS88: 1.900383 | CT88: 1.9821606 | CU88: 1.9708872 | CV88: 1.960127 | CW88: 1.9481508 | CX88: 0.015844155 | CY88: 0.0045454544 | CZ88: 0.014148604 | DA88: 0.016034969 | DB88: 0.017716419 | DC88: 0.019629488 | DD88: 5.0044375 | DE88: 2.6540577 | DF88: 2.9792386 | DG88: 3.3572442 | DH88: 3.6890438 | DI88: 4.0624138 | DJ88: -0.17675768 | DK88: 0.048903195 | DL88: 0.090919181 | DM88: 0.091259522 | DN88: 0.091589877 | DO88: -0.44830662 | DP88: 0.076210514 | DQ88: 0.1333256 | DR88: 0.10486304 | DS88: 0.10798015
A89: 600376.SH | B89: 600376 CH Equity | C89: Main board | D89: Beijing Capital Development | E89: Real estate | F89: 宋志达 | G89: Zhida SONG | H89: N | I89: Neutral | J89: 2.7 | K89: 5.52 | L89: -0.0054 | M89: -0.1649 | N89: 2579.57 | O89: 2579.57 | P89: 14239.2 | Q89: 14239.2 | R89: 47762.93 | S89: 24213.068 | T89: 31878.72 | U89: 26035.23 | V89: 20798.91 | X89: -6338.5236 | Y89: -8140.7758 | Z89: -8244.46 | AA89: -7063.61 | AB89: -5336.2 | AD89: 14239.2 | AE89: 14239.2 | AF89: 14239.2 | AG89: 14239.2 | AH89: 14239.2 | AI89: 14239.2 | AJ89: 59855.429 | AK89: 51062.495 | AL89: 13482.49 | AM89: 6418.88 | AN89: 1082.68 | AP89: 14239.2 | AQ89: 14239.2 | AR89: 14239.2 | AS89: 14239.2 | AT89: 14239.2 | AU89: 14239.2 | BB89: 14239.2 | BC89: 14239.2 | BD89: 14239.2 | BE89: 14239.2 | BF89: 14239.2 | BG89: 14239.2 | BH89: 5667.3225 | BI89: 7381.8639 | BJ89: -7176.8 | BK89: 6897.92 | BL89: 9777.51 | BN89: -2.4572016 | BO89: -3.1558654 | BP89: -3.1960598 | BQ89: -2.7382897 | BR89: -2.0686393 | BT89: 23.203646 | BU89: 19.794964 | BV89: 5.2266424 | BW89: 2.4883527 | BX89: 0.41971336 | CF89: 2.1970028 | CG89: 2.8616645 | CH89: -2.7821691 | CI89: 2.6740581 | CJ89: 3.7903643 | CL89: -2.2464537 | CM89: -1.7491208 | CN89: -1.7271234 | CO89: -2.0158531 | CP89: -2.6684157 | CR89: 0.23789321 | CS89: 0.27885829 | CT89: 1.0561254 | CU89: 2.2183309 | CV89: 13.151808 | DD89: -10.589722 | DE89: -15.942769 | DF89: -61.149387 | DG89: -110.04428 | DH89: -492.86955 | DJ89: -0.49305732 | DK89: 0.31659152 | DL89: -0.18330378 | DM89: -0.2011244 | DO89: 0.28433311 | DP89: 0.012736405 | DQ89: -0.14322951 | DR89: -0.24455059
