Workbook

Sheet 目录
A1: 【华泰策略】新兴产业链景气指数
A3: 组合回测
A4: 面板-总览
A5: 面板-景气指数
A6: 面板-细分环节景气分位数
A7: 面板-细分环节景气指标
A8: 附录-指标体系
A9: 附录-数据来源
A11: 前瞻指标-分产业链
A12: 锂电-领先
A13: 光伏-领先
A14: 风电-领先
... A34: Email: wangyi012893@htsc.com

Sheet 组合回测
L1: 截至11.04
C2: 44562 | D2: 44593 | E2: 44621 | F2: 44652 | G2: 44682 | H2: 44713 | I2: 44743 | J2: 44774 | K2: 44805 | L2: 44835 | Q2: 1月 | R2: 2月 | S2: 3月 | T2: 4月 | U2: 5月 | V2: 6月 | W2: 7月 | X2: 8月 | Y2: 9月 | Z2: 10月 | AA2: 年初至今 | AB2: 5月以来
A3: 884790.WI | B3: 储能指数 | C3: -14.842353 | D3: 4.7821384 | E3: -13.586805 | F3: -18.740445 | G3: 20.826636 | H3: 26.753549 | I3: 6.4962536 | J3: -3.9431589 | K3: -9.0113701 | L3: 13.773565 | O3: 战略配置 奇点时刻组合 | P3: 储能 | T3: 1 | U3: 1 | V3: 1 | W3: 1 | X3: 1 | Y3: 1 | Z3: 1
A4: CI005138.WI | B4: 汽车零部件 | C4: -7.8922957 | D4: -1.4783535 | E4: -13.321728 | F4: -11.900319 | G4: 14.904159 | H4: 14.603652 | I4: 16.386087 | J4: -13.951797 | K4: -8.3148218 | L4: 12.529314 | P4: 智能汽车 | Q4: 1 | R4: 1 | T4: 1 | U4: 1 | V4: 1 | W4: 1 | X4: 1 | Y4: 1 | Z4: 1
A5: CI005459.WI | B5: 光伏设备(中信) | C5: -23.631112 | D5: 9.0565249 | E5: -9.4110188 | F5: -12.600209 | G5: 15.595733 | H5: 23.567465 | I5: 14.20303 | J5: -0.020584896 | K5: -8.1152643 | L5: 14.801592 | P5: N型电池（光伏生产设备） | T5: 1 | U5: 1 | V5: 1 | W5: 1 | X5: 1 | Y5: 1 | Z5: 1
A6: 688234.SH | B6: 半导体材料(中信) | C6: -20.444444 | D6: 0.57336078 | E6: -20.333285 | F6: -19.633028 | G6: 22.60274 | H6: 24.767225 | I6: 26.716418 | J6: 11.943463 | K6: 13.331229 | L6: 13.527063 | P6: 碳化硅 | T6: 1 | U6: 1 | V6: 1 | W6: 1 | X6: 1 | Y6: 1 | Z6: 1
A7: 884039.WI | B7: 锂电池指数 | C7: -13.242191 | D7: 7.9342773 | E7: -13.065676 | F7: -18.556395 | G7: 13.994052 | H7: 21.365571 | I7: 1.7138715 | J7: -8.1280516 | K7: -12.856294 | L7: 9.0694591 | O7: 战术轮动 月度调仓 | P7: 锂电 | U7: 1 | V7: 1
A8: 801735.SI | B8: 光伏设备(申万) | C8: -16.305612 | D8: 10.182547 | E8: -8.9640184 | F8: -12.028803 | G8: 17.036714 | H8: 21.041816 | I8: 0.87399785 | J8: -9.2103286 | K8: -7.0420092 | L8: 11.884095 | P8: 光伏 | S8: 1 | T8: 1 | U8: 1 | V8: 1
A9: 801736.SI | B9: 风电设备(申万) | C9: -6.6124316 | D9: -0.26139898 | E9: -18.69151 | F9: -16.656714 | G9: 22.015123 | H9: 21.23236 | I9: 2.8146597 | J9: -12.770029 | K9: -9.5966238 | L9: 8.5179495 | P9: 风电 | S9: 1 | T9: 1
A10: 801081.SI | B10: 半导体(申万) | C10: -14.967512 | D10: 4.921552 | E10: -12.781501 | F10: -14.929056 | G10: 9.148123 | H10: 8.70857 | I10: -8.9711692 | J10: -1.252863 | K10: -12.338245 | L10: 9.8627402 | P10: 半导体
A11: 8841291.WI | B11: IGBT指数 | C11: -10.946424 | D11: 7.8725006 | E11: -8.9973117 | F11: -12.258814 | G11: 12.062682 | H11: 13.740869 | I11: -7.8405204 | J11: -5.0237391 | K11: -12.767571 | L11: 11.492063 | P11: 功率半导体 | U11: 1
A12: 8841279.WI | B12: IDC指数 | C12: -5.5868098 | D12: 16.500487 | E12: -10.979524 | F12: -21.250942 | G12: 8.8510415 | H12: 9.4994234 | I12: 2.5542209 | J12: -5.3109646 | K12: -9.352536 | L12: 17.743989 | P12: 数字基建 | Q12: 1 | R12: 1 | U12: 1 | V12: 1
A13: 801085.SI | B13: 消费电子(申万) | C13: -12.120337 | D13: -3.4057449 | E13: -21.035115 | F13: -9.8813899 | G13: 10.822486 | H13: 3.877343 | I13: 1.3552766 | J13: 1.1547995 | K13: -15.921452 | L13: 8.0854065 | P13: 消费电子-元宇宙
A14: 884030.WI | B14: 物联网指数 | C14: -13.613309 | D14: 5.1548406 | E14: -11.448574 | F14: -19.825328 | G14: 9.0394367 | H14: 11.313892 | I14: 0.96865663 | J14: -5.2799466 | K14: -13.758684 | L14: 13.276966 | P14: 物联网 | Y14: 1 | Z14: 1
A15: CI005466.WI | B15: 工业机器人及工控系统(中信) | C15: -10.053328 | D15: 2.7083904 | E15: -10.996613 | F15: -17.87975 | G15: 10.555662 | H15: 26.866753 | I15: 14.373185 | J15: -14.647936 | K15: -10.682204 | L15: 13.50082 | P15: 工业机器人 | U15: 1 | V15: 1 | W15: 1 | Z15: 1
A16: 884766.WI | B16: 工业母机指数 | C16: -17.335223 | D16: 7.4520923 | E16: -15.798113 | F16: -15.845991 | G16: 14.084892 | H16: 14.965217 | I16: 10.788018 | J16: -11.31861 | K16: -8.2903343 | L16: 27.516358 | P16: 机床 | Z16: 1
A17: 801742.SI | B17: 航空装备Ⅱ(申万) | C17: -22.353158 | D17: 6.5202169 | E17: -10.154664 | F17: -15.221852 | G17: 11.425438 | H17: 10.826611 | I17: 1.8630868 | J17: -5.7520315 | K17: -1.5676678 | L17: 10.176835 | P17: 航空装备 | Q17: 1 | R17: 1 | U17: 1 | V17: 1
A18: 003230.CJ | B18: CRO/CMO(长江) | C18: -16.47365 | D18: 1.965621 | E18: 7.4020601 | F18: -11.908194 | G18: -4.4213125 | H18: 14.127386 | I18: -11.590546 | J18: -2.6953947 | K18: -19.05756 | L18: 13.480533 | P18: CXO | W18: 1
A19: 801980.SI | B19: 美容护理(申万) | C19: -14.092645 | D19: 4.2863431 | E19: -4.3002614 | F19: -1.7492441 | G19: 5.4233625 | H19: 10.5642 | I19: -2.1863018 | J19: -4.3630745 | K19: -7.9570961 | L19: 2.8041794 | P19: 医美-化妆品 | X19: 1 | Y19: 1 | Z19: 1
A20: 399001.SZ | B20: 创业板指 | C20: -10.293154 | D20: 0.95795892 | E20: -9.9398441 | F20: -9.0509654 | G20: 4.5927367 | H20: 11.872209 | I20: -4.8796057 | J20: -3.677593 | K20: -8.7778977 | L20: 3.7928372 | O20: 华泰策略新兴产业组合 | Q20: =SUMPRODUCT(Q3:Q19,C3:C19)/SUM(Q3:Q19)/100 -> -0.11944088 | R20: =SUMPRODUCT(R3:R19,D3:D19)/SUM(R3:R19)/100 -> 0.071807835 | S20: =SUMPRODUCT(S3:S19,E3:E19)/SUM(S3:S19)/100 -> -0.13827764 | T20: =SUMPRODUCT(T3:T19,F3:F19)/SUM(T3:T19)/100 -> -0.1525992 | U20: =SUMPRODUCT(U3:U19,G3:G19)/SUM(U3:U19)/100 -> 0.14785486 | V20: =SUMPRODUCT(V3:V19,H3:H19)/SUM(V3:V19)/100 -> 0.19921341 | W20: =SUMPRODUCT(W3:W19,I3:I19)/SUM(W3:W19)/100 -> 0.11097405 | X20: =SUMPRODUCT(X3:X19,J3:J19)/SUM(X3:X19)/100 -> -0.020670305 | ... Z20: =SUMPRODUCT(Z3:Z19,L3:L19)/SUM(Z3:Z19)/100 -> 0.13966232 | AA20: {=SUMPRODUCT(PRODUCT(1+Q20:Y20)-1)} -> -0.026027635 | AB20: =SUM(U20:Y20) -> 0.38099533
O21: 战略配置组合 | Q21: =IFERROR(SUMPRODUCT(Q3:Q6,C3:C6)/SUM(Q3:Q6)/100,0) -> -0.078922957 | R21: =IFERROR(SUMPRODUCT(R3:R6,D3:D6)/SUM(R3:R6)/100,0) -> -0.014783535 | S21: =IFERROR(SUMPRODUCT(S3:S6,E3:E6)/SUM(S3:S6)/100,0) -> 0 | T21: =IFERROR(SUMPRODUCT(T3:T6,F3:F6)/SUM(T3:T6)/100,0) -> -0.157185 | U21: =IFERROR(SUMPRODUCT(U3:U6,G3:G6)/SUM(U3:U6)/100,0) -> 0.18482317 | V21: =IFERROR(SUMPRODUCT(V3:V6,H3:H6)/SUM(V3:V6)/100,0) -> 0.22422973 | W21: =IFERROR(SUMPRODUCT(W3:W6,I3:I6)/SUM(W3:W6)/100,0) -> 0.15950447 | X21: =IFERROR(SUMPRODUCT(X3:X6,J3:J6)/SUM(X3:X6)/100,0) -> -0.014930195 | ... Z21: =IFERROR(SUMPRODUCT(Z3:Z6,L3:L6)/SUM(Z3:Z6)/100,0) -> 0.13657884 | AA21: {=SUMPRODUCT(PRODUCT(1+Q21:Y21)-1)} -> 0.22875163 | AB21: =SUM(U21:Y21) -> 0.52335161
O22: 战术配置组合 | Q22: =IFERROR(SUMPRODUCT(Q7:Q19,C7:C19)/SUM(Q7:Q19)/100,0) -> -0.13969984 | R22: =IFERROR(SUMPRODUCT(R7:R19,D7:D19)/SUM(R7:R19)/100,0) -> 0.11510352 | S22: =IFERROR(SUMPRODUCT(S7:S19,E7:E19)/SUM(S7:S19)/100,0) -> -0.13827764 | T22: =IFERROR(SUMPRODUCT(T7:T19,F7:F19)/SUM(T7:T19)/100,0) -> -0.14342758 | U22: =IFERROR(SUMPRODUCT(U7:U19,G7:G19)/SUM(U7:U19)/100,0) -> 0.12320932 | V22: =IFERROR(SUMPRODUCT(V7:V19,H7:H19)/SUM(V7:V19)/100,0) -> 0.17920035 | W22: =IFERROR(SUMPRODUCT(W7:W19,I7:I19)/SUM(W7:W19)/100,0) -> 0.013913195 | X22: =IFERROR(SUMPRODUCT(X7:X19,J7:J19)/SUM(X7:X19)/100,0) -> -0.043630745 | ... Z22: =IFERROR(SUMPRODUCT(Z7:Z19,L7:L19)/SUM(Z7:Z19)/100,0) -> 0.14274581 | AA22: {=SUMPRODUCT(PRODUCT(1+Q22:Y22)-1)} -> -0.18931111 | AB22: =SUM(U22:Y22) -> 0.16411321
O23: 创业板指 | Q23: =C20/100 -> -0.10293154 | R23: =D20/100 -> 0.0095795892 | S23: =E20/100 -> -0.099398441 | T23: =F20/100 -> -0.090509654 | U23: =G20/100 -> 0.045927367 | V23: =H20/100 -> 0.11872209 | W23: =I20/100 -> -0.048796057 | X23: =J20/100 -> -0.03677593 | ... Z23: =L20/100 -> 0.037928372 | AA23: {=SUMPRODUCT(PRODUCT(1+Q23:Y23)-1)} -> -0.27452622 | AB23: =SUM(U23:Y23) -> -0.0087015107
O24: 超额收益 | Q24: =Q20-Q23 -> -0.016509341 | R24: =R20-R23 -> 0.062228246 | S24: =S20-S23 -> -0.038879201 | T24: =T20-T23 -> -0.062089542 | U24: =U20-U23 -> 0.10192749 | V24: =V20-V23 -> 0.080491319 | W24: =W20-W23 -> 0.1597701 | X24: =X20-X23 -> 0.016105625 | ... AA24: =AA20-AA23 -> 0.24849858 | AB24: =SUM(U24:Y24) -> 0.38969684
O25: 来自战略配置部分 | Q25: =Q21-Q23 -> 0.024008581 | R25: =R21-R23 -> -0.024363124 | S25: =S21-S23 -> 0.099398441 | T25: =T21-T23 -> -0.066675348 | U25: =U21-U23 -> 0.1388958 | V25: =V21-V23 -> 0.10550764 | W25: =W21-W23 -> 0.20830053 | X25: =X21-X23 -> 0.021845735 | ... AB25: =AB21-AB23 -> 0.53205312
O26: 来自战术配置部分 | Q26: =Q22-Q23 -> -0.036768301 | R26: =R22-R23 -> 0.10552393 | S26: =S22-S23 -> -0.038879201 | T26: =T22-T23 -> -0.05291793 | U26: =U22-U23 -> 0.077281949 | V26: =V22-V23 -> 0.060478261 | W26: =W22-W23 -> 0.062709251 | X26: =X22-X23 -> -0.0068548145 | ... AB26: =AB22-AB23 -> 0.17281472

Sheet 面板-总览
A2: 景气指数 | B2: 44500 | C2: 44530 | D2: 44561 | E2: 44592 | F2: 44620 | G2: 44651 | H2: 44681 | I2: 44712 | J2: 44742 | K2: 44773 | L2: 44804 | M2: 44834 | N2: 44865 | O2: 2M变化 | Q2: 4Q22预判 | T2: 景气指数 | U2: 44500 | V2: 44530 | W2: 44561 | X2: 44592 | Y2: 44620 | Z2: 44651 | AA2: 44681 | AB2: 44712 | AC2: 44742 | AD2: 44773 | AE2: 44804 | AF2: 44834 | AG2: 44865 | AH2: 2M变化 | AJ2: 趋势图
A3: 锂电 | B3: =INDEX('面板-景气指数'!$33:$45,MATCH('面板-总览'!$A3,'面板-景气指数'!$J$33:$J$45,0),MATCH('面板-总览'!B$2,'面板-景气指数'!$32:$32,0)) -> 0.80168421 | C3: =INDEX('面板-景气指数'!$33:$45,MATCH('面板-总览'!$A3,'面板-景气指数'!$J$33:$J$45,0),MATCH('面板-总览'!C$2,'面板-景气指数'!$32:$32,0)) -> 0.73826316 | D3: =INDEX('面板-景气指数'!$33:$45,MATCH('面板-总览'!$A3,'面板-景气指数'!$J$33:$J$45,0),MATCH('面板-总览'!D$2,'面板-景气指数'!$32:$32,0)) -> 0.73242105 | E3: =INDEX('面板-景气指数'!$33:$45,MATCH('面板-总览'!$A3,'面板-景气指数'!$J$33:$J$45,0),MATCH('面板-总览'!E$2,'面板-景气指数'!$32:$32,0)) -> 0.76571053 | F3: =INDEX('面板-景气指数'!$33:$45,MATCH('面板-总览'!$A3,'面板-景气指数'!$J$33:$J$45,0),MATCH('面板-总览'!F$2,'面板-景气指数'!$32:$32,0)) -> 0.80694737 | G3: =INDEX('面板-景气指数'!$33:$45,MATCH('面板-总览'!$A3,'面板-景气指数'!$J$33:$J$45,0),MATCH('面板-总览'!G$2,'面板-景气指数'!$32:$32,0)) -> 0.82213158 | H3: =INDEX('面板-景气指数'!$33:$45,MATCH('面板-总览'!$A3,'面板-景气指数'!$J$33:$J$45,0),MATCH('面板-总览'!H$2,'面板-景气指数'!$32:$32,0)) -> 0.70592105 | I3: =INDEX('面板-景气指数'!$33:$45,MATCH('面板-总览'!$A3,'面板-景气指数'!$J$33:$J$45,0),MATCH('面板-总览'!I$2,'面板-景气指数'!$32:$32,0)) -> 0.613 | ... K3: =INDEX('面板-景气指数'!$33:$45,MATCH('面板-总览'!$A3,'面板-景气指数'!$J$33:$J$45,0),MATCH('面板-总览'!K$2,'面板-景气指数'!$32:$32,0)) -> 0.68705263 | L3: =INDEX('面板-景气指数'!$33:$46,MATCH('面板-总览'!$A3,'面板-景气指数'!$J$33:$J$46,0),MATCH('面板-总览'!L$2,'面板-景气指数'!$32:$32,0)) -> 0.65971053 | M3: =INDEX('面板-景气指数'!$33:$46,MATCH('面板-总览'!$A3,'面板-景气指数'!$J$33:$J$46,0),MATCH('面板-总览'!M$2,'面板-景气指数'!$32:$32,0)) -> 0.60428947 | N3: =INDEX('面板-景气指数'!$33:$46,MATCH('面板-总览'!$A3,'面板-景气指数'!$J$33:$J$46,0),MATCH('面板-总览'!N$2,'面板-景气指数'!$32:$32,0)) -> 0.60357895 | P3: =N3-L3 -> -0.056131579 | R3: -10 | T3: 锂电上游 | U3: =INDEX('面板-景气指数'!$48:$84,MATCH('面板-总览'!$T3,'面板-景气指数'!$J$48:$J$84,0),MATCH('面板-总览'!U$2,'面板-景气指数'!$32:$32,0)) -> 0.827 | V3: =INDEX('面板-景气指数'!$48:$84,MATCH('面板-总览'!$T3,'面板-景气指数'!$J$48:$J$84,0),MATCH('面板-总览'!V$2,'面板-景气指数'!$32:$32,0)) -> 0.85116667 | W3: =INDEX('面板-景气指数'!$48:$84,MATCH('面板-总览'!$T3,'面板-景气指数'!$J$48:$J$84,0),MATCH('面板-总览'!W$2,'面板-景气指数'!$32:$32,0)) -> 0.83916667 | X3: =INDEX('面板-景气指数'!$48:$84,MATCH('面板-总览'!$T3,'面板-景气指数'!$J$48:$J$84,0),MATCH('面板-总览'!X$2,'面板-景气指数'!$32:$32,0)) -> 0.83666667 | Y3: =INDEX('面板-景气指数'!$48:$84,MATCH('面板-总览'!$T3,'面板-景气指数'!$J$48:$J$84,0),MATCH('面板-总览'!Y$2,'面板-景气指数'!$32:$32,0)) -> 0.88033333 | Z3: =INDEX('面板-景气指数'!$48:$84,MATCH('面板-总览'!$T3,'面板-景气指数'!$J$48:$J$84,0),MATCH('面板-总览'!Z$2,'面板-景气指数'!$32:$32,0)) -> 0.91433333 | AA3: =INDEX('面板-景气指数'!$48:$84,MATCH('面板-总览'!$T3,'面板-景气指数'!$J$48:$J$84,0),MATCH('面板-总览'!AA$2,'面板-景气指数'!$32:$32,0)) -> 0.939 | AB3: =INDEX('面板-景气指数'!$48:$84,MATCH('面板-总览'!$T3,'面板-景气指数'!$J$48:$J$84,0),MATCH('面板-总览'!AB$2,'面板-景气指数'!$32:$32,0)) -> 0.864 | ... AG3: =INDEX('面板-景气指数'!$48:$84,MATCH('面板-总览'!$T3,'面板-景气指数'!$J$48:$J$84,0),MATCH('面板-总览'!AG$2,'面板-景气指数'!$32:$32,0)) -> 0.69533333 | AI3: =AG3-AE3 -> -0.0091666667
A4: 机器人 | B4: =INDEX('面板-景气指数'!$33:$45,MATCH('面板-总览'!$A4,'面板-景气指数'!$J$33:$J$45,0),MATCH('面板-总览'!B$2,'面板-景气指数'!$32:$32,0)) -> 0.51808333 | C4: =INDEX('面板-景气指数'!$33:$45,MATCH('面板-总览'!$A4,'面板-景气指数'!$J$33:$J$45,0),MATCH('面板-总览'!C$2,'面板-景气指数'!$32:$32,0)) -> 0.49891667 | D4: =INDEX('面板-景气指数'!$33:$45,MATCH('面板-总览'!$A4,'面板-景气指数'!$J$33:$J$45,0),MATCH('面板-总览'!D$2,'面板-景气指数'!$32:$32,0)) -> 0.51425 | E4: =INDEX('面板-景气指数'!$33:$45,MATCH('面板-总览'!$A4,'面板-景气指数'!$J$33:$J$45,0),MATCH('面板-总览'!E$2,'面板-景气指数'!$32:$32,0)) -> 0.50825 | F4: =INDEX('面板-景气指数'!$33:$45,MATCH('面板-总览'!$A4,'面板-景气指数'!$J$33:$J$45,0),MATCH('面板-总览'!F$2,'面板-景气指数'!$32:$32,0)) -> 0.64966667 | G4: =INDEX('面板-景气指数'!$33:$45,MATCH('面板-总览'!$A4,'面板-景气指数'!$J$33:$J$45,0),MATCH('面板-总览'!G$2,'面板-景气指数'!$32:$32,0)) -> 0.58466667 | H4: =INDEX('面板-景气指数'!$33:$45,MATCH('面板-总览'!$A4,'面板-景气指数'!$J$33:$J$45,0),MATCH('面板-总览'!H$2,'面板-景气指数'!$32:$32,0)) -> 0.36208333 | I4: =INDEX('面板-景气指数'!$33:$45,MATCH('面板-总览'!$A4,'面板-景气指数'!$J$33:$J$45,0),MATCH('面板-总览'!I$2,'面板-景气指数'!$32:$32,0)) -> 0.1995 | ... K4: =INDEX('面板-景气指数'!$33:$45,MATCH('面板-总览'!$A4,'面板-景气指数'!$J$33:$J$45,0),MATCH('面板-总览'!K$2,'面板-景气指数'!$32:$32,0)) -> 0.42275 | L4: =INDEX('面板-景气指数'!$33:$46,MATCH('面板-总览'!$A4,'面板-景气指数'!$J$33:$J$46,0),MATCH('面板-总览'!L$2,'面板-景气指数'!$32:$32,0)) -> 0.36825 | M4: =INDEX('面板-景气指数'!$33:$46,MATCH('面板-总览'!$A4,'面板-景气指数'!$J$33:$J$46,0),MATCH('面板-总览'!M$2,'面板-景气指数'!$32:$32,0)) -> 0.36575 | N4: =INDEX('面板-景气指数'!$33:$46,MATCH('面板-总览'!$A4,'面板-景气指数'!$J$33:$J$46,0),MATCH('面板-总览'!N$2,'面板-景气指数'!$32:$32,0)) -> 0.3645 | P4: =N4-L4 -> -0.00375 | R4: 10 | T4: 锂电中游 | U4: =INDEX('面板-景气指数'!$48:$84,MATCH('面板-总览'!$T4,'面板-景气指数'!$J$48:$J$84,0),MATCH('面板-总览'!U$2,'面板-景气指数'!$32:$32,0)) -> 0.71207692 | V4: =INDEX('面板-景气指数'!$48:$84,MATCH('面板-总览'!$T4,'面板-景气指数'!$J$48:$J$84,0),MATCH('面板-总览'!V$2,'面板-景气指数'!$32:$32,0)) -> 0.707 | W4: =INDEX('面板-景气指数'!$48:$84,MATCH('面板-总览'!$T4,'面板-景气指数'!$J$48:$J$84,0),MATCH('面板-总览'!W$2,'面板-景气指数'!$32:$32,0)) -> 0.73784615 | X4: =INDEX('面板-景气指数'!$48:$84,MATCH('面板-总览'!$T4,'面板-景气指数'!$J$48:$J$84,0),MATCH('面板-总览'!X$2,'面板-景气指数'!$32:$32,0)) -> 0.772 | Y4: =INDEX('面板-景气指数'!$48:$84,MATCH('面板-总览'!$T4,'面板-景气指数'!$J$48:$J$84,0),MATCH('面板-总览'!Y$2,'面板-景气指数'!$32:$32,0)) -> 0.78761538 | Z4: =INDEX('面板-景气指数'!$48:$84,MATCH('面板-总览'!$T4,'面板-景气指数'!$J$48:$J$84,0),MATCH('面板-总览'!Z$2,'面板-景气指数'!$32:$32,0)) -> 0.79584615 | AA4: =INDEX('面板-景气指数'!$48:$84,MATCH('面板-总览'!$T4,'面板-景气指数'!$J$48:$J$84,0),MATCH('面板-总览'!AA$2,'面板-景气指数'!$32:$32,0)) -> 0.74146154 | AB4: =INDEX('面板-景气指数'!$48:$84,MATCH('面板-总览'!$T4,'面板-景气指数'!$J$48:$J$84,0),MATCH('面板-总览'!AB$2,'面板-景气指数'!$32:$32,0)) -> 0.69446154 | ... AG4: =INDEX('面板-景气指数'!$48:$84,MATCH('面板-总览'!$T4,'面板-景气指数'!$J$48:$J$84,0),MATCH('面板-总览'!AG$2,'面板-景气指数'!$32:$32,0)) -> 0.66 | AI4: =AG4-AE4 -> -0.012230769
A5: 机床 | B5: =INDEX('面板-景气指数'!$33:$45,MATCH('面板-总览'!$A5,'面板-景气指数'!$J$33:$J$45,0),MATCH('面板-总览'!B$2,'面板-景气指数'!$32:$32,0)) -> 0.69716667 | C5: =INDEX('面板-景气指数'!$33:$45,MATCH('面板-总览'!$A5,'面板-景气指数'!$J$33:$J$45,0),MATCH('面板-总览'!C$2,'面板-景气指数'!$32:$32,0)) -> 0.60016667 | D5: =INDEX('面板-景气指数'!$33:$45,MATCH('面板-总览'!$A5,'面板-景气指数'!$J$33:$J$45,0),MATCH('面板-总览'!D$2,'面板-景气指数'!$32:$32,0)) -> 0.52633333 | E5: =INDEX('面板-景气指数'!$33:$45,MATCH('面板-总览'!$A5,'面板-景气指数'!$J$33:$J$45,0),MATCH('面板-总览'!E$2,'面板-景气指数'!$32:$32,0)) -> 0.6005 | F5: =INDEX('面板-景气指数'!$33:$45,MATCH('面板-总览'!$A5,'面板-景气指数'!$J$33:$J$45,0),MATCH('面板-总览'!F$2,'面板-景气指数'!$32:$32,0)) -> 0.74125 | G5: =INDEX('面板-景气指数'!$33:$45,MATCH('面板-总览'!$A5,'面板-景气指数'!$J$33:$J$45,0),MATCH('面板-总览'!G$2,'面板-景气指数'!$32:$32,0)) -> 0.60166667 | H5: =INDEX('面板-景气指数'!$33:$45,MATCH('面板-总览'!$A5,'面板-景气指数'!$J$33:$J$45,0),MATCH('面板-总览'!H$2,'面板-景气指数'!$32:$32,0)) -> 0.431 | I5: =INDEX('面板-景气指数'!$33:$45,MATCH('面板-总览'!$A5,'面板-景气指数'!$J$33:$J$45,0),MATCH('面板-总览'!I$2,'面板-景气指数'!$32:$32,0)) -> 0.44725 | ... K5: =INDEX('面板-景气指数'!$33:$45,MATCH('面板-总览'!$A5,'面板-景气指数'!$J$33:$J$45,0),MATCH('面板-总览'!K$2,'面板-景气指数'!$32:$32,0)) -> 0.32616667 | L5: =INDEX('面板-景气指数'!$33:$46,MATCH('面板-总览'!$A5,'面板-景气指数'!$J$33:$J$46,0),MATCH('面板-总览'!L$2,'面板-景气指数'!$32:$32,0)) -> 0.38966667 | M5: =INDEX('面板-景气指数'!$33:$46,MATCH('面板-总览'!$A5,'面板-景气指数'!$J$33:$J$46,0),MATCH('面板-总览'!M$2,'面板-景气指数'!$32:$32,0)) -> 0.43658333 | N5: =INDEX('面板-景气指数'!$33:$46,MATCH('面板-总览'!$A5,'面板-景气指数'!$J$33:$J$46,0),MATCH('面板-总览'!N$2,'面板-景气指数'!$32:$32,0)) -> 0.43658333 | P5: =N5-L5 -> 0.046916667 | R5: 10 | T5: 锂电下游 | U5: =INDEX('面板-景气指数'!$48:$84,MATCH('面板-总览'!$T5,'面板-景气指数'!$J$48:$J$84,0),MATCH('面板-总览'!U$2,'面板-景气指数'!$32:$32,0)) -> 0.855 | V5: =INDEX('面板-景气指数'!$48:$84,MATCH('面板-总览'!$T5,'面板-景气指数'!$J$48:$J$84,0),MATCH('面板-总览'!V$2,'面板-景气指数'!$32:$32,0)) -> 0.724 | W5: =INDEX('面板-景气指数'!$48:$84,MATCH('面板-总览'!$T5,'面板-景气指数'!$J$48:$J$84,0),MATCH('面板-总览'!W$2,'面板-景气指数'!$32:$32,0)) -> 0.695 | X5: =INDEX('面板-景气指数'!$48:$84,MATCH('面板-总览'!$T5,'面板-景气指数'!$J$48:$J$84,0),MATCH('面板-总览'!X$2,'面板-景气指数'!$32:$32,0)) -> 0.739 | Y5: =INDEX('面板-景气指数'!$48:$84,MATCH('面板-总览'!$T5,'面板-景气指数'!$J$48:$J$84,0),MATCH('面板-总览'!Y$2,'面板-景气指数'!$32:$32,0)) -> 0.797 | Z5: =INDEX('面板-景气指数'!$48:$84,MATCH('面板-总览'!$T5,'面板-景气指数'!$J$48:$J$84,0),MATCH('面板-总览'!Z$2,'面板-景气指数'!$32:$32,0)) -> 0.811 | AA5: =INDEX('面板-景气指数'!$48:$84,MATCH('面板-总览'!$T5,'面板-景气指数'!$J$48:$J$84,0),MATCH('面板-总览'!AA$2,'面板-景气指数'!$32:$32,0)) -> 0.608 | AB5: =INDEX('面板-景气指数'!$48:$84,MATCH('面板-总览'!$T5,'面板-景气指数'!$J$48:$J$84,0),MATCH('面板-总览'!AB$2,'面板-景气指数'!$32:$32,0)) -> 0.478 | ... AG5: =INDEX('面板-景气指数'!$48:$84,MATCH('面板-总览'!$T5,'面板-景气指数'!$J$48:$J$84,0),MATCH('面板-总览'!AG$2,'面板-景气指数'!$32:$32,0)) -> 0.536 | AI5: =AG5-AE5 -> -0.101
A6: 元宇宙 | B6: =INDEX('面板-景气指数'!$33:$45,MATCH('面板-总览'!$A6,'面板-景气指数'!$J$33:$J$45,0),MATCH('面板-总览'!B$2,'面板-景气指数'!$32:$32,0)) -> 0.76025 | C6: =INDEX('面板-景气指数'!$33:$45,MATCH('面板-总览'!$A6,'面板-景气指数'!$J$33:$J$45,0),MATCH('面板-总览'!C$2,'面板-景气指数'!$32:$32,0)) -> 0.710375 | D6: =INDEX('面板-景气指数'!$33:$45,MATCH('面板-总览'!$A6,'面板-景气指数'!$J$33:$J$45,0),MATCH('面板-总览'!D$2,'面板-景气指数'!$32:$32,0)) -> 0.419125 | E6: =INDEX('面板-景气指数'!$33:$45,MATCH('面板-总览'!$A6,'面板-景气指数'!$J$33:$J$45,0),MATCH('面板-总览'!E$2,'面板-景气指数'!$32:$32,0)) -> 0.493375 | F6: =INDEX('面板-景气指数'!$33:$45,MATCH('面板-总览'!$A6,'面板-景气指数'!$J$33:$J$45,0),MATCH('面板-总览'!F$2,'面板-景气指数'!$32:$32,0)) -> 0.4595 | G6: =INDEX('面板-景气指数'!$33:$45,MATCH('面板-总览'!$A6,'面板-景气指数'!$J$33:$J$45,0),MATCH('面板-总览'!G$2,'面板-景气指数'!$32:$32,0)) -> 0.464 | H6: =INDEX('面板-景气指数'!$33:$45,MATCH('面板-总览'!$A6,'面板-景气指数'!$J$33:$J$45,0),MATCH('面板-总览'!H$2,'面板-景气指数'!$32:$32,0)) -> 0.449875 | I6: =INDEX('面板-景气指数'!$33:$45,MATCH('面板-总览'!$A6,'面板-景气指数'!$J$33:$J$45,0),MATCH('面板-总览'!I$2,'面板-景气指数'!$32:$32,0)) -> 0.468375 | ... K6: =INDEX('面板-景气指数'!$33:$45,MATCH('面板-总览'!$A6,'面板-景气指数'!$J$33:$J$45,0),MATCH('面板-总览'!K$2,'面板-景气指数'!$32:$32,0)) -> 0.685875 | L6: =INDEX('面板-景气指数'!$33:$46,MATCH('面板-总览'!$A6,'面板-景气指数'!$J$33:$J$46,0),MATCH('面板-总览'!L$2,'面板-景气指数'!$32:$32,0)) -> 0.672 | M6: =INDEX('面板-景气指数'!$33:$46,MATCH('面板-总览'!$A6,'面板-景气指数'!$J$33:$J$46,0),MATCH('面板-总览'!M$2,'面板-景气指数'!$32:$32,0)) -> 0.199875 | N6: =INDEX('面板-景气指数'!$33:$46,MATCH('面板-总览'!$A6,'面板-景气指数'!$J$33:$J$46,0),MATCH('面板-总览'!N$2,'面板-景气指数'!$32:$32,0)) -> 0.185625 | P6: =N6-L6 -> -0.486375 | R6: 10 | T6: 机器人上游 | U6: =INDEX('面板-景气指数'!$48:$84,MATCH('面板-总览'!$T6,'面板-景气指数'!$J$48:$J$84,0),MATCH('面板-总览'!U$2,'面板-景气指数'!$32:$32,0)) -> 0.826 | V6: =INDEX('面板-景气指数'!$48:$84,MATCH('面板-总览'!$T6,'面板-景气指数'!$J$48:$J$84,0),MATCH('面板-总览'!V$2,'面板-景气指数'!$32:$32,0)) -> 0.869 | W6: =INDEX('面板-景气指数'!$48:$84,MATCH('面板-总览'!$T6,'面板-景气指数'!$J$48:$J$84,0),MATCH('面板-总览'!W$2,'面板-景气指数'!$32:$32,0)) -> 0.898 | X6: =INDEX('面板-景气指数'!$48:$84,MATCH('面板-总览'!$T6,'面板-景气指数'!$J$48:$J$84,0),MATCH('面板-总览'!X$2,'面板-景气指数'!$32:$32,0)) -> 0.913 | Y6: =INDEX('面板-景气指数'!$48:$84,MATCH('面板-总览'!$T6,'面板-景气指数'!$J$48:$J$84,0),MATCH('面板-总览'!Y$2,'面板-景气指数'!$32:$32,0)) -> 0.985 | Z6: =INDEX('面板-景气指数'!$48:$84,MATCH('面板-总览'!$T6,'面板-景气指数'!$J$48:$J$84,0),MATCH('面板-总览'!Z$2,'面板-景气指数'!$32:$32,0)) -> 1 | AA6: =INDEX('面板-景气指数'!$48:$84,MATCH('面板-总览'!$T6,'面板-景气指数'!$J$48:$J$84,0),MATCH('面板-总览'!AA$2,'面板-景气指数'!$32:$32,0)) -> 0.971 | AB6: =INDEX('面板-景气指数'!$48:$84,MATCH('面板-总览'!$T6,'面板-景气指数'!$J$48:$J$84,0),MATCH('面板-总览'!AB$2,'面板-景气指数'!$32:$32,0)) -> 0.927 | ... AG6: =INDEX('面板-景气指数'!$48:$84,MATCH('面板-总览'!$T6,'面板-景气指数'!$J$48:$J$84,0),MATCH('面板-总览'!AG$2,'面板-景气指数'!$32:$32,0)) -> 0.84 | AI6: =AG6-AE6 -> -0.044
A7: 光伏 | B7: =INDEX('面板-景气指数'!$33:$45,MATCH('面板-总览'!$A7,'面板-景气指数'!$J$33:$J$45,0),MATCH('面板-总览'!B$2,'面板-景气指数'!$32:$32,0)) -> 0.60390625 | C7: =INDEX('面板-景气指数'!$33:$45,MATCH('面板-总览'!$A7,'面板-景气指数'!$J$33:$J$45,0),MATCH('面板-总览'!C$2,'面板-景气指数'!$32:$32,0)) -> 0.57996875 | D7: =INDEX('面板-景气指数'!$33:$45,MATCH('面板-总览'!$A7,'面板-景气指数'!$J$33:$J$45,0),MATCH('面板-总览'!D$2,'面板-景气指数'!$32:$32,0)) -> 0.5445 | E7: =INDEX('面板-景气指数'!$33:$45,MATCH('面板-总览'!$A7,'面板-景气指数'!$J$33:$J$45,0),MATCH('面板-总览'!E$2,'面板-景气指数'!$32:$32,0)) -> 0.55065625 | F7: =INDEX('面板-景气指数'!$33:$45,MATCH('面板-总览'!$A7,'面板-景气指数'!$J$33:$J$45,0),MATCH('面板-总览'!F$2,'面板-景气指数'!$32:$32,0)) -> 0.8061875 | G7: =INDEX('面板-景气指数'!$33:$45,MATCH('面板-总览'!$A7,'面板-景气指数'!$J$33:$J$45,0),MATCH('面板-总览'!G$2,'面板-景气指数'!$32:$32,0)) -> 0.78153125 | H7: =INDEX('面板-景气指数'!$33:$45,MATCH('面板-总览'!$A7,'面板-景气指数'!$J$33:$J$45,0),MATCH('面板-总览'!H$2,'面板-景气指数'!$32:$32,0)) -> 0.80559375 | I7: =INDEX('面板-景气指数'!$33:$45,MATCH('面板-总览'!$A7,'面板-景气指数'!$J$33:$J$45,0),MATCH('面板-总览'!I$2,'面板-景气指数'!$32:$32,0)) -> 0.825375 | ... K7: =INDEX('面板-景气指数'!$33:$45,MATCH('面板-总览'!$A7,'面板-景气指数'!$J$33:$J$45,0),MATCH('面板-总览'!K$2,'面板-景气指数'!$32:$32,0)) -> 0.811875 | L7: =INDEX('面板-景气指数'!$33:$46,MATCH('面板-总览'!$A7,'面板-景气指数'!$J$33:$J$46,0),MATCH('面板-总览'!L$2,'面板-景气指数'!$32:$32,0)) -> 0.7890625 | M7: =INDEX('面板-景气指数'!$33:$46,MATCH('面板-总览'!$A7,'面板-景气指数'!$J$33:$J$46,0),MATCH('面板-总览'!M$2,'面板-景气指数'!$32:$32,0)) -> 0.7465 | N7: =INDEX('面板-景气指数'!$33:$46,MATCH('面板-总览'!$A7,'面板-景气指数'!$J$33:$J$46,0),MATCH('面板-总览'!N$2,'面板-景气指数'!$32:$32,0)) -> 0.745375 | P7: =N7-L7 -> -0.0436875 | R7: -10 | T7: 机器人中游 | U7: =INDEX('面板-景气指数'!$48:$84,MATCH('面板-总览'!$T7,'面板-景气指数'!$J$48:$J$84,0),MATCH('面板-总览'!U$2,'面板-景气指数'!$32:$32,0)) -> 0.49009091 | V7: =INDEX('面板-景气指数'!$48:$84,MATCH('面板-总览'!$T7,'面板-景气指数'!$J$48:$J$84,0),MATCH('面板-总览'!V$2,'面板-景气指数'!$32:$32,0)) -> 0.46527273 | W7: =INDEX('面板-景气指数'!$48:$84,MATCH('面板-总览'!$T7,'面板-景气指数'!$J$48:$J$84,0),MATCH('面板-总览'!W$2,'面板-景气指数'!$32:$32,0)) -> 0.47936364 | X7: =INDEX('面板-景气指数'!$48:$84,MATCH('面板-总览'!$T7,'面板-景气指数'!$J$48:$J$84,0),MATCH('面板-总览'!X$2,'面板-景气指数'!$32:$32,0)) -> 0.47145455 | Y7: =INDEX('面板-景气指数'!$48:$84,MATCH('面板-总览'!$T7,'面板-景气指数'!$J$48:$J$84,0),MATCH('面板-总览'!Y$2,'面板-景气指数'!$32:$32,0)) -> 0.61918182 | Z7: =INDEX('面板-景气指数'!$48:$84,MATCH('面板-总览'!$T7,'面板-景气指数'!$J$48:$J$84,0),MATCH('面板-总览'!Z$2,'面板-景气指数'!$32:$32,0)) -> 0.54690909 | AA7: =INDEX('面板-景气指数'!$48:$84,MATCH('面板-总览'!$T7,'面板-景气指数'!$J$48:$J$84,0),MATCH('面板-总览'!AA$2,'面板-景气指数'!$32:$32,0)) -> 0.30672727 | AB7: =INDEX('面板-景气指数'!$48:$84,MATCH('面板-总览'!$T7,'面板-景气指数'!$J$48:$J$84,0),MATCH('面板-总览'!AB$2,'面板-景气指数'!$32:$32,0)) -> 0.13336364 | ... AG7: =INDEX('面板-景气指数'!$48:$84,MATCH('面板-总览'!$T7,'面板-景气指数'!$J$48:$J$84,0),MATCH('面板-总览'!AG$2,'面板-景气指数'!$32:$32,0)) -> 0.32127273 | AI7: =AG7-AE7 -> -9.0909091e-05
A8: 风电 | B8: =INDEX('面板-景气指数'!$33:$45,MATCH('面板-总览'!$A8,'面板-景气指数'!$J$33:$J$45,0),MATCH('面板-总览'!B$2,'面板-景气指数'!$32:$32,0)) -> 0.46971154 | C8: =INDEX('面板-景气指数'!$33:$45,MATCH('面板-总览'!$A8,'面板-景气指数'!$J$33:$J$45,0),MATCH('面板-总览'!C$2,'面板-景气指数'!$32:$32,0)) -> 0.42417308 | D8: =INDEX('面板-景气指数'!$33:$45,MATCH('面板-总览'!$A8,'面板-景气指数'!$J$33:$J$45,0),MATCH('面板-总览'!D$2,'面板-景气指数'!$32:$32,0)) -> 0.35930769 | E8: =INDEX('面板-景气指数'!$33:$45,MATCH('面板-总览'!$A8,'面板-景气指数'!$J$33:$J$45,0),MATCH('面板-总览'!E$2,'面板-景气指数'!$32:$32,0)) -> 0.35619231 | F8: =INDEX('面板-景气指数'!$33:$45,MATCH('面板-总览'!$A8,'面板-景气指数'!$J$33:$J$45,0),MATCH('面板-总览'!F$2,'面板-景气指数'!$32:$32,0)) -> 0.49707692 | G8: =INDEX('面板-景气指数'!$33:$45,MATCH('面板-总览'!$A8,'面板-景气指数'!$J$33:$J$45,0),MATCH('面板-总览'!G$2,'面板-景气指数'!$32:$32,0)) -> 0.421 | H8: =INDEX('面板-景气指数'!$33:$45,MATCH('面板-总览'!$A8,'面板-景气指数'!$J$33:$J$45,0),MATCH('面板-总览'!H$2,'面板-景气指数'!$32:$32,0)) -> 0.40128846 | I8: =INDEX('面板-景气指数'!$33:$45,MATCH('面板-总览'!$A8,'面板-景气指数'!$J$33:$J$45,0),MATCH('面板-总览'!I$2,'面板-景气指数'!$32:$32,0)) -> 0.42980769 | ... K8: =INDEX('面板-景气指数'!$33:$45,MATCH('面板-总览'!$A8,'面板-景气指数'!$J$33:$J$45,0),MATCH('面板-总览'!K$2,'面板-景气指数'!$32:$32,0)) -> 0.37986538 | L8: =INDEX('面板-景气指数'!$33:$46,MATCH('面板-总览'!$A8,'面板-景气指数'!$J$33:$J$46,0),MATCH('面板-总览'!L$2,'面板-景气指数'!$32:$32,0)) -> 0.41230769 | M8: =INDEX('面板-景气指数'!$33:$46,MATCH('面板-总览'!$A8,'面板-景气指数'!$J$33:$J$46,0),MATCH('面板-总览'!M$2,'面板-景气指数'!$32:$32,0)) -> 0.41907692 | N8: =INDEX('面板-景气指数'!$33:$46,MATCH('面板-总览'!$A8,'面板-景气指数'!$J$33:$J$46,0),MATCH('面板-总览'!N$2,'面板-景气指数'!$32:$32,0)) -> 0.42663462 | P8: =N8-L8 -> 0.014326923 | R8: 10 | T8: 机床中游 | U8: =INDEX('面板-景气指数'!$48:$84,MATCH('面板-总览'!$T8,'面板-景气指数'!$J$48:$J$84,0),MATCH('面板-总览'!U$2,'面板-景气指数'!$32:$32,0)) -> 0.69716667 | V8: =INDEX('面板-景气指数'!$48:$84,MATCH('面板-总览'!$T8,'面板-景气指数'!$J$48:$J$84,0),MATCH('面板-总览'!V$2,'面板-景气指数'!$32:$32,0)) -> 0.60016667 | W8: =INDEX('面板-景气指数'!$48:$84,MATCH('面板-总览'!$T8,'面板-景气指数'!$J$48:$J$84,0),MATCH('面板-总览'!W$2,'面板-景气指数'!$32:$32,0)) -> 0.52633333 | X8: =INDEX('面板-景气指数'!$48:$84,MATCH('面板-总览'!$T8,'面板-景气指数'!$J$48:$J$84,0),MATCH('面板-总览'!X$2,'面板-景气指数'!$32:$32,0)) -> 0.6005 | Y8: =INDEX('面板-景气指数'!$48:$84,MATCH('面板-总览'!$T8,'面板-景气指数'!$J$48:$J$84,0),MATCH('面板-总览'!Y$2,'面板-景气指数'!$32:$32,0)) -> 0.74125 | Z8: =INDEX('面板-景气指数'!$48:$84,MATCH('面板-总览'!$T8,'面板-景气指数'!$J$48:$J$84,0),MATCH('面板-总览'!Z$2,'面板-景气指数'!$32:$32,0)) -> 0.60166667 | AA8: =INDEX('面板-景气指数'!$48:$84,MATCH('面板-总览'!$T8,'面板-景气指数'!$J$48:$J$84,0),MATCH('面板-总览'!AA$2,'面板-景气指数'!$32:$32,0)) -> 0.431 | AB8: =INDEX('面板-景气指数'!$48:$84,MATCH('面板-总览'!$T8,'面板-景气指数'!$J$48:$J$84,0),MATCH('面板-总览'!AB$2,'面板-景气指数'!$32:$32,0)) -> 0.44725 | ... AG8: =INDEX('面板-景气指数'!$48:$84,MATCH('面板-总览'!$T8,'面板-景气指数'!$J$48:$J$84,0),MATCH('面板-总览'!AG$2,'面板-景气指数'!$32:$32,0)) -> 0.43658333 | AI8: =AG8-AE8 -> 0.046916667
A9: 半导体 | B9: =INDEX('面板-景气指数'!$33:$45,MATCH('面板-总览'!$A9,'面板-景气指数'!$J$33:$J$45,0),MATCH('面板-总览'!B$2,'面板-景气指数'!$32:$32,0)) -> 0.66088043 | C9: =INDEX('面板-景气指数'!$33:$45,MATCH('面板-总览'!$A9,'面板-景气指数'!$J$33:$J$45,0),MATCH('面板-总览'!C$2,'面板-景气指数'!$32:$32,0)) -> 0.65001087 | D9: =INDEX('面板-景气指数'!$33:$45,MATCH('面板-总览'!$A9,'面板-景气指数'!$J$33:$J$45,0),MATCH('面板-总览'!D$2,'面板-景气指数'!$32:$32,0)) -> 0.61475 | E9: =INDEX('面板-景气指数'!$33:$45,MATCH('面板-总览'!$A9,'面板-景气指数'!$J$33:$J$45,0),MATCH('面板-总览'!E$2,'面板-景气指数'!$32:$32,0)) -> 0.60363043 | F9: =INDEX('面板-景气指数'!$33:$45,MATCH('面板-总览'!$A9,'面板-景气指数'!$J$33:$J$45,0),MATCH('面板-总览'!F$2,'面板-景气指数'!$32:$32,0)) -> 0.57363043 | G9: =INDEX('面板-景气指数'!$33:$45,MATCH('面板-总览'!$A9,'面板-景气指数'!$J$33:$J$45,0),MATCH('面板-总览'!G$2,'面板-景气指数'!$32:$32,0)) -> 0.519 | H9: =INDEX('面板-景气指数'!$33:$45,MATCH('面板-总览'!$A9,'面板-景气指数'!$J$33:$J$45,0),MATCH('面板-总览'!H$2,'面板-景气指数'!$32:$32,0)) -> 0.41781522 | I9: =INDEX('面板-景气指数'!$33:$45,MATCH('面板-总览'!$A9,'面板-景气指数'!$J$33:$J$45,0),MATCH('面板-总览'!I$2,'面板-景气指数'!$32:$32,0)) -> 0.39575 | ... K9: =INDEX('面板-景气指数'!$33:$45,MATCH('面板-总览'!$A9,'面板-景气指数'!$J$33:$J$45,0),MATCH('面板-总览'!K$2,'面板-景气指数'!$32:$32,0)) -> 0.30642391 | L9: =INDEX('面板-景气指数'!$33:$46,MATCH('面板-总览'!$A9,'面板-景气指数'!$J$33:$J$46,0),MATCH('面板-总览'!L$2,'面板-景气指数'!$32:$32,0)) -> 0.26147826 | M9: =INDEX('面板-景气指数'!$33:$46,MATCH('面板-总览'!$A9,'面板-景气指数'!$J$33:$J$46,0),MATCH('面板-总览'!M$2,'面板-景气指数'!$32:$32,0)) -> 0.19802174 | N9: =INDEX('面板-景气指数'!$33:$46,MATCH('面板-总览'!$A9,'面板-景气指数'!$J$33:$J$46,0),MATCH('面板-总览'!N$2,'面板-景气指数'!$32:$32,0)) -> 0.19676087 | P9: =N9-L9 -> -0.064717391 | R9: -10 | T9: 元宇宙中游 | U9: =INDEX('面板-景气指数'!$48:$84,MATCH('面板-总览'!$T9,'面板-景气指数'!$J$48:$J$84,0),MATCH('面板-总览'!U$2,'面板-景气指数'!$32:$32,0)) -> 0.90133333 | V9: =INDEX('面板-景气指数'!$48:$84,MATCH('面板-总览'!$T9,'面板-景气指数'!$J$48:$J$84,0),MATCH('面板-总览'!V$2,'面板-景气指数'!$32:$32,0)) -> 0.86366667 | W9: =INDEX('面板-景气指数'!$48:$84,MATCH('面板-总览'!$T9,'面板-景气指数'!$J$48:$J$84,0),MATCH('面板-总览'!W$2,'面板-景气指数'!$32:$32,0)) -> 0.45733333 | X9: =INDEX('面板-景气指数'!$48:$84,MATCH('面板-总览'!$T9,'面板-景气指数'!$J$48:$J$84,0),MATCH('面板-总览'!X$2,'面板-景气指数'!$32:$32,0)) -> 0.48266667 | Y9: =INDEX('面板-景气指数'!$48:$84,MATCH('面板-总览'!$T9,'面板-景气指数'!$J$48:$J$84,0),MATCH('面板-总览'!Y$2,'面板-景气指数'!$32:$32,0)) -> 0.48366667 | Z9: =INDEX('面板-景气指数'!$48:$84,MATCH('面板-总览'!$T9,'面板-景气指数'!$J$48:$J$84,0),MATCH('面板-总览'!Z$2,'面板-景气指数'!$32:$32,0)) -> 0.55816667 | AA9: =INDEX('面板-景气指数'!$48:$84,MATCH('面板-总览'!$T9,'面板-景气指数'!$J$48:$J$84,0),MATCH('面板-总览'!AA$2,'面板-景气指数'!$32:$32,0)) -> 0.56016667 | AB9: =INDEX('面板-景气指数'!$48:$84,MATCH('面板-总览'!$T9,'面板-景气指数'!$J$48:$J$84,0),MATCH('面板-总览'!AB$2,'面板-景气指数'!$32:$32,0)) -> 0.5265 | ... AG9: =INDEX('面板-景气指数'!$48:$84,MATCH('面板-总览'!$T9,'面板-景气指数'!$J$48:$J$84,0),MATCH('面板-总览'!AG$2,'面板-景气指数'!$32:$32,0)) -> 0.16683333 | AI9: =AG9-AE9 -> -0.54666667
A10: 数字基建 | B10: =INDEX('面板-景气指数'!$33:$45,MATCH('面板-总览'!$A10,'面板-景气指数'!$J$33:$J$45,0),MATCH('面板-总览'!B$2,'面板-景气指数'!$32:$32,0)) -> 0.56195833 | C10: =INDEX('面板-景气指数'!$33:$45,MATCH('面板-总览'!$A10,'面板-景气指数'!$J$33:$J$45,0),MATCH('面板-总览'!C$2,'面板-景气指数'!$32:$32,0)) -> 0.49430833 | D10: =INDEX('面板-景气指数'!$33:$45,MATCH('面板-总览'!$A10,'面板-景气指数'!$J$33:$J$45,0),MATCH('面板-总览'!D$2,'面板-景气指数'!$32:$32,0)) -> 0.66258333 | E10: =INDEX('面板-景气指数'!$33:$45,MATCH('面板-总览'!$A10,'面板-景气指数'!$J$33:$J$45,0),MATCH('面板-总览'!E$2,'面板-景气指数'!$32:$32,0)) -> 0.66975 | F10: =INDEX('面板-景气指数'!$33:$45,MATCH('面板-总览'!$A10,'面板-景气指数'!$J$33:$J$45,0),MATCH('面板-总览'!F$2,'面板-景气指数'!$32:$32,0)) -> 0.68066667 | G10: =INDEX('面板-景气指数'!$33:$45,MATCH('面板-总览'!$A10,'面板-景气指数'!$J$33:$J$45,0),MATCH('面板-总览'!G$2,'面板-景气指数'!$32:$32,0)) -> 0.70129167 | H10: =INDEX('面板-景气指数'!$33:$45,MATCH('面板-总览'!$A10,'面板-景气指数'!$J$33:$J$45,0),MATCH('面板-总览'!H$2,'面板-景气指数'!$32:$32,0)) -> 0.65024167 | I10: =INDEX('面板-景气指数'!$33:$45,MATCH('面板-总览'!$A10,'面板-景气指数'!$J$33:$J$45,0),MATCH('面板-总览'!I$2,'面板-景气指数'!$32:$32,0)) -> 0.66549167 | ... K10: =INDEX('面板-景气指数'!$33:$45,MATCH('面板-总览'!$A10,'面板-景气指数'!$J$33:$J$45,0),MATCH('面板-总览'!K$2,'面板-景气指数'!$32:$32,0)) -> 0.47654167 | L10: =INDEX('面板-景气指数'!$33:$46,MATCH('面板-总览'!$A10,'面板-景气指数'!$J$33:$J$46,0),MATCH('面板-总览'!L$2,'面板-景气指数'!$32:$32,0)) -> 0.46844167 | M10: =INDEX('面板-景气指数'!$33:$46,MATCH('面板-总览'!$A10,'面板-景气指数'!$J$33:$J$46,0),MATCH('面板-总览'!M$2,'面板-景气指数'!$32:$32,0)) -> 0.52689167 | N10: =INDEX('面板-景气指数'!$33:$46,MATCH('面板-总览'!$A10,'面板-景气指数'!$J$33:$J$46,0),MATCH('面板-总览'!N$2,'面板-景气指数'!$32:$32,0)) -> 0.51389167 | P10: =N10-L10 -> 0.04545 | R10: 10 | T10: 元宇宙下游 | U10: =INDEX('面板-景气指数'!$48:$84,MATCH('面板-总览'!$T10,'面板-景气指数'!$J$48:$J$84,0),MATCH('面板-总览'!U$2,'面板-景气指数'!$32:$32,0)) -> 0.337 | V10: =INDEX('面板-景气指数'!$48:$84,MATCH('面板-总览'!$T10,'面板-景气指数'!$J$48:$J$84,0),MATCH('面板-总览'!V$2,'面板-景气指数'!$32:$32,0)) -> 0.2505 | W10: =INDEX('面板-景气指数'!$48:$84,MATCH('面板-总览'!$T10,'面板-景气指数'!$J$48:$J$84,0),MATCH('面板-总览'!W$2,'面板-景气指数'!$32:$32,0)) -> 0.3045 | X10: =INDEX('面板-景气指数'!$48:$84,MATCH('面板-总览'!$T10,'面板-景气指数'!$J$48:$J$84,0),MATCH('面板-总览'!X$2,'面板-景气指数'!$32:$32,0)) -> 0.5255 | Y10: =INDEX('面板-景气指数'!$48:$84,MATCH('面板-总览'!$T10,'面板-景气指数'!$J$48:$J$84,0),MATCH('面板-总览'!Y$2,'面板-景气指数'!$32:$32,0)) -> 0.387 | Z10: =INDEX('面板-景气指数'!$48:$84,MATCH('面板-总览'!$T10,'面板-景气指数'!$J$48:$J$84,0),MATCH('面板-总览'!Z$2,'面板-景气指数'!$32:$32,0)) -> 0.1815 | AA10: =INDEX('面板-景气指数'!$48:$84,MATCH('面板-总览'!$T10,'面板-景气指数'!$J$48:$J$84,0),MATCH('面板-总览'!AA$2,'面板-景气指数'!$32:$32,0)) -> 0.119 | AB10: =INDEX('面板-景气指数'!$48:$84,MATCH('面板-总览'!$T10,'面板-景气指数'!$J$48:$J$84,0),MATCH('面板-总览'!AB$2,'面板-景气指数'!$32:$32,0)) -> 0.294 | ... AG10: =INDEX('面板-景气指数'!$48:$84,MATCH('面板-总览'!$T10,'面板-景气指数'!$J$48:$J$84,0),MATCH('面板-总览'!AG$2,'面板-景气指数'!$32:$32,0)) -> 0.242 | AI10: =AG10-AE10 -> -0.3055
A11: CXO | B11: =INDEX('面板-景气指数'!$33:$45,MATCH('面板-总览'!$A11,'面板-景气指数'!$J$33:$J$45,0),MATCH('面板-总览'!B$2,'面板-景气指数'!$32:$32,0)) -> 0.434375 | C11: =INDEX('面板-景气指数'!$33:$45,MATCH('面板-总览'!$A11,'面板-景气指数'!$J$33:$J$45,0),MATCH('面板-总览'!C$2,'面板-景气指数'!$32:$32,0)) -> 0.42325 | D11: =INDEX('面板-景气指数'!$33:$45,MATCH('面板-总览'!$A11,'面板-景气指数'!$J$33:$J$45,0),MATCH('面板-总览'!D$2,'面板-景气指数'!$32:$32,0)) -> 0.493875 | E11: =INDEX('面板-景气指数'!$33:$45,MATCH('面板-总览'!$A11,'面板-景气指数'!$J$33:$J$45,0),MATCH('面板-总览'!E$2,'面板-景气指数'!$32:$32,0)) -> 0.56425 | F11: =INDEX('面板-景气指数'!$33:$45,MATCH('面板-总览'!$A11,'面板-景气指数'!$J$33:$J$45,0),MATCH('面板-总览'!F$2,'面板-景气指数'!$32:$32,0)) -> 0.671875 | G11: =INDEX('面板-景气指数'!$33:$45,MATCH('面板-总览'!$A11,'面板-景气指数'!$J$33:$J$45,0),MATCH('面板-总览'!G$2,'面板-景气指数'!$32:$32,0)) -> 0.65925 | H11: =INDEX('面板-景气指数'!$33:$45,MATCH('面板-总览'!$A11,'面板-景气指数'!$J$33:$J$45,0),MATCH('面板-总览'!H$2,'面板-景气指数'!$32:$32,0)) -> 0.46825 | I11: =INDEX('面板-景气指数'!$33:$45,MATCH('面板-总览'!$A11,'面板-景气指数'!$J$33:$J$45,0),MATCH('面板-总览'!I$2,'面板-景气指数'!$32:$32,0)) -> 0.401875 | ... K11: =INDEX('面板-景气指数'!$33:$45,MATCH('面板-总览'!$A11,'面板-景气指数'!$J$33:$J$45,0),MATCH('面板-总览'!K$2,'面板-景气指数'!$32:$32,0)) -> 0.513 | L11: =INDEX('面板-景气指数'!$33:$46,MATCH('面板-总览'!$A11,'面板-景气指数'!$J$33:$J$46,0),MATCH('面板-总览'!L$2,'面板-景气指数'!$32:$32,0)) -> 0.701875 | M11: =INDEX('面板-景气指数'!$33:$46,MATCH('面板-总览'!$A11,'面板-景气指数'!$J$33:$J$46,0),MATCH('面板-总览'!M$2,'面板-景气指数'!$32:$32,0)) -> 0.736625 | N11: =INDEX('面板-景气指数'!$33:$46,MATCH('面板-总览'!$A11,'面板-景气指数'!$J$33:$J$46,0),MATCH('面板-总览'!N$2,'面板-景气指数'!$32:$32,0)) -> 0.748625 | P11: =N11-L11 -> 0.04675 | R11: -5 | T11: 光伏上游 | U11: =INDEX('面板-景气指数'!$48:$84,MATCH('面板-总览'!$T11,'面板-景气指数'!$J$48:$J$84,0),MATCH('面板-总览'!U$2,'面板-景气指数'!$32:$32,0)) -> 0.902 | V11: =INDEX('面板-景气指数'!$48:$84,MATCH('面板-总览'!$T11,'面板-景气指数'!$J$48:$J$84,0),MATCH('面板-总览'!V$2,'面板-景气指数'!$32:$32,0)) -> 0.91866667 | W11: =INDEX('面板-景气指数'!$48:$84,MATCH('面板-总览'!$T11,'面板-景气指数'!$J$48:$J$84,0),MATCH('面板-总览'!W$2,'面板-景气指数'!$32:$32,0)) -> 0.85283333 | X11: =INDEX('面板-景气指数'!$48:$84,MATCH('面板-总览'!$T11,'面板-景气指数'!$J$48:$J$84,0),MATCH('面板-总览'!X$2,'面板-景气指数'!$32:$32,0)) -> 0.80466667 | Y11: =INDEX('面板-景气指数'!$48:$84,MATCH('面板-总览'!$T11,'面板-景气指数'!$J$48:$J$84,0),MATCH('面板-总览'!Y$2,'面板-景气指数'!$32:$32,0)) -> 0.82633333 | Z11: =INDEX('面板-景气指数'!$48:$84,MATCH('面板-总览'!$T11,'面板-景气指数'!$J$48:$J$84,0),MATCH('面板-总览'!Z$2,'面板-景气指数'!$32:$32,0)) -> 0.77816667 | AA11: =INDEX('面板-景气指数'!$48:$84,MATCH('面板-总览'!$T11,'面板-景气指数'!$J$48:$J$84,0),MATCH('面板-总览'!AA$2,'面板-景气指数'!$32:$32,0)) -> 0.80233333 | AB11: =INDEX('面板-景气指数'!$48:$84,MATCH('面板-总览'!$T11,'面板-景气指数'!$J$48:$J$84,0),MATCH('面板-总览'!AB$2,'面板-景气指数'!$32:$32,0)) -> 0.79516667 | ... AG11: =INDEX('面板-景气指数'!$48:$84,MATCH('面板-总览'!$T11,'面板-景气指数'!$J$48:$J$84,0),MATCH('面板-总览'!AG$2,'面板-景气指数'!$32:$32,0)) -> 0.72233333 | AI11: =AG11-AE11 -> -0.065
A12: 智能汽车 | B12: =INDEX('面板-景气指数'!$33:$45,MATCH('面板-总览'!$A12,'面板-景气指数'!$J$33:$J$45,0),MATCH('面板-总览'!B$2,'面板-景气指数'!$32:$32,0)) -> 0.39216667 | C12: =INDEX('面板-景气指数'!$33:$45,MATCH('面板-总览'!$A12,'面板-景气指数'!$J$33:$J$45,0),MATCH('面板-总览'!C$2,'面板-景气指数'!$32:$32,0)) -> 0.5083 | D12: =INDEX('面板-景气指数'!$33:$45,MATCH('面板-总览'!$A12,'面板-景气指数'!$J$33:$J$45,0),MATCH('面板-总览'!D$2,'面板-景气指数'!$32:$32,0)) -> 0.47723333 | E12: =INDEX('面板-景气指数'!$33:$45,MATCH('面板-总览'!$A12,'面板-景气指数'!$J$33:$J$45,0),MATCH('面板-总览'!E$2,'面板-景气指数'!$32:$32,0)) -> 0.3686 | F12: =INDEX('面板-景气指数'!$33:$45,MATCH('面板-总览'!$A12,'面板-景气指数'!$J$33:$J$45,0),MATCH('面板-总览'!F$2,'面板-景气指数'!$32:$32,0)) -> 0.35543333 | G12: =INDEX('面板-景气指数'!$33:$45,MATCH('面板-总览'!$A12,'面板-景气指数'!$J$33:$J$45,0),MATCH('面板-总览'!G$2,'面板-景气指数'!$32:$32,0)) -> 0.3482 | H12: =INDEX('面板-景气指数'!$33:$45,MATCH('面板-总览'!$A12,'面板-景气指数'!$J$33:$J$45,0),MATCH('面板-总览'!H$2,'面板-景气指数'!$32:$32,0)) -> 0.2021 | I12: =INDEX('面板-景气指数'!$33:$45,MATCH('面板-总览'!$A12,'面板-景气指数'!$J$33:$J$45,0),MATCH('面板-总览'!I$2,'面板-景气指数'!$32:$32,0)) -> 0.14446667 | ... K12: =INDEX('面板-景气指数'!$33:$45,MATCH('面板-总览'!$A12,'面板-景气指数'!$J$33:$J$45,0),MATCH('面板-总览'!K$2,'面板-景气指数'!$32:$32,0)) -> 0.33976667 | L12: =INDEX('面板-景气指数'!$33:$46,MATCH('面板-总览'!$A12,'面板-景气指数'!$J$33:$J$46,0),MATCH('面板-总览'!L$2,'面板-景气指数'!$32:$32,0)) -> 0.40193333 | M12: =INDEX('面板-景气指数'!$33:$46,MATCH('面板-总览'!$A12,'面板-景气指数'!$J$33:$J$46,0),MATCH('面板-总览'!M$2,'面板-景气指数'!$32:$32,0)) -> 0.4704 | N12: =INDEX('面板-景气指数'!$33:$46,MATCH('面板-总览'!$A12,'面板-景气指数'!$J$33:$J$46,0),MATCH('面板-总览'!N$2,'面板-景气指数'!$32:$32,0)) -> 0.4704 | P12: =N12-L12 -> 0.068466667 | R12: 10 | T12: 光伏中游 | U12: =INDEX('面板-景气指数'!$48:$84,MATCH('面板-总览'!$T12,'面板-景气指数'!$J$48:$J$84,0),MATCH('面板-总览'!U$2,'面板-景气指数'!$32:$32,0)) -> 0.55925 | V12: =INDEX('面板-景气指数'!$48:$84,MATCH('面板-总览'!$T12,'面板-景气指数'!$J$48:$J$84,0),MATCH('面板-总览'!V$2,'面板-景气指数'!$32:$32,0)) -> 0.52233333 | W12: =INDEX('面板-景气指数'!$48:$84,MATCH('面板-总览'!$T12,'面板-景气指数'!$J$48:$J$84,0),MATCH('面板-总览'!W$2,'面板-景气指数'!$32:$32,0)) -> 0.48779167 | X12: =INDEX('面板-景气指数'!$48:$84,MATCH('面板-总览'!$T12,'面板-景气指数'!$J$48:$J$84,0),MATCH('面板-总览'!X$2,'面板-景气指数'!$32:$32,0)) -> 0.50804167 | Y12: =INDEX('面板-景气指数'!$48:$84,MATCH('面板-总览'!$T12,'面板-景气指数'!$J$48:$J$84,0),MATCH('面板-总览'!Y$2,'面板-景气指数'!$32:$32,0)) -> 0.857 | Z12: =INDEX('面板-景气指数'!$48:$84,MATCH('面板-总览'!$T12,'面板-景气指数'!$J$48:$J$84,0),MATCH('面板-总览'!Z$2,'面板-景气指数'!$32:$32,0)) -> 0.84108333 | AA12: =INDEX('面板-景气指数'!$48:$84,MATCH('面板-总览'!$T12,'面板-景气指数'!$J$48:$J$84,0),MATCH('面板-总览'!AA$2,'面板-景气指数'!$32:$32,0)) -> 0.84333333 | AB12: =INDEX('面板-景气指数'!$48:$84,MATCH('面板-总览'!$T12,'面板-景气指数'!$J$48:$J$84,0),MATCH('面板-总览'!AB$2,'面板-景气指数'!$32:$32,0)) -> 0.85270833 | ... AG12: =INDEX('面板-景气指数'!$48:$84,MATCH('面板-总览'!$T12,'面板-景气指数'!$J$48:$J$84,0),MATCH('面板-总览'!AG$2,'面板-景气指数'!$32:$32,0)) -> 0.756875 | AI12: =AG12-AE12 -> -0.045041667
A13: 航空装备 | B13: =INDEX('面板-景气指数'!$33:$45,MATCH('面板-总览'!$A13,'面板-景气指数'!$J$33:$J$45,0),MATCH('面板-总览'!B$2,'面板-景气指数'!$32:$32,0)) -> 0.83333333 | C13: =INDEX('面板-景气指数'!$33:$45,MATCH('面板-总览'!$A13,'面板-景气指数'!$J$33:$J$45,0),MATCH('面板-总览'!C$2,'面板-景气指数'!$32:$32,0)) -> 0.83988889 | D13: =INDEX('面板-景气指数'!$33:$45,MATCH('面板-总览'!$A13,'面板-景气指数'!$J$33:$J$45,0),MATCH('面板-总览'!D$2,'面板-景气指数'!$32:$32,0)) -> 0.68911111 | E13: =INDEX('面板-景气指数'!$33:$45,MATCH('面板-总览'!$A13,'面板-景气指数'!$J$33:$J$45,0),MATCH('面板-总览'!E$2,'面板-景气指数'!$32:$32,0)) -> 0.74377778 | F13: =INDEX('面板-景气指数'!$33:$45,MATCH('面板-总览'!$A13,'面板-景气指数'!$J$33:$J$45,0),MATCH('面板-总览'!F$2,'面板-景气指数'!$32:$32,0)) -> 0.77933333 | G13: =INDEX('面板-景气指数'!$33:$45,MATCH('面板-总览'!$A13,'面板-景气指数'!$J$33:$J$45,0),MATCH('面板-总览'!G$2,'面板-景气指数'!$32:$32,0)) -> 0.77088889 | H13: =INDEX('面板-景气指数'!$33:$45,MATCH('面板-总览'!$A13,'面板-景气指数'!$J$33:$J$45,0),MATCH('面板-总览'!H$2,'面板-景气指数'!$32:$32,0)) -> 0.74355556 | I13: =INDEX('面板-景气指数'!$33:$45,MATCH('面板-总览'!$A13,'面板-景气指数'!$J$33:$J$45,0),MATCH('面板-总览'!I$2,'面板-景气指数'!$32:$32,0)) -> 0.76122222 | ... K13: =INDEX('面板-景气指数'!$33:$45,MATCH('面板-总览'!$A13,'面板-景气指数'!$J$33:$J$45,0),MATCH('面板-总览'!K$2,'面板-景气指数'!$32:$32,0)) -> 0.69877778 | L13: =INDEX('面板-景气指数'!$33:$46,MATCH('面板-总览'!$A13,'面板-景气指数'!$J$33:$J$46,0),MATCH('面板-总览'!L$2,'面板-景气指数'!$32:$32,0)) -> 0.70188889 | M13: =INDEX('面板-景气指数'!$33:$46,MATCH('面板-总览'!$A13,'面板-景气指数'!$J$33:$J$46,0),MATCH('面板-总览'!M$2,'面板-景气指数'!$32:$32,0)) -> 0.65577778 | N13: =INDEX('面板-景气指数'!$33:$46,MATCH('面板-总览'!$A13,'面板-景气指数'!$J$33:$J$46,0),MATCH('面板-总览'!N$2,'面板-景气指数'!$32:$32,0)) -> 0.64288889 | P13: =N13-L13 -> -0.059 | R13: -5 | T13: 光伏下游 | U13: =INDEX('面板-景气指数'!$48:$84,MATCH('面板-总览'!$T13,'面板-景气指数'!$J$48:$J$84,0),MATCH('面板-总览'!U$2,'面板-景气指数'!$32:$32,0)) -> 0.2455 | V13: =INDEX('面板-景气指数'!$48:$84,MATCH('面板-总览'!$T13,'面板-景气指数'!$J$48:$J$84,0),MATCH('面板-总览'!V$2,'面板-景气指数'!$32:$32,0)) -> 0.2555 | W13: =INDEX('面板-景气指数'!$48:$84,MATCH('面板-总览'!$T13,'面板-景气指数'!$J$48:$J$84,0),MATCH('面板-总览'!W$2,'面板-景气指数'!$32:$32,0)) -> 0.3 | X13: =INDEX('面板-景气指数'!$48:$84,MATCH('面板-总览'!$T13,'面板-景气指数'!$J$48:$J$84,0),MATCH('面板-总览'!X$2,'面板-景气指数'!$32:$32,0)) -> 0.3 | Y13: =INDEX('面板-景气指数'!$48:$84,MATCH('面板-总览'!$T13,'面板-景气指数'!$J$48:$J$84,0),MATCH('面板-总览'!Y$2,'面板-景气指数'!$32:$32,0)) -> 0.136 | Z13: =INDEX('面板-景气指数'!$48:$84,MATCH('面板-总览'!$T13,'面板-景气指数'!$J$48:$J$84,0),MATCH('面板-总览'!Z$2,'面板-景气指数'!$32:$32,0)) -> 0.077 | AA13: =INDEX('面板-景气指数'!$48:$84,MATCH('面板-总览'!$T13,'面板-景气指数'!$J$48:$J$84,0),MATCH('面板-总览'!AA$2,'面板-景气指数'!$32:$32,0)) -> 0.3625 | AB13: =INDEX('面板-景气指数'!$48:$84,MATCH('面板-总览'!$T13,'面板-景气指数'!$J$48:$J$84,0),MATCH('面板-总览'!AB$2,'面板-景气指数'!$32:$32,0)) -> 0.588 | ... AG13: =INDEX('面板-景气指数'!$48:$84,MATCH('面板-总览'!$T13,'面板-景气指数'!$J$48:$J$84,0),MATCH('面板-总览'!AG$2,'面板-景气指数'!$32:$32,0)) -> 0.6765 | AI13: =AG13-AE13 -> 0.0365
A14: 物联网 | B14: =INDEX('面板-景气指数'!$33:$45,MATCH('面板-总览'!$A14,'面板-景气指数'!$J$33:$J$45,0),MATCH('面板-总览'!B$2,'面板-景气指数'!$32:$32,0)) -> 0.59146429 | C14: =INDEX('面板-景气指数'!$33:$45,MATCH('面板-总览'!$A14,'面板-景气指数'!$J$33:$J$45,0),MATCH('面板-总览'!C$2,'面板-景气指数'!$32:$32,0)) -> 0.56239286 | D14: =INDEX('面板-景气指数'!$33:$45,MATCH('面板-总览'!$A14,'面板-景气指数'!$J$33:$J$45,0),MATCH('面板-总览'!D$2,'面板-景气指数'!$32:$32,0)) -> 0.54221429 | E14: =INDEX('面板-景气指数'!$33:$45,MATCH('面板-总览'!$A14,'面板-景气指数'!$J$33:$J$45,0),MATCH('面板-总览'!E$2,'面板-景气指数'!$32:$32,0)) -> 0.52757143 | F14: =INDEX('面板-景气指数'!$33:$45,MATCH('面板-总览'!$A14,'面板-景气指数'!$J$33:$J$45,0),MATCH('面板-总览'!F$2,'面板-景气指数'!$32:$32,0)) -> 0.51010714 | G14: =INDEX('面板-景气指数'!$33:$45,MATCH('面板-总览'!$A14,'面板-景气指数'!$J$33:$J$45,0),MATCH('面板-总览'!G$2,'面板-景气指数'!$32:$32,0)) -> 0.44432143 | H14: =INDEX('面板-景气指数'!$33:$45,MATCH('面板-总览'!$A14,'面板-景气指数'!$J$33:$J$45,0),MATCH('面板-总览'!H$2,'面板-景气指数'!$32:$32,0)) -> 0.42064286 | I14: =INDEX('面板-景气指数'!$33:$45,MATCH('面板-总览'!$A14,'面板-景气指数'!$J$33:$J$45,0),MATCH('面板-总览'!I$2,'面板-景气指数'!$32:$32,0)) -> 0.39935714 | ... K14: =INDEX('面板-景气指数'!$33:$45,MATCH('面板-总览'!$A14,'面板-景气指数'!$J$33:$J$45,0),MATCH('面板-总览'!K$2,'面板-景气指数'!$32:$32,0)) -> 0.50096429 | L14: =INDEX('面板-景气指数'!$33:$46,MATCH('面板-总览'!$A14,'面板-景气指数'!$J$33:$J$46,0),MATCH('面板-总览'!L$2,'面板-景气指数'!$32:$32,0)) -> 0.54610714 | M14: =INDEX('面板-景气指数'!$33:$46,MATCH('面板-总览'!$A14,'面板-景气指数'!$J$33:$J$46,0),MATCH('面板-总览'!M$2,'面板-景气指数'!$32:$32,0)) -> 0.41403571 | N14: =INDEX('面板-景气指数'!$33:$46,MATCH('面板-总览'!$A14,'面板-景气指数'!$J$33:$J$46,0),MATCH('面板-总览'!N$2,'面板-景气指数'!$32:$32,0)) -> 0.46982143 | P14: =N14-L14 -> -0.076285714 | R14: 10 | T14: 风电上游 | U14: =INDEX('面板-景气指数'!$48:$84,MATCH('面板-总览'!$T14,'面板-景气指数'!$J$48:$J$84,0),MATCH('面板-总览'!U$2,'面板-景气指数'!$32:$32,0)) -> 0.86733333 | V14: =INDEX('面板-景气指数'!$48:$84,MATCH('面板-总览'!$T14,'面板-景气指数'!$J$48:$J$84,0),MATCH('面板-总览'!V$2,'面板-景气指数'!$32:$32,0)) -> 0.82466667 | W14: =INDEX('面板-景气指数'!$48:$84,MATCH('面板-总览'!$T14,'面板-景气指数'!$J$48:$J$84,0),MATCH('面板-总览'!W$2,'面板-景气指数'!$32:$32,0)) -> 0.549 | X14: =INDEX('面板-景气指数'!$48:$84,MATCH('面板-总览'!$T14,'面板-景气指数'!$J$48:$J$84,0),MATCH('面板-总览'!X$2,'面板-景气指数'!$32:$32,0)) -> 0.63733333 | Y14: =INDEX('面板-景气指数'!$48:$84,MATCH('面板-总览'!$T14,'面板-景气指数'!$J$48:$J$84,0),MATCH('面板-总览'!Y$2,'面板-景气指数'!$32:$32,0)) -> 0.71366667 | Z14: =INDEX('面板-景气指数'!$48:$84,MATCH('面板-总览'!$T14,'面板-景气指数'!$J$48:$J$84,0),MATCH('面板-总览'!Z$2,'面板-景气指数'!$32:$32,0)) -> 0.69266667 | AA14: =INDEX('面板-景气指数'!$48:$84,MATCH('面板-总览'!$T14,'面板-景气指数'!$J$48:$J$84,0),MATCH('面板-总览'!AA$2,'面板-景气指数'!$32:$32,0)) -> 0.64933333 | AB14: =INDEX('面板-景气指数'!$48:$84,MATCH('面板-总览'!$T14,'面板-景气指数'!$J$48:$J$84,0),MATCH('面板-总览'!AB$2,'面板-景气指数'!$32:$32,0)) -> 0.628 | ... AG14: =INDEX('面板-景气指数'!$48:$84,MATCH('面板-总览'!$T14,'面板-景气指数'!$J$48:$J$84,0),MATCH('面板-总览'!AG$2,'面板-景气指数'!$32:$32,0)) -> 0.55433333 | AI14: =AG14-AE14 -> -0.061333333
A15: 医美-化妆品 | B15: =INDEX('面板-景气指数'!$33:$45,MATCH('面板-总览'!$A15,'面板-景气指数'!$J$33:$J$45,0),MATCH('面板-总览'!B$2,'面板-景气指数'!$32:$32,0)) -> 0.436375 | C15: =INDEX('面板-景气指数'!$33:$45,MATCH('面板-总览'!$A15,'面板-景气指数'!$J$33:$J$45,0),MATCH('面板-总览'!C$2,'面板-景气指数'!$32:$32,0)) -> 0.37 | D15: =INDEX('面板-景气指数'!$33:$45,MATCH('面板-总览'!$A15,'面板-景气指数'!$J$33:$J$45,0),MATCH('面板-总览'!D$2,'面板-景气指数'!$32:$32,0)) -> 0.33175 | E15: =INDEX('面板-景气指数'!$33:$45,MATCH('面板-总览'!$A15,'面板-景气指数'!$J$33:$J$45,0),MATCH('面板-总览'!E$2,'面板-景气指数'!$32:$32,0)) -> 0.320875 | F15: =INDEX('面板-景气指数'!$33:$45,MATCH('面板-总览'!$A15,'面板-景气指数'!$J$33:$J$45,0),MATCH('面板-总览'!F$2,'面板-景气指数'!$32:$32,0)) -> 0.31925 | G15: =INDEX('面板-景气指数'!$33:$45,MATCH('面板-总览'!$A15,'面板-景气指数'!$J$33:$J$45,0),MATCH('面板-总览'!G$2,'面板-景气指数'!$32:$32,0)) -> 0.332125 | H15: =INDEX('面板-景气指数'!$33:$45,MATCH('面板-总览'!$A15,'面板-景气指数'!$J$33:$J$45,0),MATCH('面板-总览'!H$2,'面板-景气指数'!$32:$32,0)) -> 0.258 | I15: =INDEX('面板-景气指数'!$33:$45,MATCH('面板-总览'!$A15,'面板-景气指数'!$J$33:$J$45,0),MATCH('面板-总览'!I$2,'面板-景气指数'!$32:$32,0)) -> 0.231375 | ... K15: =INDEX('面板-景气指数'!$33:$45,MATCH('面板-总览'!$A15,'面板-景气指数'!$J$33:$J$45,0),MATCH('面板-总览'!K$2,'面板-景气指数'!$32:$32,0)) -> 0.223375 | L15: =INDEX('面板-景气指数'!$33:$46,MATCH('面板-总览'!$A15,'面板-景气指数'!$J$33:$J$46,0),MATCH('面板-总览'!L$2,'面板-景气指数'!$32:$32,0)) -> 0.248625 | M15: =INDEX('面板-景气指数'!$33:$46,MATCH('面板-总览'!$A15,'面板-景气指数'!$J$33:$J$46,0),MATCH('面板-总览'!M$2,'面板-景气指数'!$32:$32,0)) -> 0.281125 | N15: =INDEX('面板-景气指数'!$33:$46,MATCH('面板-总览'!$A15,'面板-景气指数'!$J$33:$J$46,0),MATCH('面板-总览'!N$2,'面板-景气指数'!$32:$32,0)) -> 0.288625 | P15: =N15-L15 -> 0.04 | R15: 10 | T15: 风电中游 | U15: =INDEX('面板-景气指数'!$48:$84,MATCH('面板-总览'!$T15,'面板-景气指数'!$J$48:$J$84,0),MATCH('面板-总览'!U$2,'面板-景气指数'!$32:$32,0)) -> 0.34011765 | V15: =INDEX('面板-景气指数'!$48:$84,MATCH('面板-总览'!$T15,'面板-景气指数'!$J$48:$J$84,0),MATCH('面板-总览'!V$2,'面板-景气指数'!$32:$32,0)) -> 0.25608824 | W15: =INDEX('面板-景气指数'!$48:$84,MATCH('面板-总览'!$T15,'面板-景气指数'!$J$48:$J$84,0),MATCH('面板-总览'!W$2,'面板-景气指数'!$32:$32,0)) -> 0.22852941 | X15: =INDEX('面板-景气指数'!$48:$84,MATCH('面板-总览'!$T15,'面板-景气指数'!$J$48:$J$84,0),MATCH('面板-总览'!X$2,'面板-景气指数'!$32:$32,0)) -> 0.23620588 | Y15: =INDEX('面板-景气指数'!$48:$84,MATCH('面板-总览'!$T15,'面板-景气指数'!$J$48:$J$84,0),MATCH('面板-总览'!Y$2,'面板-景气指数'!$32:$32,0)) -> 0.51326471 | Z15: =INDEX('面板-景气指数'!$48:$84,MATCH('面板-总览'!$T15,'面板-景气指数'!$J$48:$J$84,0),MATCH('面板-总览'!Z$2,'面板-景气指数'!$32:$32,0)) -> 0.44270588 | AA15: =INDEX('面板-景气指数'!$48:$84,MATCH('面板-总览'!$T15,'面板-景气指数'!$J$48:$J$84,0),MATCH('面板-总览'!AA$2,'面板-景气指数'!$32:$32,0)) -> 0.42023529 | AB15: =INDEX('面板-景气指数'!$48:$84,MATCH('面板-总览'!$T15,'面板-景气指数'!$J$48:$J$84,0),MATCH('面板-总览'!AB$2,'面板-景气指数'!$32:$32,0)) -> 0.41682353 | ... AG15: =INDEX('面板-景气指数'!$48:$84,MATCH('面板-总览'!$T15,'面板-景气指数'!$J$48:$J$84,0),MATCH('面板-总览'!AG$2,'面板-景气指数'!$32:$32,0)) -> 0.36176471 | AI15: =AG15-AE15 -> 0.016176471
A16: 储能 | B16: =INDEX('面板-景气指数'!$33:$46,MATCH('面板-总览'!$A16,'面板-景气指数'!$J$33:$J$46,0),MATCH('面板-总览'!B$2,'面板-景气指数'!$32:$32,0)) -> 0.562625 | C16: =INDEX('面板-景气指数'!$33:$46,MATCH('面板-总览'!$A16,'面板-景气指数'!$J$33:$J$46,0),MATCH('面板-总览'!C$2,'面板-景气指数'!$32:$32,0)) -> 0.52458333 | D16: =INDEX('面板-景气指数'!$33:$46,MATCH('面板-总览'!$A16,'面板-景气指数'!$J$33:$J$46,0),MATCH('面板-总览'!D$2,'面板-景气指数'!$32:$32,0)) -> 0.41141667 | E16: =INDEX('面板-景气指数'!$33:$46,MATCH('面板-总览'!$A16,'面板-景气指数'!$J$33:$J$46,0),MATCH('面板-总览'!E$2,'面板-景气指数'!$32:$32,0)) -> 0.43079167 | F16: =INDEX('面板-景气指数'!$33:$46,MATCH('面板-总览'!$A16,'面板-景气指数'!$J$33:$J$46,0),MATCH('面板-总览'!F$2,'面板-景气指数'!$32:$32,0)) -> 0.601 | G16: =INDEX('面板-景气指数'!$33:$46,MATCH('面板-总览'!$A16,'面板-景气指数'!$J$33:$J$46,0),MATCH('面板-总览'!G$2,'面板-景气指数'!$32:$32,0)) -> 0.77683333 | H16: =INDEX('面板-景气指数'!$33:$46,MATCH('面板-总览'!$A16,'面板-景气指数'!$J$33:$J$46,0),MATCH('面板-总览'!H$2,'面板-景气指数'!$32:$32,0)) -> 0.749875 | I16: =INDEX('面板-景气指数'!$33:$46,MATCH('面板-总览'!$A16,'面板-景气指数'!$J$33:$J$46,0),MATCH('面板-总览'!I$2,'面板-景气指数'!$32:$32,0)) -> 0.71775 | ... N16: =INDEX('面板-景气指数'!$33:$46,MATCH('面板-总览'!$A16,'面板-景气指数'!$J$33:$J$46,0),MATCH('面板-总览'!N$2,'面板-景气指数'!$32:$32,0)) -> 0.61483333 | P16: =N16-L16 -> -0.01025 | R16: 10 | T16: 风电下游 | U16: =INDEX('面板-景气指数'!$48:$84,MATCH('面板-总览'!$T16,'面板-景气指数'!$J$48:$J$84,0),MATCH('面板-总览'!U$2,'面板-景气指数'!$32:$32,0)) -> 0.56166667 | V16: =INDEX('面板-景气指数'!$48:$84,MATCH('面板-总览'!$T16,'面板-景气指数'!$J$48:$J$84,0),MATCH('面板-总览'!V$2,'面板-景气指数'!$32:$32,0)) -> 0.65866667 | W16: =INDEX('面板-景气指数'!$48:$84,MATCH('面板-总览'!$T16,'面板-景气指数'!$J$48:$J$84,0),MATCH('面板-总览'!W$2,'面板-景气指数'!$32:$32,0)) -> 0.66366667 | X16: =INDEX('面板-景气指数'!$48:$84,MATCH('面板-总览'!$T16,'面板-景气指数'!$J$48:$J$84,0),MATCH('面板-总览'!X$2,'面板-景气指数'!$32:$32,0)) -> 0.52833333 | Y16: =INDEX('面板-景气指数'!$48:$84,MATCH('面板-总览'!$T16,'面板-景气指数'!$J$48:$J$84,0),MATCH('面板-总览'!Y$2,'面板-景气指数'!$32:$32,0)) -> 0.21933333 | Z16: =INDEX('面板-景气指数'!$48:$84,MATCH('面板-总览'!$T16,'面板-景气指数'!$J$48:$J$84,0),MATCH('面板-总览'!Z$2,'面板-景气指数'!$32:$32,0)) -> 0.067333333 | AA16: =INDEX('面板-景气指数'!$48:$84,MATCH('面板-总览'!$T16,'面板-景气指数'!$J$48:$J$84,0),MATCH('面板-总览'!AA$2,'面板-景气指数'!$32:$32,0)) -> 0.081666667 | AB16: =INDEX('面板-景气指数'!$48:$84,MATCH('面板-总览'!$T16,'面板-景气指数'!$J$48:$J$84,0),MATCH('面板-总览'!AB$2,'面板-景气指数'!$32:$32,0)) -> 0.28066667 | ... AG16: =INDEX('面板-景气指数'!$48:$84,MATCH('面板-总览'!$T16,'面板-景气指数'!$J$48:$J$84,0),MATCH('面板-总览'!AG$2,'面板-景气指数'!$32:$32,0)) -> 0.544 | AI16: =AG16-AE16 -> 0.083
T17: 半导体上游 | U17: =INDEX('面板-景气指数'!$48:$84,MATCH('面板-总览'!$T17,'面板-景气指数'!$J$48:$J$84,0),MATCH('面板-总览'!U$2,'面板-景气指数'!$32:$32,0)) -> 0.47341667 | V17: =INDEX('面板-景气指数'!$48:$84,MATCH('面板-总览'!$T17,'面板-景气指数'!$J$48:$J$84,0),MATCH('面板-总览'!V$2,'面板-景气指数'!$32:$32,0)) -> 0.59825 | W17: =INDEX('面板-景气指数'!$48:$84,MATCH('面板-总览'!$T17,'面板-景气指数'!$J$48:$J$84,0),MATCH('面板-总览'!W$2,'面板-景气指数'!$32:$32,0)) -> 0.61925 | X17: =INDEX('面板-景气指数'!$48:$84,MATCH('面板-总览'!$T17,'面板-景气指数'!$J$48:$J$84,0),MATCH('面板-总览'!X$2,'面板-景气指数'!$32:$32,0)) -> 0.58883333 | Y17: =INDEX('面板-景气指数'!$48:$84,MATCH('面板-总览'!$T17,'面板-景气指数'!$J$48:$J$84,0),MATCH('面板-总览'!Y$2,'面板-景气指数'!$32:$32,0)) -> 0.53241667 | Z17: =INDEX('面板-景气指数'!$48:$84,MATCH('面板-总览'!$T17,'面板-景气指数'!$J$48:$J$84,0),MATCH('面板-总览'!Z$2,'面板-景气指数'!$32:$32,0)) -> 0.41233333 | AA17: =INDEX('面板-景气指数'!$48:$84,MATCH('面板-总览'!$T17,'面板-景气指数'!$J$48:$J$84,0),MATCH('面板-总览'!AA$2,'面板-景气指数'!$32:$32,0)) -> 0.32883333 | AB17: =INDEX('面板-景气指数'!$48:$84,MATCH('面板-总览'!$T17,'面板-景气指数'!$J$48:$J$84,0),MATCH('面板-总览'!AB$2,'面板-景气指数'!$32:$32,0)) -> 0.45666667 | ... AG17: =INDEX('面板-景气指数'!$48:$84,MATCH('面板-总览'!$T17,'面板-景气指数'!$J$48:$J$84,0),MATCH('面板-总览'!AG$2,'面板-景气指数'!$32:$32,0)) -> 0.359 | AI17: =AG17-AE17 -> -0.1835
T18: 半导体中游 | U18: =INDEX('面板-景气指数'!$48:$84,MATCH('面板-总览'!$T18,'面板-景气指数'!$J$48:$J$84,0),MATCH('面板-总览'!U$2,'面板-景气指数'!$32:$32,0)) -> 0.586 | V18: =INDEX('面板-景气指数'!$48:$84,MATCH('面板-总览'!$T18,'面板-景气指数'!$J$48:$J$84,0),MATCH('面板-总览'!V$2,'面板-景气指数'!$32:$32,0)) -> 0.603 | W18: =INDEX('面板-景气指数'!$48:$84,MATCH('面板-总览'!$T18,'面板-景气指数'!$J$48:$J$84,0),MATCH('面板-总览'!W$2,'面板-景气指数'!$32:$32,0)) -> 0.61872727 | X18: =INDEX('面板-景气指数'!$48:$84,MATCH('面板-总览'!$T18,'面板-景气指数'!$J$48:$J$84,0),MATCH('面板-总览'!X$2,'面板-景气指数'!$32:$32,0)) -> 0.58972727 | Y18: =INDEX('面板-景气指数'!$48:$84,MATCH('面板-总览'!$T18,'面板-景气指数'!$J$48:$J$84,0),MATCH('面板-总览'!Y$2,'面板-景气指数'!$32:$32,0)) -> 0.58854545 | Z18: =INDEX('面板-景气指数'!$48:$84,MATCH('面板-总览'!$T18,'面板-景气指数'!$J$48:$J$84,0),MATCH('面板-总览'!Z$2,'面板-景气指数'!$32:$32,0)) -> 0.59772727 | AA18: =INDEX('面板-景气指数'!$48:$84,MATCH('面板-总览'!$T18,'面板-景气指数'!$J$48:$J$84,0),MATCH('面板-总览'!AA$2,'面板-景气指数'!$32:$32,0)) -> 0.46327273 | AB18: =INDEX('面板-景气指数'!$48:$84,MATCH('面板-总览'!$T18,'面板-景气指数'!$J$48:$J$84,0),MATCH('面板-总览'!AB$2,'面板-景气指数'!$32:$32,0)) -> 0.44481818 | ... AG18: =INDEX('面板-景气指数'!$48:$84,MATCH('面板-总览'!$T18,'面板-景气指数'!$J$48:$J$84,0),MATCH('面板-总览'!AG$2,'面板-景气指数'!$32:$32,0)) -> 0.20536364 | AI18: =AG18-AE18 -> -0.085090909
T19: 数字基建上游 | U19: =INDEX('面板-景气指数'!$48:$84,MATCH('面板-总览'!$T19,'面板-景气指数'!$J$48:$J$84,0),MATCH('面板-总览'!U$2,'面板-景气指数'!$32:$32,0)) -> 0.65182051 | V19: =INDEX('面板-景气指数'!$48:$84,MATCH('面板-总览'!$T19,'面板-景气指数'!$J$48:$J$84,0),MATCH('面板-总览'!V$2,'面板-景气指数'!$32:$32,0)) -> 0.64751282 | W19: =INDEX('面板-景气指数'!$48:$84,MATCH('面板-总览'!$T19,'面板-景气指数'!$J$48:$J$84,0),MATCH('面板-总览'!W$2,'面板-景气指数'!$32:$32,0)) -> 0.66633333 | X19: =INDEX('面板-景气指数'!$48:$84,MATCH('面板-总览'!$T19,'面板-景气指数'!$J$48:$J$84,0),MATCH('面板-总览'!X$2,'面板-景气指数'!$32:$32,0)) -> 0.68838462 | Y19: =INDEX('面板-景气指数'!$48:$84,MATCH('面板-总览'!$T19,'面板-景气指数'!$J$48:$J$84,0),MATCH('面板-总览'!Y$2,'面板-景气指数'!$32:$32,0)) -> 0.67658974 | Z19: =INDEX('面板-景气指数'!$48:$84,MATCH('面板-总览'!$T19,'面板-景气指数'!$J$48:$J$84,0),MATCH('面板-总览'!Z$2,'面板-景气指数'!$32:$32,0)) -> 0.7125641 | AA19: =INDEX('面板-景气指数'!$48:$84,MATCH('面板-总览'!$T19,'面板-景气指数'!$J$48:$J$84,0),MATCH('面板-总览'!AA$2,'面板-景气指数'!$32:$32,0)) -> 0.64548718 | AB19: =INDEX('面板-景气指数'!$48:$84,MATCH('面板-总览'!$T19,'面板-景气指数'!$J$48:$J$84,0),MATCH('面板-总览'!AB$2,'面板-景气指数'!$32:$32,0)) -> 0.67010256 | ... AG19: =INDEX('面板-景气指数'!$48:$84,MATCH('面板-总览'!$T19,'面板-景气指数'!$J$48:$J$84,0),MATCH('面板-总览'!AG$2,'面板-景气指数'!$32:$32,0)) -> 0.33579487 | AI19: =AG19-AE19 -> -0.037871795
T20: 数字基建中游 | U20: =INDEX('面板-景气指数'!$48:$84,MATCH('面板-总览'!$T20,'面板-景气指数'!$J$48:$J$84,0),MATCH('面板-总览'!U$2,'面板-景气指数'!$32:$32,0)) -> 0.52733333 | V20: =INDEX('面板-景气指数'!$48:$84,MATCH('面板-总览'!$T20,'面板-景气指数'!$J$48:$J$84,0),MATCH('面板-总览'!V$2,'面板-景气指数'!$32:$32,0)) -> 0.35066667 | W20: =INDEX('面板-景气指数'!$48:$84,MATCH('面板-总览'!$T20,'面板-景气指数'!$J$48:$J$84,0),MATCH('面板-总览'!W$2,'面板-景气指数'!$32:$32,0)) -> 0.775 | X20: =INDEX('面板-景气指数'!$48:$84,MATCH('面板-总览'!$T20,'面板-景气指数'!$J$48:$J$84,0),MATCH('面板-总览'!X$2,'面板-景气指数'!$32:$32,0)) -> 0.775 | Y20: =INDEX('面板-景气指数'!$48:$84,MATCH('面板-总览'!$T20,'面板-景气指数'!$J$48:$J$84,0),MATCH('面板-总览'!Y$2,'面板-景气指数'!$32:$32,0)) -> 0.81433333 | Z20: =INDEX('面板-景气指数'!$48:$84,MATCH('面板-总览'!$T20,'面板-景气指数'!$J$48:$J$84,0),MATCH('面板-总览'!Z$2,'面板-景气指数'!$32:$32,0)) -> 0.833 | AA20: =INDEX('面板-景气指数'!$48:$84,MATCH('面板-总览'!$T20,'面板-景气指数'!$J$48:$J$84,0),MATCH('面板-总览'!AA$2,'面板-景气指数'!$32:$32,0)) -> 0.755 | AB20: =INDEX('面板-景气指数'!$48:$84,MATCH('面板-总览'!$T20,'面板-景气指数'!$J$48:$J$84,0),MATCH('面板-总览'!AB$2,'面板-景气指数'!$32:$32,0)) -> 0.77433333 | ... AG20: =INDEX('面板-景气指数'!$48:$84,MATCH('面板-总览'!$T20,'面板-景气指数'!$J$48:$J$84,0),MATCH('面板-总览'!AG$2,'面板-景气指数'!$32:$32,0)) -> 0.779 | AI20: =AG20-AE20 -> 0.199
T21: 数字基建下游 | U21: =INDEX('面板-景气指数'!$48:$84,MATCH('面板-总览'!$T21,'面板-景气指数'!$J$48:$J$84,0),MATCH('面板-总览'!U$2,'面板-景气指数'!$32:$32,0)) -> 0.50788889 | V21: =INDEX('面板-景气指数'!$48:$84,MATCH('面板-总览'!$T21,'面板-景气指数'!$J$48:$J$84,0),MATCH('面板-总览'!V$2,'面板-景气指数'!$32:$32,0)) -> 0.50788889 | W21: =INDEX('面板-景气指数'!$48:$84,MATCH('面板-总览'!$T21,'面板-景气指数'!$J$48:$J$84,0),MATCH('面板-总览'!W$2,'面板-景气指数'!$32:$32,0)) -> 0.518 | X21: =INDEX('面板-景气指数'!$48:$84,MATCH('面板-总览'!$T21,'面板-景气指数'!$J$48:$J$84,0),MATCH('面板-总览'!X$2,'面板-景气指数'!$32:$32,0)) -> 0.518 | Y21: =INDEX('面板-景气指数'!$48:$84,MATCH('面板-总览'!$T21,'面板-景气指数'!$J$48:$J$84,0),MATCH('面板-总览'!Y$2,'面板-景气指数'!$32:$32,0)) -> 0.518 | Z21: =INDEX('面板-景气指数'!$48:$84,MATCH('面板-总览'!$T21,'面板-景气指数'!$J$48:$J$84,0),MATCH('面板-总览'!Z$2,'面板-景气指数'!$32:$32,0)) -> 0.52444444 | AA21: =INDEX('面板-景气指数'!$48:$84,MATCH('面板-总览'!$T21,'面板-景气指数'!$J$48:$J$84,0),MATCH('面板-总览'!AA$2,'面板-景气指数'!$32:$32,0)) -> 0.52444444 | AB21: =INDEX('面板-景气指数'!$48:$84,MATCH('面板-总览'!$T21,'面板-景气指数'!$J$48:$J$84,0),MATCH('面板-总览'!AB$2,'面板-景气指数'!$32:$32,0)) -> 0.52444444 | ... AG21: =INDEX('面板-景气指数'!$48:$84,MATCH('面板-总览'!$T21,'面板-景气指数'!$J$48:$J$84,0),MATCH('面板-总览'!AG$2,'面板-景气指数'!$32:$32,0)) -> 0.37544444 | AI21: =AG21-AE21 -> -0.056222222
T22: CXO上游 | U22: =INDEX('面板-景气指数'!$48:$84,MATCH('面板-总览'!$T22,'面板-景气指数'!$J$48:$J$84,0),MATCH('面板-总览'!U$2,'面板-景气指数'!$32:$32,0)) -> 0.3042 | V22: =INDEX('面板-景气指数'!$48:$84,MATCH('面板-总览'!$T22,'面板-景气指数'!$J$48:$J$84,0),MATCH('面板-总览'!V$2,'面板-景气指数'!$32:$32,0)) -> 0.2864 | W22: =INDEX('面板-景气指数'!$48:$84,MATCH('面板-总览'!$T22,'面板-景气指数'!$J$48:$J$84,0),MATCH('面板-总览'!W$2,'面板-景气指数'!$32:$32,0)) -> 0.3904 | X22: =INDEX('面板-景气指数'!$48:$84,MATCH('面板-总览'!$T22,'面板-景气指数'!$J$48:$J$84,0),MATCH('面板-总览'!X$2,'面板-景气指数'!$32:$32,0)) -> 0.503 | Y22: =INDEX('面板-景气指数'!$48:$84,MATCH('面板-总览'!$T22,'面板-景气指数'!$J$48:$J$84,0),MATCH('面板-总览'!Y$2,'面板-景气指数'!$32:$32,0)) -> 0.6752 | Z22: =INDEX('面板-景气指数'!$48:$84,MATCH('面板-总览'!$T22,'面板-景气指数'!$J$48:$J$84,0),MATCH('面板-总览'!Z$2,'面板-景气指数'!$32:$32,0)) -> 0.649 | AA22: =INDEX('面板-景气指数'!$48:$84,MATCH('面板-总览'!$T22,'面板-景气指数'!$J$48:$J$84,0),MATCH('面板-总览'!AA$2,'面板-景气指数'!$32:$32,0)) -> 0.3434 | AB22: =INDEX('面板-景气指数'!$48:$84,MATCH('面板-总览'!$T22,'面板-景气指数'!$J$48:$J$84,0),MATCH('面板-总览'!AB$2,'面板-景气指数'!$32:$32,0)) -> 0.2372 | ... AG22: =INDEX('面板-景气指数'!$48:$84,MATCH('面板-总览'!$T22,'面板-景气指数'!$J$48:$J$84,0),MATCH('面板-总览'!AG$2,'面板-景气指数'!$32:$32,0)) -> 0.822 | AI22: =AG22-AE22 -> 0.078
T23: CXO中游 | U23: =INDEX('面板-景气指数'!$48:$84,MATCH('面板-总览'!$T23,'面板-景气指数'!$J$48:$J$84,0),MATCH('面板-总览'!U$2,'面板-景气指数'!$32:$32,0)) -> 0.65133333 | V23: =INDEX('面板-景气指数'!$48:$84,MATCH('面板-总览'!$T23,'面板-景气指数'!$J$48:$J$84,0),MATCH('面板-总览'!V$2,'面板-景气指数'!$32:$32,0)) -> 0.65133333 | W23: =INDEX('面板-景气指数'!$48:$84,MATCH('面板-总览'!$T23,'面板-景气指数'!$J$48:$J$84,0),MATCH('面板-总览'!W$2,'面板-景气指数'!$32:$32,0)) -> 0.66633333 | X23: =INDEX('面板-景气指数'!$48:$84,MATCH('面板-总览'!$T23,'面板-景气指数'!$J$48:$J$84,0),MATCH('面板-总览'!X$2,'面板-景气指数'!$32:$32,0)) -> 0.66633333 | Y23: =INDEX('面板-景气指数'!$48:$84,MATCH('面板-总览'!$T23,'面板-景气指数'!$J$48:$J$84,0),MATCH('面板-总览'!Y$2,'面板-景气指数'!$32:$32,0)) -> 0.66633333 | Z23: =INDEX('面板-景气指数'!$48:$84,MATCH('面板-总览'!$T23,'面板-景气指数'!$J$48:$J$84,0),MATCH('面板-总览'!Z$2,'面板-景气指数'!$32:$32,0)) -> 0.67633333 | AA23: =INDEX('面板-景气指数'!$48:$84,MATCH('面板-总览'!$T23,'面板-景气指数'!$J$48:$J$84,0),MATCH('面板-总览'!AA$2,'面板-景气指数'!$32:$32,0)) -> 0.67633333 | AB23: =INDEX('面板-景气指数'!$48:$84,MATCH('面板-总览'!$T23,'面板-景气指数'!$J$48:$J$84,0),MATCH('面板-总览'!AB$2,'面板-景气指数'!$32:$32,0)) -> 0.67633333 | ... AG23: =INDEX('面板-景气指数'!$48:$84,MATCH('面板-总览'!$T23,'面板-景气指数'!$J$48:$J$84,0),MATCH('面板-总览'!AG$2,'面板-景气指数'!$32:$32,0)) -> 0.62633333 | AI23: =AG23-AE23 -> -0.0053333333
T24: 智能汽车上游 | U24: =INDEX('面板-景气指数'!$48:$84,MATCH('面板-总览'!$T24,'面板-景气指数'!$J$48:$J$84,0),MATCH('面板-总览'!U$2,'面板-景气指数'!$32:$32,0)) -> 0.44925 | V24: =INDEX('面板-景气指数'!$48:$84,MATCH('面板-总览'!$T24,'面板-景气指数'!$J$48:$J$84,0),MATCH('面板-总览'!V$2,'面板-景气指数'!$32:$32,0)) -> 0.45875 | W24: =INDEX('面板-景气指数'!$48:$84,MATCH('面板-总览'!$T24,'面板-景气指数'!$J$48:$J$84,0),MATCH('面板-总览'!W$2,'面板-景气指数'!$32:$32,0)) -> 0.44575 | X24: =INDEX('面板-景气指数'!$48:$84,MATCH('面板-总览'!$T24,'面板-景气指数'!$J$48:$J$84,0),MATCH('面板-总览'!X$2,'面板-景气指数'!$32:$32,0)) -> 0.4695 | Y24: =INDEX('面板-景气指数'!$48:$84,MATCH('面板-总览'!$T24,'面板-景气指数'!$J$48:$J$84,0),MATCH('面板-总览'!Y$2,'面板-景气指数'!$32:$32,0)) -> 0.5085 | Z24: =INDEX('面板-景气指数'!$48:$84,MATCH('面板-总览'!$T24,'面板-景气指数'!$J$48:$J$84,0),MATCH('面板-总览'!Z$2,'面板-景气指数'!$32:$32,0)) -> 0.51475 | AA24: =INDEX('面板-景气指数'!$48:$84,MATCH('面板-总览'!$T24,'面板-景气指数'!$J$48:$J$84,0),MATCH('面板-总览'!AA$2,'面板-景气指数'!$32:$32,0)) -> 0.472 | AB24: =INDEX('面板-景气指数'!$48:$84,MATCH('面板-总览'!$T24,'面板-景气指数'!$J$48:$J$84,0),MATCH('面板-总览'!AB$2,'面板-景气指数'!$32:$32,0)) -> 0.50175 | ... AG24: =INDEX('面板-景气指数'!$48:$84,MATCH('面板-总览'!$T24,'面板-景气指数'!$J$48:$J$84,0),MATCH('面板-总览'!AG$2,'面板-景气指数'!$32:$32,0)) -> 0.56625 | AI24: =AG24-AE24 -> 0.08075
T25: 智能汽车中游 | U25: =INDEX('面板-景气指数'!$48:$84,MATCH('面板-总览'!$T25,'面板-景气指数'!$J$48:$J$84,0),MATCH('面板-总览'!U$2,'面板-景气指数'!$32:$32,0)) -> 0.41118182 | V25: =INDEX('面板-景气指数'!$48:$84,MATCH('面板-总览'!$T25,'面板-景气指数'!$J$48:$J$84,0),MATCH('面板-总览'!V$2,'面板-景气指数'!$32:$32,0)) -> 0.43536364 | W25: =INDEX('面板-景气指数'!$48:$84,MATCH('面板-总览'!$T25,'面板-景气指数'!$J$48:$J$84,0),MATCH('面板-总览'!W$2,'面板-景气指数'!$32:$32,0)) -> 0.56127273 | X25: =INDEX('面板-景气指数'!$48:$84,MATCH('面板-总览'!$T25,'面板-景气指数'!$J$48:$J$84,0),MATCH('面板-总览'!X$2,'面板-景气指数'!$32:$32,0)) -> 0.62863636 | Y25: =INDEX('面板-景气指数'!$48:$84,MATCH('面板-总览'!$T25,'面板-景气指数'!$J$48:$J$84,0),MATCH('面板-总览'!Y$2,'面板-景气指数'!$32:$32,0)) -> 0.66172727 | Z25: =INDEX('面板-景气指数'!$48:$84,MATCH('面板-总览'!$T25,'面板-景气指数'!$J$48:$J$84,0),MATCH('面板-总览'!Z$2,'面板-景气指数'!$32:$32,0)) -> 0.59745455 | AA25: =INDEX('面板-景气指数'!$48:$84,MATCH('面板-总览'!$T25,'面板-景气指数'!$J$48:$J$84,0),MATCH('面板-总览'!AA$2,'面板-景气指数'!$32:$32,0)) -> 0.33863636 | AB25: =INDEX('面板-景气指数'!$48:$84,MATCH('面板-总览'!$T25,'面板-景气指数'!$J$48:$J$84,0),MATCH('面板-总览'!AB$2,'面板-景气指数'!$32:$32,0)) -> 0.21154545 | ... AG25: =INDEX('面板-景气指数'!$48:$84,MATCH('面板-总览'!$T25,'面板-景气指数'!$J$48:$J$84,0),MATCH('面板-总览'!AG$2,'面板-景气指数'!$32:$32,0)) -> 0.37472727 | AI25: =AG25-AE25 -> -0.090818182
T26: 智能汽车下游 | U26: =INDEX('面板-景气指数'!$48:$84,MATCH('面板-总览'!$T26,'面板-景气指数'!$J$48:$J$84,0),MATCH('面板-总览'!U$2,'面板-景气指数'!$32:$32,0)) -> 0.363 | V26: =INDEX('面板-景气指数'!$48:$84,MATCH('面板-总览'!$T26,'面板-景气指数'!$J$48:$J$84,0),MATCH('面板-总览'!V$2,'面板-景气指数'!$32:$32,0)) -> 0.575 | W26: =INDEX('面板-景气指数'!$48:$84,MATCH('面板-总览'!$T26,'面板-景气指数'!$J$48:$J$84,0),MATCH('面板-总览'!W$2,'面板-景气指数'!$32:$32,0)) -> 0.424 | X26: =INDEX('面板-景气指数'!$48:$84,MATCH('面板-总览'!$T26,'面板-景气指数'!$J$48:$J$84,0),MATCH('面板-总览'!X$2,'面板-景气指数'!$32:$32,0)) -> 0.151 | Y26: =INDEX('面板-景气指数'!$48:$84,MATCH('面板-总览'!$T26,'面板-景气指数'!$J$48:$J$84,0),MATCH('面板-总览'!Y$2,'面板-景气指数'!$32:$32,0)) -> 0.09 | Z26: =INDEX('面板-景气指数'!$48:$84,MATCH('面板-总览'!$T26,'面板-景气指数'!$J$48:$J$84,0),MATCH('面板-总览'!Z$2,'面板-景气指数'!$32:$32,0)) -> 0.121 | AA26: =INDEX('面板-景气指数'!$48:$84,MATCH('面板-总览'!$T26,'面板-景气指数'!$J$48:$J$84,0),MATCH('面板-总览'!AA$2,'面板-景气指数'!$32:$32,0)) -> 0.03 | AB26: =INDEX('面板-景气指数'!$48:$84,MATCH('面板-总览'!$T26,'面板-景气指数'!$J$48:$J$84,0),MATCH('面板-总览'!AB$2,'面板-景气指数'!$32:$32,0)) -> 0 | ... AG26: =INDEX('面板-景气指数'!$48:$84,MATCH('面板-总览'!$T26,'面板-景气指数'!$J$48:$J$84,0),MATCH('面板-总览'!AG$2,'面板-景气指数'!$32:$32,0)) -> 0.515 | AI26: =AG26-AE26 -> 0.182
T27: 航空装备上游 | U27: =INDEX('面板-景气指数'!$48:$84,MATCH('面板-总览'!$T27,'面板-景气指数'!$J$48:$J$84,0),MATCH('面板-总览'!U$2,'面板-景气指数'!$32:$32,0)) -> 0.88675 | V27: =INDEX('面板-景气指数'!$48:$84,MATCH('面板-总览'!$T27,'面板-景气指数'!$J$48:$J$84,0),MATCH('面板-总览'!V$2,'面板-景气指数'!$32:$32,0)) -> 0.9015 | W27: =INDEX('面板-景气指数'!$48:$84,MATCH('面板-总览'!$T27,'面板-景气指数'!$J$48:$J$84,0),MATCH('面板-总览'!W$2,'面板-景气指数'!$32:$32,0)) -> 0.74525 | X27: =INDEX('面板-景气指数'!$48:$84,MATCH('面板-总览'!$T27,'面板-景气指数'!$J$48:$J$84,0),MATCH('面板-总览'!X$2,'面板-景气指数'!$32:$32,0)) -> 0.86825 | Y27: =INDEX('面板-景气指数'!$48:$84,MATCH('面板-总览'!$T27,'面板-景气指数'!$J$48:$J$84,0),MATCH('面板-总览'!Y$2,'面板-景气指数'!$32:$32,0)) -> 0.94825 | Z27: =INDEX('面板-景气指数'!$48:$84,MATCH('面板-总览'!$T27,'面板-景气指数'!$J$48:$J$84,0),MATCH('面板-总览'!Z$2,'面板-景气指数'!$32:$32,0)) -> 0.933 | AA27: =INDEX('面板-景气指数'!$48:$84,MATCH('面板-总览'!$T27,'面板-景气指数'!$J$48:$J$84,0),MATCH('面板-总览'!AA$2,'面板-景气指数'!$32:$32,0)) -> 0.8715 | AB27: =INDEX('面板-景气指数'!$48:$84,MATCH('面板-总览'!$T27,'面板-景气指数'!$J$48:$J$84,0),MATCH('面板-总览'!AB$2,'面板-景气指数'!$32:$32,0)) -> 0.91125 | ... AG27: =INDEX('面板-景气指数'!$48:$84,MATCH('面板-总览'!$T27,'面板-景气指数'!$J$48:$J$84,0),MATCH('面板-总览'!AG$2,'面板-景气指数'!$32:$32,0)) -> 0.809 | AI27: =AG27-AE27 -> -0.06925
T28: 航空装备中游 | U28: =INDEX('面板-景气指数'!$48:$84,MATCH('面板-总览'!$T28,'面板-景气指数'!$J$48:$J$84,0),MATCH('面板-总览'!U$2,'面板-景气指数'!$32:$32,0)) -> 0.85775 | V28: =INDEX('面板-景气指数'!$48:$84,MATCH('面板-总览'!$T28,'面板-景气指数'!$J$48:$J$84,0),MATCH('面板-总览'!V$2,'面板-景气指数'!$32:$32,0)) -> 0.85775 | W28: =INDEX('面板-景气指数'!$48:$84,MATCH('面板-总览'!$T28,'面板-景气指数'!$J$48:$J$84,0),MATCH('面板-总览'!W$2,'面板-景气指数'!$32:$32,0)) -> 0.727 | X28: =INDEX('面板-景气指数'!$48:$84,MATCH('面板-总览'!$T28,'面板-景气指数'!$J$48:$J$84,0),MATCH('面板-总览'!X$2,'面板-景气指数'!$32:$32,0)) -> 0.727 | Y28: =INDEX('面板-景气指数'!$48:$84,MATCH('面板-总览'!$T28,'面板-景气指数'!$J$48:$J$84,0),MATCH('面板-总览'!Y$2,'面板-景气指数'!$32:$32,0)) -> 0.727 | Z28: =INDEX('面板-景气指数'!$48:$84,MATCH('面板-总览'!$T28,'面板-景气指数'!$J$48:$J$84,0),MATCH('面板-总览'!Z$2,'面板-景气指数'!$32:$32,0)) -> 0.74575 | AA28: =INDEX('面板-景气指数'!$48:$84,MATCH('面板-总览'!$T28,'面板-景气指数'!$J$48:$J$84,0),MATCH('面板-总览'!AA$2,'面板-景气指数'!$32:$32,0)) -> 0.74575 | AB28: =INDEX('面板-景气指数'!$48:$84,MATCH('面板-总览'!$T28,'面板-景气指数'!$J$48:$J$84,0),MATCH('面板-总览'!AB$2,'面板-景气指数'!$32:$32,0)) -> 0.74575 | ... AG28: =INDEX('面板-景气指数'!$48:$84,MATCH('面板-总览'!$T28,'面板-景气指数'!$J$48:$J$84,0),MATCH('面板-总览'!AG$2,'面板-景气指数'!$32:$32,0)) -> 0.52575 | AI28: =AG28-AE28 -> -0.056
... T38: 储能下游 | U38: =INDEX('面板-景气指数'!$48:$84,MATCH('面板-总览'!$T38,'面板-景气指数'!$J$48:$J$84,0),MATCH('面板-总览'!U$2,'面板-景气指数'!$32:$32,0)) -> 0.60041667 | V38: =INDEX('面板-景气指数'!$48:$84,MATCH('面板-总览'!$T38,'面板-景气指数'!$J$48:$J$84,0),MATCH('面板-总览'!V$2,'面板-景气指数'!$32:$32,0)) -> 0.50725 | W38: =INDEX('面板-景气指数'!$48:$84,MATCH('面板-总览'!$T38,'面板-景气指数'!$J$48:$J$84,0),MATCH('面板-总览'!W$2,'面板-景气指数'!$32:$32,0)) -> 0.41516667 | X38: =INDEX('面板-景气指数'!$48:$84,MATCH('面板-总览'!$T38,'面板-景气指数'!$J$48:$J$84,0),MATCH('面板-总览'!X$2,'面板-景气指数'!$32:$32,0)) -> 0.43333333 | Y38: =INDEX('面板-景气指数'!$48:$84,MATCH('面板-总览'!$T38,'面板-景气指数'!$J$48:$J$84,0),MATCH('面板-总览'!Y$2,'面板-景气指数'!$32:$32,0)) -> 0.7725 | Z38: =INDEX('面板-景气指数'!$48:$84,MATCH('面板-总览'!$T38,'面板-景气指数'!$J$48:$J$84,0),MATCH('面板-总览'!Z$2,'面板-景气指数'!$32:$32,0)) -> 0.82358333 | AA38: =INDEX('面板-景气指数'!$48:$84,MATCH('面板-总览'!$T38,'面板-景气指数'!$J$48:$J$84,0),MATCH('面板-总览'!AA$2,'面板-景气指数'!$32:$32,0)) -> 0.80366667 | AB38: =INDEX('面板-景气指数'!$48:$84,MATCH('面板-总览'!$T38,'面板-景气指数'!$J$48:$J$84,0),MATCH('面板-总览'!AB$2,'面板-景气指数'!$32:$32,0)) -> 0.78691667 | ... AG38: =INDEX('面板-景气指数'!$48:$84,MATCH('面板-总览'!$T38,'面板-景气指数'!$J$48:$J$84,0),MATCH('面板-总览'!AG$2,'面板-景气指数'!$32:$32,0)) -> 0.66725 | AI38: =AG38-AE38 -> 0.037

Sheet 面板-景气指数
L32: Pct chg | M32: 44865 | N32: 44834 | O32: 44804 | P32: 44773 | Q32: 44742 | R32: 44712 | S32: 44681 | T32: 44651 | U32: 44620 | V32: 44592 | W32: 44561 | X32: 44530 | Y32: 44500 | Z32: 44469 | AA32: 44439 | AB32: 44408 | AC32: 44377 | AD32: 44347 | AE32: 44316 | AF32: 44286 | AG32: 44255 | AH32: 44227 | AI32: 44196 | AJ32: 44165 | AK32: 44135 | AL32: 44104 | AM32: 44074 | AN32: 44043 | AO32: 44012 | AP32: 43982 | AQ32: 43951 | AR32: 43921 | AS32: 43890 | AT32: 43861 | AU32: 43830 | AV32: 43799 | AW32: 43769 | AX32: 43738 | AY32: 43708 | AZ32: 43677 | BA32: 43646 | BB32: 43616 | BC32: 43585 | BD32: 43555 | BE32: 43524 | BF32: 43496 | BG32: 43465 | BH32: 43434 | BI32: 43404 | BJ32: 43373 | BK32: 43343 | BL32: 43312 | BM32: 43281 | BN32: 43251 | BO32: 43220 | BP32: 43190 | BQ32: 43159 | BR32: 43131 | BS32: 43100 | BT32: 43069 | BU32: 43039 | BV32: 43008 | BW32: 42978 | BX32: 42947 | BY32: 42916 | BZ32: 42886 | CA32: 42855 | CB32: 42825 | CC32: 42794 | CD32: 42766
J33: 锂电 | K33: 2C | L33: =(M33-O33)*100 -> -5.6131579 | M33: {=SUMPRODUCT(('面板-分位数'!$A$3:$A$178='面板-景气指数'!$J33)*('面板-分位数'!$E$3:$E$178)*('面板-分位数'!G$3:G$178))} -> 0.60357895 | N33: {=SUMPRODUCT(('面板-分位数'!$A$3:$A$178='面板-景气指数'!$J33)*('面板-分位数'!$E$3:$E$178)*('面板-分位数'!H$3:H$178))} -> 0.60428947 | O33: {=SUMPRODUCT(('面板-分位数'!$A$3:$A$178='面板-景气指数'!$J33)*('面板-分位数'!$E$3:$E$178)*('面板-分位数'!I$3:I$178))} -> 0.65971053 | P33: {=SUMPRODUCT(('面板-分位数'!$A$3:$A$178='面板-景气指数'!$J33)*('面板-分位数'!$E$3:$E$178)*('面板-分位数'!J$3:J$178))} -> 0.68705263 | Q33: {=SUMPRODUCT(('面板-分位数'!$A$3:$A$178='面板-景气指数'!$J33)*('面板-分位数'!$E$3:$E$178)*('面板-分位数'!K$3:K$178))} -> 0.67594737 | R33: {=SUMPRODUCT(('面板-分位数'!$A$3:$A$178='面板-景气指数'!$J33)*('面板-分位数'!$E$3:$E$178)*('面板-分位数'!L$3:L$178))} -> 0.613 | S33: {=SUMPRODUCT(('面板-分位数'!$A$3:$A$178='面板-景气指数'!$J33)*('面板-分位数'!$E$3:$E$178)*('面板-分位数'!M$3:M$178))} -> 0.70592105 | T33: {=SUMPRODUCT(('面板-分位数'!$A$3:$A$178='面板-景气指数'!$J33)*('面板-分位数'!$E$3:$E$178)*('面板-分位数'!N$3:N$178))} -> 0.82213158 | ... CD33: {=SUMPRODUCT(('面板-分位数'!$A$3:$A$178='面板-景气指数'!$J33)*('面板-分位数'!$E$3:$E$178)*('面板-分位数'!BX$3:BX$178))} -> 0.25781579
J34: 机器人 | K34: 2B | L34: =(M34-O34)*100 -> -0.375 | M34: {=SUMPRODUCT(('面板-分位数'!$A$3:$A$178='面板-景气指数'!$J34)*('面板-分位数'!$E$3:$E$178)*('面板-分位数'!G$3:G$178))} -> 0.3645 | N34: {=SUMPRODUCT(('面板-分位数'!$A$3:$A$178='面板-景气指数'!$J34)*('面板-分位数'!$E$3:$E$178)*('面板-分位数'!H$3:H$178))} -> 0.36575 | O34: {=SUMPRODUCT(('面板-分位数'!$A$3:$A$178='面板-景气指数'!$J34)*('面板-分位数'!$E$3:$E$178)*('面板-分位数'!I$3:I$178))} -> 0.36825 | P34: {=SUMPRODUCT(('面板-分位数'!$A$3:$A$178='面板-景气指数'!$J34)*('面板-分位数'!$E$3:$E$178)*('面板-分位数'!J$3:J$178))} -> 0.42275 | Q34: {=SUMPRODUCT(('面板-分位数'!$A$3:$A$178='面板-景气指数'!$J34)*('面板-分位数'!$E$3:$E$178)*('面板-分位数'!K$3:K$178))} -> 0.346 | R34: {=SUMPRODUCT(('面板-分位数'!$A$3:$A$178='面板-景气指数'!$J34)*('面板-分位数'!$E$3:$E$178)*('面板-分位数'!L$3:L$178))} -> 0.1995 | S34: {=SUMPRODUCT(('面板-分位数'!$A$3:$A$178='面板-景气指数'!$J34)*('面板-分位数'!$E$3:$E$178)*('面板-分位数'!M$3:M$178))} -> 0.36208333 | T34: {=SUMPRODUCT(('面板-分位数'!$A$3:$A$178='面板-景气指数'!$J34)*('面板-分位数'!$E$3:$E$178)*('面板-分位数'!N$3:N$178))} -> 0.58466667 | ... CD34: {=SUMPRODUCT(('面板-分位数'!$A$3:$A$178='面板-景气指数'!$J34)*('面板-分位数'!$E$3:$E$178)*('面板-分位数'!BX$3:BX$178))} -> 0.45833333
J35: 机床 | K35: 2B | L35: =(M35-O35)*100 -> 4.6916667 | M35: {=SUMPRODUCT(('面板-分位数'!$A$3:$A$178='面板-景气指数'!$J35)*('面板-分位数'!$E$3:$E$178)*('面板-分位数'!G$3:G$178))} -> 0.43658333 | N35: {=SUMPRODUCT(('面板-分位数'!$A$3:$A$178='面板-景气指数'!$J35)*('面板-分位数'!$E$3:$E$178)*('面板-分位数'!H$3:H$178))} -> 0.43658333 | O35: {=SUMPRODUCT(('面板-分位数'!$A$3:$A$178='面板-景气指数'!$J35)*('面板-分位数'!$E$3:$E$178)*('面板-分位数'!I$3:I$178))} -> 0.38966667 | P35: {=SUMPRODUCT(('面板-分位数'!$A$3:$A$178='面板-景气指数'!$J35)*('面板-分位数'!$E$3:$E$178)*('面板-分位数'!J$3:J$178))} -> 0.32616667 | Q35: {=SUMPRODUCT(('面板-分位数'!$A$3:$A$178='面板-景气指数'!$J35)*('面板-分位数'!$E$3:$E$178)*('面板-分位数'!K$3:K$178))} -> 0.47116667 | R35: {=SUMPRODUCT(('面板-分位数'!$A$3:$A$178='面板-景气指数'!$J35)*('面板-分位数'!$E$3:$E$178)*('面板-分位数'!L$3:L$178))} -> 0.44725 | S35: {=SUMPRODUCT(('面板-分位数'!$A$3:$A$178='面板-景气指数'!$J35)*('面板-分位数'!$E$3:$E$178)*('面板-分位数'!M$3:M$178))} -> 0.431 | T35: {=SUMPRODUCT(('面板-分位数'!$A$3:$A$178='面板-景气指数'!$J35)*('面板-分位数'!$E$3:$E$178)*('面板-分位数'!N$3:N$178))} -> 0.60166667 | ... CD35: {=SUMPRODUCT(('面板-分位数'!$A$3:$A$178='面板-景气指数'!$J35)*('面板-分位数'!$E$3:$E$178)*('面板-分位数'!BX$3:BX$178))} -> 0.4055
J36: 元宇宙 | K36: 2C | L36: =(M36-O36)*100 -> -48.6375 | M36: {=SUMPRODUCT(('面板-分位数'!$A$3:$A$178='面板-景气指数'!$J36)*('面板-分位数'!$E$3:$E$178)*('面板-分位数'!G$3:G$178))} -> 0.185625 | N36: {=SUMPRODUCT(('面板-分位数'!$A$3:$A$178='面板-景气指数'!$J36)*('面板-分位数'!$E$3:$E$178)*('面板-分位数'!H$3:H$178))} -> 0.199875 | O36: {=SUMPRODUCT(('面板-分位数'!$A$3:$A$178='面板-景气指数'!$J36)*('面板-分位数'!$E$3:$E$178)*('面板-分位数'!I$3:I$178))} -> 0.672 | P36: {=SUMPRODUCT(('面板-分位数'!$A$3:$A$178='面板-景气指数'!$J36)*('面板-分位数'!$E$3:$E$178)*('面板-分位数'!J$3:J$178))} -> 0.685875 | Q36: {=SUMPRODUCT(('面板-分位数'!$A$3:$A$178='面板-景气指数'!$J36)*('面板-分位数'!$E$3:$E$178)*('面板-分位数'!K$3:K$178))} -> 0.618375 | R36: {=SUMPRODUCT(('面板-分位数'!$A$3:$A$178='面板-景气指数'!$J36)*('面板-分位数'!$E$3:$E$178)*('面板-分位数'!L$3:L$178))} -> 0.468375 | S36: {=SUMPRODUCT(('面板-分位数'!$A$3:$A$178='面板-景气指数'!$J36)*('面板-分位数'!$E$3:$E$178)*('面板-分位数'!M$3:M$178))} -> 0.449875 | T36: {=SUMPRODUCT(('面板-分位数'!$A$3:$A$178='面板-景气指数'!$J36)*('面板-分位数'!$E$3:$E$178)*('面板-分位数'!N$3:N$178))} -> 0.464 | ... CD36: {=SUMPRODUCT(('面板-分位数'!$A$3:$A$178='面板-景气指数'!$J36)*('面板-分位数'!$E$3:$E$178)*('面板-分位数'!BX$3:BX$178))} -> 0.544375
J37: 光伏 | K37: 2G | L37: =(M37-O37)*100 -> -4.36875 | M37: {=SUMPRODUCT(('面板-分位数'!$A$3:$A$178='面板-景气指数'!$J37)*('面板-分位数'!$E$3:$E$178)*('面板-分位数'!G$3:G$178))} -> 0.745375 | N37: {=SUMPRODUCT(('面板-分位数'!$A$3:$A$178='面板-景气指数'!$J37)*('面板-分位数'!$E$3:$E$178)*('面板-分位数'!H$3:H$178))} -> 0.7465 | O37: {=SUMPRODUCT(('面板-分位数'!$A$3:$A$178='面板-景气指数'!$J37)*('面板-分位数'!$E$3:$E$178)*('面板-分位数'!I$3:I$178))} -> 0.7890625 | P37: {=SUMPRODUCT(('面板-分位数'!$A$3:$A$178='面板-景气指数'!$J37)*('面板-分位数'!$E$3:$E$178)*('面板-分位数'!J$3:J$178))} -> 0.811875 | Q37: {=SUMPRODUCT(('面板-分位数'!$A$3:$A$178='面板-景气指数'!$J37)*('面板-分位数'!$E$3:$E$178)*('面板-分位数'!K$3:K$178))} -> 0.824625 | R37: {=SUMPRODUCT(('面板-分位数'!$A$3:$A$178='面板-景气指数'!$J37)*('面板-分位数'!$E$3:$E$178)*('面板-分位数'!L$3:L$178))} -> 0.825375 | S37: {=SUMPRODUCT(('面板-分位数'!$A$3:$A$178='面板-景气指数'!$J37)*('面板-分位数'!$E$3:$E$178)*('面板-分位数'!M$3:M$178))} -> 0.80559375 | T37: {=SUMPRODUCT(('面板-分位数'!$A$3:$A$178='面板-景气指数'!$J37)*('面板-分位数'!$E$3:$E$178)*('面板-分位数'!N$3:N$178))} -> 0.78153125 | ... CD37: {=SUMPRODUCT(('面板-分位数'!$A$3:$A$178='面板-景气指数'!$J37)*('面板-分位数'!$E$3:$E$178)*('面板-分位数'!BX$3:BX$178))} -> 0.4974375
J38: 风电 | K38: 2G | L38: =(M38-O38)*100 -> 1.4326923 | M38: {=SUMPRODUCT(('面板-分位数'!$A$3:$A$178='面板-景气指数'!$J38)*('面板-分位数'!$E$3:$E$178)*('面板-分位数'!G$3:G$178))} -> 0.42663462 | N38: {=SUMPRODUCT(('面板-分位数'!$A$3:$A$178='面板-景气指数'!$J38)*('面板-分位数'!$E$3:$E$178)*('面板-分位数'!H$3:H$178))} -> 0.41907692 | O38: {=SUMPRODUCT(('面板-分位数'!$A$3:$A$178='面板-景气指数'!$J38)*('面板-分位数'!$E$3:$E$178)*('面板-分位数'!I$3:I$178))} -> 0.41230769 | P38: {=SUMPRODUCT(('面板-分位数'!$A$3:$A$178='面板-景气指数'!$J38)*('面板-分位数'!$E$3:$E$178)*('面板-分位数'!J$3:J$178))} -> 0.37986538 | Q38: {=SUMPRODUCT(('面板-分位数'!$A$3:$A$178='面板-景气指数'!$J38)*('面板-分位数'!$E$3:$E$178)*('面板-分位数'!K$3:K$178))} -> 0.39523077 | R38: {=SUMPRODUCT(('面板-分位数'!$A$3:$A$178='面板-景气指数'!$J38)*('面板-分位数'!$E$3:$E$178)*('面板-分位数'!L$3:L$178))} -> 0.42980769 | S38: {=SUMPRODUCT(('面板-分位数'!$A$3:$A$178='面板-景气指数'!$J38)*('面板-分位数'!$E$3:$E$178)*('面板-分位数'!M$3:M$178))} -> 0.40128846 | T38: {=SUMPRODUCT(('面板-分位数'!$A$3:$A$178='面板-景气指数'!$J38)*('面板-分位数'!$E$3:$E$178)*('面板-分位数'!N$3:N$178))} -> 0.421 | ... CD38: {=SUMPRODUCT(('面板-分位数'!$A$3:$A$178='面板-景气指数'!$J38)*('面板-分位数'!$E$3:$E$178)*('面板-分位数'!BX$3:BX$178))} -> 0.62178846
J39: 半导体 | K39: 2B | L39: =(M39-O39)*100 -> -6.4717391 | M39: {=SUMPRODUCT(('面板-分位数'!$A$3:$A$178='面板-景气指数'!$J39)*('面板-分位数'!$E$3:$E$178)*('面板-分位数'!G$3:G$178))} -> 0.19676087 | N39: {=SUMPRODUCT(('面板-分位数'!$A$3:$A$178='面板-景气指数'!$J39)*('面板-分位数'!$E$3:$E$178)*('面板-分位数'!H$3:H$178))} -> 0.19802174 | O39: {=SUMPRODUCT(('面板-分位数'!$A$3:$A$178='面板-景气指数'!$J39)*('面板-分位数'!$E$3:$E$178)*('面板-分位数'!I$3:I$178))} -> 0.26147826 | P39: {=SUMPRODUCT(('面板-分位数'!$A$3:$A$178='面板-景气指数'!$J39)*('面板-分位数'!$E$3:$E$178)*('面板-分位数'!J$3:J$178))} -> 0.30642391 | Q39: {=SUMPRODUCT(('面板-分位数'!$A$3:$A$178='面板-景气指数'!$J39)*('面板-分位数'!$E$3:$E$178)*('面板-分位数'!K$3:K$178))} -> 0.36916304 | R39: {=SUMPRODUCT(('面板-分位数'!$A$3:$A$178='面板-景气指数'!$J39)*('面板-分位数'!$E$3:$E$178)*('面板-分位数'!L$3:L$178))} -> 0.39575 | S39: {=SUMPRODUCT(('面板-分位数'!$A$3:$A$178='面板-景气指数'!$J39)*('面板-分位数'!$E$3:$E$178)*('面板-分位数'!M$3:M$178))} -> 0.41781522 | T39: {=SUMPRODUCT(('面板-分位数'!$A$3:$A$178='面板-景气指数'!$J39)*('面板-分位数'!$E$3:$E$178)*('面板-分位数'!N$3:N$178))} -> 0.519 | ... CD39: {=SUMPRODUCT(('面板-分位数'!$A$3:$A$178='面板-景气指数'!$J39)*('面板-分位数'!$E$3:$E$178)*('面板-分位数'!BX$3:BX$178))} -> 0.5393587
J40: 数字基建 | K40: 2B | L40: =(M40-O40)*100 -> 4.545 | M40: {=SUMPRODUCT(('面板-分位数'!$A$3:$A$178='面板-景气指数'!$J40)*('面板-分位数'!$E$3:$E$178)*('面板-分位数'!G$3:G$178))} -> 0.51389167 | N40: {=SUMPRODUCT(('面板-分位数'!$A$3:$A$178='面板-景气指数'!$J40)*('面板-分位数'!$E$3:$E$178)*('面板-分位数'!H$3:H$178))} -> 0.52689167 | O40: {=SUMPRODUCT(('面板-分位数'!$A$3:$A$178='面板-景气指数'!$J40)*('面板-分位数'!$E$3:$E$178)*('面板-分位数'!I$3:I$178))} -> 0.46844167 | P40: {=SUMPRODUCT(('面板-分位数'!$A$3:$A$178='面板-景气指数'!$J40)*('面板-分位数'!$E$3:$E$178)*('面板-分位数'!J$3:J$178))} -> 0.47654167 | Q40: {=SUMPRODUCT(('面板-分位数'!$A$3:$A$178='面板-景气指数'!$J40)*('面板-分位数'!$E$3:$E$178)*('面板-分位数'!K$3:K$178))} -> 0.50830833 | R40: {=SUMPRODUCT(('面板-分位数'!$A$3:$A$178='面板-景气指数'!$J40)*('面板-分位数'!$E$3:$E$178)*('面板-分位数'!L$3:L$178))} -> 0.66549167 | S40: {=SUMPRODUCT(('面板-分位数'!$A$3:$A$178='面板-景气指数'!$J40)*('面板-分位数'!$E$3:$E$178)*('面板-分位数'!M$3:M$178))} -> 0.65024167 | T40: {=SUMPRODUCT(('面板-分位数'!$A$3:$A$178='面板-景气指数'!$J40)*('面板-分位数'!$E$3:$E$178)*('面板-分位数'!N$3:N$178))} -> 0.70129167 | ... CD40: {=SUMPRODUCT(('面板-分位数'!$A$3:$A$178='面板-景气指数'!$J40)*('面板-分位数'!$E$3:$E$178)*('面板-分位数'!BX$3:BX$178))} -> 0.4828
J41: CXO | K41: 2B | L41: =(M41-O41)*100 -> 4.675 | M41: {=SUMPRODUCT(('面板-分位数'!$A$3:$A$178='面板-景气指数'!$J41)*('面板-分位数'!$E$3:$E$178)*('面板-分位数'!G$3:G$178))} -> 0.748625 | N41: {=SUMPRODUCT(('面板-分位数'!$A$3:$A$178='面板-景气指数'!$J41)*('面板-分位数'!$E$3:$E$178)*('面板-分位数'!H$3:H$178))} -> 0.736625 | O41: {=SUMPRODUCT(('面板-分位数'!$A$3:$A$178='面板-景气指数'!$J41)*('面板-分位数'!$E$3:$E$178)*('面板-分位数'!I$3:I$178))} -> 0.701875 | P41: {=SUMPRODUCT(('面板-分位数'!$A$3:$A$178='面板-景气指数'!$J41)*('面板-分位数'!$E$3:$E$178)*('面板-分位数'!J$3:J$178))} -> 0.513 | Q41: {=SUMPRODUCT(('面板-分位数'!$A$3:$A$178='面板-景气指数'!$J41)*('面板-分位数'!$E$3:$E$178)*('面板-分位数'!K$3:K$178))} -> 0.454375 | R41: {=SUMPRODUCT(('面板-分位数'!$A$3:$A$178='面板-景气指数'!$J41)*('面板-分位数'!$E$3:$E$178)*('面板-分位数'!L$3:L$178))} -> 0.401875 | S41: {=SUMPRODUCT(('面板-分位数'!$A$3:$A$178='面板-景气指数'!$J41)*('面板-分位数'!$E$3:$E$178)*('面板-分位数'!M$3:M$178))} -> 0.46825 | T41: {=SUMPRODUCT(('面板-分位数'!$A$3:$A$178='面板-景气指数'!$J41)*('面板-分位数'!$E$3:$E$178)*('面板-分位数'!N$3:N$178))} -> 0.65925 | ... CD41: {=SUMPRODUCT(('面板-分位数'!$A$3:$A$178='面板-景气指数'!$J41)*('面板-分位数'!$E$3:$E$178)*('面板-分位数'!BX$3:BX$178))} -> 0.526
J42: 智能汽车 | K42: 2C | L42: =(M42-O42)*100 -> 6.8466667 | M42: {=SUMPRODUCT(('面板-分位数'!$A$3:$A$178='面板-景气指数'!$J42)*('面板-分位数'!$E$3:$E$178)*('面板-分位数'!G$3:G$178))} -> 0.4704 | N42: {=SUMPRODUCT(('面板-分位数'!$A$3:$A$178='面板-景气指数'!$J42)*('面板-分位数'!$E$3:$E$178)*('面板-分位数'!H$3:H$178))} -> 0.4704 | O42: {=SUMPRODUCT(('面板-分位数'!$A$3:$A$178='面板-景气指数'!$J42)*('面板-分位数'!$E$3:$E$178)*('面板-分位数'!I$3:I$178))} -> 0.40193333 | P42: {=SUMPRODUCT(('面板-分位数'!$A$3:$A$178='面板-景气指数'!$J42)*('面板-分位数'!$E$3:$E$178)*('面板-分位数'!J$3:J$178))} -> 0.33976667 | Q42: {=SUMPRODUCT(('面板-分位数'!$A$3:$A$178='面板-景气指数'!$J42)*('面板-分位数'!$E$3:$E$178)*('面板-分位数'!K$3:K$178))} -> 0.2383 | R42: {=SUMPRODUCT(('面板-分位数'!$A$3:$A$178='面板-景气指数'!$J42)*('面板-分位数'!$E$3:$E$178)*('面板-分位数'!L$3:L$178))} -> 0.14446667 | S42: {=SUMPRODUCT(('面板-分位数'!$A$3:$A$178='面板-景气指数'!$J42)*('面板-分位数'!$E$3:$E$178)*('面板-分位数'!M$3:M$178))} -> 0.2021 | T42: {=SUMPRODUCT(('面板-分位数'!$A$3:$A$178='面板-景气指数'!$J42)*('面板-分位数'!$E$3:$E$178)*('面板-分位数'!N$3:N$178))} -> 0.3482 | ... CD42: {=SUMPRODUCT(('面板-分位数'!$A$3:$A$178='面板-景气指数'!$J42)*('面板-分位数'!$E$3:$E$178)*('面板-分位数'!BX$3:BX$178))} -> 0.48643333
J43: 航空装备 | K43: 2G | L43: =(M43-O43)*100 -> -5.9 | M43: {=SUMPRODUCT(('面板-分位数'!$A$3:$A$178='面板-景气指数'!$J43)*('面板-分位数'!$E$3:$E$178)*('面板-分位数'!G$3:G$178))} -> 0.64288889 | N43: {=SUMPRODUCT(('面板-分位数'!$A$3:$A$178='面板-景气指数'!$J43)*('面板-分位数'!$E$3:$E$178)*('面板-分位数'!H$3:H$178))} -> 0.65577778 | O43: {=SUMPRODUCT(('面板-分位数'!$A$3:$A$178='面板-景气指数'!$J43)*('面板-分位数'!$E$3:$E$178)*('面板-分位数'!I$3:I$178))} -> 0.70188889 | P43: {=SUMPRODUCT(('面板-分位数'!$A$3:$A$178='面板-景气指数'!$J43)*('面板-分位数'!$E$3:$E$178)*('面板-分位数'!J$3:J$178))} -> 0.69877778 | Q43: {=SUMPRODUCT(('面板-分位数'!$A$3:$A$178='面板-景气指数'!$J43)*('面板-分位数'!$E$3:$E$178)*('面板-分位数'!K$3:K$178))} -> 0.71 | R43: {=SUMPRODUCT(('面板-分位数'!$A$3:$A$178='面板-景气指数'!$J43)*('面板-分位数'!$E$3:$E$178)*('面板-分位数'!L$3:L$178))} -> 0.76122222 | S43: {=SUMPRODUCT(('面板-分位数'!$A$3:$A$178='面板-景气指数'!$J43)*('面板-分位数'!$E$3:$E$178)*('面板-分位数'!M$3:M$178))} -> 0.74355556 | T43: {=SUMPRODUCT(('面板-分位数'!$A$3:$A$178='面板-景气指数'!$J43)*('面板-分位数'!$E$3:$E$178)*('面板-分位数'!N$3:N$178))} -> 0.77088889 | ... CD43: {=SUMPRODUCT(('面板-分位数'!$A$3:$A$178='面板-景气指数'!$J43)*('面板-分位数'!$E$3:$E$178)*('面板-分位数'!BX$3:BX$178))} -> 0.51688889
J44: 物联网 | K44: 2C | L44: =(M44-O44)*100 -> -7.6285714 | M44: {=SUMPRODUCT(('面板-分位数'!$A$3:$A$178='面板-景气指数'!$J44)*('面板-分位数'!$E$3:$E$178)*('面板-分位数'!G$3:G$178))} -> 0.46982143 | N44: {=SUMPRODUCT(('面板-分位数'!$A$3:$A$178='面板-景气指数'!$J44)*('面板-分位数'!$E$3:$E$178)*('面板-分位数'!H$3:H$178))} -> 0.41403571 | O44: {=SUMPRODUCT(('面板-分位数'!$A$3:$A$178='面板-景气指数'!$J44)*('面板-分位数'!$E$3:$E$178)*('面板-分位数'!I$3:I$178))} -> 0.54610714 | P44: {=SUMPRODUCT(('面板-分位数'!$A$3:$A$178='面板-景气指数'!$J44)*('面板-分位数'!$E$3:$E$178)*('面板-分位数'!J$3:J$178))} -> 0.50096429 | Q44: {=SUMPRODUCT(('面板-分位数'!$A$3:$A$178='面板-景气指数'!$J44)*('面板-分位数'!$E$3:$E$178)*('面板-分位数'!K$3:K$178))} -> 0.44692857 | R44: {=SUMPRODUCT(('面板-分位数'!$A$3:$A$178='面板-景气指数'!$J44)*('面板-分位数'!$E$3:$E$178)*('面板-分位数'!L$3:L$178))} -> 0.39935714 | S44: {=SUMPRODUCT(('面板-分位数'!$A$3:$A$178='面板-景气指数'!$J44)*('面板-分位数'!$E$3:$E$178)*('面板-分位数'!M$3:M$178))} -> 0.42064286 | T44: {=SUMPRODUCT(('面板-分位数'!$A$3:$A$178='面板-景气指数'!$J44)*('面板-分位数'!$E$3:$E$178)*('面板-分位数'!N$3:N$178))} -> 0.44432143 | ... CD44: {=SUMPRODUCT(('面板-分位数'!$A$3:$A$178='面板-景气指数'!$J44)*('面板-分位数'!$E$3:$E$178)*('面板-分位数'!BX$3:BX$178))} -> 0.46428571
... J46: 储能 | K46: 2G | L46: =(M46-O46)*100 -> -1.025 | M46: {=SUMPRODUCT(('面板-分位数'!$A$3:$A$178='面板-景气指数'!$J46)*('面板-分位数'!$E$3:$E$178)*('面板-分位数'!G$3:G$178))} -> 0.61483333 | N46: {=SUMPRODUCT(('面板-分位数'!$A$3:$A$178='面板-景气指数'!$J46)*('面板-分位数'!$E$3:$E$178)*('面板-分位数'!H$3:H$178))} -> 0.616 | O46: {=SUMPRODUCT(('面板-分位数'!$A$3:$A$178='面板-景气指数'!$J46)*('面板-分位数'!$E$3:$E$178)*('面板-分位数'!I$3:I$178))} -> 0.62508333 | P46: {=SUMPRODUCT(('面板-分位数'!$A$3:$A$178='面板-景气指数'!$J46)*('面板-分位数'!$E$3:$E$178)*('面板-分位数'!J$3:J$178))} -> 0.64579167 | Q46: {=SUMPRODUCT(('面板-分位数'!$A$3:$A$178='面板-景气指数'!$J46)*('面板-分位数'!$E$3:$E$178)*('面板-分位数'!K$3:K$178))} -> 0.6735 | R46: {=SUMPRODUCT(('面板-分位数'!$A$3:$A$178='面板-景气指数'!$J46)*('面板-分位数'!$E$3:$E$178)*('面板-分位数'!L$3:L$178))} -> 0.71775 | S46: {=SUMPRODUCT(('面板-分位数'!$A$3:$A$178='面板-景气指数'!$J46)*('面板-分位数'!$E$3:$E$178)*('面板-分位数'!M$3:M$178))} -> 0.749875 | T46: {=SUMPRODUCT(('面板-分位数'!$A$3:$A$178='面板-景气指数'!$J46)*('面板-分位数'!$E$3:$E$178)*('面板-分位数'!N$3:N$178))} -> 0.77683333 | ... CD46: {=SUMPRODUCT(('面板-分位数'!$A$3:$A$178='面板-景气指数'!$J46)*('面板-分位数'!$E$3:$E$178)*('面板-分位数'!BX$3:BX$178))} -> 0.46245833
J48: 锂电上游 | L48: =(M48-O48)*100 -> -0.91666667 | M48: {=SUMPRODUCT(('面板-分位数'!$F$3:$F$178='面板-景气指数'!$J48)*('面板-分位数'!$E$3:$E$178)*('面板-分位数'!G$3:G$178))/SUMIFS('面板-分位数'!$E:$E,'面板-分位数'!$F:$F,'面板-景气指数'!$J48)} -> 0.69533333 | N48: {=SUMPRODUCT(('面板-分位数'!$F$3:$F$178='面板-景气指数'!$J48)*('面板-分位数'!$E$3:$E$178)*('面板-分位数'!H$3:H$178))/SUMIFS('面板-分位数'!$E:$E,'面板-分位数'!$F:$F,'面板-景气指数'!$J48)} -> 0.68283333 | O48: {=SUMPRODUCT(('面板-分位数'!$F$3:$F$178='面板-景气指数'!$J48)*('面板-分位数'!$E$3:$E$178)*('面板-分位数'!I$3:I$178))/SUMIFS('面板-分位数'!$E:$E,'面板-分位数'!$F:$F,'面板-景气指数'!$J48)} -> 0.7045 | P48: {=SUMPRODUCT(('面板-分位数'!$F$3:$F$178='面板-景气指数'!$J48)*('面板-分位数'!$E$3:$E$178)*('面板-分位数'!J$3:J$178))/SUMIFS('面板-分位数'!$E:$E,'面板-分位数'!$F:$F,'面板-景气指数'!$J48)} -> 0.75033333 | Q48: {=SUMPRODUCT(('面板-分位数'!$F$3:$F$178='面板-景气指数'!$J48)*('面板-分位数'!$E$3:$E$178)*('面板-分位数'!K$3:K$178))/SUMIFS('面板-分位数'!$E:$E,'面板-分位数'!$F:$F,'面板-景气指数'!$J48)} -> 0.81533333 | R48: {=SUMPRODUCT(('面板-分位数'!$F$3:$F$178='面板-景气指数'!$J48)*('面板-分位数'!$E$3:$E$178)*('面板-分位数'!L$3:L$178))/SUMIFS('面板-分位数'!$E:$E,'面板-分位数'!$F:$F,'面板-景气指数'!$J48)} -> 0.864 | S48: {=SUMPRODUCT(('面板-分位数'!$F$3:$F$178='面板-景气指数'!$J48)*('面板-分位数'!$E$3:$E$178)*('面板-分位数'!M$3:M$178))/SUMIFS('面板-分位数'!$E:$E,'面板-分位数'!$F:$F,'面板-景气指数'!$J48)} -> 0.939 | T48: {=SUMPRODUCT(('面板-分位数'!$F$3:$F$178='面板-景气指数'!$J48)*('面板-分位数'!$E$3:$E$178)*('面板-分位数'!N$3:N$178))/SUMIFS('面板-分位数'!$E:$E,'面板-分位数'!$F:$F,'面板-景气指数'!$J48)} -> 0.91433333 | ... CD48: {=SUMPRODUCT(('面板-分位数'!$F$3:$F$178='面板-景气指数'!$J48)*('面板-分位数'!$E$3:$E$178)*('面板-分位数'!BX$3:BX$178))/SUMIFS('面板-分位数'!$E:$E,'面板-分位数'!$F:$F,'面板-景气指数'!$J48)} -> 0.36816667
J49: 锂电中游 | L49: =(M49-O49)*100 -> -1.2230769 | M49: {=SUMPRODUCT(('面板-分位数'!$F$3:$F$178='面板-景气指数'!$J49)*('面板-分位数'!$E$3:$E$178)*('面板-分位数'!G$3:G$178))/SUMIFS('面板-分位数'!$E:$E,'面板-分位数'!$F:$F,'面板-景气指数'!$J49)} -> 0.66 | N49: {=SUMPRODUCT(('面板-分位数'!$F$3:$F$178='面板-景气指数'!$J49)*('面板-分位数'!$E$3:$E$178)*('面板-分位数'!H$3:H$178))/SUMIFS('面板-分位数'!$E:$E,'面板-分位数'!$F:$F,'面板-景气指数'!$J49)} -> 0.66784615 | O49: {=SUMPRODUCT(('面板-分位数'!$F$3:$F$178='面板-景气指数'!$J49)*('面板-分位数'!$E$3:$E$178)*('面板-分位数'!I$3:I$178))/SUMIFS('面板-分位数'!$E:$E,'面板-分位数'!$F:$F,'面板-景气指数'!$J49)} -> 0.67223077 | P49: {=SUMPRODUCT(('面板-分位数'!$F$3:$F$178='面板-景气指数'!$J49)*('面板-分位数'!$E$3:$E$178)*('面板-分位数'!J$3:J$178))/SUMIFS('面板-分位数'!$E:$E,'面板-分位数'!$F:$F,'面板-景气指数'!$J49)} -> 0.68861538 | Q49: {=SUMPRODUCT(('面板-分位数'!$F$3:$F$178='面板-景气指数'!$J49)*('面板-分位数'!$E$3:$E$178)*('面板-分位数'!K$3:K$178))/SUMIFS('面板-分位数'!$E:$E,'面板-分位数'!$F:$F,'面板-景气指数'!$J49)} -> 0.689 | R49: {=SUMPRODUCT(('面板-分位数'!$F$3:$F$178='面板-景气指数'!$J49)*('面板-分位数'!$E$3:$E$178)*('面板-分位数'!L$3:L$178))/SUMIFS('面板-分位数'!$E:$E,'面板-分位数'!$F:$F,'面板-景气指数'!$J49)} -> 0.69446154 | S49: {=SUMPRODUCT(('面板-分位数'!$F$3:$F$178='面板-景气指数'!$J49)*('面板-分位数'!$E$3:$E$178)*('面板-分位数'!M$3:M$178))/SUMIFS('面板-分位数'!$E:$E,'面板-分位数'!$F:$F,'面板-景气指数'!$J49)} -> 0.74146154 | T49: {=SUMPRODUCT(('面板-分位数'!$F$3:$F$178='面板-景气指数'!$J49)*('面板-分位数'!$E$3:$E$178)*('面板-分位数'!N$3:N$178))/SUMIFS('面板-分位数'!$E:$E,'面板-分位数'!$F:$F,'面板-景气指数'!$J49)} -> 0.79584615 | ... CD49: {=SUMPRODUCT(('面板-分位数'!$F$3:$F$178='面板-景气指数'!$J49)*('面板-分位数'!$E$3:$E$178)*('面板-分位数'!BX$3:BX$178))/SUMIFS('面板-分位数'!$E:$E,'面板-分位数'!$F:$F,'面板-景气指数'!$J49)} -> 0.39369231
J50: 锂电下游 | L50: =(M50-O50)*100 -> -10.1 | M50: {=SUMPRODUCT(('面板-分位数'!$F$3:$F$178='面板-景气指数'!$J50)*('面板-分位数'!$E$3:$E$178)*('面板-分位数'!G$3:G$178))/SUMIFS('面板-分位数'!$E:$E,'面板-分位数'!$F:$F,'面板-景气指数'!$J50)} -> 0.536 | N50: {=SUMPRODUCT(('面板-分位数'!$F$3:$F$178='面板-景气指数'!$J50)*('面板-分位数'!$E$3:$E$178)*('面板-分位数'!H$3:H$178))/SUMIFS('面板-分位数'!$E:$E,'面板-分位数'!$F:$F,'面板-景气指数'!$J50)} -> 0.536 | O50: {=SUMPRODUCT(('面板-分位数'!$F$3:$F$178='面板-景气指数'!$J50)*('面板-分位数'!$E$3:$E$178)*('面板-分位数'!I$3:I$178))/SUMIFS('面板-分位数'!$E:$E,'面板-分位数'!$F:$F,'面板-景气指数'!$J50)} -> 0.637 | P50: {=SUMPRODUCT(('面板-分位数'!$F$3:$F$178='面板-景气指数'!$J50)*('面板-分位数'!$E$3:$E$178)*('面板-分位数'!J$3:J$178))/SUMIFS('面板-分位数'!$E:$E,'面板-分位数'!$F:$F,'面板-景气指数'!$J50)} -> 0.666 | Q50: {=SUMPRODUCT(('面板-分位数'!$F$3:$F$178='面板-景气指数'!$J50)*('面板-分位数'!$E$3:$E$178)*('面板-分位数'!K$3:K$178))/SUMIFS('面板-分位数'!$E:$E,'面板-分位数'!$F:$F,'面板-景气指数'!$J50)} -> 0.623 | R50: {=SUMPRODUCT(('面板-分位数'!$F$3:$F$178='面板-景气指数'!$J50)*('面板-分位数'!$E$3:$E$178)*('面板-分位数'!L$3:L$178))/SUMIFS('面板-分位数'!$E:$E,'面板-分位数'!$F:$F,'面板-景气指数'!$J50)} -> 0.478 | S50: {=SUMPRODUCT(('面板-分位数'!$F$3:$F$178='面板-景气指数'!$J50)*('面板-分位数'!$E$3:$E$178)*('面板-分位数'!M$3:M$178))/SUMIFS('面板-分位数'!$E:$E,'面板-分位数'!$F:$F,'面板-景气指数'!$J50)} -> 0.608 | T50: {=SUMPRODUCT(('面板-分位数'!$F$3:$F$178='面板-景气指数'!$J50)*('面板-分位数'!$E$3:$E$178)*('面板-分位数'!N$3:N$178))/SUMIFS('面板-分位数'!$E:$E,'面板-分位数'!$F:$F,'面板-景气指数'!$J50)} -> 0.811 | ... CD50: {=SUMPRODUCT(('面板-分位数'!$F$3:$F$178='面板-景气指数'!$J50)*('面板-分位数'!$E$3:$E$178)*('面板-分位数'!BX$3:BX$178))/SUMIFS('面板-分位数'!$E:$E,'面板-分位数'!$F:$F,'面板-景气指数'!$J50)} -> 0.13
J51: 机器人上游 | L51: =(M51-O51)*100 -> -4.4 | M51: {=SUMPRODUCT(('面板-分位数'!$F$3:$F$178='面板-景气指数'!$J51)*('面板-分位数'!$E$3:$E$178)*('面板-分位数'!G$3:G$178))/SUMIFS('面板-分位数'!$E:$E,'面板-分位数'!$F:$F,'面板-景气指数'!$J51)} -> 0.84 | N51: {=SUMPRODUCT(('面板-分位数'!$F$3:$F$178='面板-景气指数'!$J51)*('面板-分位数'!$E$3:$E$178)*('面板-分位数'!H$3:H$178))/SUMIFS('面板-分位数'!$E:$E,'面板-分位数'!$F:$F,'面板-景气指数'!$J51)} -> 0.855 | O51: {=SUMPRODUCT(('面板-分位数'!$F$3:$F$178='面板-景气指数'!$J51)*('面板-分位数'!$E$3:$E$178)*('面板-分位数'!I$3:I$178))/SUMIFS('面板-分位数'!$E:$E,'面板-分位数'!$F:$F,'面板-景气指数'!$J51)} -> 0.884 | P51: {=SUMPRODUCT(('面板-分位数'!$F$3:$F$178='面板-景气指数'!$J51)*('面板-分位数'!$E$3:$E$178)*('面板-分位数'!J$3:J$178))/SUMIFS('面板-分位数'!$E:$E,'面板-分位数'!$F:$F,'面板-景气指数'!$J51)} -> 0.942 | Q51: {=SUMPRODUCT(('面板-分位数'!$F$3:$F$178='面板-景气指数'!$J51)*('面板-分位数'!$E$3:$E$178)*('面板-分位数'!K$3:K$178))/SUMIFS('面板-分位数'!$E:$E,'面板-分位数'!$F:$F,'面板-景气指数'!$J51)} -> 0.956 | R51: {=SUMPRODUCT(('面板-分位数'!$F$3:$F$178='面板-景气指数'!$J51)*('面板-分位数'!$E$3:$E$178)*('面板-分位数'!L$3:L$178))/SUMIFS('面板-分位数'!$E:$E,'面板-分位数'!$F:$F,'面板-景气指数'!$J51)} -> 0.927 | S51: {=SUMPRODUCT(('面板-分位数'!$F$3:$F$178='面板-景气指数'!$J51)*('面板-分位数'!$E$3:$E$178)*('面板-分位数'!M$3:M$178))/SUMIFS('面板-分位数'!$E:$E,'面板-分位数'!$F:$F,'面板-景气指数'!$J51)} -> 0.971 | T51: {=SUMPRODUCT(('面板-分位数'!$F$3:$F$178='面板-景气指数'!$J51)*('面板-分位数'!$E$3:$E$178)*('面板-分位数'!N$3:N$178))/SUMIFS('面板-分位数'!$E:$E,'面板-分位数'!$F:$F,'面板-景气指数'!$J51)} -> 1 | ... CD51: {=SUMPRODUCT(('面板-分位数'!$F$3:$F$178='面板-景气指数'!$J51)*('面板-分位数'!$E$3:$E$178)*('面板-分位数'!BX$3:BX$178))/SUMIFS('面板-分位数'!$E:$E,'面板-分位数'!$F:$F,'面板-景气指数'!$J51)} -> 0
J52: 机器人中游 | L52: =(M52-O52)*100 -> -0.0090909091 | M52: {=SUMPRODUCT(('面板-分位数'!$F$3:$F$178='面板-景气指数'!$J52)*('面板-分位数'!$E$3:$E$178)*('面板-分位数'!G$3:G$178))/SUMIFS('面板-分位数'!$E:$E,'面板-分位数'!$F:$F,'面板-景气指数'!$J52)} -> 0.32127273 | N52: {=SUMPRODUCT(('面板-分位数'!$F$3:$F$178='面板-景气指数'!$J52)*('面板-分位数'!$E$3:$E$178)*('面板-分位数'!H$3:H$178))/SUMIFS('面板-分位数'!$E:$E,'面板-分位数'!$F:$F,'面板-景气指数'!$J52)} -> 0.32127273 | O52: {=SUMPRODUCT(('面板-分位数'!$F$3:$F$178='面板-景气指数'!$J52)*('面板-分位数'!$E$3:$E$178)*('面板-分位数'!I$3:I$178))/SUMIFS('面板-分位数'!$E:$E,'面板-分位数'!$F:$F,'面板-景气指数'!$J52)} -> 0.32136364 | P52: {=SUMPRODUCT(('面板-分位数'!$F$3:$F$178='面板-景气指数'!$J52)*('面板-分位数'!$E$3:$E$178)*('面板-分位数'!J$3:J$178))/SUMIFS('面板-分位数'!$E:$E,'面板-分位数'!$F:$F,'面板-景气指数'!$J52)} -> 0.37554545 | Q52: {=SUMPRODUCT(('面板-分位数'!$F$3:$F$178='面板-景气指数'!$J52)*('面板-分位数'!$E$3:$E$178)*('面板-分位数'!K$3:K$178))/SUMIFS('面板-分位数'!$E:$E,'面板-分位数'!$F:$F,'面板-景气指数'!$J52)} -> 0.29054545 | R52: {=SUMPRODUCT(('面板-分位数'!$F$3:$F$178='面板-景气指数'!$J52)*('面板-分位数'!$E$3:$E$178)*('面板-分位数'!L$3:L$178))/SUMIFS('面板-分位数'!$E:$E,'面板-分位数'!$F:$F,'面板-景气指数'!$J52)} -> 0.13336364 | S52: {=SUMPRODUCT(('面板-分位数'!$F$3:$F$178='面板-景气指数'!$J52)*('面板-分位数'!$E$3:$E$178)*('面板-分位数'!M$3:M$178))/SUMIFS('面板-分位数'!$E:$E,'面板-分位数'!$F:$F,'面板-景气指数'!$J52)} -> 0.30672727 | T52: {=SUMPRODUCT(('面板-分位数'!$F$3:$F$178='面板-景气指数'!$J52)*('面板-分位数'!$E$3:$E$178)*('面板-分位数'!N$3:N$178))/SUMIFS('面板-分位数'!$E:$E,'面板-分位数'!$F:$F,'面板-景气指数'!$J52)} -> 0.54690909 | ... CD52: {=SUMPRODUCT(('面板-分位数'!$F$3:$F$178='面板-景气指数'!$J52)*('面板-分位数'!$E$3:$E$178)*('面板-分位数'!BX$3:BX$178))/SUMIFS('面板-分位数'!$E:$E,'面板-分位数'!$F:$F,'面板-景气指数'!$J52)} -> 0.5
J53: 机床中游 | L53: =(M53-O53)*100 -> 4.6916667 | M53: {=SUMPRODUCT(('面板-分位数'!$F$3:$F$178='面板-景气指数'!$J53)*('面板-分位数'!$E$3:$E$178)*('面板-分位数'!G$3:G$178))/SUMIFS('面板-分位数'!$E:$E,'面板-分位数'!$F:$F,'面板-景气指数'!$J53)} -> 0.43658333 | N53: {=SUMPRODUCT(('面板-分位数'!$F$3:$F$178='面板-景气指数'!$J53)*('面板-分位数'!$E$3:$E$178)*('面板-分位数'!H$3:H$178))/SUMIFS('面板-分位数'!$E:$E,'面板-分位数'!$F:$F,'面板-景气指数'!$J53)} -> 0.43658333 | O53: {=SUMPRODUCT(('面板-分位数'!$F$3:$F$178='面板-景气指数'!$J53)*('面板-分位数'!$E$3:$E$178)*('面板-分位数'!I$3:I$178))/SUMIFS('面板-分位数'!$E:$E,'面板-分位数'!$F:$F,'面板-景气指数'!$J53)} -> 0.38966667 | P53: {=SUMPRODUCT(('面板-分位数'!$F$3:$F$178='面板-景气指数'!$J53)*('面板-分位数'!$E$3:$E$178)*('面板-分位数'!J$3:J$178))/SUMIFS('面板-分位数'!$E:$E,'面板-分位数'!$F:$F,'面板-景气指数'!$J53)} -> 0.32616667 | Q53: {=SUMPRODUCT(('面板-分位数'!$F$3:$F$178='面板-景气指数'!$J53)*('面板-分位数'!$E$3:$E$178)*('面板-分位数'!K$3:K$178))/SUMIFS('面板-分位数'!$E:$E,'面板-分位数'!$F:$F,'面板-景气指数'!$J53)} -> 0.47116667 | R53: {=SUMPRODUCT(('面板-分位数'!$F$3:$F$178='面板-景气指数'!$J53)*('面板-分位数'!$E$3:$E$178)*('面板-分位数'!L$3:L$178))/SUMIFS('面板-分位数'!$E:$E,'面板-分位数'!$F:$F,'面板-景气指数'!$J53)} -> 0.44725 | S53: {=SUMPRODUCT(('面板-分位数'!$F$3:$F$178='面板-景气指数'!$J53)*('面板-分位数'!$E$3:$E$178)*('面板-分位数'!M$3:M$178))/SUMIFS('面板-分位数'!$E:$E,'面板-分位数'!$F:$F,'面板-景气指数'!$J53)} -> 0.431 | T53: {=SUMPRODUCT(('面板-分位数'!$F$3:$F$178='面板-景气指数'!$J53)*('面板-分位数'!$E$3:$E$178)*('面板-分位数'!N$3:N$178))/SUMIFS('面板-分位数'!$E:$E,'面板-分位数'!$F:$F,'面板-景气指数'!$J53)} -> 0.60166667 | ... CD53: {=SUMPRODUCT(('面板-分位数'!$F$3:$F$178='面板-景气指数'!$J53)*('面板-分位数'!$E$3:$E$178)*('面板-分位数'!BX$3:BX$178))/SUMIFS('面板-分位数'!$E:$E,'面板-分位数'!$F:$F,'面板-景气指数'!$J53)} -> 0.4055
J54: 元宇宙中游 | L54: =(M54-O54)*100 -> -54.666667 | M54: {=SUMPRODUCT(('面板-分位数'!$F$3:$F$178='面板-景气指数'!$J54)*('面板-分位数'!$E$3:$E$178)*('面板-分位数'!G$3:G$178))/SUMIFS('面板-分位数'!$E:$E,'面板-分位数'!$F:$F,'面板-景气指数'!$J54)} -> 0.16683333 | N54: {=SUMPRODUCT(('面板-分位数'!$F$3:$F$178='面板-景气指数'!$J54)*('面板-分位数'!$E$3:$E$178)*('面板-分位数'!H$3:H$178))/SUMIFS('面板-分位数'!$E:$E,'面板-分位数'!$F:$F,'面板-景气指数'!$J54)} -> 0.18583333 | O54: {=SUMPRODUCT(('面板-分位数'!$F$3:$F$178='面板-景气指数'!$J54)*('面板-分位数'!$E$3:$E$178)*('面板-分位数'!I$3:I$178))/SUMIFS('面板-分位数'!$E:$E,'面板-分位数'!$F:$F,'面板-景气指数'!$J54)} -> 0.7135 | P54: {=SUMPRODUCT(('面板-分位数'!$F$3:$F$178='面板-景气指数'!$J54)*('面板-分位数'!$E$3:$E$178)*('面板-分位数'!J$3:J$178))/SUMIFS('面板-分位数'!$E:$E,'面板-分位数'!$F:$F,'面板-景气指数'!$J54)} -> 0.72933333 | Q54: {=SUMPRODUCT(('面板-分位数'!$F$3:$F$178='面板-景气指数'!$J54)*('面板-分位数'!$E$3:$E$178)*('面板-分位数'!K$3:K$178))/SUMIFS('面板-分位数'!$E:$E,'面板-分位数'!$F:$F,'面板-景气指数'!$J54)} -> 0.72216667 | R54: {=SUMPRODUCT(('面板-分位数'!$F$3:$F$178='面板-景气指数'!$J54)*('面板-分位数'!$E$3:$E$178)*('面板-分位数'!L$3:L$178))/SUMIFS('面板-分位数'!$E:$E,'面板-分位数'!$F:$F,'面板-景气指数'!$J54)} -> 0.5265 | S54: {=SUMPRODUCT(('面板-分位数'!$F$3:$F$178='面板-景气指数'!$J54)*('面板-分位数'!$E$3:$E$178)*('面板-分位数'!M$3:M$178))/SUMIFS('面板-分位数'!$E:$E,'面板-分位数'!$F:$F,'面板-景气指数'!$J54)} -> 0.56016667 | T54: {=SUMPRODUCT(('面板-分位数'!$F$3:$F$178='面板-景气指数'!$J54)*('面板-分位数'!$E$3:$E$178)*('面板-分位数'!N$3:N$178))/SUMIFS('面板-分位数'!$E:$E,'面板-分位数'!$F:$F,'面板-景气指数'!$J54)} -> 0.55816667 | ... CD54: {=SUMPRODUCT(('面板-分位数'!$F$3:$F$178='面板-景气指数'!$J54)*('面板-分位数'!$E$3:$E$178)*('面板-分位数'!BX$3:BX$178))/SUMIFS('面板-分位数'!$E:$E,'面板-分位数'!$F:$F,'面板-景气指数'!$J54)} -> 0.55916667
J55: 元宇宙下游 | L55: =(M55-O55)*100 -> -30.55 | M55: {=SUMPRODUCT(('面板-分位数'!$F$3:$F$178='面板-景气指数'!$J55)*('面板-分位数'!$E$3:$E$178)*('面板-分位数'!G$3:G$178))/SUMIFS('面板-分位数'!$E:$E,'面板-分位数'!$F:$F,'面板-景气指数'!$J55)} -> 0.242 | N55: {=SUMPRODUCT(('面板-分位数'!$F$3:$F$178='面板-景气指数'!$J55)*('面板-分位数'!$E$3:$E$178)*('面板-分位数'!H$3:H$178))/SUMIFS('面板-分位数'!$E:$E,'面板-分位数'!$F:$F,'面板-景气指数'!$J55)} -> 0.242 | O55: {=SUMPRODUCT(('面板-分位数'!$F$3:$F$178='面板-景气指数'!$J55)*('面板-分位数'!$E$3:$E$178)*('面板-分位数'!I$3:I$178))/SUMIFS('面板-分位数'!$E:$E,'面板-分位数'!$F:$F,'面板-景气指数'!$J55)} -> 0.5475 | P55: {=SUMPRODUCT(('面板-分位数'!$F$3:$F$178='面板-景气指数'!$J55)*('面板-分位数'!$E$3:$E$178)*('面板-分位数'!J$3:J$178))/SUMIFS('面板-分位数'!$E:$E,'面板-分位数'!$F:$F,'面板-景气指数'!$J55)} -> 0.5555 | Q55: {=SUMPRODUCT(('面板-分位数'!$F$3:$F$178='面板-景气指数'!$J55)*('面板-分位数'!$E$3:$E$178)*('面板-分位数'!K$3:K$178))/SUMIFS('面板-分位数'!$E:$E,'面板-分位数'!$F:$F,'面板-景气指数'!$J55)} -> 0.307 | R55: {=SUMPRODUCT(('面板-分位数'!$F$3:$F$178='面板-景气指数'!$J55)*('面板-分位数'!$E$3:$E$178)*('面板-分位数'!L$3:L$178))/SUMIFS('面板-分位数'!$E:$E,'面板-分位数'!$F:$F,'面板-景气指数'!$J55)} -> 0.294 | S55: {=SUMPRODUCT(('面板-分位数'!$F$3:$F$178='面板-景气指数'!$J55)*('面板-分位数'!$E$3:$E$178)*('面板-分位数'!M$3:M$178))/SUMIFS('面板-分位数'!$E:$E,'面板-分位数'!$F:$F,'面板-景气指数'!$J55)} -> 0.119 | T55: {=SUMPRODUCT(('面板-分位数'!$F$3:$F$178='面板-景气指数'!$J55)*('面板-分位数'!$E$3:$E$178)*('面板-分位数'!N$3:N$178))/SUMIFS('面板-分位数'!$E:$E,'面板-分位数'!$F:$F,'面板-景气指数'!$J55)} -> 0.1815 | ... CD55: {=SUMPRODUCT(('面板-分位数'!$F$3:$F$178='面板-景气指数'!$J55)*('面板-分位数'!$E$3:$E$178)*('面板-分位数'!BX$3:BX$178))/SUMIFS('面板-分位数'!$E:$E,'面板-分位数'!$F:$F,'面板-景气指数'!$J55)} -> 0.5
J56: 光伏上游 | L56: =(M56-O56)*100 -> -6.5 | M56: {=SUMPRODUCT(('面板-分位数'!$F$3:$F$178='面板-景气指数'!$J56)*('面板-分位数'!$E$3:$E$178)*('面板-分位数'!G$3:G$178))/SUMIFS('面板-分位数'!$E:$E,'面板-分位数'!$F:$F,'面板-景气指数'!$J56)} -> 0.72233333 | N56: {=SUMPRODUCT(('面板-分位数'!$F$3:$F$178='面板-景气指数'!$J56)*('面板-分位数'!$E$3:$E$178)*('面板-分位数'!H$3:H$178))/SUMIFS('面板-分位数'!$E:$E,'面板-分位数'!$F:$F,'面板-景气指数'!$J56)} -> 0.7175 | O56: {=SUMPRODUCT(('面板-分位数'!$F$3:$F$178='面板-景气指数'!$J56)*('面板-分位数'!$E$3:$E$178)*('面板-分位数'!I$3:I$178))/SUMIFS('面板-分位数'!$E:$E,'面板-分位数'!$F:$F,'面板-景气指数'!$J56)} -> 0.78733333 | P56: {=SUMPRODUCT(('面板-分位数'!$F$3:$F$178='面板-景气指数'!$J56)*('面板-分位数'!$E$3:$E$178)*('面板-分位数'!J$3:J$178))/SUMIFS('面板-分位数'!$E:$E,'面板-分位数'!$F:$F,'面板-景气指数'!$J56)} -> 0.78483333 | Q56: {=SUMPRODUCT(('面板-分位数'!$F$3:$F$178='面板-景气指数'!$J56)*('面板-分位数'!$E$3:$E$178)*('面板-分位数'!K$3:K$178))/SUMIFS('面板-分位数'!$E:$E,'面板-分位数'!$F:$F,'面板-景气指数'!$J56)} -> 0.78266667 | R56: {=SUMPRODUCT(('面板-分位数'!$F$3:$F$178='面板-景气指数'!$J56)*('面板-分位数'!$E$3:$E$178)*('面板-分位数'!L$3:L$178))/SUMIFS('面板-分位数'!$E:$E,'面板-分位数'!$F:$F,'面板-景气指数'!$J56)} -> 0.79516667 | S56: {=SUMPRODUCT(('面板-分位数'!$F$3:$F$178='面板-景气指数'!$J56)*('面板-分位数'!$E$3:$E$178)*('面板-分位数'!M$3:M$178))/SUMIFS('面板-分位数'!$E:$E,'面板-分位数'!$F:$F,'面板-景气指数'!$J56)} -> 0.80233333 | T56: {=SUMPRODUCT(('面板-分位数'!$F$3:$F$178='面板-景气指数'!$J56)*('面板-分位数'!$E$3:$E$178)*('面板-分位数'!N$3:N$178))/SUMIFS('面板-分位数'!$E:$E,'面板-分位数'!$F:$F,'面板-景气指数'!$J56)} -> 0.77816667 | ... CD56: {=SUMPRODUCT(('面板-分位数'!$F$3:$F$178='面板-景气指数'!$J56)*('面板-分位数'!$E$3:$E$178)*('面板-分位数'!BX$3:BX$178))/SUMIFS('面板-分位数'!$E:$E,'面板-分位数'!$F:$F,'面板-景气指数'!$J56)} -> 0.48283333
J57: 光伏中游 | L57: =(M57-O57)*100 -> -4.5041667 | M57: {=SUMPRODUCT(('面板-分位数'!$F$3:$F$178='面板-景气指数'!$J57)*('面板-分位数'!$E$3:$E$178)*('面板-分位数'!G$3:G$178))/SUMIFS('面板-分位数'!$E:$E,'面板-分位数'!$F:$F,'面板-景气指数'!$J57)} -> 0.756875 | N57: {=SUMPRODUCT(('面板-分位数'!$F$3:$F$178='面板-景气指数'!$J57)*('面板-分位数'!$E$3:$E$178)*('面板-分位数'!H$3:H$178))/SUMIFS('面板-分位数'!$E:$E,'面板-分位数'!$F:$F,'面板-景气指数'!$J57)} -> 0.75958333 | O57: {=SUMPRODUCT(('面板-分位数'!$F$3:$F$178='面板-景气指数'!$J57)*('面板-分位数'!$E$3:$E$178)*('面板-分位数'!I$3:I$178))/SUMIFS('面板-分位数'!$E:$E,'面板-分位数'!$F:$F,'面板-景气指数'!$J57)} -> 0.80191667 | P57: {=SUMPRODUCT(('面板-分位数'!$F$3:$F$178='面板-景气指数'!$J57)*('面板-分位数'!$E$3:$E$178)*('面板-分位数'!J$3:J$178))/SUMIFS('面板-分位数'!$E:$E,'面板-分位数'!$F:$F,'面板-景气指数'!$J57)} -> 0.837375 | Q57: {=SUMPRODUCT(('面板-分位数'!$F$3:$F$178='面板-景气指数'!$J57)*('面板-分位数'!$E$3:$E$178)*('面板-分位数'!K$3:K$178))/SUMIFS('面板-分位数'!$E:$E,'面板-分位数'!$F:$F,'面板-景气指数'!$J57)} -> 0.850875 | R57: {=SUMPRODUCT(('面板-分位数'!$F$3:$F$178='面板-景气指数'!$J57)*('面板-分位数'!$E$3:$E$178)*('面板-分位数'!L$3:L$178))/SUMIFS('面板-分位数'!$E:$E,'面板-分位数'!$F:$F,'面板-景气指数'!$J57)} -> 0.85270833 | S57: {=SUMPRODUCT(('面板-分位数'!$F$3:$F$178='面板-景气指数'!$J57)*('面板-分位数'!$E$3:$E$178)*('面板-分位数'!M$3:M$178))/SUMIFS('面板-分位数'!$E:$E,'面板-分位数'!$F:$F,'面板-景气指数'!$J57)} -> 0.84333333 | T57: {=SUMPRODUCT(('面板-分位数'!$F$3:$F$178='面板-景气指数'!$J57)*('面板-分位数'!$E$3:$E$178)*('面板-分位数'!N$3:N$178))/SUMIFS('面板-分位数'!$E:$E,'面板-分位数'!$F:$F,'面板-景气指数'!$J57)} -> 0.84108333 | ... CD57: {=SUMPRODUCT(('面板-分位数'!$F$3:$F$178='面板-景气指数'!$J57)*('面板-分位数'!$E$3:$E$178)*('面板-分位数'!BX$3:BX$178))/SUMIFS('面板-分位数'!$E:$E,'面板-分位数'!$F:$F,'面板-景气指数'!$J57)} -> 0.500875
J58: 光伏下游 | L58: =(M58-O58)*100 -> 3.65 | M58: {=SUMPRODUCT(('面板-分位数'!$F$3:$F$178='面板-景气指数'!$J58)*('面板-分位数'!$E$3:$E$178)*('面板-分位数'!G$3:G$178))/SUMIFS('面板-分位数'!$E:$E,'面板-分位数'!$F:$F,'面板-景气指数'!$J58)} -> 0.6765 | N58: {=SUMPRODUCT(('面板-分位数'!$F$3:$F$178='面板-景气指数'!$J58)*('面板-分位数'!$E$3:$E$178)*('面板-分位数'!H$3:H$178))/SUMIFS('面板-分位数'!$E:$E,'面板-分位数'!$F:$F,'面板-景气指数'!$J58)} -> 0.6765 | O58: {=SUMPRODUCT(('面板-分位数'!$F$3:$F$178='面板-景气指数'!$J58)*('面板-分位数'!$E$3:$E$178)*('面板-分位数'!I$3:I$178))/SUMIFS('面板-分位数'!$E:$E,'面板-分位数'!$F:$F,'面板-景气指数'!$J58)} -> 0.64 | P58: {=SUMPRODUCT(('面板-分位数'!$F$3:$F$178='面板-景气指数'!$J58)*('面板-分位数'!$E$3:$E$178)*('面板-分位数'!J$3:J$178))/SUMIFS('面板-分位数'!$E:$E,'面板-分位数'!$F:$F,'面板-景气指数'!$J58)} -> 0.587 | Q58: {=SUMPRODUCT(('面板-分位数'!$F$3:$F$178='面板-景气指数'!$J58)*('面板-分位数'!$E$3:$E$178)*('面板-分位数'!K$3:K$178))/SUMIFS('面板-分位数'!$E:$E,'面板-分位数'!$F:$F,'面板-景气指数'!$J58)} -> 0.6355 | R58: {=SUMPRODUCT(('面板-分位数'!$F$3:$F$178='面板-景气指数'!$J58)*('面板-分位数'!$E$3:$E$178)*('面板-分位数'!L$3:L$178))/SUMIFS('面板-分位数'!$E:$E,'面板-分位数'!$F:$F,'面板-景气指数'!$J58)} -> 0.588 | S58: {=SUMPRODUCT(('面板-分位数'!$F$3:$F$178='面板-景气指数'!$J58)*('面板-分位数'!$E$3:$E$178)*('面板-分位数'!M$3:M$178))/SUMIFS('面板-分位数'!$E:$E,'面板-分位数'!$F:$F,'面板-景气指数'!$J58)} -> 0.3625 | T58: {=SUMPRODUCT(('面板-分位数'!$F$3:$F$178='面板-景气指数'!$J58)*('面板-分位数'!$E$3:$E$178)*('面板-分位数'!N$3:N$178))/SUMIFS('面板-分位数'!$E:$E,'面板-分位数'!$F:$F,'面板-景气指数'!$J58)} -> 0.077 | ... CD58: {=SUMPRODUCT(('面板-分位数'!$F$3:$F$178='面板-景气指数'!$J58)*('面板-分位数'!$E$3:$E$178)*('面板-分位数'!BX$3:BX$178))/SUMIFS('面板-分位数'!$E:$E,'面板-分位数'!$F:$F,'面板-景气指数'!$J58)} -> 0.5
J59: 风电上游 | L59: =(M59-O59)*100 -> -6.1333333 | M59: {=SUMPRODUCT(('面板-分位数'!$F$3:$F$178='面板-景气指数'!$J59)*('面板-分位数'!$E$3:$E$178)*('面板-分位数'!G$3:G$178))/SUMIFS('面板-分位数'!$E:$E,'面板-分位数'!$F:$F,'面板-景气指数'!$J59)} -> 0.55433333 | N59: {=SUMPRODUCT(('面板-分位数'!$F$3:$F$178='面板-景气指数'!$J59)*('面板-分位数'!$E$3:$E$178)*('面板-分位数'!H$3:H$178))/SUMIFS('面板-分位数'!$E:$E,'面板-分位数'!$F:$F,'面板-景气指数'!$J59)} -> 0.58266667 | O59: {=SUMPRODUCT(('面板-分位数'!$F$3:$F$178='面板-景气指数'!$J59)*('面板-分位数'!$E$3:$E$178)*('面板-分位数'!I$3:I$178))/SUMIFS('面板-分位数'!$E:$E,'面板-分位数'!$F:$F,'面板-景气指数'!$J59)} -> 0.61566667 | P59: {=SUMPRODUCT(('面板-分位数'!$F$3:$F$178='面板-景气指数'!$J59)*('面板-分位数'!$E$3:$E$178)*('面板-分位数'!J$3:J$178))/SUMIFS('面板-分位数'!$E:$E,'面板-分位数'!$F:$F,'面板-景气指数'!$J59)} -> 0.60266667 | Q59: {=SUMPRODUCT(('面板-分位数'!$F$3:$F$178='面板-景气指数'!$J59)*('面板-分位数'!$E$3:$E$178)*('面板-分位数'!K$3:K$178))/SUMIFS('面板-分位数'!$E:$E,'面板-分位数'!$F:$F,'面板-景气指数'!$J59)} -> 0.62733333 | R59: {=SUMPRODUCT(('面板-分位数'!$F$3:$F$178='面板-景气指数'!$J59)*('面板-分位数'!$E$3:$E$178)*('面板-分位数'!L$3:L$178))/SUMIFS('面板-分位数'!$E:$E,'面板-分位数'!$F:$F,'面板-景气指数'!$J59)} -> 0.628 | S59: {=SUMPRODUCT(('面板-分位数'!$F$3:$F$178='面板-景气指数'!$J59)*('面板-分位数'!$E$3:$E$178)*('面板-分位数'!M$3:M$178))/SUMIFS('面板-分位数'!$E:$E,'面板-分位数'!$F:$F,'面板-景气指数'!$J59)} -> 0.64933333 | T59: {=SUMPRODUCT(('面板-分位数'!$F$3:$F$178='面板-景气指数'!$J59)*('面板-分位数'!$E$3:$E$178)*('面板-分位数'!N$3:N$178))/SUMIFS('面板-分位数'!$E:$E,'面板-分位数'!$F:$F,'面板-景气指数'!$J59)} -> 0.69266667 | ... CD59: {=SUMPRODUCT(('面板-分位数'!$F$3:$F$178='面板-景气指数'!$J59)*('面板-分位数'!$E$3:$E$178)*('面板-分位数'!BX$3:BX$178))/SUMIFS('面板-分位数'!$E:$E,'面板-分位数'!$F:$F,'面板-景气指数'!$J59)} -> 0.60866667
... J83: 储能下游 | L83: =(M83-O83)*100 -> 3.7 | M83: {=SUMPRODUCT(('面板-分位数'!$F$3:$F$178='面板-景气指数'!$J83)*('面板-分位数'!$E$3:$E$178)*('面板-分位数'!G$3:G$178))/SUMIFS('面板-分位数'!$E:$E,'面板-分位数'!$F:$F,'面板-景气指数'!$J83)} -> 0.66725 | N83: {=SUMPRODUCT(('面板-分位数'!$F$3:$F$178='面板-景气指数'!$J83)*('面板-分位数'!$E$3:$E$178)*('面板-分位数'!H$3:H$178))/SUMIFS('面板-分位数'!$E:$E,'面板-分位数'!$F:$F,'面板-景气指数'!$J83)} -> 0.66725 | O83: {=SUMPRODUCT(('面板-分位数'!$F$3:$F$178='面板-景气指数'!$J83)*('面板-分位数'!$E$3:$E$178)*('面板-分位数'!I$3:I$178))/SUMIFS('面板-分位数'!$E:$E,'面板-分位数'!$F:$F,'面板-景气指数'!$J83)} -> 0.63025 | P83: {=SUMPRODUCT(('面板-分位数'!$F$3:$F$178='面板-景气指数'!$J83)*('面板-分位数'!$E$3:$E$178)*('面板-分位数'!J$3:J$178))/SUMIFS('面板-分位数'!$E:$E,'面板-分位数'!$F:$F,'面板-景气指数'!$J83)} -> 0.67891667 | Q83: {=SUMPRODUCT(('面板-分位数'!$F$3:$F$178='面板-景气指数'!$J83)*('面板-分位数'!$E$3:$E$178)*('面板-分位数'!K$3:K$178))/SUMIFS('面板-分位数'!$E:$E,'面板-分位数'!$F:$F,'面板-景气指数'!$J83)} -> 0.74016667 | R83: {=SUMPRODUCT(('面板-分位数'!$F$3:$F$178='面板-景气指数'!$J83)*('面板-分位数'!$E$3:$E$178)*('面板-分位数'!L$3:L$178))/SUMIFS('面板-分位数'!$E:$E,'面板-分位数'!$F:$F,'面板-景气指数'!$J83)} -> 0.78691667 | S83: {=SUMPRODUCT(('面板-分位数'!$F$3:$F$178='面板-景气指数'!$J83)*('面板-分位数'!$E$3:$E$178)*('面板-分位数'!M$3:M$178))/SUMIFS('面板-分位数'!$E:$E,'面板-分位数'!$F:$F,'面板-景气指数'!$J83)} -> 0.80366667 | T83: {=SUMPRODUCT(('面板-分位数'!$F$3:$F$178='面板-景气指数'!$J83)*('面板-分位数'!$E$3:$E$178)*('面板-分位数'!N$3:N$178))/SUMIFS('面板-分位数'!$E:$E,'面板-分位数'!$F:$F,'面板-景气指数'!$J83)} -> 0.82358333 | ... CD83: {=SUMPRODUCT(('面板-分位数'!$F$3:$F$178='面板-景气指数'!$J83)*('面板-分位数'!$E$3:$E$178)*('面板-分位数'!BX$3:BX$178))/SUMIFS('面板-分位数'!$E:$E,'面板-分位数'!$F:$F,'面板-景气指数'!$J83)} -> 0.52475
J84: 上游 | M84: =AVERAGE(M48,M51,M56,M59,M62,M69,M72) -> 0.64946429 | N84: =AVERAGE(N48,N51,N56,N59,N62,N69,N72) -> 0.65732143 | O84: =AVERAGE(O48,O51,O56,O59,O62,O69,O72) -> 0.69967857 | P84: =AVERAGE(P48,P51,P56,P59,P62,P69,P72) -> 0.70977381 | Q84: =AVERAGE(Q48,Q51,Q56,Q59,Q62,Q69,Q72) -> 0.72702381 | R84: =AVERAGE(R48,R51,R56,R59,R62,R69,R72) -> 0.7262619 | S84: =AVERAGE(S48,S51,S56,S59,S62,S69,S72) -> 0.71914286 | T84: =AVERAGE(T48,T51,T56,T59,T62,T69,T72) -> 0.74932143 | ... CD84: =AVERAGE(CD48,CD51,CD56,CD59,CD62,CD69,CD72) -> 0.44670238
J85: 中游 | M85: =AVERAGE(M49,M52,M53,M57,M60,M63,M70,M73) -> 0.45529208 | N85: =AVERAGE(N49,N52,N53,N57,N60,N63,N70,N73) -> 0.45488813 | O85: =AVERAGE(O49,O52,O53,O57,O60,O63,O70,O73) -> 0.4835645 | P85: =AVERAGE(P49,P52,P53,P57,P60,P63,P70,P73) -> 0.49184366 | Q85: =AVERAGE(Q49,Q52,Q53,Q57,Q60,Q63,Q70,Q73) -> 0.50152008 | R85: =AVERAGE(R49,R52,R53,R57,R60,R63,R70,R73) -> 0.49334008 | S85: =AVERAGE(S49,S52,S53,S57,S60,S63,S70,S73) -> 0.53630207 | T85: =AVERAGE(T49,T52,T53,T57,T60,T63,T70,T73) -> 0.64614287 | ... CD85: =AVERAGE(CD49,CD52,CD53,CD57,CD60,CD63,CD70,CD73) -> 0.4863647
J86: 下游 | M86: =AVERAGEIFS(M$48:M$83,$J$48:$J$83,"*下游*") -> 0.46183611 | N86: =AVERAGEIFS(N$48:N$83,$J$48:$J$83,"*下游*") -> 0.46183611 | O86: =AVERAGEIFS(O$48:O$83,$J$48:$J$83,"*下游*") -> 0.46130833 | P86: =AVERAGEIFS(P$48:P$83,$J$48:$J$83,"*下游*") -> 0.418475 | Q86: =AVERAGEIFS(Q$48:Q$83,$J$48:$J$83,"*下游*") -> 0.37776667 | R86: =AVERAGEIFS(R$48:R$83,$J$48:$J$83,"*下游*") -> 0.32923611 | S86: =AVERAGEIFS(S$48:S$83,$J$48:$J$83,"*下游*") -> 0.28452778 | T86: =AVERAGEIFS(T$48:T$83,$J$48:$J$83,"*下游*") -> 0.30746944 | ... CD86: =AVERAGEIFS(CD$48:CD$83,$J$48:$J$83,"*下游*") -> 0.46640833
J88: 2G | M88: =AVERAGEIFS(M$33:M$46,$K$33:$K$46,$J88) -> 0.60743296 | N88: =AVERAGEIFS(N$33:N$46,$K$33:$K$46,$J88) -> 0.60933868 | O88: =AVERAGEIFS(O$33:O$46,$K$33:$K$46,$J88) -> 0.6320856 | P88: =AVERAGEIFS(P$33:P$46,$K$33:$K$46,$J88) -> 0.63407746 | Q88: =AVERAGEIFS(Q$33:Q$46,$K$33:$K$46,$J88) -> 0.65083894 | R88: =AVERAGEIFS(R$33:R$46,$K$33:$K$46,$J88) -> 0.68353873 | S88: =AVERAGEIFS(S$33:S$46,$K$33:$K$46,$J88) -> 0.67507819 | T88: =AVERAGEIFS(T$33:T$46,$K$33:$K$46,$J88) -> 0.68756337 | ... CD88: =AVERAGEIFS(CD$33:CD$46,$K$33:$K$46,$J88) -> 0.5246433
J89: 2B | M89: =AVERAGEIFS(M$33:M$46,$K$33:$K$46,$J89) -> 0.45207217 | N89: =AVERAGEIFS(N$33:N$46,$K$33:$K$46,$J89) -> 0.45277435 | O89: =AVERAGEIFS(O$33:O$46,$K$33:$K$46,$J89) -> 0.43794232 | P89: =AVERAGEIFS(P$33:P$46,$K$33:$K$46,$J89) -> 0.40897645 | Q89: =AVERAGEIFS(Q$33:Q$46,$K$33:$K$46,$J89) -> 0.42980261 | R89: =AVERAGEIFS(R$33:R$46,$K$33:$K$46,$J89) -> 0.42197333 | S89: =AVERAGEIFS(S$33:S$46,$K$33:$K$46,$J89) -> 0.46587804 | T89: =AVERAGEIFS(T$33:T$46,$K$33:$K$46,$J89) -> 0.613175 | ... CD89: =AVERAGEIFS(CD$33:CD$46,$K$33:$K$46,$J89) -> 0.48239841
J90: 2C | M90: =AVERAGEIFS(M$33:M$46,$K$33:$K$46,$J90) -> 0.40361008 | N90: =AVERAGEIFS(N$33:N$46,$K$33:$K$46,$J90) -> 0.39394504 | O90: =AVERAGEIFS(O$33:O$46,$K$33:$K$46,$J90) -> 0.5056752 | P90: =AVERAGEIFS(P$33:P$46,$K$33:$K$46,$J90) -> 0.48740672 | Q90: =AVERAGEIFS(Q$33:Q$46,$K$33:$K$46,$J90) -> 0.43513519 | R90: =AVERAGEIFS(R$33:R$46,$K$33:$K$46,$J90) -> 0.37131476 | S90: =AVERAGEIFS(S$33:S$46,$K$33:$K$46,$J90) -> 0.40730778 | T90: =AVERAGEIFS(T$33:T$46,$K$33:$K$46,$J90) -> 0.4821556 | ... CD90: =AVERAGEIFS(CD$33:CD$46,$K$33:$K$46,$J90) -> 0.43353197

Sheet 面板-分位数
A2: 产业链 | B2: 环节 | C2: 细分环节 | D2: 同步指标 | E2: 权重 | G2: 44865 | H2: 44834 | I2: 44804 | J2: 44773 | K2: 44742 | L2: 44712 | M2: 44681 | N2: 44651 | O2: 44620 | P2: 44592 | Q2: 44561 | R2: 44530 | S2: 44500 | T2: 44469 | U2: 44439 | V2: 44408 | W2: 44377 | X2: 44347 | Y2: 44316 | Z2: 44286 | AA2: 44255 | AB2: 44227 | AC2: 44196 | AD2: 44165 | AE2: 44135 | AF2: 44104 | AG2: 44074 | AH2: 44043 | AI2: 44012 | AJ2: 43982 | AK2: 43951 | AL2: 43921 | AM2: 43890 | AN2: 43861 | AO2: 43830 | AP2: 43799 | AQ2: 43769 | AR2: 43738 | AS2: 43708 | AT2: 43677 | AU2: 43646 | AV2: 43616 | AW2: 43585 | AX2: 43555 | AY2: 43524 | AZ2: 43496 | BA2: 43465 | BB2: 43434 | BC2: 43404 | BD2: 43373 | BE2: 43343 | BF2: 43312 | BG2: 43281 | BH2: 43251 | BI2: 43220 | BJ2: 43190 | BK2: 43159 | BL2: 43131 | BM2: 43100 | BN2: 43069 | BO2: 43039 | BP2: 43008 | BQ2: 42978 | BR2: 42947 | BS2: 42916 | BT2: 42886 | BU2: 42855 | BV2: 42825 | BW2: 42794 | BX2: 42766
A3: 锂电 | B3: 上游 | C3: 钴精矿 | D3: 华东钴精矿价格 | E3: =0.5/19 -> 0.026315789 | F3: =A3&B3 -> 锂电上游 | G3: =IFERROR(_xlfn.PERCENTRANK.INC('面板-MA'!3:3,'面板-MA'!E3),0.5) -> 0.608 | H3: =IFERROR(_xlfn.PERCENTRANK.INC('面板-MA'!3:3,'面板-MA'!F3),0.5) -> 0.579 | I3: =IFERROR(_xlfn.PERCENTRANK.INC('面板-MA'!3:3,'面板-MA'!G3),0.5) -> 0.652 | J3: =IFERROR(_xlfn.PERCENTRANK.INC('面板-MA'!3:3,'面板-MA'!H3),0.5) -> 0.739 | K3: =IFERROR(_xlfn.PERCENTRANK.INC('面板-MA'!3:3,'面板-MA'!I3),0.5) -> 0.84 | L3: =IFERROR(_xlfn.PERCENTRANK.INC('面板-MA'!3:3,'面板-MA'!J3),0.5) -> 0.884 | M3: =IFERROR(_xlfn.PERCENTRANK.INC('面板-MA'!3:3,'面板-MA'!K3),0.5) -> 0.869 | N3: =IFERROR(_xlfn.PERCENTRANK.INC('面板-MA'!3:3,'面板-MA'!L3),0.5) -> 0.826 | ... BX3: =IFERROR(_xlfn.PERCENTRANK.INC('面板-MA'!3:3,'面板-MA'!BV3),0.5) -> 0
A4: 锂电 | B4: 上游 | C4: 锂盐-氢氧化锂 | D4: 电池级氢氧化锂价格（≥56.5%） | E4: =0.5/19 -> 0.026315789 | F4: =A4&B4 -> 锂电上游 | G4: =IFERROR(_xlfn.PERCENTRANK.INC('面板-MA'!4:4,'面板-MA'!E4),0.5) -> 1 | H4: =IFERROR(_xlfn.PERCENTRANK.INC('面板-MA'!4:4,'面板-MA'!F4),0.5) -> 0.969 | I4: =IFERROR(_xlfn.PERCENTRANK.INC('面板-MA'!4:4,'面板-MA'!G4),0.5) -> 0.939 | J4: =IFERROR(_xlfn.PERCENTRANK.INC('面板-MA'!4:4,'面板-MA'!H4),0.5) -> 0.909 | K4: =IFERROR(_xlfn.PERCENTRANK.INC('面板-MA'!4:4,'面板-MA'!I4),0.5) -> 0.924 | L4: =IFERROR(_xlfn.PERCENTRANK.INC('面板-MA'!4:4,'面板-MA'!J4),0.5) -> 0.954 | M4: =IFERROR(_xlfn.PERCENTRANK.INC('面板-MA'!4:4,'面板-MA'!K4),0.5) -> 0.984 | N4: =IFERROR(_xlfn.PERCENTRANK.INC('面板-MA'!4:4,'面板-MA'!L4),0.5) -> 0.893 | ... BX4: =IFERROR(_xlfn.PERCENTRANK.INC('面板-MA'!4:4,'面板-MA'!BV4),0.5) -> 0.5
A5: 锂电 | B5: 上游 | C5: 锂盐-碳酸锂 | D5: 电池级碳酸锂价格 | E5: =0.5/19 -> 0.026315789 | F5: =A5&B5 -> 锂电上游 | G5: =IFERROR(_xlfn.PERCENTRANK.INC('面板-MA'!5:5,'面板-MA'!E5),0.5) -> 1 | H5: =IFERROR(_xlfn.PERCENTRANK.INC('面板-MA'!5:5,'面板-MA'!F5),0.5) -> 0.971 | I5: =IFERROR(_xlfn.PERCENTRANK.INC('面板-MA'!5:5,'面板-MA'!G5),0.5) -> 0.956 | J5: =IFERROR(_xlfn.PERCENTRANK.INC('面板-MA'!5:5,'面板-MA'!H5),0.5) -> 0.942 | K5: =IFERROR(_xlfn.PERCENTRANK.INC('面板-MA'!5:5,'面板-MA'!I5),0.5) -> 0.898 | L5: =IFERROR(_xlfn.PERCENTRANK.INC('面板-MA'!5:5,'面板-MA'!J5),0.5) -> 0.927 | M5: =IFERROR(_xlfn.PERCENTRANK.INC('面板-MA'!5:5,'面板-MA'!K5),0.5) -> 0.985 | N5: =IFERROR(_xlfn.PERCENTRANK.INC('面板-MA'!5:5,'面板-MA'!L5),0.5) -> 0.913 | ... BX5: =IFERROR(_xlfn.PERCENTRANK.INC('面板-MA'!5:5,'面板-MA'!BV5),0.5) -> 0.565
A6: 锂电 | B6: 上游 | C6: 三元前驱体（镍钴锰） | D6: 三元前驱体价格（523) | E6: =0.5/19 -> 0.026315789 | F6: =A6&B6 -> 锂电上游 | G6: =IFERROR(_xlfn.PERCENTRANK.INC('面板-MA'!6:6,'面板-MA'!E6),0.5) -> 0.536 | H6: =IFERROR(_xlfn.PERCENTRANK.INC('面板-MA'!6:6,'面板-MA'!F6),0.5) -> 0.521 | I6: =IFERROR(_xlfn.PERCENTRANK.INC('面板-MA'!6:6,'面板-MA'!G6),0.5) -> 0.608 | J6: =IFERROR(_xlfn.PERCENTRANK.INC('面板-MA'!6:6,'面板-MA'!H6),0.5) -> 0.768 | K6: =IFERROR(_xlfn.PERCENTRANK.INC('面板-MA'!6:6,'面板-MA'!I6),0.5) -> 0.927 | L6: =IFERROR(_xlfn.PERCENTRANK.INC('面板-MA'!6:6,'面板-MA'!J6),0.5) -> 0.985 | M6: =IFERROR(_xlfn.PERCENTRANK.INC('面板-MA'!6:6,'面板-MA'!K6),0.5) -> 1 | N6: =IFERROR(_xlfn.PERCENTRANK.INC('面板-MA'!6:6,'面板-MA'!L6),0.5) -> 0.956 | ... BX6: =IFERROR(_xlfn.PERCENTRANK.INC('面板-MA'!6:6,'面板-MA'!BV6),0.5) -> 0.13
A7: 锂电 | B7: 上游 | C7: 电解液溶剂（DMC) | D7: DMC价格 | E7: =0.5/19 -> 0.026315789 | F7: =A7&B7 -> 锂电上游 | G7: =IFERROR(_xlfn.PERCENTRANK.INC('面板-MA'!7:7,'面板-MA'!E7),0.5) -> 0.246 | H7: =IFERROR(_xlfn.PERCENTRANK.INC('面板-MA'!7:7,'面板-MA'!F7),0.5) -> 0.333 | I7: =IFERROR(_xlfn.PERCENTRANK.INC('面板-MA'!7:7,'面板-MA'!G7),0.5) -> 0.362 | J7: =IFERROR(_xlfn.PERCENTRANK.INC('面板-MA'!7:7,'面板-MA'!H7),0.5) -> 0.449 | K7: =IFERROR(_xlfn.PERCENTRANK.INC('面板-MA'!7:7,'面板-MA'!I7),0.5) -> 0.55 | L7: =IFERROR(_xlfn.PERCENTRANK.INC('面板-MA'!7:7,'面板-MA'!J7),0.5) -> 0.608 | M7: =IFERROR(_xlfn.PERCENTRANK.INC('面板-MA'!7:7,'面板-MA'!K7),0.5) -> 0.869 | N7: =IFERROR(_xlfn.PERCENTRANK.INC('面板-MA'!7:7,'面板-MA'!L7),0.5) -> 0.927 | ... BX7: =IFERROR(_xlfn.PERCENTRANK.INC('面板-MA'!7:7,'面板-MA'!BV7),0.5) -> 0.159
A8: 锂电 | B8: 上游 | C8: 电解液溶质（六氟磷酸锂） | D8: 六氟磷酸锂价格 | E8: =0.5/19 -> 0.026315789 | F8: =A8&B8 -> 锂电上游 | G8: =IFERROR(_xlfn.PERCENTRANK.INC('面板-MA'!8:8,'面板-MA'!E8),0.5) -> 0.782 | H8: =IFERROR(_xlfn.PERCENTRANK.INC('面板-MA'!8:8,'面板-MA'!F8),0.5) -> 0.724 | I8: =IFERROR(_xlfn.PERCENTRANK.INC('面板-MA'!8:8,'面板-MA'!G8),0.5) -> 0.71 | J8: =IFERROR(_xlfn.PERCENTRANK.INC('面板-MA'!8:8,'面板-MA'!H8),0.5) -> 0.695 | K8: =IFERROR(_xlfn.PERCENTRANK.INC('面板-MA'!8:8,'面板-MA'!I8),0.5) -> 0.753 | L8: =IFERROR(_xlfn.PERCENTRANK.INC('面板-MA'!8:8,'面板-MA'!J8),0.5) -> 0.826 | M8: =IFERROR(_xlfn.PERCENTRANK.INC('面板-MA'!8:8,'面板-MA'!K8),0.5) -> 0.927 | N8: =IFERROR(_xlfn.PERCENTRANK.INC('面板-MA'!8:8,'面板-MA'!L8),0.5) -> 0.971 | ... BX8: =IFERROR(_xlfn.PERCENTRANK.INC('面板-MA'!8:8,'面板-MA'!BV8),0.5) -> 0.855
A9: 锂电 | B9: 中游 | C9: 锂电设备 | D9: 锂电设备财报营收 | E9: =0.5/19 -> 0.026315789 | F9: =A9&B9 -> 锂电中游 | G9: =IFERROR(_xlfn.PERCENTRANK.INC('面板-MA'!9:9,'面板-MA'!E9),0.5) -> 0.716 | H9: =IFERROR(_xlfn.PERCENTRANK.INC('面板-MA'!9:9,'面板-MA'!F9),0.5) -> 0.716 | I9: =IFERROR(_xlfn.PERCENTRANK.INC('面板-MA'!9:9,'面板-MA'!G9),0.5) -> 0.716 | J9: =IFERROR(_xlfn.PERCENTRANK.INC('面板-MA'!9:9,'面板-MA'!H9),0.5) -> 0.895 | K9: =IFERROR(_xlfn.PERCENTRANK.INC('面板-MA'!9:9,'面板-MA'!I9),0.5) -> 0.895 | L9: =IFERROR(_xlfn.PERCENTRANK.INC('面板-MA'!9:9,'面板-MA'!J9),0.5) -> 0.97 | M9: =IFERROR(_xlfn.PERCENTRANK.INC('面板-MA'!9:9,'面板-MA'!K9),0.5) -> 0.97 | N9: =IFERROR(_xlfn.PERCENTRANK.INC('面板-MA'!9:9,'面板-MA'!L9),0.5) -> 0.97 | ... BX9: =IFERROR(_xlfn.PERCENTRANK.INC('面板-MA'!9:9,'面板-MA'!BV9),0.5) -> 0.5
A10: 锂电 | B10: 中游 | C10: 正极材料-磷酸铁锂 | D10: 磷酸铁锂产量 | E10: =0.5/19 -> 0.026315789 | F10: =A10&B10 -> 锂电中游 | G10: =IFERROR(_xlfn.PERCENTRANK.INC('面板-MA'!10:10,'面板-MA'!E10),0.5) -> 0.826 | H10: =IFERROR(_xlfn.PERCENTRANK.INC('面板-MA'!10:10,'面板-MA'!F10),0.5) -> 0.782 | I10: =IFERROR(_xlfn.PERCENTRANK.INC('面板-MA'!10:10,'面板-MA'!G10),0.5) -> 0.681 | J10: =IFERROR(_xlfn.PERCENTRANK.INC('面板-MA'!10:10,'面板-MA'!H10),0.5) -> 0.71 | K10: =IFERROR(_xlfn.PERCENTRANK.INC('面板-MA'!10:10,'面板-MA'!I10),0.5) -> 0.768 | L10: =IFERROR(_xlfn.PERCENTRANK.INC('面板-MA'!10:10,'面板-MA'!J10),0.5) -> 0.724 | M10: =IFERROR(_xlfn.PERCENTRANK.INC('面板-MA'!10:10,'面板-MA'!K10),0.5) -> 0.695 | N10: =IFERROR(_xlfn.PERCENTRANK.INC('面板-MA'!10:10,'面板-MA'!L10),0.5) -> 0.753 | ... BX10: =IFERROR(_xlfn.PERCENTRANK.INC('面板-MA'!10:10,'面板-MA'!BV10),0.5) -> 0.173
A11: 锂电 | B11: 中游 | C11: 正极材料-三元材料 | D11: 三元材料产量 | E11: =0.5/19 -> 0.026315789 | F11: =A11&B11 -> 锂电中游 | G11: =IFERROR(_xlfn.PERCENTRANK.INC('面板-MA'!11:11,'面板-MA'!E11),0.5) -> 0.55 | H11: =IFERROR(_xlfn.PERCENTRANK.INC('面板-MA'!11:11,'面板-MA'!F11),0.5) -> 0.536 | I11: =IFERROR(_xlfn.PERCENTRANK.INC('面板-MA'!11:11,'面板-MA'!G11),0.5) -> 0.463 | J11: =IFERROR(_xlfn.PERCENTRANK.INC('面板-MA'!11:11,'面板-MA'!H11),0.5) -> 0.391 | K11: =IFERROR(_xlfn.PERCENTRANK.INC('面板-MA'!11:11,'面板-MA'!I11),0.5) -> 0.362 | L11: =IFERROR(_xlfn.PERCENTRANK.INC('面板-MA'!11:11,'面板-MA'!J11),0.5) -> 0.478 | M11: =IFERROR(_xlfn.PERCENTRANK.INC('面板-MA'!11:11,'面板-MA'!K11),0.5) -> 0.565 | N11: =IFERROR(_xlfn.PERCENTRANK.INC('面板-MA'!11:11,'面板-MA'!L11),0.5) -> 0.681 | ... BX11: =IFERROR(_xlfn.PERCENTRANK.INC('面板-MA'!11:11,'面板-MA'!BV11),0.5) -> 0.652
A12: 锂电 | B12: 中游 | C12: 正极材料-钴酸锂 | D12: 钴酸锂产量 | E12: =0.5/19 -> 0.026315789 | F12: =A12&B12 -> 锂电中游 | G12: =IFERROR(_xlfn.PERCENTRANK.INC('面板-MA'!12:12,'面板-MA'!E12),0.5) -> 0.043 | H12: =IFERROR(_xlfn.PERCENTRANK.INC('面板-MA'!12:12,'面板-MA'!F12),0.5) -> 0.014 | I12: =IFERROR(_xlfn.PERCENTRANK.INC('面板-MA'!12:12,'面板-MA'!G12),0.5) -> 0 | J12: =IFERROR(_xlfn.PERCENTRANK.INC('面板-MA'!12:12,'面板-MA'!H12),0.5) -> 0.028 | K12: =IFERROR(_xlfn.PERCENTRANK.INC('面板-MA'!12:12,'面板-MA'!I12),0.5) -> 0.057 | L12: =IFERROR(_xlfn.PERCENTRANK.INC('面板-MA'!12:12,'面板-MA'!J12),0.5) -> 0.072 | M12: =IFERROR(_xlfn.PERCENTRANK.INC('面板-MA'!12:12,'面板-MA'!K12),0.5) -> 0.173 | N12: =IFERROR(_xlfn.PERCENTRANK.INC('面板-MA'!12:12,'面板-MA'!L12),0.5) -> 0.347 | ... BX12: =IFERROR(_xlfn.PERCENTRANK.INC('面板-MA'!12:12,'面板-MA'!BV12),0.5) -> 0.637
A13: 锂电 | B13: 中游 | C13: 负级材料 | D13: 中端人造石墨负极价格 | E13: =0.5/19 -> 0.026315789 | F13: =A13&B13 -> 锂电中游 | G13: =IFERROR(_xlfn.PERCENTRANK.INC('面板-MA'!13:13,'面板-MA'!E13),0.5) -> 0.898 | H13: =IFERROR(_xlfn.PERCENTRANK.INC('面板-MA'!13:13,'面板-MA'!F13),0.5) -> 0.971 | I13: =IFERROR(_xlfn.PERCENTRANK.INC('面板-MA'!13:13,'面板-MA'!G13),0.5) -> 0.971 | J13: =IFERROR(_xlfn.PERCENTRANK.INC('面板-MA'!13:13,'面板-MA'!H13),0.5) -> 0.971 | K13: =IFERROR(_xlfn.PERCENTRANK.INC('面板-MA'!13:13,'面板-MA'!I13),0.5) -> 0.927 | L13: =IFERROR(_xlfn.PERCENTRANK.INC('面板-MA'!13:13,'面板-MA'!J13),0.5) -> 0.869 | M13: =IFERROR(_xlfn.PERCENTRANK.INC('面板-MA'!13:13,'面板-MA'!K13),0.5) -> 0.84 | N13: =IFERROR(_xlfn.PERCENTRANK.INC('面板-MA'!13:13,'面板-MA'!L13),0.5) -> 0.797 | ... BX13: =IFERROR(_xlfn.PERCENTRANK.INC('面板-MA'!13:13,'面板-MA'!BV13),0.5) -> 0.449
A14: 锂电 | B14: 中游 | C14: 电解液 | D14: 电解液产量 | E14: =0.5/19 -> 0.026315789 | F14: =A14&B14 -> 锂电中游 | G14: =IFERROR(_xlfn.PERCENTRANK.INC('面板-MA'!14:14,'面板-MA'!E14),0.5) -> 0.855 | H14: =IFERROR(_xlfn.PERCENTRANK.INC('面板-MA'!14:14,'面板-MA'!F14),0.5) -> 0.956 | I14: =IFERROR(_xlfn.PERCENTRANK.INC('面板-MA'!14:14,'面板-MA'!G14),0.5) -> 0.971 | J14: =IFERROR(_xlfn.PERCENTRANK.INC('面板-MA'!14:14,'面板-MA'!H14),0.5) -> 0.869 | K14: =IFERROR(_xlfn.PERCENTRANK.INC('面板-MA'!14:14,'面板-MA'!I14),0.5) -> 0.71 | L14: =IFERROR(_xlfn.PERCENTRANK.INC('面板-MA'!14:14,'面板-MA'!J14),0.5) -> 0.478 | M14: =IFERROR(_xlfn.PERCENTRANK.INC('面板-MA'!14:14,'面板-MA'!K14),0.5) -> 0.753 | N14: =IFERROR(_xlfn.PERCENTRANK.INC('面板-MA'!14:14,'面板-MA'!L14),0.5) -> 0.898 | ... BX14: =IFERROR(_xlfn.PERCENTRANK.INC('面板-MA'!14:14,'面板-MA'!BV14),0.5) -> 0.101
A15: 锂电 | B15: 中游 | C15: 隔膜 | D15: 隔膜产量 | E15: =0.5/19 -> 0.026315789 | F15: =A15&B15 -> 锂电中游 | G15: =IFERROR(_xlfn.PERCENTRANK.INC('面板-MA'!15:15,'面板-MA'!E15),0.5) -> 0.753 | H15: =IFERROR(_xlfn.PERCENTRANK.INC('面板-MA'!15:15,'面板-MA'!F15),0.5) -> 0.724 | I15: =IFERROR(_xlfn.PERCENTRANK.INC('面板-MA'!15:15,'面板-MA'!G15),0.5) -> 0.652 | J15: =IFERROR(_xlfn.PERCENTRANK.INC('面板-MA'!15:15,'面板-MA'!H15),0.5) -> 0.608 | K15: =IFERROR(_xlfn.PERCENTRANK.INC('面板-MA'!15:15,'面板-MA'!I15),0.5) -> 0.594 | L15: =IFERROR(_xlfn.PERCENTRANK.INC('面板-MA'!15:15,'面板-MA'!J15),0.5) -> 0.623 | M15: =IFERROR(_xlfn.PERCENTRANK.INC('面板-MA'!15:15,'面板-MA'!K15),0.5) -> 0.768 | N15: =IFERROR(_xlfn.PERCENTRANK.INC('面板-MA'!15:15,'面板-MA'!L15),0.5) -> 0.884 | ... BX15: =IFERROR(_xlfn.PERCENTRANK.INC('面板-MA'!15:15,'面板-MA'!BV15),0.5) -> 0.028
A16: 锂电 | B16: 中游 | C16: 辅材-铜箔 | D16: 电池级铜箔价格（8um) | E16: =0.5/19 -> 0.026315789 | F16: =A16&B16 -> 锂电中游 | G16: =IFERROR(_xlfn.PERCENTRANK.INC('面板-MA'!16:16,'面板-MA'!E16),0.5) -> 0.623 | H16: =IFERROR(_xlfn.PERCENTRANK.INC('面板-MA'!16:16,'面板-MA'!F16),0.5) -> 0.652 | I16: =IFERROR(_xlfn.PERCENTRANK.INC('面板-MA'!16:16,'面板-MA'!G16),0.5) -> 0.666 | J16: =IFERROR(_xlfn.PERCENTRANK.INC('面板-MA'!16:16,'面板-MA'!H16),0.5) -> 0.797 | K16: =IFERROR(_xlfn.PERCENTRANK.INC('面板-MA'!16:16,'面板-MA'!I16),0.5) -> 0.985 | L16: =IFERROR(_xlfn.PERCENTRANK.INC('面板-MA'!16:16,'面板-MA'!J16),0.5) -> 1 | M16: =IFERROR(_xlfn.PERCENTRANK.INC('面板-MA'!16:16,'面板-MA'!K16),0.5) -> 0.971 | N16: =IFERROR(_xlfn.PERCENTRANK.INC('面板-MA'!16:16,'面板-MA'!L16),0.5) -> 0.898 | ... BX16: =IFERROR(_xlfn.PERCENTRANK.INC('面板-MA'!16:16,'面板-MA'!BV16),0.5) -> 0.173
A17: 锂电 | B17: 中游 | C17: 辅材-铝箔 | D17: 辅材-铝箔财报营收 | E17: =0.5/19 -> 0.026315789 | F17: =A17&B17 -> 锂电中游 | G17: =IFERROR(_xlfn.PERCENTRANK.INC('面板-MA'!17:17,'面板-MA'!E17),0.5) -> 0.62 | H17: =IFERROR(_xlfn.PERCENTRANK.INC('面板-MA'!17:17,'面板-MA'!F17),0.5) -> 0.62 | I17: =IFERROR(_xlfn.PERCENTRANK.INC('面板-MA'!17:17,'面板-MA'!G17),0.5) -> 0.758 | J17: =IFERROR(_xlfn.PERCENTRANK.INC('面板-MA'!17:17,'面板-MA'!H17),0.5) -> 0.758 | K17: =IFERROR(_xlfn.PERCENTRANK.INC('面板-MA'!17:17,'面板-MA'!I17),0.5) -> 0.758 | L17: =IFERROR(_xlfn.PERCENTRANK.INC('面板-MA'!17:17,'面板-MA'!J17),0.5) -> 0.965 | M17: =IFERROR(_xlfn.PERCENTRANK.INC('面板-MA'!17:17,'面板-MA'!K17),0.5) -> 0.965 | N17: =IFERROR(_xlfn.PERCENTRANK.INC('面板-MA'!17:17,'面板-MA'!L17),0.5) -> 0.965 | ... BX17: =IFERROR(_xlfn.PERCENTRANK.INC('面板-MA'!17:17,'面板-MA'!BV17),0.5) -> 0.5
A18: 锂电 | B18: 中游 | C18: 辅材-导电剂（碳纳米管） | D18: 辅材-导电剂（碳纳米管）财报营收 | E18: =0.5/19 -> 0.026315789 | F18: =A18&B18 -> 锂电中游 | G18: =IFERROR(_xlfn.PERCENTRANK.INC('面板-MA'!18:18,'面板-MA'!E18),0.5) -> 0.568 | H18: =IFERROR(_xlfn.PERCENTRANK.INC('面板-MA'!18:18,'面板-MA'!F18),0.5) -> 0.568 | I18: =IFERROR(_xlfn.PERCENTRANK.INC('面板-MA'!18:18,'面板-MA'!G18),0.5) -> 0.603 | J18: =IFERROR(_xlfn.PERCENTRANK.INC('面板-MA'!18:18,'面板-MA'!H18),0.5) -> 0.603 | K18: =IFERROR(_xlfn.PERCENTRANK.INC('面板-MA'!18:18,'面板-MA'!I18),0.5) -> 0.603 | L18: =IFERROR(_xlfn.PERCENTRANK.INC('面板-MA'!18:18,'面板-MA'!J18),0.5) -> 0.655 | M18: =IFERROR(_xlfn.PERCENTRANK.INC('面板-MA'!18:18,'面板-MA'!K18),0.5) -> 0.655 | N18: =IFERROR(_xlfn.PERCENTRANK.INC('面板-MA'!18:18,'面板-MA'!L18),0.5) -> 0.655 | ... BX18: =IFERROR(_xlfn.PERCENTRANK.INC('面板-MA'!18:18,'面板-MA'!BV18),0.5) -> 0.5
A19: 锂电 | B19: 中游 | C19: 辅材-粘结剂（锂电级PVDF） | D19: 华东地区电池级PVDF价格 | E19: =0.5/19 -> 0.026315789 | F19: =A19&B19 -> 锂电中游 | G19: =IFERROR(_xlfn.PERCENTRANK.INC('面板-MA'!19:19,'面板-MA'!E19),0.5) -> 0.869 | H19: =IFERROR(_xlfn.PERCENTRANK.INC('面板-MA'!19:19,'面板-MA'!F19),0.5) -> 0.884 | I19: =IFERROR(_xlfn.PERCENTRANK.INC('面板-MA'!19:19,'面板-MA'!G19),0.5) -> 0.898 | J19: =IFERROR(_xlfn.PERCENTRANK.INC('面板-MA'!19:19,'面板-MA'!H19),0.5) -> 0.927 | K19: =IFERROR(_xlfn.PERCENTRANK.INC('面板-MA'!19:19,'面板-MA'!I19),0.5) -> 0.956 | L19: =IFERROR(_xlfn.PERCENTRANK.INC('面板-MA'!19:19,'面板-MA'!J19),0.5) -> 1 | M19: =IFERROR(_xlfn.PERCENTRANK.INC('面板-MA'!19:19,'面板-MA'!K19),0.5) -> 0.985 | N19: =IFERROR(_xlfn.PERCENTRANK.INC('面板-MA'!19:19,'面板-MA'!L19),0.5) -> 0.971 | ... BX19: =IFERROR(_xlfn.PERCENTRANK.INC('面板-MA'!19:19,'面板-MA'!BV19),0.5) -> 0.405
A20: 锂电 | B20: 中游 | C20: 薄膜电容 | D20: 薄膜电容财报营收 | E20: =0.5/19 -> 0.026315789 | F20: =A20&B20 -> 锂电中游 | G20: =IFERROR(_xlfn.PERCENTRANK.INC('面板-MA'!20:20,'面板-MA'!E20),0.5) -> 0.716 | H20: =IFERROR(_xlfn.PERCENTRANK.INC('面板-MA'!20:20,'面板-MA'!F20),0.5) -> 0.716 | I20: =IFERROR(_xlfn.PERCENTRANK.INC('面板-MA'!20:20,'面板-MA'!G20),0.5) -> 0.746 | J20: =IFERROR(_xlfn.PERCENTRANK.INC('面板-MA'!20:20,'面板-MA'!H20),0.5) -> 0.746 | K20: =IFERROR(_xlfn.PERCENTRANK.INC('面板-MA'!20:20,'面板-MA'!I20),0.5) -> 0.746 | L20: =IFERROR(_xlfn.PERCENTRANK.INC('面板-MA'!20:20,'面板-MA'!J20),0.5) -> 0.791 | M20: =IFERROR(_xlfn.PERCENTRANK.INC('面板-MA'!20:20,'面板-MA'!K20),0.5) -> 0.791 | N20: =IFERROR(_xlfn.PERCENTRANK.INC('面板-MA'!20:20,'面板-MA'!L20),0.5) -> 0.791 | ... BX20: =IFERROR(_xlfn.PERCENTRANK.INC('面板-MA'!20:20,'面板-MA'!BV20),0.5) -> 0.5
A21: 锂电 | B21: 中游 | C21: 电芯与Pack | D21: 动力电池装车量 | E21: =0.5/19 -> 0.026315789 | F21: =A21&B21 -> 锂电中游 | G21: =IFERROR(_xlfn.PERCENTRANK.INC('面板-MA'!21:21,'面板-MA'!E21),0.5) -> 0.543 | H21: =IFERROR(_xlfn.PERCENTRANK.INC('面板-MA'!21:21,'面板-MA'!F21),0.5) -> 0.543 | I21: =IFERROR(_xlfn.PERCENTRANK.INC('面板-MA'!21:21,'面板-MA'!G21),0.5) -> 0.614 | J21: =IFERROR(_xlfn.PERCENTRANK.INC('面板-MA'!21:21,'面板-MA'!H21),0.5) -> 0.649 | K21: =IFERROR(_xlfn.PERCENTRANK.INC('面板-MA'!21:21,'面板-MA'!I21),0.5) -> 0.596 | L21: =IFERROR(_xlfn.PERCENTRANK.INC('面板-MA'!21:21,'面板-MA'!J21),0.5) -> 0.403 | M21: =IFERROR(_xlfn.PERCENTRANK.INC('面板-MA'!21:21,'面板-MA'!K21),0.5) -> 0.508 | N21: =IFERROR(_xlfn.PERCENTRANK.INC('面板-MA'!21:21,'面板-MA'!L21),0.5) -> 0.736 | ... BX21: =IFERROR(_xlfn.PERCENTRANK.INC('面板-MA'!21:21,'面板-MA'!BV21),0.5) -> 0.5
A22: 锂电 | B22: 下游 | C22: 整车制造（电动车） | D22: 新能源乘用车销量（国内） | E22: 0.5 | F22: =A22&B22 -> 锂电下游 | G22: =IFERROR(_xlfn.PERCENTRANK.INC('面板-MA'!22:22,'面板-MA'!E22),0.5) -> 0.536 | H22: =IFERROR(_xlfn.PERCENTRANK.INC('面板-MA'!22:22,'面板-MA'!F22),0.5) -> 0.536 | I22: =IFERROR(_xlfn.PERCENTRANK.INC('面板-MA'!22:22,'面板-MA'!G22),0.5) -> 0.637 | J22: =IFERROR(_xlfn.PERCENTRANK.INC('面板-MA'!22:22,'面板-MA'!H22),0.5) -> 0.666 | K22: =IFERROR(_xlfn.PERCENTRANK.INC('面板-MA'!22:22,'面板-MA'!I22),0.5) -> 0.623 | L22: =IFERROR(_xlfn.PERCENTRANK.INC('面板-MA'!22:22,'面板-MA'!J22),0.5) -> 0.478 | M22: =IFERROR(_xlfn.PERCENTRANK.INC('面板-MA'!22:22,'面板-MA'!K22),0.5) -> 0.608 | N22: =IFERROR(_xlfn.PERCENTRANK.INC('面板-MA'!22:22,'面板-MA'!L22),0.5) -> 0.811 | ... BX22: =IFERROR(_xlfn.PERCENTRANK.INC('面板-MA'!22:22,'面板-MA'!BV22),0.5) -> 0.13
A23: 机器人 | B23: 上游 | C23: 稀土磁材 | D23: 氧化镨钕价格 | E23: =0.5/6 -> 0.083333333 | F23: =A23&B23 -> 机器人上游 | G23: =IFERROR(_xlfn.PERCENTRANK.INC('面板-MA'!23:23,'面板-MA'!E23),0.5) -> 0.84 | H23: =IFERROR(_xlfn.PERCENTRANK.INC('面板-MA'!23:23,'面板-MA'!F23),0.5) -> 0.855 | I23: =IFERROR(_xlfn.PERCENTRANK.INC('面板-MA'!23:23,'面板-MA'!G23),0.5) -> 0.884 | J23: =IFERROR(_xlfn.PERCENTRANK.INC('面板-MA'!23:23,'面板-MA'!H23),0.5) -> 0.942 | K23: =IFERROR(_xlfn.PERCENTRANK.INC('面板-MA'!23:23,'面板-MA'!I23),0.5) -> 0.956 | L23: =IFERROR(_xlfn.PERCENTRANK.INC('面板-MA'!23:23,'面板-MA'!J23),0.5) -> 0.927 | M23: =IFERROR(_xlfn.PERCENTRANK.INC('面板-MA'!23:23,'面板-MA'!K23),0.5) -> 0.971 | N23: =IFERROR(_xlfn.PERCENTRANK.INC('面板-MA'!23:23,'面板-MA'!L23),0.5) -> 1 | ... BX23: =IFERROR(_xlfn.PERCENTRANK.INC('面板-MA'!23:23,'面板-MA'!BV23),0.5) -> 0
A24: 机器人 | B24: 中游 | C24: 伺服系统 | D24: 安川+松下+台达订单量 | E24: =0.5/6 -> 0.083333333 | F24: =A24&B24 -> 机器人中游 | G24: =IFERROR(_xlfn.PERCENTRANK.INC('面板-MA'!24:24,'面板-MA'!E24),0.5) -> 0.06 | H24: =IFERROR(_xlfn.PERCENTRANK.INC('面板-MA'!24:24,'面板-MA'!F24),0.5) -> 0.06 | I24: =IFERROR(_xlfn.PERCENTRANK.INC('面板-MA'!24:24,'面板-MA'!G24),0.5) -> 0.121 | J24: =IFERROR(_xlfn.PERCENTRANK.INC('面板-MA'!24:24,'面板-MA'!H24),0.5) -> 0.181 | K24: =IFERROR(_xlfn.PERCENTRANK.INC('面板-MA'!24:24,'面板-MA'!I24),0.5) -> 0.151 | L24: =IFERROR(_xlfn.PERCENTRANK.INC('面板-MA'!24:24,'面板-MA'!J24),0.5) -> 0.03 | M24: =IFERROR(_xlfn.PERCENTRANK.INC('面板-MA'!24:24,'面板-MA'!K24),0.5) -> 0 | N24: =IFERROR(_xlfn.PERCENTRANK.INC('面板-MA'!24:24,'面板-MA'!L24),0.5) -> 0.212 | ... BX24: =IFERROR(_xlfn.PERCENTRANK.INC('面板-MA'!24:24,'面板-MA'!BV24),0.5) -> 0.5
A25: 机器人 | B25: 中游 | C25: 变频器 | D25: ABB+安川订单量 | E25: =0.5/6 -> 0.083333333 | F25: =A25&B25 -> 机器人中游 | G25: =IFERROR(_xlfn.PERCENTRANK.INC('面板-MA'!25:25,'面板-MA'!E25),0.5) -> 0.696 | H25: =IFERROR(_xlfn.PERCENTRANK.INC('面板-MA'!25:25,'面板-MA'!F25),0.5) -> 0.696 | I25: =IFERROR(_xlfn.PERCENTRANK.INC('面板-MA'!25:25,'面板-MA'!G25),0.5) -> 0.545 | J25: =IFERROR(_xlfn.PERCENTRANK.INC('面板-MA'!25:25,'面板-MA'!H25),0.5) -> 0.848 | K25: =IFERROR(_xlfn.PERCENTRANK.INC('面板-MA'!25:25,'面板-MA'!I25),0.5) -> 0.575 | L25: =IFERROR(_xlfn.PERCENTRANK.INC('面板-MA'!25:25,'面板-MA'!J25),0.5) -> 0.06 | M25: =IFERROR(_xlfn.PERCENTRANK.INC('面板-MA'!25:25,'面板-MA'!K25),0.5) -> 0.09 | N25: =IFERROR(_xlfn.PERCENTRANK.INC('面板-MA'!25:25,'面板-MA'!L25),0.5) -> 0.757 | ... BX25: =IFERROR(_xlfn.PERCENTRANK.INC('面板-MA'!25:25,'面板-MA'!BV25),0.5) -> 0.5
A26: 机器人 | B26: 中游 | C26: 减速器-RV减速器 | D26: 减速器-RV减速器财报营收 | E26: =0.5/6 -> 0.083333333 | F26: =A26&B26 -> 机器人中游 | G26: =IFERROR(_xlfn.PERCENTRANK.INC('面板-MA'!26:26,'面板-MA'!E26),0.5) -> 0.402 | H26: =IFERROR(_xlfn.PERCENTRANK.INC('面板-MA'!26:26,'面板-MA'!F26),0.5) -> 0.402 | I26: =IFERROR(_xlfn.PERCENTRANK.INC('面板-MA'!26:26,'面板-MA'!G26),0.5) -> 0.358 | J26: =IFERROR(_xlfn.PERCENTRANK.INC('面板-MA'!26:26,'面板-MA'!H26),0.5) -> 0.358 | K26: =IFERROR(_xlfn.PERCENTRANK.INC('面板-MA'!26:26,'面板-MA'!I26),0.5) -> 0.358 | L26: =IFERROR(_xlfn.PERCENTRANK.INC('面板-MA'!26:26,'面板-MA'!J26),0.5) -> 0.567 | M26: =IFERROR(_xlfn.PERCENTRANK.INC('面板-MA'!26:26,'面板-MA'!K26),0.5) -> 0.567 | N26: =IFERROR(_xlfn.PERCENTRANK.INC('面板-MA'!26:26,'面板-MA'!L26),0.5) -> 0.567 | ... BX26: =IFERROR(_xlfn.PERCENTRANK.INC('面板-MA'!26:26,'面板-MA'!BV26),0.5) -> 0.5
A27: 机器人 | B27: 中游 | C27: 减速器-谐波减速器 | D27: 减速器-谐波减速器财报营收 | E27: =0.5/6 -> 0.083333333 | F27: =A27&B27 -> 机器人中游 | G27: =IFERROR(_xlfn.PERCENTRANK.INC('面板-MA'!27:27,'面板-MA'!E27),0.5) -> 0.13 | H27: =IFERROR(_xlfn.PERCENTRANK.INC('面板-MA'!27:27,'面板-MA'!F27),0.5) -> 0.13 | I27: =IFERROR(_xlfn.PERCENTRANK.INC('面板-MA'!27:27,'面板-MA'!G27),0.5) -> 0.695 | J27: =IFERROR(_xlfn.PERCENTRANK.INC('面板-MA'!27:27,'面板-MA'!H27),0.5) -> 0.695 | K27: =IFERROR(_xlfn.PERCENTRANK.INC('面板-MA'!27:27,'面板-MA'!I27),0.5) -> 0.695 | L27: =IFERROR(_xlfn.PERCENTRANK.INC('面板-MA'!27:27,'面板-MA'!J27),0.5) -> 0.369 | M27: =IFERROR(_xlfn.PERCENTRANK.INC('面板-MA'!27:27,'面板-MA'!K27),0.5) -> 0.369 | N27: =IFERROR(_xlfn.PERCENTRANK.INC('面板-MA'!27:27,'面板-MA'!L27),0.5) -> 0.369 | ... BX27: =IFERROR(_xlfn.PERCENTRANK.INC('面板-MA'!27:27,'面板-MA'!BV27),0.5) -> 0.5
A28: 机器人 | B28: 中游 | C28: 控制器（PLC） | D28: 施耐德订单量 | E28: =0.5/6 -> 0.083333333 | F28: =A28&B28 -> 机器人中游 | G28: =IFERROR(_xlfn.PERCENTRANK.INC('面板-MA'!28:28,'面板-MA'!E28),0.5) -> 0.218 | H28: =IFERROR(_xlfn.PERCENTRANK.INC('面板-MA'!28:28,'面板-MA'!F28),0.5) -> 0.218 | I28: =IFERROR(_xlfn.PERCENTRANK.INC('面板-MA'!28:28,'面板-MA'!G28),0.5) -> 0.406 | J28: =IFERROR(_xlfn.PERCENTRANK.INC('面板-MA'!28:28,'面板-MA'!H28),0.5) -> 0.375 | K28: =IFERROR(_xlfn.PERCENTRANK.INC('面板-MA'!28:28,'面板-MA'!I28),0.5) -> 0.187 | L28: =IFERROR(_xlfn.PERCENTRANK.INC('面板-MA'!28:28,'面板-MA'!J28),0.5) -> 0.093 | M28: =IFERROR(_xlfn.PERCENTRANK.INC('面板-MA'!28:28,'面板-MA'!K28),0.5) -> 0.5 | N28: =IFERROR(_xlfn.PERCENTRANK.INC('面板-MA'!28:28,'面板-MA'!L28),0.5) -> 0.937 | ... BX28: =IFERROR(_xlfn.PERCENTRANK.INC('面板-MA'!28:28,'面板-MA'!BV28),0.5) -> 0.5
A29: 机器人 | B29: 中游 | C29: 机器人本体 | D29: 工业机器人产量 | E29: 0.5 | F29: =A29&B29 -> 机器人中游 | G29: =IFERROR(_xlfn.PERCENTRANK.INC('面板-MA'!29:29,'面板-MA'!E29),0.5) -> 0.338 | H29: =IFERROR(_xlfn.PERCENTRANK.INC('面板-MA'!29:29,'面板-MA'!F29),0.5) -> 0.338 | I29: =IFERROR(_xlfn.PERCENTRANK.INC('面板-MA'!29:29,'面板-MA'!G29),0.5) -> 0.235 | J29: =IFERROR(_xlfn.PERCENTRANK.INC('面板-MA'!29:29,'面板-MA'!H29),0.5) -> 0.279 | K29: =IFERROR(_xlfn.PERCENTRANK.INC('面板-MA'!29:29,'面板-MA'!I29),0.5) -> 0.205 | L29: =IFERROR(_xlfn.PERCENTRANK.INC('面板-MA'!29:29,'面板-MA'!J29),0.5) -> 0.058 | M29: =IFERROR(_xlfn.PERCENTRANK.INC('面板-MA'!29:29,'面板-MA'!K29),0.5) -> 0.308 | N29: =IFERROR(_xlfn.PERCENTRANK.INC('面板-MA'!29:29,'面板-MA'!L29),0.5) -> 0.529 | ... BX29: =IFERROR(_xlfn.PERCENTRANK.INC('面板-MA'!29:29,'面板-MA'!BV29),0.5) -> 0.5
A30: 机床 | B30: 中游 | C30: 主轴 | D30: 机床工具行业营收 | E30: =0.5/3 -> 0.16666667 | F30: =A30&B30 -> 机床中游 | G30: =IFERROR(_xlfn.PERCENTRANK.INC('面板-MA'!30:30,'面板-MA'!E30),0.5) -> 0.343 | H30: =IFERROR(_xlfn.PERCENTRANK.INC('面板-MA'!30:30,'面板-MA'!F30),0.5) -> 0.343 | I30: =IFERROR(_xlfn.PERCENTRANK.INC('面板-MA'!30:30,'面板-MA'!G30),0.5) -> 0.343 | J30: =IFERROR(_xlfn.PERCENTRANK.INC('面板-MA'!30:30,'面板-MA'!H30),0.5) -> 0.208 | K30: =IFERROR(_xlfn.PERCENTRANK.INC('面板-MA'!30:30,'面板-MA'!I30),0.5) -> 0.388 | L30: =IFERROR(_xlfn.PERCENTRANK.INC('面板-MA'!30:30,'面板-MA'!J30),0.5) -> 0.432 | M30: =IFERROR(_xlfn.PERCENTRANK.INC('面板-MA'!30:30,'面板-MA'!K30),0.5) -> 0.477 | N30: =IFERROR(_xlfn.PERCENTRANK.INC('面板-MA'!30:30,'面板-MA'!L30),0.5) -> 0.492 | ... BX30: =IFERROR(_xlfn.PERCENTRANK.INC('面板-MA'!30:30,'面板-MA'!BV30),0.5) -> 0.5
A31: 机床 | B31: 中游 | C31: 刀具 | D31: 机床工具行业营收 | E31: =0.5/3 -> 0.16666667 | F31: =A31&B31 -> 机床中游 | G31: =IFERROR(_xlfn.PERCENTRANK.INC('面板-MA'!31:31,'面板-MA'!E31),0.5) -> 0.343 | H31: =IFERROR(_xlfn.PERCENTRANK.INC('面板-MA'!31:31,'面板-MA'!F31),0.5) -> 0.343 | I31: =IFERROR(_xlfn.PERCENTRANK.INC('面板-MA'!31:31,'面板-MA'!G31),0.5) -> 0.343 | J31: =IFERROR(_xlfn.PERCENTRANK.INC('面板-MA'!31:31,'面板-MA'!H31),0.5) -> 0.208 | K31: =IFERROR(_xlfn.PERCENTRANK.INC('面板-MA'!31:31,'面板-MA'!I31),0.5) -> 0.388 | L31: =IFERROR(_xlfn.PERCENTRANK.INC('面板-MA'!31:31,'面板-MA'!J31),0.5) -> 0.432 | M31: =IFERROR(_xlfn.PERCENTRANK.INC('面板-MA'!31:31,'面板-MA'!K31),0.5) -> 0.477 | N31: =IFERROR(_xlfn.PERCENTRANK.INC('面板-MA'!31:31,'面板-MA'!L31),0.5) -> 0.492 | ... BX31: =IFERROR(_xlfn.PERCENTRANK.INC('面板-MA'!31:31,'面板-MA'!BV31),0.5) -> 0.5
A32: 机床 | B32: 中游 | C32: 变频器 | D32: ABB+安川订单量 | E32: =0.5/3 -> 0.16666667 | F32: =A32&B32 -> 机床中游 | G32: =IFERROR(_xlfn.PERCENTRANK.INC('面板-MA'!32:32,'面板-MA'!E32),0.5) -> 0.696 | H32: =IFERROR(_xlfn.PERCENTRANK.INC('面板-MA'!32:32,'面板-MA'!F32),0.5) -> 0.696 | I32: =IFERROR(_xlfn.PERCENTRANK.INC('面板-MA'!32:32,'面板-MA'!G32),0.5) -> 0.545 | J32: =IFERROR(_xlfn.PERCENTRANK.INC('面板-MA'!32:32,'面板-MA'!H32),0.5) -> 0.848 | K32: =IFERROR(_xlfn.PERCENTRANK.INC('面板-MA'!32:32,'面板-MA'!I32),0.5) -> 0.575 | L32: =IFERROR(_xlfn.PERCENTRANK.INC('面板-MA'!32:32,'面板-MA'!J32),0.5) -> 0.06 | M32: =IFERROR(_xlfn.PERCENTRANK.INC('面板-MA'!32:32,'面板-MA'!K32),0.5) -> 0.09 | N32: =IFERROR(_xlfn.PERCENTRANK.INC('面板-MA'!32:32,'面板-MA'!L32),0.5) -> 0.757 | ... BX32: =IFERROR(_xlfn.PERCENTRANK.INC('面板-MA'!32:32,'面板-MA'!BV32),0.5) -> 0.5
A33: 机床 | B33: 中游 | C33: 数控系统 | D33: 机床进口量 | E33: 0.25 | F33: =A33&B33 -> 机床中游 | G33: =IFERROR(_xlfn.PERCENTRANK.INC('面板-MA'!33:33,'面板-MA'!E33),0.5) -> 0.478 | H33: =IFERROR(_xlfn.PERCENTRANK.INC('面板-MA'!33:33,'面板-MA'!F33),0.5) -> 0.478 | I33: =IFERROR(_xlfn.PERCENTRANK.INC('面板-MA'!33:33,'面板-MA'!G33),0.5) -> 0.434 | J33: =IFERROR(_xlfn.PERCENTRANK.INC('面板-MA'!33:33,'面板-MA'!H33),0.5) -> 0.144 | K33: =IFERROR(_xlfn.PERCENTRANK.INC('面板-MA'!33:33,'面板-MA'!I33),0.5) -> 0.289 | L33: =IFERROR(_xlfn.PERCENTRANK.INC('面板-MA'!33:33,'面板-MA'!J33),0.5) -> 0.362 | M33: =IFERROR(_xlfn.PERCENTRANK.INC('面板-MA'!33:33,'面板-MA'!K33),0.5) -> 0.376 | N33: =IFERROR(_xlfn.PERCENTRANK.INC('面板-MA'!33:33,'面板-MA'!L33),0.5) -> 0.652 | ... BX33: =IFERROR(_xlfn.PERCENTRANK.INC('面板-MA'!33:33,'面板-MA'!BV33),0.5) -> 0.463
A34: 机床 | B34: 中游 | C34: 机床本体-金属加工机床 | D34: 金属加工机床产量 | E34: 0.25 | F34: =A34&B34 -> 机床中游 | G34: =IFERROR(_xlfn.PERCENTRANK.INC('面板-MA'!34:34,'面板-MA'!E34),0.5) -> 0.347 | H34: =IFERROR(_xlfn.PERCENTRANK.INC('面板-MA'!34:34,'面板-MA'!F34),0.5) -> 0.347 | I34: =IFERROR(_xlfn.PERCENTRANK.INC('面板-MA'!34:34,'面板-MA'!G34),0.5) -> 0.304 | J34: =IFERROR(_xlfn.PERCENTRANK.INC('面板-MA'!34:34,'面板-MA'!H34),0.5) -> 0.318 | K34: =IFERROR(_xlfn.PERCENTRANK.INC('面板-MA'!34:34,'面板-MA'!I34),0.5) -> 0.695 | L34: =IFERROR(_xlfn.PERCENTRANK.INC('面板-MA'!34:34,'面板-MA'!J34),0.5) -> 0.811 | M34: =IFERROR(_xlfn.PERCENTRANK.INC('面板-MA'!34:34,'面板-MA'!K34),0.5) -> 0.652 | N34: =IFERROR(_xlfn.PERCENTRANK.INC('面板-MA'!34:34,'面板-MA'!L34),0.5) -> 0.594 | ... BX34: =IFERROR(_xlfn.PERCENTRANK.INC('面板-MA'!34:34,'面板-MA'!BV34),0.5) -> 0.159
A35: 元宇宙 | B35: 上游 | C35: 覆铜板 | D35: 台股营收（PCB原料） | E35: 0 | F35: =A35&B35 -> 元宇宙上游 | G35: =IFERROR(_xlfn.PERCENTRANK.INC('面板-MA'!35:35,'面板-MA'!E35),0.5) -> 0 | H35: =IFERROR(_xlfn.PERCENTRANK.INC('面板-MA'!35:35,'面板-MA'!F35),0.5) -> 0 | I35: =IFERROR(_xlfn.PERCENTRANK.INC('面板-MA'!35:35,'面板-MA'!G35),0.5) -> 0.028 | J35: =IFERROR(_xlfn.PERCENTRANK.INC('面板-MA'!35:35,'面板-MA'!H35),0.5) -> 0.043 | K35: =IFERROR(_xlfn.PERCENTRANK.INC('面板-MA'!35:35,'面板-MA'!I35),0.5) -> 0.115 | L35: =IFERROR(_xlfn.PERCENTRANK.INC('面板-MA'!35:35,'面板-MA'!J35),0.5) -> 0.246 | M35: =IFERROR(_xlfn.PERCENTRANK.INC('面板-MA'!35:35,'面板-MA'!K35),0.5) -> 0.463 | N35: =IFERROR(_xlfn.PERCENTRANK.INC('面板-MA'!35:35,'面板-MA'!L35),0.5) -> 0.594 | ... BX35: =IFERROR(_xlfn.PERCENTRANK.INC('面板-MA'!35:35,'面板-MA'!BV35),0.5) -> 0.739
A36: 元宇宙 | B36: 中游 | C36: 芯片 | D36: 台股营收（IC设计） | E36: 0 | F36: =A36&B36 -> 元宇宙中游 | G36: =IFERROR(_xlfn.PERCENTRANK.INC('面板-MA'!36:36,'面板-MA'!E36),0.5) -> 0 | H36: =IFERROR(_xlfn.PERCENTRANK.INC('面板-MA'!36:36,'面板-MA'!F36),0.5) -> 0 | I36: =IFERROR(_xlfn.PERCENTRANK.INC('面板-MA'!36:36,'面板-MA'!G36),0.5) -> 0.028 | J36: =IFERROR(_xlfn.PERCENTRANK.INC('面板-MA'!36:36,'面板-MA'!H36),0.5) -> 0.057 | K36: =IFERROR(_xlfn.PERCENTRANK.INC('面板-MA'!36:36,'面板-MA'!I36),0.5) -> 0.347 | L36: =IFERROR(_xlfn.PERCENTRANK.INC('面板-MA'!36:36,'面板-MA'!J36),0.5) -> 0.652 | M36: =IFERROR(_xlfn.PERCENTRANK.INC('面板-MA'!36:36,'面板-MA'!K36),0.5) -> 0.724 | N36: =IFERROR(_xlfn.PERCENTRANK.INC('面板-MA'!36:36,'面板-MA'!L36),0.5) -> 0.782 | ... BX36: =IFERROR(_xlfn.PERCENTRANK.INC('面板-MA'!36:36,'面板-MA'!BV36),0.5) -> 0.217
A37: 元宇宙 | B37: 中游 | C37: PCB | D37: 台股营收（PCB制造） | E37: 0 | F37: =A37&B37 -> 元宇宙中游 | G37: =IFERROR(_xlfn.PERCENTRANK.INC('面板-MA'!37:37,'面板-MA'!E37),0.5) -> 0.463 | H37: =IFERROR(_xlfn.PERCENTRANK.INC('面板-MA'!37:37,'面板-MA'!F37),0.5) -> 0.463 | I37: =IFERROR(_xlfn.PERCENTRANK.INC('面板-MA'!37:37,'面板-MA'!G37),0.5) -> 0.347 | J37: =IFERROR(_xlfn.PERCENTRANK.INC('面板-MA'!37:37,'面板-MA'!H37),0.5) -> 0.797 | K37: =IFERROR(_xlfn.PERCENTRANK.INC('面板-MA'!37:37,'面板-MA'!I37),0.5) -> 1 | L37: =IFERROR(_xlfn.PERCENTRANK.INC('面板-MA'!37:37,'面板-MA'!J37),0.5) -> 0.855 | M37: =IFERROR(_xlfn.PERCENTRANK.INC('面板-MA'!37:37,'面板-MA'!K37),0.5) -> 0.811 | N37: =IFERROR(_xlfn.PERCENTRANK.INC('面板-MA'!37:37,'面板-MA'!L37),0.5) -> 0.971 | ... BX37: =IFERROR(_xlfn.PERCENTRANK.INC('面板-MA'!37:37,'面板-MA'!BV37),0.5) -> 0.13
A38: 元宇宙 | B38: 中游 | C38: 存储器 | D38: DXI指数 | E38: 0.125 | F38: =A38&B38 -> 元宇宙中游 | G38: =IFERROR(_xlfn.PERCENTRANK.INC('面板-MA'!38:38,'面板-MA'!E38),0.5) -> 0.159 | H38: =IFERROR(_xlfn.PERCENTRANK.INC('面板-MA'!38:38,'面板-MA'!F38),0.5) -> 0.217 | I38: =IFERROR(_xlfn.PERCENTRANK.INC('面板-MA'!38:38,'面板-MA'!G38),0.5) -> 0.275 | J38: =IFERROR(_xlfn.PERCENTRANK.INC('面板-MA'!38:38,'面板-MA'!H38),0.5) -> 0.318 | K38: =IFERROR(_xlfn.PERCENTRANK.INC('面板-MA'!38:38,'面板-MA'!I38),0.5) -> 0.362 | L38: =IFERROR(_xlfn.PERCENTRANK.INC('面板-MA'!38:38,'面板-MA'!J38),0.5) -> 0.405 | M38: =IFERROR(_xlfn.PERCENTRANK.INC('面板-MA'!38:38,'面板-MA'!K38),0.5) -> 0.449 | N38: =IFERROR(_xlfn.PERCENTRANK.INC('面板-MA'!38:38,'面板-MA'!L38),0.5) -> 0.507 | ... BX38: =IFERROR(_xlfn.PERCENTRANK.INC('面板-MA'!38:38,'面板-MA'!BV38),0.5) -> 0.855
A39: 元宇宙 | B39: 中游 | C39: 传感器 | D39: 日本传感器产值 | E39: 0.125 | F39: =A39&B39 -> 元宇宙中游 | G39: =IFERROR(_xlfn.PERCENTRANK.INC('面板-MA'!39:39,'面板-MA'!E39),0.5) -> 0.842 | H39: =IFERROR(_xlfn.PERCENTRANK.INC('面板-MA'!39:39,'面板-MA'!F39),0.5) -> 0.842 | I39: =IFERROR(_xlfn.PERCENTRANK.INC('面板-MA'!39:39,'面板-MA'!G39),0.5) -> 0.842 | J39: =IFERROR(_xlfn.PERCENTRANK.INC('面板-MA'!39:39,'面板-MA'!H39),0.5) -> 0.894 | K39: =IFERROR(_xlfn.PERCENTRANK.INC('面板-MA'!39:39,'面板-MA'!I39),0.5) -> 0.807 | L39: =IFERROR(_xlfn.PERCENTRANK.INC('面板-MA'!39:39,'面板-MA'!J39),0.5) -> 0.666 | M39: =IFERROR(_xlfn.PERCENTRANK.INC('面板-MA'!39:39,'面板-MA'!K39),0.5) -> 0.824 | N39: =IFERROR(_xlfn.PERCENTRANK.INC('面板-MA'!39:39,'面板-MA'!L39),0.5) -> 0.754 | ... BX39: =IFERROR(_xlfn.PERCENTRANK.INC('面板-MA'!39:39,'面板-MA'!BV39),0.5) -> 0.5
A40: 元宇宙 | B40: 中游 | C40: 电池模组 | D40: 电池模组财报营收 | E40: 0 | F40: =A40&B40 -> 元宇宙中游 | G40: =IFERROR(_xlfn.PERCENTRANK.INC('面板-MA'!40:40,'面板-MA'!E40),0.5) -> 0.94 | H40: =IFERROR(_xlfn.PERCENTRANK.INC('面板-MA'!40:40,'面板-MA'!F40),0.5) -> 0.94 | I40: =IFERROR(_xlfn.PERCENTRANK.INC('面板-MA'!40:40,'面板-MA'!G40),0.5) -> 0.895 | J40: =IFERROR(_xlfn.PERCENTRANK.INC('面板-MA'!40:40,'面板-MA'!H40),0.5) -> 0.895 | K40: =IFERROR(_xlfn.PERCENTRANK.INC('面板-MA'!40:40,'面板-MA'!I40),0.5) -> 0.895 | L40: =IFERROR(_xlfn.PERCENTRANK.INC('面板-MA'!40:40,'面板-MA'!J40),0.5) -> 0.85 | M40: =IFERROR(_xlfn.PERCENTRANK.INC('面板-MA'!40:40,'面板-MA'!K40),0.5) -> 0.85 | N40: =IFERROR(_xlfn.PERCENTRANK.INC('面板-MA'!40:40,'面板-MA'!L40),0.5) -> 0.85 | ... BX40: =IFERROR(_xlfn.PERCENTRANK.INC('面板-MA'!40:40,'面板-MA'!BV40),0.5) -> 0.5
A41: 元宇宙 | B41: 中游 | C41: 整机代工 | D41: 整机代工财报营收 | E41: 0 | F41: =A41&B41 -> 元宇宙中游 | G41: =IFERROR(_xlfn.PERCENTRANK.INC('面板-MA'!41:41,'面板-MA'!E41),0.5) -> 0.805 | H41: =IFERROR(_xlfn.PERCENTRANK.INC('面板-MA'!41:41,'面板-MA'!F41),0.5) -> 0.805 | I41: =IFERROR(_xlfn.PERCENTRANK.INC('面板-MA'!41:41,'面板-MA'!G41),0.5) -> 0.671 | J41: =IFERROR(_xlfn.PERCENTRANK.INC('面板-MA'!41:41,'面板-MA'!H41),0.5) -> 0.671 | K41: =IFERROR(_xlfn.PERCENTRANK.INC('面板-MA'!41:41,'面板-MA'!I41),0.5) -> 0.671 | L41: =IFERROR(_xlfn.PERCENTRANK.INC('面板-MA'!41:41,'面板-MA'!J41),0.5) -> 0.925 | M41: =IFERROR(_xlfn.PERCENTRANK.INC('面板-MA'!41:41,'面板-MA'!K41),0.5) -> 0.925 | N41: =IFERROR(_xlfn.PERCENTRANK.INC('面板-MA'!41:41,'面板-MA'!L41),0.5) -> 0.925 | ... BX41: =IFERROR(_xlfn.PERCENTRANK.INC('面板-MA'!41:41,'面板-MA'!BV41),0.5) -> 0.5
A42: 元宇宙 | B42: 中游 | C42: XR终端 | D42: Facebook非广告收入 | E42: 0.5 | F42: =A42&B42 -> 元宇宙中游 | G42: =IFERROR(_xlfn.PERCENTRANK.INC('面板-MA'!42:42,'面板-MA'!E42),0.5) -> 0 | H42: =IFERROR(_xlfn.PERCENTRANK.INC('面板-MA'!42:42,'面板-MA'!F42),0.5) -> 0.014 | I42: =IFERROR(_xlfn.PERCENTRANK.INC('面板-MA'!42:42,'面板-MA'!G42),0.5) -> 0.791 | J42: =IFERROR(_xlfn.PERCENTRANK.INC('面板-MA'!42:42,'面板-MA'!H42),0.5) -> 0.791 | K42: =IFERROR(_xlfn.PERCENTRANK.INC('面板-MA'!42:42,'面板-MA'!I42),0.5) -> 0.791 | L42: =IFERROR(_xlfn.PERCENTRANK.INC('面板-MA'!42:42,'面板-MA'!J42),0.5) -> 0.522 | M42: =IFERROR(_xlfn.PERCENTRANK.INC('面板-MA'!42:42,'面板-MA'!K42),0.5) -> 0.522 | N42: =IFERROR(_xlfn.PERCENTRANK.INC('面板-MA'!42:42,'面板-MA'!L42),0.5) -> 0.522 | ... BX42: =IFERROR(_xlfn.PERCENTRANK.INC('面板-MA'!42:42,'面板-MA'!BV42),0.5) -> 0.5
A43: 元宇宙 | B43: 下游 | C43: 游戏 | D43: Steam平台VR渗透率 | E43: 0.125 | F43: =A43&B43 -> 元宇宙下游 | G43: =IFERROR(_xlfn.PERCENTRANK.INC('面板-MA'!43:43,'面板-MA'!E43),0.5) -> 0.484 | H43: =IFERROR(_xlfn.PERCENTRANK.INC('面板-MA'!43:43,'面板-MA'!F43),0.5) -> 0.484 | I43: =IFERROR(_xlfn.PERCENTRANK.INC('面板-MA'!43:43,'面板-MA'!G43),0.5) -> 1 | J43: =IFERROR(_xlfn.PERCENTRANK.INC('面板-MA'!43:43,'面板-MA'!H43),0.5) -> 0.969 | K43: =IFERROR(_xlfn.PERCENTRANK.INC('面板-MA'!43:43,'面板-MA'!I43),0.5) -> 0.424 | L43: =IFERROR(_xlfn.PERCENTRANK.INC('面板-MA'!43:43,'面板-MA'!J43),0.5) -> 0.303 | M43: =IFERROR(_xlfn.PERCENTRANK.INC('面板-MA'!43:43,'面板-MA'!K43),0.5) -> 0 | N43: =IFERROR(_xlfn.PERCENTRANK.INC('面板-MA'!43:43,'面板-MA'!L43),0.5) -> 0.03 | ... BX43: =IFERROR(_xlfn.PERCENTRANK.INC('面板-MA'!43:43,'面板-MA'!BV43),0.5) -> 0.5
A44: 元宇宙 | B44: 下游 | C44: 游戏 | D44: 中国移动游戏收入 | E44: 0.125 | F44: =A44&B44 -> 元宇宙下游 | G44: =IFERROR(_xlfn.PERCENTRANK.INC('面板-MA'!44:44,'面板-MA'!E44),0.5) -> 0 | H44: =IFERROR(_xlfn.PERCENTRANK.INC('面板-MA'!44:44,'面板-MA'!F44),0.5) -> 0 | I44: =IFERROR(_xlfn.PERCENTRANK.INC('面板-MA'!44:44,'面板-MA'!G44),0.5) -> 0.095 | J44: =IFERROR(_xlfn.PERCENTRANK.INC('面板-MA'!44:44,'面板-MA'!H44),0.5) -> 0.142 | K44: =IFERROR(_xlfn.PERCENTRANK.INC('面板-MA'!44:44,'面板-MA'!I44),0.5) -> 0.19 | L44: =IFERROR(_xlfn.PERCENTRANK.INC('面板-MA'!44:44,'面板-MA'!J44),0.5) -> 0.285 | M44: =IFERROR(_xlfn.PERCENTRANK.INC('面板-MA'!44:44,'面板-MA'!K44),0.5) -> 0.238 | N44: =IFERROR(_xlfn.PERCENTRANK.INC('面板-MA'!44:44,'面板-MA'!L44),0.5) -> 0.333 | ... BX44: =IFERROR(_xlfn.PERCENTRANK.INC('面板-MA'!44:44,'面板-MA'!BV44),0.5) -> 0.5
A45: 元宇宙 | B45: 下游 | C45: 短视频 | D45: 抖音+快手活跃用户数 | E45: 0 | F45: =A45&B45 -> 元宇宙下游 | G45: =IFERROR(_xlfn.PERCENTRANK.INC('面板-MA'!45:45,'面板-MA'!E45),0.5) -> 0.35 | H45: =IFERROR(_xlfn.PERCENTRANK.INC('面板-MA'!45:45,'面板-MA'!F45),0.5) -> 0.35 | I45: =IFERROR(_xlfn.PERCENTRANK.INC('面板-MA'!45:45,'面板-MA'!G45),0.5) -> 0.28 | J45: =IFERROR(_xlfn.PERCENTRANK.INC('面板-MA'!45:45,'面板-MA'!H45),0.5) -> 0.228 | K45: =IFERROR(_xlfn.PERCENTRANK.INC('面板-MA'!45:45,'面板-MA'!I45),0.5) -> 0.245 | L45: =IFERROR(_xlfn.PERCENTRANK.INC('面板-MA'!45:45,'面板-MA'!J45),0.5) -> 0.263 | M45: =IFERROR(_xlfn.PERCENTRANK.INC('面板-MA'!45:45,'面板-MA'!K45),0.5) -> 0.14 | N45: =IFERROR(_xlfn.PERCENTRANK.INC('面板-MA'!45:45,'面板-MA'!L45),0.5) -> 0 | ... BX45: =IFERROR(_xlfn.PERCENTRANK.INC('面板-MA'!45:45,'面板-MA'!BV45),0.5) -> 0.5
A46: 元宇宙 | B46: 下游 | C46: 长视频 | D46: 爱优腾芒活跃用户数 | E46: 0 | F46: =A46&B46 -> 元宇宙下游 | G46: =IFERROR(_xlfn.PERCENTRANK.INC('面板-MA'!46:46,'面板-MA'!E46),0.5) -> 0.014 | H46: =IFERROR(_xlfn.PERCENTRANK.INC('面板-MA'!46:46,'面板-MA'!F46),0.5) -> 0.014 | I46: =IFERROR(_xlfn.PERCENTRANK.INC('面板-MA'!46:46,'面板-MA'!G46),0.5) -> 0 | J46: =IFERROR(_xlfn.PERCENTRANK.INC('面板-MA'!46:46,'面板-MA'!H46),0.5) -> 0.072 | K46: =IFERROR(_xlfn.PERCENTRANK.INC('面板-MA'!46:46,'面板-MA'!I46),0.5) -> 0.101 | L46: =IFERROR(_xlfn.PERCENTRANK.INC('面板-MA'!46:46,'面板-MA'!J46),0.5) -> 0.13 | M46: =IFERROR(_xlfn.PERCENTRANK.INC('面板-MA'!46:46,'面板-MA'!K46),0.5) -> 0.086 | N46: =IFERROR(_xlfn.PERCENTRANK.INC('面板-MA'!46:46,'面板-MA'!L46),0.5) -> 0.043 | ... BX46: =IFERROR(_xlfn.PERCENTRANK.INC('面板-MA'!46:46,'面板-MA'!BV46),0.5) -> 0.855
A47: 光伏 | B47: 上游 | C47: 金属硅 | D47: 金属硅价格（441） | E47: =0.5/16 -> 0.03125 | F47: =A47&B47 -> 光伏上游 | G47: =IFERROR(_xlfn.PERCENTRANK.INC('面板-MA'!47:47,'面板-MA'!E47),0.5) -> 0.898 | H47: =IFERROR(_xlfn.PERCENTRANK.INC('面板-MA'!47:47,'面板-MA'!F47),0.5) -> 0.869 | I47: =IFERROR(_xlfn.PERCENTRANK.INC('面板-MA'!47:47,'面板-MA'!G47),0.5) -> 0.84 | J47: =IFERROR(_xlfn.PERCENTRANK.INC('面板-MA'!47:47,'面板-MA'!H47),0.5) -> 0.811 | K47: =IFERROR(_xlfn.PERCENTRANK.INC('面板-MA'!47:47,'面板-MA'!I47),0.5) -> 0.826 | L47: =IFERROR(_xlfn.PERCENTRANK.INC('面板-MA'!47:47,'面板-MA'!J47),0.5) -> 0.855 | M47: =IFERROR(_xlfn.PERCENTRANK.INC('面板-MA'!47:47,'面板-MA'!K47),0.5) -> 0.927 | N47: =IFERROR(_xlfn.PERCENTRANK.INC('面板-MA'!47:47,'面板-MA'!L47),0.5) -> 0.942 | ... BX47: =IFERROR(_xlfn.PERCENTRANK.INC('面板-MA'!47:47,'面板-MA'!BV47),0.5) -> 0.159
A48: 光伏 | B48: 上游 | C48: 硅料 | D48: 多晶硅价格（一级料） | E48: =0.5/16 -> 0.03125 | F48: =A48&B48 -> 光伏上游 | G48: =IFERROR(_xlfn.PERCENTRANK.INC('面板-MA'!48:48,'面板-MA'!E48),0.5) -> 0.971 | H48: =IFERROR(_xlfn.PERCENTRANK.INC('面板-MA'!48:48,'面板-MA'!F48),0.5) -> 1 | I48: =IFERROR(_xlfn.PERCENTRANK.INC('面板-MA'!48:48,'面板-MA'!G48),0.5) -> 0.985 | J48: =IFERROR(_xlfn.PERCENTRANK.INC('面板-MA'!48:48,'面板-MA'!H48),0.5) -> 0.942 | K48: =IFERROR(_xlfn.PERCENTRANK.INC('面板-MA'!48:48,'面板-MA'!I48),0.5) -> 0.913 | L48: =IFERROR(_xlfn.PERCENTRANK.INC('面板-MA'!48:48,'面板-MA'!J48),0.5) -> 0.884 | M48: =IFERROR(_xlfn.PERCENTRANK.INC('面板-MA'!48:48,'面板-MA'!K48),0.5) -> 0.898 | N48: =IFERROR(_xlfn.PERCENTRANK.INC('面板-MA'!48:48,'面板-MA'!L48),0.5) -> 0.869 | ... BX48: =IFERROR(_xlfn.PERCENTRANK.INC('面板-MA'!48:48,'面板-MA'!BV48),0.5) -> 0.594
A49: 光伏 | B49: 上游 | C49: 硅片 | D49: 单晶硅片价格（156） | E49: =0.5/16 -> 0.03125 | F49: =A49&B49 -> 光伏上游 | G49: =IFERROR(_xlfn.PERCENTRANK.INC('面板-MA'!49:49,'面板-MA'!E49),0.5) -> 0.985 | H49: =IFERROR(_xlfn.PERCENTRANK.INC('面板-MA'!49:49,'面板-MA'!F49),0.5) -> 0.985 | I49: =IFERROR(_xlfn.PERCENTRANK.INC('面板-MA'!49:49,'面板-MA'!G49),0.5) -> 0.971 | J49: =IFERROR(_xlfn.PERCENTRANK.INC('面板-MA'!49:49,'面板-MA'!H49),0.5) -> 0.956 | K49: =IFERROR(_xlfn.PERCENTRANK.INC('面板-MA'!49:49,'面板-MA'!I49),0.5) -> 0.942 | L49: =IFERROR(_xlfn.PERCENTRANK.INC('面板-MA'!49:49,'面板-MA'!J49),0.5) -> 0.927 | M49: =IFERROR(_xlfn.PERCENTRANK.INC('面板-MA'!49:49,'面板-MA'!K49),0.5) -> 0.913 | N49: =IFERROR(_xlfn.PERCENTRANK.INC('面板-MA'!49:49,'面板-MA'!L49),0.5) -> 0.869 | ... BX49: =IFERROR(_xlfn.PERCENTRANK.INC('面板-MA'!49:49,'面板-MA'!BV49),0.5) -> 0.782
A50: 光伏 | B50: 上游 | C50: 银浆（光伏正银） | D50: 银浆（光伏正银）财报营收 | E50: =0.5/16 -> 0.03125 | F50: =A50&B50 -> 光伏上游 | G50: =IFERROR(_xlfn.PERCENTRANK.INC('面板-MA'!50:50,'面板-MA'!E50),0.5) -> 0.402 | H50: =IFERROR(_xlfn.PERCENTRANK.INC('面板-MA'!50:50,'面板-MA'!F50),0.5) -> 0.402 | I50: =IFERROR(_xlfn.PERCENTRANK.INC('面板-MA'!50:50,'面板-MA'!G50),0.5) -> 0.477 | J50: =IFERROR(_xlfn.PERCENTRANK.INC('面板-MA'!50:50,'面板-MA'!H50),0.5) -> 0.477 | K50: =IFERROR(_xlfn.PERCENTRANK.INC('面板-MA'!50:50,'面板-MA'!I50),0.5) -> 0.477 | L50: =IFERROR(_xlfn.PERCENTRANK.INC('面板-MA'!50:50,'面板-MA'!J50),0.5) -> 0.432 | M50: =IFERROR(_xlfn.PERCENTRANK.INC('面板-MA'!50:50,'面板-MA'!K50),0.5) -> 0.432 | N50: =IFERROR(_xlfn.PERCENTRANK.INC('面板-MA'!50:50,'面板-MA'!L50),0.5) -> 0.432 | ... BX50: =IFERROR(_xlfn.PERCENTRANK.INC('面板-MA'!50:50,'面板-MA'!BV50),0.5) -> 0.5
A51: 光伏 | B51: 上游 | C51: PET基膜 | D51: PET基膜财报营收 | E51: =0.5/16 -> 0.03125 | F51: =A51&B51 -> 光伏上游 | G51: =IFERROR(_xlfn.PERCENTRANK.INC('面板-MA'!51:51,'面板-MA'!E51),0.5) -> 0.223 | H51: =IFERROR(_xlfn.PERCENTRANK.INC('面板-MA'!51:51,'面板-MA'!F51),0.5) -> 0.223 | I51: =IFERROR(_xlfn.PERCENTRANK.INC('面板-MA'!51:51,'面板-MA'!G51),0.5) -> 0.567 | J51: =IFERROR(_xlfn.PERCENTRANK.INC('面板-MA'!51:51,'面板-MA'!H51),0.5) -> 0.567 | K51: =IFERROR(_xlfn.PERCENTRANK.INC('面板-MA'!51:51,'面板-MA'!I51),0.5) -> 0.567 | L51: =IFERROR(_xlfn.PERCENTRANK.INC('面板-MA'!51:51,'面板-MA'!J51),0.5) -> 0.746 | M51: =IFERROR(_xlfn.PERCENTRANK.INC('面板-MA'!51:51,'面板-MA'!K51),0.5) -> 0.746 | N51: =IFERROR(_xlfn.PERCENTRANK.INC('面板-MA'!51:51,'面板-MA'!L51),0.5) -> 0.746 | ... BX51: =IFERROR(_xlfn.PERCENTRANK.INC('面板-MA'!51:51,'面板-MA'!BV51),0.5) -> 0.5
A52: 光伏 | B52: 上游 | C52: EVA树脂 | D52: EVA树脂价格 | E52: =0.5/16 -> 0.03125 | F52: =A52&B52 -> 光伏上游 | G52: =IFERROR(_xlfn.PERCENTRANK.INC('面板-MA'!52:52,'面板-MA'!E52),0.5) -> 0.855 | H52: =IFERROR(_xlfn.PERCENTRANK.INC('面板-MA'!52:52,'面板-MA'!F52),0.5) -> 0.826 | I52: =IFERROR(_xlfn.PERCENTRANK.INC('面板-MA'!52:52,'面板-MA'!G52),0.5) -> 0.884 | J52: =IFERROR(_xlfn.PERCENTRANK.INC('面板-MA'!52:52,'面板-MA'!H52),0.5) -> 0.956 | K52: =IFERROR(_xlfn.PERCENTRANK.INC('面板-MA'!52:52,'面板-MA'!I52),0.5) -> 0.971 | L52: =IFERROR(_xlfn.PERCENTRANK.INC('面板-MA'!52:52,'面板-MA'!J52),0.5) -> 0.927 | M52: =IFERROR(_xlfn.PERCENTRANK.INC('面板-MA'!52:52,'面板-MA'!K52),0.5) -> 0.898 | N52: =IFERROR(_xlfn.PERCENTRANK.INC('面板-MA'!52:52,'面板-MA'!L52),0.5) -> 0.811 | ... BX52: =IFERROR(_xlfn.PERCENTRANK.INC('面板-MA'!52:52,'面板-MA'!BV52),0.5) -> 0.362
A53: 光伏 | B53: 中游 | C53: 光伏设备 | D53: 光伏设备财报营收 | E53: =0.5/16 -> 0.03125 | F53: =A53&B53 -> 光伏中游 | G53: =IFERROR(_xlfn.PERCENTRANK.INC('面板-MA'!53:53,'面板-MA'!E53),0.5) -> 0.671 | H53: =IFERROR(_xlfn.PERCENTRANK.INC('面板-MA'!53:53,'面板-MA'!F53),0.5) -> 0.671 | I53: =IFERROR(_xlfn.PERCENTRANK.INC('面板-MA'!53:53,'面板-MA'!G53),0.5) -> 0.537 | J53: =IFERROR(_xlfn.PERCENTRANK.INC('面板-MA'!53:53,'面板-MA'!H53),0.5) -> 0.537 | K53: =IFERROR(_xlfn.PERCENTRANK.INC('面板-MA'!53:53,'面板-MA'!I53),0.5) -> 0.537 | L53: =IFERROR(_xlfn.PERCENTRANK.INC('面板-MA'!53:53,'面板-MA'!J53),0.5) -> 0.746 | M53: =IFERROR(_xlfn.PERCENTRANK.INC('面板-MA'!53:53,'面板-MA'!K53),0.5) -> 0.746 | N53: =IFERROR(_xlfn.PERCENTRANK.INC('面板-MA'!53:53,'面板-MA'!L53),0.5) -> 0.746 | ... BX53: =IFERROR(_xlfn.PERCENTRANK.INC('面板-MA'!53:53,'面板-MA'!BV53),0.5) -> 0.5
A54: 光伏 | B54: 中游 | C54: 电池片 | D54: 多晶电池片价格（156） | E54: =0.5/16 -> 0.03125 | F54: =A54&B54 -> 光伏中游 | G54: =IFERROR(_xlfn.PERCENTRANK.INC('面板-MA'!54:54,'面板-MA'!E54),0.5) -> 1 | H54: =IFERROR(_xlfn.PERCENTRANK.INC('面板-MA'!54:54,'面板-MA'!F54),0.5) -> 0.977 | I54: =IFERROR(_xlfn.PERCENTRANK.INC('面板-MA'!54:54,'面板-MA'!G54),0.5) -> 0.933 | J54: =IFERROR(_xlfn.PERCENTRANK.INC('面板-MA'!54:54,'面板-MA'!H54),0.5) -> 0.933 | K54: =IFERROR(_xlfn.PERCENTRANK.INC('面板-MA'!54:54,'面板-MA'!I54),0.5) -> 0.911 | L54: =IFERROR(_xlfn.PERCENTRANK.INC('面板-MA'!54:54,'面板-MA'!J54),0.5) -> 0.888 | M54: =IFERROR(_xlfn.PERCENTRANK.INC('面板-MA'!54:54,'面板-MA'!K54),0.5) -> 0.711 | N54: =IFERROR(_xlfn.PERCENTRANK.INC('面板-MA'!54:54,'面板-MA'!L54),0.5) -> 0.733 | ... BX54: =IFERROR(_xlfn.PERCENTRANK.INC('面板-MA'!54:54,'面板-MA'!BV54),0.5) -> 0.5
A55: 光伏 | B55: 中游 | C55: 组件 | D55: 组件出口量 | E55: =0.5/16 -> 0.03125 | F55: =A55&B55 -> 光伏中游 | G55: =IFERROR(_xlfn.PERCENTRANK.INC('面板-MA'!55:55,'面板-MA'!E55),0.5) -> 0.4 | H55: =IFERROR(_xlfn.PERCENTRANK.INC('面板-MA'!55:55,'面板-MA'!F55),0.5) -> 0.422 | I55: =IFERROR(_xlfn.PERCENTRANK.INC('面板-MA'!55:55,'面板-MA'!G55),0.5) -> 0.644 | J55: =IFERROR(_xlfn.PERCENTRANK.INC('面板-MA'!55:55,'面板-MA'!H55),0.5) -> 0.866 | K55: =IFERROR(_xlfn.PERCENTRANK.INC('面板-MA'!55:55,'面板-MA'!I55),0.5) -> 0.8 | L55: =IFERROR(_xlfn.PERCENTRANK.INC('面板-MA'!55:55,'面板-MA'!J55),0.5) -> 0.755 | M55: =IFERROR(_xlfn.PERCENTRANK.INC('面板-MA'!55:55,'面板-MA'!K55),0.5) -> 0.844 | N55: =IFERROR(_xlfn.PERCENTRANK.INC('面板-MA'!55:55,'面板-MA'!L55),0.5) -> 0.933 | ... BX55: =IFERROR(_xlfn.PERCENTRANK.INC('面板-MA'!55:55,'面板-MA'!BV55),0.5) -> 0.5
A56: 光伏 | B56: 中游 | C56: 跟踪支架 | D56: 电池片出口额 | E56: =0.5/16 -> 0.03125 | F56: =A56&B56 -> 光伏中游 | G56: =IFERROR(_xlfn.PERCENTRANK.INC('面板-MA'!56:56,'面板-MA'!E56),0.5) -> 0.424 | H56: =IFERROR(_xlfn.PERCENTRANK.INC('面板-MA'!56:56,'面板-MA'!F56),0.5) -> 0.424 | I56: =IFERROR(_xlfn.PERCENTRANK.INC('面板-MA'!56:56,'面板-MA'!G56),0.5) -> 0.787 | J56: =IFERROR(_xlfn.PERCENTRANK.INC('面板-MA'!56:56,'面板-MA'!H56),0.5) -> 0.969 | K56: =IFERROR(_xlfn.PERCENTRANK.INC('面板-MA'!56:56,'面板-MA'!I56),0.5) -> 0.909 | L56: =IFERROR(_xlfn.PERCENTRANK.INC('面板-MA'!56:56,'面板-MA'!J56),0.5) -> 0.848 | M56: =IFERROR(_xlfn.PERCENTRANK.INC('面板-MA'!56:56,'面板-MA'!K56),0.5) -> 0.818 | N56: =IFERROR(_xlfn.PERCENTRANK.INC('面板-MA'!56:56,'面板-MA'!L56),0.5) -> 0.939 | ... BX56: =IFERROR(_xlfn.PERCENTRANK.INC('面板-MA'!56:56,'面板-MA'!BV56),0.5) -> 0.5
A57: 光伏 | B57: 中游 | C57: 辅材-光伏玻璃 | D57: 3.2mm镀膜光伏玻璃价格 | E57: =0.5/16 -> 0.03125 | F57: =A57&B57 -> 光伏中游 | G57: =IFERROR(_xlfn.PERCENTRANK.INC('面板-MA'!57:57,'面板-MA'!E57),0.5) -> 0.342 | H57: =IFERROR(_xlfn.PERCENTRANK.INC('面板-MA'!57:57,'面板-MA'!F57),0.5) -> 0.394 | I57: =IFERROR(_xlfn.PERCENTRANK.INC('面板-MA'!57:57,'面板-MA'!G57),0.5) -> 0.473 | J57: =IFERROR(_xlfn.PERCENTRANK.INC('面板-MA'!57:57,'面板-MA'!H57),0.5) -> 0.552 | K57: =IFERROR(_xlfn.PERCENTRANK.INC('面板-MA'!57:57,'面板-MA'!I57),0.5) -> 0.657 | L57: =IFERROR(_xlfn.PERCENTRANK.INC('面板-MA'!57:57,'面板-MA'!J57),0.5) -> 0.552 | M57: =IFERROR(_xlfn.PERCENTRANK.INC('面板-MA'!57:57,'面板-MA'!K57),0.5) -> 0.368 | N57: =IFERROR(_xlfn.PERCENTRANK.INC('面板-MA'!57:57,'面板-MA'!L57),0.5) -> 0.236 | ... BX57: =IFERROR(_xlfn.PERCENTRANK.INC('面板-MA'!57:57,'面板-MA'!BV57),0.5) -> 0.5
A58: 光伏 | B58: 中游 | C58: 辅材-EVA胶膜 | D58: 辅材-EVA胶膜财报营收 | E58: =0.5/16 -> 0.03125 | F58: =A58&B58 -> 光伏中游 | G58: =IFERROR(_xlfn.PERCENTRANK.INC('面板-MA'!58:58,'面板-MA'!E58),0.5) -> 0.5 | H58: =IFERROR(_xlfn.PERCENTRANK.INC('面板-MA'!58:58,'面板-MA'!F58),0.5) -> 0.5 | I58: =IFERROR(_xlfn.PERCENTRANK.INC('面板-MA'!58:58,'面板-MA'!G58),0.5) -> 0.5 | J58: =IFERROR(_xlfn.PERCENTRANK.INC('面板-MA'!58:58,'面板-MA'!H58),0.5) -> 0.5 | K58: =IFERROR(_xlfn.PERCENTRANK.INC('面板-MA'!58:58,'面板-MA'!I58),0.5) -> 0.5 | L58: =IFERROR(_xlfn.PERCENTRANK.INC('面板-MA'!58:58,'面板-MA'!J58),0.5) -> 0.5 | M58: =IFERROR(_xlfn.PERCENTRANK.INC('面板-MA'!58:58,'面板-MA'!K58),0.5) -> 0.5 | N58: =IFERROR(_xlfn.PERCENTRANK.INC('面板-MA'!58:58,'面板-MA'!L58),0.5) -> 0.5 | ... BX58: =IFERROR(_xlfn.PERCENTRANK.INC('面板-MA'!58:58,'面板-MA'!BV58),0.5) -> 0.5
A59: 光伏 | B59: 中游 | C59: 辅材-背板 | D59: 光伏玻璃产量 | E59: =0.5/16 -> 0.03125 | F59: =A59&B59 -> 光伏中游 | G59: =IFERROR(_xlfn.PERCENTRANK.INC('面板-MA'!59:59,'面板-MA'!E59),0.5) -> 0.971 | H59: =IFERROR(_xlfn.PERCENTRANK.INC('面板-MA'!59:59,'面板-MA'!F59),0.5) -> 0.985 | I59: =IFERROR(_xlfn.PERCENTRANK.INC('面板-MA'!59:59,'面板-MA'!G59),0.5) -> 1 | J59: =IFERROR(_xlfn.PERCENTRANK.INC('面板-MA'!59:59,'面板-MA'!H59),0.5) -> 0.956 | K59: =IFERROR(_xlfn.PERCENTRANK.INC('面板-MA'!59:59,'面板-MA'!I59),0.5) -> 0.913 | L59: =IFERROR(_xlfn.PERCENTRANK.INC('面板-MA'!59:59,'面板-MA'!J59),0.5) -> 0.811 | M59: =IFERROR(_xlfn.PERCENTRANK.INC('面板-MA'!59:59,'面板-MA'!K59),0.5) -> 0.753 | N59: =IFERROR(_xlfn.PERCENTRANK.INC('面板-MA'!59:59,'面板-MA'!L59),0.5) -> 0.71 | ... BX59: =IFERROR(_xlfn.PERCENTRANK.INC('面板-MA'!59:59,'面板-MA'!BV59),0.5) -> 0.521
A60: 光伏 | B60: 中游 | C60: 辅材-逆变器 | D60: 逆变器出口额 | E60: =0.5/16 -> 0.03125 | F60: =A60&B60 -> 光伏中游 | G60: =IFERROR(_xlfn.PERCENTRANK.INC('面板-MA'!60:60,'面板-MA'!E60),0.5) -> 0.929 | H60: =IFERROR(_xlfn.PERCENTRANK.INC('面板-MA'!60:60,'面板-MA'!F60),0.5) -> 0.929 | I60: =IFERROR(_xlfn.PERCENTRANK.INC('面板-MA'!60:60,'面板-MA'!G60),0.5) -> 0.964 | J60: =IFERROR(_xlfn.PERCENTRANK.INC('面板-MA'!60:60,'面板-MA'!H60),0.5) -> 0.912 | K60: =IFERROR(_xlfn.PERCENTRANK.INC('面板-MA'!60:60,'面板-MA'!I60),0.5) -> 0.842 | L60: =IFERROR(_xlfn.PERCENTRANK.INC('面板-MA'!60:60,'面板-MA'!J60),0.5) -> 0.789 | M60: =IFERROR(_xlfn.PERCENTRANK.INC('面板-MA'!60:60,'面板-MA'!K60),0.5) -> 0.684 | N60: =IFERROR(_xlfn.PERCENTRANK.INC('面板-MA'!60:60,'面板-MA'!L60),0.5) -> 0.333 | ... BX60: =IFERROR(_xlfn.PERCENTRANK.INC('面板-MA'!60:60,'面板-MA'!BV60),0.5) -> 0.5
A61: 光伏 | B61: 中游 | C61: EPC | D61: 光伏新增装机量 | E61: 0.5 | F61: =A61&B61 -> 光伏中游 | G61: =IFERROR(_xlfn.PERCENTRANK.INC('面板-MA'!61:61,'面板-MA'!E61),0.5) -> 0.808 | H61: =IFERROR(_xlfn.PERCENTRANK.INC('面板-MA'!61:61,'面板-MA'!F61),0.5) -> 0.808 | I61: =IFERROR(_xlfn.PERCENTRANK.INC('面板-MA'!61:61,'面板-MA'!G61),0.5) -> 0.838 | J61: =IFERROR(_xlfn.PERCENTRANK.INC('面板-MA'!61:61,'面板-MA'!H61),0.5) -> 0.867 | K61: =IFERROR(_xlfn.PERCENTRANK.INC('面板-MA'!61:61,'面板-MA'!I61),0.5) -> 0.897 | L61: =IFERROR(_xlfn.PERCENTRANK.INC('面板-MA'!61:61,'面板-MA'!J61),0.5) -> 0.911 | M61: =IFERROR(_xlfn.PERCENTRANK.INC('面板-MA'!61:61,'面板-MA'!K61),0.5) -> 0.926 | N61: =IFERROR(_xlfn.PERCENTRANK.INC('面板-MA'!61:61,'面板-MA'!L61),0.5) -> 0.941 | ... BX61: =IFERROR(_xlfn.PERCENTRANK.INC('面板-MA'!61:61,'面板-MA'!BV61),0.5) -> 0.5
A62: 光伏 | B62: 下游 | C62: 光伏电站 | D62: 光伏发电量 | E62: =0.5/16 -> 0.03125 | F62: =A62&B62 -> 光伏下游 | G62: =IFERROR(_xlfn.PERCENTRANK.INC('面板-MA'!62:62,'面板-MA'!E62),0.5) -> 0.558 | H62: =IFERROR(_xlfn.PERCENTRANK.INC('面板-MA'!62:62,'面板-MA'!F62),0.5) -> 0.558 | I62: =IFERROR(_xlfn.PERCENTRANK.INC('面板-MA'!62:62,'面板-MA'!G62),0.5) -> 0.485 | J62: =IFERROR(_xlfn.PERCENTRANK.INC('面板-MA'!62:62,'面板-MA'!H62),0.5) -> 0.47 | K62: =IFERROR(_xlfn.PERCENTRANK.INC('面板-MA'!62:62,'面板-MA'!I62),0.5) -> 0.544 | L62: =IFERROR(_xlfn.PERCENTRANK.INC('面板-MA'!62:62,'面板-MA'!J62),0.5) -> 0.426 | M62: =IFERROR(_xlfn.PERCENTRANK.INC('面板-MA'!62:62,'面板-MA'!K62),0.5) -> 0.294 | N62: =IFERROR(_xlfn.PERCENTRANK.INC('面板-MA'!62:62,'面板-MA'!L62),0.5) -> 0.132 | ... BX62: =IFERROR(_xlfn.PERCENTRANK.INC('面板-MA'!62:62,'面板-MA'!BV62),0.5) -> 0.5
A63: 光伏 | B63: 下游 | C63: 光伏电站 | D63: 光伏利用小时数 | E63: =0.5/16 -> 0.03125 | F63: =A63&B63 -> 光伏下游 | G63: =IFERROR(_xlfn.PERCENTRANK.INC('面板-MA'!63:63,'面板-MA'!E63),0.5) -> 0.795 | H63: =IFERROR(_xlfn.PERCENTRANK.INC('面板-MA'!63:63,'面板-MA'!F63),0.5) -> 0.795 | I63: =IFERROR(_xlfn.PERCENTRANK.INC('面板-MA'!63:63,'面板-MA'!G63),0.5) -> 0.795 | J63: =IFERROR(_xlfn.PERCENTRANK.INC('面板-MA'!63:63,'面板-MA'!H63),0.5) -> 0.704 | K63: =IFERROR(_xlfn.PERCENTRANK.INC('面板-MA'!63:63,'面板-MA'!I63),0.5) -> 0.727 | L63: =IFERROR(_xlfn.PERCENTRANK.INC('面板-MA'!63:63,'面板-MA'!J63),0.5) -> 0.75 | M63: =IFERROR(_xlfn.PERCENTRANK.INC('面板-MA'!63:63,'面板-MA'!K63),0.5) -> 0.431 | N63: =IFERROR(_xlfn.PERCENTRANK.INC('面板-MA'!63:63,'面板-MA'!L63),0.5) -> 0.022 | ... BX63: =IFERROR(_xlfn.PERCENTRANK.INC('面板-MA'!63:63,'面板-MA'!BV63),0.5) -> 0.5
A64: 风电 | B64: 上游 | C64: 碳纤维 | D64: 碳纤维进口额 | E64: =0.75/13 -> 0.057692308 | F64: =A64&B64 -> 风电上游 | G64: =IFERROR(_xlfn.PERCENTRANK.INC('面板-MA'!64:64,'面板-MA'!E64),0.5) -> 0.898 | H64: =IFERROR(_xlfn.PERCENTRANK.INC('面板-MA'!64:64,'面板-MA'!F64),0.5) -> 0.898 | I64: =IFERROR(_xlfn.PERCENTRANK.INC('面板-MA'!64:64,'面板-MA'!G64),0.5) -> 0.956 | J64: =IFERROR(_xlfn.PERCENTRANK.INC('面板-MA'!64:64,'面板-MA'!H64),0.5) -> 0.942 | K64: =IFERROR(_xlfn.PERCENTRANK.INC('面板-MA'!64:64,'面板-MA'!I64),0.5) -> 0.971 | L64: =IFERROR(_xlfn.PERCENTRANK.INC('面板-MA'!64:64,'面板-MA'!J64),0.5) -> 0.927 | M64: =IFERROR(_xlfn.PERCENTRANK.INC('面板-MA'!64:64,'面板-MA'!K64),0.5) -> 0.855 | N64: =IFERROR(_xlfn.PERCENTRANK.INC('面板-MA'!64:64,'面板-MA'!L64),0.5) -> 0.985 | ... BX64: =IFERROR(_xlfn.PERCENTRANK.INC('面板-MA'!64:64,'面板-MA'!BV64),0.5) -> 0.826
A65: 风电 | B65: 上游 | C65: 环氧树脂 | D65: 环氧树脂价差 | E65: =0.75/13 -> 0.057692308 | F65: =A65&B65 -> 风电上游 | G65: =IFERROR(_xlfn.PERCENTRANK.INC('面板-MA'!65:65,'面板-MA'!E65),0.5) -> 0.232 | H65: =IFERROR(_xlfn.PERCENTRANK.INC('面板-MA'!65:65,'面板-MA'!F65),0.5) -> 0.162 | I65: =IFERROR(_xlfn.PERCENTRANK.INC('面板-MA'!65:65,'面板-MA'!G65),0.5) -> 0.069 | J65: =IFERROR(_xlfn.PERCENTRANK.INC('面板-MA'!65:65,'面板-MA'!H65),0.5) -> 0 | K65: =IFERROR(_xlfn.PERCENTRANK.INC('面板-MA'!65:65,'面板-MA'!I65),0.5) -> 0.023 | L65: =IFERROR(_xlfn.PERCENTRANK.INC('面板-MA'!65:65,'面板-MA'!J65),0.5) -> 0.046 | M65: =IFERROR(_xlfn.PERCENTRANK.INC('面板-MA'!65:65,'面板-MA'!K65),0.5) -> 0.093 | N65: =IFERROR(_xlfn.PERCENTRANK.INC('面板-MA'!65:65,'面板-MA'!L65),0.5) -> 0.116 | ... BX65: =IFERROR(_xlfn.PERCENTRANK.INC('面板-MA'!65:65,'面板-MA'!BV65),0.5) -> 0.5
A66: 风电 | B66: 上游 | C66: 聚醚胺 | D66: 聚醚胺价差 | E66: =0.75/13 -> 0.057692308 | F66: =A66&B66 -> 风电上游 | G66: =IFERROR(_xlfn.PERCENTRANK.INC('面板-MA'!66:66,'面板-MA'!E66),0.5) -> 0.533 | H66: =IFERROR(_xlfn.PERCENTRANK.INC('面板-MA'!66:66,'面板-MA'!F66),0.5) -> 0.688 | I66: =IFERROR(_xlfn.PERCENTRANK.INC('面板-MA'!66:66,'面板-MA'!G66),0.5) -> 0.822 | J66: =IFERROR(_xlfn.PERCENTRANK.INC('面板-MA'!66:66,'面板-MA'!H66),0.5) -> 0.866 | K66: =IFERROR(_xlfn.PERCENTRANK.INC('面板-MA'!66:66,'面板-MA'!I66),0.5) -> 0.888 | L66: =IFERROR(_xlfn.PERCENTRANK.INC('面板-MA'!66:66,'面板-MA'!J66),0.5) -> 0.911 | M66: =IFERROR(_xlfn.PERCENTRANK.INC('面板-MA'!66:66,'面板-MA'!K66),0.5) -> 1 | N66: =IFERROR(_xlfn.PERCENTRANK.INC('面板-MA'!66:66,'面板-MA'!L66),0.5) -> 0.977 | ... BX66: =IFERROR(_xlfn.PERCENTRANK.INC('面板-MA'!66:66,'面板-MA'!BV66),0.5) -> 0.5
A67: 风电 | B67: 中游 | C67: 风电叶片 | D67: 风电叶片财报营收 | E67: =0.75/13 -> 0.057692308 | F67: =A67&B67 -> 风电中游 | G67: =IFERROR(_xlfn.PERCENTRANK.INC('面板-MA'!67:67,'面板-MA'!E67),0.5) -> 0.223 | H67: =IFERROR(_xlfn.PERCENTRANK.INC('面板-MA'!67:67,'面板-MA'!F67),0.5) -> 0.223 | I67: =IFERROR(_xlfn.PERCENTRANK.INC('面板-MA'!67:67,'面板-MA'!G67),0.5) -> 0.343 | J67: =IFERROR(_xlfn.PERCENTRANK.INC('面板-MA'!67:67,'面板-MA'!H67),0.5) -> 0.343 | K67: =IFERROR(_xlfn.PERCENTRANK.INC('面板-MA'!67:67,'面板-MA'!I67),0.5) -> 0.343 | L67: =IFERROR(_xlfn.PERCENTRANK.INC('面板-MA'!67:67,'面板-MA'!J67),0.5) -> 0.746 | M67: =IFERROR(_xlfn.PERCENTRANK.INC('面板-MA'!67:67,'面板-MA'!K67),0.5) -> 0.746 | N67: =IFERROR(_xlfn.PERCENTRANK.INC('面板-MA'!67:67,'面板-MA'!L67),0.5) -> 0.746 | ... BX67: =IFERROR(_xlfn.PERCENTRANK.INC('面板-MA'!67:67,'面板-MA'!BV67),0.5) -> 0.5
A68: 风电 | B68: 中游 | C68: 风电机舱罩 | D68: 风电机舱罩财报营收 | E68: =0.75/13 -> 0.057692308 | F68: =A68&B68 -> 风电中游 | G68: =IFERROR(_xlfn.PERCENTRANK.INC('面板-MA'!68:68,'面板-MA'!E68),0.5) -> 0.375 | H68: =IFERROR(_xlfn.PERCENTRANK.INC('面板-MA'!68:68,'面板-MA'!F68),0.5) -> 0.375 | I68: =IFERROR(_xlfn.PERCENTRANK.INC('面板-MA'!68:68,'面板-MA'!G68),0.5) -> 0.187 | J68: =IFERROR(_xlfn.PERCENTRANK.INC('面板-MA'!68:68,'面板-MA'!H68),0.5) -> 0.187 | K68: =IFERROR(_xlfn.PERCENTRANK.INC('面板-MA'!68:68,'面板-MA'!I68),0.5) -> 0.187 | L68: =IFERROR(_xlfn.PERCENTRANK.INC('面板-MA'!68:68,'面板-MA'!J68),0.5) -> 0 | M68: =IFERROR(_xlfn.PERCENTRANK.INC('面板-MA'!68:68,'面板-MA'!K68),0.5) -> 0 | N68: =IFERROR(_xlfn.PERCENTRANK.INC('面板-MA'!68:68,'面板-MA'!L68),0.5) -> 0 | ... BX68: =IFERROR(_xlfn.PERCENTRANK.INC('面板-MA'!68:68,'面板-MA'!BV68),0.5) -> 0.5
A69: 风电 | B69: 中游 | C69: 大功率主轴轴承 | D69: Myspic综合钢价指数 | E69: =0.75/13 -> 0.057692308 | F69: =A69&B69 -> 风电中游 | G69: =IFERROR(1-_xlfn.PERCENTRANK.INC('面板-MA'!69:69,'面板-MA'!E69),0.5) -> 0.522 | H69: =IFERROR(1-_xlfn.PERCENTRANK.INC('面板-MA'!69:69,'面板-MA'!F69),0.5) -> 0.45 | I69: =IFERROR(1-_xlfn.PERCENTRANK.INC('面板-MA'!69:69,'面板-MA'!G69),0.5) -> 0.421 | J69: =IFERROR(1-_xlfn.PERCENTRANK.INC('面板-MA'!69:69,'面板-MA'!H69),0.5) -> 0.29 | K69: =IFERROR(1-_xlfn.PERCENTRANK.INC('面板-MA'!69:69,'面板-MA'!I69),0.5) -> 0.203 | L69: =IFERROR(1-_xlfn.PERCENTRANK.INC('面板-MA'!69:69,'面板-MA'!J69),0.5) -> 0.131 | M69: =IFERROR(1-_xlfn.PERCENTRANK.INC('面板-MA'!69:69,'面板-MA'!K69),0.5) -> 0.102 | N69: =IFERROR(1-_xlfn.PERCENTRANK.INC('面板-MA'!69:69,'面板-MA'!L69),0.5) -> 0.145 | ... BX69: =IFERROR(1-_xlfn.PERCENTRANK.INC('面板-MA'!69:69,'面板-MA'!BV69),0.5) -> 0.972
A70: 风电 | B70: 中游 | C70: 风电铸件 | D70: Myspic综合钢价指数 | E70: =0.75/13 -> 0.057692308 | F70: =A70&B70 -> 风电中游 | G70: =IFERROR(1-_xlfn.PERCENTRANK.INC('面板-MA'!70:70,'面板-MA'!E70),0.5) -> 0.522 | H70: =IFERROR(1-_xlfn.PERCENTRANK.INC('面板-MA'!70:70,'面板-MA'!F70),0.5) -> 0.45 | I70: =IFERROR(1-_xlfn.PERCENTRANK.INC('面板-MA'!70:70,'面板-MA'!G70),0.5) -> 0.421 | J70: =IFERROR(1-_xlfn.PERCENTRANK.INC('面板-MA'!70:70,'面板-MA'!H70),0.5) -> 0.29 | K70: =IFERROR(1-_xlfn.PERCENTRANK.INC('面板-MA'!70:70,'面板-MA'!I70),0.5) -> 0.203 | L70: =IFERROR(1-_xlfn.PERCENTRANK.INC('面板-MA'!70:70,'面板-MA'!J70),0.5) -> 0.131 | M70: =IFERROR(1-_xlfn.PERCENTRANK.INC('面板-MA'!70:70,'面板-MA'!K70),0.5) -> 0.102 | N70: =IFERROR(1-_xlfn.PERCENTRANK.INC('面板-MA'!70:70,'面板-MA'!L70),0.5) -> 0.145 | ... BX70: =IFERROR(1-_xlfn.PERCENTRANK.INC('面板-MA'!70:70,'面板-MA'!BV70),0.5) -> 0.972
A71: 风电 | B71: 中游 | C71: 风电塔筒 | D71: Myspic综合钢价指数 | E71: =0.75/13 -> 0.057692308 | F71: =A71&B71 -> 风电中游 | G71: =IFERROR(1-_xlfn.PERCENTRANK.INC('面板-MA'!71:71,'面板-MA'!E71),0.5) -> 0.522 | H71: =IFERROR(1-_xlfn.PERCENTRANK.INC('面板-MA'!71:71,'面板-MA'!F71),0.5) -> 0.45 | I71: =IFERROR(1-_xlfn.PERCENTRANK.INC('面板-MA'!71:71,'面板-MA'!G71),0.5) -> 0.421 | J71: =IFERROR(1-_xlfn.PERCENTRANK.INC('面板-MA'!71:71,'面板-MA'!H71),0.5) -> 0.29 | K71: =IFERROR(1-_xlfn.PERCENTRANK.INC('面板-MA'!71:71,'面板-MA'!I71),0.5) -> 0.203 | L71: =IFERROR(1-_xlfn.PERCENTRANK.INC('面板-MA'!71:71,'面板-MA'!J71),0.5) -> 0.131 | M71: =IFERROR(1-_xlfn.PERCENTRANK.INC('面板-MA'!71:71,'面板-MA'!K71),0.5) -> 0.102 | N71: =IFERROR(1-_xlfn.PERCENTRANK.INC('面板-MA'!71:71,'面板-MA'!L71),0.5) -> 0.145 | ... BX71: =IFERROR(1-_xlfn.PERCENTRANK.INC('面板-MA'!71:71,'面板-MA'!BV71),0.5) -> 0.972
A72: 风电 | B72: 中游 | C72: 风电主机 | D72: 风电新增装机量 | E72: 0.25 | F72: =A72&B72 -> 风电中游 | G72: =IFERROR(_xlfn.PERCENTRANK.INC('面板-MA'!72:72,'面板-MA'!E72),0.5) -> 0.426 | H72: =IFERROR(_xlfn.PERCENTRANK.INC('面板-MA'!72:72,'面板-MA'!F72),0.5) -> 0.426 | I72: =IFERROR(_xlfn.PERCENTRANK.INC('面板-MA'!72:72,'面板-MA'!G72),0.5) -> 0.455 | J72: =IFERROR(_xlfn.PERCENTRANK.INC('面板-MA'!72:72,'面板-MA'!H72),0.5) -> 0.529 | K72: =IFERROR(_xlfn.PERCENTRANK.INC('面板-MA'!72:72,'面板-MA'!I72),0.5) -> 0.617 | L72: =IFERROR(_xlfn.PERCENTRANK.INC('面板-MA'!72:72,'面板-MA'!J72),0.5) -> 0.75 | M72: =IFERROR(_xlfn.PERCENTRANK.INC('面板-MA'!72:72,'面板-MA'!K72),0.5) -> 0.779 | N72: =IFERROR(_xlfn.PERCENTRANK.INC('面板-MA'!72:72,'面板-MA'!L72),0.5) -> 0.808 | ... BX72: =IFERROR(_xlfn.PERCENTRANK.INC('面板-MA'!72:72,'面板-MA'!BV72),0.5) -> 0.5
A73: 风电 | B73: 中游 | C73: 海缆 | D73: 海缆财报营收 | E73: =0.75/13 -> 0.057692308 | F73: =A73&B73 -> 风电中游 | G73: =IFERROR(_xlfn.PERCENTRANK.INC('面板-MA'!73:73,'面板-MA'!E73),0.5) -> 0.044 | H73: =IFERROR(_xlfn.PERCENTRANK.INC('面板-MA'!73:73,'面板-MA'!F73),0.5) -> 0.044 | I73: =IFERROR(_xlfn.PERCENTRANK.INC('面板-MA'!73:73,'面板-MA'!G73),0.5) -> 0.074 | J73: =IFERROR(_xlfn.PERCENTRANK.INC('面板-MA'!73:73,'面板-MA'!H73),0.5) -> 0.074 | K73: =IFERROR(_xlfn.PERCENTRANK.INC('面板-MA'!73:73,'面板-MA'!I73),0.5) -> 0.074 | L73: =IFERROR(_xlfn.PERCENTRANK.INC('面板-MA'!73:73,'面板-MA'!J73),0.5) -> 0.164 | M73: =IFERROR(_xlfn.PERCENTRANK.INC('面板-MA'!73:73,'面板-MA'!K73),0.5) -> 0.164 | N73: =IFERROR(_xlfn.PERCENTRANK.INC('面板-MA'!73:73,'面板-MA'!L73),0.5) -> 0.164 | ... BX73: =IFERROR(_xlfn.PERCENTRANK.INC('面板-MA'!73:73,'面板-MA'!BV73),0.5) -> 0.5
A74: 风电 | B74: 中游 | C74: 高空作业 | D74: 高空作业财报营收 | E74: =0.75/13 -> 0.057692308 | F74: =A74&B74 -> 风电中游 | G74: =IFERROR(_xlfn.PERCENTRANK.INC('面板-MA'!74:74,'面板-MA'!E74),0.5) -> 0.046 | H74: =IFERROR(_xlfn.PERCENTRANK.INC('面板-MA'!74:74,'面板-MA'!F74),0.5) -> 0.046 | I74: =IFERROR(_xlfn.PERCENTRANK.INC('面板-MA'!74:74,'面板-MA'!G74),0.5) -> 0.078 | J74: =IFERROR(_xlfn.PERCENTRANK.INC('面板-MA'!74:74,'面板-MA'!H74),0.5) -> 0.078 | K74: =IFERROR(_xlfn.PERCENTRANK.INC('面板-MA'!74:74,'面板-MA'!I74),0.5) -> 0.078 | L74: =IFERROR(_xlfn.PERCENTRANK.INC('面板-MA'!74:74,'面板-MA'!J74),0.5) -> 0.171 | M74: =IFERROR(_xlfn.PERCENTRANK.INC('面板-MA'!74:74,'面板-MA'!K74),0.5) -> 0.171 | N74: =IFERROR(_xlfn.PERCENTRANK.INC('面板-MA'!74:74,'面板-MA'!L74),0.5) -> 0.171 | ... BX74: =IFERROR(_xlfn.PERCENTRANK.INC('面板-MA'!74:74,'面板-MA'!BV74),0.5) -> 0.5
A75: 风电 | B75: 下游 | C75: 风电运营商-1 | D75: 风电发电量 | E75: =0.75/13 -> 0.057692308 | F75: =A75&B75 -> 风电下游 | G75: =IFERROR(_xlfn.PERCENTRANK.INC('面板-MA'!75:75,'面板-MA'!E75),0.5) -> 0.397 | H75: =IFERROR(_xlfn.PERCENTRANK.INC('面板-MA'!75:75,'面板-MA'!F75),0.5) -> 0.397 | I75: =IFERROR(_xlfn.PERCENTRANK.INC('面板-MA'!75:75,'面板-MA'!G75),0.5) -> 0.352 | J75: =IFERROR(_xlfn.PERCENTRANK.INC('面板-MA'!75:75,'面板-MA'!H75),0.5) -> 0.308 | K75: =IFERROR(_xlfn.PERCENTRANK.INC('面板-MA'!75:75,'面板-MA'!I75),0.5) -> 0.279 | L75: =IFERROR(_xlfn.PERCENTRANK.INC('面板-MA'!75:75,'面板-MA'!J75),0.5) -> 0.147 | M75: =IFERROR(_xlfn.PERCENTRANK.INC('面板-MA'!75:75,'面板-MA'!K75),0.5) -> 0.029 | N75: =IFERROR(_xlfn.PERCENTRANK.INC('面板-MA'!75:75,'面板-MA'!L75),0.5) -> 0 | ... BX75: =IFERROR(_xlfn.PERCENTRANK.INC('面板-MA'!75:75,'面板-MA'!BV75),0.5) -> 0.5
A76: 风电 | B76: 下游 | C76: 风电运营商-2 | D76: 风电利用小时数 | E76: =0.75/13 -> 0.057692308 | F76: =A76&B76 -> 风电下游 | G76: =IFERROR(_xlfn.PERCENTRANK.INC('面板-MA'!76:76,'面板-MA'!E76),0.5) -> 0.25 | H76: =IFERROR(_xlfn.PERCENTRANK.INC('面板-MA'!76:76,'面板-MA'!F76),0.5) -> 0.25 | I76: =IFERROR(_xlfn.PERCENTRANK.INC('面板-MA'!76:76,'面板-MA'!G76),0.5) -> 0.176 | J76: =IFERROR(_xlfn.PERCENTRANK.INC('面板-MA'!76:76,'面板-MA'!H76),0.5) -> 0.132 | K76: =IFERROR(_xlfn.PERCENTRANK.INC('面板-MA'!76:76,'面板-MA'!I76),0.5) -> 0.102 | L76: =IFERROR(_xlfn.PERCENTRANK.INC('面板-MA'!76:76,'面板-MA'!J76),0.5) -> 0.029 | M76: =IFERROR(_xlfn.PERCENTRANK.INC('面板-MA'!76:76,'面板-MA'!K76),0.5) -> 0.014 | N76: =IFERROR(_xlfn.PERCENTRANK.INC('面板-MA'!76:76,'面板-MA'!L76),0.5) -> 0 | ... BX76: =IFERROR(_xlfn.PERCENTRANK.INC('面板-MA'!76:76,'面板-MA'!BV76),0.5) -> 0.5
A77: 风电 | B77: 下游 | C77: 风电运营商-3 | D77: 龙源电力风电发电量 | E77: =0.75/13 -> 0.057692308 | F77: =A77&B77 -> 风电下游 | G77: =IFERROR(_xlfn.PERCENTRANK.INC('面板-MA'!77:77,'面板-MA'!E77),0.5) -> 0.985 | H77: =IFERROR(_xlfn.PERCENTRANK.INC('面板-MA'!77:77,'面板-MA'!F77),0.5) -> 0.985 | I77: =IFERROR(_xlfn.PERCENTRANK.INC('面板-MA'!77:77,'面板-MA'!G77),0.5) -> 0.855 | J77: =IFERROR(_xlfn.PERCENTRANK.INC('面板-MA'!77:77,'面板-MA'!H77),0.5) -> 0.492 | K77: =IFERROR(_xlfn.PERCENTRANK.INC('面板-MA'!77:77,'面板-MA'!I77),0.5) -> 0.623 | L77: =IFERROR(_xlfn.PERCENTRANK.INC('面板-MA'!77:77,'面板-MA'!J77),0.5) -> 0.666 | M77: =IFERROR(_xlfn.PERCENTRANK.INC('面板-MA'!77:77,'面板-MA'!K77),0.5) -> 0.202 | N77: =IFERROR(_xlfn.PERCENTRANK.INC('面板-MA'!77:77,'面板-MA'!L77),0.5) -> 0.202 | ... BX77: =IFERROR(_xlfn.PERCENTRANK.INC('面板-MA'!77:77,'面板-MA'!BV77),0.5) -> 0.869
A78: 半导体 | B78: 上游 | C78: 刻蚀机 | D78: 半导体设备进口额 | E78: =0.5/23 -> 0.02173913 | F78: =A78&B78 -> 半导体上游 | G78: =IFERROR(_xlfn.PERCENTRANK.INC('面板-MA'!78:78,'面板-MA'!E78),0.5) -> 0.28 | H78: =IFERROR(_xlfn.PERCENTRANK.INC('面板-MA'!78:78,'面板-MA'!F78),0.5) -> 0.28 | I78: =IFERROR(_xlfn.PERCENTRANK.INC('面板-MA'!78:78,'面板-MA'!G78),0.5) -> 0.192 | J78: =IFERROR(_xlfn.PERCENTRANK.INC('面板-MA'!78:78,'面板-MA'!H78),0.5) -> 0.052 | K78: =IFERROR(_xlfn.PERCENTRANK.INC('面板-MA'!78:78,'面板-MA'!I78),0.5) -> 0.087 | L78: =IFERROR(_xlfn.PERCENTRANK.INC('面板-MA'!78:78,'面板-MA'!J78),0.5) -> 0.21 | M78: =IFERROR(_xlfn.PERCENTRANK.INC('面板-MA'!78:78,'面板-MA'!K78),0.5) -> 0.228 | N78: =IFERROR(_xlfn.PERCENTRANK.INC('面板-MA'!78:78,'面板-MA'!L78),0.5) -> 0.245 | ... BX78: =IFERROR(_xlfn.PERCENTRANK.INC('面板-MA'!78:78,'面板-MA'!BV78),0.5) -> 0.5
A79: 半导体 | B79: 上游 | C79: 薄膜沉积设备（PVD） | D79: 半导体设备进口额 | E79: =0.5/23 -> 0.02173913 | F79: =A79&B79 -> 半导体上游 | G79: =IFERROR(_xlfn.PERCENTRANK.INC('面板-MA'!79:79,'面板-MA'!E79),0.5) -> 0.28 | H79: =IFERROR(_xlfn.PERCENTRANK.INC('面板-MA'!79:79,'面板-MA'!F79),0.5) -> 0.28 | I79: =IFERROR(_xlfn.PERCENTRANK.INC('面板-MA'!79:79,'面板-MA'!G79),0.5) -> 0.192 | J79: =IFERROR(_xlfn.PERCENTRANK.INC('面板-MA'!79:79,'面板-MA'!H79),0.5) -> 0.052 | K79: =IFERROR(_xlfn.PERCENTRANK.INC('面板-MA'!79:79,'面板-MA'!I79),0.5) -> 0.087 | L79: =IFERROR(_xlfn.PERCENTRANK.INC('面板-MA'!79:79,'面板-MA'!J79),0.5) -> 0.21 | M79: =IFERROR(_xlfn.PERCENTRANK.INC('面板-MA'!79:79,'面板-MA'!K79),0.5) -> 0.228 | N79: =IFERROR(_xlfn.PERCENTRANK.INC('面板-MA'!79:79,'面板-MA'!L79),0.5) -> 0.245 | ... BX79: =IFERROR(_xlfn.PERCENTRANK.INC('面板-MA'!79:79,'面板-MA'!BV79),0.5) -> 0.5
A80: 半导体 | B80: 上游 | C80: 清洗设备 | D80: 半导体设备进口额 | E80: =0.5/23 -> 0.02173913 | F80: =A80&B80 -> 半导体上游 | G80: =IFERROR(_xlfn.PERCENTRANK.INC('面板-MA'!80:80,'面板-MA'!E80),0.5) -> 0.28 | H80: =IFERROR(_xlfn.PERCENTRANK.INC('面板-MA'!80:80,'面板-MA'!F80),0.5) -> 0.28 | I80: =IFERROR(_xlfn.PERCENTRANK.INC('面板-MA'!80:80,'面板-MA'!G80),0.5) -> 0.192 | J80: =IFERROR(_xlfn.PERCENTRANK.INC('面板-MA'!80:80,'面板-MA'!H80),0.5) -> 0.052 | K80: =IFERROR(_xlfn.PERCENTRANK.INC('面板-MA'!80:80,'面板-MA'!I80),0.5) -> 0.087 | L80: =IFERROR(_xlfn.PERCENTRANK.INC('面板-MA'!80:80,'面板-MA'!J80),0.5) -> 0.21 | M80: =IFERROR(_xlfn.PERCENTRANK.INC('面板-MA'!80:80,'面板-MA'!K80),0.5) -> 0.228 | N80: =IFERROR(_xlfn.PERCENTRANK.INC('面板-MA'!80:80,'面板-MA'!L80),0.5) -> 0.245 | ... BX80: =IFERROR(_xlfn.PERCENTRANK.INC('面板-MA'!80:80,'面板-MA'!BV80),0.5) -> 0.5
A81: 半导体 | B81: 上游 | C81: 涂胶显影设备 | D81: 半导体设备进口额 | E81: =0.5/23 -> 0.02173913 | F81: =A81&B81 -> 半导体上游 | G81: =IFERROR(_xlfn.PERCENTRANK.INC('面板-MA'!81:81,'面板-MA'!E81),0.5) -> 0.28 | H81: =IFERROR(_xlfn.PERCENTRANK.INC('面板-MA'!81:81,'面板-MA'!F81),0.5) -> 0.28 | I81: =IFERROR(_xlfn.PERCENTRANK.INC('面板-MA'!81:81,'面板-MA'!G81),0.5) -> 0.192 | J81: =IFERROR(_xlfn.PERCENTRANK.INC('面板-MA'!81:81,'面板-MA'!H81),0.5) -> 0.052 | K81: =IFERROR(_xlfn.PERCENTRANK.INC('面板-MA'!81:81,'面板-MA'!I81),0.5) -> 0.087 | L81: =IFERROR(_xlfn.PERCENTRANK.INC('面板-MA'!81:81,'面板-MA'!J81),0.5) -> 0.21 | M81: =IFERROR(_xlfn.PERCENTRANK.INC('面板-MA'!81:81,'面板-MA'!K81),0.5) -> 0.228 | N81: =IFERROR(_xlfn.PERCENTRANK.INC('面板-MA'!81:81,'面板-MA'!L81),0.5) -> 0.245 | ... BX81: =IFERROR(_xlfn.PERCENTRANK.INC('面板-MA'!81:81,'面板-MA'!BV81),0.5) -> 0.5
A82: 半导体 | B82: 上游 | C82: 测试设备 | D82: 半导体设备进口额 | E82: =0.5/23 -> 0.02173913 | F82: =A82&B82 -> 半导体上游 | G82: =IFERROR(_xlfn.PERCENTRANK.INC('面板-MA'!82:82,'面板-MA'!E82),0.5) -> 0.28 | H82: =IFERROR(_xlfn.PERCENTRANK.INC('面板-MA'!82:82,'面板-MA'!F82),0.5) -> 0.28 | I82: =IFERROR(_xlfn.PERCENTRANK.INC('面板-MA'!82:82,'面板-MA'!G82),0.5) -> 0.192 | J82: =IFERROR(_xlfn.PERCENTRANK.INC('面板-MA'!82:82,'面板-MA'!H82),0.5) -> 0.052 | K82: =IFERROR(_xlfn.PERCENTRANK.INC('面板-MA'!82:82,'面板-MA'!I82),0.5) -> 0.087 | L82: =IFERROR(_xlfn.PERCENTRANK.INC('面板-MA'!82:82,'面板-MA'!J82),0.5) -> 0.21 | M82: =IFERROR(_xlfn.PERCENTRANK.INC('面板-MA'!82:82,'面板-MA'!K82),0.5) -> 0.228 | N82: =IFERROR(_xlfn.PERCENTRANK.INC('面板-MA'!82:82,'面板-MA'!L82),0.5) -> 0.245 | ... BX82: =IFERROR(_xlfn.PERCENTRANK.INC('面板-MA'!82:82,'面板-MA'!BV82),0.5) -> 0.5
A83: 半导体 | B83: 上游 | C83: 半导体硅片 | D83: 台湾四大硅片厂合计营收 | E83: =0.5/23 -> 0.02173913 | F83: =A83&B83 -> 半导体上游 | G83: =IFERROR(_xlfn.PERCENTRANK.INC('面板-MA'!83:83,'面板-MA'!E83),0.5) -> 0.652 | H83: =IFERROR(_xlfn.PERCENTRANK.INC('面板-MA'!83:83,'面板-MA'!F83),0.5) -> 0.652 | I83: =IFERROR(_xlfn.PERCENTRANK.INC('面板-MA'!83:83,'面板-MA'!G83),0.5) -> 0.768 | J83: =IFERROR(_xlfn.PERCENTRANK.INC('面板-MA'!83:83,'面板-MA'!H83),0.5) -> 0.695 | K83: =IFERROR(_xlfn.PERCENTRANK.INC('面板-MA'!83:83,'面板-MA'!I83),0.5) -> 0.724 | L83: =IFERROR(_xlfn.PERCENTRANK.INC('面板-MA'!83:83,'面板-MA'!J83),0.5) -> 0.608 | M83: =IFERROR(_xlfn.PERCENTRANK.INC('面板-MA'!83:83,'面板-MA'!K83),0.5) -> 0.376 | N83: =IFERROR(_xlfn.PERCENTRANK.INC('面板-MA'!83:83,'面板-MA'!L83),0.5) -> 0.507 | ... BX83: =IFERROR(_xlfn.PERCENTRANK.INC('面板-MA'!83:83,'面板-MA'!BV83),0.5) -> 0.884
A84: 半导体 | B84: 上游 | C84: 碳化硅 | D84: 台股营收（半导体材料） | E84: =0.5/23 -> 0.02173913 | F84: =A84&B84 -> 半导体上游 | G84: =IFERROR(_xlfn.PERCENTRANK.INC('面板-MA'!84:84,'面板-MA'!E84),0.5) -> 0.376 | H84: =IFERROR(_xlfn.PERCENTRANK.INC('面板-MA'!84:84,'面板-MA'!F84),0.5) -> 0.376 | I84: =IFERROR(_xlfn.PERCENTRANK.INC('面板-MA'!84:84,'面板-MA'!G84),0.5) -> 0.797 | J84: =IFERROR(_xlfn.PERCENTRANK.INC('面板-MA'!84:84,'面板-MA'!H84),0.5) -> 0.724 | K84: =IFERROR(_xlfn.PERCENTRANK.INC('面板-MA'!84:84,'面板-MA'!I84),0.5) -> 0.71 | L84: =IFERROR(_xlfn.PERCENTRANK.INC('面板-MA'!84:84,'面板-MA'!J84),0.5) -> 0.637 | M84: =IFERROR(_xlfn.PERCENTRANK.INC('面板-MA'!84:84,'面板-MA'!K84),0.5) -> 0.405 | N84: =IFERROR(_xlfn.PERCENTRANK.INC('面板-MA'!84:84,'面板-MA'!L84),0.5) -> 0.536 | ... BX84: =IFERROR(_xlfn.PERCENTRANK.INC('面板-MA'!84:84,'面板-MA'!BV84),0.5) -> 0.898
A85: 半导体 | B85: 上游 | C85: 光刻胶 | D85: 台股营收（半导体材料） | E85: =0.5/23 -> 0.02173913 | F85: =A85&B85 -> 半导体上游 | G85: =IFERROR(_xlfn.PERCENTRANK.INC('面板-MA'!85:85,'面板-MA'!E85),0.5) -> 0.376 | H85: =IFERROR(_xlfn.PERCENTRANK.INC('面板-MA'!85:85,'面板-MA'!F85),0.5) -> 0.376 | I85: =IFERROR(_xlfn.PERCENTRANK.INC('面板-MA'!85:85,'面板-MA'!G85),0.5) -> 0.797 | J85: =IFERROR(_xlfn.PERCENTRANK.INC('面板-MA'!85:85,'面板-MA'!H85),0.5) -> 0.724 | K85: =IFERROR(_xlfn.PERCENTRANK.INC('面板-MA'!85:85,'面板-MA'!I85),0.5) -> 0.71 | L85: =IFERROR(_xlfn.PERCENTRANK.INC('面板-MA'!85:85,'面板-MA'!J85),0.5) -> 0.637 | M85: =IFERROR(_xlfn.PERCENTRANK.INC('面板-MA'!85:85,'面板-MA'!K85),0.5) -> 0.405 | N85: =IFERROR(_xlfn.PERCENTRANK.INC('面板-MA'!85:85,'面板-MA'!L85),0.5) -> 0.536 | ... BX85: =IFERROR(_xlfn.PERCENTRANK.INC('面板-MA'!85:85,'面板-MA'!BV85),0.5) -> 0.898
A86: 半导体 | B86: 上游 | C86: 特种气体 | D86: 台股营收（半导体材料） | E86: =0.5/23 -> 0.02173913 | F86: =A86&B86 -> 半导体上游 | G86: =IFERROR(_xlfn.PERCENTRANK.INC('面板-MA'!86:86,'面板-MA'!E86),0.5) -> 0.376 | H86: =IFERROR(_xlfn.PERCENTRANK.INC('面板-MA'!86:86,'面板-MA'!F86),0.5) -> 0.376 | I86: =IFERROR(_xlfn.PERCENTRANK.INC('面板-MA'!86:86,'面板-MA'!G86),0.5) -> 0.797 | J86: =IFERROR(_xlfn.PERCENTRANK.INC('面板-MA'!86:86,'面板-MA'!H86),0.5) -> 0.724 | K86: =IFERROR(_xlfn.PERCENTRANK.INC('面板-MA'!86:86,'面板-MA'!I86),0.5) -> 0.71 | L86: =IFERROR(_xlfn.PERCENTRANK.INC('面板-MA'!86:86,'面板-MA'!J86),0.5) -> 0.637 | M86: =IFERROR(_xlfn.PERCENTRANK.INC('面板-MA'!86:86,'面板-MA'!K86),0.5) -> 0.405 | N86: =IFERROR(_xlfn.PERCENTRANK.INC('面板-MA'!86:86,'面板-MA'!L86),0.5) -> 0.536 | ... BX86: =IFERROR(_xlfn.PERCENTRANK.INC('面板-MA'!86:86,'面板-MA'!BV86),0.5) -> 0.898
A87: 半导体 | B87: 上游 | C87: CMP抛光材料-抛光液 | D87: 台股营收（半导体材料） | E87: =0.5/23 -> 0.02173913 | F87: =A87&B87 -> 半导体上游 | G87: =IFERROR(_xlfn.PERCENTRANK.INC('面板-MA'!87:87,'面板-MA'!E87),0.5) -> 0.376 | H87: =IFERROR(_xlfn.PERCENTRANK.INC('面板-MA'!87:87,'面板-MA'!F87),0.5) -> 0.376 | I87: =IFERROR(_xlfn.PERCENTRANK.INC('面板-MA'!87:87,'面板-MA'!G87),0.5) -> 0.797 | J87: =IFERROR(_xlfn.PERCENTRANK.INC('面板-MA'!87:87,'面板-MA'!H87),0.5) -> 0.724 | K87: =IFERROR(_xlfn.PERCENTRANK.INC('面板-MA'!87:87,'面板-MA'!I87),0.5) -> 0.71 | L87: =IFERROR(_xlfn.PERCENTRANK.INC('面板-MA'!87:87,'面板-MA'!J87),0.5) -> 0.637 | M87: =IFERROR(_xlfn.PERCENTRANK.INC('面板-MA'!87:87,'面板-MA'!K87),0.5) -> 0.405 | N87: =IFERROR(_xlfn.PERCENTRANK.INC('面板-MA'!87:87,'面板-MA'!L87),0.5) -> 0.536 | ... BX87: =IFERROR(_xlfn.PERCENTRANK.INC('面板-MA'!87:87,'面板-MA'!BV87),0.5) -> 0.898
A88: 半导体 | B88: 上游 | C88: CMP抛光材料-抛光垫 | D88: 台股营收（半导体材料） | E88: =0.5/23 -> 0.02173913 | F88: =A88&B88 -> 半导体上游 | G88: =IFERROR(_xlfn.PERCENTRANK.INC('面板-MA'!88:88,'面板-MA'!E88),0.5) -> 0.376 | H88: =IFERROR(_xlfn.PERCENTRANK.INC('面板-MA'!88:88,'面板-MA'!F88),0.5) -> 0.376 | I88: =IFERROR(_xlfn.PERCENTRANK.INC('面板-MA'!88:88,'面板-MA'!G88),0.5) -> 0.797 | J88: =IFERROR(_xlfn.PERCENTRANK.INC('面板-MA'!88:88,'面板-MA'!H88),0.5) -> 0.724 | K88: =IFERROR(_xlfn.PERCENTRANK.INC('面板-MA'!88:88,'面板-MA'!I88),0.5) -> 0.71 | L88: =IFERROR(_xlfn.PERCENTRANK.INC('面板-MA'!88:88,'面板-MA'!J88),0.5) -> 0.637 | M88: =IFERROR(_xlfn.PERCENTRANK.INC('面板-MA'!88:88,'面板-MA'!K88),0.5) -> 0.405 | N88: =IFERROR(_xlfn.PERCENTRANK.INC('面板-MA'!88:88,'面板-MA'!L88),0.5) -> 0.536 | ... BX88: =IFERROR(_xlfn.PERCENTRANK.INC('面板-MA'!88:88,'面板-MA'!BV88),0.5) -> 0.898
A89: 半导体 | B89: 上游 | C89: 溅射靶材 | D89: 台股营收（半导体材料） | E89: =0.5/23 -> 0.02173913 | F89: =A89&B89 -> 半导体上游 | G89: =IFERROR(_xlfn.PERCENTRANK.INC('面板-MA'!89:89,'面板-MA'!E89),0.5) -> 0.376 | H89: =IFERROR(_xlfn.PERCENTRANK.INC('面板-MA'!89:89,'面板-MA'!F89),0.5) -> 0.376 | I89: =IFERROR(_xlfn.PERCENTRANK.INC('面板-MA'!89:89,'面板-MA'!G89),0.5) -> 0.797 | J89: =IFERROR(_xlfn.PERCENTRANK.INC('面板-MA'!89:89,'面板-MA'!H89),0.5) -> 0.724 | K89: =IFERROR(_xlfn.PERCENTRANK.INC('面板-MA'!89:89,'面板-MA'!I89),0.5) -> 0.71 | L89: =IFERROR(_xlfn.PERCENTRANK.INC('面板-MA'!89:89,'面板-MA'!J89),0.5) -> 0.637 | M89: =IFERROR(_xlfn.PERCENTRANK.INC('面板-MA'!89:89,'面板-MA'!K89),0.5) -> 0.405 | N89: =IFERROR(_xlfn.PERCENTRANK.INC('面板-MA'!89:89,'面板-MA'!L89),0.5) -> 0.536 | ... BX89: =IFERROR(_xlfn.PERCENTRANK.INC('面板-MA'!89:89,'面板-MA'!BV89),0.5) -> 0.898
A90: 半导体 | B90: 中游 | C90: IC设计-CIS | D90: 原相营收 | E90: =0.5/23 -> 0.02173913 | F90: =A90&B90 -> 半导体中游 | G90: =IFERROR(_xlfn.PERCENTRANK.INC('面板-MA'!90:90,'面板-MA'!E90),0.5) -> 0 | H90: =IFERROR(_xlfn.PERCENTRANK.INC('面板-MA'!90:90,'面板-MA'!F90),0.5) -> 0 | I90: =IFERROR(_xlfn.PERCENTRANK.INC('面板-MA'!90:90,'面板-MA'!G90),0.5) -> 0.028 | J90: =IFERROR(_xlfn.PERCENTRANK.INC('面板-MA'!90:90,'面板-MA'!H90),0.5) -> 0.043 | K90: =IFERROR(_xlfn.PERCENTRANK.INC('面板-MA'!90:90,'面板-MA'!I90),0.5) -> 0.086 | L90: =IFERROR(_xlfn.PERCENTRANK.INC('面板-MA'!90:90,'面板-MA'!J90),0.5) -> 0.13 | M90: =IFERROR(_xlfn.PERCENTRANK.INC('面板-MA'!90:90,'面板-MA'!K90),0.5) -> 0.072 | N90: =IFERROR(_xlfn.PERCENTRANK.INC('面板-MA'!90:90,'面板-MA'!L90),0.5) -> 0.101 | ... BX90: =IFERROR(_xlfn.PERCENTRANK.INC('面板-MA'!90:90,'面板-MA'!BV90),0.5) -> 0.463
A91: 半导体 | B91: 中游 | C91: IC设计-存储器（DRAM） | D91: DXI指数 | E91: =0.5/23 -> 0.02173913 | F91: =A91&B91 -> 半导体中游 | G91: =IFERROR(_xlfn.PERCENTRANK.INC('面板-MA'!91:91,'面板-MA'!E91),0.5) -> 0.159 | H91: =IFERROR(_xlfn.PERCENTRANK.INC('面板-MA'!91:91,'面板-MA'!F91),0.5) -> 0.217 | I91: =IFERROR(_xlfn.PERCENTRANK.INC('面板-MA'!91:91,'面板-MA'!G91),0.5) -> 0.275 | J91: =IFERROR(_xlfn.PERCENTRANK.INC('面板-MA'!91:91,'面板-MA'!H91),0.5) -> 0.318 | K91: =IFERROR(_xlfn.PERCENTRANK.INC('面板-MA'!91:91,'面板-MA'!I91),0.5) -> 0.362 | L91: =IFERROR(_xlfn.PERCENTRANK.INC('面板-MA'!91:91,'面板-MA'!J91),0.5) -> 0.405 | M91: =IFERROR(_xlfn.PERCENTRANK.INC('面板-MA'!91:91,'面板-MA'!K91),0.5) -> 0.449 | N91: =IFERROR(_xlfn.PERCENTRANK.INC('面板-MA'!91:91,'面板-MA'!L91),0.5) -> 0.507 | ... BX91: =IFERROR(_xlfn.PERCENTRANK.INC('面板-MA'!91:91,'面板-MA'!BV91),0.5) -> 0.855
A92: 半导体 | B92: 中游 | C92: IC设计-存储器（NAND/Nor) | D92: 台股营收（NAND/Nor） | E92: =0.5/23 -> 0.02173913 | F92: =A92&B92 -> 半导体中游 | G92: =IFERROR(_xlfn.PERCENTRANK.INC('面板-MA'!92:92,'面板-MA'!E92),0.5) -> 0 | H92: =IFERROR(_xlfn.PERCENTRANK.INC('面板-MA'!92:92,'面板-MA'!F92),0.5) -> 0 | I92: =IFERROR(_xlfn.PERCENTRANK.INC('面板-MA'!92:92,'面板-MA'!G92),0.5) -> 0.086 | J92: =IFERROR(_xlfn.PERCENTRANK.INC('面板-MA'!92:92,'面板-MA'!H92),0.5) -> 0.159 | K92: =IFERROR(_xlfn.PERCENTRANK.INC('面板-MA'!92:92,'面板-MA'!I92),0.5) -> 0.231 | L92: =IFERROR(_xlfn.PERCENTRANK.INC('面板-MA'!92:92,'面板-MA'!J92),0.5) -> 0.246 | M92: =IFERROR(_xlfn.PERCENTRANK.INC('面板-MA'!92:92,'面板-MA'!K92),0.5) -> 0.318 | N92: =IFERROR(_xlfn.PERCENTRANK.INC('面板-MA'!92:92,'面板-MA'!L92),0.5) -> 0.42 | ... BX92: =IFERROR(_xlfn.PERCENTRANK.INC('面板-MA'!92:92,'面板-MA'!BV92),0.5) -> 0.376
A93: 半导体 | B93: 中游 | C93: IC设计-射频芯片（射频开关） | D93: 立积营收 | E93: =0.5/23 -> 0.02173913 | F93: =A93&B93 -> 半导体中游 | G93: =IFERROR(_xlfn.PERCENTRANK.INC('面板-MA'!93:93,'面板-MA'!E93),0.5) -> 0.333 | H93: =IFERROR(_xlfn.PERCENTRANK.INC('面板-MA'!93:93,'面板-MA'!F93),0.5) -> 0.333 | I93: =IFERROR(_xlfn.PERCENTRANK.INC('面板-MA'!93:93,'面板-MA'!G93),0.5) -> 0.246 | J93: =IFERROR(_xlfn.PERCENTRANK.INC('面板-MA'!93:93,'面板-MA'!H93),0.5) -> 0.159 | K93: =IFERROR(_xlfn.PERCENTRANK.INC('面板-MA'!93:93,'面板-MA'!I93),0.5) -> 0.101 | L93: =IFERROR(_xlfn.PERCENTRANK.INC('面板-MA'!93:93,'面板-MA'!J93),0.5) -> 0.057 | M93: =IFERROR(_xlfn.PERCENTRANK.INC('面板-MA'!93:93,'面板-MA'!K93),0.5) -> 0.115 | N93: =IFERROR(_xlfn.PERCENTRANK.INC('面板-MA'!93:93,'面板-MA'!L93),0.5) -> 0.072 | ... BX93: =IFERROR(_xlfn.PERCENTRANK.INC('面板-MA'!93:93,'面板-MA'!BV93),0.5) -> 0.71
A94: 半导体 | B94: 中游 | C94: IC设计-模拟芯片 | D94: 矽力杰营收 | E94: =0.5/23 -> 0.02173913 | F94: =A94&B94 -> 半导体中游 | G94: =IFERROR(_xlfn.PERCENTRANK.INC('面板-MA'!94:94,'面板-MA'!E94),0.5) -> 0.072 | H94: =IFERROR(_xlfn.PERCENTRANK.INC('面板-MA'!94:94,'面板-MA'!F94),0.5) -> 0.072 | I94: =IFERROR(_xlfn.PERCENTRANK.INC('面板-MA'!94:94,'面板-MA'!G94),0.5) -> 0.144 | J94: =IFERROR(_xlfn.PERCENTRANK.INC('面板-MA'!94:94,'面板-MA'!H94),0.5) -> 0.362 | K94: =IFERROR(_xlfn.PERCENTRANK.INC('面板-MA'!94:94,'面板-MA'!I94),0.5) -> 0.579 | L94: =IFERROR(_xlfn.PERCENTRANK.INC('面板-MA'!94:94,'面板-MA'!J94),0.5) -> 0.623 | M94: =IFERROR(_xlfn.PERCENTRANK.INC('面板-MA'!94:94,'面板-MA'!K94),0.5) -> 0.681 | N94: =IFERROR(_xlfn.PERCENTRANK.INC('面板-MA'!94:94,'面板-MA'!L94),0.5) -> 0.884 | ... BX94: =IFERROR(_xlfn.PERCENTRANK.INC('面板-MA'!94:94,'面板-MA'!BV94),0.5) -> 0.695
A95: 半导体 | B95: 中游 | C95: IC设计-WiFiMCU芯片 | D95: 台股营收（IC设计） | E95: =0.5/23 -> 0.02173913 | F95: =A95&B95 -> 半导体中游 | G95: =IFERROR(_xlfn.PERCENTRANK.INC('面板-MA'!95:95,'面板-MA'!E95),0.5) -> 0 | H95: =IFERROR(_xlfn.PERCENTRANK.INC('面板-MA'!95:95,'面板-MA'!F95),0.5) -> 0 | I95: =IFERROR(_xlfn.PERCENTRANK.INC('面板-MA'!95:95,'面板-MA'!G95),0.5) -> 0.028 | J95: =IFERROR(_xlfn.PERCENTRANK.INC('面板-MA'!95:95,'面板-MA'!H95),0.5) -> 0.057 | K95: =IFERROR(_xlfn.PERCENTRANK.INC('面板-MA'!95:95,'面板-MA'!I95),0.5) -> 0.347 | L95: =IFERROR(_xlfn.PERCENTRANK.INC('面板-MA'!95:95,'面板-MA'!J95),0.5) -> 0.652 | M95: =IFERROR(_xlfn.PERCENTRANK.INC('面板-MA'!95:95,'面板-MA'!K95),0.5) -> 0.724 | N95: =IFERROR(_xlfn.PERCENTRANK.INC('面板-MA'!95:95,'面板-MA'!L95),0.5) -> 0.782 | ... BX95: =IFERROR(_xlfn.PERCENTRANK.INC('面板-MA'!95:95,'面板-MA'!BV95),0.5) -> 0.217
A96: 半导体 | B96: 中游 | C96: IC设计-指纹识别芯片 | D96: 台股营收（IC设计） | E96: =0.5/23 -> 0.02173913 | F96: =A96&B96 -> 半导体中游 | G96: =IFERROR(_xlfn.PERCENTRANK.INC('面板-MA'!96:96,'面板-MA'!E96),0.5) -> 0 | H96: =IFERROR(_xlfn.PERCENTRANK.INC('面板-MA'!96:96,'面板-MA'!F96),0.5) -> 0 | I96: =IFERROR(_xlfn.PERCENTRANK.INC('面板-MA'!96:96,'面板-MA'!G96),0.5) -> 0.028 | J96: =IFERROR(_xlfn.PERCENTRANK.INC('面板-MA'!96:96,'面板-MA'!H96),0.5) -> 0.057 | K96: =IFERROR(_xlfn.PERCENTRANK.INC('面板-MA'!96:96,'面板-MA'!I96),0.5) -> 0.347 | L96: =IFERROR(_xlfn.PERCENTRANK.INC('面板-MA'!96:96,'面板-MA'!J96),0.5) -> 0.652 | M96: =IFERROR(_xlfn.PERCENTRANK.INC('面板-MA'!96:96,'面板-MA'!K96),0.5) -> 0.724 | N96: =IFERROR(_xlfn.PERCENTRANK.INC('面板-MA'!96:96,'面板-MA'!L96),0.5) -> 0.782 | ... BX96: =IFERROR(_xlfn.PERCENTRANK.INC('面板-MA'!96:96,'面板-MA'!BV96),0.5) -> 0.217
A97: 半导体 | B97: 中游 | C97: IC设计-功率半导体（IGBT） | D97: 全球IGBT单管销售额 | E97: =0.5/23 -> 0.02173913 | F97: =A97&B97 -> 半导体中游 | G97: =IFERROR(_xlfn.PERCENTRANK.INC('面板-MA'!97:97,'面板-MA'!E97),0.5) -> 0.71 | H97: =IFERROR(_xlfn.PERCENTRANK.INC('面板-MA'!97:97,'面板-MA'!F97),0.5) -> 0.71 | I97: =IFERROR(_xlfn.PERCENTRANK.INC('面板-MA'!97:97,'面板-MA'!G97),0.5) -> 0.695 | J97: =IFERROR(_xlfn.PERCENTRANK.INC('面板-MA'!97:97,'面板-MA'!H97),0.5) -> 0.492 | K97: =IFERROR(_xlfn.PERCENTRANK.INC('面板-MA'!97:97,'面板-MA'!I97),0.5) -> 0.318 | L97: =IFERROR(_xlfn.PERCENTRANK.INC('面板-MA'!97:97,'面板-MA'!J97),0.5) -> 0.115 | M97: =IFERROR(_xlfn.PERCENTRANK.INC('面板-MA'!97:97,'面板-MA'!K97),0.5) -> 0 | N97: =IFERROR(_xlfn.PERCENTRANK.INC('面板-MA'!97:97,'面板-MA'!L97),0.5) -> 0.797 | ... BX97: =IFERROR(_xlfn.PERCENTRANK.INC('面板-MA'!97:97,'面板-MA'!BV97),0.5) -> 0.333
A98: 半导体 | B98: 中游 | C98: IC设计-功率半导体（MOSFET） | D98: 台湾三大功率厂合计营收 | E98: =0.5/23 -> 0.02173913 | F98: =A98&B98 -> 半导体中游 | G98: =IFERROR(_xlfn.PERCENTRANK.INC('面板-MA'!98:98,'面板-MA'!E98),0.5) -> 0.072 | H98: =IFERROR(_xlfn.PERCENTRANK.INC('面板-MA'!98:98,'面板-MA'!F98),0.5) -> 0.072 | I98: =IFERROR(_xlfn.PERCENTRANK.INC('面板-MA'!98:98,'面板-MA'!G98),0.5) -> 0.202 | J98: =IFERROR(_xlfn.PERCENTRANK.INC('面板-MA'!98:98,'面板-MA'!H98),0.5) -> 0.304 | K98: =IFERROR(_xlfn.PERCENTRANK.INC('面板-MA'!98:98,'面板-MA'!I98),0.5) -> 0.449 | L98: =IFERROR(_xlfn.PERCENTRANK.INC('面板-MA'!98:98,'面板-MA'!J98),0.5) -> 0.434 | M98: =IFERROR(_xlfn.PERCENTRANK.INC('面板-MA'!98:98,'面板-MA'!K98),0.5) -> 0.507 | N98: =IFERROR(_xlfn.PERCENTRANK.INC('面板-MA'!98:98,'面板-MA'!L98),0.5) -> 0.753 | ... BX98: =IFERROR(_xlfn.PERCENTRANK.INC('面板-MA'!98:98,'面板-MA'!BV98),0.5) -> 0.26
A99: 半导体 | B99: 中游 | C99: IC制造-晶圆代工 | D99: 台股营收（IC制造） | E99: =0.5/23 -> 0.02173913 | F99: =A99&B99 -> 半导体中游 | G99: =IFERROR(_xlfn.PERCENTRANK.INC('面板-MA'!99:99,'面板-MA'!E99),0.5) -> 0.913 | H99: =IFERROR(_xlfn.PERCENTRANK.INC('面板-MA'!99:99,'面板-MA'!F99),0.5) -> 0.913 | I99: =IFERROR(_xlfn.PERCENTRANK.INC('面板-MA'!99:99,'面板-MA'!G99),0.5) -> 0.985 | J99: =IFERROR(_xlfn.PERCENTRANK.INC('面板-MA'!99:99,'面板-MA'!H99),0.5) -> 0.84 | K99: =IFERROR(_xlfn.PERCENTRANK.INC('面板-MA'!99:99,'面板-MA'!I99),0.5) -> 0.942 | L99: =IFERROR(_xlfn.PERCENTRANK.INC('面板-MA'!99:99,'面板-MA'!J99),0.5) -> 1 | M99: =IFERROR(_xlfn.PERCENTRANK.INC('面板-MA'!99:99,'面板-MA'!K99),0.5) -> 0.956 | N99: =IFERROR(_xlfn.PERCENTRANK.INC('面板-MA'!99:99,'面板-MA'!L99),0.5) -> 0.869 | ... BX99: =IFERROR(_xlfn.PERCENTRANK.INC('面板-MA'!99:99,'面板-MA'!BV99),0.5) -> 0.666
A100: 半导体 | B100: 中游 | C100: IC封测 | D100: 台股营收（IC封测） | E100: =0.5/23 -> 0.02173913 | F100: =A100&B100 -> 半导体中游 | G100: =IFERROR(_xlfn.PERCENTRANK.INC('面板-MA'!100:100,'面板-MA'!E100),0.5) -> 0 | H100: =IFERROR(_xlfn.PERCENTRANK.INC('面板-MA'!100:100,'面板-MA'!F100),0.5) -> 0 | I100: =IFERROR(_xlfn.PERCENTRANK.INC('面板-MA'!100:100,'面板-MA'!G100),0.5) -> 0.478 | J100: =IFERROR(_xlfn.PERCENTRANK.INC('面板-MA'!100:100,'面板-MA'!H100),0.5) -> 0.681 | K100: =IFERROR(_xlfn.PERCENTRANK.INC('面板-MA'!100:100,'面板-MA'!I100),0.5) -> 0.797 | L100: =IFERROR(_xlfn.PERCENTRANK.INC('面板-MA'!100:100,'面板-MA'!J100),0.5) -> 0.579 | M100: =IFERROR(_xlfn.PERCENTRANK.INC('面板-MA'!100:100,'面板-MA'!K100),0.5) -> 0.55 | N100: =IFERROR(_xlfn.PERCENTRANK.INC('面板-MA'!100:100,'面板-MA'!L100),0.5) -> 0.608 | ... BX100: =IFERROR(_xlfn.PERCENTRANK.INC('面板-MA'!100:100,'面板-MA'!BV100),0.5) -> 0.333
A101: 半导体 | B101: 全链 | D101: 全球半导体销售额 | E101: 0.25 | F101: =A101&B101 -> 半导体全链 | G101: =IFERROR(_xlfn.PERCENTRANK.INC('面板-MA'!101:101,'面板-MA'!E101),0.5) -> 0.202 | H101: =IFERROR(_xlfn.PERCENTRANK.INC('面板-MA'!101:101,'面板-MA'!F101),0.5) -> 0.202 | I101: =IFERROR(_xlfn.PERCENTRANK.INC('面板-MA'!101:101,'面板-MA'!G101),0.5) -> 0.202 | J101: =IFERROR(_xlfn.PERCENTRANK.INC('面板-MA'!101:101,'面板-MA'!H101),0.5) -> 0.405 | K101: =IFERROR(_xlfn.PERCENTRANK.INC('面板-MA'!101:101,'面板-MA'!I101),0.5) -> 0.521 | L101: =IFERROR(_xlfn.PERCENTRANK.INC('面板-MA'!101:101,'面板-MA'!J101),0.5) -> 0.608 | M101: =IFERROR(_xlfn.PERCENTRANK.INC('面板-MA'!101:101,'面板-MA'!K101),0.5) -> 0.768 | N101: =IFERROR(_xlfn.PERCENTRANK.INC('面板-MA'!101:101,'面板-MA'!L101),0.5) -> 0.927 | ... BX101: =IFERROR(_xlfn.PERCENTRANK.INC('面板-MA'!101:101,'面板-MA'!BV101),0.5) -> 0.449
...

Sheet 面板-MA
A2: 产业链 | B2: 环节 | C2: 细分环节 | D2: 同步指标 | E2: 44865 | F2: 44834 | G2: 44804 | H2: 44773 | I2: 44742 | J2: 44712 | K2: 44681 | L2: 44651 | M2: 44620 | N2: 44592 | O2: 44561 | P2: 44530 | Q2: 44500 | R2: 44469 | S2: 44439 | T2: 44408 | U2: 44377 | V2: 44347 | W2: 44316 | X2: 44286 | Y2: 44255 | Z2: 44227 | AA2: 44196 | AB2: 44165 | AC2: 44135 | AD2: 44104 | AE2: 44074 | AF2: 44043 | AG2: 44012 | AH2: 43982 | AI2: 43951 | AJ2: 43921 | AK2: 43890 | AL2: 43861 | AM2: 43830 | AN2: 43799 | AO2: 43769 | AP2: 43738 | AQ2: 43708 | AR2: 43677 | AS2: 43646 | AT2: 43616 | AU2: 43585 | AV2: 43555 | AW2: 43524 | AX2: 43496 | AY2: 43465 | AZ2: 43434 | BA2: 43404 | BB2: 43373 | BC2: 43343 | BD2: 43312 | BE2: 43281 | BF2: 43251 | BG2: 43220 | BH2: 43190 | BI2: 43159 | BJ2: 43131 | BK2: 43100 | BL2: 43069 | BM2: 43039 | BN2: 43008 | BO2: 42978 | BP2: 42947 | BQ2: 42916 | BR2: 42886 | BS2: 42855 | BT2: 42825 | BU2: 42794 | BV2: 42766
A3: 锂电 | B3: 上游 | C3: 钴精矿 | D3: 华东钴精矿价格 | E3: 19.485 | F3: 18.99 | G3: 20.385 | H3: 25.01 | I3: 29.66 | J3: 31.535 | K3: 30.88 | L3: 28.73 | M3: 26.835 | N3: 25.808387 | O3: 23.458387 | P3: 20.988226 | Q3: 19.526559 | R3: 18.837849 | S3: 18.664516 | T3: 17.688333 | U3: 16.912527 | V3: 17.294194 | W3: 18.460323 | X3: 18.509073 | Y3: 15.692137 | Z3: 13.198387 | AA3: 12.854167 | AB3: 13.229167 | AC3: 13.5 | AD3: 13.5 | AE3: 13.37371 | AF3: 13.22871 | AG3: 13.141935 | AH3: 13.314435 | AI3: 14.1625 | AJ3: 15.086379 | AK3: 15.292347 | AL3: 14.757097 | AM3: 14.649129 | AN3: 15.384935 | AO3: 15.471852 | AP3: 14.340965 | AQ3: 13.069274 | AR3: 13.175726 | AS3: 14.56621 | AT3: 15.622043 | AU3: 16.192366 | AV3: 17.643318 | AW3: 19.265899 | AX3: 20.593226 | AY3: 26.851613 | AZ3: 32.68 | BA3: 33.08 | BB3: 33.08 | BC3: 33.08 | BD3: 33.08 | BE3: 32.91871 | BF3: 32.73121 | BG3: 31.842694 | BH3: 29.972158 | BI3: 28.315513 | BJ3: 26.480323 | BK3: 24.006441 | BL3: 22.03128 | BM3: 19.930613 | BN3: 17.799323 | BO3: 16.690323 | BP3: 16.3 | BQ3: 15.706452 | BR3: 14.556452 | BS3: 13.903226 | BT3: 12.653226 | BU3: 11.302419 | BV3: 10.842742
A4: 锂电 | B4: 上游 | C4: 锂盐-氢氧化锂 | D4: 电池级氢氧化锂价格（≥56.5%） | E4: 50.583529 | F4: 47.703529 | G4: 46.805 | H4: 46.75 | I4: 46.765789 | J4: 47.551316 | K4: 48.022483 | L4: 41.868207 | M4: 31.470724 | N4: 23.382952 | O4: 19.291206 | P4: 18.507102 | Q4: 16.379375 | R4: 12.835909 | S4: 10.420455 | T4: 9.4581169 | U4: 9.0230159 | V4: 8.3444444 | W4: 7.3413043 | X4: 6.3713043 | Y4: 5.615 | Z4: 5.0480435 | AA4: 4.8130435 | AB4: 4.834375 | AC4: 4.884375 | AD4: 4.9 | AE4: 4.95 | AF4: 5.1825 | AG4: 5.4713889 | AH4: 5.5888889 | AI4: 5.5954545 | AJ4: 5.5379545 | AK4: 5.4675 | AL4: 5.4704545 | AM4: 5.7085498 | AN4: 6.1714286 | AO4: 6.6510833 | AP4: 7.1484318 | AQ4: 7.7045949 | AR4: 8.2897025 | AS4: 8.9320395 | AT4: 9.5114881 | AU4: 9.9535714 | AV4: 10.358333 | AW4: 10.705682 | AX4: 11.191932 | AY4: 11.824886 | AZ4: 12.413636 | BA4: 12.85 | BB4: 13.173913 | BC4: 13.747777 | BD4: 14.336364 | BE4: 14.6375 | BF4: 14.75 | BG4: 14.75 | BH4: 14.763333 | BI4: 14.813333 | BJ4: 14.85 | BK4: 14.85 | BL4: 14.682353 | BM4: 14.287115 | BN4: 14.352588 | BO4: 15.197826 | BP4: 15.75 | BQ4: 15.75 | BR4: 15.75 | BS4: 15.75
A5: 锂电 | B5: 上游 | C5: 锂盐-碳酸锂 | D5: 电池级碳酸锂价格 | E5: 51.34 | F5: 48.72 | G5: 47.452143 | H5: 46.942143 | I5: 46.335 | J5: 46.857143 | K5: 48.922143 | L5: 46.482857 | M5: 38.432143 | N5: 28.961508 | O5: 22.038889 | P5: 19.52381 | Q5: 17.029365 | R5: 12.636111 | S5: 9.5138889 | T5: 8.6964286 | U5: 8.7151786 | V5: 8.8794643 | W5: 8.6782143 | X5: 7.9025 | Y5: 6.763125 | Z5: 5.4003472 | AA5: 4.4638889 | AB5: 4.1380952 | AC5: 4.0214286 | AD5: 4 | AE5: 4.0333333 | AF5: 4.1536458 | AG5: 4.35 | AH5: 4.5890625 | AI5: 4.8746528 | AJ5: 5.0402778 | AK5: 5.08 | AL5: 5.205 | AM5: 5.702381 | AN5: 6.5418546 | AO5: 7.2289474 | AP5: 7.42811 | AQ5: 7.5092885 | AR5: 7.7048627 | AS5: 7.7842105 | AT5: 7.8034091 | AU5: 7.8784091 | AV5: 7.95 | AW5: 7.95 | AX5: 7.9681818 | AY5: 7.9681818 | AZ5: 7.95 | BA5: 8.3025 | BB5: 9.2742391 | BC5: 10.967194 | BD5: 12.63355 | BE5: 13.574459 | BF5: 14.486364 | BG5: 15.552841 | BH5: 16.049716 | BI5: 16.181658 | BJ5: 16.545497 | BK5: 16.885714 | BL5: 16.7 | BM5: 16.145 | BN5: 15.601522 | BO5: 14.931522 | BP5: 14.504545 | BQ5: 14.30998 | BR5: 13.79234 | BS5: 13.26645 | BT5: 13.054545 | BU5: 13 | BV5: 13
A6: 锂电 | B6: 上游 | C6: 三元前驱体（镍钴锰） | D6: 三元前驱体价格（523) | E6: 10.89 | F6: 10.84 | G6: 11.311429 | H6: 12.541429 | I6: 14.01625 | J6: 15.454205 | K6: 15.876433 | L6: 14.745041 | M6: 13.601562 | N6: 13.3 | O6: 13.179545 | P6: 12.86526 | Q6: 12.589123 | R6: 12.6375 | S6: 12.346591 | T6: 11.281548 | U6: 10.527381 | V6: 10.592857 | W6: 11.481263 | X6: 11.571739 | Y6: 10.21 | Z6: 8.8143478 | AA6: 8.1043478 | AB6: 8.0954545 | AC6: 8.1954545 | AD6: 8.1880952 | AE6: 7.7011387 | AF6: 7.2630435 | AG6: 7.25 | AH6: 7.302381 | AI6: 7.9251082 | AJ6: 8.3327273 | AK6: 7.99125 | AL6: 7.9039773 | AM6: 8.687013 | AN6: 9.7559524 | AO6: 9.8583333 | AP6: 8.7621212 | AQ6: 7.6269763 | AR6: 7.723627 | AS6: 8.45401 | AT6: 8.8119048 | AU6: 9.102381 | AV6: 9.552381 | AW6: 9.75 | AX6: 9.8386364 | AY6: 10.525 | AZ6: 11.305808 | BA6: 11.556287 | BB6: 11.74119 | BC6: 12.179348 | BD6: 12.8275 | BE6: 13.578587 | BF6: 14.477277 | BG6: 14.785281 | BH6: 13.98115 | BI6: 13.081841 | BJ6: 12.339545 | BK6: 11.704762 | BL6: 11.508824 | BM6: 11.258824 | BN6: 10.723913 | BO6: 10.273913 | BP6: 10.170652 | BQ6: 10.637319 | BR6: 11.300417 | BS6: 11.50875 | BT6: 10.59125 | BU6: 8.8676389 | BV6: 8.0527778
A7: 锂电 | B7: 上游 | C7: 电解液溶剂（DMC) | D7: DMC价格 | E7: 1.876339 | F7: 1.9682633 | G7: 2.0140323 | H7: 2.0912688 | I7: 2.363043 | J7: 2.6762097 | K7: 3.1891129 | L7: 3.42822 | M7: 3.1078975 | N7: 2.7964516 | O7: 2.9876613 | P7: 4.6144355 | Q7: 5.0472688 | R7: 3.7266237 | S7: 3.1462903 | T7: 2.97 | U7: 2.7764516 | V7: 2.7756183 | W7: 2.7885215 | X7: 2.4157834 | Y7: 2.1206221 | Z7: 2.5072581 | AA7: 2.7780645 | AB7: 2.241129 | AC7: 1.781129 | AD7: 1.6825806 | AE7: 1.6517742 | AF7: 1.6751935 | AG7: 1.582129 | AH7: 1.4827957 | AI7: 1.5910215 | AJ7: 1.7678031 | AK7: 1.8484483 | AL7: 1.8301613 | AM7: 1.7551613 | AN7: 1.7129032 | AO7: 1.8880699 | AP7: 2.071457 | AQ7: 1.9329032 | AR7: 1.7171129 | AS7: 1.8345323 | AT7: 2.0630323 | AU7: 2.0793571 | AV7: 1.9356696 | AW7: 1.823267 | AX7: 1.8770022 | AY7: 1.9588203 | AZ7: 2.2803283 | BA7: 2.8443651 | BB7: 3.2581573 | BC7: 3.4293478 | BD7: 3.45 | BE7: 3.4193182 | BF7: 3.2468182 | BG7: 3.0468182 | BH7: 2.9474432 | BI7: 2.8951705 | BJ7: 2.8449026 | BK7: 2.8687662 | BL7: 2.9659091 | BM7: 2.8988636 | BN7: 2.4684289 | BO7: 2.0324224 | BP7: 2.0208117 | BQ7: 2.1229545 | BR7: 2.1389474 | BS7: 2.1245995 | BT7: 2.0082838 | BU7: 1.8748538 | BV7: 1.7967677
A8: 锂电 | B8: 上游 | C8: 电解液溶质（六氟磷酸锂） | D8: 六氟磷酸锂价格 | E8: 28.798056 | F8: 27.138056 | G8: 26.145 | H8: 25.375 | I8: 28.44 | J8: 37.305 | K8: 48.12 | L8: 56.13 | M8: 58.76 | N8: 57.51 | O8: 55.41 | P8: 52.055 | Q8: 47.12 | R8: 43.155 | S8: 39.93 | T8: 34.615 | U8: 28.675 | V8: 23.595 | W8: 20.385 | X8: 17.165 | Y8: 13.36 | Z8: 11.42 | AA8: 9.95 | AB8: 8.825 | AC8: 8.0488636 | AD8: 7.2833874 | AE8: 7.0095238 | AF8: 7.40875 | AG8: 7.9573611 | AH8: 8.2236111 | AI8: 8.3272727 | AJ8: 8.4022727 | AK8: 8.55 | AL8: 8.75 | AM8: 9.0797619 | AN8: 9.4047619 | AO8: 9.5 | AP8: 9.5 | AQ8: 9.8532609 | AR8: 10.353261 | AS8: 10.5 | AT8: 10.806818 | AU8: 11.181818 | AV8: 11.25 | AW8: 11.213043 | AX8: 11.163043 | AY8: 11.105682 | AZ8: 11.030682 | BA8: 11.342105 | BB8: 11.842105 | BC8: 12 | BD8: 12 | BE8: 12 | BF8: 12.309524 | BG8: 13.354978 | BH8: 15.045455 | BI8: 16 | BJ8: 16 | BK8: 16 | BL8: 16 | BM8: 16.318182 | BN8: 16.818182 | BO8: 17.238095 | BP8: 17.488095 | BQ8: 20.309524 | BR8: 28.122024 | BS8: 35.040761 | BT8: 38.228261 | BU8: 39.5 | BV8: 39.5
A9: 锂电 | B9: 中游 | C9: 锂电设备 | D9: 锂电设备财报营收 | E9: 87.613396 | F9: 87.613396 | G9: 87.613396 | H9: 97.866506 | I9: 97.866506 | J9: 154.14525 | K9: 154.14525 | L9: 154.14525 | M9: 82.022788 | N9: 82.022788 | O9: 82.022788 | P9: 57.686952 | Q9: 57.686952 | R9: 57.686952 | S9: 63.665293 | T9: 63.665293 | U9: 63.665293 | V9: 30.61794 | W9: 30.61794 | X9: 30.61794 | Y9: 26.988069 | Z9: 26.988069 | AA9: 26.988069 | AB9: 23.813372 | AC9: 23.813372 | AD9: 23.813372 | AE9: 6.6037987 | AF9: 6.6037987 | AG9: 6.6037987 | AH9: 2.4613837 | AI9: 2.4613837 | AJ9: 2.4613837 | AK9: 8.1864452 | AL9: 8.1864452 | AM9: 8.1864452 | AN9: 11.489445 | AO9: 11.489445 | AP9: 11.489445 | AQ9: 18.656831 | AR9: 18.656831 | AS9: 18.656831 | AT9: 24.859798 | AU9: 24.859798 | AV9: 24.859798 | AW9: 56.292438 | AX9: 56.292438 | AY9: 56.292438 | AZ9: 81.805301 | BA9: 81.805301 | BB9: 81.805301 | BC9: 78.856192 | BD9: 78.856192 | BE9: 78.856192 | BF9: 106.6689 | BG9: 106.6689 | BH9: 106.6689 | BI9: 93.795591 | BJ9: 93.795591 | BK9: 93.795591 | BL9: 92.264349 | BM9: 92.264349 | BN9: 92.264349 | BO9: 89.489608 | BP9: 89.489608 | BQ9: 89.489608 | BR9: 71.216435 | BS9: 71.216435 | BT9: 71.216435
A10: 锂电 | B10: 中游 | C10: 正极材料-磷酸铁锂 | D10: 磷酸铁锂产量 | E10: 175.125 | F10: 152.25 | G10: 118.905 | H10: 130.43 | I10: 149.65 | J10: 136.775 | K10: 126.87 | L10: 148.855 | M10: 183.51 | N10: 206.545 | O10: 186.005 | P10: 164.62 | Q10: 144.845 | R10: 159.54 | S10: 202.9 | T10: 212.365 | U10: 231.16 | V10: 292.375 | W10: 351.81 | X10: 558.785 | Y10: 570.95 | Z10: 314.25 | AA10: 179.395 | AB10: 98.19 | AC10: 57.815 | AD10: 51.69 | AE10: 45.415 | AF10: 27.855 | AG10: 1.275 | AH10: -25.205 | AI10: -35.03 | AJ10: -42.83 | AK10: -41.34 | AL10: -33.88 | AM10: -18.565 | AN10: 10.355 | AO10: 27.435 | AP10: 24.475 | AQ10: 22.23 | AR10: 34.025 | AS10: 51.625 | AT10: 62.665 | AU10: 73.345 | AV10: 57.935 | AW10: 27.64 | AX10: 30.64 | AY10: 39.75 | AZ10: 33.62 | BA10: 22.275 | BB10: 6.02 | BC10: -4.42 | BD10: -7.78 | BE10: -12.265 | BF10: -14.66 | BG10: -20.45 | BH10: -19.56 | BI10: -5.725 | BJ10: 1.695 | BK10: -3.5 | BL10: -4.595 | BM10: 2.39 | BN10: 6.225 | BO10: 3.955 | BP10: 0.495 | BQ10: 5.915 | BR10: 6.46 | BS10: 1.21 | BT10: -11.32 | BU10: -16.555 | BV10: -8.8
A11: 锂电 | B11: 中游 | C11: 正极材料-三元材料 | D11: 三元材料产量 | E11: 42.34 | F11: 40.41 | G11: 30.365 | H11: 25.035 | I11: 24.61 | J11: 30.545 | K11: 44.26 | L11: 59.22 | M11: 63.935 | N11: 64.315 | O11: 58.73 | P11: 57.23 | Q11: 60.75 | R11: 72.81 | S11: 100.79 | T11: 117.29 | U11: 127.425 | V11: 158.575 | W11: 190.65 | X11: 200.84 | Y11: 149.695 | Z11: 93.185 | AA11: 80.305 | AB11: 52.28 | AC11: 21.14 | AD11: 9.815 | AE11: -2.655 | AF11: -16.465 | AG11: -26.335 | AH11: -34.31 | AI11: -36.235 | AJ11: -28.73 | AK11: -5.36 | AL11: 0.675 | AM11: -5.83 | AN11: 10.625 | AO11: 20.915 | AP11: 18.24 | AQ11: 18.45 | AR11: 20.295 | AS11: 24.685 | AT11: 18.805 | AU11: 13.32 | AV11: 9.125 | AW11: 4.01 | AX11: 19.375 | AY11: 34.99 | AZ11: 30.18 | BA11: 30.29 | BB11: 27.695 | BC11: 20.74 | BD11: 23.5 | BE11: 32.3 | BF11: 38.345 | BG11: 28.71 | BH11: 15.305 | BI11: 16.25 | BJ11: 49.83 | BK11: 75.935 | BL11: 91.155 | BM11: 94.135 | BN11: 88.285 | BO11: 86.36 | BP11: 85.67 | BQ11: 78.87 | BR11: 67.225 | BS11: 63.105 | BT11: 53.825 | BU11: 55.19 | BV11: 58.34
A12: 锂电 | B12: 中游 | C12: 正极材料-钴酸锂 | D12: 钴酸锂产量 | E12: -33.9 | F12: -38.425 | G12: -46.73 | H12: -37.4 | I12: -30.765 | J12: -24 | K12: -6.04 | L12: 4.725 | M12: 3.93 | N12: -1.135 | O12: -8.165 | P12: -8.875 | Q12: 1.575 | R12: 19 | S12: 31.08 | T12: 35.84 | U12: 40.545 | V12: 55.18 | W12: 74.875 | X12: 101.49 | Y12: 100.475 | Z12: 95.485 | AA12: 82.005 | AB12: 44.635 | AC12: 28.785 | AD12: 24.61 | AE12: 24.505 | AF12: 22.815 | AG12: 11.675 | AH12: 3.225 | AI12: -2.99 | AJ12: 4.67 | AK12: 11.255 | AL12: -8.81 | AM12: -8.66 | AN12: 6.615 | AO12: 12.605 | AP12: 12.035 | AQ12: 9.785 | AR12: 11.53 | AS12: 22.06 | AT12: 20.84 | AU12: 9.9 | AV12: -11.885 | AW12: -19.735 | AX12: 3.43 | AY12: 15.36 | AZ12: 15.495 | BA12: 14.87 | BB12: 6.99 | BC12: 4.965 | BD12: 8.925 | BE12: 6.49 | BF12: 1.3 | BG12: -2.49 | BH12: -1.135 | BI12: -1.455 | BJ12: 7.595 | BK12: 13.775 | BL12: 11.015 | BM12: 9.73 | BN12: 17.955 | BO12: 19.365 | BP12: 10.94 | BQ12: 11.315 | BR12: 17.17 | BS12: 20.8 | BT12: 14.615 | BU12: 12.4 | BV12: 14.5
A13: 锂电 | B13: 中游 | C13: 负级材料 | D13: 中端人造石墨负极价格 | E13: 5.65 | F13: 5.8 | G13: 5.8 | H13: 5.8 | I13: 5.74 | J13: 5.6066667 | K13: 5.5166667 | L13: 5.5 | M13: 5.5 | N13: 5.5 | O13: 5.4375 | P13: 5.2237903 | Q13: 4.9612903 | R13: 4.7540323 | S13: 4.5790323 | T13: 4.5 | U13: 4.5 | V13: 4.5 | W13: 4.35 | X13: 4.2 | Y13: 4.2 | Z13: 4.2 | AA13: 4.2 | AB13: 4.2 | AC13: 4.2 | AD13: 4.2 | AE13: 4.2 | AF13: 4.2 | AG13: 4.2 | AH13: 4.2479167 | AI13: 4.318078 | AJ13: 4.3451613 | AK13: 4.35 | AL13: 4.35 | AM13: 4.35 | AN13: 4.35 | AO13: 4.3533333 | AP13: 4.3783333 | AQ13: 4.45 | AR13: 4.5 | AS13: 4.5 | AT13: 4.6125 | AU13: 4.7657258 | AV13: 4.9032258 | AW13: 5 | AX13: 5 | AY13: 5.0541667 | AZ13: 5.1791667 | BA13: 5.25 | BB13: 5.25 | BC13: 5.25 | BD13: 5.27925 | BE13: 5.328 | BF13: 5.3475 | BG13: 5.3475 | BH13: 5.3475 | BI13: 5.3538581 | BJ13: 5.4674468 | BK13: 5.5619887 | BL13: 5.66965 | BM13: 5.7816667 | BN13: 5.7827828 | BO13: 5.6296597 | BP13: 5.2268735 | BQ13: 4.96833 | BR13: 4.95 | BS13: 4.95 | BT13: 4.95 | BU13: 4.95 | BV13: 4.95
A14: 锂电 | B14: 中游 | C14: 电解液 | D14: 电解液产量 | E14: 77.145 | F14: 87.275 | G14: 89.6 | H14: 77.215 | I14: 57.355 | J14: 46.68 | K14: 58.79 | L14: 81.12 | M14: 92.365 | N14: 86.06 | O14: 69.56 | P14: 59.37 | Q14: 51.665 | R14: 40.715 | S14: 34.67 | T14: 37.02 | U14: 45.585 | V14: 51.65 | W14: 51.08 | X14: 76.93 | Y14: 75.86 | Z14: 53.795 | AA14: 57.855 | AB14: 48.545 | AC14: 42.47 | AD14: 48.57 | AE14: 52.59 | AF14: 51.41 | AG14: 33.595 | AH14: 17.685 | AI14: 19.58 | AJ14: 2.535 | AK14: 1.28 | AL14: 13.585 | AM14: 10.255 | AN14: 16.19 | AO14: 23.165 | AP14: 21.51 | AQ14: 15.33 | AR14: 14.54 | AS14: 27.65 | AT14: 37.34 | AU14: 42.88 | AV14: 82.08 | AW14: 97.125 | AX14: 83.18 | AY14: 80.71 | AZ14: 65.875 | BA14: 51.37 | BB14: 50.02 | BC14: 50.445 | BD14: 49.605 | BE14: 53.315 | BF14: 52.14 | BG14: 42.81 | BH14: 24.29 | BI14: 17.58 | BJ14: 18.515 | BK14: 17.69 | BL14: 31.16 | BM14: 50.01 | BN14: 57.455 | BO14: 63.195 | BP14: 37.475 | BQ14: 1.995 | BR14: 2.19 | BS14: 23.135 | BT14: 29.125 | BU14: 16.06 | BV14: 14.59
A15: 锂电 | B15: 中游 | C15: 隔膜 | D15: 隔膜产量 | E15: 68.165 | F15: 64.72 | G15: 59.93 | H15: 57.25 | I15: 57.07 | J15: 58.8 | K15: 69.76 | L15: 86.585 | M15: 98.225 | N15: 90.04 | O15: 75.56 | P15: 74.07 | Q15: 78.58 | R15: 76.16 | S15: 84.675 | T15: 102.75 | U15: 107.74 | V15: 108.905 | W15: 100.61 | X15: 126.205 | Y15: 128.565 | Z15: 84.725 | AA15: 59.06 | AB15: 38.995 | AC15: 28.59 | AD15: 28.17 | AE15: 30.965 | AF15: 24.16 | AG15: 13.445 | AH15: 5.67 | AI15: 4.79 | AJ15: -7.68 | AK15: -14.49 | AL15: 4.085 | AM15: 17.015 | AN15: 22.64 | AO15: 27.705 | AP15: 32.145 | AQ15: 30.215 | AR15: 30.14 | AS15: 44.58 | AT15: 66.18 | AU15: 74.015 | AV15: 62.795 | AW15: 63.14 | AX15: 49.075 | AY15: 41.055 | AZ15: 60.595 | BA15: 61.67 | BB15: 51.71 | BC15: 44.365 | BD15: 45.72 | BE15: 43.07 | BF15: 29.985 | BG15: 31.42 | BH15: 49.385 | BI15: 55.165 | BJ15: 56.86 | BK15: 50.68 | BL15: 40.715 | BM15: 43.275 | BN15: 48.085 | BO15: 52.395 | BP15: 29.865 | BQ15: 3.31 | BR15: 4.835 | BS15: 17.86 | BT15: 23.8 | BU15: 11.67 | BV15: 2.03
A16: 锂电 | B16: 中游 | C16: 辅材-铜箔 | D16: 电池级铜箔价格（8um) | E16: 92.4245 | F16: 93.217 | G16: 94.3005 | H16: 103.4525 | I16: 112.5 | J16: 112.66667 | K16: 112.16667 | L16: 112 | M16: 112 | N16: 112 | O16: 112 | P16: 112 | Q16: 111.96591 | R16: 111.71591 | S16: 111.5 | T16: 110.71429 | U16: 107.75376 | V16: 104.78947 | W16: 97.695652 | X16: 89.078005 | Y16: 85.569853 | Z16: 83.4375 | AA16: 79.464286 | AB16: 76.214286 | AC16: 75.934783 | AD16: 73.934783 | AE16: 72 | AF16: 72 | AG16: 72 | AH16: 72 | AI16: 73.840909 | AJ16: 81.840909 | AK16: 88.75 | AL16: 89.5 | AM16: 89.5 | AN16: 89.5 | AO16: 89.5 | AP16: 89.5 | AQ16: 89.5 | AR16: 89.5 | AS16: 89.5 | AT16: 89.5 | AU16: 89.5 | AV16: 89.5 | AW16: 89.5 | AX16: 89.5 | AY16: 89.5 | AZ16: 89.5 | BA16: 89.736842 | BB16: 90.454233 | BC16: 91.217391 | BD16: 91.5 | BE16: 91.5 | BF16: 92.690476 | BG16: 95.190476 | BH16: 96.5 | BI16: 96.5 | BJ16: 96.5 | BK16: 96.5 | BL16: 96.5 | BM16: 96.272727 | BN16: 91.272727 | BO16: 86.5 | BP16: 86.5 | BQ16: 86.5 | BR16: 86.5 | BS16: 86.5 | BT16: 86.5 | BU16: 86.5 | BV16: 85.875
