Workbook
Name benchmark: 参数设置!$P$4:$P$48
Name comparlastrep: 参数设置!$D$6
Name comppool: 参数设置!$V:$Y
Name currencyunit: 盈利预测!$E$10
Name CurrencyUnit: 参数设置!$G$3
Name gross_items: 主营构成!$J$27:$N$31
Name holdertime: 参数设置!$G$9
Name holdertimetype: 参数设置!$C$9:$F$9
Name industrytype: 参数设置!$U$6:$U$9
Name Institutionlist: 参数设置!$B$16:$C$108
Name pricetype: 参数设置!$C$8:$E$8
Name quantity: 盈利预测!$Q$15:$Q$83
Name recentreportdate: 参数设置!$D$4
Name reporttype: 参数设置!$C$10:$F$10
Name rev_items: 主营构成!$J$20:$N$24
Name rptype: 参数设置!$G$10
Name rptype2: 参数设置!$G$11
Name rptype3: 参数设置!$G$12
Name rptype4: 参数设置!$G$13
Name rptype5: 参数设置!$G$14
Name series: 参数设置!$V:$V
Name timetype: 参数设置!$C$5:$E$5
Name Unit: 参数设置!$C$3:$F$3

Sheet 公司分析
D1: 股票速览-公司分析(港股)
C4: 交易代码 | D4: 9626.HK | E4: 证券简称 | F4: =[1]!s_info_name(D4) -> 哔哩哔哩-W
C5: 日期 | D5: =TODAY()-1 -> 45466 | E5: 单位 | F5: 亿
C7: 说明：《公司分析》提供上市公司速览、盈利预测、行业比较等内容。通过本模板，可以快速浏览上市公司的基本信息，股价、股本、股东及财务经营状况；机构的预测明细和进行相关行业的比较，了解公司在行业中的地位。
C8: 公司概况
C10: 公司名称 | D10: =[1]!s_info_compname(D4) -> 哔哩哔哩股份有限公司 | M10: EPS(摊薄) | N10: =[1]!hks_fa_eps_ttm2(D4,YEAR(行业比较!G5)-1&"-12-31",0) -> -20.230138 | O10: 现价 | P10: =RTD("wdf.rtq",,D4,5) -> 137.3 | T10: 前收盘价 | U10: =[1]!s_dq_close(D4,D5,1) -> 136.8
C11: 首发上市日期 | D11: =[1]!s_ipo_listeddate(D4) -> 2021-03-29 | M11: BPS | N11: =[1]!hks_fa_bps(D4,YEAR(行业比较!G5)-1&"-12-31") -> 38.102437 | O11: 开盘价 | P11: =RTD("wdf.rtq",,D4,2) -> 140.6 | T11: 涨跌 | U11: =RTD("wdf.rtq",,D4,26) -> 0.5
C12: 公司电话 | D12: =[1]!s_info_phone(D4) -> 0 | M12: 市盈率 | N12: =[1]!s_val_pe(D4,D5,1) -> -10.829672 | O12: 最高价 | P12: =RTD("wdf.rtq",,D4,3) -> 141.4 | T12: 涨跌幅 | U12: =RTD("wdf.rtq",,D4,27)/100 -> 0.0037
C13: 公司传真 | D13: =[1]!s_info_fax(D4) -> 0 | M13: 市净率 | N13: =[1]!s_val_pb(D4,D5,1) -> 3.6287186 | O13: 最低价 | P13: =RTD("wdf.rtq",,D4,4) -> 136.3 | T13: 成交量(万) | U13: =RTD("wdf.rtq",,D4,29)/10000 -> 40442.286
C14: 行业(SW/GICS) | D14: =[1]!s_info_industry_sw_2021(D4,D5,1)&"/"&[1]!s_info_industry_gics(D4) -> 传媒/信息技术 | M14: ="总股本"&"("&F5&")" -> 总股本(亿) | N14: =[1]!s_share_total(D4,D5)/CurrencyUnit -> 4.2126142 | O14: 均价 | P14: =RTD("wdf.rtq",,D4,28) -> 138.602 | T14: 成交额(万) | U14: =RTD("wdf.rtq",,D4,30)/10000 -> 291.7872
C15: 员工总数 | D15: =[1]!s_info_employee(D4,YEAR(行业比较!G5)-1&"-12-31") -> 11092 | M15: ="总市值"&"("&F5&")" -> 总市值(亿) | N15: =[1]!s_val_mv(D4,D5)/CurrencyUnit -> 576.28562 | O15: 60日最高/最低 | P15: =[1]!s_pq_high(D4,D5-60,D5,1)&"/"&[1]!s_pq_low(D4,D5-60,D5,1) -> 145.6/90.55
C16: 年度审计意见 | D16: =[1]!s_stmnote_audit_category(D4,YEAR(行业比较!G5)-1&"-12-31",2) -> 标准无保留意见
C20: 市场表现 | D20: 不复权 | E20: 周 | F20: PE Band | G20: =LEFT(F20,2)&"最小值=8" -> PE最小值=8 | H20: =LEFT(F20,2)&"间距="&H29 -> PE间距=12 | M20: 指数基准 | V20: 恒生科技指数
H29: 12
C37: 主要股东分析 | V37: ="单位:("&F5&")" -> 单位:(亿)
C38: 前10大股东 | F38: =D5 -> 45466 | M38: 半年前 | V38: =holdertime -> 45286
C39: 股东名称 | F39: 持股数量 | G39: 持股比例 | H39: ="较"&M38&"变动" -> 较半年前变动 | M39: 股东名称 | V39: 持股数量
C40: =[1]!s_holder_name($D$4,F$38,1) -> Deutsche Bank Aktiengesellschaft | F40: =[1]!s_holder_quantity($D$4,F$38,1)/CurrencyUnit -> 1.1022008 | G40: =[1]!s_holder_pct($D$4,F$38,1)/100 -> 0.2616 | H40: =IF(ISNA(VLOOKUP(C40,$M$40:$V$50,4,FALSE)),F40,F40-VLOOKUP(C40,$M$40:$V$50,4,FALSE)) -> 1.1022008 | M40: =[1]!s_holder_name($D$4,V$38,1) -> Vanship Limited | V40: =[1]!s_holder_quantity($D$4,V$38,1)/CurrencyUnit -> 0.49299006
C41: =[1]!s_holder_name($D$4,F$38,2) -> Vanship Limited | F41: =[1]!s_holder_quantity($D$4,F$38,2)/CurrencyUnit -> 0.49824531 | G41: =[1]!s_holder_pct($D$4,F$38,2)/100 -> 0.1183 | H41: =IF(ISNA(VLOOKUP(C41,$M$40:$V$50,4,FALSE)),F41,F41-VLOOKUP(C41,$M$40:$V$50,4,FALSE)) -> 0.49824531 | M41: =[1]!s_holder_name($D$4,V$38,2) -> Tencent Mobility Limited | V41: =[1]!s_holder_quantity($D$4,V$38,2)/CurrencyUnit -> 0.32795161
C42: =[1]!s_holder_name($D$4,F$38,3) -> Tencent Mobility Limited | F42: =[1]!s_holder_quantity($D$4,F$38,3)/CurrencyUnit -> 0.32795161 | G42: =[1]!s_holder_pct($D$4,F$38,3)/100 -> 0.077800002 | H42: =IF(ISNA(VLOOKUP(C42,$M$40:$V$50,4,FALSE)),F42,F42-VLOOKUP(C42,$M$40:$V$50,4,FALSE)) -> 0.32795161 | M42: =[1]!s_holder_name($D$4,V$38,3) -> 淘宝中国控股有限公司 | V42: =[1]!s_holder_quantity($D$4,V$38,3)/CurrencyUnit -> 0.30845657
C43: =[1]!s_holder_name($D$4,F$38,4) -> Kami Sama Limited | F43: =[1]!s_holder_quantity($D$4,F$38,4)/CurrencyUnit -> 0.27367208 | G43: =[1]!s_holder_pct($D$4,F$38,4)/100 -> 0.065 | H43: =IF(ISNA(VLOOKUP(C43,$M$40:$V$50,4,FALSE)),F43,F43-VLOOKUP(C43,$M$40:$V$50,4,FALSE)) -> 0.27367208 | M43: =[1]!s_holder_name($D$4,V$38,4) -> Kami Sama Limited | V43: =[1]!s_holder_quantity($D$4,V$38,4)/CurrencyUnit -> 0.27216108
C44: =[1]!s_holder_name($D$4,F$38,5) -> 黄河投资有限公司 | F44: =[1]!s_holder_quantity($D$4,F$38,5)/CurrencyUnit -> 0.10954357 | G44: =[1]!s_holder_pct($D$4,F$38,5)/100 -> 0.025999999 | H44: =IF(ISNA(VLOOKUP(C44,$M$40:$V$50,4,FALSE)),F44,F44-VLOOKUP(C44,$M$40:$V$50,4,FALSE)) -> 0.10954357 | M44: =[1]!s_holder_name($D$4,V$38,5) -> OPH B Limited | V44: =[1]!s_holder_quantity($D$4,V$38,5)/CurrencyUnit -> 0.10954357
C45: =[1]!s_holder_name($D$4,F$38,6) -> Saber Lily Limited | F45: =[1]!s_holder_quantity($D$4,F$38,6)/CurrencyUnit -> 0.081083 | G45: =[1]!s_holder_pct($D$4,F$38,6)/100 -> 0.0192 | H45: =IF(ISNA(VLOOKUP(C45,$M$40:$V$50,4,FALSE)),F45,F45-VLOOKUP(C45,$M$40:$V$50,4,FALSE)) -> 0.081083 | M45: =[1]!s_holder_name($D$4,V$38,6) -> Saber Lily Limited | V45: =[1]!s_holder_quantity($D$4,V$38,6)/CurrencyUnit -> 0.072
C46: =[1]!s_holder_name($D$4,F$38,7) -> 陈睿 | F46: =[1]!s_holder_quantity($D$4,F$38,7)/CurrencyUnit -> 0.05 | G46: =[1]!s_holder_pct($D$4,F$38,7)/100 -> 0.011900001 | H46: =IF(ISNA(VLOOKUP(C46,$M$40:$V$50,4,FALSE)),F46,F46-VLOOKUP(C46,$M$40:$V$50,4,FALSE)) -> 0.05 | M46: =[1]!s_holder_name($D$4,V$38,7) -> 陈睿 | V46: =[1]!s_holder_quantity($D$4,V$38,7)/CurrencyUnit -> 0.05
C47: =[1]!s_holder_name($D$4,F$38,8) -> 李旎 | F47: =[1]!s_holder_quantity($D$4,F$38,8)/CurrencyUnit -> 0.03 | G47: =[1]!s_holder_pct($D$4,F$38,8)/100 -> 0.0070999998 | H47: =IF(ISNA(VLOOKUP(C47,$M$40:$V$50,4,FALSE)),F47,F47-VLOOKUP(C47,$M$40:$V$50,4,FALSE)) -> 0.03 | M47: =[1]!s_holder_name($D$4,V$38,8) -> 李旎 | V47: =[1]!s_holder_quantity($D$4,V$38,8)/CurrencyUnit -> 0.03
C48: =[1]!s_holder_name($D$4,F$38,9) -> 徐逸 | F48: =[1]!s_holder_quantity($D$4,F$38,9)/CurrencyUnit -> 0.00045 | G48: =[1]!s_holder_pct($D$4,F$38,9)/100 -> 9.9999998e-05 | H48: =IF(ISNA(VLOOKUP(C48,$M$40:$V$50,4,FALSE)),F48,F48-VLOOKUP(C48,$M$40:$V$50,4,FALSE)) -> 0.00045 | M48: =[1]!s_holder_name($D$4,V$38,9) -> 徐逸 | V48: =[1]!s_holder_quantity($D$4,V$38,9)/CurrencyUnit -> 0.00045
C49: =[1]!s_holder_name($D$4,F$38,10) -> 0 | F49: =[1]!s_holder_quantity($D$4,F$38,10)/CurrencyUnit -> 0 | G49: =[1]!s_holder_pct($D$4,F$38,10)/100 -> 0 | H49: =IF(ISNA(VLOOKUP(C49,$M$40:$V$50,4,FALSE)),F49,F49-VLOOKUP(C49,$M$40:$V$50,4,FALSE)) -> 0 | M49: =[1]!s_holder_name($D$4,V$38,10) -> 0 | V49: =[1]!s_holder_quantity($D$4,$F38,10)/CurrencyUnit -> 0
C50: 合计 | F50: =SUM(F40:F49) -> 2.4731464 | G50: =SUM(G40:G49) -> 0.587 | H50: =IF(ISNA(VLOOKUP(C50,$M$40:$V$50,4,FALSE)),F50,F50-VLOOKUP(C50,$M$40:$V$50,4,FALSE)) -> 2.4731464 | M50: 合计 | V50: =SUM(V40:V49) -> 1.6635529
C53: 股本结构
C55: 总股本(亿） | D55: =N14 -> 4.2126142
C56: 流通A股 | D56: =[1]!S_SHARE_LIQA(D4,D5)/CurrencyUnit -> 0
C57: 流通B股 | D57: =[1]!s_share_liqb(D4,D5)/CurrencyUnit -> 0
C58: 香港上市股 | D58: =[1]!s_share_h(D4,D5)/CurrencyUnit -> 3.375463
C59: 海外上市股 | D59: =[1]!s_share_oversea(D4,D5)/CurrencyUnit -> 0
C60: 流通股合计 | D60: =[1]!s_share_totaltradable(D4,D5)/CurrencyUnit -> 0
C61: 限售股 | D61: =[1]!s_share_totalrestricted(D4,D5)/CurrencyUnit -> 0
C64: 收入与毛利分析 | H64: 年度
C66: 按行业分类 | D66: =IF($H$64="年度",YEAR(E66)-1&"/12/31",IF(MONTH(E66)=6,YEAR(E66)-1&"/12/31",YEAR(E66)&"/6/30")) -> 2019/12/31 | E66: =IF($H$64="年度",YEAR(F66)-1&"/12/31",IF(MONTH(F66)=6,YEAR(F66)-1&"/12-31",YEAR(F66)&"/6/30")) -> 2020/12/31 | F66: =IF($H$64="年度",YEAR(G66)-1&"/12/31",IF(MONTH(G66)=6,YEAR(G66)-1&"/12/31",YEAR(G66)&"/6/30")) -> 2021/12/31 | G66: =IF($H$64="年度",YEAR(H66)-1&"/12/31",IF(MONTH(H66)=6,YEAR(H66)-1&"/12/31",YEAR(H66)&"/6/30")) -> 2022/12/31 | H66: =IF(H64="年度",YEAR(TODAY())-1&"/12/31",IF(MONTH(TODAY())<9,YEAR(TODAY())-1&"/12/31",YEAR(TODAY())&"/06/30")) -> 2023/12/31
C67: 收入[合并报表] | D67: =[1]!S_STM07_IS($D$4,9,D66,1)/CurrencyUnit -> 67.77922 | E67: =[1]!S_STM07_IS($D$4,9,E66,1)/CurrencyUnit -> 119.98976 | F67: =[1]!S_STM07_IS($D$4,9,F66,1)/CurrencyUnit -> 193.83684 | G67: =[1]!S_STM07_IS($D$4,9,G66,1)/CurrencyUnit -> 218.99167 | H67: =[1]!S_STM07_IS($D$4,9,H66,1)/CurrencyUnit -> 225.27987
C68: =主营构成!C19 -> 收入[按产品分类] | D68: =SUM(D70:D74) -> 44.14825 | E68: =SUM(E70:E74) -> 66.46154 | F68: =SUM(F70:F74) -> 96.14347 | G68: =SUM(G70:G74) -> 188.02672 | H68: =SUM(H70:H74) -> 225.27987
C69: 其他 | D69: =D67-D68 -> 23.63097 | E69: =E67-E68 -> 53.52822 | F69: =F67-F68 -> 97.69337 | G69: =G67-G68 -> 30.96495 | H69: =H67-H68 -> 0
C70: =IF(主营构成!C20=0,"",主营构成!C20) -> 增值服务 | D70: =IF(ISNA(主营构成!J20),"",主营构成!J20) -> 0 | E70: =IF(ISNA(主营构成!K20),"",主营构成!K20) -> 0 | F70: =IF(ISNA(主营构成!L20),"",主营构成!L20) -> 0 | G70: =IF(ISNA(主营构成!M20),"",主营构成!M20) -> 87.1517 | H70: =IF(ISNA(主营构成!N20),"",主营构成!N20) -> 99.1008
C71: =IF(主营构成!C21=0,"",主营构成!C21) -> 广告收入 | D71: =IF(ISNA(主营构成!J21),"",主营构成!J21) -> 8.17016 | E71: =IF(ISNA(主营构成!K21),"",主营构成!K21) -> 18.42772 | F71: =IF(ISNA(主营构成!L21),"",主营构成!L21) -> 45.23421 | G71: =IF(ISNA(主营构成!M21),"",主营构成!M21) -> 50.66212 | H71: =IF(ISNA(主营构成!N21),"",主营构成!N21) -> 64.1204
C72: =IF(主营构成!C22=0,"",主营构成!C22) -> 移动游戏 | D72: =IF(ISNA(主营构成!J22),"",主营构成!J22) -> 35.97809 | E72: =IF(ISNA(主营构成!K22),"",主营构成!K22) -> 48.03382 | F72: =IF(ISNA(主营构成!L22),"",主营构成!L22) -> 50.90926 | G72: =IF(ISNA(主营构成!M22),"",主营构成!M22) -> 50.2129 | H72: =IF(ISNA(主营构成!N22),"",主营构成!N22) -> 40.21137
C73: =IF(主营构成!C23=0,"",主营构成!C23) -> 衍生工具及其他,净值 | D73: =IF(ISNA(主营构成!J23),"",主营构成!J23) -> 0 | E73: =IF(ISNA(主营构成!K23),"",主营构成!K23) -> 0 | F73: =IF(ISNA(主营构成!L23),"",主营构成!L23) -> 0 | G73: =IF(ISNA(主营构成!M23),"",主营构成!M23) -> 0 | H73: =IF(ISNA(主营构成!N23),"",主营构成!N23) -> 21.8473
C74: =IF(主营构成!C24=0,"",主营构成!C24) -> 0 | D74: =IF(ISNA(主营构成!J24),"",主营构成!J24) -> 0 | E74: =IF(ISNA(主营构成!K24),"",主营构成!K24) -> 0 | F74: =IF(ISNA(主营构成!L24),"",主营构成!L24) -> 0 | G74: =IF(ISNA(主营构成!M24),"",主营构成!M24) -> 0 | H74: =IF(ISNA(主营构成!N24),"",主营构成!N24) -> 0
C75: =C66 -> 按行业分类 | D75: =D66 -> 2019/12/31 | E75: =E66 -> 2020/12/31 | F75: =F66 -> 2021/12/31 | G75: =G66 -> 2022/12/31 | H75: =H66 -> 2023/12/31
C76: 毛利润[合并报表] | D76: =D67-[1]!S_STM07_IS($D$4,10,D66,1)/CurrencyUnit -> 11.90249 | E76: =E67-[1]!S_STM07_IS($D$4,10,E66,1)/CurrencyUnit -> 28.40176 | F76: =F67-[1]!S_STM07_IS($D$4,10,F66,1)/CurrencyUnit -> 40.43147 | G76: =G67-[1]!S_STM07_IS($D$4,10,G66,1)/CurrencyUnit -> 38.49295 | H76: =H67-[1]!S_STM07_IS($D$4,10,H66,1)/CurrencyUnit -> 54.41865
C77: =主营构成!C26 -> 利润[按产品分类] | D77: =SUM(D79:D83) -> 0 | E77: =SUM(E79:E83) -> 0 | F77: =SUM(F79:F83) -> 0 | G77: =SUM(G79:G83) -> 0 | H77: =SUM(H79:H83) -> 0
C78: 其他 | D78: =D76-D77 -> 11.90249 | E78: =E76-E77 -> 28.40176 | F78: =F76-F77 -> 40.43147 | G78: =G76-G77 -> 38.49295 | H78: =H76-H77 -> 54.41865
C79: =C70 -> 增值服务 | D79: =IF(ISNA(主营构成!J27),"",主营构成!J27) -> 0 | E79: =IF(ISNA(主营构成!K27),"",主营构成!K27) -> 0 | F79: =IF(ISNA(主营构成!L27),"",主营构成!L27) -> 0 | G79: =IF(ISNA(主营构成!M27),"",主营构成!M27) -> 0 | H79: =IF(ISNA(主营构成!N27),"",主营构成!N27) -> 0
C80: =C71 -> 广告收入 | D80: =IF(ISNA(主营构成!J28),"",主营构成!J28) -> 0 | E80: =IF(ISNA(主营构成!K28),"",主营构成!K28) -> 0 | F80: =IF(ISNA(主营构成!L28),"",主营构成!L28) -> 0 | G80: =IF(ISNA(主营构成!M28),"",主营构成!M28) -> 0 | H80: =IF(ISNA(主营构成!N28),"",主营构成!N28) -> 0
C81: =C72 -> 移动游戏 | D81: =IF(ISNA(主营构成!J29),"",主营构成!J29) -> 0 | E81: =IF(ISNA(主营构成!K29),"",主营构成!K29) -> 0 | F81: =IF(ISNA(主营构成!L29),"",主营构成!L29) -> 0 | G81: =IF(ISNA(主营构成!M29),"",主营构成!M29) -> 0 | H81: =IF(ISNA(主营构成!N29),"",主营构成!N29) -> 0
C82: =C73 -> 衍生工具及其他,净值 | D82: =IF(ISNA(主营构成!J30),"",主营构成!J30) -> 0 | E82: =IF(ISNA(主营构成!K30),"",主营构成!K30) -> 0 | F82: =IF(ISNA(主营构成!L30),"",主营构成!L30) -> 0 | G82: =IF(ISNA(主营构成!M30),"",主营构成!M30) -> 0 | H82: =IF(ISNA(主营构成!N30),"",主营构成!N30) -> 0
C83: =C74 -> 0 | D83: =IF(ISNA(主营构成!J31),"",主营构成!J31) -> 0 | E83: =IF(ISNA(主营构成!K31),"",主营构成!K31) -> 0 | F83: =IF(ISNA(主营构成!L31),"",主营构成!L31) -> 0 | G83: =IF(ISNA(主营构成!M31),"",主营构成!M31) -> 0 | H83: =IF(ISNA(主营构成!N31),"",主营构成!N31) -> 0
C84: =C66 -> 按行业分类 | D84: =D75 -> 2019/12/31 | E84: =E75 -> 2020/12/31 | F84: =F75 -> 2021/12/31 | G84: =G75 -> 2022/12/31 | H84: =H75 -> 2023/12/31
C85: 毛利率[合并报表] | D85: =IF(OR(D67="",D67=0),"",D76/D67) -> 0.17560677 | E85: =IF(OR(E67="",E67=0),"",E76/E67) -> 0.23670153 | F85: =IF(OR(F67="",F67=0),"",F76/F67) -> 0.20858507 | G85: =IF(OR(G67="",G67=0),"",G76/G67) -> 0.17577358 | H85: =IF(OR(H67="",H67=0),"",H76/H67) -> 0.2415602
C86: 毛利率[按产品分类] | D86: =IF(OR(D68="",D68=0),"",D77/D68) -> 0 | E86: =IF(OR(E68="",E68=0),"",E77/E68) -> 0 | F86: =IF(OR(F68="",F68=0),"",F77/F68) -> 0 | G86: =IF(OR(G68="",G68=0),"",G77/G68) -> 0 | H86: =IF(OR(H68="",H68=0),"",H77/H68) -> 0
C87: =C69 -> 其他 | D87: =IF(OR(D69="",D69=0),"",D78/D69) -> 0.50368182 | E87: =IF(OR(E69="",E69=0),"",E78/E69) -> 0.53059414 | F87: =IF(OR(F69="",F69=0),"",F78/F69) -> 0.41386094 | G87: =IF(OR(G69="",G69=0),"",G78/G69) -> 1.2431136 | H87: =IF(OR(H69="",H69=0),"",H78/H69)
C88: =C70 -> 增值服务 | D88: =IF(OR(D70="",D70=0),"",D79/D70) | E88: =IF(OR(E70="",E70=0),"",E79/E70) | F88: =IF(OR(F70="",F70=0),"",F79/F70) | G88: =IF(OR(G70="",G70=0),"",G79/G70) -> 0 | H88: =IF(OR(H70="",H70=0),"",H79/H70) -> 0
C89: =C71 -> 广告收入 | D89: =IF(OR(D71="",D71=0),"",D80/D71) -> 0 | E89: =IF(OR(E71="",E71=0),"",E80/E71) -> 0 | F89: =IF(OR(F71="",F71=0),"",F80/F71) -> 0 | G89: =IF(OR(G71="",G71=0),"",G80/G71) -> 0 | H89: =IF(OR(H71="",H71=0),"",H80/H71) -> 0
C90: =C72 -> 移动游戏 | D90: =IF(OR(D72="",D72=0),"",D81/D72) -> 0 | E90: =IF(OR(E72="",E72=0),"",E81/E72) -> 0 | F90: =IF(OR(F72="",F72=0),"",F81/F72) -> 0 | G90: =IF(OR(G72="",G72=0),"",G81/G72) -> 0 | H90: =IF(OR(H72="",H72=0),"",H81/H72) -> 0
C91: =C73 -> 衍生工具及其他,净值 | D91: =IF(OR(D73="",D73=0),"",D82/D73) | E91: =IF(OR(E73="",E73=0),"",E82/E73) | F91: =IF(OR(F73="",F73=0),"",F82/F73) | G91: =IF(OR(G73="",G73=0),"",G82/G73) | H91: =IF(OR(H73="",H73=0),"",H82/H73) -> 0
D92: =IF(OR(D74="",D74=0),"",D83/D74) | E92: =IF(OR(E74="",E74=0),"",E83/E74) | F92: =IF(OR(F74="",F74=0),"",F83/F74) | G92: =IF(OR(G74="",G74=0),"",G83/G74) | H92: =IF(OR(H74="",H74=0),"",H83/H74) | N92: =YEAR(N96)-1&"-12-31" -> 2018-12-31
C94: 财务数据
M96: ="利润表"&"("&F5&")" -> 利润表(亿) | N96: =YEAR(O96)-1&"/12/31" -> 2019/12/31 | O96: =YEAR(P96)-1&"/12/31" -> 2020/12/31 | P96: =YEAR(Q96)-1&"/12/31" -> 2021/12/31 | Q96: =YEAR(U96)-1&"/12/31" -> 2022/12/31 | U96: =YEAR(V96)-1&"/12/31" -> 2023/12/31 | V96: =YEAR(D5)&"/12/31" -> 2024/12/31
M97: 报表类型 | N97: 合并报表 | O97: 合并报表 | P97: 合并报表 | T97: 合并报表 | U97: 合并报表
M98: 营业收入 | N98: =[1]!S_STM07_IS($D$4,9,N96,rptype3)/CurrencyUnit -> 67.77922 | O98: =[1]!S_STM07_IS($D$4,9,O96,rptype4)/CurrencyUnit -> 119.98976 | P98: =[1]!S_STM07_IS($D$4,9,P96,rptype5)/CurrencyUnit -> 193.83684 | Q98: =[1]!S_STM07_IS($D$4,9,Q96,rptype)/CurrencyUnit -> 218.99167 | U98: =[1]!S_STM07_IS($D$4,9,U96,rptype2)/CurrencyUnit -> 225.27987 | V98: =[1]!s_est_sales($D$4,YEAR(V96),$D$5)/CurrencyUnit -> 255.9868
M99: 营业成本 | N99: =[1]!S_STM07_IS($D$4,10,N96,rptype3)/CurrencyUnit -> 55.87673 | O99: =[1]!S_STM07_IS($D$4,10,O96,rptype4)/CurrencyUnit -> 91.588 | P99: =[1]!S_STM07_IS($D$4,10,P96,rptype5)/CurrencyUnit -> 153.40537 | Q99: =[1]!S_STM07_IS($D$4,10,Q96,rptype)/CurrencyUnit -> 180.49872 | U99: =[1]!S_STM07_IS($D$4,10,U96,rptype2)/CurrencyUnit -> 170.86122
M100: 税金及附加 | N100: =[1]!S_STM07_IS($D$4,11,N96,rptype3)/CurrencyUnit -> 0 | O100: =[1]!S_STM07_IS($D$4,11,O96,rptype4)/CurrencyUnit -> 0 | P100: =[1]!S_STM07_IS($D$4,11,P96,rptype5)/CurrencyUnit -> 0 | Q100: =[1]!S_STM07_IS($D$4,11,Q96,rptype)/CurrencyUnit -> 0 | U100: =[1]!S_STM07_IS($D$4,11,U96,rptype2)/CurrencyUnit -> 0
M101: 销售费用 | N101: =[1]!S_STM07_IS($D$4,12,N96,rptype3)/CurrencyUnit -> 11.98516 | O101: =[1]!S_STM07_IS($D$4,12,O96,rptype4)/CurrencyUnit -> 34.92091 | P101: =[1]!S_STM07_IS($D$4,12,P96,rptype5)/CurrencyUnit -> 57.94853 | Q101: =[1]!S_STM07_IS($D$4,12,Q96,rptype)/CurrencyUnit -> 49.20745 | U101: =[1]!S_STM07_IS($D$4,12,U96,rptype2)/CurrencyUnit -> 39.1615
M102: 管理费用 | N102: =[1]!S_STM07_IS($D$4,13,N96,rptype3)/CurrencyUnit -> 5.92497 | O102: =[1]!S_STM07_IS($D$4,13,O96,rptype4)/CurrencyUnit -> 9.76082 | P102: =[1]!S_STM07_IS($D$4,13,P96,rptype5)/CurrencyUnit -> 18.37506 | Q102: =[1]!S_STM07_IS($D$4,13,Q96,rptype)/CurrencyUnit -> 25.21134 | U102: =[1]!S_STM07_IS($D$4,13,U96,rptype2)/CurrencyUnit -> 21.22432
M103: 财务费用 | N103: =[1]!S_STM07_IS($D$4,14,N96,rptype3)/CurrencyUnit -> 0.46543 | O103: =[1]!S_STM07_IS($D$4,14,O96,rptype4)/CurrencyUnit -> 1.08547 | P103: =[1]!S_STM07_IS($D$4,14,P96,rptype5)/CurrencyUnit -> 1.55467 | Q103: =[1]!S_STM07_IS($D$4,14,Q96,rptype)/CurrencyUnit -> 2.50923 | U103: =[1]!S_STM07_IS($D$4,14,U96,rptype2)/CurrencyUnit -> 1.64927
M104: 资产减值损失 | N104: =[1]!S_STM07_IS($D$4,15,N96,rptype3)/CurrencyUnit -> 0 | O104: =[1]!S_STM07_IS($D$4,15,O96,rptype4)/CurrencyUnit -> 0 | P104: =[1]!S_STM07_IS($D$4,15,P96,rptype5)/CurrencyUnit -> 0 | Q104: =[1]!S_STM07_IS($D$4,15,Q96,rptype)/CurrencyUnit -> 0 | U104: =[1]!S_STM07_IS($D$4,15,U96,rptype2)/CurrencyUnit -> 0
M105: 公允价值变动收益 | N105: =[1]!S_STM07_IS($D$4,16,N96,rptype3)/CurrencyUnit -> 0 | O105: =[1]!S_STM07_IS($D$4,16,O96,rptype4)/CurrencyUnit -> 0 | P105: =[1]!S_STM07_IS($D$4,16,P96,rptype5)/CurrencyUnit -> 0 | Q105: =[1]!S_STM07_IS($D$4,16,Q96,rptype)/CurrencyUnit -> 0 | U105: =[1]!S_STM07_IS($D$4,16,U96,rptype2)/CurrencyUnit -> 0
M106: 投资收益 | N106: =[1]!S_STM07_IS($D$4,17,N96,rptype3)/CurrencyUnit -> 0 | O106: =[1]!S_STM07_IS($D$4,17,O96,rptype4)/CurrencyUnit -> 0 | P106: =[1]!S_STM07_IS($D$4,17,P96,rptype5)/CurrencyUnit -> 0 | Q106: =[1]!S_STM07_IS($D$4,17,Q96,rptype)/CurrencyUnit -> 0 | U106: =[1]!S_STM07_IS($D$4,17,U96,rptype2)/CurrencyUnit -> 0
M107: 营业利润 | N107: =[1]!S_STM07_IS($D$4,48,N96,rptype3)/CurrencyUnit -> 0 | O107: =[1]!S_STM07_IS($D$4,48,O96,rptype4)/CurrencyUnit -> 0 | P107: =[1]!S_STM07_IS($D$4,48,P96,rptype5)/CurrencyUnit -> 0 | Q107: =[1]!S_STM07_IS($D$4,48,Q96,rptype)/CurrencyUnit -> 0 | U107: =[1]!S_STM07_IS($D$4,48,U96,rptype2)/CurrencyUnit -> 0 | V107: =[1]!s_est_avgoperatingprofit($D$4,YEAR(V96),$D$5)/CurrencyUnit -> -19.814211
M108: 营业外收入 | N108: =[1]!S_STM07_IS($D$4,49,N96,rptype3)/CurrencyUnit -> 0 | O108: =[1]!S_STM07_IS($D$4,49,O96,rptype4)/CurrencyUnit -> 0 | P108: =[1]!S_STM07_IS($D$4,49,P96,rptype5)/CurrencyUnit -> 0 | Q108: =[1]!S_STM07_IS($D$4,49,Q96,rptype)/CurrencyUnit -> 0 | U108: =[1]!S_STM07_IS($D$4,49,U96,rptype2)/CurrencyUnit -> 0
M109: 营业外支出 | N109: =[1]!S_STM07_IS($D$4,50,N96,rptype3)/CurrencyUnit -> 0 | O109: =[1]!S_STM07_IS($D$4,50,O96,rptype4)/CurrencyUnit -> 0 | P109: =[1]!S_STM07_IS($D$4,50,P96,rptype5)/CurrencyUnit -> 0 | Q109: =[1]!S_STM07_IS($D$4,50,Q96,rptype)/CurrencyUnit -> 0 | U109: =[1]!S_STM07_IS($D$4,50,U96,rptype2)/CurrencyUnit -> 0
M110: 利润总额 | N110: =[1]!S_STM07_IS($D$4,55,N96,rptype3)/CurrencyUnit -> -12.67703 | O110: =[1]!S_STM07_IS($D$4,55,O96,rptype4)/CurrencyUnit -> -30.00648 | P110: =[1]!S_STM07_IS($D$4,55,P96,rptype5)/CurrencyUnit -> -67.1345 | Q110: =[1]!S_STM07_IS($D$4,55,Q96,rptype)/CurrencyUnit -> -74.03508 | U110: =[1]!S_STM07_IS($D$4,55,U96,rptype2)/CurrencyUnit -> -47.33008 | V110: =[1]!s_est_avgebt($D$4,YEAR(V96),$D$5)/CurrencyUnit -> -18.089091
M111: 净利润 | N111: =[1]!S_STM07_IS($D$4,60,N96,rptype3)/CurrencyUnit -> -13.0357 | O111: =[1]!S_STM07_IS($D$4,60,O96,rptype4)/CurrencyUnit -> -30.54017 | P111: =[1]!S_STM07_IS($D$4,60,P96,rptype5)/CurrencyUnit -> -68.08739 | Q111: =[1]!S_STM07_IS($D$4,60,Q96,rptype)/CurrencyUnit -> -75.07653 | U111: =[1]!S_STM07_IS($D$4,60,U96,rptype2)/CurrencyUnit -> -48.11713
M112: 归属母公司股东 | N112: =[1]!S_STM07_IS($D$4,61,N96,rptype3)/CurrencyUnit -> -12.88973 | O112: =[1]!S_STM07_IS($D$4,61,O96,rptype4)/CurrencyUnit -> -30.11704 | P112: =[1]!S_STM07_IS($D$4,61,P96,rptype5)/CurrencyUnit -> -67.89228 | Q112: =[1]!S_STM07_IS($D$4,61,Q96,rptype)/CurrencyUnit -> -74.97013 | U112: =[1]!S_STM07_IS($D$4,61,U96,rptype2)/CurrencyUnit -> -48.22321 | V112: =[1]!s_est_netprofit($D$4,YEAR(V96),$D$5)/CurrencyUnit -> -18.058642
M114: 财务指标 | N114: =N96 -> 2019/12/31 | O114: =O96 -> 2020/12/31 | P114: =P96 -> 2021/12/31 | Q114: =Q96 -> 2022/12/31 | U114: =U96 -> 2023/12/31 | V114: =V96 -> 2024/12/31
M115: 销售毛利率 | N115: =(N98-N99)/N98 -> 0.17560677 | O115: =(O98-O99)/O98 -> 0.23670153 | P115: =(P98-P99)/P98 -> 0.20858507 | Q115: =(Q98-Q99)/Q98 -> 0.17577358 | U115: =(U98-U99)/U98 -> 0.2415602
M116: 净利润率 | N116: =N112/N98 -> -0.1901723 | O116: =O112/O98 -> -0.25099675 | P116: =P112/P98 -> -0.35025478 | Q116: =Q112/Q98 -> -0.34234238 | U116: =U112/U98 -> -0.21405912
M117: 营收增长率 | N117: =N98/([1]!S_STM07_IS($D$4,9,N92,rptype3)/CurrencyUnit)-1 -> 0.64156824 | O117: =O98/N98-1 -> 0.77030305 | P117: =P98/O98-1 -> 0.61544485 | Q117: =Q98/P98-1 -> 0.12977322 | U117: =U98/Q98-1 -> 0.028714334 | V117: =V98/U98-1 -> 0.1363057
M118: 净利增长率 | N118: =N112/([1]!S_STM07_IS($D$4,61,N92,rptype3)/CurrencyUnit)-1 -> 1.3362811 | O118: =O112/N112-1 -> 1.3365144 | P118: =P112/O112-1 -> 1.2542813 | Q118: =Q112/P112-1 -> 0.10425118 | U118: =U112/Q112-1 -> -0.35676769 | V118: =V112/U112-1 -> -0.62551971

Sheet 行业比较
D1: 股票速览-行业比较
C4: 交易代码 | D4: =公司分析!D4 -> 9626.HK | E4: =[1]!s_info_name(D4) -> 哔哩哔哩-W | F4: 行业排名 | G4: =VLOOKUP(E4,E14:R20003,14,FALSE)&"/"&MAX(series) -> 4/44 | H4: ="("&"按"&R12&")" -> (按总市值)
C5: 单位 | D5: 百万 | E5: =IF(D5="千",1000,IF(D5="百万",1000000,1000000000)) -> 1000000 | F5: 最新年报 | G5: =[1]!s_fa_lyr_bt(D4,公司分析!D5) -> 2023-12-31
C6: 行业属性 | D6: wind四级行业 | E6: =IF($D$6="申万一级行业",[1]!s_info_industry_sw_2021(D4,公司分析!D$5,1),IF($D$6="申万二级行业",[1]!s_info_industry_sw_2021(D4,公司分析!D$5,2),IF($D$6="申万三级行业",[1]!s_info_industry_sw_2021(D4,公司分析!D$5,3),IF($D$6="wind一级行业",[1]!s_info_industry_gics(D4,1),IF($D$6="wind二级行业",[1]!s_info_industry_gics(D4,2),IF($D$6="wind三级行业",[1]!s_info_industry_gics(D4,3),IF($D$6="wind四级行业",[1]!s_info_industry_gics(D4,4),IF($D$6="证监会门类行业",[1]!s_info_industry_csrc12_n(D4,公司分析!D$5,1),IF([1]!s_info_industry_csrc12_n(D4,公司分析!D$5,1)="制造业",[1]!s_info_industry_csrc12_n(D4,公司分析!D$5,2),[1]!s_info_industry_csrc12_n(D4,公司分析!D$5,1)))))))))) -> 互联网软件与服务 | F6: 分析类型 | G6: 财务摘要
C9: 行业比较
C11: 序号 | D11: 证券代码 | E11: 证券简称 | F11: 收盘价 | G11: 涨跌%[N日] | H11: =IF($G$6="财务摘要",参数设置!AC3,IF($G$6="估值分析",参数设置!AC4,参数设置!AC5)) -> 收入 | I11: =IF($G$6="财务摘要",参数设置!AD3,IF($G$6="估值分析",参数设置!AD4,参数设置!AD5)) -> 毛利率 | J11: =IF($G$6="财务摘要",参数设置!AF3,IF($G$6="估值分析",参数设置!AF4,参数设置!AF5)) -> 净利润率 | K11: =IF($G$6="财务摘要",参数设置!AG3,IF(G6="估值分析",参数设置!AG4,参数设置!AG5)) -> ROA | L11: =IF($G$6="财务摘要",参数设置!AH3,IF(G6="估值分析",参数设置!AH4,参数设置!AH5)) -> ROE | M11: =IF($G$6="财务摘要",参数设置!AI3,IF($G$6="估值分析",参数设置!AI4,参数设置!AI5)) -> EPS | N11: =IF($G$6="财务摘要",参数设置!AL3,IF(G6="估值分析",参数设置!AL4,参数设置!AL5)) -> PE | O11: =IF($G$6="财务摘要",参数设置!AN3,IF(G6="估值分析",参数设置!AN4,参数设置!AN5)) -> 总股本 | P11: =IF($G$6="财务摘要",参数设置!AO3,IF(G6="估值分析",参数设置!AO4,参数设置!AO5)) -> 总市值 | R11: 排名
G12: 20 | H12: 合并报表 | R12: 总市值
H13: =IF(H12="合并报表",1,IF(H12="母公司报表",2,IF(H12="合并报表(调整)",3,4))) -> 1
C14: =IF(ROW()-13<=MAX(series),ROW()-13,"") -> 1 | D14: =IF(C14="","",VLOOKUP(C14,comppool,2,FALSE)) -> 0484.HK | E14: =IF(C14="","",VLOOKUP(C14,comppool,3,FALSE)) -> 云游控股 | F14: =IF(C14="","",[1]!s_dq_close(D14,TODAY(),1)) -> 0.79 | G14: =IF(C14="","",[1]!s_pq_pctchange(D14,TODAY()-$G$12,TODAY())/100) -> -0.048192771 | H14: =IF(C14="","",IF($H$11="收入",[1]!S_STM07_IS(D14,9,$G$5,$H$13)/$E$5,[1]!S_STM07_IS(D14,48,$G$5,$H$13)/$E$5)) -> 60.172 | I14: =IF(C14="","",IF($I$11="毛利率",([1]!S_STM07_IS(D14,9,$G$5,$H$13)-[1]!S_STM07_IS(D14,10,$G$5,$H$13))/[1]!S_STM07_IS(D14,9,$G$5,$H$13),[1]!S_STM07_IS(D14,14,$G$5,$H$13)/$E$5)) -> 0.15025261 | J14: =IF(C14="","",IF($J$11="净利润率",[1]!S_STM07_IS(D14,61,$G$5,$H$13)/[1]!S_STM07_IS(D14,9,$G$5,$H$13),[1]!S_STM07_IS(D14,55,$G$5,$H$13)/$E$5)) -> -0.29277737 | K14: =IF(C14="","",[1]!hks_fa_roa2(D14,$G$5)) -> -2.9793 | L14: =IF(C14="","",[1]!hks_fa_roe(D14,$G$5)) -> -2.8565 | M14: =IF(C14="","",IF($M$11="EPS",[1]!S_STM07_IS(D14,61,$G$5,$H$13)/IF([1]!s_share_total(D14,$G$5)=0,[1]!s_share_total(D14,[1]!s_ipo_listeddate(D14)),[1]!s_share_total(D14,$G$5)),([1]!s_stm07_bs(D14,75,$G$5,$H$13)+[1]!s_stm07_bs(D14,88,$G$5,$H$13)+[1]!s_stm07_bs(D14,94,$G$5,$H$13)+[1]!s_stm07_bs(D14,95,$G$5,$H$13))/$E$5)) -> -0.12006808 | N14: =IF(C14="","",F14/([1]!S_STM07_IS(D14,61,$G$5,$H$13)/IF([1]!s_share_total(D14,$G$5)=0,[1]!s_share_total(D14,[1]!s_ipo_listeddate(D14)),[1]!s_share_total(D14,$G$5)))) -> -6.5796004 | O14: =IF(C14="","",[1]!s_share_total(D14,TODAY())/$E$5) -> 146.72509 | P14: =IF(C14="","",F14*O14) -> 115.91282 | Q14: =IF(C14="","",HLOOKUP($R$12,$G$11:$P$20003,ROW()-ROW($G$11)+1,FALSE)) -> 115.91282 | R14: =IF(C14="","",RANK(Q14,Q:Q,0)) -> 37
C15: =IF(ROW()-13<=MAX(series),ROW()-13,"") -> 2 | D15: =IF(C15="","",VLOOKUP(C15,comppool,2,FALSE)) -> 0700.HK | E15: =IF(C15="","",VLOOKUP(C15,comppool,3,FALSE)) -> 腾讯控股 | F15: =IF(C15="","",[1]!s_dq_close(D15,TODAY(),1)) -> 381.4 | G15: =IF(C15="","",[1]!s_pq_pctchange(D15,TODAY()-$G$12,TODAY())/100) -> 0.017066667 | H15: =IF(C15="","",IF($H$11="收入",[1]!S_STM07_IS(D15,9,$G$5,$H$13)/$E$5,[1]!S_STM07_IS(D15,48,$G$5,$H$13)/$E$5)) -> 609015 | I15: =IF(C15="","",IF($I$11="毛利率",([1]!S_STM07_IS(D15,9,$G$5,$H$13)-[1]!S_STM07_IS(D15,10,$G$5,$H$13))/[1]!S_STM07_IS(D15,9,$G$5,$H$13),[1]!S_STM07_IS(D15,14,$G$5,$H$13)/$E$5)) -> 0.48128371 | J15: =IF(C15="","",IF($J$11="净利润率",[1]!S_STM07_IS(D15,61,$G$5,$H$13)/[1]!S_STM07_IS(D15,9,$G$5,$H$13),[1]!S_STM07_IS(D15,55,$G$5,$H$13)/$E$5)) -> 0.18918417 | K15: =IF(C15="","",[1]!hks_fa_roa2(D15,$G$5)) -> 10.1035 | L15: =IF(C15="","",[1]!hks_fa_roe(D15,$G$5)) -> 15.0611 | M15: =IF(C15="","",IF($M$11="EPS",[1]!S_STM07_IS(D15,61,$G$5,$H$13)/IF([1]!s_share_total(D15,$G$5)=0,[1]!s_share_total(D15,[1]!s_ipo_listeddate(D15)),[1]!s_share_total(D15,$G$5)),([1]!s_stm07_bs(D15,75,$G$5,$H$13)+[1]!s_stm07_bs(D15,88,$G$5,$H$13)+[1]!s_stm07_bs(D15,94,$G$5,$H$13)+[1]!s_stm07_bs(D15,95,$G$5,$H$13))/$E$5)) -> 12.149751 | N15: =IF(C15="","",F15/([1]!S_STM07_IS(D15,61,$G$5,$H$13)/IF([1]!s_share_total(D15,$G$5)=0,[1]!s_share_total(D15,[1]!s_ipo_listeddate(D15)),[1]!s_share_total(D15,$G$5)))) -> 31.39159 | O15: =IF(C15="","",[1]!s_share_total(D15,TODAY())/$E$5) -> 9407.4572 | P15: =IF(C15="","",F15*O15) -> 3588004.2 | Q15: =IF(C15="","",HLOOKUP($R$12,$G$11:$P$20003,ROW()-ROW($G$11)+1,FALSE)) -> 3588004.2 | R15: =IF(C15="","",RANK(Q15,Q:Q,0)) -> 1
C16: =IF(ROW()-13<=MAX(series),ROW()-13,"") -> 3 | D16: =IF(C16="","",VLOOKUP(C16,comppool,2,FALSE)) -> 0802.HK | E16: =IF(C16="","",VLOOKUP(C16,comppool,3,FALSE)) -> 中国钱包 | F16: =IF(C16="","",[1]!s_dq_close(D16,TODAY(),1)) -> 0.045 | G16: =IF(C16="","",[1]!s_pq_pctchange(D16,TODAY()-$G$12,TODAY())/100) -> 0 | H16: =IF(C16="","",IF($H$11="收入",[1]!S_STM07_IS(D16,9,$G$5,$H$13)/$E$5,[1]!S_STM07_IS(D16,48,$G$5,$H$13)/$E$5)) -> 70.959 | I16: =IF(C16="","",IF($I$11="毛利率",([1]!S_STM07_IS(D16,9,$G$5,$H$13)-[1]!S_STM07_IS(D16,10,$G$5,$H$13))/[1]!S_STM07_IS(D16,9,$G$5,$H$13),[1]!S_STM07_IS(D16,14,$G$5,$H$13)/$E$5)) -> 0.35516284 | J16: =IF(C16="","",IF($J$11="净利润率",[1]!S_STM07_IS(D16,61,$G$5,$H$13)/[1]!S_STM07_IS(D16,9,$G$5,$H$13),[1]!S_STM07_IS(D16,55,$G$5,$H$13)/$E$5)) -> -0.45262757 | K16: =IF(C16="","",[1]!hks_fa_roa2(D16,$G$5)) -> -7.9941 | L16: =IF(C16="","",[1]!hks_fa_roe(D16,$G$5)) -> -9.2285 | M16: =IF(C16="","",IF($M$11="EPS",[1]!S_STM07_IS(D16,61,$G$5,$H$13)/IF([1]!s_share_total(D16,$G$5)=0,[1]!s_share_total(D16,[1]!s_ipo_listeddate(D16)),[1]!s_share_total(D16,$G$5)),([1]!s_stm07_bs(D16,75,$G$5,$H$13)+[1]!s_stm07_bs(D16,88,$G$5,$H$13)+[1]!s_stm07_bs(D16,94,$G$5,$H$13)+[1]!s_stm07_bs(D16,95,$G$5,$H$13))/$E$5)) -> -0.053215501 | N16: =IF(C16="","",F16/([1]!S_STM07_IS(D16,61,$G$5,$H$13)/IF([1]!s_share_total(D16,$G$5)=0,[1]!s_share_total(D16,[1]!s_ipo_listeddate(D16)),[1]!s_share_total(D16,$G$5)))) -> -0.84561827 | O16: =IF(C16="","",[1]!s_share_total(D16,TODAY())/$E$5) -> 603.54595 | P16: =IF(C16="","",F16*O16) -> 27.159568 | Q16: =IF(C16="","",HLOOKUP($R$12,$G$11:$P$20003,ROW()-ROW($G$11)+1,FALSE)) -> 27.159568 | R16: =IF(C16="","",RANK(Q16,Q:Q,0)) -> 42
C17: =IF(ROW()-13<=MAX(series),ROW()-13,"") -> 4 | D17: =IF(C17="","",VLOOKUP(C17,comppool,2,FALSE)) -> 0856.HK | E17: =IF(C17="","",VLOOKUP(C17,comppool,3,FALSE)) -> 伟仕佳杰 | F17: =IF(C17="","",[1]!s_dq_close(D17,TODAY(),1)) -> 4.47 | G17: =IF(C17="","",[1]!s_pq_pctchange(D17,TODAY()-$G$12,TODAY())/100) -> -0.0096460161 | H17: =IF(C17="","",IF($H$11="收入",[1]!S_STM07_IS(D17,9,$G$5,$H$13)/$E$5,[1]!S_STM07_IS(D17,48,$G$5,$H$13)/$E$5)) -> 73891.296 | I17: =IF(C17="","",IF($I$11="毛利率",([1]!S_STM07_IS(D17,9,$G$5,$H$13)-[1]!S_STM07_IS(D17,10,$G$5,$H$13))/[1]!S_STM07_IS(D17,9,$G$5,$H$13),[1]!S_STM07_IS(D17,14,$G$5,$H$13)/$E$5)) -> 0.047319728 | J17: =IF(C17="","",IF($J$11="净利润率",[1]!S_STM07_IS(D17,61,$G$5,$H$13)/[1]!S_STM07_IS(D17,9,$G$5,$H$13),[1]!S_STM07_IS(D17,55,$G$5,$H$13)/$E$5)) -> 0.012478236 | K17: =IF(C17="","",[1]!hks_fa_roa2(D17,$G$5)) -> 4.2214 | L17: =IF(C17="","",[1]!hks_fa_roe(D17,$G$5)) -> 11.6121 | M17: =IF(C17="","",IF($M$11="EPS",[1]!S_STM07_IS(D17,61,$G$5,$H$13)/IF([1]!s_share_total(D17,$G$5)=0,[1]!s_share_total(D17,[1]!s_ipo_listeddate(D17)),[1]!s_share_total(D17,$G$5)),([1]!s_stm07_bs(D17,75,$G$5,$H$13)+[1]!s_stm07_bs(D17,88,$G$5,$H$13)+[1]!s_stm07_bs(D17,94,$G$5,$H$13)+[1]!s_stm07_bs(D17,95,$G$5,$H$13))/$E$5)) -> 0.64038341 | N17: =IF(C17="","",F17/([1]!S_STM07_IS(D17,61,$G$5,$H$13)/IF([1]!s_share_total(D17,$G$5)=0,[1]!s_share_total(D17,[1]!s_ipo_listeddate(D17)),[1]!s_share_total(D17,$G$5)))) -> 6.9801933 | O17: =IF(C17="","",[1]!s_share_total(D17,TODAY())/$E$5) -> 1436.89 | P17: =IF(C17="","",F17*O17) -> 6422.8983 | Q17: =IF(C17="","",HLOOKUP($R$12,$G$11:$P$20003,ROW()-ROW($G$11)+1,FALSE)) -> 6422.8983 | R17: =IF(C17="","",RANK(Q17,Q:Q,0)) -> 12
C18: =IF(ROW()-13<=MAX(series),ROW()-13,"") -> 5 | D18: =IF(C18="","",VLOOKUP(C18,comppool,2,FALSE)) -> 0909.HK | E18: =IF(C18="","",VLOOKUP(C18,comppool,3,FALSE)) -> 明源云 | F18: =IF(C18="","",[1]!s_dq_close(D18,TODAY(),1)) -> 2.03 | G18: =IF(C18="","",[1]!s_pq_pctchange(D18,TODAY()-$G$12,TODAY())/100) -> -0.14345992 | H18: =IF(C18="","",IF($H$11="收入",[1]!S_STM07_IS(D18,9,$G$5,$H$13)/$E$5,[1]!S_STM07_IS(D18,48,$G$5,$H$13)/$E$5)) -> 1639.644 | I18: =IF(C18="","",IF($I$11="毛利率",([1]!S_STM07_IS(D18,9,$G$5,$H$13)-[1]!S_STM07_IS(D18,10,$G$5,$H$13))/[1]!S_STM07_IS(D18,9,$G$5,$H$13),[1]!S_STM07_IS(D18,14,$G$5,$H$13)/$E$5)) -> 0.79482314 | J18: =IF(C18="","",IF($J$11="净利润率",[1]!S_STM07_IS(D18,61,$G$5,$H$13)/[1]!S_STM07_IS(D18,9,$G$5,$H$13),[1]!S_STM07_IS(D18,55,$G$5,$H$13)/$E$5)) -> -0.35717143 | K18: =IF(C18="","",[1]!hks_fa_roa2(D18,$G$5)) -> -12.71 | L18: =IF(C18="","",[1]!hks_fa_roe(D18,$G$5)) -> -11.6698 | M18: =IF(C18="","",IF($M$11="EPS",[1]!S_STM07_IS(D18,61,$G$5,$H$13)/IF([1]!s_share_total(D18,$G$5)=0,[1]!s_share_total(D18,[1]!s_ipo_listeddate(D18)),[1]!s_share_total(D18,$G$5)),([1]!s_stm07_bs(D18,75,$G$5,$H$13)+[1]!s_stm07_bs(D18,88,$G$5,$H$13)+[1]!s_stm07_bs(D18,94,$G$5,$H$13)+[1]!s_stm07_bs(D18,95,$G$5,$H$13))/$E$5)) -> -0.30151328 | N18: =IF(C18="","",F18/([1]!S_STM07_IS(D18,61,$G$5,$H$13)/IF([1]!s_share_total(D18,$G$5)=0,[1]!s_share_total(D18,[1]!s_ipo_listeddate(D18)),[1]!s_share_total(D18,$G$5)))) -> -6.732705 | O18: =IF(C18="","",[1]!s_share_total(D18,TODAY())/$E$5) -> 1958.784 | P18: =IF(C18="","",F18*O18) -> 3976.3316 | Q18: =IF(C18="","",HLOOKUP($R$12,$G$11:$P$20003,ROW()-ROW($G$11)+1,FALSE)) -> 3976.3316 | R18: =IF(C18="","",RANK(Q18,Q:Q,0)) -> 16
C19: =IF(ROW()-13<=MAX(series),ROW()-13,"") -> 6 | D19: =IF(C19="","",VLOOKUP(C19,comppool,2,FALSE)) -> 0917.HK | E19: =IF(C19="","",VLOOKUP(C19,comppool,3,FALSE)) -> 趣致集团 | F19: =IF(C19="","",[1]!s_dq_close(D19,TODAY(),1)) -> 48.75 | G19: =IF(C19="","",[1]!s_pq_pctchange(D19,TODAY()-$G$12,TODAY())/100) -> 0.2279597 | H19: =IF(C19="","",IF($H$11="收入",[1]!S_STM07_IS(D19,9,$G$5,$H$13)/$E$5,[1]!S_STM07_IS(D19,48,$G$5,$H$13)/$E$5)) -> 1006.697 | I19: =IF(C19="","",IF($I$11="毛利率",([1]!S_STM07_IS(D19,9,$G$5,$H$13)-[1]!S_STM07_IS(D19,10,$G$5,$H$13))/[1]!S_STM07_IS(D19,9,$G$5,$H$13),[1]!S_STM07_IS(D19,14,$G$5,$H$13)/$E$5)) -> 0.53170616 | J19: =IF(C19="","",IF($J$11="净利润率",[1]!S_STM07_IS(D19,61,$G$5,$H$13)/[1]!S_STM07_IS(D19,9,$G$5,$H$13),[1]!S_STM07_IS(D19,55,$G$5,$H$13)/$E$5)) -> 0.13007092 | K19: =IF(C19="","",[1]!hks_fa_roa2(D19,$G$5)) -> 16.7331 | L19: =IF(C19="","",[1]!hks_fa_roe(D19,$G$5)) -> 0 | M19: =IF(C19="","",IF($M$11="EPS",[1]!S_STM07_IS(D19,61,$G$5,$H$13)/IF([1]!s_share_total(D19,$G$5)=0,[1]!s_share_total(D19,[1]!s_ipo_listeddate(D19)),[1]!s_share_total(D19,$G$5)),([1]!s_stm07_bs(D19,75,$G$5,$H$13)+[1]!s_stm07_bs(D19,88,$G$5,$H$13)+[1]!s_stm07_bs(D19,94,$G$5,$H$13)+[1]!s_stm07_bs(D19,95,$G$5,$H$13))/$E$5)) -> #DIV/0! | N19: =IF(C19="","",F19/([1]!S_STM07_IS(D19,61,$G$5,$H$13)/IF([1]!s_share_total(D19,$G$5)=0,[1]!s_share_total(D19,[1]!s_ipo_listeddate(D19)),[1]!s_share_total(D19,$G$5)))) -> #DIV/0! | O19: =IF(C19="","",[1]!s_share_total(D19,TODAY())/$E$5) -> 262.70545 | P19: =IF(C19="","",F19*O19) -> 12806.89 | Q19: =IF(C19="","",HLOOKUP($R$12,$G$11:$P$20003,ROW()-ROW($G$11)+1,FALSE)) -> 12806.89 | R19: =IF(C19="","",RANK(Q19,Q:Q,0)) -> 10
C20: =IF(ROW()-13<=MAX(series),ROW()-13,"") -> 7 | D20: =IF(C20="","",VLOOKUP(C20,comppool,2,FALSE)) -> 1020.HK | E20: =IF(C20="","",VLOOKUP(C20,comppool,3,FALSE)) -> 赛伯乐国际控股 | F20: =IF(C20="","",[1]!s_dq_close(D20,TODAY(),1)) -> 0.074 | G20: =IF(C20="","",[1]!s_pq_pctchange(D20,TODAY()-$G$12,TODAY())/100) -> -0.075 | H20: =IF(C20="","",IF($H$11="收入",[1]!S_STM07_IS(D20,9,$G$5,$H$13)/$E$5,[1]!S_STM07_IS(D20,48,$G$5,$H$13)/$E$5)) -> 111.544 | I20: =IF(C20="","",IF($I$11="毛利率",([1]!S_STM07_IS(D20,9,$G$5,$H$13)-[1]!S_STM07_IS(D20,10,$G$5,$H$13))/[1]!S_STM07_IS(D20,9,$G$5,$H$13),[1]!S_STM07_IS(D20,14,$G$5,$H$13)/$E$5)) -> 0.20334576 | J20: =IF(C20="","",IF($J$11="净利润率",[1]!S_STM07_IS(D20,61,$G$5,$H$13)/[1]!S_STM07_IS(D20,9,$G$5,$H$13),[1]!S_STM07_IS(D20,55,$G$5,$H$13)/$E$5)) -> -0.15747149 | K20: =IF(C20="","",[1]!hks_fa_roa2(D20,$G$5)) -> 3.9826 | L20: =IF(C20="","",[1]!hks_fa_roe(D20,$G$5)) -> -12.7225 | M20: =IF(C20="","",IF($M$11="EPS",[1]!S_STM07_IS(D20,61,$G$5,$H$13)/IF([1]!s_share_total(D20,$G$5)=0,[1]!s_share_total(D20,[1]!s_ipo_listeddate(D20)),[1]!s_share_total(D20,$G$5)),([1]!s_stm07_bs(D20,75,$G$5,$H$13)+[1]!s_stm07_bs(D20,88,$G$5,$H$13)+[1]!s_stm07_bs(D20,94,$G$5,$H$13)+[1]!s_stm07_bs(D20,95,$G$5,$H$13))/$E$5)) -> -0.0044183699 | N20: =IF(C20="","",F20/([1]!S_STM07_IS(D20,61,$G$5,$H$13)/IF([1]!s_share_total(D20,$G$5)=0,[1]!s_share_total(D20,[1]!s_ipo_listeddate(D20)),[1]!s_share_total(D20,$G$5)))) -> -16.748258 | O20: =IF(C20="","",[1]!s_share_total(D20,TODAY())/$E$5) -> 3975.448 | P20: =IF(C20="","",F20*O20) -> 294.18315 | Q20: =IF(C20="","",HLOOKUP($R$12,$G$11:$P$20003,ROW()-ROW($G$11)+1,FALSE)) -> 294.18315 | R20: =IF(C20="","",RANK(Q20,Q:Q,0)) -> 29
C21: =IF(ROW()-13<=MAX(series),ROW()-13,"") -> 8 | D21: =IF(C21="","",VLOOKUP(C21,comppool,2,FALSE)) -> 1039.HK | E21: =IF(C21="","",VLOOKUP(C21,comppool,3,FALSE)) -> 畅由联盟 | F21: =IF(C21="","",[1]!s_dq_close(D21,TODAY(),1)) -> 0.135 | G21: =IF(C21="","",[1]!s_pq_pctchange(D21,TODAY()-$G$12,TODAY())/100) -> -0.035714286 | H21: =IF(C21="","",IF($H$11="收入",[1]!S_STM07_IS(D21,9,$G$5,$H$13)/$E$5,[1]!S_STM07_IS(D21,48,$G$5,$H$13)/$E$5)) -> 226.751 | I21: =IF(C21="","",IF($I$11="毛利率",([1]!S_STM07_IS(D21,9,$G$5,$H$13)-[1]!S_STM07_IS(D21,10,$G$5,$H$13))/[1]!S_STM07_IS(D21,9,$G$5,$H$13),[1]!S_STM07_IS(D21,14,$G$5,$H$13)/$E$5)) -> 0.17320321 | J21: =IF(C21="","",IF($J$11="净利润率",[1]!S_STM07_IS(D21,61,$G$5,$H$13)/[1]!S_STM07_IS(D21,9,$G$5,$H$13),[1]!S_STM07_IS(D21,55,$G$5,$H$13)/$E$5)) -> -0.16565307 | K21: =IF(C21="","",[1]!hks_fa_roa2(D21,$G$5)) -> -5.2765 | L21: =IF(C21="","",[1]!hks_fa_roe(D21,$G$5)) -> -14.8396 | M21: =IF(C21="","",IF($M$11="EPS",[1]!S_STM07_IS(D21,61,$G$5,$H$13)/IF([1]!s_share_total(D21,$G$5)=0,[1]!s_share_total(D21,[1]!s_ipo_listeddate(D21)),[1]!s_share_total(D21,$G$5)),([1]!s_stm07_bs(D21,75,$G$5,$H$13)+[1]!s_stm07_bs(D21,88,$G$5,$H$13)+[1]!s_stm07_bs(D21,94,$G$5,$H$13)+[1]!s_stm07_bs(D21,95,$G$5,$H$13))/$E$5)) -> -0.020741562 | N21: =IF(C21="","",F21/([1]!S_STM07_IS(D21,61,$G$5,$H$13)/IF([1]!s_share_total(D21,$G$5)=0,[1]!s_share_total(D21,[1]!s_ipo_listeddate(D21)),[1]!s_share_total(D21,$G$5)))) -> -6.5086708 | O21: =IF(C21="","",[1]!s_share_total(D21,TODAY())/$E$5) -> 1810.9533 | P21: =IF(C21="","",F21*O21) -> 244.47869 | Q21: =IF(C21="","",HLOOKUP($R$12,$G$11:$P$20003,ROW()-ROW($G$11)+1,FALSE)) -> 244.47869 | R21: =IF(C21="","",RANK(Q21,Q:Q,0)) -> 32
C22: =IF(ROW()-13<=MAX(series),ROW()-13,"") -> 9 | D22: =IF(C22="","",VLOOKUP(C22,comppool,2,FALSE)) -> 1075.HK | E22: =IF(C22="","",VLOOKUP(C22,comppool,3,FALSE)) -> 首都信息 | F22: =IF(C22="","",[1]!s_dq_close(D22,TODAY(),1)) -> 0.249 | G22: =IF(C22="","",[1]!s_pq_pctchange(D22,TODAY()-$G$12,TODAY())/100) -> 0.016326531 | H22: =IF(C22="","",IF($H$11="收入",[1]!S_STM07_IS(D22,9,$G$5,$H$13)/$E$5,[1]!S_STM07_IS(D22,48,$G$5,$H$13)/$E$5)) -> 1425.5818 | I22: =IF(C22="","",IF($I$11="毛利率",([1]!S_STM07_IS(D22,9,$G$5,$H$13)-[1]!S_STM07_IS(D22,10,$G$5,$H$13))/[1]!S_STM07_IS(D22,9,$G$5,$H$13),[1]!S_STM07_IS(D22,14,$G$5,$H$13)/$E$5)) -> 0.27991651 | J22: =IF(C22="","",IF($J$11="净利润率",[1]!S_STM07_IS(D22,61,$G$5,$H$13)/[1]!S_STM07_IS(D22,9,$G$5,$H$13),[1]!S_STM07_IS(D22,55,$G$5,$H$13)/$E$5)) -> -0.05114153 | K22: =IF(C22="","",[1]!hks_fa_roa2(D22,$G$5)) -> -3.9576 | L22: =IF(C22="","",[1]!hks_fa_roe(D22,$G$5)) -> -6.0566 | M22: =IF(C22="","",IF($M$11="EPS",[1]!S_STM07_IS(D22,61,$G$5,$H$13)/IF([1]!s_share_total(D22,$G$5)=0,[1]!s_share_total(D22,[1]!s_ipo_listeddate(D22)),[1]!s_share_total(D22,$G$5)),([1]!s_stm07_bs(D22,75,$G$5,$H$13)+[1]!s_stm07_bs(D22,88,$G$5,$H$13)+[1]!s_stm07_bs(D22,94,$G$5,$H$13)+[1]!s_stm07_bs(D22,95,$G$5,$H$13))/$E$5)) -> -0.025156752 | N22: =IF(C22="","",F22/([1]!S_STM07_IS(D22,61,$G$5,$H$13)/IF([1]!s_share_total(D22,$G$5)=0,[1]!s_share_total(D22,[1]!s_ipo_listeddate(D22)),[1]!s_share_total(D22,$G$5)))) -> -9.8979391 | O22: =IF(C22="","",[1]!s_share_total(D22,TODAY())/$E$5) -> 2898.0861 | P22: =IF(C22="","",F22*O22) -> 721.62344 | Q22: =IF(C22="","",HLOOKUP($R$12,$G$11:$P$20003,ROW()-ROW($G$11)+1,FALSE)) -> 721.62344 | R22: =IF(C22="","",RANK(Q22,Q:Q,0)) -> 25
C23: =IF(ROW()-13<=MAX(series),ROW()-13,"") -> 10 | D23: =IF(C23="","",VLOOKUP(C23,comppool,2,FALSE)) -> 1274.HK | E23: =IF(C23="","",VLOOKUP(C23,comppool,3,FALSE)) -> 知行汽车科技 | F23: =IF(C23="","",[1]!s_dq_close(D23,TODAY(),1)) -> 69.95 | G23: =IF(C23="","",[1]!s_pq_pctchange(D23,TODAY()-$G$12,TODAY())/100) -> 0.10943695 | H23: =IF(C23="","",IF($H$11="收入",[1]!S_STM07_IS(D23,9,$G$5,$H$13)/$E$5,[1]!S_STM07_IS(D23,48,$G$5,$H$13)/$E$5)) -> 1216.287 | I23: =IF(C23="","",IF($I$11="毛利率",([1]!S_STM07_IS(D23,9,$G$5,$H$13)-[1]!S_STM07_IS(D23,10,$G$5,$H$13))/[1]!S_STM07_IS(D23,9,$G$5,$H$13),[1]!S_STM07_IS(D23,14,$G$5,$H$13)/$E$5)) -> 0.099444457 | J23: =IF(C23="","",IF($J$11="净利润率",[1]!S_STM07_IS(D23,61,$G$5,$H$13)/[1]!S_STM07_IS(D23,9,$G$5,$H$13),[1]!S_STM07_IS(D23,55,$G$5,$H$13)/$E$5)) -> -0.1604128 | K23: =IF(C23="","",[1]!hks_fa_roa2(D23,$G$5)) -> -13.4661 | L23: =IF(C23="","",[1]!hks_fa_roe(D23,$G$5)) -> -21.7976 | M23: =IF(C23="","",IF($M$11="EPS",[1]!S_STM07_IS(D23,61,$G$5,$H$13)/IF([1]!s_share_total(D23,$G$5)=0,[1]!s_share_total(D23,[1]!s_ipo_listeddate(D23)),[1]!s_share_total(D23,$G$5)),([1]!s_stm07_bs(D23,75,$G$5,$H$13)+[1]!s_stm07_bs(D23,88,$G$5,$H$13)+[1]!s_stm07_bs(D23,94,$G$5,$H$13)+[1]!s_stm07_bs(D23,95,$G$5,$H$13))/$E$5)) -> -0.86204969 | N23: =IF(C23="","",F23/([1]!S_STM07_IS(D23,61,$G$5,$H$13)/IF([1]!s_share_total(D23,$G$5)=0,[1]!s_share_total(D23,[1]!s_ipo_listeddate(D23)),[1]!s_share_total(D23,$G$5)))) -> -81.143814 | O23: =IF(C23="","",[1]!s_share_total(D23,TODAY())/$E$5) -> 226.33034 | P23: =IF(C23="","",F23*O23) -> 15831.807 | Q23: =IF(C23="","",HLOOKUP($R$12,$G$11:$P$20003,ROW()-ROW($G$11)+1,FALSE)) -> 15831.807 | R23: =IF(C23="","",RANK(Q23,Q:Q,0)) -> 7
C24: =IF(ROW()-13<=MAX(series),ROW()-13,"") -> 11 | D24: =IF(C24="","",VLOOKUP(C24,comppool,2,FALSE)) -> 1686.HK | E24: =IF(C24="","",VLOOKUP(C24,comppool,3,FALSE)) -> 新意网集团 | F24: =IF(C24="","",[1]!s_dq_close(D24,TODAY(),1)) -> 2.58 | G24: =IF(C24="","",[1]!s_pq_pctchange(D24,TODAY()-$G$12,TODAY())/100) -> -0.054945055 | H24: =IF(C24="","",IF($H$11="收入",[1]!S_STM07_IS(D24,9,$G$5,$H$13)/$E$5,[1]!S_STM07_IS(D24,48,$G$5,$H$13)/$E$5)) -> 2345.903 | I24: =IF(C24="","",IF($I$11="毛利率",([1]!S_STM07_IS(D24,9,$G$5,$H$13)-[1]!S_STM07_IS(D24,10,$G$5,$H$13))/[1]!S_STM07_IS(D24,9,$G$5,$H$13),[1]!S_STM07_IS(D24,14,$G$5,$H$13)/$E$5)) -> 0.56302413 | J24: =IF(C24="","",IF($J$11="净利润率",[1]!S_STM07_IS(D24,61,$G$5,$H$13)/[1]!S_STM07_IS(D24,9,$G$5,$H$13),[1]!S_STM07_IS(D24,55,$G$5,$H$13)/$E$5)) -> 0.38593454 | K24: =IF(C24="","",[1]!hks_fa_roa2(D24,$G$5)) -> 6.0985 | L24: =IF(C24="","",[1]!hks_fa_roe(D24,$G$5)) -> 19.6167 | M24: =IF(C24="","",IF($M$11="EPS",[1]!S_STM07_IS(D24,61,$G$5,$H$13)/IF([1]!s_share_total(D24,$G$5)=0,[1]!s_share_total(D24,[1]!s_ipo_listeddate(D24)),[1]!s_share_total(D24,$G$5)),([1]!s_stm07_bs(D24,75,$G$5,$H$13)+[1]!s_stm07_bs(D24,88,$G$5,$H$13)+[1]!s_stm07_bs(D24,94,$G$5,$H$13)+[1]!s_stm07_bs(D24,95,$G$5,$H$13))/$E$5)) -> 0.38706405 | N24: =IF(C24="","",F24/([1]!S_STM07_IS(D24,61,$G$5,$H$13)/IF([1]!s_share_total(D24,$G$5)=0,[1]!s_share_total(D24,[1]!s_ipo_listeddate(D24)),[1]!s_share_total(D24,$G$5)))) -> 6.6655635 | O24: =IF(C24="","",[1]!s_share_total(D24,TODAY())/$E$5) -> 2339.0573 | P24: =IF(C24="","",F24*O24) -> 6034.7679 | Q24: =IF(C24="","",HLOOKUP($R$12,$G$11:$P$20003,ROW()-ROW($G$11)+1,FALSE)) -> 6034.7679 | R24: =IF(C24="","",RANK(Q24,Q:Q,0)) -> 13
C25: =IF(ROW()-13<=MAX(series),ROW()-13,"") -> 12 | D25: =IF(C25="","",VLOOKUP(C25,comppool,2,FALSE)) -> 1736.HK | E25: =IF(C25="","",VLOOKUP(C25,comppool,3,FALSE)) -> 中国育儿网络 | F25: =IF(C25="","",[1]!s_dq_close(D25,TODAY(),1)) -> 0.072 | G25: =IF(C25="","",[1]!s_pq_pctchange(D25,TODAY()-$G$12,TODAY())/100) -> 0.10769231 | H25: =IF(C25="","",IF($H$11="收入",[1]!S_STM07_IS(D25,9,$G$5,$H$13)/$E$5,[1]!S_STM07_IS(D25,48,$G$5,$H$13)/$E$5)) -> 57.444 | I25: =IF(C25="","",IF($I$11="毛利率",([1]!S_STM07_IS(D25,9,$G$5,$H$13)-[1]!S_STM07_IS(D25,10,$G$5,$H$13))/[1]!S_STM07_IS(D25,9,$G$5,$H$13),[1]!S_STM07_IS(D25,14,$G$5,$H$13)/$E$5)) -> 0.043538054 | J25: =IF(C25="","",IF($J$11="净利润率",[1]!S_STM07_IS(D25,61,$G$5,$H$13)/[1]!S_STM07_IS(D25,9,$G$5,$H$13),[1]!S_STM07_IS(D25,55,$G$5,$H$13)/$E$5)) -> -0.8387473 | K25: =IF(C25="","",[1]!hks_fa_roa2(D25,$G$5)) -> -31.901 | L25: =IF(C25="","",[1]!hks_fa_roe(D25,$G$5)) -> -70.1667 | M25: =IF(C25="","",IF($M$11="EPS",[1]!S_STM07_IS(D25,61,$G$5,$H$13)/IF([1]!s_share_total(D25,$G$5)=0,[1]!s_share_total(D25,[1]!s_ipo_listeddate(D25)),[1]!s_share_total(D25,$G$5)),([1]!s_stm07_bs(D25,75,$G$5,$H$13)+[1]!s_stm07_bs(D25,88,$G$5,$H$13)+[1]!s_stm07_bs(D25,94,$G$5,$H$13)+[1]!s_stm07_bs(D25,95,$G$5,$H$13))/$E$5)) -> -0.16726497 | N25: =IF(C25="","",F25/([1]!S_STM07_IS(D25,61,$G$5,$H$13)/IF([1]!s_share_total(D25,$G$5)=0,[1]!s_share_total(D25,[1]!s_ipo_listeddate(D25)),[1]!s_share_total(D25,$G$5)))) -> -0.43045476 | O25: =IF(C25="","",[1]!s_share_total(D25,TODAY())/$E$5) -> 345.66234 | P25: =IF(C25="","",F25*O25) -> 24.887689 | Q25: =IF(C25="","",HLOOKUP($R$12,$G$11:$P$20003,ROW()-ROW($G$11)+1,FALSE)) -> 24.887689 | R25: =IF(C25="","",RANK(Q25,Q:Q,0)) -> 43
... C1500: =IF(ROW()-13<=MAX(series),ROW()-13,"") | D1500: =IF(C1500="","",VLOOKUP(C1500,comppool,2,FALSE)) | E1500: =IF(C1500="","",VLOOKUP(C1500,comppool,3,FALSE)) | F1500: =IF(C1500="","",[1]!s_dq_close(D1500,TODAY(),1)) | G1500: =IF(C1500="","",[1]!s_pq_pctchange(D1500,TODAY()-$G$12,TODAY())/100) | H1500: =IF(C1500="","",IF($H$11="收入",[1]!S_STM07_IS(D1500,9,$G$5,$H$13)/$E$5,[1]!S_STM07_IS(D1500,48,$G$5,$H$13)/$E$5)) | I1500: =IF(C1500="","",IF($I$11="毛利率",([1]!S_STM07_IS(D1500,9,$G$5,$H$13)-[1]!S_STM07_IS(D1500,10,$G$5,$H$13))/[1]!S_STM07_IS(D1500,9,$G$5,$H$13),[1]!S_STM07_IS(D1500,14,$G$5,$H$13)/$E$5)) | J1500: =IF(C1500="","",IF($J$11="净利润率",[1]!S_STM07_IS(D1500,61,$G$5,$H$13)/[1]!S_STM07_IS(D1500,9,$G$5,$H$13),[1]!S_STM07_IS(D1500,55,$G$5,$H$13)/$E$5)) | K1500: =IF(C1500="","",[1]!hks_fa_roa2(D1500,$G$5)) | L1500: =IF(C1500="","",[1]!hks_fa_roe(D1500,$G$5)) | M1500: =IF(C1500="","",IF($M$11="EPS",[1]!S_STM07_IS(D1500,61,$G$5,$H$13)/IF([1]!s_share_total(D1500,$G$5)=0,[1]!s_share_total(D1500,[1]!s_ipo_listeddate(D1500)),[1]!s_share_total(D1500,$G$5)),([1]!s_stm07_bs(D1500,75,$G$5,$H$13)+[1]!s_stm07_bs(D1500,88,$G$5,$H$13)+[1]!s_stm07_bs(D1500,94,$G$5,$H$13)+[1]!s_stm07_bs(D1500,95,$G$5,$H$13))/$E$5)) | N1500: =IF(C1500="","",F1500/([1]!S_STM07_IS(D1500,61,$G$5,$H$13)/IF([1]!s_share_total(D1500,$G$5)=0,[1]!s_share_total(D1500,[1]!s_ipo_listeddate(D1500)),[1]!s_share_total(D1500,$G$5)))) | O1500: =IF(C1500="","",[1]!s_share_total(D1500,TODAY())/$E$5) | P1500: =IF(C1500="","",F1500*O1500) | Q1500: =IF(C1500="","",HLOOKUP($R$12,$G$11:$P$20003,ROW()-ROW($G$11)+1,FALSE)) | R1500: =IF(C1500="","",RANK(Q1500,Q:Q,0))
C1501: =IF(ROW()-13<=MAX(series),ROW()-13,"")
C1502: =IF(ROW()-13<=MAX(series),ROW()-13,"")
C1503: =IF(ROW()-13<=MAX(series),ROW()-13,"")
C1504: =IF(ROW()-13<=MAX(series),ROW()-13,"")
C1505: =IF(ROW()-13<=MAX(series),ROW()-13,"")
C1506: =IF(ROW()-13<=MAX(series),ROW()-13,"")
C1507: =IF(ROW()-13<=MAX(series),ROW()-13,"")
C1508: =IF(ROW()-13<=MAX(series),ROW()-13,"")
C1509: =IF(ROW()-13<=MAX(series),ROW()-13,"")
C1510: =IF(ROW()-13<=MAX(series),ROW()-13,"")
C1511: =IF(ROW()-13<=MAX(series),ROW()-13,"")
C1512: =IF(ROW()-13<=MAX(series),ROW()-13,"")
... C2172: =IF(ROW()-13<=MAX(series),ROW()-13,"")

Sheet 盈利预测
E1: 股票速览-盈利预测
D2: 预测与评级明细
D4: 机构汇总 | E4: 国泰君安 | F4: =VLOOKUP(E4,参数设置!C16:D108,2,FALSE) -> 2
D6: 公司代码 | E6: =公司分析!D4 -> 9626.HK | H6: 最高/最低/均值 | J6: 评级明细 | K6: =IF(D4="自选机构","评级次数","评级家数") -> 评级家数
D7: 证券简称 | E7: =[1]!s_info_name(E6) -> 哔哩哔哩-W | G7: 预测主营收入 | H7: =DMAX(D14:Q99,H14,R14:S15)&"/"&DMIN(D14:Q99,H14,R14:S15)&"/"&TRUNC(DAVERAGE(D14:Q99,H14,R14:S15),0) -> 26107/25059/25515 | J7: 买入 | K7: =COUNTIFS($O$15:$O$99,J7,$AB$15:$AB$99,1) -> 7 | O7: 评级变动 | P7: =IF(D4="自选机构","次数","家数") -> 家数
D8: 预测年份 | E8: =YEAR(E9) -> 2024 | G8: 预测净利润 | H8: =DMAX(D14:Q99,I14,T14:U15)&"/"&DMIN(D14:Q99,I14,T14:U15)&"/"&TRUNC(DAVERAGE(D14:Q99,I14,T14:U15),0) -> -1403.9946/-2463/-1878 | J8: 增持 | K8: =COUNTIFS($O$15:$O$99,J8,$AB$15:$AB$99,1) -> 2 | O8: 首次评级 | P8: =COUNTIFS($AA$15:$AA$99,O8,$AB$15:$AB$99,1) -> 1
D9: 交易日期 | E9: =公司分析!D5 -> 45466 | G9: 预测每股收益 | H9: =TRUNC(DMAX(D14:Q99,J14,V14:W15),3)&"/"&TRUNC(DMIN(D14:Q99,J14,V14:W15),3)&"/"&TRUNC(DAVERAGE(D14:Q99,J14,V14:W15),3) -> -3.332/-5.846/-4.459 | J9: 中性 | K9: =COUNTIFS($O$15:$O$99,J9,$AB$15:$AB$99,1) -> 0 | O9: 评级上调 | P9: =COUNTIFS($AA$15:$AA$99,O9,$AB$15:$AB$99,1) -> 2
D10: 单位 | E10: 1000000 | F10: =IF(E11="自定义",F11,IF(E11="一个月",E9-30,IF(E11="三个月",E9-90,IF(E11="半年",E9-180,E9-365)))) -> 45376 | G10: =IF(D4="自选机构","预测次数","预测机构家数") -> 预测机构家数 | H10: =DCOUNT(D14:Q99,H14,R14:S15)&"/"&DCOUNT(D14:Q99,I14,T14:U15)&"/"&DCOUNT(D14:Q99,J14,V14:W15) -> 11/11/11 | J10: 减持 | K10: =COUNTIFS($O$15:$O$99,J10,$AB$15:$AB$99,1) -> 0 | O10: 评级不变 | P10: =COUNTIFS($AA$15:$AA$99,O10,$AB$15:$AB$99,1) -> 7
D11: 统计区间 | E11: 三个月 | G11: 最新报告 | H11: =MAX(X15:X99) -> 45463 | J11: 卖出 | K11: =COUNTIFS($O$15:$O$99,J11,$AB$15:$AB$99,1) -> 0 | O11: 评级下调 | P11: =COUNTIFS($AA$15:$AA$99,O11,$AB$15:$AB$99,1) -> 0
C14: 预测时间设置 | D14: 序号 | E14: 机构 | F14: 研究员 | G14: 机构最近预测时间 | H14: 机构预测主营业务收入 | I14: 机构预测净利润 | J14: 机构预测每股收益 | K14: 机构最近评级时间 | L14: 评级研究员 | M14: 机构投资评级(原始) | N14: 标准化得分 | O14: 标准化评级 | P14: 机构首次评级时间 | Q14: =E11&"内预测" -> 三个月内预测 | R14: =Q14 -> 三个月内预测 | S14: 机构预测主营业务收入 | T14: =Q14 -> 三个月内预测 | U14: 机构预测净利润 | V14: =Q14 -> 三个月内预测 | W14: 机构预测每股收益 | X14: 预测时间 | Y14: 评级时间设置 | Z14: 机构上次评级(标准化得分) | AA14: 评级变化 | AB14: =E11&"内评级" -> 三个月内评级 | AC14: 评级变动
C15: =E9 -> 45466 | D15: 1 | E15: =IF($D$4="自选机构",$E$4,VLOOKUP(D15,Institutionlist,2,FALSE)) -> 申银万国 | F15: =IF($D$4="自选机构",[1]!S_EST_ESTANALYST($E$6,$E$8,C15,$F$4),[1]!S_EST_ESTANALYST($E$6,$E$8,$E$9,D15)) -> 0 | G15: =IF($D$4="自选机构",[1]!S_EST_ESTNEWTIME_INST($E$6,$E$8,C15,$F$4),[1]!S_EST_ESTNEWTIME_INST($E$6,$E$8,$E$9,D15)) -> 0 | H15: =IF($D$4="自选机构",[1]!S_EST_SALES_INST($E$6,$E$8,C15,$F$4)/currencyunit,[1]!S_EST_SALES_INST($E$6,$E$8,$E$9,D15)/currencyunit) -> 0 | I15: =IF($D$4="自选机构",[1]!S_EST_NETPROFIT_INST($E$6,$E$8,C15,$F$4)/currencyunit,[1]!S_EST_NETPROFIT_INST($E$6,$E$8,$E$9,D15)/currencyunit) -> 0 | J15: =IF($D$4="自选机构",[1]!S_EST_EPS_INST($E$6,$E$8,C15,$F$4),[1]!S_EST_EPS_INST($E$6,$E$8,$E$9,D15)) -> 0 | K15: =IF($D$4="自选机构",[1]!S_EST_NEWRATINGTIME_INST($E$6,Y15,$F$4),[1]!S_EST_NEWRATINGTIME_INST($E$6,$E$9,D15)) -> 0 | L15: =IF($D$4="自选机构",[1]!S_EST_RATINGANALYST($E$6,Y15,$F$4),[1]!S_EST_RATINGANALYST($E$6,$E$9,D15)) -> 0 | M15: =IF($D$4="自选机构",[1]!S_EST_ORGRATING_INST($E$6,Y15,$F$4),[1]!S_EST_ORGRATING_INST($E$6,$E$9,D15)) -> 0 | N15: =IF($D$4="自选机构",[1]!S_EST_SCORERATING_INST($E$6,Y15,$F$4),[1]!S_EST_SCORERATING_INST($E$6,$E$9,D15)) -> 0 | O15: =IF($D$4="自选机构",[1]!S_EST_STDRATING_INST($E$6,Y15,$F$4),[1]!S_EST_STDRATING_INST($E$6,$E$9,D15)) -> 0 | P15: =IF($D$4="自选机构",[1]!S_EST_FRSTRATINGTIME_INST($E$6,$F$4),[1]!S_EST_FRSTRATINGTIME_INST($E$6,D15)) -> 0 | Q15: =IF(G15-$F$10>=0,1,"") | R15: 1 | S15: <>0 | T15: 1 | U15: <>0 | V15: 1 | W15: <>0 | X15: =--G15 -> 0 | Y15: =E9 -> 45466 | Z15: =IF($D$4="自选机构",[1]!S_EST_SCORERATING_INST($E$6,K15-1,$F$4),[1]!S_EST_SCORERATING_INST($E$6,K15-1,D15)) -> 0 | AA15: =IFERROR(IF(Z15/N15>1,"评级上调",IF(Z15/N15=1,"评级不变",IF(Z15/N15>0,"评级下调","首次评级"))),0) -> 0 | AB15: =IF(K15-$F$10>=0,1,"") | AC15: =IF(ISERROR(AA15),"",IF(AA15="评级不变",0,IF(AA15="评级下调",-1,IF(AA15="评级上调",1,""))))
C16: =G15-1 -> -1 | D16: 2 | E16: =IF($D$4="自选机构",$E$4,VLOOKUP(D16,Institutionlist,2,FALSE)) -> 国泰君安 | F16: =IF($D$4="自选机构",[1]!S_EST_ESTANALYST($E$6,$E$8,C16,$F$4),[1]!S_EST_ESTANALYST($E$6,$E$8,$E$9,D16)) -> 秦和平 | G16: =IF($D$4="自选机构",[1]!S_EST_ESTNEWTIME_INST($E$6,$E$8,C16,$F$4),[1]!S_EST_ESTNEWTIME_INST($E$6,$E$8,$E$9,D16)) -> 2024-03-09 | H16: =IF($D$4="自选机构",[1]!S_EST_SALES_INST($E$6,$E$8,C16,$F$4)/currencyunit,[1]!S_EST_SALES_INST($E$6,$E$8,$E$9,D16)/currencyunit) -> 25440 | I16: =IF($D$4="自选机构",[1]!S_EST_NETPROFIT_INST($E$6,$E$8,C16,$F$4)/currencyunit,[1]!S_EST_NETPROFIT_INST($E$6,$E$8,$E$9,D16)/currencyunit) -> -1851 | J16: =IF($D$4="自选机构",[1]!S_EST_EPS_INST($E$6,$E$8,C16,$F$4),[1]!S_EST_EPS_INST($E$6,$E$8,$E$9,D16)) -> -4.3939 | K16: =IF($D$4="自选机构",[1]!S_EST_NEWRATINGTIME_INST($E$6,Y16,$F$4),[1]!S_EST_NEWRATINGTIME_INST($E$6,$E$9,D16)) -> 2024-03-09 | L16: =IF($D$4="自选机构",[1]!S_EST_RATINGANALYST($E$6,Y16,$F$4),[1]!S_EST_RATINGANALYST($E$6,$E$9,D16)) -> 秦和平 | M16: =IF($D$4="自选机构",[1]!S_EST_ORGRATING_INST($E$6,Y16,$F$4),[1]!S_EST_ORGRATING_INST($E$6,$E$9,D16)) -> 国泰君安_增持 | N16: =IF($D$4="自选机构",[1]!S_EST_SCORERATING_INST($E$6,Y16,$F$4),[1]!S_EST_SCORERATING_INST($E$6,$E$9,D16)) -> 1 | O16: =IF($D$4="自选机构",[1]!S_EST_STDRATING_INST($E$6,Y16,$F$4),[1]!S_EST_STDRATING_INST($E$6,$E$9,D16)) -> 增持 | P16: =IF($D$4="自选机构",[1]!S_EST_FRSTRATINGTIME_INST($E$6,$F$4),[1]!S_EST_FRSTRATINGTIME_INST($E$6,D16)) -> 0 | Q16: =IF(G16-$F$10>=0,1,"") | X16: =--G16 -> 45360 | Y16: =K15-1 -> -1 | Z16: =IF($D$4="自选机构",[1]!S_EST_SCORERATING_INST($E$6,K16-1,$F$4),[1]!S_EST_SCORERATING_INST($E$6,K16-1,D16)) -> 1 | AA16: =IFERROR(IF(Z16/N16>1,"评级上调",IF(Z16/N16=1,"评级不变",IF(Z16/N16>0,"评级下调","首次评级"))),0) -> 评级不变 | AB16: =IF(K16-$F$10>=0,1,"") | AC16: =IF(ISERROR(AA16),"",IF(AA16="评级不变",0,IF(AA16="评级下调",-1,IF(AA16="评级上调",1,"")))) -> 0
C17: =G16-1 -> 45359 | D17: 3 | E17: =IF($D$4="自选机构",$E$4,VLOOKUP(D17,Institutionlist,2,FALSE)) -> 中银国际 | F17: =IF($D$4="自选机构",[1]!S_EST_ESTANALYST($E$6,$E$8,C17,$F$4),[1]!S_EST_ESTANALYST($E$6,$E$8,$E$9,D17)) -> 卢翌 | G17: =IF($D$4="自选机构",[1]!S_EST_ESTNEWTIME_INST($E$6,$E$8,C17,$F$4),[1]!S_EST_ESTNEWTIME_INST($E$6,$E$8,$E$9,D17)) -> 2024-05-24 | H17: =IF($D$4="自选机构",[1]!S_EST_SALES_INST($E$6,$E$8,C17,$F$4)/currencyunit,[1]!S_EST_SALES_INST($E$6,$E$8,$E$9,D17)/currencyunit) -> 25821 | I17: =IF($D$4="自选机构",[1]!S_EST_NETPROFIT_INST($E$6,$E$8,C17,$F$4)/currencyunit,[1]!S_EST_NETPROFIT_INST($E$6,$E$8,$E$9,D17)/currencyunit) -> -1966 | J17: =IF($D$4="自选机构",[1]!S_EST_EPS_INST($E$6,$E$8,C17,$F$4),[1]!S_EST_EPS_INST($E$6,$E$8,$E$9,D17)) -> -4.6669 | K17: =IF($D$4="自选机构",[1]!S_EST_NEWRATINGTIME_INST($E$6,Y17,$F$4),[1]!S_EST_NEWRATINGTIME_INST($E$6,$E$9,D17)) -> 2024-05-24 | L17: =IF($D$4="自选机构",[1]!S_EST_RATINGANALYST($E$6,Y17,$F$4),[1]!S_EST_RATINGANALYST($E$6,$E$9,D17)) -> 卢翌 | M17: =IF($D$4="自选机构",[1]!S_EST_ORGRATING_INST($E$6,Y17,$F$4),[1]!S_EST_ORGRATING_INST($E$6,$E$9,D17)) -> 中银证券_买入 | N17: =IF($D$4="自选机构",[1]!S_EST_SCORERATING_INST($E$6,Y17,$F$4),[1]!S_EST_SCORERATING_INST($E$6,$E$9,D17)) -> 1 | O17: =IF($D$4="自选机构",[1]!S_EST_STDRATING_INST($E$6,Y17,$F$4),[1]!S_EST_STDRATING_INST($E$6,$E$9,D17)) -> 买入 | P17: =IF($D$4="自选机构",[1]!S_EST_FRSTRATINGTIME_INST($E$6,$F$4),[1]!S_EST_FRSTRATINGTIME_INST($E$6,D17)) -> 0 | Q17: =IF(G17-$F$10>=0,1,"") -> 1 | X17: =--G17 -> 45436 | Y17: =K16-1 -> 45359 | Z17: =IF($D$4="自选机构",[1]!S_EST_SCORERATING_INST($E$6,K17-1,$F$4),[1]!S_EST_SCORERATING_INST($E$6,K17-1,D17)) -> 3 | AA17: =IFERROR(IF(Z17/N17>1,"评级上调",IF(Z17/N17=1,"评级不变",IF(Z17/N17>0,"评级下调","首次评级"))),0) -> 评级上调 | AB17: =IF(K17-$F$10>=0,1,"") -> 1 | AC17: =IF(ISERROR(AA17),"",IF(AA17="评级不变",0,IF(AA17="评级下调",-1,IF(AA17="评级上调",1,"")))) -> 1
C18: =G17-1 -> 45435 | D18: 4 | E18: =IF($D$4="自选机构",$E$4,VLOOKUP(D18,Institutionlist,2,FALSE)) -> 国信证券 | F18: =IF($D$4="自选机构",[1]!S_EST_ESTANALYST($E$6,$E$8,C18,$F$4),[1]!S_EST_ESTANALYST($E$6,$E$8,$E$9,D18)) -> 0 | G18: =IF($D$4="自选机构",[1]!S_EST_ESTNEWTIME_INST($E$6,$E$8,C18,$F$4),[1]!S_EST_ESTNEWTIME_INST($E$6,$E$8,$E$9,D18)) -> 0 | H18: =IF($D$4="自选机构",[1]!S_EST_SALES_INST($E$6,$E$8,C18,$F$4)/currencyunit,[1]!S_EST_SALES_INST($E$6,$E$8,$E$9,D18)/currencyunit) -> 0 | I18: =IF($D$4="自选机构",[1]!S_EST_NETPROFIT_INST($E$6,$E$8,C18,$F$4)/currencyunit,[1]!S_EST_NETPROFIT_INST($E$6,$E$8,$E$9,D18)/currencyunit) -> 0 | J18: =IF($D$4="自选机构",[1]!S_EST_EPS_INST($E$6,$E$8,C18,$F$4),[1]!S_EST_EPS_INST($E$6,$E$8,$E$9,D18)) -> 0 | K18: =IF($D$4="自选机构",[1]!S_EST_NEWRATINGTIME_INST($E$6,Y18,$F$4),[1]!S_EST_NEWRATINGTIME_INST($E$6,$E$9,D18)) -> 0 | L18: =IF($D$4="自选机构",[1]!S_EST_RATINGANALYST($E$6,Y18,$F$4),[1]!S_EST_RATINGANALYST($E$6,$E$9,D18)) -> 0 | M18: =IF($D$4="自选机构",[1]!S_EST_ORGRATING_INST($E$6,Y18,$F$4),[1]!S_EST_ORGRATING_INST($E$6,$E$9,D18)) -> 0 | N18: =IF($D$4="自选机构",[1]!S_EST_SCORERATING_INST($E$6,Y18,$F$4),[1]!S_EST_SCORERATING_INST($E$6,$E$9,D18)) -> 0 | O18: =IF($D$4="自选机构",[1]!S_EST_STDRATING_INST($E$6,Y18,$F$4),[1]!S_EST_STDRATING_INST($E$6,$E$9,D18)) -> 0 | P18: =IF($D$4="自选机构",[1]!S_EST_FRSTRATINGTIME_INST($E$6,$F$4),[1]!S_EST_FRSTRATINGTIME_INST($E$6,D18)) -> 0 | Q18: =IF(G18-$F$10>=0,1,"") | X18: =--G18 -> 0 | Y18: =K17-1 -> 45435 | Z18: =IF($D$4="自选机构",[1]!S_EST_SCORERATING_INST($E$6,K18-1,$F$4),[1]!S_EST_SCORERATING_INST($E$6,K18-1,D18)) -> 0 | AA18: =IFERROR(IF(Z18/N18>1,"评级上调",IF(Z18/N18=1,"评级不变",IF(Z18/N18>0,"评级下调","首次评级"))),0) -> 0 | AB18: =IF(K18-$F$10>=0,1,"") | AC18: =IF(ISERROR(AA18),"",IF(AA18="评级不变",0,IF(AA18="评级下调",-1,IF(AA18="评级上调",1,""))))
C19: =G18-1 -> -1 | D19: 5 | E19: =IF($D$4="自选机构",$E$4,VLOOKUP(D19,Institutionlist,2,FALSE)) -> 海通证券 | F19: =IF($D$4="自选机构",[1]!S_EST_ESTANALYST($E$6,$E$8,C19,$F$4),[1]!S_EST_ESTANALYST($E$6,$E$8,$E$9,D19)) -> 0 | G19: =IF($D$4="自选机构",[1]!S_EST_ESTNEWTIME_INST($E$6,$E$8,C19,$F$4),[1]!S_EST_ESTNEWTIME_INST($E$6,$E$8,$E$9,D19)) -> 0 | H19: =IF($D$4="自选机构",[1]!S_EST_SALES_INST($E$6,$E$8,C19,$F$4)/currencyunit,[1]!S_EST_SALES_INST($E$6,$E$8,$E$9,D19)/currencyunit) -> 0 | I19: =IF($D$4="自选机构",[1]!S_EST_NETPROFIT_INST($E$6,$E$8,C19,$F$4)/currencyunit,[1]!S_EST_NETPROFIT_INST($E$6,$E$8,$E$9,D19)/currencyunit) -> 0 | J19: =IF($D$4="自选机构",[1]!S_EST_EPS_INST($E$6,$E$8,C19,$F$4),[1]!S_EST_EPS_INST($E$6,$E$8,$E$9,D19)) -> 0 | K19: =IF($D$4="自选机构",[1]!S_EST_NEWRATINGTIME_INST($E$6,Y19,$F$4),[1]!S_EST_NEWRATINGTIME_INST($E$6,$E$9,D19)) -> 0 | L19: =IF($D$4="自选机构",[1]!S_EST_RATINGANALYST($E$6,Y19,$F$4),[1]!S_EST_RATINGANALYST($E$6,$E$9,D19)) -> 0 | M19: =IF($D$4="自选机构",[1]!S_EST_ORGRATING_INST($E$6,Y19,$F$4),[1]!S_EST_ORGRATING_INST($E$6,$E$9,D19)) -> 0 | N19: =IF($D$4="自选机构",[1]!S_EST_SCORERATING_INST($E$6,Y19,$F$4),[1]!S_EST_SCORERATING_INST($E$6,$E$9,D19)) -> 0 | O19: =IF($D$4="自选机构",[1]!S_EST_STDRATING_INST($E$6,Y19,$F$4),[1]!S_EST_STDRATING_INST($E$6,$E$9,D19)) -> 0 | P19: =IF($D$4="自选机构",[1]!S_EST_FRSTRATINGTIME_INST($E$6,$F$4),[1]!S_EST_FRSTRATINGTIME_INST($E$6,D19)) -> 0 | Q19: =IF(G19-$F$10>=0,1,"") | X19: =--G19 -> 0 | Y19: =K18-1 -> -1 | Z19: =IF($D$4="自选机构",[1]!S_EST_SCORERATING_INST($E$6,K19-1,$F$4),[1]!S_EST_SCORERATING_INST($E$6,K19-1,D19)) -> 0 | AA19: =IFERROR(IF(Z19/N19>1,"评级上调",IF(Z19/N19=1,"评级不变",IF(Z19/N19>0,"评级下调","首次评级"))),0) -> 0 | AB19: =IF(K19-$F$10>=0,1,"") | AC19: =IF(ISERROR(AA19),"",IF(AA19="评级不变",0,IF(AA19="评级下调",-1,IF(AA19="评级上调",1,""))))
C20: =G19-1 -> -1 | D20: 6 | E20: =IF($D$4="自选机构",$E$4,VLOOKUP(D20,Institutionlist,2,FALSE)) -> 招商证券 | F20: =IF($D$4="自选机构",[1]!S_EST_ESTANALYST($E$6,$E$8,C20,$F$4),[1]!S_EST_ESTANALYST($E$6,$E$8,$E$9,D20)) -> 0 | G20: =IF($D$4="自选机构",[1]!S_EST_ESTNEWTIME_INST($E$6,$E$8,C20,$F$4),[1]!S_EST_ESTNEWTIME_INST($E$6,$E$8,$E$9,D20)) -> 0 | H20: =IF($D$4="自选机构",[1]!S_EST_SALES_INST($E$6,$E$8,C20,$F$4)/currencyunit,[1]!S_EST_SALES_INST($E$6,$E$8,$E$9,D20)/currencyunit) -> 0 | I20: =IF($D$4="自选机构",[1]!S_EST_NETPROFIT_INST($E$6,$E$8,C20,$F$4)/currencyunit,[1]!S_EST_NETPROFIT_INST($E$6,$E$8,$E$9,D20)/currencyunit) -> 0 | J20: =IF($D$4="自选机构",[1]!S_EST_EPS_INST($E$6,$E$8,C20,$F$4),[1]!S_EST_EPS_INST($E$6,$E$8,$E$9,D20)) -> 0 | K20: =IF($D$4="自选机构",[1]!S_EST_NEWRATINGTIME_INST($E$6,Y20,$F$4),[1]!S_EST_NEWRATINGTIME_INST($E$6,$E$9,D20)) -> 2024-05-29 | L20: =IF($D$4="自选机构",[1]!S_EST_RATINGANALYST($E$6,Y20,$F$4),[1]!S_EST_RATINGANALYST($E$6,$E$9,D20)) -> 顾佳 | M20: =IF($D$4="自选机构",[1]!S_EST_ORGRATING_INST($E$6,Y20,$F$4),[1]!S_EST_ORGRATING_INST($E$6,$E$9,D20)) -> 招商证券_增持 | N20: =IF($D$4="自选机构",[1]!S_EST_SCORERATING_INST($E$6,Y20,$F$4),[1]!S_EST_SCORERATING_INST($E$6,$E$9,D20)) -> 2 | O20: =IF($D$4="自选机构",[1]!S_EST_STDRATING_INST($E$6,Y20,$F$4),[1]!S_EST_STDRATING_INST($E$6,$E$9,D20)) -> 增持 | P20: =IF($D$4="自选机构",[1]!S_EST_FRSTRATINGTIME_INST($E$6,$F$4),[1]!S_EST_FRSTRATINGTIME_INST($E$6,D20)) -> 0 | Q20: =IF(G20-$F$10>=0,1,"") | X20: =--G20 -> 0 | Y20: =K19-1 -> -1 | Z20: =IF($D$4="自选机构",[1]!S_EST_SCORERATING_INST($E$6,K20-1,$F$4),[1]!S_EST_SCORERATING_INST($E$6,K20-1,D20)) -> 0 | AA20: =IFERROR(IF(Z20/N20>1,"评级上调",IF(Z20/N20=1,"评级不变",IF(Z20/N20>0,"评级下调","首次评级"))),0) -> 首次评级 | AB20: =IF(K20-$F$10>=0,1,"") -> 1 | AC20: =IF(ISERROR(AA20),"",IF(AA20="评级不变",0,IF(AA20="评级下调",-1,IF(AA20="评级上调",1,""))))
C21: =G20-1 -> -1 | D21: 7 | E21: =IF($D$4="自选机构",$E$4,VLOOKUP(D21,Institutionlist,2,FALSE)) -> 光大证券 | F21: =IF($D$4="自选机构",[1]!S_EST_ESTANALYST($E$6,$E$8,C21,$F$4),[1]!S_EST_ESTANALYST($E$6,$E$8,$E$9,D21)) -> 付天姿 | G21: =IF($D$4="自选机构",[1]!S_EST_ESTNEWTIME_INST($E$6,$E$8,C21,$F$4),[1]!S_EST_ESTNEWTIME_INST($E$6,$E$8,$E$9,D21)) -> 2024-06-20 | H21: =IF($D$4="自选机构",[1]!S_EST_SALES_INST($E$6,$E$8,C21,$F$4)/currencyunit,[1]!S_EST_SALES_INST($E$6,$E$8,$E$9,D21)/currencyunit) -> 26107 | I21: =IF($D$4="自选机构",[1]!S_EST_NETPROFIT_INST($E$6,$E$8,C21,$F$4)/currencyunit,[1]!S_EST_NETPROFIT_INST($E$6,$E$8,$E$9,D21)/currencyunit) -> -1558.995 | J21: =IF($D$4="自选机构",[1]!S_EST_EPS_INST($E$6,$E$8,C21,$F$4),[1]!S_EST_EPS_INST($E$6,$E$8,$E$9,D21)) -> -3.7008 | K21: =IF($D$4="自选机构",[1]!S_EST_NEWRATINGTIME_INST($E$6,Y21,$F$4),[1]!S_EST_NEWRATINGTIME_INST($E$6,$E$9,D21)) -> 0 | L21: =IF($D$4="自选机构",[1]!S_EST_RATINGANALYST($E$6,Y21,$F$4),[1]!S_EST_RATINGANALYST($E$6,$E$9,D21)) -> 0 | M21: =IF($D$4="自选机构",[1]!S_EST_ORGRATING_INST($E$6,Y21,$F$4),[1]!S_EST_ORGRATING_INST($E$6,$E$9,D21)) -> 0 | N21: =IF($D$4="自选机构",[1]!S_EST_SCORERATING_INST($E$6,Y21,$F$4),[1]!S_EST_SCORERATING_INST($E$6,$E$9,D21)) -> 0 | O21: =IF($D$4="自选机构",[1]!S_EST_STDRATING_INST($E$6,Y21,$F$4),[1]!S_EST_STDRATING_INST($E$6,$E$9,D21)) -> 0 | P21: =IF($D$4="自选机构",[1]!S_EST_FRSTRATINGTIME_INST($E$6,$F$4),[1]!S_EST_FRSTRATINGTIME_INST($E$6,D21)) -> 0 | Q21: =IF(G21-$F$10>=0,1,"") -> 1 | X21: =--G21 -> 45463 | Y21: =K20-1 -> 45440 | Z21: =IF($D$4="自选机构",[1]!S_EST_SCORERATING_INST($E$6,K21-1,$F$4),[1]!S_EST_SCORERATING_INST($E$6,K21-1,D21)) -> 0 | AA21: =IFERROR(IF(Z21/N21>1,"评级上调",IF(Z21/N21=1,"评级不变",IF(Z21/N21>0,"评级下调","首次评级"))),0) -> 0 | AB21: =IF(K21-$F$10>=0,1,"") | AC21: =IF(ISERROR(AA21),"",IF(AA21="评级不变",0,IF(AA21="评级下调",-1,IF(AA21="评级上调",1,""))))
C22: =G21-1 -> 45462 | D22: 8 | E22: =IF($D$4="自选机构",$E$4,VLOOKUP(D22,Institutionlist,2,FALSE)) -> 中信证券 | F22: =IF($D$4="自选机构",[1]!S_EST_ESTANALYST($E$6,$E$8,C22,$F$4),[1]!S_EST_ESTANALYST($E$6,$E$8,$E$9,D22)) -> 0 | G22: =IF($D$4="自选机构",[1]!S_EST_ESTNEWTIME_INST($E$6,$E$8,C22,$F$4),[1]!S_EST_ESTNEWTIME_INST($E$6,$E$8,$E$9,D22)) -> 0 | H22: =IF($D$4="自选机构",[1]!S_EST_SALES_INST($E$6,$E$8,C22,$F$4)/currencyunit,[1]!S_EST_SALES_INST($E$6,$E$8,$E$9,D22)/currencyunit) -> 0 | I22: =IF($D$4="自选机构",[1]!S_EST_NETPROFIT_INST($E$6,$E$8,C22,$F$4)/currencyunit,[1]!S_EST_NETPROFIT_INST($E$6,$E$8,$E$9,D22)/currencyunit) -> 0 | J22: =IF($D$4="自选机构",[1]!S_EST_EPS_INST($E$6,$E$8,C22,$F$4),[1]!S_EST_EPS_INST($E$6,$E$8,$E$9,D22)) -> 0 | K22: =IF($D$4="自选机构",[1]!S_EST_NEWRATINGTIME_INST($E$6,Y22,$F$4),[1]!S_EST_NEWRATINGTIME_INST($E$6,$E$9,D22)) -> 0 | L22: =IF($D$4="自选机构",[1]!S_EST_RATINGANALYST($E$6,Y22,$F$4),[1]!S_EST_RATINGANALYST($E$6,$E$9,D22)) -> 0 | M22: =IF($D$4="自选机构",[1]!S_EST_ORGRATING_INST($E$6,Y22,$F$4),[1]!S_EST_ORGRATING_INST($E$6,$E$9,D22)) -> 0 | N22: =IF($D$4="自选机构",[1]!S_EST_SCORERATING_INST($E$6,Y22,$F$4),[1]!S_EST_SCORERATING_INST($E$6,$E$9,D22)) -> 0 | O22: =IF($D$4="自选机构",[1]!S_EST_STDRATING_INST($E$6,Y22,$F$4),[1]!S_EST_STDRATING_INST($E$6,$E$9,D22)) -> 0 | P22: =IF($D$4="自选机构",[1]!S_EST_FRSTRATINGTIME_INST($E$6,$F$4),[1]!S_EST_FRSTRATINGTIME_INST($E$6,D22)) -> 0 | Q22: =IF(G22-$F$10>=0,1,"") | X22: =--G22 -> 0 | Y22: =K21-1 -> -1 | Z22: =IF($D$4="自选机构",[1]!S_EST_SCORERATING_INST($E$6,K22-1,$F$4),[1]!S_EST_SCORERATING_INST($E$6,K22-1,D22)) -> 0 | AA22: =IFERROR(IF(Z22/N22>1,"评级上调",IF(Z22/N22=1,"评级不变",IF(Z22/N22>0,"评级下调","首次评级"))),0) -> 0 | AB22: =IF(K22-$F$10>=0,1,"") | AC22: =IF(ISERROR(AA22),"",IF(AA22="评级不变",0,IF(AA22="评级下调",-1,IF(AA22="评级上调",1,""))))
C23: =G22-1 -> -1 | D23: 9 | E23: =IF($D$4="自选机构",$E$4,VLOOKUP(D23,Institutionlist,2,FALSE)) -> 国金证券 | F23: =IF($D$4="自选机构",[1]!S_EST_ESTANALYST($E$6,$E$8,C23,$F$4),[1]!S_EST_ESTANALYST($E$6,$E$8,$E$9,D23)) -> 陈泽敏 | G23: =IF($D$4="自选机构",[1]!S_EST_ESTNEWTIME_INST($E$6,$E$8,C23,$F$4),[1]!S_EST_ESTNEWTIME_INST($E$6,$E$8,$E$9,D23)) -> 2024-03-09 | H23: =IF($D$4="自选机构",[1]!S_EST_SALES_INST($E$6,$E$8,C23,$F$4)/currencyunit,[1]!S_EST_SALES_INST($E$6,$E$8,$E$9,D23)/currencyunit) -> 25667 | I23: =IF($D$4="自选机构",[1]!S_EST_NETPROFIT_INST($E$6,$E$8,C23,$F$4)/currencyunit,[1]!S_EST_NETPROFIT_INST($E$6,$E$8,$E$9,D23)/currencyunit) -> -1767.0179 | J23: =IF($D$4="自选机构",[1]!S_EST_EPS_INST($E$6,$E$8,C23,$F$4),[1]!S_EST_EPS_INST($E$6,$E$8,$E$9,D23)) -> -4.1945 | K23: =IF($D$4="自选机构",[1]!S_EST_NEWRATINGTIME_INST($E$6,Y23,$F$4),[1]!S_EST_NEWRATINGTIME_INST($E$6,$E$9,D23)) -> 2024-03-09 | L23: =IF($D$4="自选机构",[1]!S_EST_RATINGANALYST($E$6,Y23,$F$4),[1]!S_EST_RATINGANALYST($E$6,$E$9,D23)) -> 陈泽敏 | M23: =IF($D$4="自选机构",[1]!S_EST_ORGRATING_INST($E$6,Y23,$F$4),[1]!S_EST_ORGRATING_INST($E$6,$E$9,D23)) -> 国金证券_买入 | N23: =IF($D$4="自选机构",[1]!S_EST_SCORERATING_INST($E$6,Y23,$F$4),[1]!S_EST_SCORERATING_INST($E$6,$E$9,D23)) -> 1 | O23: =IF($D$4="自选机构",[1]!S_EST_STDRATING_INST($E$6,Y23,$F$4),[1]!S_EST_STDRATING_INST($E$6,$E$9,D23)) -> 买入 | P23: =IF($D$4="自选机构",[1]!S_EST_FRSTRATINGTIME_INST($E$6,$F$4),[1]!S_EST_FRSTRATINGTIME_INST($E$6,D23)) -> 0 | Q23: =IF(G23-$F$10>=0,1,"") | X23: =--G23 -> 45360 | Y23: =K22-1 -> -1 | Z23: =IF($D$4="自选机构",[1]!S_EST_SCORERATING_INST($E$6,K23-1,$F$4),[1]!S_EST_SCORERATING_INST($E$6,K23-1,D23)) -> 0 | AA23: =IFERROR(IF(Z23/N23>1,"评级上调",IF(Z23/N23=1,"评级不变",IF(Z23/N23>0,"评级下调","首次评级"))),0) -> 首次评级 | AB23: =IF(K23-$F$10>=0,1,"") | AC23: =IF(ISERROR(AA23),"",IF(AA23="评级不变",0,IF(AA23="评级下调",-1,IF(AA23="评级上调",1,""))))
C24: =G23-1 -> 45359 | D24: 10 | E24: =IF($D$4="自选机构",$E$4,VLOOKUP(D24,Institutionlist,2,FALSE)) -> 兴业证券 | F24: =IF($D$4="自选机构",[1]!S_EST_ESTANALYST($E$6,$E$8,C24,$F$4),[1]!S_EST_ESTANALYST($E$6,$E$8,$E$9,D24)) -> 0 | G24: =IF($D$4="自选机构",[1]!S_EST_ESTNEWTIME_INST($E$6,$E$8,C24,$F$4),[1]!S_EST_ESTNEWTIME_INST($E$6,$E$8,$E$9,D24)) -> 0 | H24: =IF($D$4="自选机构",[1]!S_EST_SALES_INST($E$6,$E$8,C24,$F$4)/currencyunit,[1]!S_EST_SALES_INST($E$6,$E$8,$E$9,D24)/currencyunit) -> 0 | I24: =IF($D$4="自选机构",[1]!S_EST_NETPROFIT_INST($E$6,$E$8,C24,$F$4)/currencyunit,[1]!S_EST_NETPROFIT_INST($E$6,$E$8,$E$9,D24)/currencyunit) -> 0 | J24: =IF($D$4="自选机构",[1]!S_EST_EPS_INST($E$6,$E$8,C24,$F$4),[1]!S_EST_EPS_INST($E$6,$E$8,$E$9,D24)) -> 0 | K24: =IF($D$4="自选机构",[1]!S_EST_NEWRATINGTIME_INST($E$6,Y24,$F$4),[1]!S_EST_NEWRATINGTIME_INST($E$6,$E$9,D24)) -> 0 | L24: =IF($D$4="自选机构",[1]!S_EST_RATINGANALYST($E$6,Y24,$F$4),[1]!S_EST_RATINGANALYST($E$6,$E$9,D24)) -> 0 | M24: =IF($D$4="自选机构",[1]!S_EST_ORGRATING_INST($E$6,Y24,$F$4),[1]!S_EST_ORGRATING_INST($E$6,$E$9,D24)) -> 0 | N24: =IF($D$4="自选机构",[1]!S_EST_SCORERATING_INST($E$6,Y24,$F$4),[1]!S_EST_SCORERATING_INST($E$6,$E$9,D24)) -> 0 | O24: =IF($D$4="自选机构",[1]!S_EST_STDRATING_INST($E$6,Y24,$F$4),[1]!S_EST_STDRATING_INST($E$6,$E$9,D24)) -> 0 | P24: =IF($D$4="自选机构",[1]!S_EST_FRSTRATINGTIME_INST($E$6,$F$4),[1]!S_EST_FRSTRATINGTIME_INST($E$6,D24)) -> 0 | Q24: =IF(G24-$F$10>=0,1,"") | X24: =--G24 -> 0 | Y24: =K23-1 -> 45359 | Z24: =IF($D$4="自选机构",[1]!S_EST_SCORERATING_INST($E$6,K24-1,$F$4),[1]!S_EST_SCORERATING_INST($E$6,K24-1,D24)) -> 0 | AA24: =IFERROR(IF(Z24/N24>1,"评级上调",IF(Z24/N24=1,"评级不变",IF(Z24/N24>0,"评级下调","首次评级"))),0) -> 0 | AB24: =IF(K24-$F$10>=0,1,"") | AC24: =IF(ISERROR(AA24),"",IF(AA24="评级不变",0,IF(AA24="评级下调",-1,IF(AA24="评级上调",1,""))))
C25: =G24-1 -> -1 | D25: 11 | E25: =IF($D$4="自选机构",$E$4,VLOOKUP(D25,Institutionlist,2,FALSE)) -> 东方证券 | F25: =IF($D$4="自选机构",[1]!S_EST_ESTANALYST($E$6,$E$8,C25,$F$4),[1]!S_EST_ESTANALYST($E$6,$E$8,$E$9,D25)) -> 项雯倩 | G25: =IF($D$4="自选机构",[1]!S_EST_ESTNEWTIME_INST($E$6,$E$8,C25,$F$4),[1]!S_EST_ESTNEWTIME_INST($E$6,$E$8,$E$9,D25)) -> 2024-05-26 | H25: =IF($D$4="自选机构",[1]!S_EST_SALES_INST($E$6,$E$8,C25,$F$4)/currencyunit,[1]!S_EST_SALES_INST($E$6,$E$8,$E$9,D25)/currencyunit) -> 25711 | I25: =IF($D$4="自选机构",[1]!S_EST_NETPROFIT_INST($E$6,$E$8,C25,$F$4)/currencyunit,[1]!S_EST_NETPROFIT_INST($E$6,$E$8,$E$9,D25)/currencyunit) -> -1403.9946 | J25: =IF($D$4="自选机构",[1]!S_EST_EPS_INST($E$6,$E$8,C25,$F$4),[1]!S_EST_EPS_INST($E$6,$E$8,$E$9,D25)) -> -3.3328 | K25: =IF($D$4="自选机构",[1]!S_EST_NEWRATINGTIME_INST($E$6,Y25,$F$4),[1]!S_EST_NEWRATINGTIME_INST($E$6,$E$9,D25)) -> 2024-05-26 | L25: =IF($D$4="自选机构",[1]!S_EST_RATINGANALYST($E$6,Y25,$F$4),[1]!S_EST_RATINGANALYST($E$6,$E$9,D25)) -> 项雯倩 | M25: =IF($D$4="自选机构",[1]!S_EST_ORGRATING_INST($E$6,Y25,$F$4),[1]!S_EST_ORGRATING_INST($E$6,$E$9,D25)) -> 东方证券_买入 | N25: =IF($D$4="自选机构",[1]!S_EST_SCORERATING_INST($E$6,Y25,$F$4),[1]!S_EST_SCORERATING_INST($E$6,$E$9,D25)) -> 1 | O25: =IF($D$4="自选机构",[1]!S_EST_STDRATING_INST($E$6,Y25,$F$4),[1]!S_EST_STDRATING_INST($E$6,$E$9,D25)) -> 买入 | P25: =IF($D$4="自选机构",[1]!S_EST_FRSTRATINGTIME_INST($E$6,$F$4),[1]!S_EST_FRSTRATINGTIME_INST($E$6,D25)) -> 0 | Q25: =IF(G25-$F$10>=0,1,"") -> 1 | X25: =--G25 -> 45438 | Y25: =K24-1 -> -1 | Z25: =IF($D$4="自选机构",[1]!S_EST_SCORERATING_INST($E$6,K25-1,$F$4),[1]!S_EST_SCORERATING_INST($E$6,K25-1,D25)) -> 1 | AA25: =IFERROR(IF(Z25/N25>1,"评级上调",IF(Z25/N25=1,"评级不变",IF(Z25/N25>0,"评级下调","首次评级"))),0) -> 评级不变 | AB25: =IF(K25-$F$10>=0,1,"") -> 1 | AC25: =IF(ISERROR(AA25),"",IF(AA25="评级不变",0,IF(AA25="评级下调",-1,IF(AA25="评级上调",1,"")))) -> 0
C26: =G25-1 -> 45437 | D26: 12 | E26: =IF($D$4="自选机构",$E$4,VLOOKUP(D26,Institutionlist,2,FALSE)) -> 长江证券 | F26: =IF($D$4="自选机构",[1]!S_EST_ESTANALYST($E$6,$E$8,C26,$F$4),[1]!S_EST_ESTANALYST($E$6,$E$8,$E$9,D26)) -> 0 | G26: =IF($D$4="自选机构",[1]!S_EST_ESTNEWTIME_INST($E$6,$E$8,C26,$F$4),[1]!S_EST_ESTNEWTIME_INST($E$6,$E$8,$E$9,D26)) -> 0 | H26: =IF($D$4="自选机构",[1]!S_EST_SALES_INST($E$6,$E$8,C26,$F$4)/currencyunit,[1]!S_EST_SALES_INST($E$6,$E$8,$E$9,D26)/currencyunit) -> 0 | I26: =IF($D$4="自选机构",[1]!S_EST_NETPROFIT_INST($E$6,$E$8,C26,$F$4)/currencyunit,[1]!S_EST_NETPROFIT_INST($E$6,$E$8,$E$9,D26)/currencyunit) -> 0 | J26: =IF($D$4="自选机构",[1]!S_EST_EPS_INST($E$6,$E$8,C26,$F$4),[1]!S_EST_EPS_INST($E$6,$E$8,$E$9,D26)) -> 0 | K26: =IF($D$4="自选机构",[1]!S_EST_NEWRATINGTIME_INST($E$6,Y26,$F$4),[1]!S_EST_NEWRATINGTIME_INST($E$6,$E$9,D26)) -> 2024-03-12 | L26: =IF($D$4="自选机构",[1]!S_EST_RATINGANALYST($E$6,Y26,$F$4),[1]!S_EST_RATINGANALYST($E$6,$E$9,D26)) -> 高超 | M26: =IF($D$4="自选机构",[1]!S_EST_ORGRATING_INST($E$6,Y26,$F$4),[1]!S_EST_ORGRATING_INST($E$6,$E$9,D26)) -> 长江证券_买入 | N26: =IF($D$4="自选机构",[1]!S_EST_SCORERATING_INST($E$6,Y26,$F$4),[1]!S_EST_SCORERATING_INST($E$6,$E$9,D26)) -> 1 | O26: =IF($D$4="自选机构",[1]!S_EST_STDRATING_INST($E$6,Y26,$F$4),[1]!S_EST_STDRATING_INST($E$6,$E$9,D26)) -> 买入 | P26: =IF($D$4="自选机构",[1]!S_EST_FRSTRATINGTIME_INST($E$6,$F$4),[1]!S_EST_FRSTRATINGTIME_INST($E$6,D26)) -> 0 | Q26: =IF(G26-$F$10>=0,1,"") | X26: =--G26 -> 0 | Y26: =K25-1 -> 45437 | Z26: =IF($D$4="自选机构",[1]!S_EST_SCORERATING_INST($E$6,K26-1,$F$4),[1]!S_EST_SCORERATING_INST($E$6,K26-1,D26)) -> 1 | AA26: =IFERROR(IF(Z26/N26>1,"评级上调",IF(Z26/N26=1,"评级不变",IF(Z26/N26>0,"评级下调","首次评级"))),0) -> 评级不变 | AB26: =IF(K26-$F$10>=0,1,"") | AC26: =IF(ISERROR(AA26),"",IF(AA26="评级不变",0,IF(AA26="评级下调",-1,IF(AA26="评级上调",1,"")))) -> 0
C27: =G26-1 -> -1 | D27: 13 | E27: =IF($D$4="自选机构",$E$4,VLOOKUP(D27,Institutionlist,2,FALSE)) -> 华泰证券 | F27: =IF($D$4="自选机构",[1]!S_EST_ESTANALYST($E$6,$E$8,C27,$F$4),[1]!S_EST_ESTANALYST($E$6,$E$8,$E$9,D27)) -> 夏路路 | G27: =IF($D$4="自选机构",[1]!S_EST_ESTNEWTIME_INST($E$6,$E$8,C27,$F$4),[1]!S_EST_ESTNEWTIME_INST($E$6,$E$8,$E$9,D27)) -> 2024-05-24 | H27: =IF($D$4="自选机构",[1]!S_EST_SALES_INST($E$6,$E$8,C27,$F$4)/currencyunit,[1]!S_EST_SALES_INST($E$6,$E$8,$E$9,D27)/currencyunit) -> 25693 | I27: =IF($D$4="自选机构",[1]!S_EST_NETPROFIT_INST($E$6,$E$8,C27,$F$4)/currencyunit,[1]!S_EST_NETPROFIT_INST($E$6,$E$8,$E$9,D27)/currencyunit) -> -2090 | J27: =IF($D$4="自选机构",[1]!S_EST_EPS_INST($E$6,$E$8,C27,$F$4),[1]!S_EST_EPS_INST($E$6,$E$8,$E$9,D27)) -> -4.96 | K27: =IF($D$4="自选机构",[1]!S_EST_NEWRATINGTIME_INST($E$6,Y27,$F$4),[1]!S_EST_NEWRATINGTIME_INST($E$6,$E$9,D27)) -> 0 | L27: =IF($D$4="自选机构",[1]!S_EST_RATINGANALYST($E$6,Y27,$F$4),[1]!S_EST_RATINGANALYST($E$6,$E$9,D27)) -> 0 | M27: =IF($D$4="自选机构",[1]!S_EST_ORGRATING_INST($E$6,Y27,$F$4),[1]!S_EST_ORGRATING_INST($E$6,$E$9,D27)) -> 0 | N27: =IF($D$4="自选机构",[1]!S_EST_SCORERATING_INST($E$6,Y27,$F$4),[1]!S_EST_SCORERATING_INST($E$6,$E$9,D27)) -> 0 | O27: =IF($D$4="自选机构",[1]!S_EST_STDRATING_INST($E$6,Y27,$F$4),[1]!S_EST_STDRATING_INST($E$6,$E$9,D27)) -> 0 | P27: =IF($D$4="自选机构",[1]!S_EST_FRSTRATINGTIME_INST($E$6,$F$4),[1]!S_EST_FRSTRATINGTIME_INST($E$6,D27)) -> 0 | Q27: =IF(G27-$F$10>=0,1,"") -> 1 | X27: =--G27 -> 45436 | Y27: =K26-1 -> 45362 | Z27: =IF($D$4="自选机构",[1]!S_EST_SCORERATING_INST($E$6,K27-1,$F$4),[1]!S_EST_SCORERATING_INST($E$6,K27-1,D27)) -> 0 | AA27: =IFERROR(IF(Z27/N27>1,"评级上调",IF(Z27/N27=1,"评级不变",IF(Z27/N27>0,"评级下调","首次评级"))),0) -> 0 | AB27: =IF(K27-$F$10>=0,1,"") | AC27: =IF(ISERROR(AA27),"",IF(AA27="评级不变",0,IF(AA27="评级下调",-1,IF(AA27="评级上调",1,""))))
... C99: =G98-1 -> -1 | D99: 86 | E99: =IF($D$4="自选机构",$E$4,VLOOKUP(D99,Institutionlist,2,FALSE)) -> 0 | F99: =IF($D$4="自选机构",[1]!S_EST_ESTANALYST($E$6,$E$8,C99,$F$4),[1]!S_EST_ESTANALYST($E$6,$E$8,$E$9,D99)) -> 赵丽 | G99: =IF($D$4="自选机构",[1]!S_EST_ESTNEWTIME_INST($E$6,$E$8,C99,$F$4),[1]!S_EST_ESTNEWTIME_INST($E$6,$E$8,$E$9,D99)) -> 2024-05-24 | H99: =IF($D$4="自选机构",[1]!S_EST_SALES_INST($E$6,$E$8,C99,$F$4)/currencyunit,[1]!S_EST_SALES_INST($E$6,$E$8,$E$9,D99)/currencyunit) -> 25417 | I99: =IF($D$4="自选机构",[1]!S_EST_NETPROFIT_INST($E$6,$E$8,C99,$F$4)/currencyunit,[1]!S_EST_NETPROFIT_INST($E$6,$E$8,$E$9,D99)/currencyunit) -> -1796.0096 | J99: =IF($D$4="自选机构",[1]!S_EST_EPS_INST($E$6,$E$8,C99,$F$4),[1]!S_EST_EPS_INST($E$6,$E$8,$E$9,D99)) -> -4.2634 | K99: =IF($D$4="自选机构",[1]!S_EST_NEWRATINGTIME_INST($E$6,Y99,$F$4),[1]!S_EST_NEWRATINGTIME_INST($E$6,$E$9,D99)) -> 2024-05-27 | L99: =IF($D$4="自选机构",[1]!S_EST_RATINGANALYST($E$6,Y99,$F$4),[1]!S_EST_RATINGANALYST($E$6,$E$9,D99)) -> 交银国际 | M99: =IF($D$4="自选机构",[1]!S_EST_ORGRATING_INST($E$6,Y99,$F$4),[1]!S_EST_ORGRATING_INST($E$6,$E$9,D99)) -> 交银国际_买入 | N99: =IF($D$4="自选机构",[1]!S_EST_SCORERATING_INST($E$6,Y99,$F$4),[1]!S_EST_SCORERATING_INST($E$6,$E$9,D99)) -> 2 | O99: =IF($D$4="自选机构",[1]!S_EST_STDRATING_INST($E$6,Y99,$F$4),[1]!S_EST_STDRATING_INST($E$6,$E$9,D99)) -> 买入 | P99: =IF($D$4="自选机构",[1]!S_EST_FRSTRATINGTIME_INST($E$6,$F$4),[1]!S_EST_FRSTRATINGTIME_INST($E$6,D99)) -> 0 | Q99: =IF(G99-$F$10>=0,1,"") -> 1 | X99: =--G99 -> 45436 | Y99: =K98-1 -> -1 | Z99: =IF($D$4="自选机构",[1]!S_EST_SCORERATING_INST($E$6,K99-1,$F$4),[1]!S_EST_SCORERATING_INST($E$6,K99-1,D99)) -> 2 | AA99: =IFERROR(IF(Z99/N99>1,"评级上调",IF(Z99/N99=1,"评级不变",IF(Z99/N99>0,"评级下调","首次评级"))),0) -> 评级不变 | AB99: =IF(K99-$F$10>=0,1,"") -> 1 | AC99: =IF(ISERROR(AA99),"",IF(AA99="评级不变",0,IF(AA99="评级下调",-1,IF(AA99="评级上调",1,"")))) -> 0

Sheet 主营构成
A1: 返回 | D1: 股票速览-主营构成基础数据
C3: 按产品分类 | E3: =公司分析!H64 -> 年度
C5: =IF(MONTH(公司分析!D66)=6,YEAR(公司分析!D66)-1&"-12-31",YEAR(公司分析!D66)&"-6-30") -> 2019-6-30 | F5: =公司分析!D66 -> 2019/12/31 | I5: =公司分析!E66 -> 2020/12/31 | L5: =公司分析!F66 -> 2021/12/31 | O5: =公司分析!G66 -> 2022/12/31 | R5: =公司分析!H66 -> 2023/12/31
C6: ="项目"&"["&C3&"]" -> 项目[按产品分类] | D6: ="收入"&"["&C3&"]" -> 收入[按产品分类] | E6: ="利润"&"["&C3&"]" -> 利润[按产品分类] | F6: ="项目"&"["&C3&"]" -> 项目[按产品分类] | G6: ="收入"&"["&C3&"]" -> 收入[按产品分类] | H6: ="利润"&"["&C3&"]" -> 利润[按产品分类] | I6: ="项目"&"["&C3&"]" -> 项目[按产品分类] | J6: ="收入"&"["&C3&"]" -> 收入[按产品分类] | K6: ="利润"&"["&C3&"]" -> 利润[按产品分类] | L6: ="项目"&"["&C3&"]" -> 项目[按产品分类] | M6: ="收入"&"["&C3&"]" -> 收入[按产品分类] | N6: ="利润"&"["&C3&"]" -> 利润[按产品分类] | O6: ="项目"&"["&C3&"]" -> 项目[按产品分类] | P6: ="收入"&"["&C3&"]" -> 收入[按产品分类] | Q6: ="利润"&"["&C3&"]" -> 利润[按产品分类] | R6: ="项目"&"["&C3&"]" -> 项目[按产品分类] | S6: ="收入"&"["&C3&"]" -> 收入[按产品分类] | T6: ="利润"&"["&C3&"]" -> 利润[按产品分类]
C7: =IF($C$3="按行业分类",[1]!s_segment_industry_item(公司分析!$D$4,C$5,ROW()-ROW($C$6)),IF($C$3="按产品分类",[1]!s_segment_product_item(公司分析!$D$4,C$5,ROW()-ROW($C$6)),[1]!S_SEGMENT_REGION_ITEM(公司分析!$D$4,C$5,ROW()-ROW($C$6)))) -> 移动游戏 | D7: =IF($C$3="按行业分类",[1]!s_segment_industry_sales(公司分析!$D$4,C$5,ROW()-ROW($C$6)),IF($C$3="按产品分类",[1]!s_segment_product_sales(公司分析!$D$4,C$5,ROW()-ROW($C$6)),[1]!S_SEGMENT_REGION_SALES(公司分析!$D$4,C$5,ROW()-ROW($C$6))))/CurrencyUnit -> 17.93311 | E7: =IF($C$3="按行业分类",[1]!s_segment_industry_profit(公司分析!$D$4,C$5,ROW()-ROW($C$6)),IF($C$3="按产品分类",[1]!s_segment_product_profit(公司分析!$D$4,C$5,ROW()-ROW($C$6)),[1]!S_SEGMENT_REGION_PROFIT(公司分析!$D$4,C$5,ROW()-ROW($C$6))))/CurrencyUnit -> 0 | F7: =IF($C$3="按行业分类",[1]!s_segment_industry_item(公司分析!$D$4,F$5,ROW()-ROW($C$6)),IF($C$3="按产品分类",[1]!s_segment_product_item(公司分析!$D$4,F$5,ROW()-ROW($C$6)),[1]!S_SEGMENT_REGION_ITEM(公司分析!$D$4,F$5,ROW()-ROW($C$6)))) -> 移动游戏 | G7: =IF($C$3="按行业分类",[1]!s_segment_industry_sales(公司分析!$D$4,F$5,ROW()-ROW($C$6)),IF($C$3="按产品分类",[1]!s_segment_product_sales(公司分析!$D$4,F$5,ROW()-ROW($C$6)),[1]!S_SEGMENT_REGION_SALES(公司分析!$D$4,F$5,ROW()-ROW($C$6))))/CurrencyUnit -> 35.97809 | H7: =IF($C$3="按行业分类",[1]!s_segment_industry_profit(公司分析!$D$4,F$5,ROW()-ROW($C$6)),IF($C$3="按产品分类",[1]!s_segment_product_profit(公司分析!$D$4,F$5,ROW()-ROW($C$6)),[1]!S_SEGMENT_REGION_PROFIT(公司分析!$D$4,F$5,ROW()-ROW($C$6))))/CurrencyUnit -> 0 | I7: =IF($C$3="按行业分类",[1]!s_segment_industry_item(公司分析!$D$4,I$5,ROW()-ROW($C$6)),IF($C$3="按产品分类",[1]!s_segment_product_item(公司分析!$D$4,I$5,ROW()-ROW($C$6)),[1]!S_SEGMENT_REGION_ITEM(公司分析!$D$4,I$5,ROW()-ROW($C$6)))) -> 移动游戏 | J7: =IF($C$3="按行业分类",[1]!s_segment_industry_sales(公司分析!$D$4,I$5,ROW()-ROW($C$6)),IF($C$3="按产品分类",[1]!s_segment_product_sales(公司分析!$D$4,I$5,ROW()-ROW($C$6)),[1]!S_SEGMENT_REGION_SALES(公司分析!$D$4,I$5,ROW()-ROW($C$6))))/CurrencyUnit -> 48.03382 | K7: =IF($C$3="按行业分类",[1]!s_segment_industry_profit(公司分析!$D$4,I$5,ROW()-ROW($C$6)),IF($C$3="按产品分类",[1]!s_segment_product_profit(公司分析!$D$4,I$5,ROW()-ROW($C$6)),[1]!S_SEGMENT_REGION_PROFIT(公司分析!$D$4,I$5,ROW()-ROW($C$6))))/CurrencyUnit -> 0 | L7: =IF($C$3="按行业分类",[1]!s_segment_industry_item(公司分析!$D$4,L$5,ROW()-ROW($C$6)),IF($C$3="按产品分类",[1]!s_segment_product_item(公司分析!$D$4,L$5,ROW()-ROW($C$6)),[1]!S_SEGMENT_REGION_ITEM(公司分析!$D$4,L$5,ROW()-ROW($C$6)))) -> 直播及增值业务 | M7: =IF($C$3="按行业分类",[1]!s_segment_industry_sales(公司分析!$D$4,L$5,ROW()-ROW($C$6)),IF($C$3="按产品分类",[1]!s_segment_product_sales(公司分析!$D$4,L$5,ROW()-ROW($C$6)),[1]!S_SEGMENT_REGION_SALES(公司分析!$D$4,L$5,ROW()-ROW($C$6))))/CurrencyUnit -> 69.34886 | N7: =IF($C$3="按行业分类",[1]!s_segment_industry_profit(公司分析!$D$4,L$5,ROW()-ROW($C$6)),IF($C$3="按产品分类",[1]!s_segment_product_profit(公司分析!$D$4,L$5,ROW()-ROW($C$6)),[1]!S_SEGMENT_REGION_PROFIT(公司分析!$D$4,L$5,ROW()-ROW($C$6))))/CurrencyUnit -> 0 | O7: =IF($C$3="按行业分类",[1]!s_segment_industry_item(公司分析!$D$4,O$5,ROW()-ROW($C$6)),IF($C$3="按产品分类",[1]!s_segment_product_item(公司分析!$D$4,O$5,ROW()-ROW($C$6)),[1]!S_SEGMENT_REGION_ITEM(公司分析!$D$4,O$5,ROW()-ROW($C$6)))) -> 增值服务 | P7: =IF($C$3="按行业分类",[1]!s_segment_industry_sales(公司分析!$D$4,O$5,ROW()-ROW($C$6)),IF($C$3="按产品分类",[1]!s_segment_product_sales(公司分析!$D$4,O$5,ROW()-ROW($C$6)),[1]!S_SEGMENT_REGION_SALES(公司分析!$D$4,O$5,ROW()-ROW($C$6))))/CurrencyUnit -> 87.1517 | Q7: =IF($C$3="按行业分类",[1]!s_segment_industry_profit(公司分析!$D$4,O$5,ROW()-ROW($C$6)),IF($C$3="按产品分类",[1]!s_segment_product_profit(公司分析!$D$4,O$5,ROW()-ROW($C$6)),[1]!S_SEGMENT_REGION_PROFIT(公司分析!$D$4,O$5,ROW()-ROW($C$6))))/CurrencyUnit -> 0 | R7: =IF($C$3="按行业分类",[1]!s_segment_industry_item(公司分析!$D$4,R$5,ROW()-ROW($C$6)),IF($C$3="按产品分类",[1]!s_segment_product_item(公司分析!$D$4,R$5,ROW()-ROW($C$6)),[1]!S_SEGMENT_REGION_ITEM(公司分析!$D$4,R$5,ROW()-ROW($C$6)))) -> 增值服务 | S7: =IF($C$3="按行业分类",[1]!s_segment_industry_sales(公司分析!$D$4,R$5,ROW()-ROW($C$6)),IF($C$3="按产品分类",[1]!s_segment_product_sales(公司分析!$D$4,R$5,ROW()-ROW($C$6)),[1]!S_SEGMENT_REGION_SALES(公司分析!$D$4,R$5,ROW()-ROW($C$6))))/CurrencyUnit -> 99.1008 | T7: =IF($C$3="按行业分类",[1]!s_segment_industry_profit(公司分析!$D$4,R$5,ROW()-ROW($C$6)),IF($C$3="按产品分类",[1]!s_segment_product_profit(公司分析!$D$4,R$5,ROW()-ROW($C$6)),[1]!S_SEGMENT_REGION_PROFIT(公司分析!$D$4,R$5,ROW()-ROW($C$6))))/CurrencyUnit -> 0
C8: =IF($C$3="按行业分类",[1]!s_segment_industry_item(公司分析!$D$4,C$5,ROW()-ROW($C$6)),IF($C$3="按产品分类",[1]!s_segment_product_item(公司分析!$D$4,C$5,ROW()-ROW($C$6)),[1]!S_SEGMENT_REGION_ITEM(公司分析!$D$4,C$5,ROW()-ROW($C$6)))) -> 直播及增值业务 | D8: =IF($C$3="按行业分类",[1]!s_segment_industry_sales(公司分析!$D$4,C$5,ROW()-ROW($C$6)),IF($C$3="按产品分类",[1]!s_segment_product_sales(公司分析!$D$4,C$5,ROW()-ROW($C$6)),[1]!S_SEGMENT_REGION_SALES(公司分析!$D$4,C$5,ROW()-ROW($C$6))))/CurrencyUnit -> 6.17665 | E8: =IF($C$3="按行业分类",[1]!s_segment_industry_profit(公司分析!$D$4,C$5,ROW()-ROW($C$6)),IF($C$3="按产品分类",[1]!s_segment_product_profit(公司分析!$D$4,C$5,ROW()-ROW($C$6)),[1]!S_SEGMENT_REGION_PROFIT(公司分析!$D$4,C$5,ROW()-ROW($C$6))))/CurrencyUnit -> 0 | F8: =IF($C$3="按行业分类",[1]!s_segment_industry_item(公司分析!$D$4,F$5,ROW()-ROW($C$6)),IF($C$3="按产品分类",[1]!s_segment_product_item(公司分析!$D$4,F$5,ROW()-ROW($C$6)),[1]!S_SEGMENT_REGION_ITEM(公司分析!$D$4,F$5,ROW()-ROW($C$6)))) -> 直播及增值业务 | G8: =IF($C$3="按行业分类",[1]!s_segment_industry_sales(公司分析!$D$4,F$5,ROW()-ROW($C$6)),IF($C$3="按产品分类",[1]!s_segment_product_sales(公司分析!$D$4,F$5,ROW()-ROW($C$6)),[1]!S_SEGMENT_REGION_SALES(公司分析!$D$4,F$5,ROW()-ROW($C$6))))/CurrencyUnit -> 16.41043 | H8: =IF($C$3="按行业分类",[1]!s_segment_industry_profit(公司分析!$D$4,F$5,ROW()-ROW($C$6)),IF($C$3="按产品分类",[1]!s_segment_product_profit(公司分析!$D$4,F$5,ROW()-ROW($C$6)),[1]!S_SEGMENT_REGION_PROFIT(公司分析!$D$4,F$5,ROW()-ROW($C$6))))/CurrencyUnit -> 0 | I8: =IF($C$3="按行业分类",[1]!s_segment_industry_item(公司分析!$D$4,I$5,ROW()-ROW($C$6)),IF($C$3="按产品分类",[1]!s_segment_product_item(公司分析!$D$4,I$5,ROW()-ROW($C$6)),[1]!S_SEGMENT_REGION_ITEM(公司分析!$D$4,I$5,ROW()-ROW($C$6)))) -> 直播及增值业务 | J8: =IF($C$3="按行业分类",[1]!s_segment_industry_sales(公司分析!$D$4,I$5,ROW()-ROW($C$6)),IF($C$3="按产品分类",[1]!s_segment_product_sales(公司分析!$D$4,I$5,ROW()-ROW($C$6)),[1]!S_SEGMENT_REGION_SALES(公司分析!$D$4,I$5,ROW()-ROW($C$6))))/CurrencyUnit -> 38.45663 | K8: =IF($C$3="按行业分类",[1]!s_segment_industry_profit(公司分析!$D$4,I$5,ROW()-ROW($C$6)),IF($C$3="按产品分类",[1]!s_segment_product_profit(公司分析!$D$4,I$5,ROW()-ROW($C$6)),[1]!S_SEGMENT_REGION_PROFIT(公司分析!$D$4,I$5,ROW()-ROW($C$6))))/CurrencyUnit -> 0 | L8: =IF($C$3="按行业分类",[1]!s_segment_industry_item(公司分析!$D$4,L$5,ROW()-ROW($C$6)),IF($C$3="按产品分类",[1]!s_segment_product_item(公司分析!$D$4,L$5,ROW()-ROW($C$6)),[1]!S_SEGMENT_REGION_ITEM(公司分析!$D$4,L$5,ROW()-ROW($C$6)))) -> 移动游戏 | M8: =IF($C$3="按行业分类",[1]!s_segment_industry_sales(公司分析!$D$4,L$5,ROW()-ROW($C$6)),IF($C$3="按产品分类",[1]!s_segment_product_sales(公司分析!$D$4,L$5,ROW()-ROW($C$6)),[1]!S_SEGMENT_REGION_SALES(公司分析!$D$4,L$5,ROW()-ROW($C$6))))/CurrencyUnit -> 50.90926 | N8: =IF($C$3="按行业分类",[1]!s_segment_industry_profit(公司分析!$D$4,L$5,ROW()-ROW($C$6)),IF($C$3="按产品分类",[1]!s_segment_product_profit(公司分析!$D$4,L$5,ROW()-ROW($C$6)),[1]!S_SEGMENT_REGION_PROFIT(公司分析!$D$4,L$5,ROW()-ROW($C$6))))/CurrencyUnit -> 0 | O8: =IF($C$3="按行业分类",[1]!s_segment_industry_item(公司分析!$D$4,O$5,ROW()-ROW($C$6)),IF($C$3="按产品分类",[1]!s_segment_product_item(公司分析!$D$4,O$5,ROW()-ROW($C$6)),[1]!S_SEGMENT_REGION_ITEM(公司分析!$D$4,O$5,ROW()-ROW($C$6)))) -> 广告收入 | P8: =IF($C$3="按行业分类",[1]!s_segment_industry_sales(公司分析!$D$4,O$5,ROW()-ROW($C$6)),IF($C$3="按产品分类",[1]!s_segment_product_sales(公司分析!$D$4,O$5,ROW()-ROW($C$6)),[1]!S_SEGMENT_REGION_SALES(公司分析!$D$4,O$5,ROW()-ROW($C$6))))/CurrencyUnit -> 50.66212 | Q8: =IF($C$3="按行业分类",[1]!s_segment_industry_profit(公司分析!$D$4,O$5,ROW()-ROW($C$6)),IF($C$3="按产品分类",[1]!s_segment_product_profit(公司分析!$D$4,O$5,ROW()-ROW($C$6)),[1]!S_SEGMENT_REGION_PROFIT(公司分析!$D$4,O$5,ROW()-ROW($C$6))))/CurrencyUnit -> 0 | R8: =IF($C$3="按行业分类",[1]!s_segment_industry_item(公司分析!$D$4,R$5,ROW()-ROW($C$6)),IF($C$3="按产品分类",[1]!s_segment_product_item(公司分析!$D$4,R$5,ROW()-ROW($C$6)),[1]!S_SEGMENT_REGION_ITEM(公司分析!$D$4,R$5,ROW()-ROW($C$6)))) -> 广告收入 | S8: =IF($C$3="按行业分类",[1]!s_segment_industry_sales(公司分析!$D$4,R$5,ROW()-ROW($C$6)),IF($C$3="按产品分类",[1]!s_segment_product_sales(公司分析!$D$4,R$5,ROW()-ROW($C$6)),[1]!S_SEGMENT_REGION_SALES(公司分析!$D$4,R$5,ROW()-ROW($C$6))))/CurrencyUnit -> 64.1204 | T8: =IF($C$3="按行业分类",[1]!s_segment_industry_profit(公司分析!$D$4,R$5,ROW()-ROW($C$6)),IF($C$3="按产品分类",[1]!s_segment_product_profit(公司分析!$D$4,R$5,ROW()-ROW($C$6)),[1]!S_SEGMENT_REGION_PROFIT(公司分析!$D$4,R$5,ROW()-ROW($C$6))))/CurrencyUnit -> 0
C9: =IF($C$3="按行业分类",[1]!s_segment_industry_item(公司分析!$D$4,C$5,ROW()-ROW($C$6)),IF($C$3="按产品分类",[1]!s_segment_product_item(公司分析!$D$4,C$5,ROW()-ROW($C$6)),[1]!S_SEGMENT_REGION_ITEM(公司分析!$D$4,C$5,ROW()-ROW($C$6)))) -> 广告收入 | D9: =IF($C$3="按行业分类",[1]!s_segment_industry_sales(公司分析!$D$4,C$5,ROW()-ROW($C$6)),IF($C$3="按产品分类",[1]!s_segment_product_sales(公司分析!$D$4,C$5,ROW()-ROW($C$6)),[1]!S_SEGMENT_REGION_SALES(公司分析!$D$4,C$5,ROW()-ROW($C$6))))/CurrencyUnit -> 2.80235 | E9: =IF($C$3="按行业分类",[1]!s_segment_industry_profit(公司分析!$D$4,C$5,ROW()-ROW($C$6)),IF($C$3="按产品分类",[1]!s_segment_product_profit(公司分析!$D$4,C$5,ROW()-ROW($C$6)),[1]!S_SEGMENT_REGION_PROFIT(公司分析!$D$4,C$5,ROW()-ROW($C$6))))/CurrencyUnit -> 0 | F9: =IF($C$3="按行业分类",[1]!s_segment_industry_item(公司分析!$D$4,F$5,ROW()-ROW($C$6)),IF($C$3="按产品分类",[1]!s_segment_product_item(公司分析!$D$4,F$5,ROW()-ROW($C$6)),[1]!S_SEGMENT_REGION_ITEM(公司分析!$D$4,F$5,ROW()-ROW($C$6)))) -> 广告收入 | G9: =IF($C$3="按行业分类",[1]!s_segment_industry_sales(公司分析!$D$4,F$5,ROW()-ROW($C$6)),IF($C$3="按产品分类",[1]!s_segment_product_sales(公司分析!$D$4,F$5,ROW()-ROW($C$6)),[1]!S_SEGMENT_REGION_SALES(公司分析!$D$4,F$5,ROW()-ROW($C$6))))/CurrencyUnit -> 8.17016 | H9: =IF($C$3="按行业分类",[1]!s_segment_industry_profit(公司分析!$D$4,F$5,ROW()-ROW($C$6)),IF($C$3="按产品分类",[1]!s_segment_product_profit(公司分析!$D$4,F$5,ROW()-ROW($C$6)),[1]!S_SEGMENT_REGION_PROFIT(公司分析!$D$4,F$5,ROW()-ROW($C$6))))/CurrencyUnit -> 0 | I9: =IF($C$3="按行业分类",[1]!s_segment_industry_item(公司分析!$D$4,I$5,ROW()-ROW($C$6)),IF($C$3="按产品分类",[1]!s_segment_product_item(公司分析!$D$4,I$5,ROW()-ROW($C$6)),[1]!S_SEGMENT_REGION_ITEM(公司分析!$D$4,I$5,ROW()-ROW($C$6)))) -> 广告收入 | J9: =IF($C$3="按行业分类",[1]!s_segment_industry_sales(公司分析!$D$4,I$5,ROW()-ROW($C$6)),IF($C$3="按产品分类",[1]!s_segment_product_sales(公司分析!$D$4,I$5,ROW()-ROW($C$6)),[1]!S_SEGMENT_REGION_SALES(公司分析!$D$4,I$5,ROW()-ROW($C$6))))/CurrencyUnit -> 18.42772 | K9: =IF($C$3="按行业分类",[1]!s_segment_industry_profit(公司分析!$D$4,I$5,ROW()-ROW($C$6)),IF($C$3="按产品分类",[1]!s_segment_product_profit(公司分析!$D$4,I$5,ROW()-ROW($C$6)),[1]!S_SEGMENT_REGION_PROFIT(公司分析!$D$4,I$5,ROW()-ROW($C$6))))/CurrencyUnit -> 0 | L9: =IF($C$3="按行业分类",[1]!s_segment_industry_item(公司分析!$D$4,L$5,ROW()-ROW($C$6)),IF($C$3="按产品分类",[1]!s_segment_product_item(公司分析!$D$4,L$5,ROW()-ROW($C$6)),[1]!S_SEGMENT_REGION_ITEM(公司分析!$D$4,L$5,ROW()-ROW($C$6)))) -> 广告收入 | M9: =IF($C$3="按行业分类",[1]!s_segment_industry_sales(公司分析!$D$4,L$5,ROW()-ROW($C$6)),IF($C$3="按产品分类",[1]!s_segment_product_sales(公司分析!$D$4,L$5,ROW()-ROW($C$6)),[1]!S_SEGMENT_REGION_SALES(公司分析!$D$4,L$5,ROW()-ROW($C$6))))/CurrencyUnit -> 45.23421 | N9: =IF($C$3="按行业分类",[1]!s_segment_industry_profit(公司分析!$D$4,L$5,ROW()-ROW($C$6)),IF($C$3="按产品分类",[1]!s_segment_product_profit(公司分析!$D$4,L$5,ROW()-ROW($C$6)),[1]!S_SEGMENT_REGION_PROFIT(公司分析!$D$4,L$5,ROW()-ROW($C$6))))/CurrencyUnit -> 0 | O9: =IF($C$3="按行业分类",[1]!s_segment_industry_item(公司分析!$D$4,O$5,ROW()-ROW($C$6)),IF($C$3="按产品分类",[1]!s_segment_product_item(公司分析!$D$4,O$5,ROW()-ROW($C$6)),[1]!S_SEGMENT_REGION_ITEM(公司分析!$D$4,O$5,ROW()-ROW($C$6)))) -> 移动游戏 | P9: =IF($C$3="按行业分类",[1]!s_segment_industry_sales(公司分析!$D$4,O$5,ROW()-ROW($C$6)),IF($C$3="按产品分类",[1]!s_segment_product_sales(公司分析!$D$4,O$5,ROW()-ROW($C$6)),[1]!S_SEGMENT_REGION_SALES(公司分析!$D$4,O$5,ROW()-ROW($C$6))))/CurrencyUnit -> 50.2129 | Q9: =IF($C$3="按行业分类",[1]!s_segment_industry_profit(公司分析!$D$4,O$5,ROW()-ROW($C$6)),IF($C$3="按产品分类",[1]!s_segment_product_profit(公司分析!$D$4,O$5,ROW()-ROW($C$6)),[1]!S_SEGMENT_REGION_PROFIT(公司分析!$D$4,O$5,ROW()-ROW($C$6))))/CurrencyUnit -> 0 | R9: =IF($C$3="按行业分类",[1]!s_segment_industry_item(公司分析!$D$4,R$5,ROW()-ROW($C$6)),IF($C$3="按产品分类",[1]!s_segment_product_item(公司分析!$D$4,R$5,ROW()-ROW($C$6)),[1]!S_SEGMENT_REGION_ITEM(公司分析!$D$4,R$5,ROW()-ROW($C$6)))) -> 移动游戏 | S9: =IF($C$3="按行业分类",[1]!s_segment_industry_sales(公司分析!$D$4,R$5,ROW()-ROW($C$6)),IF($C$3="按产品分类",[1]!s_segment_product_sales(公司分析!$D$4,R$5,ROW()-ROW($C$6)),[1]!S_SEGMENT_REGION_SALES(公司分析!$D$4,R$5,ROW()-ROW($C$6))))/CurrencyUnit -> 40.21137 | T9: =IF($C$3="按行业分类",[1]!s_segment_industry_profit(公司分析!$D$4,R$5,ROW()-ROW($C$6)),IF($C$3="按产品分类",[1]!s_segment_product_profit(公司分析!$D$4,R$5,ROW()-ROW($C$6)),[1]!S_SEGMENT_REGION_PROFIT(公司分析!$D$4,R$5,ROW()-ROW($C$6))))/CurrencyUnit -> 0
C10: =IF($C$3="按行业分类",[1]!s_segment_industry_item(公司分析!$D$4,C$5,ROW()-ROW($C$6)),IF($C$3="按产品分类",[1]!s_segment_product_item(公司分析!$D$4,C$5,ROW()-ROW($C$6)),[1]!S_SEGMENT_REGION_ITEM(公司分析!$D$4,C$5,ROW()-ROW($C$6)))) -> 其他业务 | D10: =IF($C$3="按行业分类",[1]!s_segment_industry_sales(公司分析!$D$4,C$5,ROW()-ROW($C$6)),IF($C$3="按产品分类",[1]!s_segment_product_sales(公司分析!$D$4,C$5,ROW()-ROW($C$6)),[1]!S_SEGMENT_REGION_SALES(公司分析!$D$4,C$5,ROW()-ROW($C$6))))/CurrencyUnit -> 2.19979 | E10: =IF($C$3="按行业分类",[1]!s_segment_industry_profit(公司分析!$D$4,C$5,ROW()-ROW($C$6)),IF($C$3="按产品分类",[1]!s_segment_product_profit(公司分析!$D$4,C$5,ROW()-ROW($C$6)),[1]!S_SEGMENT_REGION_PROFIT(公司分析!$D$4,C$5,ROW()-ROW($C$6))))/CurrencyUnit -> 0 | F10: =IF($C$3="按行业分类",[1]!s_segment_industry_item(公司分析!$D$4,F$5,ROW()-ROW($C$6)),IF($C$3="按产品分类",[1]!s_segment_product_item(公司分析!$D$4,F$5,ROW()-ROW($C$6)),[1]!S_SEGMENT_REGION_ITEM(公司分析!$D$4,F$5,ROW()-ROW($C$6)))) -> 其他业务 | G10: =IF($C$3="按行业分类",[1]!s_segment_industry_sales(公司分析!$D$4,F$5,ROW()-ROW($C$6)),IF($C$3="按产品分类",[1]!s_segment_product_sales(公司分析!$D$4,F$5,ROW()-ROW($C$6)),[1]!S_SEGMENT_REGION_SALES(公司分析!$D$4,F$5,ROW()-ROW($C$6))))/CurrencyUnit -> 7.22054 | H10: =IF($C$3="按行业分类",[1]!s_segment_industry_profit(公司分析!$D$4,F$5,ROW()-ROW($C$6)),IF($C$3="按产品分类",[1]!s_segment_product_profit(公司分析!$D$4,F$5,ROW()-ROW($C$6)),[1]!S_SEGMENT_REGION_PROFIT(公司分析!$D$4,F$5,ROW()-ROW($C$6))))/CurrencyUnit -> 0 | I10: =IF($C$3="按行业分类",[1]!s_segment_industry_item(公司分析!$D$4,I$5,ROW()-ROW($C$6)),IF($C$3="按产品分类",[1]!s_segment_product_item(公司分析!$D$4,I$5,ROW()-ROW($C$6)),[1]!S_SEGMENT_REGION_ITEM(公司分析!$D$4,I$5,ROW()-ROW($C$6)))) -> 其他业务 | J10: =IF($C$3="按行业分类",[1]!s_segment_industry_sales(公司分析!$D$4,I$5,ROW()-ROW($C$6)),IF($C$3="按产品分类",[1]!s_segment_product_sales(公司分析!$D$4,I$5,ROW()-ROW($C$6)),[1]!S_SEGMENT_REGION_SALES(公司分析!$D$4,I$5,ROW()-ROW($C$6))))/CurrencyUnit -> 15.07159 | K10: =IF($C$3="按行业分类",[1]!s_segment_industry_profit(公司分析!$D$4,I$5,ROW()-ROW($C$6)),IF($C$3="按产品分类",[1]!s_segment_product_profit(公司分析!$D$4,I$5,ROW()-ROW($C$6)),[1]!S_SEGMENT_REGION_PROFIT(公司分析!$D$4,I$5,ROW()-ROW($C$6))))/CurrencyUnit -> 0 | L10: =IF($C$3="按行业分类",[1]!s_segment_industry_item(公司分析!$D$4,L$5,ROW()-ROW($C$6)),IF($C$3="按产品分类",[1]!s_segment_product_item(公司分析!$D$4,L$5,ROW()-ROW($C$6)),[1]!S_SEGMENT_REGION_ITEM(公司分析!$D$4,L$5,ROW()-ROW($C$6)))) -> 其他业务 | M10: =IF($C$3="按行业分类",[1]!s_segment_industry_sales(公司分析!$D$4,L$5,ROW()-ROW($C$6)),IF($C$3="按产品分类",[1]!s_segment_product_sales(公司分析!$D$4,L$5,ROW()-ROW($C$6)),[1]!S_SEGMENT_REGION_SALES(公司分析!$D$4,L$5,ROW()-ROW($C$6))))/CurrencyUnit -> 28.34451 | N10: =IF($C$3="按行业分类",[1]!s_segment_industry_profit(公司分析!$D$4,L$5,ROW()-ROW($C$6)),IF($C$3="按产品分类",[1]!s_segment_product_profit(公司分析!$D$4,L$5,ROW()-ROW($C$6)),[1]!S_SEGMENT_REGION_PROFIT(公司分析!$D$4,L$5,ROW()-ROW($C$6))))/CurrencyUnit -> 0 | O10: =IF($C$3="按行业分类",[1]!s_segment_industry_item(公司分析!$D$4,O$5,ROW()-ROW($C$6)),IF($C$3="按产品分类",[1]!s_segment_product_item(公司分析!$D$4,O$5,ROW()-ROW($C$6)),[1]!S_SEGMENT_REGION_ITEM(公司分析!$D$4,O$5,ROW()-ROW($C$6)))) -> 其他业务 | P10: =IF($C$3="按行业分类",[1]!s_segment_industry_sales(公司分析!$D$4,O$5,ROW()-ROW($C$6)),IF($C$3="按产品分类",[1]!s_segment_product_sales(公司分析!$D$4,O$5,ROW()-ROW($C$6)),[1]!S_SEGMENT_REGION_SALES(公司分析!$D$4,O$5,ROW()-ROW($C$6))))/CurrencyUnit -> 30.96495 | Q10: =IF($C$3="按行业分类",[1]!s_segment_industry_profit(公司分析!$D$4,O$5,ROW()-ROW($C$6)),IF($C$3="按产品分类",[1]!s_segment_product_profit(公司分析!$D$4,O$5,ROW()-ROW($C$6)),[1]!S_SEGMENT_REGION_PROFIT(公司分析!$D$4,O$5,ROW()-ROW($C$6))))/CurrencyUnit -> 0 | R10: =IF($C$3="按行业分类",[1]!s_segment_industry_item(公司分析!$D$4,R$5,ROW()-ROW($C$6)),IF($C$3="按产品分类",[1]!s_segment_product_item(公司分析!$D$4,R$5,ROW()-ROW($C$6)),[1]!S_SEGMENT_REGION_ITEM(公司分析!$D$4,R$5,ROW()-ROW($C$6)))) -> 衍生工具及其他,净值 | S10: =IF($C$3="按行业分类",[1]!s_segment_industry_sales(公司分析!$D$4,R$5,ROW()-ROW($C$6)),IF($C$3="按产品分类",[1]!s_segment_product_sales(公司分析!$D$4,R$5,ROW()-ROW($C$6)),[1]!S_SEGMENT_REGION_SALES(公司分析!$D$4,R$5,ROW()-ROW($C$6))))/CurrencyUnit -> 21.8473 | T10: =IF($C$3="按行业分类",[1]!s_segment_industry_profit(公司分析!$D$4,R$5,ROW()-ROW($C$6)),IF($C$3="按产品分类",[1]!s_segment_product_profit(公司分析!$D$4,R$5,ROW()-ROW($C$6)),[1]!S_SEGMENT_REGION_PROFIT(公司分析!$D$4,R$5,ROW()-ROW($C$6))))/CurrencyUnit -> 0
C11: =IF($C$3="按行业分类",[1]!s_segment_industry_item(公司分析!$D$4,C$5,ROW()-ROW($C$6)),IF($C$3="按产品分类",[1]!s_segment_product_item(公司分析!$D$4,C$5,ROW()-ROW($C$6)),[1]!S_SEGMENT_REGION_ITEM(公司分析!$D$4,C$5,ROW()-ROW($C$6)))) -> 0 | D11: =IF($C$3="按行业分类",[1]!s_segment_industry_sales(公司分析!$D$4,C$5,ROW()-ROW($C$6)),IF($C$3="按产品分类",[1]!s_segment_product_sales(公司分析!$D$4,C$5,ROW()-ROW($C$6)),[1]!S_SEGMENT_REGION_SALES(公司分析!$D$4,C$5,ROW()-ROW($C$6))))/CurrencyUnit -> 0 | E11: =IF($C$3="按行业分类",[1]!s_segment_industry_profit(公司分析!$D$4,C$5,ROW()-ROW($C$6)),IF($C$3="按产品分类",[1]!s_segment_product_profit(公司分析!$D$4,C$5,ROW()-ROW($C$6)),[1]!S_SEGMENT_REGION_PROFIT(公司分析!$D$4,C$5,ROW()-ROW($C$6))))/CurrencyUnit -> 0 | F11: =IF($C$3="按行业分类",[1]!s_segment_industry_item(公司分析!$D$4,F$5,ROW()-ROW($C$6)),IF($C$3="按产品分类",[1]!s_segment_product_item(公司分析!$D$4,F$5,ROW()-ROW($C$6)),[1]!S_SEGMENT_REGION_ITEM(公司分析!$D$4,F$5,ROW()-ROW($C$6)))) -> 0 | G11: =IF($C$3="按行业分类",[1]!s_segment_industry_sales(公司分析!$D$4,F$5,ROW()-ROW($C$6)),IF($C$3="按产品分类",[1]!s_segment_product_sales(公司分析!$D$4,F$5,ROW()-ROW($C$6)),[1]!S_SEGMENT_REGION_SALES(公司分析!$D$4,F$5,ROW()-ROW($C$6))))/CurrencyUnit -> 0 | H11: =IF($C$3="按行业分类",[1]!s_segment_industry_profit(公司分析!$D$4,F$5,ROW()-ROW($C$6)),IF($C$3="按产品分类",[1]!s_segment_product_profit(公司分析!$D$4,F$5,ROW()-ROW($C$6)),[1]!S_SEGMENT_REGION_PROFIT(公司分析!$D$4,F$5,ROW()-ROW($C$6))))/CurrencyUnit -> 0 | I11: =IF($C$3="按行业分类",[1]!s_segment_industry_item(公司分析!$D$4,I$5,ROW()-ROW($C$6)),IF($C$3="按产品分类",[1]!s_segment_product_item(公司分析!$D$4,I$5,ROW()-ROW($C$6)),[1]!S_SEGMENT_REGION_ITEM(公司分析!$D$4,I$5,ROW()-ROW($C$6)))) -> 0 | J11: =IF($C$3="按行业分类",[1]!s_segment_industry_sales(公司分析!$D$4,I$5,ROW()-ROW($C$6)),IF($C$3="按产品分类",[1]!s_segment_product_sales(公司分析!$D$4,I$5,ROW()-ROW($C$6)),[1]!S_SEGMENT_REGION_SALES(公司分析!$D$4,I$5,ROW()-ROW($C$6))))/CurrencyUnit -> 0 | K11: =IF($C$3="按行业分类",[1]!s_segment_industry_profit(公司分析!$D$4,I$5,ROW()-ROW($C$6)),IF($C$3="按产品分类",[1]!s_segment_product_profit(公司分析!$D$4,I$5,ROW()-ROW($C$6)),[1]!S_SEGMENT_REGION_PROFIT(公司分析!$D$4,I$5,ROW()-ROW($C$6))))/CurrencyUnit -> 0 | L11: =IF($C$3="按行业分类",[1]!s_segment_industry_item(公司分析!$D$4,L$5,ROW()-ROW($C$6)),IF($C$3="按产品分类",[1]!s_segment_product_item(公司分析!$D$4,L$5,ROW()-ROW($C$6)),[1]!S_SEGMENT_REGION_ITEM(公司分析!$D$4,L$5,ROW()-ROW($C$6)))) -> 0 | M11: =IF($C$3="按行业分类",[1]!s_segment_industry_sales(公司分析!$D$4,L$5,ROW()-ROW($C$6)),IF($C$3="按产品分类",[1]!s_segment_product_sales(公司分析!$D$4,L$5,ROW()-ROW($C$6)),[1]!S_SEGMENT_REGION_SALES(公司分析!$D$4,L$5,ROW()-ROW($C$6))))/CurrencyUnit -> 0 | N11: =IF($C$3="按行业分类",[1]!s_segment_industry_profit(公司分析!$D$4,L$5,ROW()-ROW($C$6)),IF($C$3="按产品分类",[1]!s_segment_product_profit(公司分析!$D$4,L$5,ROW()-ROW($C$6)),[1]!S_SEGMENT_REGION_PROFIT(公司分析!$D$4,L$5,ROW()-ROW($C$6))))/CurrencyUnit -> 0 | O11: =IF($C$3="按行业分类",[1]!s_segment_industry_item(公司分析!$D$4,O$5,ROW()-ROW($C$6)),IF($C$3="按产品分类",[1]!s_segment_product_item(公司分析!$D$4,O$5,ROW()-ROW($C$6)),[1]!S_SEGMENT_REGION_ITEM(公司分析!$D$4,O$5,ROW()-ROW($C$6)))) -> 0 | P11: =IF($C$3="按行业分类",[1]!s_segment_industry_sales(公司分析!$D$4,O$5,ROW()-ROW($C$6)),IF($C$3="按产品分类",[1]!s_segment_product_sales(公司分析!$D$4,O$5,ROW()-ROW($C$6)),[1]!S_SEGMENT_REGION_SALES(公司分析!$D$4,O$5,ROW()-ROW($C$6))))/CurrencyUnit -> 0 | Q11: =IF($C$3="按行业分类",[1]!s_segment_industry_profit(公司分析!$D$4,O$5,ROW()-ROW($C$6)),IF($C$3="按产品分类",[1]!s_segment_product_profit(公司分析!$D$4,O$5,ROW()-ROW($C$6)),[1]!S_SEGMENT_REGION_PROFIT(公司分析!$D$4,O$5,ROW()-ROW($C$6))))/CurrencyUnit -> 0 | R11: =IF($C$3="按行业分类",[1]!s_segment_industry_item(公司分析!$D$4,R$5,ROW()-ROW($C$6)),IF($C$3="按产品分类",[1]!s_segment_product_item(公司分析!$D$4,R$5,ROW()-ROW($C$6)),[1]!S_SEGMENT_REGION_ITEM(公司分析!$D$4,R$5,ROW()-ROW($C$6)))) -> 0 | S11: =IF($C$3="按行业分类",[1]!s_segment_industry_sales(公司分析!$D$4,R$5,ROW()-ROW($C$6)),IF($C$3="按产品分类",[1]!s_segment_product_sales(公司分析!$D$4,R$5,ROW()-ROW($C$6)),[1]!S_SEGMENT_REGION_SALES(公司分析!$D$4,R$5,ROW()-ROW($C$6))))/CurrencyUnit -> 0 | T11: =IF($C$3="按行业分类",[1]!s_segment_industry_profit(公司分析!$D$4,R$5,ROW()-ROW($C$6)),IF($C$3="按产品分类",[1]!s_segment_product_profit(公司分析!$D$4,R$5,ROW()-ROW($C$6)),[1]!S_SEGMENT_REGION_PROFIT(公司分析!$D$4,R$5,ROW()-ROW($C$6))))/CurrencyUnit -> 0
C12: =IF($C$3="按行业分类",[1]!s_segment_industry_item(公司分析!$D$4,C$5,ROW()-ROW($C$6)),IF($C$3="按产品分类",[1]!s_segment_product_item(公司分析!$D$4,C$5,ROW()-ROW($C$6)),[1]!S_SEGMENT_REGION_ITEM(公司分析!$D$4,C$5,ROW()-ROW($C$6)))) -> 0 | D12: =IF($C$3="按行业分类",[1]!s_segment_industry_sales(公司分析!$D$4,C$5,ROW()-ROW($C$6)),IF($C$3="按产品分类",[1]!s_segment_product_sales(公司分析!$D$4,C$5,ROW()-ROW($C$6)),[1]!S_SEGMENT_REGION_SALES(公司分析!$D$4,C$5,ROW()-ROW($C$6))))/CurrencyUnit -> 0 | E12: =IF($C$3="按行业分类",[1]!s_segment_industry_profit(公司分析!$D$4,C$5,ROW()-ROW($C$6)),IF($C$3="按产品分类",[1]!s_segment_product_profit(公司分析!$D$4,C$5,ROW()-ROW($C$6)),[1]!S_SEGMENT_REGION_PROFIT(公司分析!$D$4,C$5,ROW()-ROW($C$6))))/CurrencyUnit -> 0 | F12: =IF($C$3="按行业分类",[1]!s_segment_industry_item(公司分析!$D$4,F$5,ROW()-ROW($C$6)),IF($C$3="按产品分类",[1]!s_segment_product_item(公司分析!$D$4,F$5,ROW()-ROW($C$6)),[1]!S_SEGMENT_REGION_ITEM(公司分析!$D$4,F$5,ROW()-ROW($C$6)))) -> 0 | G12: =IF($C$3="按行业分类",[1]!s_segment_industry_sales(公司分析!$D$4,F$5,ROW()-ROW($C$6)),IF($C$3="按产品分类",[1]!s_segment_product_sales(公司分析!$D$4,F$5,ROW()-ROW($C$6)),[1]!S_SEGMENT_REGION_SALES(公司分析!$D$4,F$5,ROW()-ROW($C$6))))/CurrencyUnit -> 0 | H12: =IF($C$3="按行业分类",[1]!s_segment_industry_profit(公司分析!$D$4,F$5,ROW()-ROW($C$6)),IF($C$3="按产品分类",[1]!s_segment_product_profit(公司分析!$D$4,F$5,ROW()-ROW($C$6)),[1]!S_SEGMENT_REGION_PROFIT(公司分析!$D$4,F$5,ROW()-ROW($C$6))))/CurrencyUnit -> 0 | I12: =IF($C$3="按行业分类",[1]!s_segment_industry_item(公司分析!$D$4,I$5,ROW()-ROW($C$6)),IF($C$3="按产品分类",[1]!s_segment_product_item(公司分析!$D$4,I$5,ROW()-ROW($C$6)),[1]!S_SEGMENT_REGION_ITEM(公司分析!$D$4,I$5,ROW()-ROW($C$6)))) -> 0 | J12: =IF($C$3="按行业分类",[1]!s_segment_industry_sales(公司分析!$D$4,I$5,ROW()-ROW($C$6)),IF($C$3="按产品分类",[1]!s_segment_product_sales(公司分析!$D$4,I$5,ROW()-ROW($C$6)),[1]!S_SEGMENT_REGION_SALES(公司分析!$D$4,I$5,ROW()-ROW($C$6))))/CurrencyUnit -> 0 | K12: =IF($C$3="按行业分类",[1]!s_segment_industry_profit(公司分析!$D$4,I$5,ROW()-ROW($C$6)),IF($C$3="按产品分类",[1]!s_segment_product_profit(公司分析!$D$4,I$5,ROW()-ROW($C$6)),[1]!S_SEGMENT_REGION_PROFIT(公司分析!$D$4,I$5,ROW()-ROW($C$6))))/CurrencyUnit -> 0 | L12: =IF($C$3="按行业分类",[1]!s_segment_industry_item(公司分析!$D$4,L$5,ROW()-ROW($C$6)),IF($C$3="按产品分类",[1]!s_segment_product_item(公司分析!$D$4,L$5,ROW()-ROW($C$6)),[1]!S_SEGMENT_REGION_ITEM(公司分析!$D$4,L$5,ROW()-ROW($C$6)))) -> 0 | M12: =IF($C$3="按行业分类",[1]!s_segment_industry_sales(公司分析!$D$4,L$5,ROW()-ROW($C$6)),IF($C$3="按产品分类",[1]!s_segment_product_sales(公司分析!$D$4,L$5,ROW()-ROW($C$6)),[1]!S_SEGMENT_REGION_SALES(公司分析!$D$4,L$5,ROW()-ROW($C$6))))/CurrencyUnit -> 0 | N12: =IF($C$3="按行业分类",[1]!s_segment_industry_profit(公司分析!$D$4,L$5,ROW()-ROW($C$6)),IF($C$3="按产品分类",[1]!s_segment_product_profit(公司分析!$D$4,L$5,ROW()-ROW($C$6)),[1]!S_SEGMENT_REGION_PROFIT(公司分析!$D$4,L$5,ROW()-ROW($C$6))))/CurrencyUnit -> 0 | O12: =IF($C$3="按行业分类",[1]!s_segment_industry_item(公司分析!$D$4,O$5,ROW()-ROW($C$6)),IF($C$3="按产品分类",[1]!s_segment_product_item(公司分析!$D$4,O$5,ROW()-ROW($C$6)),[1]!S_SEGMENT_REGION_ITEM(公司分析!$D$4,O$5,ROW()-ROW($C$6)))) -> 0 | P12: =IF($C$3="按行业分类",[1]!s_segment_industry_sales(公司分析!$D$4,O$5,ROW()-ROW($C$6)),IF($C$3="按产品分类",[1]!s_segment_product_sales(公司分析!$D$4,O$5,ROW()-ROW($C$6)),[1]!S_SEGMENT_REGION_SALES(公司分析!$D$4,O$5,ROW()-ROW($C$6))))/CurrencyUnit -> 0 | Q12: =IF($C$3="按行业分类",[1]!s_segment_industry_profit(公司分析!$D$4,O$5,ROW()-ROW($C$6)),IF($C$3="按产品分类",[1]!s_segment_product_profit(公司分析!$D$4,O$5,ROW()-ROW($C$6)),[1]!S_SEGMENT_REGION_PROFIT(公司分析!$D$4,O$5,ROW()-ROW($C$6))))/CurrencyUnit -> 0 | R12: =IF($C$3="按行业分类",[1]!s_segment_industry_item(公司分析!$D$4,R$5,ROW()-ROW($C$6)),IF($C$3="按产品分类",[1]!s_segment_product_item(公司分析!$D$4,R$5,ROW()-ROW($C$6)),[1]!S_SEGMENT_REGION_ITEM(公司分析!$D$4,R$5,ROW()-ROW($C$6)))) -> 0 | S12: =IF($C$3="按行业分类",[1]!s_segment_industry_sales(公司分析!$D$4,R$5,ROW()-ROW($C$6)),IF($C$3="按产品分类",[1]!s_segment_product_sales(公司分析!$D$4,R$5,ROW()-ROW($C$6)),[1]!S_SEGMENT_REGION_SALES(公司分析!$D$4,R$5,ROW()-ROW($C$6))))/CurrencyUnit -> 0 | T12: =IF($C$3="按行业分类",[1]!s_segment_industry_profit(公司分析!$D$4,R$5,ROW()-ROW($C$6)),IF($C$3="按产品分类",[1]!s_segment_product_profit(公司分析!$D$4,R$5,ROW()-ROW($C$6)),[1]!S_SEGMENT_REGION_PROFIT(公司分析!$D$4,R$5,ROW()-ROW($C$6))))/CurrencyUnit -> 0
C13: =IF($C$3="按行业分类",[1]!s_segment_industry_item(公司分析!$D$4,C$5,ROW()-ROW($C$6)),IF($C$3="按产品分类",[1]!s_segment_product_item(公司分析!$D$4,C$5,ROW()-ROW($C$6)),[1]!S_SEGMENT_REGION_ITEM(公司分析!$D$4,C$5,ROW()-ROW($C$6)))) -> 0 | D13: =IF($C$3="按行业分类",[1]!s_segment_industry_sales(公司分析!$D$4,C$5,ROW()-ROW($C$6)),IF($C$3="按产品分类",[1]!s_segment_product_sales(公司分析!$D$4,C$5,ROW()-ROW($C$6)),[1]!S_SEGMENT_REGION_SALES(公司分析!$D$4,C$5,ROW()-ROW($C$6))))/CurrencyUnit -> 0 | E13: =IF($C$3="按行业分类",[1]!s_segment_industry_profit(公司分析!$D$4,C$5,ROW()-ROW($C$6)),IF($C$3="按产品分类",[1]!s_segment_product_profit(公司分析!$D$4,C$5,ROW()-ROW($C$6)),[1]!S_SEGMENT_REGION_PROFIT(公司分析!$D$4,C$5,ROW()-ROW($C$6))))/CurrencyUnit -> 0 | F13: =IF($C$3="按行业分类",[1]!s_segment_industry_item(公司分析!$D$4,F$5,ROW()-ROW($C$6)),IF($C$3="按产品分类",[1]!s_segment_product_item(公司分析!$D$4,F$5,ROW()-ROW($C$6)),[1]!S_SEGMENT_REGION_ITEM(公司分析!$D$4,F$5,ROW()-ROW($C$6)))) -> 0 | G13: =IF($C$3="按行业分类",[1]!s_segment_industry_sales(公司分析!$D$4,F$5,ROW()-ROW($C$6)),IF($C$3="按产品分类",[1]!s_segment_product_sales(公司分析!$D$4,F$5,ROW()-ROW($C$6)),[1]!S_SEGMENT_REGION_SALES(公司分析!$D$4,F$5,ROW()-ROW($C$6))))/CurrencyUnit -> 0 | H13: =IF($C$3="按行业分类",[1]!s_segment_industry_profit(公司分析!$D$4,F$5,ROW()-ROW($C$6)),IF($C$3="按产品分类",[1]!s_segment_product_profit(公司分析!$D$4,F$5,ROW()-ROW($C$6)),[1]!S_SEGMENT_REGION_PROFIT(公司分析!$D$4,F$5,ROW()-ROW($C$6))))/CurrencyUnit -> 0 | I13: =IF($C$3="按行业分类",[1]!s_segment_industry_item(公司分析!$D$4,I$5,ROW()-ROW($C$6)),IF($C$3="按产品分类",[1]!s_segment_product_item(公司分析!$D$4,I$5,ROW()-ROW($C$6)),[1]!S_SEGMENT_REGION_ITEM(公司分析!$D$4,I$5,ROW()-ROW($C$6)))) -> 0 | J13: =IF($C$3="按行业分类",[1]!s_segment_industry_sales(公司分析!$D$4,I$5,ROW()-ROW($C$6)),IF($C$3="按产品分类",[1]!s_segment_product_sales(公司分析!$D$4,I$5,ROW()-ROW($C$6)),[1]!S_SEGMENT_REGION_SALES(公司分析!$D$4,I$5,ROW()-ROW($C$6))))/CurrencyUnit -> 0 | K13: =IF($C$3="按行业分类",[1]!s_segment_industry_profit(公司分析!$D$4,I$5,ROW()-ROW($C$6)),IF($C$3="按产品分类",[1]!s_segment_product_profit(公司分析!$D$4,I$5,ROW()-ROW($C$6)),[1]!S_SEGMENT_REGION_PROFIT(公司分析!$D$4,I$5,ROW()-ROW($C$6))))/CurrencyUnit -> 0 | L13: =IF($C$3="按行业分类",[1]!s_segment_industry_item(公司分析!$D$4,L$5,ROW()-ROW($C$6)),IF($C$3="按产品分类",[1]!s_segment_product_item(公司分析!$D$4,L$5,ROW()-ROW($C$6)),[1]!S_SEGMENT_REGION_ITEM(公司分析!$D$4,L$5,ROW()-ROW($C$6)))) -> 0 | M13: =IF($C$3="按行业分类",[1]!s_segment_industry_sales(公司分析!$D$4,L$5,ROW()-ROW($C$6)),IF($C$3="按产品分类",[1]!s_segment_product_sales(公司分析!$D$4,L$5,ROW()-ROW($C$6)),[1]!S_SEGMENT_REGION_SALES(公司分析!$D$4,L$5,ROW()-ROW($C$6))))/CurrencyUnit -> 0 | N13: =IF($C$3="按行业分类",[1]!s_segment_industry_profit(公司分析!$D$4,L$5,ROW()-ROW($C$6)),IF($C$3="按产品分类",[1]!s_segment_product_profit(公司分析!$D$4,L$5,ROW()-ROW($C$6)),[1]!S_SEGMENT_REGION_PROFIT(公司分析!$D$4,L$5,ROW()-ROW($C$6))))/CurrencyUnit -> 0 | O13: =IF($C$3="按行业分类",[1]!s_segment_industry_item(公司分析!$D$4,O$5,ROW()-ROW($C$6)),IF($C$3="按产品分类",[1]!s_segment_product_item(公司分析!$D$4,O$5,ROW()-ROW($C$6)),[1]!S_SEGMENT_REGION_ITEM(公司分析!$D$4,O$5,ROW()-ROW($C$6)))) -> 0 | P13: =IF($C$3="按行业分类",[1]!s_segment_industry_sales(公司分析!$D$4,O$5,ROW()-ROW($C$6)),IF($C$3="按产品分类",[1]!s_segment_product_sales(公司分析!$D$4,O$5,ROW()-ROW($C$6)),[1]!S_SEGMENT_REGION_SALES(公司分析!$D$4,O$5,ROW()-ROW($C$6))))/CurrencyUnit -> 0 | Q13: =IF($C$3="按行业分类",[1]!s_segment_industry_profit(公司分析!$D$4,O$5,ROW()-ROW($C$6)),IF($C$3="按产品分类",[1]!s_segment_product_profit(公司分析!$D$4,O$5,ROW()-ROW($C$6)),[1]!S_SEGMENT_REGION_PROFIT(公司分析!$D$4,O$5,ROW()-ROW($C$6))))/CurrencyUnit -> 0 | R13: =IF($C$3="按行业分类",[1]!s_segment_industry_item(公司分析!$D$4,R$5,ROW()-ROW($C$6)),IF($C$3="按产品分类",[1]!s_segment_product_item(公司分析!$D$4,R$5,ROW()-ROW($C$6)),[1]!S_SEGMENT_REGION_ITEM(公司分析!$D$4,R$5,ROW()-ROW($C$6)))) -> 0 | S13: =IF($C$3="按行业分类",[1]!s_segment_industry_sales(公司分析!$D$4,R$5,ROW()-ROW($C$6)),IF($C$3="按产品分类",[1]!s_segment_product_sales(公司分析!$D$4,R$5,ROW()-ROW($C$6)),[1]!S_SEGMENT_REGION_SALES(公司分析!$D$4,R$5,ROW()-ROW($C$6))))/CurrencyUnit -> 0 | T13: =IF($C$3="按行业分类",[1]!s_segment_industry_profit(公司分析!$D$4,R$5,ROW()-ROW($C$6)),IF($C$3="按产品分类",[1]!s_segment_product_profit(公司分析!$D$4,R$5,ROW()-ROW($C$6)),[1]!S_SEGMENT_REGION_PROFIT(公司分析!$D$4,R$5,ROW()-ROW($C$6))))/CurrencyUnit -> 0
C14: =IF($C$3="按行业分类",[1]!s_segment_industry_item(公司分析!$D$4,C$5,ROW()-ROW($C$6)),IF($C$3="按产品分类",[1]!s_segment_product_item(公司分析!$D$4,C$5,ROW()-ROW($C$6)),[1]!S_SEGMENT_REGION_ITEM(公司分析!$D$4,C$5,ROW()-ROW($C$6)))) -> 0 | D14: =IF($C$3="按行业分类",[1]!s_segment_industry_sales(公司分析!$D$4,C$5,ROW()-ROW($C$6)),IF($C$3="按产品分类",[1]!s_segment_product_sales(公司分析!$D$4,C$5,ROW()-ROW($C$6)),[1]!S_SEGMENT_REGION_SALES(公司分析!$D$4,C$5,ROW()-ROW($C$6))))/CurrencyUnit -> 0 | E14: =IF($C$3="按行业分类",[1]!s_segment_industry_profit(公司分析!$D$4,C$5,ROW()-ROW($C$6)),IF($C$3="按产品分类",[1]!s_segment_product_profit(公司分析!$D$4,C$5,ROW()-ROW($C$6)),[1]!S_SEGMENT_REGION_PROFIT(公司分析!$D$4,C$5,ROW()-ROW($C$6))))/CurrencyUnit -> 0 | F14: =IF($C$3="按行业分类",[1]!s_segment_industry_item(公司分析!$D$4,F$5,ROW()-ROW($C$6)),IF($C$3="按产品分类",[1]!s_segment_product_item(公司分析!$D$4,F$5,ROW()-ROW($C$6)),[1]!S_SEGMENT_REGION_ITEM(公司分析!$D$4,F$5,ROW()-ROW($C$6)))) -> 0 | G14: =IF($C$3="按行业分类",[1]!s_segment_industry_sales(公司分析!$D$4,F$5,ROW()-ROW($C$6)),IF($C$3="按产品分类",[1]!s_segment_product_sales(公司分析!$D$4,F$5,ROW()-ROW($C$6)),[1]!S_SEGMENT_REGION_SALES(公司分析!$D$4,F$5,ROW()-ROW($C$6))))/CurrencyUnit -> 0 | H14: =IF($C$3="按行业分类",[1]!s_segment_industry_profit(公司分析!$D$4,F$5,ROW()-ROW($C$6)),IF($C$3="按产品分类",[1]!s_segment_product_profit(公司分析!$D$4,F$5,ROW()-ROW($C$6)),[1]!S_SEGMENT_REGION_PROFIT(公司分析!$D$4,F$5,ROW()-ROW($C$6))))/CurrencyUnit -> 0 | I14: =IF($C$3="按行业分类",[1]!s_segment_industry_item(公司分析!$D$4,I$5,ROW()-ROW($C$6)),IF($C$3="按产品分类",[1]!s_segment_product_item(公司分析!$D$4,I$5,ROW()-ROW($C$6)),[1]!S_SEGMENT_REGION_ITEM(公司分析!$D$4,I$5,ROW()-ROW($C$6)))) -> 0 | J14: =IF($C$3="按行业分类",[1]!s_segment_industry_sales(公司分析!$D$4,I$5,ROW()-ROW($C$6)),IF($C$3="按产品分类",[1]!s_segment_product_sales(公司分析!$D$4,I$5,ROW()-ROW($C$6)),[1]!S_SEGMENT_REGION_SALES(公司分析!$D$4,I$5,ROW()-ROW($C$6))))/CurrencyUnit -> 0 | K14: =IF($C$3="按行业分类",[1]!s_segment_industry_profit(公司分析!$D$4,I$5,ROW()-ROW($C$6)),IF($C$3="按产品分类",[1]!s_segment_product_profit(公司分析!$D$4,I$5,ROW()-ROW($C$6)),[1]!S_SEGMENT_REGION_PROFIT(公司分析!$D$4,I$5,ROW()-ROW($C$6))))/CurrencyUnit -> 0 | L14: =IF($C$3="按行业分类",[1]!s_segment_industry_item(公司分析!$D$4,L$5,ROW()-ROW($C$6)),IF($C$3="按产品分类",[1]!s_segment_product_item(公司分析!$D$4,L$5,ROW()-ROW($C$6)),[1]!S_SEGMENT_REGION_ITEM(公司分析!$D$4,L$5,ROW()-ROW($C$6)))) -> 0 | M14: =IF($C$3="按行业分类",[1]!s_segment_industry_sales(公司分析!$D$4,L$5,ROW()-ROW($C$6)),IF($C$3="按产品分类",[1]!s_segment_product_sales(公司分析!$D$4,L$5,ROW()-ROW($C$6)),[1]!S_SEGMENT_REGION_SALES(公司分析!$D$4,L$5,ROW()-ROW($C$6))))/CurrencyUnit -> 0 | N14: =IF($C$3="按行业分类",[1]!s_segment_industry_profit(公司分析!$D$4,L$5,ROW()-ROW($C$6)),IF($C$3="按产品分类",[1]!s_segment_product_profit(公司分析!$D$4,L$5,ROW()-ROW($C$6)),[1]!S_SEGMENT_REGION_PROFIT(公司分析!$D$4,L$5,ROW()-ROW($C$6))))/CurrencyUnit -> 0 | O14: =IF($C$3="按行业分类",[1]!s_segment_industry_item(公司分析!$D$4,O$5,ROW()-ROW($C$6)),IF($C$3="按产品分类",[1]!s_segment_product_item(公司分析!$D$4,O$5,ROW()-ROW($C$6)),[1]!S_SEGMENT_REGION_ITEM(公司分析!$D$4,O$5,ROW()-ROW($C$6)))) -> 0 | P14: =IF($C$3="按行业分类",[1]!s_segment_industry_sales(公司分析!$D$4,O$5,ROW()-ROW($C$6)),IF($C$3="按产品分类",[1]!s_segment_product_sales(公司分析!$D$4,O$5,ROW()-ROW($C$6)),[1]!S_SEGMENT_REGION_SALES(公司分析!$D$4,O$5,ROW()-ROW($C$6))))/CurrencyUnit -> 0 | Q14: =IF($C$3="按行业分类",[1]!s_segment_industry_profit(公司分析!$D$4,O$5,ROW()-ROW($C$6)),IF($C$3="按产品分类",[1]!s_segment_product_profit(公司分析!$D$4,O$5,ROW()-ROW($C$6)),[1]!S_SEGMENT_REGION_PROFIT(公司分析!$D$4,O$5,ROW()-ROW($C$6))))/CurrencyUnit -> 0 | R14: =IF($C$3="按行业分类",[1]!s_segment_industry_item(公司分析!$D$4,R$5,ROW()-ROW($C$6)),IF($C$3="按产品分类",[1]!s_segment_product_item(公司分析!$D$4,R$5,ROW()-ROW($C$6)),[1]!S_SEGMENT_REGION_ITEM(公司分析!$D$4,R$5,ROW()-ROW($C$6)))) -> 0 | S14: =IF($C$3="按行业分类",[1]!s_segment_industry_sales(公司分析!$D$4,R$5,ROW()-ROW($C$6)),IF($C$3="按产品分类",[1]!s_segment_product_sales(公司分析!$D$4,R$5,ROW()-ROW($C$6)),[1]!S_SEGMENT_REGION_SALES(公司分析!$D$4,R$5,ROW()-ROW($C$6))))/CurrencyUnit -> 0 | T14: =IF($C$3="按行业分类",[1]!s_segment_industry_profit(公司分析!$D$4,R$5,ROW()-ROW($C$6)),IF($C$3="按产品分类",[1]!s_segment_product_profit(公司分析!$D$4,R$5,ROW()-ROW($C$6)),[1]!S_SEGMENT_REGION_PROFIT(公司分析!$D$4,R$5,ROW()-ROW($C$6))))/CurrencyUnit -> 0
C15: =IF($C$3="按行业分类",[1]!s_segment_industry_item(公司分析!$D$4,C$5,ROW()-ROW($C$6)),IF($C$3="按产品分类",[1]!s_segment_product_item(公司分析!$D$4,C$5,ROW()-ROW($C$6)),[1]!S_SEGMENT_REGION_ITEM(公司分析!$D$4,C$5,ROW()-ROW($C$6)))) -> 0 | D15: =IF($C$3="按行业分类",[1]!s_segment_industry_sales(公司分析!$D$4,C$5,ROW()-ROW($C$6)),IF($C$3="按产品分类",[1]!s_segment_product_sales(公司分析!$D$4,C$5,ROW()-ROW($C$6)),[1]!S_SEGMENT_REGION_SALES(公司分析!$D$4,C$5,ROW()-ROW($C$6))))/CurrencyUnit -> 0 | E15: =IF($C$3="按行业分类",[1]!s_segment_industry_profit(公司分析!$D$4,C$5,ROW()-ROW($C$6)),IF($C$3="按产品分类",[1]!s_segment_product_profit(公司分析!$D$4,C$5,ROW()-ROW($C$6)),[1]!S_SEGMENT_REGION_PROFIT(公司分析!$D$4,C$5,ROW()-ROW($C$6))))/CurrencyUnit -> 0 | F15: =IF($C$3="按行业分类",[1]!s_segment_industry_item(公司分析!$D$4,F$5,ROW()-ROW($C$6)),IF($C$3="按产品分类",[1]!s_segment_product_item(公司分析!$D$4,F$5,ROW()-ROW($C$6)),[1]!S_SEGMENT_REGION_ITEM(公司分析!$D$4,F$5,ROW()-ROW($C$6)))) -> 0 | G15: =IF($C$3="按行业分类",[1]!s_segment_industry_sales(公司分析!$D$4,F$5,ROW()-ROW($C$6)),IF($C$3="按产品分类",[1]!s_segment_product_sales(公司分析!$D$4,F$5,ROW()-ROW($C$6)),[1]!S_SEGMENT_REGION_SALES(公司分析!$D$4,F$5,ROW()-ROW($C$6))))/CurrencyUnit -> 0 | H15: =IF($C$3="按行业分类",[1]!s_segment_industry_profit(公司分析!$D$4,F$5,ROW()-ROW($C$6)),IF($C$3="按产品分类",[1]!s_segment_product_profit(公司分析!$D$4,F$5,ROW()-ROW($C$6)),[1]!S_SEGMENT_REGION_PROFIT(公司分析!$D$4,F$5,ROW()-ROW($C$6))))/CurrencyUnit -> 0 | I15: =IF($C$3="按行业分类",[1]!s_segment_industry_item(公司分析!$D$4,I$5,ROW()-ROW($C$6)),IF($C$3="按产品分类",[1]!s_segment_product_item(公司分析!$D$4,I$5,ROW()-ROW($C$6)),[1]!S_SEGMENT_REGION_ITEM(公司分析!$D$4,I$5,ROW()-ROW($C$6)))) -> 0 | J15: =IF($C$3="按行业分类",[1]!s_segment_industry_sales(公司分析!$D$4,I$5,ROW()-ROW($C$6)),IF($C$3="按产品分类",[1]!s_segment_product_sales(公司分析!$D$4,I$5,ROW()-ROW($C$6)),[1]!S_SEGMENT_REGION_SALES(公司分析!$D$4,I$5,ROW()-ROW($C$6))))/CurrencyUnit -> 0 | K15: =IF($C$3="按行业分类",[1]!s_segment_industry_profit(公司分析!$D$4,I$5,ROW()-ROW($C$6)),IF($C$3="按产品分类",[1]!s_segment_product_profit(公司分析!$D$4,I$5,ROW()-ROW($C$6)),[1]!S_SEGMENT_REGION_PROFIT(公司分析!$D$4,I$5,ROW()-ROW($C$6))))/CurrencyUnit -> 0 | L15: =IF($C$3="按行业分类",[1]!s_segment_industry_item(公司分析!$D$4,L$5,ROW()-ROW($C$6)),IF($C$3="按产品分类",[1]!s_segment_product_item(公司分析!$D$4,L$5,ROW()-ROW($C$6)),[1]!S_SEGMENT_REGION_ITEM(公司分析!$D$4,L$5,ROW()-ROW($C$6)))) -> 0 | M15: =IF($C$3="按行业分类",[1]!s_segment_industry_sales(公司分析!$D$4,L$5,ROW()-ROW($C$6)),IF($C$3="按产品分类",[1]!s_segment_product_sales(公司分析!$D$4,L$5,ROW()-ROW($C$6)),[1]!S_SEGMENT_REGION_SALES(公司分析!$D$4,L$5,ROW()-ROW($C$6))))/CurrencyUnit -> 0 | N15: =IF($C$3="按行业分类",[1]!s_segment_industry_profit(公司分析!$D$4,L$5,ROW()-ROW($C$6)),IF($C$3="按产品分类",[1]!s_segment_product_profit(公司分析!$D$4,L$5,ROW()-ROW($C$6)),[1]!S_SEGMENT_REGION_PROFIT(公司分析!$D$4,L$5,ROW()-ROW($C$6))))/CurrencyUnit -> 0 | O15: =IF($C$3="按行业分类",[1]!s_segment_industry_item(公司分析!$D$4,O$5,ROW()-ROW($C$6)),IF($C$3="按产品分类",[1]!s_segment_product_item(公司分析!$D$4,O$5,ROW()-ROW($C$6)),[1]!S_SEGMENT_REGION_ITEM(公司分析!$D$4,O$5,ROW()-ROW($C$6)))) -> 0 | P15: =IF($C$3="按行业分类",[1]!s_segment_industry_sales(公司分析!$D$4,O$5,ROW()-ROW($C$6)),IF($C$3="按产品分类",[1]!s_segment_product_sales(公司分析!$D$4,O$5,ROW()-ROW($C$6)),[1]!S_SEGMENT_REGION_SALES(公司分析!$D$4,O$5,ROW()-ROW($C$6))))/CurrencyUnit -> 0 | Q15: =IF($C$3="按行业分类",[1]!s_segment_industry_profit(公司分析!$D$4,O$5,ROW()-ROW($C$6)),IF($C$3="按产品分类",[1]!s_segment_product_profit(公司分析!$D$4,O$5,ROW()-ROW($C$6)),[1]!S_SEGMENT_REGION_PROFIT(公司分析!$D$4,O$5,ROW()-ROW($C$6))))/CurrencyUnit -> 0 | R15: =IF($C$3="按行业分类",[1]!s_segment_industry_item(公司分析!$D$4,R$5,ROW()-ROW($C$6)),IF($C$3="按产品分类",[1]!s_segment_product_item(公司分析!$D$4,R$5,ROW()-ROW($C$6)),[1]!S_SEGMENT_REGION_ITEM(公司分析!$D$4,R$5,ROW()-ROW($C$6)))) -> 0 | S15: =IF($C$3="按行业分类",[1]!s_segment_industry_sales(公司分析!$D$4,R$5,ROW()-ROW($C$6)),IF($C$3="按产品分类",[1]!s_segment_product_sales(公司分析!$D$4,R$5,ROW()-ROW($C$6)),[1]!S_SEGMENT_REGION_SALES(公司分析!$D$4,R$5,ROW()-ROW($C$6))))/CurrencyUnit -> 0 | T15: =IF($C$3="按行业分类",[1]!s_segment_industry_profit(公司分析!$D$4,R$5,ROW()-ROW($C$6)),IF($C$3="按产品分类",[1]!s_segment_product_profit(公司分析!$D$4,R$5,ROW()-ROW($C$6)),[1]!S_SEGMENT_REGION_PROFIT(公司分析!$D$4,R$5,ROW()-ROW($C$6))))/CurrencyUnit -> 0
C16: =IF($C$3="按行业分类",[1]!s_segment_industry_item(公司分析!$D$4,C$5,ROW()-ROW($C$6)),IF($C$3="按产品分类",[1]!s_segment_product_item(公司分析!$D$4,C$5,ROW()-ROW($C$6)),[1]!S_SEGMENT_REGION_ITEM(公司分析!$D$4,C$5,ROW()-ROW($C$6)))) -> 0 | D16: =IF($C$3="按行业分类",[1]!s_segment_industry_sales(公司分析!$D$4,C$5,ROW()-ROW($C$6)),IF($C$3="按产品分类",[1]!s_segment_product_sales(公司分析!$D$4,C$5,ROW()-ROW($C$6)),[1]!S_SEGMENT_REGION_SALES(公司分析!$D$4,C$5,ROW()-ROW($C$6))))/CurrencyUnit -> 0 | E16: =IF($C$3="按行业分类",[1]!s_segment_industry_profit(公司分析!$D$4,C$5,ROW()-ROW($C$6)),IF($C$3="按产品分类",[1]!s_segment_product_profit(公司分析!$D$4,C$5,ROW()-ROW($C$6)),[1]!S_SEGMENT_REGION_PROFIT(公司分析!$D$4,C$5,ROW()-ROW($C$6))))/CurrencyUnit -> 0 | F16: =IF($C$3="按行业分类",[1]!s_segment_industry_item(公司分析!$D$4,F$5,ROW()-ROW($C$6)),IF($C$3="按产品分类",[1]!s_segment_product_item(公司分析!$D$4,F$5,ROW()-ROW($C$6)),[1]!S_SEGMENT_REGION_ITEM(公司分析!$D$4,F$5,ROW()-ROW($C$6)))) -> 0 | G16: =IF($C$3="按行业分类",[1]!s_segment_industry_sales(公司分析!$D$4,F$5,ROW()-ROW($C$6)),IF($C$3="按产品分类",[1]!s_segment_product_sales(公司分析!$D$4,F$5,ROW()-ROW($C$6)),[1]!S_SEGMENT_REGION_SALES(公司分析!$D$4,F$5,ROW()-ROW($C$6))))/CurrencyUnit -> 0 | H16: =IF($C$3="按行业分类",[1]!s_segment_industry_profit(公司分析!$D$4,F$5,ROW()-ROW($C$6)),IF($C$3="按产品分类",[1]!s_segment_product_profit(公司分析!$D$4,F$5,ROW()-ROW($C$6)),[1]!S_SEGMENT_REGION_PROFIT(公司分析!$D$4,F$5,ROW()-ROW($C$6))))/CurrencyUnit -> 0 | I16: =IF($C$3="按行业分类",[1]!s_segment_industry_item(公司分析!$D$4,I$5,ROW()-ROW($C$6)),IF($C$3="按产品分类",[1]!s_segment_product_item(公司分析!$D$4,I$5,ROW()-ROW($C$6)),[1]!S_SEGMENT_REGION_ITEM(公司分析!$D$4,I$5,ROW()-ROW($C$6)))) -> 0 | J16: =IF($C$3="按行业分类",[1]!s_segment_industry_sales(公司分析!$D$4,I$5,ROW()-ROW($C$6)),IF($C$3="按产品分类",[1]!s_segment_product_sales(公司分析!$D$4,I$5,ROW()-ROW($C$6)),[1]!S_SEGMENT_REGION_SALES(公司分析!$D$4,I$5,ROW()-ROW($C$6))))/CurrencyUnit -> 0 | K16: =IF($C$3="按行业分类",[1]!s_segment_industry_profit(公司分析!$D$4,I$5,ROW()-ROW($C$6)),IF($C$3="按产品分类",[1]!s_segment_product_profit(公司分析!$D$4,I$5,ROW()-ROW($C$6)),[1]!S_SEGMENT_REGION_PROFIT(公司分析!$D$4,I$5,ROW()-ROW($C$6))))/CurrencyUnit -> 0 | L16: =IF($C$3="按行业分类",[1]!s_segment_industry_item(公司分析!$D$4,L$5,ROW()-ROW($C$6)),IF($C$3="按产品分类",[1]!s_segment_product_item(公司分析!$D$4,L$5,ROW()-ROW($C$6)),[1]!S_SEGMENT_REGION_ITEM(公司分析!$D$4,L$5,ROW()-ROW($C$6)))) -> 0 | M16: =IF($C$3="按行业分类",[1]!s_segment_industry_sales(公司分析!$D$4,L$5,ROW()-ROW($C$6)),IF($C$3="按产品分类",[1]!s_segment_product_sales(公司分析!$D$4,L$5,ROW()-ROW($C$6)),[1]!S_SEGMENT_REGION_SALES(公司分析!$D$4,L$5,ROW()-ROW($C$6))))/CurrencyUnit -> 0 | N16: =IF($C$3="按行业分类",[1]!s_segment_industry_profit(公司分析!$D$4,L$5,ROW()-ROW($C$6)),IF($C$3="按产品分类",[1]!s_segment_product_profit(公司分析!$D$4,L$5,ROW()-ROW($C$6)),[1]!S_SEGMENT_REGION_PROFIT(公司分析!$D$4,L$5,ROW()-ROW($C$6))))/CurrencyUnit -> 0 | O16: =IF($C$3="按行业分类",[1]!s_segment_industry_item(公司分析!$D$4,O$5,ROW()-ROW($C$6)),IF($C$3="按产品分类",[1]!s_segment_product_item(公司分析!$D$4,O$5,ROW()-ROW($C$6)),[1]!S_SEGMENT_REGION_ITEM(公司分析!$D$4,O$5,ROW()-ROW($C$6)))) -> 0 | P16: =IF($C$3="按行业分类",[1]!s_segment_industry_sales(公司分析!$D$4,O$5,ROW()-ROW($C$6)),IF($C$3="按产品分类",[1]!s_segment_product_sales(公司分析!$D$4,O$5,ROW()-ROW($C$6)),[1]!S_SEGMENT_REGION_SALES(公司分析!$D$4,O$5,ROW()-ROW($C$6))))/CurrencyUnit -> 0 | Q16: =IF($C$3="按行业分类",[1]!s_segment_industry_profit(公司分析!$D$4,O$5,ROW()-ROW($C$6)),IF($C$3="按产品分类",[1]!s_segment_product_profit(公司分析!$D$4,O$5,ROW()-ROW($C$6)),[1]!S_SEGMENT_REGION_PROFIT(公司分析!$D$4,O$5,ROW()-ROW($C$6))))/CurrencyUnit -> 0 | R16: =IF($C$3="按行业分类",[1]!s_segment_industry_item(公司分析!$D$4,R$5,ROW()-ROW($C$6)),IF($C$3="按产品分类",[1]!s_segment_product_item(公司分析!$D$4,R$5,ROW()-ROW($C$6)),[1]!S_SEGMENT_REGION_ITEM(公司分析!$D$4,R$5,ROW()-ROW($C$6)))) -> 0 | S16: =IF($C$3="按行业分类",[1]!s_segment_industry_sales(公司分析!$D$4,R$5,ROW()-ROW($C$6)),IF($C$3="按产品分类",[1]!s_segment_product_sales(公司分析!$D$4,R$5,ROW()-ROW($C$6)),[1]!S_SEGMENT_REGION_SALES(公司分析!$D$4,R$5,ROW()-ROW($C$6))))/CurrencyUnit -> 0 | T16: =IF($C$3="按行业分类",[1]!s_segment_industry_profit(公司分析!$D$4,R$5,ROW()-ROW($C$6)),IF($C$3="按产品分类",[1]!s_segment_product_profit(公司分析!$D$4,R$5,ROW()-ROW($C$6)),[1]!S_SEGMENT_REGION_PROFIT(公司分析!$D$4,R$5,ROW()-ROW($C$6))))/CurrencyUnit -> 0
C17: =IF($C$3="按行业分类",[1]!s_segment_industry_item(公司分析!$D$4,C$5,ROW()-ROW($C$6)),IF($C$3="按产品分类",[1]!s_segment_product_item(公司分析!$D$4,C$5,ROW()-ROW($C$6)),[1]!S_SEGMENT_REGION_ITEM(公司分析!$D$4,C$5,ROW()-ROW($C$6)))) -> 0 | D17: =IF($C$3="按行业分类",[1]!s_segment_industry_sales(公司分析!$D$4,C$5,ROW()-ROW($C$6)),IF($C$3="按产品分类",[1]!s_segment_product_sales(公司分析!$D$4,C$5,ROW()-ROW($C$6)),[1]!S_SEGMENT_REGION_SALES(公司分析!$D$4,C$5,ROW()-ROW($C$6))))/CurrencyUnit -> 0 | E17: =IF($C$3="按行业分类",[1]!s_segment_industry_profit(公司分析!$D$4,C$5,ROW()-ROW($C$6)),IF($C$3="按产品分类",[1]!s_segment_product_profit(公司分析!$D$4,C$5,ROW()-ROW($C$6)),[1]!S_SEGMENT_REGION_PROFIT(公司分析!$D$4,C$5,ROW()-ROW($C$6))))/CurrencyUnit -> 0 | F17: =IF($C$3="按行业分类",[1]!s_segment_industry_item(公司分析!$D$4,F$5,ROW()-ROW($C$6)),IF($C$3="按产品分类",[1]!s_segment_product_item(公司分析!$D$4,F$5,ROW()-ROW($C$6)),[1]!S_SEGMENT_REGION_ITEM(公司分析!$D$4,F$5,ROW()-ROW($C$6)))) -> 0 | G17: =IF($C$3="按行业分类",[1]!s_segment_industry_sales(公司分析!$D$4,F$5,ROW()-ROW($C$6)),IF($C$3="按产品分类",[1]!s_segment_product_sales(公司分析!$D$4,F$5,ROW()-ROW($C$6)),[1]!S_SEGMENT_REGION_SALES(公司分析!$D$4,F$5,ROW()-ROW($C$6))))/CurrencyUnit -> 0 | H17: =IF($C$3="按行业分类",[1]!s_segment_industry_profit(公司分析!$D$4,F$5,ROW()-ROW($C$6)),IF($C$3="按产品分类",[1]!s_segment_product_profit(公司分析!$D$4,F$5,ROW()-ROW($C$6)),[1]!S_SEGMENT_REGION_PROFIT(公司分析!$D$4,F$5,ROW()-ROW($C$6))))/CurrencyUnit -> 0 | I17: =IF($C$3="按行业分类",[1]!s_segment_industry_item(公司分析!$D$4,I$5,ROW()-ROW($C$6)),IF($C$3="按产品分类",[1]!s_segment_product_item(公司分析!$D$4,I$5,ROW()-ROW($C$6)),[1]!S_SEGMENT_REGION_ITEM(公司分析!$D$4,I$5,ROW()-ROW($C$6)))) -> 0 | J17: =IF($C$3="按行业分类",[1]!s_segment_industry_sales(公司分析!$D$4,I$5,ROW()-ROW($C$6)),IF($C$3="按产品分类",[1]!s_segment_product_sales(公司分析!$D$4,I$5,ROW()-ROW($C$6)),[1]!S_SEGMENT_REGION_SALES(公司分析!$D$4,I$5,ROW()-ROW($C$6))))/CurrencyUnit -> 0 | K17: =IF($C$3="按行业分类",[1]!s_segment_industry_profit(公司分析!$D$4,I$5,ROW()-ROW($C$6)),IF($C$3="按产品分类",[1]!s_segment_product_profit(公司分析!$D$4,I$5,ROW()-ROW($C$6)),[1]!S_SEGMENT_REGION_PROFIT(公司分析!$D$4,I$5,ROW()-ROW($C$6))))/CurrencyUnit -> 0 | L17: =IF($C$3="按行业分类",[1]!s_segment_industry_item(公司分析!$D$4,L$5,ROW()-ROW($C$6)),IF($C$3="按产品分类",[1]!s_segment_product_item(公司分析!$D$4,L$5,ROW()-ROW($C$6)),[1]!S_SEGMENT_REGION_ITEM(公司分析!$D$4,L$5,ROW()-ROW($C$6)))) -> 0 | M17: =IF($C$3="按行业分类",[1]!s_segment_industry_sales(公司分析!$D$4,L$5,ROW()-ROW($C$6)),IF($C$3="按产品分类",[1]!s_segment_product_sales(公司分析!$D$4,L$5,ROW()-ROW($C$6)),[1]!S_SEGMENT_REGION_SALES(公司分析!$D$4,L$5,ROW()-ROW($C$6))))/CurrencyUnit -> 0 | N17: =IF($C$3="按行业分类",[1]!s_segment_industry_profit(公司分析!$D$4,L$5,ROW()-ROW($C$6)),IF($C$3="按产品分类",[1]!s_segment_product_profit(公司分析!$D$4,L$5,ROW()-ROW($C$6)),[1]!S_SEGMENT_REGION_PROFIT(公司分析!$D$4,L$5,ROW()-ROW($C$6))))/CurrencyUnit -> 0 | O17: =IF($C$3="按行业分类",[1]!s_segment_industry_item(公司分析!$D$4,O$5,ROW()-ROW($C$6)),IF($C$3="按产品分类",[1]!s_segment_product_item(公司分析!$D$4,O$5,ROW()-ROW($C$6)),[1]!S_SEGMENT_REGION_ITEM(公司分析!$D$4,O$5,ROW()-ROW($C$6)))) -> 0 | P17: =IF($C$3="按行业分类",[1]!s_segment_industry_sales(公司分析!$D$4,O$5,ROW()-ROW($C$6)),IF($C$3="按产品分类",[1]!s_segment_product_sales(公司分析!$D$4,O$5,ROW()-ROW($C$6)),[1]!S_SEGMENT_REGION_SALES(公司分析!$D$4,O$5,ROW()-ROW($C$6))))/CurrencyUnit -> 0 | Q17: =IF($C$3="按行业分类",[1]!s_segment_industry_profit(公司分析!$D$4,O$5,ROW()-ROW($C$6)),IF($C$3="按产品分类",[1]!s_segment_product_profit(公司分析!$D$4,O$5,ROW()-ROW($C$6)),[1]!S_SEGMENT_REGION_PROFIT(公司分析!$D$4,O$5,ROW()-ROW($C$6))))/CurrencyUnit -> 0 | R17: =IF($C$3="按行业分类",[1]!s_segment_industry_item(公司分析!$D$4,R$5,ROW()-ROW($C$6)),IF($C$3="按产品分类",[1]!s_segment_product_item(公司分析!$D$4,R$5,ROW()-ROW($C$6)),[1]!S_SEGMENT_REGION_ITEM(公司分析!$D$4,R$5,ROW()-ROW($C$6)))) -> 0 | S17: =IF($C$3="按行业分类",[1]!s_segment_industry_sales(公司分析!$D$4,R$5,ROW()-ROW($C$6)),IF($C$3="按产品分类",[1]!s_segment_product_sales(公司分析!$D$4,R$5,ROW()-ROW($C$6)),[1]!S_SEGMENT_REGION_SALES(公司分析!$D$4,R$5,ROW()-ROW($C$6))))/CurrencyUnit -> 0 | T17: =IF($C$3="按行业分类",[1]!s_segment_industry_profit(公司分析!$D$4,R$5,ROW()-ROW($C$6)),IF($C$3="按产品分类",[1]!s_segment_product_profit(公司分析!$D$4,R$5,ROW()-ROW($C$6)),[1]!S_SEGMENT_REGION_PROFIT(公司分析!$D$4,R$5,ROW()-ROW($C$6))))/CurrencyUnit -> 0
C19: ="收入"&"["&C3&"]" -> 收入[按产品分类] | D19: =IF(MONTH(公司分析!D66)=6,YEAR(公司分析!D66)-1&"-12-31",YEAR(公司分析!D66)&"-6-30") -> 2019-6-30 | E19: =公司分析!D66 -> 2019/12/31 | F19: =I5 -> 2020/12/31 | G19: =L5 -> 2021/12/31 | H19: =O5 -> 2022/12/31 | I19: =R5 -> 2023/12/31 | J19: =公司分析!D66 -> 2019/12/31 | K19: =公司分析!E66 -> 2020/12/31 | L19: =公司分析!F66 -> 2021/12/31 | M19: =公司分析!G66 -> 2022/12/31 | N19: =公司分析!H66 -> 2023/12/31
C20: =IF(R7=0,"",R7) -> 增值服务 | D20: =IFERROR(VLOOKUP(C20,$C$7:$D$11,2,FALSE),0) -> 0 | E20: =IFERROR(VLOOKUP(C20,$F$7:$G$11,2,FALSE),0) -> 0 | F20: =IFERROR(VLOOKUP(C20,$I$7:$J$11,2,FALSE),0) -> 0 | G20: =IFERROR(VLOOKUP(C20,$L$7:$M$11,2,FALSE),0) -> 0 | H20: =IFERROR(VLOOKUP(C20,$O$7:$P$11,2,FALSE),0) -> 87.1517 | I20: =IFERROR(VLOOKUP(C20,$R$7:$S$11,2,FALSE),0) -> 99.1008 | J20: =IF($E$3="年度",E20,IF(MONTH(J$19)=6,E20,E20-D20)) -> 0 | K20: =IF($E$3="年度",F20,IF(MONTH(K$19)=6,F20,F20-E20)) -> 0 | L20: =IF($E$3="年度",G20,IF(MONTH(L$19)=6,G20,G20-F20)) -> 0 | M20: =IF($E$3="年度",H20,IF(MONTH(M$19)=6,H20,H20-G20)) -> 87.1517 | N20: =IF($E$3="年度",I20,IF(MONTH(N$19)=6,I20,I20-H20)) -> 99.1008
C21: =IF(R8=0,"",R8) -> 广告收入 | D21: =IFERROR(VLOOKUP(C21,$C$7:$D$11,2,FALSE),0) -> 2.80235 | E21: =IFERROR(VLOOKUP(C21,$F$7:$G$11,2,FALSE),0) -> 8.17016 | F21: =IFERROR(VLOOKUP(C21,$I$7:$J$11,2,FALSE),0) -> 18.42772 | G21: =IFERROR(VLOOKUP(C21,$L$7:$M$11,2,FALSE),0) -> 45.23421 | H21: =IFERROR(VLOOKUP(C21,$O$7:$P$11,2,FALSE),0) -> 50.66212 | I21: =IFERROR(VLOOKUP(C21,$R$7:$S$11,2,FALSE),0) -> 64.1204 | J21: =IF($E$3="年度",E21,IF(MONTH(J$19)=6,E21,E21-D21)) -> 8.17016 | K21: =IF($E$3="年度",F21,IF(MONTH(K$19)=6,F21,F21-E21)) -> 18.42772 | L21: =IF($E$3="年度",G21,IF(MONTH(L$19)=6,G21,G21-F21)) -> 45.23421 | M21: =IF($E$3="年度",H21,IF(MONTH(M$19)=6,H21,H21-G21)) -> 50.66212 | N21: =IF($E$3="年度",I21,IF(MONTH(N$19)=6,I21,I21-H21)) -> 64.1204
C22: =IF(R9=0,"",R9) -> 移动游戏 | D22: =IFERROR(VLOOKUP(C22,$C$7:$D$11,2,FALSE),0) -> 17.93311 | E22: =IFERROR(VLOOKUP(C22,$F$7:$G$11,2,FALSE),0) -> 35.97809 | F22: =IFERROR(VLOOKUP(C22,$I$7:$J$11,2,FALSE),0) -> 48.03382 | G22: =IFERROR(VLOOKUP(C22,$L$7:$M$11,2,FALSE),0) -> 50.90926 | H22: =IFERROR(VLOOKUP(C22,$O$7:$P$11,2,FALSE),0) -> 50.2129 | I22: =IFERROR(VLOOKUP(C22,$R$7:$S$11,2,FALSE),0) -> 40.21137 | J22: =IF($E$3="年度",E22,IF(MONTH(J$19)=6,E22,E22-D22)) -> 35.97809 | K22: =IF($E$3="年度",F22,IF(MONTH(K$19)=6,F22,F22-E22)) -> 48.03382 | L22: =IF($E$3="年度",G22,IF(MONTH(L$19)=6,G22,G22-F22)) -> 50.90926 | M22: =IF($E$3="年度",H22,IF(MONTH(M$19)=6,H22,H22-G22)) -> 50.2129 | N22: =IF($E$3="年度",I22,IF(MONTH(N$19)=6,I22,I22-H22)) -> 40.21137
C23: =IF(R10=0,"",R10) -> 衍生工具及其他,净值 | D23: =IFERROR(VLOOKUP(C23,$C$7:$D$11,2,FALSE),0) -> 0 | E23: =IFERROR(VLOOKUP(C23,$F$7:$G$11,2,FALSE),0) -> 0 | F23: =IFERROR(VLOOKUP(C23,$I$7:$J$11,2,FALSE),0) -> 0 | G23: =IFERROR(VLOOKUP(C23,$L$7:$M$11,2,FALSE),0) -> 0 | H23: =IFERROR(VLOOKUP(C23,$O$7:$P$11,2,FALSE),0) -> 0 | I23: =IFERROR(VLOOKUP(C23,$R$7:$S$11,2,FALSE),0) -> 21.8473 | J23: =IF($E$3="年度",E23,IF(MONTH(J$19)=6,E23,E23-D23)) -> 0 | K23: =IF($E$3="年度",F23,IF(MONTH(K$19)=6,F23,F23-E23)) -> 0 | L23: =IF($E$3="年度",G23,IF(MONTH(L$19)=6,G23,G23-F23)) -> 0 | M23: =IF($E$3="年度",H23,IF(MONTH(M$19)=6,H23,H23-G23)) -> 0 | N23: =IF($E$3="年度",I23,IF(MONTH(N$19)=6,I23,I23-H23)) -> 21.8473
C24: =IF(R11=0,"",R11) -> 0 | D24: =IFERROR(VLOOKUP(C24,$C$7:$D$11,2,FALSE),0) -> 0 | E24: =IFERROR(VLOOKUP(C24,$F$7:$G$11,2,FALSE),0) -> 0 | F24: =IFERROR(VLOOKUP(C24,$I$7:$J$11,2,FALSE),0) -> 0 | G24: =IFERROR(VLOOKUP(C24,$L$7:$M$11,2,FALSE),0) -> 0 | H24: =IFERROR(VLOOKUP(C24,$O$7:$P$11,2,FALSE),0) -> 0 | I24: =IFERROR(VLOOKUP(C24,$R$7:$S$11,2,FALSE),0) -> 0 | J24: =IF($E$3="年度",E24,IF(MONTH(J$19)=6,E24,E24-D24)) -> 0 | K24: =IF($E$3="年度",F24,IF(MONTH(K$19)=6,F24,F24-E24)) -> 0 | L24: =IF($E$3="年度",G24,IF(MONTH(L$19)=6,G24,G24-F24)) -> 0 | M24: =IF($E$3="年度",H24,IF(MONTH(M$19)=6,H24,H24-G24)) -> 0 | N24: =IF($E$3="年度",I24,IF(MONTH(N$19)=6,I24,I24-H24)) -> 0
C26: =T6 -> 利润[按产品分类] | D26: =D19 -> 2019-6-30 | E26: =E19 -> 2019/12/31 | F26: =F19 -> 2020/12/31 | G26: =G19 -> 2021/12/31 | H26: =H19 -> 2022/12/31 | I26: =I19 -> 2023/12/31 | J26: =E26 -> 2019/12/31 | K26: =F26 -> 2020/12/31 | L26: =G26 -> 2021/12/31 | M26: =H26 -> 2022/12/31 | N26: =I26 -> 2023/12/31
C27: =C20 -> 增值服务 | D27: =IFERROR(VLOOKUP(C27,$C$7:$E$11,3,FALSE),0) -> 0 | E27: =IFERROR(VLOOKUP(C27,$F$7:$H$11,3,FALSE),0) -> 0 | F27: =IFERROR(VLOOKUP(C27,$I$7:$K$11,3,FALSE),0) -> 0 | G27: =IFERROR(VLOOKUP(C27,$L$7:$N$11,3,FALSE),0) -> 0 | H27: =IFERROR(VLOOKUP(C27,$O$7:$Q$11,3,FALSE),0) -> 0 | I27: =IFERROR(VLOOKUP(C27,$R$7:$T$11,3,FALSE),0) -> 0 | J27: =IF($E$3="年度",E27,IF(MONTH(J$19)=6,E27,E27-D27)) -> 0 | K27: =IF($E$3="年度",F27,IF(MONTH(K$19)=6,F27,F27-E27)) -> 0 | L27: =IF($E$3="年度",G27,IF(MONTH(L$19)=6,G27,G27-F27)) -> 0 | M27: =IF($E$3="年度",H27,IF(MONTH(M$19)=6,H27,H27-G27)) -> 0 | N27: =IF($E$3="年度",I27,IF(MONTH(N$19)=6,I27,I27-H27)) -> 0
C28: =C21 -> 广告收入 | D28: =IFERROR(VLOOKUP(C28,$C$7:$E$11,3,FALSE),0) -> 0 | E28: =IFERROR(VLOOKUP(C28,$F$7:$H$11,3,FALSE),0) -> 0 | F28: =IFERROR(VLOOKUP(C28,$I$7:$K$11,3,FALSE),0) -> 0 | G28: =IFERROR(VLOOKUP(C28,$L$7:$N$11,3,FALSE),0) -> 0 | H28: =IFERROR(VLOOKUP(C28,$O$7:$Q$11,3,FALSE),0) -> 0 | I28: =IFERROR(VLOOKUP(C28,$R$7:$T$11,3,FALSE),0) -> 0 | J28: =IF($E$3="年度",E28,IF(MONTH(J$19)=6,E28,E28-D28)) -> 0 | K28: =IF($E$3="年度",F28,IF(MONTH(K$19)=6,F28,F28-E28)) -> 0 | L28: =IF($E$3="年度",G28,IF(MONTH(L$19)=6,G28,G28-F28)) -> 0 | M28: =IF($E$3="年度",H28,IF(MONTH(M$19)=6,H28,H28-G28)) -> 0 | N28: =IF($E$3="年度",I28,IF(MONTH(N$19)=6,I28,I28-H28)) -> 0
C29: =C22 -> 移动游戏 | D29: =IFERROR(VLOOKUP(C29,$C$7:$E$11,3,FALSE),0) -> 0 | E29: =IFERROR(VLOOKUP(C29,$F$7:$H$11,3,FALSE),0) -> 0 | F29: =IFERROR(VLOOKUP(C29,$I$7:$K$11,3,FALSE),0) -> 0 | G29: =IFERROR(VLOOKUP(C29,$L$7:$N$11,3,FALSE),0) -> 0 | H29: =IFERROR(VLOOKUP(C29,$O$7:$Q$11,3,FALSE),0) -> 0 | I29: =IFERROR(VLOOKUP(C29,$R$7:$T$11,3,FALSE),0) -> 0 | J29: =IF($E$3="年度",E29,IF(MONTH(J$19)=6,E29,E29-D29)) -> 0 | K29: =IF($E$3="年度",F29,IF(MONTH(K$19)=6,F29,F29-E29)) -> 0 | L29: =IF($E$3="年度",G29,IF(MONTH(L$19)=6,G29,G29-F29)) -> 0 | M29: =IF($E$3="年度",H29,IF(MONTH(M$19)=6,H29,H29-G29)) -> 0 | N29: =IF($E$3="年度",I29,IF(MONTH(N$19)=6,I29,I29-H29)) -> 0
C30: =C23 -> 衍生工具及其他,净值 | D30: =IFERROR(VLOOKUP(C30,$C$7:$E$11,3,FALSE),0) -> 0 | E30: =IFERROR(VLOOKUP(C30,$F$7:$H$11,3,FALSE),0) -> 0 | F30: =IFERROR(VLOOKUP(C30,$I$7:$K$11,3,FALSE),0) -> 0 | G30: =IFERROR(VLOOKUP(C30,$L$7:$N$11,3,FALSE),0) -> 0 | H30: =IFERROR(VLOOKUP(C30,$O$7:$Q$11,3,FALSE),0) -> 0 | I30: =IFERROR(VLOOKUP(C30,$R$7:$T$11,3,FALSE),0) -> 0 | J30: =IF($E$3="年度",E30,IF(MONTH(J$19)=6,E30,E30-D30)) -> 0 | K30: =IF($E$3="年度",F30,IF(MONTH(K$19)=6,F30,F30-E30)) -> 0 | L30: =IF($E$3="年度",G30,IF(MONTH(L$19)=6,G30,G30-F30)) -> 0 | M30: =IF($E$3="年度",H30,IF(MONTH(M$19)=6,H30,H30-G30)) -> 0 | N30: =IF($E$3="年度",I30,IF(MONTH(N$19)=6,I30,I30-H30)) -> 0
C31: =C24 -> 0 | D31: =IFERROR(VLOOKUP(C31,$C$7:$E$11,3,FALSE),0) -> 0 | E31: =IFERROR(VLOOKUP(C31,$F$7:$H$11,3,FALSE),0) -> 0 | F31: =IFERROR(VLOOKUP(C31,$I$7:$K$11,3,FALSE),0) -> 0 | G31: =IFERROR(VLOOKUP(C31,$L$7:$N$11,3,FALSE),0) -> 0 | H31: =IFERROR(VLOOKUP(C31,$O$7:$Q$11,3,FALSE),0) -> 0 | I31: =IFERROR(VLOOKUP(C31,$R$7:$T$11,3,FALSE),0) -> 0 | J31: =IF($E$3="年度",E31,IF(MONTH(J$19)=6,E31,E31-D31)) -> 0 | K31: =IF($E$3="年度",F31,IF(MONTH(K$19)=6,F31,F31-E31)) -> 0 | L31: =IF($E$3="年度",G31,IF(MONTH(L$19)=6,G31,G31-F31)) -> 0 | M31: =IF($E$3="年度",H31,IF(MONTH(M$19)=6,H31,H31-G31)) -> 0 | N31: =IF($E$3="年度",I31,IF(MONTH(N$19)=6,I31,I31-H31)) -> 0

Sheet Wind模板
A1: 股票速览-公司分析

Sheet 参数设置
C1: 股票速览-参数设置
I2: =公司分析!F20 -> PE Band | M2: =IF(公司分析!D20="前复权",3,IF(公司分析!D20="后复权",2,1)) -> 1 | N2: =IF(OR(公司分析!E20="日",公司分析!E20="day"),1,IF(OR(公司分析!E20="周",公司分析!E20="week"),7,30)) -> 7
B3: 单位 | C3: 千 | D3: 百万 | E3: 亿 | F3: 十亿 | G3: =IF(OR(公司分析!F5="千",公司分析!F5="thousand"),1000,IF(OR(公司分析!F5="百万",公司分析!F5="million"),1000000,IF(OR(公司分析!F5="十亿",公司分析!F5="billion"),1000000000,100000000))) -> 100000000 | H3: =公司分析!D4 -> 9626.HK | I3: 日期 | J3: 收盘价 | K3: =RIGHT(公司分析!G20,LEN(公司分析!G20)-6)&"X" -> 8X | L3: =LEFT(K3,LEN(K3)-1)+RIGHT(公司分析!H20,LEN(公司分析!H20)-5)&"X" -> 20X | M3: =LEFT(L3,LEN(L3)-1)+RIGHT(公司分析!H20,LEN(公司分析!H20)-5)&"X" -> 32X | N3: 区间涨跌幅 | O3: 指数基准 | P3: 名称_x0000__x0000_ | Q3: 代码_x0000__x0000_ | R3: =公司分析!V20 -> 恒生科技指数 | S3: =VLOOKUP(R3,P4:Q48,2,FALSE) -> HSTECH.HI | U3: 申万一级行业 | V3: 序号 | W3: 证券代码 | X3: 证券简称 | Y3: =行业比较!D6 -> wind四级行业 | Z3: 行业 | AB3: 财务摘要 | AC3: 收入 | AD3: 毛利率 | AE3: 营业利润率 | AF3: 净利润率 | AG3: ROA | AH3: ROE | AI3: EPS | AJ3: BPS | AK3: CFPS | AL3: PE | AM3: PB | AN3: 总股本 | AO3: 总市值
B4: 报告期 | C4: 最新报告期 | D4: =IF(MONTH(公司分析!D5)>10,YEAR(公司分析!D5)&"-09-30",IF(MONTH(公司分析!D5)>8,YEAR(公司分析!D5)&"-06-30",IF(MONTH(公司分析!D5)>4,YEAR(公司分析!D5)&"-03-31",YEAR(公司分析!D5)-1&"-09-30"))) -> 2024-03-31 | E4: 上一报告期 | F4: =IF(MONTH(recentreportdate)=6,YEAR(recentreportdate)&"-03-31",IF(MONTH(recentreportdate)=9,YEAR(recentreportdate)&"-06-30",IF(MONTH(recentreportdate)=12,YEAR(recentreportdate)&"-09-30",YEAR(recentreportdate)-1&"-12-31"))) -> 2023-12-31 | H4: =IF(I2="PE Band",[1]!s_est_eps(H3,YEAR(I4),I4),[1]!s_est_avgbps(H3,YEAR(I4),I4)) -> -4.2868 | I4: =--[1]!td(TODAY()-1) -> 45464 | J4: =IF([1]!s_dq_close(公司分析!$D$4,I4,$M$2)=0,NA(),[1]!s_dq_close(公司分析!$D$4,I4,$M$2)) -> 136.8 | K4: =H4*LEFT($K$3,LEN($K$3)-1) -> -34.2944 | L4: =H4*LEFT($L$3,LEN($L$3)-1) -> -85.736 | M4: =H4*LEFT($M$3,LEN($M$3)-1) -> -137.1776 | N4: =J4/$J$64-1 -> -0.18909306 | O4: =R4/$R$64-1 -> -0.12654007 | P4: 上证综合指数_x0000__x0000__x0000__x0000__x0000__x0000_ | Q4: 000001.SH | R4: =IF([1]!s_dq_close($S$3,I4,$M$2)=0,NA(),[1]!s_dq_close($S$3,I4,$M$2)) -> 3701.4 | U4: 申万二级行业 | V4: =IF(Z4="",0,RANK(Z4,Z:Z,1)) -> 0 | W4: =IF(板块成分!B6="","",板块成分!B6) -> 0001.HK | X4: =[1]!s_info_name(W4) -> 长和 | Y4: =IF($Y$3="申万一级行业",[1]!s_info_industry_sw_2021(W4,公司分析!D$5,1),IF($Y$3="申万二级行业",[1]!s_info_industry_sw_2021(W4,公司分析!D$5,2),IF($Y$3="申万三级行业",[1]!s_info_industry_sw_2021(W4,公司分析!D$5,3),IF($Y$3="wind一级行业",[1]!s_info_industry_gics(W4,1),IF($Y$3="wind二级行业",[1]!s_info_industry_gics(W4,2),IF($Y$3="wind三级行业",[1]!s_info_industry_gics(W4,3),IF($Y$3="wind四级行业",[1]!s_info_industry_gics(W4,4),IF($Y$3="证监会门类行业",[1]!s_info_industry_csrc12_n(W4,公司分析!D$5,1),"")))))))) -> 综合类行业 | Z4: =IF(Y4=行业比较!$E$6,ROW(),"") | AB4: 估值分析 | AC4: 营业利润 | AD4: 财务费用 | AE4: 折旧及摊销 | AF4: 利润总额 | AG4: 所得税 | AH4: 营运资本 | AI4: 计息债务 | AJ4: 资本支出 | AK4: 现金及等价物 | AL4: PE | AM4: PB | AN4: 总股本 | AO4: 总市值
B5: 行情周期 | C5: 日 | D5: 周 | E5: 月 | H5: =IF(([1]!s_share_total($H$3,I5)/[1]!s_share_total($H$3,I6))/(YEAR(I5)/YEAR(I4))=1,NA(),IF($I$2="PE Band",[1]!S_STM07_IS($H$3,61,YEAR(I5)-1&"-12-31",1)/[1]!s_share_total($H$3,I5),[1]!s_stm07_bs($H$3,140,YEAR(I5)-1&"-12-31",1)/[1]!s_share_total($H$3,I5))) -> #N/A | I5: =--[1]!td(I4-$N$2) -> 45457 | J5: =IF([1]!s_dq_close(公司分析!$D$4,I5,$M$2)=0,NA(),[1]!s_dq_close(公司分析!$D$4,I5,$M$2)) -> 117.1 | K5: =H5*LEFT($K$3,LEN($K$3)-1) -> #N/A | L5: =H5*LEFT($L$3,LEN($L$3)-1) -> #N/A | M5: =H5*LEFT($M$3,LEN($M$3)-1) -> #N/A | N5: =J5/$J$64-1 -> -0.30586841 | O5: =R5/$R$64-1 -> -0.12507227 | P5: 上证A股指数_x0000__x0000__x0000__x0000__x0000_ | Q5: 000002.SH | R5: =IF([1]!s_dq_close($S$3,I5,$M$2)=0,NA(),[1]!s_dq_close($S$3,I5,$M$2)) -> 3707.62 | U5: 申万三级行业 | V5: =IF(Z5="",0,RANK(Z5,Z:Z,1)) -> 0 | W5: =IF(板块成分!B7="","",板块成分!B7) -> 0002.HK | X5: =[1]!s_info_name(W5) -> 中电控股 | Y5: =IF($Y$3="申万一级行业",[1]!s_info_industry_sw_2021(W5,公司分析!D$5,1),IF($Y$3="申万二级行业",[1]!s_info_industry_sw_2021(W5,公司分析!D$5,2),IF($Y$3="申万三级行业",[1]!s_info_industry_sw_2021(W5,公司分析!D$5,3),IF($Y$3="wind一级行业",[1]!s_info_industry_gics(W5,1),IF($Y$3="wind二级行业",[1]!s_info_industry_gics(W5,2),IF($Y$3="wind三级行业",[1]!s_info_industry_gics(W5,3),IF($Y$3="wind四级行业",[1]!s_info_industry_gics(W5,4),IF($Y$3="证监会门类行业",[1]!s_info_industry_csrc12_n(W5,公司分析!D$5,1),"")))))))) -> 电力 | Z5: =IF(Y5=行业比较!$E$6,ROW(),"") | AC5: 1 | AD5: 2 | AE5: 3 | AF5: 4 | AG5: 5 | AH5: 6 | AI5: 7 | AJ5: 8 | AK5: 9 | AL5: 10 | AM5: 11 | AN5: 12 | AO5: 13
B6: 股东持股 | C6: 流通股东持股合计 | D6: =公司分析!U61-F6 -> 0 | E6: 户均持股数量上期 | F6: =[1]!S_HOLDER_AVGNUM(公司分析!D4,F4,2) -> 0 | H6: =IF(([1]!s_share_total($H$3,I6)/[1]!s_share_total($H$3,I7))/(YEAR(I6)/YEAR(I5))=1,NA(),IF($I$2="PE Band",[1]!S_STM07_IS($H$3,61,YEAR(I6)-1&"-12-31",1)/[1]!s_share_total($H$3,I6),[1]!s_stm07_bs($H$3,140,YEAR(I6)-1&"-12-31",1)/[1]!s_share_total($H$3,I6))) -> #N/A | I6: =--[1]!td(I5-$N$2) -> 45450 | J6: =IF([1]!s_dq_close(公司分析!$D$4,I6,$M$2)=0,NA(),[1]!s_dq_close(公司分析!$D$4,I6,$M$2)) -> 113.6 | K6: =H6*LEFT($K$3,LEN($K$3)-1) -> #N/A | L6: =H6*LEFT($L$3,LEN($L$3)-1) -> #N/A | M6: =H6*LEFT($M$3,LEN($M$3)-1) -> #N/A | N6: =J6/$J$64-1 -> -0.32661529 | O6: =R6/$R$64-1 -> -0.1097689 | P6: 上证B股指数_x0000__x0000__x0000__x0000__x0000_ | Q6: 000003.SH | R6: =IF([1]!s_dq_close($S$3,I6,$M$2)=0,NA(),[1]!s_dq_close($S$3,I6,$M$2)) -> 3772.47 | U6: wind一级行业 | V6: =IF(Z6="",0,RANK(Z6,Z:Z,1)) -> 0 | W6: =IF(板块成分!B8="","",板块成分!B8) -> 0003.HK | X6: =[1]!s_info_name(W6) -> 香港中华煤气 | Y6: =IF($Y$3="申万一级行业",[1]!s_info_industry_sw_2021(W6,公司分析!D$5,1),IF($Y$3="申万二级行业",[1]!s_info_industry_sw_2021(W6,公司分析!D$5,2),IF($Y$3="申万三级行业",[1]!s_info_industry_sw_2021(W6,公司分析!D$5,3),IF($Y$3="wind一级行业",[1]!s_info_industry_gics(W6,1),IF($Y$3="wind二级行业",[1]!s_info_industry_gics(W6,2),IF($Y$3="wind三级行业",[1]!s_info_industry_gics(W6,3),IF($Y$3="wind四级行业",[1]!s_info_industry_gics(W6,4),IF($Y$3="证监会门类行业",[1]!s_info_industry_csrc12_n(W6,公司分析!D$5,1),"")))))))) -> 燃气 | Z6: =IF(Y6=行业比较!$E$6,ROW(),"")
B7: 图标 | C7: 图标标题1 | H7: =IF(([1]!s_share_total($H$3,I7)/[1]!s_share_total($H$3,I8))/(YEAR(I7)/YEAR(I6))=1,NA(),IF($I$2="PE Band",[1]!S_STM07_IS($H$3,61,YEAR(I7)-1&"-12-31",1)/[1]!s_share_total($H$3,I7),[1]!s_stm07_bs($H$3,140,YEAR(I7)-1&"-12-31",1)/[1]!s_share_total($H$3,I7))) -> #N/A | I7: =--[1]!td(I6-$N$2) -> 45443 | J7: =IF([1]!s_dq_close(公司分析!$D$4,I7,$M$2)=0,NA(),[1]!s_dq_close(公司分析!$D$4,I7,$M$2)) -> 111.2 | K7: =H7*LEFT($K$3,LEN($K$3)-1) -> #N/A | L7: =H7*LEFT($L$3,LEN($L$3)-1) -> #N/A | M7: =H7*LEFT($M$3,LEN($M$3)-1) -> #N/A | N7: =J7/$J$64-1 -> -0.34084173 | O7: =R7/$R$64-1 -> -0.12905091 | P7: 上证180指数_x0000__x0000__x0000__x0000_ | Q7: 000010.SH | R7: =IF([1]!s_dq_close($S$3,I7,$M$2)=0,NA(),[1]!s_dq_close($S$3,I7,$M$2)) -> 3690.76 | U7: wind二级行业 | V7: =IF(Z7="",0,RANK(Z7,Z:Z,1)) -> 0 | W7: =IF(板块成分!B9="","",板块成分!B9) -> 0004.HK | X7: =[1]!s_info_name(W7) -> 九龙仓集团 | Y7: =IF($Y$3="申万一级行业",[1]!s_info_industry_sw_2021(W7,公司分析!D$5,1),IF($Y$3="申万二级行业",[1]!s_info_industry_sw_2021(W7,公司分析!D$5,2),IF($Y$3="申万三级行业",[1]!s_info_industry_sw_2021(W7,公司分析!D$5,3),IF($Y$3="wind一级行业",[1]!s_info_industry_gics(W7,1),IF($Y$3="wind二级行业",[1]!s_info_industry_gics(W7,2),IF($Y$3="wind三级行业",[1]!s_info_industry_gics(W7,3),IF($Y$3="wind四级行业",[1]!s_info_industry_gics(W7,4),IF($Y$3="证监会门类行业",[1]!s_info_industry_csrc12_n(W7,公司分析!D$5,1),"")))))))) -> 多样化房地产活动 | Z7: =IF(Y7=行业比较!$E$6,ROW(),"")
B8: 股价类型 | C8: 前复权 | D8: 后复权 | E8: 不复权 | H8: =IF(([1]!s_share_total($H$3,I8)/[1]!s_share_total($H$3,I9))/(YEAR(I8)/YEAR(I7))=1,NA(),IF($I$2="PE Band",[1]!S_STM07_IS($H$3,61,YEAR(I8)-1&"-12-31",1)/[1]!s_share_total($H$3,I8),[1]!s_stm07_bs($H$3,140,YEAR(I8)-1&"-12-31",1)/[1]!s_share_total($H$3,I8))) -> #N/A | I8: =--[1]!td(I7-$N$2) -> 45436 | J8: =IF([1]!s_dq_close(公司分析!$D$4,I8,$M$2)=0,NA(),[1]!s_dq_close(公司分析!$D$4,I8,$M$2)) -> 106.3 | K8: =H8*LEFT($K$3,LEN($K$3)-1) -> #N/A | L8: =H8*LEFT($L$3,LEN($L$3)-1) -> #N/A | M8: =H8*LEFT($M$3,LEN($M$3)-1) -> #N/A | N8: =J8/$J$64-1 -> -0.36988737 | O8: =R8/$R$64-1 -> -0.10339742 | P8: 上证50指数_x0000__x0000__x0000__x0000_ | Q8: 000016.SH | R8: =IF([1]!s_dq_close($S$3,I8,$M$2)=0,NA(),[1]!s_dq_close($S$3,I8,$M$2)) -> 3799.47 | U8: wind三级行业 | V8: =IF(Z8="",0,RANK(Z8,Z:Z,1)) -> 0 | W8: =IF(板块成分!B10="","",板块成分!B10) -> 0005.HK | X8: =[1]!s_info_name(W8) -> 汇丰控股 | Y8: =IF($Y$3="申万一级行业",[1]!s_info_industry_sw_2021(W8,公司分析!D$5,1),IF($Y$3="申万二级行业",[1]!s_info_industry_sw_2021(W8,公司分析!D$5,2),IF($Y$3="申万三级行业",[1]!s_info_industry_sw_2021(W8,公司分析!D$5,3),IF($Y$3="wind一级行业",[1]!s_info_industry_gics(W8,1),IF($Y$3="wind二级行业",[1]!s_info_industry_gics(W8,2),IF($Y$3="wind三级行业",[1]!s_info_industry_gics(W8,3),IF($Y$3="wind四级行业",[1]!s_info_industry_gics(W8,4),IF($Y$3="证监会门类行业",[1]!s_info_industry_csrc12_n(W8,公司分析!D$5,1),"")))))))) -> 多元化银行 | Z8: =IF(Y8=行业比较!$E$6,ROW(),"")
B9: 股东持股区间查询 | C9: 1月前 | D9: 1季前 | E9: 半年前 | F9: 1年前 | G9: =IF(公司分析!M38="1月前",公司分析!F38-30,IF(公司分析!M38="1季前",公司分析!F38-90,IF(公司分析!M38="半年前",公司分析!F38-180,公司分析!F38-365))) -> 45286 | H9: =IF(([1]!s_share_total($H$3,I9)/[1]!s_share_total($H$3,I10))/(YEAR(I9)/YEAR(I8))=1,NA(),IF($I$2="PE Band",[1]!S_STM07_IS($H$3,61,YEAR(I9)-1&"-12-31",1)/[1]!s_share_total($H$3,I9),[1]!s_stm07_bs($H$3,140,YEAR(I9)-1&"-12-31",1)/[1]!s_share_total($H$3,I9))) -> #N/A | I9: =--[1]!td(I8-$N$2) -> 45429 | J9: =IF([1]!s_dq_close(公司分析!$D$4,I9,$M$2)=0,NA(),[1]!s_dq_close(公司分析!$D$4,I9,$M$2)) -> 129 | K9: =H9*LEFT($K$3,LEN($K$3)-1) -> #N/A | L9: =H9*LEFT($L$3,LEN($L$3)-1) -> #N/A | M9: =H9*LEFT($M$3,LEN($M$3)-1) -> #N/A | N9: =J9/$J$64-1 -> -0.23532899 | O9: =R9/$R$64-1 -> -0.029507059 | P9: 新综指_x0000__x0000__x0000_ | Q9: 000017.SH | R9: =IF([1]!s_dq_close($S$3,I9,$M$2)=0,NA(),[1]!s_dq_close($S$3,I9,$M$2)) -> 4112.59 | U9: wind四级行业 | V9: =IF(Z9="",0,RANK(Z9,Z:Z,1)) -> 0 | W9: =IF(板块成分!B11="","",板块成分!B11) -> 0006.HK | X9: =[1]!s_info_name(W9) -> 电能实业 | Y9: =IF($Y$3="申万一级行业",[1]!s_info_industry_sw_2021(W9,公司分析!D$5,1),IF($Y$3="申万二级行业",[1]!s_info_industry_sw_2021(W9,公司分析!D$5,2),IF($Y$3="申万三级行业",[1]!s_info_industry_sw_2021(W9,公司分析!D$5,3),IF($Y$3="wind一级行业",[1]!s_info_industry_gics(W9,1),IF($Y$3="wind二级行业",[1]!s_info_industry_gics(W9,2),IF($Y$3="wind三级行业",[1]!s_info_industry_gics(W9,3),IF($Y$3="wind四级行业",[1]!s_info_industry_gics(W9,4),IF($Y$3="证监会门类行业",[1]!s_info_industry_csrc12_n(W9,公司分析!D$5,1),"")))))))) -> 电力 | Z9: =IF(Y9=行业比较!$E$6,ROW(),"")
B10: 报表类型 | C10: 合并报表 | D10: 母公司报表 | E10: 合并报表(调整) | F10: 母公司报表(调整) | G10: =IF(公司分析!T97="合并报表",1,IF(公司分析!T97="母公司报表",2,IF(公司分析!T97="合并报表(调整)",3,4))) -> 1 | H10: =IF(([1]!s_share_total($H$3,I10)/[1]!s_share_total($H$3,I11))/(YEAR(I10)/YEAR(I9))=1,NA(),IF($I$2="PE Band",[1]!S_STM07_IS($H$3,61,YEAR(I10)-1&"-12-31",1)/[1]!s_share_total($H$3,I10),[1]!s_stm07_bs($H$3,140,YEAR(I10)-1&"-12-31",1)/[1]!s_share_total($H$3,I10))) -> #N/A | I10: =--[1]!td(I9-$N$2) -> 45422 | J10: =IF([1]!s_dq_close(公司分析!$D$4,I10,$M$2)=0,NA(),[1]!s_dq_close(公司分析!$D$4,I10,$M$2)) -> 108.3 | K10: =H10*LEFT($K$3,LEN($K$3)-1) -> #N/A | L10: =H10*LEFT($L$3,LEN($L$3)-1) -> #N/A | M10: =H10*LEFT($M$3,LEN($M$3)-1) -> #N/A | N10: =J10/$J$64-1 -> -0.35803201 | O10: =R10/$R$64-1 -> -0.064967918 | P10: 沪深300_x0000__x0000_ | Q10: 000300.SH | R10: =IF([1]!s_dq_close($S$3,I10,$M$2)=0,NA(),[1]!s_dq_close($S$3,I10,$M$2)) -> 3962.32 | U10: 证监会门类行业 | V10: =IF(Z10="",0,RANK(Z10,Z:Z,1)) -> 0 | W10: =IF(板块成分!B12="","",板块成分!B12) -> 0007.HK | X10: =[1]!s_info_name(W10) -> 智富资源投资 | Y10: =IF($Y$3="申万一级行业",[1]!s_info_industry_sw_2021(W10,公司分析!D$5,1),IF($Y$3="申万二级行业",[1]!s_info_industry_sw_2021(W10,公司分析!D$5,2),IF($Y$3="申万三级行业",[1]!s_info_industry_sw_2021(W10,公司分析!D$5,3),IF($Y$3="wind一级行业",[1]!s_info_industry_gics(W10,1),IF($Y$3="wind二级行业",[1]!s_info_industry_gics(W10,2),IF($Y$3="wind三级行业",[1]!s_info_industry_gics(W10,3),IF($Y$3="wind四级行业",[1]!s_info_industry_gics(W10,4),IF($Y$3="证监会门类行业",[1]!s_info_industry_csrc12_n(W10,公司分析!D$5,1),"")))))))) -> 消费电子产品 | Z10: =IF(Y10=行业比较!$E$6,ROW(),"")
B11: 报表类型1 | G11: =IF(公司分析!U97="合并报表",1,IF(公司分析!U97="母公司报表",2,IF(公司分析!U97="合并报表(调整)",3,4))) -> 1 | H11: =IF(([1]!s_share_total($H$3,I11)/[1]!s_share_total($H$3,I12))/(YEAR(I11)/YEAR(I10))=1,NA(),IF($I$2="PE Band",[1]!S_STM07_IS($H$3,61,YEAR(I11)-1&"-12-31",1)/[1]!s_share_total($H$3,I11),[1]!s_stm07_bs($H$3,140,YEAR(I11)-1&"-12-31",1)/[1]!s_share_total($H$3,I11))) -> #N/A | I11: =--[1]!td(I10-$N$2) -> 45412 | J11: =IF([1]!s_dq_close(公司分析!$D$4,I11,$M$2)=0,NA(),[1]!s_dq_close(公司分析!$D$4,I11,$M$2)) -> 102.8 | K11: =H11*LEFT($K$3,LEN($K$3)-1) -> #N/A | L11: =H11*LEFT($L$3,LEN($L$3)-1) -> #N/A | M11: =H11*LEFT($M$3,LEN($M$3)-1) -> #N/A | N11: =J11/$J$64-1 -> -0.39063426 | O11: =R11/$R$64-1 -> -0.12671234 | P11: 中证100_x0000__x0000_ | Q11: 000903.SH | R11: =IF([1]!s_dq_close($S$3,I11,$M$2)=0,NA(),[1]!s_dq_close($S$3,I11,$M$2)) -> 3700.67 | V11: =IF(Z11="",0,RANK(Z11,Z:Z,1)) -> 0 | W11: =IF(板块成分!B13="","",板块成分!B13) -> 0008.HK | X11: =[1]!s_info_name(W11) -> 电讯盈科 | Y11: =IF($Y$3="申万一级行业",[1]!s_info_industry_sw_2021(W11,公司分析!D$5,1),IF($Y$3="申万二级行业",[1]!s_info_industry_sw_2021(W11,公司分析!D$5,2),IF($Y$3="申万三级行业",[1]!s_info_industry_sw_2021(W11,公司分析!D$5,3),IF($Y$3="wind一级行业",[1]!s_info_industry_gics(W11,1),IF($Y$3="wind二级行业",[1]!s_info_industry_gics(W11,2),IF($Y$3="wind三级行业",[1]!s_info_industry_gics(W11,3),IF($Y$3="wind四级行业",[1]!s_info_industry_gics(W11,4),IF($Y$3="证监会门类行业",[1]!s_info_industry_csrc12_n(W11,公司分析!D$5,1),"")))))))) -> 综合电信服务 | Z11: =IF(Y11=行业比较!$E$6,ROW(),"")
G12: =IF(公司分析!N97="合并报表",1,IF(公司分析!N97="母公司报表",2,IF(公司分析!N97="合并报表(调整)",3,4))) -> 1 | H12: =IF(([1]!s_share_total($H$3,I12)/[1]!s_share_total($H$3,I13))/(YEAR(I12)/YEAR(I11))=1,NA(),IF($I$2="PE Band",[1]!S_STM07_IS($H$3,61,YEAR(I12)-1&"-12-31",1)/[1]!s_share_total($H$3,I12),[1]!s_stm07_bs($H$3,140,YEAR(I12)-1&"-12-31",1)/[1]!s_share_total($H$3,I12))) -> #N/A | I12: =--[1]!td(I11-$N$2) -> 45405 | J12: =IF([1]!s_dq_close(公司分析!$D$4,I12,$M$2)=0,NA(),[1]!s_dq_close(公司分析!$D$4,I12,$M$2)) -> 90.35 | K12: =H12*LEFT($K$3,LEN($K$3)-1) -> #N/A | L12: =H12*LEFT($L$3,LEN($L$3)-1) -> #N/A | M12: =H12*LEFT($M$3,LEN($M$3)-1) -> #N/A | N12: =J12/$J$64-1 -> -0.46443391 | O12: =R12/$R$64-1 -> -0.18607807 | P12: 深证成份指数_x0000__x0000__x0000__x0000__x0000__x0000_ | Q12: 399001.SZ | R12: =IF([1]!s_dq_close($S$3,I12,$M$2)=0,NA(),[1]!s_dq_close($S$3,I12,$M$2)) -> 3449.1 | V12: =IF(Z12="",0,RANK(Z12,Z:Z,1)) -> 0 | W12: =IF(板块成分!B14="","",板块成分!B14) -> 0009.HK | X12: =[1]!s_info_name(W12) -> 金奥国际 | Y12: =IF($Y$3="申万一级行业",[1]!s_info_industry_sw_2021(W12,公司分析!D$5,1),IF($Y$3="申万二级行业",[1]!s_info_industry_sw_2021(W12,公司分析!D$5,2),IF($Y$3="申万三级行业",[1]!s_info_industry_sw_2021(W12,公司分析!D$5,3),IF($Y$3="wind一级行业",[1]!s_info_industry_gics(W12,1),IF($Y$3="wind二级行业",[1]!s_info_industry_gics(W12,2),IF($Y$3="wind三级行业",[1]!s_info_industry_gics(W12,3),IF($Y$3="wind四级行业",[1]!s_info_industry_gics(W12,4),IF($Y$3="证监会门类行业",[1]!s_info_industry_csrc12_n(W12,公司分析!D$5,1),"")))))))) -> 房地产经营公司 | Z12: =IF(Y12=行业比较!$E$6,ROW(),"")
G13: =IF(公司分析!O97="合并报表",1,IF(公司分析!O97="母公司报表",2,IF(公司分析!O97="合并报表(调整)",3,4))) -> 1 | H13: =IF(([1]!s_share_total($H$3,I13)/[1]!s_share_total($H$3,I14))/(YEAR(I13)/YEAR(I12))=1,NA(),IF($I$2="PE Band",[1]!S_STM07_IS($H$3,61,YEAR(I13)-1&"-12-31",1)/[1]!s_share_total($H$3,I13),[1]!s_stm07_bs($H$3,140,YEAR(I13)-1&"-12-31",1)/[1]!s_share_total($H$3,I13))) -> #N/A | I13: =--[1]!td(I12-$N$2) -> 45398 | J13: =IF([1]!s_dq_close(公司分析!$D$4,I13,$M$2)=0,NA(),[1]!s_dq_close(公司分析!$D$4,I13,$M$2)) -> 86.85 | K13: =H13*LEFT($K$3,LEN($K$3)-1) -> #N/A | L13: =H13*LEFT($L$3,LEN($L$3)-1) -> #N/A | M13: =H13*LEFT($M$3,LEN($M$3)-1) -> #N/A | N13: =J13/$J$64-1 -> -0.48518079 | O13: =R13/$R$64-1 -> -0.21233095 | P13: 深证100指数_x0000__x0000__x0000__x0000_ | Q13: 399004.SZ | R13: =IF([1]!s_dq_close($S$3,I13,$M$2)=0,NA(),[1]!s_dq_close($S$3,I13,$M$2)) -> 3337.85 | V13: =IF(Z13="",0,RANK(Z13,Z:Z,1)) -> 0 | W13: =IF(板块成分!B15="","",板块成分!B15) -> 0010.HK | X13: =[1]!s_info_name(W13) -> 恒隆集团 | Y13: =IF($Y$3="申万一级行业",[1]!s_info_industry_sw_2021(W13,公司分析!D$5,1),IF($Y$3="申万二级行业",[1]!s_info_industry_sw_2021(W13,公司分析!D$5,2),IF($Y$3="申万三级行业",[1]!s_info_industry_sw_2021(W13,公司分析!D$5,3),IF($Y$3="wind一级行业",[1]!s_info_industry_gics(W13,1),IF($Y$3="wind二级行业",[1]!s_info_industry_gics(W13,2),IF($Y$3="wind三级行业",[1]!s_info_industry_gics(W13,3),IF($Y$3="wind四级行业",[1]!s_info_industry_gics(W13,4),IF($Y$3="证监会门类行业",[1]!s_info_industry_csrc12_n(W13,公司分析!D$5,1),"")))))))) -> 房地产经营公司 | Z13: =IF(Y13=行业比较!$E$6,ROW(),"")
G14: =IF(公司分析!P97="合并报表",1,IF(公司分析!P97="母公司报表",2,IF(公司分析!P97="合并报表(调整)",3,4))) -> 1 | H14: =IF(([1]!s_share_total($H$3,I14)/[1]!s_share_total($H$3,I15))/(YEAR(I14)/YEAR(I13))=1,NA(),IF($I$2="PE Band",[1]!S_STM07_IS($H$3,61,YEAR(I14)-1&"-12-31",1)/[1]!s_share_total($H$3,I14),[1]!s_stm07_bs($H$3,140,YEAR(I14)-1&"-12-31",1)/[1]!s_share_total($H$3,I14))) -> #N/A | I14: =--[1]!td(I13-$N$2) -> 45391 | J14: =IF([1]!s_dq_close(公司分析!$D$4,I14,$M$2)=0,NA(),[1]!s_dq_close(公司分析!$D$4,I14,$M$2)) -> 89.35 | K14: =H14*LEFT($K$3,LEN($K$3)-1) -> #N/A | L14: =H14*LEFT($L$3,LEN($L$3)-1) -> #N/A | M14: =H14*LEFT($M$3,LEN($M$3)-1) -> #N/A | N14: =J14/$J$64-1 -> -0.47036159 | O14: =R14/$R$64-1 -> -0.17920158 | P14: 中小板指_x0000__x0000__x0000__x0000_ | Q14: 399005.SZ | R14: =IF([1]!s_dq_close($S$3,I14,$M$2)=0,NA(),[1]!s_dq_close($S$3,I14,$M$2)) -> 3478.24 | V14: =IF(Z14="",0,RANK(Z14,Z:Z,1)) -> 0 | W14: =IF(板块成分!B16="","",板块成分!B16) -> 0011.HK | X14: =[1]!s_info_name(W14) -> 恒生银行 | Y14: =IF($Y$3="申万一级行业",[1]!s_info_industry_sw_2021(W14,公司分析!D$5,1),IF($Y$3="申万二级行业",[1]!s_info_industry_sw_2021(W14,公司分析!D$5,2),IF($Y$3="申万三级行业",[1]!s_info_industry_sw_2021(W14,公司分析!D$5,3),IF($Y$3="wind一级行业",[1]!s_info_industry_gics(W14,1),IF($Y$3="wind二级行业",[1]!s_info_industry_gics(W14,2),IF($Y$3="wind三级行业",[1]!s_info_industry_gics(W14,3),IF($Y$3="wind四级行业",[1]!s_info_industry_gics(W14,4),IF($Y$3="证监会门类行业",[1]!s_info_industry_csrc12_n(W14,公司分析!D$5,1),"")))))))) -> 多元化银行 | Z14: =IF(Y14=行业比较!$E$6,ROW(),"")
B15: 机构代码 | C15: 机构 | D15: 代码 | H15: =IF(([1]!s_share_total($H$3,I15)/[1]!s_share_total($H$3,I16))/(YEAR(I15)/YEAR(I14))=1,NA(),IF($I$2="PE Band",[1]!S_STM07_IS($H$3,61,YEAR(I15)-1&"-12-31",1)/[1]!s_share_total($H$3,I15),[1]!s_stm07_bs($H$3,140,YEAR(I15)-1&"-12-31",1)/[1]!s_share_total($H$3,I15))) -> #N/A | I15: =--[1]!td(I14-$N$2) -> 45384 | J15: =IF([1]!s_dq_close(公司分析!$D$4,I15,$M$2)=0,NA(),[1]!s_dq_close(公司分析!$D$4,I15,$M$2)) -> 90.65 | K15: =H15*LEFT($K$3,LEN($K$3)-1) -> #N/A | L15: =H15*LEFT($L$3,LEN($L$3)-1) -> #N/A | M15: =H15*LEFT($M$3,LEN($M$3)-1) -> #N/A | N15: =J15/$J$64-1 -> -0.4626556 | O15: =R15/$R$64-1 -> -0.16389114 | P15: 创业板指_x0000__x0000__x0000__x0000_ | Q15: 399006.SZ | R15: =IF([1]!s_dq_close($S$3,I15,$M$2)=0,NA(),[1]!s_dq_close($S$3,I15,$M$2)) -> 3543.12 | V15: =IF(Z15="",0,RANK(Z15,Z:Z,1)) -> 0 | W15: =IF(板块成分!B17="","",板块成分!B17) -> 0012.HK | X15: =[1]!s_info_name(W15) -> 恒基地产 | Y15: =IF($Y$3="申万一级行业",[1]!s_info_industry_sw_2021(W15,公司分析!D$5,1),IF($Y$3="申万二级行业",[1]!s_info_industry_sw_2021(W15,公司分析!D$5,2),IF($Y$3="申万三级行业",[1]!s_info_industry_sw_2021(W15,公司分析!D$5,3),IF($Y$3="wind一级行业",[1]!s_info_industry_gics(W15,1),IF($Y$3="wind二级行业",[1]!s_info_industry_gics(W15,2),IF($Y$3="wind三级行业",[1]!s_info_industry_gics(W15,3),IF($Y$3="wind四级行业",[1]!s_info_industry_gics(W15,4),IF($Y$3="证监会门类行业",[1]!s_info_industry_csrc12_n(W15,公司分析!D$5,1),"")))))))) -> 多样化房地产活动 | Z15: =IF(Y15=行业比较!$E$6,ROW(),"")
B16: 1 | C16: 申银万国 | D16: =B16 -> 1 | H16: =IF(([1]!s_share_total($H$3,I16)/[1]!s_share_total($H$3,I17))/(YEAR(I16)/YEAR(I15))=1,NA(),IF($I$2="PE Band",[1]!S_STM07_IS($H$3,61,YEAR(I16)-1&"-12-31",1)/[1]!s_share_total($H$3,I16),[1]!s_stm07_bs($H$3,140,YEAR(I16)-1&"-12-31",1)/[1]!s_share_total($H$3,I16))) -> #N/A | I16: =--[1]!td(I15-$N$2) -> 45377 | J16: =IF([1]!s_dq_close(公司分析!$D$4,I16,$M$2)=0,NA(),[1]!s_dq_close(公司分析!$D$4,I16,$M$2)) -> 84.8 | K16: =H16*LEFT($K$3,LEN($K$3)-1) -> #N/A | L16: =H16*LEFT($L$3,LEN($L$3)-1) -> #N/A | M16: =H16*LEFT($M$3,LEN($M$3)-1) -> #N/A | N16: =J16/$J$64-1 -> -0.49733254 | O16: =R16/$R$64-1 -> -0.18079445 | P16: 深证新指数_x0000__x0000__x0000__x0000__x0000_ | Q16: 399100.SZ | R16: =IF([1]!s_dq_close($S$3,I16,$M$2)=0,NA(),[1]!s_dq_close($S$3,I16,$M$2)) -> 3471.49 | V16: =IF(Z16="",0,RANK(Z16,Z:Z,1)) -> 0 | W16: =IF(板块成分!B18="","",板块成分!B18) -> 0013.HK | X16: =[1]!s_info_name(W16) -> 和黄医药 | Y16: =IF($Y$3="申万一级行业",[1]!s_info_industry_sw_2021(W16,公司分析!D$5,1),IF($Y$3="申万二级行业",[1]!s_info_industry_sw_2021(W16,公司分析!D$5,2),IF($Y$3="申万三级行业",[1]!s_info_industry_sw_2021(W16,公司分析!D$5,3),IF($Y$3="wind一级行业",[1]!s_info_industry_gics(W16,1),IF($Y$3="wind二级行业",[1]!s_info_industry_gics(W16,2),IF($Y$3="wind三级行业",[1]!s_info_industry_gics(W16,3),IF($Y$3="wind四级行业",[1]!s_info_industry_gics(W16,4),IF($Y$3="证监会门类行业",[1]!s_info_industry_csrc12_n(W16,公司分析!D$5,1),"")))))))) -> 西药 | Z16: =IF(Y16=行业比较!$E$6,ROW(),"")
B17: 2 | C17: 国泰君安 | D17: =B17 -> 2 | H17: =IF(([1]!s_share_total($H$3,I17)/[1]!s_share_total($H$3,I18))/(YEAR(I17)/YEAR(I16))=1,NA(),IF($I$2="PE Band",[1]!S_STM07_IS($H$3,61,YEAR(I17)-1&"-12-31",1)/[1]!s_share_total($H$3,I17),[1]!s_stm07_bs($H$3,140,YEAR(I17)-1&"-12-31",1)/[1]!s_share_total($H$3,I17))) -> #N/A | I17: =--[1]!td(I16-$N$2) -> 45370 | J17: =IF([1]!s_dq_close(公司分析!$D$4,I17,$M$2)=0,NA(),[1]!s_dq_close(公司分析!$D$4,I17,$M$2)) -> 92 | K17: =H17*LEFT($K$3,LEN($K$3)-1) -> #N/A | L17: =H17*LEFT($L$3,LEN($L$3)-1) -> #N/A | M17: =H17*LEFT($M$3,LEN($M$3)-1) -> #N/A | N17: =J17/$J$64-1 -> -0.45465323 | O17: =R17/$R$64-1 -> -0.16734826 | P17: 中小板综_x0000__x0000__x0000__x0000_ | Q17: 399101.SZ | R17: =IF([1]!s_dq_close($S$3,I17,$M$2)=0,NA(),[1]!s_dq_close($S$3,I17,$M$2)) -> 3528.47 | V17: =IF(Z17="",0,RANK(Z17,Z:Z,1)) -> 0 | W17: =IF(板块成分!B19="","",板块成分!B19) -> 0014.HK | X17: =[1]!s_info_name(W17) -> 希慎兴业 | Y17: =IF($Y$3="申万一级行业",[1]!s_info_industry_sw_2021(W17,公司分析!D$5,1),IF($Y$3="申万二级行业",[1]!s_info_industry_sw_2021(W17,公司分析!D$5,2),IF($Y$3="申万三级行业",[1]!s_info_industry_sw_2021(W17,公司分析!D$5,3),IF($Y$3="wind一级行业",[1]!s_info_industry_gics(W17,1),IF($Y$3="wind二级行业",[1]!s_info_industry_gics(W17,2),IF($Y$3="wind三级行业",[1]!s_info_industry_gics(W17,3),IF($Y$3="wind四级行业",[1]!s_info_industry_gics(W17,4),IF($Y$3="证监会门类行业",[1]!s_info_industry_csrc12_n(W17,公司分析!D$5,1),"")))))))) -> 房地产经营公司 | Z17: =IF(Y17=行业比较!$E$6,ROW(),"")
B18: 3 | C18: 中银国际 | D18: =B18 -> 3 | H18: =IF(([1]!s_share_total($H$3,I18)/[1]!s_share_total($H$3,I19))/(YEAR(I18)/YEAR(I17))=1,NA(),IF($I$2="PE Band",[1]!S_STM07_IS($H$3,61,YEAR(I18)-1&"-12-31",1)/[1]!s_share_total($H$3,I18),[1]!s_stm07_bs($H$3,140,YEAR(I18)-1&"-12-31",1)/[1]!s_share_total($H$3,I18))) -> #N/A | I18: =--[1]!td(I17-$N$2) -> 45363 | J18: =IF([1]!s_dq_close(公司分析!$D$4,I18,$M$2)=0,NA(),[1]!s_dq_close(公司分析!$D$4,I18,$M$2)) -> 103.6 | K18: =H18*LEFT($K$3,LEN($K$3)-1) -> #N/A | L18: =H18*LEFT($L$3,LEN($L$3)-1) -> #N/A | M18: =H18*LEFT($M$3,LEN($M$3)-1) -> #N/A | N18: =J18/$J$64-1 -> -0.38589212 | O18: =R18/$R$64-1 -> -0.14010662 | P18: 深证综合指数_x0000__x0000__x0000__x0000__x0000__x0000_ | Q18: 399106.SZ | R18: =IF([1]!s_dq_close($S$3,I18,$M$2)=0,NA(),[1]!s_dq_close($S$3,I18,$M$2)) -> 3643.91 | V18: =IF(Z18="",0,RANK(Z18,Z:Z,1)) -> 0 | W18: =IF(板块成分!B20="","",板块成分!B20) -> 0016.HK | X18: =[1]!s_info_name(W18) -> 新鸿基地产 | Y18: =IF($Y$3="申万一级行业",[1]!s_info_industry_sw_2021(W18,公司分析!D$5,1),IF($Y$3="申万二级行业",[1]!s_info_industry_sw_2021(W18,公司分析!D$5,2),IF($Y$3="申万三级行业",[1]!s_info_industry_sw_2021(W18,公司分析!D$5,3),IF($Y$3="wind一级行业",[1]!s_info_industry_gics(W18,1),IF($Y$3="wind二级行业",[1]!s_info_industry_gics(W18,2),IF($Y$3="wind三级行业",[1]!s_info_industry_gics(W18,3),IF($Y$3="wind四级行业",[1]!s_info_industry_gics(W18,4),IF($Y$3="证监会门类行业",[1]!s_info_industry_csrc12_n(W18,公司分析!D$5,1),"")))))))) -> 多样化房地产活动 | Z18: =IF(Y18=行业比较!$E$6,ROW(),"")
B19: 4 | C19: 国信证券 | D19: =B19 -> 4 | H19: =IF(([1]!s_share_total($H$3,I19)/[1]!s_share_total($H$3,I20))/(YEAR(I19)/YEAR(I18))=1,NA(),IF($I$2="PE Band",[1]!S_STM07_IS($H$3,61,YEAR(I19)-1&"-12-31",1)/[1]!s_share_total($H$3,I19),[1]!s_stm07_bs($H$3,140,YEAR(I19)-1&"-12-31",1)/[1]!s_share_total($H$3,I19))) -> #N/A | I19: =--[1]!td(I18-$N$2) -> 45356 | J19: =IF([1]!s_dq_close(公司分析!$D$4,I19,$M$2)=0,NA(),[1]!s_dq_close(公司分析!$D$4,I19,$M$2)) -> 80.3 | K19: =H19*LEFT($K$3,LEN($K$3)-1) -> #N/A | L19: =H19*LEFT($L$3,LEN($L$3)-1) -> #N/A | M19: =H19*LEFT($M$3,LEN($M$3)-1) -> #N/A | N19: =J19/$J$64-1 -> -0.52400711 | O19: =R19/$R$64-1 -> -0.21562524 | P19: 深证A股指数_x0000__x0000__x0000__x0000__x0000_ | Q19: 399107.SZ | R19: =IF([1]!s_dq_close($S$3,I19,$M$2)=0,NA(),[1]!s_dq_close($S$3,I19,$M$2)) -> 3323.89 | V19: =IF(Z19="",0,RANK(Z19,Z:Z,1)) -> 0 | W19: =IF(板块成分!B21="","",板块成分!B21) -> 0017.HK | X19: =[1]!s_info_name(W19) -> 新世界发展 | Y19: =IF($Y$3="申万一级行业",[1]!s_info_industry_sw_2021(W19,公司分析!D$5,1),IF($Y$3="申万二级行业",[1]!s_info_industry_sw_2021(W19,公司分析!D$5,2),IF($Y$3="申万三级行业",[1]!s_info_industry_sw_2021(W19,公司分析!D$5,3),IF($Y$3="wind一级行业",[1]!s_info_industry_gics(W19,1),IF($Y$3="wind二级行业",[1]!s_info_industry_gics(W19,2),IF($Y$3="wind三级行业",[1]!s_info_industry_gics(W19,3),IF($Y$3="wind四级行业",[1]!s_info_industry_gics(W19,4),IF($Y$3="证监会门类行业",[1]!s_info_industry_csrc12_n(W19,公司分析!D$5,1),"")))))))) -> 多样化房地产活动 | Z19: =IF(Y19=行业比较!$E$6,ROW(),"")
B20: 5 | C20: 海通证券 | D20: =B20 -> 5 | H20: =IF(([1]!s_share_total($H$3,I20)/[1]!s_share_total($H$3,I21))/(YEAR(I20)/YEAR(I19))=1,NA(),IF($I$2="PE Band",[1]!S_STM07_IS($H$3,61,YEAR(I20)-1&"-12-31",1)/[1]!s_share_total($H$3,I20),[1]!s_stm07_bs($H$3,140,YEAR(I20)-1&"-12-31",1)/[1]!s_share_total($H$3,I20))) -> #N/A | I20: =--[1]!td(I19-$N$2) -> 45349 | J20: =IF([1]!s_dq_close(公司分析!$D$4,I20,$M$2)=0,NA(),[1]!s_dq_close(公司分析!$D$4,I20,$M$2)) -> 80.15 | K20: =H20*LEFT($K$3,LEN($K$3)-1) -> #N/A | L20: =H20*LEFT($L$3,LEN($L$3)-1) -> #N/A | M20: =H20*LEFT($M$3,LEN($M$3)-1) -> #N/A | N20: =J20/$J$64-1 -> -0.52489627 | O20: =R20/$R$64-1 -> -0.17331858 | P20: 深证B股指数_x0000__x0000__x0000__x0000__x0000_ | Q20: 399108.SZ | R20: =IF([1]!s_dq_close($S$3,I20,$M$2)=0,NA(),[1]!s_dq_close($S$3,I20,$M$2)) -> 3503.17 | V20: =IF(Z20="",0,RANK(Z20,Z:Z,1)) -> 0 | W20: =IF(板块成分!B22="","",板块成分!B22) -> 0018.HK | X20: =[1]!s_info_name(W20) -> 东方企控集团 | Y20: =IF($Y$3="申万一级行业",[1]!s_info_industry_sw_2021(W20,公司分析!D$5,1),IF($Y$3="申万二级行业",[1]!s_info_industry_sw_2021(W20,公司分析!D$5,2),IF($Y$3="申万三级行业",[1]!s_info_industry_sw_2021(W20,公司分析!D$5,3),IF($Y$3="wind一级行业",[1]!s_info_industry_gics(W20,1),IF($Y$3="wind二级行业",[1]!s_info_industry_gics(W20,2),IF($Y$3="wind三级行业",[1]!s_info_industry_gics(W20,3),IF($Y$3="wind四级行业",[1]!s_info_industry_gics(W20,4),IF($Y$3="证监会门类行业",[1]!s_info_industry_csrc12_n(W20,公司分析!D$5,1),"")))))))) -> 出版 | Z20: =IF(Y20=行业比较!$E$6,ROW(),"")
B21: 6 | C21: 招商证券 | D21: =B21 -> 6 | H21: =IF(([1]!s_share_total($H$3,I21)/[1]!s_share_total($H$3,I22))/(YEAR(I21)/YEAR(I20))=1,NA(),IF($I$2="PE Band",[1]!S_STM07_IS($H$3,61,YEAR(I21)-1&"-12-31",1)/[1]!s_share_total($H$3,I21),[1]!s_stm07_bs($H$3,140,YEAR(I21)-1&"-12-31",1)/[1]!s_share_total($H$3,I21))) -> #N/A | I21: =--[1]!td(I20-$N$2) -> 45342 | J21: =IF([1]!s_dq_close(公司分析!$D$4,I21,$M$2)=0,NA(),[1]!s_dq_close(公司分析!$D$4,I21,$M$2)) -> 79.2 | K21: =H21*LEFT($K$3,LEN($K$3)-1) -> #N/A | L21: =H21*LEFT($L$3,LEN($L$3)-1) -> #N/A | M21: =H21*LEFT($M$3,LEN($M$3)-1) -> #N/A | N21: =J21/$J$64-1 -> -0.53052756 | O21: =R21/$R$64-1 -> -0.22966375 | P21: 申万50_x0000__x0000_ | Q21: 801001.SI | R21: =IF([1]!s_dq_close($S$3,I21,$M$2)=0,NA(),[1]!s_dq_close($S$3,I21,$M$2)) -> 3264.4 | V21: =IF(Z21="",0,RANK(Z21,Z:Z,1)) -> 0 | W21: =IF(板块成分!B23="","",板块成分!B23) -> 0019.HK | X21: =[1]!s_info_name(W21) -> 太古股份公司A | Y21: =IF($Y$3="申万一级行业",[1]!s_info_industry_sw_2021(W21,公司分析!D$5,1),IF($Y$3="申万二级行业",[1]!s_info_industry_sw_2021(W21,公司分析!D$5,2),IF($Y$3="申万三级行业",[1]!s_info_industry_sw_2021(W21,公司分析!D$5,3),IF($Y$3="wind一级行业",[1]!s_info_industry_gics(W21,1),IF($Y$3="wind二级行业",[1]!s_info_industry_gics(W21,2),IF($Y$3="wind三级行业",[1]!s_info_industry_gics(W21,3),IF($Y$3="wind四级行业",[1]!s_info_industry_gics(W21,4),IF($Y$3="证监会门类行业",[1]!s_info_industry_csrc12_n(W21,公司分析!D$5,1),"")))))))) -> 综合类行业 | Z21: =IF(Y21=行业比较!$E$6,ROW(),"")
B22: 7 | C22: 光大证券 | D22: =B22 -> 7 | H22: =IF(([1]!s_share_total($H$3,I22)/[1]!s_share_total($H$3,I23))/(YEAR(I22)/YEAR(I21))=1,NA(),IF($I$2="PE Band",[1]!S_STM07_IS($H$3,61,YEAR(I22)-1&"-12-31",1)/[1]!s_share_total($H$3,I22),[1]!s_stm07_bs($H$3,140,YEAR(I22)-1&"-12-31",1)/[1]!s_share_total($H$3,I22))) -> #N/A | I22: =--[1]!td(I21-$N$2) -> 45330 | J22: =IF([1]!s_dq_close(公司分析!$D$4,I22,$M$2)=0,NA(),[1]!s_dq_close(公司分析!$D$4,I22,$M$2)) -> 76.15 | K22: =H22*LEFT($K$3,LEN($K$3)-1) -> #N/A | L22: =H22*LEFT($L$3,LEN($L$3)-1) -> #N/A | M22: =H22*LEFT($M$3,LEN($M$3)-1) -> #N/A | N22: =J22/$J$64-1 -> -0.54860699 | O22: =R22/$R$64-1 -> -0.25228253 | P22: 申万中小板_x0000__x0000__x0000__x0000__x0000_ | Q22: 801002.SI | R22: =IF([1]!s_dq_close($S$3,I22,$M$2)=0,NA(),[1]!s_dq_close($S$3,I22,$M$2)) -> 3168.55 | V22: =IF(Z22="",0,RANK(Z22,Z:Z,1)) -> 0 | W22: =IF(板块成分!B24="","",板块成分!B24) -> 0020.HK | X22: =[1]!s_info_name(W22) -> 商汤-W | Y22: =IF($Y$3="申万一级行业",[1]!s_info_industry_sw_2021(W22,公司分析!D$5,1),IF($Y$3="申万二级行业",[1]!s_info_industry_sw_2021(W22,公司分析!D$5,2),IF($Y$3="申万三级行业",[1]!s_info_industry_sw_2021(W22,公司分析!D$5,3),IF($Y$3="wind一级行业",[1]!s_info_industry_gics(W22,1),IF($Y$3="wind二级行业",[1]!s_info_industry_gics(W22,2),IF($Y$3="wind三级行业",[1]!s_info_industry_gics(W22,3),IF($Y$3="wind四级行业",[1]!s_info_industry_gics(W22,4),IF($Y$3="证监会门类行业",[1]!s_info_industry_csrc12_n(W22,公司分析!D$5,1),"")))))))) -> 系统软件 | Z22: =IF(Y22=行业比较!$E$6,ROW(),"")
B23: 8 | C23: 中信证券 | D23: =B23 -> 8 | H23: =IF(([1]!s_share_total($H$3,I23)/[1]!s_share_total($H$3,I24))/(YEAR(I23)/YEAR(I22))=1,NA(),IF($I$2="PE Band",[1]!S_STM07_IS($H$3,61,YEAR(I23)-1&"-12-31",1)/[1]!s_share_total($H$3,I23),[1]!s_stm07_bs($H$3,140,YEAR(I23)-1&"-12-31",1)/[1]!s_share_total($H$3,I23))) -> #N/A | I23: =--[1]!td(I22-$N$2) -> 45323 | J23: =IF([1]!s_dq_close(公司分析!$D$4,I23,$M$2)=0,NA(),[1]!s_dq_close(公司分析!$D$4,I23,$M$2)) -> 72.1 | K23: =H23*LEFT($K$3,LEN($K$3)-1) -> #N/A | L23: =H23*LEFT($L$3,LEN($L$3)-1) -> #N/A | M23: =H23*LEFT($M$3,LEN($M$3)-1) -> #N/A | N23: =J23/$J$64-1 -> -0.57261411 | O23: =R23/$R$64-1 -> -0.27649417 | P23: 申万A股_x0000__x0000__x0000_ | Q23: 801003.SI | R23: =IF([1]!s_dq_close($S$3,I23,$M$2)=0,NA(),[1]!s_dq_close($S$3,I23,$M$2)) -> 3065.95 | V23: =IF(Z23="",0,RANK(Z23,Z:Z,1)) -> 0 | W23: =IF(板块成分!B25="","",板块成分!B25) -> 0021.HK | X23: =[1]!s_info_name(W23) -> 大中华控股 | Y23: =IF($Y$3="申万一级行业",[1]!s_info_industry_sw_2021(W23,公司分析!D$5,1),IF($Y$3="申万二级行业",[1]!s_info_industry_sw_2021(W23,公司分析!D$5,2),IF($Y$3="申万三级行业",[1]!s_info_industry_sw_2021(W23,公司分析!D$5,3),IF($Y$3="wind一级行业",[1]!s_info_industry_gics(W23,1),IF($Y$3="wind二级行业",[1]!s_info_industry_gics(W23,2),IF($Y$3="wind三级行业",[1]!s_info_industry_gics(W23,3),IF($Y$3="wind四级行业",[1]!s_info_industry_gics(W23,4),IF($Y$3="证监会门类行业",[1]!s_info_industry_csrc12_n(W23,公司分析!D$5,1),"")))))))) -> 房地产经营公司 | Z23: =IF(Y23=行业比较!$E$6,ROW(),"")
B24: 9 | C24: 国金证券 | D24: =B24 -> 9 | H24: =IF(([1]!s_share_total($H$3,I24)/[1]!s_share_total($H$3,I25))/(YEAR(I24)/YEAR(I23))=1,NA(),IF($I$2="PE Band",[1]!S_STM07_IS($H$3,61,YEAR(I24)-1&"-12-31",1)/[1]!s_share_total($H$3,I24),[1]!s_stm07_bs($H$3,140,YEAR(I24)-1&"-12-31",1)/[1]!s_share_total($H$3,I24))) -> #N/A | I24: =--[1]!td(I23-$N$2) -> 45316 | J24: =IF([1]!s_dq_close(公司分析!$D$4,I24,$M$2)=0,NA(),[1]!s_dq_close(公司分析!$D$4,I24,$M$2)) -> 77.8 | K24: =H24*LEFT($K$3,LEN($K$3)-1) -> #N/A | L24: =H24*LEFT($L$3,LEN($L$3)-1) -> #N/A | M24: =H24*LEFT($M$3,LEN($M$3)-1) -> #N/A | N24: =J24/$J$64-1 -> -0.53882632 | O24: =R24/$R$64-1 -> -0.21874019 | P24: 申万创业板_x0000__x0000__x0000__x0000__x0000_ | Q24: 801005.SI | R24: =IF([1]!s_dq_close($S$3,I24,$M$2)=0,NA(),[1]!s_dq_close($S$3,I24,$M$2)) -> 3310.69 | V24: =IF(Z24="",0,RANK(Z24,Z:Z,1)) -> 0 | W24: =IF(板块成分!B26="","",板块成分!B26) -> 0022.HK | X24: =[1]!s_info_name(W24) -> 茂盛控股 | Y24: =IF($Y$3="申万一级行业",[1]!s_info_industry_sw_2021(W24,公司分析!D$5,1),IF($Y$3="申万二级行业",[1]!s_info_industry_sw_2021(W24,公司分析!D$5,2),IF($Y$3="申万三级行业",[1]!s_info_industry_sw_2021(W24,公司分析!D$5,3),IF($Y$3="wind一级行业",[1]!s_info_industry_gics(W24,1),IF($Y$3="wind二级行业",[1]!s_info_industry_gics(W24,2),IF($Y$3="wind三级行业",[1]!s_info_industry_gics(W24,3),IF($Y$3="wind四级行业",[1]!s_info_industry_gics(W24,4),IF($Y$3="证监会门类行业",[1]!s_info_industry_csrc12_n(W24,公司分析!D$5,1),"")))))))) -> 酒店、度假村与豪华游轮 | Z24: =IF(Y24=行业比较!$E$6,ROW(),"")
B25: 10 | C25: 兴业证券 | D25: =B25 -> 10 | H25: =IF(([1]!s_share_total($H$3,I25)/[1]!s_share_total($H$3,I26))/(YEAR(I25)/YEAR(I24))=1,NA(),IF($I$2="PE Band",[1]!S_STM07_IS($H$3,61,YEAR(I25)-1&"-12-31",1)/[1]!s_share_total($H$3,I25),[1]!s_stm07_bs($H$3,140,YEAR(I25)-1&"-12-31",1)/[1]!s_share_total($H$3,I25))) -> #N/A | I25: =--[1]!td(I24-$N$2) -> 45309 | J25: =IF([1]!s_dq_close(公司分析!$D$4,I25,$M$2)=0,NA(),[1]!s_dq_close(公司分析!$D$4,I25,$M$2)) -> 77.25 | K25: =H25*LEFT($K$3,LEN($K$3)-1) -> #N/A | L25: =H25*LEFT($L$3,LEN($L$3)-1) -> #N/A | M25: =H25*LEFT($M$3,LEN($M$3)-1) -> #N/A | N25: =J25/$J$64-1 -> -0.54208654 | O25: =R25/$R$64-1 -> -0.25050559 | P25: 申万300_x0000__x0000_ | Q25: 801300.SI | R25: =IF([1]!s_dq_close($S$3,I25,$M$2)=0,NA(),[1]!s_dq_close($S$3,I25,$M$2)) -> 3176.08 | V25: =IF(Z25="",0,RANK(Z25,Z:Z,1)) -> 0 | W25: =IF(板块成分!B27="","",板块成分!B27) -> 0023.HK | X25: =[1]!s_info_name(W25) -> 东亚银行 | Y25: =IF($Y$3="申万一级行业",[1]!s_info_industry_sw_2021(W25,公司分析!D$5,1),IF($Y$3="申万二级行业",[1]!s_info_industry_sw_2021(W25,公司分析!D$5,2),IF($Y$3="申万三级行业",[1]!s_info_industry_sw_2021(W25,公司分析!D$5,3),IF($Y$3="wind一级行业",[1]!s_info_industry_gics(W25,1),IF($Y$3="wind二级行业",[1]!s_info_industry_gics(W25,2),IF($Y$3="wind三级行业",[1]!s_info_industry_gics(W25,3),IF($Y$3="wind四级行业",[1]!s_info_industry_gics(W25,4),IF($Y$3="证监会门类行业",[1]!s_info_industry_csrc12_n(W25,公司分析!D$5,1),"")))))))) -> 多元化银行 | Z25: =IF(Y25=行业比较!$E$6,ROW(),"")
B26: 11 | C26: 东方证券 | D26: =B26 -> 11 | H26: =IF(([1]!s_share_total($H$3,I26)/[1]!s_share_total($H$3,I27))/(YEAR(I26)/YEAR(I25))=1,NA(),IF($I$2="PE Band",[1]!S_STM07_IS($H$3,61,YEAR(I26)-1&"-12-31",1)/[1]!s_share_total($H$3,I26),[1]!s_stm07_bs($H$3,140,YEAR(I26)-1&"-12-31",1)/[1]!s_share_total($H$3,I26))) -> #N/A | I26: =--[1]!td(I25-$N$2) -> 45302 | J26: =IF([1]!s_dq_close(公司分析!$D$4,I26,$M$2)=0,NA(),[1]!s_dq_close(公司分析!$D$4,I26,$M$2)) -> 86.95 | K26: =H26*LEFT($K$3,LEN($K$3)-1) -> #N/A | L26: =H26*LEFT($L$3,LEN($L$3)-1) -> #N/A | M26: =H26*LEFT($M$3,LEN($M$3)-1) -> #N/A | N26: =J26/$J$64-1 -> -0.48458803 | O26: =R26/$R$64-1 -> -0.17335397 | P26: 申万基金重仓_x0000__x0000__x0000__x0000__x0000__x0000_ | Q26: 801901.SI | R26: =IF([1]!s_dq_close($S$3,I26,$M$2)=0,NA(),[1]!s_dq_close($S$3,I26,$M$2)) -> 3503.02 | V26: =IF(Z26="",0,RANK(Z26,Z:Z,1)) -> 0 | W26: =IF(板块成分!B28="","",板块成分!B28) -> 0025.HK | X26: =[1]!s_info_name(W26) -> CHEVALIER INT'L | Y26: =IF($Y$3="申万一级行业",[1]!s_info_industry_sw_2021(W26,公司分析!D$5,1),IF($Y$3="申万二级行业",[1]!s_info_industry_sw_2021(W26,公司分析!D$5,2),IF($Y$3="申万三级行业",[1]!s_info_industry_sw_2021(W26,公司分析!D$5,3),IF($Y$3="wind一级行业",[1]!s_info_industry_gics(W26,1),IF($Y$3="wind二级行业",[1]!s_info_industry_gics(W26,2),IF($Y$3="wind三级行业",[1]!s_info_industry_gics(W26,3),IF($Y$3="wind四级行业",[1]!s_info_industry_gics(W26,4),IF($Y$3="证监会门类行业",[1]!s_info_industry_csrc12_n(W26,公司分析!D$5,1),"")))))))) -> 综合类行业 | Z26: =IF(Y26=行业比较!$E$6,ROW(),"")
B27: 12 | C27: 长江证券 | D27: =B27 -> 12 | H27: =IF(([1]!s_share_total($H$3,I27)/[1]!s_share_total($H$3,I28))/(YEAR(I27)/YEAR(I26))=1,NA(),IF($I$2="PE Band",[1]!S_STM07_IS($H$3,61,YEAR(I27)-1&"-12-31",1)/[1]!s_share_total($H$3,I27),[1]!s_stm07_bs($H$3,140,YEAR(I27)-1&"-12-31",1)/[1]!s_share_total($H$3,I27))) -> #N/A | I27: =--[1]!td(I26-$N$2) -> 45295 | J27: =IF([1]!s_dq_close(公司分析!$D$4,I27,$M$2)=0,NA(),[1]!s_dq_close(公司分析!$D$4,I27,$M$2)) -> 94.2 | K27: =H27*LEFT($K$3,LEN($K$3)-1) -> #N/A | L27: =H27*LEFT($L$3,LEN($L$3)-1) -> #N/A | M27: =H27*LEFT($M$3,LEN($M$3)-1) -> #N/A | N27: =J27/$J$64-1 -> -0.44161233 | O27: =R27/$R$64-1 -> -0.13750375 | P27: 申万基金核心_x0000__x0000__x0000__x0000__x0000__x0000_ | Q27: 801903.SI | R27: =IF([1]!s_dq_close($S$3,I27,$M$2)=0,NA(),[1]!s_dq_close($S$3,I27,$M$2)) -> 3654.94 | V27: =IF(Z27="",0,RANK(Z27,Z:Z,1)) -> 0 | W27: =IF(板块成分!B29="","",板块成分!B29) -> 0026.HK | X27: =[1]!s_info_name(W27) -> 中华汽车 | Y27: =IF($Y$3="申万一级行业",[1]!s_info_industry_sw_2021(W27,公司分析!D$5,1),IF($Y$3="申万二级行业",[1]!s_info_industry_sw_2021(W27,公司分析!D$5,2),IF($Y$3="申万三级行业",[1]!s_info_industry_sw_2021(W27,公司分析!D$5,3),IF($Y$3="wind一级行业",[1]!s_info_industry_gics(W27,1),IF($Y$3="wind二级行业",[1]!s_info_industry_gics(W27,2),IF($Y$3="wind三级行业",[1]!s_info_industry_gics(W27,3),IF($Y$3="wind四级行业",[1]!s_info_industry_gics(W27,4),IF($Y$3="证监会门类行业",[1]!s_info_industry_csrc12_n(W27,公司分析!D$5,1),"")))))))) -> 多样化房地产活动 | Z27: =IF(Y27=行业比较!$E$6,ROW(),"")
... B48: 35 | C48: 大通证券 | D48: =B48 -> 35 | H48: =IF(([1]!s_share_total($H$3,I48)/[1]!s_share_total($H$3,I49))/(YEAR(I48)/YEAR(I47))=1,NA(),IF($I$2="PE Band",[1]!S_STM07_IS($H$3,61,YEAR(I48)-1&"-12-31",1)/[1]!s_share_total($H$3,I48),[1]!s_stm07_bs($H$3,140,YEAR(I48)-1&"-12-31",1)/[1]!s_share_total($H$3,I48))) -> #N/A | I48: =--[1]!td(I47-$N$2) -> 45141 | J48: =IF([1]!s_dq_close(公司分析!$D$4,I48,$M$2)=0,NA(),[1]!s_dq_close(公司分析!$D$4,I48,$M$2)) -> 135.2 | K48: =H48*LEFT($K$3,LEN($K$3)-1) -> #N/A | L48: =H48*LEFT($L$3,LEN($L$3)-1) -> #N/A | M48: =H48*LEFT($M$3,LEN($M$3)-1) -> #N/A | N48: =J48/$J$64-1 -> -0.19857736 | O48: =R48/$R$64-1 -> 0.039835946 | P48: 恒生科技指数 | Q48: HSTECH.HI | R48: =IF([1]!s_dq_close($S$3,I48,$M$2)=0,NA(),[1]!s_dq_close($S$3,I48,$M$2)) -> 4406.44 | V48: =IF(Z48="",0,RANK(Z48,Z:Z,1)) -> 0 | W48: =IF(板块成分!B50="","",板块成分!B50) -> 0051.HK | X48: =[1]!s_info_name(W48) -> 海港企业 | Y48: =IF($Y$3="申万一级行业",[1]!s_info_industry_sw_2021(W48,公司分析!D$5,1),IF($Y$3="申万二级行业",[1]!s_info_industry_sw_2021(W48,公司分析!D$5,2),IF($Y$3="申万三级行业",[1]!s_info_industry_sw_2021(W48,公司分析!D$5,3),IF($Y$3="wind一级行业",[1]!s_info_industry_gics(W48,1),IF($Y$3="wind二级行业",[1]!s_info_industry_gics(W48,2),IF($Y$3="wind三级行业",[1]!s_info_industry_gics(W48,3),IF($Y$3="wind四级行业",[1]!s_info_industry_gics(W48,4),IF($Y$3="证监会门类行业",[1]!s_info_industry_csrc12_n(W48,公司分析!D$5,1),"")))))))) -> 酒店、度假村与豪华游轮 | Z48: =IF(Y48=行业比较!$E$6,ROW(),"")
B49: 36 | C49: 大同证券 | D49: =B49 -> 36 | H49: =IF(([1]!s_share_total($H$3,I49)/[1]!s_share_total($H$3,I50))/(YEAR(I49)/YEAR(I48))=1,NA(),IF($I$2="PE Band",[1]!S_STM07_IS($H$3,61,YEAR(I49)-1&"-12-31",1)/[1]!s_share_total($H$3,I49),[1]!s_stm07_bs($H$3,140,YEAR(I49)-1&"-12-31",1)/[1]!s_share_total($H$3,I49))) -> #N/A | I49: =--[1]!td(I48-$N$2) -> 45134 | J49: =IF([1]!s_dq_close(公司分析!$D$4,I49,$M$2)=0,NA(),[1]!s_dq_close(公司分析!$D$4,I49,$M$2)) -> 132.1 | K49: =H49*LEFT($K$3,LEN($K$3)-1) -> #N/A | L49: =H49*LEFT($L$3,LEN($L$3)-1) -> #N/A | M49: =H49*LEFT($M$3,LEN($M$3)-1) -> #N/A | N49: =J49/$J$64-1 -> -0.21695317 | O49: =R49/$R$64-1 -> 0.024438188 | R49: =IF([1]!s_dq_close($S$3,I49,$M$2)=0,NA(),[1]!s_dq_close($S$3,I49,$M$2)) -> 4341.19 | V49: =IF(Z49="",0,RANK(Z49,Z:Z,1)) -> 0 | W49: =IF(板块成分!B51="","",板块成分!B51) -> 0052.HK | X49: =[1]!s_info_name(W49) -> 大快活集团 | Y49: =IF($Y$3="申万一级行业",[1]!s_info_industry_sw_2021(W49,公司分析!D$5,1),IF($Y$3="申万二级行业",[1]!s_info_industry_sw_2021(W49,公司分析!D$5,2),IF($Y$3="申万三级行业",[1]!s_info_industry_sw_2021(W49,公司分析!D$5,3),IF($Y$3="wind一级行业",[1]!s_info_industry_gics(W49,1),IF($Y$3="wind二级行业",[1]!s_info_industry_gics(W49,2),IF($Y$3="wind三级行业",[1]!s_info_industry_gics(W49,3),IF($Y$3="wind四级行业",[1]!s_info_industry_gics(W49,4),IF($Y$3="证监会门类行业",[1]!s_info_industry_csrc12_n(W49,公司分析!D$5,1),"")))))))) -> 餐馆 | Z49: =IF(Y49=行业比较!$E$6,ROW(),"")
B50: 37 | C50: 德邦证券 | D50: =B50 -> 37 | H50: =IF(([1]!s_share_total($H$3,I50)/[1]!s_share_total($H$3,I51))/(YEAR(I50)/YEAR(I49))=1,NA(),IF($I$2="PE Band",[1]!S_STM07_IS($H$3,61,YEAR(I50)-1&"-12-31",1)/[1]!s_share_total($H$3,I50),[1]!s_stm07_bs($H$3,140,YEAR(I50)-1&"-12-31",1)/[1]!s_share_total($H$3,I50))) -> #N/A | I50: =--[1]!td(I49-$N$2) -> 45127 | J50: =IF([1]!s_dq_close(公司分析!$D$4,I50,$M$2)=0,NA(),[1]!s_dq_close(公司分析!$D$4,I50,$M$2)) -> 122.1 | K50: =H50*LEFT($K$3,LEN($K$3)-1) -> #N/A | L50: =H50*LEFT($L$3,LEN($L$3)-1) -> #N/A | M50: =H50*LEFT($M$3,LEN($M$3)-1) -> #N/A | N50: =J50/$J$64-1 -> -0.27622999 | O50: =R50/$R$64-1 -> -0.041034729 | R50: =IF([1]!s_dq_close($S$3,I50,$M$2)=0,NA(),[1]!s_dq_close($S$3,I50,$M$2)) -> 4063.74 | V50: =IF(Z50="",0,RANK(Z50,Z:Z,1)) -> 0 | W50: =IF(板块成分!B52="","",板块成分!B52) -> 0053.HK | X50: =[1]!s_info_name(W50) -> 国浩集团 | Y50: =IF($Y$3="申万一级行业",[1]!s_info_industry_sw_2021(W50,公司分析!D$5,1),IF($Y$3="申万二级行业",[1]!s_info_industry_sw_2021(W50,公司分析!D$5,2),IF($Y$3="申万三级行业",[1]!s_info_industry_sw_2021(W50,公司分析!D$5,3),IF($Y$3="wind一级行业",[1]!s_info_industry_gics(W50,1),IF($Y$3="wind二级行业",[1]!s_info_industry_gics(W50,2),IF($Y$3="wind三级行业",[1]!s_info_industry_gics(W50,3),IF($Y$3="wind四级行业",[1]!s_info_industry_gics(W50,4),IF($Y$3="证监会门类行业",[1]!s_info_industry_csrc12_n(W50,公司分析!D$5,1),"")))))))) -> 房地产经营公司 | Z50: =IF(Y50=行业比较!$E$6,ROW(),"")
B51: 38 | C51: 东北证券 | D51: =B51 -> 38 | H51: =IF(([1]!s_share_total($H$3,I51)/[1]!s_share_total($H$3,I52))/(YEAR(I51)/YEAR(I50))=1,NA(),IF($I$2="PE Band",[1]!S_STM07_IS($H$3,61,YEAR(I51)-1&"-12-31",1)/[1]!s_share_total($H$3,I51),[1]!s_stm07_bs($H$3,140,YEAR(I51)-1&"-12-31",1)/[1]!s_share_total($H$3,I51))) -> #N/A | I51: =--[1]!td(I50-$N$2) -> 45120 | J51: =IF([1]!s_dq_close(公司分析!$D$4,I51,$M$2)=0,NA(),[1]!s_dq_close(公司分析!$D$4,I51,$M$2)) -> 133 | K51: =H51*LEFT($K$3,LEN($K$3)-1) -> #N/A | L51: =H51*LEFT($L$3,LEN($L$3)-1) -> #N/A | M51: =H51*LEFT($M$3,LEN($M$3)-1) -> #N/A | N51: =J51/$J$64-1 -> -0.21161826 | O51: =R51/$R$64-1 -> -0.00012742972 | R51: =IF([1]!s_dq_close($S$3,I51,$M$2)=0,NA(),[1]!s_dq_close($S$3,I51,$M$2)) -> 4237.09 | V51: =IF(Z51="",0,RANK(Z51,Z:Z,1)) -> 0 | W51: =IF(板块成分!B53="","",板块成分!B53) -> 0055.HK | X51: =[1]!s_info_name(W51) -> 中星集团控股 | Y51: =IF($Y$3="申万一级行业",[1]!s_info_industry_sw_2021(W51,公司分析!D$5,1),IF($Y$3="申万二级行业",[1]!s_info_industry_sw_2021(W51,公司分析!D$5,2),IF($Y$3="申万三级行业",[1]!s_info_industry_sw_2021(W51,公司分析!D$5,3),IF($Y$3="wind一级行业",[1]!s_info_industry_gics(W51,1),IF($Y$3="wind二级行业",[1]!s_info_industry_gics(W51,2),IF($Y$3="wind三级行业",[1]!s_info_industry_gics(W51,3),IF($Y$3="wind四级行业",[1]!s_info_industry_gics(W51,4),IF($Y$3="证监会门类行业",[1]!s_info_industry_csrc12_n(W51,公司分析!D$5,1),"")))))))) -> 商业印刷 | Z51: =IF(Y51=行业比较!$E$6,ROW(),"")
B52: 39 | C52: 东莞证券 | D52: =B52 -> 39 | H52: =IF(([1]!s_share_total($H$3,I52)/[1]!s_share_total($H$3,I53))/(YEAR(I52)/YEAR(I51))=1,NA(),IF($I$2="PE Band",[1]!S_STM07_IS($H$3,61,YEAR(I52)-1&"-12-31",1)/[1]!s_share_total($H$3,I52),[1]!s_stm07_bs($H$3,140,YEAR(I52)-1&"-12-31",1)/[1]!s_share_total($H$3,I52))) -> #N/A | I52: =--[1]!td(I51-$N$2) -> 45113 | J52: =IF([1]!s_dq_close(公司分析!$D$4,I52,$M$2)=0,NA(),[1]!s_dq_close(公司分析!$D$4,I52,$M$2)) -> 116.5 | K52: =H52*LEFT($K$3,LEN($K$3)-1) -> #N/A | L52: =H52*LEFT($L$3,LEN($L$3)-1) -> #N/A | M52: =H52*LEFT($M$3,LEN($M$3)-1) -> #N/A | N52: =J52/$J$64-1 -> -0.30942501 | O52: =R52/$R$64-1 -> -0.068153661 | R52: =IF([1]!s_dq_close($S$3,I52,$M$2)=0,NA(),[1]!s_dq_close($S$3,I52,$M$2)) -> 3948.82 | V52: =IF(Z52="",0,RANK(Z52,Z:Z,1)) -> 0 | W52: =IF(板块成分!B54="","",板块成分!B54) -> 0057.HK | X52: =[1]!s_info_name(W52) -> 震雄集团 | Y52: =IF($Y$3="申万一级行业",[1]!s_info_industry_sw_2021(W52,公司分析!D$5,1),IF($Y$3="申万二级行业",[1]!s_info_industry_sw_2021(W52,公司分析!D$5,2),IF($Y$3="申万三级行业",[1]!s_info_industry_sw_2021(W52,公司分析!D$5,3),IF($Y$3="wind一级行业",[1]!s_info_industry_gics(W52,1),IF($Y$3="wind二级行业",[1]!s_info_industry_gics(W52,2),IF($Y$3="wind三级行业",[1]!s_info_industry_gics(W52,3),IF($Y$3="wind四级行业",[1]!s_info_industry_gics(W52,4),IF($Y$3="证监会门类行业",[1]!s_info_industry_csrc12_n(W52,公司分析!D$5,1),"")))))))) -> 工业机械 | Z52: =IF(Y52=行业比较!$E$6,ROW(),"")
B53: 40 | C53: 东吴证券 | D53: =B53 -> 40 | H53: =IF(([1]!s_share_total($H$3,I53)/[1]!s_share_total($H$3,I54))/(YEAR(I53)/YEAR(I52))=1,NA(),IF($I$2="PE Band",[1]!S_STM07_IS($H$3,61,YEAR(I53)-1&"-12-31",1)/[1]!s_share_total($H$3,I53),[1]!s_stm07_bs($H$3,140,YEAR(I53)-1&"-12-31",1)/[1]!s_share_total($H$3,I53))) -> #N/A | I53: =--[1]!td(I52-$N$2) -> 45106 | J53: =IF([1]!s_dq_close(公司分析!$D$4,I53,$M$2)=0,NA(),[1]!s_dq_close(公司分析!$D$4,I53,$M$2)) -> 117.4 | K53: =H53*LEFT($K$3,LEN($K$3)-1) -> #N/A | L53: =H53*LEFT($L$3,LEN($L$3)-1) -> #N/A | M53: =H53*LEFT($M$3,LEN($M$3)-1) -> #N/A | N53: =J53/$J$64-1 -> -0.3040901 | O53: =R53/$R$64-1 -> -0.071783049 | R53: =IF([1]!s_dq_close($S$3,I53,$M$2)=0,NA(),[1]!s_dq_close($S$3,I53,$M$2)) -> 3933.44 | V53: =IF(Z53="",0,RANK(Z53,Z:Z,1)) -> 0 | W53: =IF(板块成分!B55="","",板块成分!B55) -> 0058.HK | X53: =[1]!s_info_name(W53) -> 新威国际 | Y53: =IF($Y$3="申万一级行业",[1]!s_info_industry_sw_2021(W53,公司分析!D$5,1),IF($Y$3="申万二级行业",[1]!s_info_industry_sw_2021(W53,公司分析!D$5,2),IF($Y$3="申万三级行业",[1]!s_info_industry_sw_2021(W53,公司分析!D$5,3),IF($Y$3="wind一级行业",[1]!s_info_industry_gics(W53,1),IF($Y$3="wind二级行业",[1]!s_info_industry_gics(W53,2),IF($Y$3="wind三级行业",[1]!s_info_industry_gics(W53,3),IF($Y$3="wind四级行业",[1]!s_info_industry_gics(W53,4),IF($Y$3="证监会门类行业",[1]!s_info_industry_csrc12_n(W53,公司分析!D$5,1),"")))))))) -> 建材 | Z53: =IF(Y53=行业比较!$E$6,ROW(),"")
B54: 41 | C54: 东兴证券 | D54: =B54 -> 41 | H54: =IF(([1]!s_share_total($H$3,I54)/[1]!s_share_total($H$3,I55))/(YEAR(I54)/YEAR(I53))=1,NA(),IF($I$2="PE Band",[1]!S_STM07_IS($H$3,61,YEAR(I54)-1&"-12-31",1)/[1]!s_share_total($H$3,I54),[1]!s_stm07_bs($H$3,140,YEAR(I54)-1&"-12-31",1)/[1]!s_share_total($H$3,I54))) -> #N/A | I54: =--[1]!td(I53-$N$2) -> 45098 | J54: =IF([1]!s_dq_close(公司分析!$D$4,I54,$M$2)=0,NA(),[1]!s_dq_close(公司分析!$D$4,I54,$M$2)) -> 122.3 | K54: =H54*LEFT($K$3,LEN($K$3)-1) -> #N/A | L54: =H54*LEFT($L$3,LEN($L$3)-1) -> #N/A | M54: =H54*LEFT($M$3,LEN($M$3)-1) -> #N/A | N54: =J54/$J$64-1 -> -0.27504446 | O54: =R54/$R$64-1 -> -0.065142544 | R54: =IF([1]!s_dq_close($S$3,I54,$M$2)=0,NA(),[1]!s_dq_close($S$3,I54,$M$2)) -> 3961.58 | V54: =IF(Z54="",0,RANK(Z54,Z:Z,1)) -> 0 | W54: =IF(板块成分!B56="","",板块成分!B56) -> 0059.HK | X54: =[1]!s_info_name(W54) -> 天誉置业 | Y54: =IF($Y$3="申万一级行业",[1]!s_info_industry_sw_2021(W54,公司分析!D$5,1),IF($Y$3="申万二级行业",[1]!s_info_industry_sw_2021(W54,公司分析!D$5,2),IF($Y$3="申万三级行业",[1]!s_info_industry_sw_2021(W54,公司分析!D$5,3),IF($Y$3="wind一级行业",[1]!s_info_industry_gics(W54,1),IF($Y$3="wind二级行业",[1]!s_info_industry_gics(W54,2),IF($Y$3="wind三级行业",[1]!s_info_industry_gics(W54,3),IF($Y$3="wind四级行业",[1]!s_info_industry_gics(W54,4),IF($Y$3="证监会门类行业",[1]!s_info_industry_csrc12_n(W54,公司分析!D$5,1),"")))))))) -> 多样化房地产活动 | Z54: =IF(Y54=行业比较!$E$6,ROW(),"")
B55: 42 | C55: 方正证券 | D55: =B55 -> 42 | H55: =IF(([1]!s_share_total($H$3,I55)/[1]!s_share_total($H$3,I56))/(YEAR(I55)/YEAR(I54))=1,NA(),IF($I$2="PE Band",[1]!S_STM07_IS($H$3,61,YEAR(I55)-1&"-12-31",1)/[1]!s_share_total($H$3,I55),[1]!s_stm07_bs($H$3,140,YEAR(I55)-1&"-12-31",1)/[1]!s_share_total($H$3,I55))) -> #N/A | I55: =--[1]!td(I54-$N$2) -> 45091 | J55: =IF([1]!s_dq_close(公司分析!$D$4,I55,$M$2)=0,NA(),[1]!s_dq_close(公司分析!$D$4,I55,$M$2)) -> 132.4 | K55: =H55*LEFT($K$3,LEN($K$3)-1) -> #N/A | L55: =H55*LEFT($L$3,LEN($L$3)-1) -> #N/A | M55: =H55*LEFT($M$3,LEN($M$3)-1) -> #N/A | N55: =J55/$J$64-1 -> -0.21517487 | O55: =R55/$R$64-1 -> -0.043642319 | R55: =IF([1]!s_dq_close($S$3,I55,$M$2)=0,NA(),[1]!s_dq_close($S$3,I55,$M$2)) -> 4052.69 | V55: =IF(Z55="",0,RANK(Z55,Z:Z,1)) -> 0 | W55: =IF(板块成分!B57="","",板块成分!B57) -> 0060.HK | X55: =[1]!s_info_name(W55) -> 香港食品投资 | Y55: =IF($Y$3="申万一级行业",[1]!s_info_industry_sw_2021(W55,公司分析!D$5,1),IF($Y$3="申万二级行业",[1]!s_info_industry_sw_2021(W55,公司分析!D$5,2),IF($Y$3="申万三级行业",[1]!s_info_industry_sw_2021(W55,公司分析!D$5,3),IF($Y$3="wind一级行业",[1]!s_info_industry_gics(W55,1),IF($Y$3="wind二级行业",[1]!s_info_industry_gics(W55,2),IF($Y$3="wind三级行业",[1]!s_info_industry_gics(W55,3),IF($Y$3="wind四级行业",[1]!s_info_industry_gics(W55,4),IF($Y$3="证监会门类行业",[1]!s_info_industry_csrc12_n(W55,公司分析!D$5,1),"")))))))) -> 食品加工与肉类 | Z55: =IF(Y55=行业比较!$E$6,ROW(),"")
B56: 43 | C56: 广州证券 | D56: =B56 -> 43 | H56: =IF(([1]!s_share_total($H$3,I56)/[1]!s_share_total($H$3,I57))/(YEAR(I56)/YEAR(I55))=1,NA(),IF($I$2="PE Band",[1]!S_STM07_IS($H$3,61,YEAR(I56)-1&"-12-31",1)/[1]!s_share_total($H$3,I56),[1]!s_stm07_bs($H$3,140,YEAR(I56)-1&"-12-31",1)/[1]!s_share_total($H$3,I56))) -> #N/A | I56: =--[1]!td(I55-$N$2) -> 45084 | J56: =IF([1]!s_dq_close(公司分析!$D$4,I56,$M$2)=0,NA(),[1]!s_dq_close(公司分析!$D$4,I56,$M$2)) -> 123.1 | K56: =H56*LEFT($K$3,LEN($K$3)-1) -> #N/A | L56: =H56*LEFT($L$3,LEN($L$3)-1) -> #N/A | M56: =H56*LEFT($M$3,LEN($M$3)-1) -> #N/A | N56: =J56/$J$64-1 -> -0.27030231 | O56: =R56/$R$64-1 -> -0.074713932 | R56: =IF([1]!s_dq_close($S$3,I56,$M$2)=0,NA(),[1]!s_dq_close($S$3,I56,$M$2)) -> 3921.02 | V56: =IF(Z56="",0,RANK(Z56,Z:Z,1)) -> 0 | W56: =IF(板块成分!B58="","",板块成分!B58) -> 0061.HK | X56: =[1]!s_info_name(W56) -> 绿领控股 | Y56: =IF($Y$3="申万一级行业",[1]!s_info_industry_sw_2021(W56,公司分析!D$5,1),IF($Y$3="申万二级行业",[1]!s_info_industry_sw_2021(W56,公司分析!D$5,2),IF($Y$3="申万三级行业",[1]!s_info_industry_sw_2021(W56,公司分析!D$5,3),IF($Y$3="wind一级行业",[1]!s_info_industry_gics(W56,1),IF($Y$3="wind二级行业",[1]!s_info_industry_gics(W56,2),IF($Y$3="wind三级行业",[1]!s_info_industry_gics(W56,3),IF($Y$3="wind四级行业",[1]!s_info_industry_gics(W56,4),IF($Y$3="证监会门类行业",[1]!s_info_industry_csrc12_n(W56,公司分析!D$5,1),"")))))))) -> 煤炭与消费用燃料 | Z56: =IF(Y56=行业比较!$E$6,ROW(),"")
B57: 44 | C57: 国都证券 | D57: =B57 -> 44 | H57: =IF(([1]!s_share_total($H$3,I57)/[1]!s_share_total($H$3,I58))/(YEAR(I57)/YEAR(I56))=1,NA(),IF($I$2="PE Band",[1]!S_STM07_IS($H$3,61,YEAR(I57)-1&"-12-31",1)/[1]!s_share_total($H$3,I57),[1]!s_stm07_bs($H$3,140,YEAR(I57)-1&"-12-31",1)/[1]!s_share_total($H$3,I57))) -> #N/A | I57: =--[1]!td(I56-$N$2) -> 45077 | J57: =IF([1]!s_dq_close(公司分析!$D$4,I57,$M$2)=0,NA(),[1]!s_dq_close(公司分析!$D$4,I57,$M$2)) -> 127.5 | K57: =H57*LEFT($K$3,LEN($K$3)-1) -> #N/A | L57: =H57*LEFT($L$3,LEN($L$3)-1) -> #N/A | M57: =H57*LEFT($M$3,LEN($M$3)-1) -> #N/A | N57: =J57/$J$64-1 -> -0.24422051 | O57: =R57/$R$64-1 -> -0.14416077 | R57: =IF([1]!s_dq_close($S$3,I57,$M$2)=0,NA(),[1]!s_dq_close($S$3,I57,$M$2)) -> 3626.73 | V57: =IF(Z57="",0,RANK(Z57,Z:Z,1)) -> 0 | W57: =IF(板块成分!B59="","",板块成分!B59) -> 0062.HK | X57: =[1]!s_info_name(W57) -> 载通 | Y57: =IF($Y$3="申万一级行业",[1]!s_info_industry_sw_2021(W57,公司分析!D$5,1),IF($Y$3="申万二级行业",[1]!s_info_industry_sw_2021(W57,公司分析!D$5,2),IF($Y$3="申万三级行业",[1]!s_info_industry_sw_2021(W57,公司分析!D$5,3),IF($Y$3="wind一级行业",[1]!s_info_industry_gics(W57,1),IF($Y$3="wind二级行业",[1]!s_info_industry_gics(W57,2),IF($Y$3="wind三级行业",[1]!s_info_industry_gics(W57,3),IF($Y$3="wind四级行业",[1]!s_info_industry_gics(W57,4),IF($Y$3="证监会门类行业",[1]!s_info_industry_csrc12_n(W57,公司分析!D$5,1),"")))))))) -> 公路运输 | Z57: =IF(Y57=行业比较!$E$6,ROW(),"")
B58: 45 | C58: 国海证券 | D58: =B58 -> 45 | H58: =IF(([1]!s_share_total($H$3,I58)/[1]!s_share_total($H$3,I59))/(YEAR(I58)/YEAR(I57))=1,NA(),IF($I$2="PE Band",[1]!S_STM07_IS($H$3,61,YEAR(I58)-1&"-12-31",1)/[1]!s_share_total($H$3,I58),[1]!s_stm07_bs($H$3,140,YEAR(I58)-1&"-12-31",1)/[1]!s_share_total($H$3,I58))) -> #N/A | I58: =--[1]!td(I57-$N$2) -> 45070 | J58: =IF([1]!s_dq_close(公司分析!$D$4,I58,$M$2)=0,NA(),[1]!s_dq_close(公司分析!$D$4,I58,$M$2)) -> 138.5 | K58: =H58*LEFT($K$3,LEN($K$3)-1) -> #N/A | L58: =H58*LEFT($L$3,LEN($L$3)-1) -> #N/A | M58: =H58*LEFT($M$3,LEN($M$3)-1) -> #N/A | N58: =J58/$J$64-1 -> -0.179016 | O58: =R58/$R$64-1 -> -0.10895241 | R58: =IF([1]!s_dq_close($S$3,I58,$M$2)=0,NA(),[1]!s_dq_close($S$3,I58,$M$2)) -> 3775.93 | V58: =IF(Z58="",0,RANK(Z58,Z:Z,1)) -> 0 | W58: =IF(板块成分!B60="","",板块成分!B60) -> 0063.HK | X58: =[1]!s_info_name(W58) -> 中亚烯谷集团 | Y58: =IF($Y$3="申万一级行业",[1]!s_info_industry_sw_2021(W58,公司分析!D$5,1),IF($Y$3="申万二级行业",[1]!s_info_industry_sw_2021(W58,公司分析!D$5,2),IF($Y$3="申万三级行业",[1]!s_info_industry_sw_2021(W58,公司分析!D$5,3),IF($Y$3="wind一级行业",[1]!s_info_industry_gics(W58,1),IF($Y$3="wind二级行业",[1]!s_info_industry_gics(W58,2),IF($Y$3="wind三级行业",[1]!s_info_industry_gics(W58,3),IF($Y$3="wind四级行业",[1]!s_info_industry_gics(W58,4),IF($Y$3="证监会门类行业",[1]!s_info_industry_csrc12_n(W58,公司分析!D$5,1),"")))))))) -> 房地产经营公司 | Z58: =IF(Y58=行业比较!$E$6,ROW(),"")
B59: 46 | C59: 国联证券 | D59: =B59 -> 46 | H59: =IF(([1]!s_share_total($H$3,I59)/[1]!s_share_total($H$3,I60))/(YEAR(I59)/YEAR(I58))=1,NA(),IF($I$2="PE Band",[1]!S_STM07_IS($H$3,61,YEAR(I59)-1&"-12-31",1)/[1]!s_share_total($H$3,I59),[1]!s_stm07_bs($H$3,140,YEAR(I59)-1&"-12-31",1)/[1]!s_share_total($H$3,I59))) -> #N/A | I59: =--[1]!td(I58-$N$2) -> 45063 | J59: =IF([1]!s_dq_close(公司分析!$D$4,I59,$M$2)=0,NA(),[1]!s_dq_close(公司分析!$D$4,I59,$M$2)) -> 141.6 | K59: =H59*LEFT($K$3,LEN($K$3)-1) -> #N/A | L59: =H59*LEFT($L$3,LEN($L$3)-1) -> #N/A | M59: =H59*LEFT($M$3,LEN($M$3)-1) -> #N/A | N59: =J59/$J$64-1 -> -0.16064019 | O59: =R59/$R$64-1 -> -0.086732442 | R59: =IF([1]!s_dq_close($S$3,I59,$M$2)=0,NA(),[1]!s_dq_close($S$3,I59,$M$2)) -> 3870.09 | V59: =IF(Z59="",0,RANK(Z59,Z:Z,1)) -> 0 | W59: =IF(板块成分!B61="","",板块成分!B61) -> 0064.HK | X59: =[1]!s_info_name(W59) -> 结好控股 | Y59: =IF($Y$3="申万一级行业",[1]!s_info_industry_sw_2021(W59,公司分析!D$5,1),IF($Y$3="申万二级行业",[1]!s_info_industry_sw_2021(W59,公司分析!D$5,2),IF($Y$3="申万三级行业",[1]!s_info_industry_sw_2021(W59,公司分析!D$5,3),IF($Y$3="wind一级行业",[1]!s_info_industry_gics(W59,1),IF($Y$3="wind二级行业",[1]!s_info_industry_gics(W59,2),IF($Y$3="wind三级行业",[1]!s_info_industry_gics(W59,3),IF($Y$3="wind四级行业",[1]!s_info_industry_gics(W59,4),IF($Y$3="证监会门类行业",[1]!s_info_industry_csrc12_n(W59,公司分析!D$5,1),"")))))))) -> 投资银行业与经纪业 | Z59: =IF(Y59=行业比较!$E$6,ROW(),"")
B60: 47 | C60: 国盛证券 | D60: =B60 -> 47 | H60: =IF(([1]!s_share_total($H$3,I60)/[1]!s_share_total($H$3,I61))/(YEAR(I60)/YEAR(I59))=1,NA(),IF($I$2="PE Band",[1]!S_STM07_IS($H$3,61,YEAR(I60)-1&"-12-31",1)/[1]!s_share_total($H$3,I60),[1]!s_stm07_bs($H$3,140,YEAR(I60)-1&"-12-31",1)/[1]!s_share_total($H$3,I60))) -> #N/A | I60: =--[1]!td(I59-$N$2) -> 45056 | J60: =IF([1]!s_dq_close(公司分析!$D$4,I60,$M$2)=0,NA(),[1]!s_dq_close(公司分析!$D$4,I60,$M$2)) -> 147.3 | K60: =H60*LEFT($K$3,LEN($K$3)-1) -> #N/A | L60: =H60*LEFT($L$3,LEN($L$3)-1) -> #N/A | M60: =H60*LEFT($M$3,LEN($M$3)-1) -> #N/A | N60: =J60/$J$64-1 -> -0.1268524 | O60: =R60/$R$64-1 -> -0.10052081 | R60: =IF([1]!s_dq_close($S$3,I60,$M$2)=0,NA(),[1]!s_dq_close($S$3,I60,$M$2)) -> 3811.66 | V60: =IF(Z60="",0,RANK(Z60,Z:Z,1)) -> 0 | W60: =IF(板块成分!B62="","",板块成分!B62) -> 0065.HK | X60: =[1]!s_info_name(W60) -> 弘海高新资源 | Y60: =IF($Y$3="申万一级行业",[1]!s_info_industry_sw_2021(W60,公司分析!D$5,1),IF($Y$3="申万二级行业",[1]!s_info_industry_sw_2021(W60,公司分析!D$5,2),IF($Y$3="申万三级行业",[1]!s_info_industry_sw_2021(W60,公司分析!D$5,3),IF($Y$3="wind一级行业",[1]!s_info_industry_gics(W60,1),IF($Y$3="wind二级行业",[1]!s_info_industry_gics(W60,2),IF($Y$3="wind三级行业",[1]!s_info_industry_gics(W60,3),IF($Y$3="wind四级行业",[1]!s_info_industry_gics(W60,4),IF($Y$3="证监会门类行业",[1]!s_info_industry_csrc12_n(W60,公司分析!D$5,1),"")))))))) -> 煤炭与消费用燃料 | Z60: =IF(Y60=行业比较!$E$6,ROW(),"")
... B62: 49 | C62: 华安证券 | D62: =B62 -> 49 | H62: =IF(([1]!s_share_total($H$3,I62)/[1]!s_share_total($H$3,I63))/(YEAR(I62)/YEAR(I61))=1,NA(),IF($I$2="PE Band",[1]!S_STM07_IS($H$3,61,YEAR(I62)-1&"-12-31",1)/[1]!s_share_total($H$3,I62),[1]!s_stm07_bs($H$3,140,YEAR(I62)-1&"-12-31",1)/[1]!s_share_total($H$3,I62))) -> #N/A | I62: =--[1]!td(I61-$N$2) -> 45037 | J62: =IF([1]!s_dq_close(公司分析!$D$4,I62,$M$2)=0,NA(),[1]!s_dq_close(公司分析!$D$4,I62,$M$2)) -> 158 | K62: =H62*LEFT($K$3,LEN($K$3)-1) -> #N/A | L62: =H62*LEFT($L$3,LEN($L$3)-1) -> #N/A | M62: =H62*LEFT($M$3,LEN($M$3)-1) -> #N/A | N62: =J62/$J$64-1 -> -0.0634262 | O62: =R62/$R$64-1 -> -0.063169743 | R62: =IF([1]!s_dq_close($S$3,I62,$M$2)=0,NA(),[1]!s_dq_close($S$3,I62,$M$2)) -> 3969.94 | V62: =IF(Z62="",0,RANK(Z62,Z:Z,1)) -> 0 | W62: =IF(板块成分!B64="","",板块成分!B64) -> 0069.HK | X62: =[1]!s_info_name(W62) -> 香格里拉(亚洲) | Y62: =IF($Y$3="申万一级行业",[1]!s_info_industry_sw_2021(W62,公司分析!D$5,1),IF($Y$3="申万二级行业",[1]!s_info_industry_sw_2021(W62,公司分析!D$5,2),IF($Y$3="申万三级行业",[1]!s_info_industry_sw_2021(W62,公司分析!D$5,3),IF($Y$3="wind一级行业",[1]!s_info_industry_gics(W62,1),IF($Y$3="wind二级行业",[1]!s_info_industry_gics(W62,2),IF($Y$3="wind三级行业",[1]!s_info_industry_gics(W62,3),IF($Y$3="wind四级行业",[1]!s_info_industry_gics(W62,4),IF($Y$3="证监会门类行业",[1]!s_info_industry_csrc12_n(W62,公司分析!D$5,1),"")))))))) -> 酒店、度假村与豪华游轮 | Z62: =IF(Y62=行业比较!$E$6,ROW(),"")
B63: 50 | C63: 华创证券 | D63: =B63 -> 50 | H63: =[1]!S_STM07_IS($H$3,61,YEAR(I63)-1&"-12-31",1)/[1]!s_share_total($H$3,I63) -> -18.053719 | I63: =--[1]!td(I62-$N$2) -> 45030 | J63: =IF([1]!s_dq_close(公司分析!$D$4,I63,$M$2)=0,NA(),[1]!s_dq_close(公司分析!$D$4,I63,$M$2)) -> 167.6 | K63: =H63*LEFT($K$3,LEN($K$3)-1) -> -144.42975 | L63: =H63*LEFT($L$3,LEN($L$3)-1) -> -361.07438 | M63: =H63*LEFT($M$3,LEN($M$3)-1) -> -577.71901 | N63: =J63/$J$64-1 -> -0.0065204505 | O63: =R63/$R$64-1 -> -0.017368199 | R63: =IF([1]!s_dq_close($S$3,I63,$M$2)=0,NA(),[1]!s_dq_close($S$3,I63,$M$2)) -> 4164.03 | V63: =IF(Z63="",0,RANK(Z63,Z:Z,1)) -> 0 | W63: =IF(板块成分!B65="","",板块成分!B65) -> 0070.HK | X63: =[1]!s_info_name(W63) -> 金粤控股 | Y63: =IF($Y$3="申万一级行业",[1]!s_info_industry_sw_2021(W63,公司分析!D$5,1),IF($Y$3="申万二级行业",[1]!s_info_industry_sw_2021(W63,公司分析!D$5,2),IF($Y$3="申万三级行业",[1]!s_info_industry_sw_2021(W63,公司分析!D$5,3),IF($Y$3="wind一级行业",[1]!s_info_industry_gics(W63,1),IF($Y$3="wind二级行业",[1]!s_info_industry_gics(W63,2),IF($Y$3="wind三级行业",[1]!s_info_industry_gics(W63,3),IF($Y$3="wind四级行业",[1]!s_info_industry_gics(W63,4),IF($Y$3="证监会门类行业",[1]!s_info_industry_csrc12_n(W63,公司分析!D$5,1),"")))))))) -> 赌场与赌博 | Z63: =IF(Y63=行业比较!$E$6,ROW(),"")
B64: 51 | C64: 华林证券 | D64: =B64 -> 51 | I64: =--[1]!td(I63-$N$2) -> 45023 | J64: =IF([1]!s_dq_close(公司分析!$D$4,I64,$M$2)=0,NA(),[1]!s_dq_close(公司分析!$D$4,I64,$M$2)) -> 168.7 | K64: =H64*LEFT($K$3,LEN($K$3)-1) -> 0 | L64: =H64*LEFT($L$3,LEN($L$3)-1) -> 0 | M64: =H64*LEFT($M$3,LEN($M$3)-1) -> 0 | R64: =IF([1]!s_dq_close($S$3,I64,$M$2)=0,NA(),[1]!s_dq_close($S$3,I64,$M$2)) -> 4237.63 | V64: =IF(Z64="",0,RANK(Z64,Z:Z,1)) -> 0 | W64: =IF(板块成分!B66="","",板块成分!B66) -> 0071.HK | X64: =[1]!s_info_name(W64) -> 美丽华酒店 | Y64: =IF($Y$3="申万一级行业",[1]!s_info_industry_sw_2021(W64,公司分析!D$5,1),IF($Y$3="申万二级行业",[1]!s_info_industry_sw_2021(W64,公司分析!D$5,2),IF($Y$3="申万三级行业",[1]!s_info_industry_sw_2021(W64,公司分析!D$5,3),IF($Y$3="wind一级行业",[1]!s_info_industry_gics(W64,1),IF($Y$3="wind二级行业",[1]!s_info_industry_gics(W64,2),IF($Y$3="wind三级行业",[1]!s_info_industry_gics(W64,3),IF($Y$3="wind四级行业",[1]!s_info_industry_gics(W64,4),IF($Y$3="证监会门类行业",[1]!s_info_industry_csrc12_n(W64,公司分析!D$5,1),"")))))))) -> 酒店、度假村与豪华游轮 | Z64: =IF(Y64=行业比较!$E$6,ROW(),"")
B65: 52 | C65: 华融证券 | D65: =B65 -> 52 | V65: =IF(Z65="",0,RANK(Z65,Z:Z,1)) -> 0 | W65: =IF(板块成分!B67="","",板块成分!B67) -> 0072.HK | X65: =[1]!s_info_name(W65) -> 超媒体控股 | Y65: =IF($Y$3="申万一级行业",[1]!s_info_industry_sw_2021(W65,公司分析!D$5,1),IF($Y$3="申万二级行业",[1]!s_info_industry_sw_2021(W65,公司分析!D$5,2),IF($Y$3="申万三级行业",[1]!s_info_industry_sw_2021(W65,公司分析!D$5,3),IF($Y$3="wind一级行业",[1]!s_info_industry_gics(W65,1),IF($Y$3="wind二级行业",[1]!s_info_industry_gics(W65,2),IF($Y$3="wind三级行业",[1]!s_info_industry_gics(W65,3),IF($Y$3="wind四级行业",[1]!s_info_industry_gics(W65,4),IF($Y$3="证监会门类行业",[1]!s_info_industry_csrc12_n(W65,公司分析!D$5,1),"")))))))) -> 广告 | Z65: =IF(Y65=行业比较!$E$6,ROW(),"")
B66: 53 | C66: 江海证券 | D66: =B66 -> 53 | V66: =IF(Z66="",0,RANK(Z66,Z:Z,1)) -> 0 | W66: =IF(板块成分!B68="","",板块成分!B68) -> 0073.HK | X66: =[1]!s_info_name(W66) -> 亚洲果业 | Y66: =IF($Y$3="申万一级行业",[1]!s_info_industry_sw_2021(W66,公司分析!D$5,1),IF($Y$3="申万二级行业",[1]!s_info_industry_sw_2021(W66,公司分析!D$5,2),IF($Y$3="申万三级行业",[1]!s_info_industry_sw_2021(W66,公司分析!D$5,3),IF($Y$3="wind一级行业",[1]!s_info_industry_gics(W66,1),IF($Y$3="wind二级行业",[1]!s_info_industry_gics(W66,2),IF($Y$3="wind三级行业",[1]!s_info_industry_gics(W66,3),IF($Y$3="wind四级行业",[1]!s_info_industry_gics(W66,4),IF($Y$3="证监会门类行业",[1]!s_info_industry_csrc12_n(W66,公司分析!D$5,1),"")))))))) -> 农产品 | Z66: =IF(Y66=行业比较!$E$6,ROW(),"")
B67: 54 | C67: 金元证券 | D67: =B67 -> 54 | V67: =IF(Z67="",0,RANK(Z67,Z:Z,1)) -> 0 | W67: =IF(板块成分!B69="","",板块成分!B69) -> 0075.HK | X67: =[1]!s_info_name(W67) -> 渝太地产 | Y67: =IF($Y$3="申万一级行业",[1]!s_info_industry_sw_2021(W67,公司分析!D$5,1),IF($Y$3="申万二级行业",[1]!s_info_industry_sw_2021(W67,公司分析!D$5,2),IF($Y$3="申万三级行业",[1]!s_info_industry_sw_2021(W67,公司分析!D$5,3),IF($Y$3="wind一级行业",[1]!s_info_industry_gics(W67,1),IF($Y$3="wind二级行业",[1]!s_info_industry_gics(W67,2),IF($Y$3="wind三级行业",[1]!s_info_industry_gics(W67,3),IF($Y$3="wind四级行业",[1]!s_info_industry_gics(W67,4),IF($Y$3="证监会门类行业",[1]!s_info_industry_csrc12_n(W67,公司分析!D$5,1),"")))))))) -> 房地产经营公司 | Z67: =IF(Y67=行业比较!$E$6,ROW(),"")
B68: 55 | C68: 民生证券 | D68: =B68 -> 55 | V68: =IF(Z68="",0,RANK(Z68,Z:Z,1)) -> 0 | W68: =IF(板块成分!B70="","",板块成分!B70) -> 0076.HK | X68: =[1]!s_info_name(W68) -> 谊砾控股 | Y68: =IF($Y$3="申万一级行业",[1]!s_info_industry_sw_2021(W68,公司分析!D$5,1),IF($Y$3="申万二级行业",[1]!s_info_industry_sw_2021(W68,公司分析!D$5,2),IF($Y$3="申万三级行业",[1]!s_info_industry_sw_2021(W68,公司分析!D$5,3),IF($Y$3="wind一级行业",[1]!s_info_industry_gics(W68,1),IF($Y$3="wind二级行业",[1]!s_info_industry_gics(W68,2),IF($Y$3="wind三级行业",[1]!s_info_industry_gics(W68,3),IF($Y$3="wind四级行业",[1]!s_info_industry_gics(W68,4),IF($Y$3="证监会门类行业",[1]!s_info_industry_csrc12_n(W68,公司分析!D$5,1),"")))))))) -> 电子制造服务 | Z68: =IF(Y68=行业比较!$E$6,ROW(),"")
B69: 56 | C69: 南京证券 | D69: =B69 -> 56 | V69: =IF(Z69="",0,RANK(Z69,Z:Z,1)) -> 0 | W69: =IF(板块成分!B71="","",板块成分!B71) -> 0077.HK | X69: =[1]!s_info_name(W69) -> 进智公共交通 | Y69: =IF($Y$3="申万一级行业",[1]!s_info_industry_sw_2021(W69,公司分析!D$5,1),IF($Y$3="申万二级行业",[1]!s_info_industry_sw_2021(W69,公司分析!D$5,2),IF($Y$3="申万三级行业",[1]!s_info_industry_sw_2021(W69,公司分析!D$5,3),IF($Y$3="wind一级行业",[1]!s_info_industry_gics(W69,1),IF($Y$3="wind二级行业",[1]!s_info_industry_gics(W69,2),IF($Y$3="wind三级行业",[1]!s_info_industry_gics(W69,3),IF($Y$3="wind四级行业",[1]!s_info_industry_gics(W69,4),IF($Y$3="证监会门类行业",[1]!s_info_industry_csrc12_n(W69,公司分析!D$5,1),"")))))))) -> 公路运输 | Z69: =IF(Y69=行业比较!$E$6,ROW(),"")
B70: 57 | C70: 齐鲁证券 | D70: =B70 -> 57 | V70: =IF(Z70="",0,RANK(Z70,Z:Z,1)) -> 0 | W70: =IF(板块成分!B72="","",板块成分!B72) -> 0078.HK | X70: =[1]!s_info_name(W70) -> REGAL INT'L | Y70: =IF($Y$3="申万一级行业",[1]!s_info_industry_sw_2021(W70,公司分析!D$5,1),IF($Y$3="申万二级行业",[1]!s_info_industry_sw_2021(W70,公司分析!D$5,2),IF($Y$3="申万三级行业",[1]!s_info_industry_sw_2021(W70,公司分析!D$5,3),IF($Y$3="wind一级行业",[1]!s_info_industry_gics(W70,1),IF($Y$3="wind二级行业",[1]!s_info_industry_gics(W70,2),IF($Y$3="wind三级行业",[1]!s_info_industry_gics(W70,3),IF($Y$3="wind四级行业",[1]!s_info_industry_gics(W70,4),IF($Y$3="证监会门类行业",[1]!s_info_industry_csrc12_n(W70,公司分析!D$5,1),"")))))))) -> 酒店、度假村与豪华游轮 | Z70: =IF(Y70=行业比较!$E$6,ROW(),"")
B71: 58 | C71: 日信证券 | D71: =B71 -> 58 | V71: =IF(Z71="",0,RANK(Z71,Z:Z,1)) -> 0 | W71: =IF(板块成分!B73="","",板块成分!B73) -> 0079.HK | X71: =[1]!s_info_name(W71) -> 世纪建业 | Y71: =IF($Y$3="申万一级行业",[1]!s_info_industry_sw_2021(W71,公司分析!D$5,1),IF($Y$3="申万二级行业",[1]!s_info_industry_sw_2021(W71,公司分析!D$5,2),IF($Y$3="申万三级行业",[1]!s_info_industry_sw_2021(W71,公司分析!D$5,3),IF($Y$3="wind一级行业",[1]!s_info_industry_gics(W71,1),IF($Y$3="wind二级行业",[1]!s_info_industry_gics(W71,2),IF($Y$3="wind三级行业",[1]!s_info_industry_gics(W71,3),IF($Y$3="wind四级行业",[1]!s_info_industry_gics(W71,4),IF($Y$3="证监会门类行业",[1]!s_info_industry_csrc12_n(W71,公司分析!D$5,1),"")))))))) -> 特殊消费者服务 | Z71: =IF(Y71=行业比较!$E$6,ROW(),"")
B72: 59 | C72: 瑞信方正 | D72: =B72 -> 59 | V72: =IF(Z72="",0,RANK(Z72,Z:Z,1)) -> 0 | W72: =IF(板块成分!B74="","",板块成分!B74) -> 0080.HK | X72: =[1]!s_info_name(W72) -> 中国新经济投资 | Y72: =IF($Y$3="申万一级行业",[1]!s_info_industry_sw_2021(W72,公司分析!D$5,1),IF($Y$3="申万二级行业",[1]!s_info_industry_sw_2021(W72,公司分析!D$5,2),IF($Y$3="申万三级行业",[1]!s_info_industry_sw_2021(W72,公司分析!D$5,3),IF($Y$3="wind一级行业",[1]!s_info_industry_gics(W72,1),IF($Y$3="wind二级行业",[1]!s_info_industry_gics(W72,2),IF($Y$3="wind三级行业",[1]!s_info_industry_gics(W72,3),IF($Y$3="wind四级行业",[1]!s_info_industry_gics(W72,4),IF($Y$3="证监会门类行业",[1]!s_info_industry_csrc12_n(W72,公司分析!D$5,1),"")))))))) -> 资产管理与托管银行 | Z72: =IF(Y72=行业比较!$E$6,ROW(),"")
B73: 60 | C73: 瑞银证券 | D73: =B73 -> 60 | V73: =IF(Z73="",0,RANK(Z73,Z:Z,1)) -> 0 | W73: =IF(板块成分!B75="","",板块成分!B75) -> 0081.HK | X73: =[1]!s_info_name(W73) -> 中国海外宏洋集团 | Y73: =IF($Y$3="申万一级行业",[1]!s_info_industry_sw_2021(W73,公司分析!D$5,1),IF($Y$3="申万二级行业",[1]!s_info_industry_sw_2021(W73,公司分析!D$5,2),IF($Y$3="申万三级行业",[1]!s_info_industry_sw_2021(W73,公司分析!D$5,3),IF($Y$3="wind一级行业",[1]!s_info_industry_gics(W73,1),IF($Y$3="wind二级行业",[1]!s_info_industry_gics(W73,2),IF($Y$3="wind三级行业",[1]!s_info_industry_gics(W73,3),IF($Y$3="wind四级行业",[1]!s_info_industry_gics(W73,4),IF($Y$3="证监会门类行业",[1]!s_info_industry_csrc12_n(W73,公司分析!D$5,1),"")))))))) -> 房地产开发 | Z73: =IF(Y73=行业比较!$E$6,ROW(),"")
B74: 61 | C74: 山西证券 | D74: =B74 -> 61 | V74: =IF(Z74="",0,RANK(Z74,Z:Z,1)) -> 0 | W74: =IF(板块成分!B76="","",板块成分!B76) -> 0082.HK | X74: =[1]!s_info_name(W74) -> 疯狂体育 | Y74: =IF($Y$3="申万一级行业",[1]!s_info_industry_sw_2021(W74,公司分析!D$5,1),IF($Y$3="申万二级行业",[1]!s_info_industry_sw_2021(W74,公司分析!D$5,2),IF($Y$3="申万三级行业",[1]!s_info_industry_sw_2021(W74,公司分析!D$5,3),IF($Y$3="wind一级行业",[1]!s_info_industry_gics(W74,1),IF($Y$3="wind二级行业",[1]!s_info_industry_gics(W74,2),IF($Y$3="wind三级行业",[1]!s_info_industry_gics(W74,3),IF($Y$3="wind四级行业",[1]!s_info_industry_gics(W74,4),IF($Y$3="证监会门类行业",[1]!s_info_industry_csrc12_n(W74,公司分析!D$5,1),"")))))))) -> 应用软件 | Z74: =IF(Y74=行业比较!$E$6,ROW(),"")
B75: 62 | C75: 万联证券 | D75: =B75 -> 62 | V75: =IF(Z75="",0,RANK(Z75,Z:Z,1)) -> 0 | W75: =IF(板块成分!B77="","",板块成分!B77) -> 0083.HK | X75: =[1]!s_info_name(W75) -> 信和置业 | Y75: =IF($Y$3="申万一级行业",[1]!s_info_industry_sw_2021(W75,公司分析!D$5,1),IF($Y$3="申万二级行业",[1]!s_info_industry_sw_2021(W75,公司分析!D$5,2),IF($Y$3="申万三级行业",[1]!s_info_industry_sw_2021(W75,公司分析!D$5,3),IF($Y$3="wind一级行业",[1]!s_info_industry_gics(W75,1),IF($Y$3="wind二级行业",[1]!s_info_industry_gics(W75,2),IF($Y$3="wind三级行业",[1]!s_info_industry_gics(W75,3),IF($Y$3="wind四级行业",[1]!s_info_industry_gics(W75,4),IF($Y$3="证监会门类行业",[1]!s_info_industry_csrc12_n(W75,公司分析!D$5,1),"")))))))) -> 房地产开发 | Z75: =IF(Y75=行业比较!$E$6,ROW(),"")
B76: 63 | C76: 湘财证券 | D76: =B76 -> 63 | V76: =IF(Z76="",0,RANK(Z76,Z:Z,1)) -> 0 | W76: =IF(板块成分!B78="","",板块成分!B78) -> 0084.HK | X76: =[1]!s_info_name(W76) -> 宝光实业 | Y76: =IF($Y$3="申万一级行业",[1]!s_info_industry_sw_2021(W76,公司分析!D$5,1),IF($Y$3="申万二级行业",[1]!s_info_industry_sw_2021(W76,公司分析!D$5,2),IF($Y$3="申万三级行业",[1]!s_info_industry_sw_2021(W76,公司分析!D$5,3),IF($Y$3="wind一级行业",[1]!s_info_industry_gics(W76,1),IF($Y$3="wind二级行业",[1]!s_info_industry_gics(W76,2),IF($Y$3="wind三级行业",[1]!s_info_industry_gics(W76,3),IF($Y$3="wind四级行业",[1]!s_info_industry_gics(W76,4),IF($Y$3="证监会门类行业",[1]!s_info_industry_csrc12_n(W76,公司分析!D$5,1),"")))))))) -> 专卖店 | Z76: =IF(Y76=行业比较!$E$6,ROW(),"")
... B85: 23 | C85: 新疆证券 | D85: =B85 -> 23 | V85: =IF(Z85="",0,RANK(Z85,Z:Z,1)) -> 0 | W85: =IF(板块成分!B87="","",板块成分!B87) -> 0093.HK | X85: =[1]!s_info_name(W85) -> TERMBRAY IND | Y85: =IF($Y$3="申万一级行业",[1]!s_info_industry_sw_2021(W85,公司分析!D$5,1),IF($Y$3="申万二级行业",[1]!s_info_industry_sw_2021(W85,公司分析!D$5,2),IF($Y$3="申万三级行业",[1]!s_info_industry_sw_2021(W85,公司分析!D$5,3),IF($Y$3="wind一级行业",[1]!s_info_industry_gics(W85,1),IF($Y$3="wind二级行业",[1]!s_info_industry_gics(W85,2),IF($Y$3="wind三级行业",[1]!s_info_industry_gics(W85,3),IF($Y$3="wind四级行业",[1]!s_info_industry_gics(W85,4),IF($Y$3="证监会门类行业",[1]!s_info_industry_csrc12_n(W85,公司分析!D$5,1),"")))))))) -> 消费信贷 | Z85: =IF(Y85=行业比较!$E$6,ROW(),"")
B86: 72 | D86: =B86 -> 72 | V86: =IF(Z86="",0,RANK(Z86,Z:Z,1)) -> 0 | W86: =IF(板块成分!B88="","",板块成分!B88) -> 0094.HK | X86: =[1]!s_info_name(W86) -> 绿心集团 | Y86: =IF($Y$3="申万一级行业",[1]!s_info_industry_sw_2021(W86,公司分析!D$5,1),IF($Y$3="申万二级行业",[1]!s_info_industry_sw_2021(W86,公司分析!D$5,2),IF($Y$3="申万三级行业",[1]!s_info_industry_sw_2021(W86,公司分析!D$5,3),IF($Y$3="wind一级行业",[1]!s_info_industry_gics(W86,1),IF($Y$3="wind二级行业",[1]!s_info_industry_gics(W86,2),IF($Y$3="wind三级行业",[1]!s_info_industry_gics(W86,3),IF($Y$3="wind四级行业",[1]!s_info_industry_gics(W86,4),IF($Y$3="证监会门类行业",[1]!s_info_industry_csrc12_n(W86,公司分析!D$5,1),"")))))))) -> 林木产品 | Z86: =IF(Y86=行业比较!$E$6,ROW(),"")
B87: 73 | D87: =B87 -> 73 | V87: =IF(Z87="",0,RANK(Z87,Z:Z,1)) -> 0 | W87: =IF(板块成分!B89="","",板块成分!B89) -> 0095.HK | X87: =[1]!s_info_name(W87) -> 绿景中国地产 | Y87: =IF($Y$3="申万一级行业",[1]!s_info_industry_sw_2021(W87,公司分析!D$5,1),IF($Y$3="申万二级行业",[1]!s_info_industry_sw_2021(W87,公司分析!D$5,2),IF($Y$3="申万三级行业",[1]!s_info_industry_sw_2021(W87,公司分析!D$5,3),IF($Y$3="wind一级行业",[1]!s_info_industry_gics(W87,1),IF($Y$3="wind二级行业",[1]!s_info_industry_gics(W87,2),IF($Y$3="wind三级行业",[1]!s_info_industry_gics(W87,3),IF($Y$3="wind四级行业",[1]!s_info_industry_gics(W87,4),IF($Y$3="证监会门类行业",[1]!s_info_industry_csrc12_n(W87,公司分析!D$5,1),"")))))))) -> 房地产开发 | Z87: =IF(Y87=行业比较!$E$6,ROW(),"")
B88: 74 | D88: =B88 -> 74 | V88: =IF(Z88="",0,RANK(Z88,Z:Z,1)) -> 0 | W88: =IF(板块成分!B90="","",板块成分!B90) -> 0096.HK | X88: =[1]!s_info_name(W88) -> YUSEI | Y88: =IF($Y$3="申万一级行业",[1]!s_info_industry_sw_2021(W88,公司分析!D$5,1),IF($Y$3="申万二级行业",[1]!s_info_industry_sw_2021(W88,公司分析!D$5,2),IF($Y$3="申万三级行业",[1]!s_info_industry_sw_2021(W88,公司分析!D$5,3),IF($Y$3="wind一级行业",[1]!s_info_industry_gics(W88,1),IF($Y$3="wind二级行业",[1]!s_info_industry_gics(W88,2),IF($Y$3="wind三级行业",[1]!s_info_industry_gics(W88,3),IF($Y$3="wind四级行业",[1]!s_info_industry_gics(W88,4),IF($Y$3="证监会门类行业",[1]!s_info_industry_csrc12_n(W88,公司分析!D$5,1),"")))))))) -> 基础化工 | Z88: =IF(Y88=行业比较!$E$6,ROW(),"")
B89: 75 | D89: =B89 -> 75 | V89: =IF(Z89="",0,RANK(Z89,Z:Z,1)) -> 0 | W89: =IF(板块成分!B91="","",板块成分!B91) -> 0097.HK | X89: =[1]!s_info_name(W89) -> 恒基发展 | Y89: =IF($Y$3="申万一级行业",[1]!s_info_industry_sw_2021(W89,公司分析!D$5,1),IF($Y$3="申万二级行业",[1]!s_info_industry_sw_2021(W89,公司分析!D$5,2),IF($Y$3="申万三级行业",[1]!s_info_industry_sw_2021(W89,公司分析!D$5,3),IF($Y$3="wind一级行业",[1]!s_info_industry_gics(W89,1),IF($Y$3="wind二级行业",[1]!s_info_industry_gics(W89,2),IF($Y$3="wind三级行业",[1]!s_info_industry_gics(W89,3),IF($Y$3="wind四级行业",[1]!s_info_industry_gics(W89,4),IF($Y$3="证监会门类行业",[1]!s_info_industry_csrc12_n(W89,公司分析!D$5,1),"")))))))) -> 百货商店 | Z89: =IF(Y89=行业比较!$E$6,ROW(),"")
B90: 76 | D90: =B90 -> 76 | V90: =IF(Z90="",0,RANK(Z90,Z:Z,1)) -> 0 | W90: =IF(板块成分!B92="","",板块成分!B92) -> 0098.HK | X90: =[1]!s_info_name(W90) -> 兴发铝业 | Y90: =IF($Y$3="申万一级行业",[1]!s_info_industry_sw_2021(W90,公司分析!D$5,1),IF($Y$3="申万二级行业",[1]!s_info_industry_sw_2021(W90,公司分析!D$5,2),IF($Y$3="申万三级行业",[1]!s_info_industry_sw_2021(W90,公司分析!D$5,3),IF($Y$3="wind一级行业",[1]!s_info_industry_gics(W90,1),IF($Y$3="wind二级行业",[1]!s_info_industry_gics(W90,2),IF($Y$3="wind三级行业",[1]!s_info_industry_gics(W90,3),IF($Y$3="wind四级行业",[1]!s_info_industry_gics(W90,4),IF($Y$3="证监会门类行业",[1]!s_info_industry_csrc12_n(W90,公司分析!D$5,1),"")))))))) -> 铝 | Z90: =IF(Y90=行业比较!$E$6,ROW(),"")
B91: 77 | D91: =B91 -> 77 | V91: =IF(Z91="",0,RANK(Z91,Z:Z,1)) -> 0 | W91: =IF(板块成分!B93="","",板块成分!B93) -> 0099.HK | X91: =[1]!s_info_name(W91) -> 王氏国际 | Y91: =IF($Y$3="申万一级行业",[1]!s_info_industry_sw_2021(W91,公司分析!D$5,1),IF($Y$3="申万二级行业",[1]!s_info_industry_sw_2021(W91,公司分析!D$5,2),IF($Y$3="申万三级行业",[1]!s_info_industry_sw_2021(W91,公司分析!D$5,3),IF($Y$3="wind一级行业",[1]!s_info_industry_gics(W91,1),IF($Y$3="wind二级行业",[1]!s_info_industry_gics(W91,2),IF($Y$3="wind三级行业",[1]!s_info_industry_gics(W91,3),IF($Y$3="wind四级行业",[1]!s_info_industry_gics(W91,4),IF($Y$3="证监会门类行业",[1]!s_info_industry_csrc12_n(W91,公司分析!D$5,1),"")))))))) -> 电子制造服务 | Z91: =IF(Y91=行业比较!$E$6,ROW(),"")
B92: 78 | D92: =B92 -> 78 | V92: =IF(Z92="",0,RANK(Z92,Z:Z,1)) -> 0 | W92: =IF(板块成分!B94="","",板块成分!B94) -> 0101.HK | X92: =[1]!s_info_name(W92) -> 恒隆地产 | Y92: =IF($Y$3="申万一级行业",[1]!s_info_industry_sw_2021(W92,公司分析!D$5,1),IF($Y$3="申万二级行业",[1]!s_info_industry_sw_2021(W92,公司分析!D$5,2),IF($Y$3="申万三级行业",[1]!s_info_industry_sw_2021(W92,公司分析!D$5,3),IF($Y$3="wind一级行业",[1]!s_info_industry_gics(W92,1),IF($Y$3="wind二级行业",[1]!s_info_industry_gics(W92,2),IF($Y$3="wind三级行业",[1]!s_info_industry_gics(W92,3),IF($Y$3="wind四级行业",[1]!s_info_industry_gics(W92,4),IF($Y$3="证监会门类行业",[1]!s_info_industry_csrc12_n(W92,公司分析!D$5,1),"")))))))) -> 多样化房地产活动 | Z92: =IF(Y92=行业比较!$E$6,ROW(),"")
