Workbook
Name CASH: 现金流!$C$5:$C$62
Name DAT: 现金流!$B$5:$B$62
Name DUR: 现金流!$D$5:$D$62
Name RATE_1d: 现金流!$E$5:$E$62
Name RATE_1M: 现金流!$I$5:$I$62
Name RATE_1Y: 现金流!$M$5:$M$62
Name RATE_2M: 现金流!$J$5:$J$62
Name RATE_2W: 现金流!$G$5:$G$62
Name RATE_3M: 现金流!$K$5:$K$62
Name RATE_3W: 现金流!$H$5:$H$62
Name RATE_5M: 现金流!$L$5:$L$62
Name RATE_7d: 现金流!$F$5:$F$62
Name RATE_XD: 现金流!$N$5:$N$62

Sheet 模拟分析
B5: 债券简称 | C5: 220010.IB | D5: 债券简称 | E5: =[1]!b_info_name(C5) -> 22附息国债10 | F5: 票面利率 | G5: =[1]!b_info_couponrate2(C5) -> 2.76 | H5: 付息频率 | I5: =[1]!b_info_interestfrequency(C5) -> 2 | J5: 次/年 | Q5: 编码 | R5: 曲线名称
B6: 信用评级 | C6: =[1]!b_rate_latestcredit(C5) -> 0 | D6: 发行主体 | E6: =[1]!b_info_issuer(C5) -> 中华人民共和国财政部 | F6: 剩余期限(年） | G6: =[1]!b_anal_ptmyear(C5,TODAY()) -> 8.0765027 | H6: 剩余额度 | I6: =[1]!b_info_issueamount(C5)/100000000 -> 1981.6 | J6: 亿 | Q6: 1882 | R6: 固定利率铁道部收益率曲线 | S6: 持有期收益率
Q7: 1802 | R7: 交易所浮动利率企业债(1y)点差收益率曲线(AAA) | S7: 年化收益率
B8: 购买日期 | C8: =TODAY()-1 -> 45398 | D8: 清算速度 | E8: T+0 | F8: 应计利息 | G8: =[1]!b_calc_accrint(C5,I8) -> 1.1601099 | H8: 实际结算日期 | I8: =IF(E8="T+1",C8+1,C8) -> 45398 | J8: 交易日净价 | K8: =[1]!b_dq_originclose(C5,I8,1) -> 103.221 | Q8: 1802 | R8: 交易所浮动利率企业债(1y)点差收益率曲线(AAA)
B9: 购买净价 | C9: 100.0149 | D9: 交易面额（百万） | E9: 500 | F9: 购买全价 | G9: =G8+C9 -> 101.17501 | H9: 交易金额（百万） | I9: =E9*G9/100 -> 505.87505 | J9: 是否含权 | K9: =[1]!b_info_clause(C5) -> 0 | Q9: 1012 | R9: 交易所固定利率国债收益率曲线 | S9: T+0
Q10: 1022 | R10: 交易所固定利率企业债收益率曲线(AAA) | S10: T+1
B11: 资金成本 | C11: 0.1 | D11: 要求收益率 | E11: 0.15 | F11: 曲线选择日 | G11: =TODAY()-1 -> 45398 | H11: 是否行权 | I11: 否 | J11: 行权价格 | K11: =IF(LEFT(K9,2)="赎回",[1]!b_info_redemptionprice(C5),IF(LEFT(K9,2)="回售",[1]!b_info_repurchaseprice(C5),"")) | Q11: 1032 | R11: 央行票据收益率曲线
B12: 折算曲线 | C12: 银行间固定利率国债收益率曲线 | F12: 曲线平移 | G12: 3 | H12: 曲线方法 | I12: 远期曲线法 | J12: 行权日期 | K12: =IF(LEFT(K9,2)="赎回",[1]!b_info_redemptiondate(C5),IF(LEFT(K9,2)="回售",[1]!b_info_repurchasedate(C5),"")) | Q12: 1112 | R12: 银行间浮动利率国债点差(1y)收益率曲线
Q13: 1472 | R13: 银行间浮动利率企业债(1y)点差收益率曲线(AA+) | S13: 远期曲线法
B14: 定价情景分析(全价） | Q14: 1122 | R14: 银行间浮动利率企业债(1y)点差收益率曲线(AAA) | S14: 到期平移法
C15: 1d | D15: 7d | E15: 2W | F15: 3W | G15: 1M | H15: 2M | I15: 3M | J15: 5M | K15: 1Y | L15: 365 | M15: Day | Q15: 1132 | R15: 银行间浮动利率企业债(R07D)点差收益率曲线
C16: 1 | D16: 7 | E16: 14 | F16: 21 | G16: 30 | H16: 60 | I16: 90 | J16: 150 | K16: 365 | L16: =L15 -> 365 | Q16: 1412 | R16: 银行间浮动利率企业债(SHIBOR)点差收益率曲线
A17: 0.005 | B17: +50bp | C17: =IF(C$16/365>$G$6,"",SUMPRODUCT(CASH,(1/(1+RATE_1d/100+$A17)^(DUR-C$16/365))*((DUR-C$16/365)>0))) -> 101.15486 | D17: =IF(D$16/365>$G$6,"",SUMPRODUCT(CASH,(1/(1+RATE_7d/100+$A17)^(DUR-D$16/365))*((DUR-D$16/365)>0))) -> 101.18715 | E17: =IF(E$16/365>$G$6,"",SUMPRODUCT(CASH,(1/(1+RATE_2W/100+$A17)^(DUR-E$16/365))*((DUR-E$16/365)>0))) -> 101.22578 | F17: =IF(F$16/365>$G$6,"",SUMPRODUCT(CASH,(1/(1+RATE_3W/100+$A17)^(DUR-F$16/365))*((DUR-F$16/365)>0))) -> 101.26545 | G17: =IF(G$16/365>$G$6,"",SUMPRODUCT(CASH,(1/(1+RATE_1M/100+$A17)^(DUR-G$16/365))*((DUR-G$16/365)>0))) -> 99.937679 | H17: =IF(H$16/365>$G$6,"",SUMPRODUCT(CASH,(1/(1+RATE_2M/100+$A17)^(DUR-H$16/365))*((DUR-H$16/365)>0))) -> 100.10808 | I17: =IF(I$16/365>$G$6,"",SUMPRODUCT(CASH,(1/(1+RATE_3M/100+$A17)^(DUR-I$16/365))*((DUR-I$16/365)>0))) -> 100.27723 | J17: =IF(J$16/365>$G$6,"",SUMPRODUCT(CASH,(1/(1+RATE_5M/100+$A17)^(DUR-J$16/365))*((DUR-J$16/365)>0))) -> 100.63359 | K17: =IF(K$16/365>$G$6,"",SUMPRODUCT(CASH,(1/(1+RATE_1Y/100+$A17)^(DUR-K$16/365))*((DUR-K$16/365)>0))) -> 100.62624 | L17: =IF(L$16/365>$G$6,"",SUMPRODUCT(CASH,(1/(1+RATE_XD/100+$A17)^(DUR-L$16/365))*((DUR-L$16/365)>0))) -> 100.62624 | Q17: 1862 | R17: 银行间浮动利率企业债(SHIBOR_1Y_10D)点差收益率曲线(AA+(2)) | S17: 是
A18: 0.003 | B18: +30bp | C18: =IF(C$16/365>$G$6,"",SUMPRODUCT(CASH,(1/(1+RATE_1d/100+$A18)^(DUR-C$16/365))*((DUR-C$16/365)>0))) -> 102.58608 | D18: =IF(D$16/365>$G$6,"",SUMPRODUCT(CASH,(1/(1+RATE_7d/100+$A18)^(DUR-D$16/365))*((DUR-D$16/365)>0))) -> 102.61552 | E18: =IF(E$16/365>$G$6,"",SUMPRODUCT(CASH,(1/(1+RATE_2W/100+$A18)^(DUR-E$16/365))*((DUR-E$16/365)>0))) -> 102.65083 | F18: =IF(F$16/365>$G$6,"",SUMPRODUCT(CASH,(1/(1+RATE_3W/100+$A18)^(DUR-F$16/365))*((DUR-F$16/365)>0))) -> 102.6872 | G18: =IF(G$16/365>$G$6,"",SUMPRODUCT(CASH,(1/(1+RATE_1M/100+$A18)^(DUR-G$16/365))*((DUR-G$16/365)>0))) -> 101.35521 | H18: =IF(H$16/365>$G$6,"",SUMPRODUCT(CASH,(1/(1+RATE_2M/100+$A18)^(DUR-H$16/365))*((DUR-H$16/365)>0))) -> 101.51167 | I18: =IF(I$16/365>$G$6,"",SUMPRODUCT(CASH,(1/(1+RATE_3M/100+$A18)^(DUR-I$16/365))*((DUR-I$16/365)>0))) -> 101.6668 | J18: =IF(J$16/365>$G$6,"",SUMPRODUCT(CASH,(1/(1+RATE_5M/100+$A18)^(DUR-J$16/365))*((DUR-J$16/365)>0))) -> 101.99524 | K18: =IF(K$16/365>$G$6,"",SUMPRODUCT(CASH,(1/(1+RATE_1Y/100+$A18)^(DUR-K$16/365))*((DUR-K$16/365)>0))) -> 101.88873 | L18: =IF(L$16/365>$G$6,"",SUMPRODUCT(CASH,(1/(1+RATE_XD/100+$A18)^(DUR-L$16/365))*((DUR-L$16/365)>0))) -> 101.88873 | Q18: 1142 | R18: 银行间浮动利率商业银行债(1y)点差收益率曲线(AA) | S18: 否
A19: 0.002 | B19: +20bp | C19: =IF(C$16/365>$G$6,"",SUMPRODUCT(CASH,(1/(1+RATE_1d/100+$A19)^(DUR-C$16/365))*((DUR-C$16/365)>0))) -> 103.31094 | D19: =IF(D$16/365>$G$6,"",SUMPRODUCT(CASH,(1/(1+RATE_7d/100+$A19)^(DUR-D$16/365))*((DUR-D$16/365)>0))) -> 103.33891 | E19: =IF(E$16/365>$G$6,"",SUMPRODUCT(CASH,(1/(1+RATE_2W/100+$A19)^(DUR-E$16/365))*((DUR-E$16/365)>0))) -> 103.37252 | F19: =IF(F$16/365>$G$6,"",SUMPRODUCT(CASH,(1/(1+RATE_3W/100+$A19)^(DUR-F$16/365))*((DUR-F$16/365)>0))) -> 103.40719 | G19: =IF(G$16/365>$G$6,"",SUMPRODUCT(CASH,(1/(1+RATE_1M/100+$A19)^(DUR-G$16/365))*((DUR-G$16/365)>0))) -> 102.07305 | H19: =IF(H$16/365>$G$6,"",SUMPRODUCT(CASH,(1/(1+RATE_2M/100+$A19)^(DUR-H$16/365))*((DUR-H$16/365)>0))) -> 102.22237 | I19: =IF(I$16/365>$G$6,"",SUMPRODUCT(CASH,(1/(1+RATE_3M/100+$A19)^(DUR-I$16/365))*((DUR-I$16/365)>0))) -> 102.37032 | J19: =IF(J$16/365>$G$6,"",SUMPRODUCT(CASH,(1/(1+RATE_5M/100+$A19)^(DUR-J$16/365))*((DUR-J$16/365)>0))) -> 102.68448 | K19: =IF(K$16/365>$G$6,"",SUMPRODUCT(CASH,(1/(1+RATE_1Y/100+$A19)^(DUR-K$16/365))*((DUR-K$16/365)>0))) -> 102.52725 | L19: =IF(L$16/365>$G$6,"",SUMPRODUCT(CASH,(1/(1+RATE_XD/100+$A19)^(DUR-L$16/365))*((DUR-L$16/365)>0))) -> 102.52725 | Q19: 1152 | R19: 银行间浮动利率商业银行债(1y)点差收益率曲线(AA-)
A20: 0.0015 | B20: +15bp | C20: =IF(C$16/365>$G$6,"",SUMPRODUCT(CASH,(1/(1+RATE_1d/100+$A20)^(DUR-C$16/365))*((DUR-C$16/365)>0))) -> 103.6757 | D20: =IF(D$16/365>$G$6,"",SUMPRODUCT(CASH,(1/(1+RATE_7d/100+$A20)^(DUR-D$16/365))*((DUR-D$16/365)>0))) -> 103.70293 | E20: =IF(E$16/365>$G$6,"",SUMPRODUCT(CASH,(1/(1+RATE_2W/100+$A20)^(DUR-E$16/365))*((DUR-E$16/365)>0))) -> 103.73569 | F20: =IF(F$16/365>$G$6,"",SUMPRODUCT(CASH,(1/(1+RATE_3W/100+$A20)^(DUR-F$16/365))*((DUR-F$16/365)>0))) -> 103.7695 | G20: =IF(G$16/365>$G$6,"",SUMPRODUCT(CASH,(1/(1+RATE_1M/100+$A20)^(DUR-G$16/365))*((DUR-G$16/365)>0))) -> 102.43426 | H20: =IF(H$16/365>$G$6,"",SUMPRODUCT(CASH,(1/(1+RATE_2M/100+$A20)^(DUR-H$16/365))*((DUR-H$16/365)>0))) -> 102.57997 | I20: =IF(I$16/365>$G$6,"",SUMPRODUCT(CASH,(1/(1+RATE_3M/100+$A20)^(DUR-I$16/365))*((DUR-I$16/365)>0))) -> 102.72429 | J20: =IF(J$16/365>$G$6,"",SUMPRODUCT(CASH,(1/(1+RATE_5M/100+$A20)^(DUR-J$16/365))*((DUR-J$16/365)>0))) -> 103.03122 | K20: =IF(K$16/365>$G$6,"",SUMPRODUCT(CASH,(1/(1+RATE_1Y/100+$A20)^(DUR-K$16/365))*((DUR-K$16/365)>0))) -> 102.84835 | L20: =IF(L$16/365>$G$6,"",SUMPRODUCT(CASH,(1/(1+RATE_XD/100+$A20)^(DUR-L$16/365))*((DUR-L$16/365)>0))) -> 102.84835 | Q20: 1922 | R20: 银行间浮动利率商业银行债(1y)点差收益率曲线(AA+)
A21: 0.001 | B21: +10bp | C21: =IF(C$16/365>$G$6,"",SUMPRODUCT(CASH,(1/(1+RATE_1d/100+$A21)^(DUR-C$16/365))*((DUR-C$16/365)>0))) -> 104.04203 | D21: =IF(D$16/365>$G$6,"",SUMPRODUCT(CASH,(1/(1+RATE_7d/100+$A21)^(DUR-D$16/365))*((DUR-D$16/365)>0))) -> 104.06851 | E21: =IF(E$16/365>$G$6,"",SUMPRODUCT(CASH,(1/(1+RATE_2W/100+$A21)^(DUR-E$16/365))*((DUR-E$16/365)>0))) -> 104.1004 | F21: =IF(F$16/365>$G$6,"",SUMPRODUCT(CASH,(1/(1+RATE_3W/100+$A21)^(DUR-F$16/365))*((DUR-F$16/365)>0))) -> 104.13335 | G21: =IF(G$16/365>$G$6,"",SUMPRODUCT(CASH,(1/(1+RATE_1M/100+$A21)^(DUR-G$16/365))*((DUR-G$16/365)>0))) -> 102.79701 | H21: =IF(H$16/365>$G$6,"",SUMPRODUCT(CASH,(1/(1+RATE_2M/100+$A21)^(DUR-H$16/365))*((DUR-H$16/365)>0))) -> 102.93908 | I21: =IF(I$16/365>$G$6,"",SUMPRODUCT(CASH,(1/(1+RATE_3M/100+$A21)^(DUR-I$16/365))*((DUR-I$16/365)>0))) -> 103.07973 | J21: =IF(J$16/365>$G$6,"",SUMPRODUCT(CASH,(1/(1+RATE_5M/100+$A21)^(DUR-J$16/365))*((DUR-J$16/365)>0))) -> 103.37938 | K21: =IF(K$16/365>$G$6,"",SUMPRODUCT(CASH,(1/(1+RATE_1Y/100+$A21)^(DUR-K$16/365))*((DUR-K$16/365)>0))) -> 103.17068 | L21: =IF(L$16/365>$G$6,"",SUMPRODUCT(CASH,(1/(1+RATE_XD/100+$A21)^(DUR-L$16/365))*((DUR-L$16/365)>0))) -> 103.17068 | Q21: 1162 | R21: 银行间浮动利率商业银行债(1y)点差收益率曲线(AAA)
A22: 0.0005 | B22: +5bp | C22: =IF(C$16/365>$G$6,"",SUMPRODUCT(CASH,(1/(1+RATE_1d/100+$A22)^(DUR-C$16/365))*((DUR-C$16/365)>0))) -> 104.40993 | D22: =IF(D$16/365>$G$6,"",SUMPRODUCT(CASH,(1/(1+RATE_7d/100+$A22)^(DUR-D$16/365))*((DUR-D$16/365)>0))) -> 104.43567 | E22: =IF(E$16/365>$G$6,"",SUMPRODUCT(CASH,(1/(1+RATE_2W/100+$A22)^(DUR-E$16/365))*((DUR-E$16/365)>0))) -> 104.46668 | F22: =IF(F$16/365>$G$6,"",SUMPRODUCT(CASH,(1/(1+RATE_3W/100+$A22)^(DUR-F$16/365))*((DUR-F$16/365)>0))) -> 104.49876 | G22: =IF(G$16/365>$G$6,"",SUMPRODUCT(CASH,(1/(1+RATE_1M/100+$A22)^(DUR-G$16/365))*((DUR-G$16/365)>0))) -> 103.16131 | H22: =IF(H$16/365>$G$6,"",SUMPRODUCT(CASH,(1/(1+RATE_2M/100+$A22)^(DUR-H$16/365))*((DUR-H$16/365)>0))) -> 103.2997 | I22: =IF(I$16/365>$G$6,"",SUMPRODUCT(CASH,(1/(1+RATE_3M/100+$A22)^(DUR-I$16/365))*((DUR-I$16/365)>0))) -> 103.43667 | J22: =IF(J$16/365>$G$6,"",SUMPRODUCT(CASH,(1/(1+RATE_5M/100+$A22)^(DUR-J$16/365))*((DUR-J$16/365)>0))) -> 103.72898 | K22: =IF(K$16/365>$G$6,"",SUMPRODUCT(CASH,(1/(1+RATE_1Y/100+$A22)^(DUR-K$16/365))*((DUR-K$16/365)>0))) -> 103.49425 | L22: =IF(L$16/365>$G$6,"",SUMPRODUCT(CASH,(1/(1+RATE_XD/100+$A22)^(DUR-L$16/365))*((DUR-L$16/365)>0))) -> 103.49425 | Q22: 1172 | R22: 银行间浮动利率商业银行债(R07D)点差收益率曲线(AAA)
A23: 0 | B23: 0bp | C23: =IF(C$16/365>$G$6,"",SUMPRODUCT(CASH,(1/(1+RATE_1d/100+$A23)^(DUR-C$16/365))*((DUR-C$16/365)>0))) -> 104.77941 | D23: =IF(D$16/365>$G$6,"",SUMPRODUCT(CASH,(1/(1+RATE_7d/100+$A23)^(DUR-D$16/365))*((DUR-D$16/365)>0))) -> 104.80439 | E23: =IF(E$16/365>$G$6,"",SUMPRODUCT(CASH,(1/(1+RATE_2W/100+$A23)^(DUR-E$16/365))*((DUR-E$16/365)>0))) -> 104.83453 | F23: =IF(F$16/365>$G$6,"",SUMPRODUCT(CASH,(1/(1+RATE_3W/100+$A23)^(DUR-F$16/365))*((DUR-F$16/365)>0))) -> 104.86573 | G23: =IF(G$16/365>$G$6,"",SUMPRODUCT(CASH,(1/(1+RATE_1M/100+$A23)^(DUR-G$16/365))*((DUR-G$16/365)>0))) -> 103.52716 | H23: =IF(H$16/365>$G$6,"",SUMPRODUCT(CASH,(1/(1+RATE_2M/100+$A23)^(DUR-H$16/365))*((DUR-H$16/365)>0))) -> 103.66185 | I23: =IF(I$16/365>$G$6,"",SUMPRODUCT(CASH,(1/(1+RATE_3M/100+$A23)^(DUR-I$16/365))*((DUR-I$16/365)>0))) -> 103.7951 | J23: =IF(J$16/365>$G$6,"",SUMPRODUCT(CASH,(1/(1+RATE_5M/100+$A23)^(DUR-J$16/365))*((DUR-J$16/365)>0))) -> 104.08001 | K23: =IF(K$16/365>$G$6,"",SUMPRODUCT(CASH,(1/(1+RATE_1Y/100+$A23)^(DUR-K$16/365))*((DUR-K$16/365)>0))) -> 103.81906 | L23: =IF(L$16/365>$G$6,"",SUMPRODUCT(CASH,(1/(1+RATE_XD/100+$A23)^(DUR-L$16/365))*((DUR-L$16/365)>0))) -> 103.81906 | Q23: 1702 | R23: 银行间浮动利率商业银行债(SHIBOR)点差收益率曲线(AA)
A24: -0.0005 | B24: -5bp | C24: =IF(C$16/365>$G$6,"",SUMPRODUCT(CASH,(1/(1+RATE_1d/100+$A24)^(DUR-C$16/365))*((DUR-C$16/365)>0))) -> 105.15049 | D24: =IF(D$16/365>$G$6,"",SUMPRODUCT(CASH,(1/(1+RATE_7d/100+$A24)^(DUR-D$16/365))*((DUR-D$16/365)>0))) -> 105.17471 | E24: =IF(E$16/365>$G$6,"",SUMPRODUCT(CASH,(1/(1+RATE_2W/100+$A24)^(DUR-E$16/365))*((DUR-E$16/365)>0))) -> 105.20395 | F24: =IF(F$16/365>$G$6,"",SUMPRODUCT(CASH,(1/(1+RATE_3W/100+$A24)^(DUR-F$16/365))*((DUR-F$16/365)>0))) -> 105.23427 | G24: =IF(G$16/365>$G$6,"",SUMPRODUCT(CASH,(1/(1+RATE_1M/100+$A24)^(DUR-G$16/365))*((DUR-G$16/365)>0))) -> 103.89458 | H24: =IF(H$16/365>$G$6,"",SUMPRODUCT(CASH,(1/(1+RATE_2M/100+$A24)^(DUR-H$16/365))*((DUR-H$16/365)>0))) -> 104.02554 | I24: =IF(I$16/365>$G$6,"",SUMPRODUCT(CASH,(1/(1+RATE_3M/100+$A24)^(DUR-I$16/365))*((DUR-I$16/365)>0))) -> 104.15504 | J24: =IF(J$16/365>$G$6,"",SUMPRODUCT(CASH,(1/(1+RATE_5M/100+$A24)^(DUR-J$16/365))*((DUR-J$16/365)>0))) -> 104.43249 | K24: =IF(K$16/365>$G$6,"",SUMPRODUCT(CASH,(1/(1+RATE_1Y/100+$A24)^(DUR-K$16/365))*((DUR-K$16/365)>0))) -> 104.14512 | L24: =IF(L$16/365>$G$6,"",SUMPRODUCT(CASH,(1/(1+RATE_XD/100+$A24)^(DUR-L$16/365))*((DUR-L$16/365)>0))) -> 104.14512 | Q24: 1402 | R24: 银行间浮动利率商业银行债(SHIBOR)点差收益率曲线(AAA)
A25: -0.001 | B25: -10bp | C25: =IF(C$16/365>$G$6,"",SUMPRODUCT(CASH,(1/(1+RATE_1d/100+$A25)^(DUR-C$16/365))*((DUR-C$16/365)>0))) -> 105.52317 | D25: =IF(D$16/365>$G$6,"",SUMPRODUCT(CASH,(1/(1+RATE_7d/100+$A25)^(DUR-D$16/365))*((DUR-D$16/365)>0))) -> 105.54661 | E25: =IF(E$16/365>$G$6,"",SUMPRODUCT(CASH,(1/(1+RATE_2W/100+$A25)^(DUR-E$16/365))*((DUR-E$16/365)>0))) -> 105.57496 | F25: =IF(F$16/365>$G$6,"",SUMPRODUCT(CASH,(1/(1+RATE_3W/100+$A25)^(DUR-F$16/365))*((DUR-F$16/365)>0))) -> 105.60439 | G25: =IF(G$16/365>$G$6,"",SUMPRODUCT(CASH,(1/(1+RATE_1M/100+$A25)^(DUR-G$16/365))*((DUR-G$16/365)>0))) -> 104.26356 | H25: =IF(H$16/365>$G$6,"",SUMPRODUCT(CASH,(1/(1+RATE_2M/100+$A25)^(DUR-H$16/365))*((DUR-H$16/365)>0))) -> 104.39076 | I25: =IF(I$16/365>$G$6,"",SUMPRODUCT(CASH,(1/(1+RATE_3M/100+$A25)^(DUR-I$16/365))*((DUR-I$16/365)>0))) -> 104.51648 | J25: =IF(J$16/365>$G$6,"",SUMPRODUCT(CASH,(1/(1+RATE_5M/100+$A25)^(DUR-J$16/365))*((DUR-J$16/365)>0))) -> 104.78642 | K25: =IF(K$16/365>$G$6,"",SUMPRODUCT(CASH,(1/(1+RATE_1Y/100+$A25)^(DUR-K$16/365))*((DUR-K$16/365)>0))) -> 104.47244 | L25: =IF(L$16/365>$G$6,"",SUMPRODUCT(CASH,(1/(1+RATE_XD/100+$A25)^(DUR-L$16/365))*((DUR-L$16/365)>0))) -> 104.47244 | Q25: 1182 | R25: 银行间浮动利率资产支持证券(1y)点差收益率曲线(A)
A26: -0.0015 | B26: -15bp | C26: =IF(C$16/365>$G$6,"",SUMPRODUCT(CASH,(1/(1+RATE_1d/100+$A26)^(DUR-C$16/365))*((DUR-C$16/365)>0))) -> 105.89744 | D26: =IF(D$16/365>$G$6,"",SUMPRODUCT(CASH,(1/(1+RATE_7d/100+$A26)^(DUR-D$16/365))*((DUR-D$16/365)>0))) -> 105.92011 | E26: =IF(E$16/365>$G$6,"",SUMPRODUCT(CASH,(1/(1+RATE_2W/100+$A26)^(DUR-E$16/365))*((DUR-E$16/365)>0))) -> 105.94756 | F26: =IF(F$16/365>$G$6,"",SUMPRODUCT(CASH,(1/(1+RATE_3W/100+$A26)^(DUR-F$16/365))*((DUR-F$16/365)>0))) -> 105.9761 | G26: =IF(G$16/365>$G$6,"",SUMPRODUCT(CASH,(1/(1+RATE_1M/100+$A26)^(DUR-G$16/365))*((DUR-G$16/365)>0))) -> 104.63412 | H26: =IF(H$16/365>$G$6,"",SUMPRODUCT(CASH,(1/(1+RATE_2M/100+$A26)^(DUR-H$16/365))*((DUR-H$16/365)>0))) -> 104.75753 | I26: =IF(I$16/365>$G$6,"",SUMPRODUCT(CASH,(1/(1+RATE_3M/100+$A26)^(DUR-I$16/365))*((DUR-I$16/365)>0))) -> 104.87944 | J26: =IF(J$16/365>$G$6,"",SUMPRODUCT(CASH,(1/(1+RATE_5M/100+$A26)^(DUR-J$16/365))*((DUR-J$16/365)>0))) -> 105.14181 | K26: =IF(K$16/365>$G$6,"",SUMPRODUCT(CASH,(1/(1+RATE_1Y/100+$A26)^(DUR-K$16/365))*((DUR-K$16/365)>0))) -> 104.80102 | L26: =IF(L$16/365>$G$6,"",SUMPRODUCT(CASH,(1/(1+RATE_XD/100+$A26)^(DUR-L$16/365))*((DUR-L$16/365)>0))) -> 104.80102 | Q26: 1192 | R26: 银行间浮动利率资产支持证券(R07D)点差收益率曲线(A)
A27: -0.002 | B27: -20bp | C27: =IF(C$16/365>$G$6,"",SUMPRODUCT(CASH,(1/(1+RATE_1d/100+$A27)^(DUR-C$16/365))*((DUR-C$16/365)>0))) -> 106.27334 | D27: =IF(D$16/365>$G$6,"",SUMPRODUCT(CASH,(1/(1+RATE_7d/100+$A27)^(DUR-D$16/365))*((DUR-D$16/365)>0))) -> 106.29523 | E27: =IF(E$16/365>$G$6,"",SUMPRODUCT(CASH,(1/(1+RATE_2W/100+$A27)^(DUR-E$16/365))*((DUR-E$16/365)>0))) -> 106.32177 | F27: =IF(F$16/365>$G$6,"",SUMPRODUCT(CASH,(1/(1+RATE_3W/100+$A27)^(DUR-F$16/365))*((DUR-F$16/365)>0))) -> 106.34939 | G27: =IF(G$16/365>$G$6,"",SUMPRODUCT(CASH,(1/(1+RATE_1M/100+$A27)^(DUR-G$16/365))*((DUR-G$16/365)>0))) -> 105.00626 | H27: =IF(H$16/365>$G$6,"",SUMPRODUCT(CASH,(1/(1+RATE_2M/100+$A27)^(DUR-H$16/365))*((DUR-H$16/365)>0))) -> 105.12585 | I27: =IF(I$16/365>$G$6,"",SUMPRODUCT(CASH,(1/(1+RATE_3M/100+$A27)^(DUR-I$16/365))*((DUR-I$16/365)>0))) -> 105.24393 | J27: =IF(J$16/365>$G$6,"",SUMPRODUCT(CASH,(1/(1+RATE_5M/100+$A27)^(DUR-J$16/365))*((DUR-J$16/365)>0))) -> 105.49866 | K27: =IF(K$16/365>$G$6,"",SUMPRODUCT(CASH,(1/(1+RATE_1Y/100+$A27)^(DUR-K$16/365))*((DUR-K$16/365)>0))) -> 105.13086 | L27: =IF(L$16/365>$G$6,"",SUMPRODUCT(CASH,(1/(1+RATE_XD/100+$A27)^(DUR-L$16/365))*((DUR-L$16/365)>0))) -> 105.13086 | Q27: 1202 | R27: 银行间浮动利率资产支持证券(R07D)点差收益率曲线(AAA)
A28: -0.003 | B28: -30bp | C28: =IF(C$16/365>$G$6,"",SUMPRODUCT(CASH,(1/(1+RATE_1d/100+$A28)^(DUR-C$16/365))*((DUR-C$16/365)>0))) -> 107.03 | D28: =IF(D$16/365>$G$6,"",SUMPRODUCT(CASH,(1/(1+RATE_7d/100+$A28)^(DUR-D$16/365))*((DUR-D$16/365)>0))) -> 107.0503 | E28: =IF(E$16/365>$G$6,"",SUMPRODUCT(CASH,(1/(1+RATE_2W/100+$A28)^(DUR-E$16/365))*((DUR-E$16/365)>0))) -> 107.075 | F28: =IF(F$16/365>$G$6,"",SUMPRODUCT(CASH,(1/(1+RATE_3W/100+$A28)^(DUR-F$16/365))*((DUR-F$16/365)>0))) -> 107.1008 | G28: =IF(G$16/365>$G$6,"",SUMPRODUCT(CASH,(1/(1+RATE_1M/100+$A28)^(DUR-G$16/365))*((DUR-G$16/365)>0))) -> 105.75533 | H28: =IF(H$16/365>$G$6,"",SUMPRODUCT(CASH,(1/(1+RATE_2M/100+$A28)^(DUR-H$16/365))*((DUR-H$16/365)>0))) -> 105.86718 | I28: =IF(I$16/365>$G$6,"",SUMPRODUCT(CASH,(1/(1+RATE_3M/100+$A28)^(DUR-I$16/365))*((DUR-I$16/365)>0))) -> 105.9775 | J28: =IF(J$16/365>$G$6,"",SUMPRODUCT(CASH,(1/(1+RATE_5M/100+$A28)^(DUR-J$16/365))*((DUR-J$16/365)>0))) -> 106.2168 | K28: =IF(K$16/365>$G$6,"",SUMPRODUCT(CASH,(1/(1+RATE_1Y/100+$A28)^(DUR-K$16/365))*((DUR-K$16/365)>0))) -> 105.79436 | L28: =IF(L$16/365>$G$6,"",SUMPRODUCT(CASH,(1/(1+RATE_XD/100+$A28)^(DUR-L$16/365))*((DUR-L$16/365)>0))) -> 105.79436 | Q28: 1212 | R28: 银行间浮动利率资产支持证券(R07D)点差收益率曲线(BBB)
A29: -0.005 | B29: -50bp | C29: =IF(C$16/365>$G$6,"",SUMPRODUCT(CASH,(1/(1+RATE_1d/100+$A29)^(DUR-C$16/365))*((DUR-C$16/365)>0))) -> 108.56302 | D29: =IF(D$16/365>$G$6,"",SUMPRODUCT(CASH,(1/(1+RATE_7d/100+$A29)^(DUR-D$16/365))*((DUR-D$16/365)>0))) -> 108.58009 | E29: =IF(E$16/365>$G$6,"",SUMPRODUCT(CASH,(1/(1+RATE_2W/100+$A29)^(DUR-E$16/365))*((DUR-E$16/365)>0))) -> 108.60102 | F29: =IF(F$16/365>$G$6,"",SUMPRODUCT(CASH,(1/(1+RATE_3W/100+$A29)^(DUR-F$16/365))*((DUR-F$16/365)>0))) -> 108.62307 | G29: =IF(G$16/365>$G$6,"",SUMPRODUCT(CASH,(1/(1+RATE_1M/100+$A29)^(DUR-G$16/365))*((DUR-G$16/365)>0))) -> 107.27281 | H29: =IF(H$16/365>$G$6,"",SUMPRODUCT(CASH,(1/(1+RATE_2M/100+$A29)^(DUR-H$16/365))*((DUR-H$16/365)>0))) -> 107.36883 | I29: =IF(I$16/365>$G$6,"",SUMPRODUCT(CASH,(1/(1+RATE_3M/100+$A29)^(DUR-I$16/365))*((DUR-I$16/365)>0))) -> 107.46325 | J29: =IF(J$16/365>$G$6,"",SUMPRODUCT(CASH,(1/(1+RATE_5M/100+$A29)^(DUR-J$16/365))*((DUR-J$16/365)>0))) -> 107.67094 | K29: =IF(K$16/365>$G$6,"",SUMPRODUCT(CASH,(1/(1+RATE_1Y/100+$A29)^(DUR-K$16/365))*((DUR-K$16/365)>0))) -> 107.13679 | L29: =IF(L$16/365>$G$6,"",SUMPRODUCT(CASH,(1/(1+RATE_XD/100+$A29)^(DUR-L$16/365))*((DUR-L$16/365)>0))) -> 107.13679 | Q29: 1422 | R29: 银行间浮动利率资产支持证券点差(1y)收益率曲线(A+)
A30: =B30/10000 -> 0.001 | B30: 10 | C30: =IF(C$16/365>$G$6,"",SUMPRODUCT(CASH,(1/(1+RATE_1d/100+$A30)^(DUR-C$16/365))*((DUR-C$16/365)>0))) -> 104.04203 | D30: =IF(D$16/365>$G$6,"",SUMPRODUCT(CASH,(1/(1+RATE_7d/100+$A30)^(DUR-D$16/365))*((DUR-D$16/365)>0))) -> 104.06851 | E30: =IF(E$16/365>$G$6,"",SUMPRODUCT(CASH,(1/(1+RATE_2W/100+$A30)^(DUR-E$16/365))*((DUR-E$16/365)>0))) -> 104.1004 | F30: =IF(F$16/365>$G$6,"",SUMPRODUCT(CASH,(1/(1+RATE_3W/100+$A30)^(DUR-F$16/365))*((DUR-F$16/365)>0))) -> 104.13335 | G30: =IF(G$16/365>$G$6,"",SUMPRODUCT(CASH,(1/(1+RATE_1M/100+$A30)^(DUR-G$16/365))*((DUR-G$16/365)>0))) -> 102.79701 | H30: =IF(H$16/365>$G$6,"",SUMPRODUCT(CASH,(1/(1+RATE_2M/100+$A30)^(DUR-H$16/365))*((DUR-H$16/365)>0))) -> 102.93908 | I30: =IF(I$16/365>$G$6,"",SUMPRODUCT(CASH,(1/(1+RATE_3M/100+$A30)^(DUR-I$16/365))*((DUR-I$16/365)>0))) -> 103.07973 | J30: =IF(J$16/365>$G$6,"",SUMPRODUCT(CASH,(1/(1+RATE_5M/100+$A30)^(DUR-J$16/365))*((DUR-J$16/365)>0))) -> 103.37938 | K30: =IF(K$16/365>$G$6,"",SUMPRODUCT(CASH,(1/(1+RATE_1Y/100+$A30)^(DUR-K$16/365))*((DUR-K$16/365)>0))) -> 103.17068 | L30: =IF(L$16/365>$G$6,"",SUMPRODUCT(CASH,(1/(1+RATE_XD/100+$A30)^(DUR-L$16/365))*((DUR-L$16/365)>0))) -> 103.17068 | Q30: 1812 | R30: 银行间浮动利率资产支持证券点差(1y)收益率曲线(AA-)
Q31: 1222 | R31: 银行间浮动利率资产支持证券点差(1y)收益率曲线(AAA)
B32: 收益类型 | C32: 年化收益率 | Q32: 1432 | R32: 银行间浮动利率资产支持证券点差(1y)收益率曲线(BBB)
B33: 投资超额收益分析 | Q33: 1232 | R33: 银行间固定利率国债收益率曲线
C34: 1d | D34: 7d | E34: 2W | F34: 3W | G34: 1M | H34: 2M | I34: 3M | J34: 5M | K34: 1Y | L34: =L15&"d" -> 365d | Q34: 1242 | R34: 银行间固定利率美元债券收益率曲线
B35: +50bp | C35: =IF(C17="","",IF($C$32="年化收益率",((SUMPRODUCT(((DUR-C$16/365)<0)*CASH)+C17-$G$9*(1+C$16*$C$11/365))/$G$9)*365/C$16,((SUMPRODUCT(((DUR-C$16/365)<0)*CASH)+C17-$G$9*(1+C$16*$C$11/365))/$G$9))) -> -0.17269783 | D35: =IF(D17="","",IF($C$32="年化收益率",((SUMPRODUCT(((DUR-D$16/365)<0)*CASH)+D17-$G$9*(1+D$16*$C$11/365))/$G$9)*365/D$16,((SUMPRODUCT(((DUR-D$16/365)<0)*CASH)+D17-$G$9*(1+D$16*$C$11/365))/$G$9))) -> -0.093743646 | E35: =IF(E17="","",IF($C$32="年化收益率",((SUMPRODUCT(((DUR-E$16/365)<0)*CASH)+E17-$G$9*(1+E$16*$C$11/365))/$G$9)*365/E$16,((SUMPRODUCT(((DUR-E$16/365)<0)*CASH)+E17-$G$9*(1+E$16*$C$11/365))/$G$9))) -> -0.086916805 | F35: =IF(F17="","",IF($C$32="年化收益率",((SUMPRODUCT(((DUR-F$16/365)<0)*CASH)+F17-$G$9*(1+F$16*$C$11/365))/$G$9)*365/F$16,((SUMPRODUCT(((DUR-F$16/365)<0)*CASH)+F17-$G$9*(1+F$16*$C$11/365))/$G$9))) -> -0.084463497 | G35: =IF(G17="","",IF($C$32="年化收益率",((SUMPRODUCT(((DUR-G$16/365)<0)*CASH)+G17-$G$9*(1+G$16*$C$11/365))/$G$9)*365/G$16,((SUMPRODUCT(((DUR-G$16/365)<0)*CASH)+G17-$G$9*(1+G$16*$C$11/365))/$G$9))) -> -0.082843569 | H35: =IF(H17="","",IF($C$32="年化收益率",((SUMPRODUCT(((DUR-H$16/365)<0)*CASH)+H17-$G$9*(1+H$16*$C$11/365))/$G$9)*365/H$16,((SUMPRODUCT(((DUR-H$16/365)<0)*CASH)+H17-$G$9*(1+H$16*$C$11/365))/$G$9))) -> -0.081175838 | I35: =IF(I17="","",IF($C$32="年化收益率",((SUMPRODUCT(((DUR-I$16/365)<0)*CASH)+I17-$G$9*(1+I$16*$C$11/365))/$G$9)*365/I$16,((SUMPRODUCT(((DUR-I$16/365)<0)*CASH)+I17-$G$9*(1+I$16*$C$11/365))/$G$9))) -> -0.080670483 | J35: =IF(J17="","",IF($C$32="年化收益率",((SUMPRODUCT(((DUR-J$16/365)<0)*CASH)+J17-$G$9*(1+J$16*$C$11/365))/$G$9)*365/J$16,((SUMPRODUCT(((DUR-J$16/365)<0)*CASH)+J17-$G$9*(1+J$16*$C$11/365))/$G$9))) -> -0.079831514 | ... L35: =IF(L17="","",IF($C$32="年化收益率",((SUMPRODUCT(((DUR-L$16/365)<0)*CASH)+L17-$G$9*(1+L$16*$C$11/365))/$G$9)*365/L$16,((SUMPRODUCT(((DUR-L$16/365)<0)*CASH)+L17-$G$9*(1+L$16*$C$11/365))/$G$9))) -> -0.078144536 | Q35: 1902 | R35: 银行间固定利率企业债收益率曲线(A)
B36: +30bp | C36: =IF(C18="","",IF($C$32="年化收益率",((SUMPRODUCT(((DUR-C$16/365)<0)*CASH)+C18-$G$9*(1+C$16*$C$11/365))/$G$9)*365/C$16,((SUMPRODUCT(((DUR-C$16/365)<0)*CASH)+C18-$G$9*(1+C$16*$C$11/365))/$G$9))) -> 4.9906062 | D36: =IF(D18="","",IF($C$32="年化收益率",((SUMPRODUCT(((DUR-D$16/365)<0)*CASH)+D18-$G$9*(1+D$16*$C$11/365))/$G$9)*365/D$16,((SUMPRODUCT(((DUR-D$16/365)<0)*CASH)+D18-$G$9*(1+D$16*$C$11/365))/$G$9))) -> 0.64239977 | E36: =IF(E18="","",IF($C$32="年化收益率",((SUMPRODUCT(((DUR-E$16/365)<0)*CASH)+E18-$G$9*(1+E$16*$C$11/365))/$G$9)*365/E$16,((SUMPRODUCT(((DUR-E$16/365)<0)*CASH)+E18-$G$9*(1+E$16*$C$11/365))/$G$9))) -> 0.28029987 | F36: =IF(F18="","",IF($C$32="年化收益率",((SUMPRODUCT(((DUR-F$16/365)<0)*CASH)+F18-$G$9*(1+F$16*$C$11/365))/$G$9)*365/F$16,((SUMPRODUCT(((DUR-F$16/365)<0)*CASH)+F18-$G$9*(1+F$16*$C$11/365))/$G$9))) -> 0.15977996 | G36: =IF(G18="","",IF($C$32="年化收益率",((SUMPRODUCT(((DUR-G$16/365)<0)*CASH)+G18-$G$9*(1+G$16*$C$11/365))/$G$9)*365/G$16,((SUMPRODUCT(((DUR-G$16/365)<0)*CASH)+G18-$G$9*(1+G$16*$C$11/365))/$G$9))) -> 0.087619887 | H36: =IF(H18="","",IF($C$32="年化收益率",((SUMPRODUCT(((DUR-H$16/365)<0)*CASH)+H18-$G$9*(1+H$16*$C$11/365))/$G$9)*365/H$16,((SUMPRODUCT(((DUR-H$16/365)<0)*CASH)+H18-$G$9*(1+H$16*$C$11/365))/$G$9))) -> 0.0032174535 | I36: =IF(I18="","",IF($C$32="年化收益率",((SUMPRODUCT(((DUR-I$16/365)<0)*CASH)+I18-$G$9*(1+I$16*$C$11/365))/$G$9)*365/I$16,((SUMPRODUCT(((DUR-I$16/365)<0)*CASH)+I18-$G$9*(1+I$16*$C$11/365))/$G$9))) -> -0.024970196 | J36: =IF(J18="","",IF($C$32="年化收益率",((SUMPRODUCT(((DUR-J$16/365)<0)*CASH)+J18-$G$9*(1+J$16*$C$11/365))/$G$9)*365/J$16,((SUMPRODUCT(((DUR-J$16/365)<0)*CASH)+J18-$G$9*(1+J$16*$C$11/365))/$G$9))) -> -0.047082729 | ... L36: =IF(L18="","",IF($C$32="年化收益率",((SUMPRODUCT(((DUR-L$16/365)<0)*CASH)+L18-$G$9*(1+L$16*$C$11/365))/$G$9)*365/L$16,((SUMPRODUCT(((DUR-L$16/365)<0)*CASH)+L18-$G$9*(1+L$16*$C$11/365))/$G$9))) -> -0.065666264 | Q36: 1852 | R36: 银行间固定利率企业债收益率曲线(A+)
B37: +20bp | C37: =IF(C19="","",IF($C$32="年化收益率",((SUMPRODUCT(((DUR-C$16/365)<0)*CASH)+C19-$G$9*(1+C$16*$C$11/365))/$G$9)*365/C$16,((SUMPRODUCT(((DUR-C$16/365)<0)*CASH)+C19-$G$9*(1+C$16*$C$11/365))/$G$9))) -> 7.605587 | D37: =IF(D19="","",IF($C$32="年化收益率",((SUMPRODUCT(((DUR-D$16/365)<0)*CASH)+D19-$G$9*(1+D$16*$C$11/365))/$G$9)*365/D$16,((SUMPRODUCT(((DUR-D$16/365)<0)*CASH)+D19-$G$9*(1+D$16*$C$11/365))/$G$9))) -> 1.0152149 | E37: =IF(E19="","",IF($C$32="年化收益率",((SUMPRODUCT(((DUR-E$16/365)<0)*CASH)+E19-$G$9*(1+E$16*$C$11/365))/$G$9)*365/E$16,((SUMPRODUCT(((DUR-E$16/365)<0)*CASH)+E19-$G$9*(1+E$16*$C$11/365))/$G$9))) -> 0.46626957 | F37: =IF(F19="","",IF($C$32="年化收益率",((SUMPRODUCT(((DUR-F$16/365)<0)*CASH)+F19-$G$9*(1+F$16*$C$11/365))/$G$9)*365/F$16,((SUMPRODUCT(((DUR-F$16/365)<0)*CASH)+F19-$G$9*(1+F$16*$C$11/365))/$G$9))) -> 0.28346906 | G37: =IF(G19="","",IF($C$32="年化收益率",((SUMPRODUCT(((DUR-G$16/365)<0)*CASH)+G19-$G$9*(1+G$16*$C$11/365))/$G$9)*365/G$16,((SUMPRODUCT(((DUR-G$16/365)<0)*CASH)+G19-$G$9*(1+G$16*$C$11/365))/$G$9))) -> 0.17394264 | H37: =IF(H19="","",IF($C$32="年化收益率",((SUMPRODUCT(((DUR-H$16/365)<0)*CASH)+H19-$G$9*(1+H$16*$C$11/365))/$G$9)*365/H$16,((SUMPRODUCT(((DUR-H$16/365)<0)*CASH)+H19-$G$9*(1+H$16*$C$11/365))/$G$9))) -> 0.045949421 | I37: =IF(I19="","",IF($C$32="年化收益率",((SUMPRODUCT(((DUR-I$16/365)<0)*CASH)+I19-$G$9*(1+I$16*$C$11/365))/$G$9)*365/I$16,((SUMPRODUCT(((DUR-I$16/365)<0)*CASH)+I19-$G$9*(1+I$16*$C$11/365))/$G$9))) -> 0.003230085 | J37: =IF(J19="","",IF($C$32="年化收益率",((SUMPRODUCT(((DUR-J$16/365)<0)*CASH)+J19-$G$9*(1+J$16*$C$11/365))/$G$9)*365/J$16,((SUMPRODUCT(((DUR-J$16/365)<0)*CASH)+J19-$G$9*(1+J$16*$C$11/365))/$G$9))) -> -0.030506198 | ... L37: =IF(L19="","",IF($C$32="年化收益率",((SUMPRODUCT(((DUR-L$16/365)<0)*CASH)+L19-$G$9*(1+L$16*$C$11/365))/$G$9)*365/L$16,((SUMPRODUCT(((DUR-L$16/365)<0)*CASH)+L19-$G$9*(1+L$16*$C$11/365))/$G$9))) -> -0.059355194 | Q37: 1872 | R37: 银行间固定利率企业债收益率曲线(AA(2))
B38: +15bp | C38: =IF(C20="","",IF($C$32="年化收益率",((SUMPRODUCT(((DUR-C$16/365)<0)*CASH)+C20-$G$9*(1+C$16*$C$11/365))/$G$9)*365/C$16,((SUMPRODUCT(((DUR-C$16/365)<0)*CASH)+C20-$G$9*(1+C$16*$C$11/365))/$G$9))) -> 8.9215039 | D38: =IF(D20="","",IF($C$32="年化收益率",((SUMPRODUCT(((DUR-D$16/365)<0)*CASH)+D20-$G$9*(1+D$16*$C$11/365))/$G$9)*365/D$16,((SUMPRODUCT(((DUR-D$16/365)<0)*CASH)+D20-$G$9*(1+D$16*$C$11/365))/$G$9))) -> 1.2028217 | E38: =IF(E20="","",IF($C$32="年化收益率",((SUMPRODUCT(((DUR-E$16/365)<0)*CASH)+E20-$G$9*(1+E$16*$C$11/365))/$G$9)*365/E$16,((SUMPRODUCT(((DUR-E$16/365)<0)*CASH)+E20-$G$9*(1+E$16*$C$11/365))/$G$9))) -> 0.55985143 | F38: =IF(F20="","",IF($C$32="年化收益率",((SUMPRODUCT(((DUR-F$16/365)<0)*CASH)+F20-$G$9*(1+F$16*$C$11/365))/$G$9)*365/F$16,((SUMPRODUCT(((DUR-F$16/365)<0)*CASH)+F20-$G$9*(1+F$16*$C$11/365))/$G$9))) -> 0.34570987 | G38: =IF(G20="","",IF($C$32="年化收益率",((SUMPRODUCT(((DUR-G$16/365)<0)*CASH)+G20-$G$9*(1+G$16*$C$11/365))/$G$9)*365/G$16,((SUMPRODUCT(((DUR-G$16/365)<0)*CASH)+G20-$G$9*(1+G$16*$C$11/365))/$G$9))) -> 0.21737983 | H38: =IF(H20="","",IF($C$32="年化收益率",((SUMPRODUCT(((DUR-H$16/365)<0)*CASH)+H20-$G$9*(1+H$16*$C$11/365))/$G$9)*365/H$16,((SUMPRODUCT(((DUR-H$16/365)<0)*CASH)+H20-$G$9*(1+H$16*$C$11/365))/$G$9))) -> 0.067450726 | I38: =IF(I20="","",IF($C$32="年化收益率",((SUMPRODUCT(((DUR-I$16/365)<0)*CASH)+I20-$G$9*(1+I$16*$C$11/365))/$G$9)*365/I$16,((SUMPRODUCT(((DUR-I$16/365)<0)*CASH)+I20-$G$9*(1+I$16*$C$11/365))/$G$9))) -> 0.017418727 | J38: =IF(J20="","",IF($C$32="年化收益率",((SUMPRODUCT(((DUR-J$16/365)<0)*CASH)+J20-$G$9*(1+J$16*$C$11/365))/$G$9)*365/J$16,((SUMPRODUCT(((DUR-J$16/365)<0)*CASH)+J20-$G$9*(1+J$16*$C$11/365))/$G$9))) -> -0.022166848 | ... L38: =IF(L20="","",IF($C$32="年化收益率",((SUMPRODUCT(((DUR-L$16/365)<0)*CASH)+L20-$G$9*(1+L$16*$C$11/365))/$G$9)*365/L$16,((SUMPRODUCT(((DUR-L$16/365)<0)*CASH)+L20-$G$9*(1+L$16*$C$11/365))/$G$9))) -> -0.056181492 | Q38: 1822 | R38: 银行间固定利率企业债收益率曲线(AA-(2))
B39: +10bp | C39: =IF(C21="","",IF($C$32="年化收益率",((SUMPRODUCT(((DUR-C$16/365)<0)*CASH)+C21-$G$9*(1+C$16*$C$11/365))/$G$9)*365/C$16,((SUMPRODUCT(((DUR-C$16/365)<0)*CASH)+C21-$G$9*(1+C$16*$C$11/365))/$G$9))) -> 10.243075 | D39: =IF(D21="","",IF($C$32="年化收益率",((SUMPRODUCT(((DUR-D$16/365)<0)*CASH)+D21-$G$9*(1+D$16*$C$11/365))/$G$9)*365/D$16,((SUMPRODUCT(((DUR-D$16/365)<0)*CASH)+D21-$G$9*(1+D$16*$C$11/365))/$G$9))) -> 1.3912332 | E39: =IF(E21="","",IF($C$32="年化收益率",((SUMPRODUCT(((DUR-E$16/365)<0)*CASH)+E21-$G$9*(1+E$16*$C$11/365))/$G$9)*365/E$16,((SUMPRODUCT(((DUR-E$16/365)<0)*CASH)+E21-$G$9*(1+E$16*$C$11/365))/$G$9))) -> 0.65383385 | F39: =IF(F21="","",IF($C$32="年化收益率",((SUMPRODUCT(((DUR-F$16/365)<0)*CASH)+F21-$G$9*(1+F$16*$C$11/365))/$G$9)*365/F$16,((SUMPRODUCT(((DUR-F$16/365)<0)*CASH)+F21-$G$9*(1+F$16*$C$11/365))/$G$9))) -> 0.40821656 | G39: =IF(G21="","",IF($C$32="年化收益率",((SUMPRODUCT(((DUR-G$16/365)<0)*CASH)+G21-$G$9*(1+G$16*$C$11/365))/$G$9)*365/G$16,((SUMPRODUCT(((DUR-G$16/365)<0)*CASH)+G21-$G$9*(1+G$16*$C$11/365))/$G$9))) -> 0.26100209 | H39: =IF(H21="","",IF($C$32="年化收益率",((SUMPRODUCT(((DUR-H$16/365)<0)*CASH)+H21-$G$9*(1+H$16*$C$11/365))/$G$9)*365/H$16,((SUMPRODUCT(((DUR-H$16/365)<0)*CASH)+H21-$G$9*(1+H$16*$C$11/365))/$G$9))) -> 0.08904282 | I39: =IF(I21="","",IF($C$32="年化收益率",((SUMPRODUCT(((DUR-I$16/365)<0)*CASH)+I21-$G$9*(1+I$16*$C$11/365))/$G$9)*365/I$16,((SUMPRODUCT(((DUR-I$16/365)<0)*CASH)+I21-$G$9*(1+I$16*$C$11/365))/$G$9))) -> 0.031666743 | J39: =IF(J21="","",IF($C$32="年化收益率",((SUMPRODUCT(((DUR-J$16/365)<0)*CASH)+J21-$G$9*(1+J$16*$C$11/365))/$G$9)*365/J$16,((SUMPRODUCT(((DUR-J$16/365)<0)*CASH)+J21-$G$9*(1+J$16*$C$11/365))/$G$9))) -> -0.013793232 | ... L39: =IF(L21="","",IF($C$32="年化收益率",((SUMPRODUCT(((DUR-L$16/365)<0)*CASH)+L21-$G$9*(1+L$16*$C$11/365))/$G$9)*365/L$16,((SUMPRODUCT(((DUR-L$16/365)<0)*CASH)+L21-$G$9*(1+L$16*$C$11/365))/$G$9))) -> -0.052995608 | Q39: 1252 | R39: 银行间固定利率企业债收益率曲线(AA)
B40: +5bp | C40: =IF(C22="","",IF($C$32="年化收益率",((SUMPRODUCT(((DUR-C$16/365)<0)*CASH)+C22-$G$9*(1+C$16*$C$11/365))/$G$9)*365/C$16,((SUMPRODUCT(((DUR-C$16/365)<0)*CASH)+C22-$G$9*(1+C$16*$C$11/365))/$G$9))) -> 11.570327 | D40: =IF(D22="","",IF($C$32="年化收益率",((SUMPRODUCT(((DUR-D$16/365)<0)*CASH)+D22-$G$9*(1+D$16*$C$11/365))/$G$9)*365/D$16,((SUMPRODUCT(((DUR-D$16/365)<0)*CASH)+D22-$G$9*(1+D$16*$C$11/365))/$G$9))) -> 1.5804533 | E40: =IF(E22="","",IF($C$32="年化收益率",((SUMPRODUCT(((DUR-E$16/365)<0)*CASH)+E22-$G$9*(1+E$16*$C$11/365))/$G$9)*365/E$16,((SUMPRODUCT(((DUR-E$16/365)<0)*CASH)+E22-$G$9*(1+E$16*$C$11/365))/$G$9))) -> 0.74821878 | F40: =IF(F22="","",IF($C$32="年化收益率",((SUMPRODUCT(((DUR-F$16/365)<0)*CASH)+F22-$G$9*(1+F$16*$C$11/365))/$G$9)*365/F$16,((SUMPRODUCT(((DUR-F$16/365)<0)*CASH)+F22-$G$9*(1+F$16*$C$11/365))/$G$9))) -> 0.4709904 | G40: =IF(G22="","",IF($C$32="年化收益率",((SUMPRODUCT(((DUR-G$16/365)<0)*CASH)+G22-$G$9*(1+G$16*$C$11/365))/$G$9)*365/G$16,((SUMPRODUCT(((DUR-G$16/365)<0)*CASH)+G22-$G$9*(1+G$16*$C$11/365))/$G$9))) -> 0.3048103 | H40: =IF(H22="","",IF($C$32="年化收益率",((SUMPRODUCT(((DUR-H$16/365)<0)*CASH)+H22-$G$9*(1+H$16*$C$11/365))/$G$9)*365/H$16,((SUMPRODUCT(((DUR-H$16/365)<0)*CASH)+H22-$G$9*(1+H$16*$C$11/365))/$G$9))) -> 0.11072614 | I40: =IF(I22="","",IF($C$32="年化收益率",((SUMPRODUCT(((DUR-I$16/365)<0)*CASH)+I22-$G$9*(1+I$16*$C$11/365))/$G$9)*365/I$16,((SUMPRODUCT(((DUR-I$16/365)<0)*CASH)+I22-$G$9*(1+I$16*$C$11/365))/$G$9))) -> 0.045974414 | J40: =IF(J22="","",IF($C$32="年化收益率",((SUMPRODUCT(((DUR-J$16/365)<0)*CASH)+J22-$G$9*(1+J$16*$C$11/365))/$G$9)*365/J$16,((SUMPRODUCT(((DUR-J$16/365)<0)*CASH)+J22-$G$9*(1+J$16*$C$11/365))/$G$9))) -> -0.0053851879 | ... L40: =IF(L22="","",IF($C$32="年化收益率",((SUMPRODUCT(((DUR-L$16/365)<0)*CASH)+L22-$G$9*(1+L$16*$C$11/365))/$G$9)*365/L$16,((SUMPRODUCT(((DUR-L$16/365)<0)*CASH)+L22-$G$9*(1+L$16*$C$11/365))/$G$9))) -> -0.049797488 | Q40: 1482 | R40: 银行间固定利率企业债收益率曲线(AA-)
B41: 0bp | C41: =IF(C23="","",IF($C$32="年化收益率",((SUMPRODUCT(((DUR-C$16/365)<0)*CASH)+C23-$G$9*(1+C$16*$C$11/365))/$G$9)*365/C$16,((SUMPRODUCT(((DUR-C$16/365)<0)*CASH)+C23-$G$9*(1+C$16*$C$11/365))/$G$9))) -> 12.903289 | D41: =IF(D23="","",IF($C$32="年化收益率",((SUMPRODUCT(((DUR-D$16/365)<0)*CASH)+D23-$G$9*(1+D$16*$C$11/365))/$G$9)*365/D$16,((SUMPRODUCT(((DUR-D$16/365)<0)*CASH)+D23-$G$9*(1+D$16*$C$11/365))/$G$9))) -> 1.7704859 | E41: =IF(E23="","",IF($C$32="年化收益率",((SUMPRODUCT(((DUR-E$16/365)<0)*CASH)+E23-$G$9*(1+E$16*$C$11/365))/$G$9)*365/E$16,((SUMPRODUCT(((DUR-E$16/365)<0)*CASH)+E23-$G$9*(1+E$16*$C$11/365))/$G$9))) -> 0.84300815 | F41: =IF(F23="","",IF($C$32="年化收益率",((SUMPRODUCT(((DUR-F$16/365)<0)*CASH)+F23-$G$9*(1+F$16*$C$11/365))/$G$9)*365/F$16,((SUMPRODUCT(((DUR-F$16/365)<0)*CASH)+F23-$G$9*(1+F$16*$C$11/365))/$G$9))) -> 0.53403268 | G41: =IF(G23="","",IF($C$32="年化收益率",((SUMPRODUCT(((DUR-G$16/365)<0)*CASH)+G23-$G$9*(1+G$16*$C$11/365))/$G$9)*365/G$16,((SUMPRODUCT(((DUR-G$16/365)<0)*CASH)+G23-$G$9*(1+G$16*$C$11/365))/$G$9))) -> 0.34880535 | H41: =IF(H23="","",IF($C$32="年化收益率",((SUMPRODUCT(((DUR-H$16/365)<0)*CASH)+H23-$G$9*(1+H$16*$C$11/365))/$G$9)*365/H$16,((SUMPRODUCT(((DUR-H$16/365)<0)*CASH)+H23-$G$9*(1+H$16*$C$11/365))/$G$9))) -> 0.13250111 | I41: =IF(I23="","",IF($C$32="年化收益率",((SUMPRODUCT(((DUR-I$16/365)<0)*CASH)+I23-$G$9*(1+I$16*$C$11/365))/$G$9)*365/I$16,((SUMPRODUCT(((DUR-I$16/365)<0)*CASH)+I23-$G$9*(1+I$16*$C$11/365))/$G$9))) -> 0.060342022 | J41: =IF(J23="","",IF($C$32="年化收益率",((SUMPRODUCT(((DUR-J$16/365)<0)*CASH)+J23-$G$9*(1+J$16*$C$11/365))/$G$9)*365/J$16,((SUMPRODUCT(((DUR-J$16/365)<0)*CASH)+J23-$G$9*(1+J$16*$C$11/365))/$G$9))) -> 0.0030574431 | ... L41: =IF(L23="","",IF($C$32="年化收益率",((SUMPRODUCT(((DUR-L$16/365)<0)*CASH)+L23-$G$9*(1+L$16*$C$11/365))/$G$9)*365/L$16,((SUMPRODUCT(((DUR-L$16/365)<0)*CASH)+L23-$G$9*(1+L$16*$C$11/365))/$G$9))) -> -0.04658708 | Q41: 1832 | R41: 银行间固定利率企业债收益率曲线(AA+(2))
B42: -5bp | C42: =IF(C24="","",IF($C$32="年化收益率",((SUMPRODUCT(((DUR-C$16/365)<0)*CASH)+C24-$G$9*(1+C$16*$C$11/365))/$G$9)*365/C$16,((SUMPRODUCT(((DUR-C$16/365)<0)*CASH)+C24-$G$9*(1+C$16*$C$11/365))/$G$9))) -> 14.241987 | D42: =IF(D24="","",IF($C$32="年化收益率",((SUMPRODUCT(((DUR-D$16/365)<0)*CASH)+D24-$G$9*(1+D$16*$C$11/365))/$G$9)*365/D$16,((SUMPRODUCT(((DUR-D$16/365)<0)*CASH)+D24-$G$9*(1+D$16*$C$11/365))/$G$9))) -> 1.9613349 | E42: =IF(E24="","",IF($C$32="年化收益率",((SUMPRODUCT(((DUR-E$16/365)<0)*CASH)+E24-$G$9*(1+E$16*$C$11/365))/$G$9)*365/E$16,((SUMPRODUCT(((DUR-E$16/365)<0)*CASH)+E24-$G$9*(1+E$16*$C$11/365))/$G$9))) -> 0.93820394 | F42: =IF(F24="","",IF($C$32="年化收益率",((SUMPRODUCT(((DUR-F$16/365)<0)*CASH)+F24-$G$9*(1+F$16*$C$11/365))/$G$9)*365/F$16,((SUMPRODUCT(((DUR-F$16/365)<0)*CASH)+F24-$G$9*(1+F$16*$C$11/365))/$G$9))) -> 0.5973447 | G42: =IF(G24="","",IF($C$32="年化收益率",((SUMPRODUCT(((DUR-G$16/365)<0)*CASH)+G24-$G$9*(1+G$16*$C$11/365))/$G$9)*365/G$16,((SUMPRODUCT(((DUR-G$16/365)<0)*CASH)+G24-$G$9*(1+G$16*$C$11/365))/$G$9))) -> 0.39298815 | H42: =IF(H24="","",IF($C$32="年化收益率",((SUMPRODUCT(((DUR-H$16/365)<0)*CASH)+H24-$G$9*(1+H$16*$C$11/365))/$G$9)*365/H$16,((SUMPRODUCT(((DUR-H$16/365)<0)*CASH)+H24-$G$9*(1+H$16*$C$11/365))/$G$9))) -> 0.15436818 | I42: =IF(I24="","",IF($C$32="年化收益率",((SUMPRODUCT(((DUR-I$16/365)<0)*CASH)+I24-$G$9*(1+I$16*$C$11/365))/$G$9)*365/I$16,((SUMPRODUCT(((DUR-I$16/365)<0)*CASH)+I24-$G$9*(1+I$16*$C$11/365))/$G$9))) -> 0.074769851 | J42: =IF(J24="","",IF($C$32="年化收益率",((SUMPRODUCT(((DUR-J$16/365)<0)*CASH)+J24-$G$9*(1+J$16*$C$11/365))/$G$9)*365/J$16,((SUMPRODUCT(((DUR-J$16/365)<0)*CASH)+J24-$G$9*(1+J$16*$C$11/365))/$G$9))) -> 0.011534823 | ... L42: =IF(L24="","",IF($C$32="年化收益率",((SUMPRODUCT(((DUR-L$16/365)<0)*CASH)+L24-$G$9*(1+L$16*$C$11/365))/$G$9)*365/L$16,((SUMPRODUCT(((DUR-L$16/365)<0)*CASH)+L24-$G$9*(1+L$16*$C$11/365))/$G$9))) -> -0.043364328 | Q42: 1442 | R42: 银行间固定利率企业债收益率曲线(AA+)
B43: -10bp | C43: =IF(C25="","",IF($C$32="年化收益率",((SUMPRODUCT(((DUR-C$16/365)<0)*CASH)+C25-$G$9*(1+C$16*$C$11/365))/$G$9)*365/C$16,((SUMPRODUCT(((DUR-C$16/365)<0)*CASH)+C25-$G$9*(1+C$16*$C$11/365))/$G$9))) -> 15.586449 | D43: =IF(D25="","",IF($C$32="年化收益率",((SUMPRODUCT(((DUR-D$16/365)<0)*CASH)+D25-$G$9*(1+D$16*$C$11/365))/$G$9)*365/D$16,((SUMPRODUCT(((DUR-D$16/365)<0)*CASH)+D25-$G$9*(1+D$16*$C$11/365))/$G$9))) -> 2.1530042 | E43: =IF(E25="","",IF($C$32="年化收益率",((SUMPRODUCT(((DUR-E$16/365)<0)*CASH)+E25-$G$9*(1+E$16*$C$11/365))/$G$9)*365/E$16,((SUMPRODUCT(((DUR-E$16/365)<0)*CASH)+E25-$G$9*(1+E$16*$C$11/365))/$G$9))) -> 1.0338081 | F43: =IF(F25="","",IF($C$32="年化收益率",((SUMPRODUCT(((DUR-F$16/365)<0)*CASH)+F25-$G$9*(1+F$16*$C$11/365))/$G$9)*365/F$16,((SUMPRODUCT(((DUR-F$16/365)<0)*CASH)+F25-$G$9*(1+F$16*$C$11/365))/$G$9))) -> 0.66092777 | G43: =IF(G25="","",IF($C$32="年化收益率",((SUMPRODUCT(((DUR-G$16/365)<0)*CASH)+G25-$G$9*(1+G$16*$C$11/365))/$G$9)*365/G$16,((SUMPRODUCT(((DUR-G$16/365)<0)*CASH)+G25-$G$9*(1+G$16*$C$11/365))/$G$9))) -> 0.4373596 | H43: =IF(H25="","",IF($C$32="年化收益率",((SUMPRODUCT(((DUR-H$16/365)<0)*CASH)+H25-$G$9*(1+H$16*$C$11/365))/$G$9)*365/H$16,((SUMPRODUCT(((DUR-H$16/365)<0)*CASH)+H25-$G$9*(1+H$16*$C$11/365))/$G$9))) -> 0.17632778 | I43: =IF(I25="","",IF($C$32="年化收益率",((SUMPRODUCT(((DUR-I$16/365)<0)*CASH)+I25-$G$9*(1+I$16*$C$11/365))/$G$9)*365/I$16,((SUMPRODUCT(((DUR-I$16/365)<0)*CASH)+I25-$G$9*(1+I$16*$C$11/365))/$G$9))) -> 0.089258188 | J43: =IF(J25="","",IF($C$32="年化收益率",((SUMPRODUCT(((DUR-J$16/365)<0)*CASH)+J25-$G$9*(1+J$16*$C$11/365))/$G$9)*365/J$16,((SUMPRODUCT(((DUR-J$16/365)<0)*CASH)+J25-$G$9*(1+J$16*$C$11/365))/$G$9))) -> 0.020047113 | ... L43: =IF(L25="","",IF($C$32="年化收益率",((SUMPRODUCT(((DUR-L$16/365)<0)*CASH)+L25-$G$9*(1+L$16*$C$11/365))/$G$9)*365/L$16,((SUMPRODUCT(((DUR-L$16/365)<0)*CASH)+L25-$G$9*(1+L$16*$C$11/365))/$G$9))) -> -0.04012918 | Q43: 1842 | R43: 银行间固定利率企业债收益率曲线(AAA(2))
B44: -15bp | C44: =IF(C26="","",IF($C$32="年化收益率",((SUMPRODUCT(((DUR-C$16/365)<0)*CASH)+C26-$G$9*(1+C$16*$C$11/365))/$G$9)*365/C$16,((SUMPRODUCT(((DUR-C$16/365)<0)*CASH)+C26-$G$9*(1+C$16*$C$11/365))/$G$9))) -> 16.936705 | D44: =IF(D26="","",IF($C$32="年化收益率",((SUMPRODUCT(((DUR-D$16/365)<0)*CASH)+D26-$G$9*(1+D$16*$C$11/365))/$G$9)*365/D$16,((SUMPRODUCT(((DUR-D$16/365)<0)*CASH)+D26-$G$9*(1+D$16*$C$11/365))/$G$9))) -> 2.345498 | E44: =IF(E26="","",IF($C$32="年化收益率",((SUMPRODUCT(((DUR-E$16/365)<0)*CASH)+E26-$G$9*(1+E$16*$C$11/365))/$G$9)*365/E$16,((SUMPRODUCT(((DUR-E$16/365)<0)*CASH)+E26-$G$9*(1+E$16*$C$11/365))/$G$9))) -> 1.1298226 | F44: =IF(F26="","",IF($C$32="年化收益率",((SUMPRODUCT(((DUR-F$16/365)<0)*CASH)+F26-$G$9*(1+F$16*$C$11/365))/$G$9)*365/F$16,((SUMPRODUCT(((DUR-F$16/365)<0)*CASH)+F26-$G$9*(1+F$16*$C$11/365))/$G$9))) -> 0.72478319 | G44: =IF(G26="","",IF($C$32="年化收益率",((SUMPRODUCT(((DUR-G$16/365)<0)*CASH)+G26-$G$9*(1+G$16*$C$11/365))/$G$9)*365/G$16,((SUMPRODUCT(((DUR-G$16/365)<0)*CASH)+G26-$G$9*(1+G$16*$C$11/365))/$G$9))) -> 0.48192061 | H44: =IF(H26="","",IF($C$32="年化收益率",((SUMPRODUCT(((DUR-H$16/365)<0)*CASH)+H26-$G$9*(1+H$16*$C$11/365))/$G$9)*365/H$16,((SUMPRODUCT(((DUR-H$16/365)<0)*CASH)+H26-$G$9*(1+H$16*$C$11/365))/$G$9))) -> 0.19838037 | I44: =IF(I26="","",IF($C$32="年化收益率",((SUMPRODUCT(((DUR-I$16/365)<0)*CASH)+I26-$G$9*(1+I$16*$C$11/365))/$G$9)*365/I$16,((SUMPRODUCT(((DUR-I$16/365)<0)*CASH)+I26-$G$9*(1+I$16*$C$11/365))/$G$9))) -> 0.10380732 | J44: =IF(J26="","",IF($C$32="年化收益率",((SUMPRODUCT(((DUR-J$16/365)<0)*CASH)+J26-$G$9*(1+J$16*$C$11/365))/$G$9)*365/J$16,((SUMPRODUCT(((DUR-J$16/365)<0)*CASH)+J26-$G$9*(1+J$16*$C$11/365))/$G$9))) -> 0.028594477 | ... L44: =IF(L26="","",IF($C$32="年化收益率",((SUMPRODUCT(((DUR-L$16/365)<0)*CASH)+L26-$G$9*(1+L$16*$C$11/365))/$G$9)*365/L$16,((SUMPRODUCT(((DUR-L$16/365)<0)*CASH)+L26-$G$9*(1+L$16*$C$11/365))/$G$9))) -> -0.03688158 | Q44: 1262 | R44: 银行间固定利率企业债收益率曲线(AAA)
B45: -20bp | C45: =IF(C27="","",IF($C$32="年化收益率",((SUMPRODUCT(((DUR-C$16/365)<0)*CASH)+C27-$G$9*(1+C$16*$C$11/365))/$G$9)*365/C$16,((SUMPRODUCT(((DUR-C$16/365)<0)*CASH)+C27-$G$9*(1+C$16*$C$11/365))/$G$9))) -> 18.292781 | D45: =IF(D27="","",IF($C$32="年化收益率",((SUMPRODUCT(((DUR-D$16/365)<0)*CASH)+D27-$G$9*(1+D$16*$C$11/365))/$G$9)*365/D$16,((SUMPRODUCT(((DUR-D$16/365)<0)*CASH)+D27-$G$9*(1+D$16*$C$11/365))/$G$9))) -> 2.5388201 | E45: =IF(E27="","",IF($C$32="年化收益率",((SUMPRODUCT(((DUR-E$16/365)<0)*CASH)+E27-$G$9*(1+E$16*$C$11/365))/$G$9)*365/E$16,((SUMPRODUCT(((DUR-E$16/365)<0)*CASH)+E27-$G$9*(1+E$16*$C$11/365))/$G$9))) -> 1.2262495 | F45: =IF(F27="","",IF($C$32="年化收益率",((SUMPRODUCT(((DUR-F$16/365)<0)*CASH)+F27-$G$9*(1+F$16*$C$11/365))/$G$9)*365/F$16,((SUMPRODUCT(((DUR-F$16/365)<0)*CASH)+F27-$G$9*(1+F$16*$C$11/365))/$G$9))) -> 0.78891228 | G45: =IF(G27="","",IF($C$32="年化收益率",((SUMPRODUCT(((DUR-G$16/365)<0)*CASH)+G27-$G$9*(1+G$16*$C$11/365))/$G$9)*365/G$16,((SUMPRODUCT(((DUR-G$16/365)<0)*CASH)+G27-$G$9*(1+G$16*$C$11/365))/$G$9))) -> 0.5266721 | H45: =IF(H27="","",IF($C$32="年化收益率",((SUMPRODUCT(((DUR-H$16/365)<0)*CASH)+H27-$G$9*(1+H$16*$C$11/365))/$G$9)*365/H$16,((SUMPRODUCT(((DUR-H$16/365)<0)*CASH)+H27-$G$9*(1+H$16*$C$11/365))/$G$9))) -> 0.22052638 | I45: =IF(I27="","",IF($C$32="年化收益率",((SUMPRODUCT(((DUR-I$16/365)<0)*CASH)+I27-$G$9*(1+I$16*$C$11/365))/$G$9)*365/I$16,((SUMPRODUCT(((DUR-I$16/365)<0)*CASH)+I27-$G$9*(1+I$16*$C$11/365))/$G$9))) -> 0.11841753 | J45: =IF(J27="","",IF($C$32="年化收益率",((SUMPRODUCT(((DUR-J$16/365)<0)*CASH)+J27-$G$9*(1+J$16*$C$11/365))/$G$9)*365/J$16,((SUMPRODUCT(((DUR-J$16/365)<0)*CASH)+J27-$G$9*(1+J$16*$C$11/365))/$G$9))) -> 0.037177078 | ... L45: =IF(L27="","",IF($C$32="年化收益率",((SUMPRODUCT(((DUR-L$16/365)<0)*CASH)+L27-$G$9*(1+L$16*$C$11/365))/$G$9)*365/L$16,((SUMPRODUCT(((DUR-L$16/365)<0)*CASH)+L27-$G$9*(1+L$16*$C$11/365))/$G$9))) -> -0.033621474 | Q45: 1912 | R45: 银行间固定利率企业债收益率曲线(BBB+)
B46: -30bp | C46: =IF(C28="","",IF($C$32="年化收益率",((SUMPRODUCT(((DUR-C$16/365)<0)*CASH)+C28-$G$9*(1+C$16*$C$11/365))/$G$9)*365/C$16,((SUMPRODUCT(((DUR-C$16/365)<0)*CASH)+C28-$G$9*(1+C$16*$C$11/365))/$G$9))) -> 21.022509 | D46: =IF(D28="","",IF($C$32="年化收益率",((SUMPRODUCT(((DUR-D$16/365)<0)*CASH)+D28-$G$9*(1+D$16*$C$11/365))/$G$9)*365/D$16,((SUMPRODUCT(((DUR-D$16/365)<0)*CASH)+D28-$G$9*(1+D$16*$C$11/365))/$G$9))) -> 2.9279655 | E46: =IF(E28="","",IF($C$32="年化收益率",((SUMPRODUCT(((DUR-E$16/365)<0)*CASH)+E28-$G$9*(1+E$16*$C$11/365))/$G$9)*365/E$16,((SUMPRODUCT(((DUR-E$16/365)<0)*CASH)+E28-$G$9*(1+E$16*$C$11/365))/$G$9))) -> 1.4203482 | F46: =IF(F28="","",IF($C$32="年化收益率",((SUMPRODUCT(((DUR-F$16/365)<0)*CASH)+F28-$G$9*(1+F$16*$C$11/365))/$G$9)*365/F$16,((SUMPRODUCT(((DUR-F$16/365)<0)*CASH)+F28-$G$9*(1+F$16*$C$11/365))/$G$9))) -> 0.9179968 | G46: =IF(G28="","",IF($C$32="年化收益率",((SUMPRODUCT(((DUR-G$16/365)<0)*CASH)+G28-$G$9*(1+G$16*$C$11/365))/$G$9)*365/G$16,((SUMPRODUCT(((DUR-G$16/365)<0)*CASH)+G28-$G$9*(1+G$16*$C$11/365))/$G$9))) -> 0.61675019 | H46: =IF(H28="","",IF($C$32="年化收益率",((SUMPRODUCT(((DUR-H$16/365)<0)*CASH)+H28-$G$9*(1+H$16*$C$11/365))/$G$9)*365/H$16,((SUMPRODUCT(((DUR-H$16/365)<0)*CASH)+H28-$G$9*(1+H$16*$C$11/365))/$G$9))) -> 0.26510046 | I46: =IF(I28="","",IF($C$32="年化收益率",((SUMPRODUCT(((DUR-I$16/365)<0)*CASH)+I28-$G$9*(1+I$16*$C$11/365))/$G$9)*365/I$16,((SUMPRODUCT(((DUR-I$16/365)<0)*CASH)+I28-$G$9*(1+I$16*$C$11/365))/$G$9))) -> 0.14782237 | J46: =IF(J28="","",IF($C$32="年化收益率",((SUMPRODUCT(((DUR-J$16/365)<0)*CASH)+J28-$G$9*(1+J$16*$C$11/365))/$G$9)*365/J$16,((SUMPRODUCT(((DUR-J$16/365)<0)*CASH)+J28-$G$9*(1+J$16*$C$11/365))/$G$9))) -> 0.054448651 | ... L46: =IF(L28="","",IF($C$32="年化收益率",((SUMPRODUCT(((DUR-L$16/365)<0)*CASH)+L28-$G$9*(1+L$16*$C$11/365))/$G$9)*365/L$16,((SUMPRODUCT(((DUR-L$16/365)<0)*CASH)+L28-$G$9*(1+L$16*$C$11/365))/$G$9))) -> -0.027063525 | Q46: 1492 | R46: 银行间固定利率商业银行债收益率曲线(A)
B47: -50bp | C47: =IF(C29="","",IF($C$32="年化收益率",((SUMPRODUCT(((DUR-C$16/365)<0)*CASH)+C29-$G$9*(1+C$16*$C$11/365))/$G$9)*365/C$16,((SUMPRODUCT(((DUR-C$16/365)<0)*CASH)+C29-$G$9*(1+C$16*$C$11/365))/$G$9))) -> 26.553072 | D47: =IF(D29="","",IF($C$32="年化收益率",((SUMPRODUCT(((DUR-D$16/365)<0)*CASH)+D29-$G$9*(1+D$16*$C$11/365))/$G$9)*365/D$16,((SUMPRODUCT(((DUR-D$16/365)<0)*CASH)+D29-$G$9*(1+D$16*$C$11/365))/$G$9))) -> 3.7163754 | E47: =IF(E29="","",IF($C$32="年化收益率",((SUMPRODUCT(((DUR-E$16/365)<0)*CASH)+E29-$G$9*(1+E$16*$C$11/365))/$G$9)*365/E$16,((SUMPRODUCT(((DUR-E$16/365)<0)*CASH)+E29-$G$9*(1+E$16*$C$11/365))/$G$9))) -> 1.8135825 | F47: =IF(F29="","",IF($C$32="年化收益率",((SUMPRODUCT(((DUR-F$16/365)<0)*CASH)+F29-$G$9*(1+F$16*$C$11/365))/$G$9)*365/F$16,((SUMPRODUCT(((DUR-F$16/365)<0)*CASH)+F29-$G$9*(1+F$16*$C$11/365))/$G$9))) -> 1.1795086 | G47: =IF(G29="","",IF($C$32="年化收益率",((SUMPRODUCT(((DUR-G$16/365)<0)*CASH)+G29-$G$9*(1+G$16*$C$11/365))/$G$9)*365/G$16,((SUMPRODUCT(((DUR-G$16/365)<0)*CASH)+G29-$G$9*(1+G$16*$C$11/365))/$G$9))) -> 0.79923289 | H47: =IF(H29="","",IF($C$32="年化收益率",((SUMPRODUCT(((DUR-H$16/365)<0)*CASH)+H29-$G$9*(1+H$16*$C$11/365))/$G$9)*365/H$16,((SUMPRODUCT(((DUR-H$16/365)<0)*CASH)+H29-$G$9*(1+H$16*$C$11/365))/$G$9))) -> 0.35538956 | I47: =IF(I29="","",IF($C$32="年化收益率",((SUMPRODUCT(((DUR-I$16/365)<0)*CASH)+I29-$G$9*(1+I$16*$C$11/365))/$G$9)*365/I$16,((SUMPRODUCT(((DUR-I$16/365)<0)*CASH)+I29-$G$9*(1+I$16*$C$11/365))/$G$9))) -> 0.20737791 | J47: =IF(J29="","",IF($C$32="年化收益率",((SUMPRODUCT(((DUR-J$16/365)<0)*CASH)+J29-$G$9*(1+J$16*$C$11/365))/$G$9)*365/J$16,((SUMPRODUCT(((DUR-J$16/365)<0)*CASH)+J29-$G$9*(1+J$16*$C$11/365))/$G$9))) -> 0.089421947 | ... L47: =IF(L29="","",IF($C$32="年化收益率",((SUMPRODUCT(((DUR-L$16/365)<0)*CASH)+L29-$G$9*(1+L$16*$C$11/365))/$G$9)*365/L$16,((SUMPRODUCT(((DUR-L$16/365)<0)*CASH)+L29-$G$9*(1+L$16*$C$11/365))/$G$9))) -> -0.01379512 | Q47: 1272 | R47: 银行间固定利率商业银行债收益率曲线(A-)
B48: =B30&"bp" -> 10bp | C48: =IF(C30="","",IF($C$32="年化收益率",((SUMPRODUCT(((DUR-C$16/365)<0)*CASH)+C30-$G$9*(1+C$16*$C$11/365))/$G$9)*365/C$16,((SUMPRODUCT(((DUR-C$16/365)<0)*CASH)+C30-$G$9*(1+C$16*$C$11/365))/$G$9))) -> 10.243075 | D48: =IF(D30="","",IF($C$32="年化收益率",((SUMPRODUCT(((DUR-D$16/365)<0)*CASH)+D30-$G$9*(1+D$16*$C$11/365))/$G$9)*365/D$16,((SUMPRODUCT(((DUR-D$16/365)<0)*CASH)+D30-$G$9*(1+D$16*$C$11/365))/$G$9))) -> 1.3912332 | E48: =IF(E30="","",IF($C$32="年化收益率",((SUMPRODUCT(((DUR-E$16/365)<0)*CASH)+E30-$G$9*(1+E$16*$C$11/365))/$G$9)*365/E$16,((SUMPRODUCT(((DUR-E$16/365)<0)*CASH)+E30-$G$9*(1+E$16*$C$11/365))/$G$9))) -> 0.65383385 | F48: =IF(F30="","",IF($C$32="年化收益率",((SUMPRODUCT(((DUR-F$16/365)<0)*CASH)+F30-$G$9*(1+F$16*$C$11/365))/$G$9)*365/F$16,((SUMPRODUCT(((DUR-F$16/365)<0)*CASH)+F30-$G$9*(1+F$16*$C$11/365))/$G$9))) -> 0.40821656 | G48: =IF(G30="","",IF($C$32="年化收益率",((SUMPRODUCT(((DUR-G$16/365)<0)*CASH)+G30-$G$9*(1+G$16*$C$11/365))/$G$9)*365/G$16,((SUMPRODUCT(((DUR-G$16/365)<0)*CASH)+G30-$G$9*(1+G$16*$C$11/365))/$G$9))) -> 0.26100209 | H48: =IF(H30="","",IF($C$32="年化收益率",((SUMPRODUCT(((DUR-H$16/365)<0)*CASH)+H30-$G$9*(1+H$16*$C$11/365))/$G$9)*365/H$16,((SUMPRODUCT(((DUR-H$16/365)<0)*CASH)+H30-$G$9*(1+H$16*$C$11/365))/$G$9))) -> 0.08904282 | I48: =IF(I30="","",IF($C$32="年化收益率",((SUMPRODUCT(((DUR-I$16/365)<0)*CASH)+I30-$G$9*(1+I$16*$C$11/365))/$G$9)*365/I$16,((SUMPRODUCT(((DUR-I$16/365)<0)*CASH)+I30-$G$9*(1+I$16*$C$11/365))/$G$9))) -> 0.031666743 | J48: =IF(J30="","",IF($C$32="年化收益率",((SUMPRODUCT(((DUR-J$16/365)<0)*CASH)+J30-$G$9*(1+J$16*$C$11/365))/$G$9)*365/J$16,((SUMPRODUCT(((DUR-J$16/365)<0)*CASH)+J30-$G$9*(1+J$16*$C$11/365))/$G$9))) -> -0.013793232 | ... L48: =IF(L30="","",IF($C$32="年化收益率",((SUMPRODUCT(((DUR-L$16/365)<0)*CASH)+L30-$G$9*(1+L$16*$C$11/365))/$G$9)*365/L$16,((SUMPRODUCT(((DUR-L$16/365)<0)*CASH)+L30-$G$9*(1+L$16*$C$11/365))/$G$9))) -> -0.052995608 | Q48: 1452 | R48: 银行间固定利率商业银行债收益率曲线(A+)
Q49: 1282 | R49: 银行间固定利率商业银行债收益率曲线(AA)
B50: 期末净现金流（万元） | Q50: 1302 | R50: 银行间固定利率商业银行债收益率曲线(AA-)
C51: 1d | D51: 7d | E51: 2W | F51: 3W | G51: 1M | H51: 2M | I51: 3M | J51: 5M | K51: 1Y | L51: =L34 -> 365d | Q51: 1292 | R51: 银行间固定利率商业银行债收益率曲线(AA+)
B52: +50bp | C52: =IF(C17="","",(SUMPRODUCT(((DUR-C$16/365)<0)*CASH)+C17-$G$9*(1+C$16*$C$11/365))*$I$9) -> -24.216453 | D52: =IF(D17="","",(SUMPRODUCT(((DUR-D$16/365)<0)*CASH)+D17-$G$9*(1+D$16*$C$11/365))*$I$9) -> -92.016039 | E52: =IF(E17="","",(SUMPRODUCT(((DUR-E$16/365)<0)*CASH)+E17-$G$9*(1+E$16*$C$11/365))*$I$9) -> -170.63002 | F52: =IF(F17="","",(SUMPRODUCT(((DUR-F$16/365)<0)*CASH)+F17-$G$9*(1+F$16*$C$11/365))*$I$9) -> -248.72074 | G52: =IF(G17="","",(SUMPRODUCT(((DUR-G$16/365)<0)*CASH)+G17-$G$9*(1+G$16*$C$11/365))*$I$9) -> -348.50074 | H52: =IF(H17="","",(SUMPRODUCT(((DUR-H$16/365)<0)*CASH)+H17-$G$9*(1+H$16*$C$11/365))*$I$9) -> -682.97009 | I52: =IF(I17="","",(SUMPRODUCT(((DUR-I$16/365)<0)*CASH)+I17-$G$9*(1+I$16*$C$11/365))*$I$9) -> -1018.0774 | J52: =IF(J17="","",(SUMPRODUCT(((DUR-J$16/365)<0)*CASH)+J17-$G$9*(1+J$16*$C$11/365))*$I$9) -> -1679.1492 | ... L52: =IF(L17="","",(SUMPRODUCT(((DUR-L$16/365)<0)*CASH)+L17-$G$9*(1+L$16*$C$11/365))*$I$9) -> -3999.5869 | Q52: 1312 | R52: 银行间固定利率商业银行债收益率曲线(AAA)
B53: +30bp | C53: =IF(C18="","",(SUMPRODUCT(((DUR-C$16/365)<0)*CASH)+C18-$G$9*(1+C$16*$C$11/365))*$I$9) -> 699.80486 | D53: =IF(D18="","",(SUMPRODUCT(((DUR-D$16/365)<0)*CASH)+D18-$G$9*(1+D$16*$C$11/365))*$I$9) -> 630.56094 | E53: =IF(E18="","",(SUMPRODUCT(((DUR-E$16/365)<0)*CASH)+E18-$G$9*(1+E$16*$C$11/365))*$I$9) -> 550.26841 | F53: =IF(F18="","",(SUMPRODUCT(((DUR-F$16/365)<0)*CASH)+F18-$G$9*(1+F$16*$C$11/365))*$I$9) -> 470.50608 | G53: =IF(G18="","",(SUMPRODUCT(((DUR-G$16/365)<0)*CASH)+G18-$G$9*(1+G$16*$C$11/365))*$I$9) -> 368.59343 | H53: =IF(H18="","",(SUMPRODUCT(((DUR-H$16/365)<0)*CASH)+H18-$G$9*(1+H$16*$C$11/365))*$I$9) -> 27.069933 | I53: =IF(I18="","",(SUMPRODUCT(((DUR-I$16/365)<0)*CASH)+I18-$G$9*(1+I$16*$C$11/365))*$I$9) -> -315.12881 | J53: =IF(J18="","",(SUMPRODUCT(((DUR-J$16/365)<0)*CASH)+J18-$G$9*(1+J$16*$C$11/365))*$I$9) -> -990.32225 | ... L53: =IF(L18="","",(SUMPRODUCT(((DUR-L$16/365)<0)*CASH)+L18-$G$9*(1+L$16*$C$11/365))*$I$9) -> -3360.925 | Q53: 1322 | R53: 银行间固定利率政策性金融债收益率曲线
B54: +20bp | C54: =IF(C19="","",(SUMPRODUCT(((DUR-C$16/365)<0)*CASH)+C19-$G$9*(1+C$16*$C$11/365))*$I$9) -> 1066.489 | D54: =IF(D19="","",(SUMPRODUCT(((DUR-D$16/365)<0)*CASH)+D19-$G$9*(1+D$16*$C$11/365))*$I$9) -> 996.50545 | E54: =IF(E19="","",(SUMPRODUCT(((DUR-E$16/365)<0)*CASH)+E19-$G$9*(1+E$16*$C$11/365))*$I$9) -> 915.35332 | F54: =IF(F19="","",(SUMPRODUCT(((DUR-F$16/365)<0)*CASH)+F19-$G$9*(1+F$16*$C$11/365))*$I$9) -> 834.73498 | G54: =IF(G19="","",(SUMPRODUCT(((DUR-G$16/365)<0)*CASH)+G19-$G$9*(1+G$16*$C$11/365))*$I$9) -> 731.73016 | H54: =IF(H19="","",(SUMPRODUCT(((DUR-H$16/365)<0)*CASH)+H19-$G$9*(1+H$16*$C$11/365))*$I$9) -> 386.59385 | I54: =IF(I19="","",(SUMPRODUCT(((DUR-I$16/365)<0)*CASH)+I19-$G$9*(1+I$16*$C$11/365))*$I$9) -> 40.764311 | J54: =IF(J19="","",(SUMPRODUCT(((DUR-J$16/365)<0)*CASH)+J19-$G$9*(1+J$16*$C$11/365))*$I$9) -> -641.65708 | ... L54: =IF(L19="","",(SUMPRODUCT(((DUR-L$16/365)<0)*CASH)+L19-$G$9*(1+L$16*$C$11/365))*$I$9) -> -3037.9124 | Q54: 1892 | R54: 银行间固定利率资产支持证券收益率曲线(A)
B55: +15bp | C55: =IF(C20="","",(SUMPRODUCT(((DUR-C$16/365)<0)*CASH)+C20-$G$9*(1+C$16*$C$11/365))*$I$9) -> 1251.0127 | D55: =IF(D20="","",(SUMPRODUCT(((DUR-D$16/365)<0)*CASH)+D20-$G$9*(1+D$16*$C$11/365))*$I$9) -> 1180.6549 | E55: =IF(E20="","",(SUMPRODUCT(((DUR-E$16/365)<0)*CASH)+E20-$G$9*(1+E$16*$C$11/365))*$I$9) -> 1099.0678 | F55: =IF(F20="","",(SUMPRODUCT(((DUR-F$16/365)<0)*CASH)+F20-$G$9*(1+F$16*$C$11/365))*$I$9) -> 1018.0163 | G55: =IF(G20="","",(SUMPRODUCT(((DUR-G$16/365)<0)*CASH)+G20-$G$9*(1+G$16*$C$11/365))*$I$9) -> 914.45883 | H55: =IF(H20="","",(SUMPRODUCT(((DUR-H$16/365)<0)*CASH)+H20-$G$9*(1+H$16*$C$11/365))*$I$9) -> 567.49433 | I55: =IF(I20="","",(SUMPRODUCT(((DUR-I$16/365)<0)*CASH)+I20-$G$9*(1+I$16*$C$11/365))*$I$9) -> 219.82778 | J55: =IF(J20="","",(SUMPRODUCT(((DUR-J$16/365)<0)*CASH)+J20-$G$9*(1+J$16*$C$11/365))*$I$9) -> -466.25002 | ... L55: =IF(L20="","",(SUMPRODUCT(((DUR-L$16/365)<0)*CASH)+L20-$G$9*(1+L$16*$C$11/365))*$I$9) -> -2875.4762 | Q55: 1332 | R55: 银行间固定利率资产支持证券收益率曲线(AAA)
B56: +10bp | C56: =IF(C21="","",(SUMPRODUCT(((DUR-C$16/365)<0)*CASH)+C21-$G$9*(1+C$16*$C$11/365))*$I$9) -> 1436.3292 | D56: =IF(D21="","",(SUMPRODUCT(((DUR-D$16/365)<0)*CASH)+D21-$G$9*(1+D$16*$C$11/365))*$I$9) -> 1365.5941 | E56: =IF(E21="","",(SUMPRODUCT(((DUR-E$16/365)<0)*CASH)+E21-$G$9*(1+E$16*$C$11/365))*$I$9) -> 1283.5686 | F56: =IF(F21="","",(SUMPRODUCT(((DUR-F$16/365)<0)*CASH)+F21-$G$9*(1+F$16*$C$11/365))*$I$9) -> 1202.0805 | G56: =IF(G21="","",(SUMPRODUCT(((DUR-G$16/365)<0)*CASH)+G21-$G$9*(1+G$16*$C$11/365))*$I$9) -> 1097.966 | H56: =IF(H21="","",(SUMPRODUCT(((DUR-H$16/365)<0)*CASH)+H21-$G$9*(1+H$16*$C$11/365))*$I$9) -> 749.15866 | I56: =IF(I21="","",(SUMPRODUCT(((DUR-I$16/365)<0)*CASH)+I21-$G$9*(1+I$16*$C$11/365))*$I$9) -> 399.64056 | J56: =IF(J21="","",(SUMPRODUCT(((DUR-J$16/365)<0)*CASH)+J21-$G$9*(1+J$16*$C$11/365))*$I$9) -> -290.12218 | ... L56: =IF(L21="","",(SUMPRODUCT(((DUR-L$16/365)<0)*CASH)+L21-$G$9*(1+L$16*$C$11/365))*$I$9) -> -2712.4166 | Q56: 1602 | R56: 银行间固定利率资产支持证券收益率曲线(无评级)
B57: +5bp | C57: =IF(C22="","",(SUMPRODUCT(((DUR-C$16/365)<0)*CASH)+C22-$G$9*(1+C$16*$C$11/365))*$I$9) -> 1622.4424 | D57: =IF(D22="","",(SUMPRODUCT(((DUR-D$16/365)<0)*CASH)+D22-$G$9*(1+D$16*$C$11/365))*$I$9) -> 1551.327 | E57: =IF(E22="","",(SUMPRODUCT(((DUR-E$16/365)<0)*CASH)+E22-$G$9*(1+E$16*$C$11/365))*$I$9) -> 1468.8596 | F57: =IF(F22="","",(SUMPRODUCT(((DUR-F$16/365)<0)*CASH)+F22-$G$9*(1+F$16*$C$11/365))*$I$9) -> 1386.9315 | G57: =IF(G22="","",(SUMPRODUCT(((DUR-G$16/365)<0)*CASH)+G22-$G$9*(1+G$16*$C$11/365))*$I$9) -> 1282.2554 | H57: =IF(H22="","",(SUMPRODUCT(((DUR-H$16/365)<0)*CASH)+H22-$G$9*(1+H$16*$C$11/365))*$I$9) -> 931.59048 | I57: =IF(I22="","",(SUMPRODUCT(((DUR-I$16/365)<0)*CASH)+I22-$G$9*(1+I$16*$C$11/365))*$I$9) -> 580.20619 | J57: =IF(J22="","",(SUMPRODUCT(((DUR-J$16/365)<0)*CASH)+J22-$G$9*(1+J$16*$C$11/365))*$I$9) -> -113.27023 | ... L57: =IF(L22="","",(SUMPRODUCT(((DUR-L$16/365)<0)*CASH)+L22-$G$9*(1+L$16*$C$11/365))*$I$9) -> -2548.7307 | Q57: 1342 | R57: 银行间政策性银行浮动利率(1y)债点差收益率曲线
B58: 0bp | C58: =IF(C23="","",(SUMPRODUCT(((DUR-C$16/365)<0)*CASH)+C23-$G$9*(1+C$16*$C$11/365))*$I$9) -> 1809.3561 | D58: =IF(D23="","",(SUMPRODUCT(((DUR-D$16/365)<0)*CASH)+D23-$G$9*(1+D$16*$C$11/365))*$I$9) -> 1737.8575 | E58: =IF(E23="","",(SUMPRODUCT(((DUR-E$16/365)<0)*CASH)+E23-$G$9*(1+E$16*$C$11/365))*$I$9) -> 1654.9446 | F58: =IF(F23="","",(SUMPRODUCT(((DUR-F$16/365)<0)*CASH)+F23-$G$9*(1+F$16*$C$11/365))*$I$9) -> 1572.5729 | G58: =IF(G23="","",(SUMPRODUCT(((DUR-G$16/365)<0)*CASH)+G23-$G$9*(1+G$16*$C$11/365))*$I$9) -> 1467.3308 | H58: =IF(H23="","",(SUMPRODUCT(((DUR-H$16/365)<0)*CASH)+H23-$G$9*(1+H$16*$C$11/365))*$I$9) -> 1114.7935 | I58: =IF(I23="","",(SUMPRODUCT(((DUR-I$16/365)<0)*CASH)+I23-$G$9*(1+I$16*$C$11/365))*$I$9) -> 761.52825 | J58: =IF(J23="","",(SUMPRODUCT(((DUR-J$16/365)<0)*CASH)+J23-$G$9*(1+J$16*$C$11/365))*$I$9) -> 64.309228 | ... L58: =IF(L23="","",(SUMPRODUCT(((DUR-L$16/365)<0)*CASH)+L23-$G$9*(1+L$16*$C$11/365))*$I$9) -> -2384.4159 | Q58: 1342 | R58: 银行间政策性银行浮动利率(1y)债点差收益率曲线
B59: -5bp | C59: =IF(C24="","",(SUMPRODUCT(((DUR-C$16/365)<0)*CASH)+C24-$G$9*(1+C$16*$C$11/365))*$I$9) -> 1997.0743 | D59: =IF(D24="","",(SUMPRODUCT(((DUR-D$16/365)<0)*CASH)+D24-$G$9*(1+D$16*$C$11/365))*$I$9) -> 1925.1893 | E59: =IF(E24="","",(SUMPRODUCT(((DUR-E$16/365)<0)*CASH)+E24-$G$9*(1+E$16*$C$11/365))*$I$9) -> 1841.8274 | F59: =IF(F24="","",(SUMPRODUCT(((DUR-F$16/365)<0)*CASH)+F24-$G$9*(1+F$16*$C$11/365))*$I$9) -> 1759.0086 | G59: =IF(G24="","",(SUMPRODUCT(((DUR-G$16/365)<0)*CASH)+G24-$G$9*(1+G$16*$C$11/365))*$I$9) -> 1653.1961 | H59: =IF(H24="","",(SUMPRODUCT(((DUR-H$16/365)<0)*CASH)+H24-$G$9*(1+H$16*$C$11/365))*$I$9) -> 1298.7713 | I59: =IF(I24="","",(SUMPRODUCT(((DUR-I$16/365)<0)*CASH)+I24-$G$9*(1+I$16*$C$11/365))*$I$9) -> 943.61031 | J59: =IF(J24="","",(SUMPRODUCT(((DUR-J$16/365)<0)*CASH)+J24-$G$9*(1+J$16*$C$11/365))*$I$9) -> 242.61957 | ... L59: =IF(L24="","",(SUMPRODUCT(((DUR-L$16/365)<0)*CASH)+L24-$G$9*(1+L$16*$C$11/365))*$I$9) -> -2219.4693 | Q59: 1352 | R59: 银行间政策性银行浮动利率(R07D)点差收益率曲线
B60: -10bp | C60: =IF(C25="","",(SUMPRODUCT(((DUR-C$16/365)<0)*CASH)+C25-$G$9*(1+C$16*$C$11/365))*$I$9) -> 2185.6008 | D60: =IF(D25="","",(SUMPRODUCT(((DUR-D$16/365)<0)*CASH)+D25-$G$9*(1+D$16*$C$11/365))*$I$9) -> 2113.3264 | E60: =IF(E25="","",(SUMPRODUCT(((DUR-E$16/365)<0)*CASH)+E25-$G$9*(1+E$16*$C$11/365))*$I$9) -> 2029.512 | F60: =IF(F25="","",(SUMPRODUCT(((DUR-F$16/365)<0)*CASH)+F25-$G$9*(1+F$16*$C$11/365))*$I$9) -> 1946.2425 | G60: =IF(G25="","",(SUMPRODUCT(((DUR-G$16/365)<0)*CASH)+G25-$G$9*(1+G$16*$C$11/365))*$I$9) -> 1839.8549 | H60: =IF(H25="","",(SUMPRODUCT(((DUR-H$16/365)<0)*CASH)+H25-$G$9*(1+H$16*$C$11/365))*$I$9) -> 1483.5277 | I60: =IF(I25="","",(SUMPRODUCT(((DUR-I$16/365)<0)*CASH)+I25-$G$9*(1+I$16*$C$11/365))*$I$9) -> 1126.456 | J60: =IF(J25="","",(SUMPRODUCT(((DUR-J$16/365)<0)*CASH)+J25-$G$9*(1+J$16*$C$11/365))*$I$9) -> 421.66422 | ... L60: =IF(L25="","",(SUMPRODUCT(((DUR-L$16/365)<0)*CASH)+L25-$G$9*(1+L$16*$C$11/365))*$I$9) -> -2053.8882 | Q60: 1352 | R60: 银行间政策性银行浮动利率(R07D)点差收益率曲线
B61: -15bp | C61: =IF(C26="","",(SUMPRODUCT(((DUR-C$16/365)<0)*CASH)+C26-$G$9*(1+C$16*$C$11/365))*$I$9) -> 2374.9396 | D61: =IF(D26="","",(SUMPRODUCT(((DUR-D$16/365)<0)*CASH)+D26-$G$9*(1+D$16*$C$11/365))*$I$9) -> 2302.2726 | E61: =IF(E26="","",(SUMPRODUCT(((DUR-E$16/365)<0)*CASH)+E26-$G$9*(1+E$16*$C$11/365))*$I$9) -> 2218.0021 | F61: =IF(F26="","",(SUMPRODUCT(((DUR-F$16/365)<0)*CASH)+F26-$G$9*(1+F$16*$C$11/365))*$I$9) -> 2134.2783 | G61: =IF(G26="","",(SUMPRODUCT(((DUR-G$16/365)<0)*CASH)+G26-$G$9*(1+G$16*$C$11/365))*$I$9) -> 2027.3111 | H61: =IF(H26="","",(SUMPRODUCT(((DUR-H$16/365)<0)*CASH)+H26-$G$9*(1+H$16*$C$11/365))*$I$9) -> 1669.0663 | I61: =IF(I26="","",(SUMPRODUCT(((DUR-I$16/365)<0)*CASH)+I26-$G$9*(1+I$16*$C$11/365))*$I$9) -> 1310.0689 | J61: =IF(J26="","",(SUMPRODUCT(((DUR-J$16/365)<0)*CASH)+J26-$G$9*(1+J$16*$C$11/365))*$I$9) -> 601.44659 | ... L61: =IF(L26="","",(SUMPRODUCT(((DUR-L$16/365)<0)*CASH)+L26-$G$9*(1+L$16*$C$11/365))*$I$9) -> -1887.6698 | Q61: 1382 | R61: 银行间政策性银行浮动利率(SHIBOR)债点差收益率曲线
B62: -20bp | C62: =IF(C27="","",(SUMPRODUCT(((DUR-C$16/365)<0)*CASH)+C27-$G$9*(1+C$16*$C$11/365))*$I$9) -> 2565.0946 | D62: =IF(D27="","",(SUMPRODUCT(((DUR-D$16/365)<0)*CASH)+D27-$G$9*(1+D$16*$C$11/365))*$I$9) -> 2492.032 | E62: =IF(E27="","",(SUMPRODUCT(((DUR-E$16/365)<0)*CASH)+E27-$G$9*(1+E$16*$C$11/365))*$I$9) -> 2407.3017 | F62: =IF(F27="","",(SUMPRODUCT(((DUR-F$16/365)<0)*CASH)+F27-$G$9*(1+F$16*$C$11/365))*$I$9) -> 2323.1201 | G62: =IF(G27="","",(SUMPRODUCT(((DUR-G$16/365)<0)*CASH)+G27-$G$9*(1+G$16*$C$11/365))*$I$9) -> 2215.5687 | H62: =IF(H27="","",(SUMPRODUCT(((DUR-H$16/365)<0)*CASH)+H27-$G$9*(1+H$16*$C$11/365))*$I$9) -> 1855.391 | I62: =IF(I27="","",(SUMPRODUCT(((DUR-I$16/365)<0)*CASH)+I27-$G$9*(1+I$16*$C$11/365))*$I$9) -> 1494.4527 | J62: =IF(J27="","",(SUMPRODUCT(((DUR-J$16/365)<0)*CASH)+J27-$G$9*(1+J$16*$C$11/365))*$I$9) -> 781.97012 | ... L62: =IF(L27="","",(SUMPRODUCT(((DUR-L$16/365)<0)*CASH)+L27-$G$9*(1+L$16*$C$11/365))*$I$9) -> -1720.8114 | Q62: 1382 | R62: 银行间政策性银行浮动利率(SHIBOR)债点差收益率曲线
B63: -30bp | C63: =IF(C28="","",(SUMPRODUCT(((DUR-C$16/365)<0)*CASH)+C28-$G$9*(1+C$16*$C$11/365))*$I$9) -> 2947.8692 | D63: =IF(D28="","",(SUMPRODUCT(((DUR-D$16/365)<0)*CASH)+D28-$G$9*(1+D$16*$C$11/365))*$I$9) -> 2874.0058 | E63: =IF(E28="","",(SUMPRODUCT(((DUR-E$16/365)<0)*CASH)+E28-$G$9*(1+E$16*$C$11/365))*$I$9) -> 2788.345 | F63: =IF(F28="","",(SUMPRODUCT(((DUR-F$16/365)<0)*CASH)+F28-$G$9*(1+F$16*$C$11/365))*$I$9) -> 2703.2369 | G63: =IF(G28="","",(SUMPRODUCT(((DUR-G$16/365)<0)*CASH)+G28-$G$9*(1+G$16*$C$11/365))*$I$9) -> 2594.5031 | H63: =IF(H28="","",(SUMPRODUCT(((DUR-H$16/365)<0)*CASH)+H28-$G$9*(1+H$16*$C$11/365))*$I$9) -> 2230.4135 | I63: =IF(I28="","",(SUMPRODUCT(((DUR-I$16/365)<0)*CASH)+I28-$G$9*(1+I$16*$C$11/365))*$I$9) -> 1865.5475 | J63: =IF(J28="","",(SUMPRODUCT(((DUR-J$16/365)<0)*CASH)+J28-$G$9*(1+J$16*$C$11/365))*$I$9) -> 1145.2546 | ... L63: =IF(L28="","",(SUMPRODUCT(((DUR-L$16/365)<0)*CASH)+L28-$G$9*(1+L$16*$C$11/365))*$I$9) -> -1385.163 | Q63: 1042 | R63: 银行间中短期票据收益率曲线(A)
B64: -50bp | C64: =IF(C29="","",(SUMPRODUCT(((DUR-C$16/365)<0)*CASH)+C29-$G$9*(1+C$16*$C$11/365))*$I$9) -> 3723.3891 | D64: =IF(D29="","",(SUMPRODUCT(((DUR-D$16/365)<0)*CASH)+D29-$G$9*(1+D$16*$C$11/365))*$I$9) -> 3647.8861 | E64: =IF(E29="","",(SUMPRODUCT(((DUR-E$16/365)<0)*CASH)+E29-$G$9*(1+E$16*$C$11/365))*$I$9) -> 3560.3198 | F64: =IF(F29="","",(SUMPRODUCT(((DUR-F$16/365)<0)*CASH)+F29-$G$9*(1+F$16*$C$11/365))*$I$9) -> 3473.3142 | G64: =IF(G29="","",(SUMPRODUCT(((DUR-G$16/365)<0)*CASH)+G29-$G$9*(1+G$16*$C$11/365))*$I$9) -> 3362.1591 | H64: =IF(H29="","",(SUMPRODUCT(((DUR-H$16/365)<0)*CASH)+H29-$G$9*(1+H$16*$C$11/365))*$I$9) -> 2990.0577 | I64: =IF(I29="","",(SUMPRODUCT(((DUR-I$16/365)<0)*CASH)+I29-$G$9*(1+I$16*$C$11/365))*$I$9) -> 2617.1502 | J64: =IF(J29="","",(SUMPRODUCT(((DUR-J$16/365)<0)*CASH)+J29-$G$9*(1+J$16*$C$11/365))*$I$9) -> 1880.8711 | ... L64: =IF(L29="","",(SUMPRODUCT(((DUR-L$16/365)<0)*CASH)+L29-$G$9*(1+L$16*$C$11/365))*$I$9) -> -706.06065 | Q64: 1062 | R64: 银行间中短期票据收益率曲线(A-)
B65: =B48 -> 10bp | C65: =IF(C30="","",(SUMPRODUCT(((DUR-C$16/365)<0)*CASH)+C30-$G$9*(1+C$16*$C$11/365))*$I$9) -> 1436.3292 | D65: =IF(D30="","",(SUMPRODUCT(((DUR-D$16/365)<0)*CASH)+D30-$G$9*(1+D$16*$C$11/365))*$I$9) -> 1365.5941 | E65: =IF(E30="","",(SUMPRODUCT(((DUR-E$16/365)<0)*CASH)+E30-$G$9*(1+E$16*$C$11/365))*$I$9) -> 1283.5686 | F65: =IF(F30="","",(SUMPRODUCT(((DUR-F$16/365)<0)*CASH)+F30-$G$9*(1+F$16*$C$11/365))*$I$9) -> 1202.0805 | G65: =IF(G30="","",(SUMPRODUCT(((DUR-G$16/365)<0)*CASH)+G30-$G$9*(1+G$16*$C$11/365))*$I$9) -> 1097.966 | H65: =IF(H30="","",(SUMPRODUCT(((DUR-H$16/365)<0)*CASH)+H30-$G$9*(1+H$16*$C$11/365))*$I$9) -> 749.15866 | I65: =IF(I30="","",(SUMPRODUCT(((DUR-I$16/365)<0)*CASH)+I30-$G$9*(1+I$16*$C$11/365))*$I$9) -> 399.64056 | J65: =IF(J30="","",(SUMPRODUCT(((DUR-J$16/365)<0)*CASH)+J30-$G$9*(1+J$16*$C$11/365))*$I$9) -> -290.12218 | ... L65: =IF(L30="","",(SUMPRODUCT(((DUR-L$16/365)<0)*CASH)+L30-$G$9*(1+L$16*$C$11/365))*$I$9) -> -2712.4166 | Q65: 1052 | R65: 银行间中短期票据收益率曲线(A+)
Q66: 1072 | R66: 银行间中短期票据收益率曲线(AA)
Q67: 1092 | R67: 银行间中短期票据收益率曲线(AA-)
Q68: 1082 | R68: 银行间中短期票据收益率曲线(AA+)
Q69: 1102 | R69: 银行间中短期票据收益率曲线(AAA)
Q70: 1502 | R70: 银行间中短期票据收益率曲线(AAA-)
Q71: 2022 | R71: 银行间中短期票据收益率曲线(超AAA)
Q72: 1362 | R72: 中国固定利率国债收益率曲线

Sheet 现金流
B1: 债券代码 | C1: =模拟分析!$C$5 -> 220010.IB | D1: 到期日 | E1: =[1]!b_info_maturitydate(C1) -> 2032-05-15 | F1: 曲线日期 | G1: =模拟分析!$G$11 -> 45398 | H1: 曲线代码 | I1: =LOOKUP(模拟分析!$C$12,模拟分析!$R$6:$R$67,模拟分析!$Q$6:$Q$67) -> 1232 | J1: 行权日期
E2: =模拟分析!C16 -> 1 | F2: =模拟分析!D16 -> 7 | G2: =模拟分析!E16 -> 14 | H2: =模拟分析!F16 -> 21 | I2: =模拟分析!G16 -> 30 | J2: =模拟分析!H16 -> 60 | K2: =模拟分析!I16 -> 90 | L2: =模拟分析!J16 -> 150 | ... N2: =模拟分析!L16 -> 365
D3: 远期因子 | E3: =[1]!B_CALC_CURVE_CHINABOND($I$1,$G$1,E$2/365) -> 1.4038253 | F3: =[1]!B_CALC_CURVE_CHINABOND($I$1,$G$1,F$2/365) -> 1.4267774 | G3: =[1]!B_CALC_CURVE_CHINABOND($I$1,$G$1,G$2/365) -> 1.4535548 | H3: =[1]!B_CALC_CURVE_CHINABOND($I$1,$G$1,H$2/365) -> 1.4803322 | I3: =[1]!B_CALC_CURVE_CHINABOND($I$1,$G$1,I$2/365) -> 1.5131466 | J3: =[1]!B_CALC_CURVE_CHINABOND($I$1,$G$1,J$2/365) -> 1.5387885 | K3: =[1]!B_CALC_CURVE_CHINABOND($I$1,$G$1,K$2/365) -> 1.5409315 | L3: =[1]!B_CALC_CURVE_CHINABOND($I$1,$G$1,L$2/365) -> 1.5851479 | ... N3: =[1]!B_CALC_CURVE_CHINABOND($I$1,$G$1,N$2/365) -> 1.7233
B4: 现金流日期 | C4: 现金流 | D4: 剩余期限 | E4: 1d | F4: 7d | G4: 2W | H4: 3W | I4: 1M | J4: 2M | K4: 3M | L4: 5M | M4: 1Y | N4: =N2&"d" -> 365d
B5: =[1]!b_anal_nxcupn(C1,模拟分析!$I$8) -> 2024-05-15 | C5: =IF(B5="",0,IF(模拟分析!$K$9=0,[1]!b_anal_dailycf($C$1,B5),IF(模拟分析!$I$11="否",[1]!b_anal_dailycf($C$1,B5),IF(B5<模拟分析!$K$12,[1]!b_anal_dailycf($C$1,B5),IF(B5=模拟分析!$K$12,[1]!b_anal_dailycf($C$1,B5)+模拟分析!$K$11,0))))) -> 1.38 | D5: =IF(B5="",0,(-TODAY()+B5)/365) -> 0.076712329 | E5: =IF($B5="",0,IF($D5-E$2/365<=0,0,(IF(模拟分析!$I$12="到期平移法",[1]!B_CALC_CURVE_CHINABOND($I$1,$G$1,$D5-E$2/365)+模拟分析!$G$12/100,(((1+[1]!B_CALC_CURVE_CHINABOND($I$1,$G$1,$D5)/100)^$D5/(1+E$3/100)^(E$2/365))^(1/($D5-E$2/365))-1)*100+模拟分析!$G$12/100)))) -> 1.540937 | F5: =IF($B5="",0,IF($D5-F$2/365<=0,0,(IF(模拟分析!$I$12="到期平移法",[1]!B_CALC_CURVE_CHINABOND($I$1,$G$1,$D5-F$2/365)+模拟分析!$G$12/100,(((1+[1]!B_CALC_CURVE_CHINABOND($I$1,$G$1,$D5)/100)^$D5/(1+F$3/100)^(F$2/365))^(1/($D5-F$2/365))-1)*100+模拟分析!$G$12/100)))) -> 1.5639011 | G5: =IF($B5="",0,IF($D5-G$2/365<=0,0,(IF(模拟分析!$I$12="到期平移法",[1]!B_CALC_CURVE_CHINABOND($I$1,$G$1,$D5-G$2/365)+模拟分析!$G$12/100,(((1+[1]!B_CALC_CURVE_CHINABOND($I$1,$G$1,$D5)/100)^$D5/(1+G$3/100)^(G$2/365))^(1/($D5-G$2/365))-1)*100+模拟分析!$G$12/100)))) -> 1.5906927 | H5: =IF($B5="",0,IF($D5-H$2/365<=0,0,(IF(模拟分析!$I$12="到期平移法",[1]!B_CALC_CURVE_CHINABOND($I$1,$G$1,$D5-H$2/365)+模拟分析!$G$12/100,(((1+[1]!B_CALC_CURVE_CHINABOND($I$1,$G$1,$D5)/100)^$D5/(1+H$3/100)^(H$2/365))^(1/($D5-H$2/365))-1)*100+模拟分析!$G$12/100)))) -> 1.6174842 | I5: =IF($B5="",0,IF($D5-I$2/365<=0,0,(IF(模拟分析!$I$12="到期平移法",[1]!B_CALC_CURVE_CHINABOND($I$1,$G$1,$D5-I$2/365)+模拟分析!$G$12/100,(((1+[1]!B_CALC_CURVE_CHINABOND($I$1,$G$1,$D5)/100)^$D5/(1+I$3/100)^(I$2/365))^(1/($D5-I$2/365))-1)*100+模拟分析!$G$12/100)))) -> 0 | J5: =IF($B5="",0,IF($D5-J$2/365<=0,0,(IF(模拟分析!$I$12="到期平移法",[1]!B_CALC_CURVE_CHINABOND($I$1,$G$1,$D5-J$2/365)+模拟分析!$G$12/100,(((1+[1]!B_CALC_CURVE_CHINABOND($I$1,$G$1,$D5)/100)^$D5/(1+J$3/100)^(J$2/365))^(1/($D5-J$2/365))-1)*100+模拟分析!$G$12/100)))) -> 0 | K5: =IF($B5="",0,IF($D5-K$2/365<=0,0,(IF(模拟分析!$I$12="到期平移法",[1]!B_CALC_CURVE_CHINABOND($I$1,$G$1,$D5-K$2/365)+模拟分析!$G$12/100,(((1+[1]!B_CALC_CURVE_CHINABOND($I$1,$G$1,$D5)/100)^$D5/(1+K$3/100)^(K$2/365))^(1/($D5-K$2/365))-1)*100+模拟分析!$G$12/100)))) -> 0 | L5: =IF($B5="",0,IF($D5-L$2/365<=0,0,(IF(模拟分析!$I$12="到期平移法",[1]!B_CALC_CURVE_CHINABOND($I$1,$G$1,$D5-L$2/365)+模拟分析!$G$12/100,(((1+[1]!B_CALC_CURVE_CHINABOND($I$1,$G$1,$D5)/100)^$D5/(1+L$3/100)^(L$2/365))^(1/($D5-L$2/365))-1)*100+模拟分析!$G$12/100)))) -> 0 | ... N5: =IF($B5="",0,IF($D5-N$2/365<=0,0,(IF(模拟分析!$I$12="到期平移法",[1]!B_CALC_CURVE_CHINABOND($I$1,$G$1,$D5-N$2/365)+模拟分析!$G$12/100,(((1+[1]!B_CALC_CURVE_CHINABOND($I$1,$G$1,$D5)/100)^$D5/(1+N$3/100)^(N$2/365))^(1/($D5-N$2/365))-1)*100+模拟分析!$G$12/100)))) -> 0 | O5: =IF(C5="","",C5/((1+E5/100)^(D5-21/365))) -> 1.3795953
B6: =IF(B5="","",IF(B5<$E$1,[1]!b_anal_nxcupn($C$1,B5+2),"")) -> 2024-11-15 | C6: =IF(B6="",0,IF(模拟分析!$K$9=0,[1]!b_anal_dailycf($C$1,B6),IF(模拟分析!$I$11="否",[1]!b_anal_dailycf($C$1,B6),IF(B6<模拟分析!$K$12,[1]!b_anal_dailycf($C$1,B6),IF(B6=模拟分析!$K$12,[1]!b_anal_dailycf($C$1,B6)+模拟分析!$K$11,0))))) -> 1.38 | D6: =IF(B6="",0,(-TODAY()+B6)/365) -> 0.58082192 | E6: =IF($B6="",0,IF($D6-E$2/365<=0,0,(IF(模拟分析!$I$12="到期平移法",[1]!B_CALC_CURVE_CHINABOND($I$1,$G$1,$D6-E$2/365)+模拟分析!$G$12/100,(((1+[1]!B_CALC_CURVE_CHINABOND($I$1,$G$1,$D6)/100)^$D6/(1+E$3/100)^(E$2/365))^(1/($D6-E$2/365))-1)*100+模拟分析!$G$12/100)))) -> 1.6729966 | F6: =IF($B6="",0,IF($D6-F$2/365<=0,0,(IF(模拟分析!$I$12="到期平移法",[1]!B_CALC_CURVE_CHINABOND($I$1,$G$1,$D6-F$2/365)+模拟分析!$G$12/100,(((1+[1]!B_CALC_CURVE_CHINABOND($I$1,$G$1,$D6)/100)^$D6/(1+F$3/100)^(F$2/365))^(1/($D6-F$2/365))-1)*100+模拟分析!$G$12/100)))) -> 1.6792197 | G6: =IF($B6="",0,IF($D6-G$2/365<=0,0,(IF(模拟分析!$I$12="到期平移法",[1]!B_CALC_CURVE_CHINABOND($I$1,$G$1,$D6-G$2/365)+模拟分析!$G$12/100,(((1+[1]!B_CALC_CURVE_CHINABOND($I$1,$G$1,$D6)/100)^$D6/(1+G$3/100)^(G$2/365))^(1/($D6-G$2/365))-1)*100+模拟分析!$G$12/100)))) -> 1.6851954 | H6: =IF($B6="",0,IF($D6-H$2/365<=0,0,(IF(模拟分析!$I$12="到期平移法",[1]!B_CALC_CURVE_CHINABOND($I$1,$G$1,$D6-H$2/365)+模拟分析!$G$12/100,(((1+[1]!B_CALC_CURVE_CHINABOND($I$1,$G$1,$D6)/100)^$D6/(1+H$3/100)^(H$2/365))^(1/($D6-H$2/365))-1)*100+模拟分析!$G$12/100)))) -> 1.6896432 | I6: =IF($B6="",0,IF($D6-I$2/365<=0,0,(IF(模拟分析!$I$12="到期平移法",[1]!B_CALC_CURVE_CHINABOND($I$1,$G$1,$D6-I$2/365)+模拟分析!$G$12/100,(((1+[1]!B_CALC_CURVE_CHINABOND($I$1,$G$1,$D6)/100)^$D6/(1+I$3/100)^(I$2/365))^(1/($D6-I$2/365))-1)*100+模拟分析!$G$12/100)))) -> 1.6931005 | J6: =IF($B6="",0,IF($D6-J$2/365<=0,0,(IF(模拟分析!$I$12="到期平移法",[1]!B_CALC_CURVE_CHINABOND($I$1,$G$1,$D6-J$2/365)+模拟分析!$G$12/100,(((1+[1]!B_CALC_CURVE_CHINABOND($I$1,$G$1,$D6)/100)^$D6/(1+J$3/100)^(J$2/365))^(1/($D6-J$2/365))-1)*100+模拟分析!$G$12/100)))) -> 1.7125849 | K6: =IF($B6="",0,IF($D6-K$2/365<=0,0,(IF(模拟分析!$I$12="到期平移法",[1]!B_CALC_CURVE_CHINABOND($I$1,$G$1,$D6-K$2/365)+模拟分析!$G$12/100,(((1+[1]!B_CALC_CURVE_CHINABOND($I$1,$G$1,$D6)/100)^$D6/(1+K$3/100)^(K$2/365))^(1/($D6-K$2/365))-1)*100+模拟分析!$G$12/100)))) -> 1.7463921 | L6: =IF($B6="",0,IF($D6-L$2/365<=0,0,(IF(模拟分析!$I$12="到期平移法",[1]!B_CALC_CURVE_CHINABOND($I$1,$G$1,$D6-L$2/365)+模拟分析!$G$12/100,(((1+[1]!B_CALC_CURVE_CHINABOND($I$1,$G$1,$D6)/100)^$D6/(1+L$3/100)^(L$2/365))^(1/($D6-L$2/365))-1)*100+模拟分析!$G$12/100)))) -> 1.809222 | ... N6: =IF($B6="",0,IF($D6-N$2/365<=0,0,(IF(模拟分析!$I$12="到期平移法",[1]!B_CALC_CURVE_CHINABOND($I$1,$G$1,$D6-N$2/365)+模拟分析!$G$12/100,(((1+[1]!B_CALC_CURVE_CHINABOND($I$1,$G$1,$D6)/100)^$D6/(1+N$3/100)^(N$2/365))^(1/($D6-N$2/365))-1)*100+模拟分析!$G$12/100)))) -> 0 | O6: =IF(C6="","",C6/((1+E6/100)^(D6-21/365))) -> 1.3680705
A7: =[1]!B_CALC_CURVE_CHINABOND($I$1,$G$1,$D5-E$2/365) -> 1.5032842 | B7: =IF(B6="","",IF(B6<$E$1,[1]!b_anal_nxcupn($C$1,B6+1),"")) -> 2025-05-15 | C7: =IF(B7="",0,IF(模拟分析!$K$9=0,[1]!b_anal_dailycf($C$1,B7),IF(模拟分析!$I$11="否",[1]!b_anal_dailycf($C$1,B7),IF(B7<模拟分析!$K$12,[1]!b_anal_dailycf($C$1,B7),IF(B7=模拟分析!$K$12,[1]!b_anal_dailycf($C$1,B7)+模拟分析!$K$11,0))))) -> 1.38 | D7: =IF(B7="",0,(-TODAY()+B7)/365) -> 1.0767123 | E7: =IF($B7="",0,IF($D7-E$2/365<=0,0,(IF(模拟分析!$I$12="到期平移法",[1]!B_CALC_CURVE_CHINABOND($I$1,$G$1,$D7-E$2/365)+模拟分析!$G$12/100,(((1+[1]!B_CALC_CURVE_CHINABOND($I$1,$G$1,$D7)/100)^$D7/(1+E$3/100)^(E$2/365))^(1/($D7-E$2/365))-1)*100+模拟分析!$G$12/100)))) -> 1.760269 | F7: =IF($B7="",0,IF($D7-F$2/365<=0,0,(IF(模拟分析!$I$12="到期平移法",[1]!B_CALC_CURVE_CHINABOND($I$1,$G$1,$D7-F$2/365)+模拟分析!$G$12/100,(((1+[1]!B_CALC_CURVE_CHINABOND($I$1,$G$1,$D7)/100)^$D7/(1+F$3/100)^(F$2/365))^(1/($D7-F$2/365))-1)*100+模拟分析!$G$12/100)))) -> 1.764934 | G7: =IF($B7="",0,IF($D7-G$2/365<=0,0,(IF(模拟分析!$I$12="到期平移法",[1]!B_CALC_CURVE_CHINABOND($I$1,$G$1,$D7-G$2/365)+模拟分析!$G$12/100,(((1+[1]!B_CALC_CURVE_CHINABOND($I$1,$G$1,$D7)/100)^$D7/(1+G$3/100)^(G$2/365))^(1/($D7-G$2/365))-1)*100+模拟分析!$G$12/100)))) -> 1.7696422 | H7: =IF($B7="",0,IF($D7-H$2/365<=0,0,(IF(模拟分析!$I$12="到期平移法",[1]!B_CALC_CURVE_CHINABOND($I$1,$G$1,$D7-H$2/365)+模拟分析!$G$12/100,(((1+[1]!B_CALC_CURVE_CHINABOND($I$1,$G$1,$D7)/100)^$D7/(1+H$3/100)^(H$2/365))^(1/($D7-H$2/365))-1)*100+模拟分析!$G$12/100)))) -> 1.7735176 | I7: =IF($B7="",0,IF($D7-I$2/365<=0,0,(IF(模拟分析!$I$12="到期平移法",[1]!B_CALC_CURVE_CHINABOND($I$1,$G$1,$D7-I$2/365)+模拟分析!$G$12/100,(((1+[1]!B_CALC_CURVE_CHINABOND($I$1,$G$1,$D7)/100)^$D7/(1+I$3/100)^(I$2/365))^(1/($D7-I$2/365))-1)*100+模拟分析!$G$12/100)))) -> 1.7773328 | J7: =IF($B7="",0,IF($D7-J$2/365<=0,0,(IF(模拟分析!$I$12="到期平移法",[1]!B_CALC_CURVE_CHINABOND($I$1,$G$1,$D7-J$2/365)+模拟分析!$G$12/100,(((1+[1]!B_CALC_CURVE_CHINABOND($I$1,$G$1,$D7)/100)^$D7/(1+J$3/100)^(J$2/365))^(1/($D7-J$2/365))-1)*100+模拟分析!$G$12/100)))) -> 1.7938261 | K7: =IF($B7="",0,IF($D7-K$2/365<=0,0,(IF(模拟分析!$I$12="到期平移法",[1]!B_CALC_CURVE_CHINABOND($I$1,$G$1,$D7-K$2/365)+模拟分析!$G$12/100,(((1+[1]!B_CALC_CURVE_CHINABOND($I$1,$G$1,$D7)/100)^$D7/(1+K$3/100)^(K$2/365))^(1/($D7-K$2/365))-1)*100+模拟分析!$G$12/100)))) -> 1.8154961 | L7: =IF($B7="",0,IF($D7-L$2/365<=0,0,(IF(模拟分析!$I$12="到期平移法",[1]!B_CALC_CURVE_CHINABOND($I$1,$G$1,$D7-L$2/365)+模拟分析!$G$12/100,(((1+[1]!B_CALC_CURVE_CHINABOND($I$1,$G$1,$D7)/100)^$D7/(1+L$3/100)^(L$2/365))^(1/($D7-L$2/365))-1)*100+模拟分析!$G$12/100)))) -> 1.8486066 | ... N7: =IF($B7="",0,IF($D7-N$2/365<=0,0,(IF(模拟分析!$I$12="到期平移法",[1]!B_CALC_CURVE_CHINABOND($I$1,$G$1,$D7-N$2/365)+模拟分析!$G$12/100,(((1+[1]!B_CALC_CURVE_CHINABOND($I$1,$G$1,$D7)/100)^$D7/(1+N$3/100)^(N$2/365))^(1/($D7-N$2/365))-1)*100+模拟分析!$G$12/100)))) -> 1.8394709 | O7: =IF(C7="","",C7/((1+E7/100)^(D7-21/365))) -> 1.3556747
A8: =[1]!B_CALC_CURVE_CHINABOND($I$1,$G$1,$D7-E$2/365) -> 1.7292178 | B8: =IF(B7="","",IF(B7<$E$1,[1]!b_anal_nxcupn($C$1,B7+1),"")) -> 2025-11-15 | C8: =IF(B8="",0,IF(模拟分析!$K$9=0,[1]!b_anal_dailycf($C$1,B8),IF(模拟分析!$I$11="否",[1]!b_anal_dailycf($C$1,B8),IF(B8<模拟分析!$K$12,[1]!b_anal_dailycf($C$1,B8),IF(B8=模拟分析!$K$12,[1]!b_anal_dailycf($C$1,B8)+模拟分析!$K$11,0))))) -> 1.38 | D8: =IF(B8="",0,(-TODAY()+B8)/365) -> 1.5808219 | E8: =IF($B8="",0,IF($D8-E$2/365<=0,0,(IF(模拟分析!$I$12="到期平移法",[1]!B_CALC_CURVE_CHINABOND($I$1,$G$1,$D8-E$2/365)+模拟分析!$G$12/100,(((1+[1]!B_CALC_CURVE_CHINABOND($I$1,$G$1,$D8)/100)^$D8/(1+E$3/100)^(E$2/365))^(1/($D8-E$2/365))-1)*100+模拟分析!$G$12/100)))) -> 1.8369329 | F8: =IF($B8="",0,IF($D8-F$2/365<=0,0,(IF(模拟分析!$I$12="到期平移法",[1]!B_CALC_CURVE_CHINABOND($I$1,$G$1,$D8-F$2/365)+模拟分析!$G$12/100,(((1+[1]!B_CALC_CURVE_CHINABOND($I$1,$G$1,$D8)/100)^$D8/(1+F$3/100)^(F$2/365))^(1/($D8-F$2/365))-1)*100+模拟分析!$G$12/100)))) -> 1.8409017 | G8: =IF($B8="",0,IF($D8-G$2/365<=0,0,(IF(模拟分析!$I$12="到期平移法",[1]!B_CALC_CURVE_CHINABOND($I$1,$G$1,$D8-G$2/365)+模拟分析!$G$12/100,(((1+[1]!B_CALC_CURVE_CHINABOND($I$1,$G$1,$D8)/100)^$D8/(1+G$3/100)^(G$2/365))^(1/($D8-G$2/365))-1)*100+模拟分析!$G$12/100)))) -> 1.8450185 | H8: =IF($B8="",0,IF($D8-H$2/365<=0,0,(IF(模拟分析!$I$12="到期平移法",[1]!B_CALC_CURVE_CHINABOND($I$1,$G$1,$D8-H$2/365)+模拟分析!$G$12/100,(((1+[1]!B_CALC_CURVE_CHINABOND($I$1,$G$1,$D8)/100)^$D8/(1+H$3/100)^(H$2/365))^(1/($D8-H$2/365))-1)*100+模拟分析!$G$12/100)))) -> 1.8485626 | I8: =IF($B8="",0,IF($D8-I$2/365<=0,0,(IF(模拟分析!$I$12="到期平移法",[1]!B_CALC_CURVE_CHINABOND($I$1,$G$1,$D8-I$2/365)+模拟分析!$G$12/100,(((1+[1]!B_CALC_CURVE_CHINABOND($I$1,$G$1,$D8)/100)^$D8/(1+I$3/100)^(I$2/365))^(1/($D8-I$2/365))-1)*100+模拟分析!$G$12/100)))) -> 1.8523315 | J8: =IF($B8="",0,IF($D8-J$2/365<=0,0,(IF(模拟分析!$I$12="到期平移法",[1]!B_CALC_CURVE_CHINABOND($I$1,$G$1,$D8-J$2/365)+模拟分析!$G$12/100,(((1+[1]!B_CALC_CURVE_CHINABOND($I$1,$G$1,$D8)/100)^$D8/(1+J$3/100)^(J$2/365))^(1/($D8-J$2/365))-1)*100+模拟分析!$G$12/100)))) -> 1.8673165 | K8: =IF($B8="",0,IF($D8-K$2/365<=0,0,(IF(模拟分析!$I$12="到期平移法",[1]!B_CALC_CURVE_CHINABOND($I$1,$G$1,$D8-K$2/365)+模拟分析!$G$12/100,(((1+[1]!B_CALC_CURVE_CHINABOND($I$1,$G$1,$D8)/100)^$D8/(1+K$3/100)^(K$2/365))^(1/($D8-K$2/365))-1)*100+模拟分析!$G$12/100)))) -> 1.8853377 | L8: =IF($B8="",0,IF($D8-L$2/365<=0,0,(IF(模拟分析!$I$12="到期平移法",[1]!B_CALC_CURVE_CHINABOND($I$1,$G$1,$D8-L$2/365)+模拟分析!$G$12/100,(((1+[1]!B_CALC_CURVE_CHINABOND($I$1,$G$1,$D8)/100)^$D8/(1+L$3/100)^(L$2/365))^(1/($D8-L$2/365))-1)*100+模拟分析!$G$12/100)))) -> 1.9140115 | ... N8: =IF($B8="",0,IF($D8-N$2/365<=0,0,(IF(模拟分析!$I$12="到期平移法",[1]!B_CALC_CURVE_CHINABOND($I$1,$G$1,$D8-N$2/365)+模拟分析!$G$12/100,(((1+[1]!B_CALC_CURVE_CHINABOND($I$1,$G$1,$D8)/100)^$D8/(1+N$3/100)^(N$2/365))^(1/($D8-N$2/365))-1)*100+模拟分析!$G$12/100)))) -> 1.9791767 | O8: =IF(C8="","",C8/((1+E8/100)^(D8-21/365))) -> 1.3422612
B9: =IF(B8="","",IF(B8<$E$1,[1]!b_anal_nxcupn($C$1,B8+1),"")) -> 2026-05-15 | C9: =IF(B9="",0,IF(模拟分析!$K$9=0,[1]!b_anal_dailycf($C$1,B9),IF(模拟分析!$I$11="否",[1]!b_anal_dailycf($C$1,B9),IF(B9<模拟分析!$K$12,[1]!b_anal_dailycf($C$1,B9),IF(B9=模拟分析!$K$12,[1]!b_anal_dailycf($C$1,B9)+模拟分析!$K$11,0))))) -> 1.38 | D9: =IF(B9="",0,(-TODAY()+B9)/365) -> 2.0767123 | E9: =IF($B9="",0,IF($D9-E$2/365<=0,0,(IF(模拟分析!$I$12="到期平移法",[1]!B_CALC_CURVE_CHINABOND($I$1,$G$1,$D9-E$2/365)+模拟分析!$G$12/100,(((1+[1]!B_CALC_CURVE_CHINABOND($I$1,$G$1,$D9)/100)^$D9/(1+E$3/100)^(E$2/365))^(1/($D9-E$2/365))-1)*100+模拟分析!$G$12/100)))) -> 1.9206506 | F9: =IF($B9="",0,IF($D9-F$2/365<=0,0,(IF(模拟分析!$I$12="到期平移法",[1]!B_CALC_CURVE_CHINABOND($I$1,$G$1,$D9-F$2/365)+模拟分析!$G$12/100,(((1+[1]!B_CALC_CURVE_CHINABOND($I$1,$G$1,$D9)/100)^$D9/(1+F$3/100)^(F$2/365))^(1/($D9-F$2/365))-1)*100+模拟分析!$G$12/100)))) -> 1.9243345 | G9: =IF($B9="",0,IF($D9-G$2/365<=0,0,(IF(模拟分析!$I$12="到期平移法",[1]!B_CALC_CURVE_CHINABOND($I$1,$G$1,$D9-G$2/365)+模拟分析!$G$12/100,(((1+[1]!B_CALC_CURVE_CHINABOND($I$1,$G$1,$D9)/100)^$D9/(1+G$3/100)^(G$2/365))^(1/($D9-G$2/365))-1)*100+模拟分析!$G$12/100)))) -> 1.9282376 | H9: =IF($B9="",0,IF($D9-H$2/365<=0,0,(IF(模拟分析!$I$12="到期平移法",[1]!B_CALC_CURVE_CHINABOND($I$1,$G$1,$D9-H$2/365)+模拟分析!$G$12/100,(((1+[1]!B_CALC_CURVE_CHINABOND($I$1,$G$1,$D9)/100)^$D9/(1+H$3/100)^(H$2/365))^(1/($D9-H$2/365))-1)*100+模拟分析!$G$12/100)))) -> 1.9317043 | I9: =IF($B9="",0,IF($D9-I$2/365<=0,0,(IF(模拟分析!$I$12="到期平移法",[1]!B_CALC_CURVE_CHINABOND($I$1,$G$1,$D9-I$2/365)+模拟分析!$G$12/100,(((1+[1]!B_CALC_CURVE_CHINABOND($I$1,$G$1,$D9)/100)^$D9/(1+I$3/100)^(I$2/365))^(1/($D9-I$2/365))-1)*100+模拟分析!$G$12/100)))) -> 1.9355668 | J9: =IF($B9="",0,IF($D9-J$2/365<=0,0,(IF(模拟分析!$I$12="到期平移法",[1]!B_CALC_CURVE_CHINABOND($I$1,$G$1,$D9-J$2/365)+模拟分析!$G$12/100,(((1+[1]!B_CALC_CURVE_CHINABOND($I$1,$G$1,$D9)/100)^$D9/(1+J$3/100)^(J$2/365))^(1/($D9-J$2/365))-1)*100+模拟分析!$G$12/100)))) -> 1.9502542 | K9: =IF($B9="",0,IF($D9-K$2/365<=0,0,(IF(模拟分析!$I$12="到期平移法",[1]!B_CALC_CURVE_CHINABOND($I$1,$G$1,$D9-K$2/365)+模拟分析!$G$12/100,(((1+[1]!B_CALC_CURVE_CHINABOND($I$1,$G$1,$D9)/100)^$D9/(1+K$3/100)^(K$2/365))^(1/($D9-K$2/365))-1)*100+模拟分析!$G$12/100)))) -> 1.9671296 | L9: =IF($B9="",0,IF($D9-L$2/365<=0,0,(IF(模拟分析!$I$12="到期平移法",[1]!B_CALC_CURVE_CHINABOND($I$1,$G$1,$D9-L$2/365)+模拟分析!$G$12/100,(((1+[1]!B_CALC_CURVE_CHINABOND($I$1,$G$1,$D9)/100)^$D9/(1+L$3/100)^(L$2/365))^(1/($D9-L$2/365))-1)*100+模拟分析!$G$12/100)))) -> 1.9953593 | ... N9: =IF($B9="",0,IF($D9-N$2/365<=0,0,(IF(模拟分析!$I$12="到期平移法",[1]!B_CALC_CURVE_CHINABOND($I$1,$G$1,$D9-N$2/365)+模拟分析!$G$12/100,(((1+[1]!B_CALC_CURVE_CHINABOND($I$1,$G$1,$D9)/100)^$D9/(1+N$3/100)^(N$2/365))^(1/($D9-N$2/365))-1)*100+模拟分析!$G$12/100)))) -> 2.0750811 | O9: =IF(C9="","",C9/((1+E9/100)^(D9-21/365))) -> 1.3279944
B10: =IF(B9="","",IF(B9<$E$1,[1]!b_anal_nxcupn($C$1,B9+1),"")) -> 2026-11-15 | C10: =IF(B10="",0,IF(模拟分析!$K$9=0,[1]!b_anal_dailycf($C$1,B10),IF(模拟分析!$I$11="否",[1]!b_anal_dailycf($C$1,B10),IF(B10<模拟分析!$K$12,[1]!b_anal_dailycf($C$1,B10),IF(B10=模拟分析!$K$12,[1]!b_anal_dailycf($C$1,B10)+模拟分析!$K$11,0))))) -> 1.38 | D10: =IF(B10="",0,(-TODAY()+B10)/365) -> 2.5808219 | E10: =IF($B10="",0,IF($D10-E$2/365<=0,0,(IF(模拟分析!$I$12="到期平移法",[1]!B_CALC_CURVE_CHINABOND($I$1,$G$1,$D10-E$2/365)+模拟分析!$G$12/100,(((1+[1]!B_CALC_CURVE_CHINABOND($I$1,$G$1,$D10)/100)^$D10/(1+E$3/100)^(E$2/365))^(1/($D10-E$2/365))-1)*100+模拟分析!$G$12/100)))) -> 1.9930912 | F10: =IF($B10="",0,IF($D10-F$2/365<=0,0,(IF(模拟分析!$I$12="到期平移法",[1]!B_CALC_CURVE_CHINABOND($I$1,$G$1,$D10-F$2/365)+模拟分析!$G$12/100,(((1+[1]!B_CALC_CURVE_CHINABOND($I$1,$G$1,$D10)/100)^$D10/(1+F$3/100)^(F$2/365))^(1/($D10-F$2/365))-1)*100+模拟分析!$G$12/100)))) -> 1.9965173 | G10: =IF($B10="",0,IF($D10-G$2/365<=0,0,(IF(模拟分析!$I$12="到期平移法",[1]!B_CALC_CURVE_CHINABOND($I$1,$G$1,$D10-G$2/365)+模拟分析!$G$12/100,(((1+[1]!B_CALC_CURVE_CHINABOND($I$1,$G$1,$D10)/100)^$D10/(1+G$3/100)^(G$2/365))^(1/($D10-G$2/365))-1)*100+模拟分析!$G$12/100)))) -> 2.0001934 | H10: =IF($B10="",0,IF($D10-H$2/365<=0,0,(IF(模拟分析!$I$12="到期平移法",[1]!B_CALC_CURVE_CHINABOND($I$1,$G$1,$D10-H$2/365)+模拟分析!$G$12/100,(((1+[1]!B_CALC_CURVE_CHINABOND($I$1,$G$1,$D10)/100)^$D10/(1+H$3/100)^(H$2/365))^(1/($D10-H$2/365))-1)*100+模拟分析!$G$12/100)))) -> 2.0035165 | I10: =IF($B10="",0,IF($D10-I$2/365<=0,0,(IF(模拟分析!$I$12="到期平移法",[1]!B_CALC_CURVE_CHINABOND($I$1,$G$1,$D10-I$2/365)+模拟分析!$G$12/100,(((1+[1]!B_CALC_CURVE_CHINABOND($I$1,$G$1,$D10)/100)^$D10/(1+I$3/100)^(I$2/365))^(1/($D10-I$2/365))-1)*100+模拟分析!$G$12/100)))) -> 2.0073109 | J10: =IF($B10="",0,IF($D10-J$2/365<=0,0,(IF(模拟分析!$I$12="到期平移法",[1]!B_CALC_CURVE_CHINABOND($I$1,$G$1,$D10-J$2/365)+模拟分析!$G$12/100,(((1+[1]!B_CALC_CURVE_CHINABOND($I$1,$G$1,$D10)/100)^$D10/(1+J$3/100)^(J$2/365))^(1/($D10-J$2/365))-1)*100+模拟分析!$G$12/100)))) -> 2.0213837 | K10: =IF($B10="",0,IF($D10-K$2/365<=0,0,(IF(模拟分析!$I$12="到期平移法",[1]!B_CALC_CURVE_CHINABOND($I$1,$G$1,$D10-K$2/365)+模拟分析!$G$12/100,(((1+[1]!B_CALC_CURVE_CHINABOND($I$1,$G$1,$D10)/100)^$D10/(1+K$3/100)^(K$2/365))^(1/($D10-K$2/365))-1)*100+模拟分析!$G$12/100)))) -> 2.0371294 | L10: =IF($B10="",0,IF($D10-L$2/365<=0,0,(IF(模拟分析!$I$12="到期平移法",[1]!B_CALC_CURVE_CHINABOND($I$1,$G$1,$D10-L$2/365)+模拟分析!$G$12/100,(((1+[1]!B_CALC_CURVE_CHINABOND($I$1,$G$1,$D10)/100)^$D10/(1+L$3/100)^(L$2/365))^(1/($D10-L$2/365))-1)*100+模拟分析!$G$12/100)))) -> 2.064121 | ... N10: =IF($B10="",0,IF($D10-N$2/365<=0,0,(IF(模拟分析!$I$12="到期平移法",[1]!B_CALC_CURVE_CHINABOND($I$1,$G$1,$D10-N$2/365)+模拟分析!$G$12/100,(((1+[1]!B_CALC_CURVE_CHINABOND($I$1,$G$1,$D10)/100)^$D10/(1+N$3/100)^(N$2/365))^(1/($D10-N$2/365))-1)*100+模拟分析!$G$12/100)))) -> 2.1440973 | O10: =IF(C10="","",C10/((1+E10/100)^(D10-21/365))) -> 1.3129634
B11: =IF(B10="","",IF(B10<$E$1,[1]!b_anal_nxcupn($C$1,B10+1),"")) -> 2027-05-15 | C11: =IF(B11="",0,IF(模拟分析!$K$9=0,[1]!b_anal_dailycf($C$1,B11),IF(模拟分析!$I$11="否",[1]!b_anal_dailycf($C$1,B11),IF(B11<模拟分析!$K$12,[1]!b_anal_dailycf($C$1,B11),IF(B11=模拟分析!$K$12,[1]!b_anal_dailycf($C$1,B11)+模拟分析!$K$11,0))))) -> 1.38 | D11: =IF(B11="",0,(-TODAY()+B11)/365) -> 3.0767123 | E11: =IF($B11="",0,IF($D11-E$2/365<=0,0,(IF(模拟分析!$I$12="到期平移法",[1]!B_CALC_CURVE_CHINABOND($I$1,$G$1,$D11-E$2/365)+模拟分析!$G$12/100,(((1+[1]!B_CALC_CURVE_CHINABOND($I$1,$G$1,$D11)/100)^$D11/(1+E$3/100)^(E$2/365))^(1/($D11-E$2/365))-1)*100+模拟分析!$G$12/100)))) -> 2.0607353 | F11: =IF($B11="",0,IF($D11-F$2/365<=0,0,(IF(模拟分析!$I$12="到期平移法",[1]!B_CALC_CURVE_CHINABOND($I$1,$G$1,$D11-F$2/365)+模拟分析!$G$12/100,(((1+[1]!B_CALC_CURVE_CHINABOND($I$1,$G$1,$D11)/100)^$D11/(1+F$3/100)^(F$2/365))^(1/($D11-F$2/365))-1)*100+模拟分析!$G$12/100)))) -> 2.0639714 | G11: =IF($B11="",0,IF($D11-G$2/365<=0,0,(IF(模拟分析!$I$12="到期平移法",[1]!B_CALC_CURVE_CHINABOND($I$1,$G$1,$D11-G$2/365)+模拟分析!$G$12/100,(((1+[1]!B_CALC_CURVE_CHINABOND($I$1,$G$1,$D11)/100)^$D11/(1+G$3/100)^(G$2/365))^(1/($D11-G$2/365))-1)*100+模拟分析!$G$12/100)))) -> 2.0674755 | H11: =IF($B11="",0,IF($D11-H$2/365<=0,0,(IF(模拟分析!$I$12="到期平移法",[1]!B_CALC_CURVE_CHINABOND($I$1,$G$1,$D11-H$2/365)+模拟分析!$G$12/100,(((1+[1]!B_CALC_CURVE_CHINABOND($I$1,$G$1,$D11)/100)^$D11/(1+H$3/100)^(H$2/365))^(1/($D11-H$2/365))-1)*100+模拟分析!$G$12/100)))) -> 2.0706822 | I11: =IF($B11="",0,IF($D11-I$2/365<=0,0,(IF(模拟分析!$I$12="到期平移法",[1]!B_CALC_CURVE_CHINABOND($I$1,$G$1,$D11-I$2/365)+模拟分析!$G$12/100,(((1+[1]!B_CALC_CURVE_CHINABOND($I$1,$G$1,$D11)/100)^$D11/(1+I$3/100)^(I$2/365))^(1/($D11-I$2/365))-1)*100+模拟分析!$G$12/100)))) -> 2.0744035 | J11: =IF($B11="",0,IF($D11-J$2/365<=0,0,(IF(模拟分析!$I$12="到期平移法",[1]!B_CALC_CURVE_CHINABOND($I$1,$G$1,$D11-J$2/365)+模拟分析!$G$12/100,(((1+[1]!B_CALC_CURVE_CHINABOND($I$1,$G$1,$D11)/100)^$D11/(1+J$3/100)^(J$2/365))^(1/($D11-J$2/365))-1)*100+模拟分析!$G$12/100)))) -> 2.087982 | K11: =IF($B11="",0,IF($D11-K$2/365<=0,0,(IF(模拟分析!$I$12="到期平移法",[1]!B_CALC_CURVE_CHINABOND($I$1,$G$1,$D11-K$2/365)+模拟分析!$G$12/100,(((1+[1]!B_CALC_CURVE_CHINABOND($I$1,$G$1,$D11)/100)^$D11/(1+K$3/100)^(K$2/365))^(1/($D11-K$2/365))-1)*100+模拟分析!$G$12/100)))) -> 2.1029121 | L11: =IF($B11="",0,IF($D11-L$2/365<=0,0,(IF(模拟分析!$I$12="到期平移法",[1]!B_CALC_CURVE_CHINABOND($I$1,$G$1,$D11-L$2/365)+模拟分析!$G$12/100,(((1+[1]!B_CALC_CURVE_CHINABOND($I$1,$G$1,$D11)/100)^$D11/(1+L$3/100)^(L$2/365))^(1/($D11-L$2/365))-1)*100+模拟分析!$G$12/100)))) -> 2.1289551 | ... N11: =IF($B11="",0,IF($D11-N$2/365<=0,0,(IF(模拟分析!$I$12="到期平移法",[1]!B_CALC_CURVE_CHINABOND($I$1,$G$1,$D11-N$2/365)+模拟分析!$G$12/100,(((1+[1]!B_CALC_CURVE_CHINABOND($I$1,$G$1,$D11)/100)^$D11/(1+N$3/100)^(N$2/365))^(1/($D11-N$2/365))-1)*100+模拟分析!$G$12/100)))) -> 2.2082752 | O11: =IF(C11="","",C11/((1+E11/100)^(D11-21/365))) -> 1.2975769
B12: =IF(B11="","",IF(B11<$E$1,[1]!b_anal_nxcupn($C$1,B11+1),"")) -> 2027-11-15 | C12: =IF(B12="",0,IF(模拟分析!$K$9=0,[1]!b_anal_dailycf($C$1,B12),IF(模拟分析!$I$11="否",[1]!b_anal_dailycf($C$1,B12),IF(B12<模拟分析!$K$12,[1]!b_anal_dailycf($C$1,B12),IF(B12=模拟分析!$K$12,[1]!b_anal_dailycf($C$1,B12)+模拟分析!$K$11,0))))) -> 1.38 | D12: =IF(B12="",0,(-TODAY()+B12)/365) -> 3.5808219 | E12: =IF($B12="",0,IF($D12-E$2/365<=0,0,(IF(模拟分析!$I$12="到期平移法",[1]!B_CALC_CURVE_CHINABOND($I$1,$G$1,$D12-E$2/365)+模拟分析!$G$12/100,(((1+[1]!B_CALC_CURVE_CHINABOND($I$1,$G$1,$D12)/100)^$D12/(1+E$3/100)^(E$2/365))^(1/($D12-E$2/365))-1)*100+模拟分析!$G$12/100)))) -> 2.1027436 | F12: =IF($B12="",0,IF($D12-F$2/365<=0,0,(IF(模拟分析!$I$12="到期平移法",[1]!B_CALC_CURVE_CHINABOND($I$1,$G$1,$D12-F$2/365)+模拟分析!$G$12/100,(((1+[1]!B_CALC_CURVE_CHINABOND($I$1,$G$1,$D12)/100)^$D12/(1+F$3/100)^(F$2/365))^(1/($D12-F$2/365))-1)*100+模拟分析!$G$12/100)))) -> 2.1057167 | G12: =IF($B12="",0,IF($D12-G$2/365<=0,0,(IF(模拟分析!$I$12="到期平移法",[1]!B_CALC_CURVE_CHINABOND($I$1,$G$1,$D12-G$2/365)+模拟分析!$G$12/100,(((1+[1]!B_CALC_CURVE_CHINABOND($I$1,$G$1,$D12)/100)^$D12/(1+G$3/100)^(G$2/365))^(1/($D12-G$2/365))-1)*100+模拟分析!$G$12/100)))) -> 2.1089495 | H12: =IF($B12="",0,IF($D12-H$2/365<=0,0,(IF(模拟分析!$I$12="到期平移法",[1]!B_CALC_CURVE_CHINABOND($I$1,$G$1,$D12-H$2/365)+模拟分析!$G$12/100,(((1+[1]!B_CALC_CURVE_CHINABOND($I$1,$G$1,$D12)/100)^$D12/(1+H$3/100)^(H$2/365))^(1/($D12-H$2/365))-1)*100+模拟分析!$G$12/100)))) -> 2.1119242 | I12: =IF($B12="",0,IF($D12-I$2/365<=0,0,(IF(模拟分析!$I$12="到期平移法",[1]!B_CALC_CURVE_CHINABOND($I$1,$G$1,$D12-I$2/365)+模拟分析!$G$12/100,(((1+[1]!B_CALC_CURVE_CHINABOND($I$1,$G$1,$D12)/100)^$D12/(1+I$3/100)^(I$2/365))^(1/($D12-I$2/365))-1)*100+模拟分析!$G$12/100)))) -> 2.1154014 | J12: =IF($B12="",0,IF($D12-J$2/365<=0,0,(IF(模拟分析!$I$12="到期平移法",[1]!B_CALC_CURVE_CHINABOND($I$1,$G$1,$D12-J$2/365)+模拟分析!$G$12/100,(((1+[1]!B_CALC_CURVE_CHINABOND($I$1,$G$1,$D12)/100)^$D12/(1+J$3/100)^(J$2/365))^(1/($D12-J$2/365))-1)*100+模拟分析!$G$12/100)))) -> 2.1279675 | K12: =IF($B12="",0,IF($D12-K$2/365<=0,0,(IF(模拟分析!$I$12="到期平移法",[1]!B_CALC_CURVE_CHINABOND($I$1,$G$1,$D12-K$2/365)+模拟分析!$G$12/100,(((1+[1]!B_CALC_CURVE_CHINABOND($I$1,$G$1,$D12)/100)^$D12/(1+K$3/100)^(K$2/365))^(1/($D12-K$2/365))-1)*100+模拟分析!$G$12/100)))) -> 2.1416311 | L12: =IF($B12="",0,IF($D12-L$2/365<=0,0,(IF(模拟分析!$I$12="到期平移法",[1]!B_CALC_CURVE_CHINABOND($I$1,$G$1,$D12-L$2/365)+模拟分析!$G$12/100,(((1+[1]!B_CALC_CURVE_CHINABOND($I$1,$G$1,$D12)/100)^$D12/(1+L$3/100)^(L$2/365))^(1/($D12-L$2/365))-1)*100+模拟分析!$G$12/100)))) -> 2.165549 | ... N12: =IF($B12="",0,IF($D12-N$2/365<=0,0,(IF(模拟分析!$I$12="到期平移法",[1]!B_CALC_CURVE_CHINABOND($I$1,$G$1,$D12-N$2/365)+模拟分析!$G$12/100,(((1+[1]!B_CALC_CURVE_CHINABOND($I$1,$G$1,$D12)/100)^$D12/(1+N$3/100)^(N$2/365))^(1/($D12-N$2/365))-1)*100+模拟分析!$G$12/100)))) -> 2.2377528 | O12: =IF(C12="","",C12/((1+E12/100)^(D12-21/365))) -> 1.2824419
B13: =IF(B12="","",IF(B12<$E$1,[1]!b_anal_nxcupn($C$1,B12+1),"")) -> 2028-05-15 | C13: =IF(B13="",0,IF(模拟分析!$K$9=0,[1]!b_anal_dailycf($C$1,B13),IF(模拟分析!$I$11="否",[1]!b_anal_dailycf($C$1,B13),IF(B13<模拟分析!$K$12,[1]!b_anal_dailycf($C$1,B13),IF(B13=模拟分析!$K$12,[1]!b_anal_dailycf($C$1,B13)+模拟分析!$K$11,0))))) -> 1.38 | D13: =IF(B13="",0,(-TODAY()+B13)/365) -> 4.0794521 | E13: =IF($B13="",0,IF($D13-E$2/365<=0,0,(IF(模拟分析!$I$12="到期平移法",[1]!B_CALC_CURVE_CHINABOND($I$1,$G$1,$D13-E$2/365)+模拟分析!$G$12/100,(((1+[1]!B_CALC_CURVE_CHINABOND($I$1,$G$1,$D13)/100)^$D13/(1+E$3/100)^(E$2/365))^(1/($D13-E$2/365))-1)*100+模拟分析!$G$12/100)))) -> 2.1242872 | F13: =IF($B13="",0,IF($D13-F$2/365<=0,0,(IF(模拟分析!$I$12="到期平移法",[1]!B_CALC_CURVE_CHINABOND($I$1,$G$1,$D13-F$2/365)+模拟分析!$G$12/100,(((1+[1]!B_CALC_CURVE_CHINABOND($I$1,$G$1,$D13)/100)^$D13/(1+F$3/100)^(F$2/365))^(1/($D13-F$2/365))-1)*100+模拟分析!$G$12/100)))) -> 2.126983 | G13: =IF($B13="",0,IF($D13-G$2/365<=0,0,(IF(模拟分析!$I$12="到期平移法",[1]!B_CALC_CURVE_CHINABOND($I$1,$G$1,$D13-G$2/365)+模拟分析!$G$12/100,(((1+[1]!B_CALC_CURVE_CHINABOND($I$1,$G$1,$D13)/100)^$D13/(1+G$3/100)^(G$2/365))^(1/($D13-G$2/365))-1)*100+模拟分析!$G$12/100)))) -> 2.1299183 | H13: =IF($B13="",0,IF($D13-H$2/365<=0,0,(IF(模拟分析!$I$12="到期平移法",[1]!B_CALC_CURVE_CHINABOND($I$1,$G$1,$D13-H$2/365)+模拟分析!$G$12/100,(((1+[1]!B_CALC_CURVE_CHINABOND($I$1,$G$1,$D13)/100)^$D13/(1+H$3/100)^(H$2/365))^(1/($D13-H$2/365))-1)*100+模拟分析!$G$12/100)))) -> 2.1326249 | I13: =IF($B13="",0,IF($D13-I$2/365<=0,0,(IF(模拟分析!$I$12="到期平移法",[1]!B_CALC_CURVE_CHINABOND($I$1,$G$1,$D13-I$2/365)+模拟分析!$G$12/100,(((1+[1]!B_CALC_CURVE_CHINABOND($I$1,$G$1,$D13)/100)^$D13/(1+I$3/100)^(I$2/365))^(1/($D13-I$2/365))-1)*100+模拟分析!$G$12/100)))) -> 2.1357966 | J13: =IF($B13="",0,IF($D13-J$2/365<=0,0,(IF(模拟分析!$I$12="到期平移法",[1]!B_CALC_CURVE_CHINABOND($I$1,$G$1,$D13-J$2/365)+模拟分析!$G$12/100,(((1+[1]!B_CALC_CURVE_CHINABOND($I$1,$G$1,$D13)/100)^$D13/(1+J$3/100)^(J$2/365))^(1/($D13-J$2/365))-1)*100+模拟分析!$G$12/100)))) -> 2.1471926 | K13: =IF($B13="",0,IF($D13-K$2/365<=0,0,(IF(模拟分析!$I$12="到期平移法",[1]!B_CALC_CURVE_CHINABOND($I$1,$G$1,$D13-K$2/365)+模拟分析!$G$12/100,(((1+[1]!B_CALC_CURVE_CHINABOND($I$1,$G$1,$D13)/100)^$D13/(1+K$3/100)^(K$2/365))^(1/($D13-K$2/365))-1)*100+模拟分析!$G$12/100)))) -> 2.1594932 | L13: =IF($B13="",0,IF($D13-L$2/365<=0,0,(IF(模拟分析!$I$12="到期平移法",[1]!B_CALC_CURVE_CHINABOND($I$1,$G$1,$D13-L$2/365)+模拟分析!$G$12/100,(((1+[1]!B_CALC_CURVE_CHINABOND($I$1,$G$1,$D13)/100)^$D13/(1+L$3/100)^(L$2/365))^(1/($D13-L$2/365))-1)*100+模拟分析!$G$12/100)))) -> 2.180964 | ... N13: =IF($B13="",0,IF($D13-N$2/365<=0,0,(IF(模拟分析!$I$12="到期平移法",[1]!B_CALC_CURVE_CHINABOND($I$1,$G$1,$D13-N$2/365)+模拟分析!$G$12/100,(((1+[1]!B_CALC_CURVE_CHINABOND($I$1,$G$1,$D13)/100)^$D13/(1+N$3/100)^(N$2/365))^(1/($D13-N$2/365))-1)*100+模拟分析!$G$12/100)))) -> 2.2444327 | O13: =IF(C13="","",C13/((1+E13/100)^(D13-21/365))) -> 1.2681273
B14: =IF(B13="","",IF(B13<$E$1,[1]!b_anal_nxcupn($C$1,B13+1),"")) -> 2028-11-15 | C14: =IF(B14="",0,IF(模拟分析!$K$9=0,[1]!b_anal_dailycf($C$1,B14),IF(模拟分析!$I$11="否",[1]!b_anal_dailycf($C$1,B14),IF(B14<模拟分析!$K$12,[1]!b_anal_dailycf($C$1,B14),IF(B14=模拟分析!$K$12,[1]!b_anal_dailycf($C$1,B14)+模拟分析!$K$11,0))))) -> 1.38 | D14: =IF(B14="",0,(-TODAY()+B14)/365) -> 4.5835616 | E14: =IF($B14="",0,IF($D14-E$2/365<=0,0,(IF(模拟分析!$I$12="到期平移法",[1]!B_CALC_CURVE_CHINABOND($I$1,$G$1,$D14-E$2/365)+模拟分析!$G$12/100,(((1+[1]!B_CALC_CURVE_CHINABOND($I$1,$G$1,$D14)/100)^$D14/(1+E$3/100)^(E$2/365))^(1/($D14-E$2/365))-1)*100+模拟分析!$G$12/100)))) -> 2.1402648 | F14: =IF($B14="",0,IF($D14-F$2/365<=0,0,(IF(模拟分析!$I$12="到期平移法",[1]!B_CALC_CURVE_CHINABOND($I$1,$G$1,$D14-F$2/365)+模拟分析!$G$12/100,(((1+[1]!B_CALC_CURVE_CHINABOND($I$1,$G$1,$D14)/100)^$D14/(1+F$3/100)^(F$2/365))^(1/($D14-F$2/365))-1)*100+模拟分析!$G$12/100)))) -> 2.1427208 | G14: =IF($B14="",0,IF($D14-G$2/365<=0,0,(IF(模拟分析!$I$12="到期平移法",[1]!B_CALC_CURVE_CHINABOND($I$1,$G$1,$D14-G$2/365)+模拟分析!$G$12/100,(((1+[1]!B_CALC_CURVE_CHINABOND($I$1,$G$1,$D14)/100)^$D14/(1+G$3/100)^(G$2/365))^(1/($D14-G$2/365))-1)*100+模拟分析!$G$12/100)))) -> 2.1453974 | H14: =IF($B14="",0,IF($D14-H$2/365<=0,0,(IF(模拟分析!$I$12="到期平移法",[1]!B_CALC_CURVE_CHINABOND($I$1,$G$1,$D14-H$2/365)+模拟分析!$G$12/100,(((1+[1]!B_CALC_CURVE_CHINABOND($I$1,$G$1,$D14)/100)^$D14/(1+H$3/100)^(H$2/365))^(1/($D14-H$2/365))-1)*100+模拟分析!$G$12/100)))) -> 2.1478684 | I14: =IF($B14="",0,IF($D14-I$2/365<=0,0,(IF(模拟分析!$I$12="到期平移法",[1]!B_CALC_CURVE_CHINABOND($I$1,$G$1,$D14-I$2/365)+模拟分析!$G$12/100,(((1+[1]!B_CALC_CURVE_CHINABOND($I$1,$G$1,$D14)/100)^$D14/(1+I$3/100)^(I$2/365))^(1/($D14-I$2/365))-1)*100+模拟分析!$G$12/100)))) -> 2.1507689 | J14: =IF($B14="",0,IF($D14-J$2/365<=0,0,(IF(模拟分析!$I$12="到期平移法",[1]!B_CALC_CURVE_CHINABOND($I$1,$G$1,$D14-J$2/365)+模拟分析!$G$12/100,(((1+[1]!B_CALC_CURVE_CHINABOND($I$1,$G$1,$D14)/100)^$D14/(1+J$3/100)^(J$2/365))^(1/($D14-J$2/365))-1)*100+模拟分析!$G$12/100)))) -> 2.1611448 | K14: =IF($B14="",0,IF($D14-K$2/365<=0,0,(IF(模拟分析!$I$12="到期平移法",[1]!B_CALC_CURVE_CHINABOND($I$1,$G$1,$D14-K$2/365)+模拟分析!$G$12/100,(((1+[1]!B_CALC_CURVE_CHINABOND($I$1,$G$1,$D14)/100)^$D14/(1+K$3/100)^(K$2/365))^(1/($D14-K$2/365))-1)*100+模拟分析!$G$12/100)))) -> 2.1722815 | L14: =IF($B14="",0,IF($D14-L$2/365<=0,0,(IF(模拟分析!$I$12="到期平移法",[1]!B_CALC_CURVE_CHINABOND($I$1,$G$1,$D14-L$2/365)+模拟分析!$G$12/100,(((1+[1]!B_CALC_CURVE_CHINABOND($I$1,$G$1,$D14)/100)^$D14/(1+L$3/100)^(L$2/365))^(1/($D14-L$2/365))-1)*100+模拟分析!$G$12/100)))) -> 2.1916644 | ... N14: =IF($B14="",0,IF($D14-N$2/365<=0,0,(IF(模拟分析!$I$12="到期平移法",[1]!B_CALC_CURVE_CHINABOND($I$1,$G$1,$D14-N$2/365)+模拟分析!$G$12/100,(((1+[1]!B_CALC_CURVE_CHINABOND($I$1,$G$1,$D14)/100)^$D14/(1+N$3/100)^(N$2/365))^(1/($D14-N$2/365))-1)*100+模拟分析!$G$12/100)))) -> 2.247968 | O14: =IF(C14="","",C14/((1+E14/100)^(D14-21/365))) -> 1.2538723
B15: =IF(B14="","",IF(B14<$E$1,[1]!b_anal_nxcupn($C$1,B14+1),"")) -> 2029-05-15 | C15: =IF(B15="",0,IF(模拟分析!$K$9=0,[1]!b_anal_dailycf($C$1,B15),IF(模拟分析!$I$11="否",[1]!b_anal_dailycf($C$1,B15),IF(B15<模拟分析!$K$12,[1]!b_anal_dailycf($C$1,B15),IF(B15=模拟分析!$K$12,[1]!b_anal_dailycf($C$1,B15)+模拟分析!$K$11,0))))) -> 1.38 | D15: =IF(B15="",0,(-TODAY()+B15)/365) -> 5.0794521 | E15: =IF($B15="",0,IF($D15-E$2/365<=0,0,(IF(模拟分析!$I$12="到期平移法",[1]!B_CALC_CURVE_CHINABOND($I$1,$G$1,$D15-E$2/365)+模拟分析!$G$12/100,(((1+[1]!B_CALC_CURVE_CHINABOND($I$1,$G$1,$D15)/100)^$D15/(1+E$3/100)^(E$2/365))^(1/($D15-E$2/365))-1)*100+模拟分析!$G$12/100)))) -> 2.1640418 | F15: =IF($B15="",0,IF($D15-F$2/365<=0,0,(IF(模拟分析!$I$12="到期平移法",[1]!B_CALC_CURVE_CHINABOND($I$1,$G$1,$D15-F$2/365)+模拟分析!$G$12/100,(((1+[1]!B_CALC_CURVE_CHINABOND($I$1,$G$1,$D15)/100)^$D15/(1+F$3/100)^(F$2/365))^(1/($D15-F$2/365))-1)*100+模拟分析!$G$12/100)))) -> 2.1663349 | G15: =IF($B15="",0,IF($D15-G$2/365<=0,0,(IF(模拟分析!$I$12="到期平移法",[1]!B_CALC_CURVE_CHINABOND($I$1,$G$1,$D15-G$2/365)+模拟分析!$G$12/100,(((1+[1]!B_CALC_CURVE_CHINABOND($I$1,$G$1,$D15)/100)^$D15/(1+G$3/100)^(G$2/365))^(1/($D15-G$2/365))-1)*100+模拟分析!$G$12/100)))) -> 2.1688386 | H15: =IF($B15="",0,IF($D15-H$2/365<=0,0,(IF(模拟分析!$I$12="到期平移法",[1]!B_CALC_CURVE_CHINABOND($I$1,$G$1,$D15-H$2/365)+模拟分析!$G$12/100,(((1+[1]!B_CALC_CURVE_CHINABOND($I$1,$G$1,$D15)/100)^$D15/(1+H$3/100)^(H$2/365))^(1/($D15-H$2/365))-1)*100+模拟分析!$G$12/100)))) -> 2.1711557 | I15: =IF($B15="",0,IF($D15-I$2/365<=0,0,(IF(模拟分析!$I$12="到期平移法",[1]!B_CALC_CURVE_CHINABOND($I$1,$G$1,$D15-I$2/365)+模拟分析!$G$12/100,(((1+[1]!B_CALC_CURVE_CHINABOND($I$1,$G$1,$D15)/100)^$D15/(1+I$3/100)^(I$2/365))^(1/($D15-I$2/365))-1)*100+模拟分析!$G$12/100)))) -> 2.1738838 | J15: =IF($B15="",0,IF($D15-J$2/365<=0,0,(IF(模拟分析!$I$12="到期平移法",[1]!B_CALC_CURVE_CHINABOND($I$1,$G$1,$D15-J$2/365)+模拟分析!$G$12/100,(((1+[1]!B_CALC_CURVE_CHINABOND($I$1,$G$1,$D15)/100)^$D15/(1+J$3/100)^(J$2/365))^(1/($D15-J$2/365))-1)*100+模拟分析!$G$12/100)))) -> 2.1836016 | K15: =IF($B15="",0,IF($D15-K$2/365<=0,0,(IF(模拟分析!$I$12="到期平移法",[1]!B_CALC_CURVE_CHINABOND($I$1,$G$1,$D15-K$2/365)+模拟分析!$G$12/100,(((1+[1]!B_CALC_CURVE_CHINABOND($I$1,$G$1,$D15)/100)^$D15/(1+K$3/100)^(K$2/365))^(1/($D15-K$2/365))-1)*100+模拟分析!$G$12/100)))) -> 2.1939797 | L15: =IF($B15="",0,IF($D15-L$2/365<=0,0,(IF(模拟分析!$I$12="到期平移法",[1]!B_CALC_CURVE_CHINABOND($I$1,$G$1,$D15-L$2/365)+模拟分析!$G$12/100,(((1+[1]!B_CALC_CURVE_CHINABOND($I$1,$G$1,$D15)/100)^$D15/(1+L$3/100)^(L$2/365))^(1/($D15-L$2/365))-1)*100+模拟分析!$G$12/100)))) -> 2.2120715 | ... N15: =IF($B15="",0,IF($D15-N$2/365<=0,0,(IF(模拟分析!$I$12="到期平移法",[1]!B_CALC_CURVE_CHINABOND($I$1,$G$1,$D15-N$2/365)+模拟分析!$G$12/100,(((1+[1]!B_CALC_CURVE_CHINABOND($I$1,$G$1,$D15)/100)^$D15/(1+N$3/100)^(N$2/365))^(1/($D15-N$2/365))-1)*100+模拟分析!$G$12/100)))) -> 2.2644876 | O15: =IF(C15="","",C15/((1+E15/100)^(D15-21/365))) -> 1.2393243
B16: =IF(B15="","",IF(B15<$E$1,[1]!b_anal_nxcupn($C$1,B15+1),"")) -> 2029-11-15 | C16: =IF(B16="",0,IF(模拟分析!$K$9=0,[1]!b_anal_dailycf($C$1,B16),IF(模拟分析!$I$11="否",[1]!b_anal_dailycf($C$1,B16),IF(B16<模拟分析!$K$12,[1]!b_anal_dailycf($C$1,B16),IF(B16=模拟分析!$K$12,[1]!b_anal_dailycf($C$1,B16)+模拟分析!$K$11,0))))) -> 1.38 | D16: =IF(B16="",0,(-TODAY()+B16)/365) -> 5.5835616 | E16: =IF($B16="",0,IF($D16-E$2/365<=0,0,(IF(模拟分析!$I$12="到期平移法",[1]!B_CALC_CURVE_CHINABOND($I$1,$G$1,$D16-E$2/365)+模拟分析!$G$12/100,(((1+[1]!B_CALC_CURVE_CHINABOND($I$1,$G$1,$D16)/100)^$D16/(1+E$3/100)^(E$2/365))^(1/($D16-E$2/365))-1)*100+模拟分析!$G$12/100)))) -> 2.1973418 | F16: =IF($B16="",0,IF($D16-F$2/365<=0,0,(IF(模拟分析!$I$12="到期平移法",[1]!B_CALC_CURVE_CHINABOND($I$1,$G$1,$D16-F$2/365)+模拟分析!$G$12/100,(((1+[1]!B_CALC_CURVE_CHINABOND($I$1,$G$1,$D16)/100)^$D16/(1+F$3/100)^(F$2/365))^(1/($D16-F$2/365))-1)*100+模拟分析!$G$12/100)))) -> 2.1995262 | G16: =IF($B16="",0,IF($D16-G$2/365<=0,0,(IF(模拟分析!$I$12="到期平移法",[1]!B_CALC_CURVE_CHINABOND($I$1,$G$1,$D16-G$2/365)+模拟分析!$G$12/100,(((1+[1]!B_CALC_CURVE_CHINABOND($I$1,$G$1,$D16)/100)^$D16/(1+G$3/100)^(G$2/365))^(1/($D16-G$2/365))-1)*100+模拟分析!$G$12/100)))) -> 2.2019178 | H16: =IF($B16="",0,IF($D16-H$2/365<=0,0,(IF(模拟分析!$I$12="到期平移法",[1]!B_CALC_CURVE_CHINABOND($I$1,$G$1,$D16-H$2/365)+模拟分析!$G$12/100,(((1+[1]!B_CALC_CURVE_CHINABOND($I$1,$G$1,$D16)/100)^$D16/(1+H$3/100)^(H$2/365))^(1/($D16-H$2/365))-1)*100+模拟分析!$G$12/100)))) -> 2.204139 | I16: =IF($B16="",0,IF($D16-I$2/365<=0,0,(IF(模拟分析!$I$12="到期平移法",[1]!B_CALC_CURVE_CHINABOND($I$1,$G$1,$D16-I$2/365)+模拟分析!$G$12/100,(((1+[1]!B_CALC_CURVE_CHINABOND($I$1,$G$1,$D16)/100)^$D16/(1+I$3/100)^(I$2/365))^(1/($D16-I$2/365))-1)*100+模拟分析!$G$12/100)))) -> 2.2067658 | J16: =IF($B16="",0,IF($D16-J$2/365<=0,0,(IF(模拟分析!$I$12="到期平移法",[1]!B_CALC_CURVE_CHINABOND($I$1,$G$1,$D16-J$2/365)+模拟分析!$G$12/100,(((1+[1]!B_CALC_CURVE_CHINABOND($I$1,$G$1,$D16)/100)^$D16/(1+J$3/100)^(J$2/365))^(1/($D16-J$2/365))-1)*100+模拟分析!$G$12/100)))) -> 2.2160813 | K16: =IF($B16="",0,IF($D16-K$2/365<=0,0,(IF(模拟分析!$I$12="到期平移法",[1]!B_CALC_CURVE_CHINABOND($I$1,$G$1,$D16-K$2/365)+模拟分析!$G$12/100,(((1+[1]!B_CALC_CURVE_CHINABOND($I$1,$G$1,$D16)/100)^$D16/(1+K$3/100)^(K$2/365))^(1/($D16-K$2/365))-1)*100+模拟分析!$G$12/100)))) -> 2.2259824 | L16: =IF($B16="",0,IF($D16-L$2/365<=0,0,(IF(模拟分析!$I$12="到期平移法",[1]!B_CALC_CURVE_CHINABOND($I$1,$G$1,$D16-L$2/365)+模拟分析!$G$12/100,(((1+[1]!B_CALC_CURVE_CHINABOND($I$1,$G$1,$D16)/100)^$D16/(1+L$3/100)^(L$2/365))^(1/($D16-L$2/365))-1)*100+模拟分析!$G$12/100)))) -> 2.2433333 | ... N16: =IF($B16="",0,IF($D16-N$2/365<=0,0,(IF(模拟分析!$I$12="到期平移法",[1]!B_CALC_CURVE_CHINABOND($I$1,$G$1,$D16-N$2/365)+模拟分析!$G$12/100,(((1+[1]!B_CALC_CURVE_CHINABOND($I$1,$G$1,$D16)/100)^$D16/(1+N$3/100)^(N$2/365))^(1/($D16-N$2/365))-1)*100+模拟分析!$G$12/100)))) -> 2.2940176 | O16: =IF(C16="","",C16/((1+E16/100)^(D16-21/365))) -> 1.2238145
B17: =IF(B16="","",IF(B16<$E$1,[1]!b_anal_nxcupn($C$1,B16+1),"")) -> 2030-05-15 | C17: =IF(B17="",0,IF(模拟分析!$K$9=0,[1]!b_anal_dailycf($C$1,B17),IF(模拟分析!$I$11="否",[1]!b_anal_dailycf($C$1,B17),IF(B17<模拟分析!$K$12,[1]!b_anal_dailycf($C$1,B17),IF(B17=模拟分析!$K$12,[1]!b_anal_dailycf($C$1,B17)+模拟分析!$K$11,0))))) -> 1.38 | D17: =IF(B17="",0,(-TODAY()+B17)/365) -> 6.0794521 | E17: =IF($B17="",0,IF($D17-E$2/365<=0,0,(IF(模拟分析!$I$12="到期平移法",[1]!B_CALC_CURVE_CHINABOND($I$1,$G$1,$D17-E$2/365)+模拟分析!$G$12/100,(((1+[1]!B_CALC_CURVE_CHINABOND($I$1,$G$1,$D17)/100)^$D17/(1+E$3/100)^(E$2/365))^(1/($D17-E$2/365))-1)*100+模拟分析!$G$12/100)))) -> 2.230825 | F17: =IF($B17="",0,IF($D17-F$2/365<=0,0,(IF(模拟分析!$I$12="到期平移法",[1]!B_CALC_CURVE_CHINABOND($I$1,$G$1,$D17-F$2/365)+模拟分析!$G$12/100,(((1+[1]!B_CALC_CURVE_CHINABOND($I$1,$G$1,$D17)/100)^$D17/(1+F$3/100)^(F$2/365))^(1/($D17-F$2/365))-1)*100+模拟分析!$G$12/100)))) -> 2.2329221 | G17: =IF($B17="",0,IF($D17-G$2/365<=0,0,(IF(模拟分析!$I$12="到期平移法",[1]!B_CALC_CURVE_CHINABOND($I$1,$G$1,$D17-G$2/365)+模拟分析!$G$12/100,(((1+[1]!B_CALC_CURVE_CHINABOND($I$1,$G$1,$D17)/100)^$D17/(1+G$3/100)^(G$2/365))^(1/($D17-G$2/365))-1)*100+模拟分析!$G$12/100)))) -> 2.2352242 | H17: =IF($B17="",0,IF($D17-H$2/365<=0,0,(IF(模拟分析!$I$12="到期平移法",[1]!B_CALC_CURVE_CHINABOND($I$1,$G$1,$D17-H$2/365)+模拟分析!$G$12/100,(((1+[1]!B_CALC_CURVE_CHINABOND($I$1,$G$1,$D17)/100)^$D17/(1+H$3/100)^(H$2/365))^(1/($D17-H$2/365))-1)*100+模拟分析!$G$12/100)))) -> 2.2373692 | I17: =IF($B17="",0,IF($D17-I$2/365<=0,0,(IF(模拟分析!$I$12="到期平移法",[1]!B_CALC_CURVE_CHINABOND($I$1,$G$1,$D17-I$2/365)+模拟分析!$G$12/100,(((1+[1]!B_CALC_CURVE_CHINABOND($I$1,$G$1,$D17)/100)^$D17/(1+I$3/100)^(I$2/365))^(1/($D17-I$2/365))-1)*100+模拟分析!$G$12/100)))) -> 2.2399163 | J17: =IF($B17="",0,IF($D17-J$2/365<=0,0,(IF(模拟分析!$I$12="到期平移法",[1]!B_CALC_CURVE_CHINABOND($I$1,$G$1,$D17-J$2/365)+模拟分析!$G$12/100,(((1+[1]!B_CALC_CURVE_CHINABOND($I$1,$G$1,$D17)/100)^$D17/(1+J$3/100)^(J$2/365))^(1/($D17-J$2/365))-1)*100+模拟分析!$G$12/100)))) -> 2.2489142 | K17: =IF($B17="",0,IF($D17-K$2/365<=0,0,(IF(模拟分析!$I$12="到期平移法",[1]!B_CALC_CURVE_CHINABOND($I$1,$G$1,$D17-K$2/365)+模拟分析!$G$12/100,(((1+[1]!B_CALC_CURVE_CHINABOND($I$1,$G$1,$D17)/100)^$D17/(1+K$3/100)^(K$2/365))^(1/($D17-K$2/365))-1)*100+模拟分析!$G$12/100)))) -> 2.2584392 | L17: =IF($B17="",0,IF($D17-L$2/365<=0,0,(IF(模拟分析!$I$12="到期平移法",[1]!B_CALC_CURVE_CHINABOND($I$1,$G$1,$D17-L$2/365)+模拟分析!$G$12/100,(((1+[1]!B_CALC_CURVE_CHINABOND($I$1,$G$1,$D17)/100)^$D17/(1+L$3/100)^(L$2/365))^(1/($D17-L$2/365))-1)*100+模拟分析!$G$12/100)))) -> 2.2752187 | ... N17: =IF($B17="",0,IF($D17-N$2/365<=0,0,(IF(模拟分析!$I$12="到期平移法",[1]!B_CALC_CURVE_CHINABOND($I$1,$G$1,$D17-N$2/365)+模拟分析!$G$12/100,(((1+[1]!B_CALC_CURVE_CHINABOND($I$1,$G$1,$D17)/100)^$D17/(1+N$3/100)^(N$2/365))^(1/($D17-N$2/365))-1)*100+模拟分析!$G$12/100)))) -> 2.3246679 | O17: =IF(C17="","",C17/((1+E17/100)^(D17-21/365))) -> 1.2083086
B18: =IF(B17="","",IF(B17<$E$1,[1]!b_anal_nxcupn($C$1,B17+1),"")) -> 2030-11-15 | C18: =IF(B18="",0,IF(模拟分析!$K$9=0,[1]!b_anal_dailycf($C$1,B18),IF(模拟分析!$I$11="否",[1]!b_anal_dailycf($C$1,B18),IF(B18<模拟分析!$K$12,[1]!b_anal_dailycf($C$1,B18),IF(B18=模拟分析!$K$12,[1]!b_anal_dailycf($C$1,B18)+模拟分析!$K$11,0))))) -> 1.38 | D18: =IF(B18="",0,(-TODAY()+B18)/365) -> 6.5835616 | E18: =IF($B18="",0,IF($D18-E$2/365<=0,0,(IF(模拟分析!$I$12="到期平移法",[1]!B_CALC_CURVE_CHINABOND($I$1,$G$1,$D18-E$2/365)+模拟分析!$G$12/100,(((1+[1]!B_CALC_CURVE_CHINABOND($I$1,$G$1,$D18)/100)^$D18/(1+E$3/100)^(E$2/365))^(1/($D18-E$2/365))-1)*100+模拟分析!$G$12/100)))) -> 2.2595395 | F18: =IF($B18="",0,IF($D18-F$2/365<=0,0,(IF(模拟分析!$I$12="到期平移法",[1]!B_CALC_CURVE_CHINABOND($I$1,$G$1,$D18-F$2/365)+模拟分析!$G$12/100,(((1+[1]!B_CALC_CURVE_CHINABOND($I$1,$G$1,$D18)/100)^$D18/(1+F$3/100)^(F$2/365))^(1/($D18-F$2/365))-1)*100+模拟分析!$G$12/100)))) -> 2.2615481 | G18: =IF($B18="",0,IF($D18-G$2/365<=0,0,(IF(模拟分析!$I$12="到期平移法",[1]!B_CALC_CURVE_CHINABOND($I$1,$G$1,$D18-G$2/365)+模拟分析!$G$12/100,(((1+[1]!B_CALC_CURVE_CHINABOND($I$1,$G$1,$D18)/100)^$D18/(1+G$3/100)^(G$2/365))^(1/($D18-G$2/365))-1)*100+模拟分析!$G$12/100)))) -> 2.2637574 | H18: =IF($B18="",0,IF($D18-H$2/365<=0,0,(IF(模拟分析!$I$12="到期平移法",[1]!B_CALC_CURVE_CHINABOND($I$1,$G$1,$D18-H$2/365)+模拟分析!$G$12/100,(((1+[1]!B_CALC_CURVE_CHINABOND($I$1,$G$1,$D18)/100)^$D18/(1+H$3/100)^(H$2/365))^(1/($D18-H$2/365))-1)*100+模拟分析!$G$12/100)))) -> 2.2658211 | I18: =IF($B18="",0,IF($D18-I$2/365<=0,0,(IF(模拟分析!$I$12="到期平移法",[1]!B_CALC_CURVE_CHINABOND($I$1,$G$1,$D18-I$2/365)+模拟分析!$G$12/100,(((1+[1]!B_CALC_CURVE_CHINABOND($I$1,$G$1,$D18)/100)^$D18/(1+I$3/100)^(I$2/365))^(1/($D18-I$2/365))-1)*100+模拟分析!$G$12/100)))) -> 2.2682792 | J18: =IF($B18="",0,IF($D18-J$2/365<=0,0,(IF(模拟分析!$I$12="到期平移法",[1]!B_CALC_CURVE_CHINABOND($I$1,$G$1,$D18-J$2/365)+模拟分析!$G$12/100,(((1+[1]!B_CALC_CURVE_CHINABOND($I$1,$G$1,$D18)/100)^$D18/(1+J$3/100)^(J$2/365))^(1/($D18-J$2/365))-1)*100+模拟分析!$G$12/100)))) -> 2.2769361 | K18: =IF($B18="",0,IF($D18-K$2/365<=0,0,(IF(模拟分析!$I$12="到期平移法",[1]!B_CALC_CURVE_CHINABOND($I$1,$G$1,$D18-K$2/365)+模拟分析!$G$12/100,(((1+[1]!B_CALC_CURVE_CHINABOND($I$1,$G$1,$D18)/100)^$D18/(1+K$3/100)^(K$2/365))^(1/($D18-K$2/365))-1)*100+模拟分析!$G$12/100)))) -> 2.2860693 | L18: =IF($B18="",0,IF($D18-L$2/365<=0,0,(IF(模拟分析!$I$12="到期平移法",[1]!B_CALC_CURVE_CHINABOND($I$1,$G$1,$D18-L$2/365)+模拟分析!$G$12/100,(((1+[1]!B_CALC_CURVE_CHINABOND($I$1,$G$1,$D18)/100)^$D18/(1+L$3/100)^(L$2/365))^(1/($D18-L$2/365))-1)*100+模拟分析!$G$12/100)))) -> 2.3022185 | ... N18: =IF($B18="",0,IF($D18-N$2/365<=0,0,(IF(模拟分析!$I$12="到期平移法",[1]!B_CALC_CURVE_CHINABOND($I$1,$G$1,$D18-N$2/365)+模拟分析!$G$12/100,(((1+[1]!B_CALC_CURVE_CHINABOND($I$1,$G$1,$D18)/100)^$D18/(1+N$3/100)^(N$2/365))^(1/($D18-N$2/365))-1)*100+模拟分析!$G$12/100)))) -> 2.3500641 | O18: =IF(C18="","",C18/((1+E18/100)^(D18-21/365))) -> 1.192756
B19: =IF(B18="","",IF(B18<$E$1,[1]!b_anal_nxcupn($C$1,B18+1),"")) -> 2031-05-15 | C19: =IF(B19="",0,IF(模拟分析!$K$9=0,[1]!b_anal_dailycf($C$1,B19),IF(模拟分析!$I$11="否",[1]!b_anal_dailycf($C$1,B19),IF(B19<模拟分析!$K$12,[1]!b_anal_dailycf($C$1,B19),IF(B19=模拟分析!$K$12,[1]!b_anal_dailycf($C$1,B19)+模拟分析!$K$11,0))))) -> 1.38 | D19: =IF(B19="",0,(-TODAY()+B19)/365) -> 7.0794521 | E19: =IF($B19="",0,IF($D19-E$2/365<=0,0,(IF(模拟分析!$I$12="到期平移法",[1]!B_CALC_CURVE_CHINABOND($I$1,$G$1,$D19-E$2/365)+模拟分析!$G$12/100,(((1+[1]!B_CALC_CURVE_CHINABOND($I$1,$G$1,$D19)/100)^$D19/(1+E$3/100)^(E$2/365))^(1/($D19-E$2/365))-1)*100+模拟分析!$G$12/100)))) -> 2.2770934 | F19: =IF($B19="",0,IF($D19-F$2/365<=0,0,(IF(模拟分析!$I$12="到期平移法",[1]!B_CALC_CURVE_CHINABOND($I$1,$G$1,$D19-F$2/365)+模拟分析!$G$12/100,(((1+[1]!B_CALC_CURVE_CHINABOND($I$1,$G$1,$D19)/100)^$D19/(1+F$3/100)^(F$2/365))^(1/($D19-F$2/365))-1)*100+模拟分析!$G$12/100)))) -> 2.2790021 | G19: =IF($B19="",0,IF($D19-G$2/365<=0,0,(IF(模拟分析!$I$12="到期平移法",[1]!B_CALC_CURVE_CHINABOND($I$1,$G$1,$D19-G$2/365)+模拟分析!$G$12/100,(((1+[1]!B_CALC_CURVE_CHINABOND($I$1,$G$1,$D19)/100)^$D19/(1+G$3/100)^(G$2/365))^(1/($D19-G$2/365))-1)*100+模拟分析!$G$12/100)))) -> 2.2811037 | H19: =IF($B19="",0,IF($D19-H$2/365<=0,0,(IF(模拟分析!$I$12="到期平移法",[1]!B_CALC_CURVE_CHINABOND($I$1,$G$1,$D19-H$2/365)+模拟分析!$G$12/100,(((1+[1]!B_CALC_CURVE_CHINABOND($I$1,$G$1,$D19)/100)^$D19/(1+H$3/100)^(H$2/365))^(1/($D19-H$2/365))-1)*100+模拟分析!$G$12/100)))) -> 2.2830694 | I19: =IF($B19="",0,IF($D19-I$2/365<=0,0,(IF(模拟分析!$I$12="到期平移法",[1]!B_CALC_CURVE_CHINABOND($I$1,$G$1,$D19-I$2/365)+模拟分析!$G$12/100,(((1+[1]!B_CALC_CURVE_CHINABOND($I$1,$G$1,$D19)/100)^$D19/(1+I$3/100)^(I$2/365))^(1/($D19-I$2/365))-1)*100+模拟分析!$G$12/100)))) -> 2.2854145 | J19: =IF($B19="",0,IF($D19-J$2/365<=0,0,(IF(模拟分析!$I$12="到期平移法",[1]!B_CALC_CURVE_CHINABOND($I$1,$G$1,$D19-J$2/365)+模拟分析!$G$12/100,(((1+[1]!B_CALC_CURVE_CHINABOND($I$1,$G$1,$D19)/100)^$D19/(1+J$3/100)^(J$2/365))^(1/($D19-J$2/365))-1)*100+模拟分析!$G$12/100)))) -> 2.2936556 | K19: =IF($B19="",0,IF($D19-K$2/365<=0,0,(IF(模拟分析!$I$12="到期平移法",[1]!B_CALC_CURVE_CHINABOND($I$1,$G$1,$D19-K$2/365)+模拟分析!$G$12/100,(((1+[1]!B_CALC_CURVE_CHINABOND($I$1,$G$1,$D19)/100)^$D19/(1+K$3/100)^(K$2/365))^(1/($D19-K$2/365))-1)*100+模拟分析!$G$12/100)))) -> 2.3023284 | L19: =IF($B19="",0,IF($D19-L$2/365<=0,0,(IF(模拟分析!$I$12="到期平移法",[1]!B_CALC_CURVE_CHINABOND($I$1,$G$1,$D19-L$2/365)+模拟分析!$G$12/100,(((1+[1]!B_CALC_CURVE_CHINABOND($I$1,$G$1,$D19)/100)^$D19/(1+L$3/100)^(L$2/365))^(1/($D19-L$2/365))-1)*100+模拟分析!$G$12/100)))) -> 2.3176799 | ... N19: =IF($B19="",0,IF($D19-N$2/365<=0,0,(IF(模拟分析!$I$12="到期平移法",[1]!B_CALC_CURVE_CHINABOND($I$1,$G$1,$D19-N$2/365)+模拟分析!$G$12/100,(((1+[1]!B_CALC_CURVE_CHINABOND($I$1,$G$1,$D19)/100)^$D19/(1+N$3/100)^(N$2/365))^(1/($D19-N$2/365))-1)*100+模拟分析!$G$12/100)))) -> 2.3631275 | O19: =IF(C19="","",C19/((1+E19/100)^(D19-21/365))) -> 1.1781921
B20: =IF(B19="","",IF(B19<$E$1,[1]!b_anal_nxcupn($C$1,B19+1),"")) -> 2031-11-15 | C20: =IF(B20="",0,IF(模拟分析!$K$9=0,[1]!b_anal_dailycf($C$1,B20),IF(模拟分析!$I$11="否",[1]!b_anal_dailycf($C$1,B20),IF(B20<模拟分析!$K$12,[1]!b_anal_dailycf($C$1,B20),IF(B20=模拟分析!$K$12,[1]!b_anal_dailycf($C$1,B20)+模拟分析!$K$11,0))))) -> 1.38 | D20: =IF(B20="",0,(-TODAY()+B20)/365) -> 7.5835616 | E20: =IF($B20="",0,IF($D20-E$2/365<=0,0,(IF(模拟分析!$I$12="到期平移法",[1]!B_CALC_CURVE_CHINABOND($I$1,$G$1,$D20-E$2/365)+模拟分析!$G$12/100,(((1+[1]!B_CALC_CURVE_CHINABOND($I$1,$G$1,$D20)/100)^$D20/(1+E$3/100)^(E$2/365))^(1/($D20-E$2/365))-1)*100+模拟分析!$G$12/100)))) -> 2.2875303 | F20: =IF($B20="",0,IF($D20-F$2/365<=0,0,(IF(模拟分析!$I$12="到期平移法",[1]!B_CALC_CURVE_CHINABOND($I$1,$G$1,$D20-F$2/365)+模拟分析!$G$12/100,(((1+[1]!B_CALC_CURVE_CHINABOND($I$1,$G$1,$D20)/100)^$D20/(1+F$3/100)^(F$2/365))^(1/($D20-F$2/365))-1)*100+模拟分析!$G$12/100)))) -> 2.2893346 | G20: =IF($B20="",0,IF($D20-G$2/365<=0,0,(IF(模拟分析!$I$12="到期平移法",[1]!B_CALC_CURVE_CHINABOND($I$1,$G$1,$D20-G$2/365)+模拟分析!$G$12/100,(((1+[1]!B_CALC_CURVE_CHINABOND($I$1,$G$1,$D20)/100)^$D20/(1+G$3/100)^(G$2/365))^(1/($D20-G$2/365))-1)*100+模拟分析!$G$12/100)))) -> 2.2913222 | H20: =IF($B20="",0,IF($D20-H$2/365<=0,0,(IF(模拟分析!$I$12="到期平移法",[1]!B_CALC_CURVE_CHINABOND($I$1,$G$1,$D20-H$2/365)+模拟分析!$G$12/100,(((1+[1]!B_CALC_CURVE_CHINABOND($I$1,$G$1,$D20)/100)^$D20/(1+H$3/100)^(H$2/365))^(1/($D20-H$2/365))-1)*100+模拟分析!$G$12/100)))) -> 2.2931825 | I20: =IF($B20="",0,IF($D20-I$2/365<=0,0,(IF(模拟分析!$I$12="到期平移法",[1]!B_CALC_CURVE_CHINABOND($I$1,$G$1,$D20-I$2/365)+模拟分析!$G$12/100,(((1+[1]!B_CALC_CURVE_CHINABOND($I$1,$G$1,$D20)/100)^$D20/(1+I$3/100)^(I$2/365))^(1/($D20-I$2/365))-1)*100+模拟分析!$G$12/100)))) -> 2.2954034 | J20: =IF($B20="",0,IF($D20-J$2/365<=0,0,(IF(模拟分析!$I$12="到期平移法",[1]!B_CALC_CURVE_CHINABOND($I$1,$G$1,$D20-J$2/365)+模拟分析!$G$12/100,(((1+[1]!B_CALC_CURVE_CHINABOND($I$1,$G$1,$D20)/100)^$D20/(1+J$3/100)^(J$2/365))^(1/($D20-J$2/365))-1)*100+模拟分析!$G$12/100)))) -> 2.303196 | K20: =IF($B20="",0,IF($D20-K$2/365<=0,0,(IF(模拟分析!$I$12="到期平移法",[1]!B_CALC_CURVE_CHINABOND($I$1,$G$1,$D20-K$2/365)+模拟分析!$G$12/100,(((1+[1]!B_CALC_CURVE_CHINABOND($I$1,$G$1,$D20)/100)^$D20/(1+K$3/100)^(K$2/365))^(1/($D20-K$2/365))-1)*100+模拟分析!$G$12/100)))) -> 2.3113806 | L20: =IF($B20="",0,IF($D20-L$2/365<=0,0,(IF(模拟分析!$I$12="到期平移法",[1]!B_CALC_CURVE_CHINABOND($I$1,$G$1,$D20-L$2/365)+模拟分析!$G$12/100,(((1+[1]!B_CALC_CURVE_CHINABOND($I$1,$G$1,$D20)/100)^$D20/(1+L$3/100)^(L$2/365))^(1/($D20-L$2/365))-1)*100+模拟分析!$G$12/100)))) -> 2.3258618 | ... N20: =IF($B20="",0,IF($D20-N$2/365<=0,0,(IF(模拟分析!$I$12="到期平移法",[1]!B_CALC_CURVE_CHINABOND($I$1,$G$1,$D20-N$2/365)+模拟分析!$G$12/100,(((1+[1]!B_CALC_CURVE_CHINABOND($I$1,$G$1,$D20)/100)^$D20/(1+N$3/100)^(N$2/365))^(1/($D20-N$2/365))-1)*100+模拟分析!$G$12/100)))) -> 2.3685644 | O20: =IF(C20="","",C20/((1+E20/100)^(D20-21/365))) -> 1.1640007
B21: =IF(B20="","",IF(B20<$E$1,[1]!b_anal_nxcupn($C$1,B20+1),"")) -> 2032-05-15 | C21: =IF(B21="",0,IF(模拟分析!$K$9=0,[1]!b_anal_dailycf($C$1,B21),IF(模拟分析!$I$11="否",[1]!b_anal_dailycf($C$1,B21),IF(B21<模拟分析!$K$12,[1]!b_anal_dailycf($C$1,B21),IF(B21=模拟分析!$K$12,[1]!b_anal_dailycf($C$1,B21)+模拟分析!$K$11,0))))) -> 101.38 | D21: =IF(B21="",0,(-TODAY()+B21)/365) -> 8.0821918 | E21: =IF($B21="",0,IF($D21-E$2/365<=0,0,(IF(模拟分析!$I$12="到期平移法",[1]!B_CALC_CURVE_CHINABOND($I$1,$G$1,$D21-E$2/365)+模拟分析!$G$12/100,(((1+[1]!B_CALC_CURVE_CHINABOND($I$1,$G$1,$D21)/100)^$D21/(1+E$3/100)^(E$2/365))^(1/($D21-E$2/365))-1)*100+模拟分析!$G$12/100)))) -> 2.2937325 | F21: =IF($B21="",0,IF($D21-F$2/365<=0,0,(IF(模拟分析!$I$12="到期平移法",[1]!B_CALC_CURVE_CHINABOND($I$1,$G$1,$D21-F$2/365)+模拟分析!$G$12/100,(((1+[1]!B_CALC_CURVE_CHINABOND($I$1,$G$1,$D21)/100)^$D21/(1+F$3/100)^(F$2/365))^(1/($D21-F$2/365))-1)*100+模拟分析!$G$12/100)))) -> 2.295438 | G21: =IF($B21="",0,IF($D21-G$2/365<=0,0,(IF(模拟分析!$I$12="到期平移法",[1]!B_CALC_CURVE_CHINABOND($I$1,$G$1,$D21-G$2/365)+模拟分析!$G$12/100,(((1+[1]!B_CALC_CURVE_CHINABOND($I$1,$G$1,$D21)/100)^$D21/(1+G$3/100)^(G$2/365))^(1/($D21-G$2/365))-1)*100+模拟分析!$G$12/100)))) -> 2.297317 | H21: =IF($B21="",0,IF($D21-H$2/365<=0,0,(IF(模拟分析!$I$12="到期平移法",[1]!B_CALC_CURVE_CHINABOND($I$1,$G$1,$D21-H$2/365)+模拟分析!$G$12/100,(((1+[1]!B_CALC_CURVE_CHINABOND($I$1,$G$1,$D21)/100)^$D21/(1+H$3/100)^(H$2/365))^(1/($D21-H$2/365))-1)*100+模拟分析!$G$12/100)))) -> 2.2990761 | I21: =IF($B21="",0,IF($D21-I$2/365<=0,0,(IF(模拟分析!$I$12="到期平移法",[1]!B_CALC_CURVE_CHINABOND($I$1,$G$1,$D21-I$2/365)+模拟分析!$G$12/100,(((1+[1]!B_CALC_CURVE_CHINABOND($I$1,$G$1,$D21)/100)^$D21/(1+I$3/100)^(I$2/365))^(1/($D21-I$2/365))-1)*100+模拟分析!$G$12/100)))) -> 2.3011769 | J21: =IF($B21="",0,IF($D21-J$2/365<=0,0,(IF(模拟分析!$I$12="到期平移法",[1]!B_CALC_CURVE_CHINABOND($I$1,$G$1,$D21-J$2/365)+模拟分析!$G$12/100,(((1+[1]!B_CALC_CURVE_CHINABOND($I$1,$G$1,$D21)/100)^$D21/(1+J$3/100)^(J$2/365))^(1/($D21-J$2/365))-1)*100+模拟分析!$G$12/100)))) -> 2.3085391 | K21: =IF($B21="",0,IF($D21-K$2/365<=0,0,(IF(模拟分析!$I$12="到期平移法",[1]!B_CALC_CURVE_CHINABOND($I$1,$G$1,$D21-K$2/365)+模拟分析!$G$12/100,(((1+[1]!B_CALC_CURVE_CHINABOND($I$1,$G$1,$D21)/100)^$D21/(1+K$3/100)^(K$2/365))^(1/($D21-K$2/365))-1)*100+模拟分析!$G$12/100)))) -> 2.3162592 | L21: =IF($B21="",0,IF($D21-L$2/365<=0,0,(IF(模拟分析!$I$12="到期平移法",[1]!B_CALC_CURVE_CHINABOND($I$1,$G$1,$D21-L$2/365)+模拟分析!$G$12/100,(((1+[1]!B_CALC_CURVE_CHINABOND($I$1,$G$1,$D21)/100)^$D21/(1+L$3/100)^(L$2/365))^(1/($D21-L$2/365))-1)*100+模拟分析!$G$12/100)))) -> 2.3299043 | ... N21: =IF($B21="",0,IF($D21-N$2/365<=0,0,(IF(模拟分析!$I$12="到期平移法",[1]!B_CALC_CURVE_CHINABOND($I$1,$G$1,$D21-N$2/365)+模拟分析!$G$12/100,(((1+[1]!B_CALC_CURVE_CHINABOND($I$1,$G$1,$D21)/100)^$D21/(1+N$3/100)^(N$2/365))^(1/($D21-N$2/365))-1)*100+模拟分析!$G$12/100)))) -> 2.3699378 | O21: =IF(C21="","",C21/((1+E21/100)^(D21-21/365))) -> 84.511777
B22: =IF(B21="","",IF(B21<$E$1,[1]!b_anal_nxcupn($C$1,B21+1),"")) | C22: =IF(B22="",0,IF(模拟分析!$K$9=0,[1]!b_anal_dailycf($C$1,B22),IF(模拟分析!$I$11="否",[1]!b_anal_dailycf($C$1,B22),IF(B22<模拟分析!$K$12,[1]!b_anal_dailycf($C$1,B22),IF(B22=模拟分析!$K$12,[1]!b_anal_dailycf($C$1,B22)+模拟分析!$K$11,0))))) -> 0 | D22: =IF(B22="",0,(-TODAY()+B22)/365) -> 0 | E22: =IF($B22="",0,IF($D22-E$2/365<=0,0,(IF(模拟分析!$I$12="到期平移法",[1]!B_CALC_CURVE_CHINABOND($I$1,$G$1,$D22-E$2/365),(((1+[1]!B_CALC_CURVE_CHINABOND($I$1,$G$1,$D22)/100)^$D22/(1+E$3/100)^(E$2/365))^(1/($D22-E$2/365))-1)*100+模拟分析!$G$12/100)))) -> 0 | F22: =IF($B22="",0,IF($D22-F$2/365<=0,0,(IF(模拟分析!$I$12="到期平移法",[1]!B_CALC_CURVE_CHINABOND($I$1,$G$1,$D22-F$2/365),(((1+[1]!B_CALC_CURVE_CHINABOND($I$1,$G$1,$D22)/100)^$D22/(1+F$3/100)^(F$2/365))^(1/($D22-F$2/365))-1)*100+模拟分析!$G$12/100)))) -> 0 | G22: =IF($B22="",0,IF($D22-G$2/365<=0,0,(IF(模拟分析!$I$12="到期平移法",[1]!B_CALC_CURVE_CHINABOND($I$1,$G$1,$D22-G$2/365),(((1+[1]!B_CALC_CURVE_CHINABOND($I$1,$G$1,$D22)/100)^$D22/(1+G$3/100)^(G$2/365))^(1/($D22-G$2/365))-1)*100+模拟分析!$G$12/100)))) -> 0 | H22: =IF($B22="",0,IF($D22-H$2/365<=0,0,(IF(模拟分析!$I$12="到期平移法",[1]!B_CALC_CURVE_CHINABOND($I$1,$G$1,$D22-H$2/365),(((1+[1]!B_CALC_CURVE_CHINABOND($I$1,$G$1,$D22)/100)^$D22/(1+H$3/100)^(H$2/365))^(1/($D22-H$2/365))-1)*100+模拟分析!$G$12/100)))) -> 0 | I22: =IF($B22="",0,IF($D22-I$2/365<=0,0,(IF(模拟分析!$I$12="到期平移法",[1]!B_CALC_CURVE_CHINABOND($I$1,$G$1,$D22-I$2/365),(((1+[1]!B_CALC_CURVE_CHINABOND($I$1,$G$1,$D22)/100)^$D22/(1+I$3/100)^(I$2/365))^(1/($D22-I$2/365))-1)*100+模拟分析!$G$12/100)))) -> 0 | J22: =IF($B22="",0,IF($D22-J$2/365<=0,0,(IF(模拟分析!$I$12="到期平移法",[1]!B_CALC_CURVE_CHINABOND($I$1,$G$1,$D22-J$2/365),(((1+[1]!B_CALC_CURVE_CHINABOND($I$1,$G$1,$D22)/100)^$D22/(1+J$3/100)^(J$2/365))^(1/($D22-J$2/365))-1)*100+模拟分析!$G$12/100)))) -> 0 | K22: =IF($B22="",0,IF($D22-K$2/365<=0,0,(IF(模拟分析!$I$12="到期平移法",[1]!B_CALC_CURVE_CHINABOND($I$1,$G$1,$D22-K$2/365),(((1+[1]!B_CALC_CURVE_CHINABOND($I$1,$G$1,$D22)/100)^$D22/(1+K$3/100)^(K$2/365))^(1/($D22-K$2/365))-1)*100+模拟分析!$G$12/100)))) -> 0 | L22: =IF($B22="",0,IF($D22-L$2/365<=0,0,(IF(模拟分析!$I$12="到期平移法",[1]!B_CALC_CURVE_CHINABOND($I$1,$G$1,$D22-L$2/365),(((1+[1]!B_CALC_CURVE_CHINABOND($I$1,$G$1,$D22)/100)^$D22/(1+L$3/100)^(L$2/365))^(1/($D22-L$2/365))-1)*100+模拟分析!$G$12/100)))) -> 0 | ... N22: =IF($B22="",0,IF($D22-N$2/365<=0,0,(IF(模拟分析!$I$12="到期平移法",[1]!B_CALC_CURVE_CHINABOND($I$1,$G$1,$D22-N$2/365),(((1+[1]!B_CALC_CURVE_CHINABOND($I$1,$G$1,$D22)/100)^$D22/(1+N$3/100)^(N$2/365))^(1/($D22-N$2/365))-1)*100+模拟分析!$G$12/100)))) -> 0 | O22: =IF(C22="","",C22/((1+E22/100)^(D22-21/365))) -> 0
B23: =IF(B22="","",IF(B22<$E$1,[1]!b_anal_nxcupn($C$1,B22+1),"")) | C23: =IF(B23="",0,IF(模拟分析!$K$9=0,[1]!b_anal_dailycf($C$1,B23),IF(模拟分析!$I$11="否",[1]!b_anal_dailycf($C$1,B23),IF(B23<模拟分析!$K$12,[1]!b_anal_dailycf($C$1,B23),IF(B23=模拟分析!$K$12,[1]!b_anal_dailycf($C$1,B23)+模拟分析!$K$11,0))))) -> 0 | D23: =IF(B23="",0,(-TODAY()+B23)/365) -> 0 | E23: =IF($B23="",0,IF($D23-E$2/365<=0,0,(IF(模拟分析!$I$12="到期平移法",[1]!B_CALC_CURVE_CHINABOND($I$1,$G$1,$D23-E$2/365),(((1+[1]!B_CALC_CURVE_CHINABOND($I$1,$G$1,$D23)/100)^$D23/(1+E$3/100)^(E$2/365))^(1/($D23-E$2/365))-1)*100+模拟分析!$G$12/100)))) -> 0 | F23: =IF($B23="",0,IF($D23-F$2/365<=0,0,(IF(模拟分析!$I$12="到期平移法",[1]!B_CALC_CURVE_CHINABOND($I$1,$G$1,$D23-F$2/365),(((1+[1]!B_CALC_CURVE_CHINABOND($I$1,$G$1,$D23)/100)^$D23/(1+F$3/100)^(F$2/365))^(1/($D23-F$2/365))-1)*100+模拟分析!$G$12/100)))) -> 0 | G23: =IF($B23="",0,IF($D23-G$2/365<=0,0,(IF(模拟分析!$I$12="到期平移法",[1]!B_CALC_CURVE_CHINABOND($I$1,$G$1,$D23-G$2/365),(((1+[1]!B_CALC_CURVE_CHINABOND($I$1,$G$1,$D23)/100)^$D23/(1+G$3/100)^(G$2/365))^(1/($D23-G$2/365))-1)*100+模拟分析!$G$12/100)))) -> 0 | H23: =IF($B23="",0,IF($D23-H$2/365<=0,0,(IF(模拟分析!$I$12="到期平移法",[1]!B_CALC_CURVE_CHINABOND($I$1,$G$1,$D23-H$2/365),(((1+[1]!B_CALC_CURVE_CHINABOND($I$1,$G$1,$D23)/100)^$D23/(1+H$3/100)^(H$2/365))^(1/($D23-H$2/365))-1)*100+模拟分析!$G$12/100)))) -> 0 | I23: =IF($B23="",0,IF($D23-I$2/365<=0,0,(IF(模拟分析!$I$12="到期平移法",[1]!B_CALC_CURVE_CHINABOND($I$1,$G$1,$D23-I$2/365),(((1+[1]!B_CALC_CURVE_CHINABOND($I$1,$G$1,$D23)/100)^$D23/(1+I$3/100)^(I$2/365))^(1/($D23-I$2/365))-1)*100+模拟分析!$G$12/100)))) -> 0 | J23: =IF($B23="",0,IF($D23-J$2/365<=0,0,(IF(模拟分析!$I$12="到期平移法",[1]!B_CALC_CURVE_CHINABOND($I$1,$G$1,$D23-J$2/365),(((1+[1]!B_CALC_CURVE_CHINABOND($I$1,$G$1,$D23)/100)^$D23/(1+J$3/100)^(J$2/365))^(1/($D23-J$2/365))-1)*100+模拟分析!$G$12/100)))) -> 0 | K23: =IF($B23="",0,IF($D23-K$2/365<=0,0,(IF(模拟分析!$I$12="到期平移法",[1]!B_CALC_CURVE_CHINABOND($I$1,$G$1,$D23-K$2/365),(((1+[1]!B_CALC_CURVE_CHINABOND($I$1,$G$1,$D23)/100)^$D23/(1+K$3/100)^(K$2/365))^(1/($D23-K$2/365))-1)*100+模拟分析!$G$12/100)))) -> 0 | L23: =IF($B23="",0,IF($D23-L$2/365<=0,0,(IF(模拟分析!$I$12="到期平移法",[1]!B_CALC_CURVE_CHINABOND($I$1,$G$1,$D23-L$2/365),(((1+[1]!B_CALC_CURVE_CHINABOND($I$1,$G$1,$D23)/100)^$D23/(1+L$3/100)^(L$2/365))^(1/($D23-L$2/365))-1)*100+模拟分析!$G$12/100)))) -> 0 | ... N23: =IF($B23="",0,IF($D23-N$2/365<=0,0,(IF(模拟分析!$I$12="到期平移法",[1]!B_CALC_CURVE_CHINABOND($I$1,$G$1,$D23-N$2/365),(((1+[1]!B_CALC_CURVE_CHINABOND($I$1,$G$1,$D23)/100)^$D23/(1+N$3/100)^(N$2/365))^(1/($D23-N$2/365))-1)*100+模拟分析!$G$12/100)))) -> 0 | O23: =IF(C23="","",C23/((1+E23/100)^(D23-21/365))) -> 0
B24: =IF(B23="","",IF(B23<$E$1,[1]!b_anal_nxcupn($C$1,B23+1),"")) | C24: =IF(B24="",0,IF(模拟分析!$K$9=0,[1]!b_anal_dailycf($C$1,B24),IF(模拟分析!$I$11="否",[1]!b_anal_dailycf($C$1,B24),IF(B24<模拟分析!$K$12,[1]!b_anal_dailycf($C$1,B24),IF(B24=模拟分析!$K$12,[1]!b_anal_dailycf($C$1,B24)+模拟分析!$K$11,0))))) -> 0 | D24: =IF(B24="",0,(-TODAY()+B24)/365) -> 0 | E24: =IF($B24="",0,IF($D24-E$2/365<=0,0,(IF(模拟分析!$I$12="到期平移法",[1]!B_CALC_CURVE_CHINABOND($I$1,$G$1,$D24-E$2/365),(((1+[1]!B_CALC_CURVE_CHINABOND($I$1,$G$1,$D24)/100)^$D24/(1+E$3/100)^(E$2/365))^(1/($D24-E$2/365))-1)*100+模拟分析!$G$12/100)))) -> 0 | F24: =IF($B24="",0,IF($D24-F$2/365<=0,0,(IF(模拟分析!$I$12="到期平移法",[1]!B_CALC_CURVE_CHINABOND($I$1,$G$1,$D24-F$2/365),(((1+[1]!B_CALC_CURVE_CHINABOND($I$1,$G$1,$D24)/100)^$D24/(1+F$3/100)^(F$2/365))^(1/($D24-F$2/365))-1)*100+模拟分析!$G$12/100)))) -> 0 | G24: =IF($B24="",0,IF($D24-G$2/365<=0,0,(IF(模拟分析!$I$12="到期平移法",[1]!B_CALC_CURVE_CHINABOND($I$1,$G$1,$D24-G$2/365),(((1+[1]!B_CALC_CURVE_CHINABOND($I$1,$G$1,$D24)/100)^$D24/(1+G$3/100)^(G$2/365))^(1/($D24-G$2/365))-1)*100+模拟分析!$G$12/100)))) -> 0 | H24: =IF($B24="",0,IF($D24-H$2/365<=0,0,(IF(模拟分析!$I$12="到期平移法",[1]!B_CALC_CURVE_CHINABOND($I$1,$G$1,$D24-H$2/365),(((1+[1]!B_CALC_CURVE_CHINABOND($I$1,$G$1,$D24)/100)^$D24/(1+H$3/100)^(H$2/365))^(1/($D24-H$2/365))-1)*100+模拟分析!$G$12/100)))) -> 0 | I24: =IF($B24="",0,IF($D24-I$2/365<=0,0,(IF(模拟分析!$I$12="到期平移法",[1]!B_CALC_CURVE_CHINABOND($I$1,$G$1,$D24-I$2/365),(((1+[1]!B_CALC_CURVE_CHINABOND($I$1,$G$1,$D24)/100)^$D24/(1+I$3/100)^(I$2/365))^(1/($D24-I$2/365))-1)*100+模拟分析!$G$12/100)))) -> 0 | J24: =IF($B24="",0,IF($D24-J$2/365<=0,0,(IF(模拟分析!$I$12="到期平移法",[1]!B_CALC_CURVE_CHINABOND($I$1,$G$1,$D24-J$2/365),(((1+[1]!B_CALC_CURVE_CHINABOND($I$1,$G$1,$D24)/100)^$D24/(1+J$3/100)^(J$2/365))^(1/($D24-J$2/365))-1)*100+模拟分析!$G$12/100)))) -> 0 | K24: =IF($B24="",0,IF($D24-K$2/365<=0,0,(IF(模拟分析!$I$12="到期平移法",[1]!B_CALC_CURVE_CHINABOND($I$1,$G$1,$D24-K$2/365),(((1+[1]!B_CALC_CURVE_CHINABOND($I$1,$G$1,$D24)/100)^$D24/(1+K$3/100)^(K$2/365))^(1/($D24-K$2/365))-1)*100+模拟分析!$G$12/100)))) -> 0 | L24: =IF($B24="",0,IF($D24-L$2/365<=0,0,(IF(模拟分析!$I$12="到期平移法",[1]!B_CALC_CURVE_CHINABOND($I$1,$G$1,$D24-L$2/365),(((1+[1]!B_CALC_CURVE_CHINABOND($I$1,$G$1,$D24)/100)^$D24/(1+L$3/100)^(L$2/365))^(1/($D24-L$2/365))-1)*100+模拟分析!$G$12/100)))) -> 0 | ... N24: =IF($B24="",0,IF($D24-N$2/365<=0,0,(IF(模拟分析!$I$12="到期平移法",[1]!B_CALC_CURVE_CHINABOND($I$1,$G$1,$D24-N$2/365),(((1+[1]!B_CALC_CURVE_CHINABOND($I$1,$G$1,$D24)/100)^$D24/(1+N$3/100)^(N$2/365))^(1/($D24-N$2/365))-1)*100+模拟分析!$G$12/100)))) -> 0 | O24: =IF(C24="","",C24/((1+E24/100)^(D24-21/365))) -> 0
B25: =IF(B24="","",IF(B24<$E$1,[1]!b_anal_nxcupn($C$1,B24+1),"")) | C25: =IF(B25="",0,IF(模拟分析!$K$9=0,[1]!b_anal_dailycf($C$1,B25),IF(模拟分析!$I$11="否",[1]!b_anal_dailycf($C$1,B25),IF(B25<模拟分析!$K$12,[1]!b_anal_dailycf($C$1,B25),IF(B25=模拟分析!$K$12,[1]!b_anal_dailycf($C$1,B25)+模拟分析!$K$11,0))))) -> 0 | D25: =IF(B25="",0,(-TODAY()+B25)/365) -> 0 | E25: =IF($B25="",0,IF($D25-E$2/365<=0,0,(IF(模拟分析!$I$12="到期平移法",[1]!B_CALC_CURVE_CHINABOND($I$1,$G$1,$D25-E$2/365),(((1+[1]!B_CALC_CURVE_CHINABOND($I$1,$G$1,$D25)/100)^$D25/(1+E$3/100)^(E$2/365))^(1/($D25-E$2/365))-1)*100+模拟分析!$G$12/100)))) -> 0 | F25: =IF($B25="",0,IF($D25-F$2/365<=0,0,(IF(模拟分析!$I$12="到期平移法",[1]!B_CALC_CURVE_CHINABOND($I$1,$G$1,$D25-F$2/365),(((1+[1]!B_CALC_CURVE_CHINABOND($I$1,$G$1,$D25)/100)^$D25/(1+F$3/100)^(F$2/365))^(1/($D25-F$2/365))-1)*100+模拟分析!$G$12/100)))) -> 0 | G25: =IF($B25="",0,IF($D25-G$2/365<=0,0,(IF(模拟分析!$I$12="到期平移法",[1]!B_CALC_CURVE_CHINABOND($I$1,$G$1,$D25-G$2/365),(((1+[1]!B_CALC_CURVE_CHINABOND($I$1,$G$1,$D25)/100)^$D25/(1+G$3/100)^(G$2/365))^(1/($D25-G$2/365))-1)*100+模拟分析!$G$12/100)))) -> 0 | H25: =IF($B25="",0,IF($D25-H$2/365<=0,0,(IF(模拟分析!$I$12="到期平移法",[1]!B_CALC_CURVE_CHINABOND($I$1,$G$1,$D25-H$2/365),(((1+[1]!B_CALC_CURVE_CHINABOND($I$1,$G$1,$D25)/100)^$D25/(1+H$3/100)^(H$2/365))^(1/($D25-H$2/365))-1)*100+模拟分析!$G$12/100)))) -> 0 | I25: =IF($B25="",0,IF($D25-I$2/365<=0,0,(IF(模拟分析!$I$12="到期平移法",[1]!B_CALC_CURVE_CHINABOND($I$1,$G$1,$D25-I$2/365),(((1+[1]!B_CALC_CURVE_CHINABOND($I$1,$G$1,$D25)/100)^$D25/(1+I$3/100)^(I$2/365))^(1/($D25-I$2/365))-1)*100+模拟分析!$G$12/100)))) -> 0 | J25: =IF($B25="",0,IF($D25-J$2/365<=0,0,(IF(模拟分析!$I$12="到期平移法",[1]!B_CALC_CURVE_CHINABOND($I$1,$G$1,$D25-J$2/365),(((1+[1]!B_CALC_CURVE_CHINABOND($I$1,$G$1,$D25)/100)^$D25/(1+J$3/100)^(J$2/365))^(1/($D25-J$2/365))-1)*100+模拟分析!$G$12/100)))) -> 0 | K25: =IF($B25="",0,IF($D25-K$2/365<=0,0,(IF(模拟分析!$I$12="到期平移法",[1]!B_CALC_CURVE_CHINABOND($I$1,$G$1,$D25-K$2/365),(((1+[1]!B_CALC_CURVE_CHINABOND($I$1,$G$1,$D25)/100)^$D25/(1+K$3/100)^(K$2/365))^(1/($D25-K$2/365))-1)*100+模拟分析!$G$12/100)))) -> 0 | L25: =IF($B25="",0,IF($D25-L$2/365<=0,0,(IF(模拟分析!$I$12="到期平移法",[1]!B_CALC_CURVE_CHINABOND($I$1,$G$1,$D25-L$2/365),(((1+[1]!B_CALC_CURVE_CHINABOND($I$1,$G$1,$D25)/100)^$D25/(1+L$3/100)^(L$2/365))^(1/($D25-L$2/365))-1)*100+模拟分析!$G$12/100)))) -> 0 | ... N25: =IF($B25="",0,IF($D25-N$2/365<=0,0,(IF(模拟分析!$I$12="到期平移法",[1]!B_CALC_CURVE_CHINABOND($I$1,$G$1,$D25-N$2/365),(((1+[1]!B_CALC_CURVE_CHINABOND($I$1,$G$1,$D25)/100)^$D25/(1+N$3/100)^(N$2/365))^(1/($D25-N$2/365))-1)*100+模拟分析!$G$12/100)))) -> 0 | O25: =IF(C25="","",C25/((1+E25/100)^(D25-21/365))) -> 0
B26: =IF(B25="","",IF(B25<$E$1,[1]!b_anal_nxcupn($C$1,B25+1),"")) | C26: =IF(B26="",0,IF(模拟分析!$K$9=0,[1]!b_anal_dailycf($C$1,B26),IF(模拟分析!$I$11="否",[1]!b_anal_dailycf($C$1,B26),IF(B26<模拟分析!$K$12,[1]!b_anal_dailycf($C$1,B26),IF(B26=模拟分析!$K$12,[1]!b_anal_dailycf($C$1,B26)+模拟分析!$K$11,0))))) -> 0 | D26: =IF(B26="",0,(-TODAY()+B26)/365) -> 0 | E26: =IF($B26="",0,IF($D26-E$2/365<=0,0,(IF(模拟分析!$I$12="到期平移法",[1]!B_CALC_CURVE_CHINABOND($I$1,$G$1,$D26-E$2/365),(((1+[1]!B_CALC_CURVE_CHINABOND($I$1,$G$1,$D26)/100)^$D26/(1+E$3/100)^(E$2/365))^(1/($D26-E$2/365))-1)*100+模拟分析!$G$12/100)))) -> 0 | F26: =IF($B26="",0,IF($D26-F$2/365<=0,0,(IF(模拟分析!$I$12="到期平移法",[1]!B_CALC_CURVE_CHINABOND($I$1,$G$1,$D26-F$2/365),(((1+[1]!B_CALC_CURVE_CHINABOND($I$1,$G$1,$D26)/100)^$D26/(1+F$3/100)^(F$2/365))^(1/($D26-F$2/365))-1)*100+模拟分析!$G$12/100)))) -> 0 | G26: =IF($B26="",0,IF($D26-G$2/365<=0,0,(IF(模拟分析!$I$12="到期平移法",[1]!B_CALC_CURVE_CHINABOND($I$1,$G$1,$D26-G$2/365),(((1+[1]!B_CALC_CURVE_CHINABOND($I$1,$G$1,$D26)/100)^$D26/(1+G$3/100)^(G$2/365))^(1/($D26-G$2/365))-1)*100+模拟分析!$G$12/100)))) -> 0 | H26: =IF($B26="",0,IF($D26-H$2/365<=0,0,(IF(模拟分析!$I$12="到期平移法",[1]!B_CALC_CURVE_CHINABOND($I$1,$G$1,$D26-H$2/365),(((1+[1]!B_CALC_CURVE_CHINABOND($I$1,$G$1,$D26)/100)^$D26/(1+H$3/100)^(H$2/365))^(1/($D26-H$2/365))-1)*100+模拟分析!$G$12/100)))) -> 0 | I26: =IF($B26="",0,IF($D26-I$2/365<=0,0,(IF(模拟分析!$I$12="到期平移法",[1]!B_CALC_CURVE_CHINABOND($I$1,$G$1,$D26-I$2/365),(((1+[1]!B_CALC_CURVE_CHINABOND($I$1,$G$1,$D26)/100)^$D26/(1+I$3/100)^(I$2/365))^(1/($D26-I$2/365))-1)*100+模拟分析!$G$12/100)))) -> 0 | J26: =IF($B26="",0,IF($D26-J$2/365<=0,0,(IF(模拟分析!$I$12="到期平移法",[1]!B_CALC_CURVE_CHINABOND($I$1,$G$1,$D26-J$2/365),(((1+[1]!B_CALC_CURVE_CHINABOND($I$1,$G$1,$D26)/100)^$D26/(1+J$3/100)^(J$2/365))^(1/($D26-J$2/365))-1)*100+模拟分析!$G$12/100)))) -> 0 | K26: =IF($B26="",0,IF($D26-K$2/365<=0,0,(IF(模拟分析!$I$12="到期平移法",[1]!B_CALC_CURVE_CHINABOND($I$1,$G$1,$D26-K$2/365),(((1+[1]!B_CALC_CURVE_CHINABOND($I$1,$G$1,$D26)/100)^$D26/(1+K$3/100)^(K$2/365))^(1/($D26-K$2/365))-1)*100+模拟分析!$G$12/100)))) -> 0 | L26: =IF($B26="",0,IF($D26-L$2/365<=0,0,(IF(模拟分析!$I$12="到期平移法",[1]!B_CALC_CURVE_CHINABOND($I$1,$G$1,$D26-L$2/365),(((1+[1]!B_CALC_CURVE_CHINABOND($I$1,$G$1,$D26)/100)^$D26/(1+L$3/100)^(L$2/365))^(1/($D26-L$2/365))-1)*100+模拟分析!$G$12/100)))) -> 0 | ... N26: =IF($B26="",0,IF($D26-N$2/365<=0,0,(IF(模拟分析!$I$12="到期平移法",[1]!B_CALC_CURVE_CHINABOND($I$1,$G$1,$D26-N$2/365),(((1+[1]!B_CALC_CURVE_CHINABOND($I$1,$G$1,$D26)/100)^$D26/(1+N$3/100)^(N$2/365))^(1/($D26-N$2/365))-1)*100+模拟分析!$G$12/100)))) -> 0 | O26: =IF(C26="","",C26/((1+E26/100)^(D26-21/365))) -> 0
B27: =IF(B26="","",IF(B26<$E$1,[1]!b_anal_nxcupn($C$1,B26+1),"")) | C27: =IF(B27="",0,IF(模拟分析!$K$9=0,[1]!b_anal_dailycf($C$1,B27),IF(模拟分析!$I$11="否",[1]!b_anal_dailycf($C$1,B27),IF(B27<模拟分析!$K$12,[1]!b_anal_dailycf($C$1,B27),IF(B27=模拟分析!$K$12,[1]!b_anal_dailycf($C$1,B27)+模拟分析!$K$11,0))))) -> 0 | D27: =IF(B27="",0,(-TODAY()+B27)/365) -> 0 | E27: =IF($B27="",0,IF($D27-E$2/365<=0,0,(IF(模拟分析!$I$12="到期平移法",[1]!B_CALC_CURVE_CHINABOND($I$1,$G$1,$D27-E$2/365),(((1+[1]!B_CALC_CURVE_CHINABOND($I$1,$G$1,$D27)/100)^$D27/(1+E$3/100)^(E$2/365))^(1/($D27-E$2/365))-1)*100+模拟分析!$G$12/100)))) -> 0 | F27: =IF($B27="",0,IF($D27-F$2/365<=0,0,(IF(模拟分析!$I$12="到期平移法",[1]!B_CALC_CURVE_CHINABOND($I$1,$G$1,$D27-F$2/365),(((1+[1]!B_CALC_CURVE_CHINABOND($I$1,$G$1,$D27)/100)^$D27/(1+F$3/100)^(F$2/365))^(1/($D27-F$2/365))-1)*100+模拟分析!$G$12/100)))) -> 0 | G27: =IF($B27="",0,IF($D27-G$2/365<=0,0,(IF(模拟分析!$I$12="到期平移法",[1]!B_CALC_CURVE_CHINABOND($I$1,$G$1,$D27-G$2/365),(((1+[1]!B_CALC_CURVE_CHINABOND($I$1,$G$1,$D27)/100)^$D27/(1+G$3/100)^(G$2/365))^(1/($D27-G$2/365))-1)*100+模拟分析!$G$12/100)))) -> 0 | H27: =IF($B27="",0,IF($D27-H$2/365<=0,0,(IF(模拟分析!$I$12="到期平移法",[1]!B_CALC_CURVE_CHINABOND($I$1,$G$1,$D27-H$2/365),(((1+[1]!B_CALC_CURVE_CHINABOND($I$1,$G$1,$D27)/100)^$D27/(1+H$3/100)^(H$2/365))^(1/($D27-H$2/365))-1)*100+模拟分析!$G$12/100)))) -> 0 | I27: =IF($B27="",0,IF($D27-I$2/365<=0,0,(IF(模拟分析!$I$12="到期平移法",[1]!B_CALC_CURVE_CHINABOND($I$1,$G$1,$D27-I$2/365),(((1+[1]!B_CALC_CURVE_CHINABOND($I$1,$G$1,$D27)/100)^$D27/(1+I$3/100)^(I$2/365))^(1/($D27-I$2/365))-1)*100+模拟分析!$G$12/100)))) -> 0 | J27: =IF($B27="",0,IF($D27-J$2/365<=0,0,(IF(模拟分析!$I$12="到期平移法",[1]!B_CALC_CURVE_CHINABOND($I$1,$G$1,$D27-J$2/365),(((1+[1]!B_CALC_CURVE_CHINABOND($I$1,$G$1,$D27)/100)^$D27/(1+J$3/100)^(J$2/365))^(1/($D27-J$2/365))-1)*100+模拟分析!$G$12/100)))) -> 0 | K27: =IF($B27="",0,IF($D27-K$2/365<=0,0,(IF(模拟分析!$I$12="到期平移法",[1]!B_CALC_CURVE_CHINABOND($I$1,$G$1,$D27-K$2/365),(((1+[1]!B_CALC_CURVE_CHINABOND($I$1,$G$1,$D27)/100)^$D27/(1+K$3/100)^(K$2/365))^(1/($D27-K$2/365))-1)*100+模拟分析!$G$12/100)))) -> 0 | L27: =IF($B27="",0,IF($D27-L$2/365<=0,0,(IF(模拟分析!$I$12="到期平移法",[1]!B_CALC_CURVE_CHINABOND($I$1,$G$1,$D27-L$2/365),(((1+[1]!B_CALC_CURVE_CHINABOND($I$1,$G$1,$D27)/100)^$D27/(1+L$3/100)^(L$2/365))^(1/($D27-L$2/365))-1)*100+模拟分析!$G$12/100)))) -> 0 | ... N27: =IF($B27="",0,IF($D27-N$2/365<=0,0,(IF(模拟分析!$I$12="到期平移法",[1]!B_CALC_CURVE_CHINABOND($I$1,$G$1,$D27-N$2/365),(((1+[1]!B_CALC_CURVE_CHINABOND($I$1,$G$1,$D27)/100)^$D27/(1+N$3/100)^(N$2/365))^(1/($D27-N$2/365))-1)*100+模拟分析!$G$12/100)))) -> 0 | O27: =IF(C27="","",C27/((1+E27/100)^(D27-21/365))) -> 0
B28: =IF(B27="","",IF(B27<$E$1,[1]!b_anal_nxcupn($C$1,B27+1),"")) | C28: =IF(B28="",0,IF(模拟分析!$K$9=0,[1]!b_anal_dailycf($C$1,B28),IF(模拟分析!$I$11="否",[1]!b_anal_dailycf($C$1,B28),IF(B28<模拟分析!$K$12,[1]!b_anal_dailycf($C$1,B28),IF(B28=模拟分析!$K$12,[1]!b_anal_dailycf($C$1,B28)+模拟分析!$K$11,0))))) -> 0 | D28: =IF(B28="",0,(-TODAY()+B28)/365) -> 0 | E28: =IF($B28="",0,IF($D28-E$2/365<=0,0,(IF(模拟分析!$I$12="到期平移法",[1]!B_CALC_CURVE_CHINABOND($I$1,$G$1,$D28-E$2/365),(((1+[1]!B_CALC_CURVE_CHINABOND($I$1,$G$1,$D28)/100)^$D28/(1+E$3/100)^(E$2/365))^(1/($D28-E$2/365))-1)*100+模拟分析!$G$12/100)))) -> 0 | F28: =IF($B28="",0,IF($D28-F$2/365<=0,0,(IF(模拟分析!$I$12="到期平移法",[1]!B_CALC_CURVE_CHINABOND($I$1,$G$1,$D28-F$2/365),(((1+[1]!B_CALC_CURVE_CHINABOND($I$1,$G$1,$D28)/100)^$D28/(1+F$3/100)^(F$2/365))^(1/($D28-F$2/365))-1)*100+模拟分析!$G$12/100)))) -> 0 | G28: =IF($B28="",0,IF($D28-G$2/365<=0,0,(IF(模拟分析!$I$12="到期平移法",[1]!B_CALC_CURVE_CHINABOND($I$1,$G$1,$D28-G$2/365),(((1+[1]!B_CALC_CURVE_CHINABOND($I$1,$G$1,$D28)/100)^$D28/(1+G$3/100)^(G$2/365))^(1/($D28-G$2/365))-1)*100+模拟分析!$G$12/100)))) -> 0 | H28: =IF($B28="",0,IF($D28-H$2/365<=0,0,(IF(模拟分析!$I$12="到期平移法",[1]!B_CALC_CURVE_CHINABOND($I$1,$G$1,$D28-H$2/365),(((1+[1]!B_CALC_CURVE_CHINABOND($I$1,$G$1,$D28)/100)^$D28/(1+H$3/100)^(H$2/365))^(1/($D28-H$2/365))-1)*100+模拟分析!$G$12/100)))) -> 0 | I28: =IF($B28="",0,IF($D28-I$2/365<=0,0,(IF(模拟分析!$I$12="到期平移法",[1]!B_CALC_CURVE_CHINABOND($I$1,$G$1,$D28-I$2/365),(((1+[1]!B_CALC_CURVE_CHINABOND($I$1,$G$1,$D28)/100)^$D28/(1+I$3/100)^(I$2/365))^(1/($D28-I$2/365))-1)*100+模拟分析!$G$12/100)))) -> 0 | J28: =IF($B28="",0,IF($D28-J$2/365<=0,0,(IF(模拟分析!$I$12="到期平移法",[1]!B_CALC_CURVE_CHINABOND($I$1,$G$1,$D28-J$2/365),(((1+[1]!B_CALC_CURVE_CHINABOND($I$1,$G$1,$D28)/100)^$D28/(1+J$3/100)^(J$2/365))^(1/($D28-J$2/365))-1)*100+模拟分析!$G$12/100)))) -> 0 | K28: =IF($B28="",0,IF($D28-K$2/365<=0,0,(IF(模拟分析!$I$12="到期平移法",[1]!B_CALC_CURVE_CHINABOND($I$1,$G$1,$D28-K$2/365),(((1+[1]!B_CALC_CURVE_CHINABOND($I$1,$G$1,$D28)/100)^$D28/(1+K$3/100)^(K$2/365))^(1/($D28-K$2/365))-1)*100+模拟分析!$G$12/100)))) -> 0 | L28: =IF($B28="",0,IF($D28-L$2/365<=0,0,(IF(模拟分析!$I$12="到期平移法",[1]!B_CALC_CURVE_CHINABOND($I$1,$G$1,$D28-L$2/365),(((1+[1]!B_CALC_CURVE_CHINABOND($I$1,$G$1,$D28)/100)^$D28/(1+L$3/100)^(L$2/365))^(1/($D28-L$2/365))-1)*100+模拟分析!$G$12/100)))) -> 0 | ... N28: =IF($B28="",0,IF($D28-N$2/365<=0,0,(IF(模拟分析!$I$12="到期平移法",[1]!B_CALC_CURVE_CHINABOND($I$1,$G$1,$D28-N$2/365),(((1+[1]!B_CALC_CURVE_CHINABOND($I$1,$G$1,$D28)/100)^$D28/(1+N$3/100)^(N$2/365))^(1/($D28-N$2/365))-1)*100+模拟分析!$G$12/100)))) -> 0 | O28: =IF(C28="","",C28/((1+E28/100)^(D28-21/365))) -> 0
B29: =IF(B28="","",IF(B28<$E$1,[1]!b_anal_nxcupn($C$1,B28+1),"")) | C29: =IF(B29="",0,IF(模拟分析!$K$9=0,[1]!b_anal_dailycf($C$1,B29),IF(模拟分析!$I$11="否",[1]!b_anal_dailycf($C$1,B29),IF(B29<模拟分析!$K$12,[1]!b_anal_dailycf($C$1,B29),IF(B29=模拟分析!$K$12,[1]!b_anal_dailycf($C$1,B29)+模拟分析!$K$11,0))))) -> 0 | D29: =IF(B29="",0,(-TODAY()+B29)/365) -> 0 | E29: =IF($B29="",0,IF($D29-E$2/365<=0,0,(IF(模拟分析!$I$12="到期平移法",[1]!B_CALC_CURVE_CHINABOND($I$1,$G$1,$D29-E$2/365),(((1+[1]!B_CALC_CURVE_CHINABOND($I$1,$G$1,$D29)/100)^$D29/(1+E$3/100)^(E$2/365))^(1/($D29-E$2/365))-1)*100+模拟分析!$G$12/100)))) -> 0 | F29: =IF($B29="",0,IF($D29-F$2/365<=0,0,(IF(模拟分析!$I$12="到期平移法",[1]!B_CALC_CURVE_CHINABOND($I$1,$G$1,$D29-F$2/365),(((1+[1]!B_CALC_CURVE_CHINABOND($I$1,$G$1,$D29)/100)^$D29/(1+F$3/100)^(F$2/365))^(1/($D29-F$2/365))-1)*100+模拟分析!$G$12/100)))) -> 0 | G29: =IF($B29="",0,IF($D29-G$2/365<=0,0,(IF(模拟分析!$I$12="到期平移法",[1]!B_CALC_CURVE_CHINABOND($I$1,$G$1,$D29-G$2/365),(((1+[1]!B_CALC_CURVE_CHINABOND($I$1,$G$1,$D29)/100)^$D29/(1+G$3/100)^(G$2/365))^(1/($D29-G$2/365))-1)*100+模拟分析!$G$12/100)))) -> 0 | H29: =IF($B29="",0,IF($D29-H$2/365<=0,0,(IF(模拟分析!$I$12="到期平移法",[1]!B_CALC_CURVE_CHINABOND($I$1,$G$1,$D29-H$2/365),(((1+[1]!B_CALC_CURVE_CHINABOND($I$1,$G$1,$D29)/100)^$D29/(1+H$3/100)^(H$2/365))^(1/($D29-H$2/365))-1)*100+模拟分析!$G$12/100)))) -> 0 | I29: =IF($B29="",0,IF($D29-I$2/365<=0,0,(IF(模拟分析!$I$12="到期平移法",[1]!B_CALC_CURVE_CHINABOND($I$1,$G$1,$D29-I$2/365),(((1+[1]!B_CALC_CURVE_CHINABOND($I$1,$G$1,$D29)/100)^$D29/(1+I$3/100)^(I$2/365))^(1/($D29-I$2/365))-1)*100+模拟分析!$G$12/100)))) -> 0 | J29: =IF($B29="",0,IF($D29-J$2/365<=0,0,(IF(模拟分析!$I$12="到期平移法",[1]!B_CALC_CURVE_CHINABOND($I$1,$G$1,$D29-J$2/365),(((1+[1]!B_CALC_CURVE_CHINABOND($I$1,$G$1,$D29)/100)^$D29/(1+J$3/100)^(J$2/365))^(1/($D29-J$2/365))-1)*100+模拟分析!$G$12/100)))) -> 0 | K29: =IF($B29="",0,IF($D29-K$2/365<=0,0,(IF(模拟分析!$I$12="到期平移法",[1]!B_CALC_CURVE_CHINABOND($I$1,$G$1,$D29-K$2/365),(((1+[1]!B_CALC_CURVE_CHINABOND($I$1,$G$1,$D29)/100)^$D29/(1+K$3/100)^(K$2/365))^(1/($D29-K$2/365))-1)*100+模拟分析!$G$12/100)))) -> 0 | L29: =IF($B29="",0,IF($D29-L$2/365<=0,0,(IF(模拟分析!$I$12="到期平移法",[1]!B_CALC_CURVE_CHINABOND($I$1,$G$1,$D29-L$2/365),(((1+[1]!B_CALC_CURVE_CHINABOND($I$1,$G$1,$D29)/100)^$D29/(1+L$3/100)^(L$2/365))^(1/($D29-L$2/365))-1)*100+模拟分析!$G$12/100)))) -> 0 | ... N29: =IF($B29="",0,IF($D29-N$2/365<=0,0,(IF(模拟分析!$I$12="到期平移法",[1]!B_CALC_CURVE_CHINABOND($I$1,$G$1,$D29-N$2/365),(((1+[1]!B_CALC_CURVE_CHINABOND($I$1,$G$1,$D29)/100)^$D29/(1+N$3/100)^(N$2/365))^(1/($D29-N$2/365))-1)*100+模拟分析!$G$12/100)))) -> 0 | O29: =IF(C29="","",C29/((1+E29/100)^(D29-21/365))) -> 0
B30: =IF(B29="","",IF(B29<$E$1,[1]!b_anal_nxcupn($C$1,B29+1),"")) | C30: =IF(B30="",0,IF(模拟分析!$K$9=0,[1]!b_anal_dailycf($C$1,B30),IF(模拟分析!$I$11="否",[1]!b_anal_dailycf($C$1,B30),IF(B30<模拟分析!$K$12,[1]!b_anal_dailycf($C$1,B30),IF(B30=模拟分析!$K$12,[1]!b_anal_dailycf($C$1,B30)+模拟分析!$K$11,0))))) -> 0 | D30: =IF(B30="",0,(-TODAY()+B30)/365) -> 0 | E30: =IF($B30="",0,IF($D30-E$2/365<=0,0,(IF(模拟分析!$I$12="到期平移法",[1]!B_CALC_CURVE_CHINABOND($I$1,$G$1,$D30-E$2/365),(((1+[1]!B_CALC_CURVE_CHINABOND($I$1,$G$1,$D30)/100)^$D30/(1+E$3/100)^(E$2/365))^(1/($D30-E$2/365))-1)*100+模拟分析!$G$12/100)))) -> 0 | F30: =IF($B30="",0,IF($D30-F$2/365<=0,0,(IF(模拟分析!$I$12="到期平移法",[1]!B_CALC_CURVE_CHINABOND($I$1,$G$1,$D30-F$2/365),(((1+[1]!B_CALC_CURVE_CHINABOND($I$1,$G$1,$D30)/100)^$D30/(1+F$3/100)^(F$2/365))^(1/($D30-F$2/365))-1)*100+模拟分析!$G$12/100)))) -> 0 | G30: =IF($B30="",0,IF($D30-G$2/365<=0,0,(IF(模拟分析!$I$12="到期平移法",[1]!B_CALC_CURVE_CHINABOND($I$1,$G$1,$D30-G$2/365),(((1+[1]!B_CALC_CURVE_CHINABOND($I$1,$G$1,$D30)/100)^$D30/(1+G$3/100)^(G$2/365))^(1/($D30-G$2/365))-1)*100+模拟分析!$G$12/100)))) -> 0 | H30: =IF($B30="",0,IF($D30-H$2/365<=0,0,(IF(模拟分析!$I$12="到期平移法",[1]!B_CALC_CURVE_CHINABOND($I$1,$G$1,$D30-H$2/365),(((1+[1]!B_CALC_CURVE_CHINABOND($I$1,$G$1,$D30)/100)^$D30/(1+H$3/100)^(H$2/365))^(1/($D30-H$2/365))-1)*100+模拟分析!$G$12/100)))) -> 0 | I30: =IF($B30="",0,IF($D30-I$2/365<=0,0,(IF(模拟分析!$I$12="到期平移法",[1]!B_CALC_CURVE_CHINABOND($I$1,$G$1,$D30-I$2/365),(((1+[1]!B_CALC_CURVE_CHINABOND($I$1,$G$1,$D30)/100)^$D30/(1+I$3/100)^(I$2/365))^(1/($D30-I$2/365))-1)*100+模拟分析!$G$12/100)))) -> 0 | J30: =IF($B30="",0,IF($D30-J$2/365<=0,0,(IF(模拟分析!$I$12="到期平移法",[1]!B_CALC_CURVE_CHINABOND($I$1,$G$1,$D30-J$2/365),(((1+[1]!B_CALC_CURVE_CHINABOND($I$1,$G$1,$D30)/100)^$D30/(1+J$3/100)^(J$2/365))^(1/($D30-J$2/365))-1)*100+模拟分析!$G$12/100)))) -> 0 | K30: =IF($B30="",0,IF($D30-K$2/365<=0,0,(IF(模拟分析!$I$12="到期平移法",[1]!B_CALC_CURVE_CHINABOND($I$1,$G$1,$D30-K$2/365),(((1+[1]!B_CALC_CURVE_CHINABOND($I$1,$G$1,$D30)/100)^$D30/(1+K$3/100)^(K$2/365))^(1/($D30-K$2/365))-1)*100+模拟分析!$G$12/100)))) -> 0 | L30: =IF($B30="",0,IF($D30-L$2/365<=0,0,(IF(模拟分析!$I$12="到期平移法",[1]!B_CALC_CURVE_CHINABOND($I$1,$G$1,$D30-L$2/365),(((1+[1]!B_CALC_CURVE_CHINABOND($I$1,$G$1,$D30)/100)^$D30/(1+L$3/100)^(L$2/365))^(1/($D30-L$2/365))-1)*100+模拟分析!$G$12/100)))) -> 0 | ... N30: =IF($B30="",0,IF($D30-N$2/365<=0,0,(IF(模拟分析!$I$12="到期平移法",[1]!B_CALC_CURVE_CHINABOND($I$1,$G$1,$D30-N$2/365),(((1+[1]!B_CALC_CURVE_CHINABOND($I$1,$G$1,$D30)/100)^$D30/(1+N$3/100)^(N$2/365))^(1/($D30-N$2/365))-1)*100+模拟分析!$G$12/100)))) -> 0 | O30: =IF(C30="","",C30/((1+E30/100)^(D30-21/365))) -> 0
B31: =IF(B30="","",IF(B30<$E$1,[1]!b_anal_nxcupn($C$1,B30+1),"")) | C31: =IF(B31="",0,IF(模拟分析!$K$9=0,[1]!b_anal_dailycf($C$1,B31),IF(模拟分析!$I$11="否",[1]!b_anal_dailycf($C$1,B31),IF(B31<模拟分析!$K$12,[1]!b_anal_dailycf($C$1,B31),IF(B31=模拟分析!$K$12,[1]!b_anal_dailycf($C$1,B31)+模拟分析!$K$11,0))))) -> 0 | D31: =IF(B31="",0,(-TODAY()+B31)/365) -> 0 | E31: =IF($B31="",0,IF($D31-E$2/365<=0,0,(IF(模拟分析!$I$12="到期平移法",[1]!B_CALC_CURVE_CHINABOND($I$1,$G$1,$D31-E$2/365),(((1+[1]!B_CALC_CURVE_CHINABOND($I$1,$G$1,$D31)/100)^$D31/(1+E$3/100)^(E$2/365))^(1/($D31-E$2/365))-1)*100+模拟分析!$G$12/100)))) -> 0 | F31: =IF($B31="",0,IF($D31-F$2/365<=0,0,(IF(模拟分析!$I$12="到期平移法",[1]!B_CALC_CURVE_CHINABOND($I$1,$G$1,$D31-F$2/365),(((1+[1]!B_CALC_CURVE_CHINABOND($I$1,$G$1,$D31)/100)^$D31/(1+F$3/100)^(F$2/365))^(1/($D31-F$2/365))-1)*100+模拟分析!$G$12/100)))) -> 0 | G31: =IF($B31="",0,IF($D31-G$2/365<=0,0,(IF(模拟分析!$I$12="到期平移法",[1]!B_CALC_CURVE_CHINABOND($I$1,$G$1,$D31-G$2/365),(((1+[1]!B_CALC_CURVE_CHINABOND($I$1,$G$1,$D31)/100)^$D31/(1+G$3/100)^(G$2/365))^(1/($D31-G$2/365))-1)*100+模拟分析!$G$12/100)))) -> 0 | H31: =IF($B31="",0,IF($D31-H$2/365<=0,0,(IF(模拟分析!$I$12="到期平移法",[1]!B_CALC_CURVE_CHINABOND($I$1,$G$1,$D31-H$2/365),(((1+[1]!B_CALC_CURVE_CHINABOND($I$1,$G$1,$D31)/100)^$D31/(1+H$3/100)^(H$2/365))^(1/($D31-H$2/365))-1)*100+模拟分析!$G$12/100)))) -> 0 | I31: =IF($B31="",0,IF($D31-I$2/365<=0,0,(IF(模拟分析!$I$12="到期平移法",[1]!B_CALC_CURVE_CHINABOND($I$1,$G$1,$D31-I$2/365),(((1+[1]!B_CALC_CURVE_CHINABOND($I$1,$G$1,$D31)/100)^$D31/(1+I$3/100)^(I$2/365))^(1/($D31-I$2/365))-1)*100+模拟分析!$G$12/100)))) -> 0 | J31: =IF($B31="",0,IF($D31-J$2/365<=0,0,(IF(模拟分析!$I$12="到期平移法",[1]!B_CALC_CURVE_CHINABOND($I$1,$G$1,$D31-J$2/365),(((1+[1]!B_CALC_CURVE_CHINABOND($I$1,$G$1,$D31)/100)^$D31/(1+J$3/100)^(J$2/365))^(1/($D31-J$2/365))-1)*100+模拟分析!$G$12/100)))) -> 0 | K31: =IF($B31="",0,IF($D31-K$2/365<=0,0,(IF(模拟分析!$I$12="到期平移法",[1]!B_CALC_CURVE_CHINABOND($I$1,$G$1,$D31-K$2/365),(((1+[1]!B_CALC_CURVE_CHINABOND($I$1,$G$1,$D31)/100)^$D31/(1+K$3/100)^(K$2/365))^(1/($D31-K$2/365))-1)*100+模拟分析!$G$12/100)))) -> 0 | L31: =IF($B31="",0,IF($D31-L$2/365<=0,0,(IF(模拟分析!$I$12="到期平移法",[1]!B_CALC_CURVE_CHINABOND($I$1,$G$1,$D31-L$2/365),(((1+[1]!B_CALC_CURVE_CHINABOND($I$1,$G$1,$D31)/100)^$D31/(1+L$3/100)^(L$2/365))^(1/($D31-L$2/365))-1)*100+模拟分析!$G$12/100)))) -> 0 | ... N31: =IF($B31="",0,IF($D31-N$2/365<=0,0,(IF(模拟分析!$I$12="到期平移法",[1]!B_CALC_CURVE_CHINABOND($I$1,$G$1,$D31-N$2/365),(((1+[1]!B_CALC_CURVE_CHINABOND($I$1,$G$1,$D31)/100)^$D31/(1+N$3/100)^(N$2/365))^(1/($D31-N$2/365))-1)*100+模拟分析!$G$12/100)))) -> 0 | O31: =IF(C31="","",C31/((1+E31/100)^(D31-21/365))) -> 0
B32: =IF(B31="","",IF(B31<$E$1,[1]!b_anal_nxcupn($C$1,B31+1),"")) | C32: =IF(B32="",0,IF(模拟分析!$K$9=0,[1]!b_anal_dailycf($C$1,B32),IF(模拟分析!$I$11="否",[1]!b_anal_dailycf($C$1,B32),IF(B32<模拟分析!$K$12,[1]!b_anal_dailycf($C$1,B32),IF(B32=模拟分析!$K$12,[1]!b_anal_dailycf($C$1,B32)+模拟分析!$K$11,0))))) -> 0 | D32: =IF(B32="",0,(-TODAY()+B32)/365) -> 0 | E32: =IF($B32="",0,IF($D32-E$2/365<=0,0,(IF(模拟分析!$I$12="到期平移法",[1]!B_CALC_CURVE_CHINABOND($I$1,$G$1,$D32-E$2/365),(((1+[1]!B_CALC_CURVE_CHINABOND($I$1,$G$1,$D32)/100)^$D32/(1+E$3/100)^(E$2/365))^(1/($D32-E$2/365))-1)*100+模拟分析!$G$12/100)))) -> 0 | F32: =IF($B32="",0,IF($D32-F$2/365<=0,0,(IF(模拟分析!$I$12="到期平移法",[1]!B_CALC_CURVE_CHINABOND($I$1,$G$1,$D32-F$2/365),(((1+[1]!B_CALC_CURVE_CHINABOND($I$1,$G$1,$D32)/100)^$D32/(1+F$3/100)^(F$2/365))^(1/($D32-F$2/365))-1)*100+模拟分析!$G$12/100)))) -> 0 | G32: =IF($B32="",0,IF($D32-G$2/365<=0,0,(IF(模拟分析!$I$12="到期平移法",[1]!B_CALC_CURVE_CHINABOND($I$1,$G$1,$D32-G$2/365),(((1+[1]!B_CALC_CURVE_CHINABOND($I$1,$G$1,$D32)/100)^$D32/(1+G$3/100)^(G$2/365))^(1/($D32-G$2/365))-1)*100+模拟分析!$G$12/100)))) -> 0 | H32: =IF($B32="",0,IF($D32-H$2/365<=0,0,(IF(模拟分析!$I$12="到期平移法",[1]!B_CALC_CURVE_CHINABOND($I$1,$G$1,$D32-H$2/365),(((1+[1]!B_CALC_CURVE_CHINABOND($I$1,$G$1,$D32)/100)^$D32/(1+H$3/100)^(H$2/365))^(1/($D32-H$2/365))-1)*100+模拟分析!$G$12/100)))) -> 0 | I32: =IF($B32="",0,IF($D32-I$2/365<=0,0,(IF(模拟分析!$I$12="到期平移法",[1]!B_CALC_CURVE_CHINABOND($I$1,$G$1,$D32-I$2/365),(((1+[1]!B_CALC_CURVE_CHINABOND($I$1,$G$1,$D32)/100)^$D32/(1+I$3/100)^(I$2/365))^(1/($D32-I$2/365))-1)*100+模拟分析!$G$12/100)))) -> 0 | J32: =IF($B32="",0,IF($D32-J$2/365<=0,0,(IF(模拟分析!$I$12="到期平移法",[1]!B_CALC_CURVE_CHINABOND($I$1,$G$1,$D32-J$2/365),(((1+[1]!B_CALC_CURVE_CHINABOND($I$1,$G$1,$D32)/100)^$D32/(1+J$3/100)^(J$2/365))^(1/($D32-J$2/365))-1)*100+模拟分析!$G$12/100)))) -> 0 | K32: =IF($B32="",0,IF($D32-K$2/365<=0,0,(IF(模拟分析!$I$12="到期平移法",[1]!B_CALC_CURVE_CHINABOND($I$1,$G$1,$D32-K$2/365),(((1+[1]!B_CALC_CURVE_CHINABOND($I$1,$G$1,$D32)/100)^$D32/(1+K$3/100)^(K$2/365))^(1/($D32-K$2/365))-1)*100+模拟分析!$G$12/100)))) -> 0 | L32: =IF($B32="",0,IF($D32-L$2/365<=0,0,(IF(模拟分析!$I$12="到期平移法",[1]!B_CALC_CURVE_CHINABOND($I$1,$G$1,$D32-L$2/365),(((1+[1]!B_CALC_CURVE_CHINABOND($I$1,$G$1,$D32)/100)^$D32/(1+L$3/100)^(L$2/365))^(1/($D32-L$2/365))-1)*100+模拟分析!$G$12/100)))) -> 0 | ... N32: =IF($B32="",0,IF($D32-N$2/365<=0,0,(IF(模拟分析!$I$12="到期平移法",[1]!B_CALC_CURVE_CHINABOND($I$1,$G$1,$D32-N$2/365),(((1+[1]!B_CALC_CURVE_CHINABOND($I$1,$G$1,$D32)/100)^$D32/(1+N$3/100)^(N$2/365))^(1/($D32-N$2/365))-1)*100+模拟分析!$G$12/100)))) -> 0 | O32: =IF(C32="","",C32/((1+E32/100)^(D32-21/365))) -> 0
B33: =IF(B32="","",IF(B32<$E$1,[1]!b_anal_nxcupn($C$1,B32+1),"")) | C33: =IF(B33="",0,IF(模拟分析!$K$9=0,[1]!b_anal_dailycf($C$1,B33),IF(模拟分析!$I$11="否",[1]!b_anal_dailycf($C$1,B33),IF(B33<模拟分析!$K$12,[1]!b_anal_dailycf($C$1,B33),IF(B33=模拟分析!$K$12,[1]!b_anal_dailycf($C$1,B33)+模拟分析!$K$11,0))))) -> 0 | D33: =IF(B33="",0,(-TODAY()+B33)/365) -> 0 | E33: =IF($B33="",0,IF($D33-E$2/365<=0,0,(IF(模拟分析!$I$12="到期平移法",[1]!B_CALC_CURVE_CHINABOND($I$1,$G$1,$D33-E$2/365),(((1+[1]!B_CALC_CURVE_CHINABOND($I$1,$G$1,$D33)/100)^$D33/(1+E$3/100)^(E$2/365))^(1/($D33-E$2/365))-1)*100+模拟分析!$G$12/100)))) -> 0 | F33: =IF($B33="",0,IF($D33-F$2/365<=0,0,(IF(模拟分析!$I$12="到期平移法",[1]!B_CALC_CURVE_CHINABOND($I$1,$G$1,$D33-F$2/365),(((1+[1]!B_CALC_CURVE_CHINABOND($I$1,$G$1,$D33)/100)^$D33/(1+F$3/100)^(F$2/365))^(1/($D33-F$2/365))-1)*100+模拟分析!$G$12/100)))) -> 0 | G33: =IF($B33="",0,IF($D33-G$2/365<=0,0,(IF(模拟分析!$I$12="到期平移法",[1]!B_CALC_CURVE_CHINABOND($I$1,$G$1,$D33-G$2/365),(((1+[1]!B_CALC_CURVE_CHINABOND($I$1,$G$1,$D33)/100)^$D33/(1+G$3/100)^(G$2/365))^(1/($D33-G$2/365))-1)*100+模拟分析!$G$12/100)))) -> 0 | H33: =IF($B33="",0,IF($D33-H$2/365<=0,0,(IF(模拟分析!$I$12="到期平移法",[1]!B_CALC_CURVE_CHINABOND($I$1,$G$1,$D33-H$2/365),(((1+[1]!B_CALC_CURVE_CHINABOND($I$1,$G$1,$D33)/100)^$D33/(1+H$3/100)^(H$2/365))^(1/($D33-H$2/365))-1)*100+模拟分析!$G$12/100)))) -> 0 | I33: =IF($B33="",0,IF($D33-I$2/365<=0,0,(IF(模拟分析!$I$12="到期平移法",[1]!B_CALC_CURVE_CHINABOND($I$1,$G$1,$D33-I$2/365),(((1+[1]!B_CALC_CURVE_CHINABOND($I$1,$G$1,$D33)/100)^$D33/(1+I$3/100)^(I$2/365))^(1/($D33-I$2/365))-1)*100+模拟分析!$G$12/100)))) -> 0 | J33: =IF($B33="",0,IF($D33-J$2/365<=0,0,(IF(模拟分析!$I$12="到期平移法",[1]!B_CALC_CURVE_CHINABOND($I$1,$G$1,$D33-J$2/365),(((1+[1]!B_CALC_CURVE_CHINABOND($I$1,$G$1,$D33)/100)^$D33/(1+J$3/100)^(J$2/365))^(1/($D33-J$2/365))-1)*100+模拟分析!$G$12/100)))) -> 0 | K33: =IF($B33="",0,IF($D33-K$2/365<=0,0,(IF(模拟分析!$I$12="到期平移法",[1]!B_CALC_CURVE_CHINABOND($I$1,$G$1,$D33-K$2/365),(((1+[1]!B_CALC_CURVE_CHINABOND($I$1,$G$1,$D33)/100)^$D33/(1+K$3/100)^(K$2/365))^(1/($D33-K$2/365))-1)*100+模拟分析!$G$12/100)))) -> 0 | L33: =IF($B33="",0,IF($D33-L$2/365<=0,0,(IF(模拟分析!$I$12="到期平移法",[1]!B_CALC_CURVE_CHINABOND($I$1,$G$1,$D33-L$2/365),(((1+[1]!B_CALC_CURVE_CHINABOND($I$1,$G$1,$D33)/100)^$D33/(1+L$3/100)^(L$2/365))^(1/($D33-L$2/365))-1)*100+模拟分析!$G$12/100)))) -> 0 | ... N33: =IF($B33="",0,IF($D33-N$2/365<=0,0,(IF(模拟分析!$I$12="到期平移法",[1]!B_CALC_CURVE_CHINABOND($I$1,$G$1,$D33-N$2/365),(((1+[1]!B_CALC_CURVE_CHINABOND($I$1,$G$1,$D33)/100)^$D33/(1+N$3/100)^(N$2/365))^(1/($D33-N$2/365))-1)*100+模拟分析!$G$12/100)))) -> 0 | O33: =IF(C33="","",C33/((1+E33/100)^(D33-21/365))) -> 0
... B62: =IF(B61="","",IF(B61<$E$1,[1]!b_anal_nxcupn($C$1,B61+1),"")) | C62: =IF(B62="",0,IF(模拟分析!$K$9=0,[1]!b_anal_dailycf($C$1,B62),IF(模拟分析!$I$11="否",[1]!b_anal_dailycf($C$1,B62),IF(B62<模拟分析!$K$12,[1]!b_anal_dailycf($C$1,B62),IF(B62=模拟分析!$K$12,[1]!b_anal_dailycf($C$1,B62)+模拟分析!$K$11,0))))) -> 0 | D62: =IF(B62="",0,(-TODAY()+B62)/365) -> 0 | E62: =IF($B62="",0,IF($D62-E$2/365<=0,0,(IF(模拟分析!$I$12="到期平移法",[1]!B_CALC_CURVE_CHINABOND($I$1,$G$1,$D62-E$2/365),(((1+[1]!B_CALC_CURVE_CHINABOND($I$1,$G$1,$D62)/100)^$D62/(1+E$3/100)^(E$2/365))^(1/($D62-E$2/365))-1)*100+模拟分析!$G$12/100)))) -> 0 | F62: =IF($B62="",0,IF($D62-F$2/365<=0,0,(IF(模拟分析!$I$12="到期平移法",[1]!B_CALC_CURVE_CHINABOND($I$1,$G$1,$D62-F$2/365),(((1+[1]!B_CALC_CURVE_CHINABOND($I$1,$G$1,$D62)/100)^$D62/(1+F$3/100)^(F$2/365))^(1/($D62-F$2/365))-1)*100+模拟分析!$G$12/100)))) -> 0 | G62: =IF($B62="",0,IF($D62-G$2/365<=0,0,(IF(模拟分析!$I$12="到期平移法",[1]!B_CALC_CURVE_CHINABOND($I$1,$G$1,$D62-G$2/365),(((1+[1]!B_CALC_CURVE_CHINABOND($I$1,$G$1,$D62)/100)^$D62/(1+G$3/100)^(G$2/365))^(1/($D62-G$2/365))-1)*100+模拟分析!$G$12/100)))) -> 0 | H62: =IF($B62="",0,IF($D62-H$2/365<=0,0,(IF(模拟分析!$I$12="到期平移法",[1]!B_CALC_CURVE_CHINABOND($I$1,$G$1,$D62-H$2/365),(((1+[1]!B_CALC_CURVE_CHINABOND($I$1,$G$1,$D62)/100)^$D62/(1+H$3/100)^(H$2/365))^(1/($D62-H$2/365))-1)*100+模拟分析!$G$12/100)))) -> 0 | I62: =IF($B62="",0,IF($D62-I$2/365<=0,0,(IF(模拟分析!$I$12="到期平移法",[1]!B_CALC_CURVE_CHINABOND($I$1,$G$1,$D62-I$2/365),(((1+[1]!B_CALC_CURVE_CHINABOND($I$1,$G$1,$D62)/100)^$D62/(1+I$3/100)^(I$2/365))^(1/($D62-I$2/365))-1)*100+模拟分析!$G$12/100)))) -> 0 | J62: =IF($B62="",0,IF($D62-J$2/365<=0,0,(IF(模拟分析!$I$12="到期平移法",[1]!B_CALC_CURVE_CHINABOND($I$1,$G$1,$D62-J$2/365),(((1+[1]!B_CALC_CURVE_CHINABOND($I$1,$G$1,$D62)/100)^$D62/(1+J$3/100)^(J$2/365))^(1/($D62-J$2/365))-1)*100+模拟分析!$G$12/100)))) -> 0 | K62: =IF($B62="",0,IF($D62-K$2/365<=0,0,(IF(模拟分析!$I$12="到期平移法",[1]!B_CALC_CURVE_CHINABOND($I$1,$G$1,$D62-K$2/365),(((1+[1]!B_CALC_CURVE_CHINABOND($I$1,$G$1,$D62)/100)^$D62/(1+K$3/100)^(K$2/365))^(1/($D62-K$2/365))-1)*100+模拟分析!$G$12/100)))) -> 0 | L62: =IF($B62="",0,IF($D62-L$2/365<=0,0,(IF(模拟分析!$I$12="到期平移法",[1]!B_CALC_CURVE_CHINABOND($I$1,$G$1,$D62-L$2/365),(((1+[1]!B_CALC_CURVE_CHINABOND($I$1,$G$1,$D62)/100)^$D62/(1+L$3/100)^(L$2/365))^(1/($D62-L$2/365))-1)*100+模拟分析!$G$12/100)))) -> 0 | ... N62: =IF($B62="",0,IF($D62-N$2/365<=0,0,(IF(模拟分析!$I$12="到期平移法",[1]!B_CALC_CURVE_CHINABOND($I$1,$G$1,$D62-N$2/365),(((1+[1]!B_CALC_CURVE_CHINABOND($I$1,$G$1,$D62)/100)^$D62/(1+N$3/100)^(N$2/365))^(1/($D62-N$2/365))-1)*100+模拟分析!$G$12/100)))) -> 0 | O62: =IF(C62="","",C62/((1+E62/100)^(D62-21/365))) -> 0

Sheet 使用说明
B5: 债券代码 | C5: 220010.IB | D5: 债券简称 | E5: =[1]!b_info_name(C5) -> 22附息国债10 | F5: 票面利率 | G5: =[1]!b_info_couponrate2(C5) -> 2.76 | H5: 付息频率 | I5: =[1]!b_info_interestfrequency(C5) -> 2 | J5: 次/年 | Q5: 编码 | R5: 曲线名称
B6: 信用评级 | C6: =[1]!b_rate_latestcredit(C5) -> 0 | D6: 发行主体 | E6: =[1]!b_info_issuer(C5) -> 中华人民共和国财政部 | F6: 剩余期限(年） | G6: =[1]!b_anal_ptmyear(C5,TODAY()) -> 8.0765027 | H6: 剩余额度 | I6: =[1]!b_info_issueamount(C5)/100000000 -> 1981.6 | J6: 亿 | Q6: 1882 | R6: 固定利率铁道部收益率曲线 | S6: 持有期收益率
Q7: 1802 | R7: 交易所浮动利率企业债(1y)点差收益率曲线(AAA) | S7: 年化收益率
B8: 购买日期 | C8: =TODAY()-1 -> 45398 | D8: 清算速度 | E8: T+0 | F8: 应计利息 | G8: =[1]!b_calc_accrint(C5,I8) -> 1.1601099 | H8: 实际结算日期 | I8: =IF(E8="T+1",C8+1,C8) -> 45398 | J8: 交易日净价 | K8: =[1]!b_dq_originclose(C5,I8,1) -> 103.221 | Q8: 1802 | R8: 交易所浮动利率企业债(1y)点差收益率曲线(AAA)
B9: 购买净价 | C9: 100.0149 | D9: 交易面额（百万） | E9: 500 | F9: 购买全价 | G9: =G8+C9 -> 101.17501 | H9: 交易金额（百万） | I9: =E9*G9/100 -> 505.87505 | J9: 是否含权 | K9: =[1]!b_info_clause(C5) -> 0 | Q9: 1012 | R9: 交易所固定利率国债收益率曲线 | S9: T+0
Q10: 1022 | R10: 交易所固定利率企业债收益率曲线(AAA) | S10: T+1
B11: 资金成本 | C11: 0.1 | D11: 要求收益率 | E11: 0.15 | F11: 曲线选择日 | G11: =TODAY()-1 -> 45398 | H11: 是否行权 | I11: 否 | J11: 行权价格 | K11: =IF(LEFT(K9,2)="赎回",[1]!b_info_redemptionprice(C5),IF(LEFT(K9,2)="回售",[1]!b_info_repurchaseprice(C5),"")) | Q11: 1032 | R11: 央行票据收益率曲线
B12: 折算曲线 | C12: 交易所浮动利率企业债(1y)点差收益率曲线(AAA) | F12: 曲线平移 | G12: 4 | H12: 曲线方法 | I12: 到期平移法 | J12: 行权日期 | K12: =IF(LEFT(K9,2)="赎回",[1]!b_info_redemptiondate(C5),IF(LEFT(K9,2)="回售",[1]!b_info_repurchasedate(C5),"")) | Q12: 1112 | R12: 银行间浮动利率国债点差(1y)收益率曲线
Q13: 1472 | R13: 银行间浮动利率企业债(1y)点差收益率曲线(AA+) | S13: 远期曲线法
B14: 定价情景分析(全价） | Q14: 1122 | R14: 银行间浮动利率企业债(1y)点差收益率曲线(AAA) | S14: 到期平移法
C15: 1d | D15: 7d | E15: 2W | F15: 3W | G15: 1M | H15: 2M | I15: 3M | J15: 5M | K15: 1Y | L15: 365 | M15: Day | Q15: 1132 | R15: 银行间浮动利率企业债(R07D)点差收益率曲线
C16: 1 | D16: 7 | E16: 14 | F16: 21 | G16: 30 | H16: 60 | I16: 90 | J16: 150 | K16: 365 | L16: =L15 -> 365 | Q16: 1412 | R16: 银行间浮动利率企业债(SHIBOR)点差收益率曲线
A17: 0.005 | B17: +50bp | C17: =IF(C$16/365>$G$6,"",SUMPRODUCT(CASH,(1/(1+RATE_1d/100+$A17)^(DUR-C$16/365))*((DUR-C$16/365)>0))) -> 101.15486 | D17: =IF(D$16/365>$G$6,"",SUMPRODUCT(CASH,(1/(1+RATE_7d/100+$A17)^(DUR-D$16/365))*((DUR-D$16/365)>0))) -> 101.18715 | E17: =IF(E$16/365>$G$6,"",SUMPRODUCT(CASH,(1/(1+RATE_2W/100+$A17)^(DUR-E$16/365))*((DUR-E$16/365)>0))) -> 101.22578 | F17: =IF(F$16/365>$G$6,"",SUMPRODUCT(CASH,(1/(1+RATE_3W/100+$A17)^(DUR-F$16/365))*((DUR-F$16/365)>0))) -> 101.26545 | G17: =IF(G$16/365>$G$6,"",SUMPRODUCT(CASH,(1/(1+RATE_1M/100+$A17)^(DUR-G$16/365))*((DUR-G$16/365)>0))) -> 99.937679 | H17: =IF(H$16/365>$G$6,"",SUMPRODUCT(CASH,(1/(1+RATE_2M/100+$A17)^(DUR-H$16/365))*((DUR-H$16/365)>0))) -> 100.10808 | I17: =IF(I$16/365>$G$6,"",SUMPRODUCT(CASH,(1/(1+RATE_3M/100+$A17)^(DUR-I$16/365))*((DUR-I$16/365)>0))) -> 100.27723 | J17: =IF(J$16/365>$G$6,"",SUMPRODUCT(CASH,(1/(1+RATE_5M/100+$A17)^(DUR-J$16/365))*((DUR-J$16/365)>0))) -> 100.63359 | K17: =IF(K$16/365>$G$6,"",SUMPRODUCT(CASH,(1/(1+RATE_1Y/100+$A17)^(DUR-K$16/365))*((DUR-K$16/365)>0))) -> 100.62624 | L17: =IF(L$16/365>$G$6,"",SUMPRODUCT(CASH,(1/(1+RATE_XD/100+$A17)^(DUR-L$16/365))*((DUR-L$16/365)>0))) -> 100.62624 | Q17: 1862 | R17: 银行间浮动利率企业债(SHIBOR_1Y_10D)点差收益率曲线(AA+(2)) | S17: 是
A18: 0.003 | B18: +30bp | C18: =IF(C$16/365>$G$6,"",SUMPRODUCT(CASH,(1/(1+RATE_1d/100+$A18)^(DUR-C$16/365))*((DUR-C$16/365)>0))) -> 102.58608 | D18: =IF(D$16/365>$G$6,"",SUMPRODUCT(CASH,(1/(1+RATE_7d/100+$A18)^(DUR-D$16/365))*((DUR-D$16/365)>0))) -> 102.61552 | E18: =IF(E$16/365>$G$6,"",SUMPRODUCT(CASH,(1/(1+RATE_2W/100+$A18)^(DUR-E$16/365))*((DUR-E$16/365)>0))) -> 102.65083 | F18: =IF(F$16/365>$G$6,"",SUMPRODUCT(CASH,(1/(1+RATE_3W/100+$A18)^(DUR-F$16/365))*((DUR-F$16/365)>0))) -> 102.6872 | G18: =IF(G$16/365>$G$6,"",SUMPRODUCT(CASH,(1/(1+RATE_1M/100+$A18)^(DUR-G$16/365))*((DUR-G$16/365)>0))) -> 101.35521 | H18: =IF(H$16/365>$G$6,"",SUMPRODUCT(CASH,(1/(1+RATE_2M/100+$A18)^(DUR-H$16/365))*((DUR-H$16/365)>0))) -> 101.51167 | I18: =IF(I$16/365>$G$6,"",SUMPRODUCT(CASH,(1/(1+RATE_3M/100+$A18)^(DUR-I$16/365))*((DUR-I$16/365)>0))) -> 101.6668 | J18: =IF(J$16/365>$G$6,"",SUMPRODUCT(CASH,(1/(1+RATE_5M/100+$A18)^(DUR-J$16/365))*((DUR-J$16/365)>0))) -> 101.99524 | K18: =IF(K$16/365>$G$6,"",SUMPRODUCT(CASH,(1/(1+RATE_1Y/100+$A18)^(DUR-K$16/365))*((DUR-K$16/365)>0))) -> 101.88873 | L18: =IF(L$16/365>$G$6,"",SUMPRODUCT(CASH,(1/(1+RATE_XD/100+$A18)^(DUR-L$16/365))*((DUR-L$16/365)>0))) -> 101.88873 | Q18: 1142 | R18: 银行间浮动利率商业银行债(1y)点差收益率曲线(AA) | S18: 否
A19: 0.002 | B19: +20bp | C19: =IF(C$16/365>$G$6,"",SUMPRODUCT(CASH,(1/(1+RATE_1d/100+$A19)^(DUR-C$16/365))*((DUR-C$16/365)>0))) -> 103.31094 | D19: =IF(D$16/365>$G$6,"",SUMPRODUCT(CASH,(1/(1+RATE_7d/100+$A19)^(DUR-D$16/365))*((DUR-D$16/365)>0))) -> 103.33891 | E19: =IF(E$16/365>$G$6,"",SUMPRODUCT(CASH,(1/(1+RATE_2W/100+$A19)^(DUR-E$16/365))*((DUR-E$16/365)>0))) -> 103.37252 | F19: =IF(F$16/365>$G$6,"",SUMPRODUCT(CASH,(1/(1+RATE_3W/100+$A19)^(DUR-F$16/365))*((DUR-F$16/365)>0))) -> 103.40719 | G19: =IF(G$16/365>$G$6,"",SUMPRODUCT(CASH,(1/(1+RATE_1M/100+$A19)^(DUR-G$16/365))*((DUR-G$16/365)>0))) -> 102.07305 | H19: =IF(H$16/365>$G$6,"",SUMPRODUCT(CASH,(1/(1+RATE_2M/100+$A19)^(DUR-H$16/365))*((DUR-H$16/365)>0))) -> 102.22237 | I19: =IF(I$16/365>$G$6,"",SUMPRODUCT(CASH,(1/(1+RATE_3M/100+$A19)^(DUR-I$16/365))*((DUR-I$16/365)>0))) -> 102.37032 | J19: =IF(J$16/365>$G$6,"",SUMPRODUCT(CASH,(1/(1+RATE_5M/100+$A19)^(DUR-J$16/365))*((DUR-J$16/365)>0))) -> 102.68448 | K19: =IF(K$16/365>$G$6,"",SUMPRODUCT(CASH,(1/(1+RATE_1Y/100+$A19)^(DUR-K$16/365))*((DUR-K$16/365)>0))) -> 102.52725 | L19: =IF(L$16/365>$G$6,"",SUMPRODUCT(CASH,(1/(1+RATE_XD/100+$A19)^(DUR-L$16/365))*((DUR-L$16/365)>0))) -> 102.52725 | Q19: 1152 | R19: 银行间浮动利率商业银行债(1y)点差收益率曲线(AA-)
A20: 0.0015 | B20: +15bp | C20: =IF(C$16/365>$G$6,"",SUMPRODUCT(CASH,(1/(1+RATE_1d/100+$A20)^(DUR-C$16/365))*((DUR-C$16/365)>0))) -> 103.6757 | D20: =IF(D$16/365>$G$6,"",SUMPRODUCT(CASH,(1/(1+RATE_7d/100+$A20)^(DUR-D$16/365))*((DUR-D$16/365)>0))) -> 103.70293 | E20: =IF(E$16/365>$G$6,"",SUMPRODUCT(CASH,(1/(1+RATE_2W/100+$A20)^(DUR-E$16/365))*((DUR-E$16/365)>0))) -> 103.73569 | F20: =IF(F$16/365>$G$6,"",SUMPRODUCT(CASH,(1/(1+RATE_3W/100+$A20)^(DUR-F$16/365))*((DUR-F$16/365)>0))) -> 103.7695 | G20: =IF(G$16/365>$G$6,"",SUMPRODUCT(CASH,(1/(1+RATE_1M/100+$A20)^(DUR-G$16/365))*((DUR-G$16/365)>0))) -> 102.43426 | H20: =IF(H$16/365>$G$6,"",SUMPRODUCT(CASH,(1/(1+RATE_2M/100+$A20)^(DUR-H$16/365))*((DUR-H$16/365)>0))) -> 102.57997 | I20: =IF(I$16/365>$G$6,"",SUMPRODUCT(CASH,(1/(1+RATE_3M/100+$A20)^(DUR-I$16/365))*((DUR-I$16/365)>0))) -> 102.72429 | J20: =IF(J$16/365>$G$6,"",SUMPRODUCT(CASH,(1/(1+RATE_5M/100+$A20)^(DUR-J$16/365))*((DUR-J$16/365)>0))) -> 103.03122 | K20: =IF(K$16/365>$G$6,"",SUMPRODUCT(CASH,(1/(1+RATE_1Y/100+$A20)^(DUR-K$16/365))*((DUR-K$16/365)>0))) -> 102.84835 | L20: =IF(L$16/365>$G$6,"",SUMPRODUCT(CASH,(1/(1+RATE_XD/100+$A20)^(DUR-L$16/365))*((DUR-L$16/365)>0))) -> 102.84835 | Q20: 1922 | R20: 银行间浮动利率商业银行债(1y)点差收益率曲线(AA+)
A21: 0.001 | B21: +10bp | C21: =IF(C$16/365>$G$6,"",SUMPRODUCT(CASH,(1/(1+RATE_1d/100+$A21)^(DUR-C$16/365))*((DUR-C$16/365)>0))) -> 104.04203 | D21: =IF(D$16/365>$G$6,"",SUMPRODUCT(CASH,(1/(1+RATE_7d/100+$A21)^(DUR-D$16/365))*((DUR-D$16/365)>0))) -> 104.06851 | E21: =IF(E$16/365>$G$6,"",SUMPRODUCT(CASH,(1/(1+RATE_2W/100+$A21)^(DUR-E$16/365))*((DUR-E$16/365)>0))) -> 104.1004 | F21: =IF(F$16/365>$G$6,"",SUMPRODUCT(CASH,(1/(1+RATE_3W/100+$A21)^(DUR-F$16/365))*((DUR-F$16/365)>0))) -> 104.13335 | G21: =IF(G$16/365>$G$6,"",SUMPRODUCT(CASH,(1/(1+RATE_1M/100+$A21)^(DUR-G$16/365))*((DUR-G$16/365)>0))) -> 102.79701 | H21: =IF(H$16/365>$G$6,"",SUMPRODUCT(CASH,(1/(1+RATE_2M/100+$A21)^(DUR-H$16/365))*((DUR-H$16/365)>0))) -> 102.93908 | I21: =IF(I$16/365>$G$6,"",SUMPRODUCT(CASH,(1/(1+RATE_3M/100+$A21)^(DUR-I$16/365))*((DUR-I$16/365)>0))) -> 103.07973 | J21: =IF(J$16/365>$G$6,"",SUMPRODUCT(CASH,(1/(1+RATE_5M/100+$A21)^(DUR-J$16/365))*((DUR-J$16/365)>0))) -> 103.37938 | K21: =IF(K$16/365>$G$6,"",SUMPRODUCT(CASH,(1/(1+RATE_1Y/100+$A21)^(DUR-K$16/365))*((DUR-K$16/365)>0))) -> 103.17068 | L21: =IF(L$16/365>$G$6,"",SUMPRODUCT(CASH,(1/(1+RATE_XD/100+$A21)^(DUR-L$16/365))*((DUR-L$16/365)>0))) -> 103.17068 | Q21: 1162 | R21: 银行间浮动利率商业银行债(1y)点差收益率曲线(AAA)
A22: 0.0005 | B22: +5bp | C22: =IF(C$16/365>$G$6,"",SUMPRODUCT(CASH,(1/(1+RATE_1d/100+$A22)^(DUR-C$16/365))*((DUR-C$16/365)>0))) -> 104.40993 | D22: =IF(D$16/365>$G$6,"",SUMPRODUCT(CASH,(1/(1+RATE_7d/100+$A22)^(DUR-D$16/365))*((DUR-D$16/365)>0))) -> 104.43567 | E22: =IF(E$16/365>$G$6,"",SUMPRODUCT(CASH,(1/(1+RATE_2W/100+$A22)^(DUR-E$16/365))*((DUR-E$16/365)>0))) -> 104.46668 | F22: =IF(F$16/365>$G$6,"",SUMPRODUCT(CASH,(1/(1+RATE_3W/100+$A22)^(DUR-F$16/365))*((DUR-F$16/365)>0))) -> 104.49876 | G22: =IF(G$16/365>$G$6,"",SUMPRODUCT(CASH,(1/(1+RATE_1M/100+$A22)^(DUR-G$16/365))*((DUR-G$16/365)>0))) -> 103.16131 | H22: =IF(H$16/365>$G$6,"",SUMPRODUCT(CASH,(1/(1+RATE_2M/100+$A22)^(DUR-H$16/365))*((DUR-H$16/365)>0))) -> 103.2997 | I22: =IF(I$16/365>$G$6,"",SUMPRODUCT(CASH,(1/(1+RATE_3M/100+$A22)^(DUR-I$16/365))*((DUR-I$16/365)>0))) -> 103.43667 | J22: =IF(J$16/365>$G$6,"",SUMPRODUCT(CASH,(1/(1+RATE_5M/100+$A22)^(DUR-J$16/365))*((DUR-J$16/365)>0))) -> 103.72898 | K22: =IF(K$16/365>$G$6,"",SUMPRODUCT(CASH,(1/(1+RATE_1Y/100+$A22)^(DUR-K$16/365))*((DUR-K$16/365)>0))) -> 103.49425 | L22: =IF(L$16/365>$G$6,"",SUMPRODUCT(CASH,(1/(1+RATE_XD/100+$A22)^(DUR-L$16/365))*((DUR-L$16/365)>0))) -> 103.49425 | Q22: 1172 | R22: 银行间浮动利率商业银行债(R07D)点差收益率曲线(AAA)
A23: 0 | B23: 0bp | C23: =IF(C$16/365>$G$6,"",SUMPRODUCT(CASH,(1/(1+RATE_1d/100+$A23)^(DUR-C$16/365))*((DUR-C$16/365)>0))) -> 104.77941 | D23: =IF(D$16/365>$G$6,"",SUMPRODUCT(CASH,(1/(1+RATE_7d/100+$A23)^(DUR-D$16/365))*((DUR-D$16/365)>0))) -> 104.80439 | E23: =IF(E$16/365>$G$6,"",SUMPRODUCT(CASH,(1/(1+RATE_2W/100+$A23)^(DUR-E$16/365))*((DUR-E$16/365)>0))) -> 104.83453 | F23: =IF(F$16/365>$G$6,"",SUMPRODUCT(CASH,(1/(1+RATE_3W/100+$A23)^(DUR-F$16/365))*((DUR-F$16/365)>0))) -> 104.86573 | G23: =IF(G$16/365>$G$6,"",SUMPRODUCT(CASH,(1/(1+RATE_1M/100+$A23)^(DUR-G$16/365))*((DUR-G$16/365)>0))) -> 103.52716 | H23: =IF(H$16/365>$G$6,"",SUMPRODUCT(CASH,(1/(1+RATE_2M/100+$A23)^(DUR-H$16/365))*((DUR-H$16/365)>0))) -> 103.66185 | I23: =IF(I$16/365>$G$6,"",SUMPRODUCT(CASH,(1/(1+RATE_3M/100+$A23)^(DUR-I$16/365))*((DUR-I$16/365)>0))) -> 103.7951 | J23: =IF(J$16/365>$G$6,"",SUMPRODUCT(CASH,(1/(1+RATE_5M/100+$A23)^(DUR-J$16/365))*((DUR-J$16/365)>0))) -> 104.08001 | K23: =IF(K$16/365>$G$6,"",SUMPRODUCT(CASH,(1/(1+RATE_1Y/100+$A23)^(DUR-K$16/365))*((DUR-K$16/365)>0))) -> 103.81906 | L23: =IF(L$16/365>$G$6,"",SUMPRODUCT(CASH,(1/(1+RATE_XD/100+$A23)^(DUR-L$16/365))*((DUR-L$16/365)>0))) -> 103.81906 | Q23: 1702 | R23: 银行间浮动利率商业银行债(SHIBOR)点差收益率曲线(AA)
A24: -0.0005 | B24: -5bp | C24: =IF(C$16/365>$G$6,"",SUMPRODUCT(CASH,(1/(1+RATE_1d/100+$A24)^(DUR-C$16/365))*((DUR-C$16/365)>0))) -> 105.15049 | D24: =IF(D$16/365>$G$6,"",SUMPRODUCT(CASH,(1/(1+RATE_7d/100+$A24)^(DUR-D$16/365))*((DUR-D$16/365)>0))) -> 105.17471 | E24: =IF(E$16/365>$G$6,"",SUMPRODUCT(CASH,(1/(1+RATE_2W/100+$A24)^(DUR-E$16/365))*((DUR-E$16/365)>0))) -> 105.20395 | F24: =IF(F$16/365>$G$6,"",SUMPRODUCT(CASH,(1/(1+RATE_3W/100+$A24)^(DUR-F$16/365))*((DUR-F$16/365)>0))) -> 105.23427 | G24: =IF(G$16/365>$G$6,"",SUMPRODUCT(CASH,(1/(1+RATE_1M/100+$A24)^(DUR-G$16/365))*((DUR-G$16/365)>0))) -> 103.89458 | H24: =IF(H$16/365>$G$6,"",SUMPRODUCT(CASH,(1/(1+RATE_2M/100+$A24)^(DUR-H$16/365))*((DUR-H$16/365)>0))) -> 104.02554 | I24: =IF(I$16/365>$G$6,"",SUMPRODUCT(CASH,(1/(1+RATE_3M/100+$A24)^(DUR-I$16/365))*((DUR-I$16/365)>0))) -> 104.15504 | J24: =IF(J$16/365>$G$6,"",SUMPRODUCT(CASH,(1/(1+RATE_5M/100+$A24)^(DUR-J$16/365))*((DUR-J$16/365)>0))) -> 104.43249 | K24: =IF(K$16/365>$G$6,"",SUMPRODUCT(CASH,(1/(1+RATE_1Y/100+$A24)^(DUR-K$16/365))*((DUR-K$16/365)>0))) -> 104.14512 | L24: =IF(L$16/365>$G$6,"",SUMPRODUCT(CASH,(1/(1+RATE_XD/100+$A24)^(DUR-L$16/365))*((DUR-L$16/365)>0))) -> 104.14512 | Q24: 1402 | R24: 银行间浮动利率商业银行债(SHIBOR)点差收益率曲线(AAA)
A25: -0.001 | B25: -10bp | C25: =IF(C$16/365>$G$6,"",SUMPRODUCT(CASH,(1/(1+RATE_1d/100+$A25)^(DUR-C$16/365))*((DUR-C$16/365)>0))) -> 105.52317 | D25: =IF(D$16/365>$G$6,"",SUMPRODUCT(CASH,(1/(1+RATE_7d/100+$A25)^(DUR-D$16/365))*((DUR-D$16/365)>0))) -> 105.54661 | E25: =IF(E$16/365>$G$6,"",SUMPRODUCT(CASH,(1/(1+RATE_2W/100+$A25)^(DUR-E$16/365))*((DUR-E$16/365)>0))) -> 105.57496 | F25: =IF(F$16/365>$G$6,"",SUMPRODUCT(CASH,(1/(1+RATE_3W/100+$A25)^(DUR-F$16/365))*((DUR-F$16/365)>0))) -> 105.60439 | G25: =IF(G$16/365>$G$6,"",SUMPRODUCT(CASH,(1/(1+RATE_1M/100+$A25)^(DUR-G$16/365))*((DUR-G$16/365)>0))) -> 104.26356 | H25: =IF(H$16/365>$G$6,"",SUMPRODUCT(CASH,(1/(1+RATE_2M/100+$A25)^(DUR-H$16/365))*((DUR-H$16/365)>0))) -> 104.39076 | I25: =IF(I$16/365>$G$6,"",SUMPRODUCT(CASH,(1/(1+RATE_3M/100+$A25)^(DUR-I$16/365))*((DUR-I$16/365)>0))) -> 104.51648 | J25: =IF(J$16/365>$G$6,"",SUMPRODUCT(CASH,(1/(1+RATE_5M/100+$A25)^(DUR-J$16/365))*((DUR-J$16/365)>0))) -> 104.78642 | K25: =IF(K$16/365>$G$6,"",SUMPRODUCT(CASH,(1/(1+RATE_1Y/100+$A25)^(DUR-K$16/365))*((DUR-K$16/365)>0))) -> 104.47244 | L25: =IF(L$16/365>$G$6,"",SUMPRODUCT(CASH,(1/(1+RATE_XD/100+$A25)^(DUR-L$16/365))*((DUR-L$16/365)>0))) -> 104.47244 | Q25: 1182 | R25: 银行间浮动利率资产支持证券(1y)点差收益率曲线(A)
A26: -0.0015 | B26: -15bp | C26: =IF(C$16/365>$G$6,"",SUMPRODUCT(CASH,(1/(1+RATE_1d/100+$A26)^(DUR-C$16/365))*((DUR-C$16/365)>0))) -> 105.89744 | D26: =IF(D$16/365>$G$6,"",SUMPRODUCT(CASH,(1/(1+RATE_7d/100+$A26)^(DUR-D$16/365))*((DUR-D$16/365)>0))) -> 105.92011 | E26: =IF(E$16/365>$G$6,"",SUMPRODUCT(CASH,(1/(1+RATE_2W/100+$A26)^(DUR-E$16/365))*((DUR-E$16/365)>0))) -> 105.94756 | F26: =IF(F$16/365>$G$6,"",SUMPRODUCT(CASH,(1/(1+RATE_3W/100+$A26)^(DUR-F$16/365))*((DUR-F$16/365)>0))) -> 105.9761 | G26: =IF(G$16/365>$G$6,"",SUMPRODUCT(CASH,(1/(1+RATE_1M/100+$A26)^(DUR-G$16/365))*((DUR-G$16/365)>0))) -> 104.63412 | H26: =IF(H$16/365>$G$6,"",SUMPRODUCT(CASH,(1/(1+RATE_2M/100+$A26)^(DUR-H$16/365))*((DUR-H$16/365)>0))) -> 104.75753 | I26: =IF(I$16/365>$G$6,"",SUMPRODUCT(CASH,(1/(1+RATE_3M/100+$A26)^(DUR-I$16/365))*((DUR-I$16/365)>0))) -> 104.87944 | J26: =IF(J$16/365>$G$6,"",SUMPRODUCT(CASH,(1/(1+RATE_5M/100+$A26)^(DUR-J$16/365))*((DUR-J$16/365)>0))) -> 105.14181 | K26: =IF(K$16/365>$G$6,"",SUMPRODUCT(CASH,(1/(1+RATE_1Y/100+$A26)^(DUR-K$16/365))*((DUR-K$16/365)>0))) -> 104.80102 | L26: =IF(L$16/365>$G$6,"",SUMPRODUCT(CASH,(1/(1+RATE_XD/100+$A26)^(DUR-L$16/365))*((DUR-L$16/365)>0))) -> 104.80102 | Q26: 1192 | R26: 银行间浮动利率资产支持证券(R07D)点差收益率曲线(A)
A27: -0.002 | B27: -20bp | C27: =IF(C$16/365>$G$6,"",SUMPRODUCT(CASH,(1/(1+RATE_1d/100+$A27)^(DUR-C$16/365))*((DUR-C$16/365)>0))) -> 106.27334 | D27: =IF(D$16/365>$G$6,"",SUMPRODUCT(CASH,(1/(1+RATE_7d/100+$A27)^(DUR-D$16/365))*((DUR-D$16/365)>0))) -> 106.29523 | E27: =IF(E$16/365>$G$6,"",SUMPRODUCT(CASH,(1/(1+RATE_2W/100+$A27)^(DUR-E$16/365))*((DUR-E$16/365)>0))) -> 106.32177 | F27: =IF(F$16/365>$G$6,"",SUMPRODUCT(CASH,(1/(1+RATE_3W/100+$A27)^(DUR-F$16/365))*((DUR-F$16/365)>0))) -> 106.34939 | G27: =IF(G$16/365>$G$6,"",SUMPRODUCT(CASH,(1/(1+RATE_1M/100+$A27)^(DUR-G$16/365))*((DUR-G$16/365)>0))) -> 105.00626 | H27: =IF(H$16/365>$G$6,"",SUMPRODUCT(CASH,(1/(1+RATE_2M/100+$A27)^(DUR-H$16/365))*((DUR-H$16/365)>0))) -> 105.12585 | I27: =IF(I$16/365>$G$6,"",SUMPRODUCT(CASH,(1/(1+RATE_3M/100+$A27)^(DUR-I$16/365))*((DUR-I$16/365)>0))) -> 105.24393 | J27: =IF(J$16/365>$G$6,"",SUMPRODUCT(CASH,(1/(1+RATE_5M/100+$A27)^(DUR-J$16/365))*((DUR-J$16/365)>0))) -> 105.49866 | K27: =IF(K$16/365>$G$6,"",SUMPRODUCT(CASH,(1/(1+RATE_1Y/100+$A27)^(DUR-K$16/365))*((DUR-K$16/365)>0))) -> 105.13086 | L27: =IF(L$16/365>$G$6,"",SUMPRODUCT(CASH,(1/(1+RATE_XD/100+$A27)^(DUR-L$16/365))*((DUR-L$16/365)>0))) -> 105.13086 | Q27: 1202 | R27: 银行间浮动利率资产支持证券(R07D)点差收益率曲线(AAA)
A28: -0.003 | B28: -30bp | C28: =IF(C$16/365>$G$6,"",SUMPRODUCT(CASH,(1/(1+RATE_1d/100+$A28)^(DUR-C$16/365))*((DUR-C$16/365)>0))) -> 107.03 | D28: =IF(D$16/365>$G$6,"",SUMPRODUCT(CASH,(1/(1+RATE_7d/100+$A28)^(DUR-D$16/365))*((DUR-D$16/365)>0))) -> 107.0503 | E28: =IF(E$16/365>$G$6,"",SUMPRODUCT(CASH,(1/(1+RATE_2W/100+$A28)^(DUR-E$16/365))*((DUR-E$16/365)>0))) -> 107.075 | F28: =IF(F$16/365>$G$6,"",SUMPRODUCT(CASH,(1/(1+RATE_3W/100+$A28)^(DUR-F$16/365))*((DUR-F$16/365)>0))) -> 107.1008 | G28: =IF(G$16/365>$G$6,"",SUMPRODUCT(CASH,(1/(1+RATE_1M/100+$A28)^(DUR-G$16/365))*((DUR-G$16/365)>0))) -> 105.75533 | H28: =IF(H$16/365>$G$6,"",SUMPRODUCT(CASH,(1/(1+RATE_2M/100+$A28)^(DUR-H$16/365))*((DUR-H$16/365)>0))) -> 105.86718 | I28: =IF(I$16/365>$G$6,"",SUMPRODUCT(CASH,(1/(1+RATE_3M/100+$A28)^(DUR-I$16/365))*((DUR-I$16/365)>0))) -> 105.9775 | J28: =IF(J$16/365>$G$6,"",SUMPRODUCT(CASH,(1/(1+RATE_5M/100+$A28)^(DUR-J$16/365))*((DUR-J$16/365)>0))) -> 106.2168 | K28: =IF(K$16/365>$G$6,"",SUMPRODUCT(CASH,(1/(1+RATE_1Y/100+$A28)^(DUR-K$16/365))*((DUR-K$16/365)>0))) -> 105.79436 | L28: =IF(L$16/365>$G$6,"",SUMPRODUCT(CASH,(1/(1+RATE_XD/100+$A28)^(DUR-L$16/365))*((DUR-L$16/365)>0))) -> 105.79436 | Q28: 1212 | R28: 银行间浮动利率资产支持证券(R07D)点差收益率曲线(BBB)
A29: -0.005 | B29: -50bp | C29: =IF(C$16/365>$G$6,"",SUMPRODUCT(CASH,(1/(1+RATE_1d/100+$A29)^(DUR-C$16/365))*((DUR-C$16/365)>0))) -> 108.56302 | D29: =IF(D$16/365>$G$6,"",SUMPRODUCT(CASH,(1/(1+RATE_7d/100+$A29)^(DUR-D$16/365))*((DUR-D$16/365)>0))) -> 108.58009 | E29: =IF(E$16/365>$G$6,"",SUMPRODUCT(CASH,(1/(1+RATE_2W/100+$A29)^(DUR-E$16/365))*((DUR-E$16/365)>0))) -> 108.60102 | F29: =IF(F$16/365>$G$6,"",SUMPRODUCT(CASH,(1/(1+RATE_3W/100+$A29)^(DUR-F$16/365))*((DUR-F$16/365)>0))) -> 108.62307 | G29: =IF(G$16/365>$G$6,"",SUMPRODUCT(CASH,(1/(1+RATE_1M/100+$A29)^(DUR-G$16/365))*((DUR-G$16/365)>0))) -> 107.27281 | H29: =IF(H$16/365>$G$6,"",SUMPRODUCT(CASH,(1/(1+RATE_2M/100+$A29)^(DUR-H$16/365))*((DUR-H$16/365)>0))) -> 107.36883 | I29: =IF(I$16/365>$G$6,"",SUMPRODUCT(CASH,(1/(1+RATE_3M/100+$A29)^(DUR-I$16/365))*((DUR-I$16/365)>0))) -> 107.46325 | J29: =IF(J$16/365>$G$6,"",SUMPRODUCT(CASH,(1/(1+RATE_5M/100+$A29)^(DUR-J$16/365))*((DUR-J$16/365)>0))) -> 107.67094 | K29: =IF(K$16/365>$G$6,"",SUMPRODUCT(CASH,(1/(1+RATE_1Y/100+$A29)^(DUR-K$16/365))*((DUR-K$16/365)>0))) -> 107.13679 | L29: =IF(L$16/365>$G$6,"",SUMPRODUCT(CASH,(1/(1+RATE_XD/100+$A29)^(DUR-L$16/365))*((DUR-L$16/365)>0))) -> 107.13679 | Q29: 1422 | R29: 银行间浮动利率资产支持证券点差(1y)收益率曲线(A+)
A30: =B30/10000 -> 0.001 | B30: 10 | C30: =IF(C$16/365>$G$6,"",SUMPRODUCT(CASH,(1/(1+RATE_1d/100+$A30)^(DUR-C$16/365))*((DUR-C$16/365)>0))) -> 104.04203 | D30: =IF(D$16/365>$G$6,"",SUMPRODUCT(CASH,(1/(1+RATE_7d/100+$A30)^(DUR-D$16/365))*((DUR-D$16/365)>0))) -> 104.06851 | E30: =IF(E$16/365>$G$6,"",SUMPRODUCT(CASH,(1/(1+RATE_2W/100+$A30)^(DUR-E$16/365))*((DUR-E$16/365)>0))) -> 104.1004 | F30: =IF(F$16/365>$G$6,"",SUMPRODUCT(CASH,(1/(1+RATE_3W/100+$A30)^(DUR-F$16/365))*((DUR-F$16/365)>0))) -> 104.13335 | G30: =IF(G$16/365>$G$6,"",SUMPRODUCT(CASH,(1/(1+RATE_1M/100+$A30)^(DUR-G$16/365))*((DUR-G$16/365)>0))) -> 102.79701 | H30: =IF(H$16/365>$G$6,"",SUMPRODUCT(CASH,(1/(1+RATE_2M/100+$A30)^(DUR-H$16/365))*((DUR-H$16/365)>0))) -> 102.93908 | I30: =IF(I$16/365>$G$6,"",SUMPRODUCT(CASH,(1/(1+RATE_3M/100+$A30)^(DUR-I$16/365))*((DUR-I$16/365)>0))) -> 103.07973 | J30: =IF(J$16/365>$G$6,"",SUMPRODUCT(CASH,(1/(1+RATE_5M/100+$A30)^(DUR-J$16/365))*((DUR-J$16/365)>0))) -> 103.37938 | K30: =IF(K$16/365>$G$6,"",SUMPRODUCT(CASH,(1/(1+RATE_1Y/100+$A30)^(DUR-K$16/365))*((DUR-K$16/365)>0))) -> 103.17068 | L30: =IF(L$16/365>$G$6,"",SUMPRODUCT(CASH,(1/(1+RATE_XD/100+$A30)^(DUR-L$16/365))*((DUR-L$16/365)>0))) -> 103.17068 | Q30: 1812 | R30: 银行间浮动利率资产支持证券点差(1y)收益率曲线(AA-)
Q31: 1222 | R31: 银行间浮动利率资产支持证券点差(1y)收益率曲线(AAA)
B32: 收益类型 | C32: 年化收益率 | Q32: 1432 | R32: 银行间浮动利率资产支持证券点差(1y)收益率曲线(BBB)
B33: 投资超额收益分析 | Q33: 1232 | R33: 银行间固定利率国债收益率曲线
C34: 1d | D34: 7d | E34: 2W | F34: 3W | G34: 1M | H34: 2M | I34: 3M | J34: 5M | K34: 1Y | L34: =L15&"d" -> 365d | Q34: 1242 | R34: 银行间固定利率美元债券收益率曲线
B35: +50bp | C35: =IF(C17="","",IF($C$32="年化收益率",((SUMPRODUCT(((DUR-C$16/365)<0)*CASH)+C17-$G$9*(1+C$16*$C$11/365))/$G$9)*365/C$16,((SUMPRODUCT(((DUR-C$16/365)<0)*CASH)+C17-$G$9*(1+C$16*$C$11/365))/$G$9))) -> -0.17269783 | D35: =IF(D17="","",IF($C$32="年化收益率",((SUMPRODUCT(((DUR-D$16/365)<0)*CASH)+D17-$G$9*(1+D$16*$C$11/365))/$G$9)*365/D$16,((SUMPRODUCT(((DUR-D$16/365)<0)*CASH)+D17-$G$9*(1+D$16*$C$11/365))/$G$9))) -> -0.093743646 | E35: =IF(E17="","",IF($C$32="年化收益率",((SUMPRODUCT(((DUR-E$16/365)<0)*CASH)+E17-$G$9*(1+E$16*$C$11/365))/$G$9)*365/E$16,((SUMPRODUCT(((DUR-E$16/365)<0)*CASH)+E17-$G$9*(1+E$16*$C$11/365))/$G$9))) -> -0.086916805 | F35: =IF(F17="","",IF($C$32="年化收益率",((SUMPRODUCT(((DUR-F$16/365)<0)*CASH)+F17-$G$9*(1+F$16*$C$11/365))/$G$9)*365/F$16,((SUMPRODUCT(((DUR-F$16/365)<0)*CASH)+F17-$G$9*(1+F$16*$C$11/365))/$G$9))) -> -0.084463497 | G35: =IF(G17="","",IF($C$32="年化收益率",((SUMPRODUCT(((DUR-G$16/365)<0)*CASH)+G17-$G$9*(1+G$16*$C$11/365))/$G$9)*365/G$16,((SUMPRODUCT(((DUR-G$16/365)<0)*CASH)+G17-$G$9*(1+G$16*$C$11/365))/$G$9))) -> -0.082843569 | H35: =IF(H17="","",IF($C$32="年化收益率",((SUMPRODUCT(((DUR-H$16/365)<0)*CASH)+H17-$G$9*(1+H$16*$C$11/365))/$G$9)*365/H$16,((SUMPRODUCT(((DUR-H$16/365)<0)*CASH)+H17-$G$9*(1+H$16*$C$11/365))/$G$9))) -> -0.081175838 | I35: =IF(I17="","",IF($C$32="年化收益率",((SUMPRODUCT(((DUR-I$16/365)<0)*CASH)+I17-$G$9*(1+I$16*$C$11/365))/$G$9)*365/I$16,((SUMPRODUCT(((DUR-I$16/365)<0)*CASH)+I17-$G$9*(1+I$16*$C$11/365))/$G$9))) -> -0.080670483 | J35: =IF(J17="","",IF($C$32="年化收益率",((SUMPRODUCT(((DUR-J$16/365)<0)*CASH)+J17-$G$9*(1+J$16*$C$11/365))/$G$9)*365/J$16,((SUMPRODUCT(((DUR-J$16/365)<0)*CASH)+J17-$G$9*(1+J$16*$C$11/365))/$G$9))) -> -0.079831514 | ... L35: =IF(L17="","",IF($C$32="年化收益率",((SUMPRODUCT(((DUR-L$16/365)<0)*CASH)+L17-$G$9*(1+L$16*$C$11/365))/$G$9)*365/L$16,((SUMPRODUCT(((DUR-L$16/365)<0)*CASH)+L17-$G$9*(1+L$16*$C$11/365))/$G$9))) -> -0.078144536 | Q35: 1902 | R35: 银行间固定利率企业债收益率曲线(A)
B36: +30bp | C36: =IF(C18="","",IF($C$32="年化收益率",((SUMPRODUCT(((DUR-C$16/365)<0)*CASH)+C18-$G$9*(1+C$16*$C$11/365))/$G$9)*365/C$16,((SUMPRODUCT(((DUR-C$16/365)<0)*CASH)+C18-$G$9*(1+C$16*$C$11/365))/$G$9))) -> 4.9906062 | D36: =IF(D18="","",IF($C$32="年化收益率",((SUMPRODUCT(((DUR-D$16/365)<0)*CASH)+D18-$G$9*(1+D$16*$C$11/365))/$G$9)*365/D$16,((SUMPRODUCT(((DUR-D$16/365)<0)*CASH)+D18-$G$9*(1+D$16*$C$11/365))/$G$9))) -> 0.64239977 | E36: =IF(E18="","",IF($C$32="年化收益率",((SUMPRODUCT(((DUR-E$16/365)<0)*CASH)+E18-$G$9*(1+E$16*$C$11/365))/$G$9)*365/E$16,((SUMPRODUCT(((DUR-E$16/365)<0)*CASH)+E18-$G$9*(1+E$16*$C$11/365))/$G$9))) -> 0.28029987 | F36: =IF(F18="","",IF($C$32="年化收益率",((SUMPRODUCT(((DUR-F$16/365)<0)*CASH)+F18-$G$9*(1+F$16*$C$11/365))/$G$9)*365/F$16,((SUMPRODUCT(((DUR-F$16/365)<0)*CASH)+F18-$G$9*(1+F$16*$C$11/365))/$G$9))) -> 0.15977996 | G36: =IF(G18="","",IF($C$32="年化收益率",((SUMPRODUCT(((DUR-G$16/365)<0)*CASH)+G18-$G$9*(1+G$16*$C$11/365))/$G$9)*365/G$16,((SUMPRODUCT(((DUR-G$16/365)<0)*CASH)+G18-$G$9*(1+G$16*$C$11/365))/$G$9))) -> 0.087619887 | H36: =IF(H18="","",IF($C$32="年化收益率",((SUMPRODUCT(((DUR-H$16/365)<0)*CASH)+H18-$G$9*(1+H$16*$C$11/365))/$G$9)*365/H$16,((SUMPRODUCT(((DUR-H$16/365)<0)*CASH)+H18-$G$9*(1+H$16*$C$11/365))/$G$9))) -> 0.0032174535 | I36: =IF(I18="","",IF($C$32="年化收益率",((SUMPRODUCT(((DUR-I$16/365)<0)*CASH)+I18-$G$9*(1+I$16*$C$11/365))/$G$9)*365/I$16,((SUMPRODUCT(((DUR-I$16/365)<0)*CASH)+I18-$G$9*(1+I$16*$C$11/365))/$G$9))) -> -0.024970196 | J36: =IF(J18="","",IF($C$32="年化收益率",((SUMPRODUCT(((DUR-J$16/365)<0)*CASH)+J18-$G$9*(1+J$16*$C$11/365))/$G$9)*365/J$16,((SUMPRODUCT(((DUR-J$16/365)<0)*CASH)+J18-$G$9*(1+J$16*$C$11/365))/$G$9))) -> -0.047082729 | ... L36: =IF(L18="","",IF($C$32="年化收益率",((SUMPRODUCT(((DUR-L$16/365)<0)*CASH)+L18-$G$9*(1+L$16*$C$11/365))/$G$9)*365/L$16,((SUMPRODUCT(((DUR-L$16/365)<0)*CASH)+L18-$G$9*(1+L$16*$C$11/365))/$G$9))) -> -0.065666264 | Q36: 1852 | R36: 银行间固定利率企业债收益率曲线(A+)
B37: +20bp | C37: =IF(C19="","",IF($C$32="年化收益率",((SUMPRODUCT(((DUR-C$16/365)<0)*CASH)+C19-$G$9*(1+C$16*$C$11/365))/$G$9)*365/C$16,((SUMPRODUCT(((DUR-C$16/365)<0)*CASH)+C19-$G$9*(1+C$16*$C$11/365))/$G$9))) -> 7.605587 | D37: =IF(D19="","",IF($C$32="年化收益率",((SUMPRODUCT(((DUR-D$16/365)<0)*CASH)+D19-$G$9*(1+D$16*$C$11/365))/$G$9)*365/D$16,((SUMPRODUCT(((DUR-D$16/365)<0)*CASH)+D19-$G$9*(1+D$16*$C$11/365))/$G$9))) -> 1.0152149 | E37: =IF(E19="","",IF($C$32="年化收益率",((SUMPRODUCT(((DUR-E$16/365)<0)*CASH)+E19-$G$9*(1+E$16*$C$11/365))/$G$9)*365/E$16,((SUMPRODUCT(((DUR-E$16/365)<0)*CASH)+E19-$G$9*(1+E$16*$C$11/365))/$G$9))) -> 0.46626957 | F37: =IF(F19="","",IF($C$32="年化收益率",((SUMPRODUCT(((DUR-F$16/365)<0)*CASH)+F19-$G$9*(1+F$16*$C$11/365))/$G$9)*365/F$16,((SUMPRODUCT(((DUR-F$16/365)<0)*CASH)+F19-$G$9*(1+F$16*$C$11/365))/$G$9))) -> 0.28346906 | G37: =IF(G19="","",IF($C$32="年化收益率",((SUMPRODUCT(((DUR-G$16/365)<0)*CASH)+G19-$G$9*(1+G$16*$C$11/365))/$G$9)*365/G$16,((SUMPRODUCT(((DUR-G$16/365)<0)*CASH)+G19-$G$9*(1+G$16*$C$11/365))/$G$9))) -> 0.17394264 | H37: =IF(H19="","",IF($C$32="年化收益率",((SUMPRODUCT(((DUR-H$16/365)<0)*CASH)+H19-$G$9*(1+H$16*$C$11/365))/$G$9)*365/H$16,((SUMPRODUCT(((DUR-H$16/365)<0)*CASH)+H19-$G$9*(1+H$16*$C$11/365))/$G$9))) -> 0.045949421 | I37: =IF(I19="","",IF($C$32="年化收益率",((SUMPRODUCT(((DUR-I$16/365)<0)*CASH)+I19-$G$9*(1+I$16*$C$11/365))/$G$9)*365/I$16,((SUMPRODUCT(((DUR-I$16/365)<0)*CASH)+I19-$G$9*(1+I$16*$C$11/365))/$G$9))) -> 0.003230085 | J37: =IF(J19="","",IF($C$32="年化收益率",((SUMPRODUCT(((DUR-J$16/365)<0)*CASH)+J19-$G$9*(1+J$16*$C$11/365))/$G$9)*365/J$16,((SUMPRODUCT(((DUR-J$16/365)<0)*CASH)+J19-$G$9*(1+J$16*$C$11/365))/$G$9))) -> -0.030506198 | ... L37: =IF(L19="","",IF($C$32="年化收益率",((SUMPRODUCT(((DUR-L$16/365)<0)*CASH)+L19-$G$9*(1+L$16*$C$11/365))/$G$9)*365/L$16,((SUMPRODUCT(((DUR-L$16/365)<0)*CASH)+L19-$G$9*(1+L$16*$C$11/365))/$G$9))) -> -0.059355194 | Q37: 1872 | R37: 银行间固定利率企业债收益率曲线(AA(2))
B38: +15bp | C38: =IF(C20="","",IF($C$32="年化收益率",((SUMPRODUCT(((DUR-C$16/365)<0)*CASH)+C20-$G$9*(1+C$16*$C$11/365))/$G$9)*365/C$16,((SUMPRODUCT(((DUR-C$16/365)<0)*CASH)+C20-$G$9*(1+C$16*$C$11/365))/$G$9))) -> 8.9215039 | D38: =IF(D20="","",IF($C$32="年化收益率",((SUMPRODUCT(((DUR-D$16/365)<0)*CASH)+D20-$G$9*(1+D$16*$C$11/365))/$G$9)*365/D$16,((SUMPRODUCT(((DUR-D$16/365)<0)*CASH)+D20-$G$9*(1+D$16*$C$11/365))/$G$9))) -> 1.2028217 | E38: =IF(E20="","",IF($C$32="年化收益率",((SUMPRODUCT(((DUR-E$16/365)<0)*CASH)+E20-$G$9*(1+E$16*$C$11/365))/$G$9)*365/E$16,((SUMPRODUCT(((DUR-E$16/365)<0)*CASH)+E20-$G$9*(1+E$16*$C$11/365))/$G$9))) -> 0.55985143 | F38: =IF(F20="","",IF($C$32="年化收益率",((SUMPRODUCT(((DUR-F$16/365)<0)*CASH)+F20-$G$9*(1+F$16*$C$11/365))/$G$9)*365/F$16,((SUMPRODUCT(((DUR-F$16/365)<0)*CASH)+F20-$G$9*(1+F$16*$C$11/365))/$G$9))) -> 0.34570987 | G38: =IF(G20="","",IF($C$32="年化收益率",((SUMPRODUCT(((DUR-G$16/365)<0)*CASH)+G20-$G$9*(1+G$16*$C$11/365))/$G$9)*365/G$16,((SUMPRODUCT(((DUR-G$16/365)<0)*CASH)+G20-$G$9*(1+G$16*$C$11/365))/$G$9))) -> 0.21737983 | H38: =IF(H20="","",IF($C$32="年化收益率",((SUMPRODUCT(((DUR-H$16/365)<0)*CASH)+H20-$G$9*(1+H$16*$C$11/365))/$G$9)*365/H$16,((SUMPRODUCT(((DUR-H$16/365)<0)*CASH)+H20-$G$9*(1+H$16*$C$11/365))/$G$9))) -> 0.067450726 | I38: =IF(I20="","",IF($C$32="年化收益率",((SUMPRODUCT(((DUR-I$16/365)<0)*CASH)+I20-$G$9*(1+I$16*$C$11/365))/$G$9)*365/I$16,((SUMPRODUCT(((DUR-I$16/365)<0)*CASH)+I20-$G$9*(1+I$16*$C$11/365))/$G$9))) -> 0.017418727 | J38: =IF(J20="","",IF($C$32="年化收益率",((SUMPRODUCT(((DUR-J$16/365)<0)*CASH)+J20-$G$9*(1+J$16*$C$11/365))/$G$9)*365/J$16,((SUMPRODUCT(((DUR-J$16/365)<0)*CASH)+J20-$G$9*(1+J$16*$C$11/365))/$G$9))) -> -0.022166848 | ... L38: =IF(L20="","",IF($C$32="年化收益率",((SUMPRODUCT(((DUR-L$16/365)<0)*CASH)+L20-$G$9*(1+L$16*$C$11/365))/$G$9)*365/L$16,((SUMPRODUCT(((DUR-L$16/365)<0)*CASH)+L20-$G$9*(1+L$16*$C$11/365))/$G$9))) -> -0.056181492 | Q38: 1822 | R38: 银行间固定利率企业债收益率曲线(AA-(2))
B39: +10bp | C39: =IF(C21="","",IF($C$32="年化收益率",((SUMPRODUCT(((DUR-C$16/365)<0)*CASH)+C21-$G$9*(1+C$16*$C$11/365))/$G$9)*365/C$16,((SUMPRODUCT(((DUR-C$16/365)<0)*CASH)+C21-$G$9*(1+C$16*$C$11/365))/$G$9))) -> 10.243075 | D39: =IF(D21="","",IF($C$32="年化收益率",((SUMPRODUCT(((DUR-D$16/365)<0)*CASH)+D21-$G$9*(1+D$16*$C$11/365))/$G$9)*365/D$16,((SUMPRODUCT(((DUR-D$16/365)<0)*CASH)+D21-$G$9*(1+D$16*$C$11/365))/$G$9))) -> 1.3912332 | E39: =IF(E21="","",IF($C$32="年化收益率",((SUMPRODUCT(((DUR-E$16/365)<0)*CASH)+E21-$G$9*(1+E$16*$C$11/365))/$G$9)*365/E$16,((SUMPRODUCT(((DUR-E$16/365)<0)*CASH)+E21-$G$9*(1+E$16*$C$11/365))/$G$9))) -> 0.65383385 | F39: =IF(F21="","",IF($C$32="年化收益率",((SUMPRODUCT(((DUR-F$16/365)<0)*CASH)+F21-$G$9*(1+F$16*$C$11/365))/$G$9)*365/F$16,((SUMPRODUCT(((DUR-F$16/365)<0)*CASH)+F21-$G$9*(1+F$16*$C$11/365))/$G$9))) -> 0.40821656 | G39: =IF(G21="","",IF($C$32="年化收益率",((SUMPRODUCT(((DUR-G$16/365)<0)*CASH)+G21-$G$9*(1+G$16*$C$11/365))/$G$9)*365/G$16,((SUMPRODUCT(((DUR-G$16/365)<0)*CASH)+G21-$G$9*(1+G$16*$C$11/365))/$G$9))) -> 0.26100209 | H39: =IF(H21="","",IF($C$32="年化收益率",((SUMPRODUCT(((DUR-H$16/365)<0)*CASH)+H21-$G$9*(1+H$16*$C$11/365))/$G$9)*365/H$16,((SUMPRODUCT(((DUR-H$16/365)<0)*CASH)+H21-$G$9*(1+H$16*$C$11/365))/$G$9))) -> 0.08904282 | I39: =IF(I21="","",IF($C$32="年化收益率",((SUMPRODUCT(((DUR-I$16/365)<0)*CASH)+I21-$G$9*(1+I$16*$C$11/365))/$G$9)*365/I$16,((SUMPRODUCT(((DUR-I$16/365)<0)*CASH)+I21-$G$9*(1+I$16*$C$11/365))/$G$9))) -> 0.031666743 | J39: =IF(J21="","",IF($C$32="年化收益率",((SUMPRODUCT(((DUR-J$16/365)<0)*CASH)+J21-$G$9*(1+J$16*$C$11/365))/$G$9)*365/J$16,((SUMPRODUCT(((DUR-J$16/365)<0)*CASH)+J21-$G$9*(1+J$16*$C$11/365))/$G$9))) -> -0.013793232 | ... L39: =IF(L21="","",IF($C$32="年化收益率",((SUMPRODUCT(((DUR-L$16/365)<0)*CASH)+L21-$G$9*(1+L$16*$C$11/365))/$G$9)*365/L$16,((SUMPRODUCT(((DUR-L$16/365)<0)*CASH)+L21-$G$9*(1+L$16*$C$11/365))/$G$9))) -> -0.052995608 | Q39: 1252 | R39: 银行间固定利率企业债收益率曲线(AA)
B40: +5bp | C40: =IF(C22="","",IF($C$32="年化收益率",((SUMPRODUCT(((DUR-C$16/365)<0)*CASH)+C22-$G$9*(1+C$16*$C$11/365))/$G$9)*365/C$16,((SUMPRODUCT(((DUR-C$16/365)<0)*CASH)+C22-$G$9*(1+C$16*$C$11/365))/$G$9))) -> 11.570327 | D40: =IF(D22="","",IF($C$32="年化收益率",((SUMPRODUCT(((DUR-D$16/365)<0)*CASH)+D22-$G$9*(1+D$16*$C$11/365))/$G$9)*365/D$16,((SUMPRODUCT(((DUR-D$16/365)<0)*CASH)+D22-$G$9*(1+D$16*$C$11/365))/$G$9))) -> 1.5804533 | E40: =IF(E22="","",IF($C$32="年化收益率",((SUMPRODUCT(((DUR-E$16/365)<0)*CASH)+E22-$G$9*(1+E$16*$C$11/365))/$G$9)*365/E$16,((SUMPRODUCT(((DUR-E$16/365)<0)*CASH)+E22-$G$9*(1+E$16*$C$11/365))/$G$9))) -> 0.74821878 | F40: =IF(F22="","",IF($C$32="年化收益率",((SUMPRODUCT(((DUR-F$16/365)<0)*CASH)+F22-$G$9*(1+F$16*$C$11/365))/$G$9)*365/F$16,((SUMPRODUCT(((DUR-F$16/365)<0)*CASH)+F22-$G$9*(1+F$16*$C$11/365))/$G$9))) -> 0.4709904 | G40: =IF(G22="","",IF($C$32="年化收益率",((SUMPRODUCT(((DUR-G$16/365)<0)*CASH)+G22-$G$9*(1+G$16*$C$11/365))/$G$9)*365/G$16,((SUMPRODUCT(((DUR-G$16/365)<0)*CASH)+G22-$G$9*(1+G$16*$C$11/365))/$G$9))) -> 0.3048103 | H40: =IF(H22="","",IF($C$32="年化收益率",((SUMPRODUCT(((DUR-H$16/365)<0)*CASH)+H22-$G$9*(1+H$16*$C$11/365))/$G$9)*365/H$16,((SUMPRODUCT(((DUR-H$16/365)<0)*CASH)+H22-$G$9*(1+H$16*$C$11/365))/$G$9))) -> 0.11072614 | I40: =IF(I22="","",IF($C$32="年化收益率",((SUMPRODUCT(((DUR-I$16/365)<0)*CASH)+I22-$G$9*(1+I$16*$C$11/365))/$G$9)*365/I$16,((SUMPRODUCT(((DUR-I$16/365)<0)*CASH)+I22-$G$9*(1+I$16*$C$11/365))/$G$9))) -> 0.045974414 | J40: =IF(J22="","",IF($C$32="年化收益率",((SUMPRODUCT(((DUR-J$16/365)<0)*CASH)+J22-$G$9*(1+J$16*$C$11/365))/$G$9)*365/J$16,((SUMPRODUCT(((DUR-J$16/365)<0)*CASH)+J22-$G$9*(1+J$16*$C$11/365))/$G$9))) -> -0.0053851879 | ... L40: =IF(L22="","",IF($C$32="年化收益率",((SUMPRODUCT(((DUR-L$16/365)<0)*CASH)+L22-$G$9*(1+L$16*$C$11/365))/$G$9)*365/L$16,((SUMPRODUCT(((DUR-L$16/365)<0)*CASH)+L22-$G$9*(1+L$16*$C$11/365))/$G$9))) -> -0.049797488 | Q40: 1482 | R40: 银行间固定利率企业债收益率曲线(AA-)
B41: 0bp | C41: =IF(C23="","",IF($C$32="年化收益率",((SUMPRODUCT(((DUR-C$16/365)<0)*CASH)+C23-$G$9*(1+C$16*$C$11/365))/$G$9)*365/C$16,((SUMPRODUCT(((DUR-C$16/365)<0)*CASH)+C23-$G$9*(1+C$16*$C$11/365))/$G$9))) -> 12.903289 | D41: =IF(D23="","",IF($C$32="年化收益率",((SUMPRODUCT(((DUR-D$16/365)<0)*CASH)+D23-$G$9*(1+D$16*$C$11/365))/$G$9)*365/D$16,((SUMPRODUCT(((DUR-D$16/365)<0)*CASH)+D23-$G$9*(1+D$16*$C$11/365))/$G$9))) -> 1.7704859 | E41: =IF(E23="","",IF($C$32="年化收益率",((SUMPRODUCT(((DUR-E$16/365)<0)*CASH)+E23-$G$9*(1+E$16*$C$11/365))/$G$9)*365/E$16,((SUMPRODUCT(((DUR-E$16/365)<0)*CASH)+E23-$G$9*(1+E$16*$C$11/365))/$G$9))) -> 0.84300815 | F41: =IF(F23="","",IF($C$32="年化收益率",((SUMPRODUCT(((DUR-F$16/365)<0)*CASH)+F23-$G$9*(1+F$16*$C$11/365))/$G$9)*365/F$16,((SUMPRODUCT(((DUR-F$16/365)<0)*CASH)+F23-$G$9*(1+F$16*$C$11/365))/$G$9))) -> 0.53403268 | G41: =IF(G23="","",IF($C$32="年化收益率",((SUMPRODUCT(((DUR-G$16/365)<0)*CASH)+G23-$G$9*(1+G$16*$C$11/365))/$G$9)*365/G$16,((SUMPRODUCT(((DUR-G$16/365)<0)*CASH)+G23-$G$9*(1+G$16*$C$11/365))/$G$9))) -> 0.34880535 | H41: =IF(H23="","",IF($C$32="年化收益率",((SUMPRODUCT(((DUR-H$16/365)<0)*CASH)+H23-$G$9*(1+H$16*$C$11/365))/$G$9)*365/H$16,((SUMPRODUCT(((DUR-H$16/365)<0)*CASH)+H23-$G$9*(1+H$16*$C$11/365))/$G$9))) -> 0.13250111 | I41: =IF(I23="","",IF($C$32="年化收益率",((SUMPRODUCT(((DUR-I$16/365)<0)*CASH)+I23-$G$9*(1+I$16*$C$11/365))/$G$9)*365/I$16,((SUMPRODUCT(((DUR-I$16/365)<0)*CASH)+I23-$G$9*(1+I$16*$C$11/365))/$G$9))) -> 0.060342022 | J41: =IF(J23="","",IF($C$32="年化收益率",((SUMPRODUCT(((DUR-J$16/365)<0)*CASH)+J23-$G$9*(1+J$16*$C$11/365))/$G$9)*365/J$16,((SUMPRODUCT(((DUR-J$16/365)<0)*CASH)+J23-$G$9*(1+J$16*$C$11/365))/$G$9))) -> 0.0030574431 | ... L41: =IF(L23="","",IF($C$32="年化收益率",((SUMPRODUCT(((DUR-L$16/365)<0)*CASH)+L23-$G$9*(1+L$16*$C$11/365))/$G$9)*365/L$16,((SUMPRODUCT(((DUR-L$16/365)<0)*CASH)+L23-$G$9*(1+L$16*$C$11/365))/$G$9))) -> -0.04658708 | Q41: 1832 | R41: 银行间固定利率企业债收益率曲线(AA+(2))
B42: -5bp | C42: =IF(C24="","",IF($C$32="年化收益率",((SUMPRODUCT(((DUR-C$16/365)<0)*CASH)+C24-$G$9*(1+C$16*$C$11/365))/$G$9)*365/C$16,((SUMPRODUCT(((DUR-C$16/365)<0)*CASH)+C24-$G$9*(1+C$16*$C$11/365))/$G$9))) -> 14.241987 | D42: =IF(D24="","",IF($C$32="年化收益率",((SUMPRODUCT(((DUR-D$16/365)<0)*CASH)+D24-$G$9*(1+D$16*$C$11/365))/$G$9)*365/D$16,((SUMPRODUCT(((DUR-D$16/365)<0)*CASH)+D24-$G$9*(1+D$16*$C$11/365))/$G$9))) -> 1.9613349 | E42: =IF(E24="","",IF($C$32="年化收益率",((SUMPRODUCT(((DUR-E$16/365)<0)*CASH)+E24-$G$9*(1+E$16*$C$11/365))/$G$9)*365/E$16,((SUMPRODUCT(((DUR-E$16/365)<0)*CASH)+E24-$G$9*(1+E$16*$C$11/365))/$G$9))) -> 0.93820394 | F42: =IF(F24="","",IF($C$32="年化收益率",((SUMPRODUCT(((DUR-F$16/365)<0)*CASH)+F24-$G$9*(1+F$16*$C$11/365))/$G$9)*365/F$16,((SUMPRODUCT(((DUR-F$16/365)<0)*CASH)+F24-$G$9*(1+F$16*$C$11/365))/$G$9))) -> 0.5973447 | G42: =IF(G24="","",IF($C$32="年化收益率",((SUMPRODUCT(((DUR-G$16/365)<0)*CASH)+G24-$G$9*(1+G$16*$C$11/365))/$G$9)*365/G$16,((SUMPRODUCT(((DUR-G$16/365)<0)*CASH)+G24-$G$9*(1+G$16*$C$11/365))/$G$9))) -> 0.39298815 | H42: =IF(H24="","",IF($C$32="年化收益率",((SUMPRODUCT(((DUR-H$16/365)<0)*CASH)+H24-$G$9*(1+H$16*$C$11/365))/$G$9)*365/H$16,((SUMPRODUCT(((DUR-H$16/365)<0)*CASH)+H24-$G$9*(1+H$16*$C$11/365))/$G$9))) -> 0.15436818 | I42: =IF(I24="","",IF($C$32="年化收益率",((SUMPRODUCT(((DUR-I$16/365)<0)*CASH)+I24-$G$9*(1+I$16*$C$11/365))/$G$9)*365/I$16,((SUMPRODUCT(((DUR-I$16/365)<0)*CASH)+I24-$G$9*(1+I$16*$C$11/365))/$G$9))) -> 0.074769851 | J42: =IF(J24="","",IF($C$32="年化收益率",((SUMPRODUCT(((DUR-J$16/365)<0)*CASH)+J24-$G$9*(1+J$16*$C$11/365))/$G$9)*365/J$16,((SUMPRODUCT(((DUR-J$16/365)<0)*CASH)+J24-$G$9*(1+J$16*$C$11/365))/$G$9))) -> 0.011534823 | ... L42: =IF(L24="","",IF($C$32="年化收益率",((SUMPRODUCT(((DUR-L$16/365)<0)*CASH)+L24-$G$9*(1+L$16*$C$11/365))/$G$9)*365/L$16,((SUMPRODUCT(((DUR-L$16/365)<0)*CASH)+L24-$G$9*(1+L$16*$C$11/365))/$G$9))) -> -0.043364328 | Q42: 1442 | R42: 银行间固定利率企业债收益率曲线(AA+)
B43: -10bp | C43: =IF(C25="","",IF($C$32="年化收益率",((SUMPRODUCT(((DUR-C$16/365)<0)*CASH)+C25-$G$9*(1+C$16*$C$11/365))/$G$9)*365/C$16,((SUMPRODUCT(((DUR-C$16/365)<0)*CASH)+C25-$G$9*(1+C$16*$C$11/365))/$G$9))) -> 15.586449 | D43: =IF(D25="","",IF($C$32="年化收益率",((SUMPRODUCT(((DUR-D$16/365)<0)*CASH)+D25-$G$9*(1+D$16*$C$11/365))/$G$9)*365/D$16,((SUMPRODUCT(((DUR-D$16/365)<0)*CASH)+D25-$G$9*(1+D$16*$C$11/365))/$G$9))) -> 2.1530042 | E43: =IF(E25="","",IF($C$32="年化收益率",((SUMPRODUCT(((DUR-E$16/365)<0)*CASH)+E25-$G$9*(1+E$16*$C$11/365))/$G$9)*365/E$16,((SUMPRODUCT(((DUR-E$16/365)<0)*CASH)+E25-$G$9*(1+E$16*$C$11/365))/$G$9))) -> 1.0338081 | F43: =IF(F25="","",IF($C$32="年化收益率",((SUMPRODUCT(((DUR-F$16/365)<0)*CASH)+F25-$G$9*(1+F$16*$C$11/365))/$G$9)*365/F$16,((SUMPRODUCT(((DUR-F$16/365)<0)*CASH)+F25-$G$9*(1+F$16*$C$11/365))/$G$9))) -> 0.66092777 | G43: =IF(G25="","",IF($C$32="年化收益率",((SUMPRODUCT(((DUR-G$16/365)<0)*CASH)+G25-$G$9*(1+G$16*$C$11/365))/$G$9)*365/G$16,((SUMPRODUCT(((DUR-G$16/365)<0)*CASH)+G25-$G$9*(1+G$16*$C$11/365))/$G$9))) -> 0.4373596 | H43: =IF(H25="","",IF($C$32="年化收益率",((SUMPRODUCT(((DUR-H$16/365)<0)*CASH)+H25-$G$9*(1+H$16*$C$11/365))/$G$9)*365/H$16,((SUMPRODUCT(((DUR-H$16/365)<0)*CASH)+H25-$G$9*(1+H$16*$C$11/365))/$G$9))) -> 0.17632778 | I43: =IF(I25="","",IF($C$32="年化收益率",((SUMPRODUCT(((DUR-I$16/365)<0)*CASH)+I25-$G$9*(1+I$16*$C$11/365))/$G$9)*365/I$16,((SUMPRODUCT(((DUR-I$16/365)<0)*CASH)+I25-$G$9*(1+I$16*$C$11/365))/$G$9))) -> 0.089258188 | J43: =IF(J25="","",IF($C$32="年化收益率",((SUMPRODUCT(((DUR-J$16/365)<0)*CASH)+J25-$G$9*(1+J$16*$C$11/365))/$G$9)*365/J$16,((SUMPRODUCT(((DUR-J$16/365)<0)*CASH)+J25-$G$9*(1+J$16*$C$11/365))/$G$9))) -> 0.020047113 | ... L43: =IF(L25="","",IF($C$32="年化收益率",((SUMPRODUCT(((DUR-L$16/365)<0)*CASH)+L25-$G$9*(1+L$16*$C$11/365))/$G$9)*365/L$16,((SUMPRODUCT(((DUR-L$16/365)<0)*CASH)+L25-$G$9*(1+L$16*$C$11/365))/$G$9))) -> -0.04012918 | Q43: 1842 | R43: 银行间固定利率企业债收益率曲线(AAA(2))
B44: -15bp | C44: =IF(C26="","",IF($C$32="年化收益率",((SUMPRODUCT(((DUR-C$16/365)<0)*CASH)+C26-$G$9*(1+C$16*$C$11/365))/$G$9)*365/C$16,((SUMPRODUCT(((DUR-C$16/365)<0)*CASH)+C26-$G$9*(1+C$16*$C$11/365))/$G$9))) -> 16.936705 | D44: =IF(D26="","",IF($C$32="年化收益率",((SUMPRODUCT(((DUR-D$16/365)<0)*CASH)+D26-$G$9*(1+D$16*$C$11/365))/$G$9)*365/D$16,((SUMPRODUCT(((DUR-D$16/365)<0)*CASH)+D26-$G$9*(1+D$16*$C$11/365))/$G$9))) -> 2.345498 | E44: =IF(E26="","",IF($C$32="年化收益率",((SUMPRODUCT(((DUR-E$16/365)<0)*CASH)+E26-$G$9*(1+E$16*$C$11/365))/$G$9)*365/E$16,((SUMPRODUCT(((DUR-E$16/365)<0)*CASH)+E26-$G$9*(1+E$16*$C$11/365))/$G$9))) -> 1.1298226 | F44: =IF(F26="","",IF($C$32="年化收益率",((SUMPRODUCT(((DUR-F$16/365)<0)*CASH)+F26-$G$9*(1+F$16*$C$11/365))/$G$9)*365/F$16,((SUMPRODUCT(((DUR-F$16/365)<0)*CASH)+F26-$G$9*(1+F$16*$C$11/365))/$G$9))) -> 0.72478319 | G44: =IF(G26="","",IF($C$32="年化收益率",((SUMPRODUCT(((DUR-G$16/365)<0)*CASH)+G26-$G$9*(1+G$16*$C$11/365))/$G$9)*365/G$16,((SUMPRODUCT(((DUR-G$16/365)<0)*CASH)+G26-$G$9*(1+G$16*$C$11/365))/$G$9))) -> 0.48192061 | H44: =IF(H26="","",IF($C$32="年化收益率",((SUMPRODUCT(((DUR-H$16/365)<0)*CASH)+H26-$G$9*(1+H$16*$C$11/365))/$G$9)*365/H$16,((SUMPRODUCT(((DUR-H$16/365)<0)*CASH)+H26-$G$9*(1+H$16*$C$11/365))/$G$9))) -> 0.19838037 | I44: =IF(I26="","",IF($C$32="年化收益率",((SUMPRODUCT(((DUR-I$16/365)<0)*CASH)+I26-$G$9*(1+I$16*$C$11/365))/$G$9)*365/I$16,((SUMPRODUCT(((DUR-I$16/365)<0)*CASH)+I26-$G$9*(1+I$16*$C$11/365))/$G$9))) -> 0.10380732 | J44: =IF(J26="","",IF($C$32="年化收益率",((SUMPRODUCT(((DUR-J$16/365)<0)*CASH)+J26-$G$9*(1+J$16*$C$11/365))/$G$9)*365/J$16,((SUMPRODUCT(((DUR-J$16/365)<0)*CASH)+J26-$G$9*(1+J$16*$C$11/365))/$G$9))) -> 0.028594477 | ... L44: =IF(L26="","",IF($C$32="年化收益率",((SUMPRODUCT(((DUR-L$16/365)<0)*CASH)+L26-$G$9*(1+L$16*$C$11/365))/$G$9)*365/L$16,((SUMPRODUCT(((DUR-L$16/365)<0)*CASH)+L26-$G$9*(1+L$16*$C$11/365))/$G$9))) -> -0.03688158 | Q44: 1262 | R44: 银行间固定利率企业债收益率曲线(AAA)
B45: -20bp | C45: =IF(C27="","",IF($C$32="年化收益率",((SUMPRODUCT(((DUR-C$16/365)<0)*CASH)+C27-$G$9*(1+C$16*$C$11/365))/$G$9)*365/C$16,((SUMPRODUCT(((DUR-C$16/365)<0)*CASH)+C27-$G$9*(1+C$16*$C$11/365))/$G$9))) -> 18.292781 | D45: =IF(D27="","",IF($C$32="年化收益率",((SUMPRODUCT(((DUR-D$16/365)<0)*CASH)+D27-$G$9*(1+D$16*$C$11/365))/$G$9)*365/D$16,((SUMPRODUCT(((DUR-D$16/365)<0)*CASH)+D27-$G$9*(1+D$16*$C$11/365))/$G$9))) -> 2.5388201 | E45: =IF(E27="","",IF($C$32="年化收益率",((SUMPRODUCT(((DUR-E$16/365)<0)*CASH)+E27-$G$9*(1+E$16*$C$11/365))/$G$9)*365/E$16,((SUMPRODUCT(((DUR-E$16/365)<0)*CASH)+E27-$G$9*(1+E$16*$C$11/365))/$G$9))) -> 1.2262495 | F45: =IF(F27="","",IF($C$32="年化收益率",((SUMPRODUCT(((DUR-F$16/365)<0)*CASH)+F27-$G$9*(1+F$16*$C$11/365))/$G$9)*365/F$16,((SUMPRODUCT(((DUR-F$16/365)<0)*CASH)+F27-$G$9*(1+F$16*$C$11/365))/$G$9))) -> 0.78891228 | G45: =IF(G27="","",IF($C$32="年化收益率",((SUMPRODUCT(((DUR-G$16/365)<0)*CASH)+G27-$G$9*(1+G$16*$C$11/365))/$G$9)*365/G$16,((SUMPRODUCT(((DUR-G$16/365)<0)*CASH)+G27-$G$9*(1+G$16*$C$11/365))/$G$9))) -> 0.5266721 | H45: =IF(H27="","",IF($C$32="年化收益率",((SUMPRODUCT(((DUR-H$16/365)<0)*CASH)+H27-$G$9*(1+H$16*$C$11/365))/$G$9)*365/H$16,((SUMPRODUCT(((DUR-H$16/365)<0)*CASH)+H27-$G$9*(1+H$16*$C$11/365))/$G$9))) -> 0.22052638 | I45: =IF(I27="","",IF($C$32="年化收益率",((SUMPRODUCT(((DUR-I$16/365)<0)*CASH)+I27-$G$9*(1+I$16*$C$11/365))/$G$9)*365/I$16,((SUMPRODUCT(((DUR-I$16/365)<0)*CASH)+I27-$G$9*(1+I$16*$C$11/365))/$G$9))) -> 0.11841753 | J45: =IF(J27="","",IF($C$32="年化收益率",((SUMPRODUCT(((DUR-J$16/365)<0)*CASH)+J27-$G$9*(1+J$16*$C$11/365))/$G$9)*365/J$16,((SUMPRODUCT(((DUR-J$16/365)<0)*CASH)+J27-$G$9*(1+J$16*$C$11/365))/$G$9))) -> 0.037177078 | ... L45: =IF(L27="","",IF($C$32="年化收益率",((SUMPRODUCT(((DUR-L$16/365)<0)*CASH)+L27-$G$9*(1+L$16*$C$11/365))/$G$9)*365/L$16,((SUMPRODUCT(((DUR-L$16/365)<0)*CASH)+L27-$G$9*(1+L$16*$C$11/365))/$G$9))) -> -0.033621474 | Q45: 1912 | R45: 银行间固定利率企业债收益率曲线(BBB+)
B46: -30bp | C46: =IF(C28="","",IF($C$32="年化收益率",((SUMPRODUCT(((DUR-C$16/365)<0)*CASH)+C28-$G$9*(1+C$16*$C$11/365))/$G$9)*365/C$16,((SUMPRODUCT(((DUR-C$16/365)<0)*CASH)+C28-$G$9*(1+C$16*$C$11/365))/$G$9))) -> 21.022509 | D46: =IF(D28="","",IF($C$32="年化收益率",((SUMPRODUCT(((DUR-D$16/365)<0)*CASH)+D28-$G$9*(1+D$16*$C$11/365))/$G$9)*365/D$16,((SUMPRODUCT(((DUR-D$16/365)<0)*CASH)+D28-$G$9*(1+D$16*$C$11/365))/$G$9))) -> 2.9279655 | E46: =IF(E28="","",IF($C$32="年化收益率",((SUMPRODUCT(((DUR-E$16/365)<0)*CASH)+E28-$G$9*(1+E$16*$C$11/365))/$G$9)*365/E$16,((SUMPRODUCT(((DUR-E$16/365)<0)*CASH)+E28-$G$9*(1+E$16*$C$11/365))/$G$9))) -> 1.4203482 | F46: =IF(F28="","",IF($C$32="年化收益率",((SUMPRODUCT(((DUR-F$16/365)<0)*CASH)+F28-$G$9*(1+F$16*$C$11/365))/$G$9)*365/F$16,((SUMPRODUCT(((DUR-F$16/365)<0)*CASH)+F28-$G$9*(1+F$16*$C$11/365))/$G$9))) -> 0.9179968 | G46: =IF(G28="","",IF($C$32="年化收益率",((SUMPRODUCT(((DUR-G$16/365)<0)*CASH)+G28-$G$9*(1+G$16*$C$11/365))/$G$9)*365/G$16,((SUMPRODUCT(((DUR-G$16/365)<0)*CASH)+G28-$G$9*(1+G$16*$C$11/365))/$G$9))) -> 0.61675019 | H46: =IF(H28="","",IF($C$32="年化收益率",((SUMPRODUCT(((DUR-H$16/365)<0)*CASH)+H28-$G$9*(1+H$16*$C$11/365))/$G$9)*365/H$16,((SUMPRODUCT(((DUR-H$16/365)<0)*CASH)+H28-$G$9*(1+H$16*$C$11/365))/$G$9))) -> 0.26510046 | I46: =IF(I28="","",IF($C$32="年化收益率",((SUMPRODUCT(((DUR-I$16/365)<0)*CASH)+I28-$G$9*(1+I$16*$C$11/365))/$G$9)*365/I$16,((SUMPRODUCT(((DUR-I$16/365)<0)*CASH)+I28-$G$9*(1+I$16*$C$11/365))/$G$9))) -> 0.14782237 | J46: =IF(J28="","",IF($C$32="年化收益率",((SUMPRODUCT(((DUR-J$16/365)<0)*CASH)+J28-$G$9*(1+J$16*$C$11/365))/$G$9)*365/J$16,((SUMPRODUCT(((DUR-J$16/365)<0)*CASH)+J28-$G$9*(1+J$16*$C$11/365))/$G$9))) -> 0.054448651 | ... L46: =IF(L28="","",IF($C$32="年化收益率",((SUMPRODUCT(((DUR-L$16/365)<0)*CASH)+L28-$G$9*(1+L$16*$C$11/365))/$G$9)*365/L$16,((SUMPRODUCT(((DUR-L$16/365)<0)*CASH)+L28-$G$9*(1+L$16*$C$11/365))/$G$9))) -> -0.027063525 | Q46: 1492 | R46: 银行间固定利率商业银行债收益率曲线(A)
B47: -50bp | C47: =IF(C29="","",IF($C$32="年化收益率",((SUMPRODUCT(((DUR-C$16/365)<0)*CASH)+C29-$G$9*(1+C$16*$C$11/365))/$G$9)*365/C$16,((SUMPRODUCT(((DUR-C$16/365)<0)*CASH)+C29-$G$9*(1+C$16*$C$11/365))/$G$9))) -> 26.553072 | D47: =IF(D29="","",IF($C$32="年化收益率",((SUMPRODUCT(((DUR-D$16/365)<0)*CASH)+D29-$G$9*(1+D$16*$C$11/365))/$G$9)*365/D$16,((SUMPRODUCT(((DUR-D$16/365)<0)*CASH)+D29-$G$9*(1+D$16*$C$11/365))/$G$9))) -> 3.7163754 | E47: =IF(E29="","",IF($C$32="年化收益率",((SUMPRODUCT(((DUR-E$16/365)<0)*CASH)+E29-$G$9*(1+E$16*$C$11/365))/$G$9)*365/E$16,((SUMPRODUCT(((DUR-E$16/365)<0)*CASH)+E29-$G$9*(1+E$16*$C$11/365))/$G$9))) -> 1.8135825 | F47: =IF(F29="","",IF($C$32="年化收益率",((SUMPRODUCT(((DUR-F$16/365)<0)*CASH)+F29-$G$9*(1+F$16*$C$11/365))/$G$9)*365/F$16,((SUMPRODUCT(((DUR-F$16/365)<0)*CASH)+F29-$G$9*(1+F$16*$C$11/365))/$G$9))) -> 1.1795086 | G47: =IF(G29="","",IF($C$32="年化收益率",((SUMPRODUCT(((DUR-G$16/365)<0)*CASH)+G29-$G$9*(1+G$16*$C$11/365))/$G$9)*365/G$16,((SUMPRODUCT(((DUR-G$16/365)<0)*CASH)+G29-$G$9*(1+G$16*$C$11/365))/$G$9))) -> 0.79923289 | H47: =IF(H29="","",IF($C$32="年化收益率",((SUMPRODUCT(((DUR-H$16/365)<0)*CASH)+H29-$G$9*(1+H$16*$C$11/365))/$G$9)*365/H$16,((SUMPRODUCT(((DUR-H$16/365)<0)*CASH)+H29-$G$9*(1+H$16*$C$11/365))/$G$9))) -> 0.35538956 | I47: =IF(I29="","",IF($C$32="年化收益率",((SUMPRODUCT(((DUR-I$16/365)<0)*CASH)+I29-$G$9*(1+I$16*$C$11/365))/$G$9)*365/I$16,((SUMPRODUCT(((DUR-I$16/365)<0)*CASH)+I29-$G$9*(1+I$16*$C$11/365))/$G$9))) -> 0.20737791 | J47: =IF(J29="","",IF($C$32="年化收益率",((SUMPRODUCT(((DUR-J$16/365)<0)*CASH)+J29-$G$9*(1+J$16*$C$11/365))/$G$9)*365/J$16,((SUMPRODUCT(((DUR-J$16/365)<0)*CASH)+J29-$G$9*(1+J$16*$C$11/365))/$G$9))) -> 0.089421947 | ... L47: =IF(L29="","",IF($C$32="年化收益率",((SUMPRODUCT(((DUR-L$16/365)<0)*CASH)+L29-$G$9*(1+L$16*$C$11/365))/$G$9)*365/L$16,((SUMPRODUCT(((DUR-L$16/365)<0)*CASH)+L29-$G$9*(1+L$16*$C$11/365))/$G$9))) -> -0.01379512 | Q47: 1272 | R47: 银行间固定利率商业银行债收益率曲线(A-)
B48: =B30&"bp" -> 10bp | C48: =IF(C30="","",IF($C$32="年化收益率",((SUMPRODUCT(((DUR-C$16/365)<0)*CASH)+C30-$G$9*(1+C$16*$C$11/365))/$G$9)*365/C$16,((SUMPRODUCT(((DUR-C$16/365)<0)*CASH)+C30-$G$9*(1+C$16*$C$11/365))/$G$9))) -> 10.243075 | D48: =IF(D30="","",IF($C$32="年化收益率",((SUMPRODUCT(((DUR-D$16/365)<0)*CASH)+D30-$G$9*(1+D$16*$C$11/365))/$G$9)*365/D$16,((SUMPRODUCT(((DUR-D$16/365)<0)*CASH)+D30-$G$9*(1+D$16*$C$11/365))/$G$9))) -> 1.3912332 | E48: =IF(E30="","",IF($C$32="年化收益率",((SUMPRODUCT(((DUR-E$16/365)<0)*CASH)+E30-$G$9*(1+E$16*$C$11/365))/$G$9)*365/E$16,((SUMPRODUCT(((DUR-E$16/365)<0)*CASH)+E30-$G$9*(1+E$16*$C$11/365))/$G$9))) -> 0.65383385 | F48: =IF(F30="","",IF($C$32="年化收益率",((SUMPRODUCT(((DUR-F$16/365)<0)*CASH)+F30-$G$9*(1+F$16*$C$11/365))/$G$9)*365/F$16,((SUMPRODUCT(((DUR-F$16/365)<0)*CASH)+F30-$G$9*(1+F$16*$C$11/365))/$G$9))) -> 0.40821656 | G48: =IF(G30="","",IF($C$32="年化收益率",((SUMPRODUCT(((DUR-G$16/365)<0)*CASH)+G30-$G$9*(1+G$16*$C$11/365))/$G$9)*365/G$16,((SUMPRODUCT(((DUR-G$16/365)<0)*CASH)+G30-$G$9*(1+G$16*$C$11/365))/$G$9))) -> 0.26100209 | H48: =IF(H30="","",IF($C$32="年化收益率",((SUMPRODUCT(((DUR-H$16/365)<0)*CASH)+H30-$G$9*(1+H$16*$C$11/365))/$G$9)*365/H$16,((SUMPRODUCT(((DUR-H$16/365)<0)*CASH)+H30-$G$9*(1+H$16*$C$11/365))/$G$9))) -> 0.08904282 | I48: =IF(I30="","",IF($C$32="年化收益率",((SUMPRODUCT(((DUR-I$16/365)<0)*CASH)+I30-$G$9*(1+I$16*$C$11/365))/$G$9)*365/I$16,((SUMPRODUCT(((DUR-I$16/365)<0)*CASH)+I30-$G$9*(1+I$16*$C$11/365))/$G$9))) -> 0.031666743 | J48: =IF(J30="","",IF($C$32="年化收益率",((SUMPRODUCT(((DUR-J$16/365)<0)*CASH)+J30-$G$9*(1+J$16*$C$11/365))/$G$9)*365/J$16,((SUMPRODUCT(((DUR-J$16/365)<0)*CASH)+J30-$G$9*(1+J$16*$C$11/365))/$G$9))) -> -0.013793232 | ... L48: =IF(L30="","",IF($C$32="年化收益率",((SUMPRODUCT(((DUR-L$16/365)<0)*CASH)+L30-$G$9*(1+L$16*$C$11/365))/$G$9)*365/L$16,((SUMPRODUCT(((DUR-L$16/365)<0)*CASH)+L30-$G$9*(1+L$16*$C$11/365))/$G$9))) -> -0.052995608 | Q48: 1452 | R48: 银行间固定利率商业银行债收益率曲线(A+)
Q49: 1282 | R49: 银行间固定利率商业银行债收益率曲线(AA)
B50: 期末净现金流（万元） | Q50: 1302 | R50: 银行间固定利率商业银行债收益率曲线(AA-)
C51: 1d | D51: 7d | E51: 2W | F51: 3W | G51: 1M | H51: 2M | I51: 3M | J51: 5M | K51: 1Y | L51: =L34 -> 365d | Q51: 1292 | R51: 银行间固定利率商业银行债收益率曲线(AA+)
B52: +50bp | C52: =IF(C17="","",(SUMPRODUCT(((DUR-C$16/365)<0)*CASH)+C17-$G$9*(1+C$16*$C$11/365))*$I$9) -> -24.216453 | D52: =IF(D17="","",(SUMPRODUCT(((DUR-D$16/365)<0)*CASH)+D17-$G$9*(1+D$16*$C$11/365))*$I$9) -> -92.016039 | E52: =IF(E17="","",(SUMPRODUCT(((DUR-E$16/365)<0)*CASH)+E17-$G$9*(1+E$16*$C$11/365))*$I$9) -> -170.63002 | F52: =IF(F17="","",(SUMPRODUCT(((DUR-F$16/365)<0)*CASH)+F17-$G$9*(1+F$16*$C$11/365))*$I$9) -> -248.72074 | G52: =IF(G17="","",(SUMPRODUCT(((DUR-G$16/365)<0)*CASH)+G17-$G$9*(1+G$16*$C$11/365))*$I$9) -> -348.50074 | H52: =IF(H17="","",(SUMPRODUCT(((DUR-H$16/365)<0)*CASH)+H17-$G$9*(1+H$16*$C$11/365))*$I$9) -> -682.97009 | I52: =IF(I17="","",(SUMPRODUCT(((DUR-I$16/365)<0)*CASH)+I17-$G$9*(1+I$16*$C$11/365))*$I$9) -> -1018.0774 | J52: =IF(J17="","",(SUMPRODUCT(((DUR-J$16/365)<0)*CASH)+J17-$G$9*(1+J$16*$C$11/365))*$I$9) -> -1679.1492 | ... L52: =IF(L17="","",(SUMPRODUCT(((DUR-L$16/365)<0)*CASH)+L17-$G$9*(1+L$16*$C$11/365))*$I$9) -> -3999.5869 | Q52: 1312 | R52: 银行间固定利率商业银行债收益率曲线(AAA)
B53: +30bp | C53: =IF(C18="","",(SUMPRODUCT(((DUR-C$16/365)<0)*CASH)+C18-$G$9*(1+C$16*$C$11/365))*$I$9) -> 699.80486 | D53: =IF(D18="","",(SUMPRODUCT(((DUR-D$16/365)<0)*CASH)+D18-$G$9*(1+D$16*$C$11/365))*$I$9) -> 630.56094 | E53: =IF(E18="","",(SUMPRODUCT(((DUR-E$16/365)<0)*CASH)+E18-$G$9*(1+E$16*$C$11/365))*$I$9) -> 550.26841 | F53: =IF(F18="","",(SUMPRODUCT(((DUR-F$16/365)<0)*CASH)+F18-$G$9*(1+F$16*$C$11/365))*$I$9) -> 470.50608 | G53: =IF(G18="","",(SUMPRODUCT(((DUR-G$16/365)<0)*CASH)+G18-$G$9*(1+G$16*$C$11/365))*$I$9) -> 368.59343 | H53: =IF(H18="","",(SUMPRODUCT(((DUR-H$16/365)<0)*CASH)+H18-$G$9*(1+H$16*$C$11/365))*$I$9) -> 27.069933 | I53: =IF(I18="","",(SUMPRODUCT(((DUR-I$16/365)<0)*CASH)+I18-$G$9*(1+I$16*$C$11/365))*$I$9) -> -315.12881 | J53: =IF(J18="","",(SUMPRODUCT(((DUR-J$16/365)<0)*CASH)+J18-$G$9*(1+J$16*$C$11/365))*$I$9) -> -990.32225 | ... L53: =IF(L18="","",(SUMPRODUCT(((DUR-L$16/365)<0)*CASH)+L18-$G$9*(1+L$16*$C$11/365))*$I$9) -> -3360.925 | Q53: 1322 | R53: 银行间固定利率政策性金融债收益率曲线
B54: +20bp | C54: =IF(C19="","",(SUMPRODUCT(((DUR-C$16/365)<0)*CASH)+C19-$G$9*(1+C$16*$C$11/365))*$I$9) -> 1066.489 | D54: =IF(D19="","",(SUMPRODUCT(((DUR-D$16/365)<0)*CASH)+D19-$G$9*(1+D$16*$C$11/365))*$I$9) -> 996.50545 | E54: =IF(E19="","",(SUMPRODUCT(((DUR-E$16/365)<0)*CASH)+E19-$G$9*(1+E$16*$C$11/365))*$I$9) -> 915.35332 | F54: =IF(F19="","",(SUMPRODUCT(((DUR-F$16/365)<0)*CASH)+F19-$G$9*(1+F$16*$C$11/365))*$I$9) -> 834.73498 | G54: =IF(G19="","",(SUMPRODUCT(((DUR-G$16/365)<0)*CASH)+G19-$G$9*(1+G$16*$C$11/365))*$I$9) -> 731.73016 | H54: =IF(H19="","",(SUMPRODUCT(((DUR-H$16/365)<0)*CASH)+H19-$G$9*(1+H$16*$C$11/365))*$I$9) -> 386.59385 | I54: =IF(I19="","",(SUMPRODUCT(((DUR-I$16/365)<0)*CASH)+I19-$G$9*(1+I$16*$C$11/365))*$I$9) -> 40.764311 | J54: =IF(J19="","",(SUMPRODUCT(((DUR-J$16/365)<0)*CASH)+J19-$G$9*(1+J$16*$C$11/365))*$I$9) -> -641.65708 | ... L54: =IF(L19="","",(SUMPRODUCT(((DUR-L$16/365)<0)*CASH)+L19-$G$9*(1+L$16*$C$11/365))*$I$9) -> -3037.9124 | Q54: 1892 | R54: 银行间固定利率资产支持证券收益率曲线(A)
B55: +15bp | C55: =IF(C20="","",(SUMPRODUCT(((DUR-C$16/365)<0)*CASH)+C20-$G$9*(1+C$16*$C$11/365))*$I$9) -> 1251.0127 | D55: =IF(D20="","",(SUMPRODUCT(((DUR-D$16/365)<0)*CASH)+D20-$G$9*(1+D$16*$C$11/365))*$I$9) -> 1180.6549 | E55: =IF(E20="","",(SUMPRODUCT(((DUR-E$16/365)<0)*CASH)+E20-$G$9*(1+E$16*$C$11/365))*$I$9) -> 1099.0678 | F55: =IF(F20="","",(SUMPRODUCT(((DUR-F$16/365)<0)*CASH)+F20-$G$9*(1+F$16*$C$11/365))*$I$9) -> 1018.0163 | G55: =IF(G20="","",(SUMPRODUCT(((DUR-G$16/365)<0)*CASH)+G20-$G$9*(1+G$16*$C$11/365))*$I$9) -> 914.45883 | H55: =IF(H20="","",(SUMPRODUCT(((DUR-H$16/365)<0)*CASH)+H20-$G$9*(1+H$16*$C$11/365))*$I$9) -> 567.49433 | I55: =IF(I20="","",(SUMPRODUCT(((DUR-I$16/365)<0)*CASH)+I20-$G$9*(1+I$16*$C$11/365))*$I$9) -> 219.82778 | J55: =IF(J20="","",(SUMPRODUCT(((DUR-J$16/365)<0)*CASH)+J20-$G$9*(1+J$16*$C$11/365))*$I$9) -> -466.25002 | ... L55: =IF(L20="","",(SUMPRODUCT(((DUR-L$16/365)<0)*CASH)+L20-$G$9*(1+L$16*$C$11/365))*$I$9) -> -2875.4762 | Q55: 1332 | R55: 银行间固定利率资产支持证券收益率曲线(AAA)
B56: +10bp | C56: =IF(C21="","",(SUMPRODUCT(((DUR-C$16/365)<0)*CASH)+C21-$G$9*(1+C$16*$C$11/365))*$I$9) -> 1436.3292 | D56: =IF(D21="","",(SUMPRODUCT(((DUR-D$16/365)<0)*CASH)+D21-$G$9*(1+D$16*$C$11/365))*$I$9) -> 1365.5941 | E56: =IF(E21="","",(SUMPRODUCT(((DUR-E$16/365)<0)*CASH)+E21-$G$9*(1+E$16*$C$11/365))*$I$9) -> 1283.5686 | F56: =IF(F21="","",(SUMPRODUCT(((DUR-F$16/365)<0)*CASH)+F21-$G$9*(1+F$16*$C$11/365))*$I$9) -> 1202.0805 | G56: =IF(G21="","",(SUMPRODUCT(((DUR-G$16/365)<0)*CASH)+G21-$G$9*(1+G$16*$C$11/365))*$I$9) -> 1097.966 | H56: =IF(H21="","",(SUMPRODUCT(((DUR-H$16/365)<0)*CASH)+H21-$G$9*(1+H$16*$C$11/365))*$I$9) -> 749.15866 | I56: =IF(I21="","",(SUMPRODUCT(((DUR-I$16/365)<0)*CASH)+I21-$G$9*(1+I$16*$C$11/365))*$I$9) -> 399.64056 | J56: =IF(J21="","",(SUMPRODUCT(((DUR-J$16/365)<0)*CASH)+J21-$G$9*(1+J$16*$C$11/365))*$I$9) -> -290.12218 | ... L56: =IF(L21="","",(SUMPRODUCT(((DUR-L$16/365)<0)*CASH)+L21-$G$9*(1+L$16*$C$11/365))*$I$9) -> -2712.4166 | Q56: 1602 | R56: 银行间固定利率资产支持证券收益率曲线(无评级)
B57: +5bp | C57: =IF(C22="","",(SUMPRODUCT(((DUR-C$16/365)<0)*CASH)+C22-$G$9*(1+C$16*$C$11/365))*$I$9) -> 1622.4424 | D57: =IF(D22="","",(SUMPRODUCT(((DUR-D$16/365)<0)*CASH)+D22-$G$9*(1+D$16*$C$11/365))*$I$9) -> 1551.327 | E57: =IF(E22="","",(SUMPRODUCT(((DUR-E$16/365)<0)*CASH)+E22-$G$9*(1+E$16*$C$11/365))*$I$9) -> 1468.8596 | F57: =IF(F22="","",(SUMPRODUCT(((DUR-F$16/365)<0)*CASH)+F22-$G$9*(1+F$16*$C$11/365))*$I$9) -> 1386.9315 | G57: =IF(G22="","",(SUMPRODUCT(((DUR-G$16/365)<0)*CASH)+G22-$G$9*(1+G$16*$C$11/365))*$I$9) -> 1282.2554 | H57: =IF(H22="","",(SUMPRODUCT(((DUR-H$16/365)<0)*CASH)+H22-$G$9*(1+H$16*$C$11/365))*$I$9) -> 931.59048 | I57: =IF(I22="","",(SUMPRODUCT(((DUR-I$16/365)<0)*CASH)+I22-$G$9*(1+I$16*$C$11/365))*$I$9) -> 580.20619 | J57: =IF(J22="","",(SUMPRODUCT(((DUR-J$16/365)<0)*CASH)+J22-$G$9*(1+J$16*$C$11/365))*$I$9) -> -113.27023 | ... L57: =IF(L22="","",(SUMPRODUCT(((DUR-L$16/365)<0)*CASH)+L22-$G$9*(1+L$16*$C$11/365))*$I$9) -> -2548.7307 | Q57: 1342 | R57: 银行间政策性银行浮动利率(1y)债点差收益率曲线
