Workbook

Sheet 基本资料
M1: 可比公司 V1.2 | U1: 最近更新： | V1: =TODAY() -> 45635
C4: 基础信息 | M4: 证券基本资料
C6: 时间 | D6: 日期 | E6: 月份 | F6: 季度 | G6: 年份 | H6: 年初 | I6: 年底 | M6: Wind代码 | N6: 证券简称 | O6: 上市日期 | P6: 上市地点 | Q6: 上市板 | R6: ISIN代码 | S6: 省份 | T6: 城市 | U6: 所属Wind行业 | V6: 行情速览 | Y6: 总市值 | AA6: EPS | AB6: P/E(TTM) | AC6: P/B(MRQ) | AD6: EV/EBITDA | AE6: ROA | AF6: ROE | AG6: 股本股东指标 | AP6: ESG评级
C7: 今日 | D7: =TODAY() -> 45635 | E7: =MONTH(D7) -> 12 | F7: =LEN(2^E7) -> 4 | G7: =YEAR(D7) -> 2024 | H7: =DATE(YEAR(D7),1,1) -> 45292 | I7: =DATE(YEAR(D7),12,31) -> 45657 | V7: 最近交易日 | W7: 最新收盘价 | X7: 最新涨跌幅(%) | Y7: 企业市值(亿元) | Z7: 证券总市值(亿元) | AG7: 总股本(亿股) | AH7: 已发行普通股 | AI7: A股合计 | AJ7: B股 | AK7: 香港股 | AL7: 海外股 | AM7: 股东名称(第1名) | AN7: 股东持股数量(第1名)(万股) | AO7: 股东持股比例(第1名)(%) | AP7: Wind ESG评级 | AQ7: Wind ESG综合得分
C8: 1年前 | D8: =DATE(YEAR(D7)-1,MONTH(D7),DAY(D7)) -> 45269 | E8: =MONTH(D8) -> 12 | F8: =LEN(2^E8) -> 4 | G8: =YEAR(D8) -> 2023 | H8: =DATE(YEAR(D8),1,1) -> 44927 | I8: =DATE(YEAR(D8),12,31) -> 45291 | M8: 000001.SZ | N8: =IF(M8="","",[1]!hks_info_name(M8)) -> 平安银行 | O8: =IF(M8="","",[1]!s_ipo_listeddate(M8)) -> 1991-04-03 | P8: =IF(M8="","",[1]!s_info_exchmarket(M8)) -> 深圳 | Q8: =IF(M8="","",[1]!s_info_mkt(M8)) -> 主板 | R8: =IF(M8="","",[1]!hks_info_isincode(M8)) -> CNE000000040 | S8: =IF(M8="","",[1]!s_info_province(M8)) -> 广东省 | T8: =IF(M8="","",[1]!s_info_city(M8)) -> 深圳市 | U8: =IF(M8="","",[1]!s_info_industry_gics(M8,9)) -> 金融--银行--商业银行--多元化银行 | V8: =IF(M8="","",[1]!lastradeday_s(M8,$D$7)) -> 2024-12-09 | W8: =IF(M8="","",[1]!s_dq_close(M8,V8,3)) -> 11.67 | X8: =IF(M8="","",[1]!s_dq_pctchange(M8,V8)) -> 0.085763293 | Y8: =IF(M8="","",[1]!hks_val_ev(M8,V8,"",100000000)) -> 2264.6707 | Z8: =IF(M8="","",[1]!hks_val_mv_ard(M8,V8,"",100000000)) -> 2264.6707 | AA8: =IF(M8="","",[1]!hks_fa_eps_basic(M8,[1]!s_fa_latelyrd_bt(M8,V8),"")) -> 1.94 | AB8: =IF(M8="","",[1]!hks_val_pe_ttm(M8,V8)) -> 4.8651328 | AC8: =IF(M8="","",[1]!pb_mrq(M8,V8)) -> 0.53853413 | AD8: =IF(M8="","",[1]!s_val_evtoebitda2(M8,V8)) -> 0 | AE8: =IF(M8="","",[1]!hks_fa_roa2(M8,[1]!s_fa_latelyrd_bt(M8,V8))) -> 0 | AF8: =IF(M8="","",[1]!hks_fa_roe(M8,[1]!s_fa_latelyrd_bt(M8,V8))) -> 8.2528 | AG8: =IF(M8="","",[1]!s_share_total(M8,V8,100000000)) -> 194.05918 | AH8: =IF(M8="","",[1]!hks_share_total(M8,V8,100000000)) -> 194.05918 | AI8: =IF(M8="","",[1]!hks_share_totala(M8,V8,100000000)) -> 194.05918 | AJ8: =IF(M8="","",[1]!hks_share_totalb(M8,V8,100000000)) -> 0 | AK8: =IF(M8="","",[1]!hks_share_h(M8,V8,100000000)) -> 0 | AL8: =IF(M8="","",[1]!hks_share_oversea(M8,V8,100000000)) -> 0 | AM8: =IF(M8="","",[1]!hks_holder_name(M8,V8,1)) -> 中国平安保险(集团)股份有限公司-集团本级-自有资金 | AN8: =IF(M8="","",[1]!hks_holder_quantity(M8,V8,1,10000)) -> 961854.02 | AO8: =IF(M8="","",[1]!hks_holder_pct(M8,V8,1)) -> 49.560001 | AP8: =IF(M8="","",[1]!s_esg_rating_wind(M8,V8)) -> A | AQ8: =IF(M8="","",[1]!s_esg_score_wind(M8,V8)) -> 7.19
C9: 2年前 | D9: =DATE(YEAR(D8)-1,MONTH(D8),DAY(D8)) -> 44904 | E9: =MONTH(D9) -> 12 | F9: =LEN(2^E9) -> 4 | G9: =YEAR(D9) -> 2022 | H9: =DATE(YEAR(D9),1,1) -> 44562 | I9: =DATE(YEAR(D9),12,31) -> 44926 | M9: 000002.SZ | N9: =IF(M9="","",[1]!hks_info_name(M9)) -> 万科A | O9: =IF(M9="","",[1]!s_ipo_listeddate(M9)) -> 1991-01-29 | P9: =IF(M9="","",[1]!s_info_exchmarket(M9)) -> 深圳 | Q9: =IF(M9="","",[1]!s_info_mkt(M9)) -> 主板 | R9: =IF(M9="","",[1]!hks_info_isincode(M9)) -> CNE0000000T2 | S9: =IF(M9="","",[1]!s_info_province(M9)) -> 广东省 | T9: =IF(M9="","",[1]!s_info_city(M9)) -> 深圳市 | U9: =IF(M9="","",[1]!s_info_industry_gics(M9,9)) -> 房地产--房地产Ⅱ--房地产管理和开发--房地产开发 | V9: =IF(M9="","",[1]!lastradeday_s(M9,$D$7)) -> 2024-12-09 | W9: =IF(M9="","",[1]!s_dq_close(M9,V9,3)) -> 8.42 | X9: =IF(M9="","",[1]!s_dq_pctchange(M9,V9)) -> -2.9953917 | Y9: =IF(M9="","",[1]!hks_val_ev(M9,V9,"",100000000)) -> 950.57466 | Z9: =IF(M9="","",[1]!hks_val_mv_ard(M9,V9,"",100000000)) -> 1004.5657 | AA9: =IF(M9="","",[1]!hks_fa_eps_basic(M9,[1]!s_fa_latelyrd_bt(M9,V9),"")) -> -1.5132 | AB9: =IF(M9="","",[1]!hks_val_pe_ttm(M9,V9)) -> -5.1776156 | AC9: =IF(M9="","",[1]!pb_mrq(M9,V9)) -> 0.42908166 | AD9: =IF(M9="","",[1]!s_val_evtoebitda2(M9,V9)) -> 9.3365582 | AE9: =IF(M9="","",[1]!hks_fa_roa2(M9,[1]!s_fa_latelyrd_bt(M9,V9))) -> -0.5053 | AF9: =IF(M9="","",[1]!hks_fa_roe(M9,[1]!s_fa_latelyrd_bt(M9,V9))) -> -7.4008 | AG9: =IF(M9="","",[1]!s_share_total(M9,V9,100000000)) -> 119.30709 | AH9: =IF(M9="","",[1]!hks_share_total(M9,V9,100000000)) -> 119.30709 | AI9: =IF(M9="","",[1]!hks_share_totala(M9,V9,100000000)) -> 97.241965 | AJ9: =IF(M9="","",[1]!hks_share_totalb(M9,V9,100000000)) -> 0 | AK9: =IF(M9="","",[1]!hks_share_h(M9,V9,100000000)) -> 22.065129 | AL9: =IF(M9="","",[1]!hks_share_oversea(M9,V9,100000000)) -> 0 | AM9: =IF(M9="","",[1]!hks_holder_name(M9,V9,1)) -> 深圳市地铁集团有限公司 | AN9: =IF(M9="","",[1]!hks_holder_quantity(M9,V9,1,10000)) -> 324281.08 | AO9: =IF(M9="","",[1]!hks_holder_pct(M9,V9,1)) -> 27.18 | AP9: =IF(M9="","",[1]!s_esg_rating_wind(M9,V9)) -> AA | AQ9: =IF(M9="","",[1]!s_esg_score_wind(M9,V9)) -> 8.99
C10: 1年后 | D10: =DATE(YEAR(D7)+1,MONTH(D7),DAY(D7)) -> 46000 | E10: =MONTH(D10) -> 12 | F10: =LEN(2^E10) -> 4 | G10: =YEAR(D10) -> 2025 | H10: =DATE(YEAR(D10),1,1) -> 45658 | I10: =DATE(YEAR(D10),12,31) -> 46022 | M10: 002123.SZ | N10: =IF(M10="","",[1]!hks_info_name(M10)) -> 梦网科技 | O10: =IF(M10="","",[1]!s_ipo_listeddate(M10)) -> 2007-03-28 | P10: =IF(M10="","",[1]!s_info_exchmarket(M10)) -> 深圳 | Q10: =IF(M10="","",[1]!s_info_mkt(M10)) -> 主板 | R10: =IF(M10="","",[1]!hks_info_isincode(M10)) -> CNE100000049 | S10: =IF(M10="","",[1]!s_info_province(M10)) -> 辽宁省 | T10: =IF(M10="","",[1]!s_info_city(M10)) -> 鞍山市 | U10: =IF(M10="","",[1]!s_info_industry_gics(M10,9)) -> 信息技术--技术硬件与设备--通信设备Ⅲ--通信设备 | V10: =IF(M10="","",[1]!lastradeday_s(M10,$D$7)) -> 2024-12-09 | W10: =IF(M10="","",[1]!s_dq_close(M10,V10,3)) -> 10.81 | X10: =IF(M10="","",[1]!s_dq_pctchange(M10,V10)) -> -1.1882998 | Y10: =IF(M10="","",[1]!hks_val_ev(M10,V10,"",100000000)) -> 86.523391 | Z10: =IF(M10="","",[1]!hks_val_mv_ard(M10,V10,"",100000000)) -> 86.523391 | AA10: =IF(M10="","",[1]!hks_fa_eps_basic(M10,[1]!s_fa_latelyrd_bt(M10,V10),"")) -> 0.04 | AB10: =IF(M10="","",[1]!hks_val_pe_ttm(M10,V10)) -> -4.8143735 | AC10: =IF(M10="","",[1]!pb_mrq(M10,V10)) -> 5.2245281 | AD10: =IF(M10="","",[1]!s_val_evtoebitda2(M10,V10)) -> -119.6056 | AE10: =IF(M10="","",[1]!hks_fa_roa2(M10,[1]!s_fa_latelyrd_bt(M10,V10))) -> 0.9579 | AF10: =IF(M10="","",[1]!hks_fa_roe(M10,[1]!s_fa_latelyrd_bt(M10,V10))) -> 1.8552 | AG10: =IF(M10="","",[1]!s_share_total(M10,V10,100000000)) -> 8.004014 | AH10: =IF(M10="","",[1]!hks_share_total(M10,V10,100000000)) -> 8.004014 | AI10: =IF(M10="","",[1]!hks_share_totala(M10,V10,100000000)) -> 8.004014 | AJ10: =IF(M10="","",[1]!hks_share_totalb(M10,V10,100000000)) -> 0 | AK10: =IF(M10="","",[1]!hks_share_h(M10,V10,100000000)) -> 0 | AL10: =IF(M10="","",[1]!hks_share_oversea(M10,V10,100000000)) -> 0 | AM10: =IF(M10="","",[1]!hks_holder_name(M10,V10,1)) -> 余文胜 | AN10: =IF(M10="","",[1]!hks_holder_quantity(M10,V10,1,10000)) -> 11318.737 | AO10: =IF(M10="","",[1]!hks_holder_pct(M10,V10,1)) -> 14.14 | AP10: =IF(M10="","",[1]!s_esg_rating_wind(M10,V10)) -> B | AQ10: =IF(M10="","",[1]!s_esg_score_wind(M10,V10)) -> 4.76
C11: 2年后 | D11: =DATE(YEAR(D10)+1,MONTH(D8),DAY(D8)) -> 46365 | E11: =MONTH(D11) -> 12 | F11: =LEN(2^E11) -> 4 | G11: =YEAR(D11) -> 2026 | H11: =DATE(YEAR(D11),1,1) -> 46023 | I11: =DATE(YEAR(D11),12,31) -> 46387 | M11: 002230.SZ | N11: =IF(M11="","",[1]!hks_info_name(M11)) -> 科大讯飞 | O11: =IF(M11="","",[1]!s_ipo_listeddate(M11)) -> 2008-05-12 | P11: =IF(M11="","",[1]!s_info_exchmarket(M11)) -> 深圳 | Q11: =IF(M11="","",[1]!s_info_mkt(M11)) -> 主板 | R11: =IF(M11="","",[1]!hks_info_isincode(M11)) -> CNE100000B81 | S11: =IF(M11="","",[1]!s_info_province(M11)) -> 安徽省 | T11: =IF(M11="","",[1]!s_info_city(M11)) -> 合肥市 | U11: =IF(M11="","",[1]!s_info_industry_gics(M11,9)) -> 信息技术--软件与服务--软件--应用软件 | V11: =IF(M11="","",[1]!lastradeday_s(M11,$D$7)) -> 2024-12-09 | W11: =IF(M11="","",[1]!s_dq_close(M11,V11,3)) -> 52.68 | X11: =IF(M11="","",[1]!s_dq_pctchange(M11,V11)) -> 1.6595909 | Y11: =IF(M11="","",[1]!hks_val_ev(M11,V11,"",100000000)) -> 1217.8216 | Z11: =IF(M11="","",[1]!hks_val_mv_ard(M11,V11,"",100000000)) -> 1217.8216 | AA11: =IF(M11="","",[1]!hks_fa_eps_basic(M11,[1]!s_fa_latelyrd_bt(M11,V11),"")) -> -0.1489 | AB11: =IF(M11="","",[1]!hks_val_pe_ttm(M11,V11)) -> 568.42059 | AC11: =IF(M11="","",[1]!pb_mrq(M11,V11)) -> 7.3859272 | AD11: =IF(M11="","",[1]!s_val_evtoebitda2(M11,V11)) -> 59.525166 | AE11: =IF(M11="","",[1]!hks_fa_roa2(M11,[1]!s_fa_latelyrd_bt(M11,V11))) -> -1.3872 | AF11: =IF(M11="","",[1]!hks_fa_roe(M11,[1]!s_fa_latelyrd_bt(M11,V11))) -> -2.0507 | AG11: =IF(M11="","",[1]!s_share_total(M11,V11,100000000)) -> 23.117342 | AH11: =IF(M11="","",[1]!hks_share_total(M11,V11,100000000)) -> 23.117342 | AI11: =IF(M11="","",[1]!hks_share_totala(M11,V11,100000000)) -> 23.117342 | AJ11: =IF(M11="","",[1]!hks_share_totalb(M11,V11,100000000)) -> 0 | AK11: =IF(M11="","",[1]!hks_share_h(M11,V11,100000000)) -> 0 | AL11: =IF(M11="","",[1]!hks_share_oversea(M11,V11,100000000)) -> 0 | AM11: =IF(M11="","",[1]!hks_holder_name(M11,V11,1)) -> 中国移动通信有限公司 | AN11: =IF(M11="","",[1]!hks_holder_quantity(M11,V11,1,10000)) -> 23180.05 | AO11: =IF(M11="","",[1]!hks_holder_pct(M11,V11,1)) -> 10.03 | AP11: =IF(M11="","",[1]!s_esg_rating_wind(M11,V11)) -> AAA | AQ11: =IF(M11="","",[1]!s_esg_score_wind(M11,V11)) -> 9.07
M12: 600004.SH | N12: =IF(M12="","",[1]!hks_info_name(M12)) -> 白云机场 | O12: =IF(M12="","",[1]!s_ipo_listeddate(M12)) -> 2003-04-28 | P12: =IF(M12="","",[1]!s_info_exchmarket(M12)) -> 上海 | Q12: =IF(M12="","",[1]!s_info_mkt(M12)) -> 主板 | R12: =IF(M12="","",[1]!hks_info_isincode(M12)) -> CNE000001DX0 | S12: =IF(M12="","",[1]!s_info_province(M12)) -> 广东省 | T12: =IF(M12="","",[1]!s_info_city(M12)) -> 广州市 | U12: =IF(M12="","",[1]!s_info_industry_gics(M12,9)) -> 工业--运输--交通基础设施--机场服务 | V12: =IF(M12="","",[1]!lastradeday_s(M12,$D$7)) -> 2024-12-09 | W12: =IF(M12="","",[1]!s_dq_close(M12,V12,3)) -> 9.85 | X12: =IF(M12="","",[1]!s_dq_pctchange(M12,V12)) -> -0.10141988 | Y12: =IF(M12="","",[1]!hks_val_ev(M12,V12,"",100000000)) -> 233.12175 | Z12: =IF(M12="","",[1]!hks_val_mv_ard(M12,V12,"",100000000)) -> 233.12175 | AA12: =IF(M12="","",[1]!hks_fa_eps_basic(M12,[1]!s_fa_latelyrd_bt(M12,V12),"")) -> 0.28 | AB12: =IF(M12="","",[1]!hks_val_pe_ttm(M12,V12)) -> 27.892939 | AC12: =IF(M12="","",[1]!pb_mrq(M12,V12)) -> 1.289262 | AD12: =IF(M12="","",[1]!s_val_evtoebitda2(M12,V12)) -> 8.8978944 | AE12: =IF(M12="","",[1]!hks_fa_roa2(M12,[1]!s_fa_latelyrd_bt(M12,V12))) -> 3.5914 | AF12: =IF(M12="","",[1]!hks_fa_roe(M12,[1]!s_fa_latelyrd_bt(M12,V12))) -> 3.7446 | AG12: =IF(M12="","",[1]!s_share_total(M12,V12,100000000)) -> 23.667183 | AH12: =IF(M12="","",[1]!hks_share_total(M12,V12,100000000)) -> 23.667183 | AI12: =IF(M12="","",[1]!hks_share_totala(M12,V12,100000000)) -> 23.667183 | AJ12: =IF(M12="","",[1]!hks_share_totalb(M12,V12,100000000)) -> 0 | AK12: =IF(M12="","",[1]!hks_share_h(M12,V12,100000000)) -> 0 | AL12: =IF(M12="","",[1]!hks_share_oversea(M12,V12,100000000)) -> 0 | AM12: =IF(M12="","",[1]!hks_holder_name(M12,V12,1)) -> 广东省机场管理集团有限公司 | AN12: =IF(M12="","",[1]!hks_holder_quantity(M12,V12,1,10000)) -> 135374.46 | AO12: =IF(M12="","",[1]!hks_holder_pct(M12,V12,1)) -> 57.200001 | AP12: =IF(M12="","",[1]!s_esg_rating_wind(M12,V12)) -> BBB | AQ12: =IF(M12="","",[1]!s_esg_score_wind(M12,V12)) -> 6.59
C13: *注：此excel中所有财务相关数据均采用了GSD标准 | M13: 600006.SH | N13: =IF(M13="","",[1]!hks_info_name(M13)) -> 东风股份 | O13: =IF(M13="","",[1]!s_ipo_listeddate(M13)) -> 1999-07-27 | P13: =IF(M13="","",[1]!s_info_exchmarket(M13)) -> 上海 | Q13: =IF(M13="","",[1]!s_info_mkt(M13)) -> 主板 | R13: =IF(M13="","",[1]!hks_info_isincode(M13)) -> CNE000000ZT3 | S13: =IF(M13="","",[1]!s_info_province(M13)) -> 湖北省 | T13: =IF(M13="","",[1]!s_info_city(M13)) -> 襄阳市 | U13: =IF(M13="","",[1]!s_info_industry_gics(M13,9)) -> 可选消费--汽车与汽车零部件--汽车--汽车制造 | V13: =IF(M13="","",[1]!lastradeday_s(M13,$D$7)) -> 2024-12-09 | W13: =IF(M13="","",[1]!s_dq_close(M13,V13,3)) -> 7.86 | X13: =IF(M13="","",[1]!s_dq_pctchange(M13,V13)) -> 4.3824701 | Y13: =IF(M13="","",[1]!hks_val_ev(M13,V13,"",100000000)) -> 157.2 | Z13: =IF(M13="","",[1]!hks_val_mv_ard(M13,V13,"",100000000)) -> 157.2 | AA13: =IF(M13="","",[1]!hks_fa_eps_basic(M13,[1]!s_fa_latelyrd_bt(M13,V13),"")) -> -0.0573 | AB13: =IF(M13="","",[1]!hks_val_pe_ttm(M13,V13)) -> 326.86746 | AC13: =IF(M13="","",[1]!pb_mrq(M13,V13)) -> 1.9324399 | AD13: =IF(M13="","",[1]!s_val_evtoebitda2(M13,V13)) -> -68.989772 | AE13: =IF(M13="","",[1]!hks_fa_roa2(M13,[1]!s_fa_latelyrd_bt(M13,V13))) -> -0.5868 | AF13: =IF(M13="","",[1]!hks_fa_roe(M13,[1]!s_fa_latelyrd_bt(M13,V13))) -> -1.3943 | AG13: =IF(M13="","",[1]!s_share_total(M13,V13,100000000)) -> 20 | AH13: =IF(M13="","",[1]!hks_share_total(M13,V13,100000000)) -> 20 | AI13: =IF(M13="","",[1]!hks_share_totala(M13,V13,100000000)) -> 20 | AJ13: =IF(M13="","",[1]!hks_share_totalb(M13,V13,100000000)) -> 0 | AK13: =IF(M13="","",[1]!hks_share_h(M13,V13,100000000)) -> 0 | AL13: =IF(M13="","",[1]!hks_share_oversea(M13,V13,100000000)) -> 0 | AM13: =IF(M13="","",[1]!hks_holder_name(M13,V13,1)) -> 东风汽车集团股份有限公司 | AN13: =IF(M13="","",[1]!hks_holder_quantity(M13,V13,1,10000)) -> 110000 | AO13: =IF(M13="","",[1]!hks_holder_pct(M13,V13,1)) -> 55 | AP13: =IF(M13="","",[1]!s_esg_rating_wind(M13,V13)) -> BBB | AQ13: =IF(M13="","",[1]!s_esg_score_wind(M13,V13)) -> 6.24
M14: 600007.SH | N14: =IF(M14="","",[1]!hks_info_name(M14)) -> 中国国贸 | O14: =IF(M14="","",[1]!s_ipo_listeddate(M14)) -> 1999-03-12 | P14: =IF(M14="","",[1]!s_info_exchmarket(M14)) -> 上海 | Q14: =IF(M14="","",[1]!s_info_mkt(M14)) -> 主板 | R14: =IF(M14="","",[1]!hks_info_isincode(M14)) -> CNE000000YH1 | S14: =IF(M14="","",[1]!s_info_province(M14)) -> 北京 | T14: =IF(M14="","",[1]!s_info_city(M14)) -> 北京市 | U14: =IF(M14="","",[1]!s_info_industry_gics(M14,9)) -> 房地产--房地产Ⅱ--房地产管理和开发--房地产经营公司 | V14: =IF(M14="","",[1]!lastradeday_s(M14,$D$7)) -> 2024-12-09 | W14: =IF(M14="","",[1]!s_dq_close(M14,V14,3)) -> 22.8 | X14: =IF(M14="","",[1]!s_dq_pctchange(M14,V14)) -> 0.043878894 | Y14: =IF(M14="","",[1]!hks_val_ev(M14,V14,"",100000000)) -> 229.66042 | Z14: =IF(M14="","",[1]!hks_val_mv_ard(M14,V14,"",100000000)) -> 229.66042 | AA14: =IF(M14="","",[1]!hks_fa_eps_basic(M14,[1]!s_fa_latelyrd_bt(M14,V14),"")) -> 1.01 | AB14: =IF(M14="","",[1]!hks_val_pe_ttm(M14,V14)) -> 18.005089 | AC14: =IF(M14="","",[1]!pb_mrq(M14,V14)) -> 2.4407808 | AD14: =IF(M14="","",[1]!s_val_evtoebitda2(M14,V14)) -> 9.337436 | AE14: =IF(M14="","",[1]!hks_fa_roa2(M14,[1]!s_fa_latelyrd_bt(M14,V14))) -> 10.8692 | AF14: =IF(M14="","",[1]!hks_fa_roe(M14,[1]!s_fa_latelyrd_bt(M14,V14))) -> 10.6608 | AG14: =IF(M14="","",[1]!s_share_total(M14,V14,100000000)) -> 10.072825 | AH14: =IF(M14="","",[1]!hks_share_total(M14,V14,100000000)) -> 10.072825 | AI14: =IF(M14="","",[1]!hks_share_totala(M14,V14,100000000)) -> 10.072825 | AJ14: =IF(M14="","",[1]!hks_share_totalb(M14,V14,100000000)) -> 0 | AK14: =IF(M14="","",[1]!hks_share_h(M14,V14,100000000)) -> 0 | AL14: =IF(M14="","",[1]!hks_share_oversea(M14,V14,100000000)) -> 0 | AM14: =IF(M14="","",[1]!hks_holder_name(M14,V14,1)) -> 中国国际贸易中心有限公司 | AN14: =IF(M14="","",[1]!hks_holder_quantity(M14,V14,1,10000)) -> 81236.024 | AO14: =IF(M14="","",[1]!hks_holder_pct(M14,V14,1)) -> 80.650002 | AP14: =IF(M14="","",[1]!s_esg_rating_wind(M14,V14)) -> B | AQ14: =IF(M14="","",[1]!s_esg_score_wind(M14,V14)) -> 4.62
M15: 600941.SH | N15: =IF(M15="","",[1]!hks_info_name(M15)) -> 中国移动 | O15: =IF(M15="","",[1]!s_ipo_listeddate(M15)) -> 2022-01-05 | P15: =IF(M15="","",[1]!s_info_exchmarket(M15)) -> 上海 | Q15: =IF(M15="","",[1]!s_info_mkt(M15)) -> 主板 | R15: =IF(M15="","",[1]!hks_info_isincode(M15)) -> CNE1000055G1 | S15: =IF(M15="","",[1]!s_info_province(M15)) -> 北京 | T15: =IF(M15="","",[1]!s_info_city(M15)) -> 北京市 | U15: =IF(M15="","",[1]!s_info_industry_gics(M15,9)) -> 电信服务--电信服务Ⅱ--多元电信服务--综合电信服务 | V15: =IF(M15="","",[1]!lastradeday_s(M15,$D$7)) -> 2024-12-09 | W15: =IF(M15="","",[1]!s_dq_close(M15,V15,3)) -> 107.29 | X15: =IF(M15="","",[1]!s_dq_pctchange(M15,V15)) -> 0.065286327 | Y15: =IF(M15="","",[1]!hks_val_ev(M15,V15,"",100000000)) -> 14793.594 | Z15: =IF(M15="","",[1]!hks_val_mv_ard(M15,V15,"",100000000)) -> 23053.51 | AA15: =IF(M15="","",[1]!hks_fa_eps_basic(M15,[1]!s_fa_latelyrd_bt(M15,V15),"")) -> 5.18 | AB15: =IF(M15="","",[1]!hks_val_pe_ttm(M15,V15)) -> 16.81008 | AC15: =IF(M15="","",[1]!pb_mrq(M15,V15)) -> 1.7395738 | AD15: =IF(M15="","",[1]!s_val_evtoebitda2(M15,V15)) -> 4.0123437 | AE15: =IF(M15="","",[1]!hks_fa_roa2(M15,[1]!s_fa_latelyrd_bt(M15,V15))) -> 6.42 | AF15: =IF(M15="","",[1]!hks_fa_roe(M15,[1]!s_fa_latelyrd_bt(M15,V15))) -> 8.2065 | AG15: =IF(M15="","",[1]!s_share_total(M15,V15,100000000)) -> 214.87101 | AH15: =IF(M15="","",[1]!hks_share_total(M15,V15,100000000)) -> 214.87101 | AI15: =IF(M15="","",[1]!hks_share_totala(M15,V15,100000000)) -> 9.0276787 | AJ15: =IF(M15="","",[1]!hks_share_totalb(M15,V15,100000000)) -> 0 | AK15: =IF(M15="","",[1]!hks_share_h(M15,V15,100000000)) -> 205.84333 | AL15: =IF(M15="","",[1]!hks_share_oversea(M15,V15,100000000)) -> 0 | AM15: =IF(M15="","",[1]!hks_holder_name(M15,V15,1)) -> 中国移动香港(BVI)有限公司 | AN15: =IF(M15="","",[1]!hks_holder_quantity(M15,V15,1,10000)) -> 1489011.7 | AO15: =IF(M15="","",[1]!hks_holder_pct(M15,V15,1)) -> 69.349998 | AP15: =IF(M15="","",[1]!s_esg_rating_wind(M15,V15)) -> AA | AQ15: =IF(M15="","",[1]!s_esg_score_wind(M15,V15)) -> 8.48
M16: 603160.SH | N16: =IF(M16="","",[1]!hks_info_name(M16)) -> 汇顶科技 | O16: =IF(M16="","",[1]!s_ipo_listeddate(M16)) -> 2016-10-17 | P16: =IF(M16="","",[1]!s_info_exchmarket(M16)) -> 上海 | Q16: =IF(M16="","",[1]!s_info_mkt(M16)) -> 主板 | R16: =IF(M16="","",[1]!hks_info_isincode(M16)) -> CNE100002G84 | S16: =IF(M16="","",[1]!s_info_province(M16)) -> 广东省 | T16: =IF(M16="","",[1]!s_info_city(M16)) -> 深圳市 | U16: =IF(M16="","",[1]!s_info_industry_gics(M16,9)) -> 信息技术--半导体与半导体生产设备--半导体产品与半导体设备--半导体产品 | V16: =IF(M16="","",[1]!lastradeday_s(M16,$D$7)) -> 2024-12-09 | W16: =IF(M16="","",[1]!s_dq_close(M16,V16,3)) -> 89.98 | X16: =IF(M16="","",[1]!s_dq_pctchange(M16,V16)) -> 10 | Y16: =IF(M16="","",[1]!hks_val_ev(M16,V16,"",100000000)) -> 412.34755 | Z16: =IF(M16="","",[1]!hks_val_mv_ard(M16,V16,"",100000000)) -> 412.34755 | AA16: =IF(M16="","",[1]!hks_fa_eps_basic(M16,[1]!s_fa_latelyrd_bt(M16,V16),"")) -> 0.98 | AB16: =IF(M16="","",[1]!hks_val_pe_ttm(M16,V16)) -> 68.642334 | AC16: =IF(M16="","",[1]!pb_mrq(M16,V16)) -> 4.8911095 | AD16: =IF(M16="","",[1]!s_val_evtoebitda2(M16,V16)) -> 70.516108 | AE16: =IF(M16="","",[1]!hks_fa_roa2(M16,[1]!s_fa_latelyrd_bt(M16,V16))) -> 5.3145 | AF16: =IF(M16="","",[1]!hks_fa_roe(M16,[1]!s_fa_latelyrd_bt(M16,V16))) -> 5.4397 | AG16: =IF(M16="","",[1]!s_share_total(M16,V16,100000000)) -> 4.5826578 | AH16: =IF(M16="","",[1]!hks_share_total(M16,V16,100000000)) -> 4.5826578 | AI16: =IF(M16="","",[1]!hks_share_totala(M16,V16,100000000)) -> 4.5826578 | AJ16: =IF(M16="","",[1]!hks_share_totalb(M16,V16,100000000)) -> 0 | AK16: =IF(M16="","",[1]!hks_share_h(M16,V16,100000000)) -> 0 | AL16: =IF(M16="","",[1]!hks_share_oversea(M16,V16,100000000)) -> 0 | AM16: =IF(M16="","",[1]!hks_holder_name(M16,V16,1)) -> 张帆 | AN16: =IF(M16="","",[1]!hks_holder_quantity(M16,V16,1,10000)) -> 20629.638 | AO16: =IF(M16="","",[1]!hks_holder_pct(M16,V16,1)) -> 45.0168 | AP16: =IF(M16="","",[1]!s_esg_rating_wind(M16,V16)) -> B | AQ16: =IF(M16="","",[1]!s_esg_score_wind(M16,V16)) -> 4.64
M17: 688111.SH | N17: =IF(M17="","",[1]!hks_info_name(M17)) -> 金山办公 | O17: =IF(M17="","",[1]!s_ipo_listeddate(M17)) -> 2019-11-18 | P17: =IF(M17="","",[1]!s_info_exchmarket(M17)) -> 上海 | Q17: =IF(M17="","",[1]!s_info_mkt(M17)) -> 科创板 | R17: =IF(M17="","",[1]!hks_info_isincode(M17)) -> CNE100003PM2 | S17: =IF(M17="","",[1]!s_info_province(M17)) -> 北京 | T17: =IF(M17="","",[1]!s_info_city(M17)) -> 北京市 | U17: =IF(M17="","",[1]!s_info_industry_gics(M17,9)) -> 信息技术--软件与服务--软件--应用软件 | V17: =IF(M17="","",[1]!lastradeday_s(M17,$D$7)) -> 2024-12-09 | W17: =IF(M17="","",[1]!s_dq_close(M17,V17,3)) -> 312.6 | X17: =IF(M17="","",[1]!s_dq_pctchange(M17,V17)) -> 4.189581 | Y17: =IF(M17="","",[1]!hks_val_ev(M17,V17,"",100000000)) -> 1445.8552 | Z17: =IF(M17="","",[1]!hks_val_mv_ard(M17,V17,"",100000000)) -> 1445.8552 | AA17: =IF(M17="","",[1]!hks_fa_eps_basic(M17,[1]!s_fa_latelyrd_bt(M17,V17),"")) -> 2.25 | AB17: =IF(M17="","",[1]!hks_val_pe_ttm(M17,V17)) -> 98.737564 | AC17: =IF(M17="","",[1]!pb_mrq(M17,V17)) -> 13.507145 | AD17: =IF(M17="","",[1]!s_val_evtoebitda2(M17,V17)) -> 118.53599 | AE17: =IF(M17="","",[1]!hks_fa_roa2(M17,[1]!s_fa_latelyrd_bt(M17,V17))) -> 7.6847 | AF17: =IF(M17="","",[1]!hks_fa_roe(M17,[1]!s_fa_latelyrd_bt(M17,V17))) -> 10.0699 | AG17: =IF(M17="","",[1]!s_share_total(M17,V17,100000000)) -> 4.6252564 | AH17: =IF(M17="","",[1]!hks_share_total(M17,V17,100000000)) -> 4.6252564 | AI17: =IF(M17="","",[1]!hks_share_totala(M17,V17,100000000)) -> 4.6252564 | AJ17: =IF(M17="","",[1]!hks_share_totalb(M17,V17,100000000)) -> 0 | AK17: =IF(M17="","",[1]!hks_share_h(M17,V17,100000000)) -> 0 | AL17: =IF(M17="","",[1]!hks_share_oversea(M17,V17,100000000)) -> 0 | AM17: =IF(M17="","",[1]!hks_holder_name(M17,V17,1)) -> Kingsoft WPS Corporation Limited | AN17: =IF(M17="","",[1]!hks_holder_quantity(M17,V17,1,10000)) -> 23838.735 | AO17: =IF(M17="","",[1]!hks_holder_pct(M17,V17,1)) -> 51.540001 | AP17: =IF(M17="","",[1]!s_esg_rating_wind(M17,V17)) -> AA | AQ17: =IF(M17="","",[1]!s_esg_score_wind(M17,V17)) -> 8.4
M18: 0700.HK | N18: =IF(M18="","",[1]!hks_info_name(M18)) -> 腾讯控股 | O18: =IF(M18="","",[1]!s_ipo_listeddate(M18)) -> 2004-06-16 | P18: =IF(M18="","",[1]!s_info_exchmarket(M18)) -> 香港联交所 | Q18: =IF(M18="","",[1]!s_info_mkt(M18)) -> 主板 | R18: =IF(M18="","",[1]!hks_info_isincode(M18)) -> KYG875721634 | S18: =IF(M18="","",[1]!s_info_province(M18)) -> 广东省 | T18: =IF(M18="","",[1]!s_info_city(M18)) -> 深圳市 | U18: =IF(M18="","",[1]!s_info_industry_gics(M18,9)) -> 信息技术--软件与服务--互联网软件与服务Ⅲ--互联网软件与服务 | V18: =IF(M18="","",[1]!lastradeday_s(M18,$D$7)) -> 2024-12-06 | W18: =IF(M18="","",[1]!s_dq_close(M18,V18,3)) -> 412.6 | X18: =IF(M18="","",[1]!s_dq_pctchange(M18,V18)) -> 1.8262586 | Y18: =IF(M18="","",[1]!hks_val_ev(M18,V18,"",100000000)) -> 38237.595 | Z18: =IF(M18="","",[1]!hks_val_mv_ard(M18,V18,"",100000000)) -> 38237.595 | AA18: =IF(M18="","",[1]!hks_fa_eps_basic(M18,[1]!s_fa_latelyrd_bt(M18,V18),"")) -> 15.346 | AB18: =IF(M18="","",[1]!hks_val_pe_ttm(M18,V18)) -> 20.310696 | AC18: =IF(M18="","",[1]!pb_mrq(M18,V18)) -> 3.8682324 | AD18: =IF(M18="","",[1]!s_val_evtoebitda2(M18,V18)) -> 17.197141 | AE18: =IF(M18="","",[1]!hks_fa_roa2(M18,[1]!s_fa_latelyrd_bt(M18,V18))) -> 10.6412 | AF18: =IF(M18="","",[1]!hks_fa_roe(M18,[1]!s_fa_latelyrd_bt(M18,V18))) -> 16.5874 | AG18: =IF(M18="","",[1]!s_share_total(M18,V18,100000000)) -> 92.674734 | AH18: =IF(M18="","",[1]!hks_share_total(M18,V18,100000000)) -> 92.674734 | AI18: =IF(M18="","",[1]!hks_share_totala(M18,V18,100000000)) -> 0 | AJ18: =IF(M18="","",[1]!hks_share_totalb(M18,V18,100000000)) -> 0 | AK18: =IF(M18="","",[1]!hks_share_h(M18,V18,100000000)) -> 92.674734 | AL18: =IF(M18="","",[1]!hks_share_oversea(M18,V18,100000000)) -> 0 | AM18: =IF(M18="","",[1]!hks_holder_name(M18,V18,1)) -> MIH Internet Holdings B.V. | AN18: =IF(M18="","",[1]!hks_holder_quantity(M18,V18,1,10000)) -> 228503.13 | AO18: =IF(M18="","",[1]!hks_holder_pct(M18,V18,1)) -> 24.43 | AP18: =IF(M18="","",[1]!s_esg_rating_wind(M18,V18)) -> AA | AQ18: =IF(M18="","",[1]!s_esg_score_wind(M18,V18)) -> 8.14
M19: 9896.HK | N19: =IF(M19="","",[1]!hks_info_name(M19)) -> 名创优品 | O19: =IF(M19="","",[1]!s_ipo_listeddate(M19)) -> 2022-07-13 | P19: =IF(M19="","",[1]!s_info_exchmarket(M19)) -> 香港联交所 | Q19: =IF(M19="","",[1]!s_info_mkt(M19)) -> 主板 | R19: =IF(M19="","",[1]!hks_info_isincode(M19)) -> KYG6180F1081 | S19: =IF(M19="","",[1]!s_info_province(M19)) -> 广东省 | T19: =IF(M19="","",[1]!s_info_city(M19)) -> 广州市 | U19: =IF(M19="","",[1]!s_info_industry_gics(M19,9)) -> 可选消费--零售业--多元化零售--百货商店 | V19: =IF(M19="","",[1]!lastradeday_s(M19,$D$7)) -> 2024-12-06 | W19: =IF(M19="","",[1]!s_dq_close(M19,V19,3)) -> 47.4 | X19: =IF(M19="","",[1]!s_dq_pctchange(M19,V19)) -> 0.74388948 | Y19: =IF(M19="","",[1]!hks_val_ev(M19,V19,"",100000000)) -> 595.47674 | Z19: =IF(M19="","",[1]!hks_val_mv_ard(M19,V19,"",100000000)) -> 595.47674 | AA19: =IF(M19="","",[1]!hks_fa_eps_basic(M19,[1]!s_fa_latelyrd_bt(M19,V19),"")) -> 1.46 | AB19: =IF(M19="","",[1]!hks_val_pe_ttm(M19,V19)) -> 22.843327 | AC19: =IF(M19="","",[1]!pb_mrq(M19,V19)) -> 5.7716712 | AD19: =IF(M19="","",[1]!s_val_evtoebitda2(M19,V19)) -> 0 | AE19: =IF(M19="","",[1]!hks_fa_roa2(M19,[1]!s_fa_latelyrd_bt(M19,V19))) -> 15.6207 | AF19: =IF(M19="","",[1]!hks_fa_roe(M19,[1]!s_fa_latelyrd_bt(M19,V19))) -> 19.3854 | AG19: =IF(M19="","",[1]!s_share_total(M19,V19,100000000)) -> 12.5628 | AH19: =IF(M19="","",[1]!hks_share_total(M19,V19,100000000)) -> 12.5628 | AI19: =IF(M19="","",[1]!hks_share_totala(M19,V19,100000000)) -> 0 | AJ19: =IF(M19="","",[1]!hks_share_totalb(M19,V19,100000000)) -> 0 | AK19: =IF(M19="","",[1]!hks_share_h(M19,V19,100000000)) -> 12.5628 | AL19: =IF(M19="","",[1]!hks_share_oversea(M19,V19,100000000)) -> 0 | AM19: =IF(M19="","",[1]!hks_holder_name(M19,V19,1)) -> Mini Investment Limited | AN19: =IF(M19="","",[1]!hks_holder_quantity(M19,V19,1,10000)) -> 32829.048 | AO19: =IF(M19="","",[1]!hks_holder_pct(M19,V19,1)) -> 26.1 | AP19: =IF(M19="","",[1]!s_esg_rating_wind(M19,V19)) -> AA | AQ19: =IF(M19="","",[1]!s_esg_score_wind(M19,V19)) -> 7.97
M20: 9999.HK | N20: =IF(M20="","",[1]!hks_info_name(M20)) -> 网易-S | O20: =IF(M20="","",[1]!s_ipo_listeddate(M20)) -> 2020-06-11 | P20: =IF(M20="","",[1]!s_info_exchmarket(M20)) -> 香港联交所 | Q20: =IF(M20="","",[1]!s_info_mkt(M20)) -> 主板 | R20: =IF(M20="","",[1]!hks_info_isincode(M20)) -> KYG6427A1022 | S20: =IF(M20="","",[1]!s_info_province(M20)) -> 浙江省 | T20: =IF(M20="","",[1]!s_info_city(M20)) -> 杭州市 | U20: =IF(M20="","",[1]!s_info_industry_gics(M20,9)) -> 信息技术--软件与服务--互联网软件与服务Ⅲ--互联网软件与服务 | V20: =IF(M20="","",[1]!lastradeday_s(M20,$D$7)) -> 2024-12-09 | W20: =IF(M20="","",[1]!s_dq_close(M20,V20,3)) -> 150.9 | X20: =IF(M20="","",[1]!s_dq_pctchange(M20,V20)) -> 6.0435699 | Y20: =IF(M20="","",[1]!hks_val_ev(M20,V20,"",100000000)) -> 4845.0718 | Z20: =IF(M20="","",[1]!hks_val_mv_ard(M20,V20,"",100000000)) -> 0 | AA20: =IF(M20="","",[1]!hks_fa_eps_basic(M20,[1]!s_fa_latelyrd_bt(M20,V20),"")) -> 6.52 | AB20: =IF(M20="","",[1]!hks_val_pe_ttm(M20,V20)) -> 0 | AC20: =IF(M20="","",[1]!pb_mrq(M20,V20)) -> 0 | AD20: =IF(M20="","",[1]!s_val_evtoebitda2(M20,V20)) -> 13.972753 | AE20: =IF(M20="","",[1]!hks_fa_roa2(M20,[1]!s_fa_latelyrd_bt(M20,V20))) -> 13.7068 | AF20: =IF(M20="","",[1]!hks_fa_roe(M20,[1]!s_fa_latelyrd_bt(M20,V20))) -> 16.3246 | AG20: =IF(M20="","",[1]!s_share_total(M20,V20,100000000)) -> 32.107831 | AH20: =IF(M20="","",[1]!hks_share_total(M20,V20,100000000)) -> 32.107831 | AI20: =IF(M20="","",[1]!hks_share_totala(M20,V20,100000000)) -> 0 | AJ20: =IF(M20="","",[1]!hks_share_totalb(M20,V20,100000000)) -> 0 | AK20: =IF(M20="","",[1]!hks_share_h(M20,V20,100000000)) -> 32.107831 | AL20: =IF(M20="","",[1]!hks_share_oversea(M20,V20,100000000)) -> 0 | AM20: =IF(M20="","",[1]!hks_holder_name(M20,V20,1)) -> Shining Globe International Limited | AN20: =IF(M20="","",[1]!hks_holder_quantity(M20,V20,1,10000)) -> 145030 | AO20: =IF(M20="","",[1]!hks_holder_pct(M20,V20,1)) -> 45 | AP20: =IF(M20="","",[1]!s_esg_rating_wind(M20,V20)) -> BB | AQ20: =IF(M20="","",[1]!s_esg_score_wind(M20,V20)) -> 6.05
N21: =IF(M21="","",[1]!hks_info_name(M21)) | O21: =IF(M21="","",[1]!s_ipo_listeddate(M21)) | P21: =IF(M21="","",[1]!s_info_exchmarket(M21)) | Q21: =IF(M21="","",[1]!s_info_mkt(M21)) | R21: =IF(M21="","",[1]!hks_info_isincode(M21)) | S21: =IF(M21="","",[1]!s_info_province(M21)) | T21: =IF(M21="","",[1]!s_info_city(M21)) | U21: =IF(M21="","",[1]!s_info_industry_gics(M21,9)) | V21: =IF(M21="","",[1]!lastradeday_s(M21,$D$7)) | W21: =IF(M21="","",[1]!s_dq_close(M21,V21,3)) | X21: =IF(M21="","",[1]!s_dq_pctchange(M21,V21)) | Y21: =IF(M21="","",[1]!hks_val_ev(M21,V21,"",100000000)) | Z21: =IF(M21="","",[1]!hks_val_mv_ard(M21,V21,"",100000000)) | AA21: =IF(M21="","",[1]!hks_fa_eps_basic(M21,[1]!s_fa_latelyrd_bt(M21,V21),"")) | AB21: =IF(M21="","",[1]!hks_val_pe_ttm(M21,V21)) | AC21: =IF(M21="","",[1]!pb_mrq(M21,V21)) | AD21: =IF(M21="","",[1]!s_val_evtoebitda2(M21,V21)) | AE21: =IF(M21="","",[1]!hks_fa_roa2(M21,[1]!s_fa_latelyrd_bt(M21,V21))) | AF21: =IF(M21="","",[1]!hks_fa_roe(M21,[1]!s_fa_latelyrd_bt(M21,V21))) | AG21: =IF(M21="","",[1]!s_share_total(M21,V21,100000000)) | AH21: =IF(M21="","",[1]!hks_share_total(M21,V21,100000000)) | AI21: =IF(M21="","",[1]!hks_share_totala(M21,V21,100000000)) | AJ21: =IF(M21="","",[1]!hks_share_totalb(M21,V21,100000000)) | AK21: =IF(M21="","",[1]!hks_share_h(M21,V21,100000000)) | AL21: =IF(M21="","",[1]!hks_share_oversea(M21,V21,100000000)) | AM21: =IF(M21="","",[1]!hks_holder_name(M21,V21,1)) | AN21: =IF(M21="","",[1]!hks_holder_quantity(M21,V21,1,10000)) | AO21: =IF(M21="","",[1]!hks_holder_pct(M21,V21,1)) | AP21: =IF(M21="","",[1]!s_esg_rating_wind(M21,V21)) | AQ21: =IF(M21="","",[1]!s_esg_score_wind(M21,V21))
N22: =IF(M22="","",[1]!hks_info_name(M22)) | O22: =IF(M22="","",[1]!s_ipo_listeddate(M22)) | P22: =IF(M22="","",[1]!s_info_exchmarket(M22)) | Q22: =IF(M22="","",[1]!s_info_mkt(M22)) | R22: =IF(M22="","",[1]!hks_info_isincode(M22)) | S22: =IF(M22="","",[1]!s_info_province(M22)) | T22: =IF(M22="","",[1]!s_info_city(M22)) | U22: =IF(M22="","",[1]!s_info_industry_gics(M22,9)) | V22: =IF(M22="","",[1]!lastradeday_s(M22,$D$7)) | W22: =IF(M22="","",[1]!s_dq_close(M22,V22,3)) | X22: =IF(M22="","",[1]!s_dq_pctchange(M22,V22)) | Y22: =IF(M22="","",[1]!hks_val_ev(M22,V22,"",100000000)) | Z22: =IF(M22="","",[1]!hks_val_mv_ard(M22,V22,"",100000000)) | AA22: =IF(M22="","",[1]!hks_fa_eps_basic(M22,[1]!s_fa_latelyrd_bt(M22,V22),"")) | AB22: =IF(M22="","",[1]!hks_val_pe_ttm(M22,V22)) | AC22: =IF(M22="","",[1]!pb_mrq(M22,V22)) | AD22: =IF(M22="","",[1]!s_val_evtoebitda2(M22,V22)) | AE22: =IF(M22="","",[1]!hks_fa_roa2(M22,[1]!s_fa_latelyrd_bt(M22,V22))) | AF22: =IF(M22="","",[1]!hks_fa_roe(M22,[1]!s_fa_latelyrd_bt(M22,V22))) | AG22: =IF(M22="","",[1]!s_share_total(M22,V22,100000000)) | AH22: =IF(M22="","",[1]!hks_share_total(M22,V22,100000000)) | AI22: =IF(M22="","",[1]!hks_share_totala(M22,V22,100000000)) | AJ22: =IF(M22="","",[1]!hks_share_totalb(M22,V22,100000000)) | AK22: =IF(M22="","",[1]!hks_share_h(M22,V22,100000000)) | AL22: =IF(M22="","",[1]!hks_share_oversea(M22,V22,100000000)) | AM22: =IF(M22="","",[1]!hks_holder_name(M22,V22,1)) | AN22: =IF(M22="","",[1]!hks_holder_quantity(M22,V22,1,10000)) | AO22: =IF(M22="","",[1]!hks_holder_pct(M22,V22,1)) | AP22: =IF(M22="","",[1]!s_esg_rating_wind(M22,V22)) | AQ22: =IF(M22="","",[1]!s_esg_score_wind(M22,V22))
N23: =IF(M23="","",[1]!hks_info_name(M23)) | O23: =IF(M23="","",[1]!s_ipo_listeddate(M23)) | P23: =IF(M23="","",[1]!s_info_exchmarket(M23)) | Q23: =IF(M23="","",[1]!s_info_mkt(M23)) | R23: =IF(M23="","",[1]!hks_info_isincode(M23)) | S23: =IF(M23="","",[1]!s_info_province(M23)) | T23: =IF(M23="","",[1]!s_info_city(M23)) | U23: =IF(M23="","",[1]!s_info_industry_gics(M23,9)) | V23: =IF(M23="","",[1]!lastradeday_s(M23,$D$7)) | W23: =IF(M23="","",[1]!s_dq_close(M23,V23,3)) | X23: =IF(M23="","",[1]!s_dq_pctchange(M23,V23)) | Y23: =IF(M23="","",[1]!hks_val_ev(M23,V23,"",100000000)) | Z23: =IF(M23="","",[1]!hks_val_mv_ard(M23,V23,"",100000000)) | AA23: =IF(M23="","",[1]!hks_fa_eps_basic(M23,[1]!s_fa_latelyrd_bt(M23,V23),"")) | AB23: =IF(M23="","",[1]!hks_val_pe_ttm(M23,V23)) | AC23: =IF(M23="","",[1]!pb_mrq(M23,V23)) | AD23: =IF(M23="","",[1]!s_val_evtoebitda2(M23,V23)) | AE23: =IF(M23="","",[1]!hks_fa_roa2(M23,[1]!s_fa_latelyrd_bt(M23,V23))) | AF23: =IF(M23="","",[1]!hks_fa_roe(M23,[1]!s_fa_latelyrd_bt(M23,V23))) | AG23: =IF(M23="","",[1]!s_share_total(M23,V23,100000000)) | AH23: =IF(M23="","",[1]!hks_share_total(M23,V23,100000000)) | AI23: =IF(M23="","",[1]!hks_share_totala(M23,V23,100000000)) | AJ23: =IF(M23="","",[1]!hks_share_totalb(M23,V23,100000000)) | AK23: =IF(M23="","",[1]!hks_share_h(M23,V23,100000000)) | AL23: =IF(M23="","",[1]!hks_share_oversea(M23,V23,100000000)) | AM23: =IF(M23="","",[1]!hks_holder_name(M23,V23,1)) | AN23: =IF(M23="","",[1]!hks_holder_quantity(M23,V23,1,10000)) | AO23: =IF(M23="","",[1]!hks_holder_pct(M23,V23,1)) | AP23: =IF(M23="","",[1]!s_esg_rating_wind(M23,V23)) | AQ23: =IF(M23="","",[1]!s_esg_score_wind(M23,V23))
N24: =IF(M24="","",[1]!hks_info_name(M24)) | O24: =IF(M24="","",[1]!s_ipo_listeddate(M24)) | P24: =IF(M24="","",[1]!s_info_exchmarket(M24)) | Q24: =IF(M24="","",[1]!s_info_mkt(M24)) | R24: =IF(M24="","",[1]!hks_info_isincode(M24)) | S24: =IF(M24="","",[1]!s_info_province(M24)) | T24: =IF(M24="","",[1]!s_info_city(M24)) | U24: =IF(M24="","",[1]!s_info_industry_gics(M24,9)) | V24: =IF(M24="","",[1]!lastradeday_s(M24,$D$7)) | W24: =IF(M24="","",[1]!s_dq_close(M24,V24,3)) | X24: =IF(M24="","",[1]!s_dq_pctchange(M24,V24)) | Y24: =IF(M24="","",[1]!hks_val_ev(M24,V24,"",100000000)) | Z24: =IF(M24="","",[1]!hks_val_mv_ard(M24,V24,"",100000000)) | AA24: =IF(M24="","",[1]!hks_fa_eps_basic(M24,[1]!s_fa_latelyrd_bt(M24,V24),"")) | AB24: =IF(M24="","",[1]!hks_val_pe_ttm(M24,V24)) | AC24: =IF(M24="","",[1]!pb_mrq(M24,V24)) | AD24: =IF(M24="","",[1]!s_val_evtoebitda2(M24,V24)) | AE24: =IF(M24="","",[1]!hks_fa_roa2(M24,[1]!s_fa_latelyrd_bt(M24,V24))) | AF24: =IF(M24="","",[1]!hks_fa_roe(M24,[1]!s_fa_latelyrd_bt(M24,V24))) | AG24: =IF(M24="","",[1]!s_share_total(M24,V24,100000000)) | AH24: =IF(M24="","",[1]!hks_share_total(M24,V24,100000000)) | AI24: =IF(M24="","",[1]!hks_share_totala(M24,V24,100000000)) | AJ24: =IF(M24="","",[1]!hks_share_totalb(M24,V24,100000000)) | AK24: =IF(M24="","",[1]!hks_share_h(M24,V24,100000000)) | AL24: =IF(M24="","",[1]!hks_share_oversea(M24,V24,100000000)) | AM24: =IF(M24="","",[1]!hks_holder_name(M24,V24,1)) | AN24: =IF(M24="","",[1]!hks_holder_quantity(M24,V24,1,10000)) | AO24: =IF(M24="","",[1]!hks_holder_pct(M24,V24,1)) | AP24: =IF(M24="","",[1]!s_esg_rating_wind(M24,V24)) | AQ24: =IF(M24="","",[1]!s_esg_score_wind(M24,V24))
N25: =IF(M25="","",[1]!hks_info_name(M25)) | O25: =IF(M25="","",[1]!s_ipo_listeddate(M25)) | P25: =IF(M25="","",[1]!s_info_exchmarket(M25)) | Q25: =IF(M25="","",[1]!s_info_mkt(M25)) | R25: =IF(M25="","",[1]!hks_info_isincode(M25)) | S25: =IF(M25="","",[1]!s_info_province(M25)) | T25: =IF(M25="","",[1]!s_info_city(M25)) | U25: =IF(M25="","",[1]!s_info_industry_gics(M25,9)) | V25: =IF(M25="","",[1]!lastradeday_s(M25,$D$7)) | W25: =IF(M25="","",[1]!s_dq_close(M25,V25,3)) | X25: =IF(M25="","",[1]!s_dq_pctchange(M25,V25)) | Y25: =IF(M25="","",[1]!hks_val_ev(M25,V25,"",100000000)) | Z25: =IF(M25="","",[1]!hks_val_mv_ard(M25,V25,"",100000000)) | AA25: =IF(M25="","",[1]!hks_fa_eps_basic(M25,[1]!s_fa_latelyrd_bt(M25,V25),"")) | AB25: =IF(M25="","",[1]!hks_val_pe_ttm(M25,V25)) | AC25: =IF(M25="","",[1]!pb_mrq(M25,V25)) | AD25: =IF(M25="","",[1]!s_val_evtoebitda2(M25,V25)) | AE25: =IF(M25="","",[1]!hks_fa_roa2(M25,[1]!s_fa_latelyrd_bt(M25,V25))) | AF25: =IF(M25="","",[1]!hks_fa_roe(M25,[1]!s_fa_latelyrd_bt(M25,V25))) | AG25: =IF(M25="","",[1]!s_share_total(M25,V25,100000000)) | AH25: =IF(M25="","",[1]!hks_share_total(M25,V25,100000000)) | AI25: =IF(M25="","",[1]!hks_share_totala(M25,V25,100000000)) | AJ25: =IF(M25="","",[1]!hks_share_totalb(M25,V25,100000000)) | AK25: =IF(M25="","",[1]!hks_share_h(M25,V25,100000000)) | AL25: =IF(M25="","",[1]!hks_share_oversea(M25,V25,100000000)) | AM25: =IF(M25="","",[1]!hks_holder_name(M25,V25,1)) | AN25: =IF(M25="","",[1]!hks_holder_quantity(M25,V25,1,10000)) | AO25: =IF(M25="","",[1]!hks_holder_pct(M25,V25,1)) | AP25: =IF(M25="","",[1]!s_esg_rating_wind(M25,V25)) | AQ25: =IF(M25="","",[1]!s_esg_score_wind(M25,V25))
N26: =IF(M26="","",[1]!hks_info_name(M26)) | O26: =IF(M26="","",[1]!s_ipo_listeddate(M26)) | P26: =IF(M26="","",[1]!s_info_exchmarket(M26)) | Q26: =IF(M26="","",[1]!s_info_mkt(M26)) | R26: =IF(M26="","",[1]!hks_info_isincode(M26)) | S26: =IF(M26="","",[1]!s_info_province(M26)) | T26: =IF(M26="","",[1]!s_info_city(M26)) | U26: =IF(M26="","",[1]!s_info_industry_gics(M26,9)) | V26: =IF(M26="","",[1]!lastradeday_s(M26,$D$7)) | W26: =IF(M26="","",[1]!s_dq_close(M26,V26,3)) | X26: =IF(M26="","",[1]!s_dq_pctchange(M26,V26)) | Y26: =IF(M26="","",[1]!hks_val_ev(M26,V26,"",100000000)) | Z26: =IF(M26="","",[1]!hks_val_mv_ard(M26,V26,"",100000000)) | AA26: =IF(M26="","",[1]!hks_fa_eps_basic(M26,[1]!s_fa_latelyrd_bt(M26,V26),"")) | AB26: =IF(M26="","",[1]!hks_val_pe_ttm(M26,V26)) | AC26: =IF(M26="","",[1]!pb_mrq(M26,V26)) | AD26: =IF(M26="","",[1]!s_val_evtoebitda2(M26,V26)) | AE26: =IF(M26="","",[1]!hks_fa_roa2(M26,[1]!s_fa_latelyrd_bt(M26,V26))) | AF26: =IF(M26="","",[1]!hks_fa_roe(M26,[1]!s_fa_latelyrd_bt(M26,V26))) | AG26: =IF(M26="","",[1]!s_share_total(M26,V26,100000000)) | AH26: =IF(M26="","",[1]!hks_share_total(M26,V26,100000000)) | AI26: =IF(M26="","",[1]!hks_share_totala(M26,V26,100000000)) | AJ26: =IF(M26="","",[1]!hks_share_totalb(M26,V26,100000000)) | AK26: =IF(M26="","",[1]!hks_share_h(M26,V26,100000000)) | AL26: =IF(M26="","",[1]!hks_share_oversea(M26,V26,100000000)) | AM26: =IF(M26="","",[1]!hks_holder_name(M26,V26,1)) | AN26: =IF(M26="","",[1]!hks_holder_quantity(M26,V26,1,10000)) | AO26: =IF(M26="","",[1]!hks_holder_pct(M26,V26,1)) | AP26: =IF(M26="","",[1]!s_esg_rating_wind(M26,V26)) | AQ26: =IF(M26="","",[1]!s_esg_score_wind(M26,V26))
N27: =IF(M27="","",[1]!hks_info_name(M27)) | O27: =IF(M27="","",[1]!s_ipo_listeddate(M27)) | P27: =IF(M27="","",[1]!s_info_exchmarket(M27)) | Q27: =IF(M27="","",[1]!s_info_mkt(M27)) | R27: =IF(M27="","",[1]!hks_info_isincode(M27)) | S27: =IF(M27="","",[1]!s_info_province(M27)) | T27: =IF(M27="","",[1]!s_info_city(M27)) | U27: =IF(M27="","",[1]!s_info_industry_gics(M27,9)) | V27: =IF(M27="","",[1]!lastradeday_s(M27,$D$7)) | W27: =IF(M27="","",[1]!s_dq_close(M27,V27,3)) | X27: =IF(M27="","",[1]!s_dq_pctchange(M27,V27)) | Y27: =IF(M27="","",[1]!hks_val_ev(M27,V27,"",100000000)) | Z27: =IF(M27="","",[1]!hks_val_mv_ard(M27,V27,"",100000000)) | AA27: =IF(M27="","",[1]!hks_fa_eps_basic(M27,[1]!s_fa_latelyrd_bt(M27,V27),"")) | AB27: =IF(M27="","",[1]!hks_val_pe_ttm(M27,V27)) | AC27: =IF(M27="","",[1]!pb_mrq(M27,V27)) | AD27: =IF(M27="","",[1]!s_val_evtoebitda2(M27,V27)) | AE27: =IF(M27="","",[1]!hks_fa_roa2(M27,[1]!s_fa_latelyrd_bt(M27,V27))) | AF27: =IF(M27="","",[1]!hks_fa_roe(M27,[1]!s_fa_latelyrd_bt(M27,V27))) | AG27: =IF(M27="","",[1]!s_share_total(M27,V27,100000000)) | AH27: =IF(M27="","",[1]!hks_share_total(M27,V27,100000000)) | AI27: =IF(M27="","",[1]!hks_share_totala(M27,V27,100000000)) | AJ27: =IF(M27="","",[1]!hks_share_totalb(M27,V27,100000000)) | AK27: =IF(M27="","",[1]!hks_share_h(M27,V27,100000000)) | AL27: =IF(M27="","",[1]!hks_share_oversea(M27,V27,100000000)) | AM27: =IF(M27="","",[1]!hks_holder_name(M27,V27,1)) | AN27: =IF(M27="","",[1]!hks_holder_quantity(M27,V27,1,10000)) | AO27: =IF(M27="","",[1]!hks_holder_pct(M27,V27,1)) | AP27: =IF(M27="","",[1]!s_esg_rating_wind(M27,V27)) | AQ27: =IF(M27="","",[1]!s_esg_score_wind(M27,V27))
N28: =IF(M28="","",[1]!hks_info_name(M28)) | O28: =IF(M28="","",[1]!s_ipo_listeddate(M28)) | P28: =IF(M28="","",[1]!s_info_exchmarket(M28)) | Q28: =IF(M28="","",[1]!s_info_mkt(M28)) | R28: =IF(M28="","",[1]!hks_info_isincode(M28)) | S28: =IF(M28="","",[1]!s_info_province(M28)) | T28: =IF(M28="","",[1]!s_info_city(M28)) | U28: =IF(M28="","",[1]!s_info_industry_gics(M28,9)) | V28: =IF(M28="","",[1]!lastradeday_s(M28,$D$7)) | W28: =IF(M28="","",[1]!s_dq_close(M28,V28,3)) | X28: =IF(M28="","",[1]!s_dq_pctchange(M28,V28)) | Y28: =IF(M28="","",[1]!hks_val_ev(M28,V28,"",100000000)) | Z28: =IF(M28="","",[1]!hks_val_mv_ard(M28,V28,"",100000000)) | AA28: =IF(M28="","",[1]!hks_fa_eps_basic(M28,[1]!s_fa_latelyrd_bt(M28,V28),"")) | AB28: =IF(M28="","",[1]!hks_val_pe_ttm(M28,V28)) | AC28: =IF(M28="","",[1]!pb_mrq(M28,V28)) | AD28: =IF(M28="","",[1]!s_val_evtoebitda2(M28,V28)) | AE28: =IF(M28="","",[1]!hks_fa_roa2(M28,[1]!s_fa_latelyrd_bt(M28,V28))) | AF28: =IF(M28="","",[1]!hks_fa_roe(M28,[1]!s_fa_latelyrd_bt(M28,V28))) | AG28: =IF(M28="","",[1]!s_share_total(M28,V28,100000000)) | AH28: =IF(M28="","",[1]!hks_share_total(M28,V28,100000000)) | AI28: =IF(M28="","",[1]!hks_share_totala(M28,V28,100000000)) | AJ28: =IF(M28="","",[1]!hks_share_totalb(M28,V28,100000000)) | AK28: =IF(M28="","",[1]!hks_share_h(M28,V28,100000000)) | AL28: =IF(M28="","",[1]!hks_share_oversea(M28,V28,100000000)) | AM28: =IF(M28="","",[1]!hks_holder_name(M28,V28,1)) | AN28: =IF(M28="","",[1]!hks_holder_quantity(M28,V28,1,10000)) | AO28: =IF(M28="","",[1]!hks_holder_pct(M28,V28,1)) | AP28: =IF(M28="","",[1]!s_esg_rating_wind(M28,V28)) | AQ28: =IF(M28="","",[1]!s_esg_score_wind(M28,V28))
N29: =IF(M29="","",[1]!hks_info_name(M29)) | O29: =IF(M29="","",[1]!s_ipo_listeddate(M29)) | P29: =IF(M29="","",[1]!s_info_exchmarket(M29)) | Q29: =IF(M29="","",[1]!s_info_mkt(M29)) | R29: =IF(M29="","",[1]!hks_info_isincode(M29)) | S29: =IF(M29="","",[1]!s_info_province(M29)) | T29: =IF(M29="","",[1]!s_info_city(M29)) | U29: =IF(M29="","",[1]!s_info_industry_gics(M29,9)) | V29: =IF(M29="","",[1]!lastradeday_s(M29,$D$7)) | W29: =IF(M29="","",[1]!s_dq_close(M29,V29,3)) | X29: =IF(M29="","",[1]!s_dq_pctchange(M29,V29)) | Y29: =IF(M29="","",[1]!hks_val_ev(M29,V29,"",100000000)) | Z29: =IF(M29="","",[1]!hks_val_mv_ard(M29,V29,"",100000000)) | AA29: =IF(M29="","",[1]!hks_fa_eps_basic(M29,[1]!s_fa_latelyrd_bt(M29,V29),"")) | AB29: =IF(M29="","",[1]!hks_val_pe_ttm(M29,V29)) | AC29: =IF(M29="","",[1]!pb_mrq(M29,V29)) | AD29: =IF(M29="","",[1]!s_val_evtoebitda2(M29,V29)) | AE29: =IF(M29="","",[1]!hks_fa_roa2(M29,[1]!s_fa_latelyrd_bt(M29,V29))) | AF29: =IF(M29="","",[1]!hks_fa_roe(M29,[1]!s_fa_latelyrd_bt(M29,V29))) | AG29: =IF(M29="","",[1]!s_share_total(M29,V29,100000000)) | AH29: =IF(M29="","",[1]!hks_share_total(M29,V29,100000000)) | AI29: =IF(M29="","",[1]!hks_share_totala(M29,V29,100000000)) | AJ29: =IF(M29="","",[1]!hks_share_totalb(M29,V29,100000000)) | AK29: =IF(M29="","",[1]!hks_share_h(M29,V29,100000000)) | AL29: =IF(M29="","",[1]!hks_share_oversea(M29,V29,100000000)) | AM29: =IF(M29="","",[1]!hks_holder_name(M29,V29,1)) | AN29: =IF(M29="","",[1]!hks_holder_quantity(M29,V29,1,10000)) | AO29: =IF(M29="","",[1]!hks_holder_pct(M29,V29,1)) | AP29: =IF(M29="","",[1]!s_esg_rating_wind(M29,V29)) | AQ29: =IF(M29="","",[1]!s_esg_score_wind(M29,V29))
N30: =IF(M30="","",[1]!hks_info_name(M30)) | O30: =IF(M30="","",[1]!s_ipo_listeddate(M30)) | P30: =IF(M30="","",[1]!s_info_exchmarket(M30)) | Q30: =IF(M30="","",[1]!s_info_mkt(M30)) | R30: =IF(M30="","",[1]!hks_info_isincode(M30)) | S30: =IF(M30="","",[1]!s_info_province(M30)) | T30: =IF(M30="","",[1]!s_info_city(M30)) | U30: =IF(M30="","",[1]!s_info_industry_gics(M30,9)) | V30: =IF(M30="","",[1]!lastradeday_s(M30,$D$7)) | W30: =IF(M30="","",[1]!s_dq_close(M30,V30,3)) | X30: =IF(M30="","",[1]!s_dq_pctchange(M30,V30)) | Y30: =IF(M30="","",[1]!hks_val_ev(M30,V30,"",100000000)) | Z30: =IF(M30="","",[1]!hks_val_mv_ard(M30,V30,"",100000000)) | AA30: =IF(M30="","",[1]!hks_fa_eps_basic(M30,[1]!s_fa_latelyrd_bt(M30,V30),"")) | AB30: =IF(M30="","",[1]!hks_val_pe_ttm(M30,V30)) | AC30: =IF(M30="","",[1]!pb_mrq(M30,V30)) | AD30: =IF(M30="","",[1]!s_val_evtoebitda2(M30,V30)) | AE30: =IF(M30="","",[1]!hks_fa_roa2(M30,[1]!s_fa_latelyrd_bt(M30,V30))) | AF30: =IF(M30="","",[1]!hks_fa_roe(M30,[1]!s_fa_latelyrd_bt(M30,V30))) | AG30: =IF(M30="","",[1]!s_share_total(M30,V30,100000000)) | AH30: =IF(M30="","",[1]!hks_share_total(M30,V30,100000000)) | AI30: =IF(M30="","",[1]!hks_share_totala(M30,V30,100000000)) | AJ30: =IF(M30="","",[1]!hks_share_totalb(M30,V30,100000000)) | AK30: =IF(M30="","",[1]!hks_share_h(M30,V30,100000000)) | AL30: =IF(M30="","",[1]!hks_share_oversea(M30,V30,100000000)) | AM30: =IF(M30="","",[1]!hks_holder_name(M30,V30,1)) | AN30: =IF(M30="","",[1]!hks_holder_quantity(M30,V30,1,10000)) | AO30: =IF(M30="","",[1]!hks_holder_pct(M30,V30,1)) | AP30: =IF(M30="","",[1]!s_esg_rating_wind(M30,V30)) | AQ30: =IF(M30="","",[1]!s_esg_score_wind(M30,V30))
N31: =IF(M31="","",[1]!hks_info_name(M31)) | O31: =IF(M31="","",[1]!s_ipo_listeddate(M31)) | P31: =IF(M31="","",[1]!s_info_exchmarket(M31)) | Q31: =IF(M31="","",[1]!s_info_mkt(M31)) | R31: =IF(M31="","",[1]!hks_info_isincode(M31)) | S31: =IF(M31="","",[1]!s_info_province(M31)) | T31: =IF(M31="","",[1]!s_info_city(M31)) | U31: =IF(M31="","",[1]!s_info_industry_gics(M31,9)) | V31: =IF(M31="","",[1]!lastradeday_s(M31,$D$7)) | W31: =IF(M31="","",[1]!s_dq_close(M31,V31,3)) | X31: =IF(M31="","",[1]!s_dq_pctchange(M31,V31)) | Y31: =IF(M31="","",[1]!hks_val_ev(M31,V31,"",100000000)) | Z31: =IF(M31="","",[1]!hks_val_mv_ard(M31,V31,"",100000000)) | AA31: =IF(M31="","",[1]!hks_fa_eps_basic(M31,[1]!s_fa_latelyrd_bt(M31,V31),"")) | AB31: =IF(M31="","",[1]!hks_val_pe_ttm(M31,V31)) | AC31: =IF(M31="","",[1]!pb_mrq(M31,V31)) | AD31: =IF(M31="","",[1]!s_val_evtoebitda2(M31,V31)) | AE31: =IF(M31="","",[1]!hks_fa_roa2(M31,[1]!s_fa_latelyrd_bt(M31,V31))) | AF31: =IF(M31="","",[1]!hks_fa_roe(M31,[1]!s_fa_latelyrd_bt(M31,V31))) | AG31: =IF(M31="","",[1]!s_share_total(M31,V31,100000000)) | AH31: =IF(M31="","",[1]!hks_share_total(M31,V31,100000000)) | AI31: =IF(M31="","",[1]!hks_share_totala(M31,V31,100000000)) | AJ31: =IF(M31="","",[1]!hks_share_totalb(M31,V31,100000000)) | AK31: =IF(M31="","",[1]!hks_share_h(M31,V31,100000000)) | AL31: =IF(M31="","",[1]!hks_share_oversea(M31,V31,100000000)) | AM31: =IF(M31="","",[1]!hks_holder_name(M31,V31,1)) | AN31: =IF(M31="","",[1]!hks_holder_quantity(M31,V31,1,10000)) | AO31: =IF(M31="","",[1]!hks_holder_pct(M31,V31,1)) | AP31: =IF(M31="","",[1]!s_esg_rating_wind(M31,V31)) | AQ31: =IF(M31="","",[1]!s_esg_score_wind(M31,V31))
N32: =IF(M32="","",[1]!hks_info_name(M32)) | O32: =IF(M32="","",[1]!s_ipo_listeddate(M32)) | P32: =IF(M32="","",[1]!s_info_exchmarket(M32)) | Q32: =IF(M32="","",[1]!s_info_mkt(M32)) | R32: =IF(M32="","",[1]!hks_info_isincode(M32)) | S32: =IF(M32="","",[1]!s_info_province(M32)) | T32: =IF(M32="","",[1]!s_info_city(M32)) | U32: =IF(M32="","",[1]!s_info_industry_gics(M32,9)) | V32: =IF(M32="","",[1]!lastradeday_s(M32,$D$7)) | W32: =IF(M32="","",[1]!s_dq_close(M32,V32,3)) | X32: =IF(M32="","",[1]!s_dq_pctchange(M32,V32)) | Y32: =IF(M32="","",[1]!hks_val_ev(M32,V32,"",100000000)) | Z32: =IF(M32="","",[1]!hks_val_mv_ard(M32,V32,"",100000000)) | AA32: =IF(M32="","",[1]!hks_fa_eps_basic(M32,[1]!s_fa_latelyrd_bt(M32,V32),"")) | AB32: =IF(M32="","",[1]!hks_val_pe_ttm(M32,V32)) | AC32: =IF(M32="","",[1]!pb_mrq(M32,V32)) | AD32: =IF(M32="","",[1]!s_val_evtoebitda2(M32,V32)) | AE32: =IF(M32="","",[1]!hks_fa_roa2(M32,[1]!s_fa_latelyrd_bt(M32,V32))) | AF32: =IF(M32="","",[1]!hks_fa_roe(M32,[1]!s_fa_latelyrd_bt(M32,V32))) | AG32: =IF(M32="","",[1]!s_share_total(M32,V32,100000000)) | AH32: =IF(M32="","",[1]!hks_share_total(M32,V32,100000000)) | AI32: =IF(M32="","",[1]!hks_share_totala(M32,V32,100000000)) | AJ32: =IF(M32="","",[1]!hks_share_totalb(M32,V32,100000000)) | AK32: =IF(M32="","",[1]!hks_share_h(M32,V32,100000000)) | AL32: =IF(M32="","",[1]!hks_share_oversea(M32,V32,100000000)) | AM32: =IF(M32="","",[1]!hks_holder_name(M32,V32,1)) | AN32: =IF(M32="","",[1]!hks_holder_quantity(M32,V32,1,10000)) | AO32: =IF(M32="","",[1]!hks_holder_pct(M32,V32,1)) | AP32: =IF(M32="","",[1]!s_esg_rating_wind(M32,V32)) | AQ32: =IF(M32="","",[1]!s_esg_score_wind(M32,V32))
... N100: =IF(M100="","",[1]!hks_info_name(M100)) | O100: =IF(M100="","",[1]!s_ipo_listeddate(M100)) | P100: =IF(M100="","",[1]!s_info_exchmarket(M100)) | Q100: =IF(M100="","",[1]!s_info_mkt(M100)) | R100: =IF(M100="","",[1]!hks_info_isincode(M100)) | S100: =IF(M100="","",[1]!s_info_province(M100)) | T100: =IF(M100="","",[1]!s_info_city(M100)) | U100: =IF(M100="","",[1]!s_info_industry_gics(M100,9)) | V100: =IF(M100="","",[1]!lastradeday_s(M100,$D$7)) | W100: =IF(M100="","",[1]!s_dq_close(M100,V100,3)) | X100: =IF(M100="","",[1]!s_dq_pctchange(M100,V100)) | Y100: =IF(M100="","",[1]!hks_val_ev(M100,V100,"",100000000)) | Z100: =IF(M100="","",[1]!hks_val_mv_ard(M100,V100,"",100000000)) | AA100: =IF(M100="","",[1]!hks_fa_eps_basic(M100,[1]!s_fa_latelyrd_bt(M100,V100),"")) | AB100: =IF(M100="","",[1]!hks_val_pe_ttm(M100,V100)) | AC100: =IF(M100="","",[1]!pb_mrq(M100,V100)) | AD100: =IF(M100="","",[1]!s_val_evtoebitda2(M100,V100)) | AE100: =IF(M100="","",[1]!hks_fa_roa2(M100,[1]!s_fa_latelyrd_bt(M100,V100))) | AF100: =IF(M100="","",[1]!hks_fa_roe(M100,[1]!s_fa_latelyrd_bt(M100,V100))) | AG100: =IF(M100="","",[1]!s_share_total(M100,V100,100000000)) | AH100: =IF(M100="","",[1]!hks_share_total(M100,V100,100000000)) | AI100: =IF(M100="","",[1]!hks_share_totala(M100,V100,100000000)) | AJ100: =IF(M100="","",[1]!hks_share_totalb(M100,V100,100000000)) | AK100: =IF(M100="","",[1]!hks_share_h(M100,V100,100000000)) | AL100: =IF(M100="","",[1]!hks_share_oversea(M100,V100,100000000)) | AM100: =IF(M100="","",[1]!hks_holder_name(M100,V100,1)) | AN100: =IF(M100="","",[1]!hks_holder_quantity(M100,V100,1,10000)) | AO100: =IF(M100="","",[1]!hks_holder_pct(M100,V100,1)) | AP100: =IF(M100="","",[1]!s_esg_rating_wind(M100,V100)) | AQ100: =IF(M100="","",[1]!s_esg_score_wind(M100,V100))

Sheet 财务报表摘要
D1: 可比公司-资产负债表
C4: 财务报表摘要
C6: Wind代码 | D6: 证券简称 | E6: 最新收盘日 | F6: 最近一期年报日期 | G6: 最近一期年报记账本位币 | H6: 利润表摘要(亿元) | Q6: 资产负债表摘要(亿元) | AB6: 现金流量表摘要(亿元)
H7: 营业总收入 | I7: 营业总成本 | J7: 营业利润 | K7: 净利润 | L7: 归属普通股东净利润 | M7: 非经常性损益 | N7: 研发支出 | O7: EBIT(反推法) | P7: EBITDA(反推法) | Q7: 现金及现金等价物 | R7: 流动资产 | S7: 固定资产 | T7: 非流动资产合计 | U7: 权益性投资 | V7: 资产总计 | W7: 流动负债 | X7: 非流动负债 | Y7: 负债合计 | Z7: 股东权益 | AA7: 归属母公司股东的权益 | AB7: 经营活动现金净流量 | AC7: 资本性支出 | AD7: 投资活动现金净流量 | AE7: 筹资活动现金净流量 | AF7: 现金及现金等价物净增加额 | AG7: 现金及现金等价物期末余额
C8: =IF(表1[[#This Row],[列1]]="","",表1[[#This Row],[列1]]) -> 000001.SZ | D8: =IF(C8="","",[1]!hks_info_name(C8)) -> 平安银行 | E8: =IF(C8="","",[1]!lastradeday_s(C8,TODAY())) -> 2024-12-09 | F8: =IF(C8="","",IF(OR([1]!s_stm_rpt_e(C8,基本资料!$I$8,0)="#N/A",[1]!s_stm_rpt_e(C8,基本资料!$I$8,0)="",[1]!s_stm_rpt_e(C8,基本资料!$I$8,0)=0),[1]!s_stm_rpt_e(C8,基本资料!$I$9,0),[1]!s_stm_rpt_e(C8,基本资料!$I$8,0))) -> 2023-12-31 | G8: =IF(C8="","",[1]!hks_info_cur2(C8,F8)) -> CNY | H8: =IF(C8="","",[1]!hks_stm_is(C8,"83",F8,1,"",100000000)) -> 1629.81 | I8: =IF(C8="","",[1]!hks_stm_is(C8,"1032",F8,1,"",100000000)) -> 1050.53 | J8: =IF(C8="","",[1]!hks_stm_is(C8,"1041",F8,1,"",100000000)) -> 579.28 | K8: =IF(C8="","",[1]!hks_stm_is(C8,"61",F8,1,"",100000000)) -> 464.55 | L8: =IF(C8="","",[1]!hks_stm_is(C8,"1075",F8,1,"",100000000)) -> 464.55 | M8: =IF(C8="","",[1]!hks_stm_is(C8,"1077",F8,1,"",100000000)) -> -5.64 | N8: =IF(C8="","",[1]!hks_stm_is(C8,"1030",F8,1,"",100000000)) -> 0 | O8: =IF(C8="","",[1]!hks_fa_ebit(C8,F8,1,"",100000000)) -> 0 | P8: =IF(C8="","",[1]!hks_fa_ebitda(C8,F8,1,"",100000000)) -> 0 | Q8: =IF(C8="","",[1]!hks_stm_bs(C8,"9",F8,1,"",100000000)) -> 0 | R8: =IF(C8="","",[1]!hks_stm_bs(C8,"25",F8,1,"",100000000)) -> 0 | S8: =IF(C8="","",[1]!hks_stm_bs(C8,"1088",F8,1,"",100000000)) -> 0 | T8: =IF(C8="","",[1]!hks_stm_bs(C8,"46",F8,1,"",100000000)) -> 0 | U8: =IF(C8="","",[1]!hks_stm_bs(C8,"29",F8,1,"",100000000)) -> 0 | V8: =IF(C8="","",[1]!hks_stm_bs(C8,"74",F8,1,"",100000000)) -> 55871.16 | W8: =IF(C8="","",[1]!hks_stm_bs(C8,"93",F8,1,"",100000000)) -> 0 | X8: =IF(C8="","",[1]!hks_stm_bs(C8,"1017",F8,1,"",100000000)) -> 0 | Y8: =IF(C8="","",[1]!hks_stm_bs(C8,"128",F8,1,"",100000000)) -> 51147.88 | Z8: =IF(C8="","",[1]!hks_stm_bs(C8,"145",F8,1,"",100000000)) -> 4723.28 | AA8: =IF(C8="","",[1]!hks_stm_bs(C8,"140",F8,1,"",100000000)) -> 4723.28 | AB8: =IF(C8="","",[1]!hks_stm_cs(C8,"39",F8,1,"",100000000)) -> 924.61 | AC8: =IF(C8="","",[1]!hks_stm_cs(C8,"1020",F8,1,"",100000000)) -> 30.96 | AD8: =IF(C8="","",[1]!hks_stm_cs(C8,"59",F8,1,"",100000000)) -> -261.42 | AE8: =IF(C8="","",[1]!hks_stm_cs(C8,"77",F8,1,"",100000000)) -> 80.89 | AF8: =IF(C8="","",[1]!hks_stm_cs(C8,"82",F8,1,"",100000000)) -> 758.93 | AG8: =IF(C8="","",[1]!hks_stm_cs(C8,"84",F8,1,"",100000000)) -> 2982.19
C9: =IF(表1[[#This Row],[列1]]="","",表1[[#This Row],[列1]]) -> 000002.SZ | D9: =IF(C9="","",[1]!hks_info_name(C9)) -> 万科A | E9: =IF(C9="","",[1]!lastradeday_s(C9,TODAY())) -> 2024-12-09 | F9: =IF(C9="","",IF(OR([1]!s_stm_rpt_e(C9,基本资料!$I$8,0)="#N/A",[1]!s_stm_rpt_e(C9,基本资料!$I$8,0)="",[1]!s_stm_rpt_e(C9,基本资料!$I$8,0)=0),[1]!s_stm_rpt_e(C9,基本资料!$I$9,0),[1]!s_stm_rpt_e(C9,基本资料!$I$8,0))) -> 2023-12-31 | G9: =IF(C9="","",[1]!hks_info_cur2(C9,F9)) -> CNY | H9: =IF(C9="","",[1]!hks_stm_is(C9,"83",F9,1,"",100000000)) -> 4663.5415 | I9: =IF(C9="","",[1]!hks_stm_is(C9,"1032",F9,1,"",100000000)) -> 4225.5719 | J9: =IF(C9="","",[1]!hks_stm_is(C9,"1041",F9,1,"",100000000)) -> 437.96966 | K9: =IF(C9="","",[1]!hks_stm_is(C9,"61",F9,1,"",100000000)) -> 121.62684 | L9: =IF(C9="","",[1]!hks_stm_is(C9,"1075",F9,1,"",100000000)) -> 121.62684 | M9: =IF(C9="","",[1]!hks_stm_is(C9,"1077",F9,1,"",100000000)) -> 34.67674 | N9: =IF(C9="","",[1]!hks_stm_is(C9,"1030",F9,1,"",100000000)) -> 0 | O9: =IF(C9="","",[1]!hks_fa_ebit(C9,F9,1,"",100000000)) -> 468.16806 | P9: =IF(C9="","",[1]!hks_fa_ebitda(C9,F9,1,"",100000000)) -> 558.97601 | Q9: =IF(C9="","",[1]!hks_stm_bs(C9,"9",F9,1,"",100000000)) -> 969.42577 | R9: =IF(C9="","",[1]!hks_stm_bs(C9,"25",F9,1,"",100000000)) -> 11502.821 | S9: =IF(C9="","",[1]!hks_stm_bs(C9,"1088",F9,1,"",100000000)) -> 0 | T9: =IF(C9="","",[1]!hks_stm_bs(C9,"46",F9,1,"",100000000)) -> 3545.9011 | U9: =IF(C9="","",[1]!hks_stm_bs(C9,"29",F9,1,"",100000000)) -> 1305.6253 | V9: =IF(C9="","",[1]!hks_stm_bs(C9,"74",F9,1,"",100000000)) -> 15048.722 | W9: =IF(C9="","",[1]!hks_stm_bs(C9,"93",F9,1,"",100000000)) -> 8217.8526 | X9: =IF(C9="","",[1]!hks_stm_bs(C9,"1017",F9,1,"",100000000)) -> 2801.5338 | Y9: =IF(C9="","",[1]!hks_stm_bs(C9,"128",F9,1,"",100000000)) -> 11019.386 | Z9: =IF(C9="","",[1]!hks_stm_bs(C9,"145",F9,1,"",100000000)) -> 4029.3353 | AA9: =IF(C9="","",[1]!hks_stm_bs(C9,"140",F9,1,"",100000000)) -> 2507.8461 | AB9: =IF(C9="","",[1]!hks_stm_cs(C9,"39",F9,1,"",100000000)) -> 39.12323 | AC9: =IF(C9="","",[1]!hks_stm_cs(C9,"1020",F9,1,"",100000000)) -> 83.34153 | AD9: =IF(C9="","",[1]!hks_stm_cs(C9,"59",F9,1,"",100000000)) -> -46.15642 | AE9: =IF(C9="","",[1]!hks_stm_cs(C9,"77",F9,1,"",100000000)) -> -368.13164 | AF9: =IF(C9="","",[1]!hks_stm_cs(C9,"82",F9,1,"",100000000)) -> -374.82093 | AG9: =IF(C9="","",[1]!hks_stm_cs(C9,"84",F9,1,"",100000000)) -> 969.42577
C10: =IF(表1[[#This Row],[列1]]="","",表1[[#This Row],[列1]]) -> 002123.SZ | D10: =IF(C10="","",[1]!hks_info_name(C10)) -> 梦网科技 | E10: =IF(C10="","",[1]!lastradeday_s(C10,TODAY())) -> 2024-12-09 | F10: =IF(C10="","",IF(OR([1]!s_stm_rpt_e(C10,基本资料!$I$8,0)="#N/A",[1]!s_stm_rpt_e(C10,基本资料!$I$8,0)="",[1]!s_stm_rpt_e(C10,基本资料!$I$8,0)=0),[1]!s_stm_rpt_e(C10,基本资料!$I$9,0),[1]!s_stm_rpt_e(C10,基本资料!$I$8,0))) -> 2023-12-31 | G10: =IF(C10="","",[1]!hks_info_cur2(C10,F10)) -> CNY | H10: =IF(C10="","",[1]!hks_stm_is(C10,"83",F10,1,"",100000000)) -> 52.26865 | I10: =IF(C10="","",[1]!hks_stm_is(C10,"1032",F10,1,"",100000000)) -> 87.476583 | J10: =IF(C10="","",[1]!hks_stm_is(C10,"1041",F10,1,"",100000000)) -> -35.207933 | K10: =IF(C10="","",[1]!hks_stm_is(C10,"61",F10,1,"",100000000)) -> -18.224854 | L10: =IF(C10="","",[1]!hks_stm_is(C10,"1075",F10,1,"",100000000)) -> -18.224854 | M10: =IF(C10="","",[1]!hks_stm_is(C10,"1077",F10,1,"",100000000)) -> -0.082948486 | N10: =IF(C10="","",[1]!hks_stm_is(C10,"1030",F10,1,"",100000000)) -> 0 | O10: =IF(C10="","",[1]!hks_fa_ebit(C10,F10,1,"",100000000)) -> -18.32476 | P10: =IF(C10="","",[1]!hks_fa_ebitda(C10,F10,1,"",100000000)) -> -17.900584 | Q10: =IF(C10="","",[1]!hks_stm_bs(C10,"9",F10,1,"",100000000)) -> 3.7838149 | R10: =IF(C10="","",[1]!hks_stm_bs(C10,"25",F10,1,"",100000000)) -> 34.642016 | S10: =IF(C10="","",[1]!hks_stm_bs(C10,"1088",F10,1,"",100000000)) -> 0 | T10: =IF(C10="","",[1]!hks_stm_bs(C10,"46",F10,1,"",100000000)) -> 8.8545093 | U10: =IF(C10="","",[1]!hks_stm_bs(C10,"29",F10,1,"",100000000)) -> 0.99310165 | V10: =IF(C10="","",[1]!hks_stm_bs(C10,"74",F10,1,"",100000000)) -> 43.496525 | W10: =IF(C10="","",[1]!hks_stm_bs(C10,"93",F10,1,"",100000000)) -> 25.122499 | X10: =IF(C10="","",[1]!hks_stm_bs(C10,"1017",F10,1,"",100000000)) -> 2.0673113 | Y10: =IF(C10="","",[1]!hks_stm_bs(C10,"128",F10,1,"",100000000)) -> 27.18981 | Z10: =IF(C10="","",[1]!hks_stm_bs(C10,"145",F10,1,"",100000000)) -> 16.306715 | AA10: =IF(C10="","",[1]!hks_stm_bs(C10,"140",F10,1,"",100000000)) -> 16.253357 | AB10: =IF(C10="","",[1]!hks_stm_cs(C10,"39",F10,1,"",100000000)) -> -3.9893286 | AC10: =IF(C10="","",[1]!hks_stm_cs(C10,"1020",F10,1,"",100000000)) -> 0.09988601 | AD10: =IF(C10="","",[1]!hks_stm_cs(C10,"59",F10,1,"",100000000)) -> 3.9889926 | AE10: =IF(C10="","",[1]!hks_stm_cs(C10,"77",F10,1,"",100000000)) -> -1.4448183 | AF10: =IF(C10="","",[1]!hks_stm_cs(C10,"82",F10,1,"",100000000)) -> -1.4129896 | AG10: =IF(C10="","",[1]!hks_stm_cs(C10,"84",F10,1,"",100000000)) -> 3.7838149
C11: =IF(表1[[#This Row],[列1]]="","",表1[[#This Row],[列1]]) -> 002230.SZ | D11: =IF(C11="","",[1]!hks_info_name(C11)) -> 科大讯飞 | E11: =IF(C11="","",[1]!lastradeday_s(C11,TODAY())) -> 2024-12-09 | F11: =IF(C11="","",IF(OR([1]!s_stm_rpt_e(C11,基本资料!$I$8,0)="#N/A",[1]!s_stm_rpt_e(C11,基本资料!$I$8,0)="",[1]!s_stm_rpt_e(C11,基本资料!$I$8,0)=0),[1]!s_stm_rpt_e(C11,基本资料!$I$9,0),[1]!s_stm_rpt_e(C11,基本资料!$I$8,0))) -> 2023-12-31 | G11: =IF(C11="","",[1]!hks_info_cur2(C11,F11)) -> CNY | H11: =IF(C11="","",[1]!hks_stm_is(C11,"83",F11,1,"",100000000)) -> 195.23881 | I11: =IF(C11="","",[1]!hks_stm_is(C11,"1032",F11,1,"",100000000)) -> 205.49054 | J11: =IF(C11="","",[1]!hks_stm_is(C11,"1041",F11,1,"",100000000)) -> -10.251725 | K11: =IF(C11="","",[1]!hks_stm_is(C11,"61",F11,1,"",100000000)) -> 6.5731291 | L11: =IF(C11="","",[1]!hks_stm_is(C11,"1075",F11,1,"",100000000)) -> 6.5731291 | M11: =IF(C11="","",[1]!hks_stm_is(C11,"1077",F11,1,"",100000000)) -> 0.70491983 | N11: =IF(C11="","",[1]!hks_stm_is(C11,"1030",F11,1,"",100000000)) -> 0 | O11: =IF(C11="","",[1]!hks_fa_ebit(C11,F11,1,"",100000000)) -> 4.19771 | P11: =IF(C11="","",[1]!hks_fa_ebitda(C11,F11,1,"",100000000)) -> 22.151207 | Q11: =IF(C11="","",[1]!hks_stm_bs(C11,"9",F11,1,"",100000000)) -> 33.829103 | R11: =IF(C11="","",[1]!hks_stm_bs(C11,"25",F11,1,"",100000000)) -> 211.99919 | S11: =IF(C11="","",[1]!hks_stm_bs(C11,"1088",F11,1,"",100000000)) -> 0 | T11: =IF(C11="","",[1]!hks_stm_bs(C11,"46",F11,1,"",100000000)) -> 166.31204 | U11: =IF(C11="","",[1]!hks_stm_bs(C11,"29",F11,1,"",100000000)) -> 14.37179 | V11: =IF(C11="","",[1]!hks_stm_bs(C11,"74",F11,1,"",100000000)) -> 378.31123 | W11: =IF(C11="","",[1]!hks_stm_bs(C11,"93",F11,1,"",100000000)) -> 129.07582 | X11: =IF(C11="","",[1]!hks_stm_bs(C11,"1017",F11,1,"",100000000)) -> 71.915069 | Y11: =IF(C11="","",[1]!hks_stm_bs(C11,"128",F11,1,"",100000000)) -> 200.99089 | Z11: =IF(C11="","",[1]!hks_stm_bs(C11,"145",F11,1,"",100000000)) -> 177.32034 | AA11: =IF(C11="","",[1]!hks_stm_bs(C11,"140",F11,1,"",100000000)) -> 170.32285 | AB11: =IF(C11="","",[1]!hks_stm_cs(C11,"39",F11,1,"",100000000)) -> 3.4975781 | AC11: =IF(C11="","",[1]!hks_stm_cs(C11,"1020",F11,1,"",100000000)) -> 40.818576 | AD11: =IF(C11="","",[1]!hks_stm_cs(C11,"59",F11,1,"",100000000)) -> -39.787283 | AE11: =IF(C11="","",[1]!hks_stm_cs(C11,"77",F11,1,"",100000000)) -> 28.297044 | AF11: =IF(C11="","",[1]!hks_stm_cs(C11,"82",F11,1,"",100000000)) -> -7.8994421 | AG11: =IF(C11="","",[1]!hks_stm_cs(C11,"84",F11,1,"",100000000)) -> 33.829103
C12: =IF(表1[[#This Row],[列1]]="","",表1[[#This Row],[列1]]) -> 600004.SH | D12: =IF(C12="","",[1]!hks_info_name(C12)) -> 白云机场 | E12: =IF(C12="","",[1]!lastradeday_s(C12,TODAY())) -> 2024-12-09 | F12: =IF(C12="","",IF(OR([1]!s_stm_rpt_e(C12,基本资料!$I$8,0)="#N/A",[1]!s_stm_rpt_e(C12,基本资料!$I$8,0)="",[1]!s_stm_rpt_e(C12,基本资料!$I$8,0)=0),[1]!s_stm_rpt_e(C12,基本资料!$I$9,0),[1]!s_stm_rpt_e(C12,基本资料!$I$8,0))) -> 2023-12-31 | G12: =IF(C12="","",[1]!hks_info_cur2(C12,F12)) -> CNY | H12: =IF(C12="","",[1]!hks_stm_is(C12,"83",F12,1,"",100000000)) -> 62.76789 | I12: =IF(C12="","",[1]!hks_stm_is(C12,"1032",F12,1,"",100000000)) -> 56.785818 | J12: =IF(C12="","",[1]!hks_stm_is(C12,"1041",F12,1,"",100000000)) -> 5.9820721 | K12: =IF(C12="","",[1]!hks_stm_is(C12,"61",F12,1,"",100000000)) -> 4.4190572 | L12: =IF(C12="","",[1]!hks_stm_is(C12,"1075",F12,1,"",100000000)) -> 4.4190572 | M12: =IF(C12="","",[1]!hks_stm_is(C12,"1077",F12,1,"",100000000)) -> 0.064274749 | N12: =IF(C12="","",[1]!hks_stm_is(C12,"1030",F12,1,"",100000000)) -> 0 | O12: =IF(C12="","",[1]!hks_fa_ebit(C12,F12,1,"",100000000)) -> 6.7778002 | P12: =IF(C12="","",[1]!hks_fa_ebitda(C12,F12,1,"",100000000)) -> 21.108965 | Q12: =IF(C12="","",[1]!hks_stm_bs(C12,"9",F12,1,"",100000000)) -> 25.215467 | R12: =IF(C12="","",[1]!hks_stm_bs(C12,"25",F12,1,"",100000000)) -> 40.262336 | S12: =IF(C12="","",[1]!hks_stm_bs(C12,"1088",F12,1,"",100000000)) -> 0 | T12: =IF(C12="","",[1]!hks_stm_bs(C12,"46",F12,1,"",100000000)) -> 221.63812 | U12: =IF(C12="","",[1]!hks_stm_bs(C12,"29",F12,1,"",100000000)) -> 6.4919657 | V12: =IF(C12="","",[1]!hks_stm_bs(C12,"74",F12,1,"",100000000)) -> 261.90046 | W12: =IF(C12="","",[1]!hks_stm_bs(C12,"93",F12,1,"",100000000)) -> 59.045467 | X12: =IF(C12="","",[1]!hks_stm_bs(C12,"1017",F12,1,"",100000000)) -> 24.791561 | Y12: =IF(C12="","",[1]!hks_stm_bs(C12,"128",F12,1,"",100000000)) -> 83.837027 | Z12: =IF(C12="","",[1]!hks_stm_bs(C12,"145",F12,1,"",100000000)) -> 178.06343 | AA12: =IF(C12="","",[1]!hks_stm_bs(C12,"140",F12,1,"",100000000)) -> 175.93269 | AB12: =IF(C12="","",[1]!hks_stm_cs(C12,"39",F12,1,"",100000000)) -> 23.596651 | AC12: =IF(C12="","",[1]!hks_stm_cs(C12,"1020",F12,1,"",100000000)) -> 5.9723829 | AD12: =IF(C12="","",[1]!hks_stm_cs(C12,"59",F12,1,"",100000000)) -> -5.5174124 | AE12: =IF(C12="","",[1]!hks_stm_cs(C12,"77",F12,1,"",100000000)) -> -15.055606 | AF12: =IF(C12="","",[1]!hks_stm_cs(C12,"82",F12,1,"",100000000)) -> 3.0239912 | AG12: =IF(C12="","",[1]!hks_stm_cs(C12,"84",F12,1,"",100000000)) -> 25.215467
C13: =IF(表1[[#This Row],[列1]]="","",表1[[#This Row],[列1]]) -> 600006.SH | D13: =IF(C13="","",[1]!hks_info_name(C13)) -> 东风股份 | E13: =IF(C13="","",[1]!lastradeday_s(C13,TODAY())) -> 2024-12-09 | F13: =IF(C13="","",IF(OR([1]!s_stm_rpt_e(C13,基本资料!$I$8,0)="#N/A",[1]!s_stm_rpt_e(C13,基本资料!$I$8,0)="",[1]!s_stm_rpt_e(C13,基本资料!$I$8,0)=0),[1]!s_stm_rpt_e(C13,基本资料!$I$9,0),[1]!s_stm_rpt_e(C13,基本资料!$I$8,0))) -> 2023-12-31 | G13: =IF(C13="","",[1]!hks_info_cur2(C13,F13)) -> CNY | H13: =IF(C13="","",[1]!hks_stm_is(C13,"83",F13,1,"",100000000)) -> 119.66827 | I13: =IF(C13="","",[1]!hks_stm_is(C13,"1032",F13,1,"",100000000)) -> 127.73978 | J13: =IF(C13="","",[1]!hks_stm_is(C13,"1041",F13,1,"",100000000)) -> -8.071508 | K13: =IF(C13="","",[1]!hks_stm_is(C13,"61",F13,1,"",100000000)) -> 2.0004117 | L13: =IF(C13="","",[1]!hks_stm_is(C13,"1075",F13,1,"",100000000)) -> 2.0004117 | M13: =IF(C13="","",[1]!hks_stm_is(C13,"1077",F13,1,"",100000000)) -> 0.034884019 | N13: =IF(C13="","",[1]!hks_stm_is(C13,"1030",F13,1,"",100000000)) -> 0 | O13: =IF(C13="","",[1]!hks_fa_ebit(C13,F13,1,"",100000000)) -> 2.0562679 | P13: =IF(C13="","",[1]!hks_fa_ebitda(C13,F13,1,"",100000000)) -> 4.9567804 | Q13: =IF(C13="","",[1]!hks_stm_bs(C13,"9",F13,1,"",100000000)) -> 48.640322 | R13: =IF(C13="","",[1]!hks_stm_bs(C13,"25",F13,1,"",100000000)) -> 146.10688 | S13: =IF(C13="","",[1]!hks_stm_bs(C13,"1088",F13,1,"",100000000)) -> 0 | T13: =IF(C13="","",[1]!hks_stm_bs(C13,"46",F13,1,"",100000000)) -> 45.611977 | U13: =IF(C13="","",[1]!hks_stm_bs(C13,"29",F13,1,"",100000000)) -> 15.486994 | V13: =IF(C13="","",[1]!hks_stm_bs(C13,"74",F13,1,"",100000000)) -> 191.71886 | W13: =IF(C13="","",[1]!hks_stm_bs(C13,"93",F13,1,"",100000000)) -> 97.287482 | X13: =IF(C13="","",[1]!hks_stm_bs(C13,"1017",F13,1,"",100000000)) -> 8.4510965 | Y13: =IF(C13="","",[1]!hks_stm_bs(C13,"128",F13,1,"",100000000)) -> 105.73858 | Z13: =IF(C13="","",[1]!hks_stm_bs(C13,"145",F13,1,"",100000000)) -> 85.980282 | AA13: =IF(C13="","",[1]!hks_stm_bs(C13,"140",F13,1,"",100000000)) -> 83.096374 | AB13: =IF(C13="","",[1]!hks_stm_cs(C13,"39",F13,1,"",100000000)) -> -2.6555485 | AC13: =IF(C13="","",[1]!hks_stm_cs(C13,"1020",F13,1,"",100000000)) -> 2.0320085 | AD13: =IF(C13="","",[1]!hks_stm_cs(C13,"59",F13,1,"",100000000)) -> -2.5577559 | AE13: =IF(C13="","",[1]!hks_stm_cs(C13,"77",F13,1,"",100000000)) -> -0.98847045 | AF13: =IF(C13="","",[1]!hks_stm_cs(C13,"82",F13,1,"",100000000)) -> -6.1973939 | AG13: =IF(C13="","",[1]!hks_stm_cs(C13,"84",F13,1,"",100000000)) -> 48.640322
C14: =IF(表1[[#This Row],[列1]]="","",表1[[#This Row],[列1]]) -> 600007.SH | D14: =IF(C14="","",[1]!hks_info_name(C14)) -> 中国国贸 | E14: =IF(C14="","",[1]!lastradeday_s(C14,TODAY())) -> 2024-12-09 | F14: =IF(C14="","",IF(OR([1]!s_stm_rpt_e(C14,基本资料!$I$8,0)="#N/A",[1]!s_stm_rpt_e(C14,基本资料!$I$8,0)="",[1]!s_stm_rpt_e(C14,基本资料!$I$8,0)=0),[1]!s_stm_rpt_e(C14,基本资料!$I$9,0),[1]!s_stm_rpt_e(C14,基本资料!$I$8,0))) -> 2023-12-31 | G14: =IF(C14="","",[1]!hks_info_cur2(C14,F14)) -> CNY | H14: =IF(C14="","",[1]!hks_stm_is(C14,"83",F14,1,"",100000000)) -> 35.694647 | I14: =IF(C14="","",[1]!hks_stm_is(C14,"1032",F14,1,"",100000000)) -> 18.673464 | J14: =IF(C14="","",[1]!hks_stm_is(C14,"1041",F14,1,"",100000000)) -> 17.021183 | K14: =IF(C14="","",[1]!hks_stm_is(C14,"61",F14,1,"",100000000)) -> 12.592013 | L14: =IF(C14="","",[1]!hks_stm_is(C14,"1075",F14,1,"",100000000)) -> 12.592013 | M14: =IF(C14="","",[1]!hks_stm_is(C14,"1077",F14,1,"",100000000)) -> 0.07758264 | N14: =IF(C14="","",[1]!hks_stm_is(C14,"1030",F14,1,"",100000000)) -> 0 | O14: =IF(C14="","",[1]!hks_fa_ebit(C14,F14,1,"",100000000)) -> 16.802588 | P14: =IF(C14="","",[1]!hks_fa_ebitda(C14,F14,1,"",100000000)) -> 21.518756 | Q14: =IF(C14="","",[1]!hks_stm_bs(C14,"9",F14,1,"",100000000)) -> 38.901691 | R14: =IF(C14="","",[1]!hks_stm_bs(C14,"25",F14,1,"",100000000)) -> 44.241558 | S14: =IF(C14="","",[1]!hks_stm_bs(C14,"1088",F14,1,"",100000000)) -> 0 | T14: =IF(C14="","",[1]!hks_stm_bs(C14,"46",F14,1,"",100000000)) -> 84.569793 | U14: =IF(C14="","",[1]!hks_stm_bs(C14,"29",F14,1,"",100000000)) -> 0.2942211 | V14: =IF(C14="","",[1]!hks_stm_bs(C14,"74",F14,1,"",100000000)) -> 128.81135 | W14: =IF(C14="","",[1]!hks_stm_bs(C14,"93",F14,1,"",100000000)) -> 20.543555 | X14: =IF(C14="","",[1]!hks_stm_bs(C14,"1017",F14,1,"",100000000)) -> 11.227955 | Y14: =IF(C14="","",[1]!hks_stm_bs(C14,"128",F14,1,"",100000000)) -> 31.77151 | Z14: =IF(C14="","",[1]!hks_stm_bs(C14,"145",F14,1,"",100000000)) -> 97.03984 | AA14: =IF(C14="","",[1]!hks_stm_bs(C14,"140",F14,1,"",100000000)) -> 97.001583 | AB14: =IF(C14="","",[1]!hks_stm_cs(C14,"39",F14,1,"",100000000)) -> 19.186609 | AC14: =IF(C14="","",[1]!hks_stm_cs(C14,"1020",F14,1,"",100000000)) -> 0.66012133 | AD14: =IF(C14="","",[1]!hks_stm_cs(C14,"59",F14,1,"",100000000)) -> -0.64835794 | AE14: =IF(C14="","",[1]!hks_stm_cs(C14,"77",F14,1,"",100000000)) -> -12.898338 | AF14: =IF(C14="","",[1]!hks_stm_cs(C14,"82",F14,1,"",100000000)) -> 5.6361682 | AG14: =IF(C14="","",[1]!hks_stm_cs(C14,"84",F14,1,"",100000000)) -> 38.901691
C15: =IF(表1[[#This Row],[列1]]="","",表1[[#This Row],[列1]]) -> 600941.SH | D15: =IF(C15="","",[1]!hks_info_name(C15)) -> 中国移动 | E15: =IF(C15="","",[1]!lastradeday_s(C15,TODAY())) -> 2024-12-09 | F15: =IF(C15="","",IF(OR([1]!s_stm_rpt_e(C15,基本资料!$I$8,0)="#N/A",[1]!s_stm_rpt_e(C15,基本资料!$I$8,0)="",[1]!s_stm_rpt_e(C15,基本资料!$I$8,0)=0),[1]!s_stm_rpt_e(C15,基本资料!$I$9,0),[1]!s_stm_rpt_e(C15,基本资料!$I$8,0))) -> 2023-12-31 | G15: =IF(C15="","",[1]!hks_info_cur2(C15,F15)) -> CNY | H15: =IF(C15="","",[1]!hks_stm_is(C15,"83",F15,1,"",100000000)) -> 10134.68 | I15: =IF(C15="","",[1]!hks_stm_is(C15,"1032",F15,1,"",100000000)) -> 8743.57 | J15: =IF(C15="","",[1]!hks_stm_is(C15,"1041",F15,1,"",100000000)) -> 1391.11 | K15: =IF(C15="","",[1]!hks_stm_is(C15,"61",F15,1,"",100000000)) -> 1317.66 | L15: =IF(C15="","",[1]!hks_stm_is(C15,"1075",F15,1,"",100000000)) -> 1317.66 | M15: =IF(C15="","",[1]!hks_stm_is(C15,"1077",F15,1,"",100000000)) -> 150.35 | N15: =IF(C15="","",[1]!hks_stm_is(C15,"1030",F15,1,"",100000000)) -> 68.15 | O15: =IF(C15="","",[1]!hks_fa_ebit(C15,F15,1,"",100000000)) -> 1667.51 | P15: =IF(C15="","",[1]!hks_fa_ebitda(C15,F15,1,"",100000000)) -> 3738.83 | Q15: =IF(C15="","",[1]!hks_stm_bs(C15,"9",F15,1,"",100000000)) -> 1415.59 | R15: =IF(C15="","",[1]!hks_stm_bs(C15,"25",F15,1,"",100000000)) -> 4981.04 | S15: =IF(C15="","",[1]!hks_stm_bs(C15,"1088",F15,1,"",100000000)) -> 0 | T15: =IF(C15="","",[1]!hks_stm_bs(C15,"46",F15,1,"",100000000)) -> 14945.53 | U15: =IF(C15="","",[1]!hks_stm_bs(C15,"29",F15,1,"",100000000)) -> 1817.15 | V15: =IF(C15="","",[1]!hks_stm_bs(C15,"74",F15,1,"",100000000)) -> 19926.57 | W15: =IF(C15="","",[1]!hks_stm_bs(C15,"93",F15,1,"",100000000)) -> 5585.65 | X15: =IF(C15="","",[1]!hks_stm_bs(C15,"1017",F15,1,"",100000000)) -> 881.07 | Y15: =IF(C15="","",[1]!hks_stm_bs(C15,"128",F15,1,"",100000000)) -> 6466.72 | Z15: =IF(C15="","",[1]!hks_stm_bs(C15,"145",F15,1,"",100000000)) -> 13459.85 | AA15: =IF(C15="","",[1]!hks_stm_bs(C15,"140",F15,1,"",100000000)) -> 13417.32 | AB15: =IF(C15="","",[1]!hks_stm_cs(C15,"39",F15,1,"",100000000)) -> 3037.8 | AC15: =IF(C15="","",[1]!hks_stm_cs(C15,"1020",F15,1,"",100000000)) -> 1812.63 | AD15: =IF(C15="","",[1]!hks_stm_cs(C15,"59",F15,1,"",100000000)) -> -2056.99 | AE15: =IF(C15="","",[1]!hks_stm_cs(C15,"77",F15,1,"",100000000)) -> -1238.43 | AF15: =IF(C15="","",[1]!hks_stm_cs(C15,"82",F15,1,"",100000000)) -> -255.47 | AG15: =IF(C15="","",[1]!hks_stm_cs(C15,"84",F15,1,"",100000000)) -> 1415.59
C16: =IF(表1[[#This Row],[列1]]="","",表1[[#This Row],[列1]]) -> 603160.SH | D16: =IF(C16="","",[1]!hks_info_name(C16)) -> 汇顶科技 | E16: =IF(C16="","",[1]!lastradeday_s(C16,TODAY())) -> 2024-12-09 | F16: =IF(C16="","",IF(OR([1]!s_stm_rpt_e(C16,基本资料!$I$8,0)="#N/A",[1]!s_stm_rpt_e(C16,基本资料!$I$8,0)="",[1]!s_stm_rpt_e(C16,基本资料!$I$8,0)=0),[1]!s_stm_rpt_e(C16,基本资料!$I$9,0),[1]!s_stm_rpt_e(C16,基本资料!$I$8,0))) -> 2023-12-31 | G16: =IF(C16="","",[1]!hks_info_cur2(C16,F16)) -> CNY | H16: =IF(C16="","",[1]!hks_stm_is(C16,"83",F16,1,"",100000000)) -> 43.792759 | I16: =IF(C16="","",[1]!hks_stm_is(C16,"1032",F16,1,"",100000000)) -> 48.570478 | J16: =IF(C16="","",[1]!hks_stm_is(C16,"1041",F16,1,"",100000000)) -> -4.7777189 | K16: =IF(C16="","",[1]!hks_stm_is(C16,"61",F16,1,"",100000000)) -> 1.6505493 | L16: =IF(C16="","",[1]!hks_stm_is(C16,"1075",F16,1,"",100000000)) -> 1.6505493 | M16: =IF(C16="","",[1]!hks_stm_is(C16,"1077",F16,1,"",100000000)) -> -0.27270093 | N16: =IF(C16="","",[1]!hks_stm_is(C16,"1030",F16,1,"",100000000)) -> 0 | O16: =IF(C16="","",[1]!hks_fa_ebit(C16,F16,1,"",100000000)) -> 0.74234867 | P16: =IF(C16="","",[1]!hks_fa_ebitda(C16,F16,1,"",100000000)) -> 3.7573117 | Q16: =IF(C16="","",[1]!hks_stm_bs(C16,"9",F16,1,"",100000000)) -> 8.2883179 | R16: =IF(C16="","",[1]!hks_stm_bs(C16,"25",F16,1,"",100000000)) -> 55.528055 | S16: =IF(C16="","",[1]!hks_stm_bs(C16,"1088",F16,1,"",100000000)) -> 0 | T16: =IF(C16="","",[1]!hks_stm_bs(C16,"46",F16,1,"",100000000)) -> 41.742254 | U16: =IF(C16="","",[1]!hks_stm_bs(C16,"29",F16,1,"",100000000)) -> 0 | V16: =IF(C16="","",[1]!hks_stm_bs(C16,"74",F16,1,"",100000000)) -> 97.27031 | W16: =IF(C16="","",[1]!hks_stm_bs(C16,"93",F16,1,"",100000000)) -> 13.252784 | X16: =IF(C16="","",[1]!hks_stm_bs(C16,"1017",F16,1,"",100000000)) -> 3.5647203 | Y16: =IF(C16="","",[1]!hks_stm_bs(C16,"128",F16,1,"",100000000)) -> 16.817504 | Z16: =IF(C16="","",[1]!hks_stm_bs(C16,"145",F16,1,"",100000000)) -> 80.452806 | AA16: =IF(C16="","",[1]!hks_stm_bs(C16,"140",F16,1,"",100000000)) -> 80.452798 | AB16: =IF(C16="","",[1]!hks_stm_cs(C16,"39",F16,1,"",100000000)) -> 17.857707 | AC16: =IF(C16="","",[1]!hks_stm_cs(C16,"1020",F16,1,"",100000000)) -> 4.3382635 | AD16: =IF(C16="","",[1]!hks_stm_cs(C16,"59",F16,1,"",100000000)) -> -17.282152 | AE16: =IF(C16="","",[1]!hks_stm_cs(C16,"77",F16,1,"",100000000)) -> -3.0969067 | AF16: =IF(C16="","",[1]!hks_stm_cs(C16,"82",F16,1,"",100000000)) -> -2.3844305 | AG16: =IF(C16="","",[1]!hks_stm_cs(C16,"84",F16,1,"",100000000)) -> 8.2883179
C17: =IF(表1[[#This Row],[列1]]="","",表1[[#This Row],[列1]]) -> 688111.SH | D17: =IF(C17="","",[1]!hks_info_name(C17)) -> 金山办公 | E17: =IF(C17="","",[1]!lastradeday_s(C17,TODAY())) -> 2024-12-09 | F17: =IF(C17="","",IF(OR([1]!s_stm_rpt_e(C17,基本资料!$I$8,0)="#N/A",[1]!s_stm_rpt_e(C17,基本资料!$I$8,0)="",[1]!s_stm_rpt_e(C17,基本资料!$I$8,0)=0),[1]!s_stm_rpt_e(C17,基本资料!$I$9,0),[1]!s_stm_rpt_e(C17,基本资料!$I$8,0))) -> 2023-12-31 | G17: =IF(C17="","",[1]!hks_info_cur2(C17,F17)) -> CNY | H17: =IF(C17="","",[1]!hks_stm_is(C17,"83",F17,1,"",100000000)) -> 45.188069 | I17: =IF(C17="","",[1]!hks_stm_is(C17,"1032",F17,1,"",100000000)) -> 35.842021 | J17: =IF(C17="","",[1]!hks_stm_is(C17,"1041",F17,1,"",100000000)) -> 9.3460475 | K17: =IF(C17="","",[1]!hks_stm_is(C17,"61",F17,1,"",100000000)) -> 13.17737 | L17: =IF(C17="","",[1]!hks_stm_is(C17,"1075",F17,1,"",100000000)) -> 13.17737 | M17: =IF(C17="","",[1]!hks_stm_is(C17,"1077",F17,1,"",100000000)) -> -0.13367834 | N17: =IF(C17="","",[1]!hks_stm_is(C17,"1030",F17,1,"",100000000)) -> 0 | O17: =IF(C17="","",[1]!hks_fa_ebit(C17,F17,1,"",100000000)) -> 13.898395 | P17: =IF(C17="","",[1]!hks_fa_ebitda(C17,F17,1,"",100000000)) -> 14.701951 | Q17: =IF(C17="","",[1]!hks_stm_bs(C17,"9",F17,1,"",100000000)) -> 34.739229 | R17: =IF(C17="","",[1]!hks_stm_bs(C17,"25",F17,1,"",100000000)) -> 101.46961 | S17: =IF(C17="","",[1]!hks_stm_bs(C17,"1088",F17,1,"",100000000)) -> 0 | T17: =IF(C17="","",[1]!hks_stm_bs(C17,"46",F17,1,"",100000000)) -> 38.270605 | U17: =IF(C17="","",[1]!hks_stm_bs(C17,"29",F17,1,"",100000000)) -> 10.940629 | V17: =IF(C17="","",[1]!hks_stm_bs(C17,"74",F17,1,"",100000000)) -> 139.74021 | W17: =IF(C17="","",[1]!hks_stm_bs(C17,"93",F17,1,"",100000000)) -> 31.537878 | X17: =IF(C17="","",[1]!hks_stm_bs(C17,"1017",F17,1,"",100000000)) -> 8.0062728 | Y17: =IF(C17="","",[1]!hks_stm_bs(C17,"128",F17,1,"",100000000)) -> 39.544151 | Z17: =IF(C17="","",[1]!hks_stm_bs(C17,"145",F17,1,"",100000000)) -> 100.19606 | AA17: =IF(C17="","",[1]!hks_stm_bs(C17,"140",F17,1,"",100000000)) -> 99.487977 | AB17: =IF(C17="","",[1]!hks_stm_cs(C17,"39",F17,1,"",100000000)) -> 20.575471 | AC17: =IF(C17="","",[1]!hks_stm_cs(C17,"1020",F17,1,"",100000000)) -> 1.6584838 | AD17: =IF(C17="","",[1]!hks_stm_cs(C17,"59",F17,1,"",100000000)) -> -52.099184 | AE17: =IF(C17="","",[1]!hks_stm_cs(C17,"77",F17,1,"",100000000)) -> -3.845362 | AF17: =IF(C17="","",[1]!hks_stm_cs(C17,"82",F17,1,"",100000000)) -> -35.38935 | AG17: =IF(C17="","",[1]!hks_stm_cs(C17,"84",F17,1,"",100000000)) -> 34.739229
C18: =IF(表1[[#This Row],[列1]]="","",表1[[#This Row],[列1]]) -> 0700.HK | D18: =IF(C18="","",[1]!hks_info_name(C18)) -> 腾讯控股 | E18: =IF(C18="","",[1]!lastradeday_s(C18,TODAY())) -> 2024-12-06 | F18: =IF(C18="","",IF(OR([1]!s_stm_rpt_e(C18,基本资料!$I$8,0)="#N/A",[1]!s_stm_rpt_e(C18,基本资料!$I$8,0)="",[1]!s_stm_rpt_e(C18,基本资料!$I$8,0)=0),[1]!s_stm_rpt_e(C18,基本资料!$I$9,0),[1]!s_stm_rpt_e(C18,基本资料!$I$8,0))) -> 2023-12-31 | G18: =IF(C18="","",[1]!hks_info_cur2(C18,F18)) -> CNY | H18: =IF(C18="","",[1]!hks_stm_is(C18,"83",F18,1,"",100000000)) -> 6090.15 | I18: =IF(C18="","",[1]!hks_stm_is(C18,"1032",F18,1,"",100000000)) -> 4562.31 | J18: =IF(C18="","",[1]!hks_stm_is(C18,"1041",F18,1,"",100000000)) -> 1527.84 | K18: =IF(C18="","",[1]!hks_stm_is(C18,"61",F18,1,"",100000000)) -> 1152.16 | L18: =IF(C18="","",[1]!hks_stm_is(C18,"1075",F18,1,"",100000000)) -> 1152.16 | M18: =IF(C18="","",[1]!hks_stm_is(C18,"1077",F18,1,"",100000000)) -> 65.02 | N18: =IF(C18="","",[1]!hks_stm_is(C18,"1030",F18,1,"",100000000)) -> 640.78 | O18: =IF(C18="","",[1]!hks_fa_ebit(C18,F18,1,"",100000000)) -> 1594.01 | P18: =IF(C18="","",[1]!hks_fa_ebitda(C18,F18,1,"",100000000)) -> 2184.09 | Q18: =IF(C18="","",[1]!hks_stm_bs(C18,"9",F18,1,"",100000000)) -> 1723.2 | R18: =IF(C18="","",[1]!hks_stm_bs(C18,"25",F18,1,"",100000000)) -> 5184.46 | S18: =IF(C18="","",[1]!hks_stm_bs(C18,"1088",F18,1,"",100000000)) -> 0 | T18: =IF(C18="","",[1]!hks_stm_bs(C18,"46",F18,1,"",100000000)) -> 10588 | U18: =IF(C18="","",[1]!hks_stm_bs(C18,"29",F18,1,"",100000000)) -> 2616.65 | V18: =IF(C18="","",[1]!hks_stm_bs(C18,"74",F18,1,"",100000000)) -> 15772.46 | W18: =IF(C18="","",[1]!hks_stm_bs(C18,"93",F18,1,"",100000000)) -> 3521.57 | X18: =IF(C18="","",[1]!hks_stm_bs(C18,"1017",F18,1,"",100000000)) -> 3514.08 | Y18: =IF(C18="","",[1]!hks_stm_bs(C18,"128",F18,1,"",100000000)) -> 7035.65 | Z18: =IF(C18="","",[1]!hks_stm_bs(C18,"145",F18,1,"",100000000)) -> 8736.81 | AA18: =IF(C18="","",[1]!hks_stm_bs(C18,"140",F18,1,"",100000000)) -> 8085.91 | AB18: =IF(C18="","",[1]!hks_stm_cs(C18,"39",F18,1,"",100000000)) -> 2219.62 | AC18: =IF(C18="","",[1]!hks_stm_cs(C18,"1020",F18,1,"",100000000)) -> 474.07 | AD18: =IF(C18="","",[1]!hks_stm_cs(C18,"59",F18,1,"",100000000)) -> -1251.61 | AE18: =IF(C18="","",[1]!hks_stm_cs(C18,"77",F18,1,"",100000000)) -> -825.73 | AF18: =IF(C18="","",[1]!hks_stm_cs(C18,"82",F18,1,"",100000000)) -> 155.81 | AG18: =IF(C18="","",[1]!hks_stm_cs(C18,"84",F18,1,"",100000000)) -> 1723.2
C19: =IF(表1[[#This Row],[列1]]="","",表1[[#This Row],[列1]]) -> 9896.HK | D19: =IF(C19="","",[1]!hks_info_name(C19)) -> 名创优品 | E19: =IF(C19="","",[1]!lastradeday_s(C19,TODAY())) -> 2024-12-06 | F19: =IF(C19="","",IF(OR([1]!s_stm_rpt_e(C19,基本资料!$I$8,0)="#N/A",[1]!s_stm_rpt_e(C19,基本资料!$I$8,0)="",[1]!s_stm_rpt_e(C19,基本资料!$I$8,0)=0),[1]!s_stm_rpt_e(C19,基本资料!$I$9,0),[1]!s_stm_rpt_e(C19,基本资料!$I$8,0))) -> 2023-06-30 | G19: =IF(C19="","",[1]!hks_info_cur2(C19,F19)) -> CNY | H19: =IF(C19="","",[1]!hks_stm_is(C19,"83",F19,1,"",100000000)) -> 52.66878 | I19: =IF(C19="","",[1]!hks_stm_is(C19,"1032",F19,1,"",100000000)) -> 43.93253 | J19: =IF(C19="","",[1]!hks_stm_is(C19,"1041",F19,1,"",100000000)) -> 8.73625 | K19: =IF(C19="","",[1]!hks_stm_is(C19,"61",F19,1,"",100000000)) -> 7.6409 | L19: =IF(C19="","",[1]!hks_stm_is(C19,"1075",F19,1,"",100000000)) -> 7.6409 | M19: =IF(C19="","",[1]!hks_stm_is(C19,"1077",F19,1,"",100000000)) -> -0.03716 | N19: =IF(C19="","",[1]!hks_stm_is(C19,"1030",F19,1,"",100000000)) -> 0 | O19: =IF(C19="","",[1]!hks_fa_ebit(C19,F19,1,"",100000000)) -> 9.5707 | P19: =IF(C19="","",[1]!hks_fa_ebitda(C19,F19,1,"",100000000)) -> 0 | Q19: =IF(C19="","",[1]!hks_stm_bs(C19,"9",F19,1,"",100000000)) -> 51.86601 | R19: =IF(C19="","",[1]!hks_stm_bs(C19,"25",F19,1,"",100000000)) -> 87.43692 | S19: =IF(C19="","",[1]!hks_stm_bs(C19,"1088",F19,1,"",100000000)) -> 0 | T19: =IF(C19="","",[1]!hks_stm_bs(C19,"46",F19,1,"",100000000)) -> 32.53688 | U19: =IF(C19="","",[1]!hks_stm_bs(C19,"29",F19,1,"",100000000)) -> 0 | V19: =IF(C19="","",[1]!hks_stm_bs(C19,"74",F19,1,"",100000000)) -> 119.9738 | W19: =IF(C19="","",[1]!hks_stm_bs(C19,"93",F19,1,"",100000000)) -> 37.11558 | X19: =IF(C19="","",[1]!hks_stm_bs(C19,"1017",F19,1,"",100000000)) -> 4.76795 | Y19: =IF(C19="","",[1]!hks_stm_bs(C19,"128",F19,1,"",100000000)) -> 41.88353 | Z19: =IF(C19="","",[1]!hks_stm_bs(C19,"145",F19,1,"",100000000)) -> 78.09027 | AA19: =IF(C19="","",[1]!hks_stm_bs(C19,"140",F19,1,"",100000000)) -> 78.07425 | AB19: =IF(C19="","",[1]!hks_stm_cs(C19,"39",F19,1,"",100000000)) -> 4.33256 | AC19: =IF(C19="","",[1]!hks_stm_cs(C19,"1020",F19,1,"",100000000)) -> 0.78032 | AD19: =IF(C19="","",[1]!hks_stm_cs(C19,"59",F19,1,"",100000000)) -> -4.85719 | AE19: =IF(C19="","",[1]!hks_stm_cs(C19,"77",F19,1,"",100000000)) -> -1.49789 | AF19: =IF(C19="","",[1]!hks_stm_cs(C19,"82",F19,1,"",100000000)) -> -1.61891 | AG19: =IF(C19="","",[1]!hks_stm_cs(C19,"84",F19,1,"",100000000)) -> 51.86601
... C100: =IF(表1[[#This Row],[列1]]="","",表1[[#This Row],[列1]]) | D100: =IF(C100="","",[1]!hks_info_name(C100)) | E100: =IF(C100="","",[1]!lastradeday_s(C100,TODAY())) | F100: =IF(C100="","",IF(OR([1]!s_stm_rpt_e(C100,基本资料!$I$8,0)="#N/A",[1]!s_stm_rpt_e(C100,基本资料!$I$8,0)="",[1]!s_stm_rpt_e(C100,基本资料!$I$8,0)=0),[1]!s_stm_rpt_e(C100,基本资料!$I$9,0),[1]!s_stm_rpt_e(C100,基本资料!$I$8,0))) | G100: =IF(C100="","",[1]!hks_info_cur2(C100,F100)) | H100: =IF(C100="","",[1]!hks_stm_is(C100,"83",F100,1,"",100000000)) | I100: =IF(C100="","",[1]!hks_stm_is(C100,"1032",F100,1,"",100000000)) | J100: =IF(C100="","",[1]!hks_stm_is(C100,"1041",F100,1,"",100000000)) | K100: =IF(C100="","",[1]!hks_stm_is(C100,"61",F100,1,"",100000000)) | L100: =IF(C100="","",[1]!hks_stm_is(C100,"1075",F100,1,"",100000000)) | M100: =IF(C100="","",[1]!hks_stm_is(C100,"1077",F100,1,"",100000000)) | N100: =IF(C100="","",[1]!hks_stm_is(C100,"1030",F100,1,"",100000000)) | O100: =IF(C100="","",[1]!hks_fa_ebit(C100,F100,1,"",100000000)) | P100: =IF(C100="","",[1]!hks_fa_ebitda(C100,F100,1,"",100000000)) | Q100: =IF(C100="","",[1]!hks_stm_bs(C100,"9",F100,1,"",100000000)) | R100: =IF(C100="","",[1]!hks_stm_bs(C100,"25",F100,1,"",100000000)) | S100: =IF(C100="","",[1]!hks_stm_bs(C100,"1088",F100,1,"",100000000)) | T100: =IF(C100="","",[1]!hks_stm_bs(C100,"46",F100,1,"",100000000)) | U100: =IF(C100="","",[1]!hks_stm_bs(C100,"29",F100,1,"",100000000)) | V100: =IF(C100="","",[1]!hks_stm_bs(C100,"74",F100,1,"",100000000)) | W100: =IF(C100="","",[1]!hks_stm_bs(C100,"93",F100,1,"",100000000)) | X100: =IF(C100="","",[1]!hks_stm_bs(C100,"1017",F100,1,"",100000000)) | Y100: =IF(C100="","",[1]!hks_stm_bs(C100,"128",F100,1,"",100000000)) | Z100: =IF(C100="","",[1]!hks_stm_bs(C100,"145",F100,1,"",100000000)) | AA100: =IF(C100="","",[1]!hks_stm_bs(C100,"140",F100,1,"",100000000)) | AB100: =IF(C100="","",[1]!hks_stm_cs(C100,"39",F100,1,"",100000000)) | AC100: =IF(C100="","",[1]!hks_stm_cs(C100,"1020",F100,1,"",100000000)) | AD100: =IF(C100="","",[1]!hks_stm_cs(C100,"59",F100,1,"",100000000)) | AE100: =IF(C100="","",[1]!hks_stm_cs(C100,"77",F100,1,"",100000000)) | AF100: =IF(C100="","",[1]!hks_stm_cs(C100,"82",F100,1,"",100000000)) | AG100: =IF(C100="","",[1]!hks_stm_cs(C100,"84",F100,1,"",100000000))

Sheet 估值分析
D1: 可比公司-估值分析
C4: 估值分析
C6: Wind代码 | D6: 证券简称 | E6: 最新收盘日 | F6: 企业总市值(亿元) | J6: 证券总市值(亿元) | N6: 市盈率PE | S6: 市净率PB | X6: 市销率PS | AA6: 市现率PCF | AD6: EV/EBITDA | AE6: EV/EBIT(TTM)
F7: =基本资料!$G$9&"年总市值" -> 2022年总市值 | G7: =基本资料!$G$8&"年总市值" -> 2023年总市值 | H7: 最新收盘日总市值 | I7: 趋势图 | J7: =基本资料!$G$9&"年总市值" -> 2022年总市值 | K7: =基本资料!$G$8&"年总市值" -> 2023年总市值 | L7: 最新收盘日总市值 | M7: 趋势图 | N7: =基本资料!$G$9&"年PE" -> 2022年PE | O7: =基本资料!$G$8&"年PE" -> 2023年PE | P7: 最新收盘日PE(TTM) | Q7: PE(FY1) | R7: PE(FY2) | S7: =基本资料!$G$9&"年PB" -> 2022年PB | T7: =基本资料!$G$8&"年PB" -> 2023年PB | U7: 最新收盘日PB(MRQ) | V7: PB(FY1) | W7: PB(FY2) | X7: =基本资料!$G$9&"年PS" -> 2022年PS | Y7: =基本资料!$G$8&"年PS" -> 2023年PS | Z7: 最新收盘日PS(TTM) | AA7: =基本资料!$G$9&"年PCF" -> 2022年PCF | AB7: =基本资料!$G$8&"年PCF" -> 2023年PCF | AC7: 最新收盘日PCF(TTM)
C8: =IF(表1[[#This Row],[列1]]="","",表1[[#This Row],[列1]]) -> 000001.SZ | D8: =IF(C8="","",[1]!hks_info_name(C8)) -> 平安银行 | E8: =IF(C8="","",[1]!lastradeday_s(C8,TODAY())) -> 2024-12-09 | F8: =IF(C8="","",[1]!hks_val_ev(C8,基本资料!$I$9,"",100000000)) -> 2553.8188 | G8: =IF(C8="","",[1]!hks_val_ev(C8,基本资料!$I$8,"",100000000)) -> 1822.2157 | H8: =IF(C8="","",[1]!hks_val_ev(C8,E8,"",100000000)) -> 2264.6707 | J8: =IF(C8="","",[1]!hks_val_mv_ard(C8,基本资料!$I$9,"",100000000)) -> 2553.8188 | K8: =IF(C8="","",[1]!hks_val_mv_ard(C8,基本资料!$I$8,"",100000000)) -> 1822.2157 | L8: =IF(C8="","",[1]!hks_val_mv_ard(C8,E8,"",100000000)) -> 2264.6707 | N8: =IF(C8="","",[1]!hks_val_pe(C8,基本资料!$I$9,基本资料!$G$9)) -> 5.6108156 | O8: =IF(C8="","",[1]!hks_val_pe(C8,基本资料!$I$8,基本资料!$G$8)) -> 3.9225395 | P8: =IF(C8="","",[1]!hks_val_pe_ttm(C8,E8)) -> 4.8651328 | Q8: =IF(C8="","",[1]!s_val_estpe(C8,E8,YEAR([1]!s_stm_rpt_e(C8,基本资料!$I$8,0))+1)) -> 4.9236353 | R8: =IF(C8="","",[1]!s_val_estpe(C8,E8,YEAR([1]!s_stm_rpt_e(C8,基本资料!$I$8,0))+2)) -> 4.8221148 | S8: =IF(C8="","",[1]!hks_val_pb(C8,基本资料!$I$9,基本资料!$G$9)) -> 0.58751699 | T8: =IF(C8="","",[1]!hks_val_pb(C8,基本资料!$I$8,基本资料!$G$8)) -> 0.38579456 | U8: =IF(C8="","",[1]!pb_mrq(C8,E8)) -> 0.53853413 | V8: =IF(C8="","",[1]!s_val_estpb(C8,E8,YEAR([1]!s_stm_rpt_e(C8,基本资料!$I$8,0))+1)) -> 0.52028533 | W8: =IF(C8="","",[1]!s_val_estpb(C8,E8,YEAR([1]!s_stm_rpt_e(C8,基本资料!$I$8,0))+2)) -> 0.4806821 | X8: =IF(C8="","",[1]!hks_val_ps(C8,基本资料!$I$9,基本资料!$G$9)) -> 1.4333768 | Y8: =IF(C8="","",[1]!hks_val_ps(C8,基本资料!$I$8,基本资料!$G$8)) -> 1.1180541 | Z8: =IF(C8="","",[1]!hks_val_ps_ttm(C8,E8)) -> 1.5235226 | AA8: =IF(C8="","",[1]!hks_val_pcf(C8,基本资料!$I$9,基本资料!$G$9)) -> -88.184352 | AB8: =IF(C8="","",[1]!hks_val_pcf(C8,基本资料!$I$8,基本资料!$G$8)) -> 2.4010327 | AC8: =IF(C8="","",[1]!hks_val_pcf_ttm(C8,E8)) -> -10.292554 | AD8: =IF(C8="","",[1]!s_val_evtoebitda2(C8,E8)) -> 0 | AE8: =IF(C8="","",[1]!hks_val_ev2(C8,E8,"",1)/[1]!hks_fa_ebit2_ttm(C8,[1]!s_fa_latelyrd_bt(C8,[1]!lastradeday_s(C8,基本资料!$D$7)),"",1)) -> 16357.353
C9: =IF(表1[[#This Row],[列1]]="","",表1[[#This Row],[列1]]) -> 000002.SZ | D9: =IF(C9="","",[1]!hks_info_name(C9)) -> 万科A | E9: =IF(C9="","",[1]!lastradeday_s(C9,TODAY())) -> 2024-12-09 | F9: =IF(C9="","",[1]!hks_val_ev(C9,基本资料!$I$9,"",100000000)) -> 2038.8826 | G9: =IF(C9="","",[1]!hks_val_ev(C9,基本资料!$I$8,"",100000000)) -> 1161.5211 | H9: =IF(C9="","",[1]!hks_val_ev(C9,E9,"",100000000)) -> 950.57466 | J9: =IF(C9="","",[1]!hks_val_mv_ard(C9,基本资料!$I$9,"",100000000)) -> 2116.7891 | K9: =IF(C9="","",[1]!hks_val_mv_ard(C9,基本资料!$I$8,"",100000000)) -> 1247.9522 | L9: =IF(C9="","",[1]!hks_val_mv_ard(C9,E9,"",100000000)) -> 1004.5657 | N9: =IF(C9="","",[1]!hks_val_pe(C9,基本资料!$I$9,基本资料!$G$9)) -> 9.358961 | O9: =IF(C9="","",[1]!hks_val_pe(C9,基本资料!$I$8,基本资料!$G$8)) -> 10.2605 | P9: =IF(C9="","",[1]!hks_val_pe_ttm(C9,E9)) -> -5.1776156 | Q9: =IF(C9="","",[1]!s_val_estpe(C9,E9,YEAR([1]!s_stm_rpt_e(C9,基本资料!$I$8,0))+1)) -> -9.2864231 | R9: =IF(C9="","",[1]!s_val_estpe(C9,E9,YEAR([1]!s_stm_rpt_e(C9,基本资料!$I$8,0))+2)) -> -222.75133 | S9: =IF(C9="","",[1]!hks_val_pb(C9,基本资料!$I$9,基本资料!$G$9)) -> 0.87221452 | T9: =IF(C9="","",[1]!hks_val_pb(C9,基本资料!$I$8,基本资料!$G$8)) -> 0.49761913 | U9: =IF(C9="","",[1]!pb_mrq(C9,E9)) -> 0.42908166 | V9: =IF(C9="","",[1]!s_val_estpb(C9,E9,YEAR([1]!s_stm_rpt_e(C9,基本资料!$I$8,0))+1)) -> 0.4192705 | W9: =IF(C9="","",[1]!s_val_estpb(C9,E9,YEAR([1]!s_stm_rpt_e(C9,基本资料!$I$8,0))+2)) -> 0.42445294 | X9: =IF(C9="","",[1]!hks_val_ps(C9,基本资料!$I$9,基本资料!$G$9)) -> 0.41958325 | Y9: =IF(C9="","",[1]!hks_val_ps(C9,基本资料!$I$8,基本资料!$G$8)) -> 0.26759753 | Z9: =IF(C9="","",[1]!hks_val_ps_ttm(C9,E9)) -> 0.2541111 | AA9: =IF(C9="","",[1]!hks_val_pcf(C9,基本资料!$I$9,基本资料!$G$9)) -> -33.686509 | AB9: =IF(C9="","",[1]!hks_val_pcf(C9,基本资料!$I$8,基本资料!$G$8)) -> -3.3294624 | AC9: =IF(C9="","",[1]!hks_val_pcf_ttm(C9,E9)) -> -4.2002559 | AD9: =IF(C9="","",[1]!s_val_evtoebitda2(C9,E9)) -> 9.3365582 | AE9: =IF(C9="","",[1]!hks_val_ev2(C9,E9,"",1)/[1]!hks_fa_ebit2_ttm(C9,[1]!s_fa_latelyrd_bt(C9,[1]!lastradeday_s(C9,基本资料!$D$7)),"",1)) -> 11.591206
C10: =IF(表1[[#This Row],[列1]]="","",表1[[#This Row],[列1]]) -> 002123.SZ | D10: =IF(C10="","",[1]!hks_info_name(C10)) -> 梦网科技 | E10: =IF(C10="","",[1]!lastradeday_s(C10,TODAY())) -> 2024-12-09 | F10: =IF(C10="","",[1]!hks_val_ev(C10,基本资料!$I$9,"",100000000)) -> 90.086642 | G10: =IF(C10="","",[1]!hks_val_ev(C10,基本资料!$I$8,"",100000000)) -> 89.244567 | H10: =IF(C10="","",[1]!hks_val_ev(C10,E10,"",100000000)) -> 86.523391 | J10: =IF(C10="","",[1]!hks_val_mv_ard(C10,基本资料!$I$9,"",100000000)) -> 90.086642 | K10: =IF(C10="","",[1]!hks_val_mv_ard(C10,基本资料!$I$8,"",100000000)) -> 89.244567 | L10: =IF(C10="","",[1]!hks_val_mv_ard(C10,E10,"",100000000)) -> 86.523391 | N10: =IF(C10="","",[1]!hks_val_pe(C10,基本资料!$I$9,基本资料!$G$9)) -> -12.476153 | O10: =IF(C10="","",[1]!hks_val_pe(C10,基本资料!$I$8,基本资料!$G$8)) -> -4.8968604 | P10: =IF(C10="","",[1]!hks_val_pe_ttm(C10,E10)) -> -4.8143735 | Q10: =IF(C10="","",[1]!s_val_estpe(C10,E10,YEAR([1]!s_stm_rpt_e(C10,基本资料!$I$8,0))+1)) -> 65.674362 | R10: =IF(C10="","",[1]!s_val_estpe(C10,E10,YEAR([1]!s_stm_rpt_e(C10,基本资料!$I$8,0))+2)) -> 40.730973 | S10: =IF(C10="","",[1]!hks_val_pb(C10,基本资料!$I$9,基本资料!$G$9)) -> 2.630235 | T10: =IF(C10="","",[1]!hks_val_pb(C10,基本资料!$I$8,基本资料!$G$8)) -> 5.4908391 | U10: =IF(C10="","",[1]!pb_mrq(C10,E10)) -> 5.2245281 | V10: =IF(C10="","",[1]!s_val_estpb(C10,E10,YEAR([1]!s_stm_rpt_e(C10,基本资料!$I$8,0))+1)) -> 4.9293204 | W10: =IF(C10="","",[1]!s_val_estpb(C10,E10,YEAR([1]!s_stm_rpt_e(C10,基本资料!$I$8,0))+2)) -> 4.4129654 | X10: =IF(C10="","",[1]!hks_val_ps(C10,基本资料!$I$9,基本资料!$G$9)) -> 2.1686709 | Y10: =IF(C10="","",[1]!hks_val_ps(C10,基本资料!$I$8,基本资料!$G$8)) -> 1.7074205 | Z10: =IF(C10="","",[1]!hks_val_ps_ttm(C10,E10)) -> 1.6609933 | AA10: =IF(C10="","",[1]!hks_val_pcf(C10,基本资料!$I$9,基本资料!$G$9)) -> 42.932919 | AB10: =IF(C10="","",[1]!hks_val_pcf(C10,基本资料!$I$8,基本资料!$G$8)) -> -63.160099 | AC10: =IF(C10="","",[1]!hks_val_pcf_ttm(C10,E10)) -> 225.91658 | AD10: =IF(C10="","",[1]!s_val_evtoebitda2(C10,E10)) -> -119.6056 | AE10: =IF(C10="","",[1]!hks_val_ev2(C10,E10,"",1)/[1]!hks_fa_ebit2_ttm(C10,[1]!s_fa_latelyrd_bt(C10,[1]!lastradeday_s(C10,基本资料!$D$7)),"",1)) -> -71.583245
C11: =IF(表1[[#This Row],[列1]]="","",表1[[#This Row],[列1]]) -> 002230.SZ | D11: =IF(C11="","",[1]!hks_info_name(C11)) -> 科大讯飞 | E11: =IF(C11="","",[1]!lastradeday_s(C11,TODAY())) -> 2024-12-09 | F11: =IF(C11="","",[1]!hks_val_ev(C11,基本资料!$I$9,"",100000000)) -> 762.88804 | G11: =IF(C11="","",[1]!hks_val_ev(C11,基本资料!$I$8,"",100000000)) -> 1074.0166 | H11: =IF(C11="","",[1]!hks_val_ev(C11,E11,"",100000000)) -> 1217.8216 | J11: =IF(C11="","",[1]!hks_val_mv_ard(C11,基本资料!$I$9,"",100000000)) -> 762.88804 | K11: =IF(C11="","",[1]!hks_val_mv_ard(C11,基本资料!$I$8,"",100000000)) -> 1074.0166 | L11: =IF(C11="","",[1]!hks_val_mv_ard(C11,E11,"",100000000)) -> 1217.8216 | N11: =IF(C11="","",[1]!hks_val_pe(C11,基本资料!$I$9,基本资料!$G$9)) -> 135.93556 | O11: =IF(C11="","",[1]!hks_val_pe(C11,基本资料!$I$8,基本资料!$G$8)) -> 163.39503 | P11: =IF(C11="","",[1]!hks_val_pe_ttm(C11,E11)) -> 568.42059 | Q11: =IF(C11="","",[1]!s_val_estpe(C11,E11,YEAR([1]!s_stm_rpt_e(C11,基本资料!$I$8,0))+1)) -> 202.14889 | R11: =IF(C11="","",[1]!s_val_estpe(C11,E11,YEAR([1]!s_stm_rpt_e(C11,基本资料!$I$8,0))+2)) -> 126.84806 | S11: =IF(C11="","",[1]!hks_val_pb(C11,基本资料!$I$9,基本资料!$G$9)) -> 4.6517428 | T11: =IF(C11="","",[1]!hks_val_pb(C11,基本资料!$I$8,基本资料!$G$8)) -> 6.3057697 | U11: =IF(C11="","",[1]!pb_mrq(C11,E11)) -> 7.3859272 | V11: =IF(C11="","",[1]!s_val_estpb(C11,E11,YEAR([1]!s_stm_rpt_e(C11,基本资料!$I$8,0))+1)) -> 6.9344075 | W11: =IF(C11="","",[1]!s_val_estpb(C11,E11,YEAR([1]!s_stm_rpt_e(C11,基本资料!$I$8,0))+2)) -> 6.6659917 | X11: =IF(C11="","",[1]!hks_val_ps(C11,基本资料!$I$9,基本资料!$G$9)) -> 4.0778443 | Y11: =IF(C11="","",[1]!hks_val_ps(C11,基本资料!$I$8,基本资料!$G$8)) -> 5.5010405 | Z11: =IF(C11="","",[1]!hks_val_ps_ttm(C11,E11)) -> 5.5643555 | AA11: =IF(C11="","",[1]!hks_val_pcf(C11,基本资料!$I$9,基本资料!$G$9)) -> -55.634013 | AB11: =IF(C11="","",[1]!hks_val_pcf(C11,基本资料!$I$8,基本资料!$G$8)) -> -135.96107 | AC11: =IF(C11="","",[1]!hks_val_pcf_ttm(C11,E11)) -> -181.79546 | AD11: =IF(C11="","",[1]!s_val_evtoebitda2(C11,E11)) -> 59.525166 | AE11: =IF(C11="","",[1]!hks_val_ev2(C11,E11,"",1)/[1]!hks_fa_ebit2_ttm(C11,[1]!s_fa_latelyrd_bt(C11,[1]!lastradeday_s(C11,基本资料!$D$7)),"",1)) -> 589.87313
C12: =IF(表1[[#This Row],[列1]]="","",表1[[#This Row],[列1]]) -> 600004.SH | D12: =IF(C12="","",[1]!hks_info_name(C12)) -> 白云机场 | E12: =IF(C12="","",[1]!lastradeday_s(C12,TODAY())) -> 2024-12-09 | F12: =IF(C12="","",[1]!hks_val_ev(C12,基本资料!$I$9,"",100000000)) -> 355.24441 | G12: =IF(C12="","",[1]!hks_val_ev(C12,基本资料!$I$8,"",100000000)) -> 231.46505 | H12: =IF(C12="","",[1]!hks_val_ev(C12,E12,"",100000000)) -> 233.12175 | J12: =IF(C12="","",[1]!hks_val_mv_ard(C12,基本资料!$I$9,"",100000000)) -> 355.24441 | K12: =IF(C12="","",[1]!hks_val_mv_ard(C12,基本资料!$I$8,"",100000000)) -> 231.46505 | L12: =IF(C12="","",[1]!hks_val_mv_ard(C12,E12,"",100000000)) -> 233.12175 | N12: =IF(C12="","",[1]!hks_val_pe(C12,基本资料!$I$9,基本资料!$G$9)) -> -33.163077 | O12: =IF(C12="","",[1]!hks_val_pe(C12,基本资料!$I$8,基本资料!$G$8)) -> 52.378831 | P12: =IF(C12="","",[1]!hks_val_pe_ttm(C12,E12)) -> 27.892939 | Q12: =IF(C12="","",[1]!s_val_estpe(C12,E12,YEAR([1]!s_stm_rpt_e(C12,基本资料!$I$8,0))+1)) -> 24.730103 | R12: =IF(C12="","",[1]!s_val_estpe(C12,E12,YEAR([1]!s_stm_rpt_e(C12,基本资料!$I$8,0))+2)) -> 18.783372 | S12: =IF(C12="","",[1]!hks_val_pb(C12,基本资料!$I$9,基本资料!$G$9)) -> 2.0665155 | T12: =IF(C12="","",[1]!hks_val_pb(C12,基本资料!$I$8,基本资料!$G$8)) -> 1.3156455 | U12: =IF(C12="","",[1]!pb_mrq(C12,E12)) -> 1.289262 | V12: =IF(C12="","",[1]!s_val_estpb(C12,E12,YEAR([1]!s_stm_rpt_e(C12,基本资料!$I$8,0))+1)) -> 1.265075 | W12: =IF(C12="","",[1]!s_val_estpb(C12,E12,YEAR([1]!s_stm_rpt_e(C12,基本资料!$I$8,0))+2)) -> 1.1957366 | X12: =IF(C12="","",[1]!hks_val_ps(C12,基本资料!$I$9,基本资料!$G$9)) -> 9.1777906 | Y12: =IF(C12="","",[1]!hks_val_ps(C12,基本资料!$I$8,基本资料!$G$8)) -> 3.6876347 | Z12: =IF(C12="","",[1]!hks_val_ps_ttm(C12,E12)) -> 3.2723603 | AA12: =IF(C12="","",[1]!hks_val_pcf(C12,基本资料!$I$9,基本资料!$G$9)) -> 53.993769 | AB12: =IF(C12="","",[1]!hks_val_pcf(C12,基本资料!$I$8,基本资料!$G$8)) -> 76.542896 | AC12: =IF(C12="","",[1]!hks_val_pcf_ttm(C12,E12)) -> 11.814526 | AD12: =IF(C12="","",[1]!s_val_evtoebitda2(C12,E12)) -> 8.8978944 | AE12: =IF(C12="","",[1]!hks_val_ev2(C12,E12,"",1)/[1]!hks_fa_ebit2_ttm(C12,[1]!s_fa_latelyrd_bt(C12,[1]!lastradeday_s(C12,基本资料!$D$7)),"",1)) -> 29.292958
C13: =IF(表1[[#This Row],[列1]]="","",表1[[#This Row],[列1]]) -> 600006.SH | D13: =IF(C13="","",[1]!hks_info_name(C13)) -> 东风股份 | E13: =IF(C13="","",[1]!lastradeday_s(C13,TODAY())) -> 2024-12-09 | F13: =IF(C13="","",[1]!hks_val_ev(C13,基本资料!$I$9,"",100000000)) -> 111.6 | G13: =IF(C13="","",[1]!hks_val_ev(C13,基本资料!$I$8,"",100000000)) -> 115.4 | H13: =IF(C13="","",[1]!hks_val_ev(C13,E13,"",100000000)) -> 157.2 | J13: =IF(C13="","",[1]!hks_val_mv_ard(C13,基本资料!$I$9,"",100000000)) -> 111.6 | K13: =IF(C13="","",[1]!hks_val_mv_ard(C13,基本资料!$I$8,"",100000000)) -> 115.4 | L13: =IF(C13="","",[1]!hks_val_mv_ard(C13,E13,"",100000000)) -> 157.2 | N13: =IF(C13="","",[1]!hks_val_pe(C13,基本资料!$I$9,基本资料!$G$9)) -> 39.146357 | O13: =IF(C13="","",[1]!hks_val_pe(C13,基本资料!$I$8,基本资料!$G$8)) -> 57.688124 | P13: =IF(C13="","",[1]!hks_val_pe_ttm(C13,E13)) -> 326.86746 | Q13: =IF(C13="","",[1]!s_val_estpe(C13,E13,YEAR([1]!s_stm_rpt_e(C13,基本资料!$I$8,0))+1)) -> 0 | R13: =IF(C13="","",[1]!s_val_estpe(C13,E13,YEAR([1]!s_stm_rpt_e(C13,基本资料!$I$8,0))+2)) -> 0 | S13: =IF(C13="","",[1]!hks_val_pb(C13,基本资料!$I$9,基本资料!$G$9)) -> 1.3616138 | T13: =IF(C13="","",[1]!hks_val_pb(C13,基本资料!$I$8,基本资料!$G$8)) -> 1.3887489 | U13: =IF(C13="","",[1]!pb_mrq(C13,E13)) -> 1.9324399 | V13: =IF(C13="","",[1]!s_val_estpb(C13,E13,YEAR([1]!s_stm_rpt_e(C13,基本资料!$I$8,0))+1)) -> 0 | W13: =IF(C13="","",[1]!s_val_estpb(C13,E13,YEAR([1]!s_stm_rpt_e(C13,基本资料!$I$8,0))+2)) -> 0 | X13: =IF(C13="","",[1]!hks_val_ps(C13,基本资料!$I$9,基本资料!$G$9)) -> 0.92322666 | Y13: =IF(C13="","",[1]!hks_val_ps(C13,基本资料!$I$8,基本资料!$G$8)) -> 0.96433247 | Z13: =IF(C13="","",[1]!hks_val_ps_ttm(C13,E13)) -> 1.4446775 | AA13: =IF(C13="","",[1]!hks_val_pcf(C13,基本资料!$I$9,基本资料!$G$9)) -> 23.438301 | AB13: =IF(C13="","",[1]!hks_val_pcf(C13,基本资料!$I$8,基本资料!$G$8)) -> -18.62073 | AC13: =IF(C13="","",[1]!hks_val_pcf_ttm(C13,E13)) -> -10.804343 | AD13: =IF(C13="","",[1]!s_val_evtoebitda2(C13,E13)) -> -68.989772 | AE13: =IF(C13="","",[1]!hks_val_ev2(C13,E13,"",1)/[1]!hks_fa_ebit2_ttm(C13,[1]!s_fa_latelyrd_bt(C13,[1]!lastradeday_s(C13,基本资料!$D$7)),"",1)) -> -26.096594
C14: =IF(表1[[#This Row],[列1]]="","",表1[[#This Row],[列1]]) -> 600007.SH | D14: =IF(C14="","",[1]!hks_info_name(C14)) -> 中国国贸 | E14: =IF(C14="","",[1]!lastradeday_s(C14,TODAY())) -> 2024-12-09 | F14: =IF(C14="","",[1]!hks_val_ev(C14,基本资料!$I$9,"",100000000)) -> 159.45283 | G14: =IF(C14="","",[1]!hks_val_ev(C14,基本资料!$I$8,"",100000000)) -> 195.21136 | H14: =IF(C14="","",[1]!hks_val_ev(C14,E14,"",100000000)) -> 229.66042 | J14: =IF(C14="","",[1]!hks_val_mv_ard(C14,基本资料!$I$9,"",100000000)) -> 159.45283 | K14: =IF(C14="","",[1]!hks_val_mv_ard(C14,基本资料!$I$8,"",100000000)) -> 195.21136 | L14: =IF(C14="","",[1]!hks_val_mv_ard(C14,E14,"",100000000)) -> 229.66042 | N14: =IF(C14="","",[1]!hks_val_pe(C14,基本资料!$I$9,基本资料!$G$9)) -> 14.289542 | O14: =IF(C14="","",[1]!hks_val_pe(C14,基本资料!$I$8,基本资料!$G$8)) -> 15.502791 | P14: =IF(C14="","",[1]!hks_val_pe_ttm(C14,E14)) -> 18.005089 | Q14: =IF(C14="","",[1]!s_val_estpe(C14,E14,YEAR([1]!s_stm_rpt_e(C14,基本资料!$I$8,0))+1)) -> 17.674419 | R14: =IF(C14="","",[1]!s_val_estpe(C14,E14,YEAR([1]!s_stm_rpt_e(C14,基本资料!$I$8,0))+2)) -> 17.082491 | S14: =IF(C14="","",[1]!hks_val_pb(C14,基本资料!$I$9,基本资料!$G$9)) -> 1.7435203 | T14: =IF(C14="","",[1]!hks_val_pb(C14,基本资料!$I$8,基本资料!$G$8)) -> 2.0124553 | U14: =IF(C14="","",[1]!pb_mrq(C14,E14)) -> 2.4407808 | V14: =IF(C14="","",[1]!s_val_estpb(C14,E14,YEAR([1]!s_stm_rpt_e(C14,基本资料!$I$8,0))+1)) -> 2.2428804 | W14: =IF(C14="","",[1]!s_val_estpb(C14,E14,YEAR([1]!s_stm_rpt_e(C14,基本资料!$I$8,0))+2)) -> 2.1304031 | X14: =IF(C14="","",[1]!hks_val_ps(C14,基本资料!$I$9,基本资料!$G$9)) -> 5.178203 | Y14: =IF(C14="","",[1]!hks_val_ps(C14,基本资料!$I$8,基本资料!$G$8)) -> 5.4689252 | Z14: =IF(C14="","",[1]!hks_val_ps_ttm(C14,E14)) -> 5.8079528 | AA14: =IF(C14="","",[1]!hks_val_pcf(C14,基本资料!$I$9,基本资料!$G$9)) -> 32.615462 | AB14: =IF(C14="","",[1]!hks_val_pcf(C14,基本资料!$I$8,基本资料!$G$8)) -> 34.635474 | AC14: =IF(C14="","",[1]!hks_val_pcf_ttm(C14,E14)) -> -178.37363 | AD14: =IF(C14="","",[1]!s_val_evtoebitda2(C14,E14)) -> 9.337436 | AE14: =IF(C14="","",[1]!hks_val_ev2(C14,E14,"",1)/[1]!hks_fa_ebit2_ttm(C14,[1]!s_fa_latelyrd_bt(C14,[1]!lastradeday_s(C14,基本资料!$D$7)),"",1)) -> 12.01268
C15: =IF(表1[[#This Row],[列1]]="","",表1[[#This Row],[列1]]) -> 600941.SH | D15: =IF(C15="","",[1]!hks_info_name(C15)) -> 中国移动 | E15: =IF(C15="","",[1]!lastradeday_s(C15,TODAY())) -> 2024-12-09 | F15: =IF(C15="","",[1]!hks_val_ev(C15,基本资料!$I$9,"",100000000)) -> 10068.918 | G15: =IF(C15="","",[1]!hks_val_ev(C15,基本资料!$I$8,"",100000000)) -> 12928.33 | H15: =IF(C15="","",[1]!hks_val_ev(C15,E15,"",100000000)) -> 14793.594 | J15: =IF(C15="","",[1]!hks_val_mv_ard(C15,基本资料!$I$9,"",100000000)) -> 14456.225 | K15: =IF(C15="","",[1]!hks_val_mv_ard(C15,基本资料!$I$8,"",100000000)) -> 21277.971 | L15: =IF(C15="","",[1]!hks_val_mv_ard(C15,E15,"",100000000)) -> 23053.51 | N15: =IF(C15="","",[1]!hks_val_pe(C15,基本资料!$I$9,基本资料!$G$9)) -> 11.522669 | O15: =IF(C15="","",[1]!hks_val_pe(C15,基本资料!$I$8,基本资料!$G$8)) -> 16.148302 | P15: =IF(C15="","",[1]!hks_val_pe_ttm(C15,E15)) -> 16.81008 | Q15: =IF(C15="","",[1]!s_val_estpe(C15,E15,YEAR([1]!s_stm_rpt_e(C15,基本资料!$I$8,0))+1)) -> 16.562722 | R15: =IF(C15="","",[1]!s_val_estpe(C15,E15,YEAR([1]!s_stm_rpt_e(C15,基本资料!$I$8,0))+2)) -> 15.724293 | S15: =IF(C15="","",[1]!hks_val_pb(C15,基本资料!$I$9,基本资料!$G$9)) -> 1.1142905 | T15: =IF(C15="","",[1]!hks_val_pb(C15,基本资料!$I$8,基本资料!$G$8)) -> 1.5858585 | U15: =IF(C15="","",[1]!pb_mrq(C15,E15)) -> 1.7395738 | V15: =IF(C15="","",[1]!s_val_estpb(C15,E15,YEAR([1]!s_stm_rpt_e(C15,基本资料!$I$8,0))+1)) -> 1.7299844 | W15: =IF(C15="","",[1]!s_val_estpb(C15,E15,YEAR([1]!s_stm_rpt_e(C15,基本资料!$I$8,0))+2)) -> 1.6478723 | X15: =IF(C15="","",[1]!hks_val_ps(C15,基本资料!$I$9,基本资料!$G$9)) -> 1.5358164 | Y15: =IF(C15="","",[1]!hks_val_ps(C15,基本资料!$I$8,基本资料!$G$8)) -> 2.0995208 | Z15: =IF(C15="","",[1]!hks_val_ps_ttm(C15,E15)) -> 2.2486688 | AA15: =IF(C15="","",[1]!hks_val_pcf(C15,基本资料!$I$9,基本资料!$G$9)) -> -18.814145 | AB15: =IF(C15="","",[1]!hks_val_pcf(C15,基本资料!$I$8,基本资料!$G$8)) -> -83.289511 | AC15: =IF(C15="","",[1]!hks_val_pcf_ttm(C15,E15)) -> -41.090672 | AD15: =IF(C15="","",[1]!s_val_evtoebitda2(C15,E15)) -> 4.0123437 | AE15: =IF(C15="","",[1]!hks_val_ev2(C15,E15,"",1)/[1]!hks_fa_ebit2_ttm(C15,[1]!s_fa_latelyrd_bt(C15,[1]!lastradeday_s(C15,基本资料!$D$7)),"",1)) -> 9.5160979
C16: =IF(表1[[#This Row],[列1]]="","",表1[[#This Row],[列1]]) -> 603160.SH | D16: =IF(C16="","",[1]!hks_info_name(C16)) -> 汇顶科技 | E16: =IF(C16="","",[1]!lastradeday_s(C16,TODAY())) -> 2024-12-09 | F16: =IF(C16="","",[1]!hks_val_ev(C16,基本资料!$I$9,"",100000000)) -> 229.95332 | G16: =IF(C16="","",[1]!hks_val_ev(C16,基本资料!$I$8,"",100000000)) -> 316.47326 | H16: =IF(C16="","",[1]!hks_val_ev(C16,E16,"",100000000)) -> 412.34755 | J16: =IF(C16="","",[1]!hks_val_mv_ard(C16,基本资料!$I$9,"",100000000)) -> 229.95332 | K16: =IF(C16="","",[1]!hks_val_mv_ard(C16,基本资料!$I$8,"",100000000)) -> 316.47326 | L16: =IF(C16="","",[1]!hks_val_mv_ard(C16,E16,"",100000000)) -> 412.34755 | N16: =IF(C16="","",[1]!hks_val_pe(C16,基本资料!$I$9,基本资料!$G$9)) -> -30.757148 | O16: =IF(C16="","",[1]!hks_val_pe(C16,基本资料!$I$8,基本资料!$G$8)) -> 191.73814 | P16: =IF(C16="","",[1]!hks_val_pe_ttm(C16,E16)) -> 68.642334 | Q16: =IF(C16="","",[1]!s_val_estpe(C16,E16,YEAR([1]!s_stm_rpt_e(C16,基本资料!$I$8,0))+1)) -> 59.644704 | R16: =IF(C16="","",[1]!s_val_estpe(C16,E16,YEAR([1]!s_stm_rpt_e(C16,基本资料!$I$8,0))+2)) -> 50.011114 | S16: =IF(C16="","",[1]!hks_val_pb(C16,基本资料!$I$9,基本资料!$G$9)) -> 2.956344 | T16: =IF(C16="","",[1]!hks_val_pb(C16,基本资料!$I$8,基本资料!$G$8)) -> 3.9336514 | U16: =IF(C16="","",[1]!pb_mrq(C16,E16)) -> 4.8911095 | V16: =IF(C16="","",[1]!s_val_estpb(C16,E16,YEAR([1]!s_stm_rpt_e(C16,基本资料!$I$8,0))+1)) -> 4.7366373 | W16: =IF(C16="","",[1]!s_val_estpb(C16,E16,YEAR([1]!s_stm_rpt_e(C16,基本资料!$I$8,0))+2)) -> 4.3608906 | X16: =IF(C16="","",[1]!hks_val_ps(C16,基本资料!$I$9,基本资料!$G$9)) -> 6.827655 | Y16: =IF(C16="","",[1]!hks_val_ps(C16,基本资料!$I$8,基本资料!$G$8)) -> 7.2266116 | Z16: =IF(C16="","",[1]!hks_val_ps_ttm(C16,E16)) -> 9.2991931 | AA16: =IF(C16="","",[1]!hks_val_pcf(C16,基本资料!$I$9,基本资料!$G$9)) -> -313.92097 | AB16: =IF(C16="","",[1]!hks_val_pcf(C16,基本资料!$I$8,基本资料!$G$8)) -> -132.72489 | AC16: =IF(C16="","",[1]!hks_val_pcf_ttm(C16,E16)) -> -38.287525 | AD16: =IF(C16="","",[1]!s_val_evtoebitda2(C16,E16)) -> 70.516108 | AE16: =IF(C16="","",[1]!hks_val_ev2(C16,E16,"",1)/[1]!hks_fa_ebit2_ttm(C16,[1]!s_fa_latelyrd_bt(C16,[1]!lastradeday_s(C16,基本资料!$D$7)),"",1)) -> 192.80843
C17: =IF(表1[[#This Row],[列1]]="","",表1[[#This Row],[列1]]) -> 688111.SH | D17: =IF(C17="","",[1]!hks_info_name(C17)) -> 金山办公 | E17: =IF(C17="","",[1]!lastradeday_s(C17,TODAY())) -> 2024-12-09 | F17: =IF(C17="","",[1]!hks_val_ev(C17,基本资料!$I$9,"",100000000)) -> 1219.8848 | G17: =IF(C17="","",[1]!hks_val_ev(C17,基本资料!$I$8,"",100000000)) -> 1459.9692 | H17: =IF(C17="","",[1]!hks_val_ev(C17,E17,"",100000000)) -> 1445.8552 | J17: =IF(C17="","",[1]!hks_val_mv_ard(C17,基本资料!$I$9,"",100000000)) -> 1219.8848 | K17: =IF(C17="","",[1]!hks_val_mv_ard(C17,基本资料!$I$8,"",100000000)) -> 1459.9692 | L17: =IF(C17="","",[1]!hks_val_mv_ard(C17,E17,"",100000000)) -> 1445.8552 | N17: =IF(C17="","",[1]!hks_val_pe(C17,基本资料!$I$9,基本资料!$G$9)) -> 109.15907 | O17: =IF(C17="","",[1]!hks_val_pe(C17,基本资料!$I$8,基本资料!$G$8)) -> 110.79366 | P17: =IF(C17="","",[1]!hks_val_pe_ttm(C17,E17)) -> 98.737564 | Q17: =IF(C17="","",[1]!s_val_estpe(C17,E17,YEAR([1]!s_stm_rpt_e(C17,基本资料!$I$8,0))+1)) -> 94.712925 | R17: =IF(C17="","",[1]!s_val_estpe(C17,E17,YEAR([1]!s_stm_rpt_e(C17,基本资料!$I$8,0))+2)) -> 75.441645 | S17: =IF(C17="","",[1]!hks_val_pb(C17,基本资料!$I$9,基本资料!$G$9)) -> 13.982606 | T17: =IF(C17="","",[1]!hks_val_pb(C17,基本资料!$I$8,基本资料!$G$8)) -> 14.67483 | U17: =IF(C17="","",[1]!pb_mrq(C17,E17)) -> 13.507145 | V17: =IF(C17="","",[1]!s_val_estpb(C17,E17,YEAR([1]!s_stm_rpt_e(C17,基本资料!$I$8,0))+1)) -> 12.93066 | W17: =IF(C17="","",[1]!s_val_estpb(C17,E17,YEAR([1]!s_stm_rpt_e(C17,基本资料!$I$8,0))+2)) -> 11.369671 | X17: =IF(C17="","",[1]!hks_val_ps(C17,基本资料!$I$9,基本资料!$G$9)) -> 31.683544 | Y17: =IF(C17="","",[1]!hks_val_ps(C17,基本资料!$I$8,基本资料!$G$8)) -> 32.308731 | Z17: =IF(C17="","",[1]!hks_val_ps_ttm(C17,E17)) -> 29.432633 | AA17: =IF(C17="","",[1]!hks_val_pcf(C17,基本资料!$I$9,基本资料!$G$9)) -> 21.173031 | AB17: =IF(C17="","",[1]!hks_val_pcf(C17,基本资料!$I$8,基本资料!$G$8)) -> -41.254478 | AC17: =IF(C17="","",[1]!hks_val_pcf_ttm(C17,E17)) -> -52.061802 | AD17: =IF(C17="","",[1]!s_val_evtoebitda2(C17,E17)) -> 118.53599 | AE17: =IF(C17="","",[1]!hks_val_ev2(C17,E17,"",1)/[1]!hks_fa_ebit2_ttm(C17,[1]!s_fa_latelyrd_bt(C17,[1]!lastradeday_s(C17,基本资料!$D$7)),"",1)) -> 132.03982
C18: =IF(表1[[#This Row],[列1]]="","",表1[[#This Row],[列1]]) -> 0700.HK | D18: =IF(C18="","",[1]!hks_info_name(C18)) -> 腾讯控股 | E18: =IF(C18="","",[1]!lastradeday_s(C18,TODAY())) -> 2024-12-06 | F18: =IF(C18="","",[1]!hks_val_ev(C18,基本资料!$I$9,"",100000000)) -> 31959.588 | G18: =IF(C18="","",[1]!hks_val_ev(C18,基本资料!$I$8,"",100000000)) -> 27842.067 | H18: =IF(C18="","",[1]!hks_val_ev(C18,E18,"",100000000)) -> 38237.595 | J18: =IF(C18="","",[1]!hks_val_mv_ard(C18,基本资料!$I$9,"",100000000)) -> 31984.899 | K18: =IF(C18="","",[1]!hks_val_mv_ard(C18,基本资料!$I$8,"",100000000)) -> 27842.067 | L18: =IF(C18="","",[1]!hks_val_mv_ard(C18,E18,"",100000000)) -> 38237.595 | N18: =IF(C18="","",[1]!hks_val_pe(C18,基本资料!$I$9,基本资料!$G$9)) -> 15.165792 | O18: =IF(C18="","",[1]!hks_val_pe(C18,基本资料!$I$8,基本资料!$G$8)) -> 21.898901 | P18: =IF(C18="","",[1]!hks_val_pe_ttm(C18,E18)) -> 20.310696 | Q18: =IF(C18="","",[1]!s_val_estpe(C18,E18,YEAR([1]!s_stm_rpt_e(C18,基本资料!$I$8,0))+1)) -> 19.295004 | R18: =IF(C18="","",[1]!s_val_estpe(C18,E18,YEAR([1]!s_stm_rpt_e(C18,基本资料!$I$8,0))+2)) -> 17.174304 | S18: =IF(C18="","",[1]!hks_val_pb(C18,基本资料!$I$9,基本资料!$G$9)) -> 3.9574296 | T18: =IF(C18="","",[1]!hks_val_pb(C18,基本资料!$I$8,基本资料!$G$8)) -> 3.1203709 | U18: =IF(C18="","",[1]!pb_mrq(C18,E18)) -> 3.8682324 | V18: =IF(C18="","",[1]!s_val_estpb(C18,E18,YEAR([1]!s_stm_rpt_e(C18,基本资料!$I$8,0))+1)) -> 3.6486973 | W18: =IF(C18="","",[1]!s_val_estpb(C18,E18,YEAR([1]!s_stm_rpt_e(C18,基本资料!$I$8,0))+2)) -> 3.0967953 | X18: =IF(C18="","",[1]!hks_val_ps(C18,基本资料!$I$9,基本资料!$G$9)) -> 4.1881586 | Y18: =IF(C18="","",[1]!hks_val_ps(C18,基本资料!$I$8,基本资料!$G$8)) -> 4.1429255 | Z18: =IF(C18="","",[1]!hks_val_ps_ttm(C18,E18)) -> 5.3626603 | AA18: =IF(C18="","",[1]!hks_val_pcf(C18,基本资料!$I$9,基本资料!$G$9)) -> -254.28468 | AB18: =IF(C18="","",[1]!hks_val_pcf(C18,基本资料!$I$8,基本资料!$G$8)) -> 161.93465 | AC18: =IF(C18="","",[1]!hks_val_pcf_ttm(C18,E18)) -> 0 | AD18: =IF(C18="","",[1]!s_val_evtoebitda2(C18,E18)) -> 17.197141 | AE18: =IF(C18="","",[1]!hks_val_ev2(C18,E18,"",1)/[1]!hks_fa_ebit2_ttm(C18,[1]!s_fa_latelyrd_bt(C18,[1]!lastradeday_s(C18,基本资料!$D$7)),"",1)) -> 26.305967
C19: =IF(表1[[#This Row],[列1]]="","",表1[[#This Row],[列1]]) -> 9896.HK | D19: =IF(C19="","",[1]!hks_info_name(C19)) -> 名创优品 | E19: =IF(C19="","",[1]!lastradeday_s(C19,TODAY())) -> 2024-12-06 | F19: =IF(C19="","",[1]!hks_val_ev(C19,基本资料!$I$9,"",100000000)) -> 264.80019 | G19: =IF(C19="","",[1]!hks_val_ev(C19,基本资料!$I$8,"",100000000)) -> 507.37141 | H19: =IF(C19="","",[1]!hks_val_ev(C19,E19,"",100000000)) -> 595.47674 | J19: =IF(C19="","",[1]!hks_val_mv_ard(C19,基本资料!$I$9,"",100000000)) -> 264.80019 | K19: =IF(C19="","",[1]!hks_val_mv_ard(C19,基本资料!$I$8,"",100000000)) -> 507.37141 | L19: =IF(C19="","",[1]!hks_val_mv_ard(C19,E19,"",100000000)) -> 595.47674 | N19: =IF(C19="","",[1]!hks_val_pe(C19,基本资料!$I$9,基本资料!$G$9)) -> 35.484976 | O19: =IF(C19="","",[1]!hks_val_pe(C19,基本资料!$I$8,基本资料!$G$8)) -> 26.44465 | P19: =IF(C19="","",[1]!hks_val_pe_ttm(C19,E19)) -> 22.843327 | Q19: =IF(C19="","",[1]!s_val_estpe(C19,E19,YEAR([1]!s_stm_rpt_e(C19,基本资料!$I$8,0))+1)) -> 20.115694 | R19: =IF(C19="","",[1]!s_val_estpe(C19,E19,YEAR([1]!s_stm_rpt_e(C19,基本资料!$I$8,0))+2)) -> 16.403524 | S19: =IF(C19="","",[1]!hks_val_pb(C19,基本资料!$I$9,基本资料!$G$9)) -> 3.2205063 | T19: =IF(C19="","",[1]!hks_val_pb(C19,基本资料!$I$8,基本资料!$G$8)) -> 5.2554264 | U19: =IF(C19="","",[1]!pb_mrq(C19,E19)) -> 5.7716712 | V19: =IF(C19="","",[1]!s_val_estpb(C19,E19,YEAR([1]!s_stm_rpt_e(C19,基本资料!$I$8,0))+1)) -> 4.0791297 | W19: =IF(C19="","",[1]!s_val_estpb(C19,E19,YEAR([1]!s_stm_rpt_e(C19,基本资料!$I$8,0))+2)) -> 3.3447997 | X19: =IF(C19="","",[1]!hks_val_ps(C19,基本资料!$I$9,基本资料!$G$9)) -> 2.2453139 | Y19: =IF(C19="","",[1]!hks_val_ps(C19,基本资料!$I$8,基本资料!$G$8)) -> 4.0772057 | Z19: =IF(C19="","",[1]!hks_val_ps_ttm(C19,E19)) -> 3.4570116 | AA19: =IF(C19="","",[1]!hks_val_pcf(C19,基本资料!$I$9,基本资料!$G$9)) -> -15.912077 | AB19: =IF(C19="","",[1]!hks_val_pcf(C19,基本资料!$I$8,基本资料!$G$8)) -> 41.007949 | AC19: =IF(C19="","",[1]!hks_val_pcf_ttm(C19,E19)) -> 0 | AD19: =IF(C19="","",[1]!s_val_evtoebitda2(C19,E19)) -> 0 | AE19: =IF(C19="","",[1]!hks_val_ev2(C19,E19,"",1)/[1]!hks_fa_ebit2_ttm(C19,[1]!s_fa_latelyrd_bt(C19,[1]!lastradeday_s(C19,基本资料!$D$7)),"",1)) -> 27.540597
... C100: =IF(表1[[#This Row],[列1]]="","",表1[[#This Row],[列1]]) | D100: =IF(C100="","",[1]!hks_info_name(C100)) | E100: =IF(C100="","",[1]!lastradeday_s(C100,TODAY())) | F100: =IF(C100="","",[1]!hks_val_ev(C100,基本资料!$I$9,"",100000000)) | G100: =IF(C100="","",[1]!hks_val_ev(C100,基本资料!$I$8,"",100000000)) | H100: =IF(C100="","",[1]!hks_val_ev(C100,E100,"",100000000)) | J100: =IF(C100="","",[1]!hks_val_mv_ard(C100,基本资料!$I$9,"",100000000)) | K100: =IF(C100="","",[1]!hks_val_mv_ard(C100,基本资料!$I$8,"",100000000)) | L100: =IF(C100="","",[1]!hks_val_mv_ard(C100,E100,"",100000000)) | N100: =IF(C100="","",[1]!hks_val_pe(C100,基本资料!$I$9,基本资料!$G$9)) | O100: =IF(C100="","",[1]!hks_val_pe(C100,基本资料!$I$8,基本资料!$G$8)) | P100: =IF(C100="","",[1]!hks_val_pe_ttm(C100,E100)) | Q100: =IF(C100="","",[1]!s_val_estpe(C100,E100,YEAR([1]!s_stm_rpt_e(C100,基本资料!$I$8,0))+1)) | R100: =IF(C100="","",[1]!s_val_estpe(C100,E100,YEAR([1]!s_stm_rpt_e(C100,基本资料!$I$8,0))+2)) | S100: =IF(C100="","",[1]!hks_val_pb(C100,基本资料!$I$9,基本资料!$G$9)) | T100: =IF(C100="","",[1]!hks_val_pb(C100,基本资料!$I$8,基本资料!$G$8)) | U100: =IF(C100="","",[1]!pb_mrq(C100,E100)) | V100: =IF(C100="","",[1]!s_val_estpb(C100,E100,YEAR([1]!s_stm_rpt_e(C100,基本资料!$I$8,0))+1)) | W100: =IF(C100="","",[1]!s_val_estpb(C100,E100,YEAR([1]!s_stm_rpt_e(C100,基本资料!$I$8,0))+2)) | X100: =IF(C100="","",[1]!hks_val_ps(C100,基本资料!$I$9,基本资料!$G$9)) | Y100: =IF(C100="","",[1]!hks_val_ps(C100,基本资料!$I$8,基本资料!$G$8)) | Z100: =IF(C100="","",[1]!hks_val_ps_ttm(C100,E100)) | AA100: =IF(C100="","",[1]!hks_val_pcf(C100,基本资料!$I$9,基本资料!$G$9)) | AB100: =IF(C100="","",[1]!hks_val_pcf(C100,基本资料!$I$8,基本资料!$G$8)) | AC100: =IF(C100="","",[1]!hks_val_pcf_ttm(C100,E100)) | AD100: =IF(C100="","",[1]!s_val_evtoebitda2(C100,E100)) | AE100: =IF(C100="","",[1]!hks_val_ev2(C100,E100,"",1)/[1]!hks_fa_ebit2_ttm(C100,[1]!s_fa_latelyrd_bt(C100,[1]!lastradeday_s(C100,基本资料!$D$7)),"",1))

Sheet 财务分析
D1: 可比公司-财务分析
C4: 财务分析
C6: Wind代码 | D6: 证券简称 | E6: 最新收盘日 | F6: 最近一期年报日期 | G6: 最近一期年报记账本位币 | H6: 每股指标 | L6: 盈利能力(%) | U6: 收益质量 | W6: 资本结构 | AC6: 偿债能力 | AG6: 运营能力 | AM6: 成长能力(同比增长率)(%) | AR6: 杜邦分析 | AZ6: 利润表衍生数据(亿元) | BG6: 资产负债表衍生数据(亿元) | BP6: 现金流量表衍生数据(亿元)
H7: 基本每股收益 | I7: 每股收益-最新股本摊薄 | J7: 每股净资产 | K7: 每股经营现金净流量 | L7: 毛利率 | M7: 净利率 | N7: 净资产收益率ROE | O7: 净资产收益率ROE(扣非) | P7: 总资产回报率 ROA | Q7: 投入资本回报率 ROIC | R7: 净利润/营业总收入 Profit Margin | S7: EBIT/Sales | T7: EBITDA/Sales | U7: 营业利润/利润总额 | V7: 经营活动产生的现金流量净额/营业收入 | W7: 资产负债率 | X7: 净资产负债率 | Y7: 流动资产/总资产 | Z7: 非流动资产/总资产 | AA7: 流动负债/负债合计 | AB7: 非流动负债/负债合计 | AC7: 流动比率 | AD7: 速动比率 | AE7: 已获利息倍数(EBIT/利息费用) | AF7: 净负债率 | AG7: 应收账款周转率 | AH7: 应付账款周转率 | AI7: 存货周转率 | AJ7: 流动资产周转率 | AK7: 固定资产周转率 | AL7: 总资产周转率 | AM7: 营业总收入增长率 | AN7: 营业收入增长率 | AO7: 营业利润增长率 | AP7: 利润总额增长率 | AQ7: 归母净利润增长率 | AR7: 归母净利润/净利润 | AS7: 净利润/利润总额 | AT7: 净利润/营业总收入 | AU7: 平均净资产收益率 | AV7: 利润总额/EBIT | AW7: 权益乘数 | AX7: EBIT/营业总收入 | AY7: 总资产周转率 | AZ7: 毛利润 | BA7: 息税前利润 | BB7: 息税折旧摊销前利润 | BC7: EBIT(反推法) | BD7: EBITDA(反推法) | BE7: 净利润(Non-GAAP) | BF7: 扣除非经常损益后净利润 | BG7: 留存收益 | BH7: 营运资本 | BI7: 净营运资本 | BJ7: 全部投入资本 | BK7: 有形资产 | BL7: 净债务 | BM7: 带息债务 | BN7: 无息流动负债 | BO7: 无息非流动负债 | BP7: 股权自由现金流量FCFE | BQ7: 企业自由现金流
C8: =IF(表1[[#This Row],[列1]]="","",表1[[#This Row],[列1]]) -> 000001.SZ | D8: =IF(C8="","",[1]!hks_info_name(C8)) -> 平安银行 | E8: =IF(C8="","",[1]!lastradeday_s(C8,TODAY())) -> 2024-12-09 | F8: =IF(C8="","",IF(OR([1]!s_stm_rpt_e(C8,基本资料!$I$8,0)="#N/A",[1]!s_stm_rpt_e(C8,基本资料!$I$8,0)="",[1]!s_stm_rpt_e(C8,基本资料!$I$8,0)=0),[1]!s_stm_rpt_e(C8,基本资料!$I$9,0),[1]!s_stm_rpt_e(C8,基本资料!$I$8,0))) -> 2023-12-31 | G8: =IF(C8="","",[1]!hks_info_cur2(C8,F8)) -> CNY | H8: =IF(C8="","",[1]!hks_fa_eps_basic(C8,F8,"")) -> 2.25 | I8: =IF(C8="","",[1]!hks_fa_eps_adjust2(C8,F8,"")) -> 2.3938574 | J8: =IF(C8="","",[1]!hks_fa_bps(C8,F8,"")) -> 20.7351 | K8: =IF(C8="","",[1]!hks_fa_ocfps(C8,F8,"")) -> 4.76 | L8: =IF(C8="","",[1]!hks_fa_grossprofitmargin(C8,F8)) -> 0 | M8: =IF(C8="","",[1]!hks_fa_netprofitmargin(C8,F8)) -> 28.5033 | N8: =IF(C8="","",[1]!hks_fa_roe(C8,F8)) -> 10.2436 | O8: =IF(C8="","",[1]!hks_fa_roe_deducted(C8,F8)) -> 10.3679 | P8: =IF(C8="","",[1]!hks_fa_roa2(C8,F8)) -> 0 | Q8: =IF(C8="","",[1]!hks_fa_roic(C8,F8)) -> 0 | R8: =IF(C8="","",[1]!hks_fa_dupont_nptosales(C8,F8)) -> 28.5033 | S8: =IF(C8="","",[1]!hks_fa_dupont_ebittosales(C8,F8)) -> 0 | T8: =IF(C8="","",[1]!hks_fa_ebitdatosales(C8,F8)) -> 0 | U8: =IF(C8="","",[1]!hks_fa_optoebt(C8,F8)) -> 100.3638 | V8: =IF(C8="","",[1]!hks_fa_ocftosales(C8,F8)) -> 56.7312 | W8: =IF(C8="","",[1]!hks_fa_debttoassets(C8,F8)) -> 91.5461 | X8: =IF(C8="","",[1]!s_fa_debttoeqy(C8,F8)) -> 10.82889 | Y8: =IF(C8="","",[1]!hks_fa_catoassets(C8,F8)) -> 0 | Z8: =IF(C8="","",[1]!hks_fa_ncatoassets(C8,F8)) -> 0 | AA8: =IF(C8="","",[1]!hks_fa_currentdebttodebt(C8,F8)) -> 0 | AB8: =IF(C8="","",[1]!hks_fa_longdebtodebt(C8,F8)) -> 0 | AC8: =IF(C8="","",[1]!hks_fa_current(C8,F8)) -> 0 | AD8: =IF(C8="","",[1]!hks_fa_quick(C8,F8)) -> 0 | AE8: =IF(C8="","",[1]!hks_fa_ebittointerest(C8,F8)) -> 0 | AF8: =IF(C8="","",[1]!hks_fa_netdebtratio(C8,F8)) -> 1082.889 | AG8: =IF(C8="","",[1]!hks_fa_arturn(C8,F8)) -> 0 | AH8: =IF(C8="","",[1]!hks_fa_apturn(C8,F8)) -> 0 | AI8: =IF(C8="","",[1]!hks_fa_invturn(C8,F8)) -> 0 | AJ8: =IF(C8="","",[1]!hks_fa_caturn(C8,F8)) -> 0 | AK8: =IF(C8="","",[1]!hks_fa_faturn(C8,F8)) -> 15.5985 | AL8: =IF(C8="","",[1]!hks_fa_assetsturn(C8,F8)) -> 0.0299 | AM8: =IF(C8="","",[1]!hks_fa_yoy_tr(C8,F8)) -> -8.524 | AN8: =IF(C8="","",[1]!hks_fa_yoy_or(C8,F8)) -> -8.524 | AO8: =IF(C8="","",[1]!hks_fa_yoyop2(C8,F8)) -> 0.78816877 | AP8: =IF(C8="","",[1]!hks_fa_yoyebt(C8,F8)) -> 0.8122 | AQ8: =IF(C8="","",[1]!hks_fa_yoynetprofit(C8,F8)) -> 2.063 | AR8: =IF(C8="","",[1]!hks_fa_dupont_np(C8,F8)) -> 100 | AS8: =IF(C8="","",[1]!hks_fa_dupont_taxburden(C8,F8)) -> 80.4862 | AT8: =IF(C8="","",[1]!s_fa_dupont_nptosales(C8,F8)) -> 28.206 | AU8: =IF(C8="","",[1]!s_fa_dupont_roe(C8,F8)) -> 10.2436 | AV8: =IF(C8="","",[1]!hks_fa_dupont_intburden(C8,F8)) -> 0 | AW8: =IF(C8="","",[1]!hks_fa_dupont_assetstoequity(C8,F8)) -> 12.027 | AX8: =IF(C8="","",[1]!s_fa_dupont_ebittosales(C8,F8)) -> 0 | AY8: =IF(C8="","",[1]!hks_fa_assetsturn(C8,F8)) -> 0.0299 | AZ8: =IF(C8="","",[1]!hks_fa_grossmargin2(C8,F8,"",100000000)) -> 0 | BA8: =IF(C8="","",[1]!hks_fa_ebit3(C8,F8,1,"",100000000)) -> 0 | BB8: =IF(C8="","",[1]!hks_fa_ebitda(C8,F8,1,"",100000000)) -> 0 | BC8: =IF(C8="","",[1]!hks_fa_ebit(C8,F8,1,"",100000000)) -> 0 | BD8: =IF(C8="","",[1]!hks_fa_ebitda(C8,F8,1,"",100000000)) -> 0 | BE8: =IF(C8="","",[1]!hks_fa_nogaapprofit(C8,F8,1,"",100000000)) -> 0 | BF8: =IF(C8="","",[1]!hks_fa_deductedprofit(C8,F8,1,"",100000000)) -> 470.19 | BG8: =IF(C8="","",[1]!hks_fa_retainedearnings2(C8,F8,"",100000000)) -> 2212.55 | BH8: =IF(C8="","",[1]!hks_fa_workingcapital2(C8,F8,"",100000000)) -> 0 | BI8: =IF(C8="","",[1]!hks_fa_networkingcapital2(C8,F8,"",100000000)) -> 0 | BJ8: =IF(C8="","",[1]!hks_fa_investcapital2(C8,F8,"",100000000)) -> 55871.16 | BK8: =IF(C8="","",[1]!hks_fa_tangibleasset2(C8,F8,"",100000000)) -> 0 | BL8: =IF(C8="","",[1]!hks_fa_netdebt2(C8,F8,"",100000000)) -> 51147.88 | BM8: =IF(C8="","",[1]!hks_fa_interestdebt2(C8,F8,"",100000000)) -> 51147.88 | BN8: =IF(C8="","",[1]!hks_fa_exinterestdebt_current(C8,F8,"",100000000)) -> 0 | BO8: =IF(C8="","",[1]!hks_fa_exinterestdebt_noncurrent2(C8,F8,"",100000000)) -> 0 | BP8: =IF(C8="","",[1]!hks_fa_fcfe2(C8,F8,"",100000000)) -> -8620.16 | BQ8: =IF(C8="","",[1]!hks_fa_fcff2(C8,F8,"",100000000)) -> 467.91
C9: =IF(表1[[#This Row],[列1]]="","",表1[[#This Row],[列1]]) -> 000002.SZ | D9: =IF(C9="","",[1]!hks_info_name(C9)) -> 万科A | E9: =IF(C9="","",[1]!lastradeday_s(C9,TODAY())) -> 2024-12-09 | F9: =IF(C9="","",IF(OR([1]!s_stm_rpt_e(C9,基本资料!$I$8,0)="#N/A",[1]!s_stm_rpt_e(C9,基本资料!$I$8,0)="",[1]!s_stm_rpt_e(C9,基本资料!$I$8,0)=0),[1]!s_stm_rpt_e(C9,基本资料!$I$9,0),[1]!s_stm_rpt_e(C9,基本资料!$I$8,0))) -> 2023-12-31 | G9: =IF(C9="","",[1]!hks_info_cur2(C9,F9)) -> CNY | H9: =IF(C9="","",[1]!hks_fa_eps_basic(C9,F9,"")) -> 1.03 | I9: =IF(C9="","",[1]!hks_fa_eps_adjust2(C9,F9,"")) -> 1.0194435 | J9: =IF(C9="","",[1]!hks_fa_bps(C9,F9,"")) -> 21.0201 | K9: =IF(C9="","",[1]!hks_fa_ocfps(C9,F9,"")) -> 0.3279 | L9: =IF(C9="","",[1]!hks_fa_grossprofitmargin(C9,F9)) -> 14.482 | M9: =IF(C9="","",[1]!hks_fa_netprofitmargin(C9,F9)) -> 4.3863 | N9: =IF(C9="","",[1]!hks_fa_roe(C9,F9)) -> 4.9294 | O9: =IF(C9="","",[1]!hks_fa_roe_deducted(C9,F9)) -> 3.524 | P9: =IF(C9="","",[1]!hks_fa_roa2(C9,F9)) -> 2.8704 | Q9: =IF(C9="","",[1]!hks_fa_roic(C9,F9)) -> 2.1511 | R9: =IF(C9="","",[1]!hks_fa_dupont_nptosales(C9,F9)) -> 4.3863 | S9: =IF(C9="","",[1]!hks_fa_dupont_ebittosales(C9,F9)) -> 10.0389 | T9: =IF(C9="","",[1]!hks_fa_ebitdatosales(C9,F9)) -> 11.986084 | U9: =IF(C9="","",[1]!hks_fa_optoebt(C9,F9)) -> 97.3911 | V9: =IF(C9="","",[1]!hks_fa_ocftosales(C9,F9)) -> 0.8389 | W9: =IF(C9="","",[1]!hks_fa_debttoassets(C9,F9)) -> 73.2247 | X9: =IF(C9="","",[1]!s_fa_debttoeqy(C9,F9)) -> 4.3938766 | Y9: =IF(C9="","",[1]!hks_fa_catoassets(C9,F9)) -> 76.4372 | Z9: =IF(C9="","",[1]!hks_fa_ncatoassets(C9,F9)) -> 23.5628 | AA9: =IF(C9="","",[1]!hks_fa_currentdebttodebt(C9,F9)) -> 74.5763 | AB9: =IF(C9="","",[1]!hks_fa_longdebtodebt(C9,F9)) -> 25.4237 | AC9: =IF(C9="","",[1]!hks_fa_current(C9,F9)) -> 1.3997 | AD9: =IF(C9="","",[1]!hks_fa_quick(C9,F9)) -> 0.5394 | AE9: =IF(C9="","",[1]!hks_fa_ebittointerest(C9,F9)) -> 25.3526 | AF9: =IF(C9="","",[1]!hks_fa_netdebtratio(C9,F9)) -> 55.771839 | AG9: =IF(C9="","",[1]!hks_fa_arturn(C9,F9)) -> 62.8846 | AH9: =IF(C9="","",[1]!hks_fa_apturn(C9,F9)) -> 1.5590588 | AI9: =IF(C9="","",[1]!hks_fa_invturn(C9,F9)) -> 0.4915 | AJ9: =IF(C9="","",[1]!hks_fa_caturn(C9,F9)) -> 0.3635 | AK9: =IF(C9="","",[1]!hks_fa_faturn(C9,F9)) -> 15.4282 | AL9: =IF(C9="","",[1]!hks_fa_assetsturn(C9,F9)) -> 0.2859 | AM9: =IF(C9="","",[1]!hks_fa_yoy_tr(C9,F9)) -> -7.5608 | AN9: =IF(C9="","",[1]!hks_fa_yoy_or(C9,F9)) -> -7.5618 | AO9: =IF(C9="","",[1]!hks_fa_yoyop2(C9,F9)) -> -37.304175 | AP9: =IF(C9="","",[1]!hks_fa_yoyebt(C9,F9)) -> -38.7476 | AQ9: =IF(C9="","",[1]!hks_fa_yoynetprofit(C9,F9)) -> -46.3929 | AR9: =IF(C9="","",[1]!hks_fa_dupont_np(C9,F9)) -> 59.4591 | AS9: =IF(C9="","",[1]!hks_fa_dupont_taxburden(C9,F9)) -> 45.4869 | AT9: =IF(C9="","",[1]!s_fa_dupont_nptosales(C9,F9)) -> 4.3921 | AU9: =IF(C9="","",[1]!s_fa_dupont_roe(C9,F9)) -> 4.9294 | AV9: =IF(C9="","",[1]!hks_fa_dupont_intburden(C9,F9)) -> 96.0556 | AW9: =IF(C9="","",[1]!hks_fa_dupont_assetstoequity(C9,F9)) -> 6.6103 | AX9: =IF(C9="","",[1]!s_fa_dupont_ebittosales(C9,F9)) -> 6.988 | AY9: =IF(C9="","",[1]!hks_fa_assetsturn(C9,F9)) -> 0.2859 | AZ9: =IF(C9="","",[1]!hks_fa_grossmargin2(C9,F9,"",100000000)) -> 674.48208 | BA9: =IF(C9="","",[1]!hks_fa_ebit3(C9,F9,1,"",100000000)) -> 299.27726 | BB9: =IF(C9="","",[1]!hks_fa_ebitda(C9,F9,1,"",100000000)) -> 558.97601 | BC9: =IF(C9="","",[1]!hks_fa_ebit(C9,F9,1,"",100000000)) -> 468.16806 | BD9: =IF(C9="","",[1]!hks_fa_ebitda(C9,F9,1,"",100000000)) -> 558.97601 | BE9: =IF(C9="","",[1]!hks_fa_nogaapprofit(C9,F9,1,"",100000000)) -> 0 | BF9: =IF(C9="","",[1]!hks_fa_deductedprofit(C9,F9,1,"",100000000)) -> 86.9501 | BG9: =IF(C9="","",[1]!hks_fa_retainedearnings2(C9,F9,"",100000000)) -> 936.16302 | BH9: =IF(C9="","",[1]!hks_fa_workingcapital2(C9,F9,"",100000000)) -> 3284.968 | BI9: =IF(C9="","",[1]!hks_fa_networkingcapital2(C9,F9,"",100000000)) -> 2955.8508 | BJ9: =IF(C9="","",[1]!hks_fa_investcapital2(C9,F9,"",100000000)) -> 5724.5063 | BK9: =IF(C9="","",[1]!hks_fa_tangibleasset2(C9,F9,"",100000000)) -> 2410.336 | BL9: =IF(C9="","",[1]!hks_fa_netdebt2(C9,F9,"",100000000)) -> 2247.2344 | BM9: =IF(C9="","",[1]!hks_fa_interestdebt2(C9,F9,"",100000000)) -> 3216.6602 | BN9: =IF(C9="","",[1]!hks_fa_exinterestdebt_current(C9,F9,"",100000000)) -> 7577.544 | BO9: =IF(C9="","",[1]!hks_fa_exinterestdebt_noncurrent2(C9,F9,"",100000000)) -> 225.18216 | BP9: =IF(C9="","",[1]!hks_fa_fcfe2(C9,F9,"",100000000)) -> -103.29528 | BQ9: =IF(C9="","",[1]!hks_fa_fcff2(C9,F9,"",100000000)) -> -119.59213
C10: =IF(表1[[#This Row],[列1]]="","",表1[[#This Row],[列1]]) -> 002123.SZ | D10: =IF(C10="","",[1]!hks_info_name(C10)) -> 梦网科技 | E10: =IF(C10="","",[1]!lastradeday_s(C10,TODAY())) -> 2024-12-09 | F10: =IF(C10="","",IF(OR([1]!s_stm_rpt_e(C10,基本资料!$I$8,0)="#N/A",[1]!s_stm_rpt_e(C10,基本资料!$I$8,0)="",[1]!s_stm_rpt_e(C10,基本资料!$I$8,0)=0),[1]!s_stm_rpt_e(C10,基本资料!$I$9,0),[1]!s_stm_rpt_e(C10,基本资料!$I$8,0))) -> 2023-12-31 | G10: =IF(C10="","",[1]!hks_info_cur2(C10,F10)) -> CNY | H10: =IF(C10="","",[1]!hks_fa_eps_basic(C10,F10,"")) -> -2.22 | I10: =IF(C10="","",[1]!hks_fa_eps_adjust2(C10,F10,"")) -> -2.2769643 | J10: =IF(C10="","",[1]!hks_fa_bps(C10,F10,"")) -> 2.0307 | K10: =IF(C10="","",[1]!hks_fa_ocfps(C10,F10,"")) -> -0.4984 | L10: =IF(C10="","",[1]!hks_fa_grossprofitmargin(C10,F10)) -> 6.1427 | M10: =IF(C10="","",[1]!hks_fa_netprofitmargin(C10,F10)) -> -34.9762 | N10: =IF(C10="","",[1]!hks_fa_roe(C10,F10)) -> -72.1722 | O10: =IF(C10="","",[1]!hks_fa_roe_deducted(C10,F10)) -> -71.8438 | P10: =IF(C10="","",[1]!hks_fa_roa2(C10,F10)) -> -34.4599 | Q10: =IF(C10="","",[1]!hks_fa_roic(C10,F10)) -> -40.0862 | R10: =IF(C10="","",[1]!hks_fa_dupont_nptosales(C10,F10)) -> -34.9762 | S10: =IF(C10="","",[1]!hks_fa_dupont_ebittosales(C10,F10)) -> -35.0588 | T10: =IF(C10="","",[1]!hks_fa_ebitdatosales(C10,F10)) -> -34.247268 | U10: =IF(C10="","",[1]!hks_fa_optoebt(C10,F10)) -> 0 | V10: =IF(C10="","",[1]!hks_fa_ocftosales(C10,F10)) -> -7.6324 | W10: =IF(C10="","",[1]!hks_fa_debttoassets(C10,F10)) -> 62.5103 | X10: =IF(C10="","",[1]!s_fa_debttoeqy(C10,F10)) -> 1.6728735 | Y10: =IF(C10="","",[1]!hks_fa_catoassets(C10,F10)) -> 79.6432 | Z10: =IF(C10="","",[1]!hks_fa_ncatoassets(C10,F10)) -> 20.3568 | AA10: =IF(C10="","",[1]!hks_fa_currentdebttodebt(C10,F10)) -> 92.3967 | AB10: =IF(C10="","",[1]!hks_fa_longdebtodebt(C10,F10)) -> 7.6033 | AC10: =IF(C10="","",[1]!hks_fa_current(C10,F10)) -> 1.3789 | AD10: =IF(C10="","",[1]!hks_fa_quick(C10,F10)) -> 0 | AE10: =IF(C10="","",[1]!hks_fa_ebittointerest(C10,F10)) -> 0 | AF10: =IF(C10="","",[1]!hks_fa_netdebtratio(C10,F10)) -> 95.542255 | AG10: =IF(C10="","",[1]!hks_fa_arturn(C10,F10)) -> 2.8956 | AH10: =IF(C10="","",[1]!hks_fa_apturn(C10,F10)) -> 11.133769 | AI10: =IF(C10="","",[1]!hks_fa_invturn(C10,F10)) -> 0 | AJ10: =IF(C10="","",[1]!hks_fa_caturn(C10,F10)) -> 1.4898 | AK10: =IF(C10="","",[1]!hks_fa_faturn(C10,F10)) -> 15.2923 | AL10: =IF(C10="","",[1]!hks_fa_assetsturn(C10,F10)) -> 0.9829 | AM10: =IF(C10="","",[1]!hks_fa_yoy_tr(C10,F10)) -> 25.8272 | AN10: =IF(C10="","",[1]!hks_fa_yoy_or(C10,F10)) -> 25.8272 | AO10: =IF(C10="","",[1]!hks_fa_yoyop2(C10,F10)) -> -138.08297 | AP10: =IF(C10="","",[1]!hks_fa_yoyebt(C10,F10)) -> -148.4923 | AQ10: =IF(C10="","",[1]!hks_fa_yoynetprofit(C10,F10)) -> -152.3989 | AR10: =IF(C10="","",[1]!hks_fa_dupont_np(C10,F10)) -> 99.6896 | AS10: =IF(C10="","",[1]!hks_fa_dupont_taxburden(C10,F10)) -> 99.7645 | AT10: =IF(C10="","",[1]!s_fa_dupont_nptosales(C10,F10)) -> -34.926 | AU10: =IF(C10="","",[1]!s_fa_dupont_roe(C10,F10)) -> -72.1722 | AV10: =IF(C10="","",[1]!hks_fa_dupont_intburden(C10,F10)) -> 100 | AW10: =IF(C10="","",[1]!hks_fa_dupont_assetstoequity(C10,F10)) -> 2.1059 | AX10: =IF(C10="","",[1]!s_fa_dupont_ebittosales(C10,F10)) -> -34.3409 | AY10: =IF(C10="","",[1]!hks_fa_assetsturn(C10,F10)) -> 0.9829 | AZ10: =IF(C10="","",[1]!hks_fa_grossmargin2(C10,F10,"",100000000)) -> 3.2106869 | BA10: =IF(C10="","",[1]!hks_fa_ebit3(C10,F10,1,"",100000000)) -> -1.3384228 | BB10: =IF(C10="","",[1]!hks_fa_ebitda(C10,F10,1,"",100000000)) -> -17.900584 | BC10: =IF(C10="","",[1]!hks_fa_ebit(C10,F10,1,"",100000000)) -> -18.32476 | BD10: =IF(C10="","",[1]!hks_fa_ebitda(C10,F10,1,"",100000000)) -> -17.900584 | BE10: =IF(C10="","",[1]!hks_fa_nogaapprofit(C10,F10,1,"",100000000)) -> 0 | BF10: =IF(C10="","",[1]!hks_fa_deductedprofit(C10,F10,1,"",100000000)) -> -18.141906 | BG10: =IF(C10="","",[1]!hks_fa_retainedearnings2(C10,F10,"",100000000)) -> -16.787422 | BH10: =IF(C10="","",[1]!hks_fa_workingcapital2(C10,F10,"",100000000)) -> 9.5195169 | BI10: =IF(C10="","",[1]!hks_fa_networkingcapital2(C10,F10,"",100000000)) -> 23.177601 | BJ10: =IF(C10="","",[1]!hks_fa_investcapital2(C10,F10,"",100000000)) -> 35.616975 | BK10: =IF(C10="","",[1]!hks_fa_tangibleasset2(C10,F10,"",100000000)) -> 13.868159 | BL10: =IF(C10="","",[1]!hks_fa_netdebt2(C10,F10,"",100000000)) -> 15.579803 | BM10: =IF(C10="","",[1]!hks_fa_interestdebt2(C10,F10,"",100000000)) -> 19.363618 | BN10: =IF(C10="","",[1]!hks_fa_exinterestdebt_current(C10,F10,"",100000000)) -> 7.6805998 | BO10: =IF(C10="","",[1]!hks_fa_exinterestdebt_noncurrent2(C10,F10,"",100000000)) -> 0.1455921 | BP10: =IF(C10="","",[1]!hks_fa_fcfe2(C10,F10,"",100000000)) -> -20.252815 | BQ10: =IF(C10="","",[1]!hks_fa_fcff2(C10,F10,"",100000000)) -> -18.337001
C11: =IF(表1[[#This Row],[列1]]="","",表1[[#This Row],[列1]]) -> 002230.SZ | D11: =IF(C11="","",[1]!hks_info_name(C11)) -> 科大讯飞 | E11: =IF(C11="","",[1]!lastradeday_s(C11,TODAY())) -> 2024-12-09 | F11: =IF(C11="","",IF(OR([1]!s_stm_rpt_e(C11,基本资料!$I$8,0)="#N/A",[1]!s_stm_rpt_e(C11,基本资料!$I$8,0)="",[1]!s_stm_rpt_e(C11,基本资料!$I$8,0)=0),[1]!s_stm_rpt_e(C11,基本资料!$I$9,0),[1]!s_stm_rpt_e(C11,基本资料!$I$8,0))) -> 2023-12-31 | G11: =IF(C11="","",[1]!hks_info_cur2(C11,F11)) -> CNY | H11: =IF(C11="","",[1]!hks_fa_eps_basic(C11,F11,"")) -> 0.28 | I11: =IF(C11="","",[1]!hks_fa_eps_adjust2(C11,F11,"")) -> 0.28433758 | J11: =IF(C11="","",[1]!hks_fa_bps(C11,F11,"")) -> 7.3552 | K11: =IF(C11="","",[1]!hks_fa_ocfps(C11,F11,"")) -> 0.151 | L11: =IF(C11="","",[1]!hks_fa_grossprofitmargin(C11,F11)) -> 42.2935 | M11: =IF(C11="","",[1]!hks_fa_netprofitmargin(C11,F11)) -> 3.1405 | N11: =IF(C11="","",[1]!hks_fa_roe(C11,F11)) -> 3.9322 | O11: =IF(C11="","",[1]!hks_fa_roe_deducted(C11,F11)) -> 3.5105 | P11: =IF(C11="","",[1]!hks_fa_roa2(C11,F11)) -> 1.1876 | Q11: =IF(C11="","",[1]!hks_fa_roic(C11,F11)) -> 3.1547 | R11: =IF(C11="","",[1]!hks_fa_dupont_nptosales(C11,F11)) -> 3.1405 | S11: =IF(C11="","",[1]!hks_fa_dupont_ebittosales(C11,F11)) -> 2.15 | T11: =IF(C11="","",[1]!hks_fa_ebitdatosales(C11,F11)) -> 11.345698 | U11: =IF(C11="","",[1]!hks_fa_optoebt(C11,F11)) -> -244.2218 | V11: =IF(C11="","",[1]!hks_fa_ocftosales(C11,F11)) -> 1.7914 | W11: =IF(C11="","",[1]!hks_fa_debttoassets(C11,F11)) -> 53.1285 | X11: =IF(C11="","",[1]!s_fa_debttoeqy(C11,F11)) -> 1.1800583 | Y11: =IF(C11="","",[1]!hks_fa_catoassets(C11,F11)) -> 56.0383 | Z11: =IF(C11="","",[1]!hks_fa_ncatoassets(C11,F11)) -> 43.9617 | AA11: =IF(C11="","",[1]!hks_fa_currentdebttodebt(C11,F11)) -> 64.2197 | AB11: =IF(C11="","",[1]!hks_fa_longdebtodebt(C11,F11)) -> 35.7803 | AC11: =IF(C11="","",[1]!hks_fa_current(C11,F11)) -> 1.6424 | AD11: =IF(C11="","",[1]!hks_fa_quick(C11,F11)) -> 1.4519 | AE11: =IF(C11="","",[1]!hks_fa_ebittointerest(C11,F11)) -> 0 | AF11: =IF(C11="","",[1]!hks_fa_netdebtratio(C11,F11)) -> 13.2942 | AG11: =IF(C11="","",[1]!hks_fa_arturn(C11,F11)) -> 1.6998 | AH11: =IF(C11="","",[1]!hks_fa_apturn(C11,F11)) -> 1.4661049 | AI11: =IF(C11="","",[1]!hks_fa_invturn(C11,F11)) -> 4.3432 | AJ11: =IF(C11="","",[1]!hks_fa_caturn(C11,F11)) -> 0.9534 | AK11: =IF(C11="","",[1]!hks_fa_faturn(C11,F11)) -> 4.3897 | AL11: =IF(C11="","",[1]!hks_fa_assetsturn(C11,F11)) -> 0.5524 | AM11: =IF(C11="","",[1]!hks_fa_yoy_tr(C11,F11)) -> 4.3605 | AN11: =IF(C11="","",[1]!hks_fa_yoy_or(C11,F11)) -> 4.3605 | AO11: =IF(C11="","",[1]!hks_fa_yoyop2(C11,F11)) -> -44.295434 | AP11: =IF(C11="","",[1]!hks_fa_yoyebt(C11,F11)) -> 69.4321 | AQ11: =IF(C11="","",[1]!hks_fa_yoynetprofit(C11,F11)) -> 17.1236 | AR11: =IF(C11="","",[1]!hks_fa_dupont_np(C11,F11)) -> 107.2032 | AS11: =IF(C11="","",[1]!hks_fa_dupont_taxburden(C11,F11)) -> 146.0669 | AT11: =IF(C11="","",[1]!s_fa_dupont_nptosales(C11,F11)) -> 3.1203 | AU11: =IF(C11="","",[1]!s_fa_dupont_roe(C11,F11)) -> 3.9322 | AV11: =IF(C11="","",[1]!hks_fa_dupont_intburden(C11,F11)) -> 100 | AW11: =IF(C11="","",[1]!hks_fa_dupont_assetstoequity(C11,F11)) -> 2.1144 | AX11: =IF(C11="","",[1]!s_fa_dupont_ebittosales(C11,F11)) -> 2.1901 | AY11: =IF(C11="","",[1]!hks_fa_assetsturn(C11,F11)) -> 0.5524 | AZ11: =IF(C11="","",[1]!hks_fa_grossmargin2(C11,F11,"",100000000)) -> 82.573355 | BA11: =IF(C11="","",[1]!hks_fa_ebit3(C11,F11,1,"",100000000)) -> 2.1671653 | BB11: =IF(C11="","",[1]!hks_fa_ebitda(C11,F11,1,"",100000000)) -> 22.151207 | BC11: =IF(C11="","",[1]!hks_fa_ebit(C11,F11,1,"",100000000)) -> 4.19771 | BD11: =IF(C11="","",[1]!hks_fa_ebitda(C11,F11,1,"",100000000)) -> 22.151207 | BE11: =IF(C11="","",[1]!hks_fa_nogaapprofit(C11,F11,1,"",100000000)) -> 0 | BF11: =IF(C11="","",[1]!hks_fa_deductedprofit(C11,F11,1,"",100000000)) -> 5.8682092 | BG11: =IF(C11="","",[1]!hks_fa_retainedearnings2(C11,F11,"",100000000)) -> 53.694319 | BH11: =IF(C11="","",[1]!hks_fa_workingcapital2(C11,F11,"",100000000)) -> 82.923366 | BI11: =IF(C11="","",[1]!hks_fa_networkingcapital2(C11,F11,"",100000000)) -> 60.949766 | BJ11: =IF(C11="","",[1]!hks_fa_investcapital2(C11,F11,"",100000000)) -> 227.72527 | BK11: =IF(C11="","",[1]!hks_fa_tangibleasset2(C11,F11,"",100000000)) -> 107.42003 | BL11: =IF(C11="","",[1]!hks_fa_netdebt2(C11,F11,"",100000000)) -> 23.573321 | BM11: =IF(C11="","",[1]!hks_fa_interestdebt2(C11,F11,"",100000000)) -> 57.402424 | BN11: =IF(C11="","",[1]!hks_fa_exinterestdebt_current(C11,F11,"",100000000)) -> 117.22032 | BO11: =IF(C11="","",[1]!hks_fa_exinterestdebt_noncurrent2(C11,F11,"",100000000)) -> 26.368148 | BP11: =IF(C11="","",[1]!hks_fa_fcfe2(C11,F11,"",100000000)) -> 10.099234 | BQ11: =IF(C11="","",[1]!hks_fa_fcff2(C11,F11,"",100000000)) -> -22.905588
C12: =IF(表1[[#This Row],[列1]]="","",表1[[#This Row],[列1]]) -> 600004.SH | D12: =IF(C12="","",[1]!hks_info_name(C12)) -> 白云机场 | E12: =IF(C12="","",[1]!lastradeday_s(C12,TODAY())) -> 2024-12-09 | F12: =IF(C12="","",IF(OR([1]!s_stm_rpt_e(C12,基本资料!$I$8,0)="#N/A",[1]!s_stm_rpt_e(C12,基本资料!$I$8,0)="",[1]!s_stm_rpt_e(C12,基本资料!$I$8,0)=0),[1]!s_stm_rpt_e(C12,基本资料!$I$9,0),[1]!s_stm_rpt_e(C12,基本资料!$I$8,0))) -> 2023-12-31 | G12: =IF(C12="","",[1]!hks_info_cur2(C12,F12)) -> CNY | H12: =IF(C12="","",[1]!hks_fa_eps_basic(C12,F12,"")) -> 0.19 | I12: =IF(C12="","",[1]!hks_fa_eps_adjust2(C12,F12,"")) -> 0.18671665 | J12: =IF(C12="","",[1]!hks_fa_bps(C12,F12,"")) -> 7.4336 | K12: =IF(C12="","",[1]!hks_fa_ocfps(C12,F12,"")) -> 0.997 | L12: =IF(C12="","",[1]!hks_fa_grossprofitmargin(C12,F12)) -> 19.1893 | M12: =IF(C12="","",[1]!hks_fa_netprofitmargin(C12,F12)) -> 7.6632 | N12: =IF(C12="","",[1]!hks_fa_roe(C12,F12)) -> 2.5409 | O12: =IF(C12="","",[1]!hks_fa_roe_deducted(C12,F12)) -> 2.5039 | P12: =IF(C12="","",[1]!hks_fa_roa2(C12,F12)) -> 2.5514 | Q12: =IF(C12="","",[1]!hks_fa_roic(C12,F12)) -> 2.5008 | R12: =IF(C12="","",[1]!hks_fa_dupont_nptosales(C12,F12)) -> 7.6632 | S12: =IF(C12="","",[1]!hks_fa_dupont_ebittosales(C12,F12)) -> 10.7982 | T12: =IF(C12="","",[1]!hks_fa_ebitdatosales(C12,F12)) -> 33.630196 | U12: =IF(C12="","",[1]!hks_fa_optoebt(C12,F12)) -> 88.2598 | V12: =IF(C12="","",[1]!hks_fa_ocftosales(C12,F12)) -> 37.5935 | W12: =IF(C12="","",[1]!hks_fa_debttoassets(C12,F12)) -> 32.011 | X12: =IF(C12="","",[1]!s_fa_debttoeqy(C12,F12)) -> 0.476529 | Y12: =IF(C12="","",[1]!hks_fa_catoassets(C12,F12)) -> 15.3731 | Z12: =IF(C12="","",[1]!hks_fa_ncatoassets(C12,F12)) -> 84.6269 | AA12: =IF(C12="","",[1]!hks_fa_currentdebttodebt(C12,F12)) -> 70.4289 | AB12: =IF(C12="","",[1]!hks_fa_longdebtodebt(C12,F12)) -> 29.5711 | AC12: =IF(C12="","",[1]!hks_fa_current(C12,F12)) -> 0.6819 | AD12: =IF(C12="","",[1]!hks_fa_quick(C12,F12)) -> 0.6719 | AE12: =IF(C12="","",[1]!hks_fa_ebittointerest(C12,F12)) -> 0 | AF12: =IF(C12="","",[1]!hks_fa_netdebtratio(C12,F12)) -> -12.424158 | AG12: =IF(C12="","",[1]!hks_fa_arturn(C12,F12)) -> 6.2627 | AH12: =IF(C12="","",[1]!hks_fa_apturn(C12,F12)) -> 5.448569 | AI12: =IF(C12="","",[1]!hks_fa_invturn(C12,F12)) -> 84.9322 | AJ12: =IF(C12="","",[1]!hks_fa_caturn(C12,F12)) -> 1.6714 | AK12: =IF(C12="","",[1]!hks_fa_faturn(C12,F12)) -> 0.3344 | AL12: =IF(C12="","",[1]!hks_fa_assetsturn(C12,F12)) -> 0.2363 | AM12: =IF(C12="","",[1]!hks_fa_yoy_tr(C12,F12)) -> 62.1617 | AN12: =IF(C12="","",[1]!hks_fa_yoy_or(C12,F12)) -> 62.1617 | AO12: =IF(C12="","",[1]!hks_fa_yoyop2(C12,F12)) -> 139.83462 | AP12: =IF(C12="","",[1]!hks_fa_yoyebt(C12,F12)) -> 146.8846 | AQ12: =IF(C12="","",[1]!hks_fa_yoynetprofit(C12,F12)) -> 141.2532 | AR12: =IF(C12="","",[1]!hks_fa_dupont_np(C12,F12)) -> 91.8716 | AS12: =IF(C12="","",[1]!hks_fa_dupont_taxburden(C12,F12)) -> 70.9675 | AT12: =IF(C12="","",[1]!s_fa_dupont_nptosales(C12,F12)) -> 7.4796 | AU12: =IF(C12="","",[1]!s_fa_dupont_roe(C12,F12)) -> 2.5409 | AV12: =IF(C12="","",[1]!hks_fa_dupont_intburden(C12,F12)) -> 100 | AW12: =IF(C12="","",[1]!hks_fa_dupont_assetstoequity(C12,F12)) -> 1.5275 | AX12: =IF(C12="","",[1]!s_fa_dupont_ebittosales(C12,F12)) -> 11.8872 | AY12: =IF(C12="","",[1]!hks_fa_assetsturn(C12,F12)) -> 0.2363 | AZ12: =IF(C12="","",[1]!hks_fa_grossmargin2(C12,F12,"",100000000)) -> 12.044689 | BA12: =IF(C12="","",[1]!hks_fa_ebit3(C12,F12,1,"",100000000)) -> 6.4555957 | BB12: =IF(C12="","",[1]!hks_fa_ebitda(C12,F12,1,"",100000000)) -> 21.108965 | BC12: =IF(C12="","",[1]!hks_fa_ebit(C12,F12,1,"",100000000)) -> 6.7778002 | BD12: =IF(C12="","",[1]!hks_fa_ebitda(C12,F12,1,"",100000000)) -> 21.108965 | BE12: =IF(C12="","",[1]!hks_fa_nogaapprofit(C12,F12,1,"",100000000)) -> 0 | BF12: =IF(C12="","",[1]!hks_fa_deductedprofit(C12,F12,1,"",100000000)) -> 4.3547824 | BG12: =IF(C12="","",[1]!hks_fa_retainedearnings2(C12,F12,"",100000000)) -> 44.049296 | BH12: =IF(C12="","",[1]!hks_fa_workingcapital2(C12,F12,"",100000000)) -> -18.783131 | BI12: =IF(C12="","",[1]!hks_fa_networkingcapital2(C12,F12,"",100000000)) -> -40.906013 | BJ12: =IF(C12="","",[1]!hks_fa_investcapital2(C12,F12,"",100000000)) -> 179.02527 | BK12: =IF(C12="","",[1]!hks_fa_tangibleasset2(C12,F12,"",100000000)) -> 164.78547 | BL12: =IF(C12="","",[1]!hks_fa_netdebt2(C12,F12,"",100000000)) -> -22.122882 | BM12: =IF(C12="","",[1]!hks_fa_interestdebt2(C12,F12,"",100000000)) -> 3.0925854 | BN12: =IF(C12="","",[1]!hks_fa_exinterestdebt_current(C12,F12,"",100000000)) -> 55.952881 | BO12: =IF(C12="","",[1]!hks_fa_exinterestdebt_noncurrent2(C12,F12,"",100000000)) -> 24.791561 | BP12: =IF(C12="","",[1]!hks_fa_fcfe2(C12,F12,"",100000000)) -> -12.365689 | BQ12: =IF(C12="","",[1]!hks_fa_fcff2(C12,F12,"",100000000)) -> -2.3656889
C13: =IF(表1[[#This Row],[列1]]="","",表1[[#This Row],[列1]]) -> 600006.SH | D13: =IF(C13="","",[1]!hks_info_name(C13)) -> 东风股份 | E13: =IF(C13="","",[1]!lastradeday_s(C13,TODAY())) -> 2024-12-09 | F13: =IF(C13="","",IF(OR([1]!s_stm_rpt_e(C13,基本资料!$I$8,0)="#N/A",[1]!s_stm_rpt_e(C13,基本资料!$I$8,0)="",[1]!s_stm_rpt_e(C13,基本资料!$I$8,0)=0),[1]!s_stm_rpt_e(C13,基本资料!$I$9,0),[1]!s_stm_rpt_e(C13,基本资料!$I$8,0))) -> 2023-12-31 | G13: =IF(C13="","",[1]!hks_info_cur2(C13,F13)) -> CNY | H13: =IF(C13="","",[1]!hks_fa_eps_basic(C13,F13,"")) -> 0.1 | I13: =IF(C13="","",[1]!hks_fa_eps_adjust2(C13,F13,"")) -> 0.10002059 | J13: =IF(C13="","",[1]!hks_fa_bps(C13,F13,"")) -> 4.1548 | K13: =IF(C13="","",[1]!hks_fa_ocfps(C13,F13,"")) -> -0.1328 | L13: =IF(C13="","",[1]!hks_fa_grossprofitmargin(C13,F13)) -> 3.4367 | M13: =IF(C13="","",[1]!hks_fa_netprofitmargin(C13,F13)) -> 1.6959 | N13: =IF(C13="","",[1]!hks_fa_roe(C13,F13)) -> 2.4239 | O13: =IF(C13="","",[1]!hks_fa_roe_deducted(C13,F13)) -> 2.3816 | P13: =IF(C13="","",[1]!hks_fa_roa2(C13,F13)) -> 1.1158 | Q13: =IF(C13="","",[1]!hks_fa_roic(C13,F13)) -> 2.4226 | R13: =IF(C13="","",[1]!hks_fa_dupont_nptosales(C13,F13)) -> 1.6959 | S13: =IF(C13="","",[1]!hks_fa_dupont_ebittosales(C13,F13)) -> 1.7183 | T13: =IF(C13="","",[1]!hks_fa_ebitdatosales(C13,F13)) -> 4.1421007 | U13: =IF(C13="","",[1]!hks_fa_optoebt(C13,F13)) -> -392.5319 | V13: =IF(C13="","",[1]!hks_fa_ocftosales(C13,F13)) -> -2.2191 | W13: =IF(C13="","",[1]!hks_fa_debttoassets(C13,F13)) -> 55.1529 | X13: =IF(C13="","",[1]!s_fa_debttoeqy(C13,F13)) -> 1.2724813 | Y13: =IF(C13="","",[1]!hks_fa_catoassets(C13,F13)) -> 76.2089 | Z13: =IF(C13="","",[1]!hks_fa_ncatoassets(C13,F13)) -> 23.7911 | AA13: =IF(C13="","",[1]!hks_fa_currentdebttodebt(C13,F13)) -> 92.0076 | AB13: =IF(C13="","",[1]!hks_fa_longdebtodebt(C13,F13)) -> 7.9924 | AC13: =IF(C13="","",[1]!hks_fa_current(C13,F13)) -> 1.5018 | AD13: =IF(C13="","",[1]!hks_fa_quick(C13,F13)) -> 1.2994 | AE13: =IF(C13="","",[1]!hks_fa_ebittointerest(C13,F13)) -> 0 | AF13: =IF(C13="","",[1]!hks_fa_netdebtratio(C13,F13)) -> -56.527658 | AG13: =IF(C13="","",[1]!hks_fa_arturn(C13,F13)) -> 3.091 | AH13: =IF(C13="","",[1]!hks_fa_apturn(C13,F13)) -> 1.6109551 | AI13: =IF(C13="","",[1]!hks_fa_invturn(C13,F13)) -> 6.6882 | AJ13: =IF(C13="","",[1]!hks_fa_caturn(C13,F13)) -> 0.8564 | AK13: =IF(C13="","",[1]!hks_fa_faturn(C13,F13)) -> 6.7026 | AL13: =IF(C13="","",[1]!hks_fa_assetsturn(C13,F13)) -> 0.6493 | AM13: =IF(C13="","",[1]!hks_fa_yoy_tr(C13,F13)) -> -1.0027 | AN13: =IF(C13="","",[1]!hks_fa_yoy_or(C13,F13)) -> -1.0027 | AO13: =IF(C13="","",[1]!hks_fa_yoyop2(C13,F13)) -> -83.57242 | AP13: =IF(C13="","",[1]!hks_fa_yoyebt(C13,F13)) -> -27.83 | AQ13: =IF(C13="","",[1]!hks_fa_yoynetprofit(C13,F13)) -> -29.8308 | AR13: =IF(C13="","",[1]!hks_fa_dupont_np(C13,F13)) -> 98.5698 | AS13: =IF(C13="","",[1]!hks_fa_dupont_taxburden(C13,F13)) -> 98.6951 | AT13: =IF(C13="","",[1]!s_fa_dupont_nptosales(C13,F13)) -> 1.6814 | AU13: =IF(C13="","",[1]!s_fa_dupont_roe(C13,F13)) -> 2.4239 | AV13: =IF(C13="","",[1]!hks_fa_dupont_intburden(C13,F13)) -> 100 | AW13: =IF(C13="","",[1]!hks_fa_dupont_assetstoequity(C13,F13)) -> 2.233 | AX13: =IF(C13="","",[1]!s_fa_dupont_ebittosales(C13,F13)) -> 0.4896 | AY13: =IF(C13="","",[1]!hks_fa_assetsturn(C13,F13)) -> 0.6493 | AZ13: =IF(C13="","",[1]!hks_fa_grossmargin2(C13,F13,"",100000000)) -> 4.1126413 | BA13: =IF(C13="","",[1]!hks_fa_ebit3(C13,F13,1,"",100000000)) -> -4.6876235 | BB13: =IF(C13="","",[1]!hks_fa_ebitda(C13,F13,1,"",100000000)) -> 4.9567804 | BC13: =IF(C13="","",[1]!hks_fa_ebit(C13,F13,1,"",100000000)) -> 2.0562679 | BD13: =IF(C13="","",[1]!hks_fa_ebitda(C13,F13,1,"",100000000)) -> 4.9567804 | BE13: =IF(C13="","",[1]!hks_fa_nogaapprofit(C13,F13,1,"",100000000)) -> 0 | BF13: =IF(C13="","",[1]!hks_fa_deductedprofit(C13,F13,1,"",100000000)) -> 1.9655277 | BG13: =IF(C13="","",[1]!hks_fa_retainedearnings2(C13,F13,"",100000000)) -> 47.285065 | BH13: =IF(C13="","",[1]!hks_fa_workingcapital2(C13,F13,"",100000000)) -> 48.819402 | BI13: =IF(C13="","",[1]!hks_fa_networkingcapital2(C13,F13,"",100000000)) -> 0.21676241 | BJ13: =IF(C13="","",[1]!hks_fa_investcapital2(C13,F13,"",100000000)) -> 83.134056 | BK13: =IF(C13="","",[1]!hks_fa_tangibleasset2(C13,F13,"",100000000)) -> 75.416512 | BL13: =IF(C13="","",[1]!hks_fa_netdebt2(C13,F13,"",100000000)) -> -48.60264 | BM13: =IF(C13="","",[1]!hks_fa_interestdebt2(C13,F13,"",100000000)) -> 0.03768186 | BN13: =IF(C13="","",[1]!hks_fa_exinterestdebt_current(C13,F13,"",100000000)) -> 97.2498 | BO13: =IF(C13="","",[1]!hks_fa_exinterestdebt_noncurrent2(C13,F13,"",100000000)) -> 8.4510965 | BP13: =IF(C13="","",[1]!hks_fa_fcfe2(C13,F13,"",100000000)) -> 3.9390866 | BQ13: =IF(C13="","",[1]!hks_fa_fcff2(C13,F13,"",100000000)) -> 3.9390866
C14: =IF(表1[[#This Row],[列1]]="","",表1[[#This Row],[列1]]) -> 600007.SH | D14: =IF(C14="","",[1]!hks_info_name(C14)) -> 中国国贸 | E14: =IF(C14="","",[1]!lastradeday_s(C14,TODAY())) -> 2024-12-09 | F14: =IF(C14="","",IF(OR([1]!s_stm_rpt_e(C14,基本资料!$I$8,0)="#N/A",[1]!s_stm_rpt_e(C14,基本资料!$I$8,0)="",[1]!s_stm_rpt_e(C14,基本资料!$I$8,0)=0),[1]!s_stm_rpt_e(C14,基本资料!$I$9,0),[1]!s_stm_rpt_e(C14,基本资料!$I$8,0))) -> 2023-12-31 | G14: =IF(C14="","",[1]!hks_info_cur2(C14,F14)) -> CNY | H14: =IF(C14="","",[1]!hks_fa_eps_basic(C14,F14,"")) -> 1.25 | I14: =IF(C14="","",[1]!hks_fa_eps_adjust2(C14,F14,"")) -> 1.2500974 | J14: =IF(C14="","",[1]!hks_fa_bps(C14,F14,"")) -> 9.63 | K14: =IF(C14="","",[1]!hks_fa_ocfps(C14,F14,"")) -> 1.9048 | L14: =IF(C14="","",[1]!hks_fa_grossprofitmargin(C14,F14)) -> 53.4924 | M14: =IF(C14="","",[1]!hks_fa_netprofitmargin(C14,F14)) -> 35.3023 | N14: =IF(C14="","",[1]!hks_fa_roe(C14,F14)) -> 13.3633 | O14: =IF(C14="","",[1]!hks_fa_roe_deducted(C14,F14)) -> 13.281 | P14: =IF(C14="","",[1]!hks_fa_roa2(C14,F14)) -> 13.0717 | Q14: =IF(C14="","",[1]!hks_fa_roic(C14,F14)) -> 11.1824 | R14: =IF(C14="","",[1]!hks_fa_dupont_nptosales(C14,F14)) -> 35.3023 | S14: =IF(C14="","",[1]!hks_fa_dupont_ebittosales(C14,F14)) -> 47.0731 | T14: =IF(C14="","",[1]!hks_fa_ebitdatosales(C14,F14)) -> 60.285666 | U14: =IF(C14="","",[1]!hks_fa_optoebt(C14,F14)) -> 101.301 | V14: =IF(C14="","",[1]!hks_fa_ocftosales(C14,F14)) -> 53.7521 | W14: =IF(C14="","",[1]!hks_fa_debttoassets(C14,F14)) -> 24.6651 | X14: =IF(C14="","",[1]!s_fa_debttoeqy(C14,F14)) -> 0.327536 | Y14: =IF(C14="","",[1]!hks_fa_catoassets(C14,F14)) -> 34.346 | Z14: =IF(C14="","",[1]!hks_fa_ncatoassets(C14,F14)) -> 65.654 | AA14: =IF(C14="","",[1]!hks_fa_currentdebttodebt(C14,F14)) -> 64.6603 | AB14: =IF(C14="","",[1]!hks_fa_longdebtodebt(C14,F14)) -> 35.3397 | AC14: =IF(C14="","",[1]!hks_fa_current(C14,F14)) -> 2.1535 | AD14: =IF(C14="","",[1]!hks_fa_quick(C14,F14)) -> 2.1378 | AE14: =IF(C14="","",[1]!hks_fa_ebittointerest(C14,F14)) -> 0 | AF14: =IF(C14="","",[1]!hks_fa_netdebtratio(C14,F14)) -> -23.780242 | AG14: =IF(C14="","",[1]!hks_fa_arturn(C14,F14)) -> 11.2324 | AH14: =IF(C14="","",[1]!hks_fa_apturn(C14,F14)) -> 18.326265 | AI14: =IF(C14="","",[1]!hks_fa_invturn(C14,F14)) -> 51.5397 | AJ14: =IF(C14="","",[1]!hks_fa_caturn(C14,F14)) -> 0.8538 | AK14: =IF(C14="","",[1]!hks_fa_faturn(C14,F14)) -> 2.3502 | AL14: =IF(C14="","",[1]!hks_fa_assetsturn(C14,F14)) -> 0.2777 | AM14: =IF(C14="","",[1]!hks_fa_yoy_tr(C14,F14)) -> 15.9178 | AN14: =IF(C14="","",[1]!hks_fa_yoy_or(C14,F14)) -> 15.9178 | AO14: =IF(C14="","",[1]!hks_fa_yoyop2(C14,F14)) -> 22.659382 | AP14: =IF(C14="","",[1]!hks_fa_yoyebt(C14,F14)) -> 12.4862 | AQ14: =IF(C14="","",[1]!hks_fa_yoynetprofit(C14,F14)) -> 12.8447 | AR14: =IF(C14="","",[1]!hks_fa_dupont_np(C14,F14)) -> 99.9284 | AS14: =IF(C14="","",[1]!hks_fa_dupont_taxburden(C14,F14)) -> 74.9946 | AT14: =IF(C14="","",[1]!s_fa_dupont_nptosales(C14,F14)) -> 31.871 | AU14: =IF(C14="","",[1]!s_fa_dupont_roe(C14,F14)) -> 13.3633 | AV14: =IF(C14="","",[1]!hks_fa_dupont_intburden(C14,F14)) -> 100 | AW14: =IF(C14="","",[1]!hks_fa_dupont_assetstoequity(C14,F14)) -> 1.3642 | AX14: =IF(C14="","",[1]!s_fa_dupont_ebittosales(C14,F14)) -> 43.4953 | AY14: =IF(C14="","",[1]!hks_fa_assetsturn(C14,F14)) -> 0.2777 | AZ14: =IF(C14="","",[1]!hks_fa_grossmargin2(C14,F14,"",100000000)) -> 19.093909 | BA14: =IF(C14="","",[1]!hks_fa_ebit3(C14,F14,1,"",100000000)) -> 17.109643 | BB14: =IF(C14="","",[1]!hks_fa_ebitda(C14,F14,1,"",100000000)) -> 21.518756 | BC14: =IF(C14="","",[1]!hks_fa_ebit(C14,F14,1,"",100000000)) -> 16.802588 | BD14: =IF(C14="","",[1]!hks_fa_ebitda(C14,F14,1,"",100000000)) -> 21.518756 | BE14: =IF(C14="","",[1]!hks_fa_nogaapprofit(C14,F14,1,"",100000000)) -> 0 | BF14: =IF(C14="","",[1]!hks_fa_deductedprofit(C14,F14,1,"",100000000)) -> 12.514431 | BG14: =IF(C14="","",[1]!hks_fa_retainedearnings2(C14,F14,"",100000000)) -> 63.156473 | BH14: =IF(C14="","",[1]!hks_fa_workingcapital2(C14,F14,"",100000000)) -> 23.698003 | BI14: =IF(C14="","",[1]!hks_fa_networkingcapital2(C14,F14,"",100000000)) -> -10.228306 | BJ14: =IF(C14="","",[1]!hks_fa_investcapital2(C14,F14,"",100000000)) -> 112.82697 | BK14: =IF(C14="","",[1]!hks_fa_tangibleasset2(C14,F14,"",100000000)) -> 91.851339 | BL14: =IF(C14="","",[1]!hks_fa_netdebt2(C14,F14,"",100000000)) -> -23.076308 | BM14: =IF(C14="","",[1]!hks_fa_interestdebt2(C14,F14,"",100000000)) -> 15.825383 | BN14: =IF(C14="","",[1]!hks_fa_exinterestdebt_current(C14,F14,"",100000000)) -> 15.568172 | BO14: =IF(C14="","",[1]!hks_fa_exinterestdebt_noncurrent2(C14,F14,"",100000000)) -> 0.37795541 | BP14: =IF(C14="","",[1]!hks_fa_fcfe2(C14,F14,"",100000000)) -> 11.605168 | BQ14: =IF(C14="","",[1]!hks_fa_fcff2(C14,F14,"",100000000)) -> 16.705168
C15: =IF(表1[[#This Row],[列1]]="","",表1[[#This Row],[列1]]) -> 600941.SH | D15: =IF(C15="","",[1]!hks_info_name(C15)) -> 中国移动 | E15: =IF(C15="","",[1]!lastradeday_s(C15,TODAY())) -> 2024-12-09 | F15: =IF(C15="","",IF(OR([1]!s_stm_rpt_e(C15,基本资料!$I$8,0)="#N/A",[1]!s_stm_rpt_e(C15,基本资料!$I$8,0)="",[1]!s_stm_rpt_e(C15,基本资料!$I$8,0)=0),[1]!s_stm_rpt_e(C15,基本资料!$I$9,0),[1]!s_stm_rpt_e(C15,基本资料!$I$8,0))) -> 2023-12-31 | G15: =IF(C15="","",[1]!hks_info_cur2(C15,F15)) -> CNY | H15: =IF(C15="","",[1]!hks_fa_eps_basic(C15,F15,"")) -> 6.16 | I15: =IF(C15="","",[1]!hks_fa_eps_adjust2(C15,F15,"")) -> 6.1323303 | J15: =IF(C15="","",[1]!hks_fa_bps(C15,F15,"")) -> 61.0743 | K15: =IF(C15="","",[1]!hks_fa_ocfps(C15,F15,"")) -> 14.2014 | L15: =IF(C15="","",[1]!hks_fa_grossprofitmargin(C15,F15)) -> 28.1587 | M15: =IF(C15="","",[1]!hks_fa_netprofitmargin(C15,F15)) -> 13.0182 | N15: =IF(C15="","",[1]!hks_fa_roe(C15,F15)) -> 9.9858 | O15: =IF(C15="","",[1]!hks_fa_roe_deducted(C15,F15)) -> 8.8463 | P15: =IF(C15="","",[1]!hks_fa_roa2(C15,F15)) -> 8.49 | Q15: =IF(C15="","",[1]!hks_fa_roic(C15,F15)) -> 9.9297 | R15: =IF(C15="","",[1]!hks_fa_dupont_nptosales(C15,F15)) -> 13.0182 | S15: =IF(C15="","",[1]!hks_fa_dupont_ebittosales(C15,F15)) -> 16.4535 | T15: =IF(C15="","",[1]!hks_fa_ebitdatosales(C15,F15)) -> 36.891446 | U15: =IF(C15="","",[1]!hks_fa_optoebt(C15,F15)) -> 81.5752 | V15: =IF(C15="","",[1]!hks_fa_ocftosales(C15,F15)) -> 29.9743 | W15: =IF(C15="","",[1]!hks_fa_debttoassets(C15,F15)) -> 32.4528 | X15: =IF(C15="","",[1]!s_fa_debttoeqy(C15,F15)) -> 0.49499094 | Y15: =IF(C15="","",[1]!hks_fa_catoassets(C15,F15)) -> 24.997 | Z15: =IF(C15="","",[1]!hks_fa_ncatoassets(C15,F15)) -> 75.003 | AA15: =IF(C15="","",[1]!hks_fa_currentdebttodebt(C15,F15)) -> 86.3753 | AB15: =IF(C15="","",[1]!hks_fa_longdebtodebt(C15,F15)) -> 13.6247 | AC15: =IF(C15="","",[1]!hks_fa_current(C15,F15)) -> 0.8918 | AD15: =IF(C15="","",[1]!hks_fa_quick(C15,F15)) -> 0.8702 | AE15: =IF(C15="","",[1]!hks_fa_ebittointerest(C15,F15)) -> -44.114 | AF15: =IF(C15="","",[1]!hks_fa_netdebtratio(C15,F15)) -> -10.263933 | AG15: =IF(C15="","",[1]!hks_fa_arturn(C15,F15)) -> 17.9281 | AH15: =IF(C15="","",[1]!hks_fa_apturn(C15,F15)) -> 3.3431414 | AI15: =IF(C15="","",[1]!hks_fa_invturn(C15,F15)) -> 52.3025 | AJ15: =IF(C15="","",[1]!hks_fa_caturn(C15,F15)) -> 2.1236 | AK15: =IF(C15="","",[1]!hks_fa_faturn(C15,F15)) -> 1.2642 | AL15: =IF(C15="","",[1]!hks_fa_assetsturn(C15,F15)) -> 0.516 | AM15: =IF(C15="","",[1]!hks_fa_yoy_tr(C15,F15)) -> 7.6699 | AN15: =IF(C15="","",[1]!hks_fa_yoy_or(C15,F15)) -> 6.3365 | AO15: =IF(C15="","",[1]!hks_fa_yoyop2(C15,F15)) -> 3.5907632 | AP15: =IF(C15="","",[1]!hks_fa_yoyebt(C15,F15)) -> 4.7025 | AQ15: =IF(C15="","",[1]!hks_fa_yoynetprofit(C15,F15)) -> 5.0271 | AR15: =IF(C15="","",[1]!hks_fa_dupont_np(C15,F15)) -> 99.8719 | AS15: =IF(C15="","",[1]!hks_fa_dupont_taxburden(C15,F15)) -> 77.3672 | AT15: =IF(C15="","",[1]!s_fa_dupont_nptosales(C15,F15)) -> 13.0718 | AU15: =IF(C15="","",[1]!s_fa_dupont_roe(C15,F15)) -> 10.2602 | AV15: =IF(C15="","",[1]!hks_fa_dupont_intburden(C15,F15)) -> 102.2669 | AW15: =IF(C15="","",[1]!hks_fa_dupont_assetstoequity(C15,F15)) -> 1.4885 | AX15: =IF(C15="","",[1]!s_fa_dupont_ebittosales(C15,F15)) -> 16.5389 | AY15: =IF(C15="","",[1]!hks_fa_assetsturn(C15,F15)) -> 0.516 | AZ15: =IF(C15="","",[1]!hks_fa_grossmargin2(C15,F15,"",100000000)) -> 2431.54 | BA15: =IF(C15="","",[1]!hks_fa_ebit3(C15,F15,1,"",100000000)) -> 1427.14 | BB15: =IF(C15="","",[1]!hks_fa_ebitda(C15,F15,1,"",100000000)) -> 3738.83 | BC15: =IF(C15="","",[1]!hks_fa_ebit(C15,F15,1,"",100000000)) -> 1667.51 | BD15: =IF(C15="","",[1]!hks_fa_ebitda(C15,F15,1,"",100000000)) -> 3738.83 | BE15: =IF(C15="","",[1]!hks_fa_nogaapprofit(C15,F15,1,"",100000000)) -> 0 | BF15: =IF(C15="","",[1]!hks_fa_deductedprofit(C15,F15,1,"",100000000)) -> 1167.31 | BG15: =IF(C15="","",[1]!hks_fa_retainedearnings2(C15,F15,"",100000000)) -> 7771.61 | BH15: =IF(C15="","",[1]!hks_fa_workingcapital2(C15,F15,"",100000000)) -> -604.61 | BI15: =IF(C15="","",[1]!hks_fa_networkingcapital2(C15,F15,"",100000000)) -> -1986.12 | BJ15: =IF(C15="","",[1]!hks_fa_investcapital2(C15,F15,"",100000000)) -> 13451.4 | BK15: =IF(C15="","",[1]!hks_fa_tangibleasset2(C15,F15,"",100000000)) -> 11789.58 | BL15: =IF(C15="","",[1]!hks_fa_netdebt2(C15,F15,"",100000000)) -> -1381.51 | BM15: =IF(C15="","",[1]!hks_fa_interestdebt2(C15,F15,"",100000000)) -> 34.08 | BN15: =IF(C15="","",[1]!hks_fa_exinterestdebt_current(C15,F15,"",100000000)) -> 5551.57 | BO15: =IF(C15="","",[1]!hks_fa_exinterestdebt_noncurrent2(C15,F15,"",100000000)) -> 881.07 | BP15: =IF(C15="","",[1]!hks_fa_fcfe2(C15,F15,"",100000000)) -> 681.94776 | BQ15: =IF(C15="","",[1]!hks_fa_fcff2(C15,F15,"",100000000)) -> 1023.1178
C16: =IF(表1[[#This Row],[列1]]="","",表1[[#This Row],[列1]]) -> 603160.SH | D16: =IF(C16="","",[1]!hks_info_name(C16)) -> 汇顶科技 | E16: =IF(C16="","",[1]!lastradeday_s(C16,TODAY())) -> 2024-12-09 | F16: =IF(C16="","",IF(OR([1]!s_stm_rpt_e(C16,基本资料!$I$8,0)="#N/A",[1]!s_stm_rpt_e(C16,基本资料!$I$8,0)="",[1]!s_stm_rpt_e(C16,基本资料!$I$8,0)=0),[1]!s_stm_rpt_e(C16,基本资料!$I$9,0),[1]!s_stm_rpt_e(C16,基本资料!$I$8,0))) -> 2023-12-31 | G16: =IF(C16="","",[1]!hks_info_cur2(C16,F16)) -> CNY | H16: =IF(C16="","",[1]!hks_fa_eps_basic(C16,F16,"")) -> 0.36 | I16: =IF(C16="","",[1]!hks_fa_eps_adjust2(C16,F16,"")) -> 0.36017294 | J16: =IF(C16="","",[1]!hks_fa_bps(C16,F16,"")) -> 17.566 | K16: =IF(C16="","",[1]!hks_fa_ocfps(C16,F16,"")) -> 3.899 | L16: =IF(C16="","",[1]!hks_fa_grossprofitmargin(C16,F16)) -> 40.0726 | M16: =IF(C16="","",[1]!hks_fa_netprofitmargin(C16,F16)) -> 3.7689 | N16: =IF(C16="","",[1]!hks_fa_roe(C16,F16)) -> 2.0862 | O16: =IF(C16="","",[1]!hks_fa_roe_deducted(C16,F16)) -> 2.4309 | P16: =IF(C16="","",[1]!hks_fa_roa2(C16,F16)) -> 0.7751 | Q16: =IF(C16="","",[1]!hks_fa_roic(C16,F16)) -> 1.9337 | R16: =IF(C16="","",[1]!hks_fa_dupont_nptosales(C16,F16)) -> 3.7689 | S16: =IF(C16="","",[1]!hks_fa_dupont_ebittosales(C16,F16)) -> 1.6951 | T16: =IF(C16="","",[1]!hks_fa_ebitdatosales(C16,F16)) -> 8.5797555 | U16: =IF(C16="","",[1]!hks_fa_optoebt(C16,F16)) -> -643.595 | V16: =IF(C16="","",[1]!hks_fa_ocftosales(C16,F16)) -> 40.7778 | W16: =IF(C16="","",[1]!hks_fa_debttoassets(C16,F16)) -> 17.2895 | X16: =IF(C16="","",[1]!s_fa_debttoeqy(C16,F16)) -> 0.20903566 | Y16: =IF(C16="","",[1]!hks_fa_catoassets(C16,F16)) -> 57.0863 | Z16: =IF(C16="","",[1]!hks_fa_ncatoassets(C16,F16)) -> 42.9137 | AA16: =IF(C16="","",[1]!hks_fa_currentdebttodebt(C16,F16)) -> 78.8035 | AB16: =IF(C16="","",[1]!hks_fa_longdebtodebt(C16,F16)) -> 21.1965 | AC16: =IF(C16="","",[1]!hks_fa_current(C16,F16)) -> 4.1899 | AD16: =IF(C16="","",[1]!hks_fa_quick(C16,F16)) -> 3.6497 | AE16: =IF(C16="","",[1]!hks_fa_ebittointerest(C16,F16)) -> 0 | AF16: =IF(C16="","",[1]!hks_fa_netdebtratio(C16,F16)) -> -4.3101938 | AG16: =IF(C16="","",[1]!hks_fa_arturn(C16,F16)) -> 8.5716 | AH16: =IF(C16="","",[1]!hks_fa_apturn(C16,F16)) -> 8.625834 | AI16: =IF(C16="","",[1]!hks_fa_invturn(C16,F16)) -> 2.09 | AJ16: =IF(C16="","",[1]!hks_fa_caturn(C16,F16)) -> 0.7961 | AK16: =IF(C16="","",[1]!hks_fa_faturn(C16,F16)) -> 6.238 | AL16: =IF(C16="","",[1]!hks_fa_assetsturn(C16,F16)) -> 0.4573 | AM16: =IF(C16="","",[1]!hks_fa_yoy_tr(C16,F16)) -> 30.0272 | AN16: =IF(C16="","",[1]!hks_fa_yoy_or(C16,F16)) -> 30.0272 | AO16: =IF(C16="","",[1]!hks_fa_yoyop2(C16,F16)) -> 74.875046 | AP16: =IF(C16="","",[1]!hks_fa_yoyebt(C16,F16)) -> 107.4336 | AQ16: =IF(C16="","",[1]!hks_fa_yoynetprofit(C16,F16)) -> 122.0767 | AR16: =IF(C16="","",[1]!hks_fa_dupont_np(C16,F16)) -> 100.0027 | AS16: =IF(C16="","",[1]!hks_fa_dupont_taxburden(C16,F16)) -> 222.3356 | AT16: =IF(C16="","",[1]!s_fa_dupont_nptosales(C16,F16)) -> 3.7443 | AU16: =IF(C16="","",[1]!s_fa_dupont_roe(C16,F16)) -> 2.0862 | AV16: =IF(C16="","",[1]!hks_fa_dupont_intburden(C16,F16)) -> 100 | AW16: =IF(C16="","",[1]!hks_fa_dupont_assetstoequity(C16,F16)) -> 1.2105 | AX16: =IF(C16="","",[1]!s_fa_dupont_ebittosales(C16,F16)) -> -0.04 | AY16: =IF(C16="","",[1]!hks_fa_assetsturn(C16,F16)) -> 0.4573 | AZ16: =IF(C16="","",[1]!hks_fa_grossmargin2(C16,F16,"",100000000)) -> 17.5489 | BA16: =IF(C16="","",[1]!hks_fa_ebit3(C16,F16,1,"",100000000)) -> 2.1357239 | BB16: =IF(C16="","",[1]!hks_fa_ebitda(C16,F16,1,"",100000000)) -> 3.7573117 | BC16: =IF(C16="","",[1]!hks_fa_ebit(C16,F16,1,"",100000000)) -> 0.74234867 | BD16: =IF(C16="","",[1]!hks_fa_ebitda(C16,F16,1,"",100000000)) -> 3.7573117 | BE16: =IF(C16="","",[1]!hks_fa_nogaapprofit(C16,F16,1,"",100000000)) -> 0 | BF16: =IF(C16="","",[1]!hks_fa_deductedprofit(C16,F16,1,"",100000000)) -> 1.9232503 | BG16: =IF(C16="","",[1]!hks_fa_retainedearnings2(C16,F16,"",100000000)) -> 58.583852 | BH16: =IF(C16="","",[1]!hks_fa_workingcapital2(C16,F16,"",100000000)) -> 42.275272 | BI16: =IF(C16="","",[1]!hks_fa_networkingcapital2(C16,F16,"",100000000)) -> 36.386704 | BJ16: =IF(C16="","",[1]!hks_fa_investcapital2(C16,F16,"",100000000)) -> 85.273444 | BK16: =IF(C16="","",[1]!hks_fa_tangibleasset2(C16,F16,"",100000000)) -> 58.258915 | BL16: =IF(C16="","",[1]!hks_fa_netdebt2(C16,F16,"",100000000)) -> -3.4676719 | BM16: =IF(C16="","",[1]!hks_fa_interestdebt2(C16,F16,"",100000000)) -> 4.820646 | BN16: =IF(C16="","",[1]!hks_fa_exinterestdebt_current(C16,F16,"",100000000)) -> 10.853033 | BO16: =IF(C16="","",[1]!hks_fa_exinterestdebt_noncurrent2(C16,F16,"",100000000)) -> 1.1438247 | BP16: =IF(C16="","",[1]!hks_fa_fcfe2(C16,F16,"",100000000)) -> -3.7041023 | BQ16: =IF(C16="","",[1]!hks_fa_fcff2(C16,F16,"",100000000)) -> -0.96768058
C17: =IF(表1[[#This Row],[列1]]="","",表1[[#This Row],[列1]]) -> 688111.SH | D17: =IF(C17="","",[1]!hks_info_name(C17)) -> 金山办公 | E17: =IF(C17="","",[1]!lastradeday_s(C17,TODAY())) -> 2024-12-09 | F17: =IF(C17="","",IF(OR([1]!s_stm_rpt_e(C17,基本资料!$I$8,0)="#N/A",[1]!s_stm_rpt_e(C17,基本资料!$I$8,0)="",[1]!s_stm_rpt_e(C17,基本资料!$I$8,0)=0),[1]!s_stm_rpt_e(C17,基本资料!$I$9,0),[1]!s_stm_rpt_e(C17,基本资料!$I$8,0))) -> 2023-12-31 | G17: =IF(C17="","",[1]!hks_info_cur2(C17,F17)) -> CNY | H17: =IF(C17="","",[1]!hks_fa_eps_basic(C17,F17,"")) -> 2.86 | I17: =IF(C17="","",[1]!hks_fa_eps_adjust2(C17,F17,"")) -> 2.8490032 | J17: =IF(C17="","",[1]!hks_fa_bps(C17,F17,"")) -> 21.5471 | K17: =IF(C17="","",[1]!hks_fa_ocfps(C17,F17,"")) -> 4.4562 | L17: =IF(C17="","",[1]!hks_fa_grossprofitmargin(C17,F17)) -> 85.1766 | M17: =IF(C17="","",[1]!hks_fa_netprofitmargin(C17,F17)) -> 29.0887 | N17: =IF(C17="","",[1]!hks_fa_roe(C17,F17)) -> 14.1137 | O17: =IF(C17="","",[1]!hks_fa_roe_deducted(C17,F17)) -> 14.2569 | P17: =IF(C17="","",[1]!hks_fa_roa2(C17,F17)) -> 10.6781 | Q17: =IF(C17="","",[1]!hks_fa_roic(C17,F17)) -> 14.0366 | R17: =IF(C17="","",[1]!hks_fa_dupont_nptosales(C17,F17)) -> 29.0887 | S17: =IF(C17="","",[1]!hks_fa_dupont_ebittosales(C17,F17)) -> 30.7568 | T17: =IF(C17="","",[1]!hks_fa_ebitdatosales(C17,F17)) -> 32.535029 | U17: =IF(C17="","",[1]!hks_fa_optoebt(C17,F17)) -> 67.2455 | V17: =IF(C17="","",[1]!hks_fa_ocftosales(C17,F17)) -> 45.533 | W17: =IF(C17="","",[1]!hks_fa_debttoassets(C17,F17)) -> 28.2983 | X17: =IF(C17="","",[1]!s_fa_debttoeqy(C17,F17)) -> 0.39747668 | Y17: =IF(C17="","",[1]!hks_fa_catoassets(C17,F17)) -> 72.613 | Z17: =IF(C17="","",[1]!hks_fa_ncatoassets(C17,F17)) -> 27.387 | AA17: =IF(C17="","",[1]!hks_fa_currentdebttodebt(C17,F17)) -> 79.7536 | AB17: =IF(C17="","",[1]!hks_fa_longdebtodebt(C17,F17)) -> 20.2464 | AC17: =IF(C17="","",[1]!hks_fa_current(C17,F17)) -> 3.2174 | AD17: =IF(C17="","",[1]!hks_fa_quick(C17,F17)) -> 3.2169 | AE17: =IF(C17="","",[1]!hks_fa_ebittointerest(C17,F17)) -> 0 | AF17: =IF(C17="","",[1]!hks_fa_netdebtratio(C17,F17)) -> -34.304623 | AG17: =IF(C17="","",[1]!hks_fa_arturn(C17,F17)) -> 8.4522 | AH17: =IF(C17="","",[1]!hks_fa_apturn(C17,F17)) -> 1.763226 | AI17: =IF(C17="","",[1]!hks_fa_invturn(C17,F17)) -> 521.1234 | AJ17: =IF(C17="","",[1]!hks_fa_caturn(C17,F17)) -> 0.4536 | AK17: =IF(C17="","",[1]!hks_fa_faturn(C17,F17)) -> 17.3762 | AL17: =IF(C17="","",[1]!hks_fa_assetsturn(C17,F17)) -> 0.3472 | AM17: =IF(C17="","",[1]!hks_fa_yoy_tr(C17,F17)) -> 17.365 | AN17: =IF(C17="","",[1]!hks_fa_yoy_or(C17,F17)) -> 17.365 | AO17: =IF(C17="","",[1]!hks_fa_yoyop2(C17,F17)) -> 38.743333 | AP17: =IF(C17="","",[1]!hks_fa_yoyebt(C17,F17)) -> 15.9898 | AQ17: =IF(C17="","",[1]!hks_fa_yoynetprofit(C17,F17)) -> 17.9152 | AR17: =IF(C17="","",[1]!hks_fa_dupont_np(C17,F17)) -> 100.2492 | AS17: =IF(C17="","",[1]!hks_fa_dupont_taxburden(C17,F17)) -> 94.5765 | AT17: =IF(C17="","",[1]!s_fa_dupont_nptosales(C17,F17)) -> 28.8514 | AU17: =IF(C17="","",[1]!s_fa_dupont_roe(C17,F17)) -> 14.1137 | AV17: =IF(C17="","",[1]!hks_fa_dupont_intburden(C17,F17)) -> 100 | AW17: =IF(C17="","",[1]!hks_fa_dupont_assetstoequity(C17,F17)) -> 1.3941 | AX17: =IF(C17="","",[1]!s_fa_dupont_ebittosales(C17,F17)) -> 28.4047 | AY17: =IF(C17="","",[1]!hks_fa_assetsturn(C17,F17)) -> 0.3472 | AZ17: =IF(C17="","",[1]!hks_fa_grossmargin2(C17,F17,"",100000000)) -> 38.489667 | BA17: =IF(C17="","",[1]!hks_fa_ebit3(C17,F17,1,"",100000000)) -> 10.911182 | BB17: =IF(C17="","",[1]!hks_fa_ebitda(C17,F17,1,"",100000000)) -> 14.701951 | BC17: =IF(C17="","",[1]!hks_fa_ebit(C17,F17,1,"",100000000)) -> 13.898395 | BD17: =IF(C17="","",[1]!hks_fa_ebitda(C17,F17,1,"",100000000)) -> 14.701951 | BE17: =IF(C17="","",[1]!hks_fa_nogaapprofit(C17,F17,1,"",100000000)) -> 0 | BF17: =IF(C17="","",[1]!hks_fa_deductedprofit(C17,F17,1,"",100000000)) -> 13.311049 | BG17: =IF(C17="","",[1]!hks_fa_retainedearnings2(C17,F17,"",100000000)) -> 40.930628 | BH17: =IF(C17="","",[1]!hks_fa_workingcapital2(C17,F17,"",100000000)) -> 69.93173 | BI17: =IF(C17="","",[1]!hks_fa_networkingcapital2(C17,F17,"",100000000)) -> 35.559849 | BJ17: =IF(C17="","",[1]!hks_fa_investcapital2(C17,F17,"",100000000)) -> 99.855325 | BK17: =IF(C17="","",[1]!hks_fa_tangibleasset2(C17,F17,"",100000000)) -> 96.363729 | BL17: =IF(C17="","",[1]!hks_fa_netdebt2(C17,F17,"",100000000)) -> -34.371881 | BM17: =IF(C17="","",[1]!hks_fa_interestdebt2(C17,F17,"",100000000)) -> 0.36734729 | BN17: =IF(C17="","",[1]!hks_fa_exinterestdebt_current(C17,F17,"",100000000)) -> 31.170531 | BO17: =IF(C17="","",[1]!hks_fa_exinterestdebt_noncurrent2(C17,F17,"",100000000)) -> 8.0062728 | BP17: =IF(C17="","",[1]!hks_fa_fcfe2(C17,F17,"",100000000)) -> 12.608924 | BQ17: =IF(C17="","",[1]!hks_fa_fcff2(C17,F17,"",100000000)) -> 12.608924
C18: =IF(表1[[#This Row],[列1]]="","",表1[[#This Row],[列1]]) -> 0700.HK | D18: =IF(C18="","",[1]!hks_info_name(C18)) -> 腾讯控股 | E18: =IF(C18="","",[1]!lastradeday_s(C18,TODAY())) -> 2024-12-06 | F18: =IF(C18="","",IF(OR([1]!s_stm_rpt_e(C18,基本资料!$I$8,0)="#N/A",[1]!s_stm_rpt_e(C18,基本资料!$I$8,0)="",[1]!s_stm_rpt_e(C18,基本资料!$I$8,0)=0),[1]!s_stm_rpt_e(C18,基本资料!$I$9,0),[1]!s_stm_rpt_e(C18,基本资料!$I$8,0))) -> 2023-12-31 | G18: =IF(C18="","",[1]!hks_info_cur2(C18,F18)) -> CNY | H18: =IF(C18="","",[1]!hks_fa_eps_basic(C18,F18,"")) -> 12.186 | I18: =IF(C18="","",[1]!hks_fa_eps_adjust2(C18,F18,"")) -> 12.432299 | J18: =IF(C18="","",[1]!hks_fa_bps(C18,F18,"")) -> 85.26749 | K18: =IF(C18="","",[1]!hks_fa_ocfps(C18,F18,"")) -> 23.406324 | L18: =IF(C18="","",[1]!hks_fa_grossprofitmargin(C18,F18)) -> 48.1284 | M18: =IF(C18="","",[1]!hks_fa_netprofitmargin(C18,F18)) -> 19.3834 | N18: =IF(C18="","",[1]!hks_fa_roe(C18,F18)) -> 15.0611 | O18: =IF(C18="","",[1]!hks_fa_roe_deducted(C18,F18)) -> 14.2111 | P18: =IF(C18="","",[1]!hks_fa_roa2(C18,F18)) -> 10.1035 | Q18: =IF(C18="","",[1]!hks_fa_roic(C18,F18)) -> 10.5299 | R18: =IF(C18="","",[1]!hks_fa_dupont_nptosales(C18,F18)) -> 19.3834 | S18: =IF(C18="","",[1]!hks_fa_dupont_ebittosales(C18,F18)) -> 26.1736 | T18: =IF(C18="","",[1]!hks_fa_ebitdatosales(C18,F18)) -> 35.862663 | U18: =IF(C18="","",[1]!hks_fa_optoebt(C18,F18)) -> 94.7063 | V18: =IF(C18="","",[1]!hks_fa_ocftosales(C18,F18)) -> 36.4461 | W18: =IF(C18="","",[1]!hks_fa_debttoassets(C18,F18)) -> 44.6072 | X18: =IF(C18="","",[1]!s_fa_debttoeqy(C18,F18)) -> 0.87011233 | Y18: =IF(C18="","",[1]!hks_fa_catoassets(C18,F18)) -> 32.8703 | Z18: =IF(C18="","",[1]!hks_fa_ncatoassets(C18,F18)) -> 67.1297 | AA18: =IF(C18="","",[1]!hks_fa_currentdebttodebt(C18,F18)) -> 50.0532 | AB18: =IF(C18="","",[1]!hks_fa_longdebtodebt(C18,F18)) -> 49.9468 | AC18: =IF(C18="","",[1]!hks_fa_current(C18,F18)) -> 1.4722 | AD18: =IF(C18="","",[1]!hks_fa_quick(C18,F18)) -> 1.4709 | AE18: =IF(C18="","",[1]!hks_fa_ebittointerest(C18,F18)) -> -82.8918 | AF18: =IF(C18="","",[1]!hks_fa_netdebtratio(C18,F18)) -> 18.557918 | AG18: =IF(C18="","",[1]!hks_fa_arturn(C18,F18)) -> 13.229 | AH18: =IF(C18="","",[1]!hks_fa_apturn(C18,F18)) -> 2.8990713 | AI18: =IF(C18="","",[1]!hks_fa_invturn(C18,F18)) -> 226.5371 | AJ18: =IF(C18="","",[1]!hks_fa_caturn(C18,F18)) -> 1.1232 | AK18: =IF(C18="","",[1]!hks_fa_faturn(C18,F18)) -> 9.3679 | AL18: =IF(C18="","",[1]!hks_fa_assetsturn(C18,F18)) -> 0.386 | AM18: =IF(C18="","",[1]!hks_fa_yoy_tr(C18,F18)) -> 9.8211 | AN18: =IF(C18="","",[1]!hks_fa_yoy_or(C18,F18)) -> 9.8211 | AO18: =IF(C18="","",[1]!hks_fa_yoyop2(C18,F18)) -> 53.231436 | AP18: =IF(C18="","",[1]!hks_fa_yoyebt(C18,F18)) -> -23.2613 | AQ18: =IF(C18="","",[1]!hks_fa_yoynetprofit(C18,F18)) -> -38.794 | AR18: =IF(C18="","",[1]!hks_fa_dupont_np(C18,F18)) -> 97.601 | AS18: =IF(C18="","",[1]!hks_fa_dupont_taxburden(C18,F18)) -> 73.1745 | AT18: =IF(C18="","",[1]!s_fa_dupont_nptosales(C18,F18)) -> 19.3834 | AU18: =IF(C18="","",[1]!s_fa_dupont_roe(C18,F18)) -> 15.0611 | AV18: =IF(C18="","",[1]!hks_fa_dupont_intburden(C18,F18)) -> 101.2064 | AW18: =IF(C18="","",[1]!hks_fa_dupont_assetstoequity(C18,F18)) -> 2.0624 | AX18: =IF(C18="","",[1]!s_fa_dupont_ebittosales(C18,F18)) -> 26.1736 | AY18: =IF(C18="","",[1]!hks_fa_assetsturn(C18,F18)) -> 0.386 | AZ18: =IF(C18="","",[1]!hks_fa_grossmargin2(C18,F18,"",100000000)) -> 2931.09 | BA18: =IF(C18="","",[1]!hks_fa_ebit3(C18,F18,1,"",100000000)) -> 1527.84 | BB18: =IF(C18="","",[1]!hks_fa_ebitda(C18,F18,1,"",100000000)) -> 2184.09 | BC18: =IF(C18="","",[1]!hks_fa_ebit(C18,F18,1,"",100000000)) -> 1594.01 | BD18: =IF(C18="","",[1]!hks_fa_ebitda(C18,F18,1,"",100000000)) -> 2184.09 | BE18: =IF(C18="","",[1]!hks_fa_nogaapprofit(C18,F18,1,"",100000000)) -> 1617.34 | BF18: =IF(C18="","",[1]!hks_fa_deductedprofit(C18,F18,1,"",100000000)) -> 1087.14 | BG18: =IF(C18="","",[1]!hks_fa_retainedearnings2(C18,F18,"",100000000)) -> 8139.11 | BH18: =IF(C18="","",[1]!hks_fa_workingcapital2(C18,F18,"",100000000)) -> 1662.89 | BI18: =IF(C18="","",[1]!hks_fa_networkingcapital2(C18,F18,"",100000000)) -> 355.06 | BJ18: =IF(C18="","",[1]!hks_fa_investcapital2(C18,F18,"",100000000)) -> 11430.48 | BK18: =IF(C18="","",[1]!hks_fa_tangibleasset2(C18,F18,"",100000000)) -> 6104 | BL18: =IF(C18="","",[1]!hks_fa_netdebt2(C18,F18,"",100000000)) -> 1621.37 | BM18: =IF(C18="","",[1]!hks_fa_interestdebt2(C18,F18,"",100000000)) -> 3344.57 | BN18: =IF(C18="","",[1]!hks_fa_exinterestdebt_current(C18,F18,"",100000000)) -> 3106.2 | BO18: =IF(C18="","",[1]!hks_fa_exinterestdebt_noncurrent2(C18,F18,"",100000000)) -> 584.88 | BP18: =IF(C18="","",[1]!hks_fa_fcfe2(C18,F18,"",100000000)) -> 771.71899 | BQ18: =IF(C18="","",[1]!hks_fa_fcff2(C18,F18,"",100000000)) -> 745.19899
C19: =IF(表1[[#This Row],[列1]]="","",表1[[#This Row],[列1]]) -> 9896.HK | D19: =IF(C19="","",[1]!hks_info_name(C19)) -> 名创优品 | E19: =IF(C19="","",[1]!lastradeday_s(C19,TODAY())) -> 2024-12-06 | F19: =IF(C19="","",IF(OR([1]!s_stm_rpt_e(C19,基本资料!$I$8,0)="#N/A",[1]!s_stm_rpt_e(C19,基本资料!$I$8,0)="",[1]!s_stm_rpt_e(C19,基本资料!$I$8,0)=0),[1]!s_stm_rpt_e(C19,基本资料!$I$9,0),[1]!s_stm_rpt_e(C19,基本资料!$I$8,0))) -> 2023-06-30 | G19: =IF(C19="","",[1]!hks_info_cur2(C19,F19)) -> CNY | H19: =IF(C19="","",[1]!hks_fa_eps_basic(C19,F19,"")) -> 0.61 | I19: =IF(C19="","",[1]!hks_fa_eps_adjust2(C19,F19,"")) -> 0.6082163 | J19: =IF(C19="","",[1]!hks_fa_bps(C19,F19,"")) -> 6.1622004 | K19: =IF(C19="","",[1]!hks_fa_ocfps(C19,F19,"")) -> 0.34195785 | L19: =IF(C19="","",[1]!hks_fa_grossprofitmargin(C19,F19)) -> 37.7009 | M19: =IF(C19="","",[1]!hks_fa_netprofitmargin(C19,F19)) -> 14.5041 | N19: =IF(C19="","",[1]!hks_fa_roe(C19,F19)) -> 10.2984 | O19: =IF(C19="","",[1]!hks_fa_roe_deducted(C19,F19)) -> 10.3484 | P19: =IF(C19="","",[1]!hks_fa_roa2(C19,F19)) -> 8.2225 | Q19: =IF(C19="","",[1]!hks_fa_roic(C19,F19)) -> 10.2887 | R19: =IF(C19="","",[1]!hks_fa_dupont_nptosales(C19,F19)) -> 14.5041 | S19: =IF(C19="","",[1]!hks_fa_dupont_ebittosales(C19,F19)) -> 18.1715 | T19: =IF(C19="","",[1]!hks_fa_ebitdatosales(C19,F19)) -> 0 | U19: =IF(C19="","",[1]!hks_fa_optoebt(C19,F19)) -> 86.8925 | V19: =IF(C19="","",[1]!hks_fa_ocftosales(C19,F19)) -> 8.226 | W19: =IF(C19="","",[1]!hks_fa_debttoassets(C19,F19)) -> 34.9106 | X19: =IF(C19="","",[1]!s_fa_debttoeqy(C19,F19)) -> 0.53645767 | Y19: =IF(C19="","",[1]!hks_fa_catoassets(C19,F19)) -> 72.88 | Z19: =IF(C19="","",[1]!hks_fa_ncatoassets(C19,F19)) -> 27.12 | AA19: =IF(C19="","",[1]!hks_fa_currentdebttodebt(C19,F19)) -> 88.6162 | AB19: =IF(C19="","",[1]!hks_fa_longdebtodebt(C19,F19)) -> 11.3838 | AC19: =IF(C19="","",[1]!hks_fa_current(C19,F19)) -> 2.3558 | AD19: =IF(C19="","",[1]!hks_fa_quick(C19,F19)) -> 1.9584 | AE19: =IF(C19="","",[1]!hks_fa_ebittointerest(C19,F19)) -> -19.7991 | AF19: =IF(C19="","",[1]!hks_fa_netdebtratio(C19,F19)) -> -66.328417 | AG19: =IF(C19="","",[1]!hks_fa_arturn(C19,F19)) -> 7.0968 | AH19: =IF(C19="","",[1]!hks_fa_apturn(C19,F19)) -> 1.8213927 | AI19: =IF(C19="","",[1]!hks_fa_invturn(C19,F19)) -> 2.4644 | AJ19: =IF(C19="","",[1]!hks_fa_caturn(C19,F19)) -> 0.6264 | AK19: =IF(C19="","",[1]!hks_fa_faturn(C19,F19)) -> 11.8675 | AL19: =IF(C19="","",[1]!hks_fa_assetsturn(C19,F19)) -> 0.4525 | AM19: =IF(C19="","",[1]!hks_fa_yoy_tr(C19,F19)) -> -2.9488 | AN19: =IF(C19="","",[1]!hks_fa_yoy_or(C19,F19)) -> -2.9488 | AO19: =IF(C19="","",[1]!hks_fa_yoyop2(C19,F19)) -> 101.74979 | AP19: =IF(C19="","",[1]!hks_fa_yoyebt(C19,F19)) -> 113.9368 | AQ19: =IF(C19="","",[1]!hks_fa_yoynetprofit(C19,F19)) -> 126.8817 | AR19: =IF(C19="","",[1]!hks_fa_dupont_np(C19,F19)) -> 100.0234 | AS19: =IF(C19="","",[1]!hks_fa_dupont_taxburden(C19,F19)) -> 75.9801 | AT19: =IF(C19="","",[1]!s_fa_dupont_nptosales(C19,F19)) -> 14.5041 | AU19: =IF(C19="","",[1]!s_fa_dupont_roe(C19,F19)) -> 10.2984 | AV19: =IF(C19="","",[1]!hks_fa_dupont_intburden(C19,F19)) -> 105.0507 | AW19: =IF(C19="","",[1]!hks_fa_dupont_assetstoequity(C19,F19)) -> 1.5688 | AX19: =IF(C19="","",[1]!s_fa_dupont_ebittosales(C19,F19)) -> 18.1715 | AY19: =IF(C19="","",[1]!hks_fa_assetsturn(C19,F19)) -> 0.4525 | AZ19: =IF(C19="","",[1]!hks_fa_grossmargin2(C19,F19,"",100000000)) -> 19.8566 | BA19: =IF(C19="","",[1]!hks_fa_ebit3(C19,F19,1,"",100000000)) -> 8.73625 | BB19: =IF(C19="","",[1]!hks_fa_ebitda(C19,F19,1,"",100000000)) -> 0 | BC19: =IF(C19="","",[1]!hks_fa_ebit(C19,F19,1,"",100000000)) -> 9.5707 | BD19: =IF(C19="","",[1]!hks_fa_ebitda(C19,F19,1,"",100000000)) -> 0 | BE19: =IF(C19="","",[1]!hks_fa_nogaapprofit(C19,F19,1,"",100000000)) -> 0 | BF19: =IF(C19="","",[1]!hks_fa_deductedprofit(C19,F19,1,"",100000000)) -> 7.67806 | BG19: =IF(C19="","",[1]!hks_fa_retainedearnings2(C19,F19,"",100000000)) -> -11.96403 | BH19: =IF(C19="","",[1]!hks_fa_workingcapital2(C19,F19,"",100000000)) -> 50.32134 | BI19: =IF(C19="","",[1]!hks_fa_networkingcapital2(C19,F19,"",100000000)) -> -1.54467 | BJ19: =IF(C19="","",[1]!hks_fa_investcapital2(C19,F19,"",100000000)) -> 78.14422 | BK19: =IF(C19="","",[1]!hks_fa_tangibleasset2(C19,F19,"",100000000)) -> 54.16083 | BL19: =IF(C19="","",[1]!hks_fa_netdebt2(C19,F19,"",100000000)) -> -51.79604 | BM19: =IF(C19="","",[1]!hks_fa_interestdebt2(C19,F19,"",100000000)) -> 0.06997 | BN19: =IF(C19="","",[1]!hks_fa_exinterestdebt_current(C19,F19,"",100000000)) -> 37.11558 | BO19: =IF(C19="","",[1]!hks_fa_exinterestdebt_noncurrent2(C19,F19,"",100000000)) -> 4.69798 | BP19: =IF(C19="","",[1]!hks_fa_fcfe2(C19,F19,"",100000000)) -> -4.9440365 | BQ19: =IF(C19="","",[1]!hks_fa_fcff2(C19,F19,"",100000000)) -> -3.2393965
... C100: =IF(表1[[#This Row],[列1]]="","",表1[[#This Row],[列1]]) | D100: =IF(C100="","",[1]!hks_info_name(C100)) | E100: =IF(C100="","",[1]!lastradeday_s(C100,TODAY())) | F100: =IF(C100="","",IF(OR([1]!s_stm_rpt_e(C100,基本资料!$I$8,0)="#N/A",[1]!s_stm_rpt_e(C100,基本资料!$I$8,0)="",[1]!s_stm_rpt_e(C100,基本资料!$I$8,0)=0),[1]!s_stm_rpt_e(C100,基本资料!$I$9,0),[1]!s_stm_rpt_e(C100,基本资料!$I$8,0))) | G100: =IF(C100="","",[1]!hks_info_cur2(C100,F100)) | H100: =IF(C100="","",[1]!hks_fa_eps_basic(C100,F100,"")) | I100: =IF(C100="","",[1]!hks_fa_eps_adjust2(C100,F100,"")) | J100: =IF(C100="","",[1]!hks_fa_bps(C100,F100,"")) | K100: =IF(C100="","",[1]!hks_fa_ocfps(C100,F100,"")) | L100: =IF(C100="","",[1]!hks_fa_grossprofitmargin(C100,F100)) | M100: =IF(C100="","",[1]!hks_fa_netprofitmargin(C100,F100)) | N100: =IF(C100="","",[1]!hks_fa_roe(C100,F100)) | O100: =IF(C100="","",[1]!hks_fa_roe_deducted(C100,F100)) | P100: =IF(C100="","",[1]!hks_fa_roa2(C100,F100)) | Q100: =IF(C100="","",[1]!hks_fa_roic(C100,F100)) | R100: =IF(C100="","",[1]!hks_fa_dupont_nptosales(C100,F100)) | S100: =IF(C100="","",[1]!hks_fa_dupont_ebittosales(C100,F100)) | T100: =IF(C100="","",[1]!hks_fa_ebitdatosales(C100,F100)) | U100: =IF(C100="","",[1]!hks_fa_optoebt(C100,F100)) | V100: =IF(C100="","",[1]!hks_fa_ocftosales(C100,F100)) | W100: =IF(C100="","",[1]!hks_fa_debttoassets(C100,F100)) | X100: =IF(C100="","",[1]!s_fa_debttoeqy(C100,F100)) | Y100: =IF(C100="","",[1]!hks_fa_catoassets(C100,F100)) | Z100: =IF(C100="","",[1]!hks_fa_ncatoassets(C100,F100)) | AA100: =IF(C100="","",[1]!hks_fa_currentdebttodebt(C100,F100)) | AB100: =IF(C100="","",[1]!hks_fa_longdebtodebt(C100,F100)) | AC100: =IF(C100="","",[1]!hks_fa_current(C100,F100)) | AD100: =IF(C100="","",[1]!hks_fa_quick(C100,F100)) | AE100: =IF(C100="","",[1]!hks_fa_ebittointerest(C100,F100)) | AF100: =IF(C100="","",[1]!hks_fa_netdebtratio(C100,F100)) | AG100: =IF(C100="","",[1]!hks_fa_arturn(C100,F100)) | AH100: =IF(C100="","",[1]!hks_fa_apturn(C100,F100)) | AI100: =IF(C100="","",[1]!hks_fa_invturn(C100,F100)) | AJ100: =IF(C100="","",[1]!hks_fa_caturn(C100,F100)) | AK100: =IF(C100="","",[1]!hks_fa_faturn(C100,F100)) | AL100: =IF(C100="","",[1]!hks_fa_assetsturn(C100,F100)) | AM100: =IF(C100="","",[1]!hks_fa_yoy_tr(C100,F100)) | AN100: =IF(C100="","",[1]!hks_fa_yoy_or(C100,F100)) | AO100: =IF(C100="","",[1]!hks_fa_yoyop2(C100,F100)) | AP100: =IF(C100="","",[1]!hks_fa_yoyebt(C100,F100)) | AQ100: =IF(C100="","",[1]!hks_fa_yoynetprofit(C100,F100)) | AR100: =IF(C100="","",[1]!hks_fa_dupont_np(C100,F100)) | AS100: =IF(C100="","",[1]!hks_fa_dupont_taxburden(C100,F100)) | AT100: =IF(C100="","",[1]!s_fa_dupont_nptosales(C100,F100)) | AU100: =IF(C100="","",[1]!s_fa_dupont_roe(C100,F100)) | AV100: =IF(C100="","",[1]!hks_fa_dupont_intburden(C100,F100)) | AW100: =IF(C100="","",[1]!hks_fa_dupont_assetstoequity(C100,F100)) | AX100: =IF(C100="","",[1]!s_fa_dupont_ebittosales(C100,F100)) | AY100: =IF(C100="","",[1]!hks_fa_assetsturn(C100,F100)) | AZ100: =IF(C100="","",[1]!hks_fa_grossmargin2(C100,F100,"",100000000)) | BA100: =IF(C100="","",[1]!hks_fa_ebit3(C100,F100,1,"",100000000)) | BB100: =IF(C100="","",[1]!hks_fa_ebitda(C100,F100,1,"",100000000)) | BC100: =IF(C100="","",[1]!hks_fa_ebit(C100,F100,1,"",100000000)) | BD100: =IF(C100="","",[1]!hks_fa_ebitda(C100,F100,1,"",100000000)) | BE100: =IF(C100="","",[1]!hks_fa_nogaapprofit(C100,F100,1,"",100000000)) | BF100: =IF(C100="","",[1]!hks_fa_deductedprofit(C100,F100,1,"",100000000)) | BG100: =IF(C100="","",[1]!hks_fa_retainedearnings2(C100,F100,"",100000000)) | BH100: =IF(C100="","",[1]!hks_fa_workingcapital2(C100,F100,"",100000000)) | BI100: =IF(C100="","",[1]!hks_fa_networkingcapital2(C100,F100,"",100000000)) | BJ100: =IF(C100="","",[1]!hks_fa_investcapital2(C100,F100,"",100000000)) | BK100: =IF(C100="","",[1]!hks_fa_tangibleasset2(C100,F100,"",100000000)) | BL100: =IF(C100="","",[1]!hks_fa_netdebt2(C100,F100,"",100000000)) | BM100: =IF(C100="","",[1]!hks_fa_interestdebt2(C100,F100,"",100000000)) | BN100: =IF(C100="","",[1]!hks_fa_exinterestdebt_current(C100,F100,"",100000000)) | BO100: =IF(C100="","",[1]!hks_fa_exinterestdebt_noncurrent2(C100,F100,"",100000000)) | BP100: =IF(C100="","",[1]!hks_fa_fcfe2(C100,F100,"",100000000)) | BQ100: =IF(C100="","",[1]!hks_fa_fcff2(C100,F100,"",100000000))

Sheet 盈利预测
D1: 可比公司-盈利预测
C4: 盈利预测
C6: Wind代码 | D6: 证券简称 | E6: 最新收盘日 | F6: 最近一期年报日期 | G6: 最近一期年报年份 | H6: 预测FY1年份 | I6: 预测FY2年份 | J6: 万得一致预测(FY1) | Y6: 万得一致预测(FY2)
J7: 每股收益预测机构家数 | K7: 预测每股收益均值(元) | L7: 预测营业收入均值(亿元) | M7: 预测净利润均值(亿元) | N7: 预测每股现金流均值(元) | O7: 预测每股股利均值(元) | P7: 预测EBIT均值(亿元) | Q7: 预测EDBITDA均值(亿元) | R7: 预测每股净资产均值(元) | S7: 预测利润总额均值(亿元) | T7: 预测ROA均值(%) | U7: 预测ROE均值(%) | V7: 预测营业利润均值(亿元) | W7: 预测净利润增长率(%) | X7: 预测营业收入增长率(%) | Y7: 每股收益预测机构家数 | Z7: 预测每股收益均值(元) | AA7: 预测营业收入均值(亿元) | AB7: 预测净利润均值(亿元) | AC7: 预测每股现金流均值(元) | AD7: 预测每股股利均值(元) | AE7: 预测EBIT均值(亿元) | AF7: 预测EDBITDA均值(亿元) | AG7: 预测每股净资产均值(元) | AH7: 预测利润总额均值(亿元) | AI7: 预测ROA均值(%) | AJ7: 预测ROE均值(%) | AK7: 预测营业利润均值(亿元) | AL7: 预测净利润增长率(%) | AM7: 预测营业收入增长率(%)
C8: =IF(表1[[#This Row],[列1]]="","",表1[[#This Row],[列1]]) -> 000001.SZ | D8: =IF(C8="","",[1]!hks_info_name(C8)) -> 平安银行 | E8: =IF(C8="","",[1]!lastradeday_s(C8,TODAY())) -> 2024-12-09 | F8: =IF(C8="","",IF(OR([1]!s_stm_rpt_e(C8,基本资料!$I$8,0)="#N/A",[1]!s_stm_rpt_e(C8,基本资料!$I$8,0)="",[1]!s_stm_rpt_e(C8,基本资料!$I$8,0)=0),[1]!s_stm_rpt_e(C8,基本资料!$I$9,0),[1]!s_stm_rpt_e(C8,基本资料!$I$8,0))) -> 2023-12-31 | G8: =IF(C8="","",YEAR([1]!s_stm_rpt_e(C8,F8,0))) -> 2023 | H8: =IF(C8="","",表1_31213141516[[#This Row],[列5]]+1) -> 2024 | I8: =IF(C8="","",表1_31213141516[[#This Row],[列5]]+2) -> 2025 | J8: =IF(C8="","",[1]!s_est_instnum(C8,H8,TODAY())) -> 17 | K8: =IF(C8="","",[1]!s_est_eps(C8,H8,TODAY())) -> 2.3702 | L8: =IF(C8="","",[1]!s_est_sales(C8,H8,TODAY(),100000000)) -> 1467.1865 | M8: =IF(C8="","",[1]!s_est_netprofit(C8,H8,TODAY(),100000000)) -> 459.95118 | N8: =IF(C8="","",[1]!s_est_avgcps(C8,H8,TODAY())) -> 0 | O8: =IF(C8="","",[1]!s_est_avgdps(C8,H8,TODAY())) -> 0.6918 | P8: =IF(C8="","",[1]!s_est_avgebit(C8,H8,TODAY(),100000000)) -> 0 | Q8: =IF(C8="","",[1]!s_est_avgebitda(C8,H8,TODAY(),100000000)) -> 0 | R8: =IF(C8="","",[1]!s_est_avgbps(C8,H8,TODAY())) -> 22.43 | S8: =IF(C8="","",[1]!s_est_avgebt(C8,H8,TODAY(),100000000)) -> 581.34429 | T8: =IF(C8="","",[1]!s_est_avgroa(C8,H8,TODAY())) -> 0.8207 | U8: =IF(C8="","",[1]!s_est_avgroe(C8,H8,TODAY())) -> 10.5887 | V8: =IF(C8="","",[1]!s_est_avgoperatingprofit(C8,H8,TODAY(),100000000)) -> 689.995 | W8: =IF(C8="","",[1]!s_est_yoynetprofit(C8,H8,TODAY())) -> -0.98995233 | X8: =IF(C8="","",[1]!s_est_yoysales(C8,H8,TODAY())) -> -10.917098 | Y8: =IF(C8="","",[1]!s_est_instnum(C8,I8,TODAY())) -> 17 | Z8: =IF(C8="","",[1]!s_est_eps(C8,I8,TODAY())) -> 2.4201 | AA8: =IF(C8="","",[1]!s_est_sales(C8,I8,TODAY(),100000000)) -> 1464.5819 | AB8: =IF(C8="","",[1]!s_est_netprofit(C8,I8,TODAY(),100000000)) -> 469.86647 | AC8: =IF(C8="","",[1]!s_est_avgcps(C8,I8,TODAY())) -> 0 | AD8: =IF(C8="","",[1]!s_est_avgdps(C8,I8,TODAY())) -> 0.6811 | AE8: =IF(C8="","",[1]!s_est_avgebit(C8,I8,TODAY(),100000000)) -> 0 | AF8: =IF(C8="","",[1]!s_est_avgebitda(C8,I8,TODAY(),100000000)) -> 0 | AG8: =IF(C8="","",[1]!s_est_avgbps(C8,I8,TODAY())) -> 24.278 | AH8: =IF(C8="","",[1]!s_est_avgebt(C8,I8,TODAY(),100000000)) -> 593.60214 | AI8: =IF(C8="","",[1]!s_est_avgroa(C8,I8,TODAY())) -> 0.7967 | AJ8: =IF(C8="","",[1]!s_est_avgroe(C8,I8,TODAY())) -> 10.0293 | AK8: =IF(C8="","",[1]!s_est_avgoperatingprofit(C8,I8,TODAY(),100000000)) -> 681.4775 | AL8: =IF(C8="","",[1]!s_est_yoynetprofit(C8,I8,TODAY())) -> 2.1557276 | AM8: =IF(C8="","",[1]!s_est_yoysales(C8,I8,TODAY())) -> -0.17752425
C9: =IF(表1[[#This Row],[列1]]="","",表1[[#This Row],[列1]]) -> 000002.SZ | D9: =IF(C9="","",[1]!hks_info_name(C9)) -> 万科A | E9: =IF(C9="","",[1]!lastradeday_s(C9,TODAY())) -> 2024-12-09 | F9: =IF(C9="","",IF(OR([1]!s_stm_rpt_e(C9,基本资料!$I$8,0)="#N/A",[1]!s_stm_rpt_e(C9,基本资料!$I$8,0)="",[1]!s_stm_rpt_e(C9,基本资料!$I$8,0)=0),[1]!s_stm_rpt_e(C9,基本资料!$I$9,0),[1]!s_stm_rpt_e(C9,基本资料!$I$8,0))) -> 2023-12-31 | G9: =IF(C9="","",YEAR([1]!s_stm_rpt_e(C9,F9,0))) -> 2023 | H9: =IF(C9="","",表1_31213141516[[#This Row],[列5]]+1) -> 2024 | I9: =IF(C9="","",表1_31213141516[[#This Row],[列5]]+2) -> 2025 | J9: =IF(C9="","",[1]!s_est_instnum(C9,H9,TODAY())) -> 17 | K9: =IF(C9="","",[1]!s_est_eps(C9,H9,TODAY())) -> -0.9067 | L9: =IF(C9="","",[1]!s_est_sales(C9,H9,TODAY(),100000000)) -> 3521.4016 | M9: =IF(C9="","",[1]!s_est_netprofit(C9,H9,TODAY(),100000000)) -> -108.17192 | N9: =IF(C9="","",[1]!s_est_avgcps(C9,H9,TODAY())) -> 0.7893 | O9: =IF(C9="","",[1]!s_est_avgdps(C9,H9,TODAY())) -> 0 | P9: =IF(C9="","",[1]!s_est_avgebit(C9,H9,TODAY(),100000000)) -> 126.3125 | Q9: =IF(C9="","",[1]!s_est_avgebitda(C9,H9,TODAY(),100000000)) -> -23.494589 | R9: =IF(C9="","",[1]!s_est_avgbps(C9,H9,TODAY())) -> 20.0825 | S9: =IF(C9="","",[1]!s_est_avgebt(C9,H9,TODAY(),100000000)) -> -186.47528 | T9: =IF(C9="","",[1]!s_est_avgroa(C9,H9,TODAY())) -> -0.675 | U9: =IF(C9="","",[1]!s_est_avgroe(C9,H9,TODAY())) -> -5.0380001 | V9: =IF(C9="","",[1]!s_est_avgoperatingprofit(C9,H9,TODAY(),100000000)) -> -165.78521 | W9: =IF(C9="","",[1]!s_est_yoynetprofit(C9,H9,TODAY())) -> -188.93755 | X9: =IF(C9="","",[1]!s_est_yoysales(C9,H9,TODAY())) -> -24.391108 | Y9: =IF(C9="","",[1]!s_est_instnum(C9,I9,TODAY())) -> 17 | Z9: =IF(C9="","",[1]!s_est_eps(C9,I9,TODAY())) -> -0.0378 | AA9: =IF(C9="","",[1]!s_est_sales(C9,I9,TODAY(),100000000)) -> 3198.8038 | AB9: =IF(C9="","",[1]!s_est_netprofit(C9,I9,TODAY(),100000000)) -> -4.5096059 | AC9: =IF(C9="","",[1]!s_est_avgcps(C9,I9,TODAY())) -> 4.583 | AD9: =IF(C9="","",[1]!s_est_avgdps(C9,I9,TODAY())) -> 0 | AE9: =IF(C9="","",[1]!s_est_avgebit(C9,I9,TODAY(),100000000)) -> 144.0875 | AF9: =IF(C9="","",[1]!s_est_avgebitda(C9,I9,TODAY(),100000000)) -> 136.53518 | AG9: =IF(C9="","",[1]!s_est_avgbps(C9,I9,TODAY())) -> 19.8373 | AH9: =IF(C9="","",[1]!s_est_avgebt(C9,I9,TODAY(),100000000)) -> -9.6544 | AI9: =IF(C9="","",[1]!s_est_avgroa(C9,I9,TODAY())) -> 0.145 | AJ9: =IF(C9="","",[1]!s_est_avgroe(C9,I9,TODAY())) -> -0.414 | AK9: =IF(C9="","",[1]!s_est_avgoperatingprofit(C9,I9,TODAY(),100000000)) -> 9.1643933 | AL9: =IF(C9="","",[1]!s_est_yoynetprofit(C9,I9,TODAY())) -> 95.831078 | AM9: =IF(C9="","",[1]!s_est_yoysales(C9,I9,TODAY())) -> -9.1610641
C10: =IF(表1[[#This Row],[列1]]="","",表1[[#This Row],[列1]]) -> 002123.SZ | D10: =IF(C10="","",[1]!hks_info_name(C10)) -> 梦网科技 | E10: =IF(C10="","",[1]!lastradeday_s(C10,TODAY())) -> 2024-12-09 | F10: =IF(C10="","",IF(OR([1]!s_stm_rpt_e(C10,基本资料!$I$8,0)="#N/A",[1]!s_stm_rpt_e(C10,基本资料!$I$8,0)="",[1]!s_stm_rpt_e(C10,基本资料!$I$8,0)=0),[1]!s_stm_rpt_e(C10,基本资料!$I$9,0),[1]!s_stm_rpt_e(C10,基本资料!$I$8,0))) -> 2023-12-31 | G10: =IF(C10="","",YEAR([1]!s_stm_rpt_e(C10,F10,0))) -> 2023 | H10: =IF(C10="","",表1_31213141516[[#This Row],[列5]]+1) -> 2024 | I10: =IF(C10="","",表1_31213141516[[#This Row],[列5]]+2) -> 2025 | J10: =IF(C10="","",[1]!s_est_instnum(C10,H10,TODAY())) -> 3 | K10: =IF(C10="","",[1]!s_est_eps(C10,H10,TODAY())) -> 0.1646 | L10: =IF(C10="","",[1]!s_est_sales(C10,H10,TODAY(),100000000)) -> 55.6685 | M10: =IF(C10="","",[1]!s_est_netprofit(C10,H10,TODAY(),100000000)) -> 1.3176667 | N10: =IF(C10="","",[1]!s_est_avgcps(C10,H10,TODAY())) -> 0.1734 | O10: =IF(C10="","",[1]!s_est_avgdps(C10,H10,TODAY())) -> 0.01 | P10: =IF(C10="","",[1]!s_est_avgebit(C10,H10,TODAY(),100000000)) -> 1.54 | Q10: =IF(C10="","",[1]!s_est_avgebitda(C10,H10,TODAY(),100000000)) -> 2.6356 | R10: =IF(C10="","",[1]!s_est_avgbps(C10,H10,TODAY())) -> 2.193 | S10: =IF(C10="","",[1]!s_est_avgebt(C10,H10,TODAY(),100000000)) -> 1.5792667 | T10: =IF(C10="","",[1]!s_est_avgroa(C10,H10,TODAY())) -> 1.73 | U10: =IF(C10="","",[1]!s_est_avgroe(C10,H10,TODAY())) -> 7.5 | V10: =IF(C10="","",[1]!s_est_avgoperatingprofit(C10,H10,TODAY(),100000000)) -> 1.5793667 | W10: =IF(C10="","",[1]!s_est_yoynetprofit(C10,H10,TODAY())) -> 107.23006 | X10: =IF(C10="","",[1]!s_est_yoysales(C10,H10,TODAY())) -> 6.3516107 | Y10: =IF(C10="","",[1]!s_est_instnum(C10,I10,TODAY())) -> 3 | Z10: =IF(C10="","",[1]!s_est_eps(C10,I10,TODAY())) -> 0.2654 | AA10: =IF(C10="","",[1]!s_est_sales(C10,I10,TODAY(),100000000)) -> 62.618867 | AB10: =IF(C10="","",[1]!s_est_netprofit(C10,I10,TODAY(),100000000)) -> 2.1239333 | AC10: =IF(C10="","",[1]!s_est_avgcps(C10,I10,TODAY())) -> -0.0367 | AD10: =IF(C10="","",[1]!s_est_avgdps(C10,I10,TODAY())) -> 0.02 | AE10: =IF(C10="","",[1]!s_est_avgebit(C10,I10,TODAY(),100000000)) -> 2.36 | AF10: =IF(C10="","",[1]!s_est_avgebitda(C10,I10,TODAY(),100000000)) -> 3.6771667 | AG10: =IF(C10="","",[1]!s_est_avgbps(C10,I10,TODAY())) -> 2.4496 | AH10: =IF(C10="","",[1]!s_est_avgebt(C10,I10,TODAY(),100000000)) -> 2.5286333 | AI10: =IF(C10="","",[1]!s_est_avgroa(C10,I10,TODAY())) -> 2.95 | AJ10: =IF(C10="","",[1]!s_est_avgroe(C10,I10,TODAY())) -> 10.7667 | AK10: =IF(C10="","",[1]!s_est_avgoperatingprofit(C10,I10,TODAY(),100000000)) -> 2.5434 | AL10: =IF(C10="","",[1]!s_est_yoynetprofit(C10,I10,TODAY())) -> 61.188969 | AM10: =IF(C10="","",[1]!s_est_yoysales(C10,I10,TODAY())) -> 12.485277
C11: =IF(表1[[#This Row],[列1]]="","",表1[[#This Row],[列1]]) -> 002230.SZ | D11: =IF(C11="","",[1]!hks_info_name(C11)) -> 科大讯飞 | E11: =IF(C11="","",[1]!lastradeday_s(C11,TODAY())) -> 2024-12-09 | F11: =IF(C11="","",IF(OR([1]!s_stm_rpt_e(C11,基本资料!$I$8,0)="#N/A",[1]!s_stm_rpt_e(C11,基本资料!$I$8,0)="",[1]!s_stm_rpt_e(C11,基本资料!$I$8,0)=0),[1]!s_stm_rpt_e(C11,基本资料!$I$9,0),[1]!s_stm_rpt_e(C11,基本资料!$I$8,0))) -> 2023-12-31 | G11: =IF(C11="","",YEAR([1]!s_stm_rpt_e(C11,F11,0))) -> 2023 | H11: =IF(C11="","",表1_31213141516[[#This Row],[列5]]+1) -> 2024 | I11: =IF(C11="","",表1_31213141516[[#This Row],[列5]]+2) -> 2025 | J11: =IF(C11="","",[1]!s_est_instnum(C11,H11,TODAY())) -> 30 | K11: =IF(C11="","",[1]!s_est_eps(C11,H11,TODAY())) -> 0.2606 | L11: =IF(C11="","",[1]!s_est_sales(C11,H11,TODAY(),100000000)) -> 231.35296 | M11: =IF(C11="","",[1]!s_est_netprofit(C11,H11,TODAY(),100000000)) -> 6.0248 | N11: =IF(C11="","",[1]!s_est_avgcps(C11,H11,TODAY())) -> 0.805 | O11: =IF(C11="","",[1]!s_est_avgdps(C11,H11,TODAY())) -> 0.0969 | P11: =IF(C11="","",[1]!s_est_avgebit(C11,H11,TODAY(),100000000)) -> 4.8628571 | Q11: =IF(C11="","",[1]!s_est_avgebitda(C11,H11,TODAY(),100000000)) -> 23.228693 | R11: =IF(C11="","",[1]!s_est_avgbps(C11,H11,TODAY())) -> 7.5969 | S11: =IF(C11="","",[1]!s_est_avgebt(C11,H11,TODAY(),100000000)) -> 4.9052963 | T11: =IF(C11="","",[1]!s_est_avgroa(C11,H11,TODAY())) -> 1.5191 | U11: =IF(C11="","",[1]!s_est_avgroe(C11,H11,TODAY())) -> 3.3466001 | V11: =IF(C11="","",[1]!s_est_avgoperatingprofit(C11,H11,TODAY(),100000000)) -> 4.7538107 | W11: =IF(C11="","",[1]!s_est_yoynetprofit(C11,H11,TODAY())) -> -8.34198 | X11: =IF(C11="","",[1]!s_est_yoysales(C11,H11,TODAY())) -> 17.734903 | Y11: =IF(C11="","",[1]!s_est_instnum(C11,I11,TODAY())) -> 30 | Z11: =IF(C11="","",[1]!s_est_eps(C11,I11,TODAY())) -> 0.4153 | AA11: =IF(C11="","",[1]!s_est_sales(C11,I11,TODAY(),100000000)) -> 275.888 | AB11: =IF(C11="","",[1]!s_est_netprofit(C11,I11,TODAY(),100000000)) -> 9.6023033 | AC11: =IF(C11="","",[1]!s_est_avgcps(C11,I11,TODAY())) -> 0.4806 | AD11: =IF(C11="","",[1]!s_est_avgdps(C11,I11,TODAY())) -> 0.1414 | AE11: =IF(C11="","",[1]!s_est_avgebit(C11,I11,TODAY(),100000000)) -> 7.6285714 | AF11: =IF(C11="","",[1]!s_est_avgebitda(C11,I11,TODAY(),100000000)) -> 26.754807 | AG11: =IF(C11="","",[1]!s_est_avgbps(C11,I11,TODAY())) -> 7.9028 | AH11: =IF(C11="","",[1]!s_est_avgebt(C11,I11,TODAY(),100000000)) -> 8.4005556 | AI11: =IF(C11="","",[1]!s_est_avgroa(C11,I11,TODAY())) -> 2.1536 | AJ11: =IF(C11="","",[1]!s_est_avgroe(C11,I11,TODAY())) -> 5.1620998 | AK11: =IF(C11="","",[1]!s_est_avgoperatingprofit(C11,I11,TODAY(),100000000)) -> 8.13125 | AL11: =IF(C11="","",[1]!s_est_yoynetprofit(C11,I11,TODAY())) -> 59.37962 | AM11: =IF(C11="","",[1]!s_est_yoysales(C11,I11,TODAY())) -> 19.249825
C12: =IF(表1[[#This Row],[列1]]="","",表1[[#This Row],[列1]]) -> 600004.SH | D12: =IF(C12="","",[1]!hks_info_name(C12)) -> 白云机场 | E12: =IF(C12="","",[1]!lastradeday_s(C12,TODAY())) -> 2024-12-09 | F12: =IF(C12="","",IF(OR([1]!s_stm_rpt_e(C12,基本资料!$I$8,0)="#N/A",[1]!s_stm_rpt_e(C12,基本资料!$I$8,0)="",[1]!s_stm_rpt_e(C12,基本资料!$I$8,0)=0),[1]!s_stm_rpt_e(C12,基本资料!$I$9,0),[1]!s_stm_rpt_e(C12,基本资料!$I$8,0))) -> 2023-12-31 | G12: =IF(C12="","",YEAR([1]!s_stm_rpt_e(C12,F12,0))) -> 2023 | H12: =IF(C12="","",表1_31213141516[[#This Row],[列5]]+1) -> 2024 | I12: =IF(C12="","",表1_31213141516[[#This Row],[列5]]+2) -> 2025 | J12: =IF(C12="","",[1]!s_est_instnum(C12,H12,TODAY())) -> 10 | K12: =IF(C12="","",[1]!s_est_eps(C12,H12,TODAY())) -> 0.3983 | L12: =IF(C12="","",[1]!s_est_sales(C12,H12,TODAY(),100000000)) -> 74.172 | M12: =IF(C12="","",[1]!s_est_netprofit(C12,H12,TODAY(),100000000)) -> 9.4276 | N12: =IF(C12="","",[1]!s_est_avgcps(C12,H12,TODAY())) -> 1.2678 | O12: =IF(C12="","",[1]!s_est_avgdps(C12,H12,TODAY())) -> 0.1227 | P12: =IF(C12="","",[1]!s_est_avgebit(C12,H12,TODAY(),100000000)) -> 12.965 | Q12: =IF(C12="","",[1]!s_est_avgebitda(C12,H12,TODAY(),100000000)) -> 29.434 | R12: =IF(C12="","",[1]!s_est_avgbps(C12,H12,TODAY())) -> 7.7861 | S12: =IF(C12="","",[1]!s_est_avgebt(C12,H12,TODAY(),100000000)) -> 13.386667 | T12: =IF(C12="","",[1]!s_est_avgroa(C12,H12,TODAY())) -> 3.47 | U12: =IF(C12="","",[1]!s_est_avgroe(C12,H12,TODAY())) -> 5.2077999 | V12: =IF(C12="","",[1]!s_est_avgoperatingprofit(C12,H12,TODAY(),100000000)) -> 13.335556 | W12: =IF(C12="","",[1]!s_est_yoynetprofit(C12,H12,TODAY())) -> 113.33962 | X12: =IF(C12="","",[1]!s_est_yoysales(C12,H12,TODAY())) -> 15.337459 | Y12: =IF(C12="","",[1]!s_est_instnum(C12,I12,TODAY())) -> 10 | Z12: =IF(C12="","",[1]!s_est_eps(C12,I12,TODAY())) -> 0.5244 | AA12: =IF(C12="","",[1]!s_est_sales(C12,I12,TODAY(),100000000)) -> 81.89 | AB12: =IF(C12="","",[1]!s_est_netprofit(C12,I12,TODAY(),100000000)) -> 12.412 | AC12: =IF(C12="","",[1]!s_est_avgcps(C12,I12,TODAY())) -> 1.2221 | AD12: =IF(C12="","",[1]!s_est_avgdps(C12,I12,TODAY())) -> 0.1563 | AE12: =IF(C12="","",[1]!s_est_avgebit(C12,I12,TODAY(),100000000)) -> 16.47 | AF12: =IF(C12="","",[1]!s_est_avgebitda(C12,I12,TODAY(),100000000)) -> 32.736 | AG12: =IF(C12="","",[1]!s_est_avgbps(C12,I12,TODAY())) -> 8.2376 | AH12: =IF(C12="","",[1]!s_est_avgebt(C12,I12,TODAY(),100000000)) -> 17.718889 | AI12: =IF(C12="","",[1]!s_est_avgroa(C12,I12,TODAY())) -> 4.48 | AJ12: =IF(C12="","",[1]!s_est_avgroe(C12,I12,TODAY())) -> 6.5156002 | AK12: =IF(C12="","",[1]!s_est_avgoperatingprofit(C12,I12,TODAY(),100000000)) -> 17.67 | AL12: =IF(C12="","",[1]!s_est_yoynetprofit(C12,I12,TODAY())) -> 31.655989 | AM12: =IF(C12="","",[1]!s_est_yoysales(C12,I12,TODAY())) -> 10.405544
C13: =IF(表1[[#This Row],[列1]]="","",表1[[#This Row],[列1]]) -> 600006.SH | D13: =IF(C13="","",[1]!hks_info_name(C13)) -> 东风股份 | E13: =IF(C13="","",[1]!lastradeday_s(C13,TODAY())) -> 2024-12-09 | F13: =IF(C13="","",IF(OR([1]!s_stm_rpt_e(C13,基本资料!$I$8,0)="#N/A",[1]!s_stm_rpt_e(C13,基本资料!$I$8,0)="",[1]!s_stm_rpt_e(C13,基本资料!$I$8,0)=0),[1]!s_stm_rpt_e(C13,基本资料!$I$9,0),[1]!s_stm_rpt_e(C13,基本资料!$I$8,0))) -> 2023-12-31 | G13: =IF(C13="","",YEAR([1]!s_stm_rpt_e(C13,F13,0))) -> 2023 | H13: =IF(C13="","",表1_31213141516[[#This Row],[列5]]+1) -> 2024 | I13: =IF(C13="","",表1_31213141516[[#This Row],[列5]]+2) -> 2025 | J13: =IF(C13="","",[1]!s_est_instnum(C13,H13,TODAY())) -> 1 | K13: =IF(C13="","",[1]!s_est_eps(C13,H13,TODAY())) -> 0.054 | L13: =IF(C13="","",[1]!s_est_sales(C13,H13,TODAY(),100000000)) -> 0 | M13: =IF(C13="","",[1]!s_est_netprofit(C13,H13,TODAY(),100000000)) -> 0 | N13: =IF(C13="","",[1]!s_est_avgcps(C13,H13,TODAY())) -> 0 | O13: =IF(C13="","",[1]!s_est_avgdps(C13,H13,TODAY())) -> 0 | P13: =IF(C13="","",[1]!s_est_avgebit(C13,H13,TODAY(),100000000)) -> 0 | Q13: =IF(C13="","",[1]!s_est_avgebitda(C13,H13,TODAY(),100000000)) -> 0 | R13: =IF(C13="","",[1]!s_est_avgbps(C13,H13,TODAY())) -> 0 | S13: =IF(C13="","",[1]!s_est_avgebt(C13,H13,TODAY(),100000000)) -> 0 | T13: =IF(C13="","",[1]!s_est_avgroa(C13,H13,TODAY())) -> 0 | U13: =IF(C13="","",[1]!s_est_avgroe(C13,H13,TODAY())) -> 0 | V13: =IF(C13="","",[1]!s_est_avgoperatingprofit(C13,H13,TODAY(),100000000)) -> 0 | W13: =IF(C13="","",[1]!s_est_yoynetprofit(C13,H13,TODAY())) -> 0 | X13: =IF(C13="","",[1]!s_est_yoysales(C13,H13,TODAY())) -> 0 | Y13: =IF(C13="","",[1]!s_est_instnum(C13,I13,TODAY())) -> 1 | Z13: =IF(C13="","",[1]!s_est_eps(C13,I13,TODAY())) -> 0.0665 | AA13: =IF(C13="","",[1]!s_est_sales(C13,I13,TODAY(),100000000)) -> 0 | AB13: =IF(C13="","",[1]!s_est_netprofit(C13,I13,TODAY(),100000000)) -> 0 | AC13: =IF(C13="","",[1]!s_est_avgcps(C13,I13,TODAY())) -> 0 | AD13: =IF(C13="","",[1]!s_est_avgdps(C13,I13,TODAY())) -> 0 | AE13: =IF(C13="","",[1]!s_est_avgebit(C13,I13,TODAY(),100000000)) -> 0 | AF13: =IF(C13="","",[1]!s_est_avgebitda(C13,I13,TODAY(),100000000)) -> 0 | AG13: =IF(C13="","",[1]!s_est_avgbps(C13,I13,TODAY())) -> 0 | AH13: =IF(C13="","",[1]!s_est_avgebt(C13,I13,TODAY(),100000000)) -> 0 | AI13: =IF(C13="","",[1]!s_est_avgroa(C13,I13,TODAY())) -> 0 | AJ13: =IF(C13="","",[1]!s_est_avgroe(C13,I13,TODAY())) -> 0 | AK13: =IF(C13="","",[1]!s_est_avgoperatingprofit(C13,I13,TODAY(),100000000)) -> 0 | AL13: =IF(C13="","",[1]!s_est_yoynetprofit(C13,I13,TODAY())) -> 0 | AM13: =IF(C13="","",[1]!s_est_yoysales(C13,I13,TODAY())) -> 0
C14: =IF(表1[[#This Row],[列1]]="","",表1[[#This Row],[列1]]) -> 600007.SH | D14: =IF(C14="","",[1]!hks_info_name(C14)) -> 中国国贸 | E14: =IF(C14="","",[1]!lastradeday_s(C14,TODAY())) -> 2024-12-09 | F14: =IF(C14="","",IF(OR([1]!s_stm_rpt_e(C14,基本资料!$I$8,0)="#N/A",[1]!s_stm_rpt_e(C14,基本资料!$I$8,0)="",[1]!s_stm_rpt_e(C14,基本资料!$I$8,0)=0),[1]!s_stm_rpt_e(C14,基本资料!$I$9,0),[1]!s_stm_rpt_e(C14,基本资料!$I$8,0))) -> 2023-12-31 | G14: =IF(C14="","",YEAR([1]!s_stm_rpt_e(C14,F14,0))) -> 2023 | H14: =IF(C14="","",表1_31213141516[[#This Row],[列5]]+1) -> 2024 | I14: =IF(C14="","",表1_31213141516[[#This Row],[列5]]+2) -> 2025 | J14: =IF(C14="","",[1]!s_est_instnum(C14,H14,TODAY())) -> 5 | K14: =IF(C14="","",[1]!s_est_eps(C14,H14,TODAY())) -> 1.29 | L14: =IF(C14="","",[1]!s_est_sales(C14,H14,TODAY(),100000000)) -> 40.28346 | M14: =IF(C14="","",[1]!s_est_netprofit(C14,H14,TODAY(),100000000)) -> 12.994 | N14: =IF(C14="","",[1]!s_est_avgcps(C14,H14,TODAY())) -> 1.7014 | O14: =IF(C14="","",[1]!s_est_avgdps(C14,H14,TODAY())) -> 0.8666 | P14: =IF(C14="","",[1]!s_est_avgebit(C14,H14,TODAY(),100000000)) -> 17.14 | Q14: =IF(C14="","",[1]!s_est_avgebitda(C14,H14,TODAY(),100000000)) -> 21.916667 | R14: =IF(C14="","",[1]!s_est_avgbps(C14,H14,TODAY())) -> 10.1655 | S14: =IF(C14="","",[1]!s_est_avgebt(C14,H14,TODAY(),100000000)) -> 17.30906 | T14: =IF(C14="","",[1]!s_est_avgroa(C14,H14,TODAY())) -> 9.86 | U14: =IF(C14="","",[1]!s_est_avgroe(C14,H14,TODAY())) -> 12.692 | V14: =IF(C14="","",[1]!s_est_avgoperatingprofit(C14,H14,TODAY(),100000000)) -> 17.19506 | W14: =IF(C14="","",[1]!s_est_yoynetprofit(C14,H14,TODAY())) -> 3.1923945 | X14: =IF(C14="","",[1]!s_est_yoysales(C14,H14,TODAY())) -> 1.8864092 | Y14: =IF(C14="","",[1]!s_est_instnum(C14,I14,TODAY())) -> 5 | Z14: =IF(C14="","",[1]!s_est_eps(C14,I14,TODAY())) -> 1.3347 | AA14: =IF(C14="","",[1]!s_est_sales(C14,I14,TODAY(),100000000)) -> 41.56942 | AB14: =IF(C14="","",[1]!s_est_netprofit(C14,I14,TODAY(),100000000)) -> 13.444 | AC14: =IF(C14="","",[1]!s_est_avgcps(C14,I14,TODAY())) -> 1.7784 | AD14: =IF(C14="","",[1]!s_est_avgdps(C14,I14,TODAY())) -> 0.9309 | AE14: =IF(C14="","",[1]!s_est_avgebit(C14,I14,TODAY(),100000000)) -> 17.77 | AF14: =IF(C14="","",[1]!s_est_avgebitda(C14,I14,TODAY(),100000000)) -> 22.276667 | AG14: =IF(C14="","",[1]!s_est_avgbps(C14,I14,TODAY())) -> 10.7022 | AH14: =IF(C14="","",[1]!s_est_avgebt(C14,I14,TODAY(),100000000)) -> 17.86456 | AI14: =IF(C14="","",[1]!s_est_avgroa(C14,I14,TODAY())) -> 9.9033 | AJ14: =IF(C14="","",[1]!s_est_avgroe(C14,I14,TODAY())) -> 12.48 | AK14: =IF(C14="","",[1]!s_est_avgoperatingprofit(C14,I14,TODAY(),100000000)) -> 17.76256 | AL14: =IF(C14="","",[1]!s_est_yoynetprofit(C14,I14,TODAY())) -> 3.4631369 | AM14: =IF(C14="","",[1]!s_est_yoysales(C14,I14,TODAY())) -> 3.1922779
C15: =IF(表1[[#This Row],[列1]]="","",表1[[#This Row],[列1]]) -> 600941.SH | D15: =IF(C15="","",[1]!hks_info_name(C15)) -> 中国移动 | E15: =IF(C15="","",[1]!lastradeday_s(C15,TODAY())) -> 2024-12-09 | F15: =IF(C15="","",IF(OR([1]!s_stm_rpt_e(C15,基本资料!$I$8,0)="#N/A",[1]!s_stm_rpt_e(C15,基本资料!$I$8,0)="",[1]!s_stm_rpt_e(C15,基本资料!$I$8,0)=0),[1]!s_stm_rpt_e(C15,基本资料!$I$9,0),[1]!s_stm_rpt_e(C15,基本资料!$I$8,0))) -> 2023-12-31 | G15: =IF(C15="","",YEAR([1]!s_stm_rpt_e(C15,F15,0))) -> 2023 | H15: =IF(C15="","",表1_31213141516[[#This Row],[列5]]+1) -> 2024 | I15: =IF(C15="","",表1_31213141516[[#This Row],[列5]]+2) -> 2025 | J15: =IF(C15="","",[1]!s_est_instnum(C15,H15,TODAY())) -> 28 | K15: =IF(C15="","",[1]!s_est_eps(C15,H15,TODAY())) -> 6.4778 | L15: =IF(C15="","",[1]!s_est_sales(C15,H15,TODAY(),100000000)) -> 10490.035 | M15: =IF(C15="","",[1]!s_est_netprofit(C15,H15,TODAY(),100000000)) -> 1391.8905 | N15: =IF(C15="","",[1]!s_est_avgcps(C15,H15,TODAY())) -> 14.8734 | O15: =IF(C15="","",[1]!s_est_avgdps(C15,H15,TODAY())) -> 3.8606 | P15: =IF(C15="","",[1]!s_est_avgebit(C15,H15,TODAY(),100000000)) -> 1610.624 | Q15: =IF(C15="","",[1]!s_est_avgebitda(C15,H15,TODAY(),100000000)) -> 3336.7708 | R15: =IF(C15="","",[1]!s_est_avgbps(C15,H15,TODAY())) -> 62.0179 | S15: =IF(C15="","",[1]!s_est_avgebt(C15,H15,TODAY(),100000000)) -> 1802.0204 | T15: =IF(C15="","",[1]!s_est_avgroa(C15,H15,TODAY())) -> 6.941 | U15: =IF(C15="","",[1]!s_est_avgroe(C15,H15,TODAY())) -> 10.9792 | V15: =IF(C15="","",[1]!s_est_avgoperatingprofit(C15,H15,TODAY(),100000000)) -> 1783.9193 | W15: =IF(C15="","",[1]!s_est_yoynetprofit(C15,H15,TODAY())) -> 5.6335111 | X15: =IF(C15="","",[1]!s_est_yoysales(C15,H15,TODAY())) -> 3.9328384 | Y15: =IF(C15="","",[1]!s_est_instnum(C15,I15,TODAY())) -> 28 | Z15: =IF(C15="","",[1]!s_est_eps(C15,I15,TODAY())) -> 6.8232 | AA15: =IF(C15="","",[1]!s_est_sales(C15,I15,TODAY(),100000000)) -> 10970.266 | AB15: =IF(C15="","",[1]!s_est_netprofit(C15,I15,TODAY(),100000000)) -> 1466.1064 | AC15: =IF(C15="","",[1]!s_est_avgcps(C15,I15,TODAY())) -> 13.3874 | AD15: =IF(C15="","",[1]!s_est_avgdps(C15,I15,TODAY())) -> 4.5509 | AE15: =IF(C15="","",[1]!s_est_avgebit(C15,I15,TODAY(),100000000)) -> 1726.446 | AF15: =IF(C15="","",[1]!s_est_avgebitda(C15,I15,TODAY(),100000000)) -> 3615.7052 | AG15: =IF(C15="","",[1]!s_est_avgbps(C15,I15,TODAY())) -> 65.1082 | AH15: =IF(C15="","",[1]!s_est_avgebt(C15,I15,TODAY(),100000000)) -> 1900.4011 | AI15: =IF(C15="","",[1]!s_est_avgroa(C15,I15,TODAY())) -> 7.099 | AJ15: =IF(C15="","",[1]!s_est_avgroe(C15,I15,TODAY())) -> 10.8688 | AK15: =IF(C15="","",[1]!s_est_avgoperatingprofit(C15,I15,TODAY(),100000000)) -> 1881.0052 | AL15: =IF(C15="","",[1]!s_est_yoynetprofit(C15,I15,TODAY())) -> 5.3320169 | AM15: =IF(C15="","",[1]!s_est_yoysales(C15,I15,TODAY())) -> 4.5779767
C16: =IF(表1[[#This Row],[列1]]="","",表1[[#This Row],[列1]]) -> 603160.SH | D16: =IF(C16="","",[1]!hks_info_name(C16)) -> 汇顶科技 | E16: =IF(C16="","",[1]!lastradeday_s(C16,TODAY())) -> 2024-12-09 | F16: =IF(C16="","",IF(OR([1]!s_stm_rpt_e(C16,基本资料!$I$8,0)="#N/A",[1]!s_stm_rpt_e(C16,基本资料!$I$8,0)="",[1]!s_stm_rpt_e(C16,基本资料!$I$8,0)=0),[1]!s_stm_rpt_e(C16,基本资料!$I$9,0),[1]!s_stm_rpt_e(C16,基本资料!$I$8,0))) -> 2023-12-31 | G16: =IF(C16="","",YEAR([1]!s_stm_rpt_e(C16,F16,0))) -> 2023 | H16: =IF(C16="","",表1_31213141516[[#This Row],[列5]]+1) -> 2024 | I16: =IF(C16="","",表1_31213141516[[#This Row],[列5]]+2) -> 2025 | J16: =IF(C16="","",[1]!s_est_instnum(C16,H16,TODAY())) -> 10 | K16: =IF(C16="","",[1]!s_est_eps(C16,H16,TODAY())) -> 1.5086 | L16: =IF(C16="","",[1]!s_est_sales(C16,H16,TODAY(),100000000)) -> 50.918 | M16: =IF(C16="","",[1]!s_est_netprofit(C16,H16,TODAY(),100000000)) -> 6.91351 | N16: =IF(C16="","",[1]!s_est_avgcps(C16,H16,TODAY())) -> 1.3411 | O16: =IF(C16="","",[1]!s_est_avgdps(C16,H16,TODAY())) -> 0.5748 | P16: =IF(C16="","",[1]!s_est_avgebit(C16,H16,TODAY(),100000000)) -> 5.44 | Q16: =IF(C16="","",[1]!s_est_avgebitda(C16,H16,TODAY(),100000000)) -> 8.760325 | R16: =IF(C16="","",[1]!s_est_avgbps(C16,H16,TODAY())) -> 18.9966 | S16: =IF(C16="","",[1]!s_est_avgebt(C16,H16,TODAY(),100000000)) -> 7.124 | T16: =IF(C16="","",[1]!s_est_avgroa(C16,H16,TODAY())) -> 6.49 | U16: =IF(C16="","",[1]!s_est_avgroe(C16,H16,TODAY())) -> 7.9970002 | V16: =IF(C16="","",[1]!s_est_avgoperatingprofit(C16,H16,TODAY(),100000000)) -> 7.169 | W16: =IF(C16="","",[1]!s_est_yoynetprofit(C16,H16,TODAY())) -> 318.86115 | X16: =IF(C16="","",[1]!s_est_yoysales(C16,H16,TODAY())) -> 15.511333 | Y16: =IF(C16="","",[1]!s_est_instnum(C16,I16,TODAY())) -> 10 | Z16: =IF(C16="","",[1]!s_est_eps(C16,I16,TODAY())) -> 1.7992 | AA16: =IF(C16="","",[1]!s_est_sales(C16,I16,TODAY(),100000000)) -> 59.777 | AB16: =IF(C16="","",[1]!s_est_netprofit(C16,I16,TODAY(),100000000)) -> 8.24524 | AC16: =IF(C16="","",[1]!s_est_avgcps(C16,I16,TODAY())) -> 2.5937 | AD16: =IF(C16="","",[1]!s_est_avgdps(C16,I16,TODAY())) -> 0.7047 | AE16: =IF(C16="","",[1]!s_est_avgebit(C16,I16,TODAY(),100000000)) -> 6.25 | AF16: =IF(C16="","",[1]!s_est_avgebitda(C16,I16,TODAY(),100000000)) -> 10.3958 | AG16: =IF(C16="","",[1]!s_est_avgbps(C16,I16,TODAY())) -> 20.6334 | AH16: =IF(C16="","",[1]!s_est_avgebt(C16,I16,TODAY(),100000000)) -> 8.706 | AI16: =IF(C16="","",[1]!s_est_avgroa(C16,I16,TODAY())) -> 7.0533 | AJ16: =IF(C16="","",[1]!s_est_avgroe(C16,I16,TODAY())) -> 8.7799997 | AK16: =IF(C16="","",[1]!s_est_avgoperatingprofit(C16,I16,TODAY(),100000000)) -> 8.755 | AL16: =IF(C16="","",[1]!s_est_yoynetprofit(C16,I16,TODAY())) -> 19.262718 | AM16: =IF(C16="","",[1]!s_est_yoysales(C16,I16,TODAY())) -> 17.398561
